Workbook

Sheet Januari 2026 PMG 1
C1: PRODUCTION REPORT PMG 1
C2: No | D2: ITEM | E2: Budget / Norma | F2: UoM | G2: Januari 2026 | AM2: TOTAL MONTHLY (Kg)
G3: 1 | H3: 2 | I3: 3 | J3: 4 | K3: 5 | L3: 6 | M3: 7 | N3: 8 | O3: 9 | P3: 10 | Q3: 11 | R3: 12 | S3: 13 | T3: 14 | U3: 15 | V3: 16 | W3: 17 | X3: 18 | Y3: 19 | Z3: 20 | AA3: 21 | AB3: 22 | AC3: 23 | AD3: 24 | AE3: 25 | AF3: 26 | AG3: 27 | AH3: 28 | AI3: 29 | AJ3: 30 | AK3: 31
C4: 1 | D4: PRODUCTION | AM4: Production | AO4: aktual refinery | AR4: opening stok rpo | AS4: =AS6+AS7+AS9 -> 80236
D5: Refinery | AM5: Refinery | AO5: cpo feed | AP5: =AM9 -> 16794736 | AR5: sisa rbpo tank
D6: Running Days | F6: Day | L6: 1 | M6: 1 | N6: 1 | O6: 1 | P6: 1 | Q6: 1 | R6: 1 | S6: 1 | T6: 1 | U6: 1 | V6: 1 | AM6: =SUM(G6:AK6) -> 11 | AO6: rpo prod | AP6: =AM20+AM19+AM18 -> 15901359 | AR6: tk 108 | AS6: 80236
D7: Incoming CPO | F7: Kg | L7: 2047361 | M7: 2895861 | N7: 2094222 | O7: 1599295 | P7: 2822387 | Q7: 1400949 | R7: 2135308 | S7: 2069937 | T7: 2270473 | U7: 2856728 | AM7: =SUM(G7:AK7) -> 22192521
D8: Ratio Run CPO ( utilisasi kapasitas ) | F8: % | L8: =L9/2500000 -> 0.0690872 | M8: =M9/2500000 -> 0.5847548 | N8: =N9/2500000 -> 0.8215036 | O8: =O9/2500000 -> 0.836346 | P8: =P9/2500000 -> 0.8000988 | Q8: =Q9/2500000 -> 0.8173816 | R8: =R9/2500000 -> 0.6617068 | S8: =S9/2500000 -> 0.734196 | ... V8: =V9/2500000 -> 0 | W8: 0.8090604 | X8: 0 | Y8: =Y9/2500000 -> 0 | Z8: =Z9/2500000 -> 0 | AA8: =AA9/2500000 -> 0 | AB8: =AB9/2500000 -> 0 | AC8: =AC9/2500000 -> 0 | AD8: =AD9/2500000 -> 0 | AE8: =AE9/2500000 -> 0 | AF8: =AF9/2500000 -> 0 | ... AK8: =AK9/2500000 -> 0 | AM8: =AM9/2500000/AM6 -> 0.61071767
D9: CPO Consume Total | E9: 58900000 | F9: Kg | L9: 172718 | M9: 1461887 | N9: 2053759 | O9: =2100865-10000 -> 2090865 | P9: 2000247 | Q9: 2043454 | R9: 1654267 | S9: 1835490 | T9: 1830941 | U9: 1651108 | AM9: =SUM(G9:U9) -> 16794736
D10: Avg Daily Consump CPO ( MTD ) | AM10: =AM9/AM6 -> 1526794.2
D11: CPO Consume Poram | F11: Kg | L11: =L9-L12 -> 172718 | M11: =M9-M12 -> 1461887 | N11: =N9-N12 -> 2053759 | O11: =O9-O12 -> 2090865 | P11: =P9-P12 -> 2000247 | Q11: =Q9-Q12 -> 2043454 | R11: =R9-R12 -> 1654267 | S11: =S9-S12 -> 1835490 | ... AK11: =AK9-AK12 -> 0 | AM11: =SUM(G11:AK11) -> 16794736
D12: CPO Consume Brand | F12: Kg | L12: =L40+L49+L54 -> 0 | M12: =M40+M49+M54 -> 0 | N12: =N40+N49+N54 -> 0 | O12: =O40+O49+O54 -> 0 | P12: =P40+P49+P54 -> 0 | Q12: =Q40+Q49+Q54 -> 0 | R12: =R40+R49+R54 -> 0 | S12: 0 | T12: =T40+T49+T54 -> 0 | U12: =U40+U49+U54 -> 0 | V12: =V40+V49+V54 -> 0 | W12: 0 | X12: 0 | Y12: =Y40+Y49+Y54 -> 0 | Z12: =Z40+Z49+Z54 -> 0 | AA12: =AA40+AA49+AA54 -> 0 | AB12: =AB40+AB49+AB54 -> 0 | AC12: 0 | AD12: 0 | AE12: =AE40+AE49+AE54 -> 0 | AF12: =AF40+AF49+AF54 -> 0 | AG12: =AG40+AG49+AG54 -> 0 | AH12: =AH40+AH49+AH54 -> 0 | AM12: =SUM(G12:AK12) -> 0
D13: - FFA | E13: 5 | F13: % | L13: 3.6 | M13: =(4.4+3.74)/2 -> 4.07 | N13: =(3.93+3.79)/2 -> 3.86 | O13: 3.97 | P13: 4.03 | Q13: =(4.1+3.79)/2 -> 3.945 | R13: =(4.01+3.79)/2 -> 3.9 | S13: =(4.21+4.01)/2 -> 4.11 | T13: =(4.12+3.89)/2 -> 4.005 | U13: 4.1 | V13: 4.07 | AM13: =SUM(G13:AK13)/AM6 -> 3.9690909 | AO13: rpo feed | AP13: =AP14+AP15 -> 221307 | AR13: tk131 | AS13: ='OIP Fract PMG 2'!T13 -> 133300
D14: - Moist & Impurities | E14: 0.5 | F14: % | L14: 0.38 | M14: =(0.43+0.38)/2 -> 0.405 | N14: =(0.36+0.4)/2 -> 0.38 | O14: 0.39 | P14: 0.41 | Q14: =(0.42+0.39)/2 -> 0.405 | R14: =(0.38+0.39)/2 -> 0.385 | S14: =(0.39+0.4)/2 -> 0.395 | T14: =(0.39+0.47)/2 -> 0.43 | U14: 0.4 | V14: 0.39 | AM14: =SUM(G14:AK14)/AM6 -> 0.39727273 | AO14: olein 56 | AP14: =AM33 -> 182200 | AR14: tk132 | AS14: ='OIP Fract PMG 2'!U13 -> 0
D15: - DOBI | E15: 2,20 Min | F15: % | AM15: =SUM(G15:AK15)/AM6 -> 0 | AO15: stearin 56 | AP15: =AM34 -> 39107 | AR15: after
D16: TANK | L16: 106 | M16: 104106 | N16: 104106 | O16: 104 | P16: 104 | Q16: 104107 | R16: 106107 | S16: 104106 | T16: 104107 | U16: 104 | V16: 106 | AO16: yield olein | AP16: =AP14/(AP14+AP15)*100 -> 82.329072 | AR16: tk131 | AS16: =AS13 -> 133300
D17: Product | AM17: Product | AO17: yield stearin | AP17: =AP15/(AP14+AP15)*100 -> 17.670928 | AR17: tk132 | AS17: =AS14-AP13 -> -221307
D18: OIP RBDPO | F18: Kg | M18: ='OIP Ref PMG 1'!K7 -> 0 | AM18: =SUM(G18:AK18) -> 0
D19: DIRECT RBDPO FRACT | F19: Kg | L19: 169993 | M19: 1372080 | N19: 1888301 | O19: 1997308 | P19: 1895612 | Q19: 1942581 | R19: 1563435 | S19: 1750349 | T19: 1747544 | U19: 1574156 | AM19: =SUM(G19:U19) -> 15901359
D20: RBDPO | E20: 55661000 | F20: Kg | L20: 0 | AM20: =SUM(G20:AK20) -> 0
D21: PFAD | E21: 2827000 | F21: Kg | L21: 0 | M21: 52979 | N21: 80109 | O21: 91693 | P21: 80627 | Q21: 70559 | R21: 67084 | S21: 76310 | T21: 74082 | U21: 62874 | AM21: =SUM(G21:U21) -> 656317
D22: Fractionation
D23: Running Days | F23: Day | P23: 1 | Q23: 1 | AC23: 1 | AF23: 1 | AG23: 1 | AH23: 1 | AM23: =SUM(G23:AK23) -> 6
D24: Avg Daily Consump RBDPO ( MTD ) | F24: Kg | L24: 0 | M24: 0 | N24: 0 | O24: 0 | P24: 0 | Q24: 0 | R24: 0 | S24: 0 | T24: 0 | U24: 0 | V24: 0 | W24: 0 | X24: 0 | Y24: 0 | Z24: 0 | AA24: 0 | AB24: 0 | AC24: 0 | AD24: 0 | AE24: 0 | AF24: 0 | AG24: 0 | AH24: 0 | AI24: 0 | AJ24: 0 | AK24: 0 | AM24: =AM29/AM23 -> 396151.67
D25: Total RBDPO transfer to plant | F25: Kg | AJ25: 0 | AK25: 0 | AM25: =SUM(G25:AK25) -> 0
D26: Stok TK 131 | E26: 559 | F26: ton
D27: Stok TK 132 | E27: 559 | F27: ton
D28: Ratio Run RBDPO | F28: % | L28: =L29/2500000 -> 0 | M28: =M29/2500000 -> 0 | N28: =N29/2500000 -> 0 | O28: =O29/2500000 -> 0 | P28: =P29/2500000 -> 0 | Q28: =Q29/2500000 -> 0 | R28: =R29/2500000 -> 0 | S28: =S29/2500000 -> 0 | ... V28: =V29/2500000 -> 0 | W28: 0.7274628 | X28: 0 | Y28: =Y29/2500000 -> 0 | Z28: =Z29/2500000 -> 0 | AA28: =AA29/2500000 -> 0 | AB28: =AB29/2500000 -> 0 | AC28: 0.52886 | AD28: =AD29/2500000 -> 0 | AE28: =AE29/2500000 -> 0 | AF28: =AF29/2500000 -> 0.21776 | AG28: =AG29/2500000 -> 0.40436 | AH28: =AH29/2500000 -> 0.328644 | AI28: =AI29/2500000 -> 0 | AJ28: =AJ29/2500000 -> 0 | AK28: =AK29/2500000 -> 0 | AM28: =AM29/2500000/AM23 -> 0.15846067
D29: Total Proses RBDPO | E29: 35501000 | F29: Kg | L29: =SUM(L32,L36,L41,L45,L55) -> 0 | M29: =SUM(M32,M36,M41,M45,M55) -> 0 | N29: =SUM(N32,N36,N41,N45,N55) -> 0 | O29: =SUM(O32,O36,O41,O45,O55) -> 0 | P29: =SUM(P32,P36,P41,P45,P55) -> 0 | Q29: =SUM(Q32,Q36,Q41,Q45,Q55) -> 0 | R29: =SUM(R32,R36,R41,R45,R55) -> 0 | S29: =SUM(S32,S36,S41,S45,S55) -> 0 | ... AK29: =SUM(AK32,AK36,AK41,AK45,AK55) -> 0 | AM29: =SUM(G29:AK29) -> 2376910
D30: Sisa Filling Crystalizer | F30: Kg | L30: =L25-L29 -> 0 | M30: =M25-M29 -> 0 | N30: =N25-N29 -> 0 | O30: =O25-O29 -> 0 | P30: =P25-P29 -> 0 | Q30: =Q25-Q29 -> 0 | R30: =R25-R29 -> 0 | S30: =S25-S29 -> 0 | ... AK30: =AK25-AK29 -> 0 | AM30: =SUM(G30:AK30) -> -2376910
D31: Fractionation OLEIN IV 56 | AM31: Olein IV 56
D32: RBDPO Consume | F32: Kg | L32: =L33+L34 -> 0 | M32: =M33+M34 -> 0 | N32: =N33+N34 -> 0 | O32: =O33+O34 -> 0 | P32: =P33+P34 -> 0 | Q32: =Q33+Q34 -> 0 | R32: =R33+R34 -> 0 | S32: =S33+S34 -> 0 | ... AK32: =AK33+AK34 -> 0 | AM32: =SUM(G32:AK32) -> 221307
D33: OLEIN IV 56 | E33: 25000000 | F33: Kg | AF33: 135000 | AH33: 47200 | AM33: =SUM(G33:AK33) -> 182200
D34: STEARIN | E34: 639000 | F34: Kg | AF34: 29064 | AH34: 10043 | AM34: =SUM(G34:AK34) -> 39107
D35: Fractionation OLEIN IV 57 ( Bulk ) | Z35: 0 | AM35: Olein IV 57 ( Bulk )
D36: RBDPO Consume | F36: Kg | L36: =L37+L38 -> 0 | M36: 0 | R36: =R37+R38 -> 0 | S36: 0 | T36: =T37+T38 -> 0 | U36: =U37+U38 -> 0 | V36: =V37+V38 -> 0 | W36: 0 | X36: 0 | AA36: =AA37+AA38 -> 0 | AB36: =AB37+AB38 -> 0 | AC36: 0 | AD36: =AD37+AD38 -> 0 | AE36: =AE37+AE38 -> 0 | AF36: =AF37+AF38 -> 0 | AG36: =AG37+AG38 -> 0 | AH36: =AH37+AH38 -> 0 | AM36: =SUM(G36:AK36) -> 0
D37: OLEIN IV 57 | F37: Kg | L37: 0 | M37: 0 | R37: 0 | S37: 0 | T37: 0 | U37: 0 | V37: 0 | W37: 0 | X37: 0 | AA37: 0 | AB37: 0 | AC37: 0 | AD37: 0 | AE37: 0 | AF37: 0 | AG37: 0 | AM37: =SUM(G37:AK37) -> 0
D38: STEARIN | F38: Kg | L38: 0 | M38: 0 | R38: 0 | S38: 0 | T38: 0 | U38: 0 | V38: 0 | W38: 0 | X38: 0 | AA38: 0 | AB38: 0 | AC38: 0 | AD38: 0 | AE38: 0 | AF38: 0 | AG38: 0 | AM38: =SUM(G38:AK38) -> 0
D39: Fractionation OLEIN IV 57 ( Retail ) | AM39: Olein IV 57 ( Retail )
D40: CPO Consume | F40: Kg | AM40: =SUM(G40:AK40) -> 0
D41: RBDPO Brand Consume | F41: Kg | L41: =L42+L43 -> 0 | M41: 0 | R41: =R42+R43 -> 0 | S41: 0 | T41: =T42+T43 -> 0 | U41: =U42+U43 -> 0 | V41: =V42+V43 -> 0 | W41: 0 | X41: 0 | AA41: =AA42+AA43 -> 0 | AB41: =AB42+AB43 -> 0 | AC41: 0 | AD41: =AD42+AD43 -> 0 | AE41: =AE42+AE43 -> 0 | AF41: =AF42+AF43 -> 0 | AG41: =AG42+AG43 -> 0 | AH41: =AH42+AH43 -> 0 | AM41: =SUM(G41:AK41) -> 0
D42: OLEIN IV 57 Low Color | F42: Kg | L42: 0 | M42: 0 | R42: 0 | S42: 0 | T42: 0 | U42: 0 | V42: 0 | W42: 0 | X42: 0 | AA42: 0 | AB42: 0 | AC42: 0 | AD42: 0 | AE42: 0 | AF42: 0 | AG42: 0 | AM42: =SUM(G42:AK42) -> 0
D43: STEARIN | F43: Kg | L43: 0 | M43: 0 | R43: 0 | S43: 0 | T43: 0 | U43: 0 | V43: 0 | W43: 0 | X43: 0 | AA43: 0 | AB43: 0 | AC43: 0 | AD43: 0 | AE43: 0 | AF43: 0 | AG43: 0 | AM43: =SUM(G43:AK43) -> 0
D44: Fractionation OLEIN IV 58 ( Bulk ) | AM44: Olein IV 58 ( Bulk )
D45: RBDPO Consume | E45: 17143 | F45: Kg | L45: =L46+L47 -> 0 | M45: =M46+M47 -> 0 | N45: =N46+N47 -> 0 | O45: =O46+O47 -> 0 | P45: =P46+P47 -> 0 | Q45: =Q46+Q47 -> 0 | R45: =R46+R47 -> 0 | S45: =S46+S47 -> 0 | ... AK45: =AK46+AK47 -> 0 | AM45: =SUM(G45:AK45) -> 2155603
D46: OLEIN IV 58 | E46: 12000000 | F46: Kg | AF46: 288100 | AG46: 772500 | AH46: 583900 | AM46: =SUM(G46:AK46) -> 1644500
D47: STEARIN | E47: 514300 | F47: Kg | AF47: 92236 | AG47: 238400 | AH47: 180467 | AM47: =SUM(G47:AK47) -> 511103
D48: Fractionation OLEIN IV 58 ( Retail ) | AM48: Olein IV 58 ( Retail )
D49: CPO Consume | F49: Kg | AM49: =SUM(G49:AK49) -> 0
D50: RBDPO Consume | E50: =E51+E52 -> 21429000 | F50: Kg | L50: =L51+L52 -> 0 | M50: 0 | R50: =R51+R52 -> 0 | S50: 0 | T50: =T51+T52 -> 0 | U50: =U51+U52 -> 0 | V50: =V51+V52 -> 0 | W50: 0 | X50: 0 | Y50: =Y51+Y52 -> 0 | Z50: =Z51+Z52 -> 0 | AA50: =AA51+AA52 -> 0 | AB50: =AB51+AB52 -> 0 | AC50: =AC51+AC52 -> 0 | AD50: =AD51+AD52 -> 0 | AE50: =AE51+AE52 -> 0 | AF50: =AF51+AF52 -> 0 | ... AH50: =AH51+AH52 -> 0 | AM50: =SUM(G50:AK50) -> 0
D51: OLEIN IV 58 | E51: 15000000 | F51: Kg | L51: 0 | M51: 0 | R51: 0 | S51: 0 | T51: 0 | U51: 0 | V51: 0 | W51: 0 | X51: 0 | Y51: 0 | Z51: 0 | AA51: 0 | AB51: 0 | AC51: 0 | AD51: 0 | AE51: 0 | AF51: 0 | AG51: 0 | AH51: 0 | AM51: =SUM(G51:AK51) -> 0
D52: STEARIN | E52: 6429000 | F52: Kg | L52: 0 | M52: 0 | R52: 0 | S52: 0 | T52: 0 | U52: 0 | V52: 0 | W52: 0 | X52: 0 | Y52: 0 | Z52: 0 | AA52: 0 | AB52: 0 | AC52: 0 | AD52: 0 | AE52: 0 | AF52: 0 | AG52: 0 | AH52: 0 | AM52: =SUM(G52:AK52) -> 0
D53: Fractionation OLEIN IV 60 | AM53: Olein IV 60
D54: CPO Consume | F54: Kg | AM54: =SUM(G54:AK54) -> 0
D55: RBDPO Brand Consume | E55: =E56+E57 -> 1333300 | F55: Kg | L55: =L56+L57 -> 0 | M55: 0 | S55: =S56+S57 -> 0 | T55: =T56+T57 -> 0 | U55: =U56+U57 -> 0 | V55: =V56+V57 -> 0 | W55: 0 | X55: 0 | Y55: =Y56+Y57 -> 0 | AA55: =AA56+AA57 -> 0 | AB55: =AB56+AB57 -> 0 | AC55: =AC56+AC57 -> 0 | AD55: =AD56+AD57 -> 0 | AE55: =AE56+AE57 -> 0 | AF55: =AF56+AF57 -> 0 | AG55: =AG56+AG57 -> 0 | AH55: =AH56+AH57 -> 0 | AM55: =SUM(G55:AK55) -> 0
D56: OLEIN IV 60 Salvaco | E56: 1250000 | F56: Kg | L56: 0 | M56: 0 | R56: 0 | T56: 0 | U56: 0 | V56: 0 | W56: 0 | X56: 0 | Y56: 0 | AB56: 0 | AC56: 0 | AD56: 0 | AE56: 0 | AF56: 0 | AH56: 0 | AM56: =SUM(G56:AK56) -> 0
D57: SOFT STEARIN | E57: 83300 | F57: Kg | L57: 0 | M57: 0 | R57: 0 | T57: 0 | U57: 0 | V57: 0 | W57: 0 | X57: 0 | Y57: 0 | AB57: 0 | AC57: 0 | AD57: 0 | AE57: 0 | AF57: 0 | AH57: 0 | AM57: =SUM(G57:AK57) -> 0
D58: Ratio Run RBDPO | F58: % | L58: 0 | M58: 0 | R58: 0 | S58: 0 | T58: 0 | U58: 0 | V58: 0 | W58: 0 | X58: 0 | Y58: 0 | Z58: 0 | AA58: 0 | AB58: 0 | AC58: 0 | AD58: 0 | AE58: 0 | AF58: 0 | AG58: 0 | AH58: 0 | AM58: =SUM(G58:AK58) -> 0
D59: YIELD | AM59: Yield
D60: RBDPO | E60: 94.2 | F60: % | L60: =((L20+L19+L18)/(L9))*100 -> 98.422284 | M60: =((M20+M19+M18)/(M9))*100 -> 93.856776 | N60: =((N20+N19+N18)/(N9))*100 -> 91.943651 | O60: =((O20+O19+O18)/(O9))*100 -> 95.52544 | P60: =((P20+P19+P18)/(P9))*100 -> 94.768896 | Q60: =((Q20+Q19+Q18)/(Q9))*100 -> 95.063603 | R60: =((R20+R19+R18)/(R9))*100 -> 94.50923 | S60: =((S20+S19+S18)/(S9))*100 -> 95.361402 | ... AK60: =((AK20+AK19+AK18)/(AK9))*100 -> #DIV/0! | AM60: =((AM20+AM19+AM18)/(AM9))*100 -> 94.680613
D61: PFAD | E61: 5 | F61: % | L61: =(L21/(L9))*100 -> 0 | M61: =(M21/(M9))*100 -> 3.6240147 | N61: =(N21/(N9))*100 -> 3.9006037 | O61: =(O21/(O9))*100 -> 4.3854099 | P61: =(P21/(P9))*100 -> 4.0308522 | Q61: =(Q21/(Q9))*100 -> 3.4529282 | R61: =(R21/(R9))*100 -> 4.05521 | S61: =(S21/(S9))*100 -> 4.1574729 | ... AK61: =(AK21/(AK9))*100 -> #DIV/0! | AM61: =(AM21/(AM9))*100 -> 3.9078733
D62: Olein IV 56 | E62: 82 | F62: % | L62: =L33/(L33+L34)*100 -> #DIV/0! | M62: =M33/(M33+M34)*100 -> #DIV/0! | N62: =N33/(N33+N34)*100 -> #DIV/0! | O62: =O33/(O33+O34)*100 -> #DIV/0! | P62: =P33/(P33+P34)*100 -> #DIV/0! | Q62: =Q33/(Q33+Q34)*100 -> #DIV/0! | R62: =R33/(R33+R34)*100 -> #DIV/0! | S62: =S33/(S33+S34)*100 -> #DIV/0! | ... AK62: =AK33/(AK33+AK34)*100 -> #DIV/0! | AM62: =AM33/(AM33+AM34)*100 -> 82.329072
D63: Stearin | E63: 18 | F63: % | L63: =(L34/L32)*100 -> #DIV/0! | M63: =(M34/M32)*100 -> #DIV/0! | N63: =(N34/N32)*100 -> #DIV/0! | O63: =(O34/O32)*100 -> #DIV/0! | P63: =(P34/P32)*100 -> #DIV/0! | Q63: =(Q34/Q32)*100 -> #DIV/0! | R63: =(R34/R32)*100 -> #DIV/0! | S63: =(S34/S32)*100 -> #DIV/0! | ... AK63: =(AK34/AK32)*100 -> #DIV/0! | AM63: =AM34/(AM33+AM34)*100 -> 17.670928
D64: Olein IV 57 ( Bulk ) | E64: 75 | L64: =(L37/L36)*100 -> #DIV/0! | M64: =(M37/M36)*100 -> #DIV/0! | N64: =(N37/N36)*100 -> #DIV/0! | O64: =(O37/O36)*100 -> #DIV/0! | P64: =(P37/P36)*100 -> #DIV/0! | Q64: =(Q37/Q36)*100 -> #DIV/0! | R64: =(R37/R36)*100 -> #DIV/0! | S64: =(S37/S36)*100 -> #DIV/0! | ... AK64: =(AK37/AK36)*100 -> #DIV/0! | AM64: =(AM42/AM41)*100 -> #DIV/0!
D65: Stearin | E65: 25 | L65: =(L38/L36)*100 -> #DIV/0! | M65: =(M38/M36)*100 -> #DIV/0! | N65: =(N38/N36)*100 -> #DIV/0! | O65: =(O38/O36)*100 -> #DIV/0! | P65: =(P38/P36)*100 -> #DIV/0! | Q65: =(Q38/Q36)*100 -> #DIV/0! | R65: =(R38/R36)*100 -> #DIV/0! | S65: =(S38/S36)*100 -> #DIV/0! | ... AK65: =(AK38/AK36)*100 -> #DIV/0! | AM65: =(AM43/AM41)*100 -> #DIV/0!
D66: Olein IV 57 ( Retail ) | E66: 75 | F66: % | L66: =L42/L41*100 -> #DIV/0! | M66: =M42/M41*100 -> #DIV/0! | N66: =N42/N41*100 -> #DIV/0! | O66: =O42/O41*100 -> #DIV/0! | P66: =P42/P41*100 -> #DIV/0! | Q66: =Q42/Q41*100 -> #DIV/0! | R66: =R42/R41*100 -> #DIV/0! | S66: =S42/S41*100 -> #DIV/0! | ... AK66: =AK42/AK41*100 -> #DIV/0! | AM66: =AM42/AM41*100 -> #DIV/0!
D67: Stearin | E67: 25 | F67: % | L67: =L43/L41*100 -> #DIV/0! | M67: =M43/M41*100 -> #DIV/0! | N67: =N43/N41*100 -> #DIV/0! | O67: =O43/O41*100 -> #DIV/0! | P67: =P43/P41*100 -> #DIV/0! | Q67: =Q43/Q41*100 -> #DIV/0! | R67: =R43/R41*100 -> #DIV/0! | S67: =S43/S41*100 -> #DIV/0! | ... AK67: =AK43/AK41*100 -> #DIV/0! | AM67: =AM43/AM41*100 -> #DIV/0!
D68: Olein IV 58 ( Bulk ) | E68: 70 | F68: % | L68: =L46/(L46+L47)*100 -> #DIV/0! | M68: =M46/(M46+M47)*100 -> #DIV/0! | N68: =N46/(N46+N47)*100 -> #DIV/0! | O68: =O46/(O46+O47)*100 -> #DIV/0! | P68: =P46/(P46+P47)*100 -> #DIV/0! | Q68: =Q46/(Q46+Q47)*100 -> #DIV/0! | R68: =R46/(R46+R47)*100 -> #DIV/0! | S68: =S46/(S46+S47)*100 -> #DIV/0! | ... AK68: =AK46/(AK46+AK47)*100 -> #DIV/0! | AM68: =AM46/(AM46+AM47)*100 -> 76.289558
D69: Stearin | E69: 30 | F69: % | L69: =L47/(L47+L46)*100 -> #DIV/0! | M69: =M47/(M47+M46)*100 -> #DIV/0! | N69: =N47/(N47+N46)*100 -> #DIV/0! | O69: =O47/(O47+O46)*100 -> #DIV/0! | P69: =P47/(P47+P46)*100 -> #DIV/0! | Q69: =Q47/(Q47+Q46)*100 -> #DIV/0! | R69: =R47/(R47+R46)*100 -> #DIV/0! | S69: =S47/(S47+S46)*100 -> #DIV/0! | ... AK69: =AK47/(AK47+AK46)*100 -> #DIV/0! | AM69: =AM47/AM45*100 -> 23.710442
D70: Olein IV 58 ( Retail ) | E70: 70 | F70: % | L70: =L51/(L51+L52)*100 -> #DIV/0! | M70: #DIV/0! | R70: =R51/(R51+R52)*100 -> #DIV/0! | S70: =S51/(S51+S52)*100 -> #DIV/0! | T70: =T51/(T51+T52)*100 -> #DIV/0! | U70: =U51/(U51+U52)*100 -> #DIV/0! | V70: =V51/(V51+V52)*100 -> #DIV/0! | W70: #DIV/0! | X70: =X51/(X51+X52)*100 -> #DIV/0! | Y70: =Y51/(Y51+Y52)*100 -> #DIV/0! | Z70: =Z51/(Z51+Z52)*100 -> #DIV/0! | AA70: =AA51/(AA51+AA52)*100 -> #DIV/0! | AB70: =AB51/(AB51+AB52)*100 -> #DIV/0! | AC70: =AC51/(AC51+AC52)*100 -> #DIV/0! | AD70: =AD51/(AD51+AD52)*100 -> #DIV/0! | AE70: =AE51/(AE51+AE52)*100 -> #DIV/0! | ... AK70: =AK51/(AK51+AK52)*100 -> #DIV/0! | AM70: =AM51/(AM51+AM52)*100 -> #DIV/0!
D71: Stearin | E71: 30 | F71: % | L71: =L52/(L51+L52)*100 -> #DIV/0! | M71: #DIV/0! | R71: =R52/(R51+R52)*100 -> #DIV/0! | S71: =S52/(S51+S52)*100 -> #DIV/0! | T71: =T52/(T51+T52)*100 -> #DIV/0! | U71: =U52/(U51+U52)*100 -> #DIV/0! | V71: =V52/(V51+V52)*100 -> #DIV/0! | W71: #DIV/0! | X71: =X52/(X51+X52)*100 -> #DIV/0! | Y71: =Y52/(Y51+Y52)*100 -> #DIV/0! | Z71: =Z52/(Z51+Z52)*100 -> #DIV/0! | AA71: =AA52/(AA51+AA52)*100 -> #DIV/0! | AB71: =AB52/(AB51+AB52)*100 -> #DIV/0! | AC71: =AC52/(AC51+AC52)*100 -> #DIV/0! | AD71: =AD52/(AD51+AD52)*100 -> #DIV/0! | AE71: =AE52/(AE51+AE52)*100 -> #DIV/0! | ... AK71: =AK52/(AK51+AK52)*100 -> #DIV/0! | AM71: =AM52/(AM51+AM52)*100 -> #DIV/0!
D72: Olein IV 60 | E72: 60 | F72: % | L72: =L56/(L56+L57)*100 -> #DIV/0! | M72: #DIV/0! | R72: =R56/(R56+R57)*100 -> #DIV/0! | S72: =S56/(S56+S57)*100 -> #DIV/0! | T72: =T56/(T56+T57)*100 -> #DIV/0! | U72: =U56/(U56+U57)*100 -> #DIV/0! | V72: =V56/(V56+V57)*100 -> #DIV/0! | W72: #DIV/0! | X72: =X56/(X56+X57)*100 -> #DIV/0! | Y72: =Y56/(Y56+Y57)*100 -> #DIV/0! | Z72: =Z56/(Z56+Z57)*100 -> #DIV/0! | AA72: =AA56/(AA56+AA57)*100 -> #DIV/0! | AB72: =AB56/(AB56+AB57)*100 -> #DIV/0! | AC72: =AC56/(AC56+AC57)*100 -> #DIV/0! | AD72: =AD56/(AD56+AD57)*100 -> #DIV/0! | AE72: =AE56/(AE56+AE57)*100 -> #DIV/0! | ... AK72: =AK56/(AK56+AK57)*100 -> #DIV/0! | AM72: =AM56/(AM57+AM56)*100 -> #DIV/0!
D73: Soft Stearin | E73: 40 | F73: % | L73: =L57/L55*100 -> #DIV/0! | M73: #DIV/0! | R73: =R57/R55*100 -> #DIV/0! | S73: =S57/S55*100 -> #DIV/0! | T73: =T57/T55*100 -> #DIV/0! | U73: =U57/U55*100 -> #DIV/0! | V73: =V57/V55*100 -> #DIV/0! | W73: #DIV/0! | X73: =X57/X55*100 -> #DIV/0! | Y73: =Y57/Y55*100 -> #DIV/0! | Z73: =Z57/Z55*100 -> #DIV/0! | AA73: =AA57/AA55*100 -> #DIV/0! | AB73: =AB57/AB55*100 -> #DIV/0! | AC73: =AC57/AC55*100 -> #DIV/0! | AD73: =AD57/AD55*100 -> #DIV/0! | AE73: =AE57/AE55*100 -> #DIV/0! | ... AK73: =AK57/AK55*100 -> #DIV/0! | AM73: =AM57/(AM56+AM57)*100 -> #DIV/0!
C74: 2 | D74: CHEMICAL CONSUMABLE | AM74: Chemical
D75: Bleaching Earth (BE) to Hopper | E75: 9 | F75: Kg | L75: 1770 | M75: 9750 | N75: 13246 | O75: 14055 | P75: 13993 | Q75: 14004 | R75: 10832 | S75: 12089 | T75: 10781 | U75: 9986 | V75: 5632 | AM75: =SUM(G75:AK75) -> 116138
D76: Note : BE Aktivasi start tgl 23 Bulan September (0,67 %) | F76: % | L76: =L75/(L11)*100 -> 1.0247919 | M76: =M75/(M11)*100 -> 0.66694621 | N76: =N75/(N11)*100 -> 0.6449637 | O76: =O75/(O11)*100 -> 0.67220983 | P76: =P75/(P11)*100 -> 0.6995636 | Q76: =Q75/(Q11)*100 -> 0.68531026 | R76: =R75/(R11)*1000 -> 6.5479152 | S76: =S75/(S11)*1000 -> 6.5862522 | T76: =T75/(T11)*1000 -> 5.8882291 | U76: =U75/(U11)*1000 -> 6.0480598 | V76: =V75/(V11)*1000 -> #DIV/0! | W76: =W75/(W11)*1000 -> #DIV/0! | X76: =X75/(X11)*100 -> #DIV/0! | Y76: =Y75/(Y11)*100 -> #DIV/0! | Z76: =Z75/(Z11)*100 -> #DIV/0! | AA76: =AA75/(AA11)*100 -> #DIV/0! | AB76: =AB75/(AB11)*100 -> #DIV/0! | AC76: =AC75/(AC11)*100 -> #DIV/0! | AD76: =AD75/(AD11)*100 -> #DIV/0! | AE76: =AE75/(AE11)*100 -> #DIV/0! | ... AK76: =AK75/(AK11)*100 -> #DIV/0! | AM76: =AM75/(AM11)*100 -> 0.69151429
D77: TK 630 A ( TRANSFER ) | E77: 40000 | F77: Kg | V77: 0 | W77: 0 | X77: 0 | Y77: 0 | AA77: 0 | AB77: 0 | AC77: 0 | AD77: 0 | AE77: 0 | AF77: 0 | AG77: 0 | AH77: 0 | AI77: 0 | AJ77: 0 | AK77: 0 | AM77: =SUM(G77:AK77) -> 0
D79: TK 630 B ( TRANSFER ) | E79: 40000 | F79: Kg | V79: 0 | W79: 0 | X79: 0 | Y79: 0 | Z79: 0 | AA79: 0 | AB79: 0 | AC79: 0 | AD79: 0 | AE79: 0 | AF79: 0 | AG79: 0 | AH79: 0 | AI79: 0 | AJ79: 0 | AK79: 0 | AM79: =SUM(G79:AK79) -> 0
D81: Bleaching Earth (BE) to Branded Spec | E81: 18 | F81: Kg | L81: 0 | M81: 0 | N81: 0 | O81: 0 | P81: 0 | Q81: 0 | R81: 0 | S81: 0 | T81: 0 | U81: 0 | V81: 0 | W81: 0 | X81: 0 | Y81: 0 | Z81: 0 | AA81: 0 | AB81: 0 | AC81: 0 | AD81: 0 | AE81: 0 | AF81: 0 | AG81: 0 | AH81: 0 | AI81: 0 | AJ81: 0 | AK81: 0 | AM81: =SUM(G81:AK81) -> 0
D82: Bleaching Earth (BE) to Silo
D84: Aktual Pengiisian BE | F84: Kg | L84: 0 | M84: 11000 | N84: 16000 | O84: 15000 | P84: 13000 | Q84: 14000 | R84: 17000 | S84: 8000 | T84: 12000 | U84: 7000 | V84: 0 | AM84: =SUM(G84:AK84) -> 113000
L85: =L84/L9*100 -> 0 | M85: =M84/M9*100 -> 0.75245214 | N85: =N84/N9*100 -> 0.77905928 | O85: =O84/O9*100 -> 0.71740643 | P85: =P84/P9*100 -> 0.64991973 | Q85: =Q84/Q9*100 -> 0.68511452 | R85: =R84/R9*100 -> 1.0276455 | S85: =S84/S9*100 -> 0.43585092 | ... AK85: =AK84/AK9*100 -> #DIV/0! | AM85: =AM84/AM9*100 -> 0.67282987
D86: Phosporic Acid (PA) | E86: 0.6 | F86: Kg | L86: 90.48 | M86: 661.126 | N86: 1028.412 | O86: 1068.056 | P86: 1042.404 | Q86: 1040.072 | R86: 831.358 | S86: 994.598 | T86: 884.994 | U86: 792.88 | V86: 426.756 | AM86: =SUM(G86:AK86) -> 8861.136
F87: % | L87: =L86/(L9)*100 -> 0.05238597 | M87: =M86/(M9)*100 -> 0.045224152 | N87: =N86/(N9)*100 -> 0.050074619 | O87: =O86/(O9)*100 -> 0.051082016 | P87: =P86/(P9)*100 -> 0.052113764 | Q87: =Q86/(Q9)*100 -> 0.050897745 | R87: =R86/(R9)*1000 -> 0.5025537 | S87: =S86/(S9)*1000 -> 0.54187056 | T87: =T86/(T9)*1000 -> 0.48335473 | U87: =U86/(U9)*1000 -> 0.48021086 | V87: =V86/(V9)*1000 -> #DIV/0! | W87: =W86/(W9)*1000 -> #DIV/0! | X87: =X86/(X9)*1000 -> #DIV/0! | Y87: =Y86/(Y9)*1000 -> #DIV/0! | ... AK87: =AK86/(AK9)*1000 -> #DIV/0! | AM87: =AM86/AM9*1000 -> 0.52761389
C88: 3 | D88: OIL LOSSES | E88: 0.7 | F88: % | L88: =((SUM(L19:L21))-(SUM(L9)))/(SUM(L9))*100 -> -1.5777163 | M88: =((SUM(M19:M21))-(SUM(M9)))/(SUM(M9))*100 -> -2.5192098 | N88: =((SUM(N19:N21))-(SUM(N9)))/(SUM(N9))*100 -> -4.1557456 | O88: =((SUM(O19:O21))-(SUM(O9)))/(SUM(O9))*100 -> -0.089149706 | P88: =((SUM(P19:P21))-(SUM(P9)))/(SUM(P9))*100 -> -1.2002518 | Q88: =((SUM(Q19:Q21))-(SUM(Q9)))/(SUM(Q9))*100 -> -1.4834687 | R88: =((SUM(R19:R21))-(SUM(R9)))/(SUM(R9))*100 -> -1.4355603 | S88: =((SUM(S19:S21))-(SUM(S9)))/(SUM(S9))*100 -> -0.48112493 | ... AK88: =((SUM(AK19:AK21))-(SUM(AK9)))/(SUM(AK9))*100 -> #DIV/0! | AM88: =((SUM(AM18:AM21))-(SUM(AM9)))/(SUM(AM9))*100 -> -1.4115137
F89: Kg | L89: =L88%*L9 -> -2725 | M89: =M88%*M9 -> -36828 | N89: =N88%*N9 -> -85349 | O89: =O88%*O9 -> -1864 | P89: =P88%*P9 -> -24008 | Q89: =Q88%*Q9 -> -30314 | R89: =R88%*R9 -> -23748 | S89: =S88%*S9 -> -8831 | ... AK89: =AK88%*AK9 -> #DIV/0! | AM89: =AM88%*AM9 -> -237060
D90: % Oil Content | E90: 22 | F90: % | M90: 17.18 | N90: 17.18 | O90: 17.14 | P90: 17.13 | Q90: 17.1 | R90: 17.1 | S90: 17.13 | T90: 17.13 | U90: 17.1 | V90: 17.16 | AM90: =AVERAGE(G90:AK90) -> 17.135
D91: Spent Bleaching Earth | F91: Kg | L91: =SUM(L75,L81)+(L90%*SUM(L75,L81)) -> 1770 | M91: =SUM(M75,M81)+(M90%*SUM(M75,M81)) -> 11425.05 | N91: =SUM(N75,N81)+(N90%*SUM(N75,N81)) -> 15521.663 | O91: =SUM(O75,O81)+(O90%*SUM(O75,O81)) -> 16464.027 | P91: =SUM(P75,P81)+(P90%*SUM(P75,P81)) -> 16390.001 | Q91: =SUM(Q75,Q81)+(Q90%*SUM(Q75,Q81)) -> 16398.684 | R91: =SUM(R75,R81)+(R90%*SUM(R75,R81)) -> 12684.272 | S91: =SUM(S75,S81)+(S90%*SUM(S75,S81)) -> 14159.846 | ... AK91: =SUM(AK75,AK81)+(AK90%*SUM(AK75,AK81)) -> 0 | AM91: =SUM(AM75,AM81)+(AM90%*SUM(AM75,AM81))/AM6 -> 117947.11
C92: 4 | D92: PACKAGING (Brand Salvaco) | AM92: Packaging
D93: Olein IV 60 Received | F93: Kg | AM93: 0
D94: Olein IV 60 Consume | F94: Kg | AM94: 0
D95: - finished product | F95: Kg | L95: 0 | M95: 0 | N95: 0 | O95: 0 | P95: 0 | Q95: 0 | R95: 0 | S95: 0 | T95: 0 | U95: 0 | V95: 0 | W95: 0 | X95: 0 | Y95: 0 | Z95: 0 | AA95: 0 | AB95: 0 | AC95: 0 | AD95: 0 | AE95: 0 | AF95: 0 | AG95: 0 | AH95: 0 | AM95: 0
D96: - sample | F96: Kg | L96: 0 | M96: 0 | N96: 0 | O96: 0 | P96: 0 | Q96: 0 | R96: 0 | S96: 0 | T96: 0 | U96: 0 | V96: 0 | W96: 0 | X96: 0 | Y96: 0 | Z96: 0 | AA96: 0 | AB96: 0 | AC96: 0 | AD96: 0 | AE96: 0 | AF96: 0 | AG96: 0 | AH96: 0 | AM96: 0
D97: - remelt, flushing, downgrade | F97: Kg | L97: 0 | M97: 0 | N97: 0 | O97: 0 | P97: 0 | Q97: 0 | R97: 0 | S97: 0 | T97: 0 | U97: 0 | V97: 0 | W97: 0 | X97: 0 | Y97: 0 | Z97: 0 | AA97: 0 | AB97: 0 | AC97: 0 | AD97: 0 | AE97: 0 | AF97: 0 | AG97: 0 | AH97: 0 | AM97: 0
D98: Carton | AM98: Carton
D99: Salvaco 1 Liter | F99: Box | AM99: 0
D100: Salvaco 2 Liter | F100: Box | AM100: 0 | AW100: 37542
D101: Pouch | AM101: Pouch
D102: Salvaco 1 Liter | F102: Pouch | L102: 0 | M102: 0 | N102: 0 | O102: 0 | P102: 0 | Q102: 0 | R102: 0 | S102: 0 | T102: 0 | U102: 0 | V102: 0 | W102: 0 | X102: 0 | Y102: 0 | Z102: 0 | AA102: 0 | AB102: 0 | AC102: 0 | AD102: 0 | AE102: 0 | AF102: 0 | AG102: 0 | AH102: 0 | AM102: 0
D103: Salvaco 2 Liter | F103: Pouch | L103: 0 | M103: 0 | N103: 0 | O103: 0 | P103: 0 | Q103: 0 | R103: 0 | S103: 0 | T103: 0 | U103: 0 | V103: 0 | W103: 0 | X103: 0 | Y103: 0 | Z103: 0 | AA103: 0 | AB103: 0 | AC103: 0 | AD103: 0 | AE103: 0 | AF103: 0 | AG103: 0 | AH103: 0 | AM103: 0
...

Sheet OIP Ref PMG 1
B4: Oil In Plant (OIP) Refinery pmg | I4: Oktober | J4: OIP | M4: TK131 RPO | P4: TK132 RPO | S4: TOTAL STOK RPO DI PLANT
B5: Vessel | C5: Operating Volume (m3) | D5: Oil Density (kg/m3) | E5: MT | F5: Level yg diisi | G5: Actual OIP (Kg) | I5: Tanggal | J5: Opening Stock | K5: Closing Stock | L5: balance stok | M5: Opening Stock | N5: Closing Stock | O5: CONSUMP stok | P5: Opening Stock | Q5: Closing Stock | R5: CONSUMP stok
B6: 2MX312 | C6: 5.67 | D6: 850 | E6: =C6*D6/1000 -> 4.8195 | G6: =(F6*E6/100)*1000 -> 0 | I6: 46023 | L6: =J6-K6 -> 0
B7: 2VE611A | C7: 47.22 | D7: 850 | E7: =C7*D7/1000 -> 40.137 | G7: =(F7*E7/100)*1000 -> 0 | I7: 46024 | L7: =J7-K7 -> 0
B8: 2VE611B | C8: 47.22 | D8: 850 | E8: =C8*D8/1000 -> 40.137 | G8: =(F8*E8/100)*1000 -> 0 | I8: 46025 | L8: =J8-K8 -> 0
B9: 2VE612 | C9: 35.68 | D9: 850 | E9: =C9*D9/1000 -> 30.328 | G9: =(F9*E9/100)*1000 -> 0 | I9: 46026 | L9: =J9-K9 -> 0
B10: 2VE661 | C10: 10.8 | D10: 850 | E10: =C10*D10/1000 -> 9.18 | G10: =(F10*E10/100)*1000 -> 0 | I10: 46027 | L10: =J10-K10 -> 0
B11: FL621 | C11: 10.1 | D11: 850 | E11: =C11*D11/1000 -> 8.585 | G11: =(F11*E11/100)*1000 -> 0 | I11: 46028 | J11: 0 | K11: 169993 | L11: =J11-K11 -> -169993
B12: FL622 | C12: 10.1 | D12: 850 | E12: =C12*D12/1000 -> 8.585 | G12: =(F12*E12/100)*1000 -> 0 | I12: 46029 | J12: =K11 -> 169993 | K12: 298276 | L12: =J12-K12 -> -128283
B13: FL623 | C13: 10.1 | D13: 850 | E13: =C13*D13/1000 -> 8.585 | G13: =(F13*E13/100)*1000 -> 0 | I13: 46030 | J13: =K12 -> 298276 | K13: 300521 | L13: =J13-K13 -> -2245 | N13: 0 | Q13: 174609
B14: FL624 | C14: 10.1 | D14: 850 | E14: =C14*D14/1000 -> 8.585 | G14: =(F14*E14/100)*1000 -> 0 | I14: 46031 | J14: =K13 -> 300521 | K14: 291536 | L14: =J14-K14 -> 8985 | N14: 44191 | P14: 174609 | Q14: 38852 | R14: =P14-Q14 -> 135757 | S14: =R14+O14+L14 -> 144742
B15: FL625 | C15: 10.1 | D15: 850 | E15: =C15*D15/1000 -> 8.585 | G15: =(F15*E15/100)*1000 -> 0 | I15: 46032 | J15: =K14 -> 291536 | K15: 266295 | L15: =J15-K15 -> 25241 | M15: 44191 | N15: 405272 | O15: =M15-N15 -> -361081 | P15: 38852 | Q15: 38852 | R15: =P15-Q15 -> 0 | S15: =R15+O15+L15 -> -335840
B16: 2VE701 | C16: 72.13 | D16: 850 | E16: =C16*D16/1000 -> 61.3105 | G16: =(F16*E16/100)*1000 -> 0 | I16: 46033 | J16: =K15 -> 266295 | K16: 280865 | L16: =J16-K16 -> -14570
B17: 2VE751 | C17: 4.28 | D17: 860 | E17: =C17*D17/1000 -> 3.6808 | G17: =(F17*E17/100)*1000 -> 0 | I17: 46034 | J17: =K16 -> 280865 | K17: 263772 | L17: =J17-K17 -> 17093
B18: 2HE721A (tube) | C18: 10 | D18: 810 | E18: =C18*D18/1000 -> 8.1 | G18: =(F18*E18/100)*1000 -> 0 | I18: 46035 | J18: =K17 -> 263772 | K18: 292150 | L18: =J18-K18 -> -28378
B19: 2HE721A (shell) | C19: 21.8 | D19: 800 | E19: =C19*D19/1000 -> 17.44 | G19: =(F19*E19/100)*1000 -> 0 | I19: 46036 | J19: =K18 -> 292150 | K19: 270324 | L19: =J19-K19 -> 21826
B20: HE721B (tube) | C20: 10 | D20: 810 | E20: =C20*D20/1000 -> 8.1 | G20: =(F20*E20/100)*1000 -> 0 | I20: 46037 | J20: =K19 -> 270324 | K20: 264646 | L20: =J20-K20 -> 5678
B21: 2HE722 | C21: 11.4 | D21: 790 | E21: =C21*D21/1000 -> 9.006 | G21: =(F21*E21/100)*1000 -> 0 | I21: 46038 | J21: =K20 -> 264646 | K21: 135284 | L21: =J21-K21 -> 129362
B22: 2PR731 | C22: 14 | D22: 790 | E22: =C22*D22/1000 -> 11.06 | G22: =(F22*E22/100)*1000 -> 0 | I22: 46039 | L22: =J22-K22 -> 0
B23: 2DE732 | C23: 149.76 | D23: 790 | E23: =C23*D23/1000 -> 118.3104 | G23: =(F23*E23/100)*1000 -> 0 | I23: 46040 | L23: =J23-K23 -> 0
C24: =SUM(C6:C23) -> 490.46 | E24: =SUM(E6:E23) -> 404.5342 | I24: 46041 | L24: =J24-K24 -> 0
F25: Total OIP = | G25: =SUM(G6:G24) -> 0 | I25: 46042 | L25: =J25-K25 -> 0
I26: 46043 | L26: =J26-K26 -> 0
I27: 46044 | L27: =J27-K27 -> 0
I28: 46045 | L28: =J28-K28 -> 0
I29: 46046 | L29: =J29-K29 -> 0
I30: 46047 | L30: =J30-K30 -> 0
H31: 0 | I31: 46048 | L31: =J31-K31 -> 0
I32: 46049 | L32: =J32-K32 -> 0
I33: 46050 | L33: =J33-K33 -> 0
I34: 46051 | L34: =J34-K34 -> 0
I35: 46052 | L35: =J35-K35 -> 0
I36: 46053 | L36: =J36-K36 -> 0
B38: Solar Daily Tank HPB
B39: 2TK726 | C39: =5.3+0.78 -> 6.08 | D39: 840 | E39: =C39*D39/1000 -> 5.1072 | F39: 0 | G39: =F39*E39/100*1000 -> 0
B41: Stock Chemicals In Plant
C42: Sisa Stok Di Lap | D42: Order | E42: Consumption
B43: BE
B44: 630A | D44: 298
B45: 630B
B46: H3PO4
B47: NaOH
B48: Citrid Acid

Sheet Peformance test Fract 1
C1: PT.INDUSTRI NABATI LESTARI
C2: Pabrik Minyak Goreng ( PMG 2 )
C3: Kantor Pusat: Komp. KEK Sei Mangkei, Kav.2-3, Kec. Bosar Maligas, Kab. Simalungun, Sumatera Utara, 21184
C4: ACTUAL PEFORMANCE / CONSUMPT REPORT FRAKSINASI PLANT | H4: Trial | I4: 1
H5: Start / Date / Time | I5: 17/12/24 ( 07.00 Wib )
H6: Finish / Date / Time | I6: 17/12/24 ( 07.00 Wib )
A8: No | B8: ITEM | C8: Kontrak LIPICO | D8: UOM | E8: TOTALIZER
A10: 1 | B10: PRODUCTION | C10: IV 56 | D10: 24 jam | E10: BEFORE | F10: AFTER | G10: TOTAL | H10: YIELD % | I10: STATUS/REMAKS
B11: Fraksinasi
B12: Running Days
B13: Incoming CPO
B14: Ratio Run CPO
B15: RBDPO Consume Total | C15: 2500 | D15: TPD | E15: 8982.8 | F15: 11717.8 | G15: =F15-E15 -> 2735 | H15: =G15/25000*10 -> 1.094 | I15: OK
B16: Avg Daily Consump CPO ( MTD )
B17: CPO Consume Poram | C17: 29045000
B18: CPO Consume Brand | C18: 7314000 | E18: =E49+E58+E63 -> 0
B19: QUALITY
B20: - FFA | C20: 0.1 | D20: % Max | H20: 0.063
B21: - Moist & Impurities | C21: 0.1 | D21: % Max | H21: 0.05
B22: - IV | C22: 52 - 52,5 | H22: 51.8
B23: - LC | H23: 2,6/20
B24: - Temp | C24: 68 | D24: ˚C Min | H24: 65
B25: TANK | H25: 108/109
B26: Product
B27: OLEIN IV 56 | C27: =C15*84% -> 2100 | D27: TPD | E27: 6537.1 | F27: 8213 | G27: =F27-E27 -> 1675.9 | H27: =G27/(G27+G32) -> 0.82838219 | I27: OK
B28: QUALITY
B29: - IV | C29: 56 | D29: Min
B30: - LC
B31: - Cloud Point ( metter ) | C31: 10 | D31: ˚C Max
B32: STEARIN | C32: =C15*16% -> 400 | E32: 2268.1 | F32: 2615.3 | G32: =F32-E32 -> 347.2 | H32: =G32/(G32+G27) -> 0.17161781 | I32: OK
B33: Fractionation
B34: Running Days
B35: Filling Langsung CR Fr Refinery | E35: 0
B36: Total Filling Crystalizer ( Feed ) | E36: 392100
B37: Avg Daily Consump RPO ( MTD )
B38: Total Proses RBDPO | E38: =SUM(E41,E45,E50,E54,E64) -> 0
B39: Sisa Filling Crystalizer | E39: =E36-E38 -> 392100
B40: Fractionation OLEIN IV 56
B41: RBDPO Consume | E41: =E42+E43 -> 0
B42: OLEIN IV 56 | E42: 0
B43: STEARIN | E43: 0
B44: Fractionation OLEIN IV 57 ( Bulk )
B45: RBDPO Consume | E45: =E46+E47 -> 0
B46: OLEIN IV 57 | E46: 0
B47: STEARIN | E47: 0
B48: Fractionation OLEIN IV 57 ( Retail )
B49: CPO Consume
B50: RBDPO Brand Consume | E50: =E51+E52 -> 0
B51: OLEIN IV 57 Low Color | E51: 0
B52: STEARIN | E52: 0
B53: Fractionation OLEIN IV 58 ( Bulk )
B54: RBDPO Consume | C54: =C55+C56 -> 21429000 | E54: =E55+E56 -> 0
B55: OLEIN IV 58 | C55: 15000000
B56: STEARIN | C56: 6429000
B57: Fractionation OLEIN IV 58 ( Retail )
B58: CPO Consume
B59: RBDPO Consume | C59: =C60+C61 -> 21429000 | E59: =E60+E61 -> 0
B60: OLEIN IV 58 | C60: 15000000 | E60: 0
B61: STEARIN | C61: 6429000 | E61: 0
B62: Fractionation OLEIN IV 60
B63: CPO Consume
B64: RBDPO Brand Consume | E64: =E66+E67 -> 0
B65: OLEIN IV 60 Bulk | E65: 0
B66: OLEIN IV 60 Salvaco | E66: 0
B67: SOFT STEARIN | E67: 0
B68: Ratio Run RBDPO | E68: 0
B69: YIELD
B70: RBDPO | C70: 94.2 | E70: =(#REF!/(E15))*100 -> #REF!
B71: PFAD | C71: 5 | E71: =(E32/(E15))*100 -> 25.249365
B72: Olein IV 56 | C72: 82 | E72: =E42/(E42+E43)*100 -> #DIV/0!
B73: Stearin | C73: 18 | E73: =(E43/E41)*100 -> #DIV/0!
B74: Olein IV 57 ( Bulk ) | C74: 75 | E74: =(E46/E45)*100 -> #DIV/0!
B75: Stearin | C75: 25 | E75: =(E47/E45)*100 -> #DIV/0!
B76: Olein IV 57 ( Retail ) | C76: 75 | E76: =E51/E50*100 -> #DIV/0!
B77: Stearin | C77: 25 | E77: =E52/E50*100 -> #DIV/0!
B78: Olein IV 58 ( Bulk ) | C78: 70 | E78: =E55/(E55+E56)*100 -> #DIV/0!
B79: Stearin | C79: 30 | E79: =E56/(E56+E55)*100 -> #DIV/0!
B80: Olein IV 58 ( Retail ) | C80: 70 | E80: =E60/(E60+E61)*100 -> #DIV/0!
B81: Stearin | C81: 30 | E81: =E61/(E60+E61)*100 -> #DIV/0!
B82: Olein IV 60 | C82: 60 | E82: =E65/E64*100 -> #DIV/0!
B83: Soft Stearin | C83: 40 | E83: =E67/E64*100 -> #DIV/0!
B84: QUALITY
B85: - IV | C85: 32 | D85: Max
B86: - Melting Point | C86: 52-52,5 | D86: ˚C Min
A87: 2 | B87: STEAM CONSUMPTION | E87: BEFORE | F87: AFTER | G87: TOTAL | H87: Kg/Ton RBDPO
B88: Incoming | C88: 408000 | D88: Kg/Day | G88: 183211
B89: Distribution to
B90: fraksinasi | C90: 87.5 | D90: Kg/Day | E90: 308052 | F90: 366933 | G90: =F90-E90 -> 58881 | H90: =G90/G15 -> 21.528702 | I90: OK
C91: =C90/2000 -> 0.04375
C92: =C90/2.5 -> 35 | D92: Kg/ton
B93: Fractionation | C93: 122000
B94: Others ( Tank farm & spurging OSBL ) | C94: 106000 | D94: Kg/Day
B95: Total | C95: 408000 | D95: Kg/Day | G95: =SUM(G90,G93,G94) -> 58881
A96: 3 | B96: WATER CONSUMPTION | E96: BEFORE | F96: AFTER | G96: TOTAL | H96: M³/Ton RBDPO
B97: Incoming from Kinra | C97: 1100 | D97: M³/Day | G97: 818
B98: Outgoing
B99: Softener Product (to Fraksinasi ) | C99: 0.13 | D99: M³/Day | E99: 58 | F99: 106 | G99: =F99-E99 -> 48 | H99: =G99/G15 -> 0.017550274
B100: Softener Product (to Fractionation) | C100: 179.63
C101: =C99/2500 -> 5.2e-05 | D101: M³/ton
B102: RO Product | C102: 491.59 | D102: M³/Day | G102: 304
...

Sheet Peformance Test REFINERY 1
C1: PT.INDUSTRI NABATI LESTARI
C2: Pabrik Minyak Goreng ( PMG 2 )
C3: Kantor Pusat: Komp. KEK Sei Mangkei, Kav.2-3, Kec. Bosar Maligas, Kab. Simalungun, Sumatera Utara, 21184
C4: ACTUAL PEFORMANCE / CONSUMPT REPORT REFINERY PLANT | H4: Peformance | I4: 1
H5: Start / Date / Time | I5: 17/12/24 ( 21.00 Wib )
H6: Finish / Date / Time | I6: 18/12/24 ( 21.00 Wib )
A7: No | B7: ITEM | C7: Kontrak LIPICO | D7: UOM | E7: TOTALIZER
A9: 1 | B9: PRODUCTION | E9: BEFORE | F9: AFTER | G9: TOTAL | H9: Yield ( % ) | I9: STATUS/REMAKS
B10: Refinery
B11: Running Days
B12: Incoming CPO
B13: Ratio Run CPO
B14: CPO Consume Total | C14: 2500 | D14: TPD | E14: 13533.82 | F14: 16053.42 | G14: =F14-E14 -> 2519.6 | I14: OK
B15: Avg Daily Consump CPO ( MTD )
B16: CPO Consume Poram | C16: 29045000
B17: CPO Consume Brand | C17: 7314000 | E17: =E53+E62+E67 -> 0
B18: - FFA | C18: 5 | D18: % | G18: 4
B19: - Moist & Impurities | C19: 0.5 | D19: % | G19: 0.41
B20: - DOBI | C20: 2.2 | D20: Min | G20: 2.42
B21: - TOTOX 2PV + AV | C21: 12 | D21: Max | G21: N/A
B22: - FE Content | C22: < 5 | D22: ppm | G22: N/A
B23: - PV | C23: < 4 | D23: Meg/kg | G23: N/A
B24: - Phosporus Max | C24: 25 | D24: ppm | G24: N/A
B25: TANK / TEMP | C25: 50 | D25: ˚C | G25: 50
B26: Product
B27: RBDPO | C27: =C14*94.2% -> 2355 | D27: TPD | E27: 12357.54 | F27: 14705.95 | G27: =F27-E27 -> 2348.41 | H27: =G27/G14 -> 0.93205668
B28: - FFA | C28: 0.05 | D28: % | G28: 0.06
B29: - Moist & Impurities | C29: 0.03 | D29: % | G29: 0.05
B30: - Peroxide value | D30: Nil | G30: -
B31: - Phosporous max | C31: 2 | D31: ppm | G31: N/A
B32: - LC | C32: 2.5 | D32: % | G32: 2.5
B33: - Aom stability min ( hr ) | C33: 60 | D33: min ( hr ) | G33: N/A
B34: - teste & Odor | C34: bland/Odorless | G34: N/A
B35: - temp max ( C ) | C35: 50 | D35: max˚C | G35: 50
B36: PFAD | C36: =C14*5% -> 125 | D36: TPD | E36: 572.71 | F36: 675.39 | G36: =F36-E36 -> 102.68 | H36: =G36/G14 -> 0.0407525
B37: Fractionation
B38: Running Days
B39: Filling Langsung CR Fr Refinery | E39: 0
B40: Total Filling Crystalizer ( Feed ) | E40: 392100
B41: Avg Daily Consump RPO ( MTD )
B42: Total Proses RBDPO | E42: =SUM(E45,E49,E54,E58,E68) -> 0
B43: Sisa Filling Crystalizer | E43: =E40-E42 -> 392100
B44: Fractionation OLEIN IV 56
B45: RBDPO Consume | E45: =E46+E47 -> 0
B46: OLEIN IV 56 | E46: 0
B47: STEARIN | E47: 0
B48: Fractionation OLEIN IV 57 ( Bulk )
B49: RBDPO Consume | E49: =E50+E51 -> 0
B50: OLEIN IV 57 | E50: 0
B51: STEARIN | E51: 0
B52: Fractionation OLEIN IV 57 ( Retail )
B53: CPO Consume
B54: RBDPO Brand Consume | E54: =E55+E56 -> 0
B55: OLEIN IV 57 Low Color | E55: 0
B56: STEARIN | E56: 0
B57: Fractionation OLEIN IV 58 ( Bulk )
B58: RBDPO Consume | C58: =C59+C60 -> 21429000 | E58: =E59+E60 -> 0
B59: OLEIN IV 58 | C59: 15000000
B60: STEARIN | C60: 6429000
B61: Fractionation OLEIN IV 58 ( Retail )
B62: CPO Consume
B63: RBDPO Consume | C63: =C64+C65 -> 21429000 | E63: =E64+E65 -> 0
B64: OLEIN IV 58 | C64: 15000000 | E64: 0
B65: STEARIN | C65: 6429000 | E65: 0
B66: Fractionation OLEIN IV 60
B67: CPO Consume
B68: RBDPO Brand Consume | E68: =E70+E71 -> 0
B69: OLEIN IV 60 Bulk | E69: 0
B70: OLEIN IV 60 Salvaco | E70: 0
B71: SOFT STEARIN | E71: 0
B72: Ratio Run RBDPO | E72: 0
B73: YIELD
B74: RBDPO | C74: 94.2 | E74: =(E27/(E14))*100 -> 91.308588
B75: PFAD | C75: 5 | E75: =(E36/(E14))*100 -> 4.2316951
B76: Olein IV 56 | C76: 82 | E76: =E46/(E46+E47)*100 -> #DIV/0!
B77: Stearin | C77: 18 | E77: =(E47/E45)*100 -> #DIV/0!
B78: Olein IV 57 ( Bulk ) | C78: 75 | E78: =(E50/E49)*100 -> #DIV/0!
B79: Stearin | C79: 25 | E79: =(E51/E49)*100 -> #DIV/0!
B80: Olein IV 57 ( Retail ) | C80: 75 | E80: =E55/E54*100 -> #DIV/0!
B81: Stearin | C81: 25 | E81: =E56/E54*100 -> #DIV/0!
B82: Olein IV 58 ( Bulk ) | C82: 70 | E82: =E59/(E59+E60)*100 -> #DIV/0!
B83: Stearin | C83: 30 | E83: =E60/(E60+E59)*100 -> #DIV/0!
B84: Olein IV 58 ( Retail ) | C84: 70 | E84: =E64/(E64+E65)*100 -> #DIV/0!
B85: Stearin | C85: 30 | E85: =E65/(E64+E65)*100 -> #DIV/0!
B86: Olein IV 60 | C86: 60 | E86: =E69/E68*100 -> #DIV/0!
B87: Soft Stearin | C87: 40 | E87: =E71/E68*100 -> #DIV/0!
B88: - FFA | C88: ~93 | D88: % | G88: 90.21
B89: - Moist & Impurities | C89: 0.5 | D89: % | G89: 0.33
A90: 2 | B90: CHEMICAL CONSUMABLE | E90: BEFORE | F90: AFTER | G90: TOTAL | H90: ( % )
B91: Bleaching Earth (BE) to Poram Spec | C91: 9 | D91: kg | E91: 122737 | F91: 143761 | G91: =F91-E91 -> 21024 | H91: =G91/G14/10 -> 0.83441816 | I91: OK
E92: =E91/(E16)*100 -> #DIV/0!
B93: Bleaching Earth (BE) to Branded Spec | C93: 18 | E93: 0
E94: =E93/(E17)*100 -> #DIV/0! | I94: OK
B95: Phosporic Acid (PA) | C95: 0,4 - 0,5 | D95: kg | E95: 1970.8 | F95: 867.36 | G95: =E95-F95 -> 1103.44 | H95: =G95/G14/10 -> 0.043794253 | I95: OK
A97: 3 | B97: OIL LOSSES | C97: - 0,8 | D97: % | H97: =((SUM(G27+G36))-(SUM(G14)))/(SUM(G14))*100 -> -2.7190824
H98: =H97%*G14 -> -68.51
B99: % Oil Content | C99: 20 to 21 | D99: %
B100: Spent Bleaching Earth | H100: =SUM(G91,G93)+(H99%*SUM(G91,G93)) -> 21024
A101: 4 | B101: PACKAGING (Brand Salvaco)
B102: Olein IV 60 Received
...

Sheet peformance  test REFINERY 2
A1: REFINERY PMG 2
A2: No | B2: ITEM | C2: Norma LIPICO | D2: UOM | E2: Day 2 tanggal 12/12/2024
A4: 1 | B4: PRODUCTION | E4: BEFORE | F4: AFTER | G4: TOTAL | H4: Yield ( % )
B5: Refinery
B6: Running Days
B7: Incoming CPO
B8: Ratio Run CPO
B9: CPO Consume Total | C9: 2500 | D9: TPD | E9: 5880.74 | F9: 8383.74 | G9: =F9-E9 -> 2503 | H9: =G9/2500000*100000 -> 100.12
B10: Avg Daily Consump CPO ( MTD )
B11: CPO Consume Poram | C11: 29045000
B12: CPO Consume Brand | C12: 7314000 | E12: =E43+E52+E57 -> 0
B13: - FFA | C13: 5 | D13: % | G13: 3.97
B14: - Moist & Impurities | C14: 0.5 | D14: % | G14: 0.4
B15: - DOBI | C15: 2.2 | D15: Min | G15: 2.42
B16: TANK | G16: 105
B17: Product
B18: OIP RBDPO
B19: RBDPO | C19: =C9*94.2% -> 2355 | D19: TPD | E19: 5143.38 | F19: 7493.18 | G19: =F19-E19 -> 2349.8 | H19: =G19/G9*100 -> 93.879345
B20: - FFA | C20: 0.05 | D20: % | G20: 0.043
B21: - Moist & Impurities | C21: 0.03 | D21: % | G21: 0.04
B22: - LC | C22: 2.5 | D22: % | G22: 2.5
B23: - Aom stability min ( hr ) | C23: 60 | D23: min ( hr )
B24: - teste & Odor | C24: bland/Odorless
B25: - temp max ( C ) | C25: 50 | D25: max˚C
B26: PFAD | C26: =C9*5% -> 125 | D26: TPD | E26: 243.04 | F26: 347.1 | G26: =F26-E26 -> 104.06 | H26: =G26/G9*100 -> 4.1574111
B27: Fractionation
B28: Running Days
B29: Filling Langsung CR Fr Refinery | E29: 0
B30: Total Filling Crystalizer ( Feed ) | E30: 392100
B31: Avg Daily Consump RPO ( MTD )
B32: Total Proses RBDPO | E32: =SUM(E35,E39,E44,E48,E58) -> 0
B33: Sisa Filling Crystalizer | E33: =E30-E32 -> 392100
B34: Fractionation OLEIN IV 56
B35: RBDPO Consume | E35: =E36+E37 -> 0
B36: OLEIN IV 56 | E36: 0
B37: STEARIN | E37: 0
B38: Fractionation OLEIN IV 57 ( Bulk )
B39: RBDPO Consume | E39: =E40+E41 -> 0
B40: OLEIN IV 57 | E40: 0
B41: STEARIN | E41: 0
B42: Fractionation OLEIN IV 57 ( Retail )
B43: CPO Consume
B44: RBDPO Brand Consume | E44: =E45+E46 -> 0
B45: OLEIN IV 57 Low Color | E45: 0
B46: STEARIN | E46: 0
B47: Fractionation OLEIN IV 58 ( Bulk )
B48: RBDPO Consume | C48: =C49+C50 -> 21429000 | E48: =E49+E50 -> 0
B49: OLEIN IV 58 | C49: 15000000
B50: STEARIN | C50: 6429000
B51: Fractionation OLEIN IV 58 ( Retail )
B52: CPO Consume
B53: RBDPO Consume | C53: =C54+C55 -> 21429000 | E53: =E54+E55 -> 0
B54: OLEIN IV 58 | C54: 15000000 | E54: 0
B55: STEARIN | C55: 6429000 | E55: 0
B56: Fractionation OLEIN IV 60
B57: CPO Consume
B58: RBDPO Brand Consume | E58: =E60+E61 -> 0
B59: OLEIN IV 60 Bulk | E59: 0
B60: OLEIN IV 60 Salvaco | E60: 0
B61: SOFT STEARIN | E61: 0
B62: Ratio Run RBDPO | E62: 0
B63: YIELD
B64: RBDPO | C64: 94.2 | E64: =(E19/(E9))*100 -> 87.461442
B65: PFAD | C65: 5 | E65: =(E26/(E9))*100 -> 4.1328132
B66: Olein IV 56 | C66: 82 | E66: =E36/(E36+E37)*100 -> #DIV/0!
B67: Stearin | C67: 18 | E67: =(E37/E35)*100 -> #DIV/0!
B68: Olein IV 57 ( Bulk ) | C68: 75 | E68: =(E40/E39)*100 -> #DIV/0!
B69: Stearin | C69: 25 | E69: =(E41/E39)*100 -> #DIV/0!
B70: Olein IV 57 ( Retail ) | C70: 75 | E70: =E45/E44*100 -> #DIV/0!
B71: Stearin | C71: 25 | E71: =E46/E44*100 -> #DIV/0!
B72: Olein IV 58 ( Bulk ) | C72: 70 | E72: =E49/(E49+E50)*100 -> #DIV/0!
B73: Stearin | C73: 30 | E73: =E50/(E50+E49)*100 -> #DIV/0!
B74: Olein IV 58 ( Retail ) | C74: 70 | E74: =E54/(E54+E55)*100 -> #DIV/0!
B75: Stearin | C75: 30 | E75: =E55/(E54+E55)*100 -> #DIV/0!
B76: Olein IV 60 | C76: 60 | E76: =E59/E58*100 -> #DIV/0!
B77: Soft Stearin | C77: 40 | E77: =E61/E58*100 -> #DIV/0!
B78: - FFA | C78: ~93 | D78: % | G78: 90.62
B79: - Moist & Impurities | C79: 0.5 | D79: % | G79: 0.33
A80: 2 | B80: CHEMICAL CONSUMABLE | E80: BEFORE | F80: AFTER | G80: TOTAL | H80: ( % )
B81: Bleaching Earth (BE) to Poram Spec | C81: 9 | D81: kg | E81: 51223 | F81: 74245 | G81: =F81-E81 -> 23022 | H81: =G81/G9/10 -> 0.91977627
E82: =E81/(E11)*100 -> #DIV/0!
B83: Bleaching Earth (BE) to Branded Spec | C83: 18 | E83: 0
E84: =E83/(E12)*100 -> #DIV/0!
B85: Phosporic Acid (PA) | C85: 0,4 - 0,5 | D85: kg | E85: 539.5 | F85: 1342.1 | G85: =F85-E85 -> 802.6 | H85: =G85/G9/10 -> 0.032065521
A87: 3 | B87: OIL LOSSES | C87: - 0,8 | D87: % | G87: =((SUM(G19+G26))-(SUM(G9)))/(SUM(G9))*100 -> -1.9632441
G88: =G87%*G9 -> -49.14
B89: % Oil Content | C89: 20 to 21 | D89: % | G89: 21.66
B90: Spent Bleaching Earth | G90: =SUM(G81,G83)+(G89%*SUM(G81,G83)) -> 28008.565
A91: 4 | B91: PACKAGING (Brand Salvaco)
B92: Olein IV 60 Received
B93: Olein IV 60 Consume
B94: - finished product | E94: 0
B95: - sample | E95: 0
B96: - remelt, flushing, downgrade | E96: 0
B97: Carton
B98: Salvaco 1 Liter
B99: Salvaco 2 Liter
B100: Pouch
B101: Salvaco 1 Liter | E101: 0
B102: Salvaco 2 Liter | E102: 0
...

Sheet HPP REF 
B2: Refinery Cost
B3: Through Put CPO Proses | N3: =('Januari 2026 PMG 2'!AM10)/1000 -> 2006.269 | O3: TPD
B4: Working Day | N4: ='Januari 2026 PMG 2'!AM6 -> 20 | O4: Days
B5: Total CPO Process | N5: =N4*N3 -> 40125.38 | O5: MTD
B6: KURS | N6: 16000 | O6: Rp/USD
B7: No | C7: Item Cost | D7: Norma | F7: Pemakaian / Hari | H7: HK | J7: Total Pemakaian | K7: Harga / stn | M7: Total Biaya | N7: Rp / kg | O7: USD/MT
B8: 1 | C8: Bleaching Earth | D8: ='Januari 2026 PMG 2'!$AM$76 -> 0.67460296 | F8: =($D$8*$N$3*10) -> 13534.35 | G8: Kg/day | H8: =$N$4 -> 20 | J8: =$H$8*$F$8 -> 270687 | K8: 4550 | M8: =$J$8*$K$8 -> 1.2316259e+09 | N8: =$M$8/($N$5*1000) -> 30.694435 | O8: =($M$8/$N$6)/$N$5 -> 1.9184022
B9: 2 | C9: Phosporic acid | D9: ='Januari 2026 PMG 2'!$AM$87 -> 0.60967796 | F9: =($D$9*$N$3*10) -> 12231.78 | G9: Kg/day | H9: =$H$8 -> 20 | J9: =$H$9*$F$9 -> 244635.6 | K9: 17420 | M9: =$J$9*$K$9 -> 4261552152 | N9: =$M$9/($N$5*1000) -> 106.2059 | O9: =($M$9/$N$6)/$N$5 -> 6.6378688
B10: 3 | C10: Caustic Soda | D10: 29.166667 | E10: kg/day | F10: =D10 -> 29.166667 | G10: kg/day | H10: =$H$8 -> 20 | J10: =$H$10*$F$10 -> 583.33333 | K10: 15700 | M10: =$J$10*$K$10 -> 9158333.3 | N10: =$M$10/($N$5*1000) -> 0.22824291 | O10: =($M$10/$N$6)/$N$5 -> 0.014265182
B11: 4 | C11: Pemakaian Natural Gas HPB Geka
C12: Normal Consumption | D12: ='Januari 2026 PMG 2'!$AM$249 -> 0.10825282 | E12: MMBTU/MT CPO | F12: =$D$12*$N$3 -> 217.18428 | G12: MMBTU/day | H12: =$H$8 -> 20 | J12: =$H$12*$F$12 -> 4343.6855 | K12: =11.5*$N$6 -> 184000 | M12: =$J$12*$K$12 -> 7.9923814e+08 | N12: =$M$12/($N$5*1000) -> 19.918519 | O12: =($M$12/$N$6)/$N$5 -> 1.2449074
C13: Penalty Below Consumption | D13: 0 | E13: MMBTU/MT CPO | F13: =$D$13*$N$3 -> 0 | G13: MMBTU/day | H13: =$H$8 -> 20 | J13: =$H$13*$F$13 -> 0 | K13: =11.5*$N$6 -> 184000 | M13: =$J$13*$K$13 -> 0 | N13: =$M$13/($N$5*1000) -> 0 | O13: =($M$13/$N$6)/$N$5 -> 0
C14: Penalty Above Consumption | D14: 0 | E14: MMBTU/MT CPO | F14: =$D$14*$N$3 -> 0 | G14: MMBTU/day | H14: =$H$8 -> 20 | J14: =$H$14*$F$14 -> 0 | K14: =11.5*$N$6 -> 184000 | M14: =$J$14*$K$14 -> 0 | N14: =$M$14/($N$5*1000) -> 0 | O14: =($M$14/$N$6)/$N$5 -> 0
B15: 5 | C15: Pemakaian Steam
C16: For Process | D16: ='Januari 2026 PMG 2'!AM256 -> 43131.305 | E16: Kg/MT CPO | F16: =$D$16*$N$3/1000 -> 86533 | G16: Ton/day | H16: =$H$8 -> 20 | J16: =$H$16*$F$16 -> 1730660 | K16: =Steam!H15 -> 45.029294 | M16: =$J$16*$K$16 -> 77930398 | N16: =$M$16/($N$5*1000) -> 1.9421722 | O16: =($M$16/$N$6)/$N$5 -> 0.12138576
C17: Storage Tank for Heating | D17: ='Januari 2026 PMG 2'!$AM$260 -> 69146.398 | E17: Kg/MT CPO | F17: =$D$17*$N$3/1000 -> 138726.27 | G17: Ton/day | H17: =$H$8 -> 20 | J17: =$H$17*$F$17 -> 2774525.5 | K17: =Steam!H15 -> 45.029294 | M17: =$J$17*$K$17 -> 1.2493492e+08 | N17: =$M$17/($N$5*1000) -> 3.1136135 | O17: =($M$17/$N$6)/$N$5 -> 0.19460084
B18: 6 | C18: Pemakaian Electrical
C19: For Process | D19: ='Januari 2026 PMG 2'!$AM$297 -> 6.4437271 | E19: kW/MT CPO | F19: =$D$19*$N$3 -> 12927.85 | G19: kW/day | H19: =$H$8 -> 20 | I19: 0 | J19: =$H$19*$F$19 -> 258557 | K19: 1550 | L19: =[1]Electric!H21 -> 3666.6667 | M19: =($F$19*$H$19*$K$19)+($F$19*$I$19*$L$19) -> 400763350 | N19: =$M$19/($N$5*1000) -> 9.9877771 | O19: =($M$19/$N$6)/$N$5 -> 0.62423607
C20: Cooling Tower | D20: ='Januari 2026 PMG 2'!$AM$299 -> 4.8851126 | E20: kW/MT CPO | F20: =$D$20*$N$3 -> 9800.85 | G20: kW/day | H20: =$H$8 -> 20 | I20: 0 | J20: =$H$20*$F$20 -> 196017 | K20: 1550 | L20: =L19 -> 3666.6667 | M20: =(F20*H20*K20)+(F20*I20*L20) -> 303826350 | N20: =$M$20/($N$5*1000) -> 7.5719246 | O20: =($M$20/$N$6)/$N$5 -> 0.47324528
C21: Storage Tank | D21: 0.3377877 | E21: kW/MT CPO | F21: =$D$21*$N$3 -> 677.69299 | G21: kW/day | H21: =$H$8 -> 20 | I21: 0 | J21: =$H$21*$F$21 -> 13553.86 | K21: 1550 | L21: =L20 -> 3666.6667 | M21: =($F$21*$H$21*$K$21)+($F$21*$I$21*$L$21) -> 21008483 | N21: =$M$21/($N$5*1000) -> 0.52357093 | O21: =($M$21/$N$6)/$N$5 -> 0.032723183
B22: 7 | C22: Pemakaian Water
C23: Make Up CT | D23: ='Januari 2026 PMG 2'!$AM$274 -> 0.10634167 | E23: M3/day | F23: =$D$23 -> 0.10634167 | G23: M3/day | H23: =$H$8 -> 20 | J23: =$H$23*$F$23 -> 2.1268334 | K23: =WTP!H13 -> 25239.326 | M23: =$J$23*$K$23 -> 53679.843 | N23: =$M$23/($N$5*1000) -> 0.0013378027 | O23: =($M$23/$N$6)/$N$5 -> 8.3612671e-05
B24: 8 | C24: Chemical Water | N24: =$M$24/($N$5*1000) -> 0 | O24: =($M$24/$N$6)/$N$5 -> 0
C25: EONBAC BC 3108 | D25: 0.4 | E25: Kg/day | F25: =D25 -> 0.4 | G25: Kg/day | H25: =$H$8 -> 20 | J25: =$H$25*$F$25 -> 8 | K25: 27240 | M25: =$J$25*$K$25 -> 217920 | N25: =$M$25/($N$5*1000) -> 0.0054309766 | O25: =($M$25/$N$6)/$N$5 -> 0.00033943604
C26: EONLINE T722 | D26: 0.66 | E26: Kg/day | F26: =D26 -> 0.66 | G26: Kg/day | H26: =$H$8 -> 20 | J26: =$H$26*$F$26 -> 13.2 | K26: 29120 | M26: =$J$26*$K$26 -> 384384 | N26: =$M$26/($N$5*1000) -> 0.0095795728 | O26: =($M$26/$N$6)/$N$5 -> 0.0005987233
C27: EONLINE AG5770 | D27: 0.41 | E27: Kg/day | F27: =D27 -> 0.41 | G27: Kg/day | H27: =$H$8 -> 20 | J27: =$H$27*$F$27 -> 8.2 | K27: 117212 | M27: =$J$27*$K$27 -> 961138.4 | N27: =$M$27/($N$5*1000) -> 0.023953378 | O27: =($M$27/$N$6)/$N$5 -> 0.0014970861
C28: EONScale T2511 | D28: 0.1 | E28: Kg/day | F28: =D28 -> 0.1 | G28: Kg/day | H28: =$H$8 -> 20 | J28: =$H$28*$F$28 -> 2 | K28: 45940 | M28: =$J$28*$K$28 -> 91880 | N28: =$M$28/($N$5*1000) -> 0.0022898226 | O28: =($M$28/$N$6)/$N$5 -> 0.00014311391
B29: 9 | C29: Others
C30: Filter Bag 10 Microne | D30: 0.90361446 | E30: Pcs/day | F30: =D30 -> 0.90361446 | G30: Pcs/day | H30: =$H$8 -> 20 | J30: =$H$30*$F$30 -> 18.072289 | K30: 40000 | M30: =$J$30*$K$30 -> 722891.57 | N30: =$M$30/($N$5*1000) -> 0.018015819 | O30: =($M$30/$N$6)/$N$5 -> 0.0011259887
C31: Filter Bag 100 Microne | D31: 0.63253012 | E31: Pcs/day | F31: =D31 -> 0.63253012 | G31: Pcs/day | H31: =$H$8 -> 20 | J31: =$H$31*$F$31 -> 12.650602 | K31: 125000 | M31: =$J$31*$K$31 -> 1581325.3 | N31: =$M$31/($N$5*1000) -> 0.039409603 | O31: =($M$31/$N$6)/$N$5 -> 0.0024631002
C32: Filter Cartridge 10 Microne | D32: 1.5666667 | E32: Pcs/day | F32: =D32 -> 1.5666667 | G32: Pcs/day | H32: =$H$8 -> 20 | J32: =$H$32*$F$32 -> 31.333333 | K32: 145000 | M32: =$J$32*$K$32 -> 4543333.3 | N32: =$M$32/($N$5*1000) -> 0.11322842 | O32: =($M$32/$N$6)/$N$5 -> 0.0070767762
C33: Filter Dustbag | D33: 0.12048193 | E33: Pcs/day | F33: =D33 -> 0.12048193 | G33: Pcs/day | H33: =$H$8 -> 20 | J33: =$H$33*$F$33 -> 2.4096386 | K33: 682500 | M33: =$J$33*$K$33 -> 1644578.3 | N33: =$M$33/($N$5*1000) -> 0.040985987 | O33: =($M$33/$N$6)/$N$5 -> 0.0025616242
C34: O Ring Filter Leaves | D34: 3.6144578 | E34: Pcs/day | F34: =D34 -> 3.6144578 | G34: Pcs/day | H34: =$H$8 -> 20 | J34: =$H$34*$F$34 -> 72.289157 | K34: 14500 | M34: =$J$34*$K$34 -> 1048192.8 | N34: =$M$34/($N$5*1000) -> 0.026122937 | O34: =($M$34/$N$6)/$N$5 -> 0.0016326836
B35: 10 | C35: Waste Water Treatment Plant ( WWTP ) | D35: ='Januari 2026 PMG 2'!E279 -> 330 | E35: M3/day | F35: =D35 -> 330 | G35: M3/day | H35: =$H$8 -> 20 | J35: =$H$35*$F$35 -> 6600 | K35: =WWTP!H17 -> 971.17576 | M35: =$J$35*$K$35 -> 6409760 | N35: =$M$35/($N$5*1000) -> 0.15974329 | O35: =($M$35/$N$6)/$N$5 -> 0.0099839553
B36: 11 | C36: SHE
C37: SBE | D37: ='Januari 2026 PMG 2'!$AM$91 -> 273050.1 | E37: Kg/day | F37: =D37 -> 273050.1 | G37: Kg/day | H37: =$H$8 -> 20 | J37: =$F$37 -> 273050.1 | K37: 0 | M37: =$J$37*$K$37 -> 0 | N37: =$M$37/($N$5*1000) -> 0 | O37: =($M$37/$N$6)/$N$5 -> 0
C38: Domestic | D38: 0.1 | E38: Trip/day | F38: =D38 -> 0.1 | G38: Trip/day | H38: =$H$8 -> 20 | J38: =$H$38*$F$38 -> 2 | K38: 303030.3 | M38: =$J$38*$K$38 -> 606060.61 | N38: =$M$38/($N$5*1000) -> 0.015104171 | O38: =($M$38/$N$6)/$N$5 -> 0.0009440107
B39: 12 | C39: Chemical Consumption | N39: =$M$39/($N$5*1000) -> 0 | O39: =($M$39/$N$6)/$N$5 -> 0
C40: LAB Chemical | D40: =lab!H33 -> 745255.21 | E40: Rp/day | F40: =D40 -> 745255.21 | G40: Rp/day | H40: =$H$8 -> 20 | M40: =$H$40*$F$40 -> 14905104 | N40: =$M$40/($N$5*1000) -> 0.37146325 | O40: =($M$40/$N$6)/$N$5 -> 0.023216453
C41: Chemical Boiler dan WTP | D41: =lab!H54 -> 259161.44 | E41: Rp/day | F41: =D41 -> 259161.44 | G41: Rp/day | H41: =$H$8 -> 20 | M41: =$H$41*$F$41 -> 5183228.9 | N41: =$M$41/($N$5*1000) -> 0.12917582 | O41: =($M$41/$N$6)/$N$5 -> 0.0080734888
C42: Sample and Analysis | D42: 13909.091 | E42: Rp/day | F42: =D42 -> 13909.091 | G42: Rp/day | H42: =$H$8 -> 20 | M42: =$H$42*$F$42 -> 278181.82 | N42: =$M$42/($N$5*1000) -> 0.0069328145 | O42: =($M$42/$N$6)/$N$5 -> 0.00043330091
C43: Chemical WWTP | D43: =[1]Chemical!$H$61 -> 27103.641 | E43: Rp/day | F43: =D43 -> 27103.641 | G43: Rp/day | H43: =$H$8 -> 20 | M43: =$H$43*$F$43 -> 542072.83 | N43: =$M$43/($N$5*1000) -> 0.013509475 | O43: =($M$43/$N$6)/$N$5 -> 0.0008443422
C44: Consumable Part | D44: =lab!I111 -> 135770.31 | E44: Rp/day | F44: =D44 -> 135770.31 | G44: Rp/day | H44: =$H$8 -> 20 | M44: =$H$44*$F$44 -> 2715406.2 | N44: =$M$44/($N$5*1000) -> 0.067673033 | O44: =($M$44/$N$6)/$N$5 -> 0.0042295646
B45: 13 | C45: Solar
C46: Forklift -1 (3 Ton) | D46: 15.4 | E46: Ltr/day | F46: 0 | G46: Ltr/day | H46: =$H$8 -> 20 | J46: =$H$46*$F$46 -> 0 | K46: 14500 | M46: =$J$46*$K$46 -> 0 | N46: =$M$46/($N$5*1000) -> 0 | O46: =($M$46/$N$6)/$N$5 -> 0
C47: WA Loader | D47: 0 | E47: Ltr/day | F47: =D47 -> 0 | G47: Ltr/day | H47: =$H$8 -> 20 | J47: =$H$47*$F$47 -> 0 | K47: 14500 | M47: =$J$47*$K$47 -> 0 | N47: =$M$47/($N$5*1000) -> 0 | O47: =($M$47/$N$6)/$N$5 -> 0
M48: =SUM($M$8:$M$47) -> 7.2719271e+09 | N48: =SUM($N$8:$N$47) -> 181.23011 | O48: =SUM($O$8:$O$47) -> 11.326882

Sheet HPP FRACT
B2: Fractionation Cost
B3: RPO Proses / Day | N3: TPD | O3: ='Januari 2026 PMG 2'!AM24/1000 -> 1775.536
B4: Working Day | N4: Days | O4: ='Januari 2026 PMG 2'!AM23 -> 29
B5: Total CPO Process | N5: MTD | O5: =O3*O4 -> 51490.545
B6: KURS | N6: Rp/USD | O6: 16000
B7: No | C7: Item Cost | D7: Norma | F7: Pemakaian / Hari | H7: HK | J7: Total Pemakaian | K7: Harga / stn | M7: Total Biaya | N7: Rp / kg | O7: USD/MT
B8: 1 | C8: Steam | D8: ='Januari 2026 PMG 2'!AM258 -> 21310.98 | E8: Kg/MT CPO | F8: =$D$8*$O$3/1000 -> 37838.414 | G8: Ton/day | H8: =$O$4 -> 29 | J8: =$H$8*$F$8 -> 1097314 | K8: =Steam!H15 -> 45.029294 | M8: =$K$8*$J$8 -> 49411275 | N8: =$M$8/($O$5*1000) -> 0.9596184 | O8: =($M$8/$O$6)/$O$5 -> 0.05997615
B9: 2 | C9: Electrical
C10: For Process | D10: ='Januari 2026 PMG 2'!$AM$304 -> 4.3139057 | E10: kW/MT CPO | F10: =$D$10*$O$3 -> 7659.495 | G10: kW/day | H10: =$O$4 -> 29 | I10: 0 | J10: =$H$10*$F$10 -> 222125.35 | K10: =[1]Electric!$L$5 -> 1550 | L10: 3666.6667 | M10: =($F$10*$H$10*$K$10)+($F$10*$I$10*$L$10) -> 3.442943e+08 | N10: =$M$10/($O$5*1000) -> 6.6865538 | O10: =($M$10/$O$6)/$O$5 -> 0.41790961
C11: Cooling Tower | D11: ='Januari 2026 PMG 2'!$AM$302 -> 5.7170954 | E11: kW/MT CPO | F11: =$D$11*$O$3 -> 10150.909 | G11: kW/day | H11: =$H$10 -> 29 | I11: 0 | J11: =$H$11*$F$11 -> 294376.36 | K11: =$K$10 -> 1550 | L11: 3666.6667 | M11: =($F$11*$H$11*$K$11)+($F$11*$I$11*$L$11) -> 4.5628336e+08 | N11: =$M$11/($O$5*1000) -> 8.8614979 | O11: =($M$11/$O$6)/$O$5 -> 0.55384362
B12: 3 | C12: Water
C13: Make Up CT | D13: ='Januari 2026 PMG 2'!$AM$276 -> 0.047309657 | E13: M3/day | F13: =$D$13 -> 0.047309657 | G13: M3/day | H13: =$H$11 -> 29 | J13: =$H$13*$F$13 -> 1.37198 | K13: =WTP!H13 -> 25239.326 | M13: =$K$13*$J$13 -> 34627.852 | N13: =$M$13/($O$5*1000) -> 0.00067250894 | O13: =($M$13/$O$6)/$O$5 -> 4.2031809e-05
B14: 4 | C14: Chemical Water
C15: EONBAC BC 3108 | D15: 0.4 | E15: Kg/day | F15: =$D$15 -> 0.4 | G15: Kg/day | H15: =$H$13 -> 29 | J15: =$H$15*$F$15 -> 11.6 | K15: 27240 | M15: =$K$15*$J$15 -> 315984 | N15: =$M$15/($O$5*1000) -> 0.0061367383 | O15: =($M$15/$O$6)/$O$5 -> 0.00038354614
C16: EONLINE T722 | D16: 0.66 | E16: Kg/day | F16: =$D$16 -> 0.66 | G16: Kg/day | H16: =$H$15 -> 29 | J16: =$H$16*$F$16 -> 19.14 | K16: 29120 | M16: =$K$16*$J$16 -> 557356.8 | N16: =$M$16/($O$5*1000) -> 0.010824449 | O16: =($M$16/$O$6)/$O$5 -> 0.00067652809
C17: EONLINE AG5770 | D17: 0.41 | E17: Kg/day | F17: =$D$17 -> 0.41 | G17: Kg/day | H17: =$H$15 -> 29 | J17: =$H$17*$F$17 -> 11.89 | K17: 117212 | M17: =$K$17*$J$17 -> 1393650.7 | N17: =$M$17/($O$5*1000) -> 0.027066147 | O17: =($M$17/$O$6)/$O$5 -> 0.0016916342
C18: EONScale T2511 | D18: 0.1 | E18: Kg/day | F18: =$D$18 -> 0.1 | G18: Kg/day | H18: =$H$16 -> 29 | J18: =$H$18*$F$18 -> 2.9 | K18: 45940 | M18: =$K$18*$J$18 -> 133226 | N18: =$M$18/($O$5*1000) -> 0.0025873876 | O18: =($M$18/$O$6)/$O$5 -> 0.00016171173
B19: 5 | C19: Others
C20: Filter Cloth | D20: 0.33333333 | E20: Pcs/day | F20: =$D$20 -> 0.33333333 | G20: Pcs/day | H20: =$H$18 -> 29 | J20: =$H$20*$F$20 -> 9.6666667 | K20: 895000 | M20: =$K$20*$J$20 -> 8651666.7 | N20: =$M$20/($O$5*1000) -> 0.16802438 | O20: =($M$20/$O$6)/$O$5 -> 0.010501523
C21: Filter Bag 100 Microne | D21: 0.63253012 | E21: Pcs/day | F21: =$D$21 -> 0.63253012 | G21: Pcs/day | H21: =$H$20 -> 29 | J21: =$H$21*$F$21 -> 18.343373 | K21: 125000 | M21: =$K$21*$J$21 -> 2292921.7 | N21: =$M$21/($O$5*1000) -> 0.044530927 | O21: =($M$21/$O$6)/$O$5 -> 0.0027831829
M22: =SUM(M8:M21) -> 8.6336836e+08 | N22: =SUM(N8:N21) -> 16.767513 | O22: =SUM($O$8:$O$21) -> 1.0479695

Sheet SUMMARY HPP 
B2: Production Cost OKTOBER 2025
B3: Through Put CPO Proses (Ton/Day) | H3: TPD | I3: ='HPP REF '!$N$3 -> 2006.269
B4: Working Day | F4: 1 | H4: Days | I4: ='HPP REF '!$N$4 -> 20
B5: Refined CPO ( Ton/month ) | H5: MTD | I5: =$I$4*$I$3 -> 40125.38
B6: Through Put RPO Proses (Ton/Day) | H6: TPD | I6: ='HPP FRACT'!$O$3 -> 1775.536
B7: Working Day | H7: Days | I7: ='HPP FRACT'!$O$4 -> 29
B8: Fract RPO ( ton/month ) | H8: MTD | I8: =$I$7*$I$6 -> 51490.545
B9: KURS | H9: Rp/USD | I9: 16000
B10: No | C10: Items | D10: Description | G10: Rupiah | H10: Rp/Kg | I10: USD/MT
B11: I | C11: Production Cost | D11: ● | E11: Refining Cost | G11: ='HPP REF '!$M$48 -> 7.2719271e+09 | H11: =$G$11/($I$5*1000) -> 181.23011 | I11: =(G11/$I$9)/$I$5 -> 11.326882
D12: ● | E12: Fractionation Cost | G12: ='HPP FRACT'!$M$22 -> 8.6336836e+08 | H12: =$G$12/($I$8*1000) -> 16.767513 | I12: =(G12/$I$9)/$I$8 -> 1.0479695
D13: ● | E13: Preventive Maintenance Cost | F13: 0 | G13: =MTC!$F$18*F13 -> 0 | H13: =$G$13/($I$5*1000) -> 0 | I13: =(G13/$I$9)/$I$5 -> 0
G14: =SUM(G11:$G$13) -> 8.1352955e+09 | H14: =SUM($H$11:$H$13) -> 197.99762 | I14: =SUM(I11:I13) -> 12.374852
B16: II | C16: Port Cost | D16: ● | E16: Trucking Komoditi ke Kuala Tanjung | G16: =LOG!I8+LOG!I9+LOG!$I$10 -> 4.1659775e+09 | H16: =$G$16/($I$5*1000) -> 103.824 | I16: =($G$16/$I$9)/$I$5 -> 6.489
D17: ● | E17: Sewa Tank PTI Total Volume : 24.000 MT ( 5 Unit ) | F17: =F4 -> 1 | G17: =LOG!I11+LOG!I12+LOG!I13+LOG!$I$14*F17 -> 1886000000 | H17: =$G$17/($I$5*1000) -> 47.00267 | I17: =($G$17/$I$9)/$I$5 -> 2.9376669
D18: ● | E18: Instalasi & Pemanasan, Pompa, Surveyor dan Documen | G18: =LOG!I18+LOG!I19+LOG!I20+LOG!$I$21 -> 2.1494364e+09 | H18: =$G$18/($I$5*1000) -> 53.568 | I18: =($G$18/$I$9)/$I$5 -> 3.348
D19: ● | E19: Finalty Over Capacity Tank | G19: =LOG!I15+LOG!I16+LOG!$I$17 -> 1.7115882e+09 | H19: =$G$19/($I$5*1000) -> 42.656 | I19: =($G$19/$I$9)/$I$5 -> 2.666
G20: =SUM($G$16:$G$19) -> 9.913002e+09 | H20: =SUM($H$16:$H$19) -> 247.05067 | I20: =SUM($I$16:$I$19) -> 15.440667
B22: II | C22: Fix Cost | D22: ● | E22: Manpower Cost | F22: =F4 -> 1 | G22: =[1]MPC!$H$29*$F$22 -> 2.1846655e+09 | H22: =$G$22/($I$5*1000) -> 54.445977 | I22: =($G$22/$I$9)/$I$5 -> 3.4028736
D23: ● | E23: Admin OH Cost | F23: =F4 -> 1 | G23: =OH!G51*$F$23 -> 1.4360564e+09 | H23: =$G$23/($I$5*1000) -> 35.789228 | I23: =($G$23/$I$9)/$I$5 -> 2.2368268
D24: ● | E24: Depresiasi Cost | F24: =F4 -> 1 | G24: =DEP!I9*$F$24 -> 4.1811848e+09 | H24: =$G$24/($I$5*1000) -> 104.203 | I24: =($G$24/$I$9)/$I$5 -> 6.5126872
D25: ● | E25: Amortisation of leasehold land Cost | F25: =F4 -> 1 | G25: =AMOR!$G$20*$F$25 -> 1.0484098e+09 | H25: =$G$25/($I$5*1000) -> 26.128346 | I25: =($G$25/$I$9)/$I$5 -> 1.6330216
G26: =SUM($G$22:$G$25) -> 8.8503165e+09 | H26: =SUM($H$22:$H$25) -> 220.56655 | I26: =SUM($I$22:$I$25) -> 13.785409
B28: Total Production Cost | G28: =$G$26+$G$20+$G$14 -> 2.6898614e+10 | H28: =$H$26+$H$20+$H$14 -> 665.61484 | I28: =$I$26+$I$20+$I$14 -> 41.600928

Sheet Lembar1

Sheet OIP Fract PMG 1
A4: Oil In Plant (OIP) Fraksinasi | I4: OIP | S4: BUFFER TANK | W4: DIRECT
A5: RBDPO OIP | I5: RPO CR | M5: OLEIN | P5: STEARIN | S5: TK131 RPO | U5: TK132 RPO
A6: Vessel | B6: Operating Volume (m3) | C6: Oil Density (kg/m3) | D6: MT | E6: Level Transmitter (1%/MT) | F6: Level (%) | G6: Kg | I6: Tanggal | J6: Opening Stock | K6: Closing Stock | L6: balance stok | M6: Opening Stock | N6: Closing Stock | O6: balance stok | P6: Opening Stock | Q6: Closing Stock | R6: balance stok | S6: Opening Stock | T6: Closing Stock | U6: Opening Stock | V6: Closing Stock
A7: 2CR1201 | B7: 70.51 | C7: 890 | D7: 60 | E7: =D7/100 -> 0.6 | F7: 0 | G7: =E7*F7*1000 -> 0 | I7: 46023
A8: 2CR1202 | B8: 70.51 | C8: 890 | D8: 60 | E8: =D8/100 -> 0.6 | F8: 0 | G8: =E8*F8*1000 -> 0 | I8: 46024
A9: 2CR1203 | B9: 70.51 | C9: 890 | D9: 60 | E9: =D9/100 -> 0.6 | F9: 0 | G9: =E9*F9*1000 -> 0 | I9: 46025
A10: 2CR1204 | B10: 70.51 | C10: 890 | D10: 60 | E10: =D10/100 -> 0.6 | F10: 0 | G10: =E10*F10*1000 -> 0 | I10: 46026
A11: 2CR1205 | B11: 70.51 | C11: 890 | D11: 60 | E11: =D11/100 -> 0.6 | F11: 0 | G11: =E11*F11*1000 -> 0 | I11: 46027
A12: 2CR1206 | B12: 70.51 | C12: 890 | D12: 60 | E12: =D12/100 -> 0.6 | F12: 0 | G12: =E12*F12*1000 -> 0 | I12: 46028
A13: 2CR1207 | B13: 70.51 | C13: 890 | D13: 60 | E13: =D13/100 -> 0.6 | F13: 0 | G13: =E13*F13*1000 -> 0 | I13: 46029
A14: 2CR1208 | B14: 70.51 | C14: 890 | D14: 60 | E14: =D14/100 -> 0.6 | F14: 0 | G14: =E14*F14*1000 -> 0 | I14: 46030
A15: 2CR1209 | B15: 70.51 | C15: 890 | D15: 60 | E15: =D15/100 -> 0.6 | F15: 0 | G15: =E15*F15*1000 -> 0 | I15: 46031
A16: 2CR1210 | B16: 70.51 | C16: 890 | D16: 60 | E16: =D16/100 -> 0.6 | F16: 0 | G16: =E16*F16*1000 -> 0 | I16: 46032 | K16: 168670
A17: 2CR1211 | B17: 70.51 | C17: 890 | D17: 60 | E17: =D17/100 -> 0.6 | F17: 0 | G17: =E17*F17*1000 -> 0 | I17: 46033 | J17: =K16 -> 168670 | K17: 0
A18: 2CR1212 | B18: 70.51 | C18: 890 | D18: 60 | E18: =D18/100 -> 0.6 | F18: 0 | G18: =E18*F18*1000 -> 0 | I18: 46034 | J18: =K17 -> 0
A19: 2CR1213 | B19: 70.51 | C19: 890 | D19: 60 | E19: =D19/100 -> 0.6 | F19: 0 | G19: =E19*F19*1000 -> 0 | I19: 46035 | J19: =K18 -> 0
A20: 2CR1214 | B20: 70.51 | C20: 890 | D20: 60 | E20: =D20/100 -> 0.6 | F20: 0 | G20: =E20*F20*1000 -> 0 | I20: 46036 | J20: =K19 -> 0
A21: 2CR1215 | B21: 70.51 | C21: 890 | D21: 60 | E21: =D21/100 -> 0.6 | F21: 0 | G21: =E21*F21*1000 -> 0 | I21: 46037 | J21: =K20 -> 0
I22: 46038 | J22: =K21 -> 0 | K22: 287700
F23: Total RBDPO | G23: =SUM(G7:G21) -> 0 | I23: 46039 | J23: =K22 -> 287700 | K23: 446900
I24: 46040 | J24: =K23 -> 446900 | K24: 446900
A25: Olein OIP | I25: 46041 | J25: 416900 | K25: 416900
A26: Vessel | B26: Operating Volume (m3) | C26: Oil Density (kg/m3) | D26: MT | E26: Level Transmitter (1%/MT) | F26: Level (%) | G26: Kg | I26: 46042
A27: 2TK261 | B27: 15.95 | C27: 885 | D27: =B27*C27/1000 -> 14.11575 | E27: =D27/100 -> 0.1411575 | G27: =E27*F27*1000 -> 0 | I27: 46043
A28: 2CL251 | B28: 3.02 | C28: 885 | D28: =B28*C28/1000 -> 2.6727 | E28: =D28/100 -> 0.026727 | G28: =E28*F28*1000 -> 0 | I28: 46044
A29: 2TK221 | B29: 82.48 | C29: 885 | D29: =B29*C29/1000 -> 72.9948 | E29: =D29/100 -> 0.729948 | G29: =E29*F29*1000 -> 0 | I29: 46045
A30: 2TK241 | B30: 16.95 | C30: 885 | D30: =B30*C30/1000 -> 15.00075 | E30: =D30/100 -> 0.1500075 | G30: =E30*F30*1000 -> 0 | I30: 46046
F31: Total Olein | G31: =SUM(G27:G30) -> 0 | I31: 46047
I32: 46048 | K32: 402210 | N32: 37360
I33: 46049 | J33: =K32 -> 402210 | K33: 309830 | M33: =N32 -> 37360 | N33: =280+1278+1358 -> 2916
I34: 46050 | J34: =K33 -> 309830 | M34: =N33 -> 2916
I35: 46051
I36: 46052
I37: 46053
A39: Stearin OIP
A40: Melting Tank | B40: Panjang (m) | C40: Lebar (m) | D40: tinggi (m) | E40: Density | F40: Tinggi Sounding (Cm) Maks 4,4 m | G40: Kg
A41: TK231 A | B41: 12.2 | C41: 1.75 | D41: 1.52 | E41: 0.88 | F41: 0 | G41: =B41*C41*D41*E41*F41/100 -> 0
A42: TK231 B | B42: 12.2 | C42: 1.75 | D42: 1.52 | E42: 0.88 | F42: 0 | G42: =B42*C42*D42*E42*F42/100 -> 0
F43: Total STEARIN | G43: =SUM(G41:G42) -> 0

Sheet Convert Gas
B3: CONVERT PEMAKAIAN GAS HP BOILER & MP BOILER
B4: Januari 2026
B5: Tanggal | C5: HP BOILER | F5: TOTAL CORRECTED VOLUME (Sm3) | K5: ENERGY MP BOILER (MMBTU) | L5: TOTAL GAS CONSUMPTION (MMBTU) | M5: PERCENTAGE
C6: UNCORRECTED VOLUME (UV) (Nm3) | D6: PRESS. Bar | E6: CORRECTED VOLUME (CV) (Sm3) | G6: Convert Sm3 to SCF | H6: VOLUME (MSCF) | I6: HEATING VALUE (BTU / SCF) | J6: ENERGY HP BOILER (MMBTU) | M6: HP Boiler | N6: MP Boiler
C7: 1 | D7: 2 | E7: 3 = 1 x 2 | F7: 4 = 3 | G7: 5 | H7: 6 = (4 x 5) / 1000 | I7: 7 | J7: 8 = (6 x 7) / 1000 | K7: 9 = 10 - 8 | L7: 10 | M7: 11 = 8 / 10 | N7: 12 = 9 / 10
B8: 1 | C8: 5430 | D8: 5 | E8: =C8*D8 -> 27150 | F8: =E8 -> 27150 | G8: 35.314667 | H8: =(F8*G8)/1000 -> 958.79321 | I8: 1039.3855 | J8: =(H8*I8)/1000 -> 996.55575 | K8: =L8-J8 -> -181.40615 | L8: ='Januari 2026 PMG 2'!G242 -> 815.1496 | M8: =(J8/L8) -> 1.2225434 | N8: =K8/L8 -> -0.22254338
B9: =B8+1 -> 2 | C9: 5479 | D9: 5 | E9: =C9*D9 -> 27395 | F9: =E9 -> 27395 | G9: 35.314667 | H9: =(F9*G9)/1000 -> 967.4453 | I9: 1051.3796 | J9: =(H9*I9)/1000 -> 1017.1523 | K9: =L9-J9 -> -134.18438 | L9: ='Januari 2026 PMG 2'!H242 -> 882.9679 | M9: =(J9/L9) -> 1.1519697 | N9: =K9/L9 -> -0.15196972
B10: =B9+1 -> 3 | C10: 5420 | D10: 5 | E10: =C10*D10 -> 27100 | F10: =E10 -> 27100 | G10: 35.314667 | H10: =(F10*G10)/1000 -> 957.02748 | I10: 1051.0228 | J10: =(H10*I10)/1000 -> 1005.8577 | K10: =L10-J10 -> -100.18902 | L10: ='Januari 2026 PMG 2'!I242 -> 905.6687 | M10: =(J10/L10) -> 1.1106244 | N10: =K10/L10 -> -0.11062436
B11: =B10+1 -> 4 | C11: 199 | D11: 5 | E11: =C11*D11 -> 995 | F11: =E11 -> 995 | G11: 35.314667 | H11: =(F11*G11)/1000 -> 35.138094 | I11: 1054.8217 | J11: =(H11*I11)/1000 -> 37.064422 | K11: =L11-J11 -> 533.54988 | L11: ='Januari 2026 PMG 2'!J242 -> 570.6143 | M11: =(J11/L11) -> 0.064955298 | N11: =K11/L11 -> 0.9350447
B12: =B11+1 -> 5 | C12: 0 | D12: 5 | E12: =C12*D12 -> 0 | F12: =E12 -> 0 | G12: 35.314667 | H12: =(F12*G12)/1000 -> 0 | I12: 1057.0889 | J12: =(H12*I12)/1000 -> 0 | K12: =L12-J12 -> 330.2773 | L12: ='Januari 2026 PMG 2'!K242 -> 330.2773 | M12: =(J12/L12) -> 0 | N12: =K12/L12 -> 1
B13: =B12+1 -> 6 | C13: 100 | D13: 5 | E13: =C13*D13 -> 500 | F13: =E13 -> 500 | G13: 35.314667 | H13: =(F13*G13)/1000 -> 17.657334 | I13: 1059.7585 | J13: =(H13*I13)/1000 -> 18.71251 | K13: =L13-J13 -> 403.37109 | L13: 422.0836 | M13: =(J13/L13) -> 0.044333658 | N13: =K13/L13 -> 0.95566634
B14: =B13+1 -> 7 | C14: 785.4 | D14: 5 | E14: =C14*D14 -> 3927 | F14: =E14 -> 3927 | G14: 35.314667 | H14: =(F14*G14)/1000 -> 138.6807 | I14: 1061.899 | J14: =(H14*I14)/1000 -> 147.2649 | K14: =L14-J14 -> 1118.9188 | L14: 1266.1837 | M14: =(J14/L14) -> 0.11630611 | N14: =K14/L14 -> 0.88369389
B15: =B14+1 -> 8 | C15: 769.5 | D15: 5 | E15: =C15*D15 -> 3847.5 | F15: =E15 -> 3847.5 | G15: 35.314667 | H15: =(F15*G15)/1000 -> 135.87318 | I15: 1061.7688 | J15: =(H15*I15)/1000 -> 144.2659 | K15: =L15-J15 -> 1204.7675 | L15: 1349.0334 | M15: =(J15/L15) -> 0.1069402 | N15: =K15/L15 -> 0.8930598
B16: =B15+1 -> 9 | D16: 5 | E16: =C16*D16 -> 0 | F16: =E16 -> 0 | G16: 35.314667 | H16: =(F16*G16)/1000 -> 0 | I16: 1061.1997 | J16: =(H16*I16)/1000 -> 0 | K16: =L16-J16 -> 0 | M16: =(J16/L16) -> #DIV/0! | N16: =K16/L16 -> #DIV/0!
B17: =B16+1 -> 10 | D17: 5 | E17: =C17*D17 -> 0 | F17: =E17 -> 0 | G17: 35.314667 | H17: =(F17*G17)/1000 -> 0 | I17: 1062.1747 | J17: =(H17*I17)/1000 -> 0 | K17: =L17-J17 -> 0 | M17: =(J17/L17) -> #DIV/0! | N17: =K17/L17 -> #DIV/0!
B18: =B17+1 -> 11 | D18: 5 | E18: =C18*D18 -> 0 | F18: =E18 -> 0 | G18: 35.314667 | H18: =(F18*G18)/1000 -> 0 | I18: 1061.2948 | J18: =(H18*I18)/1000 -> 0 | K18: =L18-J18 -> 0 | M18: =(J18/L18) -> #DIV/0! | N18: =K18/L18 -> #DIV/0!
B19: =B18+1 -> 12 | D19: 5 | E19: =C19*D19 -> 0 | F19: =E19 -> 0 | G19: 35.314667 | H19: =(F19*G19)/1000 -> 0 | I19: 1060.6908 | J19: =(H19*I19)/1000 -> 0 | K19: =L19-J19 -> 0 | M19: =(J19/L19) -> #DIV/0! | N19: =K19/L19 -> #DIV/0!
B20: =B19+1 -> 13 | D20: 5 | E20: =C20*D20 -> 0 | F20: =E20 -> 0 | G20: 35.314667 | H20: =(F20*G20)/1000 -> 0 | I20: 1054.3016 | J20: =(H20*I20)/1000 -> 0 | K20: =L20-J20 -> 0 | M20: =(J20/L20) -> #DIV/0! | N20: =K20/L20 -> #DIV/0!
B21: =B20+1 -> 14 | D21: 5 | E21: =C21*D21 -> 0 | F21: =E21 -> 0 | G21: 35.314667 | H21: =(F21*G21)/1000 -> 0 | I21: 1059.7623 | J21: =(H21*I21)/1000 -> 0 | K21: =L21-J21 -> 0 | M21: =(J21/L21) -> #DIV/0! | N21: =K21/L21 -> #DIV/0!
B22: =B21+1 -> 15 | D22: 5 | E22: =C22*D22 -> 0 | F22: =E22 -> 0 | G22: 36.314667 | H22: =(F22*G22)/1000 -> 0 | I22: 1063.1437 | J22: =(H22*I22)/1000 -> 0 | K22: =L22-J22 -> 0 | M22: =(J22/L22) -> #DIV/0! | N22: =K22/L22 -> #DIV/0!
B23: =B22+1 -> 16 | D23: 5 | E23: =C23*D23 -> 0 | F23: =E23 -> 0 | G23: 37.314667 | H23: =(F23*G23)/1000 -> 0 | I23: 1062.3756 | J23: =(H23*I23)/1000 -> 0 | K23: =L23-J23 -> 0 | M23: =(J23/L23) -> #DIV/0! | N23: =K23/L23 -> #DIV/0!
B24: =B23+1 -> 17 | D24: 5 | E24: =C24*D24 -> 0 | F24: =E24 -> 0 | G24: 38.314667 | H24: =(F24*G24)/1000 -> 0 | I24: 1056.7511 | J24: =(H24*I24)/1000 -> 0 | K24: =L24-J24 -> 0 | M24: =(J24/L24) -> #DIV/0! | N24: =K24/L24 -> #DIV/0!
B25: =B24+1 -> 18 | D25: 5 | E25: =C25*D25 -> 0 | F25: =E25 -> 0 | G25: 39.314667 | H25: =(F25*G25)/1000 -> 0 | I25: 1055.0821 | J25: =(H25*I25)/1000 -> 0 | K25: =L25-J25 -> 0 | M25: =(J25/L25) -> #DIV/0! | N25: =K25/L25 -> #DIV/0!
B26: =B25+1 -> 19 | D26: 5 | E26: =C26*D26 -> 0 | F26: =E26 -> 0 | G26: 40.314667 | H26: =(F26*G26)/1000 -> 0 | I26: 1057.166 | J26: =(H26*I26)/1000 -> 0 | K26: =L26-J26 -> 0 | M26: =(J26/L26) -> #DIV/0! | N26: =K26/L26 -> #DIV/0!
B27: =B26+1 -> 20 | D27: 5 | E27: =C27*D27 -> 0 | F27: =E27 -> 0 | G27: 41.314667 | H27: =(F27*G27)/1000 -> 0 | I27: 1061.4358 | J27: =(H27*I27)/1000 -> 0 | K27: =L27-J27 -> 0 | M27: =(J27/L27) -> #DIV/0! | N27: =K27/L27 -> #DIV/0!
... B38: =B37+1 -> 31 | D38: 5 | E38: =C38*D38 -> 0 | F38: =E38 -> 0 | G38: 51.314667 | H38: =(F38*G38)/1000 -> 0 | I38: 1083.7642 | J38: =(H38*I38)/1000 -> 0 | K38: =L38-J38 -> 0 | M38: =(J38/L38) -> #DIV/0! | N38: =K38/L38 -> #DIV/0!
B39: Average | F39: =E39 -> 0 | H39: =AVERAGE(H8:H38) -> 103.56824 | I39: =AVERAGE(I8:I38) -> 1062.8347 | J39: =AVERAGE(J8:J38) -> 108.60882 | K39: =AVERAGE(K8:K38) -> 102.42274 | L39: =AVERAGE(L8:L38) -> 817.74731 | M39: =AVERAGE(M8:M37) -> #DIV/0! | N39: =AVERAGE(N8:N37) -> #DIV/0!
B40: TOTAL | C40: =SUM(C8:C38) -> 18182.9 | E40: =SUM(E8:E38) -> 90914.5 | F40: =E40 -> 90914.5 | H40: =SUM(H8:H38) -> 3210.6153 | J40: =SUM(J8:J38) -> 3366.8735
B41: Koreksi
B42: Total Setelah Koreksi | H42: =H40+H41 -> 3210.6153 | J42: =J40+J41 -> 3366.8735
C44: CONVERT HP Boiler from Utility
C45: =C40 -> 18182.9 | D45: m3 | F45: =C40*5 -> 90914.5 | G45: 9983.7
C46: 5 | D46: bar | F46: 21286.9 | G46: =G45-C40 -> -8199.2
C47: =C45*C46 -> 90914.5 | D47: Sm3 | F47: =F45/F46 -> 4.2709131
C48: =#REF! -> #REF! | D48: Scf
C49: =(C47*C48)/1000 -> #REF! | D49: Volume (MSCF)
C50: =I39 -> 1062.8347 | D50: Heating Value
C51: =(C49*C50)/1000 -> #REF! | D51: Energy (mmbtu)

Sheet Januari 2026 PMG 2
C1: PRODUCTION REPORT PMG 2
C2: No | D2: ITEM | E2: Budget / Norma | F2: UoM | G2: Januari 2026 | AM2: TOTAL MONTHLY (Kg)
G3: 1 | H3: 2 | I3: 3 | J3: 4 | K3: 5 | L3: 6 | M3: 7 | N3: 8 | O3: 9 | P3: 10 | Q3: 11 | R3: 12 | S3: 13 | T3: 14 | U3: 15 | V3: 16 | W3: 17 | X3: 18 | Y3: 19 | Z3: 20 | AA3: 21 | AB3: 22 | AC3: 23 | AD3: 24 | AE3: 25 | AF3: 26 | AG3: 27 | AH3: 28 | AI3: 29 | AJ3: 30 | AK3: 31
C4: 1 | D4: PRODUCTION | AM4: Production | AO4: aktual refinery | AR4: opening stok rpo | AS4: =AS6+AS7+AS9 -> 80236
D5: Refinery | AM5: Refinery | AO5: cpo feed | AP5: =AM9 -> 40125380 | AR5: sisa rbpo tank
D6: Running Days | F6: Day | G6: 1 | H6: 1 | I6: 1 | J6: 1 | V6: 1 | W6: 1 | X6: 1 | Y6: 1 | Z6: 1 | AA6: 1 | AB6: 1 | AC6: 1 | AD6: 1 | AE6: 1 | AF6: 1 | AG6: 1 | AH6: 1 | AI6: 1 | AJ6: 1 | AK6: 1 | AM6: =SUM(G6:AK6) -> 20 | AO6: rpo prod | AP6: =AM20+AM19+AM18 -> 38270376 | AR6: tk 108 | AS6: 80236
D7: Incoming CPO | F7: Kg | G7: 0 | J7: 105280 | K7: 522460 | V7: 2298459 | W7: 1760050 | X7: 1100253 | Y7: 1170450 | Z7: 2354398 | AA7: 2685019 | AB7: 2794189 | AC7: 2277190 | AD7: 3746325 | AE7: 1563383 | AF7: 1263930 | AG7: 1485561 | AH7: 2164949 | AI7: 3173686 | AJ7: 1588046 | AK7: 3641207 | AM7: =SUM(G7:AK7) -> 35694835 | AU7: =AM7+'Januari 2026 PMG 1'!AM7 -> 57887356
D8: Ratio Run CPO ( utilisasi kapasitas ) | F8: % | G8: =G9/2500000 -> 0.7517528 | H8: =H9/2500000 -> 0.78712 | I8: =I9/2500000 -> 0.7869976 | J8: =J9/2500000 -> 0 | K8: =K9/2500000 -> 0 | L8: =L9/2500000 -> 0 | M8: =M9/2500000 -> 0 | N8: =N9/2500000 -> 0 | ... V8: =V9/2500000 -> 0.5465676 | W8: 0.8090604 | X8: 0 | Y8: =Y9/2500000 -> 0.8180376 | Z8: =Z9/2500000 -> 0.8255544 | AA8: =AA9/2500000 -> 0.8262308 | AB8: =AB9/2500000 -> 0.9176256 | AC8: =AC9/2500000 -> 0.9530264 | AD8: =AD9/2500000 -> 0.9034832 | AE8: =AE9/2500000 -> 0.9438852 | AF8: =AF9/2500000 -> 0.8196664 | ... AK8: =AK9/2500000 -> 0.8586632 | AM8: =AM9/2500000/AM6 -> 0.8025076
D9: CPO Consume Total | E9: 58900000 | F9: Kg | G9: 1879382 | H9: 1967800 | I9: 1967494 | J9: 0 | K9: 0 | V9: 1366419 | W9: 2328853 | X9: 2350380 | Y9: 2045094 | Z9: 2063886 | AA9: 2065577 | AB9: 2294064 | AC9: 2382566 | AD9: 2258708 | AE9: 2359713 | AF9: 2049166 | AG9: 2193352 | AH9: 2154090 | AI9: 2127237 | AJ9: 2124941 | AK9: 2146658 | AM9: =SUM(G9:AK9) -> 40125380
D10: Avg Daily Consump CPO ( MTD ) | AM10: =AM9/AM6 -> 2006269
D11: CPO Consume Poram | F11: Kg | G11: =G9-G12 -> 1879382 | H11: =H9-H12 -> 1967800 | I11: =I9-I12 -> 1967494 | J11: =J9-J12 -> 0 | K11: =K9-K12 -> 0 | L11: =L9-L12 -> 0 | M11: =M9-M12 -> 0 | N11: =N9-N12 -> 0 | ... AK11: =AK9-AK12 -> 2146658 | AM11: =SUM(G11:AK11) -> 40125380
D12: CPO Consume Brand | F12: Kg | G12: =G40+G49+G54 -> 0 | H12: =H40+H49+H54 -> 0 | I12: =I40+I49+I54 -> 0 | J12: =J40+J49+J54 -> 0 | K12: =K40+K49+K54 -> 0 | L12: =L40+L49+L54 -> 0 | M12: =M40+M49+M54 -> 0 | N12: =N40+N49+N54 -> 0 | ... R12: =R40+R49+R54 -> 0 | S12: 0 | T12: =T40+T49+T54 -> 0 | U12: =U40+U49+U54 -> 0 | V12: =V40+V49+V54 -> 0 | W12: 0 | X12: 0 | Y12: =Y40+Y49+Y54 -> 0 | Z12: =Z40+Z49+Z54 -> 0 | AA12: =AA40+AA49+AA54 -> 0 | AB12: =AB40+AB49+AB54 -> 0 | AC12: 0 | AD12: 0 | AE12: =AE40+AE49+AE54 -> 0 | AF12: =AF40+AF49+AF54 -> 0 | AG12: =AG40+AG49+AG54 -> 0 | AH12: =AH40+AH49+AH54 -> 0 | AM12: =SUM(G12:AK12) -> 0
D13: - FFA | E13: 5 | F13: % | G13: 4.1 | H13: =(4.15+3.97)/2 -> 4.06 | I13: 4.03 | J13: 0 | V13: 0 | W13: 4.24 | X13: 3.97 | Y13: =(4.09+3.48)/2 -> 3.785 | Z13: 4.13 | AA13: =(4.28+4.21)/2 -> 4.245 | AB13: 4.23 | AC13: 4.26 | AD13: =(4.5+3.89)/2 -> 4.195 | AE13: =(3.89+4.22)/2 -> 4.055 | AF13: 4.24 | AG13: =(5.67+4.42)/2 -> 5.045 | AH13: 4.12 | AI13: =(4.41+3.93)/2 -> 4.17 | AJ13: =(3.83+4.17)/2 -> 4 | AK13: =(4.16+4.44+3.71)/3 -> 4.1033333 | AM13: =SUM(G13:AK13)/AM6 -> 3.7489167 | AO13: rpo feed | AP13: =AP14+AP15 -> 39418618 | AR13: tk131 | AS13: ='OIP Fract PMG 2'!T13 -> 133300
D14: - Moist & Impurities | E14: 0.5 | F14: % | G14: 0.44 | H14: =(0.45+0.41)/2 -> 0.43 | I14: 0.43 | J14: 0 | V14: 0 | W14: 0.4 | X14: 0.4 | Y14: =(3.48+0.41)/2 -> 1.945 | Z14: 0.4 | AA14: =(0.41+0.44)/2 -> 0.425 | AB14: 0.45 | AC14: 0.46 | AD14: =(0.49+0.38)/2 -> 0.435 | AE14: =(0.4+0.39)/2 -> 0.395 | AF14: 0.4 | AG14: =(0.43+0.41)/2 -> 0.42 | AH14: 0.44 | AI14: =(0.4+0.36)/2 -> 0.38 | AJ14: =(0.41+0.46)/2 -> 0.435 | AK14: =(0.45+0.46+0.4)/3 -> 0.43666667 | AM14: =SUM(G14:AK14)/AM6 -> 0.45608333 | AO14: olein 56 | AP14: =AM33 -> 32649843 | AR14: tk132 | AS14: ='OIP Fract PMG 2'!U13 -> 0
D15: - DOBI | E15: 2,20 Min | F15: % | AM15: =SUM(G15:AK15)/AM6 -> 0 | AO15: stearin 56 | AP15: =AM34 -> 6768775 | AR15: after
D16: TANK | G16: 107 | H16: 107104 | I16: 104 | J16: 0 | V16: 0 | W16: 106 | X16: 107 | Y16: 104107 | Z16: 104 | AA16: 104107 | AB16: 107 | AC16: 107 | AD16: 104107 | AE16: 106107 | AF16: 107 | AG16: 107104 | AH16: 107 | AI16: 104106 | AJ16: 106107 | AK16: 106107 | AO16: yield olein | AP16: =AP14/(AP14+AP15)*100 -> 82.828482 | AR16: tk131 | AS16: =AS13 -> 133300
D17: Product | AM17: Product | AO17: yield stearin | AP17: =AP15/(AP14+AP15)*100 -> 17.171518 | AR17: tk132 | AS17: =AS14-AP13 -> -39418618
D18: OIP RBDPO | F18: Kg | AM18: =SUM(G18:AK18) -> 0
D19: DIRECT RBDPO FRACT | F19: Kg | G19: 1789520 | H19: 1871999 | I19: 1865431 | J19: 83475 | V19: 1288722 | W19: 2199287 | X19: 2244332 | Y19: 1945574 | Z19: 1960365 | AA19: 1964892 | AB19: 2186862 | AC19: 2278056 | AD19: 2159702 | AE19: 2258073 | AF19: 1949216 | AG19: 2082705 | AH19: 2049455 | AI19: 2008090 | AJ19: 2023267 | AK19: 2061353 | AM19: =SUM(G19:AK19) -> 38270376
D20: RBDPO | E20: 55661000 | F20: Kg | AM20: =SUM(G20:AK20) -> 0
D21: PFAD | E21: 2827000 | F21: Kg | G21: 79332 | H21: 86463 | I21: 83606 | J21: 4613 | V21: 67467 | W21: 109927 | X21: 94071 | Y21: 88505 | Z21: 90992 | AA21: 91336 | AB21: 104079 | AC21: 97755 | AD21: 104153 | AE21: 89862 | AF21: 91305 | AG21: 98055 | AH21: 89257 | AI21: 100135 | AJ21: 87907 | AK21: 93668 | AM21: =SUM(G21:AK21) -> 1752488
D22: Fractionation
D23: Running Days | F23: Day | G23: 1 | H23: 1 | I23: 1 | J23: 1 | M23: 1 | N23: 1 | O23: 1 | P23: 1 | Q23: 1 | R23: 1 | S23: 1 | T23: 1 | U23: 1 | V23: 1 | W23: 1 | X23: 1 | Y23: 1 | Z23: 1 | AA23: 1 | AB23: 1 | AC23: 1 | AD23: 1 | AE23: 1 | AF23: 1 | AG23: 1 | AH23: 1 | AI23: 1 | AJ23: 1 | AK23: 1 | AM23: =SUM(G23:AK23) -> 29
D24: Avg Daily Consump RBDPO ( MTD ) | F24: Kg | G24: 0 | H24: 0 | I24: 0 | J24: 0 | K24: 0 | L24: 0 | M24: 0 | N24: 0 | O24: 0 | P24: 0 | Q24: 0 | R24: 0 | S24: 0 | T24: 0 | U24: 0 | V24: 0 | W24: 0 | X24: 0 | Y24: 0 | Z24: 0 | AA24: 0 | AB24: 0 | AC24: 0 | AD24: 0 | AE24: 0 | AF24: 0 | AG24: 0 | AH24: 0 | AI24: 0 | AJ24: 0 | AK24: 0 | AM24: =AM29/AM23 -> 1775536
D25: Total RBDPO transfer to plant | F25: Kg | AJ25: 0 | AK25: 0 | AM25: =SUM(G25:AK25) -> 0
D26: Stok TK 131 | E26: 559 | F26: ton
D27: Stok TK 132 | E27: 559 | F27: ton
D28: Ratio Run RBDPO | F28: % | G28: =G29/2500000 -> 0.7676072 | H28: =H29/2500000 -> 0.6317164 | I28: =I29/2500000 -> 0.6484316 | J28: =J29/2500000 -> 0.4699164 | K28: =K29/2500000 -> 0 | L28: =L29/2500000 -> 0 | M28: =M29/2500000 -> 0.2025492 | N28: =N29/2500000 -> 0.6516948 | ... V28: =V29/2500000 -> 0.4461308 | W28: 0.7274628 | X28: 0 | Y28: =Y29/2500000 -> 0.7295156 | Z28: =Z29/2500000 -> 0.8939452 | AA28: =AA29/2500000 -> 0.8844584 | AB28: =AB29/2500000 -> 0.9157468 | AC28: 0.52886 | AD28: =AD29/2500000 -> 0.8784892 | AE28: =AE29/2500000 -> 0.6777416 | AF28: =AF29/2500000 -> 0.638504 | AG28: =AG29/2500000 -> 0.6582624 | AH28: =AH29/2500000 -> 0.6811392 | AI28: =AI29/2500000 -> 0.7545008 | AJ28: =AJ29/2500000 -> 0.7655932 | AK28: =AK29/2500000 -> 0.8334324 | AM28: =AM29/2500000/AM23 -> 0.71021441
D29: Total Proses RBDPO | E29: 35501000 | F29: Kg | G29: =SUM(G32,G36,G41,G45,G55) -> 1919018 | H29: =SUM(H32,H36,H41,H45,H55) -> 1579291 | I29: =SUM(I32,I36,I41,I45,I55) -> 1621079 | J29: =SUM(J32,J36,J41,J45,J55) -> 1174791 | K29: =SUM(K32,K36,K41,K45,K55) -> 0 | L29: =SUM(L32,L36,L41,L45,L55) -> 0 | M29: =SUM(M32,M36,M41,M45,M55) -> 506373 | N29: =SUM(N32,N36,N41,N45,N55) -> 1629237 | ... AK29: =SUM(AK32,AK36,AK41,AK45,AK55) -> 2083581 | AM29: =SUM(G29:AK29) -> 51490545
D30: Sisa Filling Crystalizer | F30: Kg | G30: =G25-G29 -> -1919018 | H30: =H25-H29 -> -1579291 | I30: =I25-I29 -> -1621079 | J30: =J25-J29 -> -1174791 | K30: =K25-K29 -> 0 | L30: =L25-L29 -> 0 | M30: =M25-M29 -> -506373 | N30: =N25-N29 -> -1629237 | ... AK30: =AK25-AK29 -> -2083581 | AM30: =SUM(G30:AK30) -> -51490545
D31: Fractionation OLEIN IV 56 | AM31: Olein IV 56
D32: RBDPO Consume | F32: Kg | G32: =G33+G34 -> 1919018 | H32: =H33+H34 -> 60632 | I32: =I33+I34 -> 0 | J32: =J33+J34 -> 0 | K32: =K33+K34 -> 0 | L32: =L33+L34 -> 0 | M32: =M33+M34 -> 0 | N32: =N33+N34 -> 0 | ... AK32: =AK33+AK34 -> 2083581 | AM32: =SUM(G32:AK32) -> 39418618
D33: OLEIN IV 56 | E33: 25000000 | F33: Kg | G33: 1638220 | H33: 45173 | O33: 1070613 | P33: 1779634 | Q33: 1641727 | R33: 1472069 | S33: 1577279 | T33: 1483953 | U33: 1470575 | V33: 931609 | W33: 1268920 | X33: 1089983 | Y33: 1344811 | Z33: 1856465 | AA33: 1830392 | AB33: 1907299 | AC33: 1809986 | AD33: 1817464 | AE33: 947513 | AF33: 419201 | AH33: 386576 | AI33: 1551630 | AJ33: 1576974 | AK33: 1731777 | AM33: =SUM(G33:AK33) -> 32649843 | AN33: ok cek konsum rpo pas
D34: STEARIN | E34: 639000 | F34: Kg | G34: 280798 | H34: 15459 | O34: 209542 | P34: 338068 | Q34: 378795 | R34: 320029 | S34: 330863 | T34: 307196 | U34: 293951 | V34: 183718 | W34: 294260 | X34: 239771 | Y34: 278732 | Z34: =135333+243065 -> 378398 | AA34: 380754 | AB34: 382068 | AC34: 397139 | AD34: 378759 | AE34: 193216 | AF34: 79368 | AH34: 84456 | AI34: 334622 | AJ34: 337009 | AK34: 351804 | AM34: =SUM(G34:AK34) -> 6768775 | AN34: ok cek konsum rpo pas
D35: Fractionation OLEIN IV 57 ( Bulk ) | Z35: 0 | AM35: Olein IV 57 ( Bulk )
D36: RBDPO Consume | F36: Kg | G36: =G37+G38 -> 0 | H36: =H37+H38 -> 0 | I36: =I37+I38 -> 0 | J36: =J37+J38 -> 0 | K36: 0 | M36: 0 | R36: =R37+R38 -> 0 | S36: 0 | T36: =T37+T38 -> 0 | U36: =U37+U38 -> 0 | V36: =V37+V38 -> 0 | W36: 0 | X36: 0 | AA36: =AA37+AA38 -> 0 | AB36: =AB37+AB38 -> 0 | AC36: 0 | AD36: =AD37+AD38 -> 0 | AE36: =AE37+AE38 -> 0 | AF36: =AF37+AF38 -> 0 | AG36: =AG37+AG38 -> 0 | AH36: =AH37+AH38 -> 0 | AM36: =SUM(G36:AK36) -> 0
D37: OLEIN IV 57 | F37: Kg | H37: 0 | I37: 0 | J37: 0 | K37: 0 | M37: 0 | R37: 0 | S37: 0 | T37: 0 | U37: 0 | V37: 0 | W37: 0 | X37: 0 | AA37: 0 | AB37: 0 | AC37: 0 | AD37: 0 | AE37: 0 | AF37: 0 | AG37: 0 | AM37: =SUM(G37:AK37) -> 0
D38: STEARIN | F38: Kg | H38: 0 | I38: 0 | J38: 0 | K38: 0 | M38: 0 | R38: 0 | S38: 0 | T38: 0 | U38: 0 | V38: 0 | W38: 0 | X38: 0 | AA38: 0 | AB38: 0 | AC38: 0 | AD38: 0 | AE38: 0 | AF38: 0 | AG38: 0 | AM38: =SUM(G38:AK38) -> 0
D39: Fractionation OLEIN IV 57 ( Retail ) | AM39: Olein IV 57 ( Retail )
D40: CPO Consume | F40: Kg | AM40: =SUM(G40:AK40) -> 0
D41: RBDPO Brand Consume | F41: Kg | G41: =G42+G43 -> 0 | H41: =H42+H43 -> 0 | I41: =I42+I43 -> 0 | J41: =J42+J43 -> 0 | K41: 0 | M41: 0 | R41: =R42+R43 -> 0 | S41: 0 | T41: =T42+T43 -> 0 | U41: =U42+U43 -> 0 | V41: =V42+V43 -> 0 | W41: 0 | X41: 0 | AA41: =AA42+AA43 -> 0 | AB41: =AB42+AB43 -> 0 | AC41: 0 | AD41: =AD42+AD43 -> 0 | AE41: =AE42+AE43 -> 0 | AF41: =AF42+AF43 -> 0 | AG41: =AG42+AG43 -> 0 | AH41: =AH42+AH43 -> 0 | AM41: =SUM(G41:AK41) -> 0
D42: OLEIN IV 57 Low Color | F42: Kg | H42: 0 | I42: 0 | J42: 0 | K42: 0 | M42: 0 | R42: 0 | S42: 0 | T42: 0 | U42: 0 | V42: 0 | W42: 0 | X42: 0 | AA42: 0 | AB42: 0 | AC42: 0 | AD42: 0 | AE42: 0 | AF42: 0 | AG42: 0 | AM42: =SUM(G42:AK42) -> 0
D43: STEARIN | F43: Kg | H43: 0 | I43: 0 | J43: 0 | K43: 0 | M43: 0 | R43: 0 | S43: 0 | T43: 0 | U43: 0 | V43: 0 | W43: 0 | X43: 0 | AA43: 0 | AB43: 0 | AC43: 0 | AD43: 0 | AE43: 0 | AF43: 0 | AG43: 0 | AM43: =SUM(G43:AK43) -> 0
D44: Fractionation OLEIN IV 58 ( Bulk ) | AM44: Olein IV 58 ( Bulk )
D45: RBDPO Consume | E45: 17143 | F45: Kg | G45: =G46+G47 -> 0 | H45: =H46+H47 -> 1518659 | I45: =I46+I47 -> 1621079 | J45: =J46+J47 -> 1174791 | K45: =K46+K47 -> 0 | L45: =L46+L47 -> 0 | M45: =M46+M47 -> 506373 | N45: =N46+N47 -> 1629237 | ... AK45: =AK46+AK47 -> 0 | AM45: =SUM(G45:AK45) -> 12071927
D46: OLEIN IV 58 | E46: 12000000 | F46: Kg | H46: 1157159 | I46: 1231986 | J46: 875130 | M46: 430867 | N46: 1243637 | O46: 354999 | X46: 286697 | Y46: 140629 | AE46: 427825 | AF46: 821660 | AG46: 1255178 | AH46: 932781 | AM46: =SUM(G46:AK46) -> 9158548 | AN46: ok cek konsum rpo pas
D47: STEARIN | E47: 514300 | F47: Kg | H47: 361500 | I47: 389093 | J47: 299661 | M47: 75506 | N47: 385600 | O47: 141058 | X47: 110000 | Y47: 59617 | AE47: 125800 | AF47: 276031 | AG47: 390478 | AH47: 299035 | AM47: =SUM(G47:AK47) -> 2913379 | AN47: ok cek konsum rpo pas
D48: Fractionation OLEIN IV 58 ( Retail ) | AM48: Olein IV 58 ( Retail )
D49: CPO Consume | F49: Kg | AM49: =SUM(G49:AK49) -> 0
D50: RBDPO Consume | E50: =E51+E52 -> 21429000 | F50: Kg | G50: =G51+G52 -> 0 | H50: =H51+H52 -> 0 | I50: =I51+I52 -> 0 | J50: =J51+J52 -> 0 | K50: 0 | M50: 0 | R50: =R51+R52 -> 0 | S50: 0 | T50: =T51+T52 -> 0 | U50: =U51+U52 -> 0 | V50: =V51+V52 -> 0 | W50: 0 | X50: 0 | Y50: =Y51+Y52 -> 0 | Z50: =Z51+Z52 -> 0 | AA50: =AA51+AA52 -> 0 | AB50: =AB51+AB52 -> 0 | AC50: =AC51+AC52 -> 0 | AD50: =AD51+AD52 -> 0 | AE50: =AE51+AE52 -> 0 | AF50: =AF51+AF52 -> 0 | ... AH50: =AH51+AH52 -> 0 | AM50: =SUM(G50:AK50) -> 0
D51: OLEIN IV 58 | E51: 15000000 | F51: Kg | H51: 0 | I51: 0 | J51: 0 | K51: 0 | M51: 0 | R51: 0 | S51: 0 | T51: 0 | U51: 0 | V51: 0 | W51: 0 | X51: 0 | Y51: 0 | Z51: 0 | AA51: 0 | AB51: 0 | AC51: 0 | AD51: 0 | AE51: 0 | AF51: 0 | AG51: 0 | AH51: 0 | AM51: =SUM(G51:AK51) -> 0
D52: STEARIN | E52: 6429000 | F52: Kg | H52: 0 | I52: 0 | J52: 0 | K52: 0 | M52: 0 | R52: 0 | S52: 0 | T52: 0 | U52: 0 | V52: 0 | W52: 0 | X52: 0 | Y52: 0 | Z52: 0 | AA52: 0 | AB52: 0 | AC52: 0 | AD52: 0 | AE52: 0 | AF52: 0 | AG52: 0 | AH52: 0 | AM52: =SUM(G52:AK52) -> 0
D53: Fractionation OLEIN IV 60 | AM53: Olein IV 60
D54: CPO Consume | F54: Kg | AM54: =SUM(G54:AK54) -> 0
D55: RBDPO Brand Consume | E55: =E56+E57 -> 1333300 | F55: Kg | G55: =G56+G57 -> 0 | H55: =H56+H57 -> 0 | I55: =I56+I57 -> 0 | J55: =J56+J57 -> 0 | K55: 0 | M55: 0 | S55: =S56+S57 -> 0 | T55: =T56+T57 -> 0 | U55: =U56+U57 -> 0 | V55: =V56+V57 -> 0 | W55: 0 | X55: 0 | Y55: =Y56+Y57 -> 0 | AA55: =AA56+AA57 -> 0 | AB55: =AB56+AB57 -> 0 | AC55: =AC56+AC57 -> 0 | AD55: =AD56+AD57 -> 0 | AE55: =AE56+AE57 -> 0 | AF55: =AF56+AF57 -> 0 | AG55: =AG56+AG57 -> 0 | AH55: =AH56+AH57 -> 0 | AM55: =SUM(G55:AK55) -> 0
D56: OLEIN IV 60 Salvaco | E56: 1250000 | F56: Kg | H56: 0 | I56: 0 | J56: 0 | K56: 0 | M56: 0 | R56: 0 | T56: 0 | U56: 0 | V56: 0 | W56: 0 | X56: 0 | Y56: 0 | AB56: 0 | AC56: 0 | AD56: 0 | AE56: 0 | AF56: 0 | AH56: 0 | AM56: =SUM(G56:AK56) -> 0
D57: SOFT STEARIN | E57: 83300 | F57: Kg | H57: 0 | I57: 0 | J57: 0 | K57: 0 | M57: 0 | R57: 0 | T57: 0 | U57: 0 | V57: 0 | W57: 0 | X57: 0 | Y57: 0 | AB57: 0 | AC57: 0 | AD57: 0 | AE57: 0 | AF57: 0 | AH57: 0 | AM57: =SUM(G57:AK57) -> 0
D58: Ratio Run RBDPO | F58: % | G58: 0 | H58: 0 | I58: 0 | J58: 0 | K58: 0 | M58: 0 | R58: 0 | S58: 0 | T58: 0 | U58: 0 | V58: 0 | W58: 0 | X58: 0 | Y58: 0 | Z58: 0 | AA58: 0 | AB58: 0 | AC58: 0 | AD58: 0 | AE58: 0 | AF58: 0 | AG58: 0 | AH58: 0 | AM58: =SUM(G58:AK58) -> 0
D59: YIELD | AM59: Yield | BA59: 40006710 | BB59: semi aktivasi
D60: RBDPO | E60: 94.2 | F60: % | G60: =((G20+G19+G18)/(G9))*100 -> 95.218535 | H60: =((H20+H19+H18)/(H9))*100 -> 95.131568 | I60: =((I20+I19+I18)/(I9))*100 -> 94.812538 | J60: =((J20+J19+J18)/(J9))*100 -> #DIV/0! | K60: =((K20+K19+K18)/(K9))*100 -> #DIV/0! | L60: =((L20+L19+L18)/(L9))*100 -> #DIV/0! | M60: =((M20+M19+M18)/(M9))*100 -> #DIV/0! | N60: =((N20+N19+N18)/(N9))*100 -> #DIV/0! | ... AK60: =((AK20+AK19+AK18)/(AK9))*100 -> 96.026149 | AM60: =((AM20+AM19+AM18)/(AM9))*100 -> 95.376981 | AY60: 40006709 | AZ60: aktivasi | BA60: 7000 | BB60: qty | BC60: jika di konsum harusnya koosng di 1013 produksi
D61: PFAD | E61: 5 | F61: % | G61: =(G21/(G9))*100 -> 4.2211748 | H61: =(H21/(H9))*100 -> 4.3938917 | I61: =(I21/(I9))*100 -> 4.2493649 | J61: =(J21/(J9))*100 -> #DIV/0! | K61: =(K21/(K9))*100 -> #DIV/0! | L61: =(L21/(L9))*100 -> #DIV/0! | M61: =(M21/(M9))*100 -> #DIV/0! | N61: =(N21/(N9))*100 -> #DIV/0! | ... AK61: =(AK21/(AK9))*100 -> 4.3634338 | AM61: =(AM21/(AM9))*100 -> 4.36753 | AY61: =40913+35000 -> 75913 | AZ61: qty
D62: Olein IV 56 | E62: 82 | F62: % | G62: =G33/(G33+G34)*100 -> 85.36762 | H62: =H33/(H33+H34)*100 -> 74.503562 | I62: =I33/(I33+I34)*100 -> #DIV/0! | J62: =J33/(J33+J34)*100 -> #DIV/0! | K62: =K33/(K33+K34)*100 -> #DIV/0! | L62: =L33/(L33+L34)*100 -> #DIV/0! | M62: =M33/(M33+M34)*100 -> #DIV/0! | N62: =N33/(N33+N34)*100 -> #DIV/0! | ... AK62: =AK33/(AK33+AK34)*100 -> 83.115415 | AM62: =AM33/(AM33+AM34)*100 -> 82.828482 | AY62: =AY61-AX76 -> 58529
D63: Stearin | E63: 18 | F63: % | G63: =(G34/G32)*100 -> 14.63238 | H63: =(H34/H32)*100 -> 25.496438 | I63: =(I34/I32)*100 -> #DIV/0! | J63: =(J34/J32)*100 -> #DIV/0! | K63: =(K34/K32)*100 -> #DIV/0! | L63: =(L34/L32)*100 -> #DIV/0! | M63: =(M34/M32)*100 -> #DIV/0! | N63: =(N34/N32)*100 -> #DIV/0! | ... AK63: =(AK34/AK32)*100 -> 16.884585 | AM63: =AM34/(AM33+AM34)*100 -> 17.171518
D64: Olein IV 57 ( Bulk ) | E64: 75 | G64: =(G37/G36)*100 -> #DIV/0! | H64: =(H37/H36)*100 -> #DIV/0! | I64: =(I37/I36)*100 -> #DIV/0! | J64: =(J37/J36)*100 -> #DIV/0! | K64: =(K37/K36)*100 -> #DIV/0! | L64: =(L37/L36)*100 -> #DIV/0! | M64: =(M37/M36)*100 -> #DIV/0! | N64: =(N37/N36)*100 -> #DIV/0! | ... AK64: =(AK37/AK36)*100 -> #DIV/0! | AM64: =(AM42/AM41)*100 -> #DIV/0!
D65: Stearin | E65: 25 | G65: =(G38/G36)*100 -> #DIV/0! | H65: =(H38/H36)*100 -> #DIV/0! | I65: =(I38/I36)*100 -> #DIV/0! | J65: =(J38/J36)*100 -> #DIV/0! | K65: =(K38/K36)*100 -> #DIV/0! | L65: =(L38/L36)*100 -> #DIV/0! | M65: =(M38/M36)*100 -> #DIV/0! | N65: =(N38/N36)*100 -> #DIV/0! | ... AK65: =(AK38/AK36)*100 -> #DIV/0! | AM65: =(AM43/AM41)*100 -> #DIV/0!
D66: Olein IV 57 ( Retail ) | E66: 75 | F66: % | G66: =G42/G41*100 -> #DIV/0! | H66: =H42/H41*100 -> #DIV/0! | I66: =I42/I41*100 -> #DIV/0! | J66: =J42/J41*100 -> #DIV/0! | K66: =K42/K41*100 -> #DIV/0! | L66: =L42/L41*100 -> #DIV/0! | M66: =M42/M41*100 -> #DIV/0! | N66: =N42/N41*100 -> #DIV/0! | ... AK66: =AK42/AK41*100 -> #DIV/0! | AM66: =AM42/AM41*100 -> #DIV/0!
D67: Stearin | E67: 25 | F67: % | G67: =G43/G41*100 -> #DIV/0! | H67: =H43/H41*100 -> #DIV/0! | I67: =I43/I41*100 -> #DIV/0! | J67: =J43/J41*100 -> #DIV/0! | K67: =K43/K41*100 -> #DIV/0! | L67: =L43/L41*100 -> #DIV/0! | M67: =M43/M41*100 -> #DIV/0! | N67: =N43/N41*100 -> #DIV/0! | ... AK67: =AK43/AK41*100 -> #DIV/0! | AM67: =AM43/AM41*100 -> #DIV/0!
D68: Olein IV 58 ( Bulk ) | E68: 70 | F68: % | G68: =G46/(G46+G47)*100 -> #DIV/0! | H68: =H46/(H46+H47)*100 -> 76.196105 | I68: =I46/(I46+I47)*100 -> 75.9979 | J68: =J46/(J46+J47)*100 -> 74.492399 | K68: =K46/(K46+K47)*100 -> #DIV/0! | L68: =L46/(L46+L47)*100 -> #DIV/0! | M68: =M46/(M46+M47)*100 -> 85.088857 | N68: =N46/(N46+N47)*100 -> 76.33248 | ... AK68: =AK46/(AK46+AK47)*100 -> #DIV/0! | AM68: =AM46/(AM46+AM47)*100 -> 75.866496
D69: Stearin | E69: 30 | F69: % | G69: =G47/(G47+G46)*100 -> #DIV/0! | H69: =H47/(H47+H46)*100 -> 23.803895 | I69: =I47/(I47+I46)*100 -> 24.0021 | J69: =J47/(J47+J46)*100 -> 25.507601 | K69: =K47/(K47+K46)*100 -> #DIV/0! | L69: =L47/(L47+L46)*100 -> #DIV/0! | M69: =M47/(M47+M46)*100 -> 14.911143 | N69: =N47/(N47+N46)*100 -> 23.66752 | ... AK69: =AK47/(AK47+AK46)*100 -> #DIV/0! | AM69: =AM47/AM45*100 -> 24.133504
D70: Olein IV 58 ( Retail ) | E70: 70 | F70: % | G70: =G51/(G51+G52)*100 -> #DIV/0! | H70: =H51/(H51+H52)*100 -> #DIV/0! | I70: =I51/(I51+I52)*100 -> #DIV/0! | J70: =J51/(J51+J52)*100 -> #DIV/0! | K70: =K51/(K51+K52)*100 -> #DIV/0! | M70: #DIV/0! | R70: =R51/(R51+R52)*100 -> #DIV/0! | S70: =S51/(S51+S52)*100 -> #DIV/0! | T70: =T51/(T51+T52)*100 -> #DIV/0! | U70: =U51/(U51+U52)*100 -> #DIV/0! | V70: =V51/(V51+V52)*100 -> #DIV/0! | W70: #DIV/0! | X70: =X51/(X51+X52)*100 -> #DIV/0! | Y70: =Y51/(Y51+Y52)*100 -> #DIV/0! | Z70: =Z51/(Z51+Z52)*100 -> #DIV/0! | AA70: =AA51/(AA51+AA52)*100 -> #DIV/0! | AB70: =AB51/(AB51+AB52)*100 -> #DIV/0! | AC70: =AC51/(AC51+AC52)*100 -> #DIV/0! | AD70: =AD51/(AD51+AD52)*100 -> #DIV/0! | AE70: =AE51/(AE51+AE52)*100 -> #DIV/0! | ... AK70: =AK51/(AK51+AK52)*100 -> #DIV/0! | AM70: =AM51/(AM51+AM52)*100 -> #DIV/0!
D71: Stearin | E71: 30 | F71: % | G71: =G52/(G51+G52)*100 -> #DIV/0! | H71: =H52/(H51+H52)*100 -> #DIV/0! | I71: =I52/(I51+I52)*100 -> #DIV/0! | J71: =J52/(J51+J52)*100 -> #DIV/0! | K71: =K52/(K51+K52)*100 -> #DIV/0! | M71: #DIV/0! | R71: =R52/(R51+R52)*100 -> #DIV/0! | S71: =S52/(S51+S52)*100 -> #DIV/0! | T71: =T52/(T51+T52)*100 -> #DIV/0! | U71: =U52/(U51+U52)*100 -> #DIV/0! | V71: =V52/(V51+V52)*100 -> #DIV/0! | W71: #DIV/0! | X71: =X52/(X51+X52)*100 -> #DIV/0! | Y71: =Y52/(Y51+Y52)*100 -> #DIV/0! | Z71: =Z52/(Z51+Z52)*100 -> #DIV/0! | AA71: =AA52/(AA51+AA52)*100 -> #DIV/0! | AB71: =AB52/(AB51+AB52)*100 -> #DIV/0! | AC71: =AC52/(AC51+AC52)*100 -> #DIV/0! | AD71: =AD52/(AD51+AD52)*100 -> #DIV/0! | AE71: =AE52/(AE51+AE52)*100 -> #DIV/0! | ... AK71: =AK52/(AK51+AK52)*100 -> #DIV/0! | AM71: =AM52/(AM51+AM52)*100 -> #DIV/0!
D72: Olein IV 60 | E72: 60 | F72: % | G72: =G56/(G56+G57)*100 -> #DIV/0! | H72: =H56/(H56+H57)*100 -> #DIV/0! | I72: =I56/(I56+I57)*100 -> #DIV/0! | J72: =J56/(J56+J57)*100 -> #DIV/0! | K72: =K56/(K56+K57)*100 -> #DIV/0! | M72: #DIV/0! | R72: =R56/(R56+R57)*100 -> #DIV/0! | S72: =S56/(S56+S57)*100 -> #DIV/0! | T72: =T56/(T56+T57)*100 -> #DIV/0! | U72: =U56/(U56+U57)*100 -> #DIV/0! | V72: =V56/(V56+V57)*100 -> #DIV/0! | W72: #DIV/0! | X72: =X56/(X56+X57)*100 -> #DIV/0! | Y72: =Y56/(Y56+Y57)*100 -> #DIV/0! | Z72: =Z56/(Z56+Z57)*100 -> #DIV/0! | AA72: =AA56/(AA56+AA57)*100 -> #DIV/0! | AB72: =AB56/(AB56+AB57)*100 -> #DIV/0! | AC72: =AC56/(AC56+AC57)*100 -> #DIV/0! | AD72: =AD56/(AD56+AD57)*100 -> #DIV/0! | AE72: =AE56/(AE56+AE57)*100 -> #DIV/0! | ... AK72: =AK56/(AK56+AK57)*100 -> #DIV/0! | AM72: =AM56/(AM57+AM56)*100 -> #DIV/0!
D73: Soft Stearin | E73: 40 | F73: % | G73: =G57/G55*100 -> #DIV/0! | H73: =H57/H55*100 -> #DIV/0! | I73: =I57/I55*100 -> #DIV/0! | J73: =J57/J55*100 -> #DIV/0! | K73: =K57/K55*100 -> #DIV/0! | M73: #DIV/0! | R73: =R57/R55*100 -> #DIV/0! | S73: =S57/S55*100 -> #DIV/0! | T73: =T57/T55*100 -> #DIV/0! | U73: =U57/U55*100 -> #DIV/0! | V73: =V57/V55*100 -> #DIV/0! | W73: #DIV/0! | X73: =X57/X55*100 -> #DIV/0! | Y73: =Y57/Y55*100 -> #DIV/0! | Z73: =Z57/Z55*100 -> #DIV/0! | AA73: =AA57/AA55*100 -> #DIV/0! | AB73: =AB57/AB55*100 -> #DIV/0! | AC73: =AC57/AC55*100 -> #DIV/0! | AD73: =AD57/AD55*100 -> #DIV/0! | AE73: =AE57/AE55*100 -> #DIV/0! | ... AK73: =AK57/AK55*100 -> #DIV/0! | AM73: =AM57/(AM56+AM57)*100 -> #DIV/0!
C74: 2 | D74: CHEMICAL CONSUMABLE | AM74: Chemical
D75: Bleaching Earth (BE) to Hopper | E75: 9 | F75: Kg | G75: 11484 | H75: 13266 | I75: 13024 | J75: 275 | K75: 0 | V75: 3839 | W75: 14707 | X75: 13233 | Y75: 11605 | Z75: 11506 | AA75: 13145 | AB75: 12298 | AC75: 12507 | AD75: 13277 | AE75: 12276 | AF75: 11858 | AG75: 13530 | AH75: 11088 | AI75: =13396+2000 -> 15396 | AJ75: =14460+2000 -> 16460 | AK75: =45913 -> 45913 | AM75: =SUM(G75:AK75) -> 270687 | AN75: =AM75-AK75 -> 224774 | AV75: ok cek | AW75: 7000 | AY75: semi 710
D76: Note : BE Aktivasi start tgl 23 Bulan September (0,67 %) | F76: % | G76: =G75/(G11)*100 -> 0.61105193 | H76: =H75/(H11)*100 -> 0.67415388 | I76: =I75/(I11)*100 -> 0.66195882 | J76: =J75/(J11)*100 -> #DIV/0! | K76: =K75/(K11)*100 -> #DIV/0! | L76: =L75/(L11)*100 -> #DIV/0! | M76: =M75/(M11)*100 -> #DIV/0! | N76: =N75/(N11)*100 -> #DIV/0! | ... Q76: =Q75/(Q11)*100 -> #DIV/0! | R76: =R75/(R11)*1000 -> #DIV/0! | S76: =S75/(S11)*1000 -> #DIV/0! | T76: =T75/(T11)*1000 -> #DIV/0! | U76: =U75/(U11)*1000 -> #DIV/0! | V76: =V75/(V11)*100 -> 0.28095335 | W76: =W75/(W11)*100 -> 0.63151259 | X76: =X75/(X11)*100 -> 0.56301534 | Y76: =Y75/(Y11)*100 -> 0.56745558 | Z76: =Z75/(Z11)*100 -> 0.55749203 | AA76: =AA75/(AA11)*100 -> 0.63638393 | AB76: =AB75/(AB11)*100 -> 0.5360792 | AC76: =AC75/(AC11)*100 -> 0.52493824 | ... AK76: =AK75/(AK11)*100 -> 2.138813 | AM76: =AM75/(AM11)*100 -> 0.67460296 | AW76: 10384 | AX76: =AW76+AW75 -> 17384 | AY76: aktivasi 709
D77: TK 630 A ( TRANSFER ) | E77: 40000 | F77: Kg | V77: 0 | W77: 0 | X77: 0 | Y77: 0 | AA77: 0 | AB77: 0 | AC77: 0 | AD77: 0 | AE77: 0 | AF77: 0 | AG77: 0 | AH77: 0 | AI77: 0 | AJ77: 0 | AK77: 0 | AM77: =SUM(G77:AK77) -> 0
D79: TK 630 B ( TRANSFER ) | E79: 40000 | F79: Kg | V79: 0 | W79: 0 | X79: 0 | Y79: 0 | Z79: 0 | AA79: 0 | AB79: 0 | AC79: 0 | AD79: 0 | AE79: 0 | AF79: 0 | AG79: 0 | AH79: 0 | AI79: 0 | AJ79: 0 | AK79: 0 | AM79: =SUM(G79:AK79) -> 0
D81: Bleaching Earth (BE) to Branded Spec | E81: 18 | F81: Kg | G81: 0 | H81: 0 | I81: 0 | J81: 0 | K81: 0 | L81: 0 | M81: 0 | N81: 0 | O81: 0 | P81: 0 | Q81: 0 | R81: 0 | S81: 0 | T81: 0 | U81: 0 | V81: 0 | W81: 0 | X81: 0 | Y81: 0 | Z81: 0 | AA81: 0 | AB81: 0 | AC81: 0 | AD81: 0 | AE81: 0 | AF81: 0 | AG81: 0 | AH81: 0 | AI81: 0 | AJ81: 0 | AK81: 0 | AM81: =SUM(G81:AK81) -> 0
D82: Bleaching Earth (BE) to Silo
D84: Aktual Pengiisian BE | F84: Kg | G84: 13000 | H84: 17000 | I84: 14000 | J84: 2000 | K84: 0 | U84: 6000 | V84: 5000 | W84: 6000 | X84: 15000 | Y84: 19000 | Z84: 14000 | AA84: 16000 | AB84: 14000 | AC84: 14000 | AD84: 14000 | AE84: 14000 | AF84: 14000 | AG84: 1000 | AH84: 14000 | AI84: 14000 | AJ84: 14000 | AK84: 14000 | AM84: =SUM(G84:AK84) -> 254000
G85: =G84/G9*100 -> 0.69171675 | H85: =H84/H9*100 -> 0.86390893 | I85: =I84/I9*100 -> 0.71156507 | J85: =J84/J9*100 -> #DIV/0! | K85: =K84/K9*100 -> #DIV/0! | L85: =L84/L9*100 -> #DIV/0! | M85: =M84/M9*100 -> #DIV/0! | N85: =N84/N9*100 -> #DIV/0! | ... V85: =V84/V9*100 -> 0.36591997 | W85: 0 | X85: =X84/X9*100 -> 0.63819467 | Y85: =Y84/Y9*100 -> 0.92905265 | Z85: =Z84/Z9*100 -> 0.67833204 | AA85: =AA84/AA9*100 -> 0.77460196 | AB85: =AB84/AB9*100 -> 0.61027068 | AC85: =AC84/AC9*100 -> 0.58760177 | AD85: =AD84/AD9*100 -> 0.61982337 | AE85: =AE84/AE9*100 -> 0.59329249 | ... AK85: =AK84/AK9*100 -> 0.65217655 | AM85: =AM84/AM9*100 -> 0.63301581
D86: Phosporic Acid (PA) | E86: 0.6 | F86: Kg | G86: 1005.68 | H86: 1073.28 | I86: 934.96 | J86: 12.48 | K86: 0 | V86: 263.12 | W86: 1050.4 | X86: 1029.6 | Y86: 899.6 | Z86: 920.4 | AA86: 946.4 | AB86: 1014 | AC86: 1021.28 | AD86: 999.44 | AE86: 974.48 | AF86: 945.36 | AG86: 960.96 | AH86: 939.12 | AI86: =983.84+300 -> 1283.84 | AJ86: =1006.72+300 -> 1306.72 | AK86: 6882.44 | AM86: =SUM(G86:AK86) -> 24463.56 | AN86: =AM86-AK86 -> 17581.12 | AV86: ok cek
F87: % | G87: =G86/(G9)*100 -> 0.053511207 | H87: =H86/(H9)*100 -> 0.054542128 | I87: =I86/(I9)*100 -> 0.047520348 | J87: =J86/(J9)*100 -> #DIV/0! | K87: =K86/(K9)*100 -> #DIV/0! | L87: =L86/(L9)*100 -> #DIV/0! | M87: =M86/(M9)*100 -> #DIV/0! | N87: =N86/(N9)*100 -> #DIV/0! | ... Q87: =Q86/(Q9)*100 -> #DIV/0! | R87: =R86/(R9)*1000 -> #DIV/0! | S87: =S86/(S9)*1000 -> #DIV/0! | T87: =T86/(T9)*1000 -> #DIV/0! | U87: =U86/(U9)*1000 -> #DIV/0! | V87: =V86/(V9)*1000 -> 0.19256173 | W87: 0.45041878 | X87: =X86/(X9)*1000 -> 0.43805682 | Y87: =Y86/(Y9)*1000 -> 0.43988198 | Z87: =Z86/(Z9)*1000 -> 0.44595486 | AA87: =AA86/(AA9)*1000 -> 0.45817706 | AB87: =AB86/(AB9)*1000 -> 0.44201034 | AC87: =AC86/(AC9)*1000 -> 0.4286471 | AD87: =AD86/(AD9)*1000 -> 0.44248305 | AE87: =AE86/(AE9)*1000 -> 0.41296548 | ... AK87: =AK86/(AK9)*1000 -> 3.2061185 | AM87: =AM86/AM9*1000 -> 0.60967796
C88: 3 | D88: OIL LOSSES | E88: 0.7 | F88: % | G88: =((SUM(G19:G21))-(SUM(G9)))/(SUM(G9))*100 -> -0.56029056 | H88: =((SUM(H19:H21))-(SUM(H9)))/(SUM(H9))*100 -> -0.4745401 | I88: =((SUM(I19:I21))-(SUM(I9)))/(SUM(I9))*100 -> -0.93809689 | J88: =((SUM(J19:J21))-(SUM(J9)))/(SUM(J9))*100 -> #DIV/0! | K88: =((SUM(K19:K21))-(SUM(K9)))/(SUM(K9))*100 -> #DIV/0! | L88: =((SUM(L19:L21))-(SUM(L9)))/(SUM(L9))*100 -> #DIV/0! | M88: =((SUM(M19:M21))-(SUM(M9)))/(SUM(M9))*100 -> #DIV/0! | N88: =((SUM(N19:N21))-(SUM(N9)))/(SUM(N9))*100 -> #DIV/0! | ... AK88: =((SUM(AK19:AK21))-(SUM(AK9)))/(SUM(AK9))*100 -> 0.38958232 | AM88: =((SUM(AM18:AM21))-(SUM(AM9)))/(SUM(AM9))*100 -> -0.25548917
F89: Kg | G89: =G88%*G9 -> -10530 | H89: =H88%*H9 -> -9338 | I89: =I88%*I9 -> -18457 | J89: =J88%*J9 -> #DIV/0! | K89: =K88%*K9 -> #DIV/0! | L89: =L88%*L9 -> #DIV/0! | M89: =M88%*M9 -> #DIV/0! | N89: =N88%*N9 -> #DIV/0! | ... AK89: =AK88%*AK9 -> 8363 | AM89: =AM88%*AM9 -> -102516
D90: % Oil Content | E90: 22 | F90: % | G90: 17.46 | H90: 17.5 | I90: 17.6 | V90: 17.1 | W90: 17.5 | X90: 17.52 | Y90: 17.52 | Z90: 17.44 | AA90: 17.54 | AB90: 17.48 | AC90: 17.42 | AD90: 17.5 | AE90: 17.49 | AF90: 17.46 | AG90: 17.45 | AH90: 17.44 | AI90: 17.43 | AJ90: 17.42 | AK90: 17.47 | AM90: =AVERAGE(G90:AK90) -> 17.46
D91: Spent Bleaching Earth | F91: Kg | G91: =SUM(G75,G81)+(G90%*SUM(G75,G81)) -> 13489.106 | H91: =SUM(H75,H81)+(H90%*SUM(H75,H81)) -> 15587.55 | I91: =SUM(I75,I81)+(I90%*SUM(I75,I81)) -> 15316.224 | J91: =SUM(J75,J81)+(J90%*SUM(J75,J81)) -> 275 | K91: =SUM(K75,K81)+(K90%*SUM(K75,K81)) -> 0 | L91: =SUM(L75,L81)+(L90%*SUM(L75,L81)) -> 0 | M91: =SUM(M75,M81)+(M90%*SUM(M75,M81)) -> 0 | N91: =SUM(N75,N81)+(N90%*SUM(N75,N81)) -> 0 | ... AK91: =SUM(AK75,AK81)+(AK90%*SUM(AK75,AK81)) -> 53934.001 | AM91: =SUM(AM75,AM81)+(AM90%*SUM(AM75,AM81))/AM6 -> 273050.1
C92: 4 | D92: PACKAGING (Brand Salvaco) | AM92: Packaging
D93: Olein IV 60 Received | F93: Kg | AM93: 0
D94: Olein IV 60 Consume | F94: Kg | AM94: 0
D95: - finished product | F95: Kg | G95: 0 | H95: 0 | I95: 0 | J95: 0 | K95: 0 | L95: 0 | M95: 0 | N95: 0 | O95: 0 | P95: 0 | Q95: 0 | R95: 0 | S95: 0 | T95: 0 | U95: 0 | V95: 0 | W95: 0 | X95: 0 | Y95: 0 | Z95: 0 | AA95: 0 | AB95: 0 | AC95: 0 | AD95: 0 | AE95: 0 | AF95: 0 | AG95: 0 | AH95: 0 | AM95: 0
D96: - sample | F96: Kg | G96: 0 | H96: 0 | I96: 0 | J96: 0 | K96: 0 | L96: 0 | M96: 0 | N96: 0 | O96: 0 | P96: 0 | Q96: 0 | R96: 0 | S96: 0 | T96: 0 | U96: 0 | V96: 0 | W96: 0 | X96: 0 | Y96: 0 | Z96: 0 | AA96: 0 | AB96: 0 | AC96: 0 | AD96: 0 | AE96: 0 | AF96: 0 | AG96: 0 | AH96: 0 | AM96: 0
D97: - remelt, flushing, downgrade | F97: Kg | G97: 0 | H97: 0 | I97: 0 | J97: 0 | K97: 0 | L97: 0 | M97: 0 | N97: 0 | O97: 0 | P97: 0 | Q97: 0 | R97: 0 | S97: 0 | T97: 0 | U97: 0 | V97: 0 | W97: 0 | X97: 0 | Y97: 0 | Z97: 0 | AA97: 0 | AB97: 0 | AC97: 0 | AD97: 0 | AE97: 0 | AF97: 0 | AG97: 0 | AH97: 0 | AM97: 0
D98: Carton | AM98: Carton
D99: Salvaco 1 Liter | F99: Box | AM99: 0
D100: Salvaco 2 Liter | F100: Box | AM100: 0 | AW100: 37542
D101: Pouch | AM101: Pouch
D102: Salvaco 1 Liter | F102: Pouch | G102: 0 | H102: 0 | I102: 0 | J102: 0 | K102: 0 | L102: 0 | M102: 0 | N102: 0 | O102: 0 | P102: 0 | Q102: 0 | R102: 0 | S102: 0 | T102: 0 | U102: 0 | V102: 0 | W102: 0 | X102: 0 | Y102: 0 | Z102: 0 | AA102: 0 | AB102: 0 | AC102: 0 | AD102: 0 | AE102: 0 | AF102: 0 | AG102: 0 | AH102: 0 | AM102: 0
D103: Salvaco 2 Liter | F103: Pouch | G103: 0 | H103: 0 | I103: 0 | J103: 0 | K103: 0 | L103: 0 | M103: 0 | N103: 0 | O103: 0 | P103: 0 | Q103: 0 | R103: 0 | S103: 0 | T103: 0 | U103: 0 | V103: 0 | W103: 0 | X103: 0 | Y103: 0 | Z103: 0 | AA103: 0 | AB103: 0 | AC103: 0 | AD103: 0 | AE103: 0 | AF103: 0 | AG103: 0 | AH103: 0 | AM103: 0
...

Sheet OIP Ref PMG 2
B4: Oil In Plant (OIP) Refinery pmg 2 | I4: Oktober | J4: OIP | M4: TK131 RPO | P4: TK132 RPO | S4: TOTAL STOK RPO DI PLANT
B5: Vessel | C5: Operating Volume (m3) | D5: Oil Density (kg/m3) | E5: MT | F5: Level yg diisi | G5: Actual OIP (Kg) | I5: Tanggal | J5: Opening Stock | K5: Closing Stock | L5: balance stok | M5: Opening Stock | N5: Closing Stock | O5: CONSUMP stok | P5: Opening Stock | Q5: Closing Stock | R5: CONSUMP stok
B6: 2MX312 | C6: 5.67 | D6: 850 | E6: =C6*D6/1000 -> 4.8195 | F6: 100 | G6: =(F6*E6/100)*1000 -> 4819.5 | I6: 46023 | J6: 282664 | K6: 297894 | L6: =J6-K6 -> -15230
B7: 2VE611A | C7: 47.22 | D7: 850 | E7: =C7*D7/1000 -> 40.137 | F7: 80 | G7: =(F7*E7/100)*1000 -> 32109.6 | I7: 46024 | J7: =K6 -> 297894 | K7: 294828 | L7: =J7-K7 -> 3066
B8: 2VE611B | C8: 47.22 | D8: 850 | E8: =C8*D8/1000 -> 40.137 | F8: 80 | G8: =(F8*E8/100)*1000 -> 32109.6 | I8: 46025 | J8: =K7 -> 294828 | K8: 312285 | L8: =J8-K8 -> -17457
B9: 2VE612 | C9: 35.68 | D9: 850 | E9: =C9*D9/1000 -> 30.328 | F9: 71 | G9: =(F9*E9/100)*1000 -> 21532.88 | I9: 46026 | J9: =K8 -> 312285 | K9: 323561 | L9: =J9-K9 -> -11276
B10: 2VE661 | C10: 10.8 | D10: 850 | E10: =C10*D10/1000 -> 9.18 | F10: 15 | G10: =(F10*E10/100)*1000 -> 1377 | I10: 46027 | J10: =K9 -> 323561 | K10: 318233 | L10: =J10-K10 -> 5328
B11: FL621 | C11: 10.1 | D11: 850 | E11: =C11*D11/1000 -> 8.585 | F11: 100 | G11: =(F11*E11/100)*1000 -> 8585 | I11: 46028 | J11: =K10 -> 318233 | K11: 318233 | L11: =J11-K11 -> 0
B12: FL622 | C12: 10.1 | D12: 850 | E12: =C12*D12/1000 -> 8.585 | F12: 100 | G12: =(F12*E12/100)*1000 -> 8585 | I12: 46029 | J12: =K11 -> 318233 | K12: 318233 | L12: =J12-K12 -> 0
B13: FL623 | C13: 10.1 | D13: 850 | E13: =C13*D13/1000 -> 8.585 | F13: 100 | G13: =(F13*E13/100)*1000 -> 8585 | I13: 46030 | J13: =K12 -> 318233 | K13: 318233 | L13: =J13-K13 -> 0 | N13: 0 | Q13: 174609
B14: FL624 | C14: 10.1 | D14: 850 | E14: =C14*D14/1000 -> 8.585 | F14: 0 | G14: =(F14*E14/100)*1000 -> 0 | I14: 46031 | J14: =K13 -> 318233 | K14: 318233 | L14: =J14-K14 -> 0 | N14: 44191 | P14: 174609 | Q14: 38852 | R14: =P14-Q14 -> 135757 | S14: =R14+O14+L14 -> 135757
B15: FL625 | C15: 10.1 | D15: 850 | E15: =C15*D15/1000 -> 8.585 | F15: 100 | G15: =(F15*E15/100)*1000 -> 8585 | I15: 46032 | J15: =K14 -> 318233 | K15: 318233 | L15: =J15-K15 -> 0 | M15: 44191 | N15: 405272 | O15: =M15-N15 -> -361081 | P15: 38852 | Q15: 38852 | R15: =P15-Q15 -> 0 | S15: =R15+O15+L15 -> -361081
B16: 2VE701 | C16: 72.13 | D16: 850 | E16: =C16*D16/1000 -> 61.3105 | F16: 37 | G16: =(F16*E16/100)*1000 -> 22684.885 | I16: 46033 | J16: =K15 -> 318233 | K16: 318233 | L16: =J16-K16 -> 0
B17: 2VE751 | C17: 4.28 | D17: 860 | E17: =C17*D17/1000 -> 3.6808 | F17: 50 | G17: =(F17*E17/100)*1000 -> 1840.4 | I17: 46034 | J17: =K16 -> 318233 | K17: 318233 | L17: =J17-K17 -> 0
B18: 2HE721A (tube) | C18: 10 | D18: 810 | E18: =C18*D18/1000 -> 8.1 | F18: 100 | G18: =(F18*E18/100)*1000 -> 8100 | I18: 46035 | J18: =K17 -> 318233 | L18: =J18-K18 -> 318233
B19: 2HE721A (shell) | C19: 21.8 | D19: 800 | E19: =C19*D19/1000 -> 17.44 | F19: 30 | G19: =(F19*E19/100)*1000 -> 5232 | I19: 46036 | J19: =K18 -> 0 | L19: =J19-K19 -> 0
B20: HE721B (tube) | C20: 10 | D20: 810 | E20: =C20*D20/1000 -> 8.1 | F20: 100 | G20: =(F20*E20/100)*1000 -> 8100 | I20: 46037 | J20: =K19 -> 0 | L20: =J20-K20 -> 0
B21: 2HE722 | C21: 11.4 | D21: 790 | E21: =C21*D21/1000 -> 9.006 | F21: 80 | G21: =(F21*E21/100)*1000 -> 7204.8 | I21: 46038 | J21: =K20 -> 0 | L21: =J21-K21 -> 0
B22: 2PR731 | C22: 14 | D22: 790 | E22: =C22*D22/1000 -> 11.06 | F22: 30 | G22: =(F22*E22/100)*1000 -> 3318 | I22: 46039 | J22: =K21 -> 0 | K22: 300254 | L22: =J22-K22 -> -300254
B23: 2DE732 | C23: 149.76 | D23: 790 | E23: =C23*D23/1000 -> 118.3104 | F23: 100 | G23: =(F23*E23/100)*1000 -> 118310.4 | I23: 46040 | J23: =K22 -> 300254 | K23: 296976 | L23: =J23-K23 -> 3278
C24: =SUM(C6:C23) -> 490.46 | E24: =SUM(E6:E23) -> 404.5342 | G24: =(F24*E24/100)*1000 -> 0 | I24: 46041 | J24: =K23 -> 296976 | K24: 318272 | L24: =J24-K24 -> -21296
F25: Total OIP = | G25: =SUM(G6:G24) -> 301079.06 | I25: 46042 | J25: =K24 -> 318272 | K25: 300254 | L25: =J25-K25 -> 18018
I26: 46043 | J26: =K25 -> 300254 | K26: 316518 | L26: =J26-K26 -> -16264
I27: 46044 | J27: =K26 -> 316518 | K27: 308256 | L27: =J27-K27 -> 8262
I28: 46045 | J28: =K27 -> 308256 | K28: 310512 | L28: =J28-K28 -> -2256
I29: 46046 | J29: =K28 -> 310512 | K29: 305936 | L29: =J29-K29 -> 4576
I30: 46047 | J30: =K29 -> 305936 | K30: 306307 | L30: =J30-K30 -> -371
H31: 0 | I31: 46048 | J31: =K30 -> 306307 | K31: 311257 | L31: =J31-K31 -> -4950
I32: 46049 | J32: =K31 -> 311257 | K32: 302600 | L32: =J32-K32 -> 8657
I33: 46050 | J33: =K32 -> 302600 | K33: 301618 | L33: =J33-K33 -> 982
I34: 46051 | J34: =K33 -> 301618 | K34: 294058 | L34: =J34-K34 -> 7560
I35: 46052 | J35: =K34 -> 294058 | K35: 298910 | L35: =J35-K35 -> -4852
I36: 46053 | J36: =K35 -> 298910 | K36: 301079 | L36: =J36-K36 -> -2169
B38: Solar Daily Tank HPB
B39: 2TK726 | C39: =5.3+0.78 -> 6.08 | D39: 840 | E39: =C39*D39/1000 -> 5.1072 | F39: 0 | G39: =F39*E39/100*1000 -> 0
B41: Stock Chemicals In Plant
C42: Sisa Stok Di Lap | D42: Order | E42: Consumption
B43: BE
B44: 630A | D44: 298
B45: 630B
B46: H3PO4
B47: NaOH
B48: Citrid Acid

Sheet OIP Fract PMG 2
A4: Oil In Plant (OIP) Fraksinasi | I4: OIP | S4: BUFFER TANK | W4: DIRECT
A5: RBDPO OIP | I5: RPO CR | M5: OLEIN | P5: STEARIN | S5: TK131 RPO | U5: TK132 RPO
A6: Vessel | B6: Operating Volume (m3) | C6: Oil Density (kg/m3) | D6: MT | E6: Level Transmitter (1%/MT) | F6: Level (%) | G6: Kg | I6: Tanggal | J6: Opening Stock | K6: Closing Stock | L6: balance stok | M6: Opening Stock | N6: Closing Stock | O6: balance stok | P6: Opening Stock | Q6: Closing Stock | R6: balance stok | S6: Opening Stock | T6: Closing Stock | U6: Opening Stock | V6: Closing Stock
A7: 2CR1201 | B7: 70.51 | C7: 890 | D7: 60 | E7: =D7/100 -> 0.6 | F7: 100 | G7: =E7*F7*1000 -> 60000 | I7: 46023 | J7: 478500 | K7: 478800 | M7: 69301 | N7: 21197 | S7: 123912 | T7: 72500 | U7: 118012 | V7: 72500
A8: 2CR1202 | B8: 70.51 | C8: 890 | D8: 60 | E8: =D8/100 -> 0.6 | F8: 100 | G8: =E8*F8*1000 -> 60000 | I8: 46024 | J8: =K7 -> 478800 | K8: 599220 | M8: =N7 -> 21197 | N8: 20558 | S8: =T7 -> 72500 | T8: 165700 | U8: =V7 -> 72500 | V8: 155293
A9: 2CR1203 | B9: 70.51 | C9: 890 | D9: 60 | E9: =D9/100 -> 0.6 | F9: 42.4 | G9: =E9*F9*1000 -> 25440 | I9: 46025 | J9: =K8 -> 599220 | K9: 592620 | M9: =N8 -> 20558 | N9: 20374 | S9: =T8 -> 165700 | T9: 255000 | U9: =V8 -> 155293 | V9: 255000
A10: 2CR1204 | B10: 70.51 | C10: 890 | D10: 60 | E10: =D10/100 -> 0.6 | F10: 100 | G10: =E10*F10*1000 -> 60000 | I10: 46026 | J10: =K9 -> 592620 | K10: 0 | M10: =N9 -> 20374 | N10: 20402 | S10: =T9 -> 255000 | T10: 0 | U10: =V9 -> 255000 | V10: 0
A11: 2CR1205 | B11: 70.51 | C11: 890 | D11: 60 | E11: =D11/100 -> 0.6 | F11: 100 | G11: =E11*F11*1000 -> 60000 | I11: 46027 | J11: =K10 -> 0 | K11: 0 | M11: =N10 -> 20402 | N11: 20402 | S11: =T10 -> 0 | T11: 0 | U11: =V10 -> 0 | V11: 0
A12: 2CR1206 | B12: 70.51 | C12: 890 | D12: 60 | E12: =D12/100 -> 0.6 | F12: 100 | G12: =E12*F12*1000 -> 60000 | I12: 46028 | J12: =K11 -> 0 | K12: 0 | M12: =N11 -> 20402 | N12: 0 | S12: =T11 -> 0 | T12: 0 | U12: =V11 -> 0 | V12: 0
A13: 2CR1207 | B13: 70.51 | C13: 890 | D13: 60 | E13: =D13/100 -> 0.6 | F13: 100 | G13: =E13*F13*1000 -> 60000 | I13: 46029 | J13: =K12 -> 0 | K13: 496020 | M13: =N12 -> 0 | N13: 21632 | S13: =T12 -> 0 | T13: 133300 | U13: =V12 -> 0 | V13: 106874
A14: 2CR1208 | B14: 70.51 | C14: 890 | D14: 60 | E14: =D14/100 -> 0.6 | F14: 100 | G14: =E14*F14*1000 -> 60000 | I14: 46030 | J14: 496020 | K14: 839700 | M14: 21632 | N14: 21009 | S14: =T13 -> 133300 | T14: 76968 | U14: =V13 -> 106874 | V14: 76968
A15: 2CR1209 | B15: 70.51 | C15: 890 | D15: 60 | E15: =D15/100 -> 0.6 | F15: 100 | G15: =E15*F15*1000 -> 60000 | I15: 46031 | J15: =K14 -> 839700 | K15: 840000 | M15: =N14 -> 21009 | N15: 21577 | S15: =T14 -> 76968 | T15: 207591 | U15: =V14 -> 76968 | V15: 175558
A16: 2CR1210 | B16: 70.51 | C16: 890 | D16: 60 | E16: =D16/100 -> 0.6 | F16: 100 | G16: =E16*F16*1000 -> 60000 | I16: 46032 | J16: =K15 -> 840000 | K16: 660000 | M16: =N15 -> 21577 | N16: 21470 | S16: =T15 -> 207591 | T16: 110351 | U16: =V15 -> 175558 | V16: 87386
A17: 2CR1211 | B17: 70.51 | C17: 890 | D17: 60 | E17: =D17/100 -> 0.6 | F17: 100 | G17: =E17*F17*1000 -> 60000 | I17: 46033 | J17: =K16 -> 660000 | K17: 580500 | M17: =N16 -> 21470 | N17: 21414 | S17: =T16 -> 110351 | T17: 194834 | U17: =V16 -> 87386 | V17: 158618
A18: 2CR1212 | B18: 70.51 | C18: 890 | D18: 60 | E18: =D18/100 -> 0.6 | F18: 100 | G18: =E18*F18*1000 -> 60000 | I18: 46034 | J18: =K17 -> 580500 | K18: 540000 | M18: =N17 -> 21414 | N18: 21472 | S18: =T17 -> 194834 | T18: 107863 | U18: =V17 -> 158618 | V18: 74461
A19: 2CR1213 | B19: 70.51 | C19: 890 | D19: 60 | E19: =D19/100 -> 0.6 | F19: 100 | G19: =E19*F19*1000 -> 60000 | I19: 46035 | J19: =K18 -> 540000 | K19: 480000 | M19: =N18 -> 21472 | N19: 21022 | S19: =T18 -> 107863 | T19: 34198 | U19: =V18 -> 74461 | V19: 22405
A20: 2CR1214 | B20: 70.51 | C20: 890 | D20: 60 | E20: =D20/100 -> 0.6 | F20: 100 | G20: =E20*F20*1000 -> 60000 | I20: 46036 | J20: =K19 -> 480000 | K20: 480000 | M20: =N19 -> 21022 | N20: 21232 | S20: =T19 -> 34198 | T20: 34614 | U20: =V19 -> 22405 | V20: 0
A21: 2CR1215 | B21: 70.51 | C21: 890 | D21: 60 | E21: =D21/100 -> 0.6 | F21: 100 | G21: =E21*F21*1000 -> 60000 | I21: 46037 | J21: =K20 -> 480000 | K21: 299640 | M21: =N20 -> 21232 | N21: 21514 | S21: =T20 -> 34614 | T21: 15000 | U21: =V20 -> 0 | V21: 15000
I22: 46038 | J22: =K21 -> 299640 | K22: 300000 | M22: =N21 -> 21514 | N22: 21211 | S22: =T21 -> 15000 | T22: 20000 | U22: =V21 -> 15000 | V22: 25000
F23: Total RBDPO | G23: =SUM(G7:G21) -> 865440 | I23: 46039 | J23: =K22 -> 300000 | K23: 718680 | M23: =N22 -> 21211 | N23: 20776 | S23: =T22 -> 20000 | T23: 128981 | U23: =V22 -> 25000 | V23: 127944
I24: 46040 | J24: =K23 -> 718680 | K24: 839040 | M24: =N23 -> 20776 | N24: 20475 | S24: =T23 -> 128981 | T24: 345329 | U24: =V23 -> 127944 | V24: 342696
A25: Olein OIP | I25: 46041 | J25: =K24 -> 839040 | K25: 778980 | M25: =N24 -> 20475 | N25: 21541 | S25: =T24 -> 345329 | T25: 420631 | U25: =V24 -> 342696 | V25: 426877
A26: Vessel | B26: Operating Volume (m3) | C26: Oil Density (kg/m3) | D26: MT | E26: Level Transmitter (1%/MT) | F26: Level (%) | G26: Kg | I26: 46042 | J26: =K25 -> 778980 | K26: 838140 | M26: =N25 -> 21541 | N26: 21496 | S26: =T25 -> 420631 | T26: 264937 | U26: =V25 -> 426877 | V26: 266976
A27: 2TK261 | B27: 15.95 | C27: 885 | D27: =B27*C27/1000 -> 14.11575 | E27: =D27/100 -> 0.1411575 | F27: 64.3 | G27: =E27*F27*1000 -> 9076.4272 | I27: 46043 | J27: =K26 -> 838140 | K27: 879480 | M27: =N26 -> 21496 | N27: 21227 | S27: =T26 -> 264937 | T27: 113344 | U27: =V26 -> 266976 | V27: 114980
A28: 2CL251 | B28: 3.02 | C28: 885 | D28: =B28*C28/1000 -> 2.6727 | E28: =D28/100 -> 0.026727 | F28: 0 | G28: =E28*F28*1000 -> 0 | I28: 46044 | J28: =K27 -> 879480 | K28: 885120 | M28: =N27 -> 21227 | N28: 21467 | S28: =T27 -> 113344 | T28: 219078 | U28: =V27 -> 114980 | V28: 216023
A29: 2TK221 | B29: 82.48 | C29: 885 | D29: =B29*C29/1000 -> 72.9948 | E29: =D29/100 -> 0.729948 | F29: 0 | G29: =E29*F29*1000 -> 0 | I29: 46045 | J29: =K28 -> 885120 | K29: 858180 | M29: =N28 -> 21467 | N29: 21101 | S29: =T28 -> 219078 | T29: =298262+22000 -> 320262 | U29: =V28 -> 216023 | V29: =297820+23000 -> 320820
A30: 2TK241 | B30: 16.95 | C30: 885 | D30: =B30*C30/1000 -> 15.00075 | E30: =D30/100 -> 0.1500075 | F30: 84.5 | G30: =E30*F30*1000 -> 12675.634 | I30: 46046 | J30: =K29 -> 858180 | K30: 843120 | M30: =N29 -> 21101 | N30: 20933 | S30: =T29 -> 320262 | T30: 313152 | U30: =V29 -> 320820 | V30: 311213
F31: Total Olein | G31: =SUM(G27:G30) -> 21752.061 | I31: 46047 | J31: =K30 -> 843120 | K31: 872700 | M31: =N30 -> 20933 | N31: 21970 | S31: =T30 -> 313152 | T31: 241827 | U31: =V30 -> 311213 | V31: 238069
I32: 46048 | J32: =K31 -> 872700 | K32: 889680 | M32: =N31 -> 21970 | N32: 23174 | S32: =T31 -> 241827 | T32: 248686 | U32: =V31 -> 238069 | V32: 254262
I33: 46049 | J33: =K32 -> 889680 | K33: 720000 | M33: =N32 -> 23174 | N33: 22432 | S33: =T32 -> 248686 | T33: 135000 | U33: =V32 -> 254262 | V33: 100000
I34: 46050 | J34: =K33 -> 720000 | K34: 660000 | M34: =N33 -> 22432 | N34: 21157 | S34: =T33 -> 135000 | T34: 70000 | U34: =V33 -> 100000 | V34: 65000
I35: 46051 | J35: =K34 -> 660000 | K35: 817260 | M35: =N34 -> 21157 | N35: 22085 | S35: =T34 -> 70000 | T35: 56174 | U35: =V34 -> 65000 | V35: 50036
I36: 46052 | J36: =K35 -> 817260 | K36: 849540 | M36: =N35 -> 22085 | N36: 22028 | S36: =T35 -> 56174 | T36: 91057 | U36: =V35 -> 50036 | V36: 87362
I37: 46053 | J37: =K36 -> 849540 | K37: 865440 | M37: =N36 -> 22028 | N37: 21752 | S37: =T36 -> 91057 | T37: 75754 | U37: =V36 -> 87362 | V37: 62644
A39: Stearin OIP
A40: Melting Tank | B40: Panjang (m) | C40: Lebar (m) | D40: tinggi (m) | E40: Density | F40: Tinggi Sounding (Cm) Maks 4,4 m | G40: Kg
A41: TK231 A | B41: 12.2 | C41: 1.75 | D41: 1.52 | E41: 0.88 | F41: 0 | G41: =B41*C41*D41*E41*F41/100 -> 0
A42: TK231 B | B42: 12.2 | C42: 1.75 | D42: 1.52 | E42: 0.88 | F42: 0 | G42: =B42*C42*D42*E42*F42/100 -> 0
F43: Total STEARIN | G43: =SUM(G41:G42) -> 0

Sheet 2026
B2: PRODUCTION REPORT 2026
B4: No | C4: ITEM | D4: Budget / Norma | E4: UoM | F4: YEARLY REPORT | S4: Yearly Report | T4: Yearly Report RKAP (Budget) | U4: Yearly Report RKAP
F5: JANUARI | G5: FEBRUARI | H5: MARET | I5: APRIL | J5: MEI | K5: JUNI | L5: JULI | M5: AGUSTUS | N5: SEPTEMBER | O5: OKTOBER | P5: NOVEMBER | Q5: DESEMBER | S5: TOTAL (Kg) | T5: TOTAL (Kg) | U5: TOTAL (%)
B6: 1 | C6: PRODUCTION | S6: Production | T6: Production | U6: Production | DF6: 29 | DG6: 30 | DH6: 31
C7: Refinery | S7: Refinery | T7: Refinery | U7: Refinery | DD7: CPO Olah | DE7: Kg | DF7: 1971320 | DG7: 2015120 | DH7: 2015230 | AIT7: Sounding | AIU7: Production | AIV7: Diff
C8: Running Days | D8: 300 | E8: Day | F8: ='Januari 2026 PMG 2'!AM6+'Januari 2026 PMG 1'!AM6 -> 31 | S8: =SUM(F8:Q8) -> 31 | T8: 231 | U8: =S8/T8*100 -> 13.419913 | OQ8: Poram | AED8: 14 Juni | AEE8: 15 Juni | AIS8: CPO | AIT8: 11008948 | AIU8: =S12 -> 56920116 | AIV8: =AIT8-AIU8 -> -45911168
C9: Ratio Run CPO
C10: Utilitas CPO vs RKAP | E10: % | F10: =F12/F15*100 -> 96638.567 | S10: =S15/S12*1000 -> 12.43236
C11: Incoming CPO | E11: Kg | F11: ='Januari 2026 PMG 2'!AM7+'Januari 2026 PMG 1'!AM7 -> 57887356
C12: CPO Consume Total | D12: 707651000 | E12: Kg | F12: ='Januari 2026 PMG 2'!AM9+'Januari 2026 PMG 1'!AM9 -> 56920116 | S12: =SUM(F12:Q12) -> 56920116 | T12: 421374000 | U12: =S12/T12 -> 0.13508217 | V12: =S12-Q12-P12 -> 56920116 | Z12: =TODAY() -> 46084 | AW12: =S12/D12 -> 0.080435294 | DD12: HP Boiler | DE12: mmbtu | DF12: 251.19642 | DG12: 257.91391 | DH12: 251.51265 | ON12: 26946.108 | OO12: 17383.234 | OQ12: RBDPO Olah | AED12: =35.8500000000058*1000 -> 35850 | AIS12: PFAD | AIT12: 566885 | AIU12: =S22 -> 2408805 | AIV12: =AIT12-AIU12 -> -1841920
C13: CPO Consume Poram | E13: Kg | F13: =F12 -> 56920116 | S13: =SUM(F13:Q13) -> 56920116 | Y13: =Q13-'Januari 2026 PMG 2'!AJ9 -> -2124941 | Z13: Consume Total | AA13: =F12 -> 56920116
C14: CPO Consume Brand | E14: Kg | S14: =SUM(F14:Q14) -> 0 | Z14: RPO | AA14: =F21 -> 54171735 | AW14: =AV14/#REF! -> #REF!
C15: Budget CPO Olah | E15: Kg | F15: 58900 | S15: 707651.37 | Z15: PFAD | AA15: =F22 -> 2408805
C16: - FFA | D16: 5 | E16: % | F16: ='Januari 2026 PMG 2'!AM13+'Januari 2026 PMG 1'!AM13 -> 7.7180076 | S16: =AVERAGE(F16:Q16) -> 7.7180076 | T16: =AVERAGE(G16:R16) -> #DIV/0! | U16: =AVERAGE(H16:S16) -> 7.7180076 | Z16: Olein 56 | AA16: =F31 -> 32832043 | DD16: Steam Ref | DE16: Kg | DF16: 182230 | DG16: 190070 | DH16: 197800 | ON16: =S12/1000 -> 56920.116 | OO16: =(S30+S53+S39)/1000 -> 39639.925 | OQ16: =SUM(OQ17:OQ18) -> #REF! | AGU16: 2000
C17: - Moist & Impurities | D17: 0.5 | E17: % | F17: ='Januari 2026 PMG 2'!AM14+'Januari 2026 PMG 1'!AM14 -> 0.85335606 | S17: =AVERAGE(F17:Q17) -> 0.85335606 | T17: =AVERAGE(G17:R17) -> #DIV/0! | U17: =AVERAGE(H17:S17) -> 0.85335606 | Z17: Stearin 56 | AA17: =F32 -> 6807882 | DE17: Kg/MT | DF17: =DF16/(DF7/1000) -> 92.440598 | DG17: =DG16/(DG7/1000) -> 94.321926 | DH17: =DH16/(DH7/1000) -> 98.152568 | OQ17: =#REF!/1000 -> #REF! | OR17: =OQ17/OQ16*100 -> #REF! | AGT17: 0.942 | AGU17: =AGT17*AGU16 -> 1884 | AGV17: Refinery | AIS17: Olein IV 56 | AIT17: 9594130 | AIU17: =S31 -> 32832043 | AIV17: =AIT17-AIU17 -> -23237913
C18: - DOBI | D18: 2,20 Min | E18: % | S18: =AVERAGE(F18:Q18) -> #DIV/0! | T18: =AVERAGE(G18:R18) -> #DIV/0! | U18: =AVERAGE(H18:S18) -> #DIV/0! | Z18: Olein 58 | AA18: =F44 -> 10803048 | ON18: =SUM(ON16:ON17) -> 56920.116 | OO18: =SUM(OO16:OO17) -> 39639.925 | OQ18: =#REF!/1000 -> #REF! | OR18: =OQ18/OQ16*100 -> #REF! | AGT18: 0.05 | AGU18: =AGT18*AGU16 -> 100 | AIS18: Stearin | AIT18: 2161151 | AIU18: =S32 -> 6807882 | AIV18: =AIT18-AIU18 -> -4646731
C19: Product | S19: Product | T19: Product | U19: Product | Z19: Stearin 58 | AA19: =F45 -> 3424482 | ON19: =ON18/ON12*100 -> 211.23687 | OO19: =OO18/OO12*100 -> 228.03539 | AEF19: Product OIP | AEP19: Juni | AEQ19: Sisa Product OIP
C21: RbdPO | D21: 668731 | E21: Kg | F21: ='Januari 2026 PMG 2'!AM19+'Januari 2026 PMG 1'!AM19 -> 54171735 | S21: =SUM(F21:Q21) -> 54171735 | T21: 399336000 | U21: =S21/T21*100 -> 13.565452 | AW21: =AW22/D21 -> 80.551754 | DD21: Tahun 2021 | AED21: 136360 | AEE21: 109340 | AEF21: =SUM(AED21:AEE21) -> 245700 | AEP21: 34157.88 | AEQ21: =AEF21-AEP21 -> 211542.12 | AGU21: =AGU17 -> 1884
C22: PFAD | D22: 33967 | E22: Kg | F22: ='Januari 2026 PMG 2'!AM21+'Januari 2026 PMG 1'!AM21 -> 2408805 | S22: =SUM(F22:Q22) -> 2408805 | T22: 19024000 | U22: =S22/T22*100 -> 12.661927 | AW22: =S30+S34+S39+S53+S43 -> 53867455 | DD22: Items | DF22: Agustus | DG22: Oktober | ON22: =ON12-ON18 -> -29974.008 | OO22: =OO12-OO18 -> -22256.691 | OQ22: Olein IV 58 | OR22: 0 | PD22: 564.70507 | PE22: =OR22/PD22*100 -> 0 | AED22: 13800 | AEE22: 2800 | AEF22: =SUM(AED22:AEE22) -> 16600 | AEP22: 1469.85 | AEQ22: =AEF22-AEP22 -> 15130.15 | AGT22: 0.75 | AGU22: =AGT22*AGU21 -> 1413
C23: Fractionation
C24: Running Days | F24: ='Januari 2026 PMG 2'!AM23+'Januari 2026 PMG 1'!AM23 -> 35 | S24: =SUM(F24:Q24) -> 35
C25: Total Filling Crystalizer ( Feed ) | D25: 426016000 | E25: Kg | S25: =SUM(F25:Q25) -> 0
C26: Total Proses RBDPO | E26: Kg | F26: =F30+F43 -> 53867455 | S26: =SUM(F26:Q26) -> 53867455
C27: Utilitas RBDPO vs RKAP | E27: % | F27: =F26/F28*100 -> #DIV/0! | S27: =S26/S28*100 -> 12644.46
C28: Budget RBDPO Olah | E28: Kg | S28: 426016.26
C29: Fractionation OLEIN IV 56 | S29: Olein IV 56 | T29: Olein IV 56 | U29: Olein IV 56 | AA29: =F12-(F21+F22) -> 339576 | DF29: 24 | DG29: 2 | DH29: 3 | OQ29: Olein IV 60 | OR29: =80.53776+PE39 -> 120.78492 | PD29: 4695.7554 | PE29: =OR29/PD29*100 -> 2.5722149 | AGT29: 0.25 | AGU29: =AGT29*AGU21 -> 471
C30: RBDPO Consume | E30: Kg | F30: ='Januari 2026 PMG 2'!AM32+'Januari 2026 PMG 1'!AM32 -> 39639925 | S30: =S31+S32 -> 39639925 | T30: =T31+T32 -> 87311000 | U30: =S30/T30*100 -> 45.400837 | AA30: =(AA29/F12) -> 0.0059658346 | DD30: CPO Olah | DE30: Kg | DF30: 2000530 | DG30: 2005167 | DH30: 2025879 | AED30: =95.28%*AED12 -> 34157.88 | AEF30: =AED21-AEP21 -> 102202.12 | AIP30: CPO Feed - Sounding
C31: OLEIN IV 56 | D31: 349333 | E31: Kg | F31: ='Januari 2026 PMG 2'!AM33+'Januari 2026 PMG 1'!AM33 -> 32832043 | S31: =SUM(F31:Q31) -> 32832043 | T31: 71627000 | U31: =S31/T31*100 -> 45.837524 | DD31: HP Boiler | DE31: mmbtu | DF31: 255.53619 | DG31: 255.09239 | DH31: 260.82455 | ON31: =#REF!/1000 -> #REF! | OQ31: INL 900 ml | OR31: 0 | PD31: 9.75348 | PE31: =(OR31*PD31)/1000 -> 0 | AED31: =4.1%*AED12 -> 1469.85 | AEF31: =AED22-AEP22 -> 12330.15
C32: STEARIN | D32: 76683 | E32: Kg | F32: ='Januari 2026 PMG 2'!AM34+'Januari 2026 PMG 1'!AM34 -> 6807882 | S32: =SUM(F32:Q32) -> 6807882 | T32: 15684000 | U32: =S32/T32*100 -> 43.406542 | DD32: Steam Ref | DE32: Kg | DF32: 146000 | DG32: 151100 | DH32: 152900 | ON32: 1796 | OQ32: Salvaco 1L | OR32: 1262 | PD32: 10.86 | PE32: =(OR32*PD32)/1000 -> 13.70532 | AIP32: Report Prod
C33: Fractionation OLEIN IV 57 ( Bulk ) | S33: Olein IV 57 ( Bulk ) | T33: Olein IV 57 ( Bulk ) | U33: Olein IV 57 ( Bulk )
C34: RBDPO Consume | E34: Kg | S34: =S35+S36 -> 0 | T34: =T35+T36 -> 5121000 | U34: =S34/T34*100 -> 0 | AW34: =S34+S39 -> 0
C35: OLEIN IV 57 | E35: Kg | S35: =SUM(F35:Q35) -> 0 | T35: 3934000 | U35: =S35/T35*100 -> 0 | AW35: =S35+S40 -> 0
C36: STEARIN | E36: Kg | S36: =SUM(F36:Q36) -> 0 | T36: 1187000 | U36: =S36/T36*100 -> 0 | AW36: =S36+S41 -> 0
C37: Fractionation OLEIN IV 57 ( Retail ) | S37: Olein IV 57 ( Retail ) | T37: Olein IV 57 ( Retail ) | U37: Olein IV 57 ( Retail ) | DE37: Kg/MT | DF37: =DF32/(DF30/1000) -> 72.98066 | DG37: =DG32/(DG30/1000) -> 75.35532 | DH37: =DH32/(DH30/1000) -> 75.473412 | ON37: =ON31/ON32*100 -> #REF! | OQ37: Salvaco 2L | OR37: 2444 | PD37: 10.86 | PE37: =(OR37*PD37)/1000 -> 26.54184 | AIP37: Diff
C38: CPO Consume | E38: Kg | S38: =SUM(F38:Q38) -> 0 | T38: =T39/T61% -> 32338304 | U38: =(S38/T38)*100 -> 0 | DE38: Kg/MT | DF38: =DF32/(DF22/1000) -> #VALUE! | DG38: =DH32/(DG22/1000) -> #VALUE! | DH38: =#REF!/(DH22/1000) -> #REF!
C39: RBDPO Brand Consume | D39: =SUM(D40:D41) -> 15000 | E39: Kg | S39: =S40+S41 -> 0 | T39: =T40+T41 -> 30647000 | U39: =(S39/T39)*100 -> 0 | PE39: =SUM(PE32:PE37) -> 40.24716
C40: OLEIN IV 57 ( Retail ) | D40: 12000 | E40: Kg | S40: =SUM(F40:Q40) -> 0 | T40: 23002000 | U40: =S40/T40*100 -> 0
C41: STEARIN | D41: 3000 | E41: Kg | S41: =SUM(F41:Q41) -> 0 | T41: 7645000 | U41: =S41/T41*100 -> 0
C42: Fractionation OLEIN IV 58 ( BULK ) | S42: Olein IV 58 | T42: Olein IV 58 | U42: Olein IV 58
C43: RBDPO Consume | E43: Kg | F43: ='Januari 2026 PMG 2'!AM45+'Januari 2026 PMG 1'!AM45 -> 14227530 | S43: =S44+S45 -> 14227530 | T43: =T44+T45 -> 249961000 | U43: =S43/T43*100 -> 5.6918999
C44: OLEIN IV 58 ( Bulk ) | D44: 205714 | E44: Kg | F44: ='Januari 2026 PMG 2'!AM46+'Januari 2026 PMG 1'!AM46 -> 10803048 | S44: =SUM(F44:Q44) -> 10803048 | T44: 175000000 | U44: =S44/T44*100 -> 6.1731703
C45: STEARIN | D45: 61714 | E45: Kg | F45: ='Januari 2026 PMG 1'!AM47+'Januari 2026 PMG 2'!AM47 -> 3424482 | S45: =SUM(F45:Q45) -> 3424482 | T45: 74961000 | U45: =S45/T45*100 -> 4.5683515
C46: Fractionation OLEIN IV 58 ( Retail )
C47: CPO Consume | E47: Kg
C48: RBDPO Consume | E48: Kg | S48: =S49+S50 -> 0
C49: OLEIN IV 58 | E49: Kg | S49: =SUM(F49:Q49) -> 0
C50: STEARIN | E50: Kg | S50: =SUM(F50:Q50) -> 0
C51: Fractionation OLEIN IV 60 | S51: Olein IV 60 | T51: Olein IV 60 | U51: Olein IV 60
C52: CPO Consume | E52: Kg | S52: =SUM(F52:Q52) -> 0 | T52: =T53/T61% -> 25913273 | U52: =S52/T52*100 -> 0
C53: RBDPO Brand Consume | E53: Kg | F53: ='Januari 2026 PMG 2'!AB55 -> 0 | S53: =S55+S56 -> 0 | T53: =T55+T56 -> 24558000 | U53: =S53/T53*100 -> 0 | DF53: 2136
C54: OLEIN IV 60 Bulk | E54: Kg | S54: =SUM(F54:Q54) -> 0 | T54: =SUM(F54:Q54) -> 0 | U54: =SUM(H54:S54) -> 0
C55: OLEIN IV 60 Salvaco | D55: 25000 | E55: Kg | F55: ='Januari 2026 PMG 2'!AB56 -> 0 | S55: =SUM(F55:Q55) -> 0 | T55: 14736000 | U55: =S55/T55*100 -> 0 | DF55: 1796
C56: SOFT STEARIN | D56: 10000 | E56: Kg | F56: ='Januari 2026 PMG 2'!AB57 -> 0 | S56: =SUM(F56:Q56) -> 0 | T56: 9822000 | U56: =S56/T56*100 -> 0 | DF56: =DF53/DF55*100 -> 118.93096
C57: Ratio Run RBDPO | S57: =+AVERAGE(F57:Q57) -> #DIV/0!
C58: Utilitas RBDPO | S58: =+AVERAGE(F58:Q58) -> #DIV/0!
C59: Budget RBDPO | S59: =SUM(F59:Q59) -> 0
C60: YIELD | S60: Yield | T60: Yield | U60: Yield | W60: =153073+111053 -> 264126 | OO60: 678
C61: RBDPO | D61: 94.2 | E61: % | F61: ='Januari 2026 PMG 2'!AM60 -> 95.376981 | S61: =(S21/(S12))*100 -> 95.171512 | T61: =(T21/(T12))*100 -> 94.769967 | OO61: 420 | OQ61: =OO61/OO60*100 -> 61.946903
C62: PFAD | D62: 5 | E62: % | F62: ='Januari 2026 PMG 2'!AM61 -> 4.36753 | S62: =(S22/(S12))*100 -> 4.2319046 | T62: =(T22/(T12))*100 -> 4.5147541 | W62: 111053 | OO62: =OO60-OO61 -> 258 | OQ62: =OO62/OO60*100 -> 38.053097
C63: Olein IV 56 | D63: 82 | E63: % | F63: ='Januari 2026 PMG 2'!AM62 -> 82.828482 | S63: =(S31/S30)*100 -> 82.825694 | T63: =(T31/T30)*100 -> 82.036628
C64: Stearin | D64: 18 | E64: % | F64: ='Januari 2026 PMG 2'!AM63 -> 17.171518 | S64: =(S32/S30)*100 -> 17.174306 | T64: =(T32/T30)*100 -> 17.963372 | W64: =S76-W69 -> -335809
C65: Olein IV 57 ( Bulk ) | D65: 75 | E65: % | S65: =(S35/S34)*100 -> #DIV/0! | T65: 75
C66: Stearin | D66: 25 | E66: % | S66: =(S36/S34)*100 -> #DIV/0! | T66: 25
C67: Olein IV 57 ( Retail ) | D67: 75 | E67: % | S67: =(S40/S39)*100 -> #DIV/0! | T67: 75
C68: Stearin | D68: 25 | E68: % | S68: =(S41/S39)*100 -> #DIV/0! | T68: 25 | FM68: 95.03
C69: Olein IV 58 ( Bulk ) | D69: 70 | E69: % | F69: ='Januari 2026 PMG 2'!AM68 -> 75.866496 | S69: =(S44/S43)*100 -> 75.930594 | T69: 70 | W69: 722634
C70: Stearin | D70: 30 | E70: % | F70: ='Januari 2026 PMG 2'!AM69 -> 24.133504 | S70: =(S45/S43)*100 -> 24.069406 | T70: 30
C71: Olein IV 58 ( Retail ) | D71: 70 | E71: %
C72: Stearin | D72: 30 | E72: %
C73: Olein IV 60 | D73: 60 | E73: % | F73: ='Januari 2026 PMG 2'!AB72 -> #DIV/0! | S73: =(S55/S53)*100 -> #DIV/0! | T73: =T55/T53*100 -> 60.004886 | W73: =153073+138655 -> 291728 | FM73: 4.23 | OQ73: =OQ74/94.2% -> 1307.8556 | OR73: MT CPO
C74: Soft Stearin | D74: 40 | E74: % | F74: ='Januari 2026 PMG 2'!AB73 -> #DIV/0! | S74: =(S56/S53)*100 -> #DIV/0! | T74: =T56/T53*100 -> 39.995114 | FM74: =100-FM68-FM73 -> 0.74 | OQ74: =22*56 -> 1232 | OR74: MT RBDPO Brand
B75: 2 | C75: CHEMICAL CONSUMABLE | S75: Chemical | T75: Chemical | U75: Chemical | OQ75: =16.5*OQ73 -> 21579.618
C76: Bleaching Earth (BE) to Poram Spec | D76: 9 | E76: Kg | F76: ='Januari 2026 PMG 1'!AM75+'Januari 2026 PMG 2'!AM75 -> 386825 | S76: =SUM(F76:Q76) -> 386825 | T76: 2767753 | U76: =S76/T76*100 -> 13.976139 | W76: =S76-611581 -> -224756
E77: % | F77: ='Januari 2026 PMG 2'!AM76+'Januari 2026 PMG 1'!AM76/F12 -> 0.67460297 | S77: =S76/(S12)*100 -> 0.67959278 | T77: 0.8 | U77: 0 | AW77: =S77*10 -> 6.7959278 | FM77: =#REF!*10 -> #REF! | OQ77: =OQ73+(S52/1000) -> 1307.8556 | OR77: Total CPO Brand
C78: Bleaching Earth (BE) to Branded Spec | D78: 16 | E78: Kg | S78: =SUM(F78:Q78) -> 0 | T78: 1357284 | U78: =S78/T78*100 -> 0 | OQ78: =OQ75+S78 -> 21579.618 | OR78: Total BE Brand
E79: % | S79: =S78/(S14)*100 -> #DIV/0! | T79: 1.8 | U79: 0 | AW79: =S79*10 -> #DIV/0! | OQ79: =OQ78/OQ77 -> 16.5 | OR79: Kg/MT CPO
C80: Phosporic Acid (PA) | D80: 0.6 | E80: Kg | F80: ='Januari 2026 PMG 2'!AM86+'Januari 2026 PMG 1'!AM86 -> 33324.696 | S80: =SUM(F80:Q80) -> 33324.696 | T80: 252824 | U80: =SUM(H80:S80) -> 33324.696 | OQ80: 16 | OR80: Budget (Kg/MT)
E81: % | F81: ='Januari 2026 PMG 2'!G87+'Januari 2026 PMG 1'!AM87/F12 -> 0.053511217 | S81: =S80/(S12+71450)*100 -> 0.058473031 | T81: 0.06 | U81: =U80/(U12+71450)*100 -> 46.640494 | AW81: =S81*10 -> 0.58473031 | FM81: =#REF!*10 -> #REF! | OQ81: =OQ79-OQ80 -> 0.5 | OR81: Over (Kg/MT)
B82: 3 | C82: Oil Losses | D82: 0.8 | E82: % | F82: =(('Januari 2026 PMG 2'!AM89+'Januari 2026 PMG 1'!AM89)/F12)*100 -> -0.59658346 | S82: =((SUM(S21:S22))-(SUM(S12)))/SUM(S12)*100 -> -0.59658346 | T82: =((SUM(T21:T22))-(SUM(T12)))/(SUM(T12))*100 -> -0.71527906 | U82: =S82/T82*100 -> 83.405694
E83: Kg | F83: ='Januari 2026 PMG 2'!AM89+'Januari 2026 PMG 1'!AM89 -> -339576
C84: % Oil Content | D84: 22 | E84: % | F84: ='Januari 2026 PMG 2'!AM90 -> 17.46 | S84: =AVERAGE(G84:K84) -> #DIV/0! | T84: 22 | U84: =AVERAGE(H84:S84) -> #DIV/0!
C85: Spent Bleaching Earth | E85: Kg | F85: ='Januari 2026 PMG 2'!AM91 -> 273050.1 | S85: =SUM(S76,S78)+(S84%*SUM(S76,S78)) -> #DIV/0! | T85: 7811279 | U85: =SUM(U76,U78)+(U84%*SUM(U76,U78)) -> #DIV/0! | FZ85: =W85+400 -> 400
B86: 5 | C86: PACKAGING (Brand Salvaco) | S86: Packaging | T86: Packaging | U86: Packaging | FW86: 17292 | OX86: =#REF!-FW86 -> #REF!
C87: Olein IV 60 Received | E87: Kg | S87: =SUM(F87:Q87) -> 0 | T87: =SUM(G87:R87) -> 0 | U87: =(S87/T87)*100 -> #DIV/0!
C88: Olein IV 60 Consume | E88: Kg | S88: =SUM(S89:S91) -> 0 | T88: =SUM(T89:T91) -> 32269046 | U88: =(S88/T88)*100 -> 0 | AFQ88: Kg | AFR88: Olein Filling to Packaging
C89: - finished product | E89: Kg | S89: =SUM(S93:S94)*10.86 -> 0 | T89: =SUM(T93:T94)*10.86 -> 32269046 | U89: =(S89/T89)*100 -> 0 | FW89: =#REF!/1000 -> #REF! | OX89: 4696 | OY89: =FW89/OX89*100 -> #REF!
C90: - sample | E90: Kg | S90: =SUM(F90:Q90) -> 0 | T90: =SUM(G90:R90) -> 0 | U90: =(S90/T90)*100 -> #DIV/0! | FW90: =#REF!/1000 -> #REF! | OX90: 565 | OY90: =FW90/OX90*100 -> #REF!
C91: - remelt, flushing, downgrade | E91: Kg | S91: =SUM(F91:Q91) -> 0 | T91: =SUM(G91:R91) -> 0
C92: Carton | S92: Carton | T92: Carton | U92: Carton
C93: Salvaco 1 Liter | E93: Box | S93: =SUM(F93:Q93) -> 0 | T93: 1254577 | U93: =(S93/T93)*100 -> 0
C94: Salvaco 2 Liter | E94: Box | S94: =SUM(F94:Q94) -> 0 | T94: 1716790 | U94: =(S94/T94)*100 -> 0
C95: Pouch | S95: Pouch | T95: Pouch | U95: Pouch
C96: Salvaco 1 Liter | E96: Pouch | S96: =S93*12 -> 0 | T96: =T93*12 -> 15054924 | U96: =(S96/T96)*100 -> 0
C97: Salvaco 2 Liter | E97: Pouch | S97: =S94*6 -> 0 | T97: =T94*6 -> 10300740 | U97: =(S97/T97)*100 -> 0
C98: Consumable Vit. A | E98: gram | S98: =SUM(F98:Q98) -> 0 | T98: =(T88*45)/1700 -> 854180.62 | U98: =(S98/T98)*100 -> 0
C99: Consumable Packing Tape | E99: Roll | S99: =SUM(F99:Q99) -> 0 | T99: =SUM(T93:T94)/500 -> 5942.734 | U99: =(S99/T99)*100 -> 0
C100: REJECT MATERIAL QTY | S100: Loss Material | T100: Loss Material | U100: Loss Material
C101: Carton | S101: Carton | T101: Carton | U101: Carton
C102: Salvaco 1 Liter | E102: Box | S102: =SUM(F102:Q102) -> 0 | T102: =SUM(G102:R102) -> 0 | U102: =SUM(H102:S102) -> 0
C103: Salvaco 2 Liter | E103: Box | S103: =SUM(F103:Q103) -> 0 | T103: =SUM(G103:R103) -> 0 | U103: =SUM(H103:S103) -> 0
...

Sheet Downtime Ref Oktober
F2: DOWN TIME SLOW FLOWRATE PRODUCTION REFINERY
F4: Periode 01/31 Oktober 2024
F5: TANGGAL | G5: CAPACITY (Kg) | H5: REMARKS | I5: Down time | M5: Tph
I6: Stop | J6: Slow | K6: % | AE6: 17 | AF6: 18 | AG6: 19 | AH6: 20 | AI6: 21 | AJ6: 22 | AK6: 23 | AL6: 24 | AM6: 25 | AN6: 26 | AO6: 27 | AP6: 28 | AQ6: 29 | AR6: 30 | AS6: 31
F7: 1 | G7: 1329220 | H7: Penyesuaian incoming CPO | J7: =(2200-(G7/1000))/91.7 -> 9.4959651 | K7: =G7/2200/1000 -> 0.60419091 | M7: =(G7/1000)/24 -> 55.384167 | O7: =249.262+270.9 -> 520.162 | P7: =1356.367+39.742 -> 1396.109 | Q7: =1086.521+50.6 -> 1137.121 | R7: =1353.558+373.309 -> 1726.867 | S7: 1942.746 | T7: 1868.212 | U7: 2057.011 | V7: 1781.844 | W7: 1250.764 | X7: 1613.486 | Y7: 1325.077 | Z7: =66.442+571.568 -> 638.01 | AA7: =815.429 -> 815.429 | AB7: =352.234+731.627 -> 1083.861 | AC7: =1626.002+13.213 -> 1639.215 | AD7: 2094.791 | AE7: 2075.375 | AF7: 2008.804 | AG7: 1946.712 | AH7: 1998.939 | AI7: =1623.839+281.468 -> 1905.307 | AJ7: 1610.024 | AK7: =1135.181+98.368 -> 1233.549 | AL7: =958.893+543.852 -> 1502.745 | AM7: 2043.15 | AN7: 1762.642 | AO7: 2170.336 | AP7: =1181.38+463.711 -> 1645.091 | AQ7: 219.474 | AR7: =48.153+1225.968+107.3 -> 1381.421
F8: 2 | G8: 1090185 | H8: Penyesuaian incoming CPO | J8: =(2200-(G8/1000))/91.7 -> 12.102672 | K8: =G8/2200/1000 -> 0.49553864 | M8: =(G8/1000)/24 -> 45.424375
F9: 3 | G9: 0 | H9: HOLD CPO Shortage | J9: =(2200-(G9/1000))/91.7 -> 23.991276 | K9: =G9/2200/1000 -> 0 | M9: =(G9/1000)/24 -> 0
F10: 4 | G10: 1214493 | H10: Penyesuaian incoming CPO | J10: =(2200-(G10/1000))/91.7 -> 10.747077 | K10: =G10/2200/1000 -> 0.55204227 | M10: =(G10/1000)/24 -> 50.603875
F11: 5 | G11: 466758 | H11: Penyesuaian incoming CPO | J11: =(2200-(G11/1000))/91.7 -> 18.901221 | K11: =G11/2000/1000 -> 0.233379 | M11: =(G11/1000)/24 -> 19.44825
F12: 6 | G12: 206159 | H12: Penyesuaian incoming CPO | J12: =(2200-(G12/1000))/91.7 -> 21.743086 | K12: =G12/2200/1000 -> 0.093708636 | M12: =(G12/1000)/24 -> 8.5899583
F13: 7 | G13: 630399 | H13: Penyesuaian incoming CPO | J13: =(2200-(G13/1000))/91.7 -> 17.116696 | K13: =G13/2200/1000 -> 0.286545 | M13: =(G13/1000)/24 -> 26.266625
F14: 8 | G14: 326961 | H14: Penyesuaian incoming CPO | J14: =(2200-(G14/1000))/91.7 -> 20.425725 | K14: =G14/2200/1000 -> 0.14861864 | M14: =(G14/1000)/24 -> 13.623375
F15: 9 | G15: 783993 | H15: Penyesuaian incoming CPO | J15: =(2200-(G15/1000))/91.7 -> 15.441734 | K15: =G15/2200/1000 -> 0.35636045 | M15: =(G15/1000)/24 -> 32.666375
F16: 10 | G16: 529241 | H16: Penyesuaian incoming CPO | J16: =(2200-(G16/1000))/91.7 -> 18.219836 | K16: =G16/2200/1000 -> 0.24056409 | M16: =(G16/1000)/24 -> 22.051708
F17: 11 | G17: 1204852 | H17: Penyesuaian incoming CPO | J17: =(2200-(G17/1000))/91.7 -> 10.852214 | K17: =G17/2200/1000 -> 0.54766 | M17: =(G17/1000)/24 -> 50.202167
F18: 12 | G18: 1651432 | H18: Penyesuaian incoming CPO | J18: =(2200-(G18/1000))/91.7 -> 5.9822028 | K18: =G18/2200/1000 -> 0.75065091 | M18: =(G18/1000)/24 -> 68.809667
F19: 13 | G19: 1336027 | H19: Penyesuaian incoming CPO | J19: =(2200-(G19/1000))/91.7 -> 9.4217339 | K19: =G19/2200/1000 -> 0.607285 | M19: =(G19/1000)/24 -> 55.667792
F20: 14 | G20: 524254 | H20: Penyesuaian incoming CPO | J20: =(2200-(G20/1000))/91.7 -> 18.27422 | K20: =G20/2200/1000 -> 0.23829727 | M20: =(G20/1000)/24 -> 21.843917
F21: 15 | G21: 935273 | H21: Penyesuaian incoming CPO | J21: =(2200-(G21/1000))/91.7 -> 13.792007 | K21: =G21/2200/1000 -> 0.42512409 | M21: =(G21/1000)/24 -> 38.969708
F22: 16 | G22: 1014253 | H22: Penyesuaian incoming CPO | J22: =(2200-(G22/1000))/91.7 -> 12.93072 | K22: =G22/2200/1000 -> 0.46102409 | M22: =(G22/1000)/24 -> 42.260542
F23: 17 | G23: 805977 | H23: Penyesuaian incoming CPO | J23: =(2200-(G23/1000))/91.7 -> 15.201996 | K23: =G23/2200/1000 -> 0.36635318 | M23: =(G23/1000)/24 -> 33.582375
... F37: 31 | G37: 498387 | H37: Penyesuaian incoming CPO | J37: =(2200-(G37/1000))/91.7 -> 18.556303 | K37: =G37/2200/1000 -> 0.22653955 | M37: =(G37/1000)/24 -> 20.766125
F38: TOTAL | G38: =SUM(G7:G37) -> 23466959 | I38: =SUM(I7:I36) -> 0 | J38: =SUM(J7:J37) -> 487.81942 | M38: =AVERAGE(M7:M37) -> 31.541612
G40: Summary
G41: 1. Slow flow rate due to Space Tank High | I41: 0 | J41: hours
G42: 2. Slow flow rate due to Olein IV 60 process | I42: 0 | J42: hours
G43: 3. Hold plant due to trip MP boiler & maintenance | I43: 0 | J43: hours
G44: 4. Penyesuaian incoming CPO | I44: =SUM(J7,J8,J10,J11,J12,J13,J14,J15,J16,J17,J18,J19,J20,J21,J22,J24,J23,J25,J28,J29,J30,J31,J32,J33,J34,J35,J36,J37) -> 415.84559 | J44: hours
G45: 5. Downtime due to Start Up Plant | J45: hours
G46: 6. Running Normal Plant | I46: 0 | J46: hours
G47: 7. Stop Plant due to Preventive Maintenance Plant | I47: 0 | J47: hours
G48: 8. Energizing PMG II | I48: 0 | J48: hours
G49: 9. Zero Suplay Gas (Problem Pertagas) | I49: 0 | J49: hours
G50: 10, Stop Plant | I50: 0 | J50: hours
G51: 11.HOLD CPO Shortage | I51: =SUM(J9,J26,J27) -> 71.973828 | J51: hours
G52: Total | I52: =SUM(I41:I51) -> 487.81942 | J52: hours
G53: Note : Kapasitas 2200 TPD

Sheet Downtime Fract Oktober
F2: DOWN TIME SLOW FLOWRATE PRODUCTION FRACTIONATION
F4: Periode 01/30 Oktober 2024
F5: TANGGAL | G5: CAPACITY (Kg) | H5: REMARKS | I5: Down time | M5: Tph
I6: Stop | J6: Slow | K6: % | AE6: 17 | AF6: 18 | AG6: 19 | AH6: 20 | AI6: 21 | AJ6: 22 | AK6: 23 | AL6: 24 | AM6: 25 | AN6: 26 | AO6: 27 | AP6: 28 | AQ6: 29 | AR6: 30 | AS6: 31
F7: 1 | G7: 823008 | H7: Slow flow rate due to Olein IV 56 process & IV 58 process | J7: =(2000-(G7/1000))/83.33 -> 14.124469 | K7: =G7/2000/1000 -> 0.411504 | M7: =(G7/1000)/24 -> 34.292 | O7: =249.262+270.9 -> 520.162 | P7: =1356.367+39.742 -> 1396.109 | Q7: =1086.521+50.6 -> 1137.121 | R7: =1353.558+373.309 -> 1726.867 | S7: 1942.746 | T7: 1868.212 | U7: 2057.011 | V7: 1781.844 | W7: 1250.764 | X7: 1613.486 | Y7: 1325.077 | Z7: =66.442+571.568 -> 638.01 | AA7: =815.429 -> 815.429 | AB7: =352.234+731.627 -> 1083.861 | AC7: =1626.002+13.213 -> 1639.215 | AD7: 2094.791 | AE7: 2075.375 | AF7: 2008.804 | AG7: 1946.712 | AH7: 1998.939 | AI7: =1623.839+281.468 -> 1905.307 | AJ7: 1610.024 | AK7: =1135.181+98.368 -> 1233.549 | AL7: =958.893+543.852 -> 1502.745 | AM7: 2043.15 | AN7: 1762.642 | AO7: 2170.336 | AP7: =1181.38+463.711 -> 1645.091 | AQ7: 219.474 | AR7: =48.153+1225.968+107.3 -> 1381.421
F8: 2 | G8: 1133656 | H8: Slow flow rate due to Olein IV 58 process | J8: =(2000-(G8/1000))/83.33 -> 10.396544 | K8: =G8/2000/1000 -> 0.566828 | M8: =(G8/1000)/24 -> 47.235667
F9: 3 | G9: 852841 | H9: Slow flow rate due to Olein IV 58 process | J9: =(2000-(G9/1000))/83.33 -> 13.766459 | K9: =G9/2000/1000 -> 0.4264205 | M9: =(G9/1000)/24 -> 35.535042
F10: 4 | G10: 285950 | H10: Slow flow rate due to Olein IV 58 process | J10: =(2000-(G10/1000))/83.33 -> 20.569423 | K10: =G10/2000/1000 -> 0.142975 | M10: =(G10/1000)/24 -> 11.914583
F11: 5 | G11: 767986 | H11: Slow flow rate due to Olein IV 58 process | J11: =(2000-(G11/1000))/83.33 -> 14.784759 | K11: =G11/2000/1000 -> 0.383993 | M11: =(G11/1000)/24 -> 31.999417
F12: 6 | G12: 178639 | H12: Slow flow rate due to Olein IV 58 process | J12: =(2000-(G12/1000))/83.33 -> 21.857206 | K12: =G12/2000/1000 -> 0.0893195 | M12: =(G12/1000)/24 -> 7.4432917
F13: 7 | G13: 216297 | H13: Slow flow rate due to Olein IV 58 process | J13: =(2000-(G13/1000))/83.33 -> 21.405292 | K13: =G13/2000/1000 -> 0.1081485 | M13: =(G13/1000)/24 -> 9.012375
F14: 8 | G14: 447025 | H14: Slow flow rate due to Olein IV 58 process | J14: =(2000-(G14/1000))/83.33 -> 18.636445 | K14: =G14/2000/1000 -> 0.2235125 | M14: =(G14/1000)/24 -> 18.626042
F15: 9 | G15: 821777 | H15: Slow flow rate due to Olein IV 58 process | J15: =(2000-(G15/1000))/83.33 -> 14.139242 | K15: =G15/2000/1000 -> 0.4108885 | M15: =(G15/1000)/24 -> 34.240708
F16: 10 | G16: 862670 | H16: Slow flow rate due to Olein IV 56 process & IV 58 process | J16: =(2000-(G16/1000))/83.33 -> 13.648506 | K16: =G16/2000/1000 -> 0.431335 | M16: =(G16/1000)/24 -> 35.944583
F17: 11 | G17: 1138713 | H17: Slow flow rate due to Olein IV 56 process & IV 58 process | J17: =(2000-(G17/1000))/83.33 -> 10.335857 | K17: =G17/2000/1000 -> 0.5693565 | M17: =(G17/1000)/24 -> 47.446375
F18: 12 | G18: 1185707 | H18: Slow flow rate due to Olein IV 56 process | J18: =(2000-(G18/1000))/83.33 -> 9.7719069 | K18: =G18/2000/1000 -> 0.5928535 | M18: =(G18/1000)/24 -> 49.404458
F19: 13 | G19: 699301 | H19: Slow flow rate due to Olein IV 56 process | J19: =(2000-(G19/1000))/83.33 -> 15.609012 | K19: =G19/2000/1000 -> 0.3496505 | M19: =(G19/1000)/24 -> 29.137542
... F37: 31 | G37: 1052080 | H37: Slow flow rate due to Olein IV 58 process | J37: =(2000-(G37/1000))/83.33 -> 11.375495 | K37: =G37/2000/1000 -> 0.52604 | M37: =(G37/1000)/24 -> 43.836667
F38: TOTAL | G38: =SUM(G7:G37) -> 20051919 | I38: =SUM(I7:I36) -> 0 | J38: =SUM(J7:J37) -> 503.39711 | M38: =AVERAGE(M7:M37) -> 26.951504
G40: Summary
G41: 1. Slow flow rate due to Space Tank High | I41: 0 | J41: hours
G42: 2. Slow flow rate due to Olein IV 60 process | I42: 0 | J42: hours
G43: 3. Slow flow rate due to Olein IV 57 process | I43: 0 | J43: hours
G44: 4. Slow Flow rate terkait material sortage & menyesuaikan | I44: 0 | J44: hours
G45: 5. Downtime due to Start/Stop Up Plant | I45: 0 | J45: hours
G46: 6. Running Normal Plant | I46: 0 | J46: hours
G47: 7. Stop Plant due to Preventive Maintenance Plant | I47: 0 | J47: hours
G48: 8. Energizing PMG II | I48: 0 | J48: hours
G49: 9. Zero Suplay Gas (Problem Pertagas) | I49: 0 | J49: hours
G50: 10. Slow flow rate due to Olein IV 58 process | I50: =SUM(J8,J9,J10,J11,J12,J13,J14,J15,J31,J32,J33,J34,J35,J36,J37) -> 245.89803 | J50: hours
G51: 11. STOP PLANT | I51: =SUM(J27,J28,J29,J30) -> 96.00384 | J51: hours
G52: 12.Slow flow rate due to Olein IV 56 process | I52: =SUM(J18,J19,J20,J21,J22,J23,J24,J25,J26) -> 123.3864 | J52: hours
G53: 13. Slow flow rate due to Olein IV 56 process & IV 57 process | I53: 0 | J53: hours
G54: 14. Slow flow rate due to Olein IV 56 process & IV 58 process | I54: =SUM(J7,J16,J17) -> 38.108832 | J54: hours
G55: Total | I55: =SUM(I41:I54) -> 503.39711 | J55: hours
G56: 8. Note : Kapasitas 2000 TPD

Sheet Prod
B2: MONTHLY PRODUCTION REPORT
B3: PT. INDUSTRI NABATI LESTARI
B4: Periode 01 s/d 31 maret 2025
B5: NO | C5: Item | D5: Unit | E5: September | H5: Remaks
E6: Budget | F6: Actual | G6: Percentage Act.
B7: 1. | C7: PRODUCTION
C8: Refinery Plant
C9: Running Days | D9: Days | E9: 19 | F9: ='Januari 2026 PMG 2'!$AM$6 -> 20 | G9: =(F9/E9) -> 1.0526316 | H9: Tercapai
C10: CPO Incoming | D10: Kg
C11: Total CPO Consume | D11: Kg | E11: ='Januari 2026 PMG 2'!E9 -> 58900000 | F11: =F12+F13 -> 40125380 | G11: =(F11/E11) -> 0.68124584 | H11: Tidak Tercapai
C12: CPO Consume Poram | F12: ='Januari 2026 PMG 2'!$AM$11 -> 40125380
C13: CPO Consume Brand | F13: ='Januari 2026 PMG 2'!$AM$12 -> 0
C14: - Avg. FFA | D14: % | E14: 5 | F14: ='Januari 2026 PMG 2'!$AM$13 -> 3.7489167 | G14: =(F14/E14) -> 0.74978333
C15: - Avg. Moist & Impurities | D15: % | E15: 0.5 | F15: ='Januari 2026 PMG 2'!$AM$14 -> 0.45608333 | G15: =(F15/E15) -> 0.91216667
C16: - Avg. DOBI | D16: % | E16: 22.2 | F16: ='Januari 2026 PMG 2'!$O$15 -> 0 | G16: =(F16/E16) -> 0
C17: Product
C18: RBDPO | D18: Kg | E18: ='Januari 2026 PMG 2'!E20 -> 55661000 | F18: ='Januari 2026 PMG 2'!$AM$20 -> 0 | G18: =(F18/E18) -> 0
C19: PFAD | D19: Kg | E19: ='Januari 2026 PMG 2'!E21 -> 2827000 | F19: ='Januari 2026 PMG 2'!$AM$21 -> 1752488 | G19: =(F19/E19) -> 0.61991086
C21: Fraksinasi Plant
C22: Total Proses RBDPO | D22: Kg | E22: ='Januari 2026 PMG 2'!E29 -> 35501000 | F22: ='Januari 2026 PMG 2'!$AM$29 -> 51490545 | G22: =(F22/E22) -> 1.450397 | H22: Tidak Tercapai
C23: Total Olah RBDPO ( Feed ) | D23: Kg | E23: 35501000 | F23: ='Januari 2026 PMG 2'!$AM$25 -> 0 | G23: =(F23/E23) -> 0 | H23: Tidak Tercapai
C24: Fractionation Olein IV 56
C25: RBDPO Consume | D25: Kg | E25: =E26+E27 -> 25639000 | F25: =F26+F27 -> 39418618 | G25: =(F25/E25) -> 1.5374476 | H25: Tercapai
C26: Olein IV 56 | D26: Kg | E26: ='Januari 2026 PMG 2'!E33 -> 25000000 | F26: ='Januari 2026 PMG 2'!$AM$33 -> 32649843 | G26: =(F26/E26) -> 1.3059937 | H26: Tercapai
C27: Stearin | D27: Kg | E27: ='Januari 2026 PMG 2'!E34 -> 639000 | F27: ='Januari 2026 PMG 2'!$AM$34 -> 6768775 | G27: =(F27/E27) -> 10.592762 | H27: Tercapai
C28: Fractionation Olein IV 57 ( Bulk )
C29: RBDPO Consume | D29: Kg | E29: 0
C30: Olein IV 57 | D30: Kg | E30: 0 | F30: 0 | G30: 0
C31: Stearin | D31: Kg | E31: 0
C32: Fractionation Olein IV 58 ( bulk )
C33: CPO | D33: Kg | E33: 1812101.9 | G33: =(F33/E33)*100 -> 0
C34: RBDPO Consume | D34: Kg | E34: =E35+E36 -> 12514300 | F34: =F35+F36 -> 0 | G34: =(F34/E34)*100 -> 0 | H34: Tidak Tercapai
C35: Olein IV 58 | D35: Kg | E35: ='Januari 2026 PMG 2'!E46 -> 12000000 | G35: =(F35/E35)*100 -> 0 | H35: Tidak Tercapai
C36: Stearin | D36: Kg | E36: ='Januari 2026 PMG 2'!E47 -> 514300 | G36: =(F36/E36)*100 -> 0 | H36: Tidak Tercapai
C37: Fractionation Olein IV 58
C38: RBDPO Consume | D38: Kg | E38: 21429000 | F38: =F39+F40 -> 12071927 | G38: =(F38/E38)*100 -> 56.334533 | H38: Tidak Tercapai
C39: Olein IV 58 | D39: Kg | E39: 15000000 | F39: ='Januari 2026 PMG 2'!$AM$46 -> 9158548 | G39: =(F39/E39)*100 -> 61.056987 | H39: Tidak Tercapai
C40: Stearin | D40: Kg | E40: 6429000 | F40: ='Januari 2026 PMG 2'!$AM$47 -> 2913379 | G40: =(F40/E40)*100 -> 45.316208 | H40: Tidak Tercapai
C41: Fractionation Olein IV 60
C42: CPO | E42: 2234607.2 | F42: 0 | G42: =(F42/E42)*100 -> 0
C43: RBDPO Consume | D43: Kg | E43: =E44+E45 -> 1333300 | F43: 0 | G43: =(F43/E43)*100 -> 0 | H43: Tidak Tercapai
C44: Olein IV 60 Salvaco | D44: Kg | E44: ='Januari 2026 PMG 2'!E56 -> 1250000 | F44: ='Januari 2026 PMG 2'!AM56 -> 0 | G44: =(F44/E44)*100 -> 0 | H44: Tidak Tercapai
C45: Soft Stearin | D45: Kg | E45: ='Januari 2026 PMG 2'!E57 -> 83300 | F45: ='Januari 2026 PMG 2'!AM57 -> 0 | G45: =(F45/E45)*100 -> 0 | H45: Tidak Tercapai
B46: 2. | C46: % YIELD
C47: RBDPO | D47: % | E47: 94.77 | F47: =(F18/F11)*100 -> 0 | G47: =(F47/E47)*100 -> 0 | H47: Tidak Tercapai
C48: PFAD | D48: % | E48: 4.5 | F48: =(F19/(F11))*100 -> 4.36753 | G48: =(F48/E48)*100 -> 97.056222 | H48: Tidak Tercapai
C49: Olein IV 56 | D49: % | E49: 82 | F49: =F26/(F26+F27)*100 -> 82.828482 | G49: =(F49/E49)*100 -> 101.01034 | H49: Tercapai
C50: Stearin | D50: % | E50: 18 | F50: =(F27/F25)*100 -> 17.171518 | G50: =(F50/E50)*100 -> 95.397321 | H50: Tercapai
C51: Olein IV 57 ( Bulk ) | D51: % | E51: 75 | F51: 0 | G51: =(F51/E51)*100 -> 0
C52: Stearin | D52: % | E52: 25 | F52: 0 | G52: =(F52/E52)*100 -> 0
C53: Olein IV 57 ( Retail ) | D53: % | E53: 75 | F53: =F35/(F35+F36)*100 -> #DIV/0! | G53: =(F53/E53)*100 -> #DIV/0! | H53: Tercapai
C54: Stearin | D54: % | E54: 25 | F54: =(F36/F34)*100 -> #DIV/0! | G54: =(F54/E54)*100 -> #DIV/0! | H54: Tercapai
C55: Olein IV 58 | D55: % | E55: 70 | F55: =F39/(F39+F40)*100 -> 75.866496 | G55: =(F55/E55)*100 -> 108.38071 | H55: Tercapai
C56: Stearin | D56: % | E56: 30 | F56: =(F40/F38)*100 -> 24.133504 | G56: =(F56/E56)*100 -> 80.445014 | H56: Tercapai
C57: Olein IV 60 | D57: % | E57: 60 | F57: 0 | G57: =(F57/E57)*100 -> 0
C58: Soft Stearin | D58: % | E58: 40 | F58: 0 | G58: =(F58/E58)*100 -> 0
B59: 3. | C59: CHEMICAL CONSUMABLE
C60: Bleaching Earth to Poram Spec | D60: Kg | E60: 530100 | F60: ='Januari 2026 PMG 2'!$AM$75 -> 270687 | G60: =(F60/E60)*100 -> 51.063384
D61: Kg/MT | E61: ='Januari 2026 PMG 2'!E75 -> 9 | F61: =(F60/F12)*1000 -> 6.7460296 | G61: =(F61/E61)*100 -> 74.955884 | H61: Tercapai
C62: Bleaching Earth to Branded Spec | D62: Kg | E62: 106326 | F62: ='Januari 2026 PMG 2'!AM12 -> 0 | G62: =(F62/E62)*100 -> 0
D63: Kg/MT | E63: 1060 | G63: =(F63/E63)*100 -> 0
C64: Phosporic Acid | D64: Kg | E64: 35340 | F64: ='Januari 2026 PMG 2'!$AM$86 -> 24463.56 | G64: =(F64/E64)*100 -> 69.22343
D65: Kg/MT | E65: 0.6 | F65: =(F64/F11)*1000 -> 0.60967796 | G65: =(F65/E65)*100 -> 101.61299 | H65: Tercapai
B66: 4. | C66: OIL LOSSES
C67: (Loss)/Gain | D67: % | E67: -0.73 | F67: ='Januari 2026 PMG 2'!$AM$88 -> -0.25548917 | G67: =(F67/E67)*100 -> 34.998516 | H67: Tidak Tercapai
C68: % Oil Content | D68: % | E68: 22 | F68: ='Januari 2026 PMG 2'!$AM$90 -> 17.46 | G68: =(F68/E68)*100 -> 79.363636
C69: Spent Bleaching Earth | D69: Kg | E69: 413199.36 | F69: ='Januari 2026 PMG 2'!$AM$91 -> 273050.1 | G69: =(F69/E69)*100 -> 66.081927
B70: NB :
B71: - BE Achieve dengan pemakaian consume Bleaching Earth 7,80 Kg/MT
B72: - Untuk hari olah Produksi terpenuhi namun dalam kondisi Slow Flowrate dikarenakan Shortage CPO dan target Shipment yang tercapai hanya Olein IV 56
B74: - Total CPO Proses sebesar : 24.046 Mt dengan total CPO Incoming ke INL sebanyak : 24.987 MT
B75: - Rata rata incoming CPO perhari 832 MT
A77: Prepared by, | D77: Checked by, | H77: Approved by,
A81: Syaiful Sembiring | D81: Reza P. Panjaitan | F81: Sudarianto | H81: Eben Jaya Ginting
A82: Admin. Process | D82: Supervisor Produksi | F82: Jr. Manager Produksi | H82: Manager Plant

Sheet Utility
D2: UTILITY (GAS, STEAM, WATER & POWER) REPORT
D3: PT. INDUSTRI NABATI LESTARI
D5: Periode 01 s/d 31 maret 2025
D6: No | E6: Item | F6: Norma | G6: UoM | H6: September | K6: Consume CPO ( MT ) | L6: Remaks
H7: Budget | I7: Actual | J7: Percentage Act.
E9: Total Feed Raw Material CPO | K9: 24046
D10: 1. | E10: GAS CONSUMPTION
E11: Incoming *base on INL | G11: mmbtu | I11: ='Januari 2026 PMG 2'!$AM$244 -> 26545.917
E12: Incoming *base on Pertagas | F12: 1460.001 | G12: mmbtu | H12: 26051.47 | I12: ='Januari 2026 PMG 2'!$AM$242 -> 26890.592 | J12: =I12/H12 -> 1.0322102 | K12: =I12/K9 -> 1.1182979
E13: Distribution to
E14: HP Boiler Refinery | G14: mmbtu | H14: 3907.73 | I14: ='Januari 2026 PMG 2'!$AM$246 -> 109902 | J14: =I14/H14 -> 28.124256 | K14: =I14/K9 -> 4.5704899
E15: MP Boiler | G15: mmbtu | H15: 22143.74 | I15: =I12-$I$14 -> -83011.408 | J15: =I15/H15 -> -3.7487528 | K15: =I15/K9 -> -3.452192
E16: Total | G16: mmbtu | H16: 26051.47 | I16: =$I$12 -> 26890.592 | J16: =I16/H16 -> 1.0322102 | K16: =SUM(K14+K15) -> 1.1182979
D17: 2. | E17: STEAM CONSUMPTION
E18: Incoming | G18: Kg | H18: 11424000 | I18: ='Januari 2026 PMG 2'!$AM$253 -> 5602499.5 | J18: =I18/H18 -> 0.49041487 | K18: =I18/$K$9 -> 232.99091
E19: Distribution to | K19: =I19/$K$9 -> 0
E20: Refinery | F20: < 90 | G20: Kg | H20: 3420000 | I20: ='Januari 2026 PMG 2'!$AM$255 -> 1730660 | J20: =I20/H20 -> 0.50604094 | K20: =I20/$K$9 -> 71.972885
E21: Fractionation | F21: < 61 | G21: Kg | H21: 2318000 | I21: ='Januari 2026 PMG 2'!$AM$257 -> 1097314 | J21: =I21/H21 -> 0.47338827 | K21: =I21/$K$9 -> 45.633952
E22: Others | F22: 106000 | G22: Kg | H22: 5686000 | I22: ='Januari 2026 PMG 2'!$AM$259 -> 2774525.5 | J22: =I22/H22 -> 0.48795735 | K22: =I22/$K$9 -> 115.38408
E23: Total | G23: Kg | H23: 11424000 | I23: =SUM(I20:I22) -> 5602499.5 | J23: =I23/H23 -> 0.49041487 | K23: =I23/$K$9 -> 232.99091
D24: 3. | E24: WATER CONSUMPTION
E25: Incoming Raw Water | G25: m3 | H25: 19123.69 | I25: =SUM(I26:$I$27) -> 16697 | J25: =I25/H25 -> 0.87310556 | K25: =I25/$K$9 -> 0.69437744
E26: - Suplay To RO Product | I26: ='Januari 2026 PMG 2'!$AM$277 -> 4814.9 | K26: =I26/$K$9 -> 0.20023705
E27: - Suplay To Proses dan Sanitary | I27: =SUM(I29:$I$31) -> 11882.1 | K27: =I27/$K$9 -> 0.4941404
E28: Rincian Outgoing Proses | K28: =I28/$K$9 -> 0
E29: Softener Product (to Refinery) | F29: < 0,5 | G29: m3 | H29: 1521.33 | I29: ='Januari 2026 PMG 2'!$AM$273 -> 4267 | J29: =I29/H29 -> 2.8047827 | K29: =I29/$K$9 -> 0.17745155
E30: Softener Product (to Fractionation) | F30: < 0,4 | G30: m3 | H30: 2622 | I30: ='Januari 2026 PMG 2'!$AM$275 -> 2436 | J30: =I30/H30 -> 0.92906178 | K30: =I30/$K$9 -> 0.10130583
E31: Others | G31: m3 | H31: 2730.3 | I31: ='Januari 2026 PMG 2'!$AM$278 -> 5179.1 | J31: =I31/H31 -> 1.8968978 | K31: =I31/$K$9 -> 0.21538302
E32: Total | G32: m3 | H32: 6873.63 | I32: =SUM(I26:I27) -> 16697 | J32: =I32/H32 -> 2.4291386 | K32: =I32/$K$9 -> 0.69437744
D33: 4 | E33: POWER CONSUMPTION
E34: Incoming
E35: PLN *base on BA Kinra | G35: Kwh | H35: 568099 | I35: ='Januari 2026 PMG 2'!$AM$292 -> 49.895 | J35: =I35/H35 -> 8.7828002e-05 | K35: =I35/$K$9 -> 0.0020749813
E36: Outgoing | K36: =I36/$K$9 -> 0
E37: - Physical Refinery Plant | F37: 5404.17 | G37: Kwh | H37: 102679 | I37: ='Januari 2026 PMG 2'!$AM$298 -> 196017 | J37: =I37/H37 -> 1.9090272 | K37: =I37/$K$9*1000 -> 8151.7508
E38: - Refinery - Cooling Water System | F38: 3850.42 | G38: Kwh | H38: 73158 | I38: ='Januari 2026 PMG 2'!$AM$296 -> 258557 | J38: =I38/H38 -> 3.5342273 | K38: =I38/$K$9*1000 -> 10752.599
E39: - Refinery - Utilities | F39: 11.81 | G39: Kwh | H39: 212 | I39: ='Januari 2026 PMG 2'!$AM$321 -> 0 | J39: =I39/H39 -> 0 | K39: =I39/$K$9*1000 -> 0
E40: - Dry Fractionation Plant | F40: 5759.67 | G40: Kwh | H40: 109440 | I40: ='Januari 2026 PMG 2'!$AM$303 -> 170048.2 | J40: =I40/H40 -> 1.553803 | K40: =I40/$K$9*1000 -> 7071.7874
E41: - Dry Fractionation CW System | F41: 1308.96 | G41: Kwh | H41: 28747 | I41: ='Januari 2026 PMG 2'!$AM$301 -> 225360 | J41: =I41/H41 -> 7.8394267 | K41: =I41/$K$9*1000 -> 9372.0369
E42: - Lighting - Refinery & Dry Fractionation | F42: 241.12 | G42: Kwh | H42: 4581 | I42: ='Januari 2026 PMG 2'!$AM$322 -> 0 | J42: =I42/H42 -> 0 | K42: =I42/$K$9*1000 -> 0
D44: Note untuk Power Consumption
D45: Selisih antara incoming dan outgoing dikarenakan hal berikut :
D47: - Over pemakaian Gas dikarenakan running sesuai RKAP 19 hari namun plant running 27 hari
E50: Prepared by, | F50: Checked by, | K50: Approved by,
E54: Syaiful Sembiring | F54: Reza P. Panjaitan | I54: Sudarianto | K54: Eben Jaya Ginting
E55: Admin. Process | F55: Supervisor Produksi | I55: Jr. Manager Produksi | K55: Manager Plant

Sheet Qty cons analysis
D2: Quantity Utility Consumption Analysis (based on Guarantee Utility Consumption)
D3: Refinery & Fractionation Plant
D4: Periode 01 s/d 31 maret 2025
D5: Consumption | E5: UoM | F5: Budget | G5: Actual | H5: Under (Over) Budget | I5: Explanation Under / Over budget
D6: CPO Consume | E6: Kg | F6: ='Januari 2026 PMG 2'!E9 -> 58900000 | G6: ='Januari 2026 PMG 2'!$AM$9 -> 40125380 | H6: =G6/F6 -> 0.68124584
D7: RbdPO Consume | E7: Kg | F7: ='Januari 2026 PMG 2'!E20 -> 55661000 | G7: ='Januari 2026 PMG 2'!$AM$25 -> 0 | H7: =G7/F7 -> 0
D8: TOTAL ACTUAL CONSUMPTION
D9: Refinery
D10: Bleaching Earth to Poram Spec | E10: Kg | F10: 232362 | G10: ='Januari 2026 PMG 2'!$AM$75 -> 270687 | H10: =F10-G10 -> -38325
D11: Bleaching Earth to Branded Spec | E11: Kg | F11: 106326 | G11: ='Januari 2026 PMG 2'!$AM$81 -> 0 | H11: =F11-G11 -> 106326
D12: Phosporic Acid | E12: Kg | F12: 20971 | G12: ='Januari 2026 PMG 2'!$AM$86 -> 24463.56 | H12: =F12-G12 -> -3492.56
D13: Gas Consumption (MP Boiler) | E13: mmbtu | F13: 22143.74 | G13: ='Januari 2026 PMG 2'!$AM$250+'Januari 2026 PMG 2'!$AM$249 -> 16712.074 | H13: =F13-G13 -> 5431.6664
D14: Gas Consumption (HP Boiler) | E14: mmbtu | F14: 3907.73 | G14: ='Januari 2026 PMG 2'!$AM$246 -> 109902 | H14: =F14-G14 -> -105994.27
D15: Cooling Water top up to Cooling Tower | E15: m3 | F15: 1521.33 | G15: ='Januari 2026 PMG 2'!$AM$273 -> 4267 | H15: =F15-G15 -> -2745.67
D16: Steam | E16: Kg | F16: 11424000 | G16: ='Januari 2026 PMG 2'!$AM$255 -> 1730660 | H16: =F16-G16 -> 9693340
D17: Power (Process Plant) | E17: Kwh | F17: 102679 | G17: ='Januari 2026 PMG 2'!$AM$298 -> 196017 | H17: =F17-G17 -> -93338
D18: Power (Cooling Tower) | E18: Kwh | F18: 73158 | G18: ='Januari 2026 PMG 2'!$AM$296 -> 258557 | H18: =F18-G18 -> -185399
D19: Fractionation
D20: Cooling Water top up to Cooling Tower | E20: m3 | F20: 2622 | G20: ='Januari 2026 PMG 2'!$AM$275 -> 2436 | H20: =F20-G20 -> 186
D21: Steam | E21: Kg | F21: 2318000 | G21: ='Januari 2026 PMG 2'!$AM$257 -> 1097314 | H21: =F21-G21 -> 1220686
D22: Power (Process Plant) | E22: Kwh | F22: 109440 | G22: ='Januari 2026 PMG 2'!$AM$303 -> 170048.2 | H22: =F22-G22 -> -60608.2
D23: Power (Cooling Tower) | E23: Kwh | F23: 28747 | G23: ='Januari 2026 PMG 2'!$AM$301 -> 225360 | H23: =F23-G23 -> -196613
D24: ACTUAL CONSUMPTION PER MT RAW MATERIAL
D25: Refinery
D26: Bleaching Earth to Poram Spec | E26: Kg/MT | F26: 9 | G26: =(G10/$G$6)*1000 -> 6.7460296 | H26: =F26-G26 -> 2.2539704
D27: Bleaching Earth to Branded Spec | E27: Kg/MT | F27: 18 | G27: =(G11/$G$6)*1000 -> 0 | H27: =F27-G27 -> 18
D28: Phosporic Acid | E28: Kg/MT | F28: 0.6 | G28: =(G12/$G$6)*1000 -> 0.60967796 | H28: =F28-G28 -> -0.0096779644
D29: Gas Consumption (HP Boiler) | E29: Nm3/MT | F29: 4.2 | G29: =(G13/$G$6)*1000 -> 0.41649633 | H29: =F29-G29 -> 3.7835037 | I29: Gas Over dikarenakan kapasitas tidak tercapai
D30: Gas Consumption (HP Boiler) **) | E30: mmbtu/MT | F30: 0.2 | G30: =(G14/$G$6)*1000 -> 2.7389647 | H30: =F30-G30 -> -2.5389647
D31: Cooling Water top up to Cooling Tower | E31: m3/MT | F31: 0.04 | G31: =(G15/$G$6)*1000 -> 0.10634167 | H31: =F31-G31 -> -0.066341672
D32: Steam | E32: Kg/MT | F32: 28 | G32: =(G16/$G$6)*1000 -> 43.131305 | H32: =F32-G32 -> -15.131305 | I32: Steam Refinery Over dikarenakan kapasitas tidak tercapai
D33: Power (Process Plant) | E33: Kwh/MT | F33: 4.4 | G33: =(G17/$G$6)*1000 -> 4.8851126 | H33: =F33-G33 -> -0.48511261 | I33: Power Over dikarenakan kapasitas tidak tercapai
D34: utility section ( chiller ) | E34: Kwh/MT | F34: 7.3 | G34: =(G18/$G$6)*1000 -> 6.4437271 | H34: =F34-G34 -> 0.85627286
D35: Fractionation
D36: Cooling Water top up to Cooling Tower | E36: m3/MT | F36: 0.13 | G36: =(G20/$G$6)*1000 -> 0.060709705 | H36: =F36-G36 -> 0.069290295
D37: Steam | E37: Kg/MT | F37: 45 | G37: =(G21/$G$6)*1000 -> 27.34713 | H37: =F37-G37 -> 17.65287 | I37: Steam Over dikarenakan menggunakan 2 unit chiller
D38: Power (Process Plant) | E38: Kwh/MT | F38: 4.1 | G38: =(G22/$G$6)*1000 -> 4.2379212 | H38: =F38-G38 -> -0.13792124 | I38: Power Over dikarenakan kapasitas tidak tercapai
D39: utility section ( chiller ) | E39: Kwh/MT | F39: 4.5 | G39: =(G23/$G$6)*1000 -> 5.6163954 | H39: =F39-G39 -> -1.1163954
D42: - BE Achieve dengan pemakaian consume Bleaching Earth 7,80 Kg/MT
D43: * Steam Refinery Over dikarenakan kapasitas tidak tercapai
D44: * Gas Refinery Over dikarenakan kapasitas tidak tercapai
D45: * Power Fractionation Over dikarenakan kapasitas tidak tercapai
D47: Prepared by, | G47: Checked by, | I47: Approved by,
D51: Syaiful Sembiring | F51: Reza P. Panjaitan | H51: Sudarianto | I51: Eben Jaya Ginting
D52: Admin. Process | F52: Supervisor Produksi | H52: Jr. Manager Produksi | I52: Manager Plant

Sheet Steam
B2: Steam Price Package Boiler | G2: Kurs | H2: 16000
B3: Consumable Item | C3: Norma | E3: Consumption, Ton/day | F3: Unit Price | H3: Total Cost
B4: Steam Production (Including Dearator) | C4: =408/24 -> 17 | D4: Ton/jam | E4: ='Januari 2026 PMG 2'!AM253 -> 5602499.5 | H4: Rp/day
B5: Gas | C5: 1000 | D5: MMBTU/day | E5: ='Januari 2026 PMG 2'!$AM$243 -> 1344.5296 | F5: 11.5 | G5: USD/MMBTU | H5: =E5*H2*F5 -> 2.4739345e+08 | I5: Harga steam tinggi dikarenakan oleh unit price gas yang tinggi, ideal (9.6)
B6: Chemical Treatment
B7: EONALKALOX B1414 | C7: 7.3 | D7: l/day | E7: =C7 -> 7.3 | F7: 25340 | G7: Rp/l | H7: =E7*F7 -> 184982
B8: EONCONDENS B1720 | C8: 2.4 | D8: l/day | E8: =C8 -> 2.4 | F8: 110000 | G8: Rp/l | H8: =E8*F8 -> 264000
B9: EONOXY B8100 | C9: 2.4 | D9: l/day | E9: =C9 -> 2.4 | F9: 20160 | G9: Rp/l | H9: =E9*F9 -> 48384
B10: EONSCALE B5100 | C10: 5.8 | D10: l/day | E10: =C10 -> 5.8 | F10: 31800 | G10: Rp/l | H10: =E10*F10 -> 184440
B11: EONDESCALER B2550 | C11: 1.4 | D11: l/day | E11: =C11 -> 1.4 | F11: 39320 | G11: Rp/l | H11: =E11*F11 -> 55048
B12: Water Demin | C12: =[2]L.Water!C12*83% -> 408.0197 | D12: M3/day | E12: =C12 -> 408.0197 | F12: =[2]L.Water!F12 -> 10162 | G12: Rp/m3 | H12: =E12*F12 -> 4146296.2
B13: Preventive Maintenance | D13: Rp/day | H13: =C13 -> 0
B14: Total Pakage Boiler | H14: =SUM(H5:H13) -> 2.522766e+08
F15: Unit Price, Rp/Ton | H15: =H14/E4 -> 45.029294
B17: Note :
B18: 1. Harga gas, secara general untuk industri adalah 9,21-9,6 usd/mmBtu
C26: Kurita H-504 18:25

Sheet WWTP
B2: Water Waste Treatment Plant | G2: Kurs | H2: ='SUMMARY HPP '!I9 -> 16000
B3: Consumable Item | C3: Norma | E3: Consumption, M3/day | F3: Unit Price | H3: Total Cost
B4: Waste Water Feed | C4: =200/24 -> 8.3333333 | D4: M3/jam | E4: ='Januari 2026 PMG 2'!AM279 -> 4349 | H4: Rp/day
B5: biaya transfer ke kawasan | F5: 0 | G5: Rp/m3 | H5: 8700
B6: Chemical Treatment
B7: Sugar | C7: 0 | D7: kg/day | E7: =C7 -> 0 | F7: 24890 | G7: Rp/kg | H7: =E7*F7 -> 0
B8: PE | C8: =E8*C4 -> 0.62305296 | D8: kg/day | E8: 0.074766355 | F8: 65340 | G8: Rp/kg | H8: =E8*F8 -> 4885.2336
B9: PAC | C9: =E9*C4 -> 46.728972 | D9: kg/day | E9: 5.6074766 | F9: 7702 | G9: Rp/kg | H9: =E9*F9 -> 43188.785
B10: Urea | C10: =E10*C4 -> 6.2305296 | D10: kg/day | E10: 0.74766355 | F10: 18634 | G10: Rp/kg | H10: =E10*F10 -> 13931.963
B11: TSP | C11: =E11*C4 -> 1.2461059 | D11: kg/day | E11: 0.14953271 | F11: 44722 | G11: Rp/kg | H11: =E11*F11 -> 6687.4019
B12: HCL | C12: 0 | D12: kg/day | E12: =C12 -> 0 | F12: 5700 | G12: Rp/kg | H12: =E12*F12 -> 0
B13: NaOH | C13: 0 | D13: kg/day | E13: =C13 -> 0 | F13: 15700 | G13: Rp/kg | H13: =E13*F13 -> 0
B14: Power | C14: 2675 | D14: kW/day | E14: =C14 -> 2675 | F14: =[3]UP.E!C28 -> 1550 | G14: Rp/kW | H14: =E14*F14 -> 4146250
B15: Preventive Maintenance | D15: Rp/day | H15: =E15*F15 -> 0
H16: =IFERROR(SUM(H5:H15),"") -> 4223643.4
F17: Unit Price, Rp/M3 | H17: =H16/E4 -> 971.17576
C29: Kurita H-504 18:25

Sheet WTP
B2: Water Treatment Plant | G2: Kurs | H2: 16000
B3: Consumable Item | C3: Norma | E3: Consumption, M3/day | F3: Unit Price | H3: Total Cost
B4: Water Treatment Plant | C4: =1000/24 -> 41.666667 | D4: M3/jam | E4: ='Januari 2026 PMG 2'!AM271 -> 834.85 | H4: Rp/day
B5: Chemical | F5: 8700 | G5: Rp/m3 | H5: =F5*E4 -> 7263195
B6: anti scalant | C6: 0.1 | D6: kg/day | E6: =C6 -> 0.1 | F6: 44500 | G6: Rp/kg | H6: =E6*F6 -> 4450
B7: caustic soda | C7: 0.1 | D7: kg/day | E7: =C7 -> 0.1 | F7: 65340 | G7: Rp/kg | H7: =E7*F7 -> 6534
B8: citrid acid | C8: 0.1 | D8: kg/day | E8: =C8 -> 0.1 | F8: 33275 | G8: Rp/kg | H8: =E8*F8 -> 3327.5
B9: bioside | C9: 0.1 | D9: kg/day | E9: =C9 -> 0.1 | F9: 47450 | G9: Rp/kg | H9: =E9*F9 -> 4745
B10: Power | C10: 8896 | D10: kW/day | E10: =C10 -> 8896 | F10: =[3]UP.E!C28 -> 1550 | G10: Rp/kW | H10: =E10*F10 -> 13788800
B11: Preventive Maintenance | D11: Rp/day | H11: =E11*F11 -> 0
H12: =IFERROR(SUM(H5:H11),"") -> 21071052
F13: Unit Price, Rp/M3 | H13: =H12/E4 -> 25239.326
C25: Kurita H-504 18:25

Sheet lab
B2: Laboratorium Chemical Cost
B3: Consumable Item | C3: Norma | E3: Consumption/ Hari | F3: Unit Price | H3: Total Biaya
H4: Per Hari
B5: Refinery, Fraksinasi, Packaging & Sotrage tank
B6: Acetic Acid Glacial | C6: 50 | D6: ml | E6: =C6 -> 50 | F6: 374 | G6: ml | H6: =E6*F6 -> 18700
B7: Aquadest | C7: 2 | D7: liter | E7: =C7 -> 2 | F7: 7250 | G7: liter | H7: =E7*F7 -> 14500
B8: BF3-methanol solution, Reagen Grade | C8: 0.5 | D8: ml | E8: =C8 -> 0.5 | F8: 500 | G8: ml | H8: =E8*F8 -> 250
B9: Chloroform | C9: 70 | D9: ml | E9: =C9 -> 70 | F9: 388 | G9: ml | H9: =E9*F9 -> 27160
B10: Cyclohexane | C10: 70 | D10: ml | E10: =C10 -> 70 | F10: 612 | G10: ml | H10: =E10*F10 -> 42840
B11: Hydrazine Sulphate | C11: 0.05 | D11: gr | E11: =C11 -> 0.05 | F11: 21000 | G11: gr | H11: =E11*F11 -> 1050
B12: Hydrochloric Acid 37% | C12: 2.6 | D12: ml | E12: =C12 -> 2.6 | F12: 236 | G12: ml | H12: =E12*F12 -> 613.6
B13: Iso Propanol Alcohol TG | C13: 5.5 | D13: liter | E13: =C13 -> 5.5 | F13: 35000 | G13: liter | H13: =E13*F13 -> 192500
B14: Isooctane | C14: 150 | D14: ml | E14: =C14 -> 150 | F14: 480 | G14: ml | H14: =E14*F14 -> 72000
B15: Indikator Phenolpthalaein 1 % | C15: 0.3 | D15: gr | E15: =C15 -> 0.3 | F15: 6750 | G15: gr | H15: =E15*F15 -> 2025
B16: Indikator Thymolpthalaein | C16: =36/357 -> 0.10084034 | D16: gr | E16: =C16 -> 0.10084034 | F16: 90000 | G16: gr | H16: =E16*F16 -> 9075.6303
B17: Starch | C17: =107/357 -> 0.29971989 | D17: gr | E17: =C17 -> 0.29971989 | F17: 3000 | G17: gr | H17: =E17*F17 -> 899.15966
B18: Liquid standard Lovibond 3,4R 30,0 Y 0,9N | C18: 0.1 | D18: ml | E18: =C18 -> 0.1 | F18: 70000 | G18: ml | H18: =E18*F18 -> 7000
B19: Liquid standard Lovibond 3,0R 28,0Y | C19: 0.1 | D19: ml | E19: =C19 -> 0.1 | F19: 70000 | G19: ml | H19: =E19*F19 -> 7000
B20: n-HexaneTehcnis | C20: 0.5 | D20: liter | E20: =C20 -> 0.5 | F20: 19300 | G20: liter | H20: =E20*F20 -> 9650
B21: p-Anisidine | C21: =48/357 -> 0.13445378 | D21: gr | E21: =C21 -> 0.13445378 | F21: 7600 | G21: gr | H21: =E21*F21 -> 1021.8487
B22: Wijs Solution | C22: 120 | D22: ml | E22: =C22 -> 120 | F22: 502 | G22: ml | H22: =E22*F22 -> 60240
B23: N2 (UHP) gas refill for GC & Foam test | C23: 0.02 | D23: Liter | E23: =C23 -> 0.02 | F23: 5000000 | G23: Liter | H23: =E23*F23 -> 100000
B24: H2 (UHP) gas refill for GC | C24: 0.03 | D24: Liter | E24: =C24 -> 0.03 | F24: 2500000 | G24: Liter | H24: =E24*F24 -> 75000
B25: UT (UHP) gas refill for GC | C25: 0.03 | D25: Liter | E25: =C25 -> 0.03 | F25: 1250000 | G25: Liter | H25: =E25*F25 -> 37500
B26: Zinc Oksida GR | C26: =179/357 -> 0.50140056 | D26: gr | E26: =C26 -> 0.50140056 | F26: 2000 | G26: gr | H26: =E26*F26 -> 1002.8011
B27: Potassium Dihydrogen Phosphate | C27: =250/357 -> 0.70028011 | D27: gr | E27: =C27 -> 0.70028011 | F27: 765 | G27: gr | H27: =E27*F27 -> 535.71429
B28: Pottasium Hydrogen Phtalate | C28: =250/357 -> 0.70028011 | D28: gr | E28: =C28 -> 0.70028011 | F28: 5200 | G28: gr | H28: =E28*F28 -> 3641.4566
B29: Sodium Thiosulphate | C29: =6069/357 -> 17 | D29: gr | E29: =C29 -> 17 | F29: 950 | G29: gr | H29: =E29*F29 -> 16150
B30: Potassium Iodide | C30: 12 | D30: gr | E30: =C30 -> 12 | F30: 2400 | G30: gr | H30: =E30*F30 -> 28800
B31: Pottasium Dichromate | C31: =357/357 -> 1 | D31: gr | E31: =C31 -> 1 | F31: 4200 | G31: gr | H31: =E31*F31 -> 4200
B32: Sodium Hydroxide | C32: =6069/357 -> 17 | D32: gr | E32: =C32 -> 17 | F32: 700 | G32: gr | H32: =E32*F32 -> 11900
B33: Sub Total | H33: =SUM(H6:H32) -> 745255.21
B35: Consumable Item | C35: Norma | E35: Consumption/day | F35: Unit Price | H35: Total Price
H36: Per Day
B37: Chemical Boiler & WTP
B38: Sodium Molybdate | C38: =286/357 -> 0.80112045 | D38: gr | E38: =C38 -> 0.80112045 | F38: 4000 | G38: gr | H38: =E38*F38 -> 3204.4818
B39: Iron test 0.0025 - 5.00 mg/l | C39: =1785/357 -> 5 | D39: Test | E39: =C39 -> 5 | F39: 10100 | G39: Test | H39: =E39*F39 -> 50500
B40: Phosphate Test 0.5 - 30 mg/l PO4-P | C40: =714/357 -> 2 | D40: pcs | E40: =C40 -> 2 | F40: 8160 | G40: pcs | H40: =E40*F40 -> 16320
B41: Sulfite Test 1,0-60,0 mg/l SO3 | C41: =360/357 -> 1.0084034 | D41: Pcs | E41: =C41 -> 1.0084034 | F41: 26550 | G41: Pcs | H41: =E41*F41 -> 26773.109
B42: Silica Test 0-800 mg/L | C42: =714/357 -> 2 | D42: pcs | E42: =C42 -> 2 | F42: 31700 | G42: pcs | H42: =E42*F42 -> 63400
B43: Silicate (Silicic Acid) 0,3-10 mg/L | C43: 2.5 | D43: pcs | E43: =C43 -> 2.5 | F43: 31006 | G43: pcs | H43: =E43*F43 -> 77515
B44: Ammonium Vanadate | C44: =179/357 -> 0.50140056 | D44: gr | E44: =C44 -> 0.50140056 | F44: 11950 | G44: gr | H44: =E44*F44 -> 5991.7367
B45: Ammonium Chloride | C45: =214/357 -> 0.59943978 | D45: gr | E45: =C45 -> 0.59943978 | F45: 2545 | G45: gr | H45: =E45*F45 -> 1525.5742
B46: Ammonium Hidroksida | C46: =1714/357 -> 4.8011204 | D46: mL | E46: =C46 -> 4.8011204 | F46: 930 | G46: mL | H46: =E46*F46 -> 4465.042
B47: Mg EDTA | C47: =71/357 -> 0.19887955 | D47: gr | E47: =C47 -> 0.19887955 | F47: 21050 | G47: gr | H47: =E47*F47 -> 4186.4146
B48: Pottasium Carbonat | C48: =12/357 -> 0.033613445 | D48: gr | E48: =C48 -> 0.033613445 | F48: 12500 | G48: gr | H48: =E48*F48 -> 420.16807
B49: Trietanolamin | C49: 0.08 | D49: mL | E49: =C49 -> 0.08 | F49: 8160 | G49: mL | H49: =E49*F49 -> 652.8
B50: Indikator EBT | C50: =12/357 -> 0.033613445 | D50: gr | E50: =C50 -> 0.033613445 | F50: 23400 | G50: gr | H50: =E50*F50 -> 786.55462
B51: Indikator Calcon | C51: =12/357 -> 0.033613445 | D51: gr | E51: =C51 -> 0.033613445 | F51: 50800 | G51: gr | H51: =E51*F51 -> 1707.563
B52: Hydroxylammonium Chloride GR | C52: 0.08 | D52: gr | E52: =C52 -> 0.08 | F52: 6250 | G52: gr | H52: =E52*F52 -> 500
B53: Eriocrom Black T-Metal | C53: 0.05 | D53: gr | E53: =C53 -> 0.05 | F53: 24260 | G53: gr | H53: =E53*F53 -> 1213
B54: Sub Total | H54: =SUM(H38:H53) -> 259161.44
B56: Consumable Item | C56: Norma | E56: Consumption/day | F56: Unit Price | H56: Total Price
H57: Per Day
B58: Chemical WWTP
B59: COD cell test 50 - 500 mg/l | C59: =59/357 -> 0.16526611 | D59: pcs | E59: =C59 -> 0.16526611 | F59: 82000 | G59: pcs | H59: =E59*F59 -> 13551.821
B60: COD cell test 500 - 10000 mg/l | C60: =59/357 -> 0.16526611 | D60: pcs | E60: =C60 -> 0.16526611 | F60: 82000 | G60: pcs | H60: =E60*F60 -> 13551.821
B61: Sub Total | H61: =SUM(H59:H60) -> 27103.641
B63: Total keseluruhan | H63: =H61+H54+H33 -> 1031520.3
C67: Spere Part Laboratorium
B68: No | C68: Consumable Item | D68: Norma | F68: Consumption/day | G68: Unit Price | I68: Total Price
I69: Per Day
B70: 1 | C70: Batang pengaduk | D70: 12 | E70: Pcs/Tahun | F70: =D70/357 -> 0.033613445 | G70: 35000 | H70: Rp/Pcs | I70: =F70*G70 -> 1176.4706
B71: =B70+1 -> 2 | C71: Beaker glass 100 mL | D71: 72 | E71: Pcs/Tahun | F71: =D71/357 -> 0.20168067 | G71: 48000 | H71: Rp/Pcs | I71: =F71*G71 -> 9680.6723
B72: =B71+1 -> 3 | C72: Beaker glass 500 mL | D72: 12 | E72: Pcs/Tahun | F72: =D72/357 -> 0.033613445 | G72: 100000 | H72: Rp/Pcs | I72: =F72*G72 -> 3361.3445
B73: =B72+1 -> 4 | C73: Beaker glass 1000 mL | D73: 6 | E73: Pcs/Tahun | F73: =D73/357 -> 0.016806723 | G73: 120000 | H73: Rp/Pcs | I73: =F73*G73 -> 2016.8067
B74: =B73+1 -> 5 | C74: Beaker glass 2000 mL | D74: 6 | E74: Pcs/Tahun | F74: =D74/357 -> 0.016806723 | G74: 142000 | H74: Rp/Pcs | I74: =F74*G74 -> 2386.5546
B75: =B74+1 -> 6 | C75: Beaker Plastik with handle 1000 mL | D75: 6 | E75: Pcs/Tahun | F75: =D75/357 -> 0.016806723 | G75: 70000 | H75: Rp/Pcs | I75: =F75*G75 -> 1176.4706
B76: =B75+1 -> 7 | C76: Boiling Round Bottom Flask 250 mL | D76: 6 | E76: Pcs/Tahun | F76: =D76/357 -> 0.016806723 | G76: 180000 | H76: Rp/Pcs | I76: =F76*G76 -> 3025.2101
B77: =B76+1 -> 8 | C77: Boiling Round Bottom Flask 1000 mL IKA | D77: 2 | E77: Pcs/Tahun | F77: =D77/357 -> 0.0056022409 | G77: 350000 | H77: Rp/Pcs | I77: =F77*G77 -> 1960.7843
B78: =B77+1 -> 9 | C78: Rotary flask 1000 mL IKA | D78: 2 | E78: Pcs/Tahun | F78: =D78/357 -> 0.0056022409 | G78: 350000 | H78: Rp/Pcs | I78: =F78*G78 -> 1960.7843
B79: =B78+1 -> 10 | C79: Corong 75 mm | D79: 6 | E79: Pcs/Tahun | F79: =D79/357 -> 0.016806723 | G79: 75000 | H79: Rp/Pcs | I79: =F79*G79 -> 1260.5042
B80: =B79+1 -> 11 | C80: Erlenmeyer 250 mL | D80: 72 | E80: Pcs/Tahun | F80: =D80/357 -> 0.20168067 | G80: 90000 | H80: Rp/Pcs | I80: =F80*G80 -> 18151.261
B81: =B80+1 -> 12 | C81: Filtering Flask 500 mL | D81: 2 | E81: Pcs/Tahun | F81: =D81/357 -> 0.0056022409 | G81: 400000 | H81: Rp/Pcs | I81: =F81*G81 -> 2240.8964
B82: =B81+1 -> 13 | C82: Gelas ukur 100 mL | D82: 2 | E82: Pcs/Tahun | F82: =D82/357 -> 0.0056022409 | G82: 85000 | H82: Rp/Pcs | I82: =F82*G82 -> 476.19048
... B110: =B109+1 -> 41 | C110: Magnetic Stirer 8 cm | D110: 12 | E110: Pcs/Tahun | F110: =D110/357 -> 0.033613445 | G110: 85000 | H110: Rp/Pcs | I110: =F110*G110 -> 2857.1429
G111: Total Cost/Days | I111: =SUM(I70:I110) -> 135770.31

Sheet genset
B2: Warming Up Genset
B3: Consumable Item | C3: Norma | E3: Consumption/day | F3: Unit Price | H3: Total Cost | K3: PLN - Power Unit Price
B4: Genset Warming Up | D4: kW/Jam | E4: 0 | H4: Rp/day | K4: Consumable Item | L4: Unit Price
B5: Solar | H5: 0 | K5: PLN Fee | L5: 1550 | M5: Rp/kWh
B6: Genset - 1 (1044 kW) | C6: 100 | D6: Ltr/Jam | E6: =(C6*25%*4)/30 -> 3.3333333 | F6: 14500 | G6: Rp/ltr | H6: =F6*E6 -> 48333.333
B7: Genset - 2 (1044 kW) | C7: 100 | D7: Ltr/Jam | E7: =(C7*25%*4)/30 -> 3.3333333 | F7: 14500 | G7: Rp/ltr | H7: =F7*E7 -> 48333.333
B8: Genset - 3 (1044 kW) | C8: 100 | D8: Ltr/Jam | E8: =(C8*25%*4)/30 -> 3.3333333 | F8: 14500 | G8: Rp/ltr | H8: =F8*E8 -> 48333.333
B9: Preventive Maintenance | D9: Rp/day | H9: 0
B10: Cost Power by Genset | H10: =SUM(H5:H9) -> 145000
B12: Genset - Power Unit Price
B13: Consumable Item | C13: Norma | E13: Power, kW/day | F13: Unit Price | H13: Total Cost
B14: Power Production by Genset | C14: 2088 | D14: kW/Jam | E14: =C14*24 -> 50112 | H14: Rp/day
B15: Solar | H15: 0
B16: Genset - 1 (1044 kW) | C16: 800 | D16: Ltr/Jam | E16: =C16*24 -> 19200 | F16: 14500 | G16: Rp/ltr | H16: =F16*E16 -> 278400000
B17: Genset - 2 (1044 kW) | C17: 800 | D17: Ltr/Jam | E17: =C17*24 -> 19200 | F17: 14500 | G17: Rp/ltr | H17: =F17*E17 -> 278400000
B18: Genset - 3 (1044 kW) | D18: Ltr/Jam | E18: 0 | F18: 14500 | G18: Rp/ltr | H18: =F18*E18 -> 0
B19: Preventive Maintenance | D19: Rp/day | H19: 0
B20: Cost Power by Genset | H20: =SUM(H15:H19) -> 556800000
F21: Unit Price, Rp/Kw | H21: =H20/E14 -> 11111.111 | I21: Unit price terlalu tinggi
B23: Note :
B24: 1. Cross cek kembali consumption solar genset per unit

Sheet AMOR
B2: Amortization
B3: Through Put CPO Proses | H3: TPD | I3: ='HPP REF '!N3 -> 2006.269
B4: Working Day | H4: Day | I4: ='HPP REF '!N4 -> 20
B5: Total CPO Refined | H5: TPM | I5: =I4*I3 -> 40125.38
B6: Kurs Rupiah | I6: 16000
B7: No | C7: Description | D7: Actual 2023 | F7: Budget 2024
D8: Years | E8: Month | F8: Years | G8: Month | H8: RP/KG | I8: USD/MT
B9: 1 | C9: Perangkat Lunak/Software | D9: 9.6270931e+08 | E9: =D9/12 -> 80225776 | F9: =G9*12 -> 5.3192735e+08 | G9: 44327279 | H9: =$G$9/($I$5*1000) -> 1.1047192 | I9: =($G$9/$I$6)/$I$5 -> 0.069044952 | J9: =D9/12 -> 80225776
B10: =B9+1 -> 2 | C10: Sertifikat/Surat Izin | D10: 2.6961444e+08 | E10: =D10/12 -> 22467870 | F10: 0 | G10: 0 | H10: =$G$10/($I$5*1000) -> 0 | I10: =($G$10/$I$6)/$I$5 -> 0
B11: =B10+1 -> 3 | C11: Inventaris Kecil (Aset Sewa) | D11: 0 | E11: =D11/12 -> 0 | F11: 0 | G11: 0 | H11: =$G$11/($I$5*1000) -> 0 | I11: =($G$11/$I$6)/$I$5 -> 0
B12: =B11+1 -> 4 | C12: Aset Hak Guna (ROU) - Kendaraan | D12: 0 | E12: =D12/12 -> 0 | F12: 0 | G12: 0 | H12: =$G$12/($I$5*1000) -> 0 | I12: =($G$12/$I$6)/$I$5 -> 0
B13: =B12+1 -> 5 | C13: Aset Hak Guna (ROU) - Tangki Timbun | D13: 0 | E13: =D13/12 -> 0 | F13: 0 | G13: 0 | H13: =$G$13/($I$5*1000) -> 0 | I13: =($G$13/$I$6)/$I$5 -> 0
B14: =B13+1 -> 6 | C14: Aset Atas Biaya Penyambungan | D14: 0 | E14: =D14/12 -> 0 | F14: 0 | G14: 0 | H14: =$G$14/($I$5*1000) -> 0 | I14: =($G$14/$I$6)/$I$5 -> 0
B15: =B14+1 -> 7 | C15: Aset Hak Guna (ROU) - Pemanfaatan Lahan Sei Mangkei + Surabaya | D15: 1.2576903e+10 | E15: =D15/12 -> 1.0480752e+09 | F15: =G15*12 -> 12048990312 | G15: 1004082526 | H15: =$G$15/($I$5*1000) -> 25.023627 | I15: =($G$15/$I$6)/$I$5 -> 1.5639767
B20: Total Cost Depreciation | D20: =SUM(D9:D19) -> 1.3809227e+10 | E20: =SUM(E9:E19) -> 1.1507689e+09 | F20: =SUM(F9:F19) -> 1.2580918e+10 | G20: =SUM(G9:G19) -> 1.0484098e+09 | H20: =SUM(H9:H19) -> 26.128346 | I20: =SUM(I9:I19) -> 1.6330216

Sheet DEP
B2: Depreciation
B3: Through Put CPO Proses | J3: TPD | K3: ='HPP REF '!N3 -> 2006.269
B4: Working Day | J4: Day | K4: ='HPP REF '!N4 -> 20
B5: Total CPO Refined | J5: TPM | K5: =K4*K3 -> 40125.38
B6: Kurs Rupiah | K6: 16000
B7: No | C7: Description | D7: Actual 2023 (Audited) | G7: Budget 2024
D8: Asset | E8: Years | F8: Month | G8: Asset | H8: Years | I8: Month | J8: RP/KG | K8: USD/MT
B9: Total Cost Depreciation | D9: =SUM(D10:D75) -> 6.7971213e+11 | E9: =SUM(E10:E75) -> 4.1807174e+10 | F9: =SUM(F10:F75) -> 3.4839312e+09 | G9: =SUM(G10:G75) -> 7.7503139e+11 | H9: =SUM(H10:H75) -> 5.0174217e+10 | I9: =SUM(I10:I75) -> 4.1811848e+09 | J9: =SUM(J10:J75) -> 104.203 | K9: =SUM(K10:K75) -> 6.5126872
B10: 1 | C10: Front Office + Canteen | D10: 3844320790 | E10: 1.9221604e+08 | F10: 16018003 | G10: 3.8443208e+09 | H10: =I10*12 -> 1.9221604e+08 | I10: 16018003 | J10: =$I$10/($K$5*1000) -> 0.39919879 | K10: =($I$10/$K$6)/$K$5 -> 0.024949925
B11: =B10+1 -> 2 | C11: Bea Cukai Building | D11: 247144032 | E11: 12357202 | F11: 1029766.8 | G11: 2.4714403e+08 | H11: =I11*12 -> 12357202 | I11: 1029766.8 | J11: =$I$11/($K$5*1000) -> 0.025663727 | K11: =($I$11/$K$6)/$K$5 -> 0.0016039829
B12: =B11+1 -> 3 | C12: Security Building | D12: 199088248 | E12: 12429395 | F12: 1035782.9 | G12: 3.9708686e+08 | H12: =I12*12 -> 19854343 | I12: 1654528.6 | J12: =$I$12/($K$5*1000) -> 0.041233967 | K12: =($I$12/$K$6)/$K$5 -> 0.0025771229
B13: =B12+1 -> 4 | C13: Bangunan Shelter / Pelataran | D13: 53111657402 | E13: 2.6555829e+09 | F13: 2.2129857e+08 | G13: 5.3111657e+10 | H13: =I13*12 -> 2.6555829e+09 | I13: 2.2129857e+08 | J13: =$I$13/($K$5*1000) -> 5.515177 | K13: =($I$13/$K$6)/$K$5 -> 0.34469856
B14: =B13+1 -> 5 | C14: Laboratorium Building | D14: 1.3920764e+09 | E14: 70956822 | F14: 5913068.5 | G14: 1.5003164e+09 | H14: =I14*12 -> 75015820 | I14: 6251318.3 | J14: =$I$14/($K$5*1000) -> 0.15579462 | K14: =($I$14/$K$6)/$K$5 -> 0.0097371637
B15: =B14+1 -> 6 | C15: Refinery Room | D15: 22378266872 | E15: 1.1189133e+09 | F15: 93242779 | G15: 2.2378267e+10 | H15: =I15*12 -> 1.1189133e+09 | I15: 93242779 | J15: =$I$15/($K$5*1000) -> 2.3237856 | K15: =($I$15/$K$6)/$K$5 -> 0.1452366
B16: =B15+1 -> 7 | C16: Fractionation Room | D16: 22378266872 | E16: 1.1189133e+09 | F16: 93242779 | G16: 2.2378267e+10 | H16: =I16*12 -> 1.1189133e+09 | I16: 93242779 | J16: =$I$16/($K$5*1000) -> 2.3237856 | K16: =($I$16/$K$6)/$K$5 -> 0.1452366
B17: =B16+1 -> 8 | C17: Utility Building | D17: 22548996820 | E17: 1.1274498e+09 | F17: 93954153 | G17: 2.2548997e+10 | H17: =I17*12 -> 1.1274498e+09 | I17: 93954153 | J17: =$I$17/($K$5*1000) -> 2.3415144 | K17: =($I$17/$K$6)/$K$5 -> 0.14634465
B18: =B17+1 -> 9 | C18: Power House & Electrical Building | D18: 3242778116 | E18: 1.6663346e+08 | F18: 13886122 | G18: 3.6023423e+09 | H18: =I18*12 -> 1.8011712e+08 | I18: 15009760 | J18: =$I$18/($K$5*1000) -> 0.37407147 | K18: =($I$18/$K$6)/$K$5 -> 0.023379467
B19: =B18+1 -> 10 | C19: Weight Bridge Building (Timbangan) | D19: 3.0883582e+09 | E19: 1.6798762e+08 | F19: 13998968 | G19: 4.173935e+09 | H19: =I19*12 -> 2.0869675e+08 | I19: 17391396 | J19: =$I$19/($K$5*1000) -> 0.43342632 | K19: =($I$19/$K$6)/$K$5 -> 0.027089145
B20: =B19+1 -> 11 | C20: Warehouse TPS Spent Earth | D20: 1.3067146e+09 | E20: 65335728 | F20: 5444644 | G20: 1.3067146e+09 | H20: =I20*12 -> 65335728 | I20: 5444644 | J20: =$I$20/($K$5*1000) -> 0.13569078 | K20: =($I$20/$K$6)/$K$5 -> 0.0084806736
B21: =B20+1 -> 12 | C21: Bangunan Shelter / Pelataran | D21: 0 | E21: 0 | F21: 0 | G21: 0 | H21: =I21*12 -> 0 | I21: 0 | J21: =$I$21/($K$5*1000) -> 0 | K21: =($I$21/$K$6)/$K$5 -> 0
B22: =B21+1 -> 13 | C22: Packaging Building | D22: 26865966199 | E22: 1.3432983e+09 | F22: 1.1194153e+08 | G22: 2.6865966e+10 | H22: =I22*12 -> 1.895783e+09 | I22: 1.5798192e+08 | J22: =$I$22/($K$5*1000) -> 3.9372068 | K22: =($I$22/$K$6)/$K$5 -> 0.24607543
B23: =B22+1 -> 14 | C23: Warehouse TPS Limbah B3 | D23: 808088751 | E23: 52164853 | F23: 4347071.1 | G23: 1.748922e+09 | H23: =I23*12 -> 87446098 | I23: 7287174.8 | J23: =$I$23/($K$5*1000) -> 0.18161011 | K23: =($I$23/$K$6)/$K$5 -> 0.011350632
B24: =B23+1 -> 15 | C24: Panel Room Loading - Unloading | D24: 669445527 | E24: 33472276 | F24: 2789356.4 | G24: 6.6944553e+08 | H24: =I24*12 -> 33472276 | I24: 2789356.4 | J24: =$I$24/($K$5*1000) -> 0.069516011 | K24: =($I$24/$K$6)/$K$5 -> 0.0043447507
B25: =B24+1 -> 16 | C25: Bangunan Shelter / Pelataran | D25: 0 | E25: 0 | F25: 0 | G25: 0 | H25: =I25*12 -> 0 | I25: 0 | J25: =$I$25/($K$5*1000) -> 0 | K25: =($I$25/$K$6)/$K$5 -> 0
B26: =B25+1 -> 17 | C26: Kantor RO Medan | D26: 35739000 | E26: 3573900 | F26: 297825 | G26: 35739000 | H26: =I26*12 -> 3573900 | I26: 297825 | J26: =$I$26/($K$5*1000) -> 0.0074223596 | K26: =($I$26/$K$6)/$K$5 -> 0.00046389748
B27: =B26+1 -> 18 | C27: Gedung Logistic | D27: 537402145 | E27: 26870107 | F27: 2239175.6 | G27: 537402145 | H27: =I27*12 -> 26870107 | I27: 2239175.6 | J27: =$I$27/($K$5*1000) -> 0.055804471 | K27: =($I$27/$K$6)/$K$5 -> 0.0034877794
B28: =B27+1 -> 19 | C28: Ruang Expansi Filling Packaging | D28: 1071796228 | E28: 26794906 | F28: 2232908.8 | G28: 1071796228 | H28: =I28*12 -> 53589811 | I28: 4465817.6 | J28: =$I$28/($K$5*1000) -> 0.11129658 | K28: =($I$28/$K$6)/$K$5 -> 0.0069560363
B29: =B28+1 -> 20 | C29: Bangunan Lainnya | D29: 236594750 | E29: 67601093 | F29: 5633424.5 | G29: 3.7519242e+09 | H29: =I29*12 -> 1.9942595e+08 | I29: 16618829 | J29: =$I$29/($K$5*1000) -> 0.4141725 | K29: =($I$29/$K$6)/$K$5 -> 0.025885781
B30: =B29+1 -> 21 | C30: Power House System | D30: 30414179484 | E30: 1.6120305e+09 | F30: 1.3433587e+08 | G30: 3.0414179e+10 | H30: =I30*12 -> 1.7106159e+09 | I30: 1.4255132e+08 | J30: =$I$30/($K$5*1000) -> 3.5526473 | K30: =($I$30/$K$6)/$K$5 -> 0.22204046
B31: =B30+1 -> 22 | C31: Reception from Road Tanker System | D31: 15714477178 | E31: 1.5906981e+09 | F31: 1.3255817e+08 | G31: 1.5714477e+10 | H31: =I31*12 -> 1.6892835e+09 | I31: 1.4077362e+08 | J31: =$I$31/($K$5*1000) -> 3.5083437 | K31: =($I$31/$K$6)/$K$5 -> 0.21927148
B32: =B31+1 -> 23 | C32: Reception & CPO Storage Tank System | D32: 3.9160256e+10 | E32: 1.8156968e+09 | F32: 1.5130807e+08 | G32: 3.9160256e+10 | H32: =I32*12 -> 1.9142822e+09 | I32: 1.5952352e+08 | J32: =$I$32/($K$5*1000) -> 3.9756264 | K32: =($I$32/$K$6)/$K$5 -> 0.24847665
B33: =B32+1 -> 24 | C33: Refinery Product System | D33: 26158484525 | E33: 1.546139e+09 | F33: 1.2884492e+08 | G33: 2.6158485e+10 | H33: =I33*12 -> 2.1043359e+09 | I33: 1.7536132e+08 | J33: =$I$33/($K$5*1000) -> 4.3703343 | K33: =($I$33/$K$6)/$K$5 -> 0.27314589
B34: =B33+1 -> 25 | C34: Fractionation Product System | D34: 44700543389 | E34: 2.5257813e+09 | F34: 2.1048177e+08 | G34: 4.4700543e+10 | H34: =I34*12 -> 2.6243667e+09 | I34: 2.1869722e+08 | J34: =$I$34/($K$5*1000) -> 5.4503465 | K34: =($I$34/$K$6)/$K$5 -> 0.34064665
B35: =B34+1 -> 26 | C35: Compressed Air System | D35: 12406716786 | E35: 6.9726354e+08 | F35: 58105295 | G35: 1.2406717e+10 | H35: =I35*12 -> 6.9726354e+08 | I35: 58105295 | J35: =$I$35/($K$5*1000) -> 1.4480933 | K35: =($I$35/$K$6)/$K$5 -> 0.090505833
B36: =B35+1 -> 27 | C36: Fuel Distribution System | D36: 2279256408 | E36: 1.6844371e+08 | F36: 14036976 | G36: 2.2792564e+09 | H36: =I36*12 -> 2.0366838e+08 | I36: 16972365 | J36: =$I$36/($K$5*1000) -> 0.42298329 | K36: =($I$36/$K$6)/$K$5 -> 0.026436456
B37: =B36+1 -> 28 | C37: Waste Water Treatment System | D37: 8173671310 | E37: 5.0165483e+08 | F37: 41804569 | G37: 8.1736713e+09 | H37: =I37*12 -> 5.1840723e+08 | I37: 43200602 | J37: =$I$37/($K$5*1000) -> 1.0766403 | K37: =($I$37/$K$6)/$K$5 -> 0.06729002
B38: =B37+1 -> 29 | C38: Clean Water System | D38: 8.1369458e+09 | E38: 4.697884e+08 | F38: 39149033 | G38: 8.1369458e+09 | H38: =I38*12 -> 4.697884e+08 | I38: 39149033 | J38: =$I$38/($K$5*1000) -> 0.97566759 | K38: =($I$38/$K$6)/$K$5 -> 0.060979225
B39: =B38+1 -> 30 | C39: Demin Water Distribution System | D39: 5554219736 | E39: 3.7021373e+08 | F39: 30851144 | G39: 5.5542197e+09 | H39: =I39*12 -> 3.7021373e+08 | I39: 30851144 | J39: =$I$39/($K$5*1000) -> 0.76886858 | K39: =($I$39/$K$6)/$K$5 -> 0.048054286
B40: =B39+1 -> 31 | C40: Steam Generation System | D40: 28411905935 | E40: 1.6009903e+09 | F40: 1.3341586e+08 | G40: 2.8411906e+10 | H40: =I40*12 -> 1.6009903e+09 | I40: 1.3341586e+08 | J40: =$I$40/($K$5*1000) -> 3.3249743 | K40: =($I$40/$K$6)/$K$5 -> 0.20781089 | L40: =H40/12 -> 1.3341586e+08
B41: =B40+1 -> 32 | C41: Cooling Water Distribution System | D41: 8813632097 | E41: 5.5719688e+08 | F41: 46433074 | G41: 8.8136321e+09 | H41: =I41*12 -> 5.5719688e+08 | I41: 46433074 | J41: =$I$41/($K$5*1000) -> 1.1571996 | K41: =($I$41/$K$6)/$K$5 -> 0.072324975
B42: =B41+1 -> 33 | C42: Fire Water System | D42: 4990631887 | E42: 3.5991574e+08 | F42: 29992978 | G42: 4.9906319e+09 | H42: =I42*12 -> 3.5991574e+08 | I42: 29992978 | J42: =$I$42/($K$5*1000) -> 0.74748147 | K42: =($I$42/$K$6)/$K$5 -> 0.046717592
B43: =B42+1 -> 34 | C43: Dual Fuel Emergency Generator | D43: 11752092639 | E43: 6.1186193e+08 | F43: 50988494 | G43: 1.1752093e+10 | H43: =I43*12 -> 6.1186193e+08 | I43: 50988494 | J43: =$I$43/($K$5*1000) -> 1.2707293 | K43: =($I$43/$K$6)/$K$5 -> 0.079420579
B44: =B43+1 -> 35 | C44: Steam Distribution & Condensate Recovery System | D44: 9891619567 | E44: 8.9987659e+08 | F44: 74989716 | G44: 9.8916196e+09 | H44: =I44*12 -> 8.9987659e+08 | I44: 74989716 | J44: =$I$44/($K$5*1000) -> 1.8688849 | K44: =($I$44/$K$6)/$K$5 -> 0.11680531
B45: =B44+1 -> 36 | C45: Fire Water Main Ring System | D45: 4518985787 | E45: 2.4463794e+08 | F45: 20386495 | G45: 4.5189858e+09 | H45: =I45*12 -> 2.4463794e+08 | I45: 20386495 | J45: =$I$45/($K$5*1000) -> 0.50806983 | K45: =($I$45/$K$6)/$K$5 -> 0.031754364
B46: =B45+1 -> 37 | C46: Packaging System | D46: 34206697993 | E46: 3.1394346e+09 | F46: 2.6161955e+08 | G46: 1.2163436e+11 | H46: =I46*12 -> 7.8746236e+09 | I46: 6.5621863e+08 | J46: =$I$46/($K$5*1000) -> 16.354204 | K46: =($I$46/$K$6)/$K$5 -> 1.0221377
B47: =B46+1 -> 38 | C47: Refinery System | D47: 93804025615 | E47: 6.3108388e+09 | F47: 5.2590324e+08 | G47: 9.3804026e+10 | H47: =I47*12 -> 6.3327722e+09 | I47: 5.2773101e+08 | J47: =$I$47/($K$5*1000) -> 13.15205 | K47: =($I$47/$K$6)/$K$5 -> 0.82200314
B48: =B47+1 -> 39 | C48: Fractionation System | D48: 69305898501 | E48: 4.7141422e+09 | F48: 3.9284518e+08 | G48: 6.9305899e+10 | H48: =I48*12 -> 4.7141422e+09 | I48: 3.9284518e+08 | J48: =$I$48/($K$5*1000) -> 9.7904415 | K48: =($I$48/$K$6)/$K$5 -> 0.61190259
B49: =B48+1 -> 40 | C49: Fat Pit System | D49: 1222833568 | E49: 76427098 | F49: 6368924.8 | G49: 1.2228336e+09 | H49: =I49*12 -> 76427098 | I49: 6368924.8 | J49: =$I$49/($K$5*1000) -> 0.1587256 | K49: =($I$49/$K$6)/$K$5 -> 0.0099203497
B50: =B49+1 -> 41 | C50: Weight Bridge | D50: 2557397646 | E50: 1.2786988e+08 | F50: 10655824 | G50: 2.5573976e+09 | H50: =I50*12 -> 1.2786988e+08 | I50: 10655824 | J50: =$I$50/($K$5*1000) -> 0.26556318 | K50: =($I$50/$K$6)/$K$5 -> 0.016597699
B51: =B50+1 -> 42 | C51: Mesin Dan Perlengkapan Pabrik | D51: 30580769059 | E51: 1.6581493e+09 | F51: 1.3817911e+08 | G51: 3.0797884e+10 | H51: =I51*12 -> 2.8889928e+09 | I51: 2.407494e+08 | J51: =$I$51/($K$5*1000) -> 5.9999282 | K51: =($I$51/$K$6)/$K$5 -> 0.37499551
B52: =B51+1 -> 43 | C52: Installation System Electrical (Auxiliary) | D52: 2460303143 | E52: 1.5376895e+08 | F52: 12814079 | G52: 2460303143 | H52: =I52*12 -> 1.5376895e+08 | I52: 12814079 | J52: =$I$52/($K$5*1000) -> 0.31935097 | K52: =($I$52/$K$6)/$K$5 -> 0.019959435
B53: =B52+1 -> 44 | C53: Mesin Dan Perlengkapan Pabrik | D53: 0 | E53: 0 | F53: 0 | G53: 0 | H53: =I53*12 -> 0 | I53: 0 | J53: =$I$53/($K$5*1000) -> 0 | K53: =($I$53/$K$6)/$K$5 -> 0
B54: =B53+1 -> 45 | C54: Mesin Dan Perlengkapan Pabrik | D54: 0 | E54: 0 | F54: 0 | G54: 0 | H54: =I54*12 -> 0 | I54: 0 | J54: =$I$54/($K$5*1000) -> 0 | K54: =($I$54/$K$6)/$K$5 -> 0
B55: =B54+1 -> 46 | C55: Refinery Product System | D55: 0 | E55: 0 | F55: 0 | G55: 0 | H55: =I55*12 -> 0 | I55: 0 | J55: =$I$55/($K$5*1000) -> 0 | K55: =($I$55/$K$6)/$K$5 -> 0
B56: =B55+1 -> 47 | C56: Perlengkapan Pabrik Lainnya | D56: 814629325 | E56: 1.3842046e+08 | F56: 11535038 | G56: 814629325 | H56: =I56*12 -> 1.3842046e+08 | I56: 11535038 | J56: =$I$56/($K$5*1000) -> 0.28747487 | K56: =($I$56/$K$6)/$K$5 -> 0.017967179
B57: =B56+1 -> 48 | C57: Bangunan Shelter / Pelataran | D57: 0 | E57: 0 | F57: 0 | G57: 0 | H57: =I57*12 -> 0 | I57: 0 | J57: =$I$57/($K$5*1000) -> 0 | K57: =($I$57/$K$6)/$K$5 -> 0
B58: =B57+1 -> 49 | C58: Saluran Drainase | D58: 3324550757 | E58: 1.6622754e+08 | F58: 13852295 | G58: 3.3245508e+09 | H58: =I58*12 -> 1.6622754e+08 | I58: 13852295 | J58: =$I$58/($K$5*1000) -> 0.34522526 | K58: =($I$58/$K$6)/$K$5 -> 0.021576579
B59: =B58+1 -> 50 | C59: Fence | D59: 1457273906 | E59: 72863695 | F59: 6071974.6 | G59: 1457273906 | H59: =I59*12 -> 72863695 | I59: 6071974.6 | J59: =$I$59/($K$5*1000) -> 0.15132504 | K59: =($I$59/$K$6)/$K$5 -> 0.0094578148
B60: =B59+1 -> 51 | C60: Bangunan Shelter / Pelataran | D60: 0 | E60: 0 | F60: 0 | G60: 0 | H60: =I60*12 -> 0 | I60: 0 | J60: =$I$60/($K$5*1000) -> 0 | K60: =($I$60/$K$6)/$K$5 -> 0
B61: =B60+1 -> 52 | C61: Alat Pengangkutan | D61: 702420000 | E61: 58515250 | F61: 4876270.8 | G61: 702420000 | H61: =I61*12 -> 92109000 | I61: 7675750 | J61: =$I$61/($K$5*1000) -> 0.19129414 | K61: =($I$61/$K$6)/$K$5 -> 0.011955884
B62: =B61+1 -> 53 | C62: Perabot & Perlengkapan Kantor | D62: 2093240354 | E62: 2.8749571e+08 | F62: 23957976 | G62: 2093240354 | H62: =I62*12 -> 2.8749571e+08 | I62: 23957976 | J62: =$I$62/($K$5*1000) -> 0.59707786 | K62: =($I$62/$K$6)/$K$5 -> 0.037317366
B63: =B62+1 -> 54 | C63: Perabot dan Perlengkapan Mess | D63: 0 | E63: 0 | F63: 0 | G63: 0 | H63: =I63*12 -> 0 | I63: 0 | J63: =$I$63/($K$5*1000) -> 0 | K63: =($I$63/$K$6)/$K$5 -> 0
B64: =B63+1 -> 55 | C64: Alat & Perlengkapan Pabrik | D64: 68073000 | E64: 13614600 | F64: 1134550 | G64: 68073000 | H64: =I64*12 -> 13614600 | I64: 1134550 | J64: =$I$64/($K$5*1000) -> 0.028275122 | K64: =($I$64/$K$6)/$K$5 -> 0.0017671951
B65: =B64+1 -> 56 | C65: Alat dan Perlengkapan Bengkel | D65: 140550000 | E65: 28110000 | F65: 2342500 | G65: 140550000 | H65: =I65*12 -> 28110000 | I65: 2342500 | J65: =$I$65/($K$5*1000) -> 0.058379509 | K65: =($I$65/$K$6)/$K$5 -> 0.0036487193
B66: =B65+1 -> 57 | C66: Alat dan Perlengkapan Laboratorium | D66: 3453064640 | E66: 3.7398892e+08 | F66: 31165744 | G66: 4405170868 | H66: =I66*12 -> 8.9603417e+08 | I66: 74669514 | J66: =$I$66/($K$5*1000) -> 1.8609049 | K66: =($I$66/$K$6)/$K$5 -> 0.11630655
B67: =B66+1 -> 58 | C67: Alat IT / Komputer | D67: 1542535419 | E67: 2.9444276e+08 | F67: 24536897 | G67: 1.9760604e+09 | H67: =I67*12 -> 2.9825396e+08 | I67: 24854497 | J67: =$I$67/($K$5*1000) -> 0.61942084 | K67: =($I$67/$K$6)/$K$5 -> 0.038713803
B68: =B67+1 -> 59 | C68: Perabot & Perlengkapan Lainnya | D68: 11270000 | E68: 2254000 | F68: 187833.33 | G68: 11270000 | H68: =I68*12 -> 2254000 | I68: 187833.33 | J68: =$I$68/($K$5*1000) -> 0.0046811602 | K68: =($I$68/$K$6)/$K$5 -> 0.00029257251
B69: =B68+1 -> 60 | C69: Aktiva Tetap Non Produktif | D69: 26932688 | E69: 5386537.6 | F69: 448878.13 | G69: 26932688 | H69: =I69*12 -> 5386537.5 | I69: 448878.13 | J69: =$I$69/($K$5*1000) -> 0.011186888 | K69: =($I$69/$K$6)/$K$5 -> 0.00069918049
B70: =B69+1 -> 61 | C70: Totem AKHLAK | D70: 30000000 | E70: 6000000 | F70: 500000 | G70: 30000000 | H70: =I70*12 -> 6000000.1 | I70: 500000.01 | J70: =$I$70/($K$5*1000) -> 0.012460941 | K70: =($I$70/$K$6)/$K$5 -> 0.00077880883
B71: =B70+1 -> 62 | C71: Main Office | D71: 6869341541 | E71: 3.4448348e+08 | F71: 28706957 | G71: 6.9506539e+09 | H71: =I71*12 -> 3.4753269e+08 | I71: 28961058 | J71: =$I$71/($K$5*1000) -> 0.72176408 | K71: =($I$71/$K$6)/$K$5 -> 0.045110255

Sheet MTC
C1: working days | F1: working days
B2: Summary - PM Electrical | C2: ='Januari 2026 PMG 2'!AM6 -> 20 | E2: Summary - PM Mechanical | F2: ='Januari 2026 PMG 2'!AM6 -> 20
B3: Consumable Item | C3: Total Price | E3: Consumable Item | F3: Total Price
C4: Per Day | F4: Per Day
B5: Biaya Pemeliharaan Unit Refinery(Listrik) | C5: 1648879.6 | E5: Biaya Pemeliharaan Unit Refinery | F5: 4911824.3
B6: HP Boiler | C6: 2678431.4 | E6: Biaya Pemeliharaan Unit Fraksinasi | F6: 1230672.3
B7: Dry Fractination - Crystalizer & Filter Press | C7: 288459.38 | E7: Biaya Pemeliharaan Unit Cooling Tower | F7: 1084733.9
B8: Physical Refinery-Bleaching and Deodorization | C8: 404271.71 | E8: Biaya Pemeliharaan Unit Packaging | F8: 833815.52
B9: BOILER | C9: 150891.4 | E9: Biaya Pemeliharaan Unit Material Handling | F9: 949299.72
B10: Water Plant, Effluent & Hydrant | C10: 58543.417 | E10: Biaya Pemeliharaan Unit Utility | F10: 1106022.4
B11: Pump House | C11: 87425.77 | E11: Barang Consumable Maintenance | F11: 5634698.9
B12: DCS-CCR ISBL | C12: 254341.74
B13: Lighting All Area | C13: 114733.89 | E13: Total | F13: =SUM(F5:F12) -> 15751067
B14: Consumable | C14: 203159.66 | E14: Total/Month | F14: =F13*F2 -> 3.1502134e+08
B15: Kalibrasi Instrument Pabrik | C15: 580672.27 | E15: Total/Yearly | F15: =F14*12 -> 3.7802561e+09
B16: Service Special Equipment | C16: 4089635.9
B17: Total/Day | C17: =SUM(C5:C16) -> 10559446 | E17: TOTAL COST
B18: Total/Month | C18: =C17*C2 -> 2.1118892e+08 | E18: PM E + PM M | F18: =F14+C18 -> 5.2621026e+08
B19: Total/Yearly | C19: =C18*12 -> 2.534267e+09 | E19: TOTAL | F19: =F18*12 -> 6.3145231e+09

Sheet LOG
B2: Port Cost Kuala Tanjung
B3: Through Put CPO Proses | J3: TPD | K3: ='HPP REF '!N3 -> 2006.269
B4: Working Day | J4: Day | K4: ='HPP REF '!N4 -> 20
B5: Total CPO Refined | J5: TPM | K5: =K4*K3 -> 40125.38
B6: Kurs Rupiah | K6: 16000
B7: No | C7: Description | G7: Norma | I7: Total Biaya ( Rp ) | J7: RP/KG | K7: USD/MT
B8: 1 | C8: Trucking Komoditi ke Kuala Tanjung | E8: Olein ( Ton ) | F8: =(100%-0.8%-1.1*5%)*80%*K5 -> 30077.985 | G8: Rp/Kg | H8: 90 | I8: =H8*F8*1000 -> 2.7070186e+09 | J8: =I8/($K$5*1000) -> 67.464 | K8: =(I8/$K$6)/$K$5 -> 4.2165
E9: Stearin ( Ton ) Iso Tank | F9: =(100%-0.8%-1.1*5%)*20%*K5 -> 7519.4962 | G9: Rp/Kg | H9: 150 | I9: =H9*F9*1000 -> 1.1279244e+09 | J9: =I9/($K$5*1000) -> 28.11 | K9: =(I9/$K$6)/$K$5 -> 1.756875
E10: PFAD ( Ton ) Iso Tank | F10: =1.1*5%*K5 -> 2206.8959 | G10: Rp/Kg | H10: 150 | I10: =H10*F10*1000 -> 331034385 | J10: =I10/($K$5*1000) -> 8.25 | K10: =(I10/$K$6)/$K$5 -> 0.515625
B11: 2 | C11: Sewa Tank PTI Total Volume : 24.000 MT ( 5 Unit ) | E11: Tank 8.000 MT >> Olein | F11: 1 | G11: Rp/Kg | H11: 77 | I11: =H11*8000*F11*1000 -> 616000000 | J11: =I11/($K$5*1000) -> 15.35188 | K11: =(I11/$K$6)/$K$5 -> 0.95949247
E12: Tank 5.000 MT >> Stearin | F12: 2 | G12: Rp/Kg | H12: 79 | I12: =H12*5000*F12*1000 -> 790000000 | J12: =I12/($K$5*1000) -> 19.688287 | K12: =(I12/$K$6)/$K$5 -> 1.2305179
E13: Tank 3.000 MT >> RBDPO | F13: 1 | G13: Rp/Kg | H13: 77 | I13: =H13*3000*F13*1000 -> 231000000 | J13: =I13/($K$5*1000) -> 5.7569548 | K13: =(I13/$K$6)/$K$5 -> 0.35980968
E14: Tank 3.000 MT S/S >> PFAD | F14: 1 | G14: Rp/Kg | H14: 83 | I14: =H14*3000*F14*1000 -> 249000000 | J14: =I14/($K$5*1000) -> 6.2055487 | K14: =(I14/$K$6)/$K$5 -> 0.38784679
B15: 3 | C15: Finalty Over Capacity dari tank | D15: 0 | E15: Over Volume Olein | F15: =F8-(8000*D15) -> 30077.985 | G15: Rp/Kg | H15: 43 | I15: =H15*F15*1000 -> 1.2933533e+09 | J15: =I15/($K$5*1000) -> 32.2328 | K15: =(I15/$K$6)/$K$5 -> 2.01455
D16: 0 | E16: Over Volume Stearin | F16: =F9-(10000*D16) -> 7519.4962 | G16: Rp/Kg | H16: 43 | I16: =H16*F16*1000 -> 3.2333834e+08 | J16: =I16/($K$5*1000) -> 8.0582 | K16: =(I16/$K$6)/$K$5 -> 0.5036375
D17: 0 | E17: Over Volume PFAD | F17: =F10-(3000*D17) -> 2206.8959 | G17: Rp/Kg | H17: 43 | I17: =H17*F17*1000 -> 94896524 | J17: =I17/($K$5*1000) -> 2.365 | K17: =(I17/$K$6)/$K$5 -> 0.1478125
B18: 3 | C18: Beban Instalasi Pemompaan dan Pemanasan | E18: Total Volume | F18: =SUM(F8:F10) -> 39804.377 | G18: Rp/Kg | H18: 22 | I18: =H18*F18*1000 -> 8.7569629e+08 | J18: =I18/($K$5*1000) -> 21.824 | K18: =(I18/$K$6)/$K$5 -> 1.364
B19: =B18+1 -> 4 | C19: Pompa | E19: Total Volume | F19: =F18 -> 39804.377 | G19: Rp/Kg | H19: 26 | I19: =H19*F18*1000 -> 1.0349138e+09 | J19: =I19/($K$5*1000) -> 25.792 | K19: =(I19/$K$6)/$K$5 -> 1.612
B20: =B19+1 -> 5 | C20: Beban Analisa ( Surveyor ) | E20: Total Volume | F20: =F18 -> 39804.377 | G20: Rp/Kg | H20: 3 | I20: =H20*F20*1000 -> 1.1941313e+08 | J20: =I20/($K$5*1000) -> 2.976 | K20: =(I20/$K$6)/$K$5 -> 0.186
B21: =B20+1 -> 6 | C21: Beban Pelabuhan ( Documen-Documen Pelabuhan ) | E21: Total Volume | F21: =F20 -> 39804.377 | G21: Rp/Kg | H21: 3 | I21: =H21*F21*1000 -> 1.1941313e+08 | J21: =I21/($K$5*1000) -> 2.976 | K21: =(I21/$K$6)/$K$5 -> 0.186
B22: =B21+1 -> 7 | C22: Beban Asuransi (Cost Insurance Freight)
B23: =B22+1 -> 8 | C23: Beban Sewa Kapal
B24: =B23+1 -> 9 | C24: Beban Pengangkutan Di Pelabuhan
B25: Total Biaya Transfer Product ke Kuala Tanjung Port | I25: =SUM(I8:I24) -> 9.913002e+09 | J25: =SUM(J8:J24) -> 247.05067 | K25: =SUM(K8:K24) -> 15.440667

Sheet OH
B2: Overhead ( OH )
B3: Through Put CPO Proses | H3: TPD | I3: ='HPP REF '!N3 -> 2006.269
B4: Working Day | H4: Day | I4: ='SUMMARY HPP '!I4 -> 20
B5: Total CPO Refined | H5: TPM | I5: =I4*I3 -> 40125.38
B6: Kurs Rupiah | I6: 16000
B7: No | C7: Description | D7: Actual 2023 (Audited) | F7: Budget 2024
D8: Years | E8: Month | F8: Years | G8: Month | H8: RP/KG | I8: USD/MT
B9: 1 | C9: Biaya Perjalanan Dinas (Dalam Provinsi) | D9: 305458258 | E9: =IFERROR(D9/12,0) -> 25454855 | F9: =G9*12 -> 3.6654991e+08 | G9: 30545826 | H9: =G9/($I$5*1000) -> 0.76125948 | I9: =(G9/$I$6)/$I$5 -> 0.047578717
B10: =B9+1 -> 2 | C10: Biaya Perjalanan Dinas (Luar Provinsi) | D10: 2.6287295e+09 | E10: =IFERROR(D10/12,0) -> 2.1906079e+08 | F10: =G10*12 -> 3.5487849e+09 | G10: 2.9573207e+08 | H10: =G10/($I$5*1000) -> 7.3701999 | I10: =(G10/$I$6)/$I$5 -> 0.46063749
B11: =B10+1 -> 3 | C11: Beban BBM Kendaraan | D11: 720175678 | E11: =IFERROR(D11/12,0) -> 60014640 | F11: =G11*12 -> 7.5618446e+08 | G11: 63015372 | H11: =G11/($I$5*1000) -> 1.5704617 | I11: =(G11/$I$6)/$I$5 -> 0.098153855
B12: =B11+1 -> 4 | C12: Beban Sewa Kendaraan | D12: 2428347903 | E12: =IFERROR(D12/12,0) -> 2.0236233e+08 | F12: =G12*12 -> 2220000000 | G12: 185000000 | H12: =G12/($I$5*1000) -> 4.6105482 | I12: =(G12/$I$6)/$I$5 -> 0.28815926
B13: =B12+1 -> 5 | C13: Beban Kendaraan Lainnya | D13: 110862850 | E13: =IFERROR(D13/12,0) -> 9238570.8 | F13: =G13*12 -> 110862850 | G13: 9238570.8 | H13: =G13/($I$5*1000) -> 0.23024258 | I13: =(G13/$I$6)/$I$5 -> 0.014390161
B14: =B13+1 -> 6 | C14: Beban Sewa Bangunan / Inventaris / Aset | D14: 126990400 | E14: =IFERROR(D14/12,0) -> 10582533 | F14: =G14*12 -> 110000400 | G14: 9166700 | H14: =G14/($I$5*1000) -> 0.22845142 | I14: =(G14/$I$6)/$I$5 -> 0.014278214
B15: =B14+1 -> 7 | C15: Beban Penelitian, Percobaan & Pengembangan | D15: 108868060 | E15: =IFERROR(D15/12,0) -> 9072338.3 | F15: =G15*12 -> 100000000 | G15: 8333333.3 | H15: =G15/($I$5*1000) -> 0.20768235 | I15: =(G15/$I$6)/$I$5 -> 0.012980147
B16: =B15+1 -> 8 | C16: Beban Pemeliharaan Bangunan Rumah | D16: 203000 | E16: =IFERROR(D16/12,0) -> 16916.667 | F16: =G16*12 -> 0 | G16: 0 | H16: =G16/($I$5*1000) -> 0 | I16: =(G16/$I$6)/$I$5 -> 0
B17: =B16+1 -> 9 | C17: Beban Pemeliharaan Bangunan Perusahaan | D17: 108952486 | E17: =IFERROR(D17/12,0) -> 9079373.8 | F17: =G17*12 -> 1.1440011e+08 | G17: 9533342.5 | H17: =G17/($I$5*1000) -> 0.23758884 | I17: =(G17/$I$6)/$I$5 -> 0.014849303
B18: =B17+1 -> 10 | C18: Beban Pemeliharaan Mesin & Instalansi | D18: 32369030 | E18: =IFERROR(D18/12,0) -> 2697419.2 | F18: =G18*12 -> 33987482 | G18: 2832290.1 | H18: =G18/($I$5*1000) -> 0.070586001 | I18: =(G18/$I$6)/$I$5 -> 0.0044116251
B19: =B18+1 -> 11 | C19: Beban Pemeliharaan Jalan, Jembatan & Saluran Air | D19: 179265600 | E19: =IFERROR(D19/12,0) -> 14938800 | F19: =G19*12 -> 188228880 | G19: 15685740 | H19: =G19/($I$5*1000) -> 0.39091817 | I19: =(G19/$I$6)/$I$5 -> 0.024432385
B20: =B19+1 -> 12 | C20: Beban Pemeliharaan Alat Inventaris Kecil | D20: 253700695 | E20: =IFERROR(D20/12,0) -> 21141725 | F20: =G20*12 -> 2.6638573e+08 | G20: 22198811 | H20: =G20/($I$5*1000) -> 0.55323615 | I20: =(G20/$I$6)/$I$5 -> 0.034577259
B21: =B20+1 -> 13 | C21: Beban Pemakaian Inventaris Kecil | D21: 1859843066 | E21: =IFERROR(D21/12,0) -> 1.5498692e+08 | F21: =G21*12 -> 335473201 | G21: 27956100 | H21: =G21/($I$5*1000) -> 0.69671864 | I21: =(G21/$I$6)/$I$5 -> 0.043544915
