Workbook

Sheet Februari 2026 PMG 1
C1: PRODUCTION REPORT PMG 1
C2: No | D2: ITEM | E2: Budget / Norma | F2: UoM | G2: Februari 2026 | AJ2: TOTAL MONTHLY (Kg)
G3: 1 | H3: 2 | I3: 3 | J3: 4 | K3: 5 | L3: 6 | M3: 7 | N3: 8 | O3: 9 | P3: 10 | Q3: 11 | R3: 12 | S3: 13 | T3: 14 | U3: 15 | V3: 16 | W3: 17 | X3: 18 | Y3: 19 | Z3: 20 | AA3: 21 | AB3: 22 | AC3: 23 | AD3: 24 | AE3: 25 | AF3: 26 | AG3: 27 | AH3: 28
C4: 1 | D4: PRODUCTION | AJ4: Production | AL4: aktual refinery | AO4: opening stok rpo | AP4: =AP6+AP7+AP9 -> 80236
D5: Refinery | AJ5: Refinery | AL5: cpo feed | AM5: =AJ9 -> 857800 | AO5: sisa rbpo tank
D6: Running Days | F6: Day | J6: 1 | K6: 1 | L6: 1 | AJ6: =SUM(G6:AH6) -> 3 | AL6: rpo prod | AM6: =AJ20+AJ19+AJ18 -> 530000 | AO6: tk 108 | AP6: 80236
D7: Incoming CPO | F7: Kg | AJ7: =SUM(G7:AH7) -> 0
D8: Ratio Run CPO ( utilisasi kapasitas ) | F8: % | J8: =J9/2500000 -> 0.11632 | K8: =K9/2500000 -> 0.2268 | L8: =L9/2500000 -> 0 | M8: =M9/2500000 -> 0 | N8: =N9/2500000 -> 0 | O8: =O9/2500000 -> 0 | P8: =P9/2500000 -> 0 | Q8: =Q9/2500000 -> 0 | ... AH8: =AH9/2500000 -> 0 | AJ8: =AJ9/2500000/AJ6 -> 0.11437333
D9: CPO Consume Total | E9: 58900000 | F9: Kg | J9: 290800 | K9: 567000 | AJ9: =SUM(G9:U9) -> 857800
D10: Avg Daily Consump CPO ( MTD ) | AJ10: =AJ9/AJ6 -> 285933.33
D11: CPO Consume Poram | F11: Kg | J11: =J9-J12 -> 290800 | K11: =K9-K12 -> 567000 | AJ11: =SUM(G11:AH11) -> 857800
D12: CPO Consume Brand | F12: Kg | J12: =J40+J49+J54 -> 0 | AJ12: =SUM(G12:AH12) -> 0
D13: - FFA | E13: 5 | F13: % | K13: 4.36 | AJ13: =SUM(G13:AH13)/AJ6 -> 1.4533333 | AL13: rpo feed | AM13: =AM14+AM15 -> 3288600 | AO13: tk131 | AP13: ='OIP Fract PMG 2'!T13 -> 200835
D14: - Moist & Impurities | E14: 0.5 | F14: % | K14: 0.35 | AJ14: =SUM(G14:AH14)/AJ6 -> 0.11666667 | AL14: olein 56 | AM14: =AJ33 -> 2712800 | AO14: tk132 | AP14: ='OIP Fract PMG 2'!U13 -> 114939
D15: - DOBI | E15: 2,20 Min | F15: % | AJ15: =SUM(G15:AH15)/AJ6 -> 0 | AL15: stearin 56 | AM15: =AJ34 -> 575800 | AO15: after
D16: TANK | K16: 107 | AL16: yield olein | AM16: =AM14/(AM14+AM15)*100 -> 82.49103 | AO16: tk131 | AP16: =AP13 -> 200835
D17: Product | AJ17: Product | AL17: yield stearin | AM17: =AM15/(AM14+AM15)*100 -> 17.50897 | AO17: tk132 | AP17: =AP14-AM13 -> -3173661
D18: OIP RBDPO | F18: Kg | AJ18: =SUM(G18:AH18) -> 0
D19: DIRECT RBDPO FRACT | F19: Kg | K19: 530000 | AJ19: =SUM(G19:U19) -> 530000
D20: RBDPO | E20: 55661000 | F20: Kg | AJ20: =SUM(G20:AH20) -> 0
D21: PFAD | E21: 2827000 | F21: Kg | J21: 13600 | K21: 32400 | AJ21: =SUM(G21:U21) -> 46000
D22: Fractionation
D23: Running Days | F23: Day | L23: 1 | M23: 1 | N23: 1 | O23: 1 | P23: 1 | X23: 1 | Y23: 1 | Z23: 1 | AA23: 1 | AB23: 1 | AC23: 1 | AD23: 1 | AE23: 1 | AF23: 1 | AG23: 1 | AH23: 1 | AJ23: =SUM(G23:AH23) -> 16
D24: Avg Daily Consump RBDPO ( MTD ) | F24: Kg | J24: 0 | K24: 0 | L24: 0 | M24: 0 | N24: 0 | O24: 0 | P24: 0 | Q24: 0 | R24: 0 | S24: 0 | T24: 0 | U24: 0 | V24: 0 | W24: 0 | X24: 0 | Y24: 0 | AJ24: =AJ29/AJ23 -> 584525
D25: Total RBDPO transfer to plant | F25: Kg | AJ25: =SUM(G25:AH25) -> 0
D26: Stok TK 131 | E26: 559 | F26: ton
D27: Stok TK 132 | E27: 559 | F27: ton
D28: Ratio Run RBDPO | F28: % | J28: =J29/2500000 -> 0 | K28: =K29/2500000 -> 0 | L28: =L29/2500000 -> 0 | M28: =M29/2500000 -> 0.20636 | N28: =N29/2500000 -> 0.363 | O28: =O29/2500000 -> 0.30008 | P28: =P29/2500000 -> 0.29308 | Q28: =Q29/2500000 -> 0 | ... AH28: =AH29/2500000 -> 0.12728 | AJ28: =AJ29/2500000/AJ23 -> 0.23381
D29: Total Proses RBDPO | E29: 35501000 | F29: Kg | J29: =SUM(J32,J36,J41,J45,J55) -> 0 | K29: =SUM(K32,K36,K41,K45,K55) -> 0 | L29: =SUM(L32,L36,L41,L45,L55) -> 0 | M29: =SUM(M32,M36,M41,M45,M55) -> 515900 | N29: =SUM(N32,N36,N41,N45,N55) -> 907500 | O29: =SUM(O32,O36,O41,O45,O55) -> 750200 | P29: =SUM(P32,P36,P41,P45,P55) -> 732700 | Q29: =SUM(Q32,Q36,Q41,Q45,Q55) -> 0 | ... AH29: =SUM(AH32,AH36,AH41,AH45,AH55) -> 318200 | AJ29: =SUM(G29:AH29) -> 9352400
D30: Sisa Filling Crystalizer | F30: Kg | J30: =J25-J29 -> 0 | AJ30: =SUM(G30:AH30) -> 0
D31: Fractionation OLEIN IV 56 | AJ31: Olein IV 56
D32: RBDPO Consume | F32: Kg | J32: =J33+J34 -> 0 | K32: =K33+K34 -> 0 | L32: =L33+L34 -> 0 | M32: =M33+M34 -> 335100 | N32: =N33+N34 -> 0 | O32: =O33+O34 -> 0 | P32: =P33+P34 -> 0 | Q32: =Q33+Q34 -> 0 | ... AH32: =AH33+AH34 -> 318200 | AJ32: =SUM(G32:AH32) -> 3288600
D33: OLEIN IV 56 | E33: 25000000 | F33: Kg | M33: 276100 | AC33: 50200 | AE33: 437200 | AF33: =362600+394400+216400 -> 973400 | AG33: 723500 | AH33: 252400 | AJ33: =SUM(G33:AH33) -> 2712800
D34: STEARIN | E34: 639000 | F34: Kg | M34: 59000 | AC34: 11000 | AE34: 90500 | AF34: 192300 | AG34: 157200 | AH34: 65800 | AJ34: =SUM(G34:AH34) -> 575800
D35: Fractionation OLEIN IV 57 ( Bulk ) | AJ35: Olein IV 57 ( Bulk )
D36: RBDPO Consume | F36: Kg | J36: =J37+J38 -> 0 | AJ36: =SUM(G36:AH36) -> 0
D37: OLEIN IV 57 | F37: Kg | J37: 0 | AJ37: =SUM(G37:AH37) -> 0
D38: STEARIN | F38: Kg | J38: 0 | AJ38: =SUM(G38:AH38) -> 0
D39: Fractionation OLEIN IV 57 ( Retail ) | AJ39: Olein IV 57 ( Retail )
D40: CPO Consume | F40: Kg | AJ40: =SUM(G40:AH40) -> 0
D41: RBDPO Brand Consume | F41: Kg | J41: =J42+J43 -> 0 | AJ41: =SUM(G41:AH41) -> 0
D42: OLEIN IV 57 Low Color | F42: Kg | J42: 0 | AJ42: =SUM(G42:AH42) -> 0
D43: STEARIN | F43: Kg | J43: 0 | AJ43: =SUM(G43:AH43) -> 0
D44: Fractionation OLEIN IV 58 ( Bulk ) | AJ44: Olein IV 58 ( Bulk )
D45: RBDPO Consume | E45: 17143 | F45: Kg | J45: =J46+J47 -> 0 | K45: =K46+K47 -> 0 | L45: =L46+L47 -> 0 | M45: =M46+M47 -> 180800 | N45: =N46+N47 -> 907500 | O45: =O46+O47 -> 750200 | P45: =P46+P47 -> 732700 | Q45: =Q46+Q47 -> 0 | ... AH45: =AH46+AH47 -> 0 | AJ45: =SUM(G45:AH45) -> 6063800
D46: OLEIN IV 58 | E46: 12000000 | F46: Kg | M46: 130800 | N46: 710100 | O46: 566100 | P46: 549600 | Y46: 390400 | Z46: 710100 | AA46: 713000 | AB46: 766300 | AC46: 102300 | AJ46: =SUM(G46:AH46) -> 4638700
D47: STEARIN | E47: 514300 | F47: Kg | M47: 50000 | N47: 197400 | O47: 184100 | P47: 183100 | Y47: 106000 | Z47: 215400 | AA47: 218100 | AB47: 228000 | AC47: 43000 | AJ47: =SUM(G47:AH47) -> 1425100
D48: Fractionation OLEIN IV 58 ( Retail ) | AJ48: Olein IV 58 ( Retail )
D49: CPO Consume | F49: Kg | AJ49: =SUM(G49:AH49) -> 0
D50: RBDPO Consume | E50: =E51+E52 -> 21429000 | F50: Kg | AJ50: =SUM(G50:AH50) -> 0
D51: OLEIN IV 58 | E51: 15000000 | F51: Kg | AJ51: =SUM(G51:AH51) -> 0
D52: STEARIN | E52: 6429000 | F52: Kg | AJ52: =SUM(G52:AH52) -> 0
D53: Fractionation OLEIN IV 60 | AJ53: Olein IV 60
D54: CPO Consume | F54: Kg | AJ54: =SUM(G54:AH54) -> 0
D55: RBDPO Brand Consume | E55: =E56+E57 -> 1333300 | F55: Kg | AJ55: =SUM(G55:AH55) -> 0
D56: OLEIN IV 60 Salvaco | E56: 1250000 | F56: Kg | AJ56: =SUM(G56:AH56) -> 0
D57: SOFT STEARIN | E57: 83300 | F57: Kg | AJ57: =SUM(G57:AH57) -> 0
D58: Ratio Run RBDPO | F58: % | AJ58: =SUM(G58:AH58) -> 0
D59: YIELD | AJ59: Yield
D60: RBDPO | E60: 94.2 | F60: % | J60: =((J20+J19+J18)/(J9))*100 -> 0 | K60: =((K20+K19+K18)/(K9))*100 -> 93.474427 | L60: =((L20+L19+L18)/(L9))*100 -> #DIV/0! | M60: =((M20+M19+M18)/(M9))*100 -> #DIV/0! | N60: =((N20+N19+N18)/(N9))*100 -> #DIV/0! | O60: =((O20+O19+O18)/(O9))*100 -> #DIV/0! | P60: =((P20+P19+P18)/(P9))*100 -> #DIV/0! | Q60: =((Q20+Q19+Q18)/(Q9))*100 -> #DIV/0! | ... AH60: =((AH20+AH19+AH18)/(AH9))*100 -> #DIV/0! | AJ60: =((AJ20+AJ19+AJ18)/(AJ9))*100 -> 61.785964
D61: PFAD | E61: 5 | F61: % | J61: =(J21/(J9))*100 -> 4.6767538 | K61: =(K21/(K9))*100 -> 5.7142857 | L61: =(L21/(L9))*100 -> #DIV/0! | M61: =(M21/(M9))*100 -> #DIV/0! | N61: =(N21/(N9))*100 -> #DIV/0! | O61: =(O21/(O9))*100 -> #DIV/0! | P61: =(P21/(P9))*100 -> #DIV/0! | Q61: =(Q21/(Q9))*100 -> #DIV/0! | ... AH61: =(AH21/(AH9))*100 -> #DIV/0! | AJ61: =(AJ21/(AJ9))*100 -> 5.3625554
D62: Olein IV 56 | E62: 82 | F62: % | J62: =J33/(J33+J34)*100 -> #DIV/0! | K62: =K33/(K33+K34)*100 -> #DIV/0! | L62: =L33/(L33+L34)*100 -> #DIV/0! | M62: =M33/(M33+M34)*100 -> 82.393315 | N62: =N33/(N33+N34)*100 -> #DIV/0! | O62: =O33/(O33+O34)*100 -> #DIV/0! | P62: =P33/(P33+P34)*100 -> #DIV/0! | Q62: =Q33/(Q33+Q34)*100 -> #DIV/0! | ... AH62: =AH33/(AH33+AH34)*100 -> 79.321182 | AJ62: =AJ33/(AJ33+AJ34)*100 -> 82.49103
D63: Stearin | E63: 18 | F63: % | J63: =(J34/J32)*100 -> #DIV/0! | K63: =(K34/K32)*100 -> #DIV/0! | L63: =(L34/L32)*100 -> #DIV/0! | M63: =(M34/M32)*100 -> 17.606685 | N63: =(N34/N32)*100 -> #DIV/0! | O63: =(O34/O32)*100 -> #DIV/0! | P63: =(P34/P32)*100 -> #DIV/0! | Q63: =(Q34/Q32)*100 -> #DIV/0! | ... AH63: =(AH34/AH32)*100 -> 20.678818 | AJ63: =AJ34/(AJ33+AJ34)*100 -> 17.50897
D64: Olein IV 57 ( Bulk ) | E64: 75 | J64: =(J37/J36)*100 -> #DIV/0! | K64: =(K37/K36)*100 -> #DIV/0! | L64: =(L37/L36)*100 -> #DIV/0! | M64: =(M37/M36)*100 -> #DIV/0! | N64: =(N37/N36)*100 -> #DIV/0! | O64: =(O37/O36)*100 -> #DIV/0! | P64: =(P37/P36)*100 -> #DIV/0! | Q64: =(Q37/Q36)*100 -> #DIV/0! | ... AH64: =(AH37/AH36)*100 -> #DIV/0! | AJ64: =(AJ42/AJ41)*100 -> #DIV/0!
D65: Stearin | E65: 25 | J65: =(J38/J36)*100 -> #DIV/0! | K65: =(K38/K36)*100 -> #DIV/0! | L65: =(L38/L36)*100 -> #DIV/0! | M65: =(M38/M36)*100 -> #DIV/0! | N65: =(N38/N36)*100 -> #DIV/0! | O65: =(O38/O36)*100 -> #DIV/0! | P65: =(P38/P36)*100 -> #DIV/0! | Q65: =(Q38/Q36)*100 -> #DIV/0! | ... AH65: =(AH38/AH36)*100 -> #DIV/0! | AJ65: =(AJ43/AJ41)*100 -> #DIV/0!
D66: Olein IV 57 ( Retail ) | E66: 75 | F66: % | J66: =J42/J41*100 -> #DIV/0! | K66: =K42/K41*100 -> #DIV/0! | L66: =L42/L41*100 -> #DIV/0! | M66: =M42/M41*100 -> #DIV/0! | N66: =N42/N41*100 -> #DIV/0! | O66: =O42/O41*100 -> #DIV/0! | P66: =P42/P41*100 -> #DIV/0! | Q66: =Q42/Q41*100 -> #DIV/0! | ... AH66: =AH42/AH41*100 -> #DIV/0! | AJ66: =AJ42/AJ41*100 -> #DIV/0!
D67: Stearin | E67: 25 | F67: % | J67: =J43/J41*100 -> #DIV/0! | K67: =K43/K41*100 -> #DIV/0! | L67: =L43/L41*100 -> #DIV/0! | M67: =M43/M41*100 -> #DIV/0! | N67: =N43/N41*100 -> #DIV/0! | O67: =O43/O41*100 -> #DIV/0! | P67: =P43/P41*100 -> #DIV/0! | Q67: =Q43/Q41*100 -> #DIV/0! | ... AH67: =AH43/AH41*100 -> #DIV/0! | AJ67: =AJ43/AJ41*100 -> #DIV/0!
D68: Olein IV 58 ( Bulk ) | E68: 70 | F68: % | J68: =J46/(J46+J47)*100 -> #DIV/0! | K68: =K46/(K46+K47)*100 -> #DIV/0! | L68: =L46/(L46+L47)*100 -> #DIV/0! | M68: =M46/(M46+M47)*100 -> 72.345133 | N68: =N46/(N46+N47)*100 -> 78.247934 | O68: =O46/(O46+O47)*100 -> 75.459877 | P68: =P46/(P46+P47)*100 -> 75.010236 | Q68: =Q46/(Q46+Q47)*100 -> #DIV/0! | ... AH68: =AH46/(AH46+AH47)*100 -> #DIV/0! | AJ68: =AJ46/(AJ46+AJ47)*100 -> 76.498235
D69: Stearin | E69: 30 | F69: % | J69: =J47/(J47+J46)*100 -> #DIV/0! | K69: =K47/(K47+K46)*100 -> #DIV/0! | L69: =L47/(L47+L46)*100 -> #DIV/0! | M69: =M47/(M47+M46)*100 -> 27.654867 | N69: =N47/(N47+N46)*100 -> 21.752066 | O69: =O47/(O47+O46)*100 -> 24.540123 | P69: =P47/(P47+P46)*100 -> 24.989764 | Q69: =Q47/(Q47+Q46)*100 -> #DIV/0! | ... AH69: =AH47/(AH47+AH46)*100 -> #DIV/0! | AJ69: =AJ47/AJ45*100 -> 23.501765
D70: Olein IV 58 ( Retail ) | E70: 70 | F70: % | AJ70: =AJ51/(AJ51+AJ52)*100 -> #DIV/0!
D71: Stearin | E71: 30 | F71: % | AJ71: =AJ52/(AJ51+AJ52)*100 -> #DIV/0!
D72: Olein IV 60 | E72: 60 | F72: % | AJ72: =AJ56/(AJ57+AJ56)*100 -> #DIV/0!
D73: Soft Stearin | E73: 40 | F73: % | AJ73: =AJ57/(AJ56+AJ57)*100 -> #DIV/0!
C74: 2 | D74: CHEMICAL CONSUMABLE | AJ74: Chemical
D75: Bleaching Earth (BE) to Hopper | E75: 9 | F75: Kg | J75: 2605 | K75: 1481 | L75: 0 | AJ75: =SUM(G75:AH75) -> 4086
D76: Note : BE Aktivasi start tgl 23 Bulan September (0,67 %) | F76: % | J76: =J75/(J11)*1000 -> 8.9580468 | K76: =K75/(K11)*1000 -> 2.6119929 | L76: =L75/(L11)*1000 -> #DIV/0! | M76: =M75/(M11)*1000 -> #DIV/0! | N76: =N75/(N11)*1000 -> #DIV/0! | O76: =O75/(O11)*1000 -> #DIV/0! | P76: =P75/(P11)*1000 -> #DIV/0! | Q76: =Q75/(Q11)*1000 -> #DIV/0! | ... AH76: =AH75/(AH11)*1000 -> #DIV/0! | AJ76: =AJ75/(AJ11)*100 -> 0.47633481
D77: TK 630 A ( TRANSFER ) | E77: 40000 | F77: Kg | AJ77: =SUM(G77:AH77) -> 0
D79: TK 630 B ( TRANSFER ) | E79: 40000 | F79: Kg | AJ79: =SUM(G79:AH79) -> 0
D81: Bleaching Earth (BE) to Branded Spec | E81: 18 | F81: Kg | AJ81: =SUM(G81:AH81) -> 0
D82: Bleaching Earth (BE) to Silo
D84: Aktual Pengiisian BE | F84: Kg | J84: 0 | K84: 6000 | AJ84: =SUM(G84:AH84) -> 6000
J85: =J84/J9*100 -> 0 | K85: =K84/K9*100 -> 1.0582011 | L85: =L84/L9*100 -> #DIV/0! | M85: =M84/M9*100 -> #DIV/0! | N85: =N84/N9*100 -> #DIV/0! | O85: =O84/O9*100 -> #DIV/0! | P85: =P84/P9*100 -> #DIV/0! | Q85: =Q84/Q9*100 -> #DIV/0! | ... AH85: =AH84/AH9*100 -> #DIV/0! | AJ85: =AJ84/AJ9*100 -> 0.69946374
D86: Phosporic Acid (PA) | E86: 0.6 | F86: Kg | J86: 128.26 | K86: 272.874 | L86: 0 | AJ86: =SUM(G86:AH86) -> 401.134
F87: % | J87: =J86/(J9)*1000 -> 0.44105915 | K87: =K86/(K9)*1000 -> 0.48125926 | L87: =L86/(L9)*1000 -> #DIV/0! | M87: =M86/(M9)*1000 -> #DIV/0! | N87: =N86/(N9)*1000 -> #DIV/0! | O87: =O86/(O9)*1000 -> #DIV/0! | P87: =P86/(P9)*1000 -> #DIV/0! | Q87: =Q86/(Q9)*1000 -> #DIV/0! | ... AH87: =AH86/(AH9)*1000 -> #DIV/0! | AJ87: =AJ86/AJ9*1000 -> 0.46763115
C88: 3 | D88: OIL LOSSES | E88: 0.7 | F88: % | J88: =((SUM(J19:J21))-(SUM(J9)))/(SUM(J9))*100 -> -95.323246 | K88: =((SUM(K19:K21))-(SUM(K9)))/(SUM(K9))*100 -> -0.81128748 | L88: =((SUM(L19:L21))-(SUM(L9)))/(SUM(L9))*100 -> #DIV/0! | M88: =((SUM(M19:M21))-(SUM(M9)))/(SUM(M9))*100 -> #DIV/0! | N88: =((SUM(N19:N21))-(SUM(N9)))/(SUM(N9))*100 -> #DIV/0! | O88: =((SUM(O19:O21))-(SUM(O9)))/(SUM(O9))*100 -> #DIV/0! | P88: =((SUM(P19:P21))-(SUM(P9)))/(SUM(P9))*100 -> #DIV/0! | Q88: =((SUM(Q19:Q21))-(SUM(Q9)))/(SUM(Q9))*100 -> #DIV/0! | ... AH88: =((SUM(AH19:AH21))-(SUM(AH9)))/(SUM(AH9))*100 -> #DIV/0! | AJ88: =((SUM(AJ18:AJ21))-(SUM(AJ9)))/(SUM(AJ9))*100 -> -32.851481
F89: Kg | J89: =J88%*J9 -> -277200 | K89: =K88%*K9 -> -4600 | L89: =L88%*L9 -> #DIV/0! | M89: =M88%*M9 -> #DIV/0! | N89: =N88%*N9 -> #DIV/0! | O89: =O88%*O9 -> #DIV/0! | P89: =P88%*P9 -> #DIV/0! | Q89: =Q88%*Q9 -> #DIV/0! | ... AH89: =AH88%*AH9 -> #DIV/0! | AJ89: =AJ88%*AJ9 -> -281800
D90: % Oil Content | E90: 22 | F90: % | J90: 17.13 | K90: 17.22 | AJ90: =AVERAGE(G90:AH90) -> 17.175
D91: Spent Bleaching Earth | F91: Kg | J91: =SUM(J75,J81)+(J90%*SUM(J75,J81)) -> 3051.2365 | K91: =SUM(K75,K81)+(K90%*SUM(K75,K81)) -> 1736.0282 | L91: =SUM(L75,L81)+(L90%*SUM(L75,L81)) -> 0 | M91: =SUM(M75,M81)+(M90%*SUM(M75,M81)) -> 0 | N91: =SUM(N75,N81)+(N90%*SUM(N75,N81)) -> 0 | O91: =SUM(O75,O81)+(O90%*SUM(O75,O81)) -> 0 | P91: =SUM(P75,P81)+(P90%*SUM(P75,P81)) -> 0 | Q91: =SUM(Q75,Q81)+(Q90%*SUM(Q75,Q81)) -> 0 | ... AH91: =SUM(AH75,AH81)+(AH90%*SUM(AH75,AH81)) -> 0 | AJ91: =SUM(AJ75,AJ81)+(AJ90%*SUM(AJ75,AJ81))/AJ6 -> 4319.9235
C92: 4 | D92: PACKAGING (Brand Salvaco) | AJ92: Packaging
D93: Olein IV 60 Received | F93: Kg | AJ93: 0
D94: Olein IV 60 Consume | F94: Kg | AJ94: 0
D95: - finished product | F95: Kg | AJ95: 0
D96: - sample | F96: Kg | AJ96: 0
D97: - remelt, flushing, downgrade | F97: Kg | AJ97: 0
D98: Carton | AJ98: Carton
D99: Salvaco 1 Liter | F99: Box | AJ99: 0
D100: Salvaco 2 Liter | F100: Box | AJ100: 0 | AT100: 37542
D101: Pouch | AJ101: Pouch
D102: Salvaco 1 Liter | F102: Pouch | AJ102: 0
D103: Salvaco 2 Liter | F103: Pouch | AJ103: 0
...

Sheet OIP Ref PMG 1
B4: Oil In Plant (OIP) Refinery pmg | I4: February | J4: OIP | M4: TK131 RPO | P4: TK132 RPO | S4: TOTAL STOK RPO DI PLANT
B5: Vessel | C5: Operating Volume (m3) | D5: Oil Density (kg/m3) | E5: MT | F5: Level yg diisi | G5: Actual OIP (Kg) | I5: Tanggal | J5: Opening Stock | K5: Closing Stock | L5: balance stok | M5: Opening Stock | N5: Closing Stock | O5: CONSUMP stok | P5: Opening Stock | Q5: Closing Stock | R5: CONSUMP stok
B6: 2MX312 | C6: 5.67 | D6: 850 | E6: =C6*D6/1000 -> 4.8195 | G6: =(F6*E6/100)*1000 -> 0 | I6: 46054 | L6: =J6-K6 -> 0
B7: 2VE611A | C7: 47.22 | D7: 850 | E7: =C7*D7/1000 -> 40.137 | G7: =(F7*E7/100)*1000 -> 0 | I7: 46055 | L7: =J7-K7 -> 0
B8: 2VE611B | C8: 47.22 | D8: 850 | E8: =C8*D8/1000 -> 40.137 | G8: =(F8*E8/100)*1000 -> 0 | I8: 46056 | L8: =J8-K8 -> 0
B9: 2VE612 | C9: 35.68 | D9: 850 | E9: =C9*D9/1000 -> 30.328 | G9: =(F9*E9/100)*1000 -> 0 | I9: 46057 | J9: 0 | K9: 269071 | L9: =J9-K9 -> -269071
B10: 2VE661 | C10: 10.8 | D10: 850 | E10: =C10*D10/1000 -> 9.18 | G10: =(F10*E10/100)*1000 -> 0 | I10: 46058 | J10: =K9 -> 269071 | K10: 180800 | L10: =J10-K10 -> 88271
B11: FL621 | C11: 10.1 | D11: 850 | E11: =C11*D11/1000 -> 8.585 | G11: =(F11*E11/100)*1000 -> 0 | I11: 46059 | J11: =K10 -> 180800 | K11: 0 | L11: =J11-K11 -> 180800
B12: FL622 | C12: 10.1 | D12: 850 | E12: =C12*D12/1000 -> 8.585 | G12: =(F12*E12/100)*1000 -> 0 | I12: 46060 | J12: =K11 -> 0 | L12: =J12-K12 -> 0
B13: FL623 | C13: 10.1 | D13: 850 | E13: =C13*D13/1000 -> 8.585 | G13: =(F13*E13/100)*1000 -> 0 | I13: 46061 | J13: =K12 -> 0 | L13: =J13-K13 -> 0 | N13: 0 | Q13: 174609
B14: FL624 | C14: 10.1 | D14: 850 | E14: =C14*D14/1000 -> 8.585 | G14: =(F14*E14/100)*1000 -> 0 | I14: 46062 | J14: =K13 -> 0 | L14: =J14-K14 -> 0 | N14: 44191 | P14: 174609 | Q14: 38852 | R14: =P14-Q14 -> 135757 | S14: =R14+O14+L14 -> 135757
B15: FL625 | C15: 10.1 | D15: 850 | E15: =C15*D15/1000 -> 8.585 | G15: =(F15*E15/100)*1000 -> 0 | I15: 46063 | J15: =K14 -> 0 | L15: =J15-K15 -> 0 | M15: 44191 | N15: 405272 | O15: =M15-N15 -> -361081 | P15: 38852 | Q15: 38852 | R15: =P15-Q15 -> 0 | S15: =R15+O15+L15 -> -361081
B16: 2VE701 | C16: 72.13 | D16: 850 | E16: =C16*D16/1000 -> 61.3105 | G16: =(F16*E16/100)*1000 -> 0 | I16: 46064 | J16: =K15 -> 0 | L16: =J16-K16 -> 0
B17: 2VE751 | C17: 4.28 | D17: 860 | E17: =C17*D17/1000 -> 3.6808 | G17: =(F17*E17/100)*1000 -> 0 | I17: 46065 | J17: =K16 -> 0 | L17: =J17-K17 -> 0
B18: 2HE721A (tube) | C18: 10 | D18: 810 | E18: =C18*D18/1000 -> 8.1 | G18: =(F18*E18/100)*1000 -> 0 | I18: 46066 | J18: =K17 -> 0 | L18: =J18-K18 -> 0
B19: 2HE721A (shell) | C19: 21.8 | D19: 800 | E19: =C19*D19/1000 -> 17.44 | G19: =(F19*E19/100)*1000 -> 0 | I19: 46067 | J19: =K18 -> 0 | L19: =J19-K19 -> 0
B20: HE721B (tube) | C20: 10 | D20: 810 | E20: =C20*D20/1000 -> 8.1 | G20: =(F20*E20/100)*1000 -> 0 | I20: 46068 | J20: =K19 -> 0 | L20: =J20-K20 -> 0
B21: 2HE722 | C21: 11.4 | D21: 790 | E21: =C21*D21/1000 -> 9.006 | G21: =(F21*E21/100)*1000 -> 0 | I21: 46069 | J21: =K20 -> 0 | L21: =J21-K21 -> 0
B22: 2PR731 | C22: 14 | D22: 790 | E22: =C22*D22/1000 -> 11.06 | G22: =(F22*E22/100)*1000 -> 0 | I22: 46070 | J22: =K21 -> 0 | L22: =J22-K22 -> 0
B23: 2DE732 | C23: 149.76 | D23: 790 | E23: =C23*D23/1000 -> 118.3104 | G23: =(F23*E23/100)*1000 -> 0 | I23: 46071 | J23: =K22 -> 0 | L23: =J23-K23 -> 0
C24: =SUM(C6:C23) -> 490.46 | E24: =SUM(E6:E23) -> 404.5342 | I24: 46072 | J24: =K23 -> 0 | L24: =J24-K24 -> 0
F25: Total OIP = | G25: =SUM(G6:G24) -> 0 | I25: 46073 | J25: =K24 -> 0 | L25: =J25-K25 -> 0
I26: 46074 | J26: =K25 -> 0 | L26: =J26-K26 -> 0
I27: 46075 | J27: =K26 -> 0 | L27: =J27-K27 -> 0
I28: 46076 | J28: =K27 -> 0 | L28: =J28-K28 -> 0
I29: 46077 | J29: =K28 -> 0 | L29: =J29-K29 -> 0
I30: 46078 | J30: =K29 -> 0 | L30: =J30-K30 -> 0
H31: 0 | I31: 46079 | J31: =K30 -> 0 | L31: =J31-K31 -> 0
I32: 46080 | J32: =K31 -> 0 | L32: =J32-K32 -> 0
I33: 46081 | J33: =K32 -> 0 | L33: =J33-K33 -> 0
B38: Solar Daily Tank HPB
B39: 2TK726 | C39: =5.3+0.78 -> 6.08 | D39: 840 | E39: =C39*D39/1000 -> 5.1072 | F39: 0 | G39: =F39*E39/100*1000 -> 0
B41: Stock Chemicals In Plant
C42: Sisa Stok Di Lap | D42: Order | E42: Consumption
B43: BE
B44: 630A | D44: 298
B45: 630B
B46: H3PO4
B47: NaOH
B48: Citrid Acid

Sheet Peformance test Fract 1
C1: PT.INDUSTRI NABATI LESTARI
C2: Pabrik Minyak Goreng ( PMG 2 )
C3: Kantor Pusat: Komp. KEK Sei Mangkei, Kav.2-3, Kec. Bosar Maligas, Kab. Simalungun, Sumatera Utara, 21184
C4: ACTUAL PEFORMANCE / CONSUMPT REPORT FRAKSINASI PLANT | H4: Trial | I4: 1
H5: Start / Date / Time | I5: 17/12/24 ( 07.00 Wib )
H6: Finish / Date / Time | I6: 17/12/24 ( 07.00 Wib )
A8: No | B8: ITEM | C8: Kontrak LIPICO | D8: UOM | E8: TOTALIZER
A10: 1 | B10: PRODUCTION | C10: IV 56 | D10: 24 jam | E10: BEFORE | F10: AFTER | G10: TOTAL | H10: YIELD % | I10: STATUS/REMAKS
B11: Fraksinasi
B12: Running Days
B13: Incoming CPO
B14: Ratio Run CPO
B15: RBDPO Consume Total | C15: 2500 | D15: TPD | E15: 8982.8 | F15: 11717.8 | G15: =F15-E15 -> 2735 | H15: =G15/25000*10 -> 1.094 | I15: OK
B16: Avg Daily Consump CPO ( MTD )
B17: CPO Consume Poram | C17: 29045000
B18: CPO Consume Brand | C18: 7314000 | E18: =E49+E58+E63 -> 0
B19: QUALITY
B20: - FFA | C20: 0.1 | D20: % Max | H20: 0.063
B21: - Moist & Impurities | C21: 0.1 | D21: % Max | H21: 0.05
B22: - IV | C22: 52 - 52,5 | H22: 51.8
B23: - LC | H23: 2,6/20
B24: - Temp | C24: 68 | D24: ˚C Min | H24: 65
B25: TANK | H25: 108/109
B26: Product
B27: OLEIN IV 56 | C27: =C15*84% -> 2100 | D27: TPD | E27: 6537.1 | F27: 8213 | G27: =F27-E27 -> 1675.9 | H27: =G27/(G27+G32) -> 0.82838219 | I27: OK
B28: QUALITY
B29: - IV | C29: 56 | D29: Min
B30: - LC
B31: - Cloud Point ( metter ) | C31: 10 | D31: ˚C Max
B32: STEARIN | C32: =C15*16% -> 400 | E32: 2268.1 | F32: 2615.3 | G32: =F32-E32 -> 347.2 | H32: =G32/(G32+G27) -> 0.17161781 | I32: OK
B33: Fractionation
B34: Running Days
B35: Filling Langsung CR Fr Refinery | E35: 0
B36: Total Filling Crystalizer ( Feed ) | E36: 392100
B37: Avg Daily Consump RPO ( MTD )
B38: Total Proses RBDPO | E38: =SUM(E41,E45,E50,E54,E64) -> 0
B39: Sisa Filling Crystalizer | E39: =E36-E38 -> 392100
B40: Fractionation OLEIN IV 56
B41: RBDPO Consume | E41: =E42+E43 -> 0
B42: OLEIN IV 56 | E42: 0
B43: STEARIN | E43: 0
B44: Fractionation OLEIN IV 57 ( Bulk )
B45: RBDPO Consume | E45: =E46+E47 -> 0
B46: OLEIN IV 57 | E46: 0
B47: STEARIN | E47: 0
B48: Fractionation OLEIN IV 57 ( Retail )
B49: CPO Consume
B50: RBDPO Brand Consume | E50: =E51+E52 -> 0
B51: OLEIN IV 57 Low Color | E51: 0
B52: STEARIN | E52: 0
B53: Fractionation OLEIN IV 58 ( Bulk )
B54: RBDPO Consume | C54: =C55+C56 -> 21429000 | E54: =E55+E56 -> 0
B55: OLEIN IV 58 | C55: 15000000
B56: STEARIN | C56: 6429000
B57: Fractionation OLEIN IV 58 ( Retail )
B58: CPO Consume
B59: RBDPO Consume | C59: =C60+C61 -> 21429000 | E59: =E60+E61 -> 0
B60: OLEIN IV 58 | C60: 15000000 | E60: 0
B61: STEARIN | C61: 6429000 | E61: 0
B62: Fractionation OLEIN IV 60
B63: CPO Consume
B64: RBDPO Brand Consume | E64: =E66+E67 -> 0
B65: OLEIN IV 60 Bulk | E65: 0
B66: OLEIN IV 60 Salvaco | E66: 0
B67: SOFT STEARIN | E67: 0
B68: Ratio Run RBDPO | E68: 0
B69: YIELD
B70: RBDPO | C70: 94.2 | E70: =(#REF!/(E15))*100 -> #REF!
B71: PFAD | C71: 5 | E71: =(E32/(E15))*100 -> 25.249365
B72: Olein IV 56 | C72: 82 | E72: =E42/(E42+E43)*100 -> #DIV/0!
B73: Stearin | C73: 18 | E73: =(E43/E41)*100 -> #DIV/0!
B74: Olein IV 57 ( Bulk ) | C74: 75 | E74: =(E46/E45)*100 -> #DIV/0!
B75: Stearin | C75: 25 | E75: =(E47/E45)*100 -> #DIV/0!
B76: Olein IV 57 ( Retail ) | C76: 75 | E76: =E51/E50*100 -> #DIV/0!
B77: Stearin | C77: 25 | E77: =E52/E50*100 -> #DIV/0!
B78: Olein IV 58 ( Bulk ) | C78: 70 | E78: =E55/(E55+E56)*100 -> #DIV/0!
B79: Stearin | C79: 30 | E79: =E56/(E56+E55)*100 -> #DIV/0!
B80: Olein IV 58 ( Retail ) | C80: 70 | E80: =E60/(E60+E61)*100 -> #DIV/0!
B81: Stearin | C81: 30 | E81: =E61/(E60+E61)*100 -> #DIV/0!
B82: Olein IV 60 | C82: 60 | E82: =E65/E64*100 -> #DIV/0!
B83: Soft Stearin | C83: 40 | E83: =E67/E64*100 -> #DIV/0!
B84: QUALITY
B85: - IV | C85: 32 | D85: Max
B86: - Melting Point | C86: 52-52,5 | D86: ˚C Min
A87: 2 | B87: STEAM CONSUMPTION | E87: BEFORE | F87: AFTER | G87: TOTAL | H87: Kg/Ton RBDPO
B88: Incoming | C88: 408000 | D88: Kg/Day | G88: 183211
B89: Distribution to
B90: fraksinasi | C90: 87.5 | D90: Kg/Day | E90: 308052 | F90: 366933 | G90: =F90-E90 -> 58881 | H90: =G90/G15 -> 21.528702 | I90: OK
C91: =C90/2000 -> 0.04375
C92: =C90/2.5 -> 35 | D92: Kg/ton
B93: Fractionation | C93: 122000
B94: Others ( Tank farm & spurging OSBL ) | C94: 106000 | D94: Kg/Day
B95: Total | C95: 408000 | D95: Kg/Day | G95: =SUM(G90,G93,G94) -> 58881
A96: 3 | B96: WATER CONSUMPTION | E96: BEFORE | F96: AFTER | G96: TOTAL | H96: M³/Ton RBDPO
B97: Incoming from Kinra | C97: 1100 | D97: M³/Day | G97: 818
B98: Outgoing
B99: Softener Product (to Fraksinasi ) | C99: 0.13 | D99: M³/Day | E99: 58 | F99: 106 | G99: =F99-E99 -> 48 | H99: =G99/G15 -> 0.017550274
B100: Softener Product (to Fractionation) | C100: 179.63
C101: =C99/2500 -> 5.2e-05 | D101: M³/ton
B102: RO Product | C102: 491.59 | D102: M³/Day | G102: 304
...

Sheet Peformance Test REFINERY 1
C1: PT.INDUSTRI NABATI LESTARI
C2: Pabrik Minyak Goreng ( PMG 2 )
C3: Kantor Pusat: Komp. KEK Sei Mangkei, Kav.2-3, Kec. Bosar Maligas, Kab. Simalungun, Sumatera Utara, 21184
C4: ACTUAL PEFORMANCE / CONSUMPT REPORT REFINERY PLANT | H4: Peformance | I4: 1
H5: Start / Date / Time | I5: 17/12/24 ( 21.00 Wib )
H6: Finish / Date / Time | I6: 18/12/24 ( 21.00 Wib )
A7: No | B7: ITEM | C7: Kontrak LIPICO | D7: UOM | E7: TOTALIZER
A9: 1 | B9: PRODUCTION | E9: BEFORE | F9: AFTER | G9: TOTAL | H9: Yield ( % ) | I9: STATUS/REMAKS
B10: Refinery
B11: Running Days
B12: Incoming CPO
B13: Ratio Run CPO
B14: CPO Consume Total | C14: 2500 | D14: TPD | E14: 13533.82 | F14: 16053.42 | G14: =F14-E14 -> 2519.6 | I14: OK
B15: Avg Daily Consump CPO ( MTD )
B16: CPO Consume Poram | C16: 29045000
B17: CPO Consume Brand | C17: 7314000 | E17: =E53+E62+E67 -> 0
B18: - FFA | C18: 5 | D18: % | G18: 4
B19: - Moist & Impurities | C19: 0.5 | D19: % | G19: 0.41
B20: - DOBI | C20: 2.2 | D20: Min | G20: 2.42
B21: - TOTOX 2PV + AV | C21: 12 | D21: Max | G21: N/A
B22: - FE Content | C22: < 5 | D22: ppm | G22: N/A
B23: - PV | C23: < 4 | D23: Meg/kg | G23: N/A
B24: - Phosporus Max | C24: 25 | D24: ppm | G24: N/A
B25: TANK / TEMP | C25: 50 | D25: ˚C | G25: 50
B26: Product
B27: RBDPO | C27: =C14*94.2% -> 2355 | D27: TPD | E27: 12357.54 | F27: 14705.95 | G27: =F27-E27 -> 2348.41 | H27: =G27/G14 -> 0.93205668
B28: - FFA | C28: 0.05 | D28: % | G28: 0.06
B29: - Moist & Impurities | C29: 0.03 | D29: % | G29: 0.05
B30: - Peroxide value | D30: Nil | G30: -
B31: - Phosporous max | C31: 2 | D31: ppm | G31: N/A
B32: - LC | C32: 2.5 | D32: % | G32: 2.5
B33: - Aom stability min ( hr ) | C33: 60 | D33: min ( hr ) | G33: N/A
B34: - teste & Odor | C34: bland/Odorless | G34: N/A
B35: - temp max ( C ) | C35: 50 | D35: max˚C | G35: 50
B36: PFAD | C36: =C14*5% -> 125 | D36: TPD | E36: 572.71 | F36: 675.39 | G36: =F36-E36 -> 102.68 | H36: =G36/G14 -> 0.0407525
B37: Fractionation
B38: Running Days
B39: Filling Langsung CR Fr Refinery | E39: 0
B40: Total Filling Crystalizer ( Feed ) | E40: 392100
B41: Avg Daily Consump RPO ( MTD )
B42: Total Proses RBDPO | E42: =SUM(E45,E49,E54,E58,E68) -> 0
B43: Sisa Filling Crystalizer | E43: =E40-E42 -> 392100
B44: Fractionation OLEIN IV 56
B45: RBDPO Consume | E45: =E46+E47 -> 0
B46: OLEIN IV 56 | E46: 0
B47: STEARIN | E47: 0
B48: Fractionation OLEIN IV 57 ( Bulk )
B49: RBDPO Consume | E49: =E50+E51 -> 0
B50: OLEIN IV 57 | E50: 0
B51: STEARIN | E51: 0
B52: Fractionation OLEIN IV 57 ( Retail )
B53: CPO Consume
B54: RBDPO Brand Consume | E54: =E55+E56 -> 0
B55: OLEIN IV 57 Low Color | E55: 0
B56: STEARIN | E56: 0
B57: Fractionation OLEIN IV 58 ( Bulk )
B58: RBDPO Consume | C58: =C59+C60 -> 21429000 | E58: =E59+E60 -> 0
B59: OLEIN IV 58 | C59: 15000000
B60: STEARIN | C60: 6429000
B61: Fractionation OLEIN IV 58 ( Retail )
B62: CPO Consume
B63: RBDPO Consume | C63: =C64+C65 -> 21429000 | E63: =E64+E65 -> 0
B64: OLEIN IV 58 | C64: 15000000 | E64: 0
B65: STEARIN | C65: 6429000 | E65: 0
B66: Fractionation OLEIN IV 60
B67: CPO Consume
B68: RBDPO Brand Consume | E68: =E70+E71 -> 0
B69: OLEIN IV 60 Bulk | E69: 0
B70: OLEIN IV 60 Salvaco | E70: 0
B71: SOFT STEARIN | E71: 0
B72: Ratio Run RBDPO | E72: 0
B73: YIELD
B74: RBDPO | C74: 94.2 | E74: =(E27/(E14))*100 -> 91.308588
B75: PFAD | C75: 5 | E75: =(E36/(E14))*100 -> 4.2316951
B76: Olein IV 56 | C76: 82 | E76: =E46/(E46+E47)*100 -> #DIV/0!
B77: Stearin | C77: 18 | E77: =(E47/E45)*100 -> #DIV/0!
B78: Olein IV 57 ( Bulk ) | C78: 75 | E78: =(E50/E49)*100 -> #DIV/0!
B79: Stearin | C79: 25 | E79: =(E51/E49)*100 -> #DIV/0!
B80: Olein IV 57 ( Retail ) | C80: 75 | E80: =E55/E54*100 -> #DIV/0!
B81: Stearin | C81: 25 | E81: =E56/E54*100 -> #DIV/0!
B82: Olein IV 58 ( Bulk ) | C82: 70 | E82: =E59/(E59+E60)*100 -> #DIV/0!
B83: Stearin | C83: 30 | E83: =E60/(E60+E59)*100 -> #DIV/0!
B84: Olein IV 58 ( Retail ) | C84: 70 | E84: =E64/(E64+E65)*100 -> #DIV/0!
B85: Stearin | C85: 30 | E85: =E65/(E64+E65)*100 -> #DIV/0!
B86: Olein IV 60 | C86: 60 | E86: =E69/E68*100 -> #DIV/0!
B87: Soft Stearin | C87: 40 | E87: =E71/E68*100 -> #DIV/0!
B88: - FFA | C88: ~93 | D88: % | G88: 90.21
B89: - Moist & Impurities | C89: 0.5 | D89: % | G89: 0.33
A90: 2 | B90: CHEMICAL CONSUMABLE | E90: BEFORE | F90: AFTER | G90: TOTAL | H90: ( % )
B91: Bleaching Earth (BE) to Poram Spec | C91: 9 | D91: kg | E91: 122737 | F91: 143761 | G91: =F91-E91 -> 21024 | H91: =G91/G14/10 -> 0.83441816 | I91: OK
E92: =E91/(E16)*100 -> #DIV/0!
B93: Bleaching Earth (BE) to Branded Spec | C93: 18 | E93: 0
E94: =E93/(E17)*100 -> #DIV/0! | I94: OK
B95: Phosporic Acid (PA) | C95: 0,4 - 0,5 | D95: kg | E95: 1970.8 | F95: 867.36 | G95: =E95-F95 -> 1103.44 | H95: =G95/G14/10 -> 0.043794253 | I95: OK
A97: 3 | B97: OIL LOSSES | C97: - 0,8 | D97: % | H97: =((SUM(G27+G36))-(SUM(G14)))/(SUM(G14))*100 -> -2.7190824
H98: =H97%*G14 -> -68.51
B99: % Oil Content | C99: 20 to 21 | D99: %
B100: Spent Bleaching Earth | H100: =SUM(G91,G93)+(H99%*SUM(G91,G93)) -> 21024
A101: 4 | B101: PACKAGING (Brand Salvaco)
B102: Olein IV 60 Received
...

Sheet peformance  test REFINERY 2
A1: REFINERY PMG 2
A2: No | B2: ITEM | C2: Norma LIPICO | D2: UOM | E2: Day 2 tanggal 12/12/2024
A4: 1 | B4: PRODUCTION | E4: BEFORE | F4: AFTER | G4: TOTAL | H4: Yield ( % )
B5: Refinery
B6: Running Days
B7: Incoming CPO
B8: Ratio Run CPO
B9: CPO Consume Total | C9: 2500 | D9: TPD | E9: 5880.74 | F9: 8383.74 | G9: =F9-E9 -> 2503 | H9: =G9/2500000*100000 -> 100.12
B10: Avg Daily Consump CPO ( MTD )
B11: CPO Consume Poram | C11: 29045000
B12: CPO Consume Brand | C12: 7314000 | E12: =E43+E52+E57 -> 0
B13: - FFA | C13: 5 | D13: % | G13: 3.97
B14: - Moist & Impurities | C14: 0.5 | D14: % | G14: 0.4
B15: - DOBI | C15: 2.2 | D15: Min | G15: 2.42
B16: TANK | G16: 105
B17: Product
B18: OIP RBDPO
B19: RBDPO | C19: =C9*94.2% -> 2355 | D19: TPD | E19: 5143.38 | F19: 7493.18 | G19: =F19-E19 -> 2349.8 | H19: =G19/G9*100 -> 93.879345
B20: - FFA | C20: 0.05 | D20: % | G20: 0.043
B21: - Moist & Impurities | C21: 0.03 | D21: % | G21: 0.04
B22: - LC | C22: 2.5 | D22: % | G22: 2.5
B23: - Aom stability min ( hr ) | C23: 60 | D23: min ( hr )
B24: - teste & Odor | C24: bland/Odorless
B25: - temp max ( C ) | C25: 50 | D25: max˚C
B26: PFAD | C26: =C9*5% -> 125 | D26: TPD | E26: 243.04 | F26: 347.1 | G26: =F26-E26 -> 104.06 | H26: =G26/G9*100 -> 4.1574111
B27: Fractionation
B28: Running Days
B29: Filling Langsung CR Fr Refinery | E29: 0
B30: Total Filling Crystalizer ( Feed ) | E30: 392100
B31: Avg Daily Consump RPO ( MTD )
B32: Total Proses RBDPO | E32: =SUM(E35,E39,E44,E48,E58) -> 0
B33: Sisa Filling Crystalizer | E33: =E30-E32 -> 392100
B34: Fractionation OLEIN IV 56
B35: RBDPO Consume | E35: =E36+E37 -> 0
B36: OLEIN IV 56 | E36: 0
B37: STEARIN | E37: 0
B38: Fractionation OLEIN IV 57 ( Bulk )
B39: RBDPO Consume | E39: =E40+E41 -> 0
B40: OLEIN IV 57 | E40: 0
B41: STEARIN | E41: 0
B42: Fractionation OLEIN IV 57 ( Retail )
B43: CPO Consume
B44: RBDPO Brand Consume | E44: =E45+E46 -> 0
B45: OLEIN IV 57 Low Color | E45: 0
B46: STEARIN | E46: 0
B47: Fractionation OLEIN IV 58 ( Bulk )
B48: RBDPO Consume | C48: =C49+C50 -> 21429000 | E48: =E49+E50 -> 0
B49: OLEIN IV 58 | C49: 15000000
B50: STEARIN | C50: 6429000
B51: Fractionation OLEIN IV 58 ( Retail )
B52: CPO Consume
B53: RBDPO Consume | C53: =C54+C55 -> 21429000 | E53: =E54+E55 -> 0
B54: OLEIN IV 58 | C54: 15000000 | E54: 0
B55: STEARIN | C55: 6429000 | E55: 0
B56: Fractionation OLEIN IV 60
B57: CPO Consume
B58: RBDPO Brand Consume | E58: =E60+E61 -> 0
B59: OLEIN IV 60 Bulk | E59: 0
B60: OLEIN IV 60 Salvaco | E60: 0
B61: SOFT STEARIN | E61: 0
B62: Ratio Run RBDPO | E62: 0
B63: YIELD
B64: RBDPO | C64: 94.2 | E64: =(E19/(E9))*100 -> 87.461442
B65: PFAD | C65: 5 | E65: =(E26/(E9))*100 -> 4.1328132
B66: Olein IV 56 | C66: 82 | E66: =E36/(E36+E37)*100 -> #DIV/0!
B67: Stearin | C67: 18 | E67: =(E37/E35)*100 -> #DIV/0!
B68: Olein IV 57 ( Bulk ) | C68: 75 | E68: =(E40/E39)*100 -> #DIV/0!
B69: Stearin | C69: 25 | E69: =(E41/E39)*100 -> #DIV/0!
B70: Olein IV 57 ( Retail ) | C70: 75 | E70: =E45/E44*100 -> #DIV/0!
B71: Stearin | C71: 25 | E71: =E46/E44*100 -> #DIV/0!
B72: Olein IV 58 ( Bulk ) | C72: 70 | E72: =E49/(E49+E50)*100 -> #DIV/0!
B73: Stearin | C73: 30 | E73: =E50/(E50+E49)*100 -> #DIV/0!
B74: Olein IV 58 ( Retail ) | C74: 70 | E74: =E54/(E54+E55)*100 -> #DIV/0!
B75: Stearin | C75: 30 | E75: =E55/(E54+E55)*100 -> #DIV/0!
B76: Olein IV 60 | C76: 60 | E76: =E59/E58*100 -> #DIV/0!
B77: Soft Stearin | C77: 40 | E77: =E61/E58*100 -> #DIV/0!
B78: - FFA | C78: ~93 | D78: % | G78: 90.62
B79: - Moist & Impurities | C79: 0.5 | D79: % | G79: 0.33
A80: 2 | B80: CHEMICAL CONSUMABLE | E80: BEFORE | F80: AFTER | G80: TOTAL | H80: ( % )
B81: Bleaching Earth (BE) to Poram Spec | C81: 9 | D81: kg | E81: 51223 | F81: 74245 | G81: =F81-E81 -> 23022 | H81: =G81/G9/10 -> 0.91977627
E82: =E81/(E11)*100 -> #DIV/0!
B83: Bleaching Earth (BE) to Branded Spec | C83: 18 | E83: 0
E84: =E83/(E12)*100 -> #DIV/0!
B85: Phosporic Acid (PA) | C85: 0,4 - 0,5 | D85: kg | E85: 539.5 | F85: 1342.1 | G85: =F85-E85 -> 802.6 | H85: =G85/G9/10 -> 0.032065521
A87: 3 | B87: OIL LOSSES | C87: - 0,8 | D87: % | G87: =((SUM(G19+G26))-(SUM(G9)))/(SUM(G9))*100 -> -1.9632441
G88: =G87%*G9 -> -49.14
B89: % Oil Content | C89: 20 to 21 | D89: % | G89: 21.66
B90: Spent Bleaching Earth | G90: =SUM(G81,G83)+(G89%*SUM(G81,G83)) -> 28008.565
A91: 4 | B91: PACKAGING (Brand Salvaco)
B92: Olein IV 60 Received
B93: Olein IV 60 Consume
B94: - finished product | E94: 0
B95: - sample | E95: 0
B96: - remelt, flushing, downgrade | E96: 0
B97: Carton
B98: Salvaco 1 Liter
B99: Salvaco 2 Liter
B100: Pouch
B101: Salvaco 1 Liter | E101: 0
B102: Salvaco 2 Liter | E102: 0
...

Sheet HPP REF 
B2: Refinery Cost
B3: Through Put CPO Proses | N3: =('Februari 2026 PMG 2'!AJ10)/1000 -> 2169.1977 | O3: TPD
B4: Working Day | N4: ='Februari 2026 PMG 2'!AJ6 -> 28 | O4: Days
B5: Total CPO Process | N5: =N4*N3 -> 60737.537 | O5: MTD
B6: KURS | N6: 16000 | O6: Rp/USD
B7: No | C7: Item Cost | D7: Norma | F7: Pemakaian / Hari | H7: HK | J7: Total Pemakaian | K7: Harga / stn | M7: Total Biaya | N7: Rp / kg | O7: USD/MT
B8: 1 | C8: Bleaching Earth | D8: ='Februari 2026 PMG 2'!$AJ$76 -> 0.53000832 | F8: =($D$8*$N$3*10) -> 11496.929 | G8: Kg/day | H8: =$N$4 -> 28 | J8: =$H$8*$F$8 -> 321914 | K8: 4550 | M8: =$J$8*$K$8 -> 1464708700 | N8: =$M$8/($N$5*1000) -> 24.115379 | O8: =($M$8/$N$6)/$N$5 -> 1.5072112
B9: 2 | C9: Phosporic acid | D9: ='Februari 2026 PMG 2'!$AJ$87 -> 0.53263842 | F9: =($D$9*$N$3*10) -> 11553.981 | G9: Kg/day | H9: =$H$8 -> 28 | J9: =$H$9*$F$9 -> 323511.46 | K9: 17420 | M9: =$J$9*$K$9 -> 5.6355696e+09 | N9: =$M$9/($N$5*1000) -> 92.785614 | O9: =($M$9/$N$6)/$N$5 -> 5.7991008
B10: 3 | C10: Caustic Soda | D10: 29.166667 | E10: kg/day | F10: =D10 -> 29.166667 | G10: kg/day | H10: =$H$8 -> 28 | J10: =$H$10*$F$10 -> 816.66667 | K10: 15700 | M10: =$J$10*$K$10 -> 12821667 | N10: =$M$10/($N$5*1000) -> 0.21109955 | O10: =($M$10/$N$6)/$N$5 -> 0.013193722
B11: 4 | C11: Pemakaian Natural Gas HPB Geka
C12: Normal Consumption | D12: ='Februari 2026 PMG 2'!$AJ$249 -> 0.10726318 | E12: MMBTU/MT CPO | F12: =$D$12*$N$3 -> 232.67504 | G12: MMBTU/day | H12: =$H$8 -> 28 | J12: =$H$12*$F$12 -> 6514.9012 | K12: =11.5*$N$6 -> 184000 | M12: =$J$12*$K$12 -> 1.1987418e+09 | N12: =$M$12/($N$5*1000) -> 19.736425 | O12: =($M$12/$N$6)/$N$5 -> 1.2335265
C13: Penalty Below Consumption | D13: 0 | E13: MMBTU/MT CPO | F13: =$D$13*$N$3 -> 0 | G13: MMBTU/day | H13: =$H$8 -> 28 | J13: =$H$13*$F$13 -> 0 | K13: =11.5*$N$6 -> 184000 | M13: =$J$13*$K$13 -> 0 | N13: =$M$13/($N$5*1000) -> 0 | O13: =($M$13/$N$6)/$N$5 -> 0
C14: Penalty Above Consumption | D14: 0 | E14: MMBTU/MT CPO | F14: =$D$14*$N$3 -> 0 | G14: MMBTU/day | H14: =$H$8 -> 28 | J14: =$H$14*$F$14 -> 0 | K14: =11.5*$N$6 -> 184000 | M14: =$J$14*$K$14 -> 0 | N14: =$M$14/($N$5*1000) -> 0 | O14: =($M$14/$N$6)/$N$5 -> 0
B15: 5 | C15: Pemakaian Steam
C16: For Process | D16: ='Februari 2026 PMG 2'!AJ256 -> 4382.6077 | E16: Kg/MT CPO | F16: =$D$16*$N$3/1000 -> 9506.7429 | G16: Ton/day | H16: =$H$8 -> 28 | J16: =$H$16*$F$16 -> 266188.8 | K16: =Steam!H15 -> 187.90511 | M16: =$J$16*$K$16 -> 50018236 | N16: =$M$16/($N$5*1000) -> 0.82351439 | O16: =($M$16/$N$6)/$N$5 -> 0.051469649
C17: Storage Tank for Heating | D17: ='Februari 2026 PMG 2'!$AJ$260 -> 9624.3039 | E17: Kg/MT CPO | F17: =$D$17*$N$3/1000 -> 20877.018 | G17: Ton/day | H17: =$H$8 -> 28 | J17: =$H$17*$F$17 -> 584556.52 | K17: =Steam!H15 -> 187.90511 | M17: =$J$17*$K$17 -> 1.0984116e+08 | N17: =$M$17/($N$5*1000) -> 1.8084559 | O17: =($M$17/$N$6)/$N$5 -> 0.11302849
B18: 6 | C18: Pemakaian Electrical
C19: For Process | D19: ='Februari 2026 PMG 2'!$AJ$297 -> 6.3594116 | E19: kW/MT CPO | F19: =$D$19*$N$3 -> 13794.821 | G19: kW/day | H19: =$H$8 -> 28 | I19: 0 | J19: =$H$19*$F$19 -> 386255 | K19: 1550 | L19: =[2]Electric!H21 -> 3666.6667 | M19: =($F$19*$H$19*$K$19)+($F$19*$I$19*$L$19) -> 598695250 | N19: =$M$19/($N$5*1000) -> 9.857088 | O19: =($M$19/$N$6)/$N$5 -> 0.616068
C20: Cooling Tower | D20: ='Februari 2026 PMG 2'!$AJ$299 -> 4.9299167 | E20: kW/MT CPO | F20: =$D$20*$N$3 -> 10693.964 | G20: kW/day | H20: =$H$8 -> 28 | I20: 0 | J20: =$H$20*$F$20 -> 299431 | K20: 1550 | L20: =L19 -> 3666.6667 | M20: =(F20*H20*K20)+(F20*I20*L20) -> 4.6411805e+08 | N20: =$M$20/($N$5*1000) -> 7.6413709 | O20: =($M$20/$N$6)/$N$5 -> 0.47758568
C21: Storage Tank | D21: 0.3377877 | E21: kW/MT CPO | F21: =$D$21*$N$3 -> 732.72832 | G21: kW/day | H21: =$H$8 -> 28 | I21: 0 | J21: =$H$21*$F$21 -> 20516.393 | K21: 1550 | L21: =L20 -> 3666.6667 | M21: =($F$21*$H$21*$K$21)+($F$21*$I$21*$L$21) -> 31800409 | N21: =$M$21/($N$5*1000) -> 0.52357093 | O21: =($M$21/$N$6)/$N$5 -> 0.032723183
B22: 7 | C22: Pemakaian Water
C23: Make Up CT | D23: ='Februari 2026 PMG 2'!$AJ$274 -> 0.11254984 | E23: M3/day | F23: =$D$23 -> 0.11254984 | G23: M3/day | H23: =$H$8 -> 28 | J23: =$H$23*$F$23 -> 3.1513955 | K23: =WTP!H13 -> 23503.384 | M23: =$J$23*$K$23 -> 74068.459 | N23: =$M$23/($N$5*1000) -> 0.0012194841 | O23: =($M$23/$N$6)/$N$5 -> 7.6217754e-05
B24: 8 | C24: Chemical Water | N24: =$M$24/($N$5*1000) -> 0 | O24: =($M$24/$N$6)/$N$5 -> 0
C25: EONBAC BC 3108 | D25: 0.4 | E25: Kg/day | F25: =D25 -> 0.4 | G25: Kg/day | H25: =$H$8 -> 28 | J25: =$H$25*$F$25 -> 11.2 | K25: 27240 | M25: =$J$25*$K$25 -> 305088 | N25: =$M$25/($N$5*1000) -> 0.0050230552 | O25: =($M$25/$N$6)/$N$5 -> 0.00031394095
C26: EONLINE T722 | D26: 0.66 | E26: Kg/day | F26: =D26 -> 0.66 | G26: Kg/day | H26: =$H$8 -> 28 | J26: =$H$26*$F$26 -> 18.48 | K26: 29120 | M26: =$J$26*$K$26 -> 538137.6 | N26: =$M$26/($N$5*1000) -> 0.0088600498 | O26: =($M$26/$N$6)/$N$5 -> 0.00055375311
C27: EONLINE AG5770 | D27: 0.41 | E27: Kg/day | F27: =D27 -> 0.41 | G27: Kg/day | H27: =$H$8 -> 28 | J27: =$H$27*$F$27 -> 11.48 | K27: 117212 | M27: =$J$27*$K$27 -> 1345593.8 | N27: =$M$27/($N$5*1000) -> 0.022154237 | O27: =($M$27/$N$6)/$N$5 -> 0.0013846398
C28: EONScale T2511 | D28: 0.1 | E28: Kg/day | F28: =D28 -> 0.1 | G28: Kg/day | H28: =$H$8 -> 28 | J28: =$H$28*$F$28 -> 2.8 | K28: 45940 | M28: =$J$28*$K$28 -> 128632 | N28: =$M$28/($N$5*1000) -> 0.0021178337 | O28: =($M$28/$N$6)/$N$5 -> 0.0001323646
B29: 9 | C29: Others
C30: Filter Bag 10 Microne | D30: 0.90361446 | E30: Pcs/day | F30: =D30 -> 0.90361446 | G30: Pcs/day | H30: =$H$8 -> 28 | J30: =$H$30*$F$30 -> 25.301205 | K30: 40000 | M30: =$J$30*$K$30 -> 1012048.2 | N30: =$M$30/($N$5*1000) -> 0.016662648 | O30: =($M$30/$N$6)/$N$5 -> 0.0010414155
C31: Filter Bag 100 Microne | D31: 0.63253012 | E31: Pcs/day | F31: =D31 -> 0.63253012 | G31: Pcs/day | H31: =$H$8 -> 28 | J31: =$H$31*$F$31 -> 17.710843 | K31: 125000 | M31: =$J$31*$K$31 -> 2213855.4 | N31: =$M$31/($N$5*1000) -> 0.036449542 | O31: =($M$31/$N$6)/$N$5 -> 0.0022780964
C32: Filter Cartridge 10 Microne | D32: 1.5666667 | E32: Pcs/day | F32: =D32 -> 1.5666667 | G32: Pcs/day | H32: =$H$8 -> 28 | J32: =$H$32*$F$32 -> 43.866667 | K32: 145000 | M32: =$J$32*$K$32 -> 6360666.7 | N32: =$M$32/($N$5*1000) -> 0.10472382 | O32: =($M$32/$N$6)/$N$5 -> 0.0065452385
C33: Filter Dustbag | D33: 0.12048193 | E33: Pcs/day | F33: =D33 -> 0.12048193 | G33: Pcs/day | H33: =$H$8 -> 28 | J33: =$H$33*$F$33 -> 3.373494 | K33: 682500 | M33: =$J$33*$K$33 -> 2302409.6 | N33: =$M$33/($N$5*1000) -> 0.037907524 | O33: =($M$33/$N$6)/$N$5 -> 0.0023692202
C34: O Ring Filter Leaves | D34: 3.6144578 | E34: Pcs/day | F34: =D34 -> 3.6144578 | G34: Pcs/day | H34: =$H$8 -> 28 | J34: =$H$34*$F$34 -> 101.20482 | K34: 14500 | M34: =$J$34*$K$34 -> 1467469.9 | N34: =$M$34/($N$5*1000) -> 0.024160839 | O34: =($M$34/$N$6)/$N$5 -> 0.0015100525
B35: 10 | C35: Waste Water Treatment Plant ( WWTP ) | D35: ='Februari 2026 PMG 2'!E279 -> 330 | E35: M3/day | F35: =D35 -> 330 | G35: M3/day | H35: =$H$8 -> 28 | J35: =$H$35*$F$35 -> 9240 | K35: =WWTP!H17 -> 473.92767 | M35: =$J$35*$K$35 -> 4379091.7 | N35: =$M$35/($N$5*1000) -> 0.072098605 | O35: =($M$35/$N$6)/$N$5 -> 0.0045061628
B36: 11 | C36: SHE
C37: SBE | D37: ='Februari 2026 PMG 2'!$AJ$91 -> 323920.17 | E37: Kg/day | F37: =D37 -> 323920.17 | G37: Kg/day | H37: =$H$8 -> 28 | J37: =$F$37 -> 323920.17 | K37: 0 | M37: =$J$37*$K$37 -> 0 | N37: =$M$37/($N$5*1000) -> 0 | O37: =($M$37/$N$6)/$N$5 -> 0
C38: Domestic | D38: 0.1 | E38: Trip/day | F38: =D38 -> 0.1 | G38: Trip/day | H38: =$H$8 -> 28 | J38: =$H$38*$F$38 -> 2.8 | K38: 303030.3 | M38: =$J$38*$K$38 -> 848484.85 | N38: =$M$38/($N$5*1000) -> 0.013969695 | O38: =($M$38/$N$6)/$N$5 -> 0.00087310592
B39: 12 | C39: Chemical Consumption | N39: =$M$39/($N$5*1000) -> 0 | O39: =($M$39/$N$6)/$N$5 -> 0
C40: LAB Chemical | D40: =lab!H33 -> 745255.21 | E40: Rp/day | F40: =D40 -> 745255.21 | G40: Rp/day | H40: =$H$8 -> 28 | M40: =$H$40*$F$40 -> 20867146 | N40: =$M$40/($N$5*1000) -> 0.3435626 | O40: =($M$40/$N$6)/$N$5 -> 0.021472662
C41: Chemical Boiler dan WTP | D41: =lab!H54 -> 259161.44 | E41: Rp/day | F41: =D41 -> 259161.44 | G41: Rp/day | H41: =$H$8 -> 28 | M41: =$H$41*$F$41 -> 7256520.4 | N41: =$M$41/($N$5*1000) -> 0.11947341 | O41: =($M$41/$N$6)/$N$5 -> 0.0074670879
C42: Sample and Analysis | D42: 13909.091 | E42: Rp/day | F42: =D42 -> 13909.091 | G42: Rp/day | H42: =$H$8 -> 28 | M42: =$H$42*$F$42 -> 389454.55 | N42: =$M$42/($N$5*1000) -> 0.0064120899 | O42: =($M$42/$N$6)/$N$5 -> 0.00040075562
C43: Chemical WWTP | D43: =[2]Chemical!$H$61 -> 27103.641 | E43: Rp/day | F43: =D43 -> 27103.641 | G43: Rp/day | H43: =$H$8 -> 28 | M43: =$H$43*$F$43 -> 758901.96 | N43: =$M$43/($N$5*1000) -> 0.012494777 | O43: =($M$43/$N$6)/$N$5 -> 0.00078092354
C44: Consumable Part | D44: =lab!I111 -> 135770.31 | E44: Rp/day | F44: =D44 -> 135770.31 | G44: Rp/day | H44: =$H$8 -> 28 | M44: =$H$44*$F$44 -> 3801568.6 | N44: =$M$44/($N$5*1000) -> 0.062590102 | O44: =($M$44/$N$6)/$N$5 -> 0.0039118814
B45: 13 | C45: Solar
C46: Forklift -1 (3 Ton) | D46: 15.4 | E46: Ltr/day | F46: 0 | G46: Ltr/day | H46: =$H$8 -> 28 | J46: =$H$46*$F$46 -> 0 | K46: 14500 | M46: =$J$46*$K$46 -> 0 | N46: =$M$46/($N$5*1000) -> 0 | O46: =($M$46/$N$6)/$N$5 -> 0
C47: WA Loader | D47: 0 | E47: Ltr/day | F47: =D47 -> 0 | G47: Ltr/day | H47: =$H$8 -> 28 | J47: =$H$47*$F$47 -> 0 | K47: 14500 | M47: =$J$47*$K$47 -> 0 | N47: =$M$47/($N$5*1000) -> 0 | O47: =($M$47/$N$6)/$N$5 -> 0
M48: =SUM($M$8:$M$47) -> 9.6203641e+09 | N48: =SUM($N$8:$N$47) -> 158.3924 | O48: =SUM($O$8:$O$47) -> 9.8995248

Sheet HPP FRACT
B2: Fractionation Cost
B3: RPO Proses / Day | N3: TPD | O3: ='Februari 2026 PMG 2'!AJ24/1000 -> 1759.9365
B4: Working Day | N4: Days | O4: ='Februari 2026 PMG 2'!AJ23 -> 28
B5: Total CPO Process | N5: MTD | O5: =O3*O4 -> 49278.223
B6: KURS | N6: Rp/USD | O6: 16000
B7: No | C7: Item Cost | D7: Norma | F7: Pemakaian / Hari | H7: HK | J7: Total Pemakaian | K7: Harga / stn | M7: Total Biaya | N7: Rp / kg | O7: USD/MT
B8: 1 | C8: Steam | D8: ='Februari 2026 PMG 2'!AJ258 -> 2347.1092 | E8: Kg/MT CPO | F8: =$D$8*$O$3/1000 -> 4130.7632 | G8: Ton/day | H8: =$O$4 -> 28 | J8: =$H$8*$F$8 -> 115661.37 | K8: =Steam!H15 -> 187.90511 | M8: =$K$8*$J$8 -> 21733362 | N8: =$M$8/($O$5*1000) -> 0.44103381 | O8: =($M$8/$O$6)/$O$5 -> 0.027564613
B9: 2 | C9: Electrical
C10: For Process | D10: ='Februari 2026 PMG 2'!$AJ$304 -> 4.473126 | E10: kW/MT CPO | F10: =$D$10*$O$3 -> 7872.4179 | G10: kW/day | H10: =$O$4 -> 28 | I10: 0 | J10: =$H$10*$F$10 -> 220427.7 | K10: =[2]Electric!$L$5 -> 1550 | L10: 3666.6667 | M10: =($F$10*$H$10*$K$10)+($F$10*$I$10*$L$10) -> 3.4166294e+08 | N10: =$M$10/($O$5*1000) -> 6.9333454 | O10: =($M$10/$O$6)/$O$5 -> 0.43333409
C11: Cooling Tower | D11: ='Februari 2026 PMG 2'!$AJ$302 -> 5.2964689 | E11: kW/MT CPO | F11: =$D$11*$O$3 -> 9321.4491 | G11: kW/day | H11: =$H$10 -> 28 | I11: 0 | J11: =$H$11*$F$11 -> 261000.58 | K11: =$K$10 -> 1550 | L11: 3666.6667 | M11: =($F$11*$H$11*$K$11)+($F$11*$I$11*$L$11) -> 4.0455089e+08 | N11: =$M$11/($O$5*1000) -> 8.2095268 | O11: =($M$11/$O$6)/$O$5 -> 0.51309542
B12: 3 | C12: Water
C13: Make Up CT | D13: ='Februari 2026 PMG 2'!$AJ$276 -> 0.045537356 | E13: M3/day | F13: =$D$13 -> 0.045537356 | G13: M3/day | H13: =$H$11 -> 28 | J13: =$H$13*$F$13 -> 1.275046 | K13: =WTP!H13 -> 23503.384 | M13: =$K$13*$J$13 -> 29967.895 | N13: =$M$13/($O$5*1000) -> 0.00060813669 | O13: =($M$13/$O$6)/$O$5 -> 3.8008543e-05
B14: 4 | C14: Chemical Water
C15: EONBAC BC 3108 | D15: 0.4 | E15: Kg/day | F15: =$D$15 -> 0.4 | G15: Kg/day | H15: =$H$13 -> 28 | J15: =$H$15*$F$15 -> 11.2 | K15: 27240 | M15: =$K$15*$J$15 -> 305088 | N15: =$M$15/($O$5*1000) -> 0.0061911323 | O15: =($M$15/$O$6)/$O$5 -> 0.00038694577
C16: EONLINE T722 | D16: 0.66 | E16: Kg/day | F16: =$D$16 -> 0.66 | G16: Kg/day | H16: =$H$15 -> 28 | J16: =$H$16*$F$16 -> 18.48 | K16: 29120 | M16: =$K$16*$J$16 -> 538137.6 | N16: =$M$16/($O$5*1000) -> 0.010920394 | O16: =($M$16/$O$6)/$O$5 -> 0.00068252461
C17: EONLINE AG5770 | D17: 0.41 | E17: Kg/day | F17: =$D$17 -> 0.41 | G17: Kg/day | H17: =$H$15 -> 28 | J17: =$H$17*$F$17 -> 11.48 | K17: 117212 | M17: =$K$17*$J$17 -> 1345593.8 | N17: =$M$17/($O$5*1000) -> 0.027306053 | O17: =($M$17/$O$6)/$O$5 -> 0.0017066283
C18: EONScale T2511 | D18: 0.1 | E18: Kg/day | F18: =$D$18 -> 0.1 | G18: Kg/day | H18: =$H$16 -> 28 | J18: =$H$18*$F$18 -> 2.8 | K18: 45940 | M18: =$K$18*$J$18 -> 128632 | N18: =$M$18/($O$5*1000) -> 0.0026103214 | O18: =($M$18/$O$6)/$O$5 -> 0.00016314509
B19: 5 | C19: Others
C20: Filter Cloth | D20: 0.33333333 | E20: Pcs/day | F20: =$D$20 -> 0.33333333 | G20: Pcs/day | H20: =$H$18 -> 28 | J20: =$H$20*$F$20 -> 9.3333333 | K20: 895000 | M20: =$K$20*$J$20 -> 8353333.3 | N20: =$M$20/($O$5*1000) -> 0.16951369 | O20: =($M$20/$O$6)/$O$5 -> 0.010594606
C21: Filter Bag 100 Microne | D21: 0.63253012 | E21: Pcs/day | F21: =$D$21 -> 0.63253012 | G21: Pcs/day | H21: =$H$20 -> 28 | J21: =$H$21*$F$21 -> 17.710843 | K21: 125000 | M21: =$K$21*$J$21 -> 2213855.4 | N21: =$M$21/($O$5*1000) -> 0.044925634 | O21: =($M$21/$O$6)/$O$5 -> 0.0028078521
M22: =SUM(M8:M21) -> 7.808618e+08 | N22: =SUM(N8:N21) -> 15.845981 | O22: =SUM($O$8:$O$21) -> 0.99037383

Sheet SUMMARY HPP 
B2: Production Cost OKTOBER 2025
B3: Through Put CPO Proses (Ton/Day) | H3: TPD | I3: ='HPP REF '!$N$3 -> 2169.1977
B4: Working Day | F4: 1 | H4: Days | I4: ='HPP REF '!$N$4 -> 28
B5: Refined CPO ( Ton/month ) | H5: MTD | I5: =$I$4*$I$3 -> 60737.537
B6: Through Put RPO Proses (Ton/Day) | H6: TPD | I6: ='HPP FRACT'!$O$3 -> 1759.9365
B7: Working Day | H7: Days | I7: ='HPP FRACT'!$O$4 -> 28
B8: Fract RPO ( ton/month ) | H8: MTD | I8: =$I$7*$I$6 -> 49278.223
B9: KURS | H9: Rp/USD | I9: 16000
B10: No | C10: Items | D10: Description | G10: Rupiah | H10: Rp/Kg | I10: USD/MT
B11: I | C11: Production Cost | D11: ● | E11: Refining Cost | G11: ='HPP REF '!$M$48 -> 9.6203641e+09 | H11: =$G$11/($I$5*1000) -> 158.3924 | I11: =(G11/$I$9)/$I$5 -> 9.8995248
D12: ● | E12: Fractionation Cost | G12: ='HPP FRACT'!$M$22 -> 7.808618e+08 | H12: =$G$12/($I$8*1000) -> 15.845981 | I12: =(G12/$I$9)/$I$8 -> 0.99037383
D13: ● | E13: Preventive Maintenance Cost | F13: 0 | G13: =MTC!$F$18*F13 -> 0 | H13: =$G$13/($I$5*1000) -> 0 | I13: =(G13/$I$9)/$I$5 -> 0
G14: =SUM(G11:$G$13) -> 1.0401226e+10 | H14: =SUM($H$11:$H$13) -> 174.23838 | I14: =SUM(I11:I13) -> 10.889899
B16: II | C16: Port Cost | D16: ● | E16: Trucking Komoditi ke Kuala Tanjung | G16: =LOG!I8+LOG!I9+LOG!$I$10 -> 6.306014e+09 | H16: =$G$16/($I$5*1000) -> 103.824 | I16: =($G$16/$I$9)/$I$5 -> 6.489
D17: ● | E17: Sewa Tank PTI Total Volume : 24.000 MT ( 5 Unit ) | F17: =F4 -> 1 | G17: =LOG!I11+LOG!I12+LOG!I13+LOG!$I$14*F17 -> 1886000000 | H17: =$G$17/($I$5*1000) -> 31.051638 | I17: =($G$17/$I$9)/$I$5 -> 1.9407274
D18: ● | E18: Instalasi & Pemanasan, Pompa, Surveyor dan Documen | G18: =LOG!I18+LOG!I19+LOG!I20+LOG!$I$21 -> 3.2535884e+09 | H18: =$G$18/($I$5*1000) -> 53.568 | I18: =($G$18/$I$9)/$I$5 -> 3.348
D19: ● | E19: Finalty Over Capacity Tank | G19: =LOG!I15+LOG!I16+LOG!$I$17 -> 2.5908204e+09 | H19: =$G$19/($I$5*1000) -> 42.656 | I19: =($G$19/$I$9)/$I$5 -> 2.666
G20: =SUM($G$16:$G$19) -> 1.4036423e+10 | H20: =SUM($H$16:$H$19) -> 231.09964 | I20: =SUM($I$16:$I$19) -> 14.443727
B22: II | C22: Fix Cost | D22: ● | E22: Manpower Cost | F22: =F4 -> 1 | G22: =[2]MPC!$H$29*$F$22 -> 2.1846655e+09 | H22: =$G$22/($I$5*1000) -> 35.968952 | I22: =($G$22/$I$9)/$I$5 -> 2.2480595
D23: ● | E23: Admin OH Cost | F23: =F4 -> 1 | G23: =OH!G51*$F$23 -> 1.4360564e+09 | H23: =$G$23/($I$5*1000) -> 23.643639 | I23: =($G$23/$I$9)/$I$5 -> 1.4777274
D24: ● | E24: Depresiasi Cost | F24: =F4 -> 1 | G24: =DEP!I9*$F$24 -> 4.1811848e+09 | H24: =$G$24/($I$5*1000) -> 68.84021 | I24: =($G$24/$I$9)/$I$5 -> 4.3025131
D25: ● | E25: Amortisation of leasehold land Cost | F25: =F4 -> 1 | G25: =AMOR!$G$20*$F$25 -> 1.0484098e+09 | H25: =$G$25/($I$5*1000) -> 17.261316 | I25: =($G$25/$I$9)/$I$5 -> 1.0788322
G26: =SUM($G$22:$G$25) -> 8.8503165e+09 | H26: =SUM($H$22:$H$25) -> 145.71412 | I26: =SUM($I$22:$I$25) -> 9.1071323
B28: Total Production Cost | G28: =$G$26+$G$20+$G$14 -> 3.3287965e+10 | H28: =$H$26+$H$20+$H$14 -> 551.05213 | I28: =$I$26+$I$20+$I$14 -> 34.440758

Sheet Lembar1

Sheet OIP Fract PMG 1
A4: Oil In Plant (OIP) Fraksinasi | I4: OIP | S4: BUFFER TANK | W4: DIRECT
A5: RBDPO OIP | I5: RPO CR | M5: OLEIN | P5: STEARIN | S5: TK131 RPO | U5: TK132 RPO
A6: Vessel | B6: Operating Volume (m3) | C6: Oil Density (kg/m3) | D6: MT | E6: Level Transmitter (1%/MT) | F6: Level (%) | G6: Kg | I6: Tanggal | J6: Opening Stock | K6: Closing Stock | L6: balance stok | M6: Opening Stock | N6: Closing Stock | O6: balance stok | P6: Opening Stock | Q6: Closing Stock | R6: balance stok | S6: Opening Stock | T6: Closing Stock | U6: Opening Stock | V6: Closing Stock
A7: 2CR1201 | B7: 70.51 | C7: 890 | D7: 60 | E7: =D7/100 -> 0.6 | F7: 0 | G7: =E7*F7*1000 -> 0 | I7: 46054
A8: 2CR1202 | B8: 70.51 | C8: 890 | D8: 60 | E8: =D8/100 -> 0.6 | F8: 0 | G8: =E8*F8*1000 -> 0 | I8: 46055
A9: 2CR1203 | B9: 70.51 | C9: 890 | D9: 60 | E9: =D9/100 -> 0.6 | F9: 0 | G9: =E9*F9*1000 -> 0 | I9: 46056
A10: 2CR1204 | B10: 70.51 | C10: 890 | D10: 60 | E10: =D10/100 -> 0.6 | F10: 0 | G10: =E10*F10*1000 -> 0 | I10: 46057
A11: 2CR1205 | B11: 70.51 | C11: 890 | D11: 60 | E11: =D11/100 -> 0.6 | F11: 0 | G11: =E11*F11*1000 -> 0 | I11: 46058
A12: 2CR1206 | B12: 70.51 | C12: 890 | D12: 60 | E12: =D12/100 -> 0.6 | F12: 0 | G12: =E12*F12*1000 -> 0 | I12: 46059
A13: 2CR1207 | B13: 70.51 | C13: 890 | D13: 60 | E13: =D13/100 -> 0.6 | F13: 0 | G13: =E13*F13*1000 -> 0 | I13: 46060
A14: 2CR1208 | B14: 70.51 | C14: 890 | D14: 60 | E14: =D14/100 -> 0.6 | F14: 0 | G14: =E14*F14*1000 -> 0 | I14: 46061
A15: 2CR1209 | B15: 70.51 | C15: 890 | D15: 60 | E15: =D15/100 -> 0.6 | F15: 0 | G15: =E15*F15*1000 -> 0 | I15: 46062
A16: 2CR1210 | B16: 70.51 | C16: 890 | D16: 60 | E16: =D16/100 -> 0.6 | F16: 0 | G16: =E16*F16*1000 -> 0 | I16: 46063
A17: 2CR1211 | B17: 70.51 | C17: 890 | D17: 60 | E17: =D17/100 -> 0.6 | F17: 0 | G17: =E17*F17*1000 -> 0 | I17: 46064
A18: 2CR1212 | B18: 70.51 | C18: 890 | D18: 60 | E18: =D18/100 -> 0.6 | F18: 0 | G18: =E18*F18*1000 -> 0 | I18: 46065
... A21: 2CR1215 | B21: 70.51 | C21: 890 | D21: 60 | E21: =D21/100 -> 0.6 | F21: 0 | G21: =E21*F21*1000 -> 0 | I21: 46068
I22: 46069
F23: Total RBDPO | G23: =SUM(G7:G21) -> 0 | I23: 46070
I24: 46071
A25: Olein OIP | I25: 46072 | J25: =K24 -> 0 | K25: 394320 | M25: =N24 -> 0 | N25: 26250
A26: Vessel | B26: Operating Volume (m3) | C26: Oil Density (kg/m3) | D26: MT | E26: Level Transmitter (1%/MT) | F26: Level (%) | G26: Kg | I26: 46073 | J26: =K25 -> 394320 | K26: 449900 | M26: =N25 -> 26250 | N26: 21050
A27: 2TK261 | B27: 15.95 | C27: 885 | D27: =B27*C27/1000 -> 14.11575 | E27: =D27/100 -> 0.1411575 | G27: =E27*F27*1000 -> 0 | I27: 46074 | J27: =K26 -> 449900 | K27: 388000 | M27: =N26 -> 21050 | N27: 33600
A28: 2CL251 | B28: 3.02 | C28: 885 | D28: =B28*C28/1000 -> 2.6727 | E28: =D28/100 -> 0.026727 | G28: =E28*F28*1000 -> 0 | I28: 46075 | J28: =K27 -> 388000 | K28: 226400 | M28: =N27 -> 33600 | N28: 25980
A29: 2TK221 | B29: 82.48 | C29: 885 | D29: =B29*C29/1000 -> 72.9948 | E29: =D29/100 -> 0.729948 | G29: =E29*F29*1000 -> 0 | I29: 46076 | J29: =K28 -> 226400 | K29: 15960 | M29: =N28 -> 25980 | N29: 26050
A30: 2TK241 | B30: 16.95 | C30: 885 | D30: =B30*C30/1000 -> 15.00075 | E30: =D30/100 -> 0.1500075 | G30: =E30*F30*1000 -> 0 | I30: 46077 | J30: =K29 -> 15960 | K30: 506180 | M30: =N29 -> 26050 | N30: 26050
F31: Total Olein | G31: =SUM(G27:G30) -> 0 | I31: 46078 | J31: =K30 -> 506180 | K31: 398700 | M31: =N30 -> 26050 | N31: 26470
I32: 46079 | J32: =K31 -> 398700 | K32: 388950 | M32: =N31 -> 26470 | N32: 40850
I33: 46080 | J33: =K32 -> 388950 | M33: =N32 -> 40850
I34: 46081 | J34: =K33 -> 0 | M34: =N33 -> 0
A39: Stearin OIP
A40: Melting Tank | B40: Panjang (m) | C40: Lebar (m) | D40: tinggi (m) | E40: Density | F40: Tinggi Sounding (Cm) Maks 4,4 m | G40: Kg
A41: TK231 A | B41: 12.2 | C41: 1.75 | D41: 1.52 | E41: 0.88 | F41: 0 | G41: =B41*C41*D41*E41*F41/100 -> 0
A42: TK231 B | B42: 12.2 | C42: 1.75 | D42: 1.52 | E42: 0.88 | F42: 0 | G42: =B42*C42*D42*E42*F42/100 -> 0
F43: Total STEARIN | G43: =SUM(G41:G42) -> 0

Sheet Februari 2026 PMG 2
C1: PRODUCTION REPORT PMG 2
C2: No | D2: ITEM | E2: Budget / Norma | F2: UoM | G2: Februari 2026 | AJ2: TOTAL MONTHLY (Kg)
G3: 1 | H3: 2 | I3: 3 | J3: 4 | K3: 5 | L3: 6 | M3: 7 | N3: 8 | O3: 9 | P3: 10 | Q3: 11 | R3: 12 | S3: 13 | T3: 14 | U3: 15 | V3: 16 | W3: 17 | X3: 18 | Y3: 19 | Z3: 20 | AA3: 21 | AB3: 22 | AC3: 23 | AD3: 24 | AE3: 25 | AF3: 26 | AG3: 27 | AH3: 28
C4: 1 | D4: PRODUCTION | AJ4: Production | AL4: aktual refinery | AO4: opening stok rpo | AP4: =AP6+AP7+AP9 -> 80236
D5: Refinery | AJ5: Refinery | AL5: cpo feed | AM5: =AJ9 -> 60737537 | AO5: sisa rbpo tank
D6: Running Days | E6: 24 | F6: Day | G6: 1 | H6: 1 | I6: 1 | J6: 1 | K6: 1 | L6: 1 | M6: 1 | N6: 1 | O6: 1 | P6: 1 | Q6: 1 | R6: 1 | S6: 1 | T6: 1 | U6: 1 | V6: 1 | W6: 1 | X6: 1 | Y6: 1 | Z6: 1 | AA6: 1 | AB6: 1 | AC6: 1 | AD6: 1 | AE6: 1 | AF6: 1 | AG6: 1 | AH6: 1 | AJ6: =SUM(G6:AH6) -> 28 | AL6: rpo prod | AM6: =AJ20+AJ19+AJ18 -> 57977499 | AO6: tk 108 | AP6: 80236
D7: Incoming CPO | F7: Kg | G7: 1565196 | H7: 770270 | I7: 2113786 | J7: 1913843 | K7: 2352974 | L7: 3345000 | M7: 2952195 | N7: 1685073 | O7: 986350 | P7: 2312199 | Q7: 3163913 | R7: 2191531 | S7: 2065679 | T7: 2294814 | U7: 1930209 | V7: 2160626 | W7: 1214092 | X7: 1849690 | Y7: 2351337 | Z7: 2999000 | AA7: 2156902 | AB7: 1660100 | AC7: 1939870 | AD7: 2515085 | AE7: 2408043 | AF7: 2711413 | AG7: 2570464 | AH7: 1934846 | AJ7: =SUM(G7:AH7) -> 60114500 | AR7: =AJ7+'Februari 2026 PMG 1'!AJ7 -> 60114500
D8: Ratio Run CPO ( utilisasi kapasitas ) | F8: % | G8: =G9/2500000 -> 0.8040568 | H8: =H9/2500000 -> 0.8868388 | I8: =I9/2500000 -> 0.8052924 | J8: =J9/2500000 -> 0.8644532 | K8: =K9/2500000 -> 0.8582316 | L8: =L9/2500000 -> 0.730854 | M8: =M9/2500000 -> 0.8053832 | N8: =N9/2500000 -> 0.7657356 | ... AH8: =AH9/2500000 -> 0.8689092 | AJ8: =AJ9/2500000/AJ6 -> 0.8676791
D9: CPO Consume Total | E9: 48093.551 | F9: Kg | G9: 2010142 | H9: 2217097 | I9: 2013231 | J9: 2161133 | K9: 2145579 | L9: 1827135 | M9: 2013458 | N9: 1914339 | O9: 2036210 | P9: 2449732 | Q9: 2207000 | R9: 2040539 | S9: 2078053 | T9: 1585660 | U9: 1776733 | V9: 1933001 | W9: 2446881 | X9: 2548876 | Y9: 2469258 | Z9: 2408490 | AA9: 2376176 | AB9: 2608876 | AC9: 2393732 | AD9: 2274218 | AE9: 2443224 | AF9: 2070039 | AG9: 2116452 | AH9: 2172273 | AJ9: =SUM(G9:AH9) -> 60737537
D10: Avg Daily Consump CPO ( MTD ) | AJ10: =AJ9/AJ6 -> 2169197.8
D11: CPO Consume Poram | F11: Kg | G11: =G9-G12 -> 2010142 | H11: =H9-H12 -> 2217097 | I11: =I9-I12 -> 2013231 | J11: =J9-J12 -> 2161133 | K11: =K9-K12 -> 2145579 | L11: =L9-L12 -> 1827135 | M11: =M9-M12 -> 2013458 | N11: =N9-N12 -> 1914339 | ... AH11: =AH9-AH12 -> 2172273 | AJ11: =SUM(G11:AH11) -> 60737537
D12: CPO Consume Brand | F12: Kg | G12: =G40+G49+G54 -> 0 | H12: =H40+H49+H54 -> 0 | AJ12: =SUM(G12:AH12) -> 0
D13: - FFA | E13: 5 | F13: % | G13: 3.94 | H13: =(3.67+3.95)/2 -> 3.81 | I13: =(4.36+3.7)/2 -> 4.03 | J13: 3.71 | K13: =(4.15+4.21)/2 -> 4.18 | L13: =(4.1+4.22)/2 -> 4.16 | M13: 4.25 | N13: =(4.2+3.98)/2 -> 4.09 | O13: 4.11 | P13: =(4.12+4.01)/2 -> 4.065 | Q13: =(4.01+3.95)/2 -> 3.98 | R13: 3.96 | S13: =(3.95+4)/2 -> 3.975 | T13: 4.01 | U13: 4.01 | V13: 3.95 | W13: 3.99 | X13: =(3.98+3.99)/2 -> 3.985 | Y13: 3.98 | Z13: =(3.99+4.12)/2 -> 4.055 | AA13: 4.12 | AB13: =(4.16+3.93)/2 -> 4.045 | AC13: 4.05 | AD13: =(3.97+4.17)/2 -> 4.07 | AE13: 4.11 | AF13: 4.14 | AG13: 4.16 | AH13: 4.05 | AJ13: =SUM(G13:AH13)/AJ6 -> 4.0351786 | AL13: rpo feed | AM13: =AM14+AM15 -> 39712496 | AO13: tk131 | AP13: ='OIP Fract PMG 2'!T13 -> 200835
D14: - Moist & Impurities | E14: 0.5 | F14: % | G14: 0.42 | H14: =(0.42+0.44)/2 -> 0.43 | I14: =(0.45+0.35)/2 -> 0.4 | J14: 0.38 | K14: =(0.4+0.46)/2 -> 0.43 | L14: =(0.4+0.46)/2 -> 0.43 | M14: 0.46 | N14: =(0.46+0.36)/2 -> 0.41 | O14: 0.4 | P14: =(0.37+0.38)/2 -> 0.375 | Q14: =(0.4+0.42)/2 -> 0.41 | R14: 0.42 | S14: =(0.42+0.41)/2 -> 0.415 | T14: 0.4 | U14: 0.4 | V14: 0.39 | W14: 0.39 | X14: =(0.4+0.4)/2 -> 0.4 | Y14: 0.4 | Z14: =(0.41+0.37)/2 -> 0.39 | AA14: 0.38 | AB14: =(0.4+0.39)/2 -> 0.395 | AC14: 0.39 | AD14: =(0.37+0.38)/2 -> 0.375 | AE14: 0.38 | AF14: 0.41 | AG14: 0.4 | AH14: 0.4 | AJ14: =SUM(G14:AH14)/AJ6 -> 0.40285714 | AL14: olein 56 | AM14: =AJ33 -> 33000682 | AO14: tk132 | AP14: ='OIP Fract PMG 2'!U13 -> 114939
D15: - DOBI | E15: 2,20 Min | F15: % | AJ15: =SUM(G15:AH15)/AJ6 -> 0 | AL15: stearin 56 | AM15: =AJ34 -> 6711814 | AO15: after
D16: TANK | G16: 107 | H16: 106107 | I16: 104106 | J16: 106 | K16: 107104 | L16: 107104 | M16: 104 | N16: 104106 | O16: 107 | P16: 106107 | Q16: 107104 | R16: 104 | S16: 104107 | T16: 106 | U16: 106 | V16: 107 | W16: 107 | X16: 106107 | Y16: 106 | Z16: 106103 | AA16: 103 | AB16: 103107 | AC16: 107 | AD16: 106103 | AE16: 103 | AF16: 106 | AG16: 106 | AH16: 106 | AL16: yield olein | AM16: =AM14/(AM14+AM15)*100 -> 83.098987 | AO16: tk131 | AP16: =AP13 -> 200835
D17: Product | AJ17: Product | AL17: yield stearin | AM17: =AM15/(AM14+AM15)*100 -> 16.901013 | AO17: tk132 | AP17: =AP14-AM13 -> -39597557
D18: OIP RBDPO | F18: Kg | AJ18: =SUM(G18:AH18) -> 0
D19: DIRECT RBDPO FRACT | F19: Kg | G19: 1917000 | H19: 2113326 | I19: 1912963 | J19: 2332133 | K19: 2035181 | L19: 1731169 | M19: 1911945 | N19: 1820597 | O19: 1934293 | P19: 2327461 | Q19: 2099971 | R19: 1942907 | S19: 1971871 | T19: 1504162 | U19: 1686679 | V19: 1847188 | W19: 2330791 | X19: 2415706 | Y19: 2344049 | Z19: 2284965 | AA19: 2246848 | AB19: 2468887 | AC19: 2266883 | AD19: 2159846 | AE19: 2321868 | AF19: 1970076 | AG19: 2005719 | AH19: 2073015 | AJ19: =SUM(G19:AH19) -> 57977499
D20: RBDPO | E20: 45448.405 | F20: Kg | AJ20: =SUM(G20:AH20) -> 0
D21: PFAD | E21: 2308.4904 | F21: Kg | G21: 85768 | H21: 93136 | I21: 89158 | J21: 90000 | K21: 99100 | L21: 86927 | M21: 88760 | N21: 83135 | O21: 88886 | P21: 106308 | Q21: 94673 | R21: 85891 | S21: 87870 | T21: 70599 | U21: 81006 | V21: 77260 | W21: 104620 | X21: 113653 | Y21: 108660 | Z21: 102639 | AA21: 111540 | AB21: 124535 | AC21: 113122 | AD21: 97957 | AE21: 102747 | AF21: 89268 | AG21: 96599 | AH21: 87729 | AJ21: =SUM(G21:AH21) -> 2661546
D22: Fractionation
D23: Running Days | F23: Day | G23: 1 | H23: 1 | I23: 1 | J23: 1 | K23: 1 | L23: 1 | M23: 1 | N23: 1 | O23: 1 | P23: 1 | Q23: 1 | R23: 1 | S23: 1 | T23: 1 | U23: 1 | V23: 1 | W23: 1 | X23: 1 | Y23: 1 | Z23: 1 | AA23: 1 | AB23: 1 | AC23: 1 | AD23: 1 | AE23: 1 | AF23: 1 | AG23: 1 | AH23: 1 | AJ23: =SUM(G23:AH23) -> 28
D24: Avg Daily Consump RBDPO ( MTD ) | F24: Kg | G24: 0 | H24: 0 | AJ24: =AJ29/AJ23 -> 1759936.5
D25: Total RBDPO transfer to plant | F25: Kg | AJ25: =SUM(G25:AH25) -> 0
D26: Stok TK 131 | E26: 559 | F26: ton
D27: Stok TK 132 | E27: 559 | F27: ton
D28: Ratio Run RBDPO | F28: % | G28: =G29/2500000 -> 0.7386484 | H28: =H29/2500000 -> 0.7752728 | I28: =I29/2500000 -> 0.798872 | J28: =J29/2500000 -> 0.8185852 | K28: =K29/2500000 -> 0.8863812 | L28: =L29/2500000 -> 0.7349376 | M28: =M29/2500000 -> 0.6574152 | N28: =N29/2500000 -> 0.5946088 | ... AH28: =AH29/2500000 -> 0.7373288 | AJ28: =AJ29/2500000/AJ23 -> 0.70397461
D29: Total Proses RBDPO | E29: 49015.009 | F29: Kg | G29: =SUM(G32,G36,G41,G45,G55) -> 1846621 | H29: =SUM(H32,H36,H41,H45,H55) -> 1938182 | I29: =SUM(I32,I36,I41,I45,I55) -> 1997180 | J29: =SUM(J32,J36,J41,J45,J55) -> 2046463 | K29: =SUM(K32,K36,K41,K45,K55) -> 2215953 | L29: =SUM(L32,L36,L41,L45,L55) -> 1837344 | M29: =SUM(M32,M36,M41,M45,M55) -> 1643538 | N29: =SUM(N32,N36,N41,N45,N55) -> 1486522 | ... AH29: =SUM(AH32,AH36,AH41,AH45,AH55) -> 1843322 | AJ29: =SUM(G29:AH29) -> 49278223
D30: Sisa Filling Crystalizer | F30: Kg | G30: =G25-G29 -> -1846621 | H30: =H25-H29 -> -1938182 | AJ30: =SUM(G30:AH30) -> -3784803
D31: Fractionation OLEIN IV 56 | AJ31: Olein IV 56
D32: RBDPO Consume | F32: Kg | G32: =G33+G34 -> 1846621 | H32: =H33+H34 -> 1938182 | I32: =I33+I34 -> 1997180 | J32: =J33+J34 -> 2046463 | K32: =K33+K34 -> 2215953 | L32: =L33+L34 -> 1837344 | M32: =M33+M34 -> 1202723 | N32: =N33+N34 -> 0 | ... AH32: =AH33+AH34 -> 1843322 | AJ32: =SUM(G32:AH32) -> 39712496
D33: OLEIN IV 56 | E33: 40192.308 | F33: Kg | G33: 1513692 | H33: 1612199 | I33: 1657711 | J33: 1699816 | K33: 1850384 | L33: 1512176 | M33: 1014930 | P33: 89177 | Q33: 1506554 | R33: 1650659 | S33: 1605938 | T33: 1651695 | U33: 1689760 | V33: 1421100 | W33: 1726177 | X33: 1672975 | Y33: 696877 | AC33: 1343911 | AD33: 1684618 | AE33: 1686144 | AF33: 724525 | AG33: 1432240 | AH33: 1557424 | AJ33: =SUM(G33:AH33) -> 33000682 | AK33: ok cek konsum rpo pas
D34: STEARIN | E34: 639000 | F34: Kg | G34: 332929 | H34: 325983 | I34: 339469 | J34: 346647 | K34: 365569 | L34: 325168 | M34: 187793 | P34: 19500 | Q34: 364890 | R34: 293500 | S34: 313329 | T34: 322834 | U34: 360538 | V34: 318939 | W34: 352933 | X34: 350573 | Y34: 130039 | AC34: 263494 | AD34: 357261 | AE34: 317070 | AF34: 146420 | AG34: 291038 | AH34: 285898 | AJ34: =SUM(G34:AH34) -> 6711814 | AK34: ok cek konsum rpo pas
D35: Fractionation OLEIN IV 57 ( Bulk ) | AJ35: Olein IV 57 ( Bulk )
D36: RBDPO Consume | F36: Kg | G36: =G37+G38 -> 0 | H36: =H37+H38 -> 0 | AJ36: =SUM(G36:AH36) -> 0
D37: OLEIN IV 57 | F37: Kg | H37: 0 | AJ37: =SUM(G37:AH37) -> 0
D38: STEARIN | F38: Kg | H38: 0 | AJ38: =SUM(G38:AH38) -> 0
D39: Fractionation OLEIN IV 57 ( Retail ) | AJ39: Olein IV 57 ( Retail )
D40: CPO Consume | F40: Kg | AJ40: =SUM(G40:AH40) -> 0
D41: RBDPO Brand Consume | F41: Kg | G41: =G42+G43 -> 0 | H41: =H42+H43 -> 0 | AJ41: =SUM(G41:AH41) -> 0
D42: OLEIN IV 57 Low Color | F42: Kg | H42: 0 | AJ42: =SUM(G42:AH42) -> 0
D43: STEARIN | F43: Kg | H43: 0 | AJ43: =SUM(G43:AH43) -> 0
D44: Fractionation OLEIN IV 58 ( Bulk ) | AJ44: Olein IV 58 ( Bulk )
D45: RBDPO Consume | E45: 17143 | F45: Kg | G45: =G46+G47 -> 0 | H45: =H46+H47 -> 0 | M45: =M46+M47 -> 440815 | N45: =N46+N47 -> 1486522 | O45: =O46+O47 -> 1098733 | P45: =P46+P47 -> 1175875 | Q45: =Q46+Q47 -> 0 | R45: =R46+R47 -> 0 | S45: =S46+S47 -> 0 | T45: =T46+T47 -> 0 | ... AF45: =AF46+AF47 -> 0 | AJ45: =SUM(G45:AH45) -> 9565727
D46: OLEIN IV 58 | E46: 12000000 | F46: Kg | M46: 340815 | N46: 1110523 | O46: 859181 | P46: 891355 | Y46: 491388 | Z46: 1162054 | AA46: 1112886 | AB46: 1178134 | AC46: 126254 | AJ46: =SUM(G46:AH46) -> 7272590 | AK46: ok cek konsum rpo pas
D47: STEARIN | E47: 514300 | F47: Kg | M47: 100000 | N47: 375999 | O47: 239552 | P47: 284520 | Y47: 155000 | Z47: 373067 | AA47: 362569 | AB47: 347930 | AC47: 54500 | AJ47: =SUM(G47:AH47) -> 2293137 | AK47: ok cek konsum rpo pas
D48: Fractionation OLEIN IV 58 ( Retail ) | AJ48: Olein IV 58 ( Retail )
D49: CPO Consume | F49: Kg | AJ49: =SUM(G49:AH49) -> 0
D50: RBDPO Consume | E50: 21429000 | F50: Kg | G50: =G51+G52 -> 0 | H50: =H51+H52 -> 0 | AJ50: =SUM(G50:AH50) -> 0
D51: OLEIN IV 58 | E51: 15000000 | F51: Kg | H51: 0 | AJ51: =SUM(G51:AH51) -> 0
D52: STEARIN | E52: 6429000 | F52: Kg | H52: 0 | AJ52: =SUM(G52:AH52) -> 0
D53: Fractionation OLEIN IV 60 | AJ53: Olein IV 60
D54: CPO Consume | F54: Kg | AJ54: =SUM(G54:AH54) -> 0
D55: RBDPO Brand Consume | E55: 1333300 | F55: Kg | G55: =G56+G57 -> 0 | H55: =H56+H57 -> 0 | AJ55: =SUM(G55:AH55) -> 0
D56: OLEIN IV 60 Salvaco | E56: 1250000 | F56: Kg | H56: 0 | AJ56: =SUM(G56:AH56) -> 0
D57: SOFT STEARIN | E57: 83300 | F57: Kg | H57: 0 | AJ57: =SUM(G57:AH57) -> 0
D58: Ratio Run RBDPO | F58: % | G58: 0 | H58: 0 | AJ58: =SUM(G58:AH58) -> 0
D59: YIELD | AJ59: Yield | AX59: 40006710 | AY59: semi aktivasi
D60: RBDPO | E60: 94.2 | F60: % | G60: =((G20+G19+G18)/(G9))*100 -> 95.366397 | H60: =((H20+H19+H18)/(H9))*100 -> 95.31951 | I60: =((I20+I19+I18)/(I9))*100 -> 95.019548 | J60: =((J20+J19+J18)/(J9))*100 -> 107.91252 | K60: =((K20+K19+K18)/(K9))*100 -> 94.854629 | L60: =((L20+L19+L18)/(L9))*100 -> 94.747733 | M60: =((M20+M19+M18)/(M9))*100 -> 94.958276 | N60: =((N20+N19+N18)/(N9))*100 -> 95.103166 | ... AH60: =((AH20+AH19+AH18)/(AH9))*100 -> 95.430685 | AJ60: =((AJ20+AJ19+AJ18)/(AJ9))*100 -> 95.455795 | AV60: 40006709 | AW60: aktivasi | AX60: 7000 | AY60: qty | AZ60: jika di konsum harusnya koosng di 1013 produksi
D61: PFAD | E61: 5 | F61: % | G61: =(G21/(G9))*100 -> 4.2667632 | H61: =(H21/(H9))*100 -> 4.2008085 | I61: =(I21/(I9))*100 -> 4.4286026 | J61: =(J21/(J9))*100 -> 4.1644822 | K61: =(K21/(K9))*100 -> 4.6187999 | L61: =(L21/(L9))*100 -> 4.7575576 | M61: =(M21/(M9))*100 -> 4.4083363 | N61: =(N21/(N9))*100 -> 4.3427523 | ... AH61: =(AH21/(AH9))*100 -> 4.0385808 | AJ61: =(AJ21/(AJ9))*100 -> 4.3820447 | AV61: =40913+35000 -> 75913 | AW61: qty
D62: Olein IV 56 | E62: 82 | F62: % | G62: =G33/(G33+G34)*100 -> 81.970908 | H62: =H33/(H33+H34)*100 -> 83.180991 | I62: =I33/(I33+I34)*100 -> 83.002584 | J62: =J33/(J33+J34)*100 -> 83.061165 | K62: =K33/(K33+K34)*100 -> 83.502854 | L62: =L33/(L33+L34)*100 -> 82.30228 | M62: =M33/(M33+M34)*100 -> 84.386014 | N62: =N33/(N33+N34)*100 -> #DIV/0! | ... AH62: =AH33/(AH33+AH34)*100 -> 84.490067 | AJ62: =AJ33/(AJ33+AJ34)*100 -> 83.098987 | AV62: =AV61-AU76 -> 58529
D63: Stearin | E63: 18 | F63: % | G63: =(G34/G32)*100 -> 18.029092 | H63: =(H34/H32)*100 -> 16.819009 | I63: =(I34/I32)*100 -> 16.997416 | J63: =(J34/J32)*100 -> 16.938835 | K63: =(K34/K32)*100 -> 16.497146 | L63: =(L34/L32)*100 -> 17.69772 | M63: =(M34/M32)*100 -> 15.613986 | N63: =(N34/N32)*100 -> #DIV/0! | ... AH63: =(AH34/AH32)*100 -> 15.509933 | AJ63: =AJ34/(AJ33+AJ34)*100 -> 16.901013
D64: Olein IV 57 ( Bulk ) | E64: 75 | G64: =(G37/G36)*100 -> #DIV/0! | H64: =(H37/H36)*100 -> #DIV/0! | I64: =(I37/I36)*100 -> #DIV/0! | J64: =(J37/J36)*100 -> #DIV/0! | K64: =(K37/K36)*100 -> #DIV/0! | L64: =(L37/L36)*100 -> #DIV/0! | M64: =(M37/M36)*100 -> #DIV/0! | N64: =(N37/N36)*100 -> #DIV/0! | ... AH64: =(AH37/AH36)*100 -> #DIV/0! | AJ64: =(AJ42/AJ41)*100 -> #DIV/0!
D65: Stearin | E65: 25 | G65: =(G38/G36)*100 -> #DIV/0! | H65: =(H38/H36)*100 -> #DIV/0! | I65: =(I38/I36)*100 -> #DIV/0! | J65: =(J38/J36)*100 -> #DIV/0! | K65: =(K38/K36)*100 -> #DIV/0! | L65: =(L38/L36)*100 -> #DIV/0! | M65: =(M38/M36)*100 -> #DIV/0! | N65: =(N38/N36)*100 -> #DIV/0! | ... AH65: =(AH38/AH36)*100 -> #DIV/0! | AJ65: =(AJ43/AJ41)*100 -> #DIV/0!
D66: Olein IV 57 ( Retail ) | E66: 75 | F66: % | G66: =G42/G41*100 -> #DIV/0! | H66: =H42/H41*100 -> #DIV/0! | I66: =I42/I41*100 -> #DIV/0! | J66: =J42/J41*100 -> #DIV/0! | K66: =K42/K41*100 -> #DIV/0! | L66: =L42/L41*100 -> #DIV/0! | M66: =M42/M41*100 -> #DIV/0! | N66: =N42/N41*100 -> #DIV/0! | ... AH66: =AH42/AH41*100 -> #DIV/0! | AJ66: =AJ42/AJ41*100 -> #DIV/0!
D67: Stearin | E67: 25 | F67: % | G67: =G43/G41*100 -> #DIV/0! | H67: =H43/H41*100 -> #DIV/0! | I67: =I43/I41*100 -> #DIV/0! | J67: =J43/J41*100 -> #DIV/0! | K67: =K43/K41*100 -> #DIV/0! | L67: =L43/L41*100 -> #DIV/0! | M67: =M43/M41*100 -> #DIV/0! | N67: =N43/N41*100 -> #DIV/0! | ... AH67: =AH43/AH41*100 -> #DIV/0! | AJ67: =AJ43/AJ41*100 -> #DIV/0!
D68: Olein IV 58 ( Bulk ) | E68: 70 | F68: % | G68: =G46/(G46+G47)*100 -> #DIV/0! | H68: =H46/(H46+H47)*100 -> #DIV/0! | I68: =I46/(I46+I47)*100 -> #DIV/0! | J68: =J46/(J46+J47)*100 -> #DIV/0! | K68: =K46/(K46+K47)*100 -> #DIV/0! | L68: =L46/(L46+L47)*100 -> #DIV/0! | M68: =M46/(M46+M47)*100 -> 77.314747 | N68: =N46/(N46+N47)*100 -> 74.706126 | ... AH68: =AH46/(AH46+AH47)*100 -> #DIV/0! | AJ68: =AJ46/(AJ46+AJ47)*100 -> 76.027572
D69: Stearin | E69: 30 | F69: % | G69: =G47/(G47+G46)*100 -> #DIV/0! | H69: =H47/(H47+H46)*100 -> #DIV/0! | I69: =I47/(I47+I46)*100 -> #DIV/0! | J69: =J47/(J47+J46)*100 -> #DIV/0! | K69: =K47/(K47+K46)*100 -> #DIV/0! | L69: =L47/(L47+L46)*100 -> #DIV/0! | M69: =M47/(M47+M46)*100 -> 22.685253 | N69: =N47/(N47+N46)*100 -> 25.293874 | ... AH69: =AH47/(AH47+AH46)*100 -> #DIV/0! | AJ69: =AJ47/AJ45*100 -> 23.972428
D70: Olein IV 58 ( Retail ) | E70: 70 | F70: % | G70: =G51/(G51+G52)*100 -> #DIV/0! | H70: =H51/(H51+H52)*100 -> #DIV/0! | AJ70: =AJ51/(AJ51+AJ52)*100 -> #DIV/0!
D71: Stearin | E71: 30 | F71: % | G71: =G52/(G51+G52)*100 -> #DIV/0! | H71: =H52/(H51+H52)*100 -> #DIV/0! | AJ71: =AJ52/(AJ51+AJ52)*100 -> #DIV/0!
D72: Olein IV 60 | E72: 60 | F72: % | G72: =G56/(G56+G57)*100 -> #DIV/0! | H72: =H56/(H56+H57)*100 -> #DIV/0! | AJ72: =AJ56/(AJ57+AJ56)*100 -> #DIV/0!
D73: Soft Stearin | E73: 40 | F73: % | G73: =G57/G55*100 -> #DIV/0! | H73: =H57/H55*100 -> #DIV/0! | AJ73: =AJ57/(AJ56+AJ57)*100 -> #DIV/0!
C74: 2 | D74: CHEMICAL CONSUMABLE | AJ74: Chemical
D75: Bleaching Earth (BE) to Hopper | E75: 9 | F75: Kg | G75: =10248+2000 -> 12248 | H75: =13086 -> 13086 | I75: 12566 | J75: 12922 | K75: 13608 | L75: 13412 | M75: 13371 | N75: 10976 | O75: 12530 | P75: 11942 | Q75: 12474 | R75: 11074 | S75: 11158 | T75: 9520 | U75: 10248 | V75: 11817 | W75: 14027 | X75: 14599 | Y75: 14209 | Z75: 12883 | AA75: 13221 | AB75: 13637 | AC75: 13312 | AD75: 12323 | AE75: 14283 | AF75: 2156 | AG75: 2156 | AH75: 2156 | AJ75: =SUM(G75:AH75) -> 321914 | AK75: =AJ75-#REF! -> #REF! | AS75: ok cek | AT75: 7000 | AV75: semi 710
D76: Note : BE Aktivasi start tgl 23 Bulan September (0,67 %) | F76: % | G76: =G75/(G11)*100 -> 0.60931019 | H76: =H75/(H11)*100 -> 0.59023128 | I76: =I75/(I11)*100 -> 0.6241708 | J76: =J75/(J11)*100 -> 0.59792711 | K76: =K75/(K11)*100 -> 0.6342344 | L76: =L75/(L11)*100 -> 0.73404538 | M76: =M75/(M11)*100 -> 0.6640814 | N76: =N75/(N11)*100 -> 0.57335717 | ... AH76: =AH75/(AH11)*100 -> 0.099250877 | AJ76: =AJ75/(AJ11)*100 -> 0.53000832 | AT76: 10384 | AU76: =AT76+AT75 -> 17384 | AV76: aktivasi 709
D77: TK 630 A ( TRANSFER ) | E77: 40000 | F77: Kg | AJ77: =SUM(G77:AH77) -> 0
D79: TK 630 B ( TRANSFER ) | E79: 40000 | F79: Kg | AJ79: =SUM(G79:AH79) -> 0
D81: Bleaching Earth (BE) to Branded Spec | E81: 18 | F81: Kg | G81: 0 | H81: 0 | AJ81: =SUM(G81:AH81) -> 0
D82: Bleaching Earth (BE) to Silo
D84: Aktual Pengiisian BE | F84: Kg | G84: 13000 | H84: 13000 | I84: 14000 | J84: 14000 | K84: 11000 | L84: 12000 | M84: 13000 | N84: 9000 | O84: 10000 | P84: 12000 | Q84: 10000 | R84: 8000 | S84: 9000 | T84: 10000 | U84: 6000 | V84: 10000 | W84: 9000 | X84: 9000 | Y84: 9000 | Z84: 13000 | AA84: 14000 | AB84: 12000 | AC84: 14000 | AD84: 11000 | AE84: 6000 | AF84: 12000 | AG84: 10000 | AH84: 12000 | AJ84: =SUM(G84:AH84) -> 305000
G85: =G84/G9*100 -> 0.64672048 | H85: =H84/H9*100 -> 0.58635233 | I85: =I84/I9*100 -> 0.69539958 | J85: =J84/J9*100 -> 0.64780835 | K85: =K84/K9*100 -> 0.51268212 | L85: =L84/L9*100 -> 0.65676592 | M85: =M84/M9*100 -> 0.64565538 | N85: =N84/N9*100 -> 0.47013617 | ... AH85: =AH84/AH9*100 -> 0.55241675 | AJ85: =AJ84/AJ9*100 -> 0.50216063
D86: Phosporic Acid (PA) | E86: 0.6 | F86: Kg | G86: =1250.08+200 -> 1450.08 | H86: 1066 | I86: 943.28 | J86: 1033.74 | K86: 934.96 | L86: 922.5 | M86: 954.8 | N86: 863.2 | O86: 994.24 | P86: 1088.88 | Q86: 1101.36 | R86: 959.92 | S86: 983.84 | T86: 747.7 | U86: 829.92 | V86: 998.4 | W86: 1172.08 | X86: 1228.24 | Y86: 1186.64 | Z86: 1019.2 | AA86: 1171.04 | AB86: 1138.8 | AC86: 1212.64 | AD86: 1161.68 | AE86: 1058.72 | AF86: 2043.0953 | AG86: 2043.0953 | AH86: 2043.0953 | AJ86: =SUM(G86:AH86) -> 32351.146 | AK86: =AJ86-#REF! -> #REF! | AS86: ok cek
F87: % | G87: =G86/(G9)*100 -> 0.072138187 | H87: =H86/(H9)*100 -> 0.048080891 | I87: =I86/(I9)*100 -> 0.046854037 | J87: =J86/(J9)*100 -> 0.047833243 | K87: =K86/(K9)*100 -> 0.043576116 | L87: =L86/(L9)*100 -> 0.05048888 | M87: =M86/(M9)*100 -> 0.047420905 | N87: =N86/(N9)*100 -> 0.045091282 | ... AH87: =AH86/(AH9)*100 -> 0.094053341 | AJ87: =AJ86/AJ9*1000 -> 0.53263842
C88: 3 | D88: OIL LOSSES | E88: 0.7 | F88: % | G88: =((SUM(G19:G21))-(SUM(G9)))/(SUM(G9))*100 -> -0.36683976 | H88: =((SUM(H19:H21))-(SUM(H9)))/(SUM(H9))*100 -> -0.47968131 | I88: =((SUM(I19:I21))-(SUM(I9)))/(SUM(I9))*100 -> -0.55184924 | J88: =((SUM(J19:J21))-(SUM(J9)))/(SUM(J9))*100 -> 12.076999 | K88: =((SUM(K19:K21))-(SUM(K9)))/(SUM(K9))*100 -> -0.52657115 | L88: =((SUM(L19:L21))-(SUM(L9)))/(SUM(L9))*100 -> -0.49470893 | M88: =((SUM(M19:M21))-(SUM(M9)))/(SUM(M9))*100 -> -0.63338793 | N88: =((SUM(N19:N21))-(SUM(N9)))/(SUM(N9))*100 -> -0.55408159 | ... AH88: =((SUM(AH19:AH21))-(SUM(AH9)))/(SUM(AH9))*100 -> -0.5307344 | AJ88: =((SUM(AJ18:AJ21))-(SUM(AJ9)))/(SUM(AJ9))*100 -> -0.16216002
F89: Kg | G89: =G88%*G9 -> -7374 | H89: =H88%*H9 -> -10635 | I89: =I88%*I9 -> -11110 | J89: =J88%*J9 -> 261000 | K89: =K88%*K9 -> -11298 | L89: =L88%*L9 -> -9039 | M89: =M88%*M9 -> -12753 | N89: =N88%*N9 -> -10607 | ... AH89: =AH88%*AH9 -> -11529 | AJ89: =AJ88%*AJ9 -> -98492
D90: % Oil Content | E90: 22 | F90: % | G90: 17.47 | H90: 17.5 | I90: 17.5 | J90: 17.51 | K90: 17.51 | L90: 17.51 | M90: 17.46 | N90: 17.44 | O90: 17.53 | P90: 17.47 | Q90: 17.49 | R90: 17.47 | S90: 17.48 | T90: 17.47 | U90: 17.48 | V90: 17.5 | W90: 17.49 | X90: 17.51 | Y90: 17.28 | Z90: 17.5 | AA90: 17.51 | AB90: 17.52 | AC90: 17.51 | AD90: 17.5 | AE90: 17.48 | AF90: 17.44 | AG90: 17.49 | AH90: 16.57 | AJ90: =AVERAGE(G90:AH90) -> 17.449643
D91: Spent Bleaching Earth | F91: Kg | G91: =SUM(G75,G81)+(G90%*SUM(G75,G81)) -> 14387.726 | H91: =SUM(H75,H81)+(H90%*SUM(H75,H81)) -> 15376.05 | I91: =SUM(I75,I81)+(I90%*SUM(I75,I81)) -> 14765.05 | J91: =SUM(J75,J81)+(J90%*SUM(J75,J81)) -> 15184.642 | K91: =SUM(K75,K81)+(K90%*SUM(K75,K81)) -> 15990.761 | L91: =SUM(L75,L81)+(L90%*SUM(L75,L81)) -> 15760.441 | M91: =SUM(M75,M81)+(M90%*SUM(M75,M81)) -> 15705.577 | N91: =SUM(N75,N81)+(N90%*SUM(N75,N81)) -> 12890.214 | ... AH91: =SUM(AH75,AH81)+(AH90%*SUM(AH75,AH81)) -> 2513.2492 | AJ91: =SUM(AJ75,AJ81)+(AJ90%*SUM(AJ75,AJ81))/AJ6 -> 323920.17
C92: 4 | D92: PACKAGING (Brand Salvaco) | AJ92: Packaging
D93: Olein IV 60 Received | F93: Kg | AJ93: 0
D94: Olein IV 60 Consume | F94: Kg | AJ94: 0
D95: - finished product | F95: Kg | G95: 0 | H95: 0 | AJ95: 0
D96: - sample | F96: Kg | G96: 0 | H96: 0 | AJ96: 0
D97: - remelt, flushing, downgrade | F97: Kg | G97: 0 | H97: 0 | AJ97: 0
D98: Carton | AJ98: Carton
D99: Salvaco 1 Liter | F99: Box | AJ99: 0
D100: Salvaco 2 Liter | F100: Box | AJ100: 0 | AT100: 37542
D101: Pouch | AJ101: Pouch
D102: Salvaco 1 Liter | F102: Pouch | G102: 0 | H102: 0 | AJ102: 0
D103: Salvaco 2 Liter | F103: Pouch | G103: 0 | H103: 0 | AJ103: 0
...

Sheet Convert Gas
B3: CONVERT PEMAKAIAN GAS HP BOILER & MP BOILER
B4: Februari 2026
B5: Tanggal | C5: HP BOILER | F5: TOTAL CORRECTED VOLUME (Sm3) | K5: ENERGY MP BOILER (MMBTU) | L5: TOTAL GAS CONSUMPTION (MMBTU) | M5: PERCENTAGE
C6: UNCORRECTED VOLUME (UV) (Nm3) | D6: PRESS. Bar | E6: CORRECTED VOLUME (CV) (Sm3) | G6: Convert Sm3 to SCF | H6: VOLUME (MSCF) | I6: HEATING VALUE (BTU / SCF) | J6: ENERGY HP BOILER (MMBTU) | M6: HP Boiler | N6: MP Boiler
C7: 1 | D7: 2 | E7: 3 = 1 x 2 | F7: 4 = 3 | G7: 5 | H7: 6 = (4 x 5) / 1000 | I7: 7 | J7: 8 = (6 x 7) / 1000 | K7: 9 = 10 - 8 | L7: 10 | M7: 11 = 8 / 10 | N7: 12 = 9 / 10
B8: 1 | D8: 5 | E8: =C8*D8 -> 0 | F8: =E8 -> 0 | G8: 35.314667 | H8: =(F8*G8)/1000 -> 0 | I8: 1064.9573 | J8: =(H8*I8)/1000 -> 0 | K8: =L8-J8 -> 0 | M8: =(J8/L8) -> #DIV/0! | N8: =K8/L8 -> #DIV/0!
B9: =B8+1 -> 2 | D9: 5 | E9: =C9*D9 -> 0 | F9: =E9 -> 0 | G9: 35.314667 | H9: =(F9*G9)/1000 -> 0 | I9: 1068.3854 | J9: =(H9*I9)/1000 -> 0 | K9: =L9-J9 -> 0 | M9: =(J9/L9) -> #DIV/0! | N9: =K9/L9 -> #DIV/0!
B10: =B9+1 -> 3 | D10: 5 | E10: =C10*D10 -> 0 | F10: =E10 -> 0 | G10: 35.314667 | H10: =(F10*G10)/1000 -> 0 | I10: 1072.5902 | J10: =(H10*I10)/1000 -> 0 | K10: =L10-J10 -> 0 | M10: =(J10/L10) -> #DIV/0! | N10: =K10/L10 -> #DIV/0!
B11: =B10+1 -> 4 | D11: 5 | E11: =C11*D11 -> 0 | F11: =E11 -> 0 | G11: 35.314667 | H11: =(F11*G11)/1000 -> 0 | J11: =(H11*I11)/1000 -> 0 | K11: =L11-J11 -> 0 | M11: =(J11/L11) -> #DIV/0! | N11: =K11/L11 -> #DIV/0!
B12: =B11+1 -> 5 | D12: 5 | E12: =C12*D12 -> 0 | F12: =E12 -> 0 | G12: 35.314667 | H12: =(F12*G12)/1000 -> 0 | J12: =(H12*I12)/1000 -> 0 | K12: =L12-J12 -> 0 | M12: =(J12/L12) -> #DIV/0! | N12: =K12/L12 -> #DIV/0!
B13: =B12+1 -> 6 | D13: 5 | E13: =C13*D13 -> 0 | F13: =E13 -> 0 | G13: 35.314667 | H13: =(F13*G13)/1000 -> 0 | J13: =(H13*I13)/1000 -> 0 | K13: =L13-J13 -> 0 | M13: =(J13/L13) -> #DIV/0! | N13: =K13/L13 -> #DIV/0!
B14: =B13+1 -> 7 | D14: 5 | E14: =C14*D14 -> 0 | F14: =E14 -> 0 | G14: 35.314667 | H14: =(F14*G14)/1000 -> 0 | J14: =(H14*I14)/1000 -> 0 | K14: =L14-J14 -> 0 | M14: =(J14/L14) -> #DIV/0! | N14: =K14/L14 -> #DIV/0!
B15: =B14+1 -> 8 | D15: 5 | E15: =C15*D15 -> 0 | F15: =E15 -> 0 | G15: 35.314667 | H15: =(F15*G15)/1000 -> 0 | J15: =(H15*I15)/1000 -> 0 | K15: =L15-J15 -> 0 | M15: =(J15/L15) -> #DIV/0! | N15: =K15/L15 -> #DIV/0!
B16: =B15+1 -> 9 | D16: 5 | E16: =C16*D16 -> 0 | F16: =E16 -> 0 | G16: 35.314667 | H16: =(F16*G16)/1000 -> 0 | J16: =(H16*I16)/1000 -> 0 | K16: =L16-J16 -> 0 | M16: =(J16/L16) -> #DIV/0! | N16: =K16/L16 -> #DIV/0!
B17: =B16+1 -> 10 | D17: 5 | E17: =C17*D17 -> 0 | F17: =E17 -> 0 | G17: 35.314667 | H17: =(F17*G17)/1000 -> 0 | J17: =(H17*I17)/1000 -> 0 | K17: =L17-J17 -> 0 | M17: =(J17/L17) -> #DIV/0! | N17: =K17/L17 -> #DIV/0!
B18: =B17+1 -> 11 | D18: 5 | E18: =C18*D18 -> 0 | F18: =E18 -> 0 | G18: 35.314667 | H18: =(F18*G18)/1000 -> 0 | J18: =(H18*I18)/1000 -> 0 | K18: =L18-J18 -> 0 | M18: =(J18/L18) -> #DIV/0! | N18: =K18/L18 -> #DIV/0!
B19: =B18+1 -> 12 | D19: 5 | E19: =C19*D19 -> 0 | F19: =E19 -> 0 | G19: 35.314667 | H19: =(F19*G19)/1000 -> 0 | J19: =(H19*I19)/1000 -> 0 | K19: =L19-J19 -> 0 | M19: =(J19/L19) -> #DIV/0! | N19: =K19/L19 -> #DIV/0!
B20: =B19+1 -> 13 | D20: 5 | E20: =C20*D20 -> 0 | F20: =E20 -> 0 | G20: 35.314667 | H20: =(F20*G20)/1000 -> 0 | J20: =(H20*I20)/1000 -> 0 | K20: =L20-J20 -> 0 | M20: =(J20/L20) -> #DIV/0! | N20: =K20/L20 -> #DIV/0!
B21: =B20+1 -> 14 | D21: 5 | E21: =C21*D21 -> 0 | F21: =E21 -> 0 | G21: 35.314667 | H21: =(F21*G21)/1000 -> 0 | J21: =(H21*I21)/1000 -> 0 | K21: =L21-J21 -> 0 | M21: =(J21/L21) -> #DIV/0! | N21: =K21/L21 -> #DIV/0!
B22: =B21+1 -> 15 | D22: 5 | E22: =C22*D22 -> 0 | F22: =E22 -> 0 | G22: 36.314667 | H22: =(F22*G22)/1000 -> 0 | J22: =(H22*I22)/1000 -> 0 | K22: =L22-J22 -> 0 | M22: =(J22/L22) -> #DIV/0! | N22: =K22/L22 -> #DIV/0!
... B35: =B34+1 -> 28 | D35: 5 | E35: =C35*D35 -> 0 | F35: =E35 -> 0 | G35: 49.314667 | H35: =(F35*G35)/1000 -> 0 | J35: =(H35*I35)/1000 -> 0 | K35: =L35-J35 -> 0 | M35: =(J35/L35) -> #DIV/0! | N35: =K35/L35 -> #DIV/0!
B36: Average | F36: =E36 -> 0 | H36: =AVERAGE(H8:H35) -> 0 | I36: =AVERAGE(I8:I35) -> 1068.6443 | J36: =AVERAGE(J8:J35) -> 0 | K36: =AVERAGE(K8:K35) -> 0 | L36: =AVERAGE(L8:L35) -> #DIV/0! | M36: =AVERAGE(M8:M35) -> #DIV/0! | N36: =AVERAGE(N8:N35) -> #DIV/0!
B37: TOTAL | C37: =SUM(C8:C35) -> 0 | E37: =SUM(E8:E35) -> 0 | F37: =E37 -> 0 | H37: =SUM(H8:H35) -> 0 | J37: =SUM(J8:J35) -> 0
B38: Koreksi
B39: Total Setelah Koreksi | H39: =H37+H38 -> 0 | J39: =J37+J38 -> 0
C41: CONVERT HP Boiler from Utility
C42: =C37 -> 0 | D42: m3 | F42: =C37*5 -> 0 | G42: 9983.7
C43: 5 | D43: bar | F43: 21286.9 | G43: =G42-C37 -> 9983.7
C44: =C42*C43 -> 0 | D44: Sm3 | F44: =F42/F43 -> 0
C45: =#REF! -> #REF! | D45: Scf
C46: =(C44*C45)/1000 -> #REF! | D46: Volume (MSCF)
C47: =I36 -> 1068.6443 | D47: Heating Value
C48: =(C46*C47)/1000 -> #REF! | D48: Energy (mmbtu)

Sheet OIP Ref PMG 2
B4: Oil In Plant (OIP) Refinery pmg 2 | I4: Februari | J4: OIP | M4: TK131 RPO | P4: TK132 RPO | S4: TOTAL STOK RPO DI PLANT
B5: Vessel | C5: Operating Volume (m3) | D5: Oil Density (kg/m3) | E5: MT | F5: Level yg diisi | G5: Actual OIP (Kg) | I5: Tanggal | J5: Opening Stock | K5: Closing Stock | L5: balance stok | M5: Opening Stock | N5: Closing Stock | O5: CONSUMP stok | P5: Opening Stock | Q5: Closing Stock | R5: CONSUMP stok
B6: 2MX312 | C6: 5.67 | D6: 850 | E6: =C6*D6/1000 -> 4.8195 | F6: 100 | G6: =(F6*E6/100)*1000 -> 4819.5 | I6: 46054 | J6: 301079 | K6: 300189 | L6: =J6-K6 -> 890
B7: 2VE611A | C7: 47.22 | D7: 850 | E7: =C7*D7/1000 -> 40.137 | F7: 80 | G7: =(F7*E7/100)*1000 -> 32109.6 | I7: 46055 | J7: =K6 -> 300189 | K7: 300254 | L7: =J7-K7 -> -65
B8: 2VE611B | C8: 47.22 | D8: 850 | E8: =C8*D8/1000 -> 40.137 | F8: 80 | G8: =(F8*E8/100)*1000 -> 32109.6 | I8: 46056 | J8: =K7 -> 300254 | K8: 300189 | L8: =J8-K8 -> 65
B9: 2VE612 | C9: 35.68 | D9: 850 | E9: =C9*D9/1000 -> 30.328 | F9: 80 | G9: =(F9*E9/100)*1000 -> 24262.4 | I9: 46057 | J9: =K8 -> 300189 | K9: 301618 | L9: =J9-K9 -> -1429
B10: 2VE661 | C10: 10.8 | D10: 850 | E10: =C10*D10/1000 -> 9.18 | F10: 17 | G10: =(F10*E10/100)*1000 -> 1560.6 | I10: 46058 | J10: =K9 -> 301618 | K10: 300254 | L10: =J10-K10 -> 1364
B11: FL621 | C11: 10.1 | D11: 850 | E11: =C11*D11/1000 -> 8.585 | F11: 100 | G11: =(F11*E11/100)*1000 -> 8585 | I11: 46059 | J11: =K10 -> 300254 | K11: 299800 | L11: =J11-K11 -> 454
B12: FL622 | C12: 10.1 | D12: 850 | E12: =C12*D12/1000 -> 8.585 | F12: 100 | G12: =(F12*E12/100)*1000 -> 8585 | I12: 46060 | J12: =K11 -> 299800 | K12: 300254 | L12: =J12-K12 -> -454
B13: FL623 | C13: 10.1 | D13: 850 | E13: =C13*D13/1000 -> 8.585 | F13: 100 | G13: =(F13*E13/100)*1000 -> 8585 | I13: 46061 | J13: =K12 -> 300254 | K13: 308759 | L13: =J13-K13 -> -8505 | N13: 0 | Q13: 174609
B14: FL624 | C14: 10.1 | D14: 850 | E14: =C14*D14/1000 -> 8.585 | F14: 0 | G14: =(F14*E14/100)*1000 -> 0 | I14: 46062 | J14: =K13 -> 308759 | K14: 302600 | L14: =J14-K14 -> 6159 | N14: 44191 | P14: 174609 | Q14: 38852 | R14: =P14-Q14 -> 135757 | S14: =R14+O14+L14 -> 141916
B15: FL625 | C15: 10.1 | D15: 850 | E15: =C15*D15/1000 -> 8.585 | F15: 100 | G15: =(F15*E15/100)*1000 -> 8585 | I15: 46063 | J15: =K14 -> 302600 | K15: 313438 | L15: =J15-K15 -> -10838 | M15: 44191 | N15: 405272 | O15: =M15-N15 -> -361081 | P15: 38852 | Q15: 38852 | R15: =P15-Q15 -> 0 | S15: =R15+O15+L15 -> -371919
B16: 2VE701 | C16: 72.13 | D16: 850 | E16: =C16*D16/1000 -> 61.3105 | F16: 15 | G16: =(F16*E16/100)*1000 -> 9196.575 | I16: 46064 | J16: =K15 -> 313438 | K16: 293386 | L16: =J16-K16 -> 20052
B17: 2VE751 | C17: 4.28 | D17: 860 | E17: =C17*D17/1000 -> 3.6808 | F17: 50 | G17: =(F17*E17/100)*1000 -> 1840.4 | I17: 46065 | J17: =K16 -> 293386 | K17: 309940 | L17: =J17-K17 -> -16554
B18: 2HE721A (tube) | C18: 10 | D18: 810 | E18: =C18*D18/1000 -> 8.1 | F18: 100 | G18: =(F18*E18/100)*1000 -> 8100 | I18: 46066 | J18: =K17 -> 309940 | K18: 296910 | L18: =J18-K18 -> 13030
B19: 2HE721A (shell) | C19: 21.8 | D19: 800 | E19: =C19*D19/1000 -> 17.44 | F19: 30 | G19: =(F19*E19/100)*1000 -> 5232 | I19: 46067 | J19: =K18 -> 296910 | K19: 295027 | L19: =J19-K19 -> 1883
B20: HE721B (tube) | C20: 10 | D20: 810 | E20: =C20*D20/1000 -> 8.1 | F20: 100 | G20: =(F20*E20/100)*1000 -> 8100 | I20: 46068 | J20: =K19 -> 295027 | K20: 286594 | L20: =J20-K20 -> 8433
B21: 2HE722 | C21: 11.4 | D21: 790 | E21: =C21*D21/1000 -> 9.006 | F21: 80 | G21: =(F21*E21/100)*1000 -> 7204.8 | I21: 46069 | J21: =K20 -> 286594 | K21: 300102 | L21: =J21-K21 -> -13508
B22: 2PR731 | C22: 14 | D22: 790 | E22: =C22*D22/1000 -> 11.06 | F22: 30 | G22: =(F22*E22/100)*1000 -> 3318 | I22: 46070 | J22: =K21 -> 300102 | K22: 295092 | L22: =J22-K22 -> 5010
B23: 2DE732 | C23: 149.76 | D23: 790 | E23: =C23*D23/1000 -> 118.3104 | F23: 100 | G23: =(F23*E23/100)*1000 -> 118310.4 | I23: 46071 | J23: =K22 -> 295092 | K23: 294300 | L23: =J23-K23 -> 792
C24: =SUM(C6:C23) -> 490.46 | E24: =SUM(E6:E23) -> 404.5342 | G24: =(F24*E24/100)*1000 -> 0 | I24: 46072 | J24: =K23 -> 294300 | K24: 298309 | L24: =J24-K24 -> -4009
F25: Total OIP = | G25: =SUM(G6:G24) -> 290503.88 | I25: 46073 | J25: =K24 -> 298309 | K25: 294600 | L25: =J25-K25 -> 3709
I26: 46074 | J26: =K25 -> 294600 | K26: 298005 | L26: =J26-K26 -> -3405
I27: 46075 | J27: =K26 -> 298005 | K27: 297702 | L27: =J27-K27 -> 303
I28: 46076 | J28: =K27 -> 297702 | K28: 295092 | L28: =J28-K28 -> 2610
I29: 46077 | J29: =K28 -> 295092 | K29: 301618 | L29: =J29-K29 -> -6526
I30: 46078 | J30: =K29 -> 301618 | K30: 297702 | L30: =J30-K30 -> 3916
H31: 0 | I31: 46079 | J31: =K30 -> 297702 | K31: 290504 | L31: =J31-K31 -> 7198
I32: 46080 | J32: =K31 -> 290504 | K32: 305832 | L32: =J32-K32 -> -15328
I33: 46081 | J33: =K32 -> 305832 | K33: 307640 | L33: =J33-K33 -> -1808
B38: Solar Daily Tank HPB
B39: 2TK726 | C39: =5.3+0.78 -> 6.08 | D39: 840 | E39: =C39*D39/1000 -> 5.1072 | F39: 0 | G39: =F39*E39/100*1000 -> 0
B41: Stock Chemicals In Plant
C42: Sisa Stok Di Lap | D42: Order | E42: Consumption
B43: BE
B44: 630A | D44: 298
B45: 630B
B46: H3PO4
B47: NaOH
B48: Citrid Acid

Sheet OIP Fract PMG 2
A4: Oil In Plant (OIP) Fraksinasi | I4: OIP | S4: BUFFER TANK | W4: DIRECT
A5: RBDPO OIP | I5: RPO CR | M5: OLEIN | P5: STEARIN | S5: TK131 RPO | U5: TK132 RPO
A6: Vessel | B6: Operating Volume (m3) | C6: Oil Density (kg/m3) | D6: MT | E6: Level Transmitter (1%/MT) | F6: Level (%) | G6: Kg | I6: Tanggal | J6: Opening Stock | K6: Closing Stock | L6: balance stok | M6: Opening Stock | N6: Closing Stock | O6: balance stok | P6: Opening Stock | Q6: Closing Stock | R6: balance stok | S6: Opening Stock | T6: Closing Stock | U6: Opening Stock | V6: Closing Stock
A7: 2CR1201 | B7: 70.51 | C7: 890 | D7: 60 | E7: =D7/100 -> 0.6 | F7: 100 | G7: =E7*F7*1000 -> 60000 | I7: 46054 | J7: 865440 | K7: 900000 | M7: 21752 | N7: 21638 | S7: 75754 | T7: 87668 | U7: 62644 | V7: 87553
A8: 2CR1202 | B8: 70.51 | C8: 890 | D8: 60 | E8: =D8/100 -> 0.6 | F8: 99.9 | G8: =E8*F8*1000 -> 59940 | I8: 46055 | J8: =K7 -> 900000 | K8: 840000 | M8: =N7 -> 21638 | N8: 21448 | S8: =T7 -> 87668 | T8: 206458 | U8: =V7 -> 87553 | V8: 204032
A9: 2CR1203 | B9: 70.51 | C9: 890 | D9: 60 | E9: =D9/100 -> 0.6 | F9: 99.8 | G9: =E9*F9*1000 -> 59880 | I9: 46056 | J9: =K8 -> 840000 | K9: 840000 | M9: =N8 -> 21448 | N9: 45871 | S9: =T8 -> 206458 | T9: 150700 | U9: =V8 -> 204032 | V9: 151215
A10: 2CR1204 | B10: 70.51 | C10: 890 | D10: 60 | E10: =D10/100 -> 0.6 | F10: 98.5 | G10: =E10*F10*1000 -> 59100 | I10: 46057 | J10: =K9 -> 840000 | K10: 840000 | M10: =N9 -> 45871 | N10: 21160 | S10: =T9 -> 150700 | T10: 172935 | U10: =V9 -> 151215 | V10: 168861
A11: 2CR1205 | B11: 70.51 | C11: 890 | D11: 60 | E11: =D11/100 -> 0.6 | F11: 99.3 | G11: =E11*F11*1000 -> 59580 | I11: 46058 | J11: =K10 -> 840000 | K11: 840000 | M11: =N10 -> 21160 | N11: 35819 | S11: =T10 -> 172935 | T11: 387069 | U11: =V10 -> 168861 | V11: 378931
A12: 2CR1206 | B12: 70.51 | C12: 890 | D12: 60 | E12: =D12/100 -> 0.6 | F12: 100 | G12: =E12*F12*1000 -> 60000 | I12: 46059 | J12: =K11 -> 840000 | K12: 840000 | M12: =N11 -> 35819 | N12: 50658 | S12: =T11 -> 387069 | T12: 124359 | U12: =V11 -> 378931 | V12: 114939
A13: 2CR1207 | B13: 70.51 | C13: 890 | D13: 60 | E13: =D13/100 -> 0.6 | F13: 100 | G13: =E13*F13*1000 -> 60000 | I13: 46060 | J13: =K12 -> 840000 | K13: 720000 | M13: =N12 -> 50658 | N13: 25140 | S13: =T12 -> 124359 | T13: 200835 | U13: =V12 -> 114939 | V13: 190826
A14: 2CR1208 | B14: 70.51 | C14: 890 | D14: 60 | E14: =D14/100 -> 0.6 | F14: 100 | G14: =E14*F14*1000 -> 60000 | I14: 46061 | J14: =K13 -> 720000 | K14: 478620 | M14: =N13 -> 25140 | N14: 21421 | S14: =T13 -> 200835 | T14: 35000 | U14: =V13 -> 190826 | V14: 35000
A15: 2CR1209 | B15: 70.51 | C15: 890 | D15: 60 | E15: =D15/100 -> 0.6 | F15: 0 | G15: =E15*F15*1000 -> 0 | I15: 46062 | J15: =K14 -> 478620 | K15: 200680 | M15: =N14 -> 21421 | N15: 38896 | S15: =T14 -> 35000 | T15: 50000 | U15: =V14 -> 35000 | V15: 50000
A16: 2CR1210 | B16: 70.51 | C16: 890 | D16: 60 | E16: =D16/100 -> 0.6 | F16: 0 | G16: =E16*F16*1000 -> 0 | I16: 46063 | J16: =K15 -> 200680 | K16: 879600 | M16: =N15 -> 38896 | N16: 21214 | S16: =T15 -> 50000 | T16: 205239 | U16: =V15 -> 50000 | V16: 171858
A17: 2CR1211 | B17: 70.51 | C17: 890 | D17: 60 | E17: =D17/100 -> 0.6 | F17: 0 | G17: =E17*F17*1000 -> 0 | I17: 46064 | J17: =K16 -> 879600 | K17: 898860 | M17: =N16 -> 21214 | N17: 20603 | S17: =T16 -> 205239 | T17: 306034 | U17: =V16 -> 171858 | V17: 300993
A18: 2CR1212 | B18: 70.51 | C18: 890 | D18: 60 | E18: =D18/100 -> 0.6 | G18: =E18*F18*1000 -> 0 | I18: 46065 | J18: =K17 -> 898860 | K18: 898860 | M18: =N17 -> 20603 | N18: 21310 | S18: =T17 -> 306034 | T18: 293967 | U18: =V17 -> 300993 | V18: 294547
A19: 2CR1213 | B19: 70.51 | C19: 890 | D19: 60 | E19: =D19/100 -> 0.6 | F19: 67.2 | G19: =E19*F19*1000 -> 40320 | I19: 46066 | J19: =K18 -> 898860 | K19: 853260 | M19: =N18 -> 21310 | N19: 21008 | S19: =T18 -> 293967 | T19: 354542 | U19: =V18 -> 294547 | V19: 345508
A20: 2CR1214 | B20: 70.51 | C20: 890 | D20: 60 | E20: =D20/100 -> 0.6 | F20: 100 | G20: =E20*F20*1000 -> 60000 | I20: 46067 | J20: =K19 -> 853260 | K20: 845220 | M20: =N19 -> 21008 | N20: 37602 | S20: =T19 -> 354542 | T20: 116226 | U20: =V19 -> 345508 | V20: 106786
A21: 2CR1215 | B21: 70.51 | C21: 890 | D21: 60 | E21: =D21/100 -> 0.6 | F21: 100 | G21: =E21*F21*1000 -> 60000 | I21: 46068 | J21: =K20 -> 845220 | K21: 700020 | M21: =N20 -> 37602 | N21: 20628 | S21: =T20 -> 116226 | T21: 15000 | U21: =V20 -> 106786 | V21: 15000
I22: 46069 | J22: =K21 -> 700020 | K22: 720000 | M22: =N21 -> 20628 | N22: 20289 | S22: =T21 -> 15000 | T22: 54000 | U22: =V21 -> 15000 | V22: 50000
F23: Total RBDPO | G23: =SUM(G7:G21) -> 638820 | I23: 46070 | J23: =K22 -> 720000 | K23: 886260 | M23: =N22 -> 20289 | N23: 20656 | S23: =T22 -> 54000 | T23: 94451 | U23: =V22 -> 50000 | V23: 99613
I24: 46071 | J24: =K23 -> 886260 | K24: 844140 | M24: =N23 -> 20656 | N24: 20290 | S24: =T23 -> 94451 | T24: 50000 | U24: =V23 -> 99613 | V24: 50000
A25: Olein OIP | I25: 46072 | J25: =K24 -> 844140 | K25: 780000 | M25: =N24 -> 20290 | N25: 20067 | S25: =T24 -> 50000 | T25: 323798 | U25: =V24 -> 50000 | V25: 319831
A26: Vessel | B26: Operating Volume (m3) | C26: Oil Density (kg/m3) | D26: MT | E26: Level Transmitter (1%/MT) | F26: Level (%) | G26: Kg | I26: 46073 | J26: =K25 -> 780000 | K26: 660000 | M26: =N25 -> 20067 | N26: 19770 | S26: =T25 -> 323798 | T26: 277341 | U26: =V25 -> 319831 | V26: 264258
A27: 2TK261 | B27: 15.95 | C27: 885 | D27: =B27*C27/1000 -> 14.11575 | E27: =D27/100 -> 0.1411575 | F27: 49.3 | G27: =E27*F27*1000 -> 6959.0647 | I27: 46074 | J27: =K26 -> 660000 | K27: 833340 | M27: =N26 -> 19770 | N27: 19914 | S27: =T26 -> 277341 | T27: 133592 | U27: =V26 -> 264258 | V27: 120761
A28: 2CL251 | B28: 3.02 | C28: 885 | D28: =B28*C28/1000 -> 2.6727 | E28: =D28/100 -> 0.026727 | F28: 0 | G28: =E28*F28*1000 -> 0 | I28: 46075 | J28: =K27 -> 833340 | K28: 840000 | M28: =N27 -> 19914 | N28: 19461 | S28: =T27 -> 133592 | T28: 183924 | U28: =V27 -> 120761 | V28: 182268
A29: 2TK221 | B29: 82.48 | C29: 885 | D29: =B29*C29/1000 -> 72.9948 | E29: =D29/100 -> 0.729948 | F29: 0 | G29: =E29*F29*1000 -> 0 | I29: 46076 | J29: =K28 -> 840000 | K29: 841200 | M29: =N28 -> 19461 | N29: 19742 | S29: =T28 -> 183924 | T29: 424601 | U29: =V28 -> 182268 | V29: 425314
A30: 2TK241 | B30: 16.95 | C30: 885 | D30: =B30*C30/1000 -> 15.00075 | E30: =D30/100 -> 0.1500075 | F30: 87.1 | G30: =E30*F30*1000 -> 13065.653 | I30: 46077 | J30: =K29 -> 841200 | K30: 840000 | M30: =N29 -> 19742 | N30: 19688 | S30: =T29 -> 424601 | T30: 237715 | U30: =V29 -> 425314 | V30: 234675
F31: Total Olein | G31: =SUM(G27:G30) -> 20024.718 | I31: 46078 | J31: =K30 -> 840000 | K31: 840000 | M31: =N30 -> 19688 | N31: 19853 | S31: =T30 -> 237715 | T31: 186010 | U31: =V30 -> 234675 | V31: 188145
I32: 46079 | J32: =K31 -> 840000 | K32: 638820 | M32: =N31 -> 19853 | N32: 20025 | S32: =T31 -> 186010 | T32: 212565 | U32: =V31 -> 188145 | V32: 209707
I33: 46080 | J33: =K32 -> 638820 | K33: 484030 | M33: =N32 -> 20025 | N33: 19550 | S33: =T32 -> 212565 | T33: 0 | U33: =V32 -> 209707 | V33: 0
I34: 46081 | J34: =K33 -> 484030 | K34: 628455 | M34: =N33 -> 19550 | N34: 58060 | S34: =T33 -> 0 | T34: 0 | U34: =V33 -> 0 | V34: 0
A39: Stearin OIP
A40: Melting Tank | B40: Panjang (m) | C40: Lebar (m) | D40: tinggi (m) | E40: Density | F40: Tinggi Sounding (Cm) Maks 4,4 m | G40: Kg
A41: TK231 A | B41: 12.2 | C41: 1.75 | D41: 1.52 | E41: 0.88 | F41: 0 | G41: =B41*C41*D41*E41*F41/100 -> 0
A42: TK231 B | B42: 12.2 | C42: 1.75 | D42: 1.52 | E42: 0.88 | F42: 0 | G42: =B42*C42*D42*E42*F42/100 -> 0
F43: Total STEARIN | G43: =SUM(G41:G42) -> 0

Sheet 2026
B2: PRODUCTION REPORT 2026
B4: No | C4: ITEM | D4: Budget / Norma | E4: UoM | F4: YEARLY REPORT | S4: Yearly Report | T4: Yearly Report RKAP (Budget) | U4: Yearly Report RKAP
F5: JANUARI | G5: FEBRUARI | H5: MARET | I5: APRIL | J5: MEI | K5: JUNI | L5: JULI | M5: AGUSTUS | N5: SEPTEMBER | O5: OKTOBER | P5: NOVEMBER | Q5: DESEMBER | S5: TOTAL (Kg) | T5: TOTAL (Kg) | U5: TOTAL (%)
B6: 1 | C6: PRODUCTION | S6: Production | T6: Production | U6: Production | DF6: 29 | DG6: 30 | DH6: 31
C7: Refinery | S7: Refinery | T7: Refinery | U7: Refinery | DD7: CPO Olah | DE7: Kg | DF7: 1971320 | DG7: 2015120 | DH7: 2015230 | AIT7: Sounding | AIU7: Production | AIV7: Diff
C8: Running Days | D8: 289 | E8: Day | F8: 31 | G8: ='Februari 2026 PMG 2'!AJ6+'Februari 2026 PMG 1'!AJ6 -> 31 | S8: =SUM(F8:Q8) -> 62 | T8: 231 | U8: =S8/T8*100 -> 26.839827 | OQ8: Poram | AED8: 14 Juni | AEE8: 15 Juni | AIS8: CPO | AIT8: 11008948 | AIU8: =S12 -> 118515453 | AIV8: =AIT8-AIU8 -> -107506505
C9: Ratio Run CPO
C10: Utilitas CPO vs RKAP | E10: % | F10: 96638.567 | G10: =G12/G15*100 -> 104576.12 | S10: =S15/S12*1000 -> 5.9709629
C11: Incoming CPO | E11: Kg | F11: 57887356 | G11: ='Februari 2026 PMG 2'!AJ7+'Februari 2026 PMG 1'!AJ7 -> 60114500
C12: CPO Consume Total | D12: 577122.61 | E12: Kg | F12: 56920116 | G12: ='Februari 2026 PMG 2'!AJ9+'Februari 2026 PMG 1'!AJ9 -> 61595337 | S12: =SUM(F12:Q12) -> 118515453 | T12: 421374000 | U12: =S12/T12 -> 0.28125953 | V12: =S12-Q12-P12 -> 118515453 | Z12: =TODAY() -> 46111 | AW12: =S12/D12 -> 205.35576 | DD12: HP Boiler | DE12: mmbtu | DF12: 251.19642 | DG12: 257.91391 | DH12: 251.51265 | ON12: 26946.108 | OO12: 17383.234 | OQ12: RBDPO Olah | AED12: =35.8500000000058*1000 -> 35850 | AIS12: PFAD | AIT12: 566885 | AIU12: =S22 -> 2707546 | AIV12: =AIT12-AIU12 -> -2140661
C13: CPO Consume Poram | E13: Kg | F13: 56920116 | G13: =G12 -> 61595337 | S13: =SUM(F13:Q13) -> 118515453 | Y13: =Q13-'Februari 2026 PMG 2'!#REF! -> #REF! | Z13: Consume Total | AA13: =G12 -> 61595337
C14: CPO Consume Brand | E14: Kg | S14: =SUM(G14:Q14) -> 0 | Z14: RPO | AA14: =G21 -> 58507499 | AW14: =AV14/#REF! -> #REF!
C15: Budget CPO Olah | E15: Kg | F15: 58900 | G15: 58900 | S15: 707651.37 | Z15: PFAD | AA15: =G22 -> 2707546
C16: - FFA | D16: 5 | E16: % | F16: 7.7180076 | G16: ='Februari 2026 PMG 2'!AJ13 -> 4.0351786 | S16: =AVERAGE(G16:Q16) -> 4.0351786 | T16: =AVERAGE(H16:R16) -> #DIV/0! | U16: =AVERAGE(H16:S16) -> 4.0351786 | Z16: Olein 56 | AA16: =G31 -> 35713482 | DD16: Steam Ref | DE16: Kg | DF16: 182230 | DG16: 190070 | DH16: 197800 | ON16: =S12/1000 -> 118515.45 | OO16: =(S30+S53+S39)/1000 -> 43001.096 | OQ16: =SUM(OQ17:OQ18) -> #REF! | AGU16: 2000
C17: - Moist & Impurities | D17: 0.5 | E17: % | F17: 0.85335606 | G17: ='Februari 2026 PMG 2'!AJ14 -> 0.40285714 | S17: =AVERAGE(G17:Q17) -> 0.40285714 | T17: =AVERAGE(H17:R17) -> #DIV/0! | U17: =AVERAGE(H17:S17) -> 0.40285714 | Z17: Stearin 56 | AA17: =G32 -> 7287614 | DE17: Kg/MT | DF17: =DF16/(DF7/1000) -> 92.440598 | DG17: =DG16/(DG7/1000) -> 94.321926 | DH17: =DH16/(DH7/1000) -> 98.152568 | OQ17: =#REF!/1000 -> #REF! | OR17: =OQ17/OQ16*100 -> #REF! | AGT17: 0.942 | AGU17: =AGT17*AGU16 -> 1884 | AGV17: Refinery | AIS17: Olein IV 56 | AIT17: 9594130 | AIU17: =S31 -> 35713482 | AIV17: =AIT17-AIU17 -> -26119352
C18: - DOBI | D18: 2,20 Min | E18: % | S18: =AVERAGE(G18:Q18) -> #DIV/0! | T18: =AVERAGE(H18:R18) -> #DIV/0! | U18: =AVERAGE(H18:S18) -> #DIV/0! | Z18: Olein 58 | AA18: =G44 -> 11911290 | ON18: =SUM(ON16:ON17) -> 118515.45 | OO18: =SUM(OO16:OO17) -> 43001.096 | OQ18: =#REF!/1000 -> #REF! | OR18: =OQ18/OQ16*100 -> #REF! | AGT18: 0.05 | AGU18: =AGT18*AGU16 -> 100 | AIS18: Stearin | AIT18: 2161151 | AIU18: =S32 -> 7287614 | AIV18: =AIT18-AIU18 -> -5126463
C19: Product | S19: Product | T19: Product | U19: Product | Z19: Stearin 58 | AA19: =G45 -> 3718237 | ON19: =ON18/ON12*100 -> 439.82401 | OO19: =OO18/OO12*100 -> 247.3711 | AEF19: Product OIP | AEP19: Juni | AEQ19: Sisa Product OIP
C21: RbdPO | D21: 430861.43 | E21: Kg | F21: 54171735 | G21: ='Februari 2026 PMG 2'!AJ19+'Februari 2026 PMG 1'!AJ19 -> 58507499 | S21: =SUM(F21:Q21) -> 112679234 | T21: 399336000 | U21: =S21/T21*100 -> 28.216648 | AW21: =AW22/D21 -> 136.07768 | DD21: Tahun 2021 | AED21: 136360 | AEE21: 109340 | AEF21: =SUM(AED21:AEE21) -> 245700 | AEP21: 34157.88 | AEQ21: =AEF21-AEP21 -> 211542.12 | AGU21: =AGU17 -> 1884
C22: PFAD | D22: 28965.025 | E22: Kg | F22: 2408805 | G22: ='Februari 2026 PMG 2'!AJ21+'Februari 2026 PMG 1'!AJ21 -> 2707546 | S22: =SUM(G22:Q22) -> 2707546 | T22: 19024000 | U22: =S22/T22*100 -> 14.232265 | AW22: =S30+S34+S39+S53+S43 -> 58630623 | DD22: Items | DF22: Agustus | DG22: Oktober | ON22: =ON12-ON18 -> -91569.345 | OO22: =OO12-OO18 -> -25617.862 | OQ22: Olein IV 58 | OR22: 0 | PD22: 564.70507 | PE22: =OR22/PD22*100 -> 0 | AED22: 13800 | AEE22: 2800 | AEF22: =SUM(AED22:AEE22) -> 16600 | AEP22: 1469.85 | AEQ22: =AEF22-AEP22 -> 15130.15 | AGT22: 0.75 | AGU22: =AGT22*AGU21 -> 1413
C23: Fractionation
C24: Running Days | F24: 35 | G24: ='Februari 2026 PMG 2'!AJ23+'Februari 2026 PMG 1'!AJ23 -> 44 | S24: =SUM(G24:Q24) -> 44
C25: Total Filling Crystalizer ( Feed ) | D25: 659099.44 | E25: Kg | S25: =SUM(G25:Q25) -> 0
C26: Total Proses RBDPO | E26: Kg | F26: =F30+F43 -> 53867455 | G26: =G30+G43 -> 58630623 | S26: =SUM(F26:Q26) -> 112498078
C27: Utilitas RBDPO vs RKAP | E27: % | F27: #DIV/0! | G27: =G26/G28*100 -> #DIV/0! | S27: =S26/S28*100 -> #DIV/0!
C28: Budget RBDPO Olah | E28: Kg
C29: Fractionation OLEIN IV 56 | S29: Olein IV 56 | T29: Olein IV 56 | U29: Olein IV 56 | AA29: =G12-(G21+G22) -> 380292 | DF29: 24 | DG29: 2 | DH29: 3 | OQ29: Olein IV 60 | OR29: =80.53776+PE39 -> 120.78492 | PD29: 4695.7554 | PE29: =OR29/PD29*100 -> 2.5722149 | AGT29: 0.25 | AGU29: =AGT29*AGU21 -> 471
C30: RBDPO Consume | E30: Kg | F30: =F31+F32 -> 39639925 | G30: ='Februari 2026 PMG 2'!AJ32+'Februari 2026 PMG 1'!AJ32 -> 43001096 | S30: =S31+S32 -> 43001096 | T30: =T31+T32 -> 87311000 | U30: =S30/T30*100 -> 49.250491 | AA30: =(AA29/G12) -> 0.0061740388 | DD30: CPO Olah | DE30: Kg | DF30: 2000530 | DG30: 2005167 | DH30: 2025879 | AED30: =95.28%*AED12 -> 34157.88 | AEF30: =AED21-AEP21 -> 102202.12 | AIP30: CPO Feed - Sounding
C31: OLEIN IV 56 | D31: 516092.31 | E31: Kg | F31: 32832043 | G31: ='Februari 2026 PMG 2'!AJ33+'Februari 2026 PMG 1'!AJ33 -> 35713482 | S31: =SUM(G31:Q31) -> 35713482 | T31: 71627000 | U31: =S31/T31*100 -> 49.860363 | DD31: HP Boiler | DE31: mmbtu | DF31: 255.53619 | DG31: 255.09239 | DH31: 260.82455 | ON31: =#REF!/1000 -> #REF! | OQ31: INL 900 ml | OR31: 0 | PD31: 9.75348 | PE31: =(OR31*PD31)/1000 -> 0 | AED31: =4.1%*AED12 -> 1469.85 | AEF31: =AED22-AEP22 -> 12330.15
C32: STEARIN | D32: 118637.9 | E32: Kg | F32: 6807882 | G32: ='Februari 2026 PMG 2'!AJ34+'Februari 2026 PMG 1'!AJ34 -> 7287614 | S32: =SUM(G32:Q32) -> 7287614 | T32: 15684000 | U32: =S32/T32*100 -> 46.465277 | DD32: Steam Ref | DE32: Kg | DF32: 146000 | DG32: 151100 | DH32: 152900 | ON32: 1796 | OQ32: Salvaco 1L | OR32: 1262 | PD32: 10.86 | PE32: =(OR32*PD32)/1000 -> 13.70532 | AIP32: Report Prod
C33: Fractionation OLEIN IV 57 ( Bulk ) | S33: Olein IV 57 ( Bulk ) | T33: Olein IV 57 ( Bulk ) | U33: Olein IV 57 ( Bulk )
C34: RBDPO Consume | E34: Kg | S34: =S35+S36 -> 0 | T34: =T35+T36 -> 5121000 | U34: =S34/T34*100 -> 0 | AW34: =S34+S39 -> 0
C35: OLEIN IV 57 | E35: Kg | S35: =SUM(G35:Q35) -> 0 | T35: 3934000 | U35: =S35/T35*100 -> 0 | AW35: =S35+S40 -> 0
C36: STEARIN | E36: Kg | S36: =SUM(G36:Q36) -> 0 | T36: 1187000 | U36: =S36/T36*100 -> 0 | AW36: =S36+S41 -> 0
C37: Fractionation OLEIN IV 57 ( Retail ) | S37: Olein IV 57 ( Retail ) | T37: Olein IV 57 ( Retail ) | U37: Olein IV 57 ( Retail ) | DE37: Kg/MT | DF37: =DF32/(DF30/1000) -> 72.98066 | DG37: =DG32/(DG30/1000) -> 75.35532 | DH37: =DH32/(DH30/1000) -> 75.473412 | ON37: =ON31/ON32*100 -> #REF! | OQ37: Salvaco 2L | OR37: 2444 | PD37: 10.86 | PE37: =(OR37*PD37)/1000 -> 26.54184 | AIP37: Diff
C38: CPO Consume | E38: Kg | S38: =SUM(G38:Q38) -> 0 | T38: =T39/T61% -> 32338304 | U38: =(S38/T38)*100 -> 0 | DE38: Kg/MT | DF38: =DF32/(DF22/1000) -> #VALUE! | DG38: =DH32/(DG22/1000) -> #VALUE! | DH38: =#REF!/(DH22/1000) -> #REF!
C39: RBDPO Brand Consume | D39: 15000 | E39: Kg | S39: =S40+S41 -> 0 | T39: =T40+T41 -> 30647000 | U39: =(S39/T39)*100 -> 0 | PE39: =SUM(PE32:PE37) -> 40.24716
C40: OLEIN IV 57 ( Retail ) | D40: 12000 | E40: Kg | S40: =SUM(G40:Q40) -> 0 | T40: 23002000 | U40: =S40/T40*100 -> 0
C41: STEARIN | D41: 3000 | E41: Kg | S41: =SUM(G41:Q41) -> 0 | T41: 7645000 | U41: =S41/T41*100 -> 0
C42: Fractionation OLEIN IV 58 ( BULK ) | S42: Olein IV 58 | T42: Olein IV 58 | U42: Olein IV 58
C43: RBDPO Consume | E43: Kg | F43: =F44+F45 -> 14227530 | G43: ='Februari 2026 PMG 2'!AJ45+'Februari 2026 PMG 1'!AJ45 -> 15629527 | S43: =S44+S45 -> 15629527 | T43: =T44+T45 -> 249961000 | U43: =S43/T43*100 -> 6.2527862
C44: OLEIN IV 58 ( Bulk ) | D44: 373200 | E44: Kg | F44: 10803048 | G44: ='Februari 2026 PMG 2'!AJ46+'Februari 2026 PMG 1'!AJ46 -> 11911290 | S44: =SUM(G44:Q44) -> 11911290 | T44: 175000000 | U44: =S44/T44*100 -> 6.8064514
C45: STEARIN | D45: 95142.857 | E45: Kg | F45: 3424482 | G45: ='Februari 2026 PMG 1'!AJ47+'Februari 2026 PMG 2'!AJ47 -> 3718237 | S45: =SUM(G45:Q45) -> 3718237 | T45: 74961000 | U45: =S45/T45*100 -> 4.9602287
C46: Fractionation OLEIN IV 58 ( Retail )
C47: CPO Consume | E47: Kg
C48: RBDPO Consume | E48: Kg | S48: =S49+S50 -> 0
C49: OLEIN IV 58 | E49: Kg | S49: =SUM(G49:Q49) -> 0
C50: STEARIN | E50: Kg | S50: =SUM(G50:Q50) -> 0
C51: Fractionation OLEIN IV 60 | S51: Olein IV 60 | T51: Olein IV 60 | U51: Olein IV 60
C52: CPO Consume | E52: Kg | S52: =SUM(G52:Q52) -> 0 | T52: =T53/T61% -> 25913273 | U52: =S52/T52*100 -> 0
C53: RBDPO Brand Consume | E53: Kg | F53: 0 | G53: ='Februari 2026 PMG 2'!AB55 -> 0 | S53: =S55+S56 -> 0 | T53: =T55+T56 -> 24558000 | U53: =S53/T53*100 -> 0 | DF53: 2136
C54: OLEIN IV 60 Bulk | E54: Kg | S54: =SUM(G54:Q54) -> 0 | T54: =SUM(G54:Q54) -> 0 | U54: =SUM(H54:S54) -> 0
C55: OLEIN IV 60 Salvaco | D55: 25000 | E55: Kg | F55: 0 | G55: ='Februari 2026 PMG 2'!AB56 -> 0 | S55: =SUM(G55:Q55) -> 0 | T55: 14736000 | U55: =S55/T55*100 -> 0 | DF55: 1796
C56: SOFT STEARIN | D56: 10000 | E56: Kg | F56: 0 | G56: ='Februari 2026 PMG 2'!AB57 -> 0 | S56: =SUM(G56:Q56) -> 0 | T56: 9822000 | U56: =S56/T56*100 -> 0 | DF56: =DF53/DF55*100 -> 118.93096
C57: Ratio Run RBDPO | S57: =+AVERAGE(G57:Q57) -> #DIV/0!
C58: Utilitas RBDPO | S58: =+AVERAGE(G58:Q58) -> #DIV/0!
C59: Budget RBDPO | S59: =SUM(G59:Q59) -> 0
C60: YIELD | S60: Yield | T60: Yield | U60: Yield | W60: =153073+111053 -> 264126 | OO60: 678
C61: RBDPO | D61: 94.2 | E61: % | F61: 95.376981 | G61: ='Februari 2026 PMG 2'!AJ60 -> 95.455795 | S61: =(S21/(S12))*100 -> 95.075563 | T61: =(T21/(T12))*100 -> 94.769967 | OO61: 420 | OQ61: =OO61/OO60*100 -> 61.946903
C62: PFAD | D62: 5 | E62: % | F62: 4.36753 | G62: ='Februari 2026 PMG 2'!AJ61 -> 4.3820447 | S62: =(S22/(S12))*100 -> 2.284551 | T62: =(T22/(T12))*100 -> 4.5147541 | W62: 111053 | OO62: =OO60-OO61 -> 258 | OQ62: =OO62/OO60*100 -> 38.053097
C63: Olein IV 56 | D63: 82 | E63: % | F63: 82.828482 | G63: ='Februari 2026 PMG 2'!AJ62 -> 83.098987 | S63: =(S31/S30)*100 -> 83.052492 | T63: =(T31/T30)*100 -> 82.036628
C64: Stearin | D64: 18 | E64: % | F64: 17.171518 | G64: ='Februari 2026 PMG 2'!AJ63 -> 16.901013 | S64: =(S32/S30)*100 -> 16.947508 | T64: =(T32/T30)*100 -> 17.963372 | W64: =S76-W69 -> -396634
C65: Olein IV 57 ( Bulk ) | D65: 75 | E65: % | S65: =(S35/S34)*100 -> #DIV/0! | T65: 75
C66: Stearin | D66: 25 | E66: % | S66: =(S36/S34)*100 -> #DIV/0! | T66: 25
C67: Olein IV 57 ( Retail ) | D67: 75 | E67: % | S67: =(S40/S39)*100 -> #DIV/0! | T67: 75
C68: Stearin | D68: 25 | E68: % | S68: =(S41/S39)*100 -> #DIV/0! | T68: 25 | FM68: 95.03
C69: Olein IV 58 ( Bulk ) | D69: 70 | E69: % | F69: 75.866496 | G69: ='Februari 2026 PMG 2'!AJ68 -> 76.027572 | S69: =(S44/S43)*100 -> 76.210176 | T69: 70 | W69: 722634
C70: Stearin | D70: 30 | E70: % | F70: 24.133504 | G70: ='Februari 2026 PMG 2'!AJ69 -> 23.972428 | S70: =(S45/S43)*100 -> 23.789824 | T70: 30
C71: Olein IV 58 ( Retail ) | D71: 70 | E71: %
C72: Stearin | D72: 30 | E72: %
C73: Olein IV 60 | D73: 60 | E73: % | F73: #DIV/0! | G73: ='Februari 2026 PMG 2'!AB72 -> 0 | S73: =(S55/S53)*100 -> #DIV/0! | T73: =T55/T53*100 -> 60.004886 | W73: =153073+138655 -> 291728 | FM73: 4.23 | OQ73: =OQ74/94.2% -> 1307.8556 | OR73: MT CPO
C74: Soft Stearin | D74: 40 | E74: % | F74: #DIV/0! | G74: ='Februari 2026 PMG 2'!AB73 -> 0 | S74: =(S56/S53)*100 -> #DIV/0! | T74: =T56/T53*100 -> 39.995114 | FM74: =100-FM68-FM73 -> 0.74 | OQ74: =22*56 -> 1232 | OR74: MT RBDPO Brand
B75: 2 | C75: CHEMICAL CONSUMABLE | S75: Chemical | T75: Chemical | U75: Chemical | OQ75: =16.5*OQ73 -> 21579.618
C76: Bleaching Earth (BE) to Poram Spec | D76: 6 | E76: Kg | F76: 386825 | G76: ='Februari 2026 PMG 1'!AJ75+'Februari 2026 PMG 2'!AJ75 -> 326000 | S76: =SUM(G76:Q76) -> 326000 | T76: 2767753 | U76: =S76/T76*100 -> 11.778508 | W76: =S76-611581 -> -285581
E77: % | F77: 0.67460297 | G77: =(G76/G12)*100 -> 0.52926084 | S77: =S76/(S12)*100 -> 0.27506961 | T77: 0.8 | U77: 0 | AW77: =S77*10 -> 2.7506961 | FM77: =#REF!*10 -> #REF! | OQ77: =OQ73+(S52/1000) -> 1307.8556 | OR77: Total CPO Brand
C78: Bleaching Earth (BE) to Branded Spec | D78: 16 | E78: Kg | S78: =SUM(G78:Q78) -> 0 | T78: 1357284 | U78: =S78/T78*100 -> 0 | OQ78: =OQ75+S78 -> 21579.618 | OR78: Total BE Brand
E79: % | S79: =S78/(S14)*100 -> #DIV/0! | T79: 1.8 | U79: 0 | AW79: =S79*10 -> #DIV/0! | OQ79: =OQ78/OQ77 -> 16.5 | OR79: Kg/MT CPO
C80: Phosporic Acid (PA) | D80: 0.055 | E80: Kg | F80: 33324.696 | G80: ='Februari 2026 PMG 2'!AJ86+'Februari 2026 PMG 1'!AJ86 -> 32752.28 | S80: =SUM(G80:Q80) -> 32752.28 | T80: 252824 | U80: =SUM(H80:S80) -> 32752.28 | OQ80: 16 | OR80: Budget (Kg/MT)
E81: % | F81: 0.053511217 | G81: =(G80/G12)*100 -> 0.053173311 | S81: =S80/(S12+71450)*100 -> 0.0276188 | T81: 0.06 | U81: =U80/(U12+71450)*100 -> 45.83926 | AW81: =S81*10 -> 0.276188 | FM81: =#REF!*10 -> #REF! | OQ81: =OQ79-OQ80 -> 0.5 | OR81: Over (Kg/MT)
B82: 3 | C82: Oil Losses | D82: 0.8 | E82: % | F82: =(('[1]Januari 2026 PMG 2'!$AM$89+'[1]Januari 2026 PMG 1'!$AM$89)/F12)*100 -> -0.59658346 | G82: =(('Februari 2026 PMG 2'!AJ89+'Februari 2026 PMG 1'!AJ89)/'2026'!G12)*100 -> -0.61740388 | S82: =((G83+F83)*(-1000)/S12)/10 -> 0.60740434 | T82: =((SUM(T21:T22))-(SUM(T12)))/(SUM(T12))*100 -> -0.71527906 | U82: =#REF!/T82*100 -> #REF!
E83: Kg | F83: =('[1]Januari 2026 PMG 2'!$AM$89)+('[1]Januari 2026 PMG 1'!$AM$89) -> -339576 | G83: =('Februari 2026 PMG 2'!AJ89)+('Februari 2026 PMG 1'!AJ89) -> -380292 | S83: =(F83+G83)*(-1000) -> 719868000
C84: % Oil Content | D84: 22 | E84: % | F84: 17.46 | G84: ='Februari 2026 PMG 2'!AJ90 -> 17.449643 | S84: =AVERAGE(H84:K84) -> #DIV/0! | T84: 22 | U84: =AVERAGE(H84:S84) -> #DIV/0!
C85: Spent Bleaching Earth | E85: Kg | F85: 273050.1 | G85: ='Februari 2026 PMG 2'!AJ91 -> 323920.17 | S85: =SUM(S76,S78)+(S84%*SUM(S76,S78)) -> #DIV/0! | T85: 7811279 | U85: =SUM(U76,U78)+(U84%*SUM(U76,U78)) -> #DIV/0! | FZ85: =W85+400 -> 400
B86: 5 | C86: PACKAGING (Brand Salvaco) | S86: Packaging | T86: Packaging | U86: Packaging | FW86: 17292 | OX86: =#REF!-FW86 -> #REF!
C87: Olein IV 60 Received | E87: Kg | S87: =SUM(G87:Q87) -> 0 | T87: =SUM(H87:R87) -> 0 | U87: =(S87/T87)*100 -> #DIV/0!
C88: Olein IV 60 Consume | E88: Kg | S88: =SUM(S89:S91) -> 0 | T88: =SUM(T89:T91) -> 32269046 | U88: =(S88/T88)*100 -> 0 | AFQ88: Kg | AFR88: Olein Filling to Packaging
C89: - finished product | E89: Kg | S89: =SUM(S93:S94)*10.86 -> 0 | T89: =SUM(T93:T94)*10.86 -> 32269046 | U89: =(S89/T89)*100 -> 0 | FW89: =#REF!/1000 -> #REF! | OX89: 4696 | OY89: =FW89/OX89*100 -> #REF!
C90: - sample | E90: Kg | S90: =SUM(G90:Q90) -> 0 | T90: =SUM(H90:R90) -> 0 | U90: =(S90/T90)*100 -> #DIV/0! | FW90: =#REF!/1000 -> #REF! | OX90: 565 | OY90: =FW90/OX90*100 -> #REF!
C91: - remelt, flushing, downgrade | E91: Kg | S91: =SUM(G91:Q91) -> 0 | T91: =SUM(H91:R91) -> 0
C92: Carton | S92: Carton | T92: Carton | U92: Carton
C93: Salvaco 1 Liter | E93: Box | S93: =SUM(G93:Q93) -> 0 | T93: 1254577 | U93: =(S93/T93)*100 -> 0
C94: Salvaco 2 Liter | E94: Box | S94: =SUM(G94:Q94) -> 0 | T94: 1716790 | U94: =(S94/T94)*100 -> 0
C95: Pouch | S95: Pouch | T95: Pouch | U95: Pouch
C96: Salvaco 1 Liter | E96: Pouch | S96: =S93*12 -> 0 | T96: =T93*12 -> 15054924 | U96: =(S96/T96)*100 -> 0
C97: Salvaco 2 Liter | E97: Pouch | S97: =S94*6 -> 0 | T97: =T94*6 -> 10300740 | U97: =(S97/T97)*100 -> 0
C98: Consumable Vit. A | E98: gram | S98: =SUM(G98:Q98) -> 0 | T98: =(T88*45)/1700 -> 854180.62 | U98: =(S98/T98)*100 -> 0
C99: Consumable Packing Tape | E99: Roll | S99: =SUM(G99:Q99) -> 0 | T99: =SUM(T93:T94)/500 -> 5942.734 | U99: =(S99/T99)*100 -> 0
C100: REJECT MATERIAL QTY | S100: Loss Material | T100: Loss Material | U100: Loss Material
C101: Carton | S101: Carton | T101: Carton | U101: Carton
C102: Salvaco 1 Liter | E102: Box | S102: =SUM(G102:Q102) -> 0 | T102: =SUM(H102:R102) -> 0 | U102: =SUM(H102:S102) -> 0
C103: Salvaco 2 Liter | E103: Box | S103: =SUM(G103:Q103) -> 0 | T103: =SUM(H103:R103) -> 0 | U103: =SUM(H103:S103) -> 0
...

Sheet Downtime Ref Oktober
F2: DOWN TIME SLOW FLOWRATE PRODUCTION REFINERY
F4: Periode 01/31 Oktober 2024
F5: TANGGAL | G5: CAPACITY (Kg) | H5: REMARKS | I5: Down time | M5: Tph
I6: Stop | J6: Slow | K6: % | AE6: 17 | AF6: 18 | AG6: 19 | AH6: 20 | AI6: 21 | AJ6: 22 | AK6: 23 | AL6: 24 | AM6: 25 | AN6: 26 | AO6: 27 | AP6: 28 | AQ6: 29 | AR6: 30 | AS6: 31
F7: 1 | G7: 1329220 | H7: Penyesuaian incoming CPO | J7: =(2200-(G7/1000))/91.7 -> 9.4959651 | K7: =G7/2200/1000 -> 0.60419091 | M7: =(G7/1000)/24 -> 55.384167 | O7: =249.262+270.9 -> 520.162 | P7: =1356.367+39.742 -> 1396.109 | Q7: =1086.521+50.6 -> 1137.121 | R7: =1353.558+373.309 -> 1726.867 | S7: 1942.746 | T7: 1868.212 | U7: 2057.011 | V7: 1781.844 | W7: 1250.764 | X7: 1613.486 | Y7: 1325.077 | Z7: =66.442+571.568 -> 638.01 | AA7: =815.429 -> 815.429 | AB7: =352.234+731.627 -> 1083.861 | AC7: =1626.002+13.213 -> 1639.215 | AD7: 2094.791 | AE7: 2075.375 | AF7: 2008.804 | AG7: 1946.712 | AH7: 1998.939 | AI7: =1623.839+281.468 -> 1905.307 | AJ7: 1610.024 | AK7: =1135.181+98.368 -> 1233.549 | AL7: =958.893+543.852 -> 1502.745 | AM7: 2043.15 | AN7: 1762.642 | AO7: 2170.336 | AP7: =1181.38+463.711 -> 1645.091 | AQ7: 219.474 | AR7: =48.153+1225.968+107.3 -> 1381.421
F8: 2 | G8: 1090185 | H8: Penyesuaian incoming CPO | J8: =(2200-(G8/1000))/91.7 -> 12.102672 | K8: =G8/2200/1000 -> 0.49553864 | M8: =(G8/1000)/24 -> 45.424375
F9: 3 | G9: 0 | H9: HOLD CPO Shortage | J9: =(2200-(G9/1000))/91.7 -> 23.991276 | K9: =G9/2200/1000 -> 0 | M9: =(G9/1000)/24 -> 0
F10: 4 | G10: 1214493 | H10: Penyesuaian incoming CPO | J10: =(2200-(G10/1000))/91.7 -> 10.747077 | K10: =G10/2200/1000 -> 0.55204227 | M10: =(G10/1000)/24 -> 50.603875
F11: 5 | G11: 466758 | H11: Penyesuaian incoming CPO | J11: =(2200-(G11/1000))/91.7 -> 18.901221 | K11: =G11/2000/1000 -> 0.233379 | M11: =(G11/1000)/24 -> 19.44825
F12: 6 | G12: 206159 | H12: Penyesuaian incoming CPO | J12: =(2200-(G12/1000))/91.7 -> 21.743086 | K12: =G12/2200/1000 -> 0.093708636 | M12: =(G12/1000)/24 -> 8.5899583
F13: 7 | G13: 630399 | H13: Penyesuaian incoming CPO | J13: =(2200-(G13/1000))/91.7 -> 17.116696 | K13: =G13/2200/1000 -> 0.286545 | M13: =(G13/1000)/24 -> 26.266625
F14: 8 | G14: 326961 | H14: Penyesuaian incoming CPO | J14: =(2200-(G14/1000))/91.7 -> 20.425725 | K14: =G14/2200/1000 -> 0.14861864 | M14: =(G14/1000)/24 -> 13.623375
F15: 9 | G15: 783993 | H15: Penyesuaian incoming CPO | J15: =(2200-(G15/1000))/91.7 -> 15.441734 | K15: =G15/2200/1000 -> 0.35636045 | M15: =(G15/1000)/24 -> 32.666375
F16: 10 | G16: 529241 | H16: Penyesuaian incoming CPO | J16: =(2200-(G16/1000))/91.7 -> 18.219836 | K16: =G16/2200/1000 -> 0.24056409 | M16: =(G16/1000)/24 -> 22.051708
F17: 11 | G17: 1204852 | H17: Penyesuaian incoming CPO | J17: =(2200-(G17/1000))/91.7 -> 10.852214 | K17: =G17/2200/1000 -> 0.54766 | M17: =(G17/1000)/24 -> 50.202167
F18: 12 | G18: 1651432 | H18: Penyesuaian incoming CPO | J18: =(2200-(G18/1000))/91.7 -> 5.9822028 | K18: =G18/2200/1000 -> 0.75065091 | M18: =(G18/1000)/24 -> 68.809667
F19: 13 | G19: 1336027 | H19: Penyesuaian incoming CPO | J19: =(2200-(G19/1000))/91.7 -> 9.4217339 | K19: =G19/2200/1000 -> 0.607285 | M19: =(G19/1000)/24 -> 55.667792
F20: 14 | G20: 524254 | H20: Penyesuaian incoming CPO | J20: =(2200-(G20/1000))/91.7 -> 18.27422 | K20: =G20/2200/1000 -> 0.23829727 | M20: =(G20/1000)/24 -> 21.843917
F21: 15 | G21: 935273 | H21: Penyesuaian incoming CPO | J21: =(2200-(G21/1000))/91.7 -> 13.792007 | K21: =G21/2200/1000 -> 0.42512409 | M21: =(G21/1000)/24 -> 38.969708
F22: 16 | G22: 1014253 | H22: Penyesuaian incoming CPO | J22: =(2200-(G22/1000))/91.7 -> 12.93072 | K22: =G22/2200/1000 -> 0.46102409 | M22: =(G22/1000)/24 -> 42.260542
F23: 17 | G23: 805977 | H23: Penyesuaian incoming CPO | J23: =(2200-(G23/1000))/91.7 -> 15.201996 | K23: =G23/2200/1000 -> 0.36635318 | M23: =(G23/1000)/24 -> 33.582375
... F37: 31 | G37: 498387 | H37: Penyesuaian incoming CPO | J37: =(2200-(G37/1000))/91.7 -> 18.556303 | K37: =G37/2200/1000 -> 0.22653955 | M37: =(G37/1000)/24 -> 20.766125
F38: TOTAL | G38: =SUM(G7:G37) -> 23466959 | I38: =SUM(I7:I36) -> 0 | J38: =SUM(J7:J37) -> 487.81942 | M38: =AVERAGE(M7:M37) -> 31.541612
G40: Summary
G41: 1. Slow flow rate due to Space Tank High | I41: 0 | J41: hours
G42: 2. Slow flow rate due to Olein IV 60 process | I42: 0 | J42: hours
G43: 3. Hold plant due to trip MP boiler & maintenance | I43: 0 | J43: hours
G44: 4. Penyesuaian incoming CPO | I44: =SUM(J7,J8,J10,J11,J12,J13,J14,J15,J16,J17,J18,J19,J20,J21,J22,J24,J23,J25,J28,J29,J30,J31,J32,J33,J34,J35,J36,J37) -> 415.84559 | J44: hours
G45: 5. Downtime due to Start Up Plant | J45: hours
G46: 6. Running Normal Plant | I46: 0 | J46: hours
G47: 7. Stop Plant due to Preventive Maintenance Plant | I47: 0 | J47: hours
G48: 8. Energizing PMG II | I48: 0 | J48: hours
G49: 9. Zero Suplay Gas (Problem Pertagas) | I49: 0 | J49: hours
G50: 10, Stop Plant | I50: 0 | J50: hours
G51: 11.HOLD CPO Shortage | I51: =SUM(J9,J26,J27) -> 71.973828 | J51: hours
G52: Total | I52: =SUM(I41:I51) -> 487.81942 | J52: hours
G53: Note : Kapasitas 2200 TPD

Sheet Downtime Fract Oktober
F2: DOWN TIME SLOW FLOWRATE PRODUCTION FRACTIONATION
F4: Periode 01/30 Oktober 2024
F5: TANGGAL | G5: CAPACITY (Kg) | H5: REMARKS | I5: Down time | M5: Tph
I6: Stop | J6: Slow | K6: % | AE6: 17 | AF6: 18 | AG6: 19 | AH6: 20 | AI6: 21 | AJ6: 22 | AK6: 23 | AL6: 24 | AM6: 25 | AN6: 26 | AO6: 27 | AP6: 28 | AQ6: 29 | AR6: 30 | AS6: 31
F7: 1 | G7: 823008 | H7: Slow flow rate due to Olein IV 56 process & IV 58 process | J7: =(2000-(G7/1000))/83.33 -> 14.124469 | K7: =G7/2000/1000 -> 0.411504 | M7: =(G7/1000)/24 -> 34.292 | O7: =249.262+270.9 -> 520.162 | P7: =1356.367+39.742 -> 1396.109 | Q7: =1086.521+50.6 -> 1137.121 | R7: =1353.558+373.309 -> 1726.867 | S7: 1942.746 | T7: 1868.212 | U7: 2057.011 | V7: 1781.844 | W7: 1250.764 | X7: 1613.486 | Y7: 1325.077 | Z7: =66.442+571.568 -> 638.01 | AA7: =815.429 -> 815.429 | AB7: =352.234+731.627 -> 1083.861 | AC7: =1626.002+13.213 -> 1639.215 | AD7: 2094.791 | AE7: 2075.375 | AF7: 2008.804 | AG7: 1946.712 | AH7: 1998.939 | AI7: =1623.839+281.468 -> 1905.307 | AJ7: 1610.024 | AK7: =1135.181+98.368 -> 1233.549 | AL7: =958.893+543.852 -> 1502.745 | AM7: 2043.15 | AN7: 1762.642 | AO7: 2170.336 | AP7: =1181.38+463.711 -> 1645.091 | AQ7: 219.474 | AR7: =48.153+1225.968+107.3 -> 1381.421
F8: 2 | G8: 1133656 | H8: Slow flow rate due to Olein IV 58 process | J8: =(2000-(G8/1000))/83.33 -> 10.396544 | K8: =G8/2000/1000 -> 0.566828 | M8: =(G8/1000)/24 -> 47.235667
F9: 3 | G9: 852841 | H9: Slow flow rate due to Olein IV 58 process | J9: =(2000-(G9/1000))/83.33 -> 13.766459 | K9: =G9/2000/1000 -> 0.4264205 | M9: =(G9/1000)/24 -> 35.535042
F10: 4 | G10: 285950 | H10: Slow flow rate due to Olein IV 58 process | J10: =(2000-(G10/1000))/83.33 -> 20.569423 | K10: =G10/2000/1000 -> 0.142975 | M10: =(G10/1000)/24 -> 11.914583
F11: 5 | G11: 767986 | H11: Slow flow rate due to Olein IV 58 process | J11: =(2000-(G11/1000))/83.33 -> 14.784759 | K11: =G11/2000/1000 -> 0.383993 | M11: =(G11/1000)/24 -> 31.999417
F12: 6 | G12: 178639 | H12: Slow flow rate due to Olein IV 58 process | J12: =(2000-(G12/1000))/83.33 -> 21.857206 | K12: =G12/2000/1000 -> 0.0893195 | M12: =(G12/1000)/24 -> 7.4432917
F13: 7 | G13: 216297 | H13: Slow flow rate due to Olein IV 58 process | J13: =(2000-(G13/1000))/83.33 -> 21.405292 | K13: =G13/2000/1000 -> 0.1081485 | M13: =(G13/1000)/24 -> 9.012375
F14: 8 | G14: 447025 | H14: Slow flow rate due to Olein IV 58 process | J14: =(2000-(G14/1000))/83.33 -> 18.636445 | K14: =G14/2000/1000 -> 0.2235125 | M14: =(G14/1000)/24 -> 18.626042
F15: 9 | G15: 821777 | H15: Slow flow rate due to Olein IV 58 process | J15: =(2000-(G15/1000))/83.33 -> 14.139242 | K15: =G15/2000/1000 -> 0.4108885 | M15: =(G15/1000)/24 -> 34.240708
F16: 10 | G16: 862670 | H16: Slow flow rate due to Olein IV 56 process & IV 58 process | J16: =(2000-(G16/1000))/83.33 -> 13.648506 | K16: =G16/2000/1000 -> 0.431335 | M16: =(G16/1000)/24 -> 35.944583
F17: 11 | G17: 1138713 | H17: Slow flow rate due to Olein IV 56 process & IV 58 process | J17: =(2000-(G17/1000))/83.33 -> 10.335857 | K17: =G17/2000/1000 -> 0.5693565 | M17: =(G17/1000)/24 -> 47.446375
F18: 12 | G18: 1185707 | H18: Slow flow rate due to Olein IV 56 process | J18: =(2000-(G18/1000))/83.33 -> 9.7719069 | K18: =G18/2000/1000 -> 0.5928535 | M18: =(G18/1000)/24 -> 49.404458
F19: 13 | G19: 699301 | H19: Slow flow rate due to Olein IV 56 process | J19: =(2000-(G19/1000))/83.33 -> 15.609012 | K19: =G19/2000/1000 -> 0.3496505 | M19: =(G19/1000)/24 -> 29.137542
... F37: 31 | G37: 1052080 | H37: Slow flow rate due to Olein IV 58 process | J37: =(2000-(G37/1000))/83.33 -> 11.375495 | K37: =G37/2000/1000 -> 0.52604 | M37: =(G37/1000)/24 -> 43.836667
F38: TOTAL | G38: =SUM(G7:G37) -> 20051919 | I38: =SUM(I7:I36) -> 0 | J38: =SUM(J7:J37) -> 503.39711 | M38: =AVERAGE(M7:M37) -> 26.951504
G40: Summary
G41: 1. Slow flow rate due to Space Tank High | I41: 0 | J41: hours
G42: 2. Slow flow rate due to Olein IV 60 process | I42: 0 | J42: hours
G43: 3. Slow flow rate due to Olein IV 57 process | I43: 0 | J43: hours
G44: 4. Slow Flow rate terkait material sortage & menyesuaikan | I44: 0 | J44: hours
G45: 5. Downtime due to Start/Stop Up Plant | I45: 0 | J45: hours
G46: 6. Running Normal Plant | I46: 0 | J46: hours
G47: 7. Stop Plant due to Preventive Maintenance Plant | I47: 0 | J47: hours
G48: 8. Energizing PMG II | I48: 0 | J48: hours
G49: 9. Zero Suplay Gas (Problem Pertagas) | I49: 0 | J49: hours
G50: 10. Slow flow rate due to Olein IV 58 process | I50: =SUM(J8,J9,J10,J11,J12,J13,J14,J15,J31,J32,J33,J34,J35,J36,J37) -> 245.89803 | J50: hours
G51: 11. STOP PLANT | I51: =SUM(J27,J28,J29,J30) -> 96.00384 | J51: hours
G52: 12.Slow flow rate due to Olein IV 56 process | I52: =SUM(J18,J19,J20,J21,J22,J23,J24,J25,J26) -> 123.3864 | J52: hours
G53: 13. Slow flow rate due to Olein IV 56 process & IV 57 process | I53: 0 | J53: hours
G54: 14. Slow flow rate due to Olein IV 56 process & IV 58 process | I54: =SUM(J7,J16,J17) -> 38.108832 | J54: hours
G55: Total | I55: =SUM(I41:I54) -> 503.39711 | J55: hours
G56: 8. Note : Kapasitas 2000 TPD

Sheet Prod
B2: MONTHLY PRODUCTION REPORT
B3: PT. INDUSTRI NABATI LESTARI
B4: Periode 01 s/d 31 maret 2025
B5: NO | C5: Item | D5: Unit | E5: September | H5: Remaks
E6: Budget | F6: Actual | G6: Percentage Act.
B7: 1. | C7: PRODUCTION
C8: Refinery Plant
C9: Running Days | D9: Days | E9: 19 | F9: ='Februari 2026 PMG 2'!$AJ$6 -> 28 | G9: =(F9/E9) -> 1.4736842 | H9: Tercapai
C10: CPO Incoming | D10: Kg
C11: Total CPO Consume | D11: Kg | E11: ='Februari 2026 PMG 2'!E9 -> 48093.551 | F11: =F12+F13 -> 60737537 | G11: =(F11/E11) -> 1262.904 | H11: Tidak Tercapai
C12: CPO Consume Poram | F12: ='Februari 2026 PMG 2'!$AJ$11 -> 60737537
C13: CPO Consume Brand | F13: ='Februari 2026 PMG 2'!$AJ$12 -> 0
C14: - Avg. FFA | D14: % | E14: 5 | F14: ='Februari 2026 PMG 2'!$AJ$13 -> 4.0351786 | G14: =(F14/E14) -> 0.80703571
C15: - Avg. Moist & Impurities | D15: % | E15: 0.5 | F15: ='Februari 2026 PMG 2'!$AJ$14 -> 0.40285714 | G15: =(F15/E15) -> 0.80571429
C16: - Avg. DOBI | D16: % | E16: 22.2 | F16: ='Februari 2026 PMG 2'!$O$15 -> 0 | G16: =(F16/E16) -> 0
C17: Product
C18: RBDPO | D18: Kg | E18: ='Februari 2026 PMG 2'!E20 -> 45448.405 | F18: ='Februari 2026 PMG 2'!$AJ$20 -> 0 | G18: =(F18/E18) -> 0
C19: PFAD | D19: Kg | E19: ='Februari 2026 PMG 2'!E21 -> 2308.4904 | F19: ='Februari 2026 PMG 2'!$AJ$21 -> 2661546 | G19: =(F19/E19) -> 1152.9379
C21: Fraksinasi Plant
C22: Total Proses RBDPO | D22: Kg | E22: ='Februari 2026 PMG 2'!E29 -> 49015.009 | F22: ='Februari 2026 PMG 2'!$AJ$29 -> 49278223 | G22: =(F22/E22) -> 1005.3701 | H22: Tidak Tercapai
C23: Total Olah RBDPO ( Feed ) | D23: Kg | E23: 35501000 | F23: ='Februari 2026 PMG 2'!$AJ$25 -> 0 | G23: =(F23/E23) -> 0 | H23: Tidak Tercapai
C24: Fractionation Olein IV 56
C25: RBDPO Consume | D25: Kg | E25: =E26+E27 -> 679192.31 | F25: =F26+F27 -> 39712496 | G25: =(F25/E25) -> 58.470179 | H25: Tercapai
C26: Olein IV 56 | D26: Kg | E26: ='Februari 2026 PMG 2'!E33 -> 40192.308 | F26: ='Februari 2026 PMG 2'!$AJ$33 -> 33000682 | G26: =(F26/E26) -> 821.0696 | H26: Tercapai
C27: Stearin | D27: Kg | E27: ='Februari 2026 PMG 2'!E34 -> 639000 | F27: ='Februari 2026 PMG 2'!$AJ$34 -> 6711814 | G27: =(F27/E27) -> 10.503621 | H27: Tercapai
C28: Fractionation Olein IV 57 ( Bulk )
C29: RBDPO Consume | D29: Kg | E29: 0
C30: Olein IV 57 | D30: Kg | E30: 0 | F30: 0 | G30: 0
C31: Stearin | D31: Kg | E31: 0
C32: Fractionation Olein IV 58 ( bulk )
C33: CPO | D33: Kg | E33: 1812101.9 | G33: =(F33/E33)*100 -> 0
C34: RBDPO Consume | D34: Kg | E34: =E35+E36 -> 12514300 | F34: =F35+F36 -> 0 | G34: =(F34/E34)*100 -> 0 | H34: Tidak Tercapai
C35: Olein IV 58 | D35: Kg | E35: ='Februari 2026 PMG 2'!E46 -> 12000000 | G35: =(F35/E35)*100 -> 0 | H35: Tidak Tercapai
C36: Stearin | D36: Kg | E36: ='Februari 2026 PMG 2'!E47 -> 514300 | G36: =(F36/E36)*100 -> 0 | H36: Tidak Tercapai
C37: Fractionation Olein IV 58
C38: RBDPO Consume | D38: Kg | E38: 21429000 | F38: =F39+F40 -> 9565727 | G38: =(F38/E38)*100 -> 44.639167 | H38: Tidak Tercapai
C39: Olein IV 58 | D39: Kg | E39: 15000000 | F39: ='Februari 2026 PMG 2'!$AJ$46 -> 7272590 | G39: =(F39/E39)*100 -> 48.483933 | H39: Tidak Tercapai
C40: Stearin | D40: Kg | E40: 6429000 | F40: ='Februari 2026 PMG 2'!$AJ$47 -> 2293137 | G40: =(F40/E40)*100 -> 35.668642 | H40: Tidak Tercapai
C41: Fractionation Olein IV 60
C42: CPO | E42: 2234607.2 | F42: 0 | G42: =(F42/E42)*100 -> 0
C43: RBDPO Consume | D43: Kg | E43: =E44+E45 -> 1333300 | F43: 0 | G43: =(F43/E43)*100 -> 0 | H43: Tidak Tercapai
C44: Olein IV 60 Salvaco | D44: Kg | E44: ='Februari 2026 PMG 2'!E56 -> 1250000 | F44: ='Februari 2026 PMG 2'!AJ56 -> 0 | G44: =(F44/E44)*100 -> 0 | H44: Tidak Tercapai
C45: Soft Stearin | D45: Kg | E45: ='Februari 2026 PMG 2'!E57 -> 83300 | F45: ='Februari 2026 PMG 2'!AJ57 -> 0 | G45: =(F45/E45)*100 -> 0 | H45: Tidak Tercapai
B46: 2. | C46: % YIELD
C47: RBDPO | D47: % | E47: 94.77 | F47: =(F18/F11)*100 -> 0 | G47: =(F47/E47)*100 -> 0 | H47: Tidak Tercapai
C48: PFAD | D48: % | E48: 4.5 | F48: =(F19/(F11))*100 -> 4.3820447 | G48: =(F48/E48)*100 -> 97.37877 | H48: Tidak Tercapai
C49: Olein IV 56 | D49: % | E49: 82 | F49: =F26/(F26+F27)*100 -> 83.098987 | G49: =(F49/E49)*100 -> 101.34023 | H49: Tercapai
C50: Stearin | D50: % | E50: 18 | F50: =(F27/F25)*100 -> 16.901013 | G50: =(F50/E50)*100 -> 93.894515 | H50: Tercapai
C51: Olein IV 57 ( Bulk ) | D51: % | E51: 75 | F51: 0 | G51: =(F51/E51)*100 -> 0
C52: Stearin | D52: % | E52: 25 | F52: 0 | G52: =(F52/E52)*100 -> 0
C53: Olein IV 57 ( Retail ) | D53: % | E53: 75 | F53: =F35/(F35+F36)*100 -> #DIV/0! | G53: =(F53/E53)*100 -> #DIV/0! | H53: Tercapai
C54: Stearin | D54: % | E54: 25 | F54: =(F36/F34)*100 -> #DIV/0! | G54: =(F54/E54)*100 -> #DIV/0! | H54: Tercapai
C55: Olein IV 58 | D55: % | E55: 70 | F55: =F39/(F39+F40)*100 -> 76.027572 | G55: =(F55/E55)*100 -> 108.61082 | H55: Tercapai
C56: Stearin | D56: % | E56: 30 | F56: =(F40/F38)*100 -> 23.972428 | G56: =(F56/E56)*100 -> 79.908093 | H56: Tercapai
C57: Olein IV 60 | D57: % | E57: 60 | F57: 0 | G57: =(F57/E57)*100 -> 0
C58: Soft Stearin | D58: % | E58: 40 | F58: 0 | G58: =(F58/E58)*100 -> 0
B59: 3. | C59: CHEMICAL CONSUMABLE
C60: Bleaching Earth to Poram Spec | D60: Kg | E60: 530100 | F60: ='Februari 2026 PMG 2'!$AJ$75 -> 321914 | G60: =(F60/E60)*100 -> 60.727033
D61: Kg/MT | E61: ='Februari 2026 PMG 2'!E75 -> 9 | F61: =(F60/F12)*1000 -> 5.3000832 | G61: =(F61/E61)*100 -> 58.889813 | H61: Tercapai
C62: Bleaching Earth to Branded Spec | D62: Kg | E62: 106326 | F62: ='Februari 2026 PMG 2'!AJ12 -> 0 | G62: =(F62/E62)*100 -> 0
D63: Kg/MT | E63: 1060 | G63: =(F63/E63)*100 -> 0
C64: Phosporic Acid | D64: Kg | E64: 35340 | F64: ='Februari 2026 PMG 2'!$AJ$86 -> 32351.146 | G64: =(F64/E64)*100 -> 91.542575
D65: Kg/MT | E65: 0.6 | F65: =(F64/F11)*1000 -> 0.53263842 | G65: =(F65/E65)*100 -> 88.773071 | H65: Tercapai
B66: 4. | C66: OIL LOSSES
C67: (Loss)/Gain | D67: % | E67: -0.73 | F67: ='Februari 2026 PMG 2'!$AJ$88 -> -0.16216002 | G67: =(F67/E67)*100 -> 22.213701 | H67: Tidak Tercapai
C68: % Oil Content | D68: % | E68: 22 | F68: ='Februari 2026 PMG 2'!$AJ$90 -> 17.449643 | G68: =(F68/E68)*100 -> 79.316558
C69: Spent Bleaching Earth | D69: Kg | E69: 413199.36 | F69: ='Februari 2026 PMG 2'!$AJ$91 -> 323920.17 | G69: =(F69/E69)*100 -> 78.393193
B70: NB :
B71: - BE Achieve dengan pemakaian consume Bleaching Earth 7,80 Kg/MT
B72: - Untuk hari olah Produksi terpenuhi namun dalam kondisi Slow Flowrate dikarenakan Shortage CPO dan target Shipment yang tercapai hanya Olein IV 56
B74: - Total CPO Proses sebesar : 24.046 Mt dengan total CPO Incoming ke INL sebanyak : 24.987 MT
B75: - Rata rata incoming CPO perhari 832 MT
A77: Prepared by, | D77: Checked by, | H77: Approved by,
A81: Syaiful Sembiring | D81: Reza P. Panjaitan | F81: Sudarianto | H81: Eben Jaya Ginting
A82: Admin. Process | D82: Supervisor Produksi | F82: Jr. Manager Produksi | H82: Manager Plant

Sheet Utility
D2: UTILITY (GAS, STEAM, WATER & POWER) REPORT
D3: PT. INDUSTRI NABATI LESTARI
D5: Periode 01 s/d 31 maret 2025
D6: No | E6: Item | F6: Norma | G6: UoM | H6: September | K6: Consume CPO ( MT ) | L6: Remaks
H7: Budget | I7: Actual | J7: Percentage Act.
E9: Total Feed Raw Material CPO | K9: 24046
D10: 1. | E10: GAS CONSUMPTION
E11: Incoming *base on INL | G11: mmbtu | I11: ='Februari 2026 PMG 2'!$AJ$244 -> 31123.868
E12: Incoming *base on Pertagas | F12: 1460.001 | G12: mmbtu | H12: 26051.47 | I12: ='Februari 2026 PMG 2'!$AJ$242 -> 26890.592 | J12: =I12/H12 -> 1.0322102 | K12: =I12/K9 -> 1.1182979
E13: Distribution to
E14: HP Boiler Refinery | G14: mmbtu | H14: 3907.73 | I14: ='Februari 2026 PMG 2'!$AJ$246 -> 164827 | J14: =I14/H14 -> 42.179731 | K14: =I14/K9 -> 6.8546536
E15: MP Boiler | G15: mmbtu | H15: 22143.74 | I15: =I12-$I$14 -> -137936.41 | J15: =I15/H15 -> -6.2291378 | K15: =I15/K9 -> -5.7363557
E16: Total | G16: mmbtu | H16: 26051.47 | I16: =$I$12 -> 26890.592 | J16: =I16/H16 -> 1.0322102 | K16: =SUM(K14+K15) -> 1.1182979
D17: 2. | E17: STEAM CONSUMPTION
E18: Incoming | G18: Kg | H18: 11424000 | I18: ='Februari 2026 PMG 2'!$AJ$253 -> 966406.69 | J18: =I18/H18 -> 0.084594423 | K18: =I18/$K$9 -> 40.189915
E19: Distribution to | K19: =I19/$K$9 -> 0
E20: Refinery | F20: < 90 | G20: Kg | H20: 3420000 | I20: ='Februari 2026 PMG 2'!$AJ$255 -> 266188.8 | J20: =I20/H20 -> 0.077832982 | K20: =I20/$K$9 -> 11.069983
E21: Fractionation | F21: < 61 | G21: Kg | H21: 2318000 | I21: ='Februari 2026 PMG 2'!$AJ$257 -> 115661.37 | J21: =I21/H21 -> 0.049897053 | K21: =I21/$K$9 -> 4.8100046
E22: Others | F22: 106000 | G22: Kg | H22: 5686000 | I22: ='Februari 2026 PMG 2'!$AJ$259 -> 584556.52 | J22: =I22/H22 -> 0.10280628 | K22: =I22/$K$9 -> 24.309928
E23: Total | G23: Kg | H23: 11424000 | I23: =SUM(I20:I22) -> 966406.69 | J23: =I23/H23 -> 0.084594423 | K23: =I23/$K$9 -> 40.189915
D24: 3. | E24: WATER CONSUMPTION
E25: Incoming Raw Water | G25: m3 | H25: 19123.69 | I25: =SUM(I26:$I$27) -> 26117 | J25: =I25/H25 -> 1.3656883 | K25: =I25/$K$9 -> 1.0861266
E26: - Suplay To RO Product | I26: ='Februari 2026 PMG 2'!$AJ$277 -> 6549 | K26: =I26/$K$9 -> 0.27235299
E27: - Suplay To Proses dan Sanitary | I27: =SUM(I29:$I$31) -> 19568 | K27: =I27/$K$9 -> 0.8137736
E28: Rincian Outgoing Proses | K28: =I28/$K$9 -> 0
E29: Softener Product (to Refinery) | F29: < 0,5 | G29: m3 | H29: 1521.33 | I29: ='Februari 2026 PMG 2'!$AJ$273 -> 6836 | J29: =I29/H29 -> 4.4934367 | K29: =I29/$K$9 -> 0.28428845
E30: Softener Product (to Fractionation) | F30: < 0,4 | G30: m3 | H30: 2622 | I30: ='Februari 2026 PMG 2'!$AJ$275 -> 2244 | J30: =I30/H30 -> 0.85583524 | K30: =I30/$K$9 -> 0.093321134
E31: Others | G31: m3 | H31: 2730.3 | I31: ='Februari 2026 PMG 2'!$AJ$278 -> 10488 | J31: =I31/H31 -> 3.8413361 | K31: =I31/$K$9 -> 0.43616402
E32: Total | G32: m3 | H32: 6873.63 | I32: =SUM(I26:I27) -> 26117 | J32: =I32/H32 -> 3.7995935 | K32: =I32/$K$9 -> 1.0861266
D33: 4 | E33: POWER CONSUMPTION
E34: Incoming
E35: PLN *base on BA Kinra | G35: Kwh | H35: 568099 | I35: ='Februari 2026 PMG 2'!$AJ$292 -> 43.821429 | J35: =I35/H35 -> 7.7136958e-05 | K35: =I35/$K$9 -> 0.0018223999
E36: Outgoing | K36: =I36/$K$9 -> 0
E37: - Physical Refinery Plant | F37: 5404.17 | G37: Kwh | H37: 102679 | I37: ='Februari 2026 PMG 2'!$AJ$298 -> 299431 | J37: =I37/H37 -> 2.9161854 | K37: =I37/$K$9*1000 -> 12452.425
E38: - Refinery - Cooling Water System | F38: 3850.42 | G38: Kwh | H38: 73158 | I38: ='Februari 2026 PMG 2'!$AJ$296 -> 386255 | J38: =I38/H38 -> 5.279737 | K38: =I38/$K$9*1000 -> 16063.171
E39: - Refinery - Utilities | F39: 11.81 | G39: Kwh | H39: 212 | I39: ='Februari 2026 PMG 2'!$AJ$321 -> 0 | J39: =I39/H39 -> 0 | K39: =I39/$K$9*1000 -> 0
E40: - Dry Fractionation Plant | F40: 5759.67 | G40: Kwh | H40: 109440 | I40: ='Februari 2026 PMG 2'!$AJ$303 -> 177639 | J40: =I40/H40 -> 1.6231634 | K40: =I40/$K$9*1000 -> 7387.4657
E41: - Dry Fractionation CW System | F41: 1308.96 | G41: Kwh | H41: 28747 | I41: ='Februari 2026 PMG 2'!$AJ$301 -> 210336 | J41: =I41/H41 -> 7.3167983 | K41: =I41/$K$9*1000 -> 8747.2345
E42: - Lighting - Refinery & Dry Fractionation | F42: 241.12 | G42: Kwh | H42: 4581 | I42: ='Februari 2026 PMG 2'!$AJ$322 -> 0 | J42: =I42/H42 -> 0 | K42: =I42/$K$9*1000 -> 0
D44: Note untuk Power Consumption
D45: Selisih antara incoming dan outgoing dikarenakan hal berikut :
D47: - Over pemakaian Gas dikarenakan running sesuai RKAP 19 hari namun plant running 27 hari
E50: Prepared by, | F50: Checked by, | K50: Approved by,
E54: Syaiful Sembiring | F54: Reza P. Panjaitan | I54: Sudarianto | K54: Eben Jaya Ginting
E55: Admin. Process | F55: Supervisor Produksi | I55: Jr. Manager Produksi | K55: Manager Plant

Sheet Qty cons analysis
D2: Quantity Utility Consumption Analysis (based on Guarantee Utility Consumption)
D3: Refinery & Fractionation Plant
D4: Periode 01 s/d 31 maret 2025
D5: Consumption | E5: UoM | F5: Budget | G5: Actual | H5: Under (Over) Budget | I5: Explanation Under / Over budget
D6: CPO Consume | E6: Kg | F6: ='Februari 2026 PMG 2'!E9 -> 48093.551 | G6: ='Februari 2026 PMG 2'!$AJ$9 -> 60737537 | H6: =G6/F6 -> 1262.904
D7: RbdPO Consume | E7: Kg | F7: ='Februari 2026 PMG 2'!E20 -> 45448.405 | G7: ='Februari 2026 PMG 2'!$AJ$25 -> 0 | H7: =G7/F7 -> 0
D8: TOTAL ACTUAL CONSUMPTION
D9: Refinery
D10: Bleaching Earth to Poram Spec | E10: Kg | F10: 232362 | G10: ='Februari 2026 PMG 2'!$AJ$75 -> 321914 | H10: =F10-G10 -> -89552
D11: Bleaching Earth to Branded Spec | E11: Kg | F11: 106326 | G11: ='Februari 2026 PMG 2'!$AJ$81 -> 0 | H11: =F11-G11 -> 106326
D12: Phosporic Acid | E12: Kg | F12: 20971 | G12: ='Februari 2026 PMG 2'!$AJ$86 -> 32351.146 | H12: =F12-G12 -> -11380.146
D13: Gas Consumption (MP Boiler) | E13: mmbtu | F13: 22143.74 | G13: ='Februari 2026 PMG 2'!$AJ$250+'Februari 2026 PMG 2'!$AJ$249 -> 24132.258 | H13: =F13-G13 -> -1988.5177
D14: Gas Consumption (HP Boiler) | E14: mmbtu | F14: 3907.73 | G14: ='Februari 2026 PMG 2'!$AJ$246 -> 164827 | H14: =F14-G14 -> -160919.27
D15: Cooling Water top up to Cooling Tower | E15: m3 | F15: 1521.33 | G15: ='Februari 2026 PMG 2'!$AJ$273 -> 6836 | H15: =F15-G15 -> -5314.67
D16: Steam | E16: Kg | F16: 11424000 | G16: ='Februari 2026 PMG 2'!$AJ$255 -> 266188.8 | H16: =F16-G16 -> 11157811
D17: Power (Process Plant) | E17: Kwh | F17: 102679 | G17: ='Februari 2026 PMG 2'!$AJ$298 -> 299431 | H17: =F17-G17 -> -196752
D18: Power (Cooling Tower) | E18: Kwh | F18: 73158 | G18: ='Februari 2026 PMG 2'!$AJ$296 -> 386255 | H18: =F18-G18 -> -313097
D19: Fractionation
D20: Cooling Water top up to Cooling Tower | E20: m3 | F20: 2622 | G20: ='Februari 2026 PMG 2'!$AJ$275 -> 2244 | H20: =F20-G20 -> 378
D21: Steam | E21: Kg | F21: 2318000 | G21: ='Februari 2026 PMG 2'!$AJ$257 -> 115661.37 | H21: =F21-G21 -> 2202338.6
D22: Power (Process Plant) | E22: Kwh | F22: 109440 | G22: ='Februari 2026 PMG 2'!$AJ$303 -> 177639 | H22: =F22-G22 -> -68199
D23: Power (Cooling Tower) | E23: Kwh | F23: 28747 | G23: ='Februari 2026 PMG 2'!$AJ$301 -> 210336 | H23: =F23-G23 -> -181589
D24: ACTUAL CONSUMPTION PER MT RAW MATERIAL
D25: Refinery
D26: Bleaching Earth to Poram Spec | E26: Kg/MT | F26: 9 | G26: =(G10/$G$6)*1000 -> 5.3000832 | H26: =F26-G26 -> 3.6999168
D27: Bleaching Earth to Branded Spec | E27: Kg/MT | F27: 18 | G27: =(G11/$G$6)*1000 -> 0 | H27: =F27-G27 -> 18
D28: Phosporic Acid | E28: Kg/MT | F28: 0.6 | G28: =(G12/$G$6)*1000 -> 0.53263842 | H28: =F28-G28 -> 0.067361576
D29: Gas Consumption (HP Boiler) | E29: Nm3/MT | F29: 4.2 | G29: =(G13/$G$6)*1000 -> 0.39732032 | H29: =F29-G29 -> 3.8026797 | I29: Gas Over dikarenakan kapasitas tidak tercapai
D30: Gas Consumption (HP Boiler) **) | E30: mmbtu/MT | F30: 0.2 | G30: =(G14/$G$6)*1000 -> 2.7137584 | H30: =F30-G30 -> -2.5137584
D31: Cooling Water top up to Cooling Tower | E31: m3/MT | F31: 0.04 | G31: =(G15/$G$6)*1000 -> 0.11254984 | H31: =F31-G31 -> -0.072549839
D32: Steam | E32: Kg/MT | F32: 28 | G32: =(G16/$G$6)*1000 -> 4.3826077 | H32: =F32-G32 -> 23.617392 | I32: Steam Refinery Over dikarenakan kapasitas tidak tercapai
D33: Power (Process Plant) | E33: Kwh/MT | F33: 4.4 | G33: =(G17/$G$6)*1000 -> 4.9299167 | H33: =F33-G33 -> -0.52991673 | I33: Power Over dikarenakan kapasitas tidak tercapai
D34: utility section ( chiller ) | E34: Kwh/MT | F34: 7.3 | G34: =(G18/$G$6)*1000 -> 6.3594116 | H34: =F34-G34 -> 0.94058836
D35: Fractionation
D36: Cooling Water top up to Cooling Tower | E36: m3/MT | F36: 0.13 | G36: =(G20/$G$6)*1000 -> 0.036945851 | H36: =F36-G36 -> 0.093054149
D37: Steam | E37: Kg/MT | F37: 45 | G37: =(G21/$G$6)*1000 -> 1.9042815 | H37: =F37-G37 -> 43.095718 | I37: Steam Over dikarenakan menggunakan 2 unit chiller
D38: Power (Process Plant) | E38: Kwh/MT | F38: 4.1 | G38: =(G22/$G$6)*1000 -> 2.9246988 | H38: =F38-G38 -> 1.1753012 | I38: Power Over dikarenakan kapasitas tidak tercapai
D39: utility section ( chiller ) | E39: Kwh/MT | F39: 4.5 | G39: =(G23/$G$6)*1000 -> 3.4630314 | H39: =F39-G39 -> 1.0369686
D42: - BE Achieve dengan pemakaian consume Bleaching Earth 7,80 Kg/MT
D43: * Steam Refinery Over dikarenakan kapasitas tidak tercapai
D44: * Gas Refinery Over dikarenakan kapasitas tidak tercapai
D45: * Power Fractionation Over dikarenakan kapasitas tidak tercapai
D47: Prepared by, | G47: Checked by, | I47: Approved by,
D51: Syaiful Sembiring | F51: Reza P. Panjaitan | H51: Sudarianto | I51: Eben Jaya Ginting
D52: Admin. Process | F52: Supervisor Produksi | H52: Jr. Manager Produksi | I52: Manager Plant

Sheet Steam
B2: Steam Price Package Boiler | G2: Kurs | H2: 16000
B3: Consumable Item | C3: Norma | E3: Consumption, Ton/day | F3: Unit Price | H3: Total Cost
B4: Steam Production (Including Dearator) | C4: =408/24 -> 17 | D4: Ton/jam | E4: ='Februari 2026 PMG 2'!AJ253 -> 966406.69 | H4: Rp/day
B5: Gas | C5: 1000 | D5: MMBTU/day | E5: ='Februari 2026 PMG 2'!$AJ$243 -> 960.37828 | F5: 11.5 | G5: USD/MMBTU | H5: =E5*H2*F5 -> 1.767096e+08 | I5: Harga steam tinggi dikarenakan oleh unit price gas yang tinggi, ideal (9.6)
B6: Chemical Treatment
B7: EONALKALOX B1414 | C7: 7.3 | D7: l/day | E7: =C7 -> 7.3 | F7: 25340 | G7: Rp/l | H7: =E7*F7 -> 184982
B8: EONCONDENS B1720 | C8: 2.4 | D8: l/day | E8: =C8 -> 2.4 | F8: 110000 | G8: Rp/l | H8: =E8*F8 -> 264000
B9: EONOXY B8100 | C9: 2.4 | D9: l/day | E9: =C9 -> 2.4 | F9: 20160 | G9: Rp/l | H9: =E9*F9 -> 48384
B10: EONSCALE B5100 | C10: 5.8 | D10: l/day | E10: =C10 -> 5.8 | F10: 31800 | G10: Rp/l | H10: =E10*F10 -> 184440
B11: EONDESCALER B2550 | C11: 1.4 | D11: l/day | E11: =C11 -> 1.4 | F11: 39320 | G11: Rp/l | H11: =E11*F11 -> 55048
B12: Water Demin | C12: =[3]L.Water!C12*83% -> 408.0197 | D12: M3/day | E12: =C12 -> 408.0197 | F12: =[3]L.Water!F12 -> 10162 | G12: Rp/m3 | H12: =E12*F12 -> 4146296.2
B13: Preventive Maintenance | D13: Rp/day | H13: =C13 -> 0
B14: Total Pakage Boiler | H14: =SUM(H5:H13) -> 1.8159275e+08
F15: Unit Price, Rp/Ton | H15: =H14/E4 -> 187.90511
B17: Note :
B18: 1. Harga gas, secara general untuk industri adalah 9,21-9,6 usd/mmBtu
C26: Kurita H-504 18:25

Sheet WWTP
B2: Water Waste Treatment Plant | G2: Kurs | H2: ='SUMMARY HPP '!I9 -> 16000
B3: Consumable Item | C3: Norma | E3: Consumption, M3/day | F3: Unit Price | H3: Total Cost
B4: Waste Water Feed | C4: =200/24 -> 8.3333333 | D4: M3/jam | E4: ='Februari 2026 PMG 2'!AJ279 -> 8912 | H4: Rp/day
B5: biaya transfer ke kawasan | F5: 0 | G5: Rp/m3 | H5: 8700
B6: Chemical Treatment
B7: Sugar | C7: 0 | D7: kg/day | E7: =C7 -> 0 | F7: 24890 | G7: Rp/kg | H7: =E7*F7 -> 0
B8: PE | C8: =E8*C4 -> 0.62305296 | D8: kg/day | E8: 0.074766355 | F8: 65340 | G8: Rp/kg | H8: =E8*F8 -> 4885.2336
B9: PAC | C9: =E9*C4 -> 46.728972 | D9: kg/day | E9: 5.6074766 | F9: 7702 | G9: Rp/kg | H9: =E9*F9 -> 43188.785
B10: Urea | C10: =E10*C4 -> 6.2305296 | D10: kg/day | E10: 0.74766355 | F10: 18634 | G10: Rp/kg | H10: =E10*F10 -> 13931.963
B11: TSP | C11: =E11*C4 -> 1.2461059 | D11: kg/day | E11: 0.14953271 | F11: 44722 | G11: Rp/kg | H11: =E11*F11 -> 6687.4019
B12: HCL | C12: 0 | D12: kg/day | E12: =C12 -> 0 | F12: 5700 | G12: Rp/kg | H12: =E12*F12 -> 0
B13: NaOH | C13: 0 | D13: kg/day | E13: =C13 -> 0 | F13: 15700 | G13: Rp/kg | H13: =E13*F13 -> 0
B14: Power | C14: 2675 | D14: kW/day | E14: =C14 -> 2675 | F14: =[4]UP.E!C28 -> 1550 | G14: Rp/kW | H14: =E14*F14 -> 4146250
B15: Preventive Maintenance | D15: Rp/day | H15: =E15*F15 -> 0
H16: =IFERROR(SUM(H5:H15),"") -> 4223643.4
F17: Unit Price, Rp/M3 | H17: =H16/E4 -> 473.92767
C29: Kurita H-504 18:25

Sheet WTP
B2: Water Treatment Plant | G2: Kurs | H2: 16000
B3: Consumable Item | C3: Norma | E3: Consumption, M3/day | F3: Unit Price | H3: Total Cost
B4: Water Treatment Plant | C4: =1000/24 -> 41.666667 | D4: M3/jam | E4: ='Februari 2026 PMG 2'!AJ271 -> 932.75 | H4: Rp/day
B5: Chemical | F5: 8700 | G5: Rp/m3 | H5: =F5*E4 -> 8114925
B6: anti scalant | C6: 0.1 | D6: kg/day | E6: =C6 -> 0.1 | F6: 44500 | G6: Rp/kg | H6: =E6*F6 -> 4450
B7: caustic soda | C7: 0.1 | D7: kg/day | E7: =C7 -> 0.1 | F7: 65340 | G7: Rp/kg | H7: =E7*F7 -> 6534
B8: citrid acid | C8: 0.1 | D8: kg/day | E8: =C8 -> 0.1 | F8: 33275 | G8: Rp/kg | H8: =E8*F8 -> 3327.5
B9: bioside | C9: 0.1 | D9: kg/day | E9: =C9 -> 0.1 | F9: 47450 | G9: Rp/kg | H9: =E9*F9 -> 4745
B10: Power | C10: 8896 | D10: kW/day | E10: =C10 -> 8896 | F10: =[4]UP.E!C28 -> 1550 | G10: Rp/kW | H10: =E10*F10 -> 13788800
B11: Preventive Maintenance | D11: Rp/day | H11: =E11*F11 -> 0
H12: =IFERROR(SUM(H5:H11),"") -> 21922782
F13: Unit Price, Rp/M3 | H13: =H12/E4 -> 23503.384
C25: Kurita H-504 18:25

Sheet lab
B2: Laboratorium Chemical Cost
B3: Consumable Item | C3: Norma | E3: Consumption/ Hari | F3: Unit Price | H3: Total Biaya
H4: Per Hari
B5: Refinery, Fraksinasi, Packaging & Sotrage tank
B6: Acetic Acid Glacial | C6: 50 | D6: ml | E6: =C6 -> 50 | F6: 374 | G6: ml | H6: =E6*F6 -> 18700
B7: Aquadest | C7: 2 | D7: liter | E7: =C7 -> 2 | F7: 7250 | G7: liter | H7: =E7*F7 -> 14500
B8: BF3-methanol solution, Reagen Grade | C8: 0.5 | D8: ml | E8: =C8 -> 0.5 | F8: 500 | G8: ml | H8: =E8*F8 -> 250
B9: Chloroform | C9: 70 | D9: ml | E9: =C9 -> 70 | F9: 388 | G9: ml | H9: =E9*F9 -> 27160
B10: Cyclohexane | C10: 70 | D10: ml | E10: =C10 -> 70 | F10: 612 | G10: ml | H10: =E10*F10 -> 42840
B11: Hydrazine Sulphate | C11: 0.05 | D11: gr | E11: =C11 -> 0.05 | F11: 21000 | G11: gr | H11: =E11*F11 -> 1050
B12: Hydrochloric Acid 37% | C12: 2.6 | D12: ml | E12: =C12 -> 2.6 | F12: 236 | G12: ml | H12: =E12*F12 -> 613.6
B13: Iso Propanol Alcohol TG | C13: 5.5 | D13: liter | E13: =C13 -> 5.5 | F13: 35000 | G13: liter | H13: =E13*F13 -> 192500
B14: Isooctane | C14: 150 | D14: ml | E14: =C14 -> 150 | F14: 480 | G14: ml | H14: =E14*F14 -> 72000
B15: Indikator Phenolpthalaein 1 % | C15: 0.3 | D15: gr | E15: =C15 -> 0.3 | F15: 6750 | G15: gr | H15: =E15*F15 -> 2025
B16: Indikator Thymolpthalaein | C16: =36/357 -> 0.10084034 | D16: gr | E16: =C16 -> 0.10084034 | F16: 90000 | G16: gr | H16: =E16*F16 -> 9075.6303
B17: Starch | C17: =107/357 -> 0.29971989 | D17: gr | E17: =C17 -> 0.29971989 | F17: 3000 | G17: gr | H17: =E17*F17 -> 899.15966
B18: Liquid standard Lovibond 3,4R 30,0 Y 0,9N | C18: 0.1 | D18: ml | E18: =C18 -> 0.1 | F18: 70000 | G18: ml | H18: =E18*F18 -> 7000
B19: Liquid standard Lovibond 3,0R 28,0Y | C19: 0.1 | D19: ml | E19: =C19 -> 0.1 | F19: 70000 | G19: ml | H19: =E19*F19 -> 7000
B20: n-HexaneTehcnis | C20: 0.5 | D20: liter | E20: =C20 -> 0.5 | F20: 19300 | G20: liter | H20: =E20*F20 -> 9650
B21: p-Anisidine | C21: =48/357 -> 0.13445378 | D21: gr | E21: =C21 -> 0.13445378 | F21: 7600 | G21: gr | H21: =E21*F21 -> 1021.8487
B22: Wijs Solution | C22: 120 | D22: ml | E22: =C22 -> 120 | F22: 502 | G22: ml | H22: =E22*F22 -> 60240
B23: N2 (UHP) gas refill for GC & Foam test | C23: 0.02 | D23: Liter | E23: =C23 -> 0.02 | F23: 5000000 | G23: Liter | H23: =E23*F23 -> 100000
B24: H2 (UHP) gas refill for GC | C24: 0.03 | D24: Liter | E24: =C24 -> 0.03 | F24: 2500000 | G24: Liter | H24: =E24*F24 -> 75000
B25: UT (UHP) gas refill for GC | C25: 0.03 | D25: Liter | E25: =C25 -> 0.03 | F25: 1250000 | G25: Liter | H25: =E25*F25 -> 37500
B26: Zinc Oksida GR | C26: =179/357 -> 0.50140056 | D26: gr | E26: =C26 -> 0.50140056 | F26: 2000 | G26: gr | H26: =E26*F26 -> 1002.8011
B27: Potassium Dihydrogen Phosphate | C27: =250/357 -> 0.70028011 | D27: gr | E27: =C27 -> 0.70028011 | F27: 765 | G27: gr | H27: =E27*F27 -> 535.71429
B28: Pottasium Hydrogen Phtalate | C28: =250/357 -> 0.70028011 | D28: gr | E28: =C28 -> 0.70028011 | F28: 5200 | G28: gr | H28: =E28*F28 -> 3641.4566
B29: Sodium Thiosulphate | C29: =6069/357 -> 17 | D29: gr | E29: =C29 -> 17 | F29: 950 | G29: gr | H29: =E29*F29 -> 16150
B30: Potassium Iodide | C30: 12 | D30: gr | E30: =C30 -> 12 | F30: 2400 | G30: gr | H30: =E30*F30 -> 28800
B31: Pottasium Dichromate | C31: =357/357 -> 1 | D31: gr | E31: =C31 -> 1 | F31: 4200 | G31: gr | H31: =E31*F31 -> 4200
B32: Sodium Hydroxide | C32: =6069/357 -> 17 | D32: gr | E32: =C32 -> 17 | F32: 700 | G32: gr | H32: =E32*F32 -> 11900
B33: Sub Total | H33: =SUM(H6:H32) -> 745255.21
B35: Consumable Item | C35: Norma | E35: Consumption/day | F35: Unit Price | H35: Total Price
H36: Per Day
B37: Chemical Boiler & WTP
B38: Sodium Molybdate | C38: =286/357 -> 0.80112045 | D38: gr | E38: =C38 -> 0.80112045 | F38: 4000 | G38: gr | H38: =E38*F38 -> 3204.4818
B39: Iron test 0.0025 - 5.00 mg/l | C39: =1785/357 -> 5 | D39: Test | E39: =C39 -> 5 | F39: 10100 | G39: Test | H39: =E39*F39 -> 50500
B40: Phosphate Test 0.5 - 30 mg/l PO4-P | C40: =714/357 -> 2 | D40: pcs | E40: =C40 -> 2 | F40: 8160 | G40: pcs | H40: =E40*F40 -> 16320
B41: Sulfite Test 1,0-60,0 mg/l SO3 | C41: =360/357 -> 1.0084034 | D41: Pcs | E41: =C41 -> 1.0084034 | F41: 26550 | G41: Pcs | H41: =E41*F41 -> 26773.109
B42: Silica Test 0-800 mg/L | C42: =714/357 -> 2 | D42: pcs | E42: =C42 -> 2 | F42: 31700 | G42: pcs | H42: =E42*F42 -> 63400
B43: Silicate (Silicic Acid) 0,3-10 mg/L | C43: 2.5 | D43: pcs | E43: =C43 -> 2.5 | F43: 31006 | G43: pcs | H43: =E43*F43 -> 77515
B44: Ammonium Vanadate | C44: =179/357 -> 0.50140056 | D44: gr | E44: =C44 -> 0.50140056 | F44: 11950 | G44: gr | H44: =E44*F44 -> 5991.7367
B45: Ammonium Chloride | C45: =214/357 -> 0.59943978 | D45: gr | E45: =C45 -> 0.59943978 | F45: 2545 | G45: gr | H45: =E45*F45 -> 1525.5742
B46: Ammonium Hidroksida | C46: =1714/357 -> 4.8011204 | D46: mL | E46: =C46 -> 4.8011204 | F46: 930 | G46: mL | H46: =E46*F46 -> 4465.042
B47: Mg EDTA | C47: =71/357 -> 0.19887955 | D47: gr | E47: =C47 -> 0.19887955 | F47: 21050 | G47: gr | H47: =E47*F47 -> 4186.4146
B48: Pottasium Carbonat | C48: =12/357 -> 0.033613445 | D48: gr | E48: =C48 -> 0.033613445 | F48: 12500 | G48: gr | H48: =E48*F48 -> 420.16807
B49: Trietanolamin | C49: 0.08 | D49: mL | E49: =C49 -> 0.08 | F49: 8160 | G49: mL | H49: =E49*F49 -> 652.8
B50: Indikator EBT | C50: =12/357 -> 0.033613445 | D50: gr | E50: =C50 -> 0.033613445 | F50: 23400 | G50: gr | H50: =E50*F50 -> 786.55462
B51: Indikator Calcon | C51: =12/357 -> 0.033613445 | D51: gr | E51: =C51 -> 0.033613445 | F51: 50800 | G51: gr | H51: =E51*F51 -> 1707.563
B52: Hydroxylammonium Chloride GR | C52: 0.08 | D52: gr | E52: =C52 -> 0.08 | F52: 6250 | G52: gr | H52: =E52*F52 -> 500
B53: Eriocrom Black T-Metal | C53: 0.05 | D53: gr | E53: =C53 -> 0.05 | F53: 24260 | G53: gr | H53: =E53*F53 -> 1213
B54: Sub Total | H54: =SUM(H38:H53) -> 259161.44
B56: Consumable Item | C56: Norma | E56: Consumption/day | F56: Unit Price | H56: Total Price
H57: Per Day
B58: Chemical WWTP
B59: COD cell test 50 - 500 mg/l | C59: =59/357 -> 0.16526611 | D59: pcs | E59: =C59 -> 0.16526611 | F59: 82000 | G59: pcs | H59: =E59*F59 -> 13551.821
B60: COD cell test 500 - 10000 mg/l | C60: =59/357 -> 0.16526611 | D60: pcs | E60: =C60 -> 0.16526611 | F60: 82000 | G60: pcs | H60: =E60*F60 -> 13551.821
B61: Sub Total | H61: =SUM(H59:H60) -> 27103.641
B63: Total keseluruhan | H63: =H61+H54+H33 -> 1031520.3
C67: Spere Part Laboratorium
B68: No | C68: Consumable Item | D68: Norma | F68: Consumption/day | G68: Unit Price | I68: Total Price
I69: Per Day
B70: 1 | C70: Batang pengaduk | D70: 12 | E70: Pcs/Tahun | F70: =D70/357 -> 0.033613445 | G70: 35000 | H70: Rp/Pcs | I70: =F70*G70 -> 1176.4706
B71: =B70+1 -> 2 | C71: Beaker glass 100 mL | D71: 72 | E71: Pcs/Tahun | F71: =D71/357 -> 0.20168067 | G71: 48000 | H71: Rp/Pcs | I71: =F71*G71 -> 9680.6723
B72: =B71+1 -> 3 | C72: Beaker glass 500 mL | D72: 12 | E72: Pcs/Tahun | F72: =D72/357 -> 0.033613445 | G72: 100000 | H72: Rp/Pcs | I72: =F72*G72 -> 3361.3445
B73: =B72+1 -> 4 | C73: Beaker glass 1000 mL | D73: 6 | E73: Pcs/Tahun | F73: =D73/357 -> 0.016806723 | G73: 120000 | H73: Rp/Pcs | I73: =F73*G73 -> 2016.8067
B74: =B73+1 -> 5 | C74: Beaker glass 2000 mL | D74: 6 | E74: Pcs/Tahun | F74: =D74/357 -> 0.016806723 | G74: 142000 | H74: Rp/Pcs | I74: =F74*G74 -> 2386.5546
B75: =B74+1 -> 6 | C75: Beaker Plastik with handle 1000 mL | D75: 6 | E75: Pcs/Tahun | F75: =D75/357 -> 0.016806723 | G75: 70000 | H75: Rp/Pcs | I75: =F75*G75 -> 1176.4706
B76: =B75+1 -> 7 | C76: Boiling Round Bottom Flask 250 mL | D76: 6 | E76: Pcs/Tahun | F76: =D76/357 -> 0.016806723 | G76: 180000 | H76: Rp/Pcs | I76: =F76*G76 -> 3025.2101
B77: =B76+1 -> 8 | C77: Boiling Round Bottom Flask 1000 mL IKA | D77: 2 | E77: Pcs/Tahun | F77: =D77/357 -> 0.0056022409 | G77: 350000 | H77: Rp/Pcs | I77: =F77*G77 -> 1960.7843
B78: =B77+1 -> 9 | C78: Rotary flask 1000 mL IKA | D78: 2 | E78: Pcs/Tahun | F78: =D78/357 -> 0.0056022409 | G78: 350000 | H78: Rp/Pcs | I78: =F78*G78 -> 1960.7843
B79: =B78+1 -> 10 | C79: Corong 75 mm | D79: 6 | E79: Pcs/Tahun | F79: =D79/357 -> 0.016806723 | G79: 75000 | H79: Rp/Pcs | I79: =F79*G79 -> 1260.5042
B80: =B79+1 -> 11 | C80: Erlenmeyer 250 mL | D80: 72 | E80: Pcs/Tahun | F80: =D80/357 -> 0.20168067 | G80: 90000 | H80: Rp/Pcs | I80: =F80*G80 -> 18151.261
B81: =B80+1 -> 12 | C81: Filtering Flask 500 mL | D81: 2 | E81: Pcs/Tahun | F81: =D81/357 -> 0.0056022409 | G81: 400000 | H81: Rp/Pcs | I81: =F81*G81 -> 2240.8964
B82: =B81+1 -> 13 | C82: Gelas ukur 100 mL | D82: 2 | E82: Pcs/Tahun | F82: =D82/357 -> 0.0056022409 | G82: 85000 | H82: Rp/Pcs | I82: =F82*G82 -> 476.19048
... B110: =B109+1 -> 41 | C110: Magnetic Stirer 8 cm | D110: 12 | E110: Pcs/Tahun | F110: =D110/357 -> 0.033613445 | G110: 85000 | H110: Rp/Pcs | I110: =F110*G110 -> 2857.1429
G111: Total Cost/Days | I111: =SUM(I70:I110) -> 135770.31

Sheet genset
B2: Warming Up Genset
B3: Consumable Item | C3: Norma | E3: Consumption/day | F3: Unit Price | H3: Total Cost | K3: PLN - Power Unit Price
B4: Genset Warming Up | D4: kW/Jam | E4: 0 | H4: Rp/day | K4: Consumable Item | L4: Unit Price
B5: Solar | H5: 0 | K5: PLN Fee | L5: 1550 | M5: Rp/kWh
B6: Genset - 1 (1044 kW) | C6: 100 | D6: Ltr/Jam | E6: =(C6*25%*4)/30 -> 3.3333333 | F6: 14500 | G6: Rp/ltr | H6: =F6*E6 -> 48333.333
B7: Genset - 2 (1044 kW) | C7: 100 | D7: Ltr/Jam | E7: =(C7*25%*4)/30 -> 3.3333333 | F7: 14500 | G7: Rp/ltr | H7: =F7*E7 -> 48333.333
B8: Genset - 3 (1044 kW) | C8: 100 | D8: Ltr/Jam | E8: =(C8*25%*4)/30 -> 3.3333333 | F8: 14500 | G8: Rp/ltr | H8: =F8*E8 -> 48333.333
B9: Preventive Maintenance | D9: Rp/day | H9: 0
B10: Cost Power by Genset | H10: =SUM(H5:H9) -> 145000
B12: Genset - Power Unit Price
B13: Consumable Item | C13: Norma | E13: Power, kW/day | F13: Unit Price | H13: Total Cost
B14: Power Production by Genset | C14: 2088 | D14: kW/Jam | E14: =C14*24 -> 50112 | H14: Rp/day
B15: Solar | H15: 0
B16: Genset - 1 (1044 kW) | C16: 800 | D16: Ltr/Jam | E16: =C16*24 -> 19200 | F16: 14500 | G16: Rp/ltr | H16: =F16*E16 -> 278400000
B17: Genset - 2 (1044 kW) | C17: 800 | D17: Ltr/Jam | E17: =C17*24 -> 19200 | F17: 14500 | G17: Rp/ltr | H17: =F17*E17 -> 278400000
B18: Genset - 3 (1044 kW) | D18: Ltr/Jam | E18: 0 | F18: 14500 | G18: Rp/ltr | H18: =F18*E18 -> 0
B19: Preventive Maintenance | D19: Rp/day | H19: 0
B20: Cost Power by Genset | H20: =SUM(H15:H19) -> 556800000
F21: Unit Price, Rp/Kw | H21: =H20/E14 -> 11111.111 | I21: Unit price terlalu tinggi
B23: Note :
B24: 1. Cross cek kembali consumption solar genset per unit

Sheet AMOR
B2: Amortization
B3: Through Put CPO Proses | H3: TPD | I3: ='HPP REF '!N3 -> 2169.1977
B4: Working Day | H4: Day | I4: ='HPP REF '!N4 -> 28
B5: Total CPO Refined | H5: TPM | I5: =I4*I3 -> 60737.537
B6: Kurs Rupiah | I6: 16000
B7: No | C7: Description | D7: Actual 2023 | F7: Budget 2024
D8: Years | E8: Month | F8: Years | G8: Month | H8: RP/KG | I8: USD/MT
B9: 1 | C9: Perangkat Lunak/Software | D9: 9.6270931e+08 | E9: =D9/12 -> 80225776 | F9: =G9*12 -> 5.3192735e+08 | G9: 44327279 | H9: =$G$9/($I$5*1000) -> 0.72981687 | I9: =($G$9/$I$6)/$I$5 -> 0.045613554 | J9: =D9/12 -> 80225776
B10: =B9+1 -> 2 | C10: Sertifikat/Surat Izin | D10: 2.6961444e+08 | E10: =D10/12 -> 22467870 | F10: 0 | G10: 0 | H10: =$G$10/($I$5*1000) -> 0 | I10: =($G$10/$I$6)/$I$5 -> 0
B11: =B10+1 -> 3 | C11: Inventaris Kecil (Aset Sewa) | D11: 0 | E11: =D11/12 -> 0 | F11: 0 | G11: 0 | H11: =$G$11/($I$5*1000) -> 0 | I11: =($G$11/$I$6)/$I$5 -> 0
B12: =B11+1 -> 4 | C12: Aset Hak Guna (ROU) - Kendaraan | D12: 0 | E12: =D12/12 -> 0 | F12: 0 | G12: 0 | H12: =$G$12/($I$5*1000) -> 0 | I12: =($G$12/$I$6)/$I$5 -> 0
B13: =B12+1 -> 5 | C13: Aset Hak Guna (ROU) - Tangki Timbun | D13: 0 | E13: =D13/12 -> 0 | F13: 0 | G13: 0 | H13: =$G$13/($I$5*1000) -> 0 | I13: =($G$13/$I$6)/$I$5 -> 0
B14: =B13+1 -> 6 | C14: Aset Atas Biaya Penyambungan | D14: 0 | E14: =D14/12 -> 0 | F14: 0 | G14: 0 | H14: =$G$14/($I$5*1000) -> 0 | I14: =($G$14/$I$6)/$I$5 -> 0
B15: =B14+1 -> 7 | C15: Aset Hak Guna (ROU) - Pemanfaatan Lahan Sei Mangkei + Surabaya | D15: 1.2576903e+10 | E15: =D15/12 -> 1.0480752e+09 | F15: =G15*12 -> 12048990312 | G15: 1004082526 | H15: =$G$15/($I$5*1000) -> 16.531499 | I15: =($G$15/$I$6)/$I$5 -> 1.0332187
B20: Total Cost Depreciation | D20: =SUM(D9:D19) -> 1.3809227e+10 | E20: =SUM(E9:E19) -> 1.1507689e+09 | F20: =SUM(F9:F19) -> 1.2580918e+10 | G20: =SUM(G9:G19) -> 1.0484098e+09 | H20: =SUM(H9:H19) -> 17.261316 | I20: =SUM(I9:I19) -> 1.0788322

Sheet DEP
B2: Depreciation
B3: Through Put CPO Proses | J3: TPD | K3: ='HPP REF '!N3 -> 2169.1977
B4: Working Day | J4: Day | K4: ='HPP REF '!N4 -> 28
B5: Total CPO Refined | J5: TPM | K5: =K4*K3 -> 60737.537
B6: Kurs Rupiah | K6: 16000
B7: No | C7: Description | D7: Actual 2023 (Audited) | G7: Budget 2024
D8: Asset | E8: Years | F8: Month | G8: Asset | H8: Years | I8: Month | J8: RP/KG | K8: USD/MT
B9: Total Cost Depreciation | D9: =SUM(D10:D75) -> 6.7971213e+11 | E9: =SUM(E10:E75) -> 4.1807174e+10 | F9: =SUM(F10:F75) -> 3.4839312e+09 | G9: =SUM(G10:G75) -> 7.7503139e+11 | H9: =SUM(H10:H75) -> 5.0174217e+10 | I9: =SUM(I10:I75) -> 4.1811848e+09 | J9: =SUM(J10:J75) -> 68.84021 | K9: =SUM(K10:K75) -> 4.3025131
B10: 1 | C10: Front Office + Canteen | D10: 3844320790 | E10: 1.9221604e+08 | F10: 16018003 | G10: 3.8443208e+09 | H10: =I10*12 -> 1.9221604e+08 | I10: 16018003 | J10: =$I$10/($K$5*1000) -> 0.26372494 | K10: =($I$10/$K$6)/$K$5 -> 0.016482809
B11: =B10+1 -> 2 | C11: Bea Cukai Building | D11: 247144032 | E11: 12357202 | F11: 1029766.8 | G11: 2.4714403e+08 | H11: =I11*12 -> 12357202 | I11: 1029766.8 | J11: =$I$11/($K$5*1000) -> 0.016954372 | K11: =($I$11/$K$6)/$K$5 -> 0.0010596483
B12: =B11+1 -> 3 | C12: Security Building | D12: 199088248 | E12: 12429395 | F12: 1035782.9 | G12: 3.9708686e+08 | H12: =I12*12 -> 19854343 | I12: 1654528.6 | J12: =$I$12/($K$5*1000) -> 0.027240627 | K12: =($I$12/$K$6)/$K$5 -> 0.0017025392
B13: =B12+1 -> 4 | C13: Bangunan Shelter / Pelataran | D13: 53111657402 | E13: 2.6555829e+09 | F13: 2.2129857e+08 | G13: 5.3111657e+10 | H13: =I13*12 -> 2.6555829e+09 | I13: 2.2129857e+08 | J13: =$I$13/($K$5*1000) -> 3.6435223 | K13: =($I$13/$K$6)/$K$5 -> 0.22772015
B14: =B13+1 -> 5 | C14: Laboratorium Building | D14: 1.3920764e+09 | E14: 70956822 | F14: 5913068.5 | G14: 1.5003164e+09 | H14: =I14*12 -> 75015820 | I14: 6251318.3 | J14: =$I$14/($K$5*1000) -> 0.10292347 | K14: =($I$14/$K$6)/$K$5 -> 0.0064327171
B15: =B14+1 -> 6 | C15: Refinery Room | D15: 22378266872 | E15: 1.1189133e+09 | F15: 93242779 | G15: 2.2378267e+10 | H15: =I15*12 -> 1.1189133e+09 | I15: 93242779 | J15: =$I$15/($K$5*1000) -> 1.5351755 | K15: =($I$15/$K$6)/$K$5 -> 0.095948469
B16: =B15+1 -> 7 | C16: Fractionation Room | D16: 22378266872 | E16: 1.1189133e+09 | F16: 93242779 | G16: 2.2378267e+10 | H16: =I16*12 -> 1.1189133e+09 | I16: 93242779 | J16: =$I$16/($K$5*1000) -> 1.5351755 | K16: =($I$16/$K$6)/$K$5 -> 0.095948469
B17: =B16+1 -> 8 | C17: Utility Building | D17: 22548996820 | E17: 1.1274498e+09 | F17: 93954153 | G17: 2.2548997e+10 | H17: =I17*12 -> 1.1274498e+09 | I17: 93954153 | J17: =$I$17/($K$5*1000) -> 1.5468878 | K17: =($I$17/$K$6)/$K$5 -> 0.096680486
B18: =B17+1 -> 9 | C18: Power House & Electrical Building | D18: 3242778116 | E18: 1.6663346e+08 | F18: 13886122 | G18: 3.6023423e+09 | H18: =I18*12 -> 1.8011712e+08 | I18: 15009760 | J18: =$I$18/($K$5*1000) -> 0.24712493 | K18: =($I$18/$K$6)/$K$5 -> 0.015445308
B19: =B18+1 -> 10 | C19: Weight Bridge Building (Timbangan) | D19: 3.0883582e+09 | E19: 1.6798762e+08 | F19: 13998968 | G19: 4.173935e+09 | H19: =I19*12 -> 2.0869675e+08 | I19: 17391396 | J19: =$I$19/($K$5*1000) -> 0.28633686 | K19: =($I$19/$K$6)/$K$5 -> 0.017896054
B20: =B19+1 -> 11 | C20: Warehouse TPS Spent Earth | D20: 1.3067146e+09 | E20: 65335728 | F20: 5444644 | G20: 1.3067146e+09 | H20: =I20*12 -> 65335728 | I20: 5444644 | J20: =$I$20/($K$5*1000) -> 0.08964216 | K20: =($I$20/$K$6)/$K$5 -> 0.005602635
B21: =B20+1 -> 12 | C21: Bangunan Shelter / Pelataran | D21: 0 | E21: 0 | F21: 0 | G21: 0 | H21: =I21*12 -> 0 | I21: 0 | J21: =$I$21/($K$5*1000) -> 0 | K21: =($I$21/$K$6)/$K$5 -> 0
B22: =B21+1 -> 13 | C22: Packaging Building | D22: 26865966199 | E22: 1.3432983e+09 | F22: 1.1194153e+08 | G22: 2.6865966e+10 | H22: =I22*12 -> 1.895783e+09 | I22: 1.5798192e+08 | J22: =$I$22/($K$5*1000) -> 2.601059 | K22: =($I$22/$K$6)/$K$5 -> 0.16256619
B23: =B22+1 -> 14 | C23: Warehouse TPS Limbah B3 | D23: 808088751 | E23: 52164853 | F23: 4347071.1 | G23: 1.748922e+09 | H23: =I23*12 -> 87446098 | I23: 7287174.8 | J23: =$I$23/($K$5*1000) -> 0.11997811 | K23: =($I$23/$K$6)/$K$5 -> 0.0074986318
B24: =B23+1 -> 15 | C24: Panel Room Loading - Unloading | D24: 669445527 | E24: 33472276 | F24: 2789356.4 | G24: 6.6944553e+08 | H24: =I24*12 -> 33472276 | I24: 2789356.4 | J24: =$I$24/($K$5*1000) -> 0.045924753 | K24: =($I$24/$K$6)/$K$5 -> 0.002870297
B25: =B24+1 -> 16 | C25: Bangunan Shelter / Pelataran | D25: 0 | E25: 0 | F25: 0 | G25: 0 | H25: =I25*12 -> 0 | I25: 0 | J25: =$I$25/($K$5*1000) -> 0 | K25: =($I$25/$K$6)/$K$5 -> 0
B26: =B25+1 -> 17 | C26: Kantor RO Medan | D26: 35739000 | E26: 3573900 | F26: 297825 | G26: 35739000 | H26: =I26*12 -> 3573900 | I26: 297825 | J26: =$I$26/($K$5*1000) -> 0.0049034751 | K26: =($I$26/$K$6)/$K$5 -> 0.00030646719
B27: =B26+1 -> 18 | C27: Gedung Logistic | D27: 537402145 | E27: 26870107 | F27: 2239175.6 | G27: 537402145 | H27: =I27*12 -> 26870107 | I27: 2239175.6 | J27: =$I$27/($K$5*1000) -> 0.036866421 | K27: =($I$27/$K$6)/$K$5 -> 0.0023041513
B28: =B27+1 -> 19 | C28: Ruang Expansi Filling Packaging | D28: 1071796228 | E28: 26794906 | F28: 2232908.8 | G28: 1071796228 | H28: =I28*12 -> 53589811 | I28: 4465817.6 | J28: =$I$28/($K$5*1000) -> 0.073526485 | K28: =($I$28/$K$6)/$K$5 -> 0.0045954053
B29: =B28+1 -> 20 | C29: Bangunan Lainnya | D29: 236594750 | E29: 67601093 | F29: 5633424.5 | G29: 3.7519242e+09 | H29: =I29*12 -> 1.9942595e+08 | I29: 16618829 | J29: =$I$29/($K$5*1000) -> 0.27361711 | K29: =($I$29/$K$6)/$K$5 -> 0.017101069
B30: =B29+1 -> 21 | C30: Power House System | D30: 30414179484 | E30: 1.6120305e+09 | F30: 1.3433587e+08 | G30: 3.0414179e+10 | H30: =I30*12 -> 1.7106159e+09 | I30: 1.4255132e+08 | J30: =$I$30/($K$5*1000) -> 2.3470054 | K30: =($I$30/$K$6)/$K$5 -> 0.14668783
B31: =B30+1 -> 22 | C31: Reception from Road Tanker System | D31: 15714477178 | E31: 1.5906981e+09 | F31: 1.3255817e+08 | G31: 1.5714477e+10 | H31: =I31*12 -> 1.6892835e+09 | I31: 1.4077362e+08 | J31: =$I$31/($K$5*1000) -> 2.3177368 | K31: =($I$31/$K$6)/$K$5 -> 0.14485855
B32: =B31+1 -> 23 | C32: Reception & CPO Storage Tank System | D32: 3.9160256e+10 | E32: 1.8156968e+09 | F32: 1.5130807e+08 | G32: 3.9160256e+10 | H32: =I32*12 -> 1.9142822e+09 | I32: 1.5952352e+08 | J32: =$I$32/($K$5*1000) -> 2.6264404 | K32: =($I$32/$K$6)/$K$5 -> 0.16415252
B33: =B32+1 -> 24 | C33: Refinery Product System | D33: 26158484525 | E33: 1.546139e+09 | F33: 1.2884492e+08 | G33: 2.6158485e+10 | H33: =I33*12 -> 2.1043359e+09 | I33: 1.7536132e+08 | J33: =$I$33/($K$5*1000) -> 2.8871985 | K33: =($I$33/$K$6)/$K$5 -> 0.18044991
B34: =B33+1 -> 25 | C34: Fractionation Product System | D34: 44700543389 | E34: 2.5257813e+09 | F34: 2.1048177e+08 | G34: 4.4700543e+10 | H34: =I34*12 -> 2.6243667e+09 | I34: 2.1869722e+08 | J34: =$I$34/($K$5*1000) -> 3.600693 | K34: =($I$34/$K$6)/$K$5 -> 0.22504331
B35: =B34+1 -> 26 | C35: Compressed Air System | D35: 12406716786 | E35: 6.9726354e+08 | F35: 58105295 | G35: 1.2406717e+10 | H35: =I35*12 -> 6.9726354e+08 | I35: 58105295 | J35: =$I$35/($K$5*1000) -> 0.95666202 | K35: =($I$35/$K$6)/$K$5 -> 0.059791376
B36: =B35+1 -> 27 | C36: Fuel Distribution System | D36: 2279256408 | E36: 1.6844371e+08 | F36: 14036976 | G36: 2.2792564e+09 | H36: =I36*12 -> 2.0366838e+08 | I36: 16972365 | J36: =$I$36/($K$5*1000) -> 0.27943783 | K36: =($I$36/$K$6)/$K$5 -> 0.017464864
B37: =B36+1 -> 28 | C37: Waste Water Treatment System | D37: 8173671310 | E37: 5.0165483e+08 | F37: 41804569 | G37: 8.1736713e+09 | H37: =I37*12 -> 5.1840723e+08 | I37: 43200602 | J37: =$I$37/($K$5*1000) -> 0.71126694 | K37: =($I$37/$K$6)/$K$5 -> 0.044454184
B38: =B37+1 -> 29 | C38: Clean Water System | D38: 8.1369458e+09 | E38: 4.697884e+08 | F38: 39149033 | G38: 8.1369458e+09 | H38: =I38*12 -> 4.697884e+08 | I38: 39149033 | J38: =$I$38/($K$5*1000) -> 0.64456076 | K38: =($I$38/$K$6)/$K$5 -> 0.040285047
B39: =B38+1 -> 30 | C39: Demin Water Distribution System | D39: 5554219736 | E39: 3.7021373e+08 | F39: 30851144 | G39: 5.5542197e+09 | H39: =I39*12 -> 3.7021373e+08 | I39: 30851144 | J39: =$I$39/($K$5*1000) -> 0.50794197 | K39: =($I$39/$K$6)/$K$5 -> 0.031746373
B40: =B39+1 -> 31 | C40: Steam Generation System | D40: 28411905935 | E40: 1.6009903e+09 | F40: 1.3341586e+08 | G40: 2.8411906e+10 | H40: =I40*12 -> 1.6009903e+09 | I40: 1.3341586e+08 | J40: =$I$40/($K$5*1000) -> 2.1965964 | K40: =($I$40/$K$6)/$K$5 -> 0.13728728 | L40: =H40/12 -> 1.3341586e+08
B41: =B40+1 -> 32 | C41: Cooling Water Distribution System | D41: 8813632097 | E41: 5.5719688e+08 | F41: 46433074 | G41: 8.8136321e+09 | H41: =I41*12 -> 5.5719688e+08 | I41: 46433074 | J41: =$I$41/($K$5*1000) -> 0.76448727 | K41: =($I$41/$K$6)/$K$5 -> 0.047780454
B42: =B41+1 -> 33 | C42: Fire Water System | D42: 4990631887 | E42: 3.5991574e+08 | F42: 29992978 | G42: 4.9906319e+09 | H42: =I42*12 -> 3.5991574e+08 | I42: 29992978 | J42: =$I$42/($K$5*1000) -> 0.49381288 | K42: =($I$42/$K$6)/$K$5 -> 0.030863305
B43: =B42+1 -> 34 | C43: Dual Fuel Emergency Generator | D43: 11752092639 | E43: 6.1186193e+08 | F43: 50988494 | G43: 1.1752093e+10 | H43: =I43*12 -> 6.1186193e+08 | I43: 50988494 | J43: =$I$43/($K$5*1000) -> 0.839489 | K43: =($I$43/$K$6)/$K$5 -> 0.052468063
B44: =B43+1 -> 35 | C44: Steam Distribution & Condensate Recovery System | D44: 9891619567 | E44: 8.9987659e+08 | F44: 74989716 | G44: 9.8916196e+09 | H44: =I44*12 -> 8.9987659e+08 | I44: 74989716 | J44: =$I$44/($K$5*1000) -> 1.2346519 | K44: =($I$44/$K$6)/$K$5 -> 0.077165744
B45: =B44+1 -> 36 | C45: Fire Water Main Ring System | D45: 4518985787 | E45: 2.4463794e+08 | F45: 20386495 | G45: 4.5189858e+09 | H45: =I45*12 -> 2.4463794e+08 | I45: 20386495 | J45: =$I$45/($K$5*1000) -> 0.33564902 | K45: =($I$45/$K$6)/$K$5 -> 0.020978064
B46: =B45+1 -> 37 | C46: Packaging System | D46: 34206697993 | E46: 3.1394346e+09 | F46: 2.6161955e+08 | G46: 1.2163436e+11 | H46: =I46*12 -> 7.8746236e+09 | I46: 6.5621863e+08 | J46: =$I$46/($K$5*1000) -> 10.804169 | K46: =($I$46/$K$6)/$K$5 -> 0.67526058
B47: =B46+1 -> 38 | C47: Refinery System | D47: 93804025615 | E47: 6.3108388e+09 | F47: 5.2590324e+08 | G47: 9.3804026e+10 | H47: =I47*12 -> 6.3327722e+09 | I47: 5.2773101e+08 | J47: =$I$47/($K$5*1000) -> 8.6887128 | K47: =($I$47/$K$6)/$K$5 -> 0.54304455
B48: =B47+1 -> 39 | C48: Fractionation System | D48: 69305898501 | E48: 4.7141422e+09 | F48: 3.9284518e+08 | G48: 6.9305899e+10 | H48: =I48*12 -> 4.7141422e+09 | I48: 3.9284518e+08 | J48: =$I$48/($K$5*1000) -> 6.4679143 | K48: =($I$48/$K$6)/$K$5 -> 0.40424464
B49: =B48+1 -> 40 | C49: Fat Pit System | D49: 1222833568 | E49: 76427098 | F49: 6368924.8 | G49: 1.2228336e+09 | H49: =I49*12 -> 76427098 | I49: 6368924.8 | J49: =$I$49/($K$5*1000) -> 0.10485978 | K49: =($I$49/$K$6)/$K$5 -> 0.0065537363
B50: =B49+1 -> 41 | C50: Weight Bridge | D50: 2557397646 | E50: 1.2786988e+08 | F50: 10655824 | G50: 2.5573976e+09 | H50: =I50*12 -> 1.2786988e+08 | I50: 10655824 | J50: =$I$50/($K$5*1000) -> 0.17544049 | K50: =($I$50/$K$6)/$K$5 -> 0.010965031
B51: =B50+1 -> 42 | C51: Mesin Dan Perlengkapan Pabrik | D51: 30580769059 | E51: 1.6581493e+09 | F51: 1.3817911e+08 | G51: 3.0797884e+10 | H51: =I51*12 -> 2.8889928e+09 | I51: 2.407494e+08 | J51: =$I$51/($K$5*1000) -> 3.9637662 | K51: =($I$51/$K$6)/$K$5 -> 0.24773539
B52: =B51+1 -> 43 | C52: Installation System Electrical (Auxiliary) | D52: 2460303143 | E52: 1.5376895e+08 | F52: 12814079 | G52: 2460303143 | H52: =I52*12 -> 1.5376895e+08 | I52: 12814079 | J52: =$I$52/($K$5*1000) -> 0.21097462 | K52: =($I$52/$K$6)/$K$5 -> 0.013185914
B53: =B52+1 -> 44 | C53: Mesin Dan Perlengkapan Pabrik | D53: 0 | E53: 0 | F53: 0 | G53: 0 | H53: =I53*12 -> 0 | I53: 0 | J53: =$I$53/($K$5*1000) -> 0 | K53: =($I$53/$K$6)/$K$5 -> 0
B54: =B53+1 -> 45 | C54: Mesin Dan Perlengkapan Pabrik | D54: 0 | E54: 0 | F54: 0 | G54: 0 | H54: =I54*12 -> 0 | I54: 0 | J54: =$I$54/($K$5*1000) -> 0 | K54: =($I$54/$K$6)/$K$5 -> 0
B55: =B54+1 -> 46 | C55: Refinery Product System | D55: 0 | E55: 0 | F55: 0 | G55: 0 | H55: =I55*12 -> 0 | I55: 0 | J55: =$I$55/($K$5*1000) -> 0 | K55: =($I$55/$K$6)/$K$5 -> 0
B56: =B55+1 -> 47 | C56: Perlengkapan Pabrik Lainnya | D56: 814629325 | E56: 1.3842046e+08 | F56: 11535038 | G56: 814629325 | H56: =I56*12 -> 1.3842046e+08 | I56: 11535038 | J56: =$I$56/($K$5*1000) -> 0.18991614 | K56: =($I$56/$K$6)/$K$5 -> 0.011869758
B57: =B56+1 -> 48 | C57: Bangunan Shelter / Pelataran | D57: 0 | E57: 0 | F57: 0 | G57: 0 | H57: =I57*12 -> 0 | I57: 0 | J57: =$I$57/($K$5*1000) -> 0 | K57: =($I$57/$K$6)/$K$5 -> 0
B58: =B57+1 -> 49 | C58: Saluran Drainase | D58: 3324550757 | E58: 1.6622754e+08 | F58: 13852295 | G58: 3.3245508e+09 | H58: =I58*12 -> 1.6622754e+08 | I58: 13852295 | J58: =$I$58/($K$5*1000) -> 0.2280681 | K58: =($I$58/$K$6)/$K$5 -> 0.014254256
B59: =B58+1 -> 50 | C59: Fence | D59: 1457273906 | E59: 72863695 | F59: 6071974.6 | G59: 1457273906 | H59: =I59*12 -> 72863695 | I59: 6071974.6 | J59: =$I$59/($K$5*1000) -> 0.099970709 | K59: =($I$59/$K$6)/$K$5 -> 0.0062481693
B60: =B59+1 -> 51 | C60: Bangunan Shelter / Pelataran | D60: 0 | E60: 0 | F60: 0 | G60: 0 | H60: =I60*12 -> 0 | I60: 0 | J60: =$I$60/($K$5*1000) -> 0 | K60: =($I$60/$K$6)/$K$5 -> 0
B61: =B60+1 -> 52 | C61: Alat Pengangkutan | D61: 702420000 | E61: 58515250 | F61: 4876270.8 | G61: 702420000 | H61: =I61*12 -> 92109000 | I61: 7675750 | J61: =$I$61/($K$5*1000) -> 0.12637572 | K61: =($I$61/$K$6)/$K$5 -> 0.0078984825
B62: =B61+1 -> 53 | C62: Perabot & Perlengkapan Kantor | D62: 2093240354 | E62: 2.8749571e+08 | F62: 23957976 | G62: 2093240354 | H62: =I62*12 -> 2.8749571e+08 | I62: 23957976 | J62: =$I$62/($K$5*1000) -> 0.3944509 | K62: =($I$62/$K$6)/$K$5 -> 0.024653181
B63: =B62+1 -> 54 | C63: Perabot dan Perlengkapan Mess | D63: 0 | E63: 0 | F63: 0 | G63: 0 | H63: =I63*12 -> 0 | I63: 0 | J63: =$I$63/($K$5*1000) -> 0 | K63: =($I$63/$K$6)/$K$5 -> 0
B64: =B63+1 -> 55 | C64: Alat & Perlengkapan Pabrik | D64: 68073000 | E64: 13614600 | F64: 1134550 | G64: 68073000 | H64: =I64*12 -> 13614600 | I64: 1134550 | J64: =$I$64/($K$5*1000) -> 0.018679552 | K64: =($I$64/$K$6)/$K$5 -> 0.001167472
B65: =B64+1 -> 56 | C65: Alat dan Perlengkapan Bengkel | D65: 140550000 | E65: 28110000 | F65: 2342500 | G65: 140550000 | H65: =I65*12 -> 28110000 | I65: 2342500 | J65: =$I$65/($K$5*1000) -> 0.038567583 | K65: =($I$65/$K$6)/$K$5 -> 0.0024104739
B66: =B65+1 -> 57 | C66: Alat dan Perlengkapan Laboratorium | D66: 3453064640 | E66: 3.7398892e+08 | F66: 31165744 | G66: 4405170868 | H66: =I66*12 -> 8.9603417e+08 | I66: 74669514 | J66: =$I$66/($K$5*1000) -> 1.22938 | K66: =($I$66/$K$6)/$K$5 -> 0.076836251
B67: =B66+1 -> 58 | C67: Alat IT / Komputer | D67: 1542535419 | E67: 2.9444276e+08 | F67: 24536897 | G67: 1.9760604e+09 | H67: =I67*12 -> 2.9825396e+08 | I67: 24854497 | J67: =$I$67/($K$5*1000) -> 0.40921147 | K67: =($I$67/$K$6)/$K$5 -> 0.025575717
B68: =B67+1 -> 59 | C68: Perabot & Perlengkapan Lainnya | D68: 11270000 | E68: 2254000 | F68: 187833.33 | G68: 11270000 | H68: =I68*12 -> 2254000 | I68: 187833.33 | J68: =$I$68/($K$5*1000) -> 0.0030925412 | K68: =($I$68/$K$6)/$K$5 -> 0.00019328382
B69: =B68+1 -> 60 | C69: Aktiva Tetap Non Produktif | D69: 26932688 | E69: 5386537.6 | F69: 448878.13 | G69: 26932688 | H69: =I69*12 -> 5386537.5 | I69: 448878.13 | J69: =$I$69/($K$5*1000) -> 0.0073904566 | K69: =($I$69/$K$6)/$K$5 -> 0.00046190353
B70: =B69+1 -> 61 | C70: Totem AKHLAK | D70: 30000000 | E70: 6000000 | F70: 500000 | G70: 30000000 | H70: =I70*12 -> 6000000.1 | I70: 500000.01 | J70: =$I$70/($K$5*1000) -> 0.0082321416 | K70: =($I$70/$K$6)/$K$5 -> 0.00051450885
B71: =B70+1 -> 62 | C71: Main Office | D71: 6869341541 | E71: 3.4448348e+08 | F71: 28706957 | G71: 6.9506539e+09 | H71: =I71*12 -> 3.4753269e+08 | I71: 28961058 | J71: =$I$71/($K$5*1000) -> 0.47682305 | K71: =($I$71/$K$6)/$K$5 -> 0.029801441

Sheet MTC
C1: working days | F1: working days
B2: Summary - PM Electrical | C2: ='Februari 2026 PMG 2'!AJ6 -> 28 | E2: Summary - PM Mechanical | F2: ='Februari 2026 PMG 2'!AJ6 -> 28
B3: Consumable Item | C3: Total Price | E3: Consumable Item | F3: Total Price
C4: Per Day | F4: Per Day
B5: Biaya Pemeliharaan Unit Refinery(Listrik) | C5: 1648879.6 | E5: Biaya Pemeliharaan Unit Refinery | F5: 4911824.3
B6: HP Boiler | C6: 2678431.4 | E6: Biaya Pemeliharaan Unit Fraksinasi | F6: 1230672.3
B7: Dry Fractination - Crystalizer & Filter Press | C7: 288459.38 | E7: Biaya Pemeliharaan Unit Cooling Tower | F7: 1084733.9
B8: Physical Refinery-Bleaching and Deodorization | C8: 404271.71 | E8: Biaya Pemeliharaan Unit Packaging | F8: 833815.52
B9: BOILER | C9: 150891.4 | E9: Biaya Pemeliharaan Unit Material Handling | F9: 949299.72
B10: Water Plant, Effluent & Hydrant | C10: 58543.417 | E10: Biaya Pemeliharaan Unit Utility | F10: 1106022.4
B11: Pump House | C11: 87425.77 | E11: Barang Consumable Maintenance | F11: 5634698.9
B12: DCS-CCR ISBL | C12: 254341.74
B13: Lighting All Area | C13: 114733.89 | E13: Total | F13: =SUM(F5:F12) -> 15751067
B14: Consumable | C14: 203159.66 | E14: Total/Month | F14: =F13*F2 -> 4.4102987e+08
B15: Kalibrasi Instrument Pabrik | C15: 580672.27 | E15: Total/Yearly | F15: =F14*12 -> 5.2923585e+09
B16: Service Special Equipment | C16: 4089635.9
B17: Total/Day | C17: =SUM(C5:C16) -> 10559446 | E17: TOTAL COST
B18: Total/Month | C18: =C17*C2 -> 2.9566449e+08 | E18: PM E + PM M | F18: =F14+C18 -> 7.3669436e+08
B19: Total/Yearly | C19: =C18*12 -> 3.5479739e+09 | E19: TOTAL | F19: =F18*12 -> 8.8403324e+09

Sheet LOG
B2: Port Cost Kuala Tanjung
B3: Through Put CPO Proses | J3: TPD | K3: ='HPP REF '!N3 -> 2169.1977
B4: Working Day | J4: Day | K4: ='HPP REF '!N4 -> 28
B5: Total CPO Refined | J5: TPM | K5: =K4*K3 -> 60737.537
B6: Kurs Rupiah | K6: 16000
B7: No | C7: Description | G7: Norma | I7: Total Biaya ( Rp ) | J7: RP/KG | K7: USD/MT
B8: 1 | C8: Trucking Komoditi ke Kuala Tanjung | E8: Olein ( Ton ) | F8: =(100%-0.8%-1.1*5%)*80%*K5 -> 45528.858 | G8: Rp/Kg | H8: 90 | I8: =H8*F8*1000 -> 4.0975972e+09 | J8: =I8/($K$5*1000) -> 67.464 | K8: =(I8/$K$6)/$K$5 -> 4.2165
E9: Stearin ( Ton ) Iso Tank | F9: =(100%-0.8%-1.1*5%)*20%*K5 -> 11382.214 | G9: Rp/Kg | H9: 150 | I9: =H9*F9*1000 -> 1.7073322e+09 | J9: =I9/($K$5*1000) -> 28.11 | K9: =(I9/$K$6)/$K$5 -> 1.756875
E10: PFAD ( Ton ) Iso Tank | F10: =1.1*5%*K5 -> 3340.5645 | G10: Rp/Kg | H10: 150 | I10: =H10*F10*1000 -> 5.0108468e+08 | J10: =I10/($K$5*1000) -> 8.25 | K10: =(I10/$K$6)/$K$5 -> 0.515625
B11: 2 | C11: Sewa Tank PTI Total Volume : 24.000 MT ( 5 Unit ) | E11: Tank 8.000 MT >> Olein | F11: 1 | G11: Rp/Kg | H11: 77 | I11: =H11*8000*F11*1000 -> 616000000 | J11: =I11/($K$5*1000) -> 10.141998 | K11: =(I11/$K$6)/$K$5 -> 0.6338749
E12: Tank 5.000 MT >> Stearin | F12: 2 | G12: Rp/Kg | H12: 79 | I12: =H12*5000*F12*1000 -> 790000000 | J12: =I12/($K$5*1000) -> 13.006784 | K12: =(I12/$K$6)/$K$5 -> 0.81292397
E13: Tank 3.000 MT >> RBDPO | F13: 1 | G13: Rp/Kg | H13: 77 | I13: =H13*3000*F13*1000 -> 231000000 | J13: =I13/($K$5*1000) -> 3.8032494 | K13: =(I13/$K$6)/$K$5 -> 0.23770309
E14: Tank 3.000 MT S/S >> PFAD | F14: 1 | G14: Rp/Kg | H14: 83 | I14: =H14*3000*F14*1000 -> 249000000 | J14: =I14/($K$5*1000) -> 4.0996065 | K14: =(I14/$K$6)/$K$5 -> 0.2562254
B15: 3 | C15: Finalty Over Capacity dari tank | D15: 0 | E15: Over Volume Olein | F15: =F8-(8000*D15) -> 45528.858 | G15: Rp/Kg | H15: 43 | I15: =H15*F15*1000 -> 1.9577409e+09 | J15: =I15/($K$5*1000) -> 32.2328 | K15: =(I15/$K$6)/$K$5 -> 2.01455
D16: 0 | E16: Over Volume Stearin | F16: =F9-(10000*D16) -> 11382.214 | G16: Rp/Kg | H16: 43 | I16: =H16*F16*1000 -> 4.8943522e+08 | J16: =I16/($K$5*1000) -> 8.0582 | K16: =(I16/$K$6)/$K$5 -> 0.5036375
D17: 0 | E17: Over Volume PFAD | F17: =F10-(3000*D17) -> 3340.5645 | G17: Rp/Kg | H17: 43 | I17: =H17*F17*1000 -> 1.4364428e+08 | J17: =I17/($K$5*1000) -> 2.365 | K17: =(I17/$K$6)/$K$5 -> 0.1478125
B18: 3 | C18: Beban Instalasi Pemompaan dan Pemanasan | E18: Total Volume | F18: =SUM(F8:F10) -> 60251.637 | G18: Rp/Kg | H18: 22 | I18: =H18*F18*1000 -> 1.325536e+09 | J18: =I18/($K$5*1000) -> 21.824 | K18: =(I18/$K$6)/$K$5 -> 1.364
B19: =B18+1 -> 4 | C19: Pompa | E19: Total Volume | F19: =F18 -> 60251.637 | G19: Rp/Kg | H19: 26 | I19: =H19*F18*1000 -> 1.5665426e+09 | J19: =I19/($K$5*1000) -> 25.792 | K19: =(I19/$K$6)/$K$5 -> 1.612
B20: =B19+1 -> 5 | C20: Beban Analisa ( Surveyor ) | E20: Total Volume | F20: =F18 -> 60251.637 | G20: Rp/Kg | H20: 3 | I20: =H20*F20*1000 -> 1.8075491e+08 | J20: =I20/($K$5*1000) -> 2.976 | K20: =(I20/$K$6)/$K$5 -> 0.186
B21: =B20+1 -> 6 | C21: Beban Pelabuhan ( Documen-Documen Pelabuhan ) | E21: Total Volume | F21: =F20 -> 60251.637 | G21: Rp/Kg | H21: 3 | I21: =H21*F21*1000 -> 1.8075491e+08 | J21: =I21/($K$5*1000) -> 2.976 | K21: =(I21/$K$6)/$K$5 -> 0.186
B22: =B21+1 -> 7 | C22: Beban Asuransi (Cost Insurance Freight)
B23: =B22+1 -> 8 | C23: Beban Sewa Kapal
B24: =B23+1 -> 9 | C24: Beban Pengangkutan Di Pelabuhan
B25: Total Biaya Transfer Product ke Kuala Tanjung Port | I25: =SUM(I8:I24) -> 1.4036423e+10 | J25: =SUM(J8:J24) -> 231.09964 | K25: =SUM(K8:K24) -> 14.443727

Sheet OH
B2: Overhead ( OH )
B3: Through Put CPO Proses | H3: TPD | I3: ='HPP REF '!N3 -> 2169.1977
B4: Working Day | H4: Day | I4: ='SUMMARY HPP '!I4 -> 28
B5: Total CPO Refined | H5: TPM | I5: =I4*I3 -> 60737.537
B6: Kurs Rupiah | I6: 16000
B7: No | C7: Description | D7: Actual 2023 (Audited) | F7: Budget 2024
D8: Years | E8: Month | F8: Years | G8: Month | H8: RP/KG | I8: USD/MT
B9: 1 | C9: Biaya Perjalanan Dinas (Dalam Provinsi) | D9: 305458258 | E9: =IFERROR(D9/12,0) -> 25454855 | F9: =G9*12 -> 3.6654991e+08 | G9: 30545826 | H9: =G9/($I$5*1000) -> 0.50291512 | I9: =(G9/$I$6)/$I$5 -> 0.031432195
B10: =B9+1 -> 2 | C10: Biaya Perjalanan Dinas (Luar Provinsi) | D10: 2.6287295e+09 | E10: =IFERROR(D10/12,0) -> 2.1906079e+08 | F10: =G10*12 -> 3.5487849e+09 | G10: 2.9573207e+08 | H10: =G10/($I$5*1000) -> 4.8690165 | I10: =(G10/$I$6)/$I$5 -> 0.30431353
B11: =B10+1 -> 3 | C11: Beban BBM Kendaraan | D11: 720175678 | E11: =IFERROR(D11/12,0) -> 60014640 | F11: =G11*12 -> 7.5618446e+08 | G11: 63015372 | H11: =G11/($I$5*1000) -> 1.0375029 | I11: =(G11/$I$6)/$I$5 -> 0.064843932
B12: =B11+1 -> 4 | C12: Beban Sewa Kendaraan | D12: 2428347903 | E12: =IFERROR(D12/12,0) -> 2.0236233e+08 | F12: =G12*12 -> 2220000000 | G12: 185000000 | H12: =G12/($I$5*1000) -> 3.0458924 | I12: =(G12/$I$6)/$I$5 -> 0.19036827
B13: =B12+1 -> 5 | C13: Beban Kendaraan Lainnya | D13: 110862850 | E13: =IFERROR(D13/12,0) -> 9238570.8 | F13: =G13*12 -> 110862850 | G13: 9238570.8 | H13: =G13/($I$5*1000) -> 0.15210645 | I13: =(G13/$I$6)/$I$5 -> 0.0095066528
B14: =B13+1 -> 6 | C14: Beban Sewa Bangunan / Inventaris / Aset | D14: 126990400 | E14: =IFERROR(D14/12,0) -> 10582533 | F14: =G14*12 -> 110000400 | G14: 9166700 | H14: =G14/($I$5*1000) -> 0.15092314 | I14: =(G14/$I$6)/$I$5 -> 0.0094326965
B15: =B14+1 -> 7 | C15: Beban Penelitian, Percobaan & Pengembangan | D15: 108868060 | E15: =IFERROR(D15/12,0) -> 9072338.3 | F15: =G15*12 -> 100000000 | G15: 8333333.3 | H15: =G15/($I$5*1000) -> 0.13720236 | I15: =(G15/$I$6)/$I$5 -> 0.0085751474
B16: =B15+1 -> 8 | C16: Beban Pemeliharaan Bangunan Rumah | D16: 203000 | E16: =IFERROR(D16/12,0) -> 16916.667 | F16: =G16*12 -> 0 | G16: 0 | H16: =G16/($I$5*1000) -> 0 | I16: =(G16/$I$6)/$I$5 -> 0
B17: =B16+1 -> 9 | C17: Beban Pemeliharaan Bangunan Perusahaan | D17: 108952486 | E17: =IFERROR(D17/12,0) -> 9079373.8 | F17: =G17*12 -> 1.1440011e+08 | G17: 9533342.5 | H17: =G17/($I$5*1000) -> 0.15695965 | I17: =(G17/$I$6)/$I$5 -> 0.0098099781
B18: =B17+1 -> 10 | C18: Beban Pemeliharaan Mesin & Instalansi | D18: 32369030 | E18: =IFERROR(D18/12,0) -> 2697419.2 | F18: =G18*12 -> 33987482 | G18: 2832290.1 | H18: =G18/($I$5*1000) -> 0.046631626 | I18: =(G18/$I$6)/$I$5 -> 0.0029144766
B19: =B18+1 -> 11 | C19: Beban Pemeliharaan Jalan, Jembatan & Saluran Air | D19: 179265600 | E19: =IFERROR(D19/12,0) -> 14938800 | F19: =G19*12 -> 188228880 | G19: 15685740 | H19: =G19/($I$5*1000) -> 0.25825446 | I19: =(G19/$I$6)/$I$5 -> 0.016140904
B20: =B19+1 -> 12 | C20: Beban Pemeliharaan Alat Inventaris Kecil | D20: 253700695 | E20: =IFERROR(D20/12,0) -> 21141725 | F20: =G20*12 -> 2.6638573e+08 | G20: 22198811 | H20: =G20/($I$5*1000) -> 0.3654875 | I20: =(G20/$I$6)/$I$5 -> 0.022842969
B21: =B20+1 -> 13 | C21: Beban Pemakaian Inventaris Kecil | D21: 1859843066 | E21: =IFERROR(D21/12,0) -> 1.5498692e+08 | F21: =G21*12 -> 335473201 | G21: 27956100 | H21: =G21/($I$5*1000) -> 0.46027714 | I21: =(G21/$I$6)/$I$5 -> 0.028767322
B22: =B21+1 -> 14 | C22: Beban Iuran, Sumbangan, & Bina Lingkungan | D22: 694460474 | E22: =IFERROR(D22/12,0) -> 57871706 | F22: =G22*12 -> 2.6839105e+08 | G22: 22365921 | H22: =G22/($I$5*1000) -> 0.36823886 | I22: =(G22/$I$6)/$I$5 -> 0.023014928
B23: =B22+1 -> 15 | C23: Beban Instansi Kelembagaan | E23: =IFERROR(D23/12,0) -> 0 | F23: =G23*12 -> 60000000 | G23: 5000000 | H23: =G23/($I$5*1000) -> 0.082321415 | I23: =(G23/$I$6)/$I$5 -> 0.0051450884
B24: =B23+1 -> 16 | C24: Beban Pajak & Retribusi | D24: 659276883 | E24: =IFERROR(D24/12,0) -> 54939740 | F24: =G24*12 -> 1518332400 | G24: 126527700 | H24: =G24/($I$5*1000) -> 2.0831879 | I24: =(G24/$I$6)/$I$5 -> 0.13019924
B25: =B24+1 -> 17 | C25: Beban Premi Assuransi | E25: =IFERROR(D25/12,0) -> 0 | F25: =G25*12 -> 197000000 | G25: 16416667 | H25: =G25/($I$5*1000) -> 0.27028865 | I25: =(G25/$I$6)/$I$5 -> 0.01689304
B26: =B25+1 -> 18 | C26: Beban Penerangan | D26: 62716328 | E26: =IFERROR(D26/12,0) -> 5226360.7 | F26: =G26*12 -> 80400000 | G26: 6700000 | H26: =G26/($I$5*1000) -> 0.1103107 | I26: =(G26/$I$6)/$I$5 -> 0.0068944185
B27: =B26+1 -> 19 | C27: Beban Persediaan Air | D27: 1756590 | E27: =IFERROR(D27/12,0) -> 146382.5 | F27: =G27*12 -> 6840000 | G27: 570000 | H27: =G27/($I$5*1000) -> 0.0093846413 | I27: =(G27/$I$6)/$I$5 -> 0.00058654008
B28: =B27+1 -> 20 | C28: Beban Pemakaian Perlengkapan Kantor | D28: 1.1936208e+09 | E28: =IFERROR(D28/12,0) -> 99468402 | F28: =G28*12 -> 1.1936208e+09 | G28: 99468402 | H28: =G28/($I$5*1000) -> 1.6376759 | I28: =(G28/$I$6)/$I$5 -> 0.10235474
B29: =B28+1 -> 21 | C29: Beban Pengendalian Lingkungan (ISO 14000) | D29: 488020500 | E29: =IFERROR(D29/12,0) -> 40668375 | F29: =G29*12 -> 264000000 | G29: 22000000 | H29: =G29/($I$5*1000) -> 0.36221423 | I29: =(G29/$I$6)/$I$5 -> 0.022638389
B30: =B29+1 -> 22 | C30: Beban Sistem Manajemen Keselamatan & Kesehatan Kerja (SMK3) | D30: 68171900 | E30: =IFERROR(D30/12,0) -> 5680991.7 | F30: =G30*12 -> 258000000 | G30: 21500000 | H30: =G30/($I$5*1000) -> 0.35398209 | I30: =(G30/$I$6)/$I$5 -> 0.02212388
B31: =B30+1 -> 23 | C31: Beban Pendidikan & Pengembangan SDM | D31: 1186354647 | E31: =IFERROR(D31/12,0) -> 98862887 | F31: =G31*12 -> 10000000 | G31: 833333.33 | H31: =G31/($I$5*1000) -> 0.013720236 | I31: =(G31/$I$6)/$I$5 -> 0.00085751474
B32: =B31+1 -> 24 | C32: Beban Audit (Independent Auditor) | D32: 8.477783e+08 | E32: =IFERROR(D32/12,0) -> 70648192 | F32: =G32*12 -> 9.0712278e+08 | G32: 75593565 | H32: =G32/($I$5*1000) -> 1.2445938 | I32: =(G32/$I$6)/$I$5 -> 0.077787116
B33: =B32+1 -> 25 | C33: Beban Konsultan - Eksternal | D33: 245454645 | E33: =IFERROR(D33/12,0) -> 20454554 | F33: =G33*12 -> 2.7000011e+08 | G33: 22500009 | H33: =G33/($I$5*1000) -> 0.37044652 | I33: =(G33/$I$6)/$I$5 -> 0.023152907
B34: =B33+1 -> 26 | C34: Beban Insentif Karyawan | E34: =IFERROR(D34/12,0) -> 0 | F34: =G34*12 -> 0 | G34: 0 | H34: =G34/($I$5*1000) -> 0 | I34: =(G34/$I$6)/$I$5 -> 0
B35: =B34+1 -> 27 | C35: Beban Jasa Produksi Karyawan | E35: =IFERROR(D35/12,0) -> 0 | F35: =G35*12 -> 0 | G35: 0 | H35: =G35/($I$5*1000) -> 0 | I35: =(G35/$I$6)/$I$5 -> 0
B36: =B35+1 -> 28 | C36: Beban Uang Jasa (Jubilium, SHT, Dll) | D36: 188207400 | E36: =IFERROR(D36/12,0) -> 15683950 | F36: =G36*12 -> 207028140 | G36: 17252345 | H36: =G36/($I$5*1000) -> 0.28404749 | I36: =(G36/$I$6)/$I$5 -> 0.017752968
B37: =B36+1 -> 29 | C37: Beban Imbalan Pasca Kerja | D37: 4384212523 | E37: =IFERROR(D37/12,0) -> 3.6535104e+08 | F37: =G37*12 -> 666345107 | G37: 55528759 | H37: =G37/($I$5*1000) -> 0.9142412 | I37: =(G37/$I$6)/$I$5 -> 0.057140075
B38: =B37+1 -> 30 | C38: Beban Pengurusan Sertifikasi / Hak Merk / Izin / Dll | D38: 108648500 | E38: =IFERROR(D38/12,0) -> 9054041.7 | F38: =G38*12 -> 114080925 | G38: 9506743.8 | H38: =G38/($I$5*1000) -> 0.15652172 | I38: =(G38/$I$6)/$I$5 -> 0.0097826075
B39: =B38+1 -> 31 | C39: Beban Entertainment | D39: 80056015 | E39: =IFERROR(D39/12,0) -> 6671334.6 | F39: =G39*12 -> 0 | G39: 0 | H39: =G39/($I$5*1000) -> 0 | I39: =(G39/$I$6)/$I$5 -> 0
B40: =B39+1 -> 32 | C40: Beban Akomodasi Rapat | D40: 84564877 | E40: =IFERROR(D40/12,0) -> 7047073.1 | F40: =G40*12 -> 88793121 | G40: 7399426.7 | H40: =G40/($I$5*1000) -> 0.12182626 | I40: =(G40/$I$6)/$I$5 -> 0.007614141
B41: =B40+1 -> 33 | C41: Beban Bonus Karyawan | E41: =IFERROR(D41/12,0) -> 0 | F41: =G41*12 -> 0 | G41: 0 | H41: =G41/($I$5*1000) -> 0 | I41: =(G41/$I$6)/$I$5 -> 0
B42: =B41+1 -> 34 | C42: Beban Tantiem | E42: =IFERROR(D42/12,0) -> 0 | F42: =G42*12 -> 0 | G42: 0 | H42: =G42/($I$5*1000) -> 0 | I42: =(G42/$I$6)/$I$5 -> 0
B43: =B42+1 -> 35 | C43: Beban Konsumsi | D43: 3864122096 | E43: =IFERROR(D43/12,0) -> 3.2201017e+08 | F43: =G43*12 -> 2223000000 | G43: 185250000 | H43: =G43/($I$5*1000) -> 3.0500084 | I43: =(G43/$I$6)/$I$5 -> 0.19062553
B44: =B43+1 -> 36 | C44: Beban Ekstra Fooding | D44: 810000 | E44: =IFERROR(D44/12,0) -> 67500 | F44: =G44*12 -> 0 | G44: 0 | H44: =G44/($I$5*1000) -> 0 | I44: =(G44/$I$6)/$I$5 -> 0
B45: =B44+1 -> 37 | C45: Beban Pemeriksaan Kesehatan / Perobatan | D45: 185612516 | E45: =IFERROR(D45/12,0) -> 15467710 | F45: =G45*12 -> 41405668 | G45: 3450472.3 | H45: =G45/($I$5*1000) -> 0.056809553 | I45: =(G45/$I$6)/$I$5 -> 0.0035505971
B46: =B45+1 -> 38 | C46: Beban Peringatan Hari Besar | D46: 300000 | E46: =IFERROR(D46/12,0) -> 25000 | F46: =G46*12 -> 25000000 | G46: 2083333.3 | H46: =G46/($I$5*1000) -> 0.03430059 | I46: =(G46/$I$6)/$I$5 -> 0.0021437869
B47: =B46+1 -> 39 | C47: Beban Perlengkapan Karyawan | D47: 497881607 | E47: =IFERROR(D47/12,0) -> 41490134 | F47: =G47*12 -> 420000000 | G47: 35000000 | H47: =G47/($I$5*1000) -> 0.57624991 | I47: =(G47/$I$6)/$I$5 -> 0.036015619
B48: =B47+1 -> 40 | C48: Beban Keperluan Dapur / Pantry | D48: 79298165 | E48: =IFERROR(D48/12,0) -> 6608180.4 | F48: =G48*12 -> 12458700 | G48: 1038225 | H48: =G48/($I$5*1000) -> 0.01709363 | I48: =(G48/$I$6)/$I$5 -> 0.0010683519
B49: =B48+1 -> 41 | C49: Beban Employee Gathering | E49: =IFERROR(D49/12,0) -> 0 | F49: =G49*12 -> 250000000 | G49: 20833333 | H49: =G49/($I$5*1000) -> 0.3430059 | I49: =(G49/$I$6)/$I$5 -> 0.021437869
B50: =B49+1 -> 42 | C50: Beban Kebersihan | D50: 11059767 | E50: =IFERROR(D50/12,0) -> 921647.25 | F50: =G50*12 -> 0 | G50: 0 | H50: =G50/($I$5*1000) -> 0 | I50: =(G50/$I$6)/$I$5 -> 0
D51: =SUM(D9:D50) -> 2.3796151e+10 | E51: =SUM(E9:E50) -> 1.9830126e+09 | F51: =SUM(F9:F50) -> 1.7232677e+10 | G51: =SUM(G9:G50) -> 1.4360564e+09 | H51: =SUM(H9:H50) -> 23.643639 | I51: =SUM(I9:I50) -> 1.4777274

Sheet Time Sheet Bulanan
A1: Nomor | B1: Tanggal | C1: Keterangan
C2: Refinery | D2: Fraksinasi
A3: 1 | B3: 45536
A4: 2 | B4: 45537
A5: 3 | B5: 45538
A6: 4 | B6: 45539
A7: 5 | B7: 45540
A8: 6 | B8: 45541
A9: 7 | B9: 45542
A10: 8 | B10: 45543
A11: 9 | B11: 45544
A12: 10 | B12: 45545
A13: 11 | B13: 45546
A14: 12 | B14: 45547
... A25: 23 | B25: 45558
A26: 24 | B26: 45559 | C26: Update tgal 24/09/2024 Refinery * 07.00 ref HOLD * 22.00 steam masuk ke plant * 01.20 ref firing hpb * 02.00 sirkulasi * 03.00-07.00 plant HOLD terkait pressure gas HPB drop | D26: Stop sementara & aktifitas cleaning chiller
A27: 25 | B27: 45560 | C27: Refinery * 07.40 start sirkulasi | D27: Fraksinasi * Stop sementara dan pagi ini kunci mainhole chiller pak
A28: 26 | B28: 45561
A29: 27 | B29: 45562
A30: 28 | B30: 45563
A31: 29 | B31: 45564
A32: 30 | B32: 45565

Sheet Flow Meter
A2: TOTAL TONASE FLOWMETER PRODUK
A3: REFINERY
A5: TANGGAL VALIDASI
A6: NO | B6: NAMA PRODUK | C6: 01 Juli | D6: 02 Juli | E6: 03 Juli | F6: 04 Juli | G6: 05 Juli | H6: 06 Juli | I6: 07 Juli | J6: 08 Juli | K6: 09 Juli | L6: 10 Juli | M6: 11 Juli | N6: 12 Juli | O6: 13 Juli | P6: 14 Juli | Q6: 15 Juli | R6: TOTAL | S6: Sounding | T6: Yield Theory | U6: Yield Aktual
A7: 1 | B7: CPO | C7: ='[5]01 '!$Q$14 -> 744924 | D7: ='[5]02'!$Q$14 -> 743972 | E7: ='[5]03'!$Q$14 -> 1048435 | F7: ='[5]04'!$Q$14 -> 1114821 | G7: 248126 | H7: 389481 | I7: 104168 | J7: 320907 | K7: 100743 | L7: 512647 | M7: 441064 | N7: 524002 | O7: 568358 | P7: 430750 | R7: =SUM(C7:Q7) -> 7292398
A8: 2 | B8: RBDPO | C8: 713300 | D8: 708000 | E8: 993100 | F8: 1056000 | G8: 237021 | H8: 365100 | I8: 44001 | J8: 300010 | K8: 94507 | L8: 488153 | M8: 414337 | N8: 492952 | O8: 532902 | P8: 497845 | R8: =SUM(C8:Q8) -> 6937228 | T8: =R8/R7 -> 0.95129586 | U8: =S8/S7 -> #DIV/0! | W8: =4984655+#REF! -> #REF!
A9: 3 | B9: PFAD | C9: ='[5]01 '!$P$25 -> 25659 | D9: 28786 | E9: ='[5]03'!$P$25 -> 46938 | F9: ='[5]04'!$P$24 -> 48667 | G9: 8070 | H9: 19280 | I9: 3234 | J9: 18283 | K9: 5131 | L9: 20426 | M9: 23275 | N9: 27655 | O9: 25803 | P9: 20173 | R9: =SUM(C9:Q9) -> 321380 | T9: =R9/R7 -> 0.044070551 | U9: =S9/S7 -> #DIV/0!
C10: =C8/C7 -> 0.95754735 | D10: =D8/D7 -> 0.95164872 | E10: =E8/E7 -> 0.94722133 | F10: =F8/F7 -> 0.94723727 | G10: =G8/G7 -> 0.95524451 | H10: =H8/H7 -> 0.93740131 | I10: =I8/I7 -> 0.42240419 | J10: =J8/J7 -> 0.93488145 | ... P10: =P8/P7 -> 1.1557632
C11: =C9/C7*1 -> 0.034445125 | D11: =D9/D7*1 -> 0.038692316 | E11: =E9/E7*1 -> 0.044769585 | F11: =F9/F7*1 -> 0.043654542 | G11: =G9/G7*1 -> 0.032523798 | H11: =H9/H7*1 -> 0.049501773 | I11: =I9/I7*1 -> 0.031046003 | J11: =J9/J7*1 -> 0.056972892 | ... P11: =P9/P7*1 -> 0.046832269
B12: LOSIS | C12: =(C7-C8-C9)/C7 -> 0.0080075283 | D12: =(D7-D8-D9)/D7 -> 0.0096589657 | E12: =(E7-E8-E9)/E7 -> 0.0080090802 | F12: =(F7-F8-F9)/F7 -> 0.0091081887 | G12: =(G7-G8-G9)/G7 -> 0.012231689 | H12: =(H7-H8-H9)/H7 -> 0.013096916 | I12: =(I7-I8-I9)/I7 -> 0.5465498 | J12: =(J7-J8-J9)/J7 -> 0.0081456621 | ... P12: =(P7-P8-P9)/P7 -> -0.20259547
A14: TANGGAL flow meter
A15: NO | B15: NAMA PRODUK | C15: 01 Juli | D15: 02 Juli | E15: 03 Juli | F15: 04 Juli | G15: 05 Juli | H15: 06 Juli | I15: 07 Juli | J15: 08 Juli | K15: 09 Juli | L15: 10 Juli | M15: 11 Juli | N15: 12 Juli | O15: 13 Juli | P15: 14 Juli | Q15: 15 Juli | R15: TOTAL | S15: Sounding | T15: Yield Theory | U15: Yield Aktual
A16: 1 | B16: CPO | C16: 680800 | D16: 806400 | E16: 858600 | F16: 898100 | G16: 26100 | H16: 513200 | I16: 119200 | J16: 208900 | K16: 147700 | L16: 425800 | M16: 347900 | N16: 459100 | O16: 509200 | P16: 396700 | Q16: 20200 | R16: =SUM(C16:Q16) -> 6417900 | S16: =5745000+14073+R19 -> 7292813
A17: 2 | B17: RBDPO | C17: 722400 | D17: 826700 | E17: 980700 | F17: 980600 | G17: 19900 | H17: 582000 | I17: 150500 | J17: 215300 | K17: 70837 | L17: 488153 | M17: 379337 | N17: 502200 | O17: 535800 | P17: 412600 | Q17: 92100 | R17: =SUM(C17:Q17) -> 6959127 | S17: =SUM(C17:M17)+R20 -> 6940126 | T17: =R17/R16 -> 1.0843309 | U17: =S17/S16 -> 0.9516391 | W17: =4984655+R20 -> 6508354
A18: 3 | B18: PFAD | C18: 37300 | D18: 38700 | E18: 49500 | F18: 47100 | G18: 3800 | H18: 30300 | I18: 9300 | J18: 14000 | K18: 14800 | L18: 25100 | M18: 23400 | N18: 23900 | O18: 26800 | P18: 22200 | Q18: 5900 | R18: =SUM(C18:Q18) -> 372100 | S18: =248746+R21 -> 322377 | T18: =R18/R16 -> 0.057978466 | U18: =S18/S16 -> 0.044204753
C19: =C17/C16 -> 1.0611046 | D19: =D17/D16 -> 1.0251736 | E19: =E17/E16 -> 1.1422082 | F19: =F17/F16 -> 1.0918606 | G19: =G17/G16 -> 0.76245211 | H19: =H17/H16 -> 1.1340608 | I19: =I17/I16 -> 1.2625839 | J19: =J17/J16 -> 1.0306367 | K19: =K17/K16 -> 0.47960054 | L19: 269515 | M19: CPO | N19: 534002 | O19: 568773 | P19: 430750 | Q19: 269300 | R19: =L19+N19+O19+P19-Q19 -> 1533740 | U19: =100%-U17-U18 -> 0.0041561466 | V19: Losses
M20: RBDPO | N20: 492952 | O20: 532902 | P20: 497845 | R20: =SUM(N20:P20) -> 1523699
N21: 27655 | O21: 25803 | P21: 20173 | R21: =SUM(N21:P21) -> 73631
B22: Nb : | C22: 1. 5.745.000 adalaha angka consume CPO tanggal 1 - 11 ( Opening Stock + Incoming - Closing tanggal 11 )
C23: 2. 14.073 ( Beda Pembacaan antara sounding dan timbangan )
C24: 3. 1.533.740 adalah angka sounding CPO 12, 13, 14
A25: FRAKSINASI
A26: TANGGAL
A27: NO | B27: NAMA PRODUK | C27: 01 Juli | D27: 02 Juli | E27: 03 Juli | F27: 04 Juli | G27: 05 Juli | H27: 06 Juli | I27: 07 Juli | J27: 08 Juli | K27: 09 Juli | L27: 10 Juli | M27: 11 Juli | N27: 12 Juli | O27: 13 Juli | P27: 14 Juli | Q27: 15 Juli | R27: TOTAL | S27: Sounding | T27: Yield
A28: 1 | B28: RBDPO | C28: 667300 | D28: 695000 | E28: 814100 | F28: 760000 | G28: 620300 | H28: 587100 | I28: 118500 | J28: 0 | K28: 253000 | L28: 0 | M28: 466900 | N28: 258400 | O28: 584400 | P28: 680200 | R28: =SUM(C28:Q28) -> 6505200
A29: 2 | B29: OLEIN IV 58 | C29: 518400 | D29: 487200 | E29: 539100 | F29: 571900 | G29: 554300 | H29: 449900 | I29: 209900 | J29: 0 | K29: 297100 | L29: 0 | M29: 472500 | N29: 207400 | O29: 239100 | P29: 414100 | R29: =SUM(C29:Q29) -> 4960900
A30: 3 | B30: STEARIN | C30: 207500 | D30: 202900 | E30: 215500 | F30: =27400+151100+55600 -> 234100 | G30: 213300 | H30: 183700 | I30: 104800 | J30: 0 | K30: 93900 | L30: 0 | M30: 172400 | N30: 111100 | O30: 81200 | P30: 193200 | R30: =SUM(C30:Q30) -> 2013600
O32: STOCK OPNAME | R32: =1311190 -> 1311190
O33: TOTAL TERIMA 1- 11 TIMBANGAN | R33: 3865830
O34: PIPANISASI DAN GK 1 - 11 | R34: 1888995
O35: STOCK AKHIR OPNAME 11 JULI | R35: 1320540.6
R36: =R32+R33+R34-R35 -> 5745474.4
O38: STOCK OPNAME 1 JULI | R38: 178489.22
O39: TOTAL FLOW METER 11 | R39: =SUM(C28:M28) -> 4982200
O40: STOCK AKHIR OPNAME 11 JULI
