Workbook

Sheet JUNI 2025
C1: PRODUCTION REPORT PMG2
C2: No | D2: ITEM | E2: Budget / Norma | F2: UoM | G2: JUNI 2025 | AL2: TOTAL MONTHLY (Kg)
G3: 1 | H3: 2 | I3: 3 | J3: 4 | K3: 5 | L3: 6 | M3: 7 | N3: 8 | O3: 9 | P3: 10 | Q3: 11 | R3: 12 | S3: 13 | T3: 14 | U3: 15 | V3: 16 | W3: 17 | X3: 18 | Y3: 19 | Z3: 20 | AA3: 21 | AB3: 22 | AC3: 23 | AD3: 24 | AE3: 25 | AF3: 26 | AG3: 27 | AH3: 28 | AI3: 29 | AJ3: 30
C4: 1 | D4: PRODUCTION | AL4: Production | AN4: aktual refinery
D5: Refinery | AL5: Refinery | AN5: cpo feed | AO5: =AL9 -> 17813187 | AQ5: sisa rbpo tank
D6: Running Days | F6: Day | N6: 1 | O6: 1 | P6: 1 | Q6: 1 | R6: 1 | S6: 1 | T6: 1 | U6: 1 | V6: 1 | W6: 1 | AL6: =SUM(G6:AJ6) -> 10 | AN6: rpo prod | AO6: =AL20+AL19+AL18 -> 16884686 | AQ6: tk 108 | AR6: 80236
D7: Incoming CPO | F7: Kg | G7: ='[1]01 (stock opname)'!$Q$15 -> 0 | H7: ='[1]02'!$Q$15 -> 393366 | I7: ='[1]03'!$Q$15 -> 1185533 | J7: ='[2]04'!$Q$15 -> 0 | K7: ='[2]05'!$Q$15 -> 445557 | L7: ='[2]06'!$Q$15 -> 0 | M7: ='[2]07'!$Q$15 -> 0 | N7: ='[2]08'!$Q$15 -> 0 | O7: ='[2]09'!$Q$15 -> 0 | P7: ='[2]10'!$Q$15 -> 0 | Q7: ='[2]11'!$Q$15 -> 224431 | R7: ='[2]12'!$Q$15 -> 0 | S7: ='[2]13 (Rev)'!$Q$15 -> 0 | T7: ='[2]14'!$Q$15 -> 208963 | U7: ='[2]15'!$Q$15 -> 0 | V7: ='[2]16'!$Q$15 -> 0 | W7: ='[2]17'!$Q$15 -> 516088 | X7: ='[2]18'!$Q$15 -> 0 | Y7: ='[2]19'!$Q$15 -> 0 | Z7: ='[2]20'!$Q$15 -> 218854 | AA7: ='[2]21'!$Q$15 -> 671086 | AB7: ='[2]22'!$Q$15 -> 0 | AC7: ='[2]23'!$Q$15 -> 132192 | AD7: ='[2]24'!$Q$15 -> 210307 | AE7: ='[2]25'!$Q$15 -> 277054 | AF7: ='[2]26'!$Q$15 -> 161951 | AG7: ='[2]27'!$Q$15 -> 0 | AH7: ='[2]28'!$Q$15 -> 501448 | AI7: ='[2]29'!$Q$15 -> 0 | AJ7: ='[2]30'!$Q$15 -> 1020823 | AL7: =SUM(G7:AJ7) -> 6167653 | AN7: pfad prod | AO7: =AL21 -> 866309 | AQ7: tk 109 | AR7: 70298
D8: Ratio Run CPO ( utilisasi kapasitas ) | F8: % | G8: =G9/2500000 -> 0 | H8: =H9/2500000 -> 0 | I8: =I9/2500000 -> 0 | J8: =J9/2500000 -> 0 | K8: =K9/2500000 -> 0 | L8: =L9/2500000 -> 0 | M8: 0 | N8: =N9/2500000 -> 0.2955432 | O8: =O9/2500000 -> 0.8925324 | P8: =P9/2500000 -> 0.87464 | Q8: =Q9/2500000 -> 1.0053404 | R8: =R9/2500000 -> 0.919868 | S8: =S9/2500000 -> 0.7951732 | T8: =T9/2500000 -> 0.6404488 | U8: =U9/2500000 -> 0.8040796 | ... W8: =W9/2500000 -> 0.1286836 | X8: 0 | Y8: =Y9/2500000 -> 0 | Z8: =Z9/2500000 -> 0 | AA8: =AA9/2500000 -> 0 | AB8: =AB9/2500000 -> 0 | AC8: =AC9/2500000 -> 0 | AD8: =AD9/2500000 -> 0 | AE8: =AE9/2500000 -> 0 | AF8: =AF9/2500000 -> 0 | ... AJ8: =AJ9/2500000 -> 0 | AL8: =AL9/2500000/AL6 -> 0.71252748 | AN8: yield rpo | AO8: =AO6/AO5*100 -> 94.787564 | AQ8: total rpo tank | AR8: =AR6+AR7 -> 150534
D9: CPO Consume Total | E9: 58900000 | F9: Kg | G9: ='[1]01 (stock opname)'!$R$15 -> 0 | H9: ='[1]02'!$R$15 -> 0 | I9: 0 | J9: =[1]MTD!$R$15 -> 0 | K9: ='[1]04'!$R$15 -> 0 | L9: ='[1]05'!$R$15 -> 0 | M9: 0 | N9: 738858 | O9: 2231331 | P9: 2186600 | Q9: 2513351 | R9: 2299670 | S9: 1987933 | T9: 1601122 | U9: 2010199 | V9: 1922414 | W9: 321709 | X9: Stop plant, Refinery tgl 18 Pukul 17.00 WIB Fraksinasi tgl 17 Pukul 04.00 WIB | AL9: =SUM(G9:AJ9) -> 17813187 | AN9: yield pfad | AO9: =AO7/AO5*100 -> 4.8633016 | AQ9: oip | AR9: 307166
D10: Avg Daily Consump CPO ( MTD ) | AL10: =AL9/AL6 -> 1781318.7 | AN10: lossis | AO10: =(AO5-AO6-AO7)/AO5*100 -> 0.3491346 | AQ10: total keseluruhan rpo | AR10: =AR8+AR9 -> 457700
D11: CPO Consume Poram | F11: Kg | G11: =G9-G12 -> 0 | H11: =H9-H12 -> 0 | I11: =I9-I12 -> 0 | J11: =J9-J12 -> 0 | L11: =L9-L12 -> 0 | M11: =M9-M12 -> 0 | N11: =N9-N12 -> 738858 | O11: =O9-O12 -> 2231331 | P11: =P9-P12 -> 2186600 | Q11: =Q9-Q12 -> 2513351 | R11: =R9-R12 -> 2299670 | S11: =S9-S12 -> 1987933 | ... W11: =W9-W12 -> 321709 | Y11: =Y9-Y12 -> 0 | Z11: =Z9-Z12 -> 0 | AA11: =AA9-AA12 -> 0 | AB11: =AB9-AB12 -> 0 | AC11: 0 | AD11: =AD9-AD12 -> 0 | AE11: =AE9-AE12 -> 0 | AF11: =AF9-AF12 -> 0 | AG11: =AG9-AG12 -> 0 | AH11: =AH9-AH12 -> 0 | AJ11: =AJ9-AJ12 -> 0 | AL11: =SUM(G11:AJ11) -> 17813187
D12: CPO Consume Brand | F12: Kg | G12: =G40+G49+G54 -> 0 | H12: =H40+H49+H54 -> 0 | I12: =I40+I49+I54 -> 0 | J12: =J40+J49+J54 -> 0 | K12: 0 | L12: =L40+L49+L54 -> 0 | M12: =M40+M49+M54 -> 0 | N12: =N40+N49+N54 -> 0 | O12: =O40+O49+O54 -> 0 | P12: =P40+P49+P54 -> 0 | R12: =R40+R49+R54 -> 0 | S12: 0 | T12: =T40+T49+T54 -> 0 | U12: =U40+U49+U54 -> 0 | V12: =V40+V49+V54 -> 0 | W12: =W40+W49+W54 -> 0 | X12: 0 | Y12: =Y40+Y49+Y54 -> 0 | Z12: =Z40+Z49+Z54 -> 0 | AA12: =AA40+AA49+AA54 -> 0 | AB12: =AB40+AB49+AB54 -> 0 | AC12: 0 | AD12: =AD40+AD49+AD54 -> 0 | AE12: =AE40+AE49+AE54 -> 0 | AF12: =AF40+AF49+AF54 -> 0 | AG12: =AG40+AG49+AG54 -> 0 | AH12: =AH40+AH49+AH54 -> 0 | AJ12: =AJ40+AJ49+AJ54 -> 0 | AL12: =SUM(G12:AJ12) -> 0 | AN12: aktual fraksinasi
D13: - FFA | E13: 5 | F13: % | G13: 0 | H13: 0 | I13: 0 | J13: 0 | K13: 0 | L13: 0 | M13: 0 | N13: 3.95 | O13: 3.98 | P13: 4.425 | Q13: =(4.66+4.69)/2 -> 4.675 | R13: 4.405 | S13: 4.9833333 | T13: 4.8333333 | U13: 4.48 | V13: =(4.59+5.36)/2 -> 4.975 | W13: 4.995 | AE13: 0 | AF13: 0 | AL13: =SUM(G13:AJ13)/AL6 -> 4.5701667 | AN13: rpo feed | AO13: =AO14+AO15 -> 17792607
D14: - Moist & Impurities | E14: 0.5 | F14: % | G14: 0 | H14: 0 | I14: 0 | J14: 0 | K14: 0 | L14: 0 | M14: 0 | N14: 0.49 | O14: 0.47 | P14: 0.43 | Q14: =(0.44+0.45)/2 -> 0.445 | R14: 0.47 | S14: 0.42 | T14: 0.44666667 | U14: 0.44 | V14: =(0.46+0.45)/2 -> 0.455 | W14: 0.5 | AE14: 0 | AF14: 0 | AL14: =SUM(G14:AJ14)/AL6 -> 0.45666667 | AN14: olein 56 | AO14: =AL33 -> 14325558
D15: - DOBI | E15: 2,20 Min | F15: % | AL15: =SUM(G15:AJ15)/AL6 -> 0 | AN15: stearin 56 | AO15: =AL34 -> 3467049
D16: TANK | N16: 107 | O16: 107 | P16: 105&107 | Q16: 105&104 | R16: 107&104 | S16: 104,105&106 | T16: 104,103&106 | U16: 103 | V16: 103&106 | W16: 103&106 | AN16: yield olein | AO16: =AO14/(AO14+AO15)*100 -> 80.514103
D17: Product | AL17: Product | AN17: yield stearin | AO17: =AO15/(AO14+AO15)*100 -> 19.485897
D18: OIP RBDPO | F18: Kg | N18: ='[3]OIP Refinery '!L13 -> 311880 | O18: 4410 | P18: 0 | Q18: 6558 | R18: 9650 | S18: 0 | T18: 9873 | V18: 15966 | AL18: =SUM(N18:X18) -> 358337
D19: DIRECT RBDPO FRACT | F19: Kg | N19: 30000 | O19: 90000 | P19: 20000 | Q19: 60000 | R19: 0 | S19: 70000 | T19: 8000 | U19: 15000 | AL19: =SUM(N19:X19) -> 293000 | AN19: sap refinery | AQ19: sisa rbdo di gudang bulky 1014
D20: RBDPO | E20: 55661000 | F20: Kg | N20: =407840 -> 407840 | O20: =2031338 -> 2031338 | P20: 2046616 | Q20: 2312694 | R20: 2167692 | S20: 1801948 | T20: 1485187 | U20: 1883642 | V20: 1786212 | W20: 301271 | X20: 8909 | AL20: =SUM(G20:AJ20) -> 16233349 | AN20: cpo feed | AO20: 17813187 | AQ20: tk 108 | AR20: 195993 | AS20: =AR20-AR6 -> 115757
D21: PFAD | E21: 2827000 | F21: Kg | N21: 13234 | O21: 90330 | P21: 110892 | Q21: 119505 | R21: 104139 | S21: 97005 | T21: 84749 | U21: 96539 | V21: 106075 | W21: 32094 | X21: 11747 | AL21: =SUM(G21:AJ21) -> 866309 | AN21: rpo prod | AO21: 17065034 | AQ21: tk 109 | AR21: 390524 | AS21: =AR21-AR7 -> 320226 | AU21: =AS21/AS20*100 -> 276.6364
D22: Fractionation | AN22: pfad prod | AO22: 748153 | AQ22: total | AR22: =AR20+AR21 -> 586517 | AU22: =AS22/AS20*100 -> 0
D23: Running Days | F23: Day | N23: 1 | O23: 1 | P23: 1 | Q23: 1 | R23: 1 | S23: 1 | T23: 1 | U23: 1 | V23: 1 | W23: 1 | AL23: =SUM(G23:AJ23) -> 10 | AQ23: OIP actual | AR23: 435983 | AS23: adjust
D24: Avg Daily Consump RBDPO ( MTD ) | F24: Kg | G24: 0 | H24: 0 | I24: 0 | J24: 0 | K24: 0 | M24: 0 | N24: 0 | O24: 0 | P24: 0 | R24: 0 | S24: 0 | T24: 0 | U24: 0 | V24: 0 | W24: 0 | X24: 0 | Y24: 0 | Z24: 0 | AA24: 0 | AB24: 0 | AC24: 0 | AD24: 0 | AE24: 0 | AF24: 0 | AG24: 0 | AH24: 0 | AJ24: 0 | AL24: =AL29/AL23 -> 1779260.7 | AN24: yield rpo | AO24: =AO21/AO20*100 -> 95.800005 | AQ24: stok actual | AR24: =AR22-AR23 -> 150534
D25: Total RBDPO transfer to plant | F25: Kg | N25: 586396 | O25: 1842499 | P25: =1537236+1219751 -> 2756987 | Q25: =1183492+1051025 -> 2234517 | R25: =1166617+996624 -> 2163241 | S25: =907358+972093 -> 1879451 | T25: =944532+806441 -> 1750973 | U25: =750862+786319 -> 1537181 | V25: =1151822+657738 -> 1809560 | W25: 662642 | AF25: ='[4]26'!$R$18 -> 0 | AL25: =SUM(G25:AJ25) -> 17223447 | AN25: yield pfad | AO25: =AO22/AO20*100 -> 4.1999952 | AQ25: opening stok rpo sap | AR25: =AR23+AR24 -> 586517
D26: Stok TK 131 | E26: 559 | F26: ton | M26: ='[3]Oip Fract .'!T13 -> 0 | N26: ='[3]Oip Fract .'!T14 -> 34865 | O26: ='[3]Oip Fract .'!T15 -> 195375 | P26: 296343 | Q26: ='[3]Oip Fract .'!T17 -> 207866 | R26: ='[3]Oip Fract .'!T18 -> 175767 | S26: ='[3]Oip Fract .'!T19 -> 200007 | T26: ='[3]Oip Fract .'!T20 -> 158440 | U26: ='[3]Oip Fract .'!T21 -> 59863 | V26: ='[3]Oip Fract .'!T22 -> 34480 | W26: ='[3]Oip Fract .'!T23 -> 34859 | AN26: loss | AO26: =AO20-AO21-AO22 -> 0
D27: Stok TK 132 | E27: 559 | F27: ton | M27: ='[3]Oip Fract .'!V13 -> 0 | N27: ='[3]Oip Fract .'!V14 -> 52290 | O27: ='[3]Oip Fract .'!V15 -> 53075 | P27: 53075 | Q27: ='[3]Oip Fract .'!V17 -> 75063 | R27: ='[3]Oip Fract .'!V18 -> 97032 | S27: ='[3]Oip Fract .'!V19 -> 115080 | T27: ='[3]Oip Fract .'!V20 -> 130221 | U27: ='[3]Oip Fract .'!V21 -> 148827 | V27: ='[3]Oip Fract .'!V22 -> 165316 | W27: ='[3]Oip Fract .'!V23 -> 78396 | X27: ='[3]Oip Fract .'!V24 -> 272307
D28: Ratio Run RBDPO | G28: =G29/2500000 -> 0 | H28: =H29/2500000 -> 0 | I28: =I29/2500000 -> 0 | J28: =J29/2500000 -> 0 | K28: =K29/2500000 -> 0 | L28: =L29/2500000 -> 0 | M28: =M29/2500000 -> 0 | N28: =N29/2500000 -> 0.0762112 | ... W28: =W29/2500000 -> 0.577254 | X28: 0 | Y28: =Y29/2500000 -> 0 | Z28: =Z29/2500000 -> 0 | AA28: =AA29/2500000 -> 0 | AB28: =AB29/2500000 -> 0 | AC28: 0.52886 | AD28: =AD29/2500000 -> 0 | AE28: =AE29/2500000 -> 0 | AF28: =AF29/2500000 -> 0 | AG28: =AG29/2500000 -> 0 | AH28: =AH29/2500000 -> 0 | AI28: =AI29/2500000 -> 0 | AJ28: =AJ29/2500000 -> 0 | AL28: =AL29/2500000/10 -> 0.71170428 | AN28: sap fraksinasi
D29: Total Proses RBDPO | E29: 35501000 | F29: Kg | G29: =SUM(G32,G36,G41,G45,G55) -> 0 | H29: =SUM(H32,H36,H41,H45,H55) -> 0 | I29: =SUM(I32,I36,I41,I45,I55) -> 0 | J29: =SUM(J32,J36,J41,J45,J55) -> 0 | L29: =SUM(L32,L36,L41,L45,L55) -> 0 | M29: =SUM(M32,M36,M41,M45,M55) -> 0 | N29: =SUM(N32,N36,N41,N45,N55) -> 190528 | O29: =SUM(O32,O36,O41,O45,O55) -> 1817708 | P29: =SUM(P32,P36,P41,P45,P55) -> 2405788 | Q29: =SUM(Q32,Q36,Q41,Q45,Q55) -> 2393434 | R29: =SUM(R32,R36,R41,R45,R55) -> 2405045 | S29: =SUM(S32,S36,S41,S45,S55) -> 1825948 | ... AB29: =SUM(AB32,AB36,AB41,AB45,AB55) -> 0 | AC29: =AC46+AC47+AC56+AC57 -> 0 | AD29: =SUM(AD32,AD36,AD41,AD45,AD55) -> 0 | AE29: =SUM(AE32,AE36,AE41,AE45,AE55) -> 0 | AF29: =SUM(AF32,AF36,AF41,AF45,AF55) -> 0 | AG29: =SUM(AG32,AG36,AG41,AG45,AG55) -> 0 | AH29: =SUM(AH32,AH36,AH41,AH45,AH55) -> 0 | AJ29: =SUM(AJ32,AJ36,AJ41,AJ45,AJ55) -> 0 | AL29: =SUM(G29:AJ29) -> 17792607 | AN29: rpo feed | AO29: =AO31+AO32 -> 17792608
D30: Sisa Filling Crystalizer | F30: Kg | G30: =G25-G29 -> 0 | I30: =I25-I29 -> 0 | J30: =SUM(J33,J37,J42,J46,#REF!) -> #REF! | K30: 68473 | L30: =L25-L29 -> 0 | M30: =M25-M29 -> 0 | N30: =N25-N29 -> 395868 | O30: =O25-O29 -> 24791 | P30: =P25-P29 -> 351199 | Q30: =Q25-Q29 -> -158917 | R30: =R25-R29 -> -241804 | S30: 122463 | T30: =T25-T29 -> -485041 | U30: =U25-U29 -> 376836 | V30: =V25-V29 -> -80715 | W30: =W25-W29 -> -780493 | X30: -255281 | Y30: =Y25-Y29 -> 0 | Z30: =Z25-Z29 -> 0 | AA30: =AA25-AA29 -> 0 | AB30: =AB25-AB29 -> 0 | AC30: 390824 | AD30: =AD25-AD29 -> 0 | AE30: =AE25-AE29 -> 0 | AF30: =AF25-AF29 -> 0 | AG30: =AG25-AG29 -> 0 | AH30: =AH25-AH29 -> 0 | AJ30: =AJ25-AJ29 -> 0 | AL30: =SUM(G30:AJ30) -> #REF!
D31: Fractionation OLEIN IV 56 | AL31: Olein IV 56 | AN31: olein 56 | AO31: 14624233
D32: RBDPO Consume | F32: Kg | G32: =G33+G34 -> 0 | H32: =H33+H34 -> 0 | I32: =I33+I34 -> 0 | J32: =J33+J34 -> 0 | K32: 0 | L32: =L33+L34 -> 0 | M32: =M33+M34 -> 0 | N32: =N33+N34 -> 190528 | O32: =O33+O34 -> 1817708 | P32: =P33+P34 -> 2405788 | Q32: =Q33+Q34 -> 2393434 | R32: =R33+R34 -> 2405045 | S32: =S33+S34 -> 1825948 | ... AB32: =AB33+AB34 -> 0 | AC32: 0 | AD32: =AD33+AD34 -> 0 | AE32: =AE33+AE34 -> 0 | AF32: =AF33+AF34 -> 0 | AG32: =AG33+AG34 -> 0 | AH32: =AH33+AH34 -> 0 | AJ32: =AJ33+AJ34 -> 0 | AL32: =SUM(G32:AJ32) -> 17792607 | AN32: stearin 56 | AO32: 3168375
D33: OLEIN IV 56 | E33: 25000000 | F33: Kg | G33: 0 | H33: 0 | I33: 0 | J33: 0 | K33: 0 | L33: 0 | M33: 0 | N33: 190528 | O33: 1477571 | P33: 1922667 | Q33: 1924360 | R33: =1376983+564099 -> 1941082 | S33: 1474626 | T33: =1676048+133231 -> 1809279 | U33: =511790+424142 -> 935932 | V33: =591257+913865 -> 1505122 | W33: 1134304 | X33: 10087 | Z33: 0 | AA33: 0 | AB33: 0 | AC33: 0 | AD33: 0 | AF33: 0 | AG33: 0 | AH33: 0 | AJ33: 0 | AL33: =SUM(G33:AJ33) -> 14325558 | AN33: yield olein | AO33: =AO31/(AO31+AO32)*100 -> 82.192745
D34: STEARIN | E34: 639000 | F34: Kg | G34: 0 | H34: 0 | I34: 0 | J34: 0 | K34: 0 | L34: 0 | M34: 0 | N34: 0 | O34: 340137 | P34: 483121 | Q34: 469074 | R34: 463963 | S34: =242278+109044 -> 351322 | T34: 426735 | U34: 224413 | V34: 385153 | W34: 308831 | X34: 14300 | Z34: 0 | AA34: 0 | AB34: 0 | AC34: 0 | AD34: 0 | AF34: 0 | AG34: 0 | AJ34: 0 | AL34: =SUM(G34:AJ34) -> 3467049 | AN34: yiel stearin | AO34: =AO32/(AO31+AO32)*100 -> 17.807255
D35: Fractionation OLEIN IV 57 ( Bulk ) | AL35: Olein IV 57 ( Bulk )
D36: RBDPO Consume | F36: Kg | G36: =G37+G38 -> 0 | H36: =H37+H38 -> 0 | I36: =I37+I38 -> 0 | J36: =J37+J38 -> 0 | K36: 0 | L36: =L37+L38 -> 0 | M36: =M37+M38 -> 0 | N36: =N37+N38 -> 0 | O36: =O37+O38 -> 0 | P36: =P37+P38 -> 0 | Q36: =Q37+Q38 -> 0 | R36: =R37+R38 -> 0 | S36: 0 | T36: =T37+T38 -> 0 | U36: =U37+U38 -> 0 | V36: =V37+V38 -> 0 | W36: =W37+W38 -> 0 | X36: 0 | AA36: =AA37+AA38 -> 0 | AB36: =AB37+AB38 -> 0 | AC36: 0 | AD36: =AD37+AD38 -> 0 | AE36: =AE37+AE38 -> 0 | AF36: =AF37+AF38 -> 0 | AG36: =AG37+AG38 -> 0 | AH36: =AH37+AH38 -> 0 | AJ36: =AJ37+AJ38 -> 0 | AL36: =SUM(G36:AJ36) -> 0
D37: OLEIN IV 57 | F37: Kg | G37: 0 | H37: 0 | I37: 0 | J37: 0 | K37: 0 | L37: 0 | M37: 0 | N37: 0 | O37: 0 | P37: 0 | Q37: 0 | R37: 0 | S37: 0 | T37: 0 | U37: 0 | V37: 0 | W37: 0 | X37: 0 | AA37: 0 | AB37: 0 | AC37: 0 | AD37: 0 | AE37: 0 | AF37: 0 | AG37: 0 | AL37: =SUM(G37:AJ37) -> 0
D38: STEARIN | F38: Kg | G38: 0 | H38: 0 | I38: 0 | J38: 0 | K38: 0 | L38: 0 | M38: 0 | N38: 0 | O38: 0 | P38: 0 | Q38: 0 | R38: 0 | S38: 0 | T38: 0 | U38: 0 | V38: 0 | W38: 0 | X38: 0 | AA38: 0 | AB38: 0 | AC38: 0 | AD38: 0 | AE38: 0 | AF38: 0 | AG38: 0 | AL38: =SUM(G38:AJ38) -> 0
D39: Fractionation OLEIN IV 57 ( Retail ) | AL39: Olein IV 57 ( Retail )
D40: CPO Consume | F40: Kg | AL40: =SUM(G40:AJ40) -> 0
D41: RBDPO Brand Consume | F41: Kg | G41: =G42+G43 -> 0 | H41: =H42+H43 -> 0 | I41: =I42+I43 -> 0 | J41: =J42+J43 -> 0 | K41: 0 | L41: =L42+L43 -> 0 | M41: =M42+M43 -> 0 | N41: =N42+N43 -> 0 | O41: =O42+O43 -> 0 | P41: =P42+P43 -> 0 | Q41: =Q42+Q43 -> 0 | R41: =R42+R43 -> 0 | S41: 0 | T41: =T42+T43 -> 0 | U41: =U42+U43 -> 0 | V41: =V42+V43 -> 0 | W41: =W42+W43 -> 0 | X41: 0 | AA41: =AA42+AA43 -> 0 | AB41: =AB42+AB43 -> 0 | AC41: 0 | AD41: =AD42+AD43 -> 0 | AE41: =AE42+AE43 -> 0 | AF41: =AF42+AF43 -> 0 | AG41: =AG42+AG43 -> 0 | AH41: =AH42+AH43 -> 0 | AJ41: =AJ42+AJ43 -> 0 | AL41: =SUM(G41:AJ41) -> 0
D42: OLEIN IV 57 Low Color | F42: Kg | G42: 0 | H42: 0 | I42: 0 | J42: 0 | K42: 0 | L42: 0 | M42: 0 | N42: 0 | O42: 0 | P42: 0 | Q42: 0 | R42: 0 | S42: 0 | T42: 0 | U42: 0 | V42: 0 | W42: 0 | X42: 0 | AA42: 0 | AB42: 0 | AC42: 0 | AD42: 0 | AE42: 0 | AF42: 0 | AG42: 0 | AL42: =SUM(G42:AJ42) -> 0
D43: STEARIN | F43: Kg | G43: 0 | H43: 0 | I43: 0 | J43: 0 | K43: 0 | L43: 0 | M43: 0 | N43: 0 | O43: 0 | P43: 0 | Q43: 0 | R43: 0 | S43: 0 | T43: 0 | U43: 0 | V43: 0 | W43: 0 | X43: 0 | AA43: 0 | AB43: 0 | AC43: 0 | AD43: 0 | AE43: 0 | AF43: 0 | AG43: 0 | AL43: =SUM(G43:AJ43) -> 0
D44: Fractionation OLEIN IV 58 ( Bulk ) | AL44: Olein IV 58 ( Bulk )
D45: RBDPO Consume | E45: 17143 | F45: Kg | G45: =G46+G47 -> 0 | H45: =H46+H47 -> 0 | I45: =I46+I47 -> 0 | J45: =J46+J47 -> 0 | L45: =L46+L47 -> 0 | M45: =M46+M47 -> 0 | N45: =N46+N47 -> 0 | O45: =O46+O47 -> 0 | Q45: =Q46+Q47 -> 0 | R45: =R46+R47 -> 0 | T45: =T46+T47 -> 0 | U45: =U46+U47 -> 0 | V45: =V46+V47 -> 0 | W45: =W46+W47 -> 0 | X45: 0 | Y45: =Y46+Y47 -> 0 | Z45: =Z46+Z47 -> 0 | AA45: =AA46+AA47 -> 0 | AB45: =AB46+AB47 -> 0 | AC45: =AC46+AC47 -> 0 | AD45: =AD46+AD47 -> 0 | AE45: =AE46+AE47 -> 0 | AF45: =AF46+AF47 -> 0 | ... AH45: =AH46+AH47 -> 0 | AJ45: =AJ46+AJ47 -> 0 | AL45: =SUM(G45:AJ45) -> 0
D46: OLEIN IV 58 | E46: 12000000 | F46: Kg | J46: =K46-L46 -> 0 | K46: =L46-M46 -> 0 | L46: =M46-N46 -> 0 | M46: =N46-O46 -> 0 | N46: =O46-P46 -> 0 | O46: =P46-Q46 -> 0 | Q46: 0 | R46: 0 | V46: 0 | W46: 0 | X46: 0 | Y46: 0 | Z46: 0 | AF46: 0 | AG46: 0 | AH46: 0 | AJ46: 0 | AL46: =SUM(G46:AJ46) -> 0
D47: STEARIN | E47: 514300 | F47: Kg | J47: =K47-L47 -> 0 | K47: =L47-M47 -> 0 | L47: =M47-N47 -> 0 | M47: =N47-O47 -> 0 | N47: =O47-P47 -> 0 | O47: =P47-Q47 -> 0 | Q47: 0 | R47: 0 | V47: 0 | W47: 0 | X47: 0 | Y47: 0 | Z47: 0 | AF47: 0 | AG47: 0 | AJ47: 0 | AL47: =SUM(G47:AJ47) -> 0
D48: Fractionation OLEIN IV 58 ( Retail ) | AL48: Olein IV 58 ( Bulk )
D49: CPO Consume | F49: Kg | AL49: =SUM(G49:AJ49) -> 0
D50: RBDPO Consume | E50: =E51+E52 -> 21429000 | F50: Kg | G50: =G51+G52 -> 0 | H50: =H51+H52 -> 0 | I50: =I51+I52 -> 0 | J50: =J51+J52 -> 0 | K50: 0 | L50: =L51+L52 -> 0 | M50: =M51+M52 -> 0 | N50: =N51+N52 -> 0 | O50: =O51+O52 -> 0 | P50: =P51+P52 -> 0 | Q50: =Q51+Q52 -> 0 | R50: =R51+R52 -> 0 | S50: 0 | T50: =T51+T52 -> 0 | U50: =U51+U52 -> 0 | V50: =V51+V52 -> 0 | W50: =W51+W52 -> 0 | X50: 0 | Y50: =Y51+Y52 -> 0 | Z50: =Z51+Z52 -> 0 | AA50: =AA51+AA52 -> 0 | AB50: =AB51+AB52 -> 0 | AC50: 0 | AD50: =AD51+AD52 -> 0 | AE50: =AE51+AE52 -> 0 | AF50: =AF51+AF52 -> 0 | AG50: =AG51+AG52 -> 0 | AH50: =AH51+AH52 -> 0 | AJ50: =AJ51+AJ52 -> 0 | AL50: =SUM(G50:AJ50) -> 0
D51: OLEIN IV 58 | E51: 15000000 | F51: Kg | G51: 0 | H51: 0 | I51: 0 | J51: 0 | K51: 0 | L51: 0 | M51: 0 | N51: 0 | O51: 0 | P51: 0 | Q51: 0 | R51: 0 | S51: 0 | T51: 0 | U51: 0 | V51: 0 | W51: 0 | X51: 0 | Y51: 0 | Z51: 0 | AA51: 0 | AB51: 0 | AC51: 0 | AD51: 0 | AE51: 0 | AF51: 0 | AG51: 0 | AH51: 0 | AL51: =SUM(G51:AJ51) -> 0
D52: STEARIN | E52: 6429000 | F52: Kg | G52: 0 | H52: 0 | I52: 0 | J52: 0 | K52: 0 | L52: 0 | M52: 0 | N52: 0 | O52: 0 | P52: 0 | Q52: 0 | R52: 0 | S52: 0 | T52: 0 | U52: 0 | V52: 0 | W52: 0 | X52: 0 | Y52: 0 | Z52: 0 | AA52: 0 | AB52: 0 | AC52: 0 | AD52: 0 | AE52: 0 | AF52: 0 | AG52: 0 | AH52: 0 | AL52: =SUM(G52:AJ52) -> 0
D53: Fractionation OLEIN IV 60 | AL53: Olein IV 60
D54: CPO Consume | F54: Kg | AL54: =SUM(G54:AJ54) -> 0
D55: RBDPO Brand Consume | E55: =E56+E57 -> 1333300 | F55: Kg | G55: =G56+G57 -> 0 | H55: =H56+H57 -> 0 | I55: =I56+I57 -> 0 | J55: =J56+J57 -> 0 | K55: 0 | L55: 0 | M55: =M56+M57 -> 0 | N55: =N56+N57 -> 0 | O55: =O56+O57 -> 0 | P55: =P56+P57 -> 0 | Q55: =Q56+Q57 -> 0 | S55: =S56+S57 -> 0 | T55: =T56+T57 -> 0 | U55: =U56+U57 -> 0 | V55: =V56+V57 -> 0 | W55: =W56+W57 -> 0 | X55: 0 | Y55: =Y56+Y57 -> 0 | Z55: =Z56+Z57 -> 0 | AA55: =AA56+AA57 -> 0 | AB55: =AB56+AB57 -> 0 | AC55: =AC56+AC57 -> 0 | AD55: =AD56+AD57 -> 0 | AE55: =AE56+AE57 -> 0 | AF55: =AF56+AF57 -> 0 | ... AH55: =AH56+AH57 -> 0 | AJ55: =AJ56+AJ57 -> 0 | AL55: =SUM(G55:AJ55) -> 0
D56: OLEIN IV 60 Salvaco | E56: 1250000 | F56: Kg | G56: 0 | H56: 0 | I56: 0 | J56: 0 | K56: 0 | L56: 0 | M56: 0 | N56: 0 | O56: 0 | P56: 0 | Q56: 0 | R56: 0 | T56: 0 | U56: 0 | V56: 0 | W56: 0 | X56: 0 | Y56: 0 | Z56: 0 | AA56: 0 | AB56: 0 | AD56: 0 | AE56: 0 | AF56: 0 | AH56: 0 | AL56: =SUM(G56:AJ56) -> 0
D57: SOFT STEARIN | E57: 83300 | F57: Kg | G57: 0 | H57: 0 | I57: 0 | J57: 0 | K57: 0 | L57: 0 | M57: 0 | N57: 0 | O57: 0 | P57: 0 | Q57: 0 | R57: 0 | T57: 0 | U57: 0 | V57: 0 | W57: 0 | X57: 0 | Y57: 0 | Z57: 0 | AA57: 0 | AB57: 0 | AD57: 0 | AE57: 0 | AF57: 0 | AH57: 0 | AL57: =SUM(G57:AJ57) -> 0
D58: Ratio Run RBDPO | F58: % | G58: 0 | H58: 0 | I58: 0 | J58: 0 | K58: 0 | L58: 0 | M58: 0 | N58: 0 | O58: 0 | P58: 0 | Q58: 0 | R58: 0 | S58: 0 | T58: 0 | U58: 0 | V58: 0 | W58: 0 | X58: 0 | Y58: 0 | Z58: 0 | AA58: 0 | AB58: 0 | AC58: 0 | AD58: 0 | AE58: 0 | AF58: 0 | AG58: 0 | AH58: 0 | AJ58: 0 | AL58: =SUM(G58:AJ58) -> 0
D59: YIELD | AL59: Yield
D60: RBDPO | E60: 94.2 | F60: % | G60: =(G20/(G9))*100 -> #DIV/0! | H60: =(H20/(H9))*100 -> #DIV/0! | I60: =(I20/(I9))*100 -> #DIV/0! | J60: =(J20/(J9))*100 -> #DIV/0! | K60: =(K20/(K9))*100 -> #DIV/0! | L60: =(L20/(L9))*100 -> #DIV/0! | M60: =(M20/(M9))*100 -> #DIV/0! | N60: =((N20+N19+N18)/(N9))*100 -> 101.47011 | O60: =((O20+O19+O18)/(O9))*100 -> 95.268161 | P60: =((P20+P19+P18)/(P9))*100 -> 94.51276 | Q60: =((Q20+Q19+Q18)/(Q9))*100 -> 94.664534 | R60: =((R20+R19+R18)/(R9))*100 -> 94.680628 | S60: =((S20+S19+S18)/(S9))*100 -> 94.165548 | T60: =((T20+T19+T18)/(T9))*100 -> 93.87542 | U60: =((U20+U19+U18)/(U9))*100 -> 94.45045 | ... W60: =((W20+W19+W18)/(W9))*100 -> 93.647054 | X60: 0 | Y60: =((Y20+Y19+Y18)/(Y9))*100 -> #DIV/0! | Z60: =((Z20+Z19+Z18)/(Z9))*100 -> #DIV/0! | AA60: =((AA20+AA19+AA18)/(AA9))*100 -> #DIV/0! | AB60: =((AB20+AB19+AB18)/(AB9))*100 -> #DIV/0! | AC60: =((AC20+AC19+AC18)/(AC9))*100 -> #DIV/0! | AD60: =((AD20+AD19+AD18)/(AD9))*100 -> #DIV/0! | AE60: =((AE20+AE19+AE18)/(AE9))*100 -> #DIV/0! | AF60: =((AF20+AF19+AF18)/(AF9))*100 -> #DIV/0! | ... AJ60: =((AJ20+AJ19+AJ18)/(AJ9))*100 -> #DIV/0! | AL60: =((AL20+AL19+AL18)/(AL9))*100 -> 94.787564
D61: PFAD | E61: 5 | F61: % | G61: =(G21/(G9))*100 -> #DIV/0! | H61: =(H21/(H9))*100 -> #DIV/0! | I61: =(I21/(I9))*100 -> #DIV/0! | J61: =(J21/(J9))*100 -> #DIV/0! | K61: =(K21/(K9))*100 -> #DIV/0! | L61: =(L21/(L9))*100 -> #DIV/0! | M61: =(M21/(M9))*100 -> #DIV/0! | N61: =(N21/(N9))*100 -> 1.7911425 | ... W61: =(W21/(W9))*100 -> 9.9760964 | X61: 0 | Y61: =(Y21/(Y9))*100 -> #DIV/0! | Z61: =(Z21/(Z9))*100 -> #DIV/0! | AA61: =(AA21/(AA9))*100 -> #DIV/0! | AB61: =(AB21/(AB9))*100 -> #DIV/0! | AC61: =(AC21/(AC9))*100 -> #DIV/0! | AD61: =(AD21/(AD9))*100 -> #DIV/0! | AE61: =(AE21/(AE9))*100 -> #DIV/0! | AF61: =(AF21/(AF9))*100 -> #DIV/0! | ... AJ61: =(AJ21/(AJ9))*100 -> #DIV/0! | AL61: =(AL21/(AL9))*100 -> 4.8633016
D62: Olein IV 56 | E62: 82 | F62: % | G62: =G33/(G33+G34)*100 -> #DIV/0! | H62: =H33/(H33+H34)*100 -> #DIV/0! | I62: =I33/(I33+I34)*100 -> #DIV/0! | J62: =J33/(J33+J34)*100 -> #DIV/0! | K62: #DIV/0! | L62: =L33/(L33+L34)*100 -> #DIV/0! | M62: =M33/(M33+M34)*100 -> #DIV/0! | N62: =N33/(N33+N34)*100 -> 100 | O62: =O33/(O33+O34)*100 -> 81.287589 | P62: =P33/(P33+P34)*100 -> 79.918388 | Q62: =Q33/(Q33+Q34)*100 -> 80.401632 | R62: =R33/(R33+R34)*100 -> 80.70876 | S62: =S33/(S33+S34)*100 -> 80.759474 | ... AJ62: =AJ33/(AJ33+AJ34)*100 -> #DIV/0! | AL62: =AL33/(AL33+AL34)*100 -> 80.514103
D63: Stearin | E63: 18 | F63: % | G63: =(G34/G32)*100 -> #DIV/0! | H63: =(H34/H32)*100 -> #DIV/0! | I63: =(I34/I32)*100 -> #DIV/0! | J63: =(J34/J32)*100 -> #DIV/0! | K63: #DIV/0! | L63: =(L34/L32)*100 -> #DIV/0! | M63: =(M34/M32)*100 -> #DIV/0! | N63: =(N34/N32)*100 -> 0 | O63: =(O34/O32)*100 -> 18.712411 | P63: =(P34/P32)*100 -> 20.081612 | Q63: =(Q34/Q32)*100 -> 19.598368 | R63: =(R34/R32)*100 -> 19.29124 | S63: =(S34/S32)*100 -> 19.240526 | ... AJ63: =(AJ34/AJ32)*100 -> #DIV/0! | AL63: =AL34/(AL33+AL34)*100 -> 19.485897
D64: Olein IV 57 ( Bulk ) | E64: 75 | G64: =(G37/G36)*100 -> #DIV/0! | H64: =(H37/H36)*100 -> #DIV/0! | I64: =(I37/I36)*100 -> #DIV/0! | J64: =(J37/J36)*100 -> #DIV/0! | K64: #DIV/0! | L64: =(L37/L36)*100 -> #DIV/0! | M64: =(M37/M36)*100 -> #DIV/0! | N64: =(N37/N36)*100 -> #DIV/0! | O64: =(O37/O36)*100 -> #DIV/0! | P64: =(P37/P36)*100 -> #DIV/0! | Q64: =(Q37/Q36)*100 -> #DIV/0! | R64: =(R37/R36)*100 -> #DIV/0! | S64: =(S37/S36)*100 -> #DIV/0! | ... AJ64: =(AJ37/AJ36)*100 -> #DIV/0! | AL64: =(AL42/AL41)*100 -> #DIV/0!
D65: Stearin | E65: 25 | G65: =(G38/G36)*100 -> #DIV/0! | H65: =(H38/H36)*100 -> #DIV/0! | I65: =(I38/I36)*100 -> #DIV/0! | J65: =(J38/J36)*100 -> #DIV/0! | K65: #DIV/0! | L65: =(L38/L36)*100 -> #DIV/0! | M65: =(M38/M36)*100 -> #DIV/0! | N65: =(N38/N36)*100 -> #DIV/0! | O65: =(O38/O36)*100 -> #DIV/0! | P65: =(P38/P36)*100 -> #DIV/0! | Q65: =(Q38/Q36)*100 -> #DIV/0! | R65: =(R38/R36)*100 -> #DIV/0! | S65: =(S38/S36)*100 -> #DIV/0! | ... AJ65: =(AJ38/AJ36)*100 -> #DIV/0! | AL65: =(AL43/AL41)*100 -> #DIV/0!
D66: Olein IV 57 ( Retail ) | E66: 75 | F66: % | G66: =G42/G41*100 -> #DIV/0! | H66: =H42/H41*100 -> #DIV/0! | I66: =I42/I41*100 -> #DIV/0! | J66: =J42/J41*100 -> #DIV/0! | K66: #DIV/0! | L66: =L42/L41*100 -> #DIV/0! | M66: =M42/M41*100 -> #DIV/0! | N66: =N42/N41*100 -> #DIV/0! | O66: =O42/O41*100 -> #DIV/0! | P66: =P42/P41*100 -> #DIV/0! | Q66: =Q42/Q41*100 -> #DIV/0! | R66: =R42/R41*100 -> #DIV/0! | S66: =S42/S41*100 -> #DIV/0! | ... AJ66: =AJ42/AJ41*100 -> #DIV/0! | AL66: =AL42/AL41*100 -> #DIV/0!
D67: Stearin | E67: 25 | F67: % | G67: =G43/G41*100 -> #DIV/0! | H67: =H43/H41*100 -> #DIV/0! | I67: =I43/I41*100 -> #DIV/0! | J67: =J43/J41*100 -> #DIV/0! | K67: #DIV/0! | L67: =L43/L41*100 -> #DIV/0! | M67: =M43/M41*100 -> #DIV/0! | N67: =N43/N41*100 -> #DIV/0! | O67: =O43/O41*100 -> #DIV/0! | P67: =P43/P41*100 -> #DIV/0! | Q67: =Q43/Q41*100 -> #DIV/0! | R67: =R43/R41*100 -> #DIV/0! | S67: =S43/S41*100 -> #DIV/0! | ... AJ67: =AJ43/AJ41*100 -> #DIV/0! | AL67: =AL43/AL41*100 -> #DIV/0!
D68: Olein IV 58 ( Bulk ) | E68: 70 | F68: % | G68: =G46/(G46+G47)*100 -> #DIV/0! | H68: =H46/(H46+H47)*100 -> #DIV/0! | I68: =I46/(I46+I47)*100 -> #DIV/0! | J68: =J46/(J46+J47)*100 -> #DIV/0! | K68: =K46/(K46+K47)*100 -> #DIV/0! | L68: =L46/(L46+L47)*100 -> #DIV/0! | M68: =M46/(M46+M47)*100 -> #DIV/0! | N68: =N46/(N46+N47)*100 -> #DIV/0! | ... AJ68: =AJ46/(AJ46+AJ47)*100 -> #DIV/0! | AL68: =AL46/(AL46+AL47)*100 -> #DIV/0!
D69: Stearin | E69: 30 | F69: % | G69: =G47/(G47+G46)*100 -> #DIV/0! | H69: =H47/(H47+H46)*100 -> #DIV/0! | I69: =I47/(I47+I46)*100 -> #DIV/0! | J69: =J47/(J47+J46)*100 -> #DIV/0! | K69: =K47/(K47+K46)*100 -> #DIV/0! | L69: =L47/(L47+L46)*100 -> #DIV/0! | M69: =M47/(M47+M46)*100 -> #DIV/0! | N69: =N47/(N47+N46)*100 -> #DIV/0! | ... AJ69: =AJ47/(AJ47+AJ46)*100 -> #DIV/0! | AL69: =AL47/AL45*100 -> #DIV/0!
D70: Olein IV 58 ( Retail ) | E70: 70 | F70: % | G70: =G51/(G51+G52)*100 -> #DIV/0! | H70: =H51/(H51+H52)*100 -> #DIV/0! | I70: =I51/(I51+I52)*100 -> #DIV/0! | J70: =J51/(J51+J52)*100 -> #DIV/0! | K70: #DIV/0! | L70: =L51/(L51+L52)*100 -> #DIV/0! | M70: =M51/(M51+M52)*100 -> #DIV/0! | N70: =N51/(N51+N52)*100 -> #DIV/0! | O70: =O51/(O51+O52)*100 -> #DIV/0! | P70: =P51/(P51+P52)*100 -> #DIV/0! | Q70: =Q51/(Q51+Q52)*100 -> #DIV/0! | R70: =R51/(R51+R52)*100 -> #DIV/0! | S70: =S51/(S51+S52)*100 -> #DIV/0! | ... AJ70: =AJ51/(AJ51+AJ52)*100 -> #DIV/0! | AL70: =AL51/(AL51+AL52)*100 -> #DIV/0!
D71: Stearin | E71: 30 | F71: % | G71: =G52/(G51+G52)*100 -> #DIV/0! | H71: =H52/(H51+H52)*100 -> #DIV/0! | I71: =I52/(I51+I52)*100 -> #DIV/0! | J71: =J52/(J51+J52)*100 -> #DIV/0! | K71: #DIV/0! | L71: =L52/(L51+L52)*100 -> #DIV/0! | M71: =M52/(M51+M52)*100 -> #DIV/0! | N71: =N52/(N51+N52)*100 -> #DIV/0! | O71: =O52/(O51+O52)*100 -> #DIV/0! | P71: =P52/(P51+P52)*100 -> #DIV/0! | Q71: =Q52/(Q51+Q52)*100 -> #DIV/0! | R71: =R52/(R51+R52)*100 -> #DIV/0! | S71: =S52/(S51+S52)*100 -> #DIV/0! | ... AJ71: =AJ52/(AJ51+AJ52)*100 -> #DIV/0! | AL71: =AL52/(AL51+AL52)*100 -> #DIV/0!
D72: Olein IV 60 | E72: 60 | F72: % | G72: =G56/(G56+G57)*100 -> #DIV/0! | H72: =H56/(H56+H57)*100 -> #DIV/0! | I72: =I56/(I56+I57)*100 -> #DIV/0! | J72: =J56/(J56+J57)*100 -> #DIV/0! | K72: =K56/(K56+K57)*100 -> #DIV/0! | L72: =L56/(L56+L57)*100 -> #DIV/0! | M72: =M56/(M56+M57)*100 -> #DIV/0! | N72: =N56/(N56+N57)*100 -> #DIV/0! | ... AJ72: =AJ56/(AJ56+AJ57)*100 -> #DIV/0! | AL72: =AL56/(AL55+AL51)*100 -> #DIV/0!
D73: Soft Stearin | E73: 40 | F73: % | G73: =G57/G55*100 -> #DIV/0! | H73: =H57/H55*100 -> #DIV/0! | I73: =I57/I55*100 -> #DIV/0! | J73: =J57/J55*100 -> #DIV/0! | K73: #DIV/0! | L73: =L57/L55*100 -> #DIV/0! | M73: =M57/M55*100 -> #DIV/0! | N73: =N57/N55*100 -> #DIV/0! | O73: =O57/O55*100 -> #DIV/0! | P73: =P57/P55*100 -> #DIV/0! | Q73: =Q57/Q55*100 -> #DIV/0! | R73: =R57/R55*100 -> #DIV/0! | S73: =S57/S55*100 -> #DIV/0! | ... AJ73: =AJ57/AJ55*100 -> #DIV/0! | AL73: =AL57/AL55*100 -> #DIV/0!
C74: 2 | D74: CHEMICAL CONSUMABLE | AL74: Chemical | AV74: =AV68-AV69-AV70-AV71-AV72-AV73 -> 0
D75: Bleaching Earth (BE) to Poram Spec | E75: 9 | F75: Kg | G75: 0 | H75: 0 | I75: 0 | J75: 0 | K75: 0 | L75: 0 | M75: 0 | N75: 7810 | O75: 16300 | P75: 19120 | Q75: 22910 | R75: 18560 | S75: 17082 | T75: 14265 | U75: 15058 | V75: 18296 | W75: 3672 | AL75: =SUM(G75:AJ75) -> 153073
F76: % | G76: =G75/(G11)*100 -> #DIV/0! | H76: =H75/(H11)*100 -> #DIV/0! | I76: =I75/(I11)*100 -> #DIV/0! | J76: =J75/(J11)*100 -> #DIV/0! | K76: =K75/(K11)*100 -> #DIV/0! | L76: =L75/(L11)*100 -> #DIV/0! | M76: =M75/(M11)*100 -> #DIV/0! | N76: =N75/(N11)*1000 -> 10.570367 | O76: =O75/(O11)*1000 -> 7.3050569 | P76: =P75/(P11)*1000 -> 8.744169 | Q76: =Q75/(Q11)*1000 -> 9.1153205 | R76: =R75/(R11)*1000 -> 8.0707232 | S76: =S75/(S11)*1000 -> 8.5928449 | T76: =T75/(T11)*1000 -> 8.9093773 | U76: =U75/(U11)*1000 -> 7.4908007 | V76: =V75/(V11)*1000 -> 9.5172008 | W76: =W75/(W11)*100 -> 1.1414042 | X76: =X75/(X11)*100 -> #DIV/0! | Y76: =Y75/(Y11)*100 -> #DIV/0! | Z76: =Z75/(Z11)*100 -> #DIV/0! | AA76: =AA75/(AA11)*100 -> #DIV/0! | AB76: =AB75/(AB11)*100 -> #DIV/0! | AC76: =AC75/(AC11)*100 -> #DIV/0! | AD76: =AD75/(AD11)*100 -> #DIV/0! | ... AJ76: =AJ75/(AJ11)*100 -> #DIV/0! | AL76: =AL75/(AL11)*1000 -> 8.5932405
D77: TK 630 A ( TRANSFER ) | E77: 40000 | F77: Kg | V77: 0 | W77: 0 | X77: 0 | Y77: 0 | AA77: 0 | AB77: 0 | AC77: 0 | AD77: 0 | AE77: 0 | AF77: 0 | AG77: 0 | AL77: =SUM(G77:AJ77) -> 0
D79: TK 630 B ( TRANSFER ) | E79: 40000 | F79: Kg | V79: 0 | W79: 0 | X79: 0 | Y79: 0 | Z79: 0 | AA79: 0 | AB79: 0 | AC79: 0 | AD79: 0 | AE79: 0 | AF79: 0 | AG79: 0 | AL79: =SUM(G79:AJ79) -> 0
D81: Bleaching Earth (BE) to Branded Spec | E81: 18 | F81: Kg | G81: 0 | H81: 0 | I81: 0 | J81: 0 | K81: 0 | L81: 0 | M81: 0 | N81: 0 | O81: 0 | P81: 0 | Q81: 0 | R81: 0 | S81: 0 | T81: 0 | U81: 0 | V81: 0 | W81: 0 | X81: 0 | Y81: 0 | Z81: 0 | AA81: 0 | AB81: 0 | AC81: 0 | AD81: 0 | AE81: 0 | AF81: 0 | AG81: 0 | AH81: 0 | AJ81: 0 | AL81: =SUM(G81:AJ81) -> 0
F82: % | G82: =G81/(G12)*100 -> #DIV/0! | H82: =H81/(H12)*100 -> #DIV/0! | I82: =I81/(I12)*100 -> #DIV/0! | J82: =J81/(J12)*100 -> #DIV/0! | K82: #DIV/0! | L82: =L81/(L12)*100 -> #DIV/0! | M82: =M81/(M12)*100 -> #DIV/0! | N82: =N81/(N12)*100 -> #DIV/0! | O82: =O81/(O12)*100 -> #DIV/0! | P82: =P81/(P12)*100 -> #DIV/0! | Q82: =Q81/(Q12)*100 -> #DIV/0! | R82: =R81/(R12)*100 -> #DIV/0! | S82: #DIV/0! | T82: =T81/(T12)*100 -> #DIV/0! | U82: =U81/(U12)*100 -> #DIV/0! | V82: =V81/(V12)*100 -> #DIV/0! | W82: =W81/(W12)*100 -> #DIV/0! | X82: #DIV/0! | Y82: =Y81/(Y12)*100 -> #DIV/0! | Z82: =Z81/(Z12)*100 -> #DIV/0! | AA82: =AA81/(AA12)*100 -> #DIV/0! | AB82: =AB81/(AB12)*100 -> #DIV/0! | AC82: #DIV/0! | AD82: =AD81/(AD12)*100 -> #DIV/0! | AE82: =AE81/(AE12)*100 -> #DIV/0! | AF82: =AF81/(AF12)*100 -> #DIV/0! | AG82: =AG81/(AG12)*100 -> #DIV/0! | AH82: =AH81/(AH12)*100 -> #DIV/0! | AI82: =AI81/(AI12)*100 -> #DIV/0! | AJ82: =AJ81/(AJ12)*100 -> #DIV/0! | AL82: =AL81/(AL12)*100 -> #DIV/0!
D83: Phosporic Acid (PA) | E83: 0.6 | F83: Kg | G83: 0 | H83: 0 | I83: 0 | J83: 0 | K83: 0 | L83: 0 | M83: 0 | N83: 365.72 | O83: 1043.24 | P83: 1120.32 | Q83: 1230.87 | R83: 1150.32 | S83: 955.82 | T83: 802.2 | U83: 985.95 | V83: 937.04 | W83: 201.76 | AL83: =SUM(G83:AJ83) -> 8793.24
F84: % | G84: =G83/(G9)*100 -> #DIV/0! | H84: =H83/(H9)*100 -> #DIV/0! | I84: =I83/(I9)*100 -> #DIV/0! | J84: =J83/(J9)*1000 -> #DIV/0! | K84: =K83/(K9)*1000 -> #DIV/0! | L84: =L83/(L9)*100 -> #DIV/0! | M84: =M83/(M9)*100 -> #DIV/0! | N84: =N83/(N9)*100 -> 0.049498009 | O84: =O83/(O9)*100 -> 0.046754157 | P84: =P83/(P9)*100 -> 0.051235708 | Q84: =Q83/(Q9)*1000 -> 0.48973263 | R84: =R83/(R9)*1000 -> 0.5002109 | S84: =S83/(S9)*1000 -> 0.48081097 | T84: =T83/(T9)*1000 -> 0.50102366 | U84: =U83/(U9)*1000 -> 0.49047383 | V84: =V83/(V9)*1000 -> 0.48742883 | W84: =W83/(W9)*1000 -> 0.62715062 | X84: =X83/(X9)*1000 -> #VALUE! | ... AF84: =AF83/(AF9)*1000 -> #DIV/0! | AG84: =AG83/(AG9)*100 -> #DIV/0! | AH84: =AH83/(AH9)*100 -> #DIV/0! | AI84: =AI83/(AI9)*100 -> #DIV/0! | AJ84: =AJ83/(AJ9)*100 -> #DIV/0! | AL84: =AL83/AL9*1000 -> 0.49363654
C85: 3 | D85: OIL LOSSES | E85: 0.7 | F85: % | G85: =((SUM(G20:G21))-(SUM(G9)))/(SUM(G9))*100 -> #DIV/0! | H85: =((SUM(H20:H21))-(SUM(H9)))/(SUM(H9))*100 -> #DIV/0! | I85: =((SUM(I20:I21))-(SUM(I9)))/(SUM(I9))*100 -> #DIV/0! | J85: =((SUM(J20:J21))-(SUM(J9)))/(SUM(J9))*100 -> #DIV/0! | K85: =((SUM(K20:K21))-(SUM(K9)))/(SUM(K9))*100 -> #DIV/0! | L85: =((SUM(L20:L21))-(SUM(L9)))/(SUM(L9))*100 -> #DIV/0! | M85: =((SUM(M20:M21))-(SUM(M9)))/(SUM(M9))*100 -> #DIV/0! | N85: =((SUM(N18:N21))-(SUM(N9)))/(SUM(N9))*100 -> 3.2612491 | O85: =((SUM(O19:O21))-(SUM(O9)))/(SUM(O9))*100 -> -0.88122291 | P85: =((SUM(P18:P21))-(SUM(P9)))/(SUM(P9))*100 -> -0.41580536 | Q85: =((SUM(Q18:Q21))-(SUM(Q9)))/(SUM(Q9))*100 -> -0.58065905 | R85: =((SUM(R18:R21))-(SUM(R9)))/(SUM(R9))*100 -> -0.79093957 | S85: =((SUM(S18:S21))-(SUM(S9)))/(SUM(S9))*100 -> -0.95476055 | T85: =((SUM(T18:T21))-(SUM(T9)))/(SUM(T9))*100 -> -0.83147943 | U85: =((SUM(U18:U21))-(SUM(U9)))/(SUM(U9))*100 -> -0.74709021 | V85: =((SUM(V18:V21))-(SUM(V9)))/(SUM(V9))*100 -> -0.73662593 | W85: =((SUM(W18:W21))-(SUM(W9)))/(SUM(W9))*100 -> 3.6231501 | X85: =((SUM(X20:X21))-(SUM(X9)))/(SUM(X9))*100 -> #DIV/0! | Y85: =((SUM(Y20:Y21))-(SUM(Y9)))/(SUM(Y9))*100 -> #DIV/0! | Z85: =((SUM(Z20:Z21))-(SUM(Z9)))/(SUM(Z9))*100 -> #DIV/0! | AA85: =((SUM(AA20:AA21))-(SUM(AA9)))/(SUM(AA9))*100 -> #DIV/0! | AB85: =((SUM(AB20:AB21))-(SUM(AB9)))/(SUM(AB9))*100 -> #DIV/0! | AC85: =((SUM(AC20:AC21))-(SUM(AC9)))/(SUM(AC9))*100 -> #DIV/0! | AD85: =((SUM(AD20:AD21))-(SUM(AD9)))/(SUM(AD9))*100 -> #DIV/0! | AE85: =((SUM(AE20:AE21))-(SUM(AE9)))/(SUM(AE9))*100 -> #DIV/0! | ... AJ85: =((SUM(AJ20:AJ21))-(SUM(AJ9)))/(SUM(AJ9))*100 -> #DIV/0! | AL85: =((SUM(AL18:AL21))-(SUM(AL9)))/(SUM(AL9))*100 -> -0.3491346
F86: Kg | G86: =G85%*G9 -> #DIV/0! | H86: =H85%*H9 -> #DIV/0! | I86: =I85%*I9 -> #DIV/0! | J86: =J85%*J9 -> #DIV/0! | K86: =K85%*K9 -> #DIV/0! | L86: =L85%*L9 -> #DIV/0! | M86: =M85%*M9 -> #DIV/0! | N86: =N85%*N9 -> 24096 | ... AJ86: =AJ85%*AJ9 -> #DIV/0! | AL86: =AL85%*AL9 -> -62192
D87: % Oil Content | E87: 22 | F87: % | J87: 0 | K87: 0 | L87: 0 | M87: 0 | N87: 22.87 | O87: 21.13 | P87: 20.78 | Q87: 21.01 | R87: 20.91 | S87: 20.39 | T87: 20.33 | U87: 20.69 | V87: 20.77 | W87: 21.26 | Z87: 0 | AE87: 0 | AF87: 0 | AL87: =AVERAGE(N87:X87) -> 21.014
D88: Spent Bleaching Earth | F88: Kg | N88: =SUM(N75,N81)+(N87%*SUM(N75,N81))/N6 -> 9596.147 | O88: =SUM(O75,O81)+(O87%*SUM(O75,O81))/O6 -> 19744.19 | P88: =SUM(P75,P81)+(P87%*SUM(P75,P81))/P6 -> 23093.136 | Q88: =SUM(Q75,Q81)+(Q87%*SUM(Q75,Q81)) -> 27723.391 | R88: =SUM(R75,R81)+(R87%*SUM(R75,R81)) -> 22440.896 | S88: =SUM(S75,S81)+(S87%*SUM(S75,S81)) -> 20565.02 | T88: =SUM(T75,T81)+(T87%*SUM(T75,T81)) -> 17165.074 | U88: =SUM(U75,U81)+(U87%*SUM(U75,U81)) -> 18173.5 | V88: =SUM(V75,V81)+(V87%*SUM(V75,V81)) -> 22096.079 | W88: =SUM(W75,W81)+(W87%*SUM(W75,W81)) -> 4452.6672 | X88: =SUM(X75,X81)+(X87%*SUM(X75,X81)) -> 0 | ... AB88: =SUM(AB75,AB81)+(AB87%*SUM(AB75,AB81)) -> 0 | AD88: =SUM(AD75,AD81)+(AD87%*SUM(AD75,AD81)) -> 0 | AE88: =SUM(AE75,AE81)+(AE87%*SUM(AE75,AE81)) -> 0 | AF88: =SUM(AF75,AF81)+(AF87%*SUM(AF75,AF81)) -> 0 | AJ88: =SUM(AJ75,AJ81)+(AJ87%*SUM(AJ75,AJ81)) -> 0 | AL88: =SUM(AL75,AL81)+(AL87%*SUM(AL75,AL81))/AL6 -> 156289.68
C89: 4 | D89: PACKAGING (Brand Salvaco) | AL89: Packaging
D90: Olein IV 60 Received | F90: Kg | AL90: 0
D91: Olein IV 60 Consume | F91: Kg | AL91: 0
D92: - finished product | F92: Kg | G92: 0 | H92: 0 | I92: 0 | J92: 0 | K92: 0 | L92: 0 | M92: 0 | N92: 0 | O92: 0 | P92: 0 | Q92: 0 | R92: 0 | S92: 0 | T92: 0 | U92: 0 | V92: 0 | W92: 0 | X92: 0 | Y92: 0 | Z92: 0 | AA92: 0 | AB92: 0 | AC92: 0 | AD92: 0 | AE92: 0 | AF92: 0 | AG92: 0 | AH92: 0 | AJ92: 0 | AL92: 0
D93: - sample | F93: Kg | G93: 0 | H93: 0 | I93: 0 | J93: 0 | K93: 0 | L93: 0 | M93: 0 | N93: 0 | O93: 0 | P93: 0 | Q93: 0 | R93: 0 | S93: 0 | T93: 0 | U93: 0 | V93: 0 | W93: 0 | X93: 0 | Y93: 0 | Z93: 0 | AA93: 0 | AB93: 0 | AC93: 0 | AD93: 0 | AE93: 0 | AF93: 0 | AG93: 0 | AH93: 0 | AJ93: 0 | AL93: 0
D94: - remelt, flushing, downgrade | F94: Kg | G94: 0 | H94: 0 | I94: 0 | J94: 0 | K94: 0 | L94: 0 | M94: 0 | N94: 0 | O94: 0 | P94: 0 | Q94: 0 | R94: 0 | S94: 0 | T94: 0 | U94: 0 | V94: 0 | W94: 0 | X94: 0 | Y94: 0 | Z94: 0 | AA94: 0 | AB94: 0 | AC94: 0 | AD94: 0 | AE94: 0 | AF94: 0 | AG94: 0 | AH94: 0 | AJ94: 0 | AL94: 0
D95: Carton | AL95: Carton
D96: Salvaco 1 Liter | F96: Box | AL96: 0
D97: Salvaco 2 Liter | F97: Box | AL97: 0 | AV97: 37542
D98: Pouch | AL98: Pouch
D99: Salvaco 1 Liter | F99: Pouch | G99: 0 | H99: 0 | I99: 0 | J99: 0 | K99: 0 | L99: 0 | M99: 0 | N99: 0 | O99: 0 | P99: 0 | Q99: 0 | R99: 0 | S99: 0 | T99: 0 | U99: 0 | V99: 0 | W99: 0 | X99: 0 | Y99: 0 | Z99: 0 | AA99: 0 | AB99: 0 | AC99: 0 | AD99: 0 | AE99: 0 | AF99: 0 | AG99: 0 | AH99: 0 | AJ99: 0 | AL99: 0
D100: Salvaco 2 Liter | F100: Pouch | G100: 0 | H100: 0 | I100: 0 | J100: 0 | K100: 0 | L100: 0 | M100: 0 | N100: 0 | O100: 0 | P100: 0 | Q100: 0 | R100: 0 | S100: 0 | T100: 0 | U100: 0 | V100: 0 | W100: 0 | X100: 0 | Y100: 0 | Z100: 0 | AA100: 0 | AB100: 0 | AC100: 0 | AD100: 0 | AE100: 0 | AF100: 0 | AG100: 0 | AH100: 0 | AJ100: 0 | AL100: 0
D101: Consumable Vit. A | F101: gram | G101: 0 | H101: 0 | I101: 0 | J101: 0 | K101: 0 | L101: 0 | M101: 0 | N101: 0 | O101: 0 | P101: 0 | Q101: 0 | R101: 0 | S101: 0 | T101: 0 | U101: 0 | V101: 0 | W101: 0 | X101: 0 | Y101: 0 | Z101: 0 | AA101: 0 | AB101: 0 | AC101: 0 | AD101: 0 | AE101: 0 | AF101: 0 | AG101: 0 | AH101: 0 | AJ101: 0 | AL101: 0
D102: Consumable Packing Tape | F102: Roll | G102: 0 | H102: 0 | I102: 0 | J102: 0 | K102: 0 | L102: 0 | M102: 0 | N102: 0 | O102: 0 | P102: 0 | Q102: 0 | R102: 0 | S102: 0 | T102: 0 | U102: 0 | V102: 0 | W102: 0 | X102: 0 | Y102: 0 | Z102: 0 | AA102: 0 | AB102: 0 | AC102: 0 | AD102: 0 | AE102: 0 | AF102: 0 | AG102: 0 | AH102: 0 | AJ102: 0 | AL102: 0
...

Sheet Peformance test Fract 1
C1: PT.INDUSTRI NABATI LESTARI
C2: Pabrik Minyak Goreng ( PMG 2 )
C3: Kantor Pusat: Komp. KEK Sei Mangkei, Kav.2-3, Kec. Bosar Maligas, Kab. Simalungun, Sumatera Utara, 21184
C4: ACTUAL PEFORMANCE / CONSUMPT REPORT FRAKSINASI PLANT | H4: Trial | I4: 1
H5: Start / Date / Time | I5: 17/12/24 ( 07.00 Wib )
H6: Finish / Date / Time | I6: 17/12/24 ( 07.00 Wib )
A8: No | B8: ITEM | C8: Kontrak LIPICO | D8: UOM | E8: TOTALIZER
A10: 1 | B10: PRODUCTION | C10: IV 56 | D10: 24 jam | E10: BEFORE | F10: AFTER | G10: TOTAL | H10: YIELD % | I10: STATUS/REMAKS
B11: Fraksinasi
B12: Running Days
B13: Incoming CPO
B14: Ratio Run CPO
B15: RBDPO Consume Total | C15: 2500 | D15: TPD | E15: 8982.8 | F15: 11717.8 | G15: =F15-E15 -> 2735 | H15: =G15/25000*10 -> 1.094 | I15: OK
B16: Avg Daily Consump CPO ( MTD )
B17: CPO Consume Poram | C17: 29045000
B18: CPO Consume Brand | C18: 7314000 | E18: =E49+E58+E63 -> 0
B19: QUALITY
B20: - FFA | C20: 0.1 | D20: % Max | H20: 0.063
B21: - Moist & Impurities | C21: 0.1 | D21: % Max | H21: 0.05
B22: - IV | C22: 52 - 52,5 | H22: 51.8
B23: - LC | H23: 2,6/20
B24: - Temp | C24: 68 | D24: ˚C Min | H24: 65
B25: TANK | H25: 108/109
B26: Product
B27: OLEIN IV 56 | C27: =C15*84% -> 2100 | D27: TPD | E27: 6537.1 | F27: 8213 | G27: =F27-E27 -> 1675.9 | H27: =G27/(G27+G32) -> 0.82838219 | I27: OK
B28: QUALITY
B29: - IV | C29: 56 | D29: Min
B30: - LC
B31: - Cloud Point ( metter ) | C31: 10 | D31: ˚C Max
B32: STEARIN | C32: =C15*16% -> 400 | E32: 2268.1 | F32: 2615.3 | G32: =F32-E32 -> 347.2 | H32: =G32/(G32+G27) -> 0.17161781 | I32: OK
B33: Fractionation
B34: Running Days
B35: Filling Langsung CR Fr Refinery | E35: 0
B36: Total Filling Crystalizer ( Feed ) | E36: 392100
B37: Avg Daily Consump RPO ( MTD )
B38: Total Proses RBDPO | E38: =SUM(E41,E45,E50,E54,E64) -> 0
B39: Sisa Filling Crystalizer | E39: =E36-E38 -> 392100
B40: Fractionation OLEIN IV 56
B41: RBDPO Consume | E41: =E42+E43 -> 0
B42: OLEIN IV 56 | E42: 0
B43: STEARIN | E43: 0
B44: Fractionation OLEIN IV 57 ( Bulk )
B45: RBDPO Consume | E45: =E46+E47 -> 0
B46: OLEIN IV 57 | E46: 0
B47: STEARIN | E47: 0
B48: Fractionation OLEIN IV 57 ( Retail )
B49: CPO Consume
B50: RBDPO Brand Consume | E50: =E51+E52 -> 0
B51: OLEIN IV 57 Low Color | E51: 0
B52: STEARIN | E52: 0
B53: Fractionation OLEIN IV 58 ( Bulk )
B54: RBDPO Consume | C54: =C55+C56 -> 21429000 | E54: =E55+E56 -> 0
B55: OLEIN IV 58 | C55: 15000000
B56: STEARIN | C56: 6429000
B57: Fractionation OLEIN IV 58 ( Retail )
B58: CPO Consume
B59: RBDPO Consume | C59: =C60+C61 -> 21429000 | E59: =E60+E61 -> 0
B60: OLEIN IV 58 | C60: 15000000 | E60: 0
B61: STEARIN | C61: 6429000 | E61: 0
B62: Fractionation OLEIN IV 60
B63: CPO Consume
B64: RBDPO Brand Consume | E64: =E66+E67 -> 0
B65: OLEIN IV 60 Bulk | E65: 0
B66: OLEIN IV 60 Salvaco | E66: 0
B67: SOFT STEARIN | E67: 0
B68: Ratio Run RBDPO | E68: 0
B69: YIELD
B70: RBDPO | C70: 94.2 | E70: =(#REF!/(E15))*100 -> #REF!
B71: PFAD | C71: 5 | E71: =(E32/(E15))*100 -> 25.249365
B72: Olein IV 56 | C72: 82 | E72: =E42/(E42+E43)*100 -> #DIV/0!
B73: Stearin | C73: 18 | E73: =(E43/E41)*100 -> #DIV/0!
B74: Olein IV 57 ( Bulk ) | C74: 75 | E74: =(E46/E45)*100 -> #DIV/0!
B75: Stearin | C75: 25 | E75: =(E47/E45)*100 -> #DIV/0!
B76: Olein IV 57 ( Retail ) | C76: 75 | E76: =E51/E50*100 -> #DIV/0!
B77: Stearin | C77: 25 | E77: =E52/E50*100 -> #DIV/0!
B78: Olein IV 58 ( Bulk ) | C78: 70 | E78: =E55/(E55+E56)*100 -> #DIV/0!
B79: Stearin | C79: 30 | E79: =E56/(E56+E55)*100 -> #DIV/0!
B80: Olein IV 58 ( Retail ) | C80: 70 | E80: =E60/(E60+E61)*100 -> #DIV/0!
B81: Stearin | C81: 30 | E81: =E61/(E60+E61)*100 -> #DIV/0!
B82: Olein IV 60 | C82: 60 | E82: =E65/E64*100 -> #DIV/0!
B83: Soft Stearin | C83: 40 | E83: =E67/E64*100 -> #DIV/0!
B84: QUALITY
B85: - IV | C85: 32 | D85: Max
B86: - Melting Point | C86: 52-52,5 | D86: ˚C Min
A87: 2 | B87: STEAM CONSUMPTION | E87: BEFORE | F87: AFTER | G87: TOTAL | H87: Kg/Ton RBDPO
B88: Incoming | C88: 408000 | D88: Kg/Day | G88: 183211
B89: Distribution to
B90: fraksinasi | C90: 87.5 | D90: Kg/Day | E90: 308052 | F90: 366933 | G90: =F90-E90 -> 58881 | H90: =G90/G15 -> 21.528702 | I90: OK
C91: =C90/2000 -> 0.04375
C92: =C90/2.5 -> 35 | D92: Kg/ton
B93: Fractionation | C93: 122000
B94: Others ( Tank farm & spurging OSBL ) | C94: 106000 | D94: Kg/Day
B95: Total | C95: 408000 | D95: Kg/Day | G95: =SUM(G90,G93,G94) -> 58881
A96: 3 | B96: WATER CONSUMPTION | E96: BEFORE | F96: AFTER | G96: TOTAL | H96: M³/Ton RBDPO
B97: Incoming from Kinra | C97: 1100 | D97: M³/Day | G97: 818
B98: Outgoing
B99: Softener Product (to Fraksinasi ) | C99: 0.13 | D99: M³/Day | E99: 58 | F99: 106 | G99: =F99-E99 -> 48 | H99: =G99/G15 -> 0.017550274
B100: Softener Product (to Fractionation) | C100: 179.63
C101: =C99/2500 -> 5.2e-05 | D101: M³/ton
B102: RO Product | C102: 491.59 | D102: M³/Day | G102: 304
...

Sheet Peformance Test REFINERY 1
C1: PT.INDUSTRI NABATI LESTARI
C2: Pabrik Minyak Goreng ( PMG 2 )
C3: Kantor Pusat: Komp. KEK Sei Mangkei, Kav.2-3, Kec. Bosar Maligas, Kab. Simalungun, Sumatera Utara, 21184
C4: ACTUAL PEFORMANCE / CONSUMPT REPORT REFINERY PLANT | H4: Peformance | I4: 1
H5: Start / Date / Time | I5: 17/12/24 ( 21.00 Wib )
H6: Finish / Date / Time | I6: 18/12/24 ( 21.00 Wib )
A7: No | B7: ITEM | C7: Kontrak LIPICO | D7: UOM | E7: TOTALIZER
A9: 1 | B9: PRODUCTION | E9: BEFORE | F9: AFTER | G9: TOTAL | H9: Yield ( % ) | I9: STATUS/REMAKS
B10: Refinery
B11: Running Days
B12: Incoming CPO
B13: Ratio Run CPO
B14: CPO Consume Total | C14: 2500 | D14: TPD | E14: 13533.82 | F14: 16053.42 | G14: =F14-E14 -> 2519.6 | I14: OK
B15: Avg Daily Consump CPO ( MTD )
B16: CPO Consume Poram | C16: 29045000
B17: CPO Consume Brand | C17: 7314000 | E17: =E53+E62+E67 -> 0
B18: - FFA | C18: 5 | D18: % | G18: 4
B19: - Moist & Impurities | C19: 0.5 | D19: % | G19: 0.41
B20: - DOBI | C20: 2.2 | D20: Min | G20: 2.42
B21: - TOTOX 2PV + AV | C21: 12 | D21: Max | G21: N/A
B22: - FE Content | C22: < 5 | D22: ppm | G22: N/A
B23: - PV | C23: < 4 | D23: Meg/kg | G23: N/A
B24: - Phosporus Max | C24: 25 | D24: ppm | G24: N/A
B25: TANK / TEMP | C25: 50 | D25: ˚C | G25: 50
B26: Product
B27: RBDPO | C27: =C14*94.2% -> 2355 | D27: TPD | E27: 12357.54 | F27: 14705.95 | G27: =F27-E27 -> 2348.41 | H27: =G27/G14 -> 0.93205668
B28: - FFA | C28: 0.05 | D28: % | G28: 0.06
B29: - Moist & Impurities | C29: 0.03 | D29: % | G29: 0.05
B30: - Peroxide value | D30: Nil | G30: -
B31: - Phosporous max | C31: 2 | D31: ppm | G31: N/A
B32: - LC | C32: 2.5 | D32: % | G32: 2.5
B33: - Aom stability min ( hr ) | C33: 60 | D33: min ( hr ) | G33: N/A
B34: - teste & Odor | C34: bland/Odorless | G34: N/A
B35: - temp max ( C ) | C35: 50 | D35: max˚C | G35: 50
B36: PFAD | C36: =C14*5% -> 125 | D36: TPD | E36: 572.71 | F36: 675.39 | G36: =F36-E36 -> 102.68 | H36: =G36/G14 -> 0.0407525
B37: Fractionation
B38: Running Days
B39: Filling Langsung CR Fr Refinery | E39: 0
B40: Total Filling Crystalizer ( Feed ) | E40: 392100
B41: Avg Daily Consump RPO ( MTD )
B42: Total Proses RBDPO | E42: =SUM(E45,E49,E54,E58,E68) -> 0
B43: Sisa Filling Crystalizer | E43: =E40-E42 -> 392100
B44: Fractionation OLEIN IV 56
B45: RBDPO Consume | E45: =E46+E47 -> 0
B46: OLEIN IV 56 | E46: 0
B47: STEARIN | E47: 0
B48: Fractionation OLEIN IV 57 ( Bulk )
B49: RBDPO Consume | E49: =E50+E51 -> 0
B50: OLEIN IV 57 | E50: 0
B51: STEARIN | E51: 0
B52: Fractionation OLEIN IV 57 ( Retail )
B53: CPO Consume
B54: RBDPO Brand Consume | E54: =E55+E56 -> 0
B55: OLEIN IV 57 Low Color | E55: 0
B56: STEARIN | E56: 0
B57: Fractionation OLEIN IV 58 ( Bulk )
B58: RBDPO Consume | C58: =C59+C60 -> 21429000 | E58: =E59+E60 -> 0
B59: OLEIN IV 58 | C59: 15000000
B60: STEARIN | C60: 6429000
B61: Fractionation OLEIN IV 58 ( Retail )
B62: CPO Consume
B63: RBDPO Consume | C63: =C64+C65 -> 21429000 | E63: =E64+E65 -> 0
B64: OLEIN IV 58 | C64: 15000000 | E64: 0
B65: STEARIN | C65: 6429000 | E65: 0
B66: Fractionation OLEIN IV 60
B67: CPO Consume
B68: RBDPO Brand Consume | E68: =E70+E71 -> 0
B69: OLEIN IV 60 Bulk | E69: 0
B70: OLEIN IV 60 Salvaco | E70: 0
B71: SOFT STEARIN | E71: 0
B72: Ratio Run RBDPO | E72: 0
B73: YIELD
B74: RBDPO | C74: 94.2 | E74: =(E27/(E14))*100 -> 91.308588
B75: PFAD | C75: 5 | E75: =(E36/(E14))*100 -> 4.2316951
B76: Olein IV 56 | C76: 82 | E76: =E46/(E46+E47)*100 -> #DIV/0!
B77: Stearin | C77: 18 | E77: =(E47/E45)*100 -> #DIV/0!
B78: Olein IV 57 ( Bulk ) | C78: 75 | E78: =(E50/E49)*100 -> #DIV/0!
B79: Stearin | C79: 25 | E79: =(E51/E49)*100 -> #DIV/0!
B80: Olein IV 57 ( Retail ) | C80: 75 | E80: =E55/E54*100 -> #DIV/0!
B81: Stearin | C81: 25 | E81: =E56/E54*100 -> #DIV/0!
B82: Olein IV 58 ( Bulk ) | C82: 70 | E82: =E59/(E59+E60)*100 -> #DIV/0!
B83: Stearin | C83: 30 | E83: =E60/(E60+E59)*100 -> #DIV/0!
B84: Olein IV 58 ( Retail ) | C84: 70 | E84: =E64/(E64+E65)*100 -> #DIV/0!
B85: Stearin | C85: 30 | E85: =E65/(E64+E65)*100 -> #DIV/0!
B86: Olein IV 60 | C86: 60 | E86: =E69/E68*100 -> #DIV/0!
B87: Soft Stearin | C87: 40 | E87: =E71/E68*100 -> #DIV/0!
B88: - FFA | C88: ~93 | D88: % | G88: 90.21
B89: - Moist & Impurities | C89: 0.5 | D89: % | G89: 0.33
A90: 2 | B90: CHEMICAL CONSUMABLE | E90: BEFORE | F90: AFTER | G90: TOTAL | H90: ( % )
B91: Bleaching Earth (BE) to Poram Spec | C91: 9 | D91: kg | E91: 122737 | F91: 143761 | G91: =F91-E91 -> 21024 | H91: =G91/G14/10 -> 0.83441816 | I91: OK
E92: =E91/(E16)*100 -> #DIV/0!
B93: Bleaching Earth (BE) to Branded Spec | C93: 18 | E93: 0
E94: =E93/(E17)*100 -> #DIV/0! | I94: OK
B95: Phosporic Acid (PA) | C95: 0,4 - 0,5 | D95: kg | E95: 1970.8 | F95: 867.36 | G95: =E95-F95 -> 1103.44 | H95: =G95/G14/10 -> 0.043794253 | I95: OK
A97: 3 | B97: OIL LOSSES | C97: - 0,8 | D97: % | H97: =((SUM(G27+G36))-(SUM(G14)))/(SUM(G14))*100 -> -2.7190824
H98: =H97%*G14 -> -68.51
B99: % Oil Content | C99: 20 to 21 | D99: %
B100: Spent Bleaching Earth | H100: =SUM(G91,G93)+(H99%*SUM(G91,G93)) -> 21024
A101: 4 | B101: PACKAGING (Brand Salvaco)
B102: Olein IV 60 Received
...

Sheet peformance  test REFINERY 2
A1: REFINERY PMG 2
A2: No | B2: ITEM | C2: Norma LIPICO | D2: UOM | E2: Day 2 tanggal 12/12/2024
A4: 1 | B4: PRODUCTION | E4: BEFORE | F4: AFTER | G4: TOTAL | H4: Yield ( % )
B5: Refinery
B6: Running Days
B7: Incoming CPO
B8: Ratio Run CPO
B9: CPO Consume Total | C9: 2500 | D9: TPD | E9: 5880.74 | F9: 8383.74 | G9: =F9-E9 -> 2503 | H9: =G9/2500000*100000 -> 100.12
B10: Avg Daily Consump CPO ( MTD )
B11: CPO Consume Poram | C11: 29045000
B12: CPO Consume Brand | C12: 7314000 | E12: =E43+E52+E57 -> 0
B13: - FFA | C13: 5 | D13: % | G13: 3.97
B14: - Moist & Impurities | C14: 0.5 | D14: % | G14: 0.4
B15: - DOBI | C15: 2.2 | D15: Min | G15: 2.42
B16: TANK | G16: 105
B17: Product
B18: OIP RBDPO
B19: RBDPO | C19: =C9*94.2% -> 2355 | D19: TPD | E19: 5143.38 | F19: 7493.18 | G19: =F19-E19 -> 2349.8 | H19: =G19/G9*100 -> 93.879345
B20: - FFA | C20: 0.05 | D20: % | G20: 0.043
B21: - Moist & Impurities | C21: 0.03 | D21: % | G21: 0.04
B22: - LC | C22: 2.5 | D22: % | G22: 2.5
B23: - Aom stability min ( hr ) | C23: 60 | D23: min ( hr )
B24: - teste & Odor | C24: bland/Odorless
B25: - temp max ( C ) | C25: 50 | D25: max˚C
B26: PFAD | C26: =C9*5% -> 125 | D26: TPD | E26: 243.04 | F26: 347.1 | G26: =F26-E26 -> 104.06 | H26: =G26/G9*100 -> 4.1574111
B27: Fractionation
B28: Running Days
B29: Filling Langsung CR Fr Refinery | E29: 0
B30: Total Filling Crystalizer ( Feed ) | E30: 392100
B31: Avg Daily Consump RPO ( MTD )
B32: Total Proses RBDPO | E32: =SUM(E35,E39,E44,E48,E58) -> 0
B33: Sisa Filling Crystalizer | E33: =E30-E32 -> 392100
B34: Fractionation OLEIN IV 56
B35: RBDPO Consume | E35: =E36+E37 -> 0
B36: OLEIN IV 56 | E36: 0
B37: STEARIN | E37: 0
B38: Fractionation OLEIN IV 57 ( Bulk )
B39: RBDPO Consume | E39: =E40+E41 -> 0
B40: OLEIN IV 57 | E40: 0
B41: STEARIN | E41: 0
B42: Fractionation OLEIN IV 57 ( Retail )
B43: CPO Consume
B44: RBDPO Brand Consume | E44: =E45+E46 -> 0
B45: OLEIN IV 57 Low Color | E45: 0
B46: STEARIN | E46: 0
B47: Fractionation OLEIN IV 58 ( Bulk )
B48: RBDPO Consume | C48: =C49+C50 -> 21429000 | E48: =E49+E50 -> 0
B49: OLEIN IV 58 | C49: 15000000
B50: STEARIN | C50: 6429000
B51: Fractionation OLEIN IV 58 ( Retail )
B52: CPO Consume
B53: RBDPO Consume | C53: =C54+C55 -> 21429000 | E53: =E54+E55 -> 0
B54: OLEIN IV 58 | C54: 15000000 | E54: 0
B55: STEARIN | C55: 6429000 | E55: 0
B56: Fractionation OLEIN IV 60
B57: CPO Consume
B58: RBDPO Brand Consume | E58: =E60+E61 -> 0
B59: OLEIN IV 60 Bulk | E59: 0
B60: OLEIN IV 60 Salvaco | E60: 0
B61: SOFT STEARIN | E61: 0
B62: Ratio Run RBDPO | E62: 0
B63: YIELD
B64: RBDPO | C64: 94.2 | E64: =(E19/(E9))*100 -> 87.461442
B65: PFAD | C65: 5 | E65: =(E26/(E9))*100 -> 4.1328132
B66: Olein IV 56 | C66: 82 | E66: =E36/(E36+E37)*100 -> #DIV/0!
B67: Stearin | C67: 18 | E67: =(E37/E35)*100 -> #DIV/0!
B68: Olein IV 57 ( Bulk ) | C68: 75 | E68: =(E40/E39)*100 -> #DIV/0!
B69: Stearin | C69: 25 | E69: =(E41/E39)*100 -> #DIV/0!
B70: Olein IV 57 ( Retail ) | C70: 75 | E70: =E45/E44*100 -> #DIV/0!
B71: Stearin | C71: 25 | E71: =E46/E44*100 -> #DIV/0!
B72: Olein IV 58 ( Bulk ) | C72: 70 | E72: =E49/(E49+E50)*100 -> #DIV/0!
B73: Stearin | C73: 30 | E73: =E50/(E50+E49)*100 -> #DIV/0!
B74: Olein IV 58 ( Retail ) | C74: 70 | E74: =E54/(E54+E55)*100 -> #DIV/0!
B75: Stearin | C75: 30 | E75: =E55/(E54+E55)*100 -> #DIV/0!
B76: Olein IV 60 | C76: 60 | E76: =E59/E58*100 -> #DIV/0!
B77: Soft Stearin | C77: 40 | E77: =E61/E58*100 -> #DIV/0!
B78: - FFA | C78: ~93 | D78: % | G78: 90.62
B79: - Moist & Impurities | C79: 0.5 | D79: % | G79: 0.33
A80: 2 | B80: CHEMICAL CONSUMABLE | E80: BEFORE | F80: AFTER | G80: TOTAL | H80: ( % )
B81: Bleaching Earth (BE) to Poram Spec | C81: 9 | D81: kg | E81: 51223 | F81: 74245 | G81: =F81-E81 -> 23022 | H81: =G81/G9/10 -> 0.91977627
E82: =E81/(E11)*100 -> #DIV/0!
B83: Bleaching Earth (BE) to Branded Spec | C83: 18 | E83: 0
E84: =E83/(E12)*100 -> #DIV/0!
B85: Phosporic Acid (PA) | C85: 0,4 - 0,5 | D85: kg | E85: 539.5 | F85: 1342.1 | G85: =F85-E85 -> 802.6 | H85: =G85/G9/10 -> 0.032065521
A87: 3 | B87: OIL LOSSES | C87: - 0,8 | D87: % | G87: =((SUM(G19+G26))-(SUM(G9)))/(SUM(G9))*100 -> -1.9632441
G88: =G87%*G9 -> -49.14
B89: % Oil Content | C89: 20 to 21 | D89: % | G89: 21.66
B90: Spent Bleaching Earth | G90: =SUM(G81,G83)+(G89%*SUM(G81,G83)) -> 28008.565
A91: 4 | B91: PACKAGING (Brand Salvaco)
B92: Olein IV 60 Received
B93: Olein IV 60 Consume
B94: - finished product | E94: 0
B95: - sample | E95: 0
B96: - remelt, flushing, downgrade | E96: 0
B97: Carton
B98: Salvaco 1 Liter
B99: Salvaco 2 Liter
B100: Pouch
B101: Salvaco 1 Liter | E101: 0
B102: Salvaco 2 Liter | E102: 0
...

Sheet HPP REF 
B2: Refinery Cost
B3: Through Put CPO Proses | N3: =('JUNI 2025'!AL10)/1000 -> 1781.3187 | O3: TPD
B4: Working Day | N4: ='JUNI 2025'!AL6 -> 10 | O4: Days
B5: Total CPO Process | N5: =N4*N3 -> 17813.187 | O5: MTD
B6: KURS | N6: 16000 | O6: Rp/USD
B7: No | C7: Item Cost | D7: Norma | F7: Pemakaian / Hari | H7: HK | J7: Total Pemakaian | K7: Harga / stn | M7: Total Biaya | N7: Rp / kg | O7: USD/MT
B8: 1 | C8: Bleaching Earth | D8: ='JUNI 2025'!$AL$76 -> 8.5932405 | F8: =($D$8*$N$3*10) -> 153073 | G8: Kg/day | H8: =$N$4 -> 10 | J8: =$H$8*$F$8 -> 1530730 | K8: 2400 | M8: =$J$8*$K$8 -> 3673752000 | N8: =$M$8/($N$5*1000) -> 206.23777 | O8: =($M$8/$N$6)/$N$5 -> 12.889861
B9: 2 | C9: Phosporic acid | D9: ='JUNI 2025'!$AL$84 -> 0.49363654 | F9: =($D$9*$N$3*10) -> 8793.24 | G9: Kg/day | H9: =$H$8 -> 10 | J9: =$H$9*$F$9 -> 87932.4 | K9: 17420 | M9: =$J$9*$K$9 -> 1531782408 | N9: =$M$9/($N$5*1000) -> 85.991485 | O9: =($M$9/$N$6)/$N$5 -> 5.3744678
B10: 3 | C10: Caustic Soda | D10: 29.166667 | E10: kg/day | F10: =D10 -> 29.166667 | G10: kg/day | H10: =$H$8 -> 10 | J10: =$H$10*$F$10 -> 291.66667 | K10: 15700 | M10: =$J$10*$K$10 -> 4579166.7 | N10: =$M$10/($N$5*1000) -> 0.25706611 | O10: =($M$10/$N$6)/$N$5 -> 0.016066632
B11: 4 | C11: Pemakaian Natural Gas HPB Geka
C12: Normal Consumption | D12: ='JUNI 2025'!$AL$244 -> 2032.2784 | E12: MMBTU/MT CPO | F12: =$D$12*$N$3 -> 3620135.4 | G12: MMBTU/day | H12: =$H$8 -> 10 | J12: =$H$12*$F$12 -> 36201354 | K12: =11.5*$N$6 -> 184000 | M12: =$J$12*$K$12 -> 6.6610492e+12 | N12: =$M$12/($N$5*1000) -> 373939.22 | O12: =($M$12/$N$6)/$N$5 -> 23371.201
C13: Penalty Below Consumption | D13: 0 | E13: MMBTU/MT CPO | F13: =$D$13*$N$3 -> 0 | G13: MMBTU/day | H13: =$H$8 -> 10 | J13: =$H$13*$F$13 -> 0 | K13: =11.5*$N$6 -> 184000 | M13: =$J$13*$K$13 -> 0 | N13: =$M$13/($N$5*1000) -> 0 | O13: =($M$13/$N$6)/$N$5 -> 0
C14: Penalty Above Consumption | D14: 0 | E14: MMBTU/MT CPO | F14: =$D$14*$N$3 -> 0 | G14: MMBTU/day | H14: =$H$8 -> 10 | J14: =$H$14*$F$14 -> 0 | K14: =11.5*$N$6 -> 184000 | M14: =$J$14*$K$14 -> 0 | N14: =$M$14/($N$5*1000) -> 0 | O14: =($M$14/$N$6)/$N$5 -> 0
B15: 5 | C15: Pemakaian Steam
C16: For Process | D16: ='JUNI 2025'!AL251 -> 790.67 | E16: Kg/MT CPO | F16: =$D$16*$N$3/1000 -> 1408.4353 | G16: Ton/day | H16: =$H$8 -> 10 | J16: =$H$16*$F$16 -> 14084.353 | K16: =Steam!H15 -> 529847.07 | M16: =$J$16*$K$16 -> 7.462553e+09 | N16: =$M$16/($N$5*1000) -> 418.93418 | O16: =($M$16/$N$6)/$N$5 -> 26.183387
C17: Storage Tank for Heating | D17: ='JUNI 2025'!$AL$255 -> 602.373 | E17: Kg/MT CPO | F17: =$D$17*$N$3/1000 -> 1073.0183 | G17: Ton/day | H17: =$H$8 -> 10 | J17: =$H$17*$F$17 -> 10730.183 | K17: =Steam!H15 -> 529847.07 | M17: =$J$17*$K$17 -> 5.685356e+09 | N17: =$M$17/($N$5*1000) -> 319.16557 | O17: =($M$17/$N$6)/$N$5 -> 19.947848
B18: 6 | C18: Pemakaian Electrical
C19: For Process | D19: ='JUNI 2025'!$AL$274 -> 135763 | E19: kW/MT CPO | F19: =$D$19*$N$3 -> 2.4183717e+08 | G19: kW/day | H19: =$H$8 -> 10 | I19: 0 | J19: =$H$19*$F$19 -> 2.4183717e+09 | K19: 1550 | L19: =[5]Electric!H21 -> 3666.6667 | M19: =($F$19*$H$19*$K$19)+($F$19*$I$19*$L$19) -> 3.7484761e+12 | N19: =$M$19/($N$5*1000) -> 210432.65 | O19: =($M$19/$N$6)/$N$5 -> 13152.041
C20: Cooling Tower | D20: ='JUNI 2025'!$AL$276 -> 99647.5 | E20: kW/MT CPO | F20: =$D$20*$N$3 -> 1.7750396e+08 | G20: kW/day | H20: =$H$8 -> 10 | I20: 0 | J20: =$H$20*$F$20 -> 1.7750396e+09 | K20: 1550 | L20: =L19 -> 3666.6667 | M20: =(F20*H20*K20)+(F20*I20*L20) -> 2.7513113e+12 | N20: =$M$20/($N$5*1000) -> 154453.62 | O20: =($M$20/$N$6)/$N$5 -> 9653.3516
C21: Storage Tank | D21: 0.3377877 | E21: kW/MT CPO | F21: =$D$21*$N$3 -> 601.70754 | G21: kW/day | H21: =$H$8 -> 10 | I21: 0 | J21: =$H$21*$F$21 -> 6017.0754 | K21: 1550 | L21: =L20 -> 3666.6667 | M21: =($F$21*$H$21*$K$21)+($F$21*$I$21*$L$21) -> 9326466.9 | N21: =$M$21/($N$5*1000) -> 0.52357093 | O21: =($M$21/$N$6)/$N$5 -> 0.032723183
B22: 7 | C22: Pemakaian Water
C23: Make Up CT | D23: ='JUNI 2025'!$AL$261 -> 1279 | E23: M3/day | F23: =$D$23 -> 1279 | G23: M3/day | H23: =$H$8 -> 10 | J23: =$H$23*$F$23 -> 12790 | K23: =WTP!H13 -> #VALUE! | M23: =$J$23*$K$23 -> #VALUE! | N23: =$M$23/($N$5*1000) -> #VALUE! | O23: =($M$23/$N$6)/$N$5 -> #VALUE!
B24: 8 | C24: Chemical Water | N24: =$M$24/($N$5*1000) -> 0 | O24: =($M$24/$N$6)/$N$5 -> 0
C25: EONBAC BC 3108 | D25: 0.4 | E25: Kg/day | F25: =D25 -> 0.4 | G25: Kg/day | H25: =$H$8 -> 10 | J25: =$H$25*$F$25 -> 4 | K25: 27240 | M25: =$J$25*$K$25 -> 108960 | N25: =$M$25/($N$5*1000) -> 0.0061168167 | O25: =($M$25/$N$6)/$N$5 -> 0.00038230104
C26: EONLINE T722 | D26: 0.66 | E26: Kg/day | F26: =D26 -> 0.66 | G26: Kg/day | H26: =$H$8 -> 10 | J26: =$H$26*$F$26 -> 6.6 | K26: 29120 | M26: =$J$26*$K$26 -> 192192 | N26: =$M$26/($N$5*1000) -> 0.01078931 | O26: =($M$26/$N$6)/$N$5 -> 0.00067433189
C27: EONLINE AG5770 | D27: 0.41 | E27: Kg/day | F27: =D27 -> 0.41 | G27: Kg/day | H27: =$H$8 -> 10 | J27: =$H$27*$F$27 -> 4.1 | K27: 117212 | M27: =$J$27*$K$27 -> 480569.2 | N27: =$M$27/($N$5*1000) -> 0.026978283 | O27: =($M$27/$N$6)/$N$5 -> 0.0016861427
C28: EONScale T2511 | D28: 0.1 | E28: Kg/day | F28: =D28 -> 0.1 | G28: Kg/day | H28: =$H$8 -> 10 | J28: =$H$28*$F$28 -> 1 | K28: 45940 | M28: =$J$28*$K$28 -> 45940 | N28: =$M$28/($N$5*1000) -> 0.0025789883 | O28: =($M$28/$N$6)/$N$5 -> 0.00016118677
B29: 9 | C29: Others
C30: Filter Bag 10 Microne | D30: 0.90361446 | E30: Pcs/day | F30: =D30 -> 0.90361446 | G30: Pcs/day | H30: =$H$8 -> 10 | J30: =$H$30*$F$30 -> 9.0361446 | K30: 40000 | M30: =$J$30*$K$30 -> 361445.78 | N30: =$M$30/($N$5*1000) -> 0.02029091 | O30: =($M$30/$N$6)/$N$5 -> 0.0012681819
C31: Filter Bag 100 Microne | D31: 0.63253012 | E31: Pcs/day | F31: =D31 -> 0.63253012 | G31: Pcs/day | H31: =$H$8 -> 10 | J31: =$H$31*$F$31 -> 6.3253012 | K31: 125000 | M31: =$J$31*$K$31 -> 790662.65 | N31: =$M$31/($N$5*1000) -> 0.044386367 | O31: =($M$31/$N$6)/$N$5 -> 0.0027741479
C32: Filter Cartridge 10 Microne | D32: 1.5666667 | E32: Pcs/day | F32: =D32 -> 1.5666667 | G32: Pcs/day | H32: =$H$8 -> 10 | J32: =$H$32*$F$32 -> 15.666667 | K32: 145000 | M32: =$J$32*$K$32 -> 2271666.7 | N32: =$M$32/($N$5*1000) -> 0.12752725 | O32: =($M$32/$N$6)/$N$5 -> 0.0079704528
C33: Filter Dustbag | D33: 0.12048193 | E33: Pcs/day | F33: =D33 -> 0.12048193 | G33: Pcs/day | H33: =$H$8 -> 10 | J33: =$H$33*$F$33 -> 1.2048193 | K33: 682500 | M33: =$J$33*$K$33 -> 822289.16 | N33: =$M$33/($N$5*1000) -> 0.046161821 | O33: =($M$33/$N$6)/$N$5 -> 0.0028851138
C34: O Ring Filter Leaves | D34: 3.6144578 | E34: Pcs/day | F34: =D34 -> 3.6144578 | G34: Pcs/day | H34: =$H$8 -> 10 | J34: =$H$34*$F$34 -> 36.144578 | K34: 14500 | M34: =$J$34*$K$34 -> 524096.39 | N34: =$M$34/($N$5*1000) -> 0.02942182 | O34: =($M$34/$N$6)/$N$5 -> 0.0018388638
B35: 10 | C35: Waste Water Treatment Plant ( WWTP ) | D35: ='JUNI 2025'!$AL$267 -> 1219 | E35: M3/day | F35: =D35 -> 1219 | G35: M3/day | H35: =$H$8 -> 10 | J35: =$H$35*$F$35 -> 12190 | K35: =WWTP!H17 -> 3464.8428 | M35: =$J$35*$K$35 -> 42236434 | N35: =$M$35/($N$5*1000) -> 2.3710768 | O35: =($M$35/$N$6)/$N$5 -> 0.1481923
B36: 11 | C36: SHE
C37: SBE | D37: ='JUNI 2025'!$AL$88 -> 156289.68 | E37: Kg/day | F37: =D37 -> 156289.68 | G37: Kg/day | H37: =$H$8 -> 10 | J37: =$F$37 -> 156289.68 | K37: 0 | M37: =$J$37*$K$37 -> 0 | N37: =$M$37/($N$5*1000) -> 0 | O37: =($M$37/$N$6)/$N$5 -> 0
C38: Domestic | D38: 0.1 | E38: Trip/day | F38: =D38 -> 0.1 | G38: Trip/day | H38: =$H$8 -> 10 | J38: =$H$38*$F$38 -> 1 | K38: 303030.3 | M38: =$J$38*$K$38 -> 303030.3 | N38: =$M$38/($N$5*1000) -> 0.017011571 | O38: =($M$38/$N$6)/$N$5 -> 0.0010632232
B39: 12 | C39: Chemical Consumption | N39: =$M$39/($N$5*1000) -> 0 | O39: =($M$39/$N$6)/$N$5 -> 0
C40: LAB Chemical | D40: =lab!H33 -> 745255.21 | E40: Rp/day | F40: =D40 -> 745255.21 | G40: Rp/day | H40: =$H$8 -> 10 | M40: =$H$40*$F$40 -> 7452552.1 | N40: =$M$40/($N$5*1000) -> 0.41837275 | O40: =($M$40/$N$6)/$N$5 -> 0.026148297
C41: Chemical Boiler dan WTP | D41: =lab!H54 -> 259161.44 | E41: Rp/day | F41: =D41 -> 259161.44 | G41: Rp/day | H41: =$H$8 -> 10 | M41: =$H$41*$F$41 -> 2591614.4 | N41: =$M$41/($N$5*1000) -> 0.14548853 | O41: =($M$41/$N$6)/$N$5 -> 0.0090930333
C42: Sample and Analysis | D42: 13909.091 | E42: Rp/day | F42: =D42 -> 13909.091 | G42: Rp/day | H42: =$H$8 -> 10 | M42: =$H$42*$F$42 -> 139090.91 | N42: =$M$42/($N$5*1000) -> 0.0078083113 | O42: =($M$42/$N$6)/$N$5 -> 0.00048801946
C43: Chemical WWTP | D43: =[5]Chemical!$H$61 -> 27103.641 | E43: Rp/day | F43: =D43 -> 27103.641 | G43: Rp/day | H43: =$H$8 -> 10 | M43: =$H$43*$F$43 -> 271036.41 | N43: =$M$43/($N$5*1000) -> 0.015215493 | O43: =($M$43/$N$6)/$N$5 -> 0.00095096829
C44: Consumable Part | D44: =lab!I111 -> 135770.31 | E44: Rp/day | F44: =D44 -> 135770.31 | G44: Rp/day | H44: =$H$8 -> 10 | M44: =$H$44*$F$44 -> 1357703.1 | N44: =$M$44/($N$5*1000) -> 0.076218988 | O44: =($M$44/$N$6)/$N$5 -> 0.0047636867
B45: 13 | C45: Solar
C46: Forklift -1 (3 Ton) | D46: 15.4 | E46: Ltr/day | F46: =D46 -> 15.4 | G46: Ltr/day | H46: =$H$8 -> 10 | J46: =$H$46*$F$46 -> 154 | K46: 14500 | M46: =$J$46*$K$46 -> 2233000 | N46: =$M$46/($N$5*1000) -> 0.12535657 | O46: =($M$46/$N$6)/$N$5 -> 0.0078347855
C47: WA Loader | D47: 0 | E47: Ltr/day | F47: =D47 -> 0 | G47: Ltr/day | H47: =$H$8 -> 10 | J47: =$H$47*$F$47 -> 0 | K47: 14500 | M47: =$J$47*$K$47 -> 0 | N47: =$M$47/($N$5*1000) -> 0 | O47: =($M$47/$N$6)/$N$5 -> 0
M48: =SUM($M$8:$M$47) -> #VALUE! | N48: =SUM($N$8:$N$47) -> #VALUE! | O48: =SUM($O$8:$O$47) -> #VALUE!

Sheet HPP FRACT
B2: Fractionation Cost
B3: RPO Proses / Day | N3: TPD | O3: ='JUNI 2025'!AL24/1000 -> 1779.2607
B4: Working Day | N4: Days | O4: ='JUNI 2025'!AL23 -> 10
B5: Total CPO Process | N5: MTD | O5: =O3*O4 -> 17792.607
B6: KURS | N6: Rp/USD | O6: 16000
B7: No | C7: Item Cost | D7: Norma | F7: Pemakaian / Hari | H7: HK | J7: Total Pemakaian | K7: Harga / stn | M7: Total Biaya | N7: Rp / kg | O7: USD/MT
B8: 1 | C8: Steam | D8: ='JUNI 2025'!AL253 -> 425.736 | E8: Kg/MT CPO | F8: =$D$8*$O$3/1000 -> 757.49533 | G8: Ton/day | H8: =$O$4 -> 10 | J8: =$H$8*$F$8 -> 7574.9533 | K8: =Steam!H15 -> 529847.07 | M8: =$K$8*$J$8 -> 4.0135668e+09 | N8: =$M$8/($O$5*1000) -> 225.57497 | O8: =($M$8/$O$6)/$O$5 -> 14.098436
B9: 2 | C9: Electrical
C10: For Process | D10: ='JUNI 2025'!$AL$281 -> 82129.1 | E10: kW/MT CPO | F10: =$D$10*$O$3 -> 1.4612908e+08 | G10: kW/day | H10: =$O$4 -> 10 | I10: 0 | J10: =$H$10*$F$10 -> 1.4612908e+09 | K10: =[5]Electric!$L$5 -> 1550 | L10: 3666.6667 | M10: =($F$10*$H$10*$K$10)+($F$10*$I$10*$L$10) -> 2.2650007e+12 | N10: =$M$10/($O$5*1000) -> 127300.11 | O10: =($M$10/$O$6)/$O$5 -> 7956.2566
C11: Cooling Tower | D11: ='JUNI 2025'!$AL$279 -> 150240 | E11: kW/MT CPO | F11: =$D$11*$O$3 -> 2.6731613e+08 | G11: kW/day | H11: =$H$10 -> 10 | I11: 0 | J11: =$H$11*$F$11 -> 2.6731613e+09 | K11: =$K$10 -> 1550 | L11: 3666.6667 | M11: =($F$11*$H$11*$K$11)+($F$11*$I$11*$L$11) -> 4.1434e+12 | N11: =$M$11/($O$5*1000) -> 232872 | O11: =($M$11/$O$6)/$O$5 -> 14554.5
B12: 3 | C12: Water
C13: Make Up CT | D13: ='JUNI 2025'!$AL$263 -> 950 | E13: M3/day | F13: =$D$13 -> 950 | G13: M3/day | H13: =$H$11 -> 10 | J13: =$H$13*$F$13 -> 9500 | K13: =WTP!H13 -> #VALUE! | M13: =$K$13*$J$13 -> #VALUE! | N13: =$M$13/($O$5*1000) -> #VALUE! | O13: =($M$13/$O$6)/$O$5 -> #VALUE!
B14: 4 | C14: Chemical Water
C15: EONBAC BC 3108 | D15: 0.4 | E15: Kg/day | F15: =$D$15 -> 0.4 | G15: Kg/day | H15: =$H$13 -> 10 | J15: =$H$15*$F$15 -> 4 | K15: 27240 | M15: =$K$15*$J$15 -> 108960 | N15: =$M$15/($O$5*1000) -> 0.0061238918 | O15: =($M$15/$O$6)/$O$5 -> 0.00038274324
C16: EONLINE T722 | D16: 0.66 | E16: Kg/day | F16: =$D$16 -> 0.66 | G16: Kg/day | H16: =$H$15 -> 10 | J16: =$H$16*$F$16 -> 6.6 | K16: 29120 | M16: =$K$16*$J$16 -> 192192 | N16: =$M$16/($O$5*1000) -> 0.01080179 | O16: =($M$16/$O$6)/$O$5 -> 0.00067511186
C17: EONLINE AG5770 | D17: 0.41 | E17: Kg/day | F17: =$D$17 -> 0.41 | G17: Kg/day | H17: =$H$15 -> 10 | J17: =$H$17*$F$17 -> 4.1 | K17: 117212 | M17: =$K$17*$J$17 -> 480569.2 | N17: =$M$17/($O$5*1000) -> 0.027009488 | O17: =($M$17/$O$6)/$O$5 -> 0.001688093
C18: EONScale T2511 | D18: 0.1 | E18: Kg/day | F18: =$D$18 -> 0.1 | G18: Kg/day | H18: =$H$16 -> 10 | J18: =$H$18*$F$18 -> 1 | K18: 45940 | M18: =$K$18*$J$18 -> 45940 | N18: =$M$18/($O$5*1000) -> 0.0025819713 | O18: =($M$18/$O$6)/$O$5 -> 0.0001613732
B19: 5 | C19: Others
C20: Filter Cloth | D20: 0.33333333 | E20: Pcs/day | F20: =$D$20 -> 0.33333333 | G20: Pcs/day | H20: =$H$18 -> 10 | J20: =$H$20*$F$20 -> 3.3333333 | K20: 895000 | M20: =$K$20*$J$20 -> 2983333.3 | N20: =$M$20/($O$5*1000) -> 0.16767264 | O20: =($M$20/$O$6)/$O$5 -> 0.01047954
C21: Filter Bag 100 Microne | D21: 0.63253012 | E21: Pcs/day | F21: =$D$21 -> 0.63253012 | G21: Pcs/day | H21: =$H$20 -> 10 | J21: =$H$21*$F$21 -> 6.3253012 | K21: 125000 | M21: =$K$21*$J$21 -> 790662.65 | N21: =$M$21/($O$5*1000) -> 0.044437707 | O21: =($M$21/$O$6)/$O$5 -> 0.0027773567
M22: =SUM(M8:M21) -> #VALUE! | N22: =SUM(N8:N21) -> #VALUE! | O22: =SUM($O$8:$O$21) -> #VALUE!

Sheet SUMMARY HPP 
B2: Production Cost MARET 2025
B3: Through Put CPO Proses (Ton/Day) | H3: TPD | I3: ='HPP REF '!$N$3 -> 1781.3187
B4: Working Day | F4: 1 | H4: Days | I4: ='HPP REF '!$N$4 -> 10
B5: Refined CPO ( Ton/month ) | H5: MTD | I5: =$I$4*$I$3 -> 17813.187
B6: Through Put RPO Proses (Ton/Day) | H6: TPD | I6: ='HPP FRACT'!$O$3 -> 1779.2607
B7: Working Day | H7: Days | I7: ='HPP FRACT'!$O$4 -> 10
B8: Fract RPO ( ton/month ) | H8: MTD | I8: =$I$7*$I$6 -> 17792.607
B9: KURS | H9: Rp/USD | I9: 16000
B10: No | C10: Items | D10: Description | G10: Rupiah | H10: Rp/Kg | I10: USD/MT
B11: I | C11: Production Cost | D11: ● | E11: Refining Cost | G11: ='HPP REF '!$M$48 -> #VALUE! | H11: =$G$11/($I$5*1000) -> #VALUE! | I11: =(G11/$I$9)/$I$5 -> #VALUE!
D12: ● | E12: Fractionation Cost | G12: ='HPP FRACT'!$M$22 -> #VALUE! | H12: =$G$12/($I$8*1000) -> #VALUE! | I12: =(G12/$I$9)/$I$8 -> #VALUE!
D13: ● | E13: Preventive Maintenance Cost | F13: 0 | G13: =MTC!$F$18*F13 -> 0 | H13: =$G$13/($I$5*1000) -> 0 | I13: =(G13/$I$9)/$I$5 -> 0
G14: =SUM(G11:$G$13) -> #VALUE! | H14: =SUM($H$11:$H$13) -> #VALUE! | I14: =SUM(I11:I13) -> #VALUE! | K14: =I14+I26 -> #VALUE!
B16: II | C16: Port Cost | D16: ● | E16: Trucking Komoditi ke Kuala Tanjung | G16: =LOG!I8+LOG!I9+LOG!$I$10 -> 1.8494363e+09 | H16: =$G$16/($I$5*1000) -> 103.824 | I16: =($G$16/$I$9)/$I$5 -> 6.489
D17: ● | E17: Sewa Tank PTI Total Volume : 24.000 MT ( 5 Unit ) | F17: =F4 -> 1 | G17: =LOG!I11+LOG!I12+LOG!I13+LOG!$I$14*F17 -> 1886000000 | H17: =$G$17/($I$5*1000) -> 105.87662 | I17: =($G$17/$I$9)/$I$5 -> 6.6172886
D18: ● | E18: Instalasi & Pemanasan, Pompa, Surveyor dan Documen | G18: =LOG!I18+LOG!I19+LOG!I20+LOG!$I$21 -> 9.542168e+08 | H18: =$G$18/($I$5*1000) -> 53.568 | I18: =($G$18/$I$9)/$I$5 -> 3.348
D19: ● | E19: Finalty Over Capacity Tank | G19: =LOG!I15+LOG!I16+LOG!$I$17 -> 7.598393e+08 | H19: =$G$19/($I$5*1000) -> 42.656 | I19: =($G$19/$I$9)/$I$5 -> 2.666
G20: =SUM($G$16:$G$19) -> 5.4494924e+09 | H20: =SUM($H$16:$H$19) -> 305.92462 | I20: =SUM($I$16:$I$19) -> 19.120289
B22: II | C22: Fix Cost | D22: ● | E22: Manpower Cost | F22: =F4 -> 1 | G22: =[5]MPC!$H$29*$F$22 -> 2.1846655e+09 | H22: =$G$22/($I$5*1000) -> 122.64316 | I22: =($G$22/$I$9)/$I$5 -> 7.6651975
D23: ● | E23: Admin OH Cost | F23: =F4 -> 1 | G23: =OH!G51*$F$23 -> 1.4360564e+09 | H23: =$G$23/($I$5*1000) -> 80.6176 | I23: =($G$23/$I$9)/$I$5 -> 5.0386
D24: ● | E24: Depresiasi Cost | F24: =F4 -> 1 | G24: =DEP!I9*$F$24 -> 4.1811848e+09 | H24: =$G$24/($I$5*1000) -> 234.72413 | I24: =($G$24/$I$9)/$I$5 -> 14.670258
D25: ● | E25: Amortisation of leasehold land Cost | F25: =F4 -> 1 | G25: =AMOR!$G$20*$F$25 -> 1.0484098e+09 | H25: =$G$25/($I$5*1000) -> 58.855824 | I25: =($G$25/$I$9)/$I$5 -> 3.678489
G26: =SUM($G$22:$G$25) -> 8.8503165e+09 | H26: =SUM($H$22:$H$25) -> 496.84071 | I26: =SUM($I$22:$I$25) -> 31.052545 | K26: =I26+I14 -> #VALUE!
B28: Total Production Cost | G28: =$G$26+$G$20+$G$14 -> #VALUE! | H28: =$H$26+$H$20+$H$14 -> #VALUE! | I28: =$I$26+$I$20+$I$14 -> #VALUE!

Sheet Convert Gas
B3: CONVERT PEMAKAIAN GAS HP BOILER & MP BOILER
D4: 2024
C5: HP BOILER | F5: TOTAL CORRECTED VOLUME (Sm3) | K5: ENERGY MP BOILER (MMBTU) | L5: TOTAL GAS CONSUMPTION (MMBTU) | M5: PERCENTAGE
C6: UNCORRECTED VOLUME (UV) (Nm3) | D6: PRESS. Bar | E6: CORRECTED VOLUME (CV) (Sm3) | G6: Convert Sm3 to SCF | H6: VOLUME (MSCF) | I6: HEATING VALUE (BTU / SCF) | J6: ENERGY HP BOILER (MMBTU) | M6: HP Boiler | N6: MP Boiler
C7: 1 | D7: 2 | E7: 3 = 1 x 2 | F7: 4 = 3 | G7: 5 | H7: 6 = (4 x 5) / 1000 | I7: 7 | J7: 8 = (6 x 7) / 1000 | K7: 9 = 10 - 8 | L7: 10 | M7: 11 = 8 / 10 | N7: 12 = 9 / 10
B8: 1 | D8: 5 | E8: =C8*D8 -> 0 | F8: =E8 -> 0 | G8: 35.314667 | H8: =(F8*G8)/1000 -> 0 | I8: 1047.7934 | J8: =(H8*I8)/1000 -> 0 | K8: =L8-J8 -> 0 | L8: 0 | M8: =(J8/L8) -> #DIV/0! | N8: =K8/L8 -> #DIV/0!
B9: =B8+1 -> 2 | D9: 5 | E9: =C9*D9 -> 0 | F9: =E9 -> 0 | G9: 35.314667 | H9: =(F9*G9)/1000 -> 0 | I9: 1042.7042 | J9: =(H9*I9)/1000 -> 0 | K9: =L9-J9 -> 0.7969 | L9: 0.7969 | M9: =(J9/L9) -> 0 | N9: =K9/L9 -> 1
B10: =B9+1 -> 3 | C10: 159.69 | D10: 5 | E10: =C10*D10 -> 798.45 | F10: =E10 -> 798.45 | G10: 35.314667 | H10: =(F10*G10)/1000 -> 28.196996 | I10: 1044.8302 | J10: =(H10*I10)/1000 -> 29.461073 | K10: =L10-J10 -> 656.37333 | L10: 685.8344 | M10: =(J10/L10) -> 0.04295654 | N10: =K10/L10 -> 0.95704346
B11: =B10+1 -> 4 | C11: 788.24 | D11: 5 | E11: =C11*D11 -> 3941.2 | F11: =E11 -> 3941.2 | G11: 35.314667 | H11: =(F11*G11)/1000 -> 139.18217 | I11: 1050.3635 | J11: =(H11*I11)/1000 -> 146.19187 | K11: =L11-J11 -> 696.04741 | L11: 842.23928 | M11: =(J11/L11) -> 0.17357522 | N11: =K11/L11 -> 0.82642478
B12: =B11+1 -> 5 | C12: 3.33 | D12: 5 | E12: =C12*D12 -> 16.65 | F12: =E12 -> 16.65 | G12: 35.314667 | H12: =(F12*G12)/1000 -> 0.58798921 | I12: 1050.6498 | J12: =(H12*I12)/1000 -> 0.61777073 | K12: =L12-J12 -> 767.54333 | L12: 768.1611 | M12: =(J12/L12) -> 0.00080422027 | N12: =K12/L12 -> 0.99919578
B13: =B12+1 -> 6 | C13: 1356.95 | D13: 5 | E13: =C13*D13 -> 6784.75 | F13: =E13 -> 6784.75 | G13: 35.314667 | H13: =(F13*G13)/1000 -> 239.60119 | I13: 1051.3912 | J13: =(H13*I13)/1000 -> 251.91459 | K13: =L13-J13 -> 389.14956 | L13: 641.06415 | M13: =(J13/L13) -> 0.39296315 | N13: =K13/L13 -> 0.60703685
B14: =B13+1 -> 7 | C14: 4051.52 | D14: 5 | E14: =C14*D14 -> 20257.6 | F14: =E14 -> 20257.6 | G14: 35.314667 | H14: =(F14*G14)/1000 -> 715.3904 | I14: 1053.7683 | J14: =(H14*I14)/1000 -> 753.85573 | K14: =L14-J14 -> 105.66983 | L14: 859.52556 | M14: =(J14/L14) -> 0.87706028 | N14: =K14/L14 -> 0.12293972
B15: =B14+1 -> 8 | C15: 5815.62 | D15: 5 | E15: =C15*D15 -> 29078.1 | F15: =E15 -> 29078.1 | G15: 35.314667 | H15: =(F15*G15)/1000 -> 1026.8834 | I15: 1055.9121 | J15: =(H15*I15)/1000 -> 1084.2986 | K15: =L15-J15 -> -55.066247 | L15: 1029.2324 | M15: =(J15/L15) -> 1.0535022 | N15: =K15/L15 -> -0.053502249
B16: =B15+1 -> 9 | C16: 5220.53 | D16: 5 | E16: =C16*D16 -> 26102.65 | F16: =E16 -> 26102.65 | G16: 35.314667 | H16: =(F16*G16)/1000 -> 921.80639 | I16: 1058.5967 | J16: =(H16*I16)/1000 -> 975.82117 | K16: =L16-J16 -> 139.90533 | L16: 1115.7265 | M16: =(J16/L16) -> 0.87460607 | N16: =K16/L16 -> 0.12539393
B17: =B16+1 -> 10 | C17: 2188 | D17: 5 | E17: =C17*D17 -> 10940 | F17: =E17 -> 10940 | G17: 35.314667 | H17: =(F17*G17)/1000 -> 386.34246 | I17: 1055.6055 | J17: =(H17*I17)/1000 -> 407.82521 | K17: =L17-J17 -> 551.84729 | L17: 959.6725 | M17: =(J17/L17) -> 0.4249629 | N17: =K17/L17 -> 0.5750371
B18: =B17+1 -> 11 | C18: 1796.49 | D18: 5 | E18: =C18*D18 -> 8982.45 | F18: =E18 -> 8982.45 | G18: 35.314667 | H18: =(F18*G18)/1000 -> 317.21223 | I18: 1056.3096 | J18: =(H18*I18)/1000 -> 335.07431 | K18: =L18-J18 -> 538.27709 | L18: 873.3514 | M18: =(J18/L18) -> 0.38366494 | N18: =K18/L18 -> 0.61633506
B19: =B18+1 -> 12 | C19: 4866.75 | D19: 5 | E19: =C19*D19 -> 24333.75 | F19: =E19 -> 24333.75 | G19: 35.314667 | H19: =(F19*G19)/1000 -> 859.33828 | I19: 1051.5483 | J19: =(H19*I19)/1000 -> 903.63574 | K19: =L19-J19 -> 6.6809602 | L19: 910.3167 | M19: =(J19/L19) -> 0.99266084 | N19: =K19/L19 -> 0.0073391603
B20: =B19+1 -> 13 | C20: 6932.28 | D20: 5 | E20: =C20*D20 -> 34661.4 | F20: =E20 -> 34661.4 | G20: 35.314667 | H20: =(F20*G20)/1000 -> 1224.0558 | I20: 1053.7374 | J20: =(H20*I20)/1000 -> 1289.8334 | K20: =L20-J20 -> -53.700699 | L20: 1236.1327 | M20: =(J20/L20) -> 1.0434425 | N20: =K20/L20 -> -0.043442504
B21: =B20+1 -> 14 | C21: 6338.15 | D21: 5 | E21: =C21*D21 -> 31690.75 | F21: =E21 -> 31690.75 | G21: 35.314667 | H21: =(F21*G21)/1000 -> 1119.1483 | I21: 1054.6459 | J21: =(H21*I21)/1000 -> 1180.3051 | K21: =L21-J21 -> -24.066515 | L21: 1156.2386 | M21: =(J21/L21) -> 1.0208145 | N21: =K21/L21 -> -0.020814488
... B24: =B23+1 -> 17 | C24: 6388.24 | D24: 5 | E24: =C24*D24 -> 31941.2 | F24: =E24 -> 31941.2 | G24: 38.314667 | H24: =(F24*G24)/1000 -> 1223.8164 | I24: 1041.3329 | J24: =(H24*I24)/1000 -> 1274.4003 | K24: =L24-J24 -> -125.496 | L24: 1148.9043 | M24: =(J24/L24) -> 1.109231 | N24: =K24/L24 -> -0.10923103
B25: =B24+1 -> 18 | C25: 7607.66 | D25: 5 | E25: =C25*D25 -> 38038.3 | F25: =E25 -> 38038.3 | G25: 39.314667 | H25: =(F25*G25)/1000 -> 1495.4631 | I25: 1042.2141 | J25: =(H25*I25)/1000 -> 1558.5927 | K25: =L25-J25 -> -1558.5927 | M25: =(J25/L25) -> #DIV/0! | N25: =K25/L25 -> #DIV/0!
B26: =B25+1 -> 19 | C26: 6514.97 | D26: 5 | E26: =C26*D26 -> 32574.85 | F26: =E26 -> 32574.85 | G26: 40.314667 | H26: =(F26*G26)/1000 -> 1313.2442 | I26: 1042.5071 | J26: =(H26*I26)/1000 -> 1369.0664 | K26: =L26-J26 -> -1369.0664 | M26: =(J26/L26) -> #DIV/0! | N26: =K26/L26 -> #DIV/0!
B27: =B26+1 -> 20 | C27: 4942.41 | D27: 5 | E27: =C27*D27 -> 24712.05 | F27: =E27 -> 24712.05 | G27: 41.314667 | H27: =(F27*G27)/1000 -> 1020.9701 | I27: 1042.9853 | J27: =(H27*I27)/1000 -> 1064.8569 | K27: =L27-J27 -> -1064.8569 | M27: =(J27/L27) -> #DIV/0! | N27: =K27/L27 -> #DIV/0!
B28: =B27+1 -> 21 | C28: 3073.52 | D28: 5 | E28: =C28*D28 -> 15367.6 | F28: =E28 -> 15367.6 | G28: 42.314667 | H28: =(F28*G28)/1000 -> 650.27488 | I28: 1043.1149 | J28: =(H28*I28)/1000 -> 678.31139 | K28: =L28-J28 -> -678.31139 | M28: =(J28/L28) -> #DIV/0! | N28: =K28/L28 -> #DIV/0!
B29: =B28+1 -> 22 | D29: 5 | E29: =C29*D29 -> 0 | F29: =E29 -> 0 | G29: 42.314667 | H29: =(F29*G29)/1000 -> 0 | I29: 1042.5884 | J29: =(H29*I29)/1000 -> 0 | K29: =L29-J29 -> 0 | M29: =(J29/L29) -> #DIV/0! | N29: =K29/L29 -> #DIV/0!
B30: =B29+1 -> 23 | D30: 5 | E30: =C30*D30 -> 0 | F30: =E30 -> 0 | G30: 44.314667 | H30: =(F30*G30)/1000 -> 0 | I30: 1042.7497 | J30: =(H30*I30)/1000 -> 0 | K30: =L30-J30 -> 0 | M30: =(J30/L30) -> #DIV/0! | N30: =K30/L30 -> #DIV/0!
B31: =B30+1 -> 24 | D31: 5 | E31: =C31*D31 -> 0 | F31: =E31 -> 0 | G31: 45.314667 | H31: =(F31*G31)/1000 -> 0 | I31: 1042.2931 | J31: =(H31*I31)/1000 -> 0 | K31: =L31-J31 -> 0 | M31: =(J31/L31) -> #DIV/0! | N31: =K31/L31 -> #DIV/0!
B32: =B31+1 -> 25 | D32: 5 | E32: =C32*D32 -> 0 | F32: =E32 -> 0 | G32: 46.314667 | H32: =(F32*G32)/1000 -> 0 | I32: 1039.4114 | J32: =(H32*I32)/1000 -> 0 | K32: =L32-J32 -> 0 | M32: =(J32/L32) -> #DIV/0! | N32: =K32/L32 -> #DIV/0!
B33: =B32+1 -> 26 | D33: 5 | E33: =C33*D33 -> 0 | F33: =E33 -> 0 | G33: 47.314667 | H33: =(F33*G33)/1000 -> 0 | I33: 1039.4407 | J33: =(H33*I33)/1000 -> 0 | K33: =L33-J33 -> 0 | M33: =(J33/L33) -> #DIV/0! | N33: =K33/L33 -> #DIV/0!
B34: =B33+1 -> 27 | D34: 5 | E34: =C34*D34 -> 0 | F34: =E34 -> 0 | G34: 48.314667 | H34: =(F34*G34)/1000 -> 0 | I34: 1040.2491 | J34: =(H34*I34)/1000 -> 0 | K34: =L34-J34 -> 0 | M34: =(J34/L34) -> #DIV/0! | N34: =K34/L34 -> #DIV/0!
B35: =B34+1 -> 28 | D35: 5 | E35: =C35*D35 -> 0 | F35: =E35 -> 0 | G35: 49.314667 | H35: =(F35*G35)/1000 -> 0 | J35: =(H35*I35)/1000 -> 0 | K35: =L35-J35 -> 0 | M35: =(J35/L35) -> #DIV/0! | N35: =K35/L35 -> #DIV/0!
B36: =B35+1 -> 29 | D36: 5 | E36: =C36*D36 -> 0 | F36: =E36 -> 0 | G36: 50.314667 | H36: =(F36*G36)/1000 -> 0 | J36: =(H36*I36)/1000 -> 0 | K36: =L36-J36 -> 0 | M36: =(J36/L36) -> #DIV/0! | N36: =K36/L36 -> #DIV/0!
B37: =B36+1 -> 30 | D37: 5 | E37: =C37*D37 -> 0 | F37: =E37 -> 0 | G37: 51.314667 | H37: =(F37*G37)/1000 -> 0 | J37: =(H37*I37)/1000 -> 0 | K37: =L37-J37 -> 0 | M37: =(J37/L37) -> #DIV/0! | N37: =K37/L37 -> #DIV/0!
B38: Average | F38: =AVERAGE(F8:F37) -> 12674.528 | H38: =AVERAGE(H8:H37) -> 471.76255 | I38: =AVERAGE(I8:I37) -> 1047.1339 | J38: =AVERAGE(J8:J37) -> 494.65048 | K38: =AVERAGE(K8:K37) -> -12.578486 | L38: =AVERAGE(L8:L37) -> 850.71528 | M38: =AVERAGE(M8:M37) -> #DIV/0! | N38: =AVERAGE(N8:N37) -> #DIV/0!
B39: TOTAL | C39: =SUM(C8:C37) -> 76047.17 | E39: =SUM(E8:E37) -> 380235.85 | F39: =SUM(F8:F37) -> 380235.85 | H39: =SUM(H8:H37) -> 14152.877 | J39: =SUM(J8:J37) -> 14839.514
B40: Koreksi
B41: Total Setelah Koreksi | H41: =H39+H40 -> 14152.877 | J41: =J39+J40 -> 14839.514
C43: CONVERT HP Boiler from Utility
C44: =C39 -> 76047.17 | D44: m3 | F44: =C39*5 -> 380235.85 | G44: 9983.7
C45: 5 | D45: bar | F45: 21286.9 | G45: =G44-C39 -> -66063.47
C46: =C44*C45 -> 380235.85 | D46: Sm3 | F46: =F44/F45 -> 17.862434
C47: =#REF! -> #REF! | D47: Scf
C48: =(C46*C47)/1000 -> #REF! | D48: Volume (MSCF)
C49: =I38 -> 1047.1339 | D49: Heating Value
C50: =(C48*C49)/1000 -> #REF! | D50: Energy (mmbtu)

Sheet Qty cons analysis
D2: Quantity Utility Consumption Analysis (based on Guarantee Utility Consumption)
D3: Refinery & Fractionation Plant
D4: Periode 01 s/d 30 Juni 2025
D5: Consumption | E5: UoM | F5: Budget | G5: Actual | H5: Under (Over) Budget | I5: Explanation Under / Over budget
D6: CPO Consume | E6: Kg | F6: ='JUNI 2025'!E9 -> 58900000 | G6: ='JUNI 2025'!$AL$9 -> 17813187 | H6: =G6/F6 -> 0.30243102
D7: RbdPO Consume | E7: Kg | F7: ='JUNI 2025'!E20 -> 55661000 | G7: ='JUNI 2025'!AL29 -> 17792607 | H7: =G7/F7 -> 0.31966021
D8: TOTAL ACTUAL CONSUMPTION
D9: Refinery
D10: Bleaching Earth to Poram Spec | E10: Kg | F10: 232362 | G10: ='JUNI 2025'!$AL$75 -> 153073 | H10: =F10-G10 -> 79289 | I10: Under Budget
D11: Bleaching Earth to Branded Spec | E11: Kg | F11: 106326 | G11: ='JUNI 2025'!$AL$81 -> 0 | H11: 0
D12: Phosporic Acid | E12: Kg | F12: 20971 | G12: ='JUNI 2025'!$AL$83 -> 8793.24 | H12: =F12-G12 -> 12177.76 | I12: Under Budget
D13: Gas Consumption (MP Boiler) | E13: mmbtu | F13: 22143.74 | G13: 9451 | H13: =F13-G13 -> 12692.74 | I13: Under Budget
D14: Gas Consumption (HP Boiler) | E14: mmbtu | F14: 3907.73 | G14: 2032 | H14: =F14-G14 -> 1875.73 | I14: Under Budget
D15: Cooling Water top up to Cooling Tower | E15: m3 | F15: 1521.33 | G15: ='JUNI 2025'!$AL$260 -> 5429 | H15: =F15-G15 -> -3907.67 | I15: Under Budget
D16: Steam | E16: Kg | F16: 11424000 | G16: ='JUNI 2025'!$AL$250 -> 102.1306 | H16: =F16-G16 -> 11423898 | I16: Under Budget
D17: Power (Process Plant) | E17: Kwh | F17: 102679 | G17: 135 | H17: =F17-G17 -> 102544 | I17: Under Budget
D18: Power (Cooling Tower) | E18: Kwh | F18: 73158 | G18: 100 | H18: =F18-G18 -> 73058 | I18: Under Budget
D19: Fractionation
D20: Cooling Water top up to Cooling Tower | E20: m3 | F20: 2622 | G20: ='JUNI 2025'!$AL$262 -> 71.80074 | H20: =F20-G20 -> 2550.1993 | I20: Under Budget
D21: Steam | E21: Kg | F21: 2318000 | G21: ='JUNI 2025'!$AL$252 -> 44.386779 | H21: =F21-G21 -> 2317955.6 | I21: Under Budget
D22: Power (Process Plant) | E22: Kwh | F22: 109440 | G22: 150 | H22: =F22-G22 -> 109290 | I22: Over Budget
D23: Power (Cooling Tower) | E23: Kwh | F23: 28747 | G23: 82 | H23: =F23-G23 -> 28665 | I23: Over Budget
D24: ACTUAL CONSUMPTION PER MT RAW MATERIAL
D25: Refinery
D26: Bleaching Earth to Poram Spec | E26: Kg/MT | F26: 9 | G26: =(G10/$G$6)*1000 -> 8.5932405 | H26: =F26-G26 -> 0.4067595 | I26: Under Budget
D27: Bleaching Earth to Branded Spec | E27: Kg/MT | F27: 18 | G27: =(G11/$G$6)*1000 -> 0 | H27: =F27-G27 -> 18 | I27: Under Budget
D28: Phosporic Acid | E28: Kg/MT | F28: 0.6 | G28: =(G12/$G$6)*1000 -> 0.49363654 | H28: =F28-G28 -> 0.10636346 | I28: Under Budget
D29: Gas Consumption (HP Boiler) | E29: Nm3/MT | F29: 4.2 | G29: =(G13/$G$6)*1000 -> 0.53056199 | H29: =F29-G29 -> 3.669438 | I29: Under Budget
D30: Gas Consumption (HP Boiler) **) | E30: mmbtu/MT | F30: 0.2 | G30: =(G14/$G$6)*1000 -> 0.11407279 | H30: =F30-G30 -> 0.085927207 | I30: Under Budget
D31: Cooling Water top up to Cooling Tower | E31: m3/MT | F31: 0.04 | G31: =(G15/$G$6)*1000 -> 0.30477421 | H31: =F31-G31 -> -0.26477421 | I31: Over Budget
D32: Steam | E32: Kg/MT | F32: 28 | G32: =(G16/$G$6)*1000000 -> 5.7334265 | H32: =F32-G32 -> 22.266574 | I32: Over Budget
D33: Power (Process Plant) | E33: Kwh/MT | F33: 4.4 | G33: =(G17/$G$6)*1000000 -> 7.5786551 | H33: =F33-G33 -> -3.1786551 | I33: Over Budget
D34: utility section ( chiller ) | E34: Kwh/MT | F34: 7.3 | G34: =(G18/$G$6)*1000000 -> 5.6138186 | H34: =F34-G34 -> 1.6861814 | I34: Over Budget
D35: Fractionation
D36: Cooling Water top up to Cooling Tower | E36: m3/MT | F36: 0.13 | G36: =(G20/$G$7)*1000 -> 0.0040354255 | H36: =F36-G36 -> 0.12596457 | I36: Under Budget
D37: Steam | E37: Kg/MT | F37: 45 | G37: =(G21/$G$7)*1000000 -> 2.4946754 | H37: =F37-G37 -> 42.505325 | I37: Under Budget
D38: Power (Process Plant) | E38: Kwh/MT | F38: 4.1 | G38: =(G22/$G$7)*1000000 -> 8.4304678 | H38: =F38-G38 -> -4.3304678 | I38: Over Budget
D39: utility section ( chiller ) | E39: Kwh/MT | F39: 4.5 | G39: =(G23/$G$7)*1000000 -> 4.6086557 | H39: =F39-G39 -> -0.10865572 | I39: Over Budget
D42: - BE Achieve dengan pemakaian consume Bleaching Earth 8,59 Kg/MT
D43: * Pemakaian Listrik Over terkait penggunaan dua unit chiller
D47: Prepared by, | G47: Checked by, | I47: Approved by,
D51: Bany Subana | F51: Reza P. Panjaitan | H51: Sudarianto | I51: Eben Jaya Ginting
D52: Admin. Process | F52: Supervisor Produksi | H52: Jr. Manager Produksi | I52: Manager Plant

Sheet Utility
D2: UTILITY (GAS, STEAM, WATER & POWER) REPORT
D3: PT. INDUSTRI NABATI LESTARI
D5: Periode 01 s/d 30 Juni 2025
D6: No | E6: Item | F6: Norma | G6: UoM | H6: Juni | K6: Consume ( MT ) | L6: Remaks
H7: Budget | I7: Actual | J7: Percentage Act.
E9: Total Feed Raw Material CPO | K9: 17813187
E10: Total Proses RBDPO | K10: ='JUNI 2025'!AL29 -> 17792607
D11: 1. | E11: GAS CONSUMPTION
E12: Incoming *base on INL | G12: mmbtu | I12: ='JUNI 2025'!$AL$241 -> 11153.207
E13: Incoming *base on Pertagas | F13: 1460.001 | G13: mmbtu | H13: 26051.47 | I13: 11483.394 | J13: =I13/H13 -> 0.4407964 | K13: =I13/K9*1000 -> 0.64465692
E14: Distribution to
E15: HP Boiler Refinery | G15: mmbtu | H15: 5907.73 | I15: 2032.278 | J15: =I15/H15 -> 0.3440032 | K15: =I15/K9*1000 -> 0.1140884
E16: MP Boiler | G16: mmbtu | H16: 20143.74 | I16: =I13-I15 -> 9451.1163 | J16: =I16/H16 -> 0.46918379 | K16: =I16/K9*1000 -> 0.53056852
E17: Total | G17: mmbtu | H17: =H15+H16 -> 26051.47 | I17: =I15+I16 -> 11483.394 | J17: =I17/H17 -> 0.4407964 | K17: =SUM(K15+K16) -> 0.64465692
D18: 2. | E18: STEAM CONSUMPTION | M18: =M19/'JUNI 2025'!E9 -> 19.783647
E19: Incoming | G19: Kg | H19: 11424000 | I19: 1817779 | J19: =I19/H19 -> 0.15911931 | K19: =I19/$K$10*1000 -> 102.16485 | M19: 1.1652568e+09
E20: Distribution to | K20: =I20/$K$9 -> 0
E21: Refinery | F21: < 28 | G21: Kg | H21: 3420000 | I21: 790670 | J21: =I21/H21 -> 0.23119006 | K21: =I21/$K$9*1000 -> 44.386779
E22: Fractionation | F22: < 45 | G22: Kg | H22: 2318000 | I22: 425736 | J22: =I22/H22 -> 0.18366523 | K22: =I22/$K$10*1000 -> 23.927691 | M22: =24*5 -> 120 | N22: =M22*2 -> 240 | O22: oring filter leaf niagara 2 bulan
E23: Others | F23: 106000 | G23: Kg | H23: 5686000 | I23: 602373 | J23: =I23/H23 -> 0.10593968 | K23: =I23/$K$9*1000 -> 33.816127
E24: Total | G24: Kg | H24: =SUM(H21:H23) -> 11424000 | I24: =SUM(I21:I23) -> 1818779 | J24: =I24/H24 -> 0.15920685 | K24: =I24/$K$9*1000 -> 102.10295
D25: 3. | E25: WATER CONSUMPTION
E26: Incoming Raw Water | G26: m3 | H26: =SUM(H30:H32) -> 41253 | I26: =SUM(I27:$I$28) -> 8754.1937 | J26: =I26/H26 -> 0.21220744 | K26: =I26/$K$9*1000 -> 0.49144455
E27: - Suplay To RO Product | I27: ='JUNI 2025'!$AL$264 -> 53.392963 | K27: =I27/$K$9*1000 -> 0.0029973841
E28: - Suplay To Proses dan Sanitary | I28: =SUM(I30:$I$32) -> 8700.8007 | K28: =I28/$K$9*1000 -> 0.48844717
E29: Rincian Outgoing Proses | K29: =I29/$K$9 -> 0
E30: Softener Product (to Refinery) | F30: < 0,04 | G30: m3 | H30: 11745 | I30: ='JUNI 2025'!$AL$260 -> 5429 | J30: =I30/H30 -> 0.46223925 | K30: =I30/$K$9*1000 -> 0.30477421 | M30: =K27+K30+K31+K32 -> 0.49144921
E31: Softener Product (to Fractionation) | F31: < 0,13 | G31: m3 | H31: 20895 | I31: ='JUNI 2025'!$AL$262 -> 71.80074 | J31: =I31/H31 -> 0.0034362642 | K31: =I31/$K$10*1000 -> 0.0040354255
E32: Others | G32: m3 | H32: 8613 | I32: ='JUNI 2025'!$AL$265 -> 3200 | J32: =I32/H32 -> 0.37153141 | K32: =I32/$K$9*1000 -> 0.17964219
E33: Total | G33: m3 | H33: =H26 -> 41253 | I33: =SUM(I27:I28) -> 8754.1937 | J33: =I33/H33 -> 0.21220744 | K33: =I33/$K$9*1000 -> 0.49144455
D34: 4 | E34: POWER CONSUMPTION
E35: Incoming
E36: PLN *base on BA Kinra | G36: Kwh | H36: =H38+H39+H41+H42 -> 704938 | I36: ='JUNI 2025'!AL270 -> Incoming | J36: =I36/H36*1000 -> #VALUE! | K36: =I36/$K$9*100000 -> #VALUE!
E37: Outgoing | K37: =I37/$K$9 -> 0
E38: - Physical Refinery Plant | F38: 4.4 | G38: Kwh | H38: 162973 | I38: 135763 | J38: =I38/H38/10 -> 0.083303983 | K38: =I38/$K$9*1000 -> 7.6214885
E39: - Refinery - Cooling Water System | F39: 7.3 | G39: Kwh | H39: 100660 | I39: 99648 | J39: =I39/H39/10 -> 0.098994635 | K39: =I39/$K$9*1000 -> 5.5940579
E40: - Refinery - Utilities | F40: 11.81 | G40: Kwh | H40: 0 | I40: ='JUNI 2025'!$AL$283 -> Others | J40: =I40/H40/10 -> #VALUE! | K40: =I40/$K$9*1000 -> #VALUE!
E41: - Dry Fractionation Plant | F41: 4.5 | G41: Kwh | H41: 287808 | I41: 150240 | J41: =I41/H41/10 -> 0.052201468 | K41: =I41/$K$10*1000 -> 8.4439565
E42: - Dry Fractionation CW System | F42: 4.1 | G42: Kwh | H42: 153497 | I42: 82129 | J42: =I42/H42/10 -> 0.05350528 | K42: =I42/$K$10*1000 -> 4.6159059
E43: - Lighting - Refinery & Dry Fractionation | F43: 241.12 | G43: Kwh | H43: 4581 | I43: ='JUNI 2025'!$AL$284 -> 0 | J43: =I43/H43 -> 0 | K43: =I43/$K$9*1000 -> 0
D45: Note untuk Power Consumption
D46: Selisih antara incoming dan outgoing dikarenakan hal berikut :
E51: Prepared by, | F51: Checked by, | K51: Approved by,
E55: Bany Subana | F55: Reza P. Panjaitan | I55: Sudarianto | K55: Eben Jaya Ginting
E56: Admin. Process | F56: Supervisor Produksi | I56: Jr. Manager Produksi | K56: Manager Plant

Sheet Prod
B2: MONTHLY PRODUCTION REPORT
B3: PT. INDUSTRI NABATI LESTARI
B4: Periode 01 s/d 30 Juni 2025
B5: NO | C5: Item | D5: Unit | E5: Juni | H5: Remaks
E6: Budget | F6: Actual | G6: Percentage Act.
B7: 1. | C7: PRODUCTION
C8: Refinery Plant
C9: Running Days | D9: Days | E9: 15 | F9: ='JUNI 2025'!$AL$6 -> 10 | G9: =(F9/E9) -> 0.66666667 | H9: Tidak Tercapai
C10: CPO Incoming | D10: Kg
C11: Total CPO Consume | D11: Kg | E11: ='JUNI 2025'!E9 -> 58900000 | F11: =F12+F13 -> 17813187 | G11: =(F11/E11) -> 0.30243102 | H11: Tidak Tercapai
C12: CPO Consume Poram | F12: ='JUNI 2025'!$AL$11 -> 17813187
C13: CPO Consume Brand | F13: ='JUNI 2025'!$AL$12 -> 0
C14: - Avg. FFA | D14: % | E14: 5 | F14: ='JUNI 2025'!$AL$13 -> 4.5701667
C15: - Avg. Moist & Impurities | D15: % | E15: 0.5 | F15: ='JUNI 2025'!$AL$14 -> 0.45666667
C16: - Avg. DOBI | D16: % | E16: 22.2 | F16: ='JUNI 2025'!$O$15 -> 0
C17: Product
C18: RBDPO | D18: Kg | E18: ='JUNI 2025'!E20 -> 55661000 | F18: ='JUNI 2025'!$AL$20 -> 16233349 | G18: =(F18/E18) -> 0.29164674 | H18: Tidak Tercapai
C19: PFAD | D19: Kg | E19: ='JUNI 2025'!E21 -> 2827000 | F19: ='JUNI 2025'!$AL$21 -> 866309 | G19: =(F19/E19) -> 0.3064411 | H19: Tidak Tercapai
C21: Fraksinasi Plant
C22: Total Proses RBDPO | D22: Kg | E22: =E25 -> 25639000 | F22: ='JUNI 2025'!$AL$29 -> 17792607 | G22: =(F22/E22) -> 0.6939665 | H22: Tercapai
C23: Total Olah RBDPO ( Feed ) | D23: Kg | E23: =E25 -> 25639000 | F23: ='JUNI 2025'!$AL$25 -> 17223447 | G23: =(F23/E23) -> 0.6717675 | H23: Tercapai
C24: Fractionation Olein IV 56
C25: RBDPO Consume | D25: Kg | E25: =E26+E27 -> 25639000 | F25: =F26+F27 -> 17792607 | G25: =(F25/E25) -> 0.6939665 | H25: Tercapai
C26: Olein IV 56 | D26: Kg | E26: ='JUNI 2025'!E33 -> 25000000 | F26: ='JUNI 2025'!$AL$33 -> 14325558 | G26: =(F26/E26) -> 0.57302232 | H26: Tercapai
C27: Stearin | D27: Kg | E27: ='JUNI 2025'!E34 -> 639000 | F27: ='JUNI 2025'!$AL$34 -> 3467049 | G27: =(F27/E27) -> 5.4257418 | H27: Tercapai
C28: Fractionation Olein IV 57 ( Bulk )
C29: RBDPO Consume | D29: Kg | E29: 0
C30: Olein IV 57 | D30: Kg | E30: 0 | F30: 0 | G30: 0
C31: Stearin | D31: Kg | E31: 0
C32: Fractionation Olein IV 58 ( bulk )
C33: CPO | D33: Kg | E33: 1812101.9 | G33: =(F33/E33)*100 -> 0
C34: RBDPO Consume | D34: Kg | E34: =E35+E36 -> 22714 | F34: =F35+F36 -> 0 | G34: =(F34/E34)*100 -> 0
C35: Olein IV 58 | D35: Kg | E35: 15900 | G35: =(F35/E35)*100 -> 0
C36: Stearin | D36: Kg | E36: 6814 | G36: =(F36/E36)*100 -> 0
C37: Fractionation Olein IV 58
C38: RBDPO Consume | D38: Kg | E38: 21429000 | F38: =F39+F40 -> 0 | G38: =(F38/E38)*100 -> 0 | H38: Tidak Tercapai
C39: Olein IV 58 | D39: Kg | E39: 15000000 | F39: ='JUNI 2025'!$AL$46 -> 0 | G39: =(F39/E39)*100 -> 0 | H39: Tidak Tercapai
C40: Stearin | D40: Kg | E40: 6429000 | F40: ='JUNI 2025'!$AL$47 -> 0 | G40: =(F40/E40)*100 -> 0 | H40: Tidak Tercapai
C41: Fractionation Olein IV 60
C42: CPO | E42: 2234607.2 | F42: 0 | G42: =(F42/E42)*100 -> 0
C43: RBDPO Consume | D43: Kg | E43: =E44+E45 -> 533 | F43: 0 | G43: =(F43/E43)*100 -> 0
C44: Olein IV 60 Salvaco | D44: Kg | E44: 320 | F44: ='JUNI 2025'!AL56 -> 0 | G44: =(F44/E44)*100 -> 0
C45: Soft Stearin | D45: Kg | E45: 213 | F45: ='JUNI 2025'!AL57 -> 0 | G45: =(F45/E45)*100 -> 0
B46: 2. | C46: % YIELD
C47: RBDPO | D47: % | E47: 94.77 | F47: ='JUNI 2025'!AL60 -> 94.787564 | G47: =(F47/E47)*100 -> 100.01853 | H47: Tercapai
C48: PFAD | D48: % | E48: 4.5 | F48: =(F19/(F11))*100 -> 4.8633016 | G48: =(F48/E48)*100 -> 108.07337 | H48: Tercapai
C49: Olein IV 56 | D49: % | E49: 82 | F49: =F26/(F26+F27)*100 -> 80.514103 | G49: =(F49/E49)*100 -> 98.187931 | H49: Tidak Tercapai
C50: Stearin | D50: % | E50: 18 | F50: =(F27/F25)*100 -> 19.485897 | G50: =(F50/E50)*100 -> 108.25498 | H50: Tercapai
C51: Olein IV 57 ( Bulk ) | D51: % | E51: 75 | F51: 0 | G51: =(F51/E51)*100 -> 0
C52: Stearin | D52: % | E52: 25 | F52: 0 | G52: =(F52/E52)*100 -> 0
C53: Olein IV 57 ( Retail ) | D53: % | E53: 75 | F53: =F35/(F35+F36)*100 -> #DIV/0! | G53: =(F53/E53)*100 -> #DIV/0!
C54: Stearin | D54: % | E54: 25 | F54: =(F36/F34)*100 -> #DIV/0! | G54: =(F54/E54)*100 -> #DIV/0!
C55: Olein IV 58 | D55: % | E55: 70 | F55: =F39/(F39+F40)*100 -> #DIV/0! | G55: =(F55/E55)*100 -> #DIV/0!
C56: Stearin | D56: % | E56: 30 | F56: =(F40/F38)*100 -> #DIV/0! | G56: =(F56/E56)*100 -> #DIV/0!
C57: Olein IV 60 | D57: % | E57: 60 | F57: 0 | G57: =(F57/E57)*100 -> 0
C58: Soft Stearin | D58: % | E58: 40 | F58: 0 | G58: =(F58/E58)*100 -> 0
B59: 3. | C59: CHEMICAL CONSUMABLE
C60: Bleaching Earth to Poram Spec | D60: Kg | E60: 675000 | F60: ='JUNI 2025'!$AL$75 -> 153073 | G60: =(F60/E60)*100 -> 22.677481 | I60: =E61*2500 -> 22500
D61: Kg/MT | E61: ='JUNI 2025'!E75 -> 9 | F61: =(F60/F12)*1000 -> 8.5932405 | G61: =(F61/E61)*100 -> 95.48045 | H61: Tercapai | I61: =I60*30 -> 675000
C62: Bleaching Earth to Branded Spec | D62: Kg | E62: 1200 | F62: ='JUNI 2025'!AL12 -> 0 | G62: =(F62/E62)*100 -> 0 | I62: =2500*30*1.6% -> 1200
D63: Kg/MT | E63: 16 | G63: =(F63/E63)*100 -> 0
C64: Phosporic Acid | D64: Kg | E64: =450*1000 -> 450000 | F64: ='JUNI 2025'!$AL$83 -> 8793.24 | G64: =(F64/E64)*100 -> 1.9540533 | I64: =2500*30*0.6% -> 450
D65: Kg/MT | E65: 0.6 | F65: =(F64/F11)*1000 -> 0.49363654 | G65: =(F65/E65)*100 -> 82.272757 | H65: Tercapai
B66: 4. | C66: OIL LOSSES
C67: (Loss)/Gain | D67: % | E67: -0.73 | F67: ='JUNI 2025'!$AL$85 -> -0.3491346 | G67: =(F67/E67)*100 -> 47.826658 | H67: Tidak Tercapai
C68: % Oil Content | D68: % | E68: 22 | F68: ='JUNI 2025'!$AL$87 -> 21.014 | G68: =(F68/E68)*100 -> 95.518182
C69: Spent Bleaching Earth | D69: Kg | E69: 413199.36 | F69: ='JUNI 2025'!$AL$88 -> 156289.68 | G69: =(F69/E69)*100 -> 37.824278
B70: NB :
B71: - BE Achieve dengan pemakaian consume Bleaching Earth 8,59 Kg/MT
B72: - Untuk hari olah Produksi adalah 10 Hari, menyesuaikan dengan kondisi jadwal shipment RIYA IV 56 12.000 MT dan 1.000 MT untuk kebutuhan Packaging
B74: - Total CPO Proses sebesar : 17.813 MT dengan opening stock sebesar 22.926 MT
A77: Prepared by, | D77: Checked by, | H77: Approved by,
A81: Bany Subana | D81: Reza P. Panjaitan | F81: Sudarianto | H81: Eben Jaya Ginting
A82: Admin. Process | D82: Supervisor Produksi | F82: Jr. Manager Produksi | H82: Manager Plant

Sheet OIP Refinery 
B4: Oil In Plant (OIP) Refinery pmg 2 | I4: FEBUARI | J4: OIP | M4: TK131 RPO | P4: TK132 RPO | S4: TOTAL STOK RPO DI PLANT
B5: Vessel | C5: Operating Volume (m3) | D5: Oil Density (kg/m3) | E5: MT | F5: Level yg diisi | G5: Actual OIP (Kg) | I5: Tanggal | J5: Opening Stock | K5: Closing Stock | L5: balance stok | M5: Opening Stock | N5: Closing Stock | O5: CONSUMP stok | P5: Opening Stock | Q5: Closing Stock | R5: CONSUMP stok
B6: 2MX312 | C6: 5.67 | D6: 850 | E6: =C6*D6/1000 -> 4.8195 | F6: 0 | G6: =(F6*E6/100)*1000 -> 0 | I6: 45809
B7: 2VE611A | C7: 47.22 | D7: 850 | E7: =C7*D7/1000 -> 40.137 | F7: 0 | G7: =(F7*E7/100)*1000 -> 0 | I7: 45810
B8: 2VE611B | C8: 47.22 | D8: 850 | E8: =C8*D8/1000 -> 40.137 | F8: 0 | G8: =(F8*E8/100)*1000 -> 0 | I8: 45811
B9: 2VE612 | C9: 35.68 | D9: 850 | E9: =C9*D9/1000 -> 30.328 | F9: 0 | G9: =(F9*E9/100)*1000 -> 0 | I9: 45812
B10: 2VE661 | C10: 10.8 | D10: 850 | E10: =C10*D10/1000 -> 9.18 | F10: 0 | G10: =(F10*E10/100)*1000 -> 0 | I10: 45813
B11: FL621 | C11: 10.1 | D11: 850 | E11: =C11*D11/1000 -> 8.585 | F11: 0 | G11: =(F11*E11/100)*1000 -> 0 | I11: 45814 | L11: =J11-K11 -> 0
B12: FL622 | C12: 10.1 | D12: 850 | E12: =C12*D12/1000 -> 8.585 | F12: 0 | G12: =(F12*E12/100)*1000 -> 0 | I12: 45815 | L12: =J12-K12 -> 0
B13: FL623 | C13: 10.1 | D13: 850 | E13: =C13*D13/1000 -> 8.585 | F13: 0 | G13: =(F13*E13/100)*1000 -> 0 | I13: 45816 | J13: 0 | K13: 311880 | L13: =K13 -> 311880 | N13: 0 | Q13: 174609
B14: FL624 | C14: 10.1 | D14: 850 | E14: =C14*D14/1000 -> 8.585 | F14: 0 | G14: =(F14*E14/100)*1000 -> 0 | I14: 45817 | J14: 311880 | K14: 316289 | L14: =J14-K14 -> -4409 | N14: 44191 | P14: 174609 | Q14: 38852 | R14: =P14-Q14 -> 135757 | S14: =R14+O14+L14 -> 131348
B15: FL625 | C15: 10.1 | D15: 850 | E15: =C15*D15/1000 -> 8.585 | F15: 0 | G15: =(F15*E15/100)*1000 -> 0 | I15: 45818 | J15: 316289 | K15: 310412 | L15: =J15-K15 -> 5877 | M15: 44191 | N15: 405272 | O15: =M15-N15 -> -361081 | P15: 38852 | Q15: 38852 | R15: =P15-Q15 -> 0 | S15: =R15+O15+L15 -> -355204
B16: 2VE701 | C16: 72.13 | D16: 850 | E16: =C16*D16/1000 -> 61.3105 | F16: 55 | G16: =(F16*E16/100)*1000 -> 33720.775 | I16: 45819 | J16: 310412 | K16: 316896 | L16: =J16-K16 -> -6484
B17: 2VE751 | C17: 4.28 | D17: 860 | E17: =C17*D17/1000 -> 3.6808 | F17: 50 | G17: =(F17*E17/100)*1000 -> 1840.4 | I17: 45820 | J17: 316896 | K17: 303575 | L17: =J17-K17 -> 13321
B18: 2HE721A (tube) | C18: 10 | D18: 810 | E18: =C18*D18/1000 -> 8.1 | F18: 100 | G18: =(F18*E18/100)*1000 -> 8100 | I18: 45821 | J18: 326546 | K18: 307265 | L18: =J18-K18 -> 19281
B19: 2HE721A (shell) | C19: 21.8 | D19: 800 | E19: =C19*D19/1000 -> 17.44 | F19: 45 | G19: =(F19*E19/100)*1000 -> 7848 | I19: 45822 | J19: 307265 | K19: 317800 | L19: =J19-K19 -> -10535
B20: HE721B (tube) | C20: 10 | D20: 810 | E20: =C20*D20/1000 -> 8.1 | F20: 100 | G20: =(F20*E20/100)*1000 -> 8100 | I20: 45823 | J20: 317800 | K20: 303575 | L20: =J20-K20 -> 14225
B21: 2HE722 | C21: 11.4 | D21: 790 | E21: =C21*D21/1000 -> 9.006 | F21: 100 | G21: =(F21*E21/100)*1000 -> 9006 | I21: 45824 | J21: 303575 | K21: 319541 | L21: =J21-K21 -> -15966
B22: 2PR731 | C22: 14 | D22: 790 | E22: =C22*D22/1000 -> 11.06 | F22: 35 | G22: =(F22*E22/100)*1000 -> 3871 | I22: 45825 | J22: 319541 | K22: 190797 | L22: =J22-K22 -> 128744
B23: 2DE732 | C23: 149.76 | D23: 790 | E23: =C23*D23/1000 -> 118.3104 | F23: 100 | G23: =(F23*E23/100)*1000 -> 118310.4 | I23: 45826 | L23: =J23-K23 -> 0
C24: =SUM(C6:C23) -> 490.46 | E24: =SUM(E6:E23) -> 404.5342 | I24: 45827 | L24: =J24-K24 -> 0
F25: Total OIP = | G25: =SUM(G6:G24) -> 190796.57 | I25: 45828 | L25: =J25-K25 -> 0
I26: 45829 | L26: =J26-K26 -> 0 | U26: =L26+L25 -> 0
I27: 45830 | L27: =J27-K27 -> 0
I28: 45831 | L28: =J28-K28 -> 0
I29: 45832 | L29: =J29-K29 -> 0
B30: Solar Daily Tank HPB | I30: 45833 | L30: =J30-K30 -> 0
B31: 2TK726 | C31: =5.3+0.78 -> 6.08 | D31: 840 | E31: =C31*D31/1000 -> 5.1072 | F31: 0 | G31: =F31*E31/100*1000 -> 0 | H31: 0 | I31: 45834
I32: 45835
B33: Stock Chemicals In Plant | I33: 45836
C34: Read | D34: End Read | E34: Consumption | I34: 45837
B35: BE | I35: 45838
B36: 630A
B37: 630B
B38: H3PO4
B39: NaOH
B40: Citrid Acid

Sheet Oip Fract .
A4: Oil In Plant (OIP) Fraksinasi | I4: OIP | S4: BUFFER TANK | W4: DIRECT
A5: RBDPO OIP pmg 2 | I5: RPO CR | M5: OLEIN | P5: STEARIN | S5: TK131 RPO | U5: TK132 RPO
A6: Vessel | B6: Operating Volume (m3) | C6: Oil Density (kg/m3) | D6: MT | E6: Level Transmitter (1%/MT) | F6: Level (%) | G6: Kg | I6: Tanggal | J6: Opening Stock | K6: Closing Stock | L6: balance stok | M6: Opening Stock | N6: Closing Stock | O6: balance stok | P6: Opening Stock | Q6: Closing Stock | R6: balance stok | S6: Opening Stock | T6: Closing Stock | U6: Opening Stock | V6: Closing Stock
A7: 2CR1201 | B7: 70.51 | C7: 890 | D7: 60 | E7: =D7/100 -> 0.6 | G7: =E7*F7*1000 -> 0 | I7: 45809
A8: 2CR1202 | B8: 70.51 | C8: 890 | D8: 60 | E8: =D8/100 -> 0.6 | G8: =E8*F8*1000 -> 0 | I8: 45810
A9: 2CR1203 | B9: 70.51 | C9: 890 | D9: 60 | E9: =D9/100 -> 0.6 | G9: =E9*F9*1000 -> 0 | I9: 45811
A10: 2CR1204 | B10: 70.51 | C10: 890 | D10: 60 | E10: =D10/100 -> 0.6 | G10: =E10*F10*1000 -> 0 | I10: 45812
A11: 2CR1205 | B11: 70.51 | C11: 890 | D11: 60 | E11: =D11/100 -> 0.6 | G11: =E11*F11*1000 -> 0 | I11: 45813
A12: 2CR1206 | B12: 70.51 | C12: 890 | D12: 60 | E12: =D12/100 -> 0.6 | G12: =E12*F12*1000 -> 0 | I12: 45814
A13: 2CR1207 | B13: 70.51 | C13: 890 | D13: 60 | E13: =D13/100 -> 0.6 | G13: =E13*F13*1000 -> 0 | I13: 45815
A14: 2CR1208 | B14: 70.51 | C14: 890 | D14: 60 | E14: =D14/100 -> 0.6 | G14: =E14*F14*1000 -> 0 | I14: 45816 | J14: 360000 | K14: 645180 | L14: =J14-K14 -> -285180 | M14: 26305 | N14: 56600 | P14: 0 | Q14: 0 | S14: 34872 | T14: 34865 | U14: 287331 | V14: 52290 | W14: 30000
A15: 2CR1209 | B15: 70.51 | C15: 890 | D15: 60 | E15: =D15/100 -> 0.6 | G15: =E15*F15*1000 -> 0 | I15: 45817 | J15: 645180 | K15: 598560 | L15: =J15-K15 -> 46620 | M15: 56600 | N15: 20315 | P15: 0 | Q15: 0 | R15: 0 | S15: 34865 | T15: =105375+W15 -> 195375 | U15: 52290 | V15: 53075 | W15: 90000
A16: 2CR1210 | B16: 70.51 | C16: 890 | D16: 60 | E16: =D16/100 -> 0.6 | G16: =E16*F16*1000 -> 0 | I16: 45818 | J16: 598560 | K16: 720000 | L16: =J16-K16 -> -121440 | M16: 20315 | N16: 23293 | O16: =M16-N16 -> -2978 | P16: 0 | Q16: 6568 | R16: =P16-Q16 -> -6568 | S16: 105375 | T16: =296343+W16 -> 316343 | U16: 53075 | V16: 53075 | W16: 20000
A17: 2CR1211 | B17: 70.51 | C17: 890 | D17: 60 | E17: =D17/100 -> 0.6 | G17: =E17*F17*1000 -> 0 | I17: 45819 | J17: 720000 | K17: 600000 | L17: =J17-K17 -> 120000 | M17: 23293 | N17: 23284.35 | O17: =M17-N17 -> 8.65 | P17: 6568 | Q17: 7139 | R17: =P17-Q17 -> -571 | S17: 296343 | T17: 207866 | U17: 53075 | V17: 75063 | W17: 60000
A18: 2CR1212 | B18: 70.51 | C18: 890 | D18: 60 | E18: =D18/100 -> 0.6 | G18: =E18*F18*1000 -> 0 | I18: 45820 | J18: 600000 | K18: 480000 | L18: =J18-K18 -> 120000 | M18: 23284 | N18: 17184 | O18: =M18-N18 -> 6100 | P18: 7139 | Q18: 5426 | R18: =P18-Q18 -> 1713 | S18: 207866 | T18: 175767 | U18: 75063 | V18: 97032
A19: 2CR1213 | B19: 70.51 | C19: 890 | D19: 60 | E19: =D19/100 -> 0.6 | G19: =E19*F19*1000 -> 0 | I19: 45821 | J19: 480000 | K19: 540000 | L19: =J19-K19 -> -60000 | M19: 17184 | N19: 11414 | O19: =M19-N19 -> 5770 | P19: 0 | Q19: 0 | R19: =P19-Q19 -> 0 | S19: 175767 | T19: 200007 | U19: 97032 | V19: 115080 | W19: 70000
A20: 2CR1214 | B20: 70.51 | C20: 890 | D20: 60 | E20: =D20/100 -> 0.6 | G20: =E20*F20*1000 -> 0 | I20: 45822 | J20: 540000 | K20: 333960 | L20: =J20-K20 -> 206040 | M20: 11414 | N20: 43930 | O20: =M20-N20 -> -32516 | P20: 0 | Q20: 0 | R20: =P20-Q20 -> 0 | S20: 200007 | T20: 158440 | U20: 115080 | V20: 130221 | W20: 8000
A21: 2CR1215 | B21: 70.51 | C21: 890 | D21: 60 | E21: =D21/100 -> 0.6 | G21: =E21*F21*1000 -> 0 | I21: 45823 | J21: 333960 | K21: 619320 | L21: =J21-K21 -> -285360 | M21: 11324 | N21: 11324 | O21: =M21-N21 -> 0 | P21: 0 | Q21: 0 | R21: =P21-Q21 -> 0 | S21: 158440 | T21: 59863 | U21: 130221 | V21: 148827 | W21: 15000
I22: 45824 | J22: 619320 | K22: 600000 | L22: =J22-K22 -> 19320 | M22: 11324 | N22: 26705 | O22: =M22-N22 -> -15381 | P22: 0 | Q22: 0 | R22: =P22-Q22 -> 0 | S22: 59863 | T22: 34480 | U22: 148827 | V22: 165316
F23: Total RBDPO | G23: =SUM(G7:G21) -> 0 | I23: 45825 | J23: 600000 | M23: 26705 | N23: 23191 | O23: =M23-N23 -> 3514 | P23: 0 | Q23: 0 | R23: =P23-Q23 -> 0 | S23: 34480 | T23: 34859 | U23: 165316 | V23: 78396
I24: 45826 | R24: =P24-Q24 -> 0 | S24: 34859 | T24: 34859 | U24: 78396 | V24: 272307 | X24: =V24-U24 -> 193911
A25: Olein OIP | I25: 45827 | R25: =P25-Q25 -> 0
A26: Vessel | B26: Operating Volume (m3) | C26: Oil Density (kg/m3) | D26: MT | E26: Level Transmitter (1%/MT) | F26: Level (%) | G26: Kg | I26: 45828
A27: 2TK261 | B27: 15.95 | C27: 885 | D27: =B27*C27/1000 -> 14.11575 | E27: =D27/100 -> 0.1411575 | F27: 69.5 | G27: =E27*F27*1000 -> 9810.4463 | I27: 45829
A28: 2CL251 | B28: 3.02 | C28: 885 | D28: =B28*C28/1000 -> 2.6727 | E28: =D28/100 -> 0.026727 | F28: 0 | G28: =E28*F28*1000 -> 0 | I28: 45830
A29: 2TK221 | B29: 82.48 | C29: 885 | D29: =B29*C29/1000 -> 72.9948 | E29: =D29/100 -> 0.729948 | F29: 0 | G29: =E29*F29*1000 -> 0 | I29: 45831
A30: 2TK241 | B30: 16.95 | C30: 885 | D30: =B30*C30/1000 -> 15.00075 | E30: =D30/100 -> 0.1500075 | F30: 89.2 | G30: =E30*F30*1000 -> 13380.669 | I30: 45832
G31: =SUM(G27:G30) -> 23191.115 | I31: 45833
A32: Stearin OIP | I32: 45834
A33: Melting Tank | B33: Panjang (m) | C33: Lebar (m) | D33: tinggi (m) | E33: Density | F33: Tinggi Sounding (Cm) Maks 4,4 m | G33: Kg | I33: 45835
A34: TK231 A | B34: 12.2 | C34: 1.75 | D34: 1.52 | E34: 0.88 | F34: 0 | G34: =B34*C34*D34*E34*F34/100 -> 0 | I34: 45836
A35: TK231 B | B35: 12.2 | C35: 1.75 | D35: 1.52 | E35: 0.88 | F35: 0 | G35: =B35*C35*D35*E35*F35/100 -> 0 | I35: 45837
F36: Total STEARIN | G36: =SUM(G34:G35) -> 0 | I36: 45838
T38: =S34+U34 -> 0

Sheet 2025
C2: PRODUCTION REPORT 2025
L3: ok | M3: ok | N3: ok
B4: No | C4: ITEM | D4: Budget / Norma | E4: UoM | F4: YEARLY REPORT | T4: Yearly Report | U4: Yearly Report RKAP (Budget) | V4: Yearly Report RKAP
F5: JANUARI | G5: FEBRUARI | H5: MARET | I5: APRIL | J5: MEI | K5: JUNI | L5: JULI | M5: AGUSTUS | N5: SEPTEMBER | O5: OKTOBER | P5: NOVEMBER | Q5: DESEMBER | R5: DESEMBER | T5: TOTAL (Kg) | U5: TOTAL (Kg) | V5: TOTAL (%)
B6: 1 | C6: PRODUCTION | T6: Production | U6: Production | V6: Production | X6: =30*5 -> 150 | DG6: 29 | DH6: 30 | DI6: 31
C7: Refinery | T7: Refinery | U7: Refinery | V7: Refinery | DE7: CPO Olah | DF7: Kg | DG7: 1971320 | DH7: 2015120 | DI7: 2015230 | AIU7: Sounding | AIV7: Production | AIW7: Diff
C8: Running Days | D8: 300 | E8: Day | F8: 0 | G8: ='[6]FEBUARI 2025'!$AK$6 -> 13 | H8: ='JUNI 2025'!AL6 -> 10 | I8: 0 | J8: 0 | K8: ='JUNI 2025'!AL6 -> 10 | R8: ='[7]Desember 24'!AL9 -> 0 | T8: =SUM(F8:R8) -> 33 | U8: 231 | V8: =T8/U8*100 -> 14.285714 | X8: =T11-K11 -> 20126670 | Y8: =X8/2500 -> 8050.668 | OR8: Poram | AEE8: 14 Juni | AEF8: 15 Juni | AIT8: CPO | AIU8: 11008948 | AIV8: =T11 -> 37939857 | AIW8: =AIU8-AIV8 -> -26930909
C9: Ratio Run CPO | G9: 0 | H9: 0 | K9: 0 | R9: ='[7]Desember 24'!AL10 -> 0 | X9: =X8/2500/150 -> 53.67112 | Y9: =Y8/150 -> 53.67112 | Z9: =Y9*100 -> 5367.112
C10: Utilitas CPO | G10: 0 | H10: 0 | K10: 0 | R10: =R11/R14*100 -> #DIV/0! | T10: =AVERAGE(F10:Q10) -> 0
C11: CPO Consume Total | D11: 707651000 | E11: Kg | F11: 0 | G11: ='[6]FEBUARI 2025'!$AK$9 -> 16619582 | H11: ='[8]MARET 2025'!$AK$9 -> 3507088 | I11: 0 | J11: 0 | K11: ='JUNI 2025'!AL9 -> 17813187 | R11: ='[7]Desember 24'!AL11 -> 0 | T11: =SUM(F11:Q11) -> 37939857 | U11: 421374000 | V11: =T11/U11 -> 0.090038439 | X11: =T11/D11*100 -> 5.3613797 | AX11: =T11/D11 -> 0.053613797 | DE11: HP Boiler | DF11: mmbtu | DG11: 251.19642 | DH11: 257.91391 | DI11: 251.51265 | OO11: 26946.108 | OP11: 17383.234 | OR11: RBDPO Olah | AEE11: =35.8500000000058*1000 -> 35850 | AIT11: PFAD | AIU11: 566885 | AIV11: =T20 -> 1775916 | AIW11: =AIU11-AIV11 -> -1209031
C12: CPO Consume Poram | E12: Kg | F12: 0 | G12: =G11 -> 16619582 | H12: =H11 -> 3507088 | I12: 0 | J12: 0 | K12: =K11 -> 17813187 | R12: ='[7]Desember 24'!AL12 -> #DIV/0! | T12: =SUM(F12:Q12) -> 37939857 | AA12: =30*5 -> 150 | AB12: 5.9 | AC12: %
C13: CPO Consume Brand | E13: Kg | F13: 0 | G13: 0 | H13: 0 | I13: 0 | J13: 0 | R13: ='[7]Desember 24'!AL13 -> #DIV/0! | T13: =SUM(F13:Q13) -> 0 | AA13: 7.37 | AX13: =AW13/Q13 -> #DIV/0!
C14: Budget CPO Olah | E14: Kg | F14: 0 | G14: ='JUNI 2025'!E9 -> 58900000 | H14: 58900 | I14: 58900 | J14: 58900 | K14: 58900 | T14: =SUM(F14:Q14) -> 59135600 | Y14: =T11/2500/T8 -> 459.87705
C15: - FFA | D15: 5 | E15: % | F15: 0 | G15: ='[6]FEBUARI 2025'!$AK$13 -> 3.5869231 | H15: ='JUNI 2025'!AL13 -> 4.5701667 | I15: 0 | J15: 0 | K15: ='JUNI 2025'!AL13 -> 4.5701667 | R15: ='[7]Desember 24'!AL14 -> #DIV/0! | T15: =AVERAGE(F15:Q15) -> 2.1212094 | U15: =AVERAGE(G15:S15) -> #DIV/0! | V15: =AVERAGE(H15:T15) -> #DIV/0! | Y15: 2 | Z15: =G11/2500000/13 -> 0.51137175 | DE15: Steam Ref | DF15: Kg | DG15: 182230 | DH15: 190070 | DI15: 197800 | OO15: =T11/1000 -> 37939.857 | OP15: =(T26+T49+T35)/1000 -> 21985.753 | OR15: =SUM(OR16:OR17) -> #REF! | AGV15: 2000
C16: - Moist & Impurities | D16: 0.5 | E16: % | F16: 0 | G16: ='[6]FEBUARI 2025'!$AK$14 -> 0.36807692 | H16: ='JUNI 2025'!AL14 -> 0.45666667 | I16: 0 | J16: 0 | K16: ='JUNI 2025'!P14 -> 0.43 | R16: ='[7]Desember 24'!AL15 -> #DIV/0! | T16: =AVERAGE(F16:Q16) -> 0.20912393 | U16: =AVERAGE(G16:S16) -> #DIV/0! | V16: =AVERAGE(H16:T16) -> #DIV/0! | Y16: 3 | Z16: =H12/2500000/13 -> 0.1079104 | DF16: Kg/MT | DG16: =DG15/(DG7/1000) -> 92.440598 | DH16: =DH15/(DH7/1000) -> 94.321926 | DI16: =DI15/(DI7/1000) -> 98.152568 | OR16: =#REF!/1000 -> #REF! | OS16: =OR16/OR15*100 -> #REF! | AGU16: 0.942 | AGV16: =AGU16*AGV15 -> 1884 | AGW16: Refinery | AIT16: Olein IV 56 | AIU16: 9594130 | AIV16: =T27 -> 17678258 | AIW16: =AIU16-AIV16 -> -8084128
C17: - DOBI | D17: 2,20 Min | E17: % | F17: 0 | G17: 0 | H17: 0 | I17: 0 | J17: 0 | R17: ='[7]Desember 24'!AL16 -> #DIV/0! | T17: =AVERAGE(F17:Q17) -> 0 | U17: =AVERAGE(G17:S17) -> #DIV/0! | V17: =AVERAGE(H17:T17) -> #DIV/0! | OO17: =SUM(OO15:OO16) -> 37939.857 | OP17: =SUM(OP15:OP16) -> 21985.753 | OR17: =#REF!/1000 -> #REF! | OS17: =OR17/OR15*100 -> #REF! | AGU17: 0.05 | AGV17: =AGU17*AGV15 -> 100 | AIT17: Stearin | AIU17: 2161151 | AIV17: =T28 -> 4168962 | AIW17: =AIU17-AIV17 -> -2007811
C18: Product | G18: 0 | T18: Product | U18: Product | V18: Product | OO18: =OO17/OO11*100 -> 140.79902 | OP18: =OP17/OP11*100 -> 126.47677 | AEG18: Product OIP | AEQ18: Juni | AER18: Sisa Product OIP
C19: RbdPO | D19: 668731 | E19: Kg | F19: 0 | G19: ='[6]FEBUARI 2025'!$AK$19 -> 15720849 | H19: ='[8]MARET 2025'!$AK$19 -> 2972524 | I19: 0 | J19: 0 | K19: ='JUNI 2025'!AL20+'JUNI 2025'!AL18+'JUNI 2025'!AL19 -> 16884686 | R19: ='[7]Desember 24'!AL18 -> 0 | T19: =SUM(F19:Q19) -> 35578059 | U19: 399336000 | V19: =T19/U19*100 -> 8.9093042 | AX19: =AX20/D19 -> 53.192583 | DE19: Tahun 2021 | AEE19: 136360 | AEF19: 109340 | AEG19: =SUM(AEE19:AEF19) -> 245700 | AEQ19: 34157.88 | AER19: =AEG19-AEQ19 -> 211542.12 | AGV19: =AGV16 -> 1884
C20: PFAD | D20: 33967 | E20: Kg | F20: 0 | G20: ='[6]FEBUARI 2025'!$AK$20 -> 769266 | H20: ='[8]MARET 2025'!$AK$20 -> 140341 | I20: 0 | J20: 0 | K20: ='JUNI 2025'!AL21 -> 866309 | R20: ='[7]Desember 24'!AL19 -> 0 | T20: =SUM(F20:Q20) -> 1775916 | U20: 19024000 | V20: =T20/U20*100 -> 9.3351346 | AX20: =T26+T30+T35+T49+T39 -> 35571529 | DE20: Items | DG20: Agustus | DH20: Oktober | OO20: =OO11-OO17 -> -10993.749 | OP20: =OP11-OP17 -> -4602.5195 | OR20: Olein IV 58 | OS20: 0 | PE20: 564.70507 | PF20: =OS20/PE20*100 -> 0 | AEE20: 13800 | AEF20: 2800 | AEG20: =SUM(AEE20:AEF20) -> 16600 | AEQ20: 1469.85 | AER20: =AEG20-AEQ20 -> 15130.15 | AGU20: 0.75 | AGV20: =AGU20*AGV19 -> 1413
C21: Fractionation
C22: Running Days | G22: ='[6]FEBUARI 2025'!$AK$22 -> 14 | H22: ='JUNI 2025'!AL23 -> 10
C23: Total Filling Crystalizer ( Feed ) | D23: 426016000 | E23: Kg | F23: =F231 -> 0 | G23: ='[6]FEBUARI 2025'!$AK$24 -> 14060204 | H23: ='[8]MARET 2025'!$AK$24 -> 4329104 | I23: =I231 -> 0 | J23: =J231 -> 0 | K23: ='JUNI 2025'!AL25 -> 17223447 | T23: =SUM(F23:Q23) -> 35612755 | X23: =T23/G23 -> 2.5328761
C24: Total Proses RBDPO | E24: Kg | F24: 0 | G24: ='[6]FEBUARI 2025'!$AK$28 -> 13935326 | H24: ='[8]MARET 2025'!$AK$31 -> 3843596 | I24: 0 | J24: 0 | K24: =K26 -> 17792607 | T24: =SUM(F24:Q24) -> 35571529
C25: Fractionation OLEIN IV 56 | T25: Olein IV 56 | U25: Olein IV 56 | V25: Olein IV 56 | DG25: 24 | DH25: 2 | DI25: 3 | OR25: Olein IV 60 | OS25: =80.53776+PF35 -> 120.78492 | PE25: 4695.7554 | PF25: =OS25/PE25*100 -> 2.5722149 | AGU25: 0.25 | AGV25: =AGU25*AGV19 -> 471
C26: RBDPO Consume | E26: Kg | F26: 0 | G26: =G27+G28 -> 211017 | H26: =H27+H28 -> 3843596 | I26: 0 | J26: 0 | K26: =K27+K28 -> 17792607 | R26: =R27+R28 -> 0 | T26: =T27+T28 -> 21847220 | U26: =U27+U28 -> 87311000 | V26: =T26/U26*100 -> 25.0223 | DE26: CPO Olah | DF26: Kg | DG26: 2000530 | DH26: 2005167 | DI26: 2025879 | AEE26: =95.28%*AEE11 -> 34157.88 | AEG26: =AEE19-AEQ19 -> 102202.12 | AIQ26: CPO Feed - Sounding
C27: OLEIN IV 56 | D27: 349333 | E27: Kg | F27: 0 | G27: ='[6]FEBUARI 2025'!$AK$32 -> 170017 | H27: ='[8]MARET 2025'!$AK$32 -> 3182683 | I27: 0 | J27: 0 | K27: ='JUNI 2025'!AL33 -> 14325558 | R27: ='[7]Desember 24'!AL22 -> 0 | T27: =SUM(F27:Q27) -> 17678258 | U27: 71627000 | V27: =T27/U27*100 -> 24.680997 | DE27: HP Boiler | DF27: mmbtu | DG27: 255.53619 | DH27: 255.09239 | DI27: 260.82455 | OO27: =#REF!/1000 -> #REF! | OR27: INL 900 ml | OS27: 0 | PE27: 9.75348 | PF27: =(OS27*PE27)/1000 -> 0 | AEE27: =4.1%*AEE11 -> 1469.85 | AEG27: =AEE20-AEQ20 -> 12330.15
C28: STEARIN | D28: 76683 | E28: Kg | F28: 0 | G28: ='[6]FEBUARI 2025'!$AK$33 -> 41000 | H28: ='[8]MARET 2025'!$AK$33 -> 660913 | I28: 0 | J28: 0 | K28: ='JUNI 2025'!AL34 -> 3467049 | R28: ='[7]Desember 24'!AL23 -> 0 | T28: =SUM(F28:Q28) -> 4168962 | U28: 15684000 | V28: =T28/U28*100 -> 26.580987 | DE28: Steam Ref | DF28: Kg | DG28: 146000 | DH28: 151100 | DI28: 152900 | OO28: 1796 | OR28: Salvaco 1L | OS28: 1262 | PE28: 10.86 | PF28: =(OS28*PE28)/1000 -> 13.70532 | AIQ28: Report Prod
C29: Fractionation OLEIN IV 57 ( Bulk ) | T29: Olein IV 57 ( Bulk ) | U29: Olein IV 57 ( Bulk ) | V29: Olein IV 57 ( Bulk )
C30: RBDPO Consume | E30: Kg | F30: 0 | G30: 0 | H30: 0 | I30: 0 | J30: 0 | R30: =R31+R32 -> 0 | T30: =T31+T32 -> 0 | U30: =U31+U32 -> 5121000 | V30: =T30/U30*100 -> 0 | AX30: =T30+T35 -> 0
C31: OLEIN IV 57 | E31: Kg | F31: 0 | G31: 0 | H31: 0 | I31: 0 | J31: 0 | R31: ='[7]Desember 24'!AL26 -> 0 | T31: =SUM(F31:Q31) -> 0 | U31: 3934000 | V31: =T31/U31*100 -> 0 | AX31: =T31+T36 -> 0
C32: STEARIN | E32: Kg | F32: 0 | G32: 0 | H32: 0 | I32: 0 | J32: 0 | R32: ='[7]Desember 24'!AL27 -> 0 | T32: =SUM(F32:Q32) -> 0 | U32: 1187000 | V32: =T32/U32*100 -> 0 | AX32: =T32+T37 -> 0
C33: Fractionation OLEIN IV 57 ( Retail ) | T33: Olein IV 57 ( Retail ) | U33: Olein IV 57 ( Retail ) | V33: Olein IV 57 ( Retail ) | DF33: Kg/MT | DG33: =DG28/(DG26/1000) -> 72.98066 | DH33: =DH28/(DH26/1000) -> 75.35532 | DI33: =DI28/(DI26/1000) -> 75.473412 | OO33: =OO27/OO28*100 -> #REF! | OR33: Salvaco 2L | OS33: 2444 | PE33: 10.86 | PF33: =(OS33*PE33)/1000 -> 26.54184 | AIQ33: Diff
C34: CPO Consume | E34: Kg | F34: 0 | G34: 0 | H34: 0 | I34: 0 | J34: 0 | R34: ='[7]Desember 24'!AL29 -> 0 | T34: =SUM(F34:Q34) -> 0 | U34: =U35/U57% -> 32338304 | V34: =(T34/U34)*100 -> 0 | DF34: Kg/MT | DG34: =DG28/(DG20/1000) -> #VALUE! | DH34: =DI28/(DH20/1000) -> #VALUE! | DI34: =#REF!/(DI20/1000) -> #REF!
C35: RBDPO Brand Consume | D35: =SUM(D36:D37) -> 15000 | E35: Kg | F35: 0 | G35: 0 | H35: 0 | I35: 0 | J35: 0 | R35: =R36+R37 -> 0 | T35: =T36+T37 -> 0 | U35: =U36+U37 -> 30647000 | V35: =(T35/U35)*100 -> 0 | PF35: =SUM(PF28:PF33) -> 40.24716
C36: OLEIN IV 57 ( Retail ) | D36: 12000 | E36: Kg | F36: 0 | G36: 0 | H36: 0 | I36: 0 | J36: 0 | R36: ='[7]Desember 24'!AL31 -> 0 | T36: =SUM(F36:Q36) -> 0 | U36: 23002000 | V36: =T36/U36*100 -> 0
C37: STEARIN | D37: 3000 | E37: Kg | F37: 0 | G37: 0 | H37: 0 | I37: 0 | J37: 0 | R37: ='[7]Desember 24'!AL32 -> 0 | T37: =SUM(F37:Q37) -> 0 | U37: 7645000 | V37: =T37/U37*100 -> 0
C38: Fractionation OLEIN IV 58 ( BULK ) | T38: Olein IV 58 | U38: Olein IV 58 | V38: Olein IV 58
C39: RBDPO Consume | E39: Kg | F39: 0 | G39: =G40+G41 -> 13585776 | H39: 0 | I39: 0 | J39: 0 | R39: =R40+R41 -> 0 | T39: =T40+T41 -> 13585776 | U39: =U40+U41 -> 249961000 | V39: =T39/U39*100 -> 5.4351583
C40: OLEIN IV 58 ( Bulk ) | D40: 205714 | E40: Kg | F40: 0 | G40: ='[6]FEBUARI 2025'!$AK$45 -> 10107561 | H40: 0 | I40: 0 | J40: 0 | R40: ='[7]Desember 24'!AL35 -> 0 | T40: =SUM(F40:Q40) -> 10107561 | U40: 175000000 | V40: =T40/U40*100 -> 5.7757491
C41: STEARIN | D41: 61714 | E41: Kg | F41: 0 | G41: ='[6]FEBUARI 2025'!$AK$46 -> 3478215 | H41: 0 | I41: 0 | J41: 0 | R41: ='[7]Desember 24'!AL36 -> 0 | T41: =SUM(F41:Q41) -> 3478215 | U41: 74961000 | V41: =T41/U41*100 -> 4.6400328
C42: Fractionation OLEIN IV 58 ( Retail ) | H42: 0
C43: CPO Consume | E43: Kg
C44: RBDPO Consume | E44: Kg
C45: OLEIN IV 58 | E45: Kg
C46: STEARIN | E46: Kg
C47: Fractionation OLEIN IV 60 | T47: Olein IV 60 | U47: Olein IV 60 | V47: Olein IV 60
C48: CPO Consume | E48: Kg | F48: 0 | G48: 0 | H48: 0 | I48: 0 | J48: 0 | T48: =SUM(F48:Q48) -> 0 | U48: =U49/U57% -> 25913273 | V48: =T48/U48*100 -> 0
C49: RBDPO Brand Consume | E49: Kg | F49: 0 | G49: =G51+G52 -> 138533 | H49: 0 | I49: 0 | J49: 0 | T49: =T51+T52 -> 138533 | U49: =U51+U52 -> 24558000 | V49: =T49/U49*100 -> 0.56410538 | DG49: 2136
C50: OLEIN IV 60 Bulk | E50: Kg | F50: 0 | G50: 0 | H50: 0 | I50: 0 | J50: 0 | T50: =SUM(F50:Q50) -> 0 | U50: =SUM(F50:R50) -> 0 | V50: =SUM(H50:T50) -> 0
C51: OLEIN IV 60 Salvaco | D51: 25000 | E51: Kg | F51: 0 | G51: ='[6]FEBUARI 2025'!$AK$55 -> 85453 | H51: 0 | I51: 0 | J51: 0 | T51: =SUM(F51:Q51) -> 85453 | U51: 14736000 | V51: =T51/U51*100 -> 0.57989278 | DG51: 1796
C52: SOFT STEARIN | D52: 10000 | E52: Kg | F52: 0 | G52: ='[6]FEBUARI 2025'!$AK$56 -> 53080 | H52: 0 | I52: 0 | J52: 0 | T52: =SUM(F52:Q52) -> 53080 | U52: 9822000 | V52: =T52/U52*100 -> 0.54041947 | DG52: =DG49/DG51*100 -> 118.93096
C53: Ratio Run RBDPO | F53: 0 | G53: 0 | H53: 0 | I53: 0 | J53: 0 | T53: =+AVERAGE(F53:Q53) -> 0
C54: Utilitas RBDPO | F54: =(F49+F39+F35+F31+F27)/F55*100 -> #DIV/0! | G54: 0 | H54: 0 | I54: =(I49+I39+I35+I31+I27)/I55*100 -> #DIV/0! | J54: =(J49+J39+J35+J31+J27)/J55*100 -> #DIV/0! | T54: =+AVERAGE(F54:Q54) -> #DIV/0!
C55: Budget RBDPO | F55: 0 | G55: 0 | H55: 0 | I55: 0 | J55: 0 | T55: =SUM(F55:Q55) -> 0
C56: YIELD | G56: 0 | H56: 0 | T56: Yield | U56: Yield | V56: Yield | OP56: 678
C57: RBDPO | D57: 94.2 | E57: % | F57: 0 | G57: ='[6]FEBUARI 2025'!$AK$59 -> 94.592325 | H57: ='[8]MARET 2025'!$AK$59 -> 84.757611 | I57: 0 | J57: 0 | K57: ='JUNI 2025'!AL60 -> 94.787564 | T57: =(T19/(T11))*100 -> 93.77489 | U57: =(U19/(U11))*100 -> 94.769967 | OP57: 420 | OR57: =OP57/OP56*100 -> 61.946903
C58: PFAD | D58: 5 | E58: % | F58: 0 | G58: ='[6]FEBUARI 2025'!$AK$60 -> 4.6286724 | H58: ='[8]MARET 2025'!$AK$60 -> 4.001639 | I58: 0 | J58: 0 | K58: ='JUNI 2025'!AL61 -> 4.8633016 | T58: =(T20/(T11))*100 -> 4.6808716 | U58: =(U20/(U11))*100 -> 4.5147541 | OP58: =OP56-OP57 -> 258 | OR58: =OP58/OP56*100 -> 38.053097
C59: Olein IV 56 | D59: 82 | E59: % | F59: 0 | G59: ='[6]FEBUARI 2025'!$AK$61 -> 80.570286 | H59: ='[8]MARET 2025'!$AK$61 -> 82.804827 | I59: 0 | J59: 0 | K59: ='JUNI 2025'!AL62 -> 80.514103 | T59: =(T27/T26)*100 -> 80.917655 | U59: =(U27/U26)*100 -> 82.036628
C60: Stearin | D60: 18 | E60: % | F60: 0 | G60: ='[6]FEBUARI 2025'!$AK$62 -> 19.429714 | H60: ='[8]MARET 2025'!$AK$62 -> 17.195173 | I60: 0 | J60: 0 | K60: ='JUNI 2025'!AL63 -> 19.485897 | T60: =(T28/T26)*100 -> 19.082345 | U60: =(U28/U26)*100 -> 17.963372
C61: Olein IV 57 ( Bulk ) | D61: 75 | E61: % | F61: 0 | G61: 0 | H61: 0 | I61: 0 | J61: 0 | T61: =(T31/T30)*100 -> #DIV/0! | U61: 75
C62: Stearin | D62: 25 | E62: % | F62: 0 | G62: 0 | H62: 0 | I62: 0 | J62: 0 | T62: =(T32/T30)*100 -> #DIV/0! | U62: 25
C63: Olein IV 57 ( Retail ) | D63: 75 | E63: % | F63: #DIV/0! | G63: 0 | H63: 0 | I63: #DIV/0! | J63: #DIV/0! | T63: =(T36/T35)*100 -> #DIV/0! | U63: 75
C64: Stearin | D64: 25 | E64: % | F64: #DIV/0! | G64: 0 | H64: 0 | I64: #DIV/0! | J64: #DIV/0! | T64: =(T37/T35)*100 -> #DIV/0! | U64: 25 | FN64: 95.03
C65: Olein IV 58 ( Bulk ) | D65: 70 | E65: % | F65: 0 | G65: ='[6]FEBUARI 2025'!$AK$67 -> 74.398113 | H65: 0 | I65: 0 | J65: 0 | T65: =(T40/T39)*100 -> 74.398113 | U65: 70
C66: Stearin | D66: 30 | E66: % | F66: 0 | G66: ='[6]FEBUARI 2025'!$AK$68 -> 25.601887 | H66: 0 | I66: 0 | J66: 0 | T66: =(T41/T39)*100 -> 25.601887 | U66: 30
C67: Olein IV 60 | D67: 60 | E67: % | F67: 0 | G67: ='[6]FEBUARI 2025'!$AK$71 -> 61.737698 | H67: 0 | I67: 0 | J67: 0 | T67: =(T51/T49)*100 -> 61.68422 | U67: =U51/U49*100 -> 60.004886 | FN67: 4.23 | OR67: =OR68/94.2% -> 1307.8556 | OS67: MT CPO
C68: Soft Stearin | D68: 40 | E68: % | F68: 0 | G68: ='[6]FEBUARI 2025'!$AK$72 -> 38.348999 | H68: 0 | I68: 0 | J68: 0 | T68: =(T52/T49)*100 -> 38.31578 | U68: =U52/U49*100 -> 39.995114 | FN68: =100-FN64-FN67 -> 0.74 | OR68: =22*56 -> 1232 | OS68: MT RBDPO Brand
B69: 3 | C69: CHEMICAL CONSUMABLE | H69: 0 | T69: Chemical | U69: Chemical | V69: Chemical | OR69: =16.5*OR67 -> 21579.618
C70: Bleaching Earth (BE) to Poram Spec | D70: 9 | E70: Kg | F70: 0 | G70: ='[6]FEBUARI 2025'!$AK$74 -> 134694 | H70: ='[8]MARET 2025'!$AK$74 -> 29720 | I70: 0 | J70: 0 | K70: ='JUNI 2025'!AL75 -> 153073 | T70: =SUM(F70:Q70) -> 317487 | U70: 2767753 | V70: =T70/U70*100 -> 11.47093
E71: % | F71: 0 | G71: ='[6]FEBUARI 2025'!$AK$75 -> 0.8104536 | H71: ='[8]MARET 2025'!$AK$75 -> 0.8474267 | I71: 0 | J71: 0 | K71: ='JUNI 2025'!AL76 -> 8.5932405 | T71: =T70/(T11)*100 -> 0.83681654 | U71: 0.8 | V71: 0 | AX71: =T71*10 -> 8.3681654 | FN71: =#REF!*10 -> #REF! | OR71: =OR67+(T48/1000) -> 1307.8556 | OS71: Total CPO Brand
C72: Bleaching Earth (BE) to Branded Spec | D72: 16 | E72: Kg | F72: 0 | G72: 0 | H72: 0 | I72: 0 | J72: 0 | T72: =SUM(F72:Q72) -> 0 | U72: 1357284 | V72: =T72/U72*100 -> 0 | OR72: =OR69+T72 -> 21579.618 | OS72: Total BE Brand
E73: % | F73: 0 | G73: 0 | H73: 0 | I73: 0 | J73: 0 | T73: =T72/(T13)*100 -> #DIV/0! | U73: 1.8 | V73: 0 | AX73: =T73*10 -> #DIV/0! | OR73: =OR72/OR71 -> 16.5 | OS73: Kg/MT CPO
C74: Phosporic Acid (PA) | D74: 0.6 | E74: Kg | F74: 0 | G74: ='[6]FEBUARI 2025'!$AK$82 -> 16720.54 | H74: ='[8]MARET 2025'!$AK$82 -> 1701.44 | I74: 0 | J74: 0 | K74: ='JUNI 2025'!AL83 -> 8793.24 | T74: =SUM(F74:Q74) -> 27215.22 | U74: 252824 | V74: =SUM(H74:T74) -> 37709.9 | OR74: 16 | OS74: Budget (Kg/MT)
E75: % | F75: 0 | G75: =G74/G11*100 -> 0.10060746 | H75: ='[8]MARET 2025'!$AK$83 -> 0.48514323 | I75: 0 | J75: 0 | K75: ='JUNI 2025'!AL84 -> 0.49363654 | T75: =T74/(T11+71450)*100 -> 0.071597696 | U75: 0.06 | V75: =V74/(V11+71450)*100 -> 52.77796 | AX75: =T75*10 -> 0.71597696 | FN75: =Q75*10 -> 0 | OR75: =OR73-OR74 -> 0.5 | OS75: Over (Kg/MT)
B76: 4 | C76: Oil Losses | D76: 0.8 | E76: % | F76: 0 | G76: ='[6]FEBUARI 2025'!$AK$84 -> -0.77900275 | H76: ='[8]MARET 2025'!$AK$84 -> -11.24075 | I76: 0 | J76: 0 | K76: ='JUNI 2025'!AL85 -> -0.3491346 | T76: =((SUM(T19:T20))-(SUM(T11)))/(SUM(T11))*100 -> -1.5442388 | U76: =((SUM(U19:U20))-(SUM(U11)))/(SUM(U11))*100 -> -0.71527906 | V76: =T76/U76*100 -> 215.89319
C77: % Oil Content | D77: 22 | E77: % | F77: 0 | G77: ='[6]FEBUARI 2025'!$AK$86 -> 19.381667 | H77: ='[8]MARET 2025'!$AK$86 -> 13.4725 | I77: 0 | J77: 0 | K77: ='JUNI 2025'!AL87 -> 21.014 | T77: =AVERAGE(G77:K77) -> 10.773633 | U77: 22 | V77: =AVERAGE(H77:T77) -> 9.0520267
C78: Spent Bleaching Earth | E78: Kg | F78: 0 | G78: ='[6]FEBUARI 2025'!$AK$87 -> 136702.15 | H78: ='[8]MARET 2025'!$AK$87 -> 31054.676 | I78: 0 | J78: 0 | K78: ='JUNI 2025'!AL88 -> 156289.68 | T78: =SUM(T70,T72)+(T77%*SUM(T70,T72)) -> 351691.89 | U78: 7811279 | V78: =SUM(V70,V72)+(V77%*SUM(V70,V72)) -> 12.509281 | GA78: =X78+400 -> 400
B79: 5 | C79: PACKAGING (Brand Salvaco) | T79: Packaging | U79: Packaging | V79: Packaging | FX79: 17292 | OY79: =#REF!-FX79 -> #REF!
C80: Olein IV 60 Received | E80: Kg | F80: ='[7]Januari 24'!AL68 -> 845858 | G80: ='[7]Februari 24'!AI68 -> #REF! | H80: ='[7]Maret 24'!AL68 -> 0 | I80: ='[7]Januari 24'!AO68 -> #REF! | J80: ='[7]Januari 24'!AP68 -> #REF! | T80: =SUM(F80:R80) -> #REF! | U80: =SUM(G80:S80) -> #REF! | V80: =(T80/U80)*100 -> #REF!
C81: Olein IV 60 Consume | E81: Kg | F81: ='[7]Januari 24'!AL69 -> 399021.28 | G81: ='[7]Februari 24'!AI69 -> #REF! | H81: ='[7]Maret 24'!AL69 -> 0 | I81: ='[7]Januari 24'!AO69 -> #REF! | J81: ='[7]Januari 24'!AP69 -> #REF! | T81: =SUM(T82:T84) -> #REF! | U81: =SUM(U82:U84) -> #REF! | V81: =(T81/U81)*100 -> #REF! | AFR81: Kg | AFS81: Olein Filling to Packaging
C82: - finished product | E82: Kg | F82: =SUM(F86:F87)*10.86 -> 400256.16 | G82: =SUM(G86:G87)*10.86 -> #REF! | H82: =SUM(H86:H87)*10.86 -> 0 | I82: =SUM(I86:I87)*10.86 -> #REF! | J82: =SUM(J86:J87)*10.86 -> #REF! | T82: =SUM(T86:T87)*10.86 -> #REF! | U82: =SUM(U86:U87)*10.86 -> 32269046 | V82: =(T82/U82)*100 -> #REF! | FX82: =#REF!/1000 -> #REF! | OY82: 4696 | OZ82: =FX82/OY82*100 -> #REF!
C83: - sample | E83: Kg | F83: =F81-F82 -> -1234.88 | G83: =G81-G82 -> #REF! | H83: =H81-H82 -> 0 | I83: =I81-I82 -> #REF! | J83: =J81-J82 -> #REF! | T83: =SUM(F83:R83) -> #REF! | U83: =SUM(G83:S83) -> #REF! | V83: =(T83/U83)*100 -> #REF! | FX83: =#REF!/1000 -> #REF! | OY83: 565 | OZ83: =FX83/OY83*100 -> #REF!
C84: - remelt, flushing, downgrade | E84: Kg | F84: ='[7]Januari 24'!AL72 -> 0 | G84: ='[7]Februari 24'!AI72 -> 0 | H84: ='[7]Maret 24'!AL72 -> 0 | I84: ='[7]Januari 24'!AO72 -> #REF! | J84: ='[7]Januari 24'!AP72 -> #REF! | T84: =SUM(F84:R84) -> #REF! | U84: =SUM(G84:S84) -> #REF!
C85: Carton | T85: Carton | U85: Carton | V85: Carton
C86: Salvaco 1 Liter | E86: Box | F86: ='[7]Januari 24'!AL74 -> 17197 | G86: ='[7]Februari 24'!AI74 -> #REF! | H86: ='[7]Maret 24'!AL74 -> 0 | I86: ='[7]Januari 24'!AO74 -> #REF! | J86: ='[7]Januari 24'!AP74 -> #REF! | T86: =SUM(F86:R86) -> #REF! | U86: 1254577 | V86: =(T86/U86)*100 -> #REF!
C87: Salvaco 2 Liter | E87: Box | F87: ='[7]Januari 24'!AL75 -> 19659 | G87: ='[7]Februari 24'!AI75 -> #REF! | H87: ='[7]Maret 24'!AL75 -> 0 | I87: ='[7]Januari 24'!AO75 -> #REF! | J87: ='[7]Januari 24'!AP75 -> #REF! | T87: =SUM(F87:R87) -> #REF! | U87: 1716790 | V87: =(T87/U87)*100 -> #REF!
C88: Pouch | T88: Pouch | U88: Pouch | V88: Pouch
C89: Salvaco 1 Liter | E89: Pouch | F89: =F86*12 -> 206364 | G89: =G86*12 -> #REF! | H89: =H86*12 -> 0 | I89: =I86*12 -> #REF! | J89: =J86*12 -> #REF! | T89: =T86*12 -> #REF! | U89: =U86*12 -> 15054924 | V89: =(T89/U89)*100 -> #REF!
C90: Salvaco 2 Liter | E90: Pouch | F90: =F87*6 -> 117954 | G90: =G87*6 -> #REF! | H90: =H87*6 -> 0 | I90: =I87*6 -> #REF! | J90: =J87*6 -> #REF! | T90: =T87*6 -> #REF! | U90: =U87*6 -> 10300740 | V90: =(T90/U90)*100 -> #REF!
C91: Consumable Vit. A | E91: gram | F91: =(F81*45)/1700 -> 10562.328 | G91: =(G81*45)/1700 -> #REF! | H91: =(H81*45)/1700 -> 0 | I91: =(I81*45)/1700 -> #REF! | J91: =(J81*45)/1700 -> #REF! | T91: =SUM(F91:R91) -> #REF! | U91: =(U81*45)/1700 -> #REF! | V91: =(T91/U91)*100 -> #REF!
C92: Consumable Packing Tape | E92: Roll | F92: =SUM(F86:F87)/500 -> 73.712 | G92: =SUM(G86:G87)/500 -> #REF! | H92: =SUM(H86:H87)/500 -> 0 | I92: =SUM(I86:I87)/500 -> #REF! | J92: =SUM(J86:J87)/500 -> #REF! | T92: =SUM(F92:R92) -> #REF! | U92: =SUM(U86:U87)/500 -> 5942.734 | V92: =(T92/U92)*100 -> #REF!
C93: REJECT MATERIAL QTY | T93: Loss Material | U93: Loss Material | V93: Loss Material
C94: Carton | T94: Carton | U94: Carton | V94: Carton
C95: Salvaco 1 Liter | E95: Box | F95: ='[7]Januari 24'!AL74 -> 17197 | G95: ='[7]Februari 24'!AI83 -> #REF! | H95: ='[7]Maret 24'!AL83 -> 0 | I95: ='[7]Januari 24'!AO74 -> #REF! | J95: ='[7]Januari 24'!AP74 -> #REF! | T95: =SUM(F95:R95) -> #REF! | U95: =SUM(G95:S95) -> #REF! | V95: =SUM(H95:T95) -> #REF!
C96: Salvaco 2 Liter | E96: Box | F96: ='[7]Januari 24'!AL75 -> 19659 | G96: ='[7]Februari 24'!AI84 -> #REF! | H96: ='[7]Maret 24'!AL84 -> 0 | I96: ='[7]Januari 24'!AO75 -> #REF! | J96: ='[7]Januari 24'!AP75 -> #REF! | T96: =SUM(F96:R96) -> #REF! | U96: =SUM(G96:S96) -> #REF! | V96: =SUM(H96:T96) -> #REF!
C97: Pouch | T97: Pouch | U97: Pouch | V97: Pouch
C98: Salvaco 1 Liter | E98: Pouch | F98: =F95*12 -> 206364 | G98: =G95*12 -> #REF! | H98: =H95*12 -> 0 | I98: =I95*12 -> #REF! | J98: =J95*12 -> #REF! | T98: =SUM(F98:R98) -> #REF! | U98: =SUM(G98:S98) -> #REF! | V98: =SUM(H98:T98) -> #REF!
C99: Salvaco 2 Liter | E99: Pouch | F99: =F96*6 -> 117954 | G99: =G96*6 -> #REF! | H99: =H96*6 -> 0 | I99: =I96*6 -> #REF! | J99: =J96*6 -> #REF! | T99: =SUM(F99:R99) -> #REF! | U99: =SUM(G99:S99) -> #REF! | V99: =SUM(H99:T99) -> #REF!
C100: REJECT MATERIAL (%) | T100: Loss Material | U100: Loss Material | V100: Loss Material
C101: Carton | T101: Carton | U101: Carton | V101: Carton
...

Sheet Downtime Juni
B3: DOWN TIME REFINERY | K3: DOWN TIME FRACTIONATION
B5: Periode Juni 2025 | K5: Periode Juni 2025
B6: TANGGAL | C6: CAPACITY (Kg) | D6: CAPACITY 2500 | E6: REMARKS | F6: Down time | J6: Tph | K6: TANGGAL | L6: CAPACITY (Kg) | M6: REMARKS | N6: Down time
F7: Stop | G7: Slow | H7: % | N7: Stop | O7: Slow | P7: %
B8: 1 | C8: 0 | D8: =(C8/1000)*24 -> 0 | E8: SHUT DOWN | G8: =(2500-(C8/1000))/105 -> 23.809524 | H8: =C8/2500/1000 -> 0 | J8: =(C8/1000)/24 -> 0 | K8: 1 | L8: 0 | M8: SHUT DOWN | O8: 23.809524 | P8: 0
B9: 2 | C9: 0 | D9: =(C9/1000)*24 -> 0 | E9: SHUT DOWN | G9: =(2500-(C9/1000))/105 -> 23.809524 | H9: =C9/2500/1000 -> 0 | J9: =(C9/1000)/24 -> 0 | K9: 2 | L9: 0 | M9: SHUT DOWN | O9: 23.809524 | P9: 0
B10: 3 | C10: 0 | D10: =(C10/1000)*24 -> 0 | E10: SHUT DOWN | G10: =(2500-(C10/1000))/105 -> 23.809524 | H10: =C10/2500/1000 -> 0 | J10: =(C10/1000)/24 -> 0 | K10: 3 | L10: 0 | M10: SHUT DOWN | O10: 23.809524 | P10: 0
B11: 4 | C11: 0 | D11: =(C11/1000)*24 -> 0 | E11: SHUT DOWN | G11: =(2500-(C11/1000))/105 -> 23.809524 | H11: =C11/2500/1000 -> 0 | J11: =(C11/1000)/24 -> 0 | K11: 4 | L11: 0 | M11: SHUT DOWN | O11: 23.809524 | P11: 0
B12: 5 | C12: 0 | D12: =(C12/1000)*24 -> 0 | E12: SHUT DOWN | G12: =(2500-(C12/1000))/105 -> 23.809524 | H12: =C12/2500/1000 -> 0 | J12: =(C12/1000)/24 -> 0 | K12: 5 | L12: 0 | M12: SHUT DOWN | O12: 23.809524 | P12: 0
B13: 6 | C13: 0 | D13: =(C13/1000)*24 -> 0 | E13: SHUT DOWN | G13: =(2500-(C13/1000))/105 -> 23.809524 | H13: =C13/2500/1000 -> 0 | J13: =(C13/1000)/24 -> 0 | K13: 6 | L13: 0 | M13: SHUT DOWN | O13: 23.809524 | P13: 0
B14: 7 | C14: 0 | D14: =(C14/1000)*24 -> 0 | E14: SHUT DOWN | G14: =(2500-(C14/1000))/105 -> 23.809524 | H14: =C14/2500/1000 -> 0 | J14: =(C14/1000)/24 -> 0 | K14: 7 | L14: 0 | M14: SHUT DOWN | O14: 23.809524 | P14: 0
B15: 8 | C15: 738858 | D15: =(C15/1000)*24 -> 17732.592 | E15: START UP | G15: =(2500-(C15/1000))/105 -> 16.772781 | H15: =C15/2500/1000 -> 0.2955432 | J15: =(C15/1000)/24 -> 30.78575 | K15: 8 | L15: 190528 | M15: START UP | O15: =(2500-(L15/1000))/105 -> 21.994971 | P15: =L15/2500/1000 -> 0.0762112
B16: 9 | C16: 2231331 | D16: =(C16/1000)*24 -> 53551.944 | E16: Tune Up Kapasitas/Sounding | G16: =(2500-(C16/1000))/105 -> 2.5587524 | H16: =C16/2500/1000 -> 0.8925324 | J16: =(C16/1000)/24 -> 92.972125 | K16: 9 | L16: 1817708 | M16: Tune up kapasitas/Sounding | O16: =(2500-(L16/1000))/105 -> 6.498019 | P16: =L16/2500/1000 -> 0.7270832
B17: 10 | C17: 2186600 | D17: =(C17/1000)*24 -> 52478.4 | E17: Sounding / Trouble Hoist Bleaching Earth | G17: =(2500-(C17/1000))/105 -> 2.9847619 | H17: =C17/2500/1000 -> 0.87464 | J17: =(C17/1000)/24 -> 91.108333 | K17: 10 | L17: 2405788 | M17: Sounding & Chiller (level switch error) | O17: =(2500-(L17/1000))/105 -> 0.89725714 | P17: =L17/2500/1000 -> 0.9623152
B18: 11 | C18: 2513351 | D18: =(C18/1000)*24 -> 60320.424 | E18: Running Normal Plant | G18: 0,13 | H18: =C18/2500/1000 -> 1.0053404 | J18: =(C18/1000)/24 -> 104.72296 | K18: 11 | L18: 2393434 | M18: Sounding & Chiller (level switch error) | O18: =(2500-(L18/1000))/105 -> 1.0149143 | P18: =L18/2500/1000 -> 0.9573736
B19: 12 | C19: 2299670 | D19: =(C19/1000)*24 -> 55192.08 | E19: HPB Sering Trip (DMV Valve) | G19: =(2500-(C19/1000))/105 -> 1.9079048 | H19: =C19/2500/1000 -> 0.919868 | J19: =(C19/1000)/24 -> 95.819583 | K19: 12 | L19: 2405045 | M19: Low Material | O19: =(2500-(L19/1000))/105 -> 0.90433333 | P19: =L19/2500/1000 -> 0.962018
B20: 13 | C20: 1987933 | D20: =(C20/1000)*24 -> 47710.392 | E20: HPB Sering Trip (DMV Valve) | G20: =(2500-(C20/1000))/105 -> 4.8768286 | H20: =C20/2500/1000 -> 0.7951732 | J20: =(C20/1000)/24 -> 82.830542 | K20: 13 | L20: 1825948 | M20: Low Material | O20: =(2500-(L20/1000))/105 -> 6.4195429 | P20: =L20/2500/1000 -> 0.7303792
B21: 14 | C21: 1601122 | D21: =(C21/1000)*24 -> 38426.928 | E21: High FFA (5,3) HPB Sering Trip (DMV Valve) | G21: =(2500-(C21/1000))/105 -> 8.5607429 | H21: =C21/2500/1000 -> 0.6404488 | J21: =(C21/1000)/24 -> 66.713417 | K21: 14 | L21: 2236014 | M21: Low Material | O21: =(2500-(L21/1000))/105 -> 2.5141524 | P21: =L21/2500/1000 -> 0.8944056
B22: 15 | C22: 2010199 | D22: =(C22/1000)*24 -> 48244.776 | E22: Koreksi LC Ke 2,8 R (Karena Shipment Mundur) Slow Flowrate | G22: =(2500-(C22/1000))/105 -> 4.6647714 | H22: =C22/2500/1000 -> 0.8040796 | J22: =(C22/1000)/24 -> 83.758292 | K22: 15 | L22: 1160345 | M22: Koreksi Quality (CP) | O22: =(2500-(L22/1000))/105 -> 12.758619 | P22: =L22/2500/1000 -> 0.464138
B23: 16 | C23: 1922414 | D23: =(C23/1000)*24 -> 46137.936 | E23: Koreksi LC Ke 2,8 R (Karena Shipment Mundur) Slow Flowrate | G23: =(2500-(C23/1000))/105 -> 5.500819 | H23: =C23/2500/1000 -> 0.7689656 | J23: =(C23/1000)/24 -> 80.100583 | K23: 16 | L23: 1890275 | M23: Koreksi Quality (CP) | O23: =(2500-(L23/1000))/105 -> 5.8069048 | P23: =L23/2500/1000 -> 0.75611
B24: 17 | C24: 321709 | D24: =(C24/1000)*24 -> 7721.016 | E24: Kunjungan Tamu BPK & Proses Shut Down | G24: =(2500-(C24/1000))/105 -> 20.745629 | H24: =C24/2500/1000 -> 0.1286836 | J24: =(C24/1000)/24 -> 13.404542 | K24: 17 | L24: 1443135 | M24: Koreksi Quality (CP) | O24: =(2500-(L24/1000))/105 -> 10.065381 | P24: =L24/2500/1000 -> 0.577254
B25: 18 | C25: 0 | D25: =(C25/1000)*24 -> 0 | E25: SHUT DOWN | G25: =(2500-(C25/1000))/105 -> 23.809524 | H25: =C25/2500/1000 -> 0 | J25: =(C25/1000)/24 -> 0 | K25: 18 | L25: 24387 | M25: SHUT DOWN | O25: =(2500-(L25/1000))/105 -> 23.577267 | P25: =L25/2500/1000 -> 0.0097548
B26: 19 | C26: 0 | D26: =(C26/1000)*24 -> 0 | E26: SHUT DOWN | G26: =(2500-(C26/1000))/105 -> 23.809524 | H26: =C26/2500/1000 -> 0 | J26: =(C26/1000)/24 -> 0 | K26: 19 | L26: 0 | M26: SHUT DOWN | O26: 23.809524 | P26: 0
B27: 20 | C27: 0 | D27: =(C27/1000)*24 -> 0 | E27: SHUT DOWN | G27: =(2500-(C27/1000))/105 -> 23.809524 | H27: =C27/2500/1000 -> 0 | J27: =(C27/1000)/24 -> 0 | K27: 20 | L27: 0 | M27: SHUT DOWN | O27: 23.809524 | P27: 0
B28: 21 | C28: 0 | D28: =(C28/1000)*24 -> 0 | E28: SHUT DOWN | G28: =(2500-(C28/1000))/105 -> 23.809524 | H28: =C28/2500/1000 -> 0 | J28: =(C28/1000)/24 -> 0 | K28: 21 | L28: 0 | M28: SHUT DOWN | O28: 23.809524 | P28: 0
B29: 22 | C29: 0 | D29: =(C29/1000)*24 -> 0 | E29: SHUT DOWN | G29: =(2500-(C29/1000))/105 -> 23.809524 | H29: =C29/2500/1000 -> 0 | J29: =(C29/1000)/24 -> 0 | K29: 22 | L29: 0 | M29: SHUT DOWN | O29: 23.809524 | P29: 0
B30: 23 | C30: 0 | D30: =(C30/1000)*24 -> 0 | E30: SHUT DOWN | G30: =(2500-(C30/1000))/105 -> 23.809524 | H30: =C30/2500/1000 -> 0 | J30: =(C30/1000)/24 -> 0 | K30: 23 | L30: 0 | M30: SHUT DOWN | O30: 23.809524 | P30: 0
B31: 24 | C31: 0 | D31: =(C31/1000)*24 -> 0 | E31: SHUT DOWN | G31: =(2500-(C31/1000))/105 -> 23.809524 | H31: =C31/2500/1000 -> 0 | J31: =(C31/1000)/24 -> 0 | K31: 24 | L31: 0 | M31: SHUT DOWN | O31: 23.809524 | P31: 0
B32: 25 | C32: 0 | D32: =(C32/1000)*24 -> 0 | E32: SHUT DOWN | G32: =(2500-(C32/1000))/105 -> 23.809524 | H32: =C32/2500/1000 -> 0 | J32: =(C32/1000)/24 -> 0 | K32: 25 | L32: 0 | M32: SHUT DOWN | O32: 23.809524 | P32: 0
B33: 26 | C33: 0 | D33: =(C33/1000)*24 -> 0 | E33: SHUT DOWN | G33: =(2500-(C33/1000))/105 -> 23.809524 | H33: =C33/2500/1000 -> 0 | J33: =(C33/1000)/24 -> 0 | K33: 26 | L33: 0 | M33: SHUT DOWN | O33: 23.809524 | P33: 0
B34: 27 | C34: 0 | D34: =(C34/1000)*24 -> 0 | E34: SHUT DOWN | G34: =(2500-(C34/1000))/105 -> 23.809524 | H34: =C34/2500/1000 -> 0 | J34: =(C34/1000)/24 -> 0 | K34: 27 | L34: 0 | M34: SHUT DOWN | O34: 23.809524 | P34: 0
B35: 28 | C35: 0 | D35: =(C35/1000)*24 -> 0 | E35: SHUT DOWN | G35: =(2500-(C35/1000))/105 -> 23.809524 | H35: =C35/2500/1000 -> 0 | J35: =(C35/1000)/24 -> 0 | K35: 28 | L35: 0 | M35: SHUT DOWN | O35: 23.809524 | P35: 0
B36: 29 | C36: 0 | D36: =(C36/1000)*24 -> 0 | E36: SHUT DOWN | G36: =(2500-(C36/1000))/105 -> 23.809524 | H36: =C36/2500/1000 -> 0 | J36: =(C36/1000)/24 -> 0 | K36: 29 | L36: 0 | M36: SHUT DOWN | O36: 23.809524 | P36: 0
B37: 30 | C37: 0 | D37: =(C37/1000)*24 -> 0 | E37: SHUT DOWN | G37: =(2500-(C37/1000))/105 -> 23.809524 | H37: =C37/2500/1000 -> 0 | J37: =(C37/1000)/24 -> 0 | K37: 30 | L37: 0 | M37: SHUT DOWN | O37: 23.809524 | P37: 0
B38: 31 | C38: 0 | D38: =(C38/1000)*24 -> 0 | E38: SHUT DOWN | G38: =(2500-(C38/1000))/105 -> 23.809524 | H38: =C38/2500/1000 -> 0 | J38: =(C38/1000)/24 -> 0 | K38: 31 | L38: 0 | M38: SHUT DOWN | O38: 23.809524 | P38: 0
B39: TOTAL | C39: =SUM(C8:C38) -> 17813187 | D39: =SUM(D8:D38) -> 427516.49 | F39: =SUM(F8:F37) -> 0 | G39: =SUM(G15:G24) -> 68.57299 | J39: =AVERAGE(J8:J38) -> 23.942456 | K39: TOTAL | L39: =SUM(L8:L38) -> 17792607 | N39: 0 | O39: =SUM(O15:O24) -> 68.874095

Sheet Downtime Ref Juni
D3: DOWN TIME SLOW FLOWRATE PRODUCTION REFINERY
D5: Periode 01 s/d 30 Juni 2025
D6: TANGGAL | E6: CAPACITY (Kg) | F6: CAPACITY 2500 | G6: REMARKS | H6: Down time | L6: Tph
H7: Stop | I7: Slow | J7: %
D8: 1 | E8: 0 | F8: =(E8/1000)*24 -> 0 | G8: SHUT DOWN | I8: =(2500-(E8/1000))/105 -> 23.809524 | J8: =E8/2500/1000 -> 0 | L8: =(E8/1000)/24 -> 0
D9: 2 | E9: 0 | F9: =(E9/1000)*24 -> 0 | G9: SHUT DOWN | I9: =(2500-(E9/1000))/105 -> 23.809524 | J9: =E9/2500/1000 -> 0 | L9: =(E9/1000)/24 -> 0
D10: 3 | E10: 0 | F10: =(E10/1000)*24 -> 0 | G10: SHUT DOWN | I10: =(2500-(E10/1000))/105 -> 23.809524 | J10: =E10/2500/1000 -> 0 | L10: =(E10/1000)/24 -> 0
D11: 4 | E11: 0 | F11: =(E11/1000)*24 -> 0 | G11: SHUT DOWN | I11: =(2500-(E11/1000))/105 -> 23.809524 | J11: =E11/2500/1000 -> 0 | L11: =(E11/1000)/24 -> 0
D12: 5 | E12: 0 | F12: =(E12/1000)*24 -> 0 | G12: SHUT DOWN | I12: =(2500-(E12/1000))/105 -> 23.809524 | J12: =E12/2500/1000 -> 0 | L12: =(E12/1000)/24 -> 0
D13: 6 | E13: 0 | F13: =(E13/1000)*24 -> 0 | G13: SHUT DOWN | I13: =(2500-(E13/1000))/105 -> 23.809524 | J13: =E13/2500/1000 -> 0 | L13: =(E13/1000)/24 -> 0
D14: 7 | E14: 0 | F14: =(E14/1000)*24 -> 0 | G14: SHUT DOWN | I14: =(2500-(E14/1000))/105 -> 23.809524 | J14: =E14/2500/1000 -> 0 | L14: =(E14/1000)/24 -> 0
D15: 8 | E15: 738858 | F15: =(E15/1000)*24 -> 17732.592 | G15: START UP | I15: =(2500-(E15/1000))/105 -> 16.772781 | J15: =E15/2500/1000 -> 0.2955432 | L15: =(E15/1000)/24 -> 30.78575
D16: 9 | E16: 2231331 | F16: =(E16/1000)*24 -> 53551.944 | G16: Tune Up Kapasitas/Sounding | I16: =(2500-(E16/1000))/105 -> 2.5587524 | J16: =E16/2500/1000 -> 0.8925324 | L16: =(E16/1000)/24 -> 92.972125
D17: 10 | E17: 2186600 | F17: =(E17/1000)*24 -> 52478.4 | G17: Sounding/Trouble Hoist Bleaching Earth | I17: =(2500-(E17/1000))/105 -> 2.9847619 | J17: =E17/2500/1000 -> 0.87464 | L17: =(E17/1000)/24 -> 91.108333
D18: 11 | E18: 2513351 | F18: =(E18/1000)*24 -> 60320.424 | G18: Running Normal Plant | I18: =(2500-(E18/1000))/105 -> -0.12715238 | J18: =E18/2500/1000 -> 1.0053404 | L18: =(E18/1000)/24 -> 104.72296
D19: 12 | E19: 2299670 | F19: =(E19/1000)*24 -> 55192.08 | G19: HPB Sering Trip (DMV Valve) | I19: =(2500-(E19/1000))/105 -> 1.9079048 | J19: =E19/2500/1000 -> 0.919868 | L19: =(E19/1000)/24 -> 95.819583
... D38: 31 | E38: 0 | F38: =(E38/1000)*24 -> 0 | G38: SHUT DOWN | I38: =(2500-(E38/1000))/105 -> 23.809524 | J38: =E38/2500/1000 -> 0 | L38: =(E38/1000)/24 -> 0
D39: TOTAL | E39: =SUM(E8:E38) -> 17813187 | F39: =SUM(F8:F38) -> 427516.49 | H39: =SUM(H8:H37) -> 0 | I39: =SUM(I8:I37) -> 544.63631 | L39: =AVERAGE(L8:L38) -> 23.942456
E41: Summary
E42: 1. Slow flow rate due to Space Tank High | H42: 0 | I42: hours
E43: 2. Slow flow rate due to Olein IV 60 process | H43: 0 | I43: hours
E44: 2. Hold plant due to trip HP boiler & maintenance | H44: =SUM(I19,I20,I21) -> 15.345476 | I44: hours
E45: 3. Penyesuaian incoming CPO | H45: 0 | I45: hours
E46: 4. Downtime due to Start Up Plant | H46: =SUM(I15,I16) -> 19.331533 | I46: hours
E47: 5. Running Normal Plant | H47: =SUM(I18) -> -0.12715238 | I47: hours
E48: 6. Stop Plant due to Preventive Maintenance Plant | H48: 0 | I48: hours
E49: 8. Energizing PMG II | H49: 0 | I49: hours
E50: 9. Zero Suplay Gas (Problem Pertagas) | H50: 0 | I50: hours
E51: 7, Stop Plant | H51: =SUM(I8,I9,I10,I11,I12,I13,I14,I25,I26,I27,I28,I29,I30,I31,I32,I33,I34,I35,I36,I37) -> 476.19048 | I51: hours
E52: 11.HOLD CPO Shortage | I52: hours
E53: 8, Visitor (BPK) | H53: =I24 -> 20.745629 | I53: hours
E54: 9, Koreksi Quality (LC) | H54: =SUM(I22:I23) -> 10.16559 | I54: hours
E55: 10.Touble hoist rusak | H55: =SUM(I17) -> 2.9847619 | I55: hours
E56: Total | H56: =SUM(H42:H55) -> 544.63631 | I56: hours
E57: Note : Kapasitas 2500 TPD
D65: Prepared by, | F65: Checked by, | G65: Checked by, | I65: Approved by,
D69: Bany Subana | F69: Reza P. Panjaitan | G69: Reza P. Panjaitan | I69: Sudarianto
D70: Admin. Process | F70: Supervisor Produksi | G70: Supervisor Produksi | I70: Jr. Manager Produksi

Sheet Downtime Fract Juni 25
C2: DOWN TIME SLOW FLOWRATE PRODUCTION FRACTIONATION
C4: Periode 01 s/d 30 Juni 2025
C5: TANGGAL | D5: CAPACITY (Kg) | E5: REMARKS | F5: Down time | J5: Tph
F6: Stop | G6: Slow | H6: %
C7: 1 | D7: 0 | E7: SHUT DOWN | G7: =(2500-(D7/1000))/105 -> 23.809524 | H7: =D7/2500/1000 -> 0 | J7: =(D7/1000)/24 -> 0
C8: 2 | D8: 0 | E8: SHUT DOWN | G8: =(2500-(D8/1000))/105 -> 23.809524 | H8: =D8/2500/1000 -> 0 | J8: =(D8/1000)/24 -> 0
C9: 3 | D9: 0 | E9: SHUT DOWN | G9: =(2500-(D9/1000))/105 -> 23.809524 | H9: =D9/2500/1000 -> 0 | J9: =(D9/1000)/24 -> 0
C10: 4 | D10: 0 | E10: SHUT DOWN | G10: =(2500-(D10/1000))/105 -> 23.809524 | H10: =D10/2500/1000 -> 0 | J10: =(D10/1000)/24 -> 0
C11: 5 | D11: 0 | E11: SHUT DOWN | G11: =(2500-(D11/1000))/105 -> 23.809524 | H11: =D11/2500/1000 -> 0 | J11: =(D11/1000)/24 -> 0
C12: 6 | D12: 0 | E12: SHUT DOWN | G12: =(2500-(D12/1000))/105 -> 23.809524 | H12: =D12/2500/1000 -> 0 | J12: =(D12/1000)/24 -> 0
C13: 7 | D13: 0 | E13: SHUT DOWN | G13: =(2500-(D13/1000))/105 -> 23.809524 | H13: =D13/2500/1000 -> 0 | J13: =(D13/1000)/24 -> 0
C14: 8 | D14: 190528 | E14: START UP | G14: =(2500-(D14/1000))/105 -> 21.994971 | H14: =D14/2500/1000 -> 0.0762112 | J14: =(D14/1000)/24 -> 7.9386667
C15: 9 | D15: 1817708 | E15: Tune up kapasitas/Sounding | G15: =(2500-(D15/1000))/105 -> 6.498019 | H15: =D15/2500/1000 -> 0.7270832 | J15: =(D15/1000)/24 -> 75.737833
C16: 10 | D16: 2405788 | E16: Sounding & Chiller (level switch error) | G16: =(2500-(D16/1000))/105 -> 0.89725714 | H16: =D16/2500/1000 -> 0.9623152 | J16: =(D16/1000)/24 -> 100.24117
C17: 11 | D17: 2393434 | E17: Sounding & Chiller (level switch error) | G17: =(2500-(D17/1000))/105 -> 1.0149143 | H17: =D17/2500/1000 -> 0.9573736 | J17: =(D17/1000)/24 -> 99.726417
C18: 12 | D18: 2405045 | E18: Low Material | G18: =(2500-(D18/1000))/105 -> 0.90433333 | H18: =D18/2500/1000 -> 0.962018 | J18: =(D18/1000)/24 -> 100.21021
... C36: 30 | D36: 0 | E36: SHUT DOWN | G36: =(2500-(D36/1000))/105 -> 23.809524 | H36: =D36/2500/1000 -> 0 | J36: =(D36/1000)/24 -> 0
C37: 31 | D37: 0 | E37: SHUT DOWN | G37: =(2500-(D37/1000))/105 -> 23.809524 | H37: =D37/2000/1000 -> 0 | J37: =(D37/1000)/24 -> 0
C38: TOTAL | D38: =SUM(D7:D37) -> 17792607 | F38: =SUM(F7:F36) -> 0 | G38: =SUM(G7:G36) -> 544.83231 | J38: =AVERAGE(J7:J37) -> 23.914794
D40: Summary
D41: 1. Slow flow rate due to Space Tank High | F41: 0 | G41: hours
D42: 2. Slow flow rate due to Olein IV 60 process | F42: 0 | G42: hours
D43: 3. Slow flow rate due to Olein IV 56 process | G43: hours
D44: 1. Slow Flow rate terkait material sortage & menyesuaikan | F44: 0 | G44: hours
D45: 2. Downtime due to Start/Stop Up Plant | F45: =G14 -> 21.994971 | G45: hours
D46: 3. Tune Up Sounding | F46: =SUM(G15) -> 6.498019 | G46: hours
D47: 7. Stop Plant due to Preventive Maintenance Plant | F47: 0 | G47: hours
D48: 8. Energizing PMG II | F48: 0 | G48: hours
D49: 4. Trouble Level Switch Error | F49: =SUM(G16:G17) -> 1.9121714 | G49: hours
D50: 10. Slow flow rate due to Olein IV 58 process | F50: 0 | G50: hours
D51: 5. STOP PLANT | F51: =SUM(G7:G13,G24:G36) -> 475.95822 | G51: hours
D52: 12.Slow flow rate due to Olein IV 56 process | F52: 0 | G52: hours
D53: 6. Koreksi Quality (LC) | F53: =SUM(G21:G23) -> 28.630905 | G53: hours
D54: 7. Low Material | F54: =SUM(G18:G20) -> 9.8380286 | G54: hours
D55: Total | F55: =SUM(F41:F54) -> 544.83231 | G55: hours
D56: Note : Kapasitas 2500 TPD
C64: Prepared by, | E64: Checked by, | G64: Approved by,
C68: Bany Subana | E68: Reza P. Panjaitan | G68: Sudarianto
C69: Admin. Process | E69: Supervisor Produksi | G69: Jr. Manager Produksi

Sheet Steam
B2: Steam Price Package Boiler | G2: Kurs | H2: 16000
B3: Consumable Item | C3: Norma | E3: Consumption, Ton/day | F3: Unit Price | H3: Total Cost
B4: Steam Production (Including Dearator) | C4: =408/24 -> 17 | D4: Ton/jam | E4: 408 | H4: Rp/day
B5: Gas | C5: 1000 | D5: MMBTU/day | E5: ='JUNI 2025'!$AL$240 -> 1148.3394 | F5: 11.5 | G5: USD/MMBTU | H5: =E5*H2*F5 -> 2.1129446e+08 | I5: Harga steam tinggi dikarenakan oleh unit price gas yang tinggi, ideal (9.6)
B6: Chemical Treatment
B7: EONALKALOX B1414 | C7: 7.3 | D7: l/day | E7: =C7 -> 7.3 | F7: 25340 | G7: Rp/l | H7: =E7*F7 -> 184982
B8: EONCONDENS B1720 | C8: 2.4 | D8: l/day | E8: =C8 -> 2.4 | F8: 110000 | G8: Rp/l | H8: =E8*F8 -> 264000
B9: EONOXY B8100 | C9: 2.4 | D9: l/day | E9: =C9 -> 2.4 | F9: 20160 | G9: Rp/l | H9: =E9*F9 -> 48384
B10: EONSCALE B5100 | C10: 5.8 | D10: l/day | E10: =C10 -> 5.8 | F10: 31800 | G10: Rp/l | H10: =E10*F10 -> 184440
B11: EONDESCALER B2550 | C11: 1.4 | D11: l/day | E11: =C11 -> 1.4 | F11: 39320 | G11: Rp/l | H11: =E11*F11 -> 55048
B12: Water Demin | C12: =[9]L.Water!C12*83% -> 408.0197 | D12: M3/day | E12: =C12 -> 408.0197 | F12: =[9]L.Water!F12 -> 10162 | G12: Rp/m3 | H12: =E12*F12 -> 4146296.2
B13: Preventive Maintenance | D13: Rp/day | H13: =C13 -> 0
B14: Total Pakage Boiler | H14: =SUM(H5:H13) -> 2.1617761e+08
F15: Unit Price, Rp/Ton | H15: =H14/E4 -> 529847.07 | I15: =H15*58900 -> 3.1207993e+10
B17: Note :
B18: 1. Harga gas, secara general untuk industri adalah 9,21-9,6 usd/mmBtu
C26: Kurita H-504 18:25

Sheet WWTP
B2: Water Waste Treatment Plant | G2: Kurs | H2: ='SUMMARY HPP '!I9 -> 16000
B3: Consumable Item | C3: Norma | E3: Consumption, M3/day | F3: Unit Price | H3: Total Cost
B4: Waste Water Feed | C4: =200/24 -> 8.3333333 | D4: M3/jam | E4: ='JUNI 2025'!AL267 -> 1219 | H4: Rp/day
B5: biaya transfer ke kawasan | F5: 0 | G5: Rp/m3 | H5: 8700
B6: Chemical Treatment
B7: Sugar | C7: 0 | D7: kg/day | E7: =C7 -> 0 | F7: 24890 | G7: Rp/kg | H7: =E7*F7 -> 0
B8: PE | C8: =E8*C4 -> 0.62305296 | D8: kg/day | E8: 0.074766355 | F8: 65340 | G8: Rp/kg | H8: =E8*F8 -> 4885.2336
B9: PAC | C9: =E9*C4 -> 46.728972 | D9: kg/day | E9: 5.6074766 | F9: 7702 | G9: Rp/kg | H9: =E9*F9 -> 43188.785
B10: Urea | C10: =E10*C4 -> 6.2305296 | D10: kg/day | E10: 0.74766355 | F10: 18634 | G10: Rp/kg | H10: =E10*F10 -> 13931.963
B11: TSP | C11: =E11*C4 -> 1.2461059 | D11: kg/day | E11: 0.14953271 | F11: 44722 | G11: Rp/kg | H11: =E11*F11 -> 6687.4019
B12: HCL | C12: 0 | D12: kg/day | E12: =C12 -> 0 | F12: 5700 | G12: Rp/kg | H12: =E12*F12 -> 0
B13: NaOH | C13: 0 | D13: kg/day | E13: =C13 -> 0 | F13: 15700 | G13: Rp/kg | H13: =E13*F13 -> 0
B14: Power | C14: 2675 | D14: kW/day | E14: =C14 -> 2675 | F14: =[10]UP.E!C28 -> 1550 | G14: Rp/kW | H14: =E14*F14 -> 4146250
B15: Preventive Maintenance | D15: Rp/day | H15: =E15*F15 -> 0
H16: =IFERROR(SUM(H5:H15),"") -> 4223643.4
F17: Unit Price, Rp/M3 | H17: =H16/E4 -> 3464.8428
C29: Kurita H-504 18:25

Sheet WTP
B2: Water Treatment Plant | G2: Kurs | H2: 16000
B3: Consumable Item | C3: Norma | E3: Consumption, M3/day | F3: Unit Price | H3: Total Cost
B4: Water Treatment Plant | C4: =1000/24 -> 41.666667 | D4: M3/jam | E4: ='JUNI 2025'!AL258 -> Water | H4: Rp/day
B5: Chemical | F5: 8700 | G5: Rp/m3 | H5: =F5*E4 -> #VALUE!
B6: anti scalant | C6: 0.1 | D6: kg/day | E6: =C6 -> 0.1 | F6: 44500 | G6: Rp/kg | H6: =E6*F6 -> 4450
B7: caustic soda | C7: 0.1 | D7: kg/day | E7: =C7 -> 0.1 | F7: 65340 | G7: Rp/kg | H7: =E7*F7 -> 6534
B8: citrid acid | C8: 0.1 | D8: kg/day | E8: =C8 -> 0.1 | F8: 33275 | G8: Rp/kg | H8: =E8*F8 -> 3327.5
B9: bioside | C9: 0.1 | D9: kg/day | E9: =C9 -> 0.1 | F9: 47450 | G9: Rp/kg | H9: =E9*F9 -> 4745
B10: Power | C10: 8896 | D10: kW/day | E10: =C10 -> 8896 | F10: =[10]UP.E!C28 -> 1550 | G10: Rp/kW | H10: =E10*F10 -> 13788800
B11: Preventive Maintenance | D11: Rp/day | H11: =E11*F11 -> 0
H12: =IFERROR(SUM(H5:H11),"")
F13: Unit Price, Rp/M3 | H13: =H12/E4 -> #VALUE!
C25: Kurita H-504 18:25

Sheet lab
B2: Laboratorium Chemical Cost
B3: Consumable Item | C3: Norma | E3: Consumption/ Hari | F3: Unit Price | H3: Total Biaya
H4: Per Hari
B5: Refinery, Fraksinasi, Packaging & Sotrage tank
B6: Acetic Acid Glacial | C6: 50 | D6: ml | E6: =C6 -> 50 | F6: 374 | G6: ml | H6: =E6*F6 -> 18700
B7: Aquadest | C7: 2 | D7: liter | E7: =C7 -> 2 | F7: 7250 | G7: liter | H7: =E7*F7 -> 14500
B8: BF3-methanol solution, Reagen Grade | C8: 0.5 | D8: ml | E8: =C8 -> 0.5 | F8: 500 | G8: ml | H8: =E8*F8 -> 250
B9: Chloroform | C9: 70 | D9: ml | E9: =C9 -> 70 | F9: 388 | G9: ml | H9: =E9*F9 -> 27160
B10: Cyclohexane | C10: 70 | D10: ml | E10: =C10 -> 70 | F10: 612 | G10: ml | H10: =E10*F10 -> 42840
B11: Hydrazine Sulphate | C11: 0.05 | D11: gr | E11: =C11 -> 0.05 | F11: 21000 | G11: gr | H11: =E11*F11 -> 1050
B12: Hydrochloric Acid 37% | C12: 2.6 | D12: ml | E12: =C12 -> 2.6 | F12: 236 | G12: ml | H12: =E12*F12 -> 613.6
B13: Iso Propanol Alcohol TG | C13: 5.5 | D13: liter | E13: =C13 -> 5.5 | F13: 35000 | G13: liter | H13: =E13*F13 -> 192500
B14: Isooctane | C14: 150 | D14: ml | E14: =C14 -> 150 | F14: 480 | G14: ml | H14: =E14*F14 -> 72000
B15: Indikator Phenolpthalaein 1 % | C15: 0.3 | D15: gr | E15: =C15 -> 0.3 | F15: 6750 | G15: gr | H15: =E15*F15 -> 2025
B16: Indikator Thymolpthalaein | C16: =36/357 -> 0.10084034 | D16: gr | E16: =C16 -> 0.10084034 | F16: 90000 | G16: gr | H16: =E16*F16 -> 9075.6303
B17: Starch | C17: =107/357 -> 0.29971989 | D17: gr | E17: =C17 -> 0.29971989 | F17: 3000 | G17: gr | H17: =E17*F17 -> 899.15966
B18: Liquid standard Lovibond 3,4R 30,0 Y 0,9N | C18: 0.1 | D18: ml | E18: =C18 -> 0.1 | F18: 70000 | G18: ml | H18: =E18*F18 -> 7000
B19: Liquid standard Lovibond 3,0R 28,0Y | C19: 0.1 | D19: ml | E19: =C19 -> 0.1 | F19: 70000 | G19: ml | H19: =E19*F19 -> 7000
B20: n-HexaneTehcnis | C20: 0.5 | D20: liter | E20: =C20 -> 0.5 | F20: 19300 | G20: liter | H20: =E20*F20 -> 9650
B21: p-Anisidine | C21: =48/357 -> 0.13445378 | D21: gr | E21: =C21 -> 0.13445378 | F21: 7600 | G21: gr | H21: =E21*F21 -> 1021.8487
B22: Wijs Solution | C22: 120 | D22: ml | E22: =C22 -> 120 | F22: 502 | G22: ml | H22: =E22*F22 -> 60240
B23: N2 (UHP) gas refill for GC & Foam test | C23: 0.02 | D23: Liter | E23: =C23 -> 0.02 | F23: 5000000 | G23: Liter | H23: =E23*F23 -> 100000
B24: H2 (UHP) gas refill for GC | C24: 0.03 | D24: Liter | E24: =C24 -> 0.03 | F24: 2500000 | G24: Liter | H24: =E24*F24 -> 75000
B25: UT (UHP) gas refill for GC | C25: 0.03 | D25: Liter | E25: =C25 -> 0.03 | F25: 1250000 | G25: Liter | H25: =E25*F25 -> 37500
B26: Zinc Oksida GR | C26: =179/357 -> 0.50140056 | D26: gr | E26: =C26 -> 0.50140056 | F26: 2000 | G26: gr | H26: =E26*F26 -> 1002.8011
B27: Potassium Dihydrogen Phosphate | C27: =250/357 -> 0.70028011 | D27: gr | E27: =C27 -> 0.70028011 | F27: 765 | G27: gr | H27: =E27*F27 -> 535.71429
B28: Pottasium Hydrogen Phtalate | C28: =250/357 -> 0.70028011 | D28: gr | E28: =C28 -> 0.70028011 | F28: 5200 | G28: gr | H28: =E28*F28 -> 3641.4566
B29: Sodium Thiosulphate | C29: =6069/357 -> 17 | D29: gr | E29: =C29 -> 17 | F29: 950 | G29: gr | H29: =E29*F29 -> 16150
B30: Potassium Iodide | C30: 12 | D30: gr | E30: =C30 -> 12 | F30: 2400 | G30: gr | H30: =E30*F30 -> 28800
B31: Pottasium Dichromate | C31: =357/357 -> 1 | D31: gr | E31: =C31 -> 1 | F31: 4200 | G31: gr | H31: =E31*F31 -> 4200
B32: Sodium Hydroxide | C32: =6069/357 -> 17 | D32: gr | E32: =C32 -> 17 | F32: 700 | G32: gr | H32: =E32*F32 -> 11900
B33: Sub Total | H33: =SUM(H6:H32) -> 745255.21
B35: Consumable Item | C35: Norma | E35: Consumption/day | F35: Unit Price | H35: Total Price
H36: Per Day
B37: Chemical Boiler & WTP
B38: Sodium Molybdate | C38: =286/357 -> 0.80112045 | D38: gr | E38: =C38 -> 0.80112045 | F38: 4000 | G38: gr | H38: =E38*F38 -> 3204.4818
B39: Iron test 0.0025 - 5.00 mg/l | C39: =1785/357 -> 5 | D39: Test | E39: =C39 -> 5 | F39: 10100 | G39: Test | H39: =E39*F39 -> 50500
B40: Phosphate Test 0.5 - 30 mg/l PO4-P | C40: =714/357 -> 2 | D40: pcs | E40: =C40 -> 2 | F40: 8160 | G40: pcs | H40: =E40*F40 -> 16320
B41: Sulfite Test 1,0-60,0 mg/l SO3 | C41: =360/357 -> 1.0084034 | D41: Pcs | E41: =C41 -> 1.0084034 | F41: 26550 | G41: Pcs | H41: =E41*F41 -> 26773.109
B42: Silica Test 0-800 mg/L | C42: =714/357 -> 2 | D42: pcs | E42: =C42 -> 2 | F42: 31700 | G42: pcs | H42: =E42*F42 -> 63400
B43: Silicate (Silicic Acid) 0,3-10 mg/L | C43: 2.5 | D43: pcs | E43: =C43 -> 2.5 | F43: 31006 | G43: pcs | H43: =E43*F43 -> 77515
B44: Ammonium Vanadate | C44: =179/357 -> 0.50140056 | D44: gr | E44: =C44 -> 0.50140056 | F44: 11950 | G44: gr | H44: =E44*F44 -> 5991.7367
B45: Ammonium Chloride | C45: =214/357 -> 0.59943978 | D45: gr | E45: =C45 -> 0.59943978 | F45: 2545 | G45: gr | H45: =E45*F45 -> 1525.5742
B46: Ammonium Hidroksida | C46: =1714/357 -> 4.8011204 | D46: mL | E46: =C46 -> 4.8011204 | F46: 930 | G46: mL | H46: =E46*F46 -> 4465.042
B47: Mg EDTA | C47: =71/357 -> 0.19887955 | D47: gr | E47: =C47 -> 0.19887955 | F47: 21050 | G47: gr | H47: =E47*F47 -> 4186.4146
B48: Pottasium Carbonat | C48: =12/357 -> 0.033613445 | D48: gr | E48: =C48 -> 0.033613445 | F48: 12500 | G48: gr | H48: =E48*F48 -> 420.16807
B49: Trietanolamin | C49: 0.08 | D49: mL | E49: =C49 -> 0.08 | F49: 8160 | G49: mL | H49: =E49*F49 -> 652.8
B50: Indikator EBT | C50: =12/357 -> 0.033613445 | D50: gr | E50: =C50 -> 0.033613445 | F50: 23400 | G50: gr | H50: =E50*F50 -> 786.55462
B51: Indikator Calcon | C51: =12/357 -> 0.033613445 | D51: gr | E51: =C51 -> 0.033613445 | F51: 50800 | G51: gr | H51: =E51*F51 -> 1707.563
B52: Hydroxylammonium Chloride GR | C52: 0.08 | D52: gr | E52: =C52 -> 0.08 | F52: 6250 | G52: gr | H52: =E52*F52 -> 500
B53: Eriocrom Black T-Metal | C53: 0.05 | D53: gr | E53: =C53 -> 0.05 | F53: 24260 | G53: gr | H53: =E53*F53 -> 1213
B54: Sub Total | H54: =SUM(H38:H53) -> 259161.44
B56: Consumable Item | C56: Norma | E56: Consumption/day | F56: Unit Price | H56: Total Price
H57: Per Day
B58: Chemical WWTP
B59: COD cell test 50 - 500 mg/l | C59: =59/357 -> 0.16526611 | D59: pcs | E59: =C59 -> 0.16526611 | F59: 82000 | G59: pcs | H59: =E59*F59 -> 13551.821
B60: COD cell test 500 - 10000 mg/l | C60: =59/357 -> 0.16526611 | D60: pcs | E60: =C60 -> 0.16526611 | F60: 82000 | G60: pcs | H60: =E60*F60 -> 13551.821
B61: Sub Total | H61: =SUM(H59:H60) -> 27103.641
B63: Total keseluruhan | H63: =H61+H54+H33 -> 1031520.3
C67: Spere Part Laboratorium
B68: No | C68: Consumable Item | D68: Norma | F68: Consumption/day | G68: Unit Price | I68: Total Price
I69: Per Day
B70: 1 | C70: Batang pengaduk | D70: 12 | E70: Pcs/Tahun | F70: =D70/357 -> 0.033613445 | G70: 35000 | H70: Rp/Pcs | I70: =F70*G70 -> 1176.4706
B71: =B70+1 -> 2 | C71: Beaker glass 100 mL | D71: 72 | E71: Pcs/Tahun | F71: =D71/357 -> 0.20168067 | G71: 48000 | H71: Rp/Pcs | I71: =F71*G71 -> 9680.6723
B72: =B71+1 -> 3 | C72: Beaker glass 500 mL | D72: 12 | E72: Pcs/Tahun | F72: =D72/357 -> 0.033613445 | G72: 100000 | H72: Rp/Pcs | I72: =F72*G72 -> 3361.3445
B73: =B72+1 -> 4 | C73: Beaker glass 1000 mL | D73: 6 | E73: Pcs/Tahun | F73: =D73/357 -> 0.016806723 | G73: 120000 | H73: Rp/Pcs | I73: =F73*G73 -> 2016.8067
B74: =B73+1 -> 5 | C74: Beaker glass 2000 mL | D74: 6 | E74: Pcs/Tahun | F74: =D74/357 -> 0.016806723 | G74: 142000 | H74: Rp/Pcs | I74: =F74*G74 -> 2386.5546
B75: =B74+1 -> 6 | C75: Beaker Plastik with handle 1000 mL | D75: 6 | E75: Pcs/Tahun | F75: =D75/357 -> 0.016806723 | G75: 70000 | H75: Rp/Pcs | I75: =F75*G75 -> 1176.4706
B76: =B75+1 -> 7 | C76: Boiling Round Bottom Flask 250 mL | D76: 6 | E76: Pcs/Tahun | F76: =D76/357 -> 0.016806723 | G76: 180000 | H76: Rp/Pcs | I76: =F76*G76 -> 3025.2101
B77: =B76+1 -> 8 | C77: Boiling Round Bottom Flask 1000 mL IKA | D77: 2 | E77: Pcs/Tahun | F77: =D77/357 -> 0.0056022409 | G77: 350000 | H77: Rp/Pcs | I77: =F77*G77 -> 1960.7843
B78: =B77+1 -> 9 | C78: Rotary flask 1000 mL IKA | D78: 2 | E78: Pcs/Tahun | F78: =D78/357 -> 0.0056022409 | G78: 350000 | H78: Rp/Pcs | I78: =F78*G78 -> 1960.7843
B79: =B78+1 -> 10 | C79: Corong 75 mm | D79: 6 | E79: Pcs/Tahun | F79: =D79/357 -> 0.016806723 | G79: 75000 | H79: Rp/Pcs | I79: =F79*G79 -> 1260.5042
B80: =B79+1 -> 11 | C80: Erlenmeyer 250 mL | D80: 72 | E80: Pcs/Tahun | F80: =D80/357 -> 0.20168067 | G80: 90000 | H80: Rp/Pcs | I80: =F80*G80 -> 18151.261
B81: =B80+1 -> 12 | C81: Filtering Flask 500 mL | D81: 2 | E81: Pcs/Tahun | F81: =D81/357 -> 0.0056022409 | G81: 400000 | H81: Rp/Pcs | I81: =F81*G81 -> 2240.8964
B82: =B81+1 -> 13 | C82: Gelas ukur 100 mL | D82: 2 | E82: Pcs/Tahun | F82: =D82/357 -> 0.0056022409 | G82: 85000 | H82: Rp/Pcs | I82: =F82*G82 -> 476.19048
... B110: =B109+1 -> 41 | C110: Magnetic Stirer 8 cm | D110: 12 | E110: Pcs/Tahun | F110: =D110/357 -> 0.033613445 | G110: 85000 | H110: Rp/Pcs | I110: =F110*G110 -> 2857.1429
G111: Total Cost/Days | I111: =SUM(I70:I110) -> 135770.31

Sheet genset
B2: Warming Up Genset
B3: Consumable Item | C3: Norma | E3: Consumption/day | F3: Unit Price | H3: Total Cost | K3: PLN - Power Unit Price
B4: Genset Warming Up | D4: kW/Jam | E4: 0 | H4: Rp/day | K4: Consumable Item | L4: Unit Price
B5: Solar | H5: 0 | K5: PLN Fee | L5: 1550 | M5: Rp/kWh
B6: Genset - 1 (1044 kW) | C6: 100 | D6: Ltr/Jam | E6: =(C6*25%*4)/30 -> 3.3333333 | F6: 14500 | G6: Rp/ltr | H6: =F6*E6 -> 48333.333
B7: Genset - 2 (1044 kW) | C7: 100 | D7: Ltr/Jam | E7: =(C7*25%*4)/30 -> 3.3333333 | F7: 14500 | G7: Rp/ltr | H7: =F7*E7 -> 48333.333
B8: Genset - 3 (1044 kW) | C8: 100 | D8: Ltr/Jam | E8: =(C8*25%*4)/30 -> 3.3333333 | F8: 14500 | G8: Rp/ltr | H8: =F8*E8 -> 48333.333
B9: Preventive Maintenance | D9: Rp/day | H9: 0
B10: Cost Power by Genset | H10: =SUM(H5:H9) -> 145000
B12: Genset - Power Unit Price
B13: Consumable Item | C13: Norma | E13: Power, kW/day | F13: Unit Price | H13: Total Cost
B14: Power Production by Genset | C14: 2088 | D14: kW/Jam | E14: =C14*24 -> 50112 | H14: Rp/day
B15: Solar | H15: 0
B16: Genset - 1 (1044 kW) | C16: 800 | D16: Ltr/Jam | E16: =C16*24 -> 19200 | F16: 14500 | G16: Rp/ltr | H16: =F16*E16 -> 278400000
B17: Genset - 2 (1044 kW) | C17: 800 | D17: Ltr/Jam | E17: =C17*24 -> 19200 | F17: 14500 | G17: Rp/ltr | H17: =F17*E17 -> 278400000
B18: Genset - 3 (1044 kW) | D18: Ltr/Jam | E18: 0 | F18: 14500 | G18: Rp/ltr | H18: =F18*E18 -> 0
B19: Preventive Maintenance | D19: Rp/day | H19: 0
B20: Cost Power by Genset | H20: =SUM(H15:H19) -> 556800000
F21: Unit Price, Rp/Kw | H21: =H20/E14 -> 11111.111 | I21: Unit price terlalu tinggi
B23: Note :
B24: 1. Cross cek kembali consumption solar genset per unit

Sheet AMOR
B2: Amortization
B3: Through Put CPO Proses | H3: TPD | I3: ='HPP REF '!N3 -> 1781.3187
B4: Working Day | H4: Day | I4: ='HPP REF '!N4 -> 10
B5: Total CPO Refined | H5: TPM | I5: =I4*I3 -> 17813.187
B6: Kurs Rupiah | I6: 16000
B7: No | C7: Description | D7: Actual 2023 | F7: Budget 2024
D8: Years | E8: Month | F8: Years | G8: Month | H8: RP/KG | I8: USD/MT
B9: 1 | C9: Perangkat Lunak/Software | D9: 9.6270931e+08 | E9: =D9/12 -> 80225776 | F9: =G9*12 -> 5.3192735e+08 | G9: 44327279 | H9: =$G$9/($I$5*1000) -> 2.488453 | I9: =($G$9/$I$6)/$I$5 -> 0.15552831 | J9: =D9/12 -> 80225776
B10: =B9+1 -> 2 | C10: Sertifikat/Surat Izin | D10: 2.6961444e+08 | E10: =D10/12 -> 22467870 | F10: 0 | G10: 0 | H10: =$G$10/($I$5*1000) -> 0 | I10: =($G$10/$I$6)/$I$5 -> 0
B11: =B10+1 -> 3 | C11: Inventaris Kecil (Aset Sewa) | D11: 0 | E11: =D11/12 -> 0 | F11: 0 | G11: 0 | H11: =$G$11/($I$5*1000) -> 0 | I11: =($G$11/$I$6)/$I$5 -> 0
B12: =B11+1 -> 4 | C12: Aset Hak Guna (ROU) - Kendaraan | D12: 0 | E12: =D12/12 -> 0 | F12: 0 | G12: 0 | H12: =$G$12/($I$5*1000) -> 0 | I12: =($G$12/$I$6)/$I$5 -> 0
B13: =B12+1 -> 5 | C13: Aset Hak Guna (ROU) - Tangki Timbun | D13: 0 | E13: =D13/12 -> 0 | F13: 0 | G13: 0 | H13: =$G$13/($I$5*1000) -> 0 | I13: =($G$13/$I$6)/$I$5 -> 0
B14: =B13+1 -> 6 | C14: Aset Atas Biaya Penyambungan | D14: 0 | E14: =D14/12 -> 0 | F14: 0 | G14: 0 | H14: =$G$14/($I$5*1000) -> 0 | I14: =($G$14/$I$6)/$I$5 -> 0
B15: =B14+1 -> 7 | C15: Aset Hak Guna (ROU) - Pemanfaatan Lahan Sei Mangkei + Surabaya | D15: 1.2576903e+10 | E15: =D15/12 -> 1.0480752e+09 | F15: =G15*12 -> 12048990312 | G15: 1004082526 | H15: =$G$15/($I$5*1000) -> 56.367371 | I15: =($G$15/$I$6)/$I$5 -> 3.5229607
B20: Total Cost Depreciation | D20: =SUM(D9:D19) -> 1.3809227e+10 | E20: =SUM(E9:E19) -> 1.1507689e+09 | F20: =SUM(F9:F19) -> 1.2580918e+10 | G20: =SUM(G9:G19) -> 1.0484098e+09 | H20: =SUM(H9:H19) -> 58.855824 | I20: =SUM(I9:I19) -> 3.678489

Sheet DEP
B2: Depreciation
B3: Through Put CPO Proses | J3: TPD | K3: ='HPP REF '!N3 -> 1781.3187
B4: Working Day | J4: Day | K4: ='HPP REF '!N4 -> 10
B5: Total CPO Refined | J5: TPM | K5: =K4*K3 -> 17813.187
B6: Kurs Rupiah | K6: 16000
B7: No | C7: Description | D7: Actual 2023 (Audited) | G7: Budget 2024
D8: Asset | E8: Years | F8: Month | G8: Asset | H8: Years | I8: Month | J8: RP/KG | K8: USD/MT
B9: Total Cost Depreciation | D9: =SUM(D10:D75) -> 6.7971213e+11 | E9: =SUM(E10:E75) -> 4.1807174e+10 | F9: =SUM(F10:F75) -> 3.4839312e+09 | G9: =SUM(G10:G75) -> 7.7503139e+11 | H9: =SUM(H10:H75) -> 5.0174217e+10 | I9: =SUM(I10:I75) -> 4.1811848e+09 | J9: =SUM(J10:J75) -> 234.72413 | K9: =SUM(K10:K75) -> 14.670258
B10: 1 | C10: Front Office + Canteen | D10: 3844320790 | E10: 1.9221604e+08 | F10: 16018003 | G10: 3.8443208e+09 | H10: =I10*12 -> 1.9221604e+08 | I10: 16018003 | J10: =$I$10/($K$5*1000) -> 0.89922164 | K10: =($I$10/$K$6)/$K$5 -> 0.056201353
B11: =B10+1 -> 2 | C11: Bea Cukai Building | D11: 247144032 | E11: 12357202 | F11: 1029766.8 | G11: 2.4714403e+08 | H11: =I11*12 -> 12357202 | I11: 1029766.8 | J11: =$I$11/($K$5*1000) -> 0.05780924 | K11: =($I$11/$K$6)/$K$5 -> 0.0036130775
B12: =B11+1 -> 3 | C12: Security Building | D12: 199088248 | E12: 12429395 | F12: 1035782.9 | G12: 3.9708686e+08 | H12: =I12*12 -> 19854343 | I12: 1654528.6 | J12: =$I$12/($K$5*1000) -> 0.092882233 | K12: =($I$12/$K$6)/$K$5 -> 0.0058051396
B13: =B12+1 -> 4 | C13: Bangunan Shelter / Pelataran | D13: 53111657402 | E13: 2.6555829e+09 | F13: 2.2129857e+08 | G13: 5.3111657e+10 | H13: =I13*12 -> 2.6555829e+09 | I13: 2.2129857e+08 | J13: =$I$13/($K$5*1000) -> 12.4233 | K13: =($I$13/$K$6)/$K$5 -> 0.77645627
B14: =B13+1 -> 5 | C14: Laboratorium Building | D14: 1.3920764e+09 | E14: 70956822 | F14: 5913068.5 | G14: 1.5003164e+09 | H14: =I14*12 -> 75015820 | I14: 6251318.3 | J14: =$I$14/($K$5*1000) -> 0.35093767 | K14: =($I$14/$K$6)/$K$5 -> 0.021933604
B15: =B14+1 -> 6 | C15: Refinery Room | D15: 22378266872 | E15: 1.1189133e+09 | F15: 93242779 | G15: 2.2378267e+10 | H15: =I15*12 -> 1.1189133e+09 | I15: 93242779 | J15: =$I$15/($K$5*1000) -> 5.2344804 | K15: =($I$15/$K$6)/$K$5 -> 0.32715503
B16: =B15+1 -> 7 | C16: Fractionation Room | D16: 22378266872 | E16: 1.1189133e+09 | F16: 93242779 | G16: 2.2378267e+10 | H16: =I16*12 -> 1.1189133e+09 | I16: 93242779 | J16: =$I$16/($K$5*1000) -> 5.2344804 | K16: =($I$16/$K$6)/$K$5 -> 0.32715503
B17: =B16+1 -> 8 | C17: Utility Building | D17: 22548996820 | E17: 1.1274498e+09 | F17: 93954153 | G17: 2.2548997e+10 | H17: =I17*12 -> 1.1274498e+09 | I17: 93954153 | J17: =$I$17/($K$5*1000) -> 5.2744157 | K17: =($I$17/$K$6)/$K$5 -> 0.32965098
B18: =B17+1 -> 9 | C18: Power House & Electrical Building | D18: 3242778116 | E18: 1.6663346e+08 | F18: 13886122 | G18: 3.6023423e+09 | H18: =I18*12 -> 1.8011712e+08 | I18: 15009760 | J18: =$I$18/($K$5*1000) -> 0.84262068 | K18: =($I$18/$K$6)/$K$5 -> 0.052663792
B19: =B18+1 -> 10 | C19: Weight Bridge Building (Timbangan) | D19: 3.0883582e+09 | E19: 1.6798762e+08 | F19: 13998968 | G19: 4.173935e+09 | H19: =I19*12 -> 2.0869675e+08 | I19: 17391396 | J19: =$I$19/($K$5*1000) -> 0.97632141 | K19: =($I$19/$K$6)/$K$5 -> 0.061020088
B20: =B19+1 -> 11 | C20: Warehouse TPS Spent Earth | D20: 1.3067146e+09 | E20: 65335728 | F20: 5444644 | G20: 1.3067146e+09 | H20: =I20*12 -> 65335728 | I20: 5444644 | J20: =$I$20/($K$5*1000) -> 0.30565244 | K20: =($I$20/$K$6)/$K$5 -> 0.019103277
B21: =B20+1 -> 12 | C21: Bangunan Shelter / Pelataran | D21: 0 | E21: 0 | F21: 0 | G21: 0 | H21: =I21*12 -> 0 | I21: 0 | J21: =$I$21/($K$5*1000) -> 0 | K21: =($I$21/$K$6)/$K$5 -> 0
B22: =B21+1 -> 13 | C22: Packaging Building | D22: 26865966199 | E22: 1.3432983e+09 | F22: 1.1194153e+08 | G22: 2.6865966e+10 | H22: =I22*12 -> 1.895783e+09 | I22: 1.5798192e+08 | J22: =$I$22/($K$5*1000) -> 8.8688183 | K22: =($I$22/$K$6)/$K$5 -> 0.55430115
B23: =B22+1 -> 14 | C23: Warehouse TPS Limbah B3 | D23: 808088751 | E23: 52164853 | F23: 4347071.1 | G23: 1.748922e+09 | H23: =I23*12 -> 87446098 | I23: 7287174.8 | J23: =$I$23/($K$5*1000) -> 0.40908877 | K23: =($I$23/$K$6)/$K$5 -> 0.025568048
B24: =B23+1 -> 15 | C24: Panel Room Loading - Unloading | D24: 669445527 | E24: 33472276 | F24: 2789356.4 | G24: 6.6944553e+08 | H24: =I24*12 -> 33472276 | I24: 2789356.4 | J24: =$I$24/($K$5*1000) -> 0.15658941 | K24: =($I$24/$K$6)/$K$5 -> 0.0097868378
B25: =B24+1 -> 16 | C25: Bangunan Shelter / Pelataran | D25: 0 | E25: 0 | F25: 0 | G25: 0 | H25: =I25*12 -> 0 | I25: 0 | J25: =$I$25/($K$5*1000) -> 0 | K25: =($I$25/$K$6)/$K$5 -> 0
B26: =B25+1 -> 17 | C26: Kantor RO Medan | D26: 35739000 | E26: 3573900 | F26: 297825 | G26: 35739000 | H26: =I26*12 -> 3573900 | I26: 297825 | J26: =$I$26/($K$5*1000) -> 0.016719355 | K26: =($I$26/$K$6)/$K$5 -> 0.0010449597
B27: =B26+1 -> 18 | C27: Gedung Logistic | D27: 537402145 | E27: 26870107 | F27: 2239175.6 | G27: 537402145 | H27: =I27*12 -> 26870107 | I27: 2239175.6 | J27: =$I$27/($K$5*1000) -> 0.12570326 | K27: =($I$27/$K$6)/$K$5 -> 0.0078564535
B28: =B27+1 -> 19 | C28: Ruang Expansi Filling Packaging | D28: 1071796228 | E28: 26794906 | F28: 2232908.8 | G28: 1071796228 | H28: =I28*12 -> 53589811 | I28: 4465817.6 | J28: =$I$28/($K$5*1000) -> 0.2507029 | K28: =($I$28/$K$6)/$K$5 -> 0.015668931
B29: =B28+1 -> 20 | C29: Bangunan Lainnya | D29: 236594750 | E29: 67601093 | F29: 5633424.5 | G29: 3.7519242e+09 | H29: =I29*12 -> 1.9942595e+08 | I29: 16618829 | J29: =$I$29/($K$5*1000) -> 0.93295091 | K29: =($I$29/$K$6)/$K$5 -> 0.058309432
B30: =B29+1 -> 21 | C30: Power House System | D30: 30414179484 | E30: 1.6120305e+09 | F30: 1.3433587e+08 | G30: 3.0414179e+10 | H30: =I30*12 -> 1.7106159e+09 | I30: 1.4255132e+08 | J30: =$I$30/($K$5*1000) -> 8.0025727 | K30: =($I$30/$K$6)/$K$5 -> 0.5001608
B31: =B30+1 -> 22 | C31: Reception from Road Tanker System | D31: 15714477178 | E31: 1.5906981e+09 | F31: 1.3255817e+08 | G31: 1.5714477e+10 | H31: =I31*12 -> 1.6892835e+09 | I31: 1.4077362e+08 | J31: =$I$31/($K$5*1000) -> 7.9027759 | K31: =($I$31/$K$6)/$K$5 -> 0.49392349
B32: =B31+1 -> 23 | C32: Reception & CPO Storage Tank System | D32: 3.9160256e+10 | E32: 1.8156968e+09 | F32: 1.5130807e+08 | G32: 3.9160256e+10 | H32: =I32*12 -> 1.9142822e+09 | I32: 1.5952352e+08 | J32: =$I$32/($K$5*1000) -> 8.955361 | K32: =($I$32/$K$6)/$K$5 -> 0.55971006
B33: =B32+1 -> 24 | C33: Refinery Product System | D33: 26158484525 | E33: 1.546139e+09 | F33: 1.2884492e+08 | G33: 2.6158485e+10 | H33: =I33*12 -> 2.1043359e+09 | I33: 1.7536132e+08 | J33: =$I$33/($K$5*1000) -> 9.8444666 | K33: =($I$33/$K$6)/$K$5 -> 0.61527916
B34: =B33+1 -> 25 | C34: Fractionation Product System | D34: 44700543389 | E34: 2.5257813e+09 | F34: 2.1048177e+08 | G34: 4.4700543e+10 | H34: =I34*12 -> 2.6243667e+09 | I34: 2.1869722e+08 | J34: =$I$34/($K$5*1000) -> 12.277265 | K34: =($I$34/$K$6)/$K$5 -> 0.76732908
B35: =B34+1 -> 26 | C35: Compressed Air System | D35: 12406716786 | E35: 6.9726354e+08 | F35: 58105295 | G35: 1.2406717e+10 | H35: =I35*12 -> 6.9726354e+08 | I35: 58105295 | J35: =$I$35/($K$5*1000) -> 3.2619258 | K35: =($I$35/$K$6)/$K$5 -> 0.20387036
B36: =B35+1 -> 27 | C36: Fuel Distribution System | D36: 2279256408 | E36: 1.6844371e+08 | F36: 14036976 | G36: 2.2792564e+09 | H36: =I36*12 -> 2.0366838e+08 | I36: 16972365 | J36: =$I$36/($K$5*1000) -> 0.9527978 | K36: =($I$36/$K$6)/$K$5 -> 0.059549862
B37: =B36+1 -> 28 | C37: Waste Water Treatment System | D37: 8173671310 | E37: 5.0165483e+08 | F37: 41804569 | G37: 8.1736713e+09 | H37: =I37*12 -> 5.1840723e+08 | I37: 43200602 | J37: =$I$37/($K$5*1000) -> 2.4252034 | K37: =($I$37/$K$6)/$K$5 -> 0.15157521
B38: =B37+1 -> 29 | C38: Clean Water System | D38: 8.1369458e+09 | E38: 4.697884e+08 | F38: 39149033 | G38: 8.1369458e+09 | H38: =I38*12 -> 4.697884e+08 | I38: 39149033 | J38: =$I$38/($K$5*1000) -> 2.1977557 | K38: =($I$38/$K$6)/$K$5 -> 0.13735973
B39: =B38+1 -> 30 | C39: Demin Water Distribution System | D39: 5554219736 | E39: 3.7021373e+08 | F39: 30851144 | G39: 5.5542197e+09 | H39: =I39*12 -> 3.7021373e+08 | I39: 30851144 | J39: =$I$39/($K$5*1000) -> 1.7319273 | K39: =($I$39/$K$6)/$K$5 -> 0.10824545
B40: =B39+1 -> 31 | C40: Steam Generation System | D40: 28411905935 | E40: 1.6009903e+09 | F40: 1.3341586e+08 | G40: 2.8411906e+10 | H40: =I40*12 -> 1.6009903e+09 | I40: 1.3341586e+08 | J40: =$I$40/($K$5*1000) -> 7.4897242 | K40: =($I$40/$K$6)/$K$5 -> 0.46810776 | L40: =H40/12 -> 1.3341586e+08
B41: =B40+1 -> 32 | C41: Cooling Water Distribution System | D41: 8813632097 | E41: 5.5719688e+08 | F41: 46433074 | G41: 8.8136321e+09 | H41: =I41*12 -> 5.5719688e+08 | I41: 46433074 | J41: =$I$41/($K$5*1000) -> 2.6066685 | K41: =($I$41/$K$6)/$K$5 -> 0.16291678
B42: =B41+1 -> 33 | C42: Fire Water System | D42: 4990631887 | E42: 3.5991574e+08 | F42: 29992978 | G42: 4.9906319e+09 | H42: =I42*12 -> 3.5991574e+08 | I42: 29992978 | J42: =$I$42/($K$5*1000) -> 1.6837514 | K42: =($I$42/$K$6)/$K$5 -> 0.10523446
B43: =B42+1 -> 34 | C43: Dual Fuel Emergency Generator | D43: 11752092639 | E43: 6.1186193e+08 | F43: 50988494 | G43: 1.1752093e+10 | H43: =I43*12 -> 6.1186193e+08 | I43: 50988494 | J43: =$I$43/($K$5*1000) -> 2.8624016 | K43: =($I$43/$K$6)/$K$5 -> 0.1789001
B44: =B43+1 -> 35 | C44: Steam Distribution & Condensate Recovery System | D44: 9891619567 | E44: 8.9987659e+08 | F44: 74989716 | G44: 9.8916196e+09 | H44: =I44*12 -> 8.9987659e+08 | I44: 74989716 | J44: =$I$44/($K$5*1000) -> 4.2097866 | K44: =($I$44/$K$6)/$K$5 -> 0.26311166
B45: =B44+1 -> 36 | C45: Fire Water Main Ring System | D45: 4518985787 | E45: 2.4463794e+08 | F45: 20386495 | G45: 4.5189858e+09 | H45: =I45*12 -> 2.4463794e+08 | I45: 20386495 | J45: =$I$45/($K$5*1000) -> 1.1444608 | K45: =($I$45/$K$6)/$K$5 -> 0.071528803
B46: =B45+1 -> 37 | C46: Packaging System | D46: 34206697993 | E46: 3.1394346e+09 | F46: 2.6161955e+08 | G46: 1.2163436e+11 | H46: =I46*12 -> 7.8746236e+09 | I46: 6.5621863e+08 | J46: =$I$46/($K$5*1000) -> 36.838923 | K46: =($I$46/$K$6)/$K$5 -> 2.3024327
B47: =B46+1 -> 38 | C47: Refinery System | D47: 93804025615 | E47: 6.3108388e+09 | F47: 5.2590324e+08 | G47: 9.3804026e+10 | H47: =I47*12 -> 6.3327722e+09 | I47: 5.2773101e+08 | J47: =$I$47/($K$5*1000) -> 29.625862 | K47: =($I$47/$K$6)/$K$5 -> 1.8516164
B48: =B47+1 -> 39 | C48: Fractionation System | D48: 69305898501 | E48: 4.7141422e+09 | F48: 3.9284518e+08 | G48: 6.9305899e+10 | H48: =I48*12 -> 4.7141422e+09 | I48: 3.9284518e+08 | J48: =$I$48/($K$5*1000) -> 22.053616 | K48: =($I$48/$K$6)/$K$5 -> 1.378351
B49: =B48+1 -> 40 | C49: Fat Pit System | D49: 1222833568 | E49: 76427098 | F49: 6368924.8 | G49: 1.2228336e+09 | H49: =I49*12 -> 76427098 | I49: 6368924.8 | J49: =$I$49/($K$5*1000) -> 0.35753989 | K49: =($I$49/$K$6)/$K$5 -> 0.022346243
B50: =B49+1 -> 41 | C50: Weight Bridge | D50: 2557397646 | E50: 1.2786988e+08 | F50: 10655824 | G50: 2.5573976e+09 | H50: =I50*12 -> 1.2786988e+08 | I50: 10655824 | J50: =$I$50/($K$5*1000) -> 0.5981986 | K50: =($I$50/$K$6)/$K$5 -> 0.037387412
B51: =B50+1 -> 42 | C51: Mesin Dan Perlengkapan Pabrik | D51: 30580769059 | E51: 1.6581493e+09 | F51: 1.3817911e+08 | G51: 3.0797884e+10 | H51: =I51*12 -> 2.8889928e+09 | I51: 2.407494e+08 | J51: =$I$51/($K$5*1000) -> 13.515234 | K51: =($I$51/$K$6)/$K$5 -> 0.84470215
B52: =B51+1 -> 43 | C52: Installation System Electrical (Auxiliary) | D52: 2460303143 | E52: 1.5376895e+08 | F52: 12814079 | G52: 2460303143 | H52: =I52*12 -> 1.5376895e+08 | I52: 12814079 | J52: =$I$52/($K$5*1000) -> 0.71935914 | K52: =($I$52/$K$6)/$K$5 -> 0.044959946
B53: =B52+1 -> 44 | C53: Mesin Dan Perlengkapan Pabrik | D53: 0 | E53: 0 | F53: 0 | G53: 0 | H53: =I53*12 -> 0 | I53: 0 | J53: =$I$53/($K$5*1000) -> 0 | K53: =($I$53/$K$6)/$K$5 -> 0
B54: =B53+1 -> 45 | C54: Mesin Dan Perlengkapan Pabrik | D54: 0 | E54: 0 | F54: 0 | G54: 0 | H54: =I54*12 -> 0 | I54: 0 | J54: =$I$54/($K$5*1000) -> 0 | K54: =($I$54/$K$6)/$K$5 -> 0
B55: =B54+1 -> 46 | C55: Refinery Product System | D55: 0 | E55: 0 | F55: 0 | G55: 0 | H55: =I55*12 -> 0 | I55: 0 | J55: =$I$55/($K$5*1000) -> 0 | K55: =($I$55/$K$6)/$K$5 -> 0
B56: =B55+1 -> 47 | C56: Perlengkapan Pabrik Lainnya | D56: 814629325 | E56: 1.3842046e+08 | F56: 11535038 | G56: 814629325 | H56: =I56*12 -> 1.3842046e+08 | I56: 11535038 | J56: =$I$56/($K$5*1000) -> 0.64755612 | K56: =($I$56/$K$6)/$K$5 -> 0.040472258
B57: =B56+1 -> 48 | C57: Bangunan Shelter / Pelataran | D57: 0 | E57: 0 | F57: 0 | G57: 0 | H57: =I57*12 -> 0 | I57: 0 | J57: =$I$57/($K$5*1000) -> 0 | K57: =($I$57/$K$6)/$K$5 -> 0
B58: =B57+1 -> 49 | C58: Saluran Drainase | D58: 3324550757 | E58: 1.6622754e+08 | F58: 13852295 | G58: 3.3245508e+09 | H58: =I58*12 -> 1.6622754e+08 | I58: 13852295 | J58: =$I$58/($K$5*1000) -> 0.7776427 | K58: =($I$58/$K$6)/$K$5 -> 0.048602669
B59: =B58+1 -> 50 | C59: Fence | D59: 1457273906 | E59: 72863695 | F59: 6071974.6 | G59: 1457273906 | H59: =I59*12 -> 72863695 | I59: 6071974.6 | J59: =$I$59/($K$5*1000) -> 0.34086964 | K59: =($I$59/$K$6)/$K$5 -> 0.021304352
B60: =B59+1 -> 51 | C60: Bangunan Shelter / Pelataran | D60: 0 | E60: 0 | F60: 0 | G60: 0 | H60: =I60*12 -> 0 | I60: 0 | J60: =$I$60/($K$5*1000) -> 0 | K60: =($I$60/$K$6)/$K$5 -> 0
B61: =B60+1 -> 52 | C61: Alat Pengangkutan | D61: 702420000 | E61: 58515250 | F61: 4876270.8 | G61: 702420000 | H61: =I61*12 -> 92109000 | I61: 7675750 | J61: =$I$61/($K$5*1000) -> 0.43090268 | K61: =($I$61/$K$6)/$K$5 -> 0.026931417
B62: =B61+1 -> 53 | C62: Perabot & Perlengkapan Kantor | D62: 2093240354 | E62: 2.8749571e+08 | F62: 23957976 | G62: 2093240354 | H62: =I62*12 -> 2.8749571e+08 | I62: 23957976 | J62: =$I$62/($K$5*1000) -> 1.3449573 | K62: =($I$62/$K$6)/$K$5 -> 0.084059832
B63: =B62+1 -> 54 | C63: Perabot dan Perlengkapan Mess | D63: 0 | E63: 0 | F63: 0 | G63: 0 | H63: =I63*12 -> 0 | I63: 0 | J63: =$I$63/($K$5*1000) -> 0 | K63: =($I$63/$K$6)/$K$5 -> 0
B64: =B63+1 -> 55 | C64: Alat & Perlengkapan Pabrik | D64: 68073000 | E64: 13614600 | F64: 1134550 | G64: 68073000 | H64: =I64*12 -> 13614600 | I64: 1134550 | J64: =$I$64/($K$5*1000) -> 0.063691579 | K64: =($I$64/$K$6)/$K$5 -> 0.0039807237
B65: =B64+1 -> 56 | C65: Alat dan Perlengkapan Bengkel | D65: 140550000 | E65: 28110000 | F65: 2342500 | G65: 140550000 | H65: =I65*12 -> 28110000 | I65: 2342500 | J65: =$I$65/($K$5*1000) -> 0.1315037 | K65: =($I$65/$K$6)/$K$5 -> 0.0082189813
B66: =B65+1 -> 57 | C66: Alat dan Perlengkapan Laboratorium | D66: 3453064640 | E66: 3.7398892e+08 | F66: 31165744 | G66: 4405170868 | H66: =I66*12 -> 8.9603417e+08 | I66: 74669514 | J66: =$I$66/($K$5*1000) -> 4.1918111 | K66: =($I$66/$K$6)/$K$5 -> 0.26198819
B67: =B66+1 -> 58 | C67: Alat IT / Komputer | D67: 1542535419 | E67: 2.9444276e+08 | F67: 24536897 | G67: 1.9760604e+09 | H67: =I67*12 -> 2.9825396e+08 | I67: 24854497 | J67: =$I$67/($K$5*1000) -> 1.3952863 | K67: =($I$67/$K$6)/$K$5 -> 0.087205397
B68: =B67+1 -> 59 | C68: Perabot & Perlengkapan Lainnya | D68: 11270000 | E68: 2254000 | F68: 187833.33 | G68: 11270000 | H68: =I68*12 -> 2254000 | I68: 187833.33 | J68: =$I$68/($K$5*1000) -> 0.010544623 | K68: =($I$68/$K$6)/$K$5 -> 0.00065903891
B69: =B68+1 -> 60 | C69: Aktiva Tetap Non Produktif | D69: 26932688 | E69: 5386537.6 | F69: 448878.13 | G69: 26932688 | H69: =I69*12 -> 5386537.5 | I69: 448878.13 | J69: =$I$69/($K$5*1000) -> 0.025199204 | K69: =($I$69/$K$6)/$K$5 -> 0.0015749502
B70: =B69+1 -> 61 | C70: Totem AKHLAK | D70: 30000000 | E70: 6000000 | F70: 500000 | G70: 30000000 | H70: =I70*12 -> 6000000.1 | I70: 500000.01 | J70: =$I$70/($K$5*1000) -> 0.028069093 | K70: =($I$70/$K$6)/$K$5 -> 0.0017543183
B71: =B70+1 -> 62 | C71: Main Office | D71: 6869341541 | E71: 3.4448348e+08 | F71: 28706957 | G71: 6.9506539e+09 | H71: =I71*12 -> 3.4753269e+08 | I71: 28961058 | J71: =$I$71/($K$5*1000) -> 1.6258212 | K71: =($I$71/$K$6)/$K$5 -> 0.10161383

Sheet MTC
C1: working days | F1: working days
B2: Summary - PM Electrical | C2: ='JUNI 2025'!AL6 -> 10 | E2: Summary - PM Mechanical | F2: ='JUNI 2025'!AL6 -> 10
B3: Consumable Item | C3: Total Price | E3: Consumable Item | F3: Total Price
C4: Per Day | F4: Per Day
B5: Biaya Pemeliharaan Unit Refinery(Listrik) | C5: 1648879.6 | E5: Biaya Pemeliharaan Unit Refinery | F5: 4911824.3
B6: HP Boiler | C6: 2678431.4 | E6: Biaya Pemeliharaan Unit Fraksinasi | F6: 1230672.3
B7: Dry Fractination - Crystalizer & Filter Press | C7: 288459.38 | E7: Biaya Pemeliharaan Unit Cooling Tower | F7: 1084733.9
B8: Physical Refinery-Bleaching and Deodorization | C8: 404271.71 | E8: Biaya Pemeliharaan Unit Packaging | F8: 833815.52
B9: BOILER | C9: 150891.4 | E9: Biaya Pemeliharaan Unit Material Handling | F9: 949299.72
B10: Water Plant, Effluent & Hydrant | C10: 58543.417 | E10: Biaya Pemeliharaan Unit Utility | F10: 1106022.4
B11: Pump House | C11: 87425.77 | E11: Barang Consumable Maintenance | F11: 5634698.9
B12: DCS-CCR ISBL | C12: 254341.74
B13: Lighting All Area | C13: 114733.89 | E13: Total | F13: =SUM(F5:F12) -> 15751067
B14: Consumable | C14: 203159.66 | E14: Total/Month | F14: =F13*F2 -> 1.5751067e+08
B15: Kalibrasi Instrument Pabrik | C15: 580672.27 | E15: Total/Yearly | F15: =F14*12 -> 1.890128e+09
B16: Service Special Equipment | C16: 4089635.9
B17: Total/Day | C17: =SUM(C5:C16) -> 10559446 | E17: TOTAL COST
B18: Total/Month | C18: =C17*C2 -> 1.0559446e+08 | E18: PM E + PM M | F18: =F14+C18 -> 2.6310513e+08
B19: Total/Yearly | C19: =C18*12 -> 1.2671335e+09 | E19: TOTAL | F19: =F18*12 -> 3.1572616e+09

Sheet LOG
B2: Port Cost Kuala Tanjung
B3: Through Put CPO Proses | J3: TPD | K3: ='HPP REF '!N3 -> 1781.3187
B4: Working Day | J4: Day | K4: ='HPP REF '!N4 -> 10
B5: Total CPO Refined | J5: TPM | K5: =K4*K3 -> 17813.187
B6: Kurs Rupiah | K6: 16000
B7: No | C7: Description | G7: Norma | I7: Total Biaya ( Rp ) | J7: RP/KG | K7: USD/MT
B8: 1 | C8: Trucking Komoditi ke Kuala Tanjung | E8: Olein ( Ton ) | F8: =(100%-0.8%-1.1*5%)*80%*K5 -> 13352.765 | G8: Rp/Kg | H8: 90 | I8: =H8*F8*1000 -> 1.2017488e+09 | J8: =I8/($K$5*1000) -> 67.464 | K8: =(I8/$K$6)/$K$5 -> 4.2165
E9: Stearin ( Ton ) Iso Tank | F9: =(100%-0.8%-1.1*5%)*20%*K5 -> 3338.1912 | G9: Rp/Kg | H9: 150 | I9: =H9*F9*1000 -> 5.0072869e+08 | J9: =I9/($K$5*1000) -> 28.11 | K9: =(I9/$K$6)/$K$5 -> 1.756875
E10: PFAD ( Ton ) Iso Tank | F10: =1.1*5%*K5 -> 979.72529 | G10: Rp/Kg | H10: 150 | I10: =H10*F10*1000 -> 1.4695879e+08 | J10: =I10/($K$5*1000) -> 8.25 | K10: =(I10/$K$6)/$K$5 -> 0.515625
B11: 2 | C11: Sewa Tank PTI Total Volume : 24.000 MT ( 5 Unit ) | E11: Tank 8.000 MT >> Olein | F11: 1 | G11: Rp/Kg | H11: 77 | I11: =H11*8000*F11*1000 -> 616000000 | J11: =I11/($K$5*1000) -> 34.581122 | K11: =(I11/$K$6)/$K$5 -> 2.1613202
E12: Tank 5.000 MT >> Stearin | F12: 2 | G12: Rp/Kg | H12: 79 | I12: =H12*5000*F12*1000 -> 790000000 | J12: =I12/($K$5*1000) -> 44.349167 | K12: =(I12/$K$6)/$K$5 -> 2.7718229
E13: Tank 3.000 MT >> RBDPO | F13: 1 | G13: Rp/Kg | H13: 77 | I13: =H13*3000*F13*1000 -> 231000000 | J13: =I13/($K$5*1000) -> 12.967921 | K13: =(I13/$K$6)/$K$5 -> 0.81049506
E14: Tank 3.000 MT S/S >> PFAD | F14: 1 | G14: Rp/Kg | H14: 83 | I14: =H14*3000*F14*1000 -> 249000000 | J14: =I14/($K$5*1000) -> 13.978408 | K14: =(I14/$K$6)/$K$5 -> 0.87365052
B15: 3 | C15: Finalty Over Capacity dari tank | D15: 0 | E15: Over Volume Olein | F15: =F8-(8000*D15) -> 13352.765 | G15: Rp/Kg | H15: 43 | I15: =H15*F15*1000 -> 5.7416889e+08 | J15: =I15/($K$5*1000) -> 32.2328 | K15: =(I15/$K$6)/$K$5 -> 2.01455
D16: 0 | E16: Over Volume Stearin | F16: =F9-(10000*D16) -> 3338.1912 | G16: Rp/Kg | H16: 43 | I16: =H16*F16*1000 -> 1.4354222e+08 | J16: =I16/($K$5*1000) -> 8.0582 | K16: =(I16/$K$6)/$K$5 -> 0.5036375
D17: 0 | E17: Over Volume PFAD | F17: =F10-(3000*D17) -> 979.72529 | G17: Rp/Kg | H17: 43 | I17: =H17*F17*1000 -> 42128187 | J17: =I17/($K$5*1000) -> 2.365 | K17: =(I17/$K$6)/$K$5 -> 0.1478125
B18: 3 | C18: Beban Instalasi Pemompaan dan Pemanasan | E18: Total Volume | F18: =SUM(F8:F10) -> 17670.682 | G18: Rp/Kg | H18: 22 | I18: =H18*F18*1000 -> 3.8875499e+08 | J18: =I18/($K$5*1000) -> 21.824 | K18: =(I18/$K$6)/$K$5 -> 1.364
B19: =B18+1 -> 4 | C19: Pompa | E19: Total Volume | F19: =F18 -> 17670.682 | G19: Rp/Kg | H19: 26 | I19: =H19*F18*1000 -> 4.5943772e+08 | J19: =I19/($K$5*1000) -> 25.792 | K19: =(I19/$K$6)/$K$5 -> 1.612
B20: =B19+1 -> 5 | C20: Beban Analisa ( Surveyor ) | E20: Total Volume | F20: =F18 -> 17670.682 | G20: Rp/Kg | H20: 3 | I20: =H20*F20*1000 -> 53012045 | J20: =I20/($K$5*1000) -> 2.976 | K20: =(I20/$K$6)/$K$5 -> 0.186
B21: =B20+1 -> 6 | C21: Beban Pelabuhan ( Documen-Documen Pelabuhan ) | E21: Total Volume | F21: =F20 -> 17670.682 | G21: Rp/Kg | H21: 3 | I21: =H21*F21*1000 -> 53012045 | J21: =I21/($K$5*1000) -> 2.976 | K21: =(I21/$K$6)/$K$5 -> 0.186
B22: =B21+1 -> 7 | C22: Beban Asuransi (Cost Insurance Freight)
B23: =B22+1 -> 8 | C23: Beban Sewa Kapal
B24: =B23+1 -> 9 | C24: Beban Pengangkutan Di Pelabuhan
B25: Total Biaya Transfer Product ke Kuala Tanjung Port | I25: =SUM(I8:I24) -> 5.4494924e+09 | J25: =SUM(J8:J24) -> 305.92462 | K25: =SUM(K8:K24) -> 19.120289

Sheet OH
B2: Overhead ( OH )
B3: Through Put CPO Proses | H3: TPD | I3: ='HPP REF '!N3 -> 1781.3187
B4: Working Day | H4: Day | I4: ='SUMMARY HPP '!I4 -> 10
B5: Total CPO Refined | H5: TPM | I5: =I4*I3 -> 17813.187
B6: Kurs Rupiah | I6: 16000
B7: No | C7: Description | D7: Actual 2023 (Audited) | F7: Budget 2024
D8: Years | E8: Month | F8: Years | G8: Month | H8: RP/KG | I8: USD/MT
B9: 1 | C9: Biaya Perjalanan Dinas (Dalam Provinsi) | D9: 305458258 | E9: =IFERROR(D9/12,0) -> 25454855 | F9: =G9*12 -> 3.6654991e+08 | G9: 30545826 | H9: =G9/($I$5*1000) -> 1.7147872 | I9: =(G9/$I$6)/$I$5 -> 0.1071742
B10: =B9+1 -> 2 | C10: Biaya Perjalanan Dinas (Luar Provinsi) | D10: 2.6287295e+09 | E10: =IFERROR(D10/12,0) -> 2.1906079e+08 | F10: =G10*12 -> 3.5487849e+09 | G10: 2.9573207e+08 | H10: =G10/($I$5*1000) -> 16.601862 | I10: =(G10/$I$6)/$I$5 -> 1.0376164
B11: =B10+1 -> 3 | C11: Beban BBM Kendaraan | D11: 720175678 | E11: =IFERROR(D11/12,0) -> 60014640 | F11: =G11*12 -> 7.5618446e+08 | G11: 63015372 | H11: =G11/($I$5*1000) -> 3.5375686 | I11: =(G11/$I$6)/$I$5 -> 0.22109804
B12: =B11+1 -> 4 | C12: Beban Sewa Kendaraan | D12: 2428347903 | E12: =IFERROR(D12/12,0) -> 2.0236233e+08 | F12: =G12*12 -> 2220000000 | G12: 185000000 | H12: =G12/($I$5*1000) -> 10.385564 | I12: =(G12/$I$6)/$I$5 -> 0.64909777
B13: =B12+1 -> 5 | C13: Beban Kendaraan Lainnya | D13: 110862850 | E13: =IFERROR(D13/12,0) -> 9238570.8 | F13: =G13*12 -> 110862850 | G13: 9238570.8 | H13: =G13/($I$5*1000) -> 0.51863661 | I13: =(G13/$I$6)/$I$5 -> 0.032414788
B14: =B13+1 -> 6 | C14: Beban Sewa Bangunan / Inventaris / Aset | D14: 126990400 | E14: =IFERROR(D14/12,0) -> 10582533 | F14: =G14*12 -> 110000400 | G14: 9166700 | H14: =G14/($I$5*1000) -> 0.51460191 | I14: =(G14/$I$6)/$I$5 -> 0.032162619
B15: =B14+1 -> 7 | C15: Beban Penelitian, Percobaan & Pengembangan | D15: 108868060 | E15: =IFERROR(D15/12,0) -> 9072338.3 | F15: =G15*12 -> 100000000 | G15: 8333333.3 | H15: =G15/($I$5*1000) -> 0.46781821 | I15: =(G15/$I$6)/$I$5 -> 0.029238638
B16: =B15+1 -> 8 | C16: Beban Pemeliharaan Bangunan Rumah | D16: 203000 | E16: =IFERROR(D16/12,0) -> 16916.667 | F16: =G16*12 -> 0 | G16: 0 | H16: =G16/($I$5*1000) -> 0 | I16: =(G16/$I$6)/$I$5 -> 0
B17: =B16+1 -> 9 | C17: Beban Pemeliharaan Bangunan Perusahaan | D17: 108952486 | E17: =IFERROR(D17/12,0) -> 9079373.8 | F17: =G17*12 -> 1.1440011e+08 | G17: 9533342.5 | H17: =G17/($I$5*1000) -> 0.53518455 | I17: =(G17/$I$6)/$I$5 -> 0.033449035
B18: =B17+1 -> 10 | C18: Beban Pemeliharaan Mesin & Instalansi | D18: 32369030 | E18: =IFERROR(D18/12,0) -> 2697419.2 | F18: =G18*12 -> 33987482 | G18: 2832290.1 | H18: =G18/($I$5*1000) -> 0.15899963 | I18: =(G18/$I$6)/$I$5 -> 0.0099374768
B19: =B18+1 -> 11 | C19: Beban Pemeliharaan Jalan, Jembatan & Saluran Air | D19: 179265600 | E19: =IFERROR(D19/12,0) -> 14938800 | F19: =G19*12 -> 188228880 | G19: 15685740 | H19: =G19/($I$5*1000) -> 0.88056899 | I19: =(G19/$I$6)/$I$5 -> 0.055035562
B20: =B19+1 -> 12 | C20: Beban Pemeliharaan Alat Inventaris Kecil | D20: 253700695 | E20: =IFERROR(D20/12,0) -> 21141725 | F20: =G20*12 -> 2.6638573e+08 | G20: 22198811 | H20: =G20/($I$5*1000) -> 1.246201 | I20: =(G20/$I$6)/$I$5 -> 0.07788756
B21: =B20+1 -> 13 | C21: Beban Pemakaian Inventaris Kecil | D21: 1859843066 | E21: =IFERROR(D21/12,0) -> 1.5498692e+08 | F21: =G21*12 -> 335473201 | G21: 27956100 | H21: =G21/($I$5*1000) -> 1.5694047 | I21: =(G21/$I$6)/$I$5 -> 0.098087796
B22: =B21+1 -> 14 | C22: Beban Iuran, Sumbangan, & Bina Lingkungan | D22: 694460474 | E22: =IFERROR(D22/12,0) -> 57871706 | F22: =G22*12 -> 2.6839105e+08 | G22: 22365921 | H22: =G22/($I$5*1000) -> 1.2555822 | I22: =(G22/$I$6)/$I$5 -> 0.07847389
B23: =B22+1 -> 15 | C23: Beban Instansi Kelembagaan | E23: =IFERROR(D23/12,0) -> 0 | F23: =G23*12 -> 60000000 | G23: 5000000 | H23: =G23/($I$5*1000) -> 0.28069093 | I23: =(G23/$I$6)/$I$5 -> 0.017543183
B24: =B23+1 -> 16 | C24: Beban Pajak & Retribusi | D24: 659276883 | E24: =IFERROR(D24/12,0) -> 54939740 | F24: =G24*12 -> 1518332400 | G24: 126527700 | H24: =G24/($I$5*1000) -> 7.1030355 | I24: =(G24/$I$6)/$I$5 -> 0.44393972
B25: =B24+1 -> 17 | C25: Beban Premi Assuransi | E25: =IFERROR(D25/12,0) -> 0 | F25: =G25*12 -> 197000000 | G25: 16416667 | H25: =G25/($I$5*1000) -> 0.92160188 | I25: =(G25/$I$6)/$I$5 -> 0.057600118
B26: =B25+1 -> 18 | C26: Beban Penerangan | D26: 62716328 | E26: =IFERROR(D26/12,0) -> 5226360.7 | F26: =G26*12 -> 80400000 | G26: 6700000 | H26: =G26/($I$5*1000) -> 0.37612584 | I26: =(G26/$I$6)/$I$5 -> 0.023507865
B27: =B26+1 -> 19 | C27: Beban Persediaan Air | D27: 1756590 | E27: =IFERROR(D27/12,0) -> 146382.5 | F27: =G27*12 -> 6840000 | G27: 570000 | H27: =G27/($I$5*1000) -> 0.031998766 | I27: =(G27/$I$6)/$I$5 -> 0.0019999229
B28: =B27+1 -> 20 | C28: Beban Pemakaian Perlengkapan Kantor | D28: 1.1936208e+09 | E28: =IFERROR(D28/12,0) -> 99468402 | F28: =G28*12 -> 1.1936208e+09 | G28: 99468402 | H28: =G28/($I$5*1000) -> 5.5839756 | I28: =(G28/$I$6)/$I$5 -> 0.34899848
B29: =B28+1 -> 21 | C29: Beban Pengendalian Lingkungan (ISO 14000) | D29: 488020500 | E29: =IFERROR(D29/12,0) -> 40668375 | F29: =G29*12 -> 264000000 | G29: 22000000 | H29: =G29/($I$5*1000) -> 1.2350401 | I29: =(G29/$I$6)/$I$5 -> 0.077190005
B30: =B29+1 -> 22 | C30: Beban Sistem Manajemen Keselamatan & Kesehatan Kerja (SMK3) | D30: 68171900 | E30: =IFERROR(D30/12,0) -> 5680991.7 | F30: =G30*12 -> 258000000 | G30: 21500000 | H30: =G30/($I$5*1000) -> 1.206971 | I30: =(G30/$I$6)/$I$5 -> 0.075435687
B31: =B30+1 -> 23 | C31: Beban Pendidikan & Pengembangan SDM | D31: 1186354647 | E31: =IFERROR(D31/12,0) -> 98862887 | F31: =G31*12 -> 10000000 | G31: 833333.33 | H31: =G31/($I$5*1000) -> 0.046781821 | I31: =(G31/$I$6)/$I$5 -> 0.0029238638
B32: =B31+1 -> 24 | C32: Beban Audit (Independent Auditor) | D32: 8.477783e+08 | E32: =IFERROR(D32/12,0) -> 70648192 | F32: =G32*12 -> 9.0712278e+08 | G32: 75593565 | H32: =G32/($I$5*1000) -> 4.2436856 | I32: =(G32/$I$6)/$I$5 -> 0.26523035
B33: =B32+1 -> 25 | C33: Beban Konsultan - Eksternal | D33: 245454645 | E33: =IFERROR(D33/12,0) -> 20454554 | F33: =G33*12 -> 2.7000011e+08 | G33: 22500009 | H33: =G33/($I$5*1000) -> 1.2631097 | I33: =(G33/$I$6)/$I$5 -> 0.078944356
B34: =B33+1 -> 26 | C34: Beban Insentif Karyawan | E34: =IFERROR(D34/12,0) -> 0 | F34: =G34*12 -> 0 | G34: 0 | H34: =G34/($I$5*1000) -> 0 | I34: =(G34/$I$6)/$I$5 -> 0
B35: =B34+1 -> 27 | C35: Beban Jasa Produksi Karyawan | E35: =IFERROR(D35/12,0) -> 0 | F35: =G35*12 -> 0 | G35: 0 | H35: =G35/($I$5*1000) -> 0 | I35: =(G35/$I$6)/$I$5 -> 0
B36: =B35+1 -> 28 | C36: Beban Uang Jasa (Jubilium, SHT, Dll) | D36: 188207400 | E36: =IFERROR(D36/12,0) -> 15683950 | F36: =G36*12 -> 207028140 | G36: 17252345 | H36: =G36/($I$5*1000) -> 0.96851535 | I36: =(G36/$I$6)/$I$5 -> 0.060532209
B37: =B36+1 -> 29 | C37: Beban Imbalan Pasca Kerja | D37: 4384212523 | E37: =IFERROR(D37/12,0) -> 3.6535104e+08 | F37: =G37*12 -> 666345107 | G37: 55528759 | H37: =G37/($I$5*1000) -> 3.1172838 | I37: =(G37/$I$6)/$I$5 -> 0.19483024
B38: =B37+1 -> 30 | C38: Beban Pengurusan Sertifikasi / Hak Merk / Izin / Dll | D38: 108648500 | E38: =IFERROR(D38/12,0) -> 9054041.7 | F38: =G38*12 -> 114080925 | G38: 9506743.8 | H38: =G38/($I$5*1000) -> 0.53369135 | I38: =(G38/$I$6)/$I$5 -> 0.033355709
B39: =B38+1 -> 31 | C39: Beban Entertainment | D39: 80056015 | E39: =IFERROR(D39/12,0) -> 6671334.6 | F39: =G39*12 -> 0 | G39: 0 | H39: =G39/($I$5*1000) -> 0 | I39: =(G39/$I$6)/$I$5 -> 0
B40: =B39+1 -> 32 | C40: Beban Akomodasi Rapat | D40: 84564877 | E40: =IFERROR(D40/12,0) -> 7047073.1 | F40: =G40*12 -> 88793121 | G40: 7399426.7 | H40: =G40/($I$5*1000) -> 0.41539039 | I40: =(G40/$I$6)/$I$5 -> 0.0259619
B41: =B40+1 -> 33 | C41: Beban Bonus Karyawan | E41: =IFERROR(D41/12,0) -> 0 | F41: =G41*12 -> 0 | G41: 0 | H41: =G41/($I$5*1000) -> 0 | I41: =(G41/$I$6)/$I$5 -> 0
B42: =B41+1 -> 34 | C42: Beban Tantiem | E42: =IFERROR(D42/12,0) -> 0 | F42: =G42*12 -> 0 | G42: 0 | H42: =G42/($I$5*1000) -> 0 | I42: =(G42/$I$6)/$I$5 -> 0
B43: =B42+1 -> 35 | C43: Beban Konsumsi | D43: 3864122096 | E43: =IFERROR(D43/12,0) -> 3.2201017e+08 | F43: =G43*12 -> 2223000000 | G43: 185250000 | H43: =G43/($I$5*1000) -> 10.399599 | I43: =(G43/$I$6)/$I$5 -> 0.64997493
B44: =B43+1 -> 36 | C44: Beban Ekstra Fooding | D44: 810000 | E44: =IFERROR(D44/12,0) -> 67500 | F44: =G44*12 -> 0 | G44: 0 | H44: =G44/($I$5*1000) -> 0 | I44: =(G44/$I$6)/$I$5 -> 0
B45: =B44+1 -> 37 | C45: Beban Pemeriksaan Kesehatan / Perobatan | D45: 185612516 | E45: =IFERROR(D45/12,0) -> 15467710 | F45: =G45*12 -> 41405668 | G45: 3450472.3 | H45: =G45/($I$5*1000) -> 0.19370326 | I45: =(G45/$I$6)/$I$5 -> 0.012106454
B46: =B45+1 -> 38 | C46: Beban Peringatan Hari Besar | D46: 300000 | E46: =IFERROR(D46/12,0) -> 25000 | F46: =G46*12 -> 25000000 | G46: 2083333.3 | H46: =G46/($I$5*1000) -> 0.11695455 | I46: =(G46/$I$6)/$I$5 -> 0.0073096596
B47: =B46+1 -> 39 | C47: Beban Perlengkapan Karyawan | D47: 497881607 | E47: =IFERROR(D47/12,0) -> 41490134 | F47: =G47*12 -> 420000000 | G47: 35000000 | H47: =G47/($I$5*1000) -> 1.9648365 | I47: =(G47/$I$6)/$I$5 -> 0.12280228
B48: =B47+1 -> 40 | C48: Beban Keperluan Dapur / Pantry | D48: 79298165 | E48: =IFERROR(D48/12,0) -> 6608180.4 | F48: =G48*12 -> 12458700 | G48: 1038225 | H48: =G48/($I$5*1000) -> 0.058284068 | I48: =(G48/$I$6)/$I$5 -> 0.0036427542
B49: =B48+1 -> 41 | C49: Beban Employee Gathering | E49: =IFERROR(D49/12,0) -> 0 | F49: =G49*12 -> 250000000 | G49: 20833333 | H49: =G49/($I$5*1000) -> 1.1695455 | I49: =(G49/$I$6)/$I$5 -> 0.073096596
B50: =B49+1 -> 42 | C50: Beban Kebersihan | D50: 11059767 | E50: =IFERROR(D50/12,0) -> 921647.25 | F50: =G50*12 -> 0 | G50: 0 | H50: =G50/($I$5*1000) -> 0 | I50: =(G50/$I$6)/$I$5 -> 0
D51: =SUM(D9:D50) -> 2.3796151e+10 | E51: =SUM(E9:E50) -> 1.9830126e+09 | F51: =SUM(F9:F50) -> 1.7232677e+10 | G51: =SUM(G9:G50) -> 1.4360564e+09 | H51: =SUM(H9:H50) -> 80.6176 | I51: =SUM(I9:I50) -> 5.0386

Sheet Time Sheet Bulanan
A1: Nomor | B1: Tanggal | C1: Keterangan
C2: Refinery | D2: Fraksinasi
A3: 1 | B3: 45536
A4: 2 | B4: 45537
A5: 3 | B5: 45538
A6: 4 | B6: 45539
A7: 5 | B7: 45540
A8: 6 | B8: 45541
A9: 7 | B9: 45542
A10: 8 | B10: 45543
A11: 9 | B11: 45544
A12: 10 | B12: 45545
A13: 11 | B13: 45546
A14: 12 | B14: 45547
... A25: 23 | B25: 45558
A26: 24 | B26: 45559 | C26: Update tgal 24/09/2024 Refinery * 07.00 ref HOLD * 22.00 steam masuk ke plant * 01.20 ref firing hpb * 02.00 sirkulasi * 03.00-07.00 plant HOLD terkait pressure gas HPB drop | D26: Stop sementara & aktifitas cleaning chiller
A27: 25 | B27: 45560 | C27: Refinery * 07.40 start sirkulasi | D27: Fraksinasi * Stop sementara dan pagi ini kunci mainhole chiller pak
A28: 26 | B28: 45561
A29: 27 | B29: 45562
A30: 28 | B30: 45563
A31: 29 | B31: 45564
A32: 30 | B32: 45565

Sheet Flow Meter
A2: TOTAL TONASE FLOWMETER PRODUK
A3: REFINERY
A5: TANGGAL VALIDASI
A6: NO | B6: NAMA PRODUK | C6: 01 Juli | D6: 02 Juli | E6: 03 Juli | F6: 04 Juli | G6: 05 Juli | H6: 06 Juli | I6: 07 Juli | J6: 08 Juli | K6: 09 Juli | L6: 10 Juli | M6: 11 Juli | N6: 12 Juli | O6: 13 Juli | P6: 14 Juli | Q6: 15 Juli | R6: TOTAL | S6: Sounding | T6: Yield Theory | U6: Yield Aktual
A7: 1 | B7: CPO | C7: ='[11]01 '!$Q$14 -> 744924 | D7: ='[11]02'!$Q$14 -> 743972 | E7: ='[11]03'!$Q$14 -> 1048435 | F7: ='[11]04'!$Q$14 -> 1114821 | G7: 248126 | H7: 389481 | I7: 104168 | J7: 320907 | K7: 100743 | L7: 512647 | M7: 441064 | N7: 524002 | O7: 568358 | P7: 430750 | R7: =SUM(C7:Q7) -> 7292398
A8: 2 | B8: RBDPO | C8: 713300 | D8: 708000 | E8: 993100 | F8: 1056000 | G8: 237021 | H8: 365100 | I8: 44001 | J8: 300010 | K8: 94507 | L8: 488153 | M8: 414337 | N8: 492952 | O8: 532902 | P8: 497845 | R8: =SUM(C8:Q8) -> 6937228 | T8: =R8/R7 -> 0.95129586 | U8: =S8/S7 -> #DIV/0! | W8: =4984655+#REF! -> #REF!
A9: 3 | B9: PFAD | C9: ='[11]01 '!$P$25 -> 25659 | D9: 28786 | E9: ='[11]03'!$P$25 -> 46938 | F9: ='[11]04'!$P$24 -> 48667 | G9: 8070 | H9: 19280 | I9: 3234 | J9: 18283 | K9: 5131 | L9: 20426 | M9: 23275 | N9: 27655 | O9: 25803 | P9: 20173 | R9: =SUM(C9:Q9) -> 321380 | T9: =R9/R7 -> 0.044070551 | U9: =S9/S7 -> #DIV/0!
C10: =C8/C7 -> 0.95754735 | D10: =D8/D7 -> 0.95164872 | E10: =E8/E7 -> 0.94722133 | F10: =F8/F7 -> 0.94723727 | G10: =G8/G7 -> 0.95524451 | H10: =H8/H7 -> 0.93740131 | I10: =I8/I7 -> 0.42240419 | J10: =J8/J7 -> 0.93488145 | ... P10: =P8/P7 -> 1.1557632
C11: =C9/C7*1 -> 0.034445125 | D11: =D9/D7*1 -> 0.038692316 | E11: =E9/E7*1 -> 0.044769585 | F11: =F9/F7*1 -> 0.043654542 | G11: =G9/G7*1 -> 0.032523798 | H11: =H9/H7*1 -> 0.049501773 | I11: =I9/I7*1 -> 0.031046003 | J11: =J9/J7*1 -> 0.056972892 | ... P11: =P9/P7*1 -> 0.046832269
B12: LOSIS | C12: =(C7-C8-C9)/C7 -> 0.0080075283 | D12: =(D7-D8-D9)/D7 -> 0.0096589657 | E12: =(E7-E8-E9)/E7 -> 0.0080090802 | F12: =(F7-F8-F9)/F7 -> 0.0091081887 | G12: =(G7-G8-G9)/G7 -> 0.012231689 | H12: =(H7-H8-H9)/H7 -> 0.013096916 | I12: =(I7-I8-I9)/I7 -> 0.5465498 | J12: =(J7-J8-J9)/J7 -> 0.0081456621 | ... P12: =(P7-P8-P9)/P7 -> -0.20259547
A14: TANGGAL flow meter
A15: NO | B15: NAMA PRODUK | C15: 01 Juli | D15: 02 Juli | E15: 03 Juli | F15: 04 Juli | G15: 05 Juli | H15: 06 Juli | I15: 07 Juli | J15: 08 Juli | K15: 09 Juli | L15: 10 Juli | M15: 11 Juli | N15: 12 Juli | O15: 13 Juli | P15: 14 Juli | Q15: 15 Juli | R15: TOTAL | S15: Sounding | T15: Yield Theory | U15: Yield Aktual
A16: 1 | B16: CPO | C16: 680800 | D16: 806400 | E16: 858600 | F16: 898100 | G16: 26100 | H16: 513200 | I16: 119200 | J16: 208900 | K16: 147700 | L16: 425800 | M16: 347900 | N16: 459100 | O16: 509200 | P16: 396700 | Q16: 20200 | R16: =SUM(C16:Q16) -> 6417900 | S16: =5745000+14073+R19 -> 7292813
A17: 2 | B17: RBDPO | C17: 722400 | D17: 826700 | E17: 980700 | F17: 980600 | G17: 19900 | H17: 582000 | I17: 150500 | J17: 215300 | K17: 70837 | L17: 488153 | M17: 379337 | N17: 502200 | O17: 535800 | P17: 412600 | Q17: 92100 | R17: =SUM(C17:Q17) -> 6959127 | S17: =SUM(C17:M17)+R20 -> 6940126 | T17: =R17/R16 -> 1.0843309 | U17: =S17/S16 -> 0.9516391 | W17: =4984655+R20 -> 6508354
A18: 3 | B18: PFAD | C18: 37300 | D18: 38700 | E18: 49500 | F18: 47100 | G18: 3800 | H18: 30300 | I18: 9300 | J18: 14000 | K18: 14800 | L18: 25100 | M18: 23400 | N18: 23900 | O18: 26800 | P18: 22200 | Q18: 5900 | R18: =SUM(C18:Q18) -> 372100 | S18: =248746+R21 -> 322377 | T18: =R18/R16 -> 0.057978466 | U18: =S18/S16 -> 0.044204753
C19: =C17/C16 -> 1.0611046 | D19: =D17/D16 -> 1.0251736 | E19: =E17/E16 -> 1.1422082 | F19: =F17/F16 -> 1.0918606 | G19: =G17/G16 -> 0.76245211 | H19: =H17/H16 -> 1.1340608 | I19: =I17/I16 -> 1.2625839 | J19: =J17/J16 -> 1.0306367 | K19: =K17/K16 -> 0.47960054 | L19: 269515 | M19: CPO | N19: 534002 | O19: 568773 | P19: 430750 | Q19: 269300 | R19: =L19+N19+O19+P19-Q19 -> 1533740 | U19: =100%-U17-U18 -> 0.0041561466 | V19: Losses
M20: RBDPO | N20: 492952 | O20: 532902 | P20: 497845 | R20: =SUM(N20:P20) -> 1523699
N21: 27655 | O21: 25803 | P21: 20173 | R21: =SUM(N21:P21) -> 73631
B22: Nb : | C22: 1. 5.745.000 adalaha angka consume CPO tanggal 1 - 11 ( Opening Stock + Incoming - Closing tanggal 11 )
C23: 2. 14.073 ( Beda Pembacaan antara sounding dan timbangan )
C24: 3. 1.533.740 adalah angka sounding CPO 12, 13, 14
A25: FRAKSINASI
A26: TANGGAL
A27: NO | B27: NAMA PRODUK | C27: 01 Juli | D27: 02 Juli | E27: 03 Juli | F27: 04 Juli | G27: 05 Juli | H27: 06 Juli | I27: 07 Juli | J27: 08 Juli | K27: 09 Juli | L27: 10 Juli | M27: 11 Juli | N27: 12 Juli | O27: 13 Juli | P27: 14 Juli | Q27: 15 Juli | R27: TOTAL | S27: Sounding | T27: Yield
A28: 1 | B28: RBDPO | C28: 667300 | D28: 695000 | E28: 814100 | F28: 760000 | G28: 620300 | H28: 587100 | I28: 118500 | J28: 0 | K28: 253000 | L28: 0 | M28: 466900 | N28: 258400 | O28: 584400 | P28: 680200 | R28: =SUM(C28:Q28) -> 6505200
A29: 2 | B29: OLEIN IV 58 | C29: 518400 | D29: 487200 | E29: 539100 | F29: 571900 | G29: 554300 | H29: 449900 | I29: 209900 | J29: 0 | K29: 297100 | L29: 0 | M29: 472500 | N29: 207400 | O29: 239100 | P29: 414100 | R29: =SUM(C29:Q29) -> 4960900
A30: 3 | B30: STEARIN | C30: 207500 | D30: 202900 | E30: 215500 | F30: =27400+151100+55600 -> 234100 | G30: 213300 | H30: 183700 | I30: 104800 | J30: 0 | K30: 93900 | L30: 0 | M30: 172400 | N30: 111100 | O30: 81200 | P30: 193200 | R30: =SUM(C30:Q30) -> 2013600
O32: STOCK OPNAME | R32: =1311190 -> 1311190
O33: TOTAL TERIMA 1- 11 TIMBANGAN | R33: 3865830
O34: PIPANISASI DAN GK 1 - 11 | R34: 1888995
O35: STOCK AKHIR OPNAME 11 JULI | R35: 1320540.6
R36: =R32+R33+R34-R35 -> 5745474.4
O38: STOCK OPNAME 1 JULI | R38: 178489.22
O39: TOTAL FLOW METER 11 | R39: =SUM(C28:M28) -> 4982200
O40: STOCK AKHIR OPNAME 11 JULI
