Workbook

Sheet JULI 2025
C1: PRODUCTION REPORT PMG2
C2: No | D2: ITEM | E2: Budget / Norma | F2: UoM | G2: JULI 2025 | AM2: TOTAL MONTHLY (Kg)
G3: 1 | H3: 2 | I3: 3 | J3: 4 | K3: 5 | L3: 6 | M3: 7 | N3: 8 | O3: 9 | P3: 10 | Q3: 11 | R3: 12 | S3: 13 | T3: 14 | U3: 15 | V3: 16 | W3: 17 | X3: 18 | Y3: 19 | Z3: 20 | AA3: 21 | AB3: 22 | AC3: 23 | AD3: 24 | AE3: 25 | AF3: 26 | AG3: 27 | AH3: 28 | AI3: 29 | AJ3: 30 | AK3: 31
C4: 1 | D4: PRODUCTION | AM4: Production | AO4: aktual refinery | AR4: opening stok rpo | AS4: =AS6+AS7+AS9 -> 451103 | AU4: =AM7/AM6 -> 1160465.1
D5: Refinery | AM5: Refinery | AO5: cpo feed | AP5: =AM9 -> 34566291 | AR5: sisa rbpo tank
D6: Running Days | F6: Day | M6: 1 | N6: 1 | O6: 1 | P6: 1 | Q6: 1 | R6: 1 | S6: 1 | T6: 1 | U6: 1 | V6: 1 | W6: 1 | X6: 1 | Y6: 1 | Z6: 1 | AA6: 1 | AB6: 1 | AC6: 1 | AD6: 1 | AE6: 1 | AF6: 1 | AG6: 1 | AH6: 1 | AI6: 1 | AJ6: 1 | AK6: 1 | AM6: =SUM(G6:AK6) -> 25 | AO6: rpo prod | AP6: =AM20+AM19+AM18 -> 33163713 | AR6: tk 108 | AS6: 80236
D7: Incoming CPO | F7: Kg | G7: 466886 | H7: 1042428 | I7: 598062 | J7: 1098366 | K7: 1154208 | L7: 0 | M7: 569874 | N7: 827244 | O7: 366660 | P7: 813396 | Q7: 1037784 | R7: 892776 | S7: 0 | T7: 1139271 | U7: 905494 | V7: 1258927 | W7: 1153068 | X7: 841278 | Y7: 1641495 | Z7: 490591 | AA7: 932649 | AB7: 1011790 | AC7: 1168715 | AD7: 1203986 | AE7: 1641206 | AF7: 1531753 | AG7: 214444 | AH7: 1312455 | AI7: 1108453 | AJ7: 875847 | AK7: 1712522 | AM7: =SUM(G7:AK7) -> 29011628 | AO7: pfad prod | AP7: =AM21 -> 1487076 | AR7: tk 109 | AS7: 70298
D8: Ratio Run CPO ( utilisasi kapasitas ) | F8: % | G8: =G9/2500000 -> 0 | H8: =H9/2500000 -> 0 | I8: =I9/2500000 -> 0 | J8: =J9/2500000 -> 0 | K8: =K9/2500000 -> 0 | L8: =L9/2500000 -> 0 | M8: 0 | N8: =N9/2500000 -> 0.6070164 | O8: =O9/2500000 -> 0.5988804 | P8: =P9/2500000 -> 0.740244 | Q8: =Q9/2500000 -> 0.6717804 | R8: =R9/2500000 -> 0.5541288 | S8: =S9/2500000 -> 0.6478244 | T8: =T9/2500000 -> 0.7902612 | U8: =U9/2500000 -> 0.7655548 | ... W8: =W9/2500000 -> 0.5332788 | X8: 0 | Y8: =Y9/2500000 -> 0.7316068 | Z8: =Z9/2500000 -> 0.7564572 | AA8: =AA9/2500000 -> 0.6752512 | AB8: =AB9/2500000 -> 0.740792 | AC8: =AC9/2500000 -> 0.526138 | AD8: =AD9/2500000 -> 0.5256036 | AE8: =AE9/2500000 -> 0.4035696 | AF8: =AF9/2500000 -> 0.7623712 | ... AK8: =AK9/2500000 -> 0.43194 | AM8: =AM9/2500000/AM6 -> 0.55306066 | AO8: yield rpo | AP8: =AP6/AP5*100 -> 95.942354 | AR8: total rpo tank | AS8: =AS6+AS7 -> 150534
D9: CPO Consume Total | E9: 58900000 | F9: Kg | G9: ='[1]01 (stock opname)'!$R$15 -> 0 | H9: ='[1]02'!$R$15 -> 0 | I9: 0 | J9: =[1]MTD!$R$15 -> 0 | K9: ='[1]04'!$R$15 -> 0 | L9: ='[1]05'!$R$15 -> 0 | M9: 297079 | N9: 1517541 | O9: 1497201 | P9: 1850610 | Q9: 1679451 | R9: 1385322 | S9: 1619561 | T9: 1975653 | U9: 1913887 | V9: 1413326 | W9: 1333197 | X9: 893602 | Y9: 1829017 | Z9: 1891143 | AA9: 1688128 | AB9: 1851980 | AC9: 1315345 | AD9: 1314009 | AE9: 1008924 | AF9: 1905928 | AG9: 853654 | AH9: 707016 | AI9: 709605 | AJ9: 1035262 | AK9: 1079850 | AM9: =SUM(G9:AK9) -> 34566291 | AO9: yield pfad | AP9: =AP7/AP5*100 -> 4.3020988 | AR9: oip | AS9: 300569 | AZ9: =AM9/AM6 -> 1382651.6
D10: Avg Daily Consump CPO ( MTD ) | AM10: =AM9/AM6 -> 1382651.6 | AO10: lossis | AP10: =(AP5-AP6-AP7)/AP5*100 -> -0.24445307 | AR10: total keseluruhan rpo | AS10: =AS8+AS9 -> 451103 | AZ10: =AM9/E9 -> 0.58686402
D11: CPO Consume Poram | F11: Kg | G11: =G9-G12 -> 0 | H11: =H9-H12 -> 0 | I11: =I9-I12 -> 0 | J11: =J9-J12 -> 0 | L11: =L9-L12 -> 0 | M11: =M9-M12 -> 297079 | N11: =N9-N12 -> 1517541 | O11: =O9-O12 -> 1497201 | P11: =P9-P12 -> 1850610 | Q11: =Q9-Q12 -> 1679451 | R11: =R9-R12 -> 1385322 | S11: =S9-S12 -> 1619561 | ... AC11: =AC9-AC12 -> 1315345 | AD11: 1314009 | AE11: =AE9-AE12 -> 1008924 | AF11: =AF9-AF12 -> 1905928 | AG11: =AG9-AG12 -> 853654 | AH11: =AH9-AH12 -> 707016 | AI11: =AI9-AI12 -> 709605 | AJ11: =AJ9-AJ12 -> 1035262 | AK11: =AK9-AK12 -> 1079850 | AM11: =SUM(G11:AK11) -> 34566291
D12: CPO Consume Brand | F12: Kg | G12: =G40+G49+G54 -> 0 | H12: =H40+H49+H54 -> 0 | I12: =I40+I49+I54 -> 0 | J12: =J40+J49+J54 -> 0 | K12: 0 | L12: =L40+L49+L54 -> 0 | M12: =M40+M49+M54 -> 0 | N12: =N40+N49+N54 -> 0 | O12: =O40+O49+O54 -> 0 | P12: =P40+P49+P54 -> 0 | R12: =R40+R49+R54 -> 0 | S12: 0 | T12: =T40+T49+T54 -> 0 | U12: =U40+U49+U54 -> 0 | V12: =V40+V49+V54 -> 0 | W12: =W40+W49+W54 -> 0 | X12: 0 | Y12: =Y40+Y49+Y54 -> 0 | Z12: =Z40+Z49+Z54 -> 0 | AA12: =AA40+AA49+AA54 -> 0 | AB12: =AB40+AB49+AB54 -> 0 | AC12: 0 | AD12: 0 | AE12: =AE40+AE49+AE54 -> 0 | AF12: =AF40+AF49+AF54 -> 0 | AG12: =AG40+AG49+AG54 -> 0 | AH12: =AH40+AH49+AH54 -> 0 | AJ12: =AJ40+AJ49+AJ54 -> 0 | AK12: =AK40+AK49+AK54 -> 0 | AM12: =SUM(G12:AK12) -> 0 | AO12: aktual fraksinasi | AR12: before
D13: - FFA | E13: 5 | F13: % | G13: 0 | H13: 0 | I13: 0 | J13: 0 | K13: 0 | L13: 0 | M13: 4.15 | N13: 4.18 | O13: 4.4 | P13: 4.06 | Q13: 3.845 | R13: 3.885 | S13: 3.94 | T13: 4.205 | U13: 4.315 | V13: 4.01 | W13: 3.77 | X13: 3.99 | Y13: 3.94 | Z13: 3.905 | AA13: 4.04 | AB13: =(4.07+3.82+3.75)/3 -> 3.88 | AC13: =(3.8+4.04)/2 -> 3.92 | AD13: 3.97 | AE13: 3.945 | AF13: 3.89 | AG13: 3.93 | AH13: =(3.62+3.93)/2 -> 3.775 | AI13: 3.61 | AJ13: =(3.61+3.62)/2 -> 3.615 | AK13: =(3.65+3.61)/2 -> 3.63 | AM13: =SUM(G13:AK13)/AM6 -> 3.952 | AO13: rpo feed | AP13: =AP14+AP15 -> 12309228 | AR13: tk131 | AS13: ='Oip Fract .'!T13 -> 34831
D14: - Moist & Impurities | E14: 0.5 | F14: % | G14: 0 | H14: 0 | I14: 0 | J14: 0 | K14: 0 | L14: 0 | M14: 0.39 | N14: 0.4 | O14: 0.42 | P14: 0.41 | Q14: 0.46 | R14: 0.46 | S14: 0.48 | T14: 0.45 | U14: 0.43 | V14: 0.435 | W14: 0.435 | X14: 0.45 | Y14: 0.465 | Z14: 0.475 | AA14: 0.46 | AB14: =(0.46+0.42+0.44)/3 -> 0.44 | AC14: =(0.43+0.46)/2 -> 0.445 | AD14: 0.43666667 | AE14: 0.455 | AF14: 0.465 | AG14: 0.43 | AH14: =(0.44+0.43)/2 -> 0.435 | AI14: 0.39 | AJ14: =(0.4+0.46)/2 -> 0.43 | AK14: =(0.43+0.44)/2 -> 0.435 | AM14: =SUM(G14:AK14)/AM6 -> 0.43926667 | AO14: olein 56 | AP14: =AM33 -> 9895094 | AR14: tk132 | AS14: ='Oip Fract .'!U13 -> 272307
D15: - DOBI | E15: 2,20 Min | F15: % | AM15: =SUM(G15:AK15)/AM6 -> 0 | AO15: stearin 56 | AP15: =AM34 -> 2414134 | AR15: after
D16: TANK | M16: 102 | N16: 102 | O16: 102107 | P16: 103107 | Q16: 103107 | R16: 103107 | S16: 103 | T16: 103102 | U16: 102106 | V16: 106107 | W16: 107105 | X16: 105 | Y16: 105107 | Z16: 104107 | AA16: 104 | AB16: 104106107 | AC16: 107103 | AD16: 103106105 | AE16: 105104 | AF16: 104107 | AG16: 105 | AH16: 104105 | AI16: 104 | AJ16: 104107 | AK16: 107105 | AO16: yield olein | AP16: =AP14/(AP14+AP15)*100 -> 80.387608 | AR16: tk131 | AS16: =AS13 -> 34831
D17: Product | AM17: Product | AO17: yield stearin | AP17: =AP15/(AP14+AP15)*100 -> 19.612392 | AR17: tk132 | AS17: =AS14-AP13 -> -12036921
D18: OIP RBDPO | F18: Kg | M18: 300569.36 | N18: 0 | O18: 0 | P18: 0 | Q18: 0 | R18: 0 | S18: 0 | T18: 0 | U18: 0 | V18: 0 | AM18: =SUM(M18:AK18) -> 300569.36
D19: DIRECT RBDPO FRACT | F19: Kg | N19: 53843 | O19: 0 | P19: 0 | Q19: 0 | R19: 0 | S19: 0 | T19: 0 | U19: 0 | AM19: =SUM(N19:AK19) -> 53843 | AO19: sap refinery | AR19: sisa rbdo di gudang bulky 1014 | AU19: sap.rpo.t | AV19: 2145555 | AW19: =AM20-AW20 -> 0
D20: RBDPO | E20: 55661000 | F20: Kg | N20: 1365197 | O20: 1564998 | P20: 1678118 | Q20: 1587178 | R20: 1366312 | S20: 1490762 | T20: 1838515 | U20: 1770735 | V20: 1421546 | W20: 1321961 | X20: 860939 | Y20: 1700000 | Z20: 1854033 | AA20: 1551384 | AB20: 1831540 | AC20: 1459334 | AD20: 1311592 | AE20: 1043325 | AF20: 1690449 | AG20: 841876 | AH20: 675289 | AI20: 654500 | AJ20: 938117 | AK20: 991601 | AM20: =SUM(G20:AK20) -> 32809301 | AO20: cpo feed | AP20: 17813187 | AR20: tk 108 | AS20: 195993 | AT20: =AS20-AS6 -> 115757 | AU20: sap.rpo.non.t | AV20: 30663746 | AW20: =AV19+AV20 -> 32809301 | AY20: =AM20-2145555 -> 30663746
D21: PFAD | E21: 2827000 | F21: Kg | M21: 14278 | N21: 68137 | O21: 74862 | P21: 74613 | Q21: 73664 | R21: 59574 | S21: 62387 | T21: 90023 | U21: 91173 | V21: 66426 | W21: 60361 | X21: 41550 | Y21: 73389 | Z21: 84906 | AA21: 69478 | AB21: 65976 | AC21: 59560 | AD21: 53922 | AE21: 45176 | AF21: 80746 | AG21: 41530 | AH21: 23224 | AI21: 33682 | AJ21: 38824 | AK21: 39615 | AM21: =SUM(G21:AK21) -> 1487076 | AO21: rpo prod | AP21: =17065034 -> 17065034 | AR21: tk 109 | AS21: 390524 | AT21: =AS21-AS7 -> 320226 | AU21: sap.rpo.t
D22: Fractionation | AO22: pfad prod | AP22: 748153 | AR22: total | AS22: =AS20+AS21 -> 586517 | AU22: sap.rpo.non.t
D23: Running Days | F23: Day | M23: 1 | N23: 1 | O23: 1 | P23: 1 | Q23: 1 | R23: 1 | S23: 1 | T23: 1 | U23: 1 | V23: 1 | W23: 1 | X23: 1 | Y23: 1 | Z23: 1 | AA23: 1 | AB23: 1 | AC23: 1 | AD23: 1 | AE23: 1 | AF23: 1 | AG23: 1 | AH23: 1 | AI23: 1 | AJ23: 1 | AK23: 1 | AM23: =SUM(G23:AK23) -> 25 | AR23: OIP actual | AS23: 435983 | AT23: adjust
D24: Avg Daily Consump RBDPO ( MTD ) | F24: Kg | G24: 0 | H24: 0 | I24: 0 | J24: 0 | K24: 0 | M24: 0 | N24: 0 | O24: 0 | P24: 0 | R24: 0 | S24: 0 | T24: 0 | U24: 0 | V24: 0 | W24: 0 | X24: 0 | Y24: 0 | Z24: 0 | AA24: 0 | AB24: 0 | AC24: 0 | AD24: 0 | AE24: 0 | AF24: 0 | AG24: 0 | AH24: 0 | AJ24: 0 | AK24: 0 | AM24: =AM29/AM23 -> 1270534.2 | AO24: yield rpo | AP24: =AP21/AP20*100 -> 95.800005 | AR24: stok actual | AS24: =AS22-AS23 -> 150534
D25: Total RBDPO transfer to plant | F25: Kg | N25: =511511+416468 -> 927979 | O25: 1330366 | P25: 1947000 | Q25: 1579000 | R25: 1391000 | S25: 1488800 | T25: 1812000 | U25: 1512300 | V25: 1574000 | W25: 1396153 | X25: 887000 | Y25: 1845120 | Z25: 1563000 | AA25: 1629100 | AB25: 1807900 | AC25: 1855000 | AD25: 1385000 | AE25: 940400 | AF25: 1771400 | AG25: 856700 | AH25: 702841 | AI25: 644515 | AJ25: 957300 | AK25: 971600 | AM25: =SUM(G25:AK25) -> 32775474 | AO25: yield pfad | AP25: =AP22/AP20*100 -> 4.1999952 | AR25: opening stok rpo sap | AS25: =AS23+AS24 -> 586517
D26: Stok TK 131 | E26: 559 | F26: ton | M26: ='Oip Fract .'!T13 -> 34831 | N26: ='Oip Fract .'!T14 -> 106130 | O26: ='Oip Fract .'!T15 -> 34893 | P26: ='Oip Fract .'!T16 -> 68629 | Q26: 34876 | AO26: loss | AP26: =AP20-AP21-AP22 -> 0
D27: Stok TK 132 | E27: 559 | F27: ton | M27: ='Oip Fract .'!V13 -> 33986 | N27: ='Oip Fract .'!V14 -> 33991 | O27: ='Oip Fract .'!V15 -> 34003 | P27: ='Oip Fract .'!V16 -> 40538 | Q27: 59415
D28: Ratio Run RBDPO | G28: =G29/2500000 -> 0 | H28: =H29/2500000 -> 0 | I28: =I29/2500000 -> 0 | J28: =J29/2500000 -> 0 | K28: =K29/2500000 -> 0 | L28: =L29/2500000 -> 0 | M28: =M29/2500000 -> 0.0830172 | N28: =N29/2500000 -> 0.14748 | ... W28: =W29/2500000 -> 0.6014596 | X28: 0 | Y28: =Y29/2500000 -> 0.5871016 | Z28: =Z29/2500000 -> 0.4891536 | AA28: =AA29/2500000 -> 0.6958416 | AB28: =AB29/2500000 -> 0.7353908 | AC28: 0.52886 | AD28: =AD29/2500000 -> 0.6797268 | AE28: =AE29/2500000 -> 0.422808 | AF28: =AF29/2500000 -> 0.5165264 | AG28: =AG29/2500000 -> 0.4069248 | AH28: =AH29/2500000 -> 0.4996276 | AI28: =AI29/2500000 -> 0.17587 | AJ28: =AJ29/2500000 -> 0.257858 | AK28: =AK29/2500000 -> 0.3378208 | AM28: =AM29/2500000/AM23 -> 0.5082137 | AO28: sap fraksinasi
D29: Total Proses RBDPO | E29: 35501000 | F29: Kg | G29: =SUM(G32,G36,G41,G45,G55) -> 0 | H29: =SUM(H32,H36,H41,H45,H55) -> 0 | I29: =SUM(I32,I36,I41,I45,I55) -> 0 | J29: =SUM(J32,J36,J41,J45,J55) -> 0 | L29: =SUM(L32,L36,L41,L45,L55) -> 0 | M29: =SUM(M32,M36,M41,M45,M55) -> 207543 | N29: =SUM(N32,N36,N41,N45,N55) -> 368700 | O29: =SUM(O32,O36,O41,O45,O55) -> 1392984 | P29: =SUM(P32,P36,P41,P45,P55) -> 1575153 | Q29: =SUM(Q32,Q36,Q41,Q45,Q55) -> 1878169 | R29: =SUM(R32,R36,R41,R45,R55) -> 1342545 | S29: =SUM(S32,S36,S41,S45,S55) -> 1510756 | ... AB29: =SUM(AB32,AB36,AB41,AB45,AB55) -> 1838477 | AC29: =AC46+AC47+AC56+AC57 -> 1823688 | AD29: =SUM(AD32,AD36,AD41,AD45,AD55) -> 1699317 | AE29: =SUM(AE32,AE36,AE41,AE45,AE55) -> 1057020 | AF29: =SUM(AF32,AF36,AF41,AF45,AF55) -> 1291316 | AG29: =SUM(AG32,AG36,AG41,AG45,AG55) -> 1017312 | AH29: =SUM(AH32,AH36,AH41,AH45,AH55) -> 1249069 | AI29: =SUM(AI32,AI36,AI41,AI45,AI55) -> 439675 | AJ29: =SUM(AJ32,AJ36,AJ41,AJ45,AJ55) -> 644645 | AK29: =SUM(AK32,AK36,AK41,AK45,AK55) -> 844552 | AM29: =SUM(G29:AK29) -> 31763356 | AO29: rpo feed | AP29: =AP31+AP32 -> 17792608
D30: Sisa Filling Crystalizer | F30: Kg | G30: =G25-G29 -> 0 | I30: =I25-I29 -> 0 | J30: =SUM(J33,J37,J42,J46,#REF!) -> #REF! | K30: 68473 | L30: =L25-L29 -> 0 | M30: =M25-M29 -> -207543 | N30: =N25-N29 -> 559279 | O30: =O25-O29 -> -62618 | P30: =P25-P29 -> 371847 | Q30: =Q25-Q29 -> -299169 | R30: =R25-R29 -> 48455 | S30: 122463 | T30: =T25-T29 -> 125292 | U30: =U25-U29 -> 216410 | V30: =V25-V29 -> -28726 | W30: =W25-W29 -> -107496 | X30: -255281 | Y30: =Y25-Y29 -> 377366 | Z30: =Z25-Z29 -> 340116 | AA30: =AA25-AA29 -> -110504 | AB30: =AB25-AB29 -> -30577 | AC30: 390824 | AD30: =AD25-AD29 -> -314317 | AE30: =AE25-AE29 -> -116620 | AF30: =AF25-AF29 -> 480084 | AG30: =AG25-AG29 -> -160612 | AH30: =AH25-AH29 -> -546228 | AJ30: =AJ25-AJ29 -> 312655 | AK30: =AK25-AK29 -> 127048 | AM30: =SUM(G30:AJ30) -> #REF!
D31: Fractionation OLEIN IV 56 | AM31: Olein IV 56 | AO31: olein 56 | AP31: 14624233
D32: RBDPO Consume | F32: Kg | G32: =G33+G34 -> 0 | H32: =H33+H34 -> 0 | I32: =I33+I34 -> 0 | J32: =J33+J34 -> 0 | K32: 0 | L32: =L33+L34 -> 0 | M32: =M33+M34 -> 207543 | N32: =N33+N34 -> 368700 | O32: =O33+O34 -> 1392984 | P32: =P33+P34 -> 1575153 | Q32: =Q33+Q34 -> 1878169 | R32: =R33+R34 -> 1342545 | S32: =S33+S34 -> 1510756 | ... AB32: =AB33+AB34 -> 0 | AC32: 0 | AD32: =AD33+AD34 -> 0 | AE32: =AE33+AE34 -> 0 | AF32: =AF33+AF34 -> 1148549 | AG32: =AG33+AG34 -> 0 | AH32: =AH33+AH34 -> 0 | AJ32: =AJ33+AJ34 -> 0 | AK32: =AK33+AK34 -> 0 | AM32: =SUM(G32:AK32) -> 12309228 | AO32: stearin 56 | AP32: 3168375
D33: OLEIN IV 56 | E33: 25000000 | F33: Kg | G33: 0 | H33: 0 | I33: 0 | J33: 0 | K33: 0 | L33: 0 | M33: 173519 | N33: 272300 | O33: 1154926 | P33: 1255804 | Q33: 1491769 | R33: 1088291 | S33: 1240812 | T33: 1368328 | U33: 700175 | V33: 0 | W33: 0 | X33: 291544 | Z33: 0 | AA33: 0 | AB33: 0 | AC33: 0 | AD33: 0 | AE33: 0 | AF33: 857626 | AG33: 0 | AH33: 0 | AI33: 0 | AJ33: 0 | AK33: 0 | AM33: =SUM(G33:AK33) -> 9895094 | AO33: yield olein | AP33: =AP31/(AP31+AP32)*100 -> 82.192745
D34: STEARIN | E34: 639000 | F34: Kg | G34: 0 | H34: 0 | I34: 0 | J34: 0 | K34: 0 | L34: 0 | M34: 34024 | N34: 96400 | O34: 238058 | P34: 319349 | Q34: 386400 | R34: 254254 | S34: 269944 | T34: 318380 | U34: 139018 | V34: 0 | W34: 0 | X34: 67384 | Z34: 0 | AA34: 0 | AB34: 0 | AC34: 0 | AD34: 0 | AE34: 0 | AF34: 290923 | AG34: 0 | AH34: 0 | AI34: 0 | AJ34: 0 | AK34: 0 | AM34: =SUM(G34:AK34) -> 2414134 | AO34: yiel stearin | AP34: =AP32/(AP31+AP32)*100 -> 17.807255 | AU34: =AM34+AM47 -> 8169423
D35: Fractionation OLEIN IV 57 ( Bulk ) | AM35: Olein IV 57 ( Bulk )
D36: RBDPO Consume | F36: Kg | G36: =G37+G38 -> 0 | H36: =H37+H38 -> 0 | I36: =I37+I38 -> 0 | J36: =J37+J38 -> 0 | K36: 0 | L36: =L37+L38 -> 0 | M36: =M37+M38 -> 0 | N36: =N37+N38 -> 0 | O36: =O37+O38 -> 0 | P36: =P37+P38 -> 0 | Q36: =Q37+Q38 -> 0 | R36: =R37+R38 -> 0 | S36: 0 | T36: =T37+T38 -> 0 | U36: =U37+U38 -> 0 | V36: =V37+V38 -> 0 | W36: =W37+W38 -> 0 | X36: 0 | AA36: =AA37+AA38 -> 0 | AB36: =AB37+AB38 -> 0 | AC36: 0 | AD36: =AD37+AD38 -> 0 | AE36: =AE37+AE38 -> 0 | AF36: =AF37+AF38 -> 0 | AG36: =AG37+AG38 -> 0 | AH36: =AH37+AH38 -> 0 | AJ36: =AJ37+AJ38 -> 0 | AK36: =AK37+AK38 -> 0 | AM36: =SUM(G36:AJ36) -> 0
D37: OLEIN IV 57 | F37: Kg | G37: 0 | H37: 0 | I37: 0 | J37: 0 | K37: 0 | L37: 0 | M37: 0 | N37: 0 | O37: 0 | P37: 0 | Q37: 0 | R37: 0 | S37: 0 | T37: 0 | U37: 0 | V37: 0 | W37: 0 | X37: 0 | AA37: 0 | AB37: 0 | AC37: 0 | AD37: 0 | AE37: 0 | AF37: 0 | AG37: 0 | AM37: =SUM(G37:AJ37) -> 0
D38: STEARIN | F38: Kg | G38: 0 | H38: 0 | I38: 0 | J38: 0 | K38: 0 | L38: 0 | M38: 0 | N38: 0 | O38: 0 | P38: 0 | Q38: 0 | R38: 0 | S38: 0 | T38: 0 | U38: 0 | V38: 0 | W38: 0 | X38: 0 | AA38: 0 | AB38: 0 | AC38: 0 | AD38: 0 | AE38: 0 | AF38: 0 | AG38: 0 | AM38: =SUM(G38:AJ38) -> 0
D39: Fractionation OLEIN IV 57 ( Retail ) | AM39: Olein IV 57 ( Retail )
D40: CPO Consume | F40: Kg | AM40: =SUM(G40:AJ40) -> 0
D41: RBDPO Brand Consume | F41: Kg | G41: =G42+G43 -> 0 | H41: =H42+H43 -> 0 | I41: =I42+I43 -> 0 | J41: =J42+J43 -> 0 | K41: 0 | L41: =L42+L43 -> 0 | M41: =M42+M43 -> 0 | N41: =N42+N43 -> 0 | O41: =O42+O43 -> 0 | P41: =P42+P43 -> 0 | Q41: =Q42+Q43 -> 0 | R41: =R42+R43 -> 0 | S41: 0 | T41: =T42+T43 -> 0 | U41: =U42+U43 -> 0 | V41: =V42+V43 -> 0 | W41: =W42+W43 -> 0 | X41: 0 | AA41: =AA42+AA43 -> 0 | AB41: =AB42+AB43 -> 0 | AC41: 0 | AD41: =AD42+AD43 -> 0 | AE41: =AE42+AE43 -> 0 | AF41: =AF42+AF43 -> 0 | AG41: =AG42+AG43 -> 0 | AH41: =AH42+AH43 -> 0 | AJ41: =AJ42+AJ43 -> 0 | AK41: =AK42+AK43 -> 0 | AM41: =SUM(G41:AJ41) -> 0
D42: OLEIN IV 57 Low Color | F42: Kg | G42: 0 | H42: 0 | I42: 0 | J42: 0 | K42: 0 | L42: 0 | M42: 0 | N42: 0 | O42: 0 | P42: 0 | Q42: 0 | R42: 0 | S42: 0 | T42: 0 | U42: 0 | V42: 0 | W42: 0 | X42: 0 | AA42: 0 | AB42: 0 | AC42: 0 | AD42: 0 | AE42: 0 | AF42: 0 | AG42: 0 | AM42: =SUM(G42:AJ42) -> 0
D43: STEARIN | F43: Kg | G43: 0 | H43: 0 | I43: 0 | J43: 0 | K43: 0 | L43: 0 | M43: 0 | N43: 0 | O43: 0 | P43: 0 | Q43: 0 | R43: 0 | S43: 0 | T43: 0 | U43: 0 | V43: 0 | W43: 0 | X43: 0 | AA43: 0 | AB43: 0 | AC43: 0 | AD43: 0 | AE43: 0 | AF43: 0 | AG43: 0 | AM43: =SUM(G43:AJ43) -> 0
D44: Fractionation OLEIN IV 58 ( Bulk ) | AM44: Olein IV 58 ( Bulk )
D45: RBDPO Consume | E45: 17143 | F45: Kg | G45: =G46+G47 -> 0 | H45: =H46+H47 -> 0 | I45: =I46+I47 -> 0 | J45: =J46+J47 -> 0 | L45: =L46+L47 -> 0 | M45: =M46+M47 -> 0 | N45: =N46+N47 -> 0 | O45: =O46+O47 -> 0 | Q45: =Q46+Q47 -> 0 | R45: =R46+R47 -> 0 | T45: =T46+T47 -> 0 | U45: =U46+U47 -> 456697 | V45: =V46+V47 -> 1602726 | W45: =W46+W47 -> 1503649 | X45: =X46+X47 -> 704292 | Y45: =Y46+Y47 -> 1467754 | Z45: =Z46+Z47 -> 1222884 | AA45: =AA46+AA47 -> 1739604 | ... AK45: =AK46+AK47 -> 844552 | AM45: =SUM(G45:AK45) -> 19454128
D46: OLEIN IV 58 | E46: 12000000 | F46: Kg | J46: =K46-L46 -> 0 | K46: =L46-M46 -> 0 | L46: =M46-N46 -> 0 | M46: =N46-O46 -> 0 | N46: =O46-P46 -> 0 | O46: =P46-Q46 -> 0 | Q46: 0 | R46: 0 | U46: 321197 | V46: 1130154 | W46: 1049139 | X46: 472528 | Y46: 820020 | Z46: 1072373 | AA46: 1210695 | AB46: 1358710 | AC46: 1300843 | AD46: 1207275 | AE46: 699420 | AF46: 100542 | AG46: 695438 | AH46: 894643 | AI46: 319620 | AJ46: 455900 | AK46: 590342 | AM46: =SUM(G46:AK46) -> 13698839
D47: STEARIN | E47: 514300 | F47: Kg | J47: =K47-L47 -> 0 | K47: =L47-M47 -> 0 | L47: =M47-N47 -> 0 | M47: =N47-O47 -> 0 | N47: =O47-P47 -> 0 | O47: =P47-Q47 -> 0 | Q47: 0 | R47: 0 | U47: 135500 | V47: 472572 | W47: 454510 | X47: 231764 | Y47: =269344+378390 -> 647734 | Z47: 150511 | AA47: 528909 | AB47: 479767 | AC47: 522845 | AD47: 492042 | AE47: 357600 | AF47: 42225 | AG47: 321874 | AH47: 354426 | AI47: =41405+78650 -> 120055 | AJ47: 188745 | AK47: =166364+87846 -> 254210 | AM47: =SUM(G47:AK47) -> 5755289
D48: Fractionation OLEIN IV 58 ( Retail ) | AM48: Olein IV 58 ( Bulk )
D49: CPO Consume | F49: Kg | AM49: =SUM(G49:AJ49) -> 0
D50: RBDPO Consume | E50: =E51+E52 -> 21429000 | F50: Kg | G50: =G51+G52 -> 0 | H50: =H51+H52 -> 0 | I50: =I51+I52 -> 0 | J50: =J51+J52 -> 0 | K50: 0 | L50: =L51+L52 -> 0 | M50: =M51+M52 -> 0 | N50: =N51+N52 -> 0 | O50: =O51+O52 -> 0 | P50: =P51+P52 -> 0 | Q50: =Q51+Q52 -> 0 | R50: =R51+R52 -> 0 | S50: 0 | T50: =T51+T52 -> 0 | U50: =U51+U52 -> 0 | V50: =V51+V52 -> 0 | W50: =W51+W52 -> 0 | X50: 0 | Y50: =Y51+Y52 -> 0 | Z50: =Z51+Z52 -> 0 | AA50: =AA51+AA52 -> 0 | AB50: =AB51+AB52 -> 0 | AC50: 0 | AD50: =AD51+AD52 -> 0 | AE50: =AE51+AE52 -> 0 | AF50: =AF51+AF52 -> 0 | AG50: =AG51+AG52 -> 0 | AH50: =AH51+AH52 -> 0 | AJ50: =AJ51+AJ52 -> 0 | AK50: =AK51+AK52 -> 0 | AM50: =SUM(G50:AJ50) -> 0
D51: OLEIN IV 58 | E51: 15000000 | F51: Kg | G51: 0 | H51: 0 | I51: 0 | J51: 0 | K51: 0 | L51: 0 | M51: 0 | N51: 0 | O51: 0 | P51: 0 | Q51: 0 | R51: 0 | S51: 0 | T51: 0 | U51: 0 | V51: 0 | W51: 0 | X51: 0 | Y51: 0 | Z51: 0 | AA51: 0 | AB51: 0 | AC51: 0 | AD51: 0 | AE51: 0 | AF51: 0 | AG51: 0 | AH51: 0 | AM51: =SUM(G51:AJ51) -> 0
D52: STEARIN | E52: 6429000 | F52: Kg | G52: 0 | H52: 0 | I52: 0 | J52: 0 | K52: 0 | L52: 0 | M52: 0 | N52: 0 | O52: 0 | P52: 0 | Q52: 0 | R52: 0 | S52: 0 | T52: 0 | U52: 0 | V52: 0 | W52: 0 | X52: 0 | Y52: 0 | Z52: 0 | AA52: 0 | AB52: 0 | AC52: 0 | AD52: 0 | AE52: 0 | AF52: 0 | AG52: 0 | AH52: 0 | AM52: =SUM(G52:AJ52) -> 0
D53: Fractionation OLEIN IV 60 | AM53: Olein IV 60
D54: CPO Consume | F54: Kg | AM54: =SUM(G54:AJ54) -> 0
D55: RBDPO Brand Consume | E55: =E56+E57 -> 1333300 | F55: Kg | G55: =G56+G57 -> 0 | H55: =H56+H57 -> 0 | I55: =I56+I57 -> 0 | J55: =J56+J57 -> 0 | K55: 0 | L55: 0 | M55: =M56+M57 -> 0 | N55: =N56+N57 -> 0 | O55: =O56+O57 -> 0 | P55: =P56+P57 -> 0 | Q55: =Q56+Q57 -> 0 | S55: =S56+S57 -> 0 | T55: =T56+T57 -> 0 | U55: =U56+U57 -> 0 | V55: =V56+V57 -> 0 | W55: =W56+W57 -> 0 | X55: 0 | Y55: =Y56+Y57 -> 0 | Z55: =Z56+Z57 -> 0 | AA55: =AA56+AA57 -> 0 | AB55: =AB56+AB57 -> 0 | AC55: =AC56+AC57 -> 0 | AD55: =AD56+AD57 -> 0 | AE55: =AE56+AE57 -> 0 | AF55: =AF56+AF57 -> 0 | ... AH55: =AH56+AH57 -> 0 | AJ55: =AJ56+AJ57 -> 0 | AK55: =AK56+AK57 -> 0 | AM55: =SUM(G55:AJ55) -> 0
D56: OLEIN IV 60 Salvaco | E56: 1250000 | F56: Kg | G56: 0 | H56: 0 | I56: 0 | J56: 0 | K56: 0 | L56: 0 | M56: 0 | N56: 0 | O56: 0 | P56: 0 | Q56: 0 | R56: 0 | T56: 0 | U56: 0 | V56: 0 | W56: 0 | X56: 0 | Y56: 0 | Z56: 0 | AA56: 0 | AB56: 0 | AD56: 0 | AE56: 0 | AF56: 0 | AH56: 0 | AM56: =SUM(G56:AJ56) -> 0
D57: SOFT STEARIN | E57: 83300 | F57: Kg | G57: 0 | H57: 0 | I57: 0 | J57: 0 | K57: 0 | L57: 0 | M57: 0 | N57: 0 | O57: 0 | P57: 0 | Q57: 0 | R57: 0 | T57: 0 | U57: 0 | V57: 0 | W57: 0 | X57: 0 | Y57: 0 | Z57: 0 | AA57: 0 | AB57: 0 | AD57: 0 | AE57: 0 | AF57: 0 | AH57: 0 | AM57: =SUM(G57:AJ57) -> 0
D58: Ratio Run RBDPO | F58: % | G58: 0 | H58: 0 | I58: 0 | J58: 0 | K58: 0 | L58: 0 | M58: 0 | N58: 0 | O58: 0 | P58: 0 | Q58: 0 | R58: 0 | S58: 0 | T58: 0 | U58: 0 | V58: 0 | W58: 0 | X58: 0 | Y58: 0 | Z58: 0 | AA58: 0 | AB58: 0 | AC58: 0 | AD58: 0 | AE58: 0 | AF58: 0 | AG58: 0 | AH58: 0 | AJ58: 0 | AK58: 0 | AM58: =SUM(G58:AJ58) -> 0
D59: YIELD | AM59: Yield
D60: RBDPO | E60: 94.2 | F60: % | G60: =(G20/(G9))*100 -> #DIV/0! | H60: =(H20/(H9))*100 -> #DIV/0! | I60: =(I20/(I9))*100 -> #DIV/0! | J60: =(J20/(J9))*100 -> #DIV/0! | K60: =(K20/(K9))*100 -> #DIV/0! | L60: =(L20/(L9))*100 -> #DIV/0! | M60: =(M20/(M9))*100 -> 0 | N60: =((N20+N19+N18)/(N9))*100 -> 93.50917 | O60: =((O20+O19+O18)/(O9))*100 -> 104.52825 | P60: =((P20+P19+P18)/(P9))*100 -> 90.679181 | Q60: =((Q20+Q19+Q18)/(Q9))*100 -> 94.505764 | R60: =((R20+R19+R18)/(R9))*100 -> 98.627756 | S60: =((S20+S19+S18)/(S9))*100 -> 92.047289 | T60: =((T20+T19+T18)/(T9))*100 -> 93.058599 | U60: =((U20+U19+U18)/(U9))*100 -> 92.520353 | ... AK60: =((AK20+AK19+AK18)/(AK9))*100 -> 91.827661 | AM60: =((AM20)/(AM9))*100 -> 94.917042
D61: PFAD | E61: 5 | F61: % | G61: =(G21/(G9))*100 -> #DIV/0! | H61: =(H21/(H9))*100 -> #DIV/0! | I61: =(I21/(I9))*100 -> #DIV/0! | J61: =(J21/(J9))*100 -> #DIV/0! | K61: =(K21/(K9))*100 -> #DIV/0! | L61: =(L21/(L9))*100 -> #DIV/0! | M61: =(M21/(M9))*100 -> 4.806129 | N61: =(N21/(N9))*100 -> 4.4899611 | ... AK61: =(AK21/(AK9))*100 -> 3.6685651 | AM61: =(AM21/(AM9))*100 -> 4.3020988
D62: Olein IV 56 | E62: 82 | F62: % | G62: =G33/(G33+G34)*100 -> #DIV/0! | H62: =H33/(H33+H34)*100 -> #DIV/0! | I62: =I33/(I33+I34)*100 -> #DIV/0! | J62: =J33/(J33+J34)*100 -> #DIV/0! | K62: #DIV/0! | L62: =L33/(L33+L34)*100 -> #DIV/0! | M62: =M33/(M33+M34)*100 -> 83.606289 | N62: =N33/(N33+N34)*100 -> 73.854082 | O62: =O33/(O33+O34)*100 -> 82.910213 | P62: =P33/(P33+P34)*100 -> 79.725843 | Q62: =Q33/(Q33+Q34)*100 -> 79.426771 | R62: =R33/(R33+R34)*100 -> 81.061789 | S62: =S33/(S33+S34)*100 -> 82.13186 | ... AK62: =AK33/(AK33+AK34)*100 -> #DIV/0! | AM62: =AM33/(AM33+AM34)*100 -> 80.387608
D63: Stearin | E63: 18 | F63: % | G63: =(G34/G32)*100 -> #DIV/0! | H63: =(H34/H32)*100 -> #DIV/0! | I63: =(I34/I32)*100 -> #DIV/0! | J63: =(J34/J32)*100 -> #DIV/0! | K63: #DIV/0! | L63: =(L34/L32)*100 -> #DIV/0! | M63: =(M34/M32)*100 -> 16.393711 | N63: =(N34/N32)*100 -> 26.145918 | O63: =(O34/O32)*100 -> 17.089787 | P63: =(P34/P32)*100 -> 20.274157 | Q63: =(Q34/Q32)*100 -> 20.573229 | R63: =(R34/R32)*100 -> 18.938211 | S63: =(S34/S32)*100 -> 17.86814 | ... AK63: =(AK34/AK32)*100 -> #DIV/0! | AM63: =AM34/(AM33+AM34)*100 -> 19.612392
D64: Olein IV 57 ( Bulk ) | E64: 75 | G64: =(G37/G36)*100 -> #DIV/0! | H64: =(H37/H36)*100 -> #DIV/0! | I64: =(I37/I36)*100 -> #DIV/0! | J64: =(J37/J36)*100 -> #DIV/0! | K64: #DIV/0! | L64: =(L37/L36)*100 -> #DIV/0! | M64: =(M37/M36)*100 -> #DIV/0! | N64: =(N37/N36)*100 -> #DIV/0! | O64: =(O37/O36)*100 -> #DIV/0! | P64: =(P37/P36)*100 -> #DIV/0! | Q64: =(Q37/Q36)*100 -> #DIV/0! | R64: =(R37/R36)*100 -> #DIV/0! | S64: =(S37/S36)*100 -> #DIV/0! | ... AK64: =(AK37/AK36)*100 -> #DIV/0! | AM64: =(AM42/AM41)*100 -> #DIV/0!
D65: Stearin | E65: 25 | G65: =(G38/G36)*100 -> #DIV/0! | H65: =(H38/H36)*100 -> #DIV/0! | I65: =(I38/I36)*100 -> #DIV/0! | J65: =(J38/J36)*100 -> #DIV/0! | K65: #DIV/0! | L65: =(L38/L36)*100 -> #DIV/0! | M65: =(M38/M36)*100 -> #DIV/0! | N65: =(N38/N36)*100 -> #DIV/0! | O65: =(O38/O36)*100 -> #DIV/0! | P65: =(P38/P36)*100 -> #DIV/0! | Q65: =(Q38/Q36)*100 -> #DIV/0! | R65: =(R38/R36)*100 -> #DIV/0! | S65: =(S38/S36)*100 -> #DIV/0! | ... AK65: =(AK38/AK36)*100 -> #DIV/0! | AM65: =(AM43/AM41)*100 -> #DIV/0!
D66: Olein IV 57 ( Retail ) | E66: 75 | F66: % | G66: =G42/G41*100 -> #DIV/0! | H66: =H42/H41*100 -> #DIV/0! | I66: =I42/I41*100 -> #DIV/0! | J66: =J42/J41*100 -> #DIV/0! | K66: #DIV/0! | L66: =L42/L41*100 -> #DIV/0! | M66: =M42/M41*100 -> #DIV/0! | N66: =N42/N41*100 -> #DIV/0! | O66: =O42/O41*100 -> #DIV/0! | P66: =P42/P41*100 -> #DIV/0! | Q66: =Q42/Q41*100 -> #DIV/0! | R66: =R42/R41*100 -> #DIV/0! | S66: =S42/S41*100 -> #DIV/0! | ... AK66: =AK42/AK41*100 -> #DIV/0! | AM66: =AM42/AM41*100 -> #DIV/0!
D67: Stearin | E67: 25 | F67: % | G67: =G43/G41*100 -> #DIV/0! | H67: =H43/H41*100 -> #DIV/0! | I67: =I43/I41*100 -> #DIV/0! | J67: =J43/J41*100 -> #DIV/0! | K67: #DIV/0! | L67: =L43/L41*100 -> #DIV/0! | M67: =M43/M41*100 -> #DIV/0! | N67: =N43/N41*100 -> #DIV/0! | O67: =O43/O41*100 -> #DIV/0! | P67: =P43/P41*100 -> #DIV/0! | Q67: =Q43/Q41*100 -> #DIV/0! | R67: =R43/R41*100 -> #DIV/0! | S67: =S43/S41*100 -> #DIV/0! | ... AK67: =AK43/AK41*100 -> #DIV/0! | AM67: =AM43/AM41*100 -> #DIV/0!
D68: Olein IV 58 ( Bulk ) | E68: 70 | F68: % | G68: =G46/(G46+G47)*100 -> #DIV/0! | H68: =H46/(H46+H47)*100 -> #DIV/0! | I68: =I46/(I46+I47)*100 -> #DIV/0! | J68: =J46/(J46+J47)*100 -> #DIV/0! | K68: =K46/(K46+K47)*100 -> #DIV/0! | L68: =L46/(L46+L47)*100 -> #DIV/0! | M68: =M46/(M46+M47)*100 -> #DIV/0! | N68: =N46/(N46+N47)*100 -> #DIV/0! | ... AK68: =AK46/(AK46+AK47)*100 -> 69.900018 | AM68: =AM46/(AM46+AM47)*100 -> 70.416104
D69: Stearin | E69: 30 | F69: % | G69: =G47/(G47+G46)*100 -> #DIV/0! | H69: =H47/(H47+H46)*100 -> #DIV/0! | I69: =I47/(I47+I46)*100 -> #DIV/0! | J69: =J47/(J47+J46)*100 -> #DIV/0! | K69: =K47/(K47+K46)*100 -> #DIV/0! | L69: =L47/(L47+L46)*100 -> #DIV/0! | M69: =M47/(M47+M46)*100 -> #DIV/0! | N69: =N47/(N47+N46)*100 -> #DIV/0! | ... AK69: =AK47/(AK47+AK46)*100 -> 30.099982 | AM69: =AM47/AM45*100 -> 29.583896
D70: Olein IV 58 ( Retail ) | E70: 70 | F70: % | G70: =G51/(G51+G52)*100 -> #DIV/0! | H70: =H51/(H51+H52)*100 -> #DIV/0! | I70: =I51/(I51+I52)*100 -> #DIV/0! | J70: =J51/(J51+J52)*100 -> #DIV/0! | K70: #DIV/0! | L70: =L51/(L51+L52)*100 -> #DIV/0! | M70: =M51/(M51+M52)*100 -> #DIV/0! | N70: =N51/(N51+N52)*100 -> #DIV/0! | O70: =O51/(O51+O52)*100 -> #DIV/0! | P70: =P51/(P51+P52)*100 -> #DIV/0! | Q70: =Q51/(Q51+Q52)*100 -> #DIV/0! | R70: =R51/(R51+R52)*100 -> #DIV/0! | S70: =S51/(S51+S52)*100 -> #DIV/0! | ... AK70: =AK51/(AK51+AK52)*100 -> #DIV/0! | AM70: =AM51/(AM51+AM52)*100 -> #DIV/0!
D71: Stearin | E71: 30 | F71: % | G71: =G52/(G51+G52)*100 -> #DIV/0! | H71: =H52/(H51+H52)*100 -> #DIV/0! | I71: =I52/(I51+I52)*100 -> #DIV/0! | J71: =J52/(J51+J52)*100 -> #DIV/0! | K71: #DIV/0! | L71: =L52/(L51+L52)*100 -> #DIV/0! | M71: =M52/(M51+M52)*100 -> #DIV/0! | N71: =N52/(N51+N52)*100 -> #DIV/0! | O71: =O52/(O51+O52)*100 -> #DIV/0! | P71: =P52/(P51+P52)*100 -> #DIV/0! | Q71: =Q52/(Q51+Q52)*100 -> #DIV/0! | R71: =R52/(R51+R52)*100 -> #DIV/0! | S71: =S52/(S51+S52)*100 -> #DIV/0! | ... AK71: =AK52/(AK51+AK52)*100 -> #DIV/0! | AM71: =AM52/(AM51+AM52)*100 -> #DIV/0!
D72: Olein IV 60 | E72: 60 | F72: % | G72: =G56/(G56+G57)*100 -> #DIV/0! | H72: =H56/(H56+H57)*100 -> #DIV/0! | I72: =I56/(I56+I57)*100 -> #DIV/0! | J72: =J56/(J56+J57)*100 -> #DIV/0! | K72: =K56/(K56+K57)*100 -> #DIV/0! | L72: =L56/(L56+L57)*100 -> #DIV/0! | M72: =M56/(M56+M57)*100 -> #DIV/0! | N72: =N56/(N56+N57)*100 -> #DIV/0! | ... AK72: =AK56/(AK56+AK57)*100 -> #DIV/0! | AM72: =AM56/(AM55+AM51)*100 -> #DIV/0!
D73: Soft Stearin | E73: 40 | F73: % | G73: =G57/G55*100 -> #DIV/0! | H73: =H57/H55*100 -> #DIV/0! | I73: =I57/I55*100 -> #DIV/0! | J73: =J57/J55*100 -> #DIV/0! | K73: #DIV/0! | L73: =L57/L55*100 -> #DIV/0! | M73: =M57/M55*100 -> #DIV/0! | N73: =N57/N55*100 -> #DIV/0! | O73: =O57/O55*100 -> #DIV/0! | P73: =P57/P55*100 -> #DIV/0! | Q73: =Q57/Q55*100 -> #DIV/0! | R73: =R57/R55*100 -> #DIV/0! | S73: =S57/S55*100 -> #DIV/0! | ... AK73: =AK57/AK55*100 -> #DIV/0! | AM73: =AM57/AM55*100 -> #DIV/0!
C74: 2 | D74: CHEMICAL CONSUMABLE | AM74: Chemical | AW74: =AW68-AW69-AW70-AW71-AW72-AW73 -> 0
D75: Bleaching Earth (BE) to Poram Spec | E75: 9 | F75: Kg | G75: 0 | H75: 0 | I75: 0 | J75: 0 | K75: 0 | L75: 0 | M75: 3421 | N75: 12321 | O75: 13316 | P75: 18514.2 | Q75: 21847.1 | R75: 18084.9 | S75: 17935 | T75: 17455 | U75: 13350 | V75: 9630 | W75: 12565 | X75: 5600 | Y75: 11450 | Z75: 11460 | AA75: 10435 | AB75: 10860 | AC75: 9175 | AD75: 8120 | AE75: 6220 | AF75: 11550 | AG75: 5450 | AH75: 4680 | AI75: 4140 | AJ75: 6470 | AK75: 7345 | AM75: =SUM(G75:AK75) -> 271394.2 | AU75: =123328+148066 -> 271394
F76: % | G76: =G75/(G11)*100 -> #DIV/0! | H76: =H75/(H11)*100 -> #DIV/0! | I76: =I75/(I11)*100 -> #DIV/0! | J76: =J75/(J11)*100 -> #DIV/0! | K76: =K75/(K11)*100 -> #DIV/0! | L76: =L75/(L11)*100 -> #DIV/0! | M76: =M75/(M11)*100 -> 1.1515455 | N76: =N75/(N11)*1000 -> 8.1190558 | O76: =O75/(O11)*1000 -> 8.8939294 | P76: =P75/(P11)*1000 -> 10.004377 | Q76: =Q75/(Q11)*1000 -> 13.008477 | R76: =R75/(R11)*1000 -> 13.054654 | S76: =S75/(S11)*1000 -> 11.073989 | T76: =T75/(T11)*1000 -> 8.8350535 | U76: =U75/(U11)*1000 -> 6.9753334 | V76: =V75/(V11)*1000 -> 6.8137146 | W76: =W75/(W11)*100 -> 0.94247137 | X76: =X75/(X11)*100 -> 0.6266772 | Y76: =Y75/(Y11)*100 -> 0.62601933 | Z76: =Z75/(Z11)*100 -> 0.60598273 | AA76: =AA75/(AA11)*100 -> 0.61814033 | AB76: =AB75/(AB11)*100 -> 0.58639942 | AC76: =AC75/(AC11)*100 -> 0.69753563 | AD76: =AD75/(AD11)*100 -> 0.61795619 | ... AK76: =AK75/(AK11)*100 -> 0.68018706 | AM76: =AM75/(AM11)*1000 -> 7.8514122
D77: TK 630 A ( TRANSFER ) | E77: 40000 | F77: Kg | V77: 0 | W77: 0 | X77: 0 | Y77: 0 | AA77: 0 | AB77: 0 | AC77: 0 | AD77: 0 | AE77: 0 | AF77: 0 | AG77: 0 | AM77: =SUM(G77:AJ77) -> 0
D79: TK 630 B ( TRANSFER ) | E79: 40000 | F79: Kg | V79: 0 | W79: 0 | X79: 0 | Y79: 0 | Z79: 0 | AA79: 0 | AB79: 0 | AC79: 0 | AD79: 0 | AE79: 0 | AF79: 0 | AG79: 0 | AM79: =SUM(G79:AJ79) -> 0
D81: Bleaching Earth (BE) to Branded Spec | E81: 18 | F81: Kg | G81: 0 | H81: 0 | I81: 0 | J81: 0 | K81: 0 | L81: 0 | M81: 0 | N81: 0 | O81: 0 | P81: 0 | Q81: 0 | R81: 0 | S81: 0 | T81: 0 | U81: 0 | V81: 0 | W81: 0 | X81: 0 | Y81: 0 | Z81: 0 | AA81: 0 | AB81: 0 | AC81: 0 | AD81: 0 | AE81: 0 | AF81: 0 | AG81: 0 | AH81: 0 | AJ81: 0 | AK81: 0 | AM81: =SUM(G81:AJ81) -> 0
F82: % | G82: =G81/(G12)*100 -> #DIV/0! | H82: =H81/(H12)*100 -> #DIV/0! | I82: =I81/(I12)*100 -> #DIV/0! | J82: =J81/(J12)*100 -> #DIV/0! | K82: #DIV/0! | L82: =L81/(L12)*100 -> #DIV/0! | M82: =M81/(M12)*100 -> #DIV/0! | N82: =N81/(N12)*100 -> #DIV/0! | O82: =O81/(O12)*100 -> #DIV/0! | P82: =P81/(P12)*100 -> #DIV/0! | Q82: =Q81/(Q12)*100 -> #DIV/0! | R82: =R81/(R12)*100 -> #DIV/0! | S82: #DIV/0! | T82: =T81/(T12)*100 -> #DIV/0! | U82: =U81/(U12)*100 -> #DIV/0! | V82: =V81/(V12)*100 -> #DIV/0! | W82: =W81/(W12)*100 -> #DIV/0! | X82: #DIV/0! | Y82: =Y81/(Y12)*100 -> #DIV/0! | Z82: =Z81/(Z12)*100 -> #DIV/0! | AA82: =AA81/(AA12)*100 -> #DIV/0! | AB82: =AB81/(AB12)*100 -> #DIV/0! | AC82: #DIV/0! | AD82: =AD81/(AD12)*100 -> #DIV/0! | AE82: =AE81/(AE12)*100 -> #DIV/0! | AF82: =AF81/(AF12)*100 -> #DIV/0! | AG82: =AG81/(AG12)*100 -> #DIV/0! | AH82: =AH81/(AH12)*100 -> #DIV/0! | AI82: =AI81/(AI12)*100 -> #DIV/0! | AJ82: =AJ81/(AJ12)*100 -> #DIV/0! | AK82: =AK81/(AK12)*100 -> #DIV/0! | AM82: =AM81/(AM12)*100 -> #DIV/0!
D83: Phosporic Acid (PA) | E83: 0.6 | F83: Kg | G83: 0 | H83: 0 | I83: 0 | J83: 0 | K83: 0 | L83: 0 | M83: 155.6 | N83: 700.96 | O83: 803.27 | P83: 874.69 | Q83: 813.28 | R83: 681.2 | S83: 775.47 | T83: 844.48 | U83: 840.32 | V83: 647.92 | W83: 670.8 | X83: 413.92 | Y83: 856.96 | Z83: 928.42 | AA83: 799.07 | AB83: 861.81 | AC83: 634 | AD83: 634.4 | AE83: 497.12 | AF83: 957.77 | AG83: 433.68 | AH83: 374.4 | AI83: 286 | AJ83: 520 | AK83: 501.19 | AM83: =SUM(G83:AK83) -> 16506.73
F84: % | G84: =G83/(G9)*100 -> #DIV/0! | H84: =H83/(H9)*100 -> #DIV/0! | I84: =I83/(I9)*100 -> #DIV/0! | J84: =J83/(J9)*1000 -> #DIV/0! | K84: =K83/(K9)*1000 -> #DIV/0! | L84: =L83/(L9)*100 -> #DIV/0! | M84: =M83/(M9)*100 -> 0.052376641 | N84: =N83/(N9)*100 -> 0.046190515 | O84: =O83/(O9)*100 -> 0.053651447 | P84: =P83/(P9)*100 -> 0.047264956 | Q84: =Q83/(Q9)*1000 -> 0.48425349 | R84: =R83/(R9)*1000 -> 0.49172683 | S84: =S83/(S9)*1000 -> 0.47881494 | T84: =T83/(T9)*1000 -> 0.42744348 | U84: =U83/(U9)*1000 -> 0.43906458 | V84: =V83/(V9)*1000 -> 0.45843634 | W84: =W83/(W9)*1000 -> 0.50315145 | X84: =X83/(X9)*1000 -> 0.46320398 | ... AF84: =AF83/(AF9)*1000 -> 0.50252161 | AG84: =AG83/(AG9)*100 -> 0.050802784 | AH84: =AH83/(AH9)*100 -> 0.052954954 | AI84: =AI83/(AI9)*100 -> 0.040304113 | AJ84: =AJ83/(AJ9)*100 -> 0.050228831 | AK84: =AK83/(AK9)*100 -> 0.046412928 | AM84: =AM83/AM9*1000 -> 0.47753836
C85: 3 | D85: OIL LOSSES | E85: 0.7 | F85: % | G85: =((SUM(G20:G21))-(SUM(G9)))/(SUM(G9))*100 -> #DIV/0! | H85: =((SUM(H20:H21))-(SUM(H9)))/(SUM(H9))*100 -> #DIV/0! | I85: =((SUM(I20:I21))-(SUM(I9)))/(SUM(I9))*100 -> #DIV/0! | J85: =((SUM(J20:J21))-(SUM(J9)))/(SUM(J9))*100 -> #DIV/0! | K85: =((SUM(K20:K21))-(SUM(K9)))/(SUM(K9))*100 -> #DIV/0! | L85: =((SUM(L20:L21))-(SUM(L9)))/(SUM(L9))*100 -> #DIV/0! | M85: =((SUM(M18:M21))-(SUM(M9)))/(SUM(M9))*100 -> 5.9810219 | N85: =((SUM(N18:N21))-(SUM(N9)))/(SUM(N9))*100 -> -2.0008685 | O85: =((SUM(O19:O21))-(SUM(O9)))/(SUM(O9))*100 -> 9.52838 | P85: =((SUM(P18:P21))-(SUM(P9)))/(SUM(P9))*100 -> -5.2890128 | Q85: =((SUM(Q18:Q21))-(SUM(Q9)))/(SUM(Q9))*100 -> -1.1080407 | R85: =((SUM(R18:R21))-(SUM(R9)))/(SUM(R9))*100 -> 2.9281279 | S85: =((SUM(S18:S21))-(SUM(S9)))/(SUM(S9))*100 -> -4.1006174 | T85: =((SUM(T18:T21))-(SUM(T9)))/(SUM(T9))*100 -> -2.3847811 | U85: =((SUM(U18:U21))-(SUM(U9)))/(SUM(U9))*100 -> -2.7158866 | V85: =((SUM(V18:V21))-(SUM(V9)))/(SUM(V9))*100 -> 5.281584 | W85: =((SUM(W18:W21))-(SUM(W9)))/(SUM(W9))*100 -> 3.6847518 | X85: =((SUM(X20:X21))-(SUM(X9)))/(SUM(X9))*100 -> 0.99451434 | Y85: =((SUM(Y20:Y21))-(SUM(Y9)))/(SUM(Y9))*100 -> -3.0414151 | Z85: =((SUM(Z20:Z21))-(SUM(Z9)))/(SUM(Z9))*100 -> 2.5273604 | AA85: =((SUM(AA20:AA21))-(SUM(AA9)))/(SUM(AA9))*100 -> -3.9846505 | AB85: =((SUM(AB20:AB21))-(SUM(AB9)))/(SUM(AB9))*100 -> 2.4587739 | AC85: =((SUM(AC20:AC21))-(SUM(AC9)))/(SUM(AC9))*100 -> 15.474951 | AD85: =((SUM(AD20:AD21))-(SUM(AD9)))/(SUM(AD9))*100 -> 3.919684 | AE85: =((SUM(AE20:AE21))-(SUM(AE9)))/(SUM(AE9))*100 -> 7.8873136 | ... AK85: =((SUM(AK20:AK21))-(SUM(AK9)))/(SUM(AK9))*100 -> -4.5037737 | AM85: =((SUM(AM20:AM21))-(SUM(AM9)))/(SUM(AM9))*100 -> -0.78085902
F86: Kg | G86: =G85%*G9 -> #DIV/0! | H86: =H85%*H9 -> #DIV/0! | I86: =I85%*I9 -> #DIV/0! | J86: =J85%*J9 -> #DIV/0! | K86: =K85%*K9 -> #DIV/0! | L86: =L85%*L9 -> #DIV/0! | M86: =M85%*M9 -> 17768.36 | N86: =N85%*N9 -> -30364 | ... AK86: =AK85%*AK9 -> -48634 | AM86: =AM85%*AM9 -> -269914
D87: % Oil Content | E87: 22 | F87: % | J87: 0 | K87: 0 | L87: 0 | M87: 0 | N87: 22.61 | O87: 22.44 | P87: 22.66 | Q87: 21.99 | R87: 21.98 | S87: 21.98 | T87: 21.96 | U87: 22.03 | V87: 22.05 | W87: 22.16 | X87: 22.08 | Y87: 20.95 | Z87: 20.62 | AA87: 20.94 | AB87: 21.19 | AC87: 21.16 | AD87: 21.2 | AE87: 21.32 | AF87: 21.62 | AG87: 21.83 | AH87: 21.18 | AI87: 21.06 | AJ87: 21.16 | AK87: 21.21 | AM87: =AVERAGE(N87:AK87) -> 21.640833
D88: Spent Bleaching Earth | F88: Kg | N88: =SUM(N75,N81)+(N87%*SUM(N75,N81))/N6 -> 15106.778 | O88: =SUM(O75,O81)+(O87%*SUM(O75,O81))/O6 -> 16304.11 | P88: =SUM(P75,P81)+(P87%*SUM(P75,P81))/P6 -> 22709.518 | Q88: =SUM(Q75,Q81)+(Q87%*SUM(Q75,Q81)) -> 26651.277 | R88: =SUM(R75,R81)+(R87%*SUM(R75,R81)) -> 22059.961 | S88: =SUM(S75,S81)+(S87%*SUM(S75,S81)) -> 21877.113 | T88: =SUM(T75,T81)+(T87%*SUM(T75,T81)) -> 21288.118 | U88: =SUM(U75,U81)+(U87%*SUM(U75,U81)) -> 16291.005 | V88: =SUM(V75,V81)+(V87%*SUM(V75,V81)) -> 11753.415 | W88: =SUM(W75,W81)+(W87%*SUM(W75,W81)) -> 15349.404 | X88: =SUM(X75,X81)+(X87%*SUM(X75,X81)) -> 6836.48 | ... AK88: =SUM(AK75,AK81)+(AK87%*SUM(AK75,AK81)) -> 8902.8745 | AM88: =SUM(AM75,AM81)+(AM87%*SUM(AM75,AM81))/AM6 -> 273743.48
C89: 4 | D89: PACKAGING (Brand Salvaco) | AM89: Packaging
D90: Olein IV 60 Received | F90: Kg | AM90: 0
D91: Olein IV 60 Consume | F91: Kg | AM91: 0
D92: - finished product | F92: Kg | G92: 0 | H92: 0 | I92: 0 | J92: 0 | K92: 0 | L92: 0 | M92: 0 | N92: 0 | O92: 0 | P92: 0 | Q92: 0 | R92: 0 | S92: 0 | T92: 0 | U92: 0 | V92: 0 | W92: 0 | X92: 0 | Y92: 0 | Z92: 0 | AA92: 0 | AB92: 0 | AC92: 0 | AD92: 0 | AE92: 0 | AF92: 0 | AG92: 0 | AH92: 0 | AJ92: 0 | AK92: 0 | AM92: 0
D93: - sample | F93: Kg | G93: 0 | H93: 0 | I93: 0 | J93: 0 | K93: 0 | L93: 0 | M93: 0 | N93: 0 | O93: 0 | P93: 0 | Q93: 0 | R93: 0 | S93: 0 | T93: 0 | U93: 0 | V93: 0 | W93: 0 | X93: 0 | Y93: 0 | Z93: 0 | AA93: 0 | AB93: 0 | AC93: 0 | AD93: 0 | AE93: 0 | AF93: 0 | AG93: 0 | AH93: 0 | AJ93: 0 | AK93: 0 | AM93: 0
D94: - remelt, flushing, downgrade | F94: Kg | G94: 0 | H94: 0 | I94: 0 | J94: 0 | K94: 0 | L94: 0 | M94: 0 | N94: 0 | O94: 0 | P94: 0 | Q94: 0 | R94: 0 | S94: 0 | T94: 0 | U94: 0 | V94: 0 | W94: 0 | X94: 0 | Y94: 0 | Z94: 0 | AA94: 0 | AB94: 0 | AC94: 0 | AD94: 0 | AE94: 0 | AF94: 0 | AG94: 0 | AH94: 0 | AJ94: 0 | AK94: 0 | AM94: 0
D95: Carton | AM95: Carton
D96: Salvaco 1 Liter | F96: Box | AM96: 0
D97: Salvaco 2 Liter | F97: Box | AM97: 0 | AW97: 37542
D98: Pouch | AM98: Pouch
D99: Salvaco 1 Liter | F99: Pouch | G99: 0 | H99: 0 | I99: 0 | J99: 0 | K99: 0 | L99: 0 | M99: 0 | N99: 0 | O99: 0 | P99: 0 | Q99: 0 | R99: 0 | S99: 0 | T99: 0 | U99: 0 | V99: 0 | W99: 0 | X99: 0 | Y99: 0 | Z99: 0 | AA99: 0 | AB99: 0 | AC99: 0 | AD99: 0 | AE99: 0 | AF99: 0 | AG99: 0 | AH99: 0 | AJ99: 0 | AK99: 0 | AM99: 0
D100: Salvaco 2 Liter | F100: Pouch | G100: 0 | H100: 0 | I100: 0 | J100: 0 | K100: 0 | L100: 0 | M100: 0 | N100: 0 | O100: 0 | P100: 0 | Q100: 0 | R100: 0 | S100: 0 | T100: 0 | U100: 0 | V100: 0 | W100: 0 | X100: 0 | Y100: 0 | Z100: 0 | AA100: 0 | AB100: 0 | AC100: 0 | AD100: 0 | AE100: 0 | AF100: 0 | AG100: 0 | AH100: 0 | AJ100: 0 | AK100: 0 | AM100: 0
D101: Consumable Vit. A | F101: gram | G101: 0 | H101: 0 | I101: 0 | J101: 0 | K101: 0 | L101: 0 | M101: 0 | N101: 0 | O101: 0 | P101: 0 | Q101: 0 | R101: 0 | S101: 0 | T101: 0 | U101: 0 | V101: 0 | W101: 0 | X101: 0 | Y101: 0 | Z101: 0 | AA101: 0 | AB101: 0 | AC101: 0 | AD101: 0 | AE101: 0 | AF101: 0 | AG101: 0 | AH101: 0 | AJ101: 0 | AK101: 0 | AM101: 0
D102: Consumable Packing Tape | F102: Roll | G102: 0 | H102: 0 | I102: 0 | J102: 0 | K102: 0 | L102: 0 | M102: 0 | N102: 0 | O102: 0 | P102: 0 | Q102: 0 | R102: 0 | S102: 0 | T102: 0 | U102: 0 | V102: 0 | W102: 0 | X102: 0 | Y102: 0 | Z102: 0 | AA102: 0 | AB102: 0 | AC102: 0 | AD102: 0 | AE102: 0 | AF102: 0 | AG102: 0 | AH102: 0 | AJ102: 0 | AK102: 0 | AM102: 0
...

Sheet Peformance test Fract 1
C1: PT.INDUSTRI NABATI LESTARI
C2: Pabrik Minyak Goreng ( PMG 2 )
C3: Kantor Pusat: Komp. KEK Sei Mangkei, Kav.2-3, Kec. Bosar Maligas, Kab. Simalungun, Sumatera Utara, 21184
C4: ACTUAL PEFORMANCE / CONSUMPT REPORT FRAKSINASI PLANT | H4: Trial | I4: 1
H5: Start / Date / Time | I5: 17/12/24 ( 07.00 Wib )
H6: Finish / Date / Time | I6: 17/12/24 ( 07.00 Wib )
A8: No | B8: ITEM | C8: Kontrak LIPICO | D8: UOM | E8: TOTALIZER
A10: 1 | B10: PRODUCTION | C10: IV 56 | D10: 24 jam | E10: BEFORE | F10: AFTER | G10: TOTAL | H10: YIELD % | I10: STATUS/REMAKS
B11: Fraksinasi
B12: Running Days
B13: Incoming CPO
B14: Ratio Run CPO
B15: RBDPO Consume Total | C15: 2500 | D15: TPD | E15: 8982.8 | F15: 11717.8 | G15: =F15-E15 -> 2735 | H15: =G15/25000*10 -> 1.094 | I15: OK
B16: Avg Daily Consump CPO ( MTD )
B17: CPO Consume Poram | C17: 29045000
B18: CPO Consume Brand | C18: 7314000 | E18: =E49+E58+E63 -> 0
B19: QUALITY
B20: - FFA | C20: 0.1 | D20: % Max | H20: 0.063
B21: - Moist & Impurities | C21: 0.1 | D21: % Max | H21: 0.05
B22: - IV | C22: 52 - 52,5 | H22: 51.8
B23: - LC | H23: 2,6/20
B24: - Temp | C24: 68 | D24: ˚C Min | H24: 65
B25: TANK | H25: 108/109
B26: Product
B27: OLEIN IV 56 | C27: =C15*84% -> 2100 | D27: TPD | E27: 6537.1 | F27: 8213 | G27: =F27-E27 -> 1675.9 | H27: =G27/(G27+G32) -> 0.82838219 | I27: OK
B28: QUALITY
B29: - IV | C29: 56 | D29: Min
B30: - LC
B31: - Cloud Point ( metter ) | C31: 10 | D31: ˚C Max
B32: STEARIN | C32: =C15*16% -> 400 | E32: 2268.1 | F32: 2615.3 | G32: =F32-E32 -> 347.2 | H32: =G32/(G32+G27) -> 0.17161781 | I32: OK
B33: Fractionation
B34: Running Days
B35: Filling Langsung CR Fr Refinery | E35: 0
B36: Total Filling Crystalizer ( Feed ) | E36: 392100
B37: Avg Daily Consump RPO ( MTD )
B38: Total Proses RBDPO | E38: =SUM(E41,E45,E50,E54,E64) -> 0
B39: Sisa Filling Crystalizer | E39: =E36-E38 -> 392100
B40: Fractionation OLEIN IV 56
B41: RBDPO Consume | E41: =E42+E43 -> 0
B42: OLEIN IV 56 | E42: 0
B43: STEARIN | E43: 0
B44: Fractionation OLEIN IV 57 ( Bulk )
B45: RBDPO Consume | E45: =E46+E47 -> 0
B46: OLEIN IV 57 | E46: 0
B47: STEARIN | E47: 0
B48: Fractionation OLEIN IV 57 ( Retail )
B49: CPO Consume
B50: RBDPO Brand Consume | E50: =E51+E52 -> 0
B51: OLEIN IV 57 Low Color | E51: 0
B52: STEARIN | E52: 0
B53: Fractionation OLEIN IV 58 ( Bulk )
B54: RBDPO Consume | C54: =C55+C56 -> 21429000 | E54: =E55+E56 -> 0
B55: OLEIN IV 58 | C55: 15000000
B56: STEARIN | C56: 6429000
B57: Fractionation OLEIN IV 58 ( Retail )
B58: CPO Consume
B59: RBDPO Consume | C59: =C60+C61 -> 21429000 | E59: =E60+E61 -> 0
B60: OLEIN IV 58 | C60: 15000000 | E60: 0
B61: STEARIN | C61: 6429000 | E61: 0
B62: Fractionation OLEIN IV 60
B63: CPO Consume
B64: RBDPO Brand Consume | E64: =E66+E67 -> 0
B65: OLEIN IV 60 Bulk | E65: 0
B66: OLEIN IV 60 Salvaco | E66: 0
B67: SOFT STEARIN | E67: 0
B68: Ratio Run RBDPO | E68: 0
B69: YIELD
B70: RBDPO | C70: 94.2 | E70: =(#REF!/(E15))*100 -> #REF!
B71: PFAD | C71: 5 | E71: =(E32/(E15))*100 -> 25.249365
B72: Olein IV 56 | C72: 82 | E72: =E42/(E42+E43)*100 -> #DIV/0!
B73: Stearin | C73: 18 | E73: =(E43/E41)*100 -> #DIV/0!
B74: Olein IV 57 ( Bulk ) | C74: 75 | E74: =(E46/E45)*100 -> #DIV/0!
B75: Stearin | C75: 25 | E75: =(E47/E45)*100 -> #DIV/0!
B76: Olein IV 57 ( Retail ) | C76: 75 | E76: =E51/E50*100 -> #DIV/0!
B77: Stearin | C77: 25 | E77: =E52/E50*100 -> #DIV/0!
B78: Olein IV 58 ( Bulk ) | C78: 70 | E78: =E55/(E55+E56)*100 -> #DIV/0!
B79: Stearin | C79: 30 | E79: =E56/(E56+E55)*100 -> #DIV/0!
B80: Olein IV 58 ( Retail ) | C80: 70 | E80: =E60/(E60+E61)*100 -> #DIV/0!
B81: Stearin | C81: 30 | E81: =E61/(E60+E61)*100 -> #DIV/0!
B82: Olein IV 60 | C82: 60 | E82: =E65/E64*100 -> #DIV/0!
B83: Soft Stearin | C83: 40 | E83: =E67/E64*100 -> #DIV/0!
B84: QUALITY
B85: - IV | C85: 32 | D85: Max
B86: - Melting Point | C86: 52-52,5 | D86: ˚C Min
A87: 2 | B87: STEAM CONSUMPTION | E87: BEFORE | F87: AFTER | G87: TOTAL | H87: Kg/Ton RBDPO
B88: Incoming | C88: 408000 | D88: Kg/Day | G88: 183211
B89: Distribution to
B90: fraksinasi | C90: 87.5 | D90: Kg/Day | E90: 308052 | F90: 366933 | G90: =F90-E90 -> 58881 | H90: =G90/G15 -> 21.528702 | I90: OK
C91: =C90/2000 -> 0.04375
C92: =C90/2.5 -> 35 | D92: Kg/ton
B93: Fractionation | C93: 122000
B94: Others ( Tank farm & spurging OSBL ) | C94: 106000 | D94: Kg/Day
B95: Total | C95: 408000 | D95: Kg/Day | G95: =SUM(G90,G93,G94) -> 58881
A96: 3 | B96: WATER CONSUMPTION | E96: BEFORE | F96: AFTER | G96: TOTAL | H96: M³/Ton RBDPO
B97: Incoming from Kinra | C97: 1100 | D97: M³/Day | G97: 818
B98: Outgoing
B99: Softener Product (to Fraksinasi ) | C99: 0.13 | D99: M³/Day | E99: 58 | F99: 106 | G99: =F99-E99 -> 48 | H99: =G99/G15 -> 0.017550274
B100: Softener Product (to Fractionation) | C100: 179.63
C101: =C99/2500 -> 5.2e-05 | D101: M³/ton
B102: RO Product | C102: 491.59 | D102: M³/Day | G102: 304
...

Sheet Peformance Test REFINERY 1
C1: PT.INDUSTRI NABATI LESTARI
C2: Pabrik Minyak Goreng ( PMG 2 )
C3: Kantor Pusat: Komp. KEK Sei Mangkei, Kav.2-3, Kec. Bosar Maligas, Kab. Simalungun, Sumatera Utara, 21184
C4: ACTUAL PEFORMANCE / CONSUMPT REPORT REFINERY PLANT | H4: Peformance | I4: 1
H5: Start / Date / Time | I5: 17/12/24 ( 21.00 Wib )
H6: Finish / Date / Time | I6: 18/12/24 ( 21.00 Wib )
A7: No | B7: ITEM | C7: Kontrak LIPICO | D7: UOM | E7: TOTALIZER
A9: 1 | B9: PRODUCTION | E9: BEFORE | F9: AFTER | G9: TOTAL | H9: Yield ( % ) | I9: STATUS/REMAKS
B10: Refinery
B11: Running Days
B12: Incoming CPO
B13: Ratio Run CPO
B14: CPO Consume Total | C14: 2500 | D14: TPD | E14: 13533.82 | F14: 16053.42 | G14: =F14-E14 -> 2519.6 | I14: OK
B15: Avg Daily Consump CPO ( MTD )
B16: CPO Consume Poram | C16: 29045000
B17: CPO Consume Brand | C17: 7314000 | E17: =E53+E62+E67 -> 0
B18: - FFA | C18: 5 | D18: % | G18: 4
B19: - Moist & Impurities | C19: 0.5 | D19: % | G19: 0.41
B20: - DOBI | C20: 2.2 | D20: Min | G20: 2.42
B21: - TOTOX 2PV + AV | C21: 12 | D21: Max | G21: N/A
B22: - FE Content | C22: < 5 | D22: ppm | G22: N/A
B23: - PV | C23: < 4 | D23: Meg/kg | G23: N/A
B24: - Phosporus Max | C24: 25 | D24: ppm | G24: N/A
B25: TANK / TEMP | C25: 50 | D25: ˚C | G25: 50
B26: Product
B27: RBDPO | C27: =C14*94.2% -> 2355 | D27: TPD | E27: 12357.54 | F27: 14705.95 | G27: =F27-E27 -> 2348.41 | H27: =G27/G14 -> 0.93205668
B28: - FFA | C28: 0.05 | D28: % | G28: 0.06
B29: - Moist & Impurities | C29: 0.03 | D29: % | G29: 0.05
B30: - Peroxide value | D30: Nil | G30: -
B31: - Phosporous max | C31: 2 | D31: ppm | G31: N/A
B32: - LC | C32: 2.5 | D32: % | G32: 2.5
B33: - Aom stability min ( hr ) | C33: 60 | D33: min ( hr ) | G33: N/A
B34: - teste & Odor | C34: bland/Odorless | G34: N/A
B35: - temp max ( C ) | C35: 50 | D35: max˚C | G35: 50
B36: PFAD | C36: =C14*5% -> 125 | D36: TPD | E36: 572.71 | F36: 675.39 | G36: =F36-E36 -> 102.68 | H36: =G36/G14 -> 0.0407525
B37: Fractionation
B38: Running Days
B39: Filling Langsung CR Fr Refinery | E39: 0
B40: Total Filling Crystalizer ( Feed ) | E40: 392100
B41: Avg Daily Consump RPO ( MTD )
B42: Total Proses RBDPO | E42: =SUM(E45,E49,E54,E58,E68) -> 0
B43: Sisa Filling Crystalizer | E43: =E40-E42 -> 392100
B44: Fractionation OLEIN IV 56
B45: RBDPO Consume | E45: =E46+E47 -> 0
B46: OLEIN IV 56 | E46: 0
B47: STEARIN | E47: 0
B48: Fractionation OLEIN IV 57 ( Bulk )
B49: RBDPO Consume | E49: =E50+E51 -> 0
B50: OLEIN IV 57 | E50: 0
B51: STEARIN | E51: 0
B52: Fractionation OLEIN IV 57 ( Retail )
B53: CPO Consume
B54: RBDPO Brand Consume | E54: =E55+E56 -> 0
B55: OLEIN IV 57 Low Color | E55: 0
B56: STEARIN | E56: 0
B57: Fractionation OLEIN IV 58 ( Bulk )
B58: RBDPO Consume | C58: =C59+C60 -> 21429000 | E58: =E59+E60 -> 0
B59: OLEIN IV 58 | C59: 15000000
B60: STEARIN | C60: 6429000
B61: Fractionation OLEIN IV 58 ( Retail )
B62: CPO Consume
B63: RBDPO Consume | C63: =C64+C65 -> 21429000 | E63: =E64+E65 -> 0
B64: OLEIN IV 58 | C64: 15000000 | E64: 0
B65: STEARIN | C65: 6429000 | E65: 0
B66: Fractionation OLEIN IV 60
B67: CPO Consume
B68: RBDPO Brand Consume | E68: =E70+E71 -> 0
B69: OLEIN IV 60 Bulk | E69: 0
B70: OLEIN IV 60 Salvaco | E70: 0
B71: SOFT STEARIN | E71: 0
B72: Ratio Run RBDPO | E72: 0
B73: YIELD
B74: RBDPO | C74: 94.2 | E74: =(E27/(E14))*100 -> 91.308588
B75: PFAD | C75: 5 | E75: =(E36/(E14))*100 -> 4.2316951
B76: Olein IV 56 | C76: 82 | E76: =E46/(E46+E47)*100 -> #DIV/0!
B77: Stearin | C77: 18 | E77: =(E47/E45)*100 -> #DIV/0!
B78: Olein IV 57 ( Bulk ) | C78: 75 | E78: =(E50/E49)*100 -> #DIV/0!
B79: Stearin | C79: 25 | E79: =(E51/E49)*100 -> #DIV/0!
B80: Olein IV 57 ( Retail ) | C80: 75 | E80: =E55/E54*100 -> #DIV/0!
B81: Stearin | C81: 25 | E81: =E56/E54*100 -> #DIV/0!
B82: Olein IV 58 ( Bulk ) | C82: 70 | E82: =E59/(E59+E60)*100 -> #DIV/0!
B83: Stearin | C83: 30 | E83: =E60/(E60+E59)*100 -> #DIV/0!
B84: Olein IV 58 ( Retail ) | C84: 70 | E84: =E64/(E64+E65)*100 -> #DIV/0!
B85: Stearin | C85: 30 | E85: =E65/(E64+E65)*100 -> #DIV/0!
B86: Olein IV 60 | C86: 60 | E86: =E69/E68*100 -> #DIV/0!
B87: Soft Stearin | C87: 40 | E87: =E71/E68*100 -> #DIV/0!
B88: - FFA | C88: ~93 | D88: % | G88: 90.21
B89: - Moist & Impurities | C89: 0.5 | D89: % | G89: 0.33
A90: 2 | B90: CHEMICAL CONSUMABLE | E90: BEFORE | F90: AFTER | G90: TOTAL | H90: ( % )
B91: Bleaching Earth (BE) to Poram Spec | C91: 9 | D91: kg | E91: 122737 | F91: 143761 | G91: =F91-E91 -> 21024 | H91: =G91/G14/10 -> 0.83441816 | I91: OK
E92: =E91/(E16)*100 -> #DIV/0!
B93: Bleaching Earth (BE) to Branded Spec | C93: 18 | E93: 0
E94: =E93/(E17)*100 -> #DIV/0! | I94: OK
B95: Phosporic Acid (PA) | C95: 0,4 - 0,5 | D95: kg | E95: 1970.8 | F95: 867.36 | G95: =E95-F95 -> 1103.44 | H95: =G95/G14/10 -> 0.043794253 | I95: OK
A97: 3 | B97: OIL LOSSES | C97: - 0,8 | D97: % | H97: =((SUM(G27+G36))-(SUM(G14)))/(SUM(G14))*100 -> -2.7190824
H98: =H97%*G14 -> -68.51
B99: % Oil Content | C99: 20 to 21 | D99: %
B100: Spent Bleaching Earth | H100: =SUM(G91,G93)+(H99%*SUM(G91,G93)) -> 21024
A101: 4 | B101: PACKAGING (Brand Salvaco)
B102: Olein IV 60 Received
...

Sheet peformance  test REFINERY 2
A1: REFINERY PMG 2
A2: No | B2: ITEM | C2: Norma LIPICO | D2: UOM | E2: Day 2 tanggal 12/12/2024
A4: 1 | B4: PRODUCTION | E4: BEFORE | F4: AFTER | G4: TOTAL | H4: Yield ( % )
B5: Refinery
B6: Running Days
B7: Incoming CPO
B8: Ratio Run CPO
B9: CPO Consume Total | C9: 2500 | D9: TPD | E9: 5880.74 | F9: 8383.74 | G9: =F9-E9 -> 2503 | H9: =G9/2500000*100000 -> 100.12
B10: Avg Daily Consump CPO ( MTD )
B11: CPO Consume Poram | C11: 29045000
B12: CPO Consume Brand | C12: 7314000 | E12: =E43+E52+E57 -> 0
B13: - FFA | C13: 5 | D13: % | G13: 3.97
B14: - Moist & Impurities | C14: 0.5 | D14: % | G14: 0.4
B15: - DOBI | C15: 2.2 | D15: Min | G15: 2.42
B16: TANK | G16: 105
B17: Product
B18: OIP RBDPO
B19: RBDPO | C19: =C9*94.2% -> 2355 | D19: TPD | E19: 5143.38 | F19: 7493.18 | G19: =F19-E19 -> 2349.8 | H19: =G19/G9*100 -> 93.879345
B20: - FFA | C20: 0.05 | D20: % | G20: 0.043
B21: - Moist & Impurities | C21: 0.03 | D21: % | G21: 0.04
B22: - LC | C22: 2.5 | D22: % | G22: 2.5
B23: - Aom stability min ( hr ) | C23: 60 | D23: min ( hr )
B24: - teste & Odor | C24: bland/Odorless
B25: - temp max ( C ) | C25: 50 | D25: max˚C
B26: PFAD | C26: =C9*5% -> 125 | D26: TPD | E26: 243.04 | F26: 347.1 | G26: =F26-E26 -> 104.06 | H26: =G26/G9*100 -> 4.1574111
B27: Fractionation
B28: Running Days
B29: Filling Langsung CR Fr Refinery | E29: 0
B30: Total Filling Crystalizer ( Feed ) | E30: 392100
B31: Avg Daily Consump RPO ( MTD )
B32: Total Proses RBDPO | E32: =SUM(E35,E39,E44,E48,E58) -> 0
B33: Sisa Filling Crystalizer | E33: =E30-E32 -> 392100
B34: Fractionation OLEIN IV 56
B35: RBDPO Consume | E35: =E36+E37 -> 0
B36: OLEIN IV 56 | E36: 0
B37: STEARIN | E37: 0
B38: Fractionation OLEIN IV 57 ( Bulk )
B39: RBDPO Consume | E39: =E40+E41 -> 0
B40: OLEIN IV 57 | E40: 0
B41: STEARIN | E41: 0
B42: Fractionation OLEIN IV 57 ( Retail )
B43: CPO Consume
B44: RBDPO Brand Consume | E44: =E45+E46 -> 0
B45: OLEIN IV 57 Low Color | E45: 0
B46: STEARIN | E46: 0
B47: Fractionation OLEIN IV 58 ( Bulk )
B48: RBDPO Consume | C48: =C49+C50 -> 21429000 | E48: =E49+E50 -> 0
B49: OLEIN IV 58 | C49: 15000000
B50: STEARIN | C50: 6429000
B51: Fractionation OLEIN IV 58 ( Retail )
B52: CPO Consume
B53: RBDPO Consume | C53: =C54+C55 -> 21429000 | E53: =E54+E55 -> 0
B54: OLEIN IV 58 | C54: 15000000 | E54: 0
B55: STEARIN | C55: 6429000 | E55: 0
B56: Fractionation OLEIN IV 60
B57: CPO Consume
B58: RBDPO Brand Consume | E58: =E60+E61 -> 0
B59: OLEIN IV 60 Bulk | E59: 0
B60: OLEIN IV 60 Salvaco | E60: 0
B61: SOFT STEARIN | E61: 0
B62: Ratio Run RBDPO | E62: 0
B63: YIELD
B64: RBDPO | C64: 94.2 | E64: =(E19/(E9))*100 -> 87.461442
B65: PFAD | C65: 5 | E65: =(E26/(E9))*100 -> 4.1328132
B66: Olein IV 56 | C66: 82 | E66: =E36/(E36+E37)*100 -> #DIV/0!
B67: Stearin | C67: 18 | E67: =(E37/E35)*100 -> #DIV/0!
B68: Olein IV 57 ( Bulk ) | C68: 75 | E68: =(E40/E39)*100 -> #DIV/0!
B69: Stearin | C69: 25 | E69: =(E41/E39)*100 -> #DIV/0!
B70: Olein IV 57 ( Retail ) | C70: 75 | E70: =E45/E44*100 -> #DIV/0!
B71: Stearin | C71: 25 | E71: =E46/E44*100 -> #DIV/0!
B72: Olein IV 58 ( Bulk ) | C72: 70 | E72: =E49/(E49+E50)*100 -> #DIV/0!
B73: Stearin | C73: 30 | E73: =E50/(E50+E49)*100 -> #DIV/0!
B74: Olein IV 58 ( Retail ) | C74: 70 | E74: =E54/(E54+E55)*100 -> #DIV/0!
B75: Stearin | C75: 30 | E75: =E55/(E54+E55)*100 -> #DIV/0!
B76: Olein IV 60 | C76: 60 | E76: =E59/E58*100 -> #DIV/0!
B77: Soft Stearin | C77: 40 | E77: =E61/E58*100 -> #DIV/0!
B78: - FFA | C78: ~93 | D78: % | G78: 90.62
B79: - Moist & Impurities | C79: 0.5 | D79: % | G79: 0.33
A80: 2 | B80: CHEMICAL CONSUMABLE | E80: BEFORE | F80: AFTER | G80: TOTAL | H80: ( % )
B81: Bleaching Earth (BE) to Poram Spec | C81: 9 | D81: kg | E81: 51223 | F81: 74245 | G81: =F81-E81 -> 23022 | H81: =G81/G9/10 -> 0.91977627
E82: =E81/(E11)*100 -> #DIV/0!
B83: Bleaching Earth (BE) to Branded Spec | C83: 18 | E83: 0
E84: =E83/(E12)*100 -> #DIV/0!
B85: Phosporic Acid (PA) | C85: 0,4 - 0,5 | D85: kg | E85: 539.5 | F85: 1342.1 | G85: =F85-E85 -> 802.6 | H85: =G85/G9/10 -> 0.032065521
A87: 3 | B87: OIL LOSSES | C87: - 0,8 | D87: % | G87: =((SUM(G19+G26))-(SUM(G9)))/(SUM(G9))*100 -> -1.9632441
G88: =G87%*G9 -> -49.14
B89: % Oil Content | C89: 20 to 21 | D89: % | G89: 21.66
B90: Spent Bleaching Earth | G90: =SUM(G81,G83)+(G89%*SUM(G81,G83)) -> 28008.565
A91: 4 | B91: PACKAGING (Brand Salvaco)
B92: Olein IV 60 Received
B93: Olein IV 60 Consume
B94: - finished product | E94: 0
B95: - sample | E95: 0
B96: - remelt, flushing, downgrade | E96: 0
B97: Carton
B98: Salvaco 1 Liter
B99: Salvaco 2 Liter
B100: Pouch
B101: Salvaco 1 Liter | E101: 0
B102: Salvaco 2 Liter | E102: 0
...

Sheet HPP REF 
B2: Refinery Cost
B3: Through Put CPO Proses | N3: =('JULI 2025'!AM10)/1000 -> 1382.6516 | O3: TPD
B4: Working Day | N4: ='JULI 2025'!AM6 -> 25 | O4: Days
B5: Total CPO Process | N5: =N4*N3 -> 34566.291 | O5: MTD
B6: KURS | N6: 16000 | O6: Rp/USD
B7: No | C7: Item Cost | D7: Norma | F7: Pemakaian / Hari | H7: HK | J7: Total Pemakaian | K7: Harga / stn | M7: Total Biaya | N7: Rp / kg | O7: USD/MT
B8: 1 | C8: Bleaching Earth | D8: ='JULI 2025'!$AM$76 -> 7.8514122 | F8: =($D$8*$N$3*10) -> 108557.68 | G8: Kg/day | H8: =$N$4 -> 25 | J8: =$H$8*$F$8 -> 2713942 | K8: 2400 | M8: =$J$8*$K$8 -> 6.5134608e+09 | N8: =$M$8/($N$5*1000) -> 188.43389 | O8: =($M$8/$N$6)/$N$5 -> 11.777118
B9: 2 | C9: Phosporic acid | D9: ='JULI 2025'!$AM$84 -> 0.47753836 | F9: =($D$9*$N$3*10) -> 6602.692 | G9: Kg/day | H9: =$H$8 -> 25 | J9: =$H$9*$F$9 -> 165067.3 | K9: 17420 | M9: =$J$9*$K$9 -> 2.8754724e+09 | N9: =$M$9/($N$5*1000) -> 83.187183 | O9: =($M$9/$N$6)/$N$5 -> 5.1991989
B10: 3 | C10: Caustic Soda | D10: 29.166667 | E10: kg/day | F10: =D10 -> 29.166667 | G10: kg/day | H10: =$H$8 -> 25 | J10: =$H$10*$F$10 -> 729.16667 | K10: 15700 | M10: =$J$10*$K$10 -> 11447917 | N10: =$M$10/($N$5*1000) -> 0.3311873 | O10: =($M$10/$N$6)/$N$5 -> 0.020699206
B11: 4 | C11: Pemakaian Natural Gas HPB Geka
C12: Normal Consumption | D12: ='JULI 2025'!$AM$245 -> 0.13987313 | E12: MMBTU/MT CPO | F12: =$D$12*$N$3 -> 193.39581 | G12: MMBTU/day | H12: =$H$8 -> 25 | J12: =$H$12*$F$12 -> 4834.8953 | K12: =11.5*$N$6 -> 184000 | M12: =$J$12*$K$12 -> 8.8962074e+08 | N12: =$M$12/($N$5*1000) -> 25.736656 | O12: =($M$12/$N$6)/$N$5 -> 1.608541
C13: Penalty Below Consumption | D13: 0 | E13: MMBTU/MT CPO | F13: =$D$13*$N$3 -> 0 | G13: MMBTU/day | H13: =$H$8 -> 25 | J13: =$H$13*$F$13 -> 0 | K13: =11.5*$N$6 -> 184000 | M13: =$J$13*$K$13 -> 0 | N13: =$M$13/($N$5*1000) -> 0 | O13: =($M$13/$N$6)/$N$5 -> 0
C14: Penalty Above Consumption | D14: 0 | E14: MMBTU/MT CPO | F14: =$D$14*$N$3 -> 0 | G14: MMBTU/day | H14: =$H$8 -> 25 | J14: =$H$14*$F$14 -> 0 | K14: =11.5*$N$6 -> 184000 | M14: =$J$14*$K$14 -> 0 | N14: =$M$14/($N$5*1000) -> 0 | O14: =($M$14/$N$6)/$N$5 -> 0
B15: 5 | C15: Pemakaian Steam
C16: For Process | D16: ='JULI 2025'!AM252 -> 46.623168 | E16: Kg/MT CPO | F16: =$D$16*$N$3/1000 -> 64.4636 | G16: Ton/day | H16: =$H$8 -> 25 | J16: =$H$16*$F$16 -> 1611.59 | K16: =Steam!H15 -> 58707.905 | M16: =$J$16*$K$16 -> 94613072 | N16: =$M$16/($N$5*1000) -> 2.7371485 | O16: =($M$16/$N$6)/$N$5 -> 0.17107178
C17: Storage Tank for Heating | D17: ='JULI 2025'!$AM$256 -> 1.4679041 | E17: Kg/MT CPO | F17: =$D$17*$N$3/1000 -> 2.0296 | G17: Ton/day | H17: =$H$8 -> 25 | J17: =$H$17*$F$17 -> 50.74 | K17: =Steam!H15 -> 58707.905 | M17: =$J$17*$K$17 -> 2978839.1 | N17: =$M$17/($N$5*1000) -> 0.086177574 | O17: =($M$17/$N$6)/$N$5 -> 0.0053860984
B18: 6 | C18: Pemakaian Electrical
C19: For Process | D19: ='JULI 2025'!$AM$275 -> 9.2559748 | E19: kW/MT CPO | F19: =$D$19*$N$3 -> 12797.789 | G19: kW/day | H19: =$H$8 -> 25 | I19: 0 | J19: =$H$19*$F$19 -> 319944.72 | K19: 1550 | L19: =[2]Electric!H21 -> 3666.6667 | M19: =($F$19*$H$19*$K$19)+($F$19*$I$19*$L$19) -> 4.9591432e+08 | N19: =$M$19/($N$5*1000) -> 14.346761 | O19: =($M$19/$N$6)/$N$5 -> 0.89667256
C20: Cooling Tower | D20: ='JULI 2025'!$AM$277 -> 6.5333304 | E20: kW/MT CPO | F20: =$D$20*$N$3 -> 9033.32 | G20: kW/day | H20: =$H$8 -> 25 | I20: 0 | J20: =$H$20*$F$20 -> 225833 | K20: 1550 | L20: =L19 -> 3666.6667 | M20: =(F20*H20*K20)+(F20*I20*L20) -> 3.5004115e+08 | N20: =$M$20/($N$5*1000) -> 10.126662 | O20: =($M$20/$N$6)/$N$5 -> 0.63291638
C21: Storage Tank | D21: 0.3377877 | E21: kW/MT CPO | F21: =$D$21*$N$3 -> 467.04272 | G21: kW/day | H21: =$H$8 -> 25 | I21: 0 | J21: =$H$21*$F$21 -> 11676.068 | K21: 1550 | L21: =L20 -> 3666.6667 | M21: =($F$21*$H$21*$K$21)+($F$21*$I$21*$L$21) -> 18097905 | N21: =$M$21/($N$5*1000) -> 0.52357093 | O21: =($M$21/$N$6)/$N$5 -> 0.032723183
B22: 7 | C22: Pemakaian Water
C23: Make Up CT | D23: ='JULI 2025'!$AM$262 -> 12.931674 | E23: M3/day | F23: =$D$23 -> 12.931674 | G23: M3/day | H23: =$H$8 -> 25 | J23: =$H$23*$F$23 -> 323.29185 | K23: =WTP!H13 -> 9401.4761 | M23: =$J$23*$K$23 -> 3039420.6 | N23: =$M$23/($N$5*1000) -> 0.087930191 | O23: =($M$23/$N$6)/$N$5 -> 0.0054956369
B24: 8 | C24: Chemical Water | N24: =$M$24/($N$5*1000) -> 0 | O24: =($M$24/$N$6)/$N$5 -> 0
C25: EONBAC BC 3108 | D25: 0.4 | E25: Kg/day | F25: =D25 -> 0.4 | G25: Kg/day | H25: =$H$8 -> 25 | J25: =$H$25*$F$25 -> 10 | K25: 27240 | M25: =$J$25*$K$25 -> 272400 | N25: =$M$25/($N$5*1000) -> 0.0078805099 | O25: =($M$25/$N$6)/$N$5 -> 0.00049253187
C26: EONLINE T722 | D26: 0.66 | E26: Kg/day | F26: =D26 -> 0.66 | G26: Kg/day | H26: =$H$8 -> 25 | J26: =$H$26*$F$26 -> 16.5 | K26: 29120 | M26: =$J$26*$K$26 -> 480480 | N26: =$M$26/($N$5*1000) -> 0.013900247 | O26: =($M$26/$N$6)/$N$5 -> 0.00086876547
C27: EONLINE AG5770 | D27: 0.41 | E27: Kg/day | F27: =D27 -> 0.41 | G27: Kg/day | H27: =$H$8 -> 25 | J27: =$H$27*$F$27 -> 10.25 | K27: 117212 | M27: =$J$27*$K$27 -> 1201423 | N27: =$M$27/($N$5*1000) -> 0.03475707 | O27: =($M$27/$N$6)/$N$5 -> 0.0021723169
C28: EONScale T2511 | D28: 0.1 | E28: Kg/day | F28: =D28 -> 0.1 | G28: Kg/day | H28: =$H$8 -> 25 | J28: =$H$28*$F$28 -> 2.5 | K28: 45940 | M28: =$J$28*$K$28 -> 114850 | N28: =$M$28/($N$5*1000) -> 0.0033226012 | O28: =($M$28/$N$6)/$N$5 -> 0.00020766258
B29: 9 | C29: Others
C30: Filter Bag 10 Microne | D30: 0.90361446 | E30: Pcs/day | F30: =D30 -> 0.90361446 | G30: Pcs/day | H30: =$H$8 -> 25 | J30: =$H$30*$F$30 -> 22.590361 | K30: 40000 | M30: =$J$30*$K$30 -> 903614.46 | N30: =$M$30/($N$5*1000) -> 0.026141493 | O30: =($M$30/$N$6)/$N$5 -> 0.0016338433
C31: Filter Bag 100 Microne | D31: 0.63253012 | E31: Pcs/day | F31: =D31 -> 0.63253012 | G31: Pcs/day | H31: =$H$8 -> 25 | J31: =$H$31*$F$31 -> 15.813253 | K31: 125000 | M31: =$J$31*$K$31 -> 1976656.6 | N31: =$M$31/($N$5*1000) -> 0.057184516 | O31: =($M$31/$N$6)/$N$5 -> 0.0035740323
C32: Filter Cartridge 10 Microne | D32: 1.5666667 | E32: Pcs/day | F32: =D32 -> 1.5666667 | G32: Pcs/day | H32: =$H$8 -> 25 | J32: =$H$32*$F$32 -> 39.166667 | K32: 145000 | M32: =$J$32*$K$32 -> 5679166.7 | N32: =$M$32/($N$5*1000) -> 0.16429783 | O32: =($M$32/$N$6)/$N$5 -> 0.010268614
C33: Filter Dustbag | D33: 0.12048193 | E33: Pcs/day | F33: =D33 -> 0.12048193 | G33: Pcs/day | H33: =$H$8 -> 25 | J33: =$H$33*$F$33 -> 3.0120482 | K33: 682500 | M33: =$J$33*$K$33 -> 2055722.9 | N33: =$M$33/($N$5*1000) -> 0.059471897 | O33: =($M$33/$N$6)/$N$5 -> 0.0037169936
C34: O Ring Filter Leaves | D34: 3.6144578 | E34: Pcs/day | F34: =D34 -> 3.6144578 | G34: Pcs/day | H34: =$H$8 -> 25 | J34: =$H$34*$F$34 -> 90.361446 | K34: 14500 | M34: =$J$34*$K$34 -> 1310241 | N34: =$M$34/($N$5*1000) -> 0.037905165 | O34: =($M$34/$N$6)/$N$5 -> 0.0023690728
B35: 10 | C35: Waste Water Treatment Plant ( WWTP ) | D35: ='JULI 2025'!$AM$268 -> 213.48 | E35: M3/day | F35: =D35 -> 213.48 | G35: M3/day | H35: =$H$8 -> 25 | J35: =$H$35*$F$35 -> 5337 | K35: =WWTP!H17 -> 19784.726 | M35: =$J$35*$K$35 -> 1.0559108e+08 | N35: =$M$35/($N$5*1000) -> 3.0547415 | O35: =($M$35/$N$6)/$N$5 -> 0.19092135
B36: 11 | C36: SHE
C37: SBE | D37: ='JULI 2025'!$AM$88 -> 273743.48 | E37: Kg/day | F37: =D37 -> 273743.48 | G37: Kg/day | H37: =$H$8 -> 25 | J37: =$F$37 -> 273743.48 | K37: 0 | M37: =$J$37*$K$37 -> 0 | N37: =$M$37/($N$5*1000) -> 0 | O37: =($M$37/$N$6)/$N$5 -> 0
C38: Domestic | D38: 0.1 | E38: Trip/day | F38: =D38 -> 0.1 | G38: Trip/day | H38: =$H$8 -> 25 | J38: =$H$38*$F$38 -> 2.5 | K38: 303030.3 | M38: =$J$38*$K$38 -> 757575.76 | N38: =$M$38/($N$5*1000) -> 0.021916605 | O38: =($M$38/$N$6)/$N$5 -> 0.0013697878
B39: 12 | C39: Chemical Consumption | N39: =$M$39/($N$5*1000) -> 0 | O39: =($M$39/$N$6)/$N$5 -> 0
C40: LAB Chemical | D40: =lab!H33 -> 745255.21 | E40: Rp/day | F40: =D40 -> 745255.21 | G40: Rp/day | H40: =$H$8 -> 25 | M40: =$H$40*$F$40 -> 18631380 | N40: =$M$40/($N$5*1000) -> 0.53900432 | O40: =($M$40/$N$6)/$N$5 -> 0.03368777
C41: Chemical Boiler dan WTP | D41: =lab!H54 -> 259161.44 | E41: Rp/day | F41: =D41 -> 259161.44 | G41: Rp/day | H41: =$H$8 -> 25 | M41: =$H$41*$F$41 -> 6479036.1 | N41: =$M$41/($N$5*1000) -> 0.18743799 | O41: =($M$41/$N$6)/$N$5 -> 0.011714874
C42: Sample and Analysis | D42: 13909.091 | E42: Rp/day | F42: =D42 -> 13909.091 | G42: Rp/day | H42: =$H$8 -> 25 | M42: =$H$42*$F$42 -> 347727.27 | N42: =$M$42/($N$5*1000) -> 0.010059722 | O42: =($M$42/$N$6)/$N$5 -> 0.00062873262
C43: Chemical WWTP | D43: =[2]Chemical!$H$61 -> 27103.641 | E43: Rp/day | F43: =D43 -> 27103.641 | G43: Rp/day | H43: =$H$8 -> 25 | M43: =$H$43*$F$43 -> 677591.04 | N43: =$M$43/($N$5*1000) -> 0.019602654 | O43: =($M$43/$N$6)/$N$5 -> 0.0012251659
C44: Consumable Part | D44: =lab!I111 -> 135770.31 | E44: Rp/day | F44: =D44 -> 135770.31 | G44: Rp/day | H44: =$H$8 -> 25 | M44: =$H$44*$F$44 -> 3394257.7 | N44: =$M$44/($N$5*1000) -> 0.098195601 | O44: =($M$44/$N$6)/$N$5 -> 0.006137225
B45: 13 | C45: Solar
C46: Forklift -1 (3 Ton) | D46: 15.4 | E46: Ltr/day | F46: =D46 -> 15.4 | G46: Ltr/day | H46: =$H$8 -> 25 | J46: =$H$46*$F$46 -> 385 | K46: 14500 | M46: =$J$46*$K$46 -> 5582500 | N46: =$M$46/($N$5*1000) -> 0.16150127 | O46: =($M$46/$N$6)/$N$5 -> 0.01009383
C47: WA Loader | D47: 0 | E47: Ltr/day | F47: =D47 -> 0 | G47: Ltr/day | H47: =$H$8 -> 25 | J47: =$H$47*$F$47 -> 0 | K47: 14500 | M47: =$J$47*$K$47 -> 0 | N47: =$M$47/($N$5*1000) -> 0 | O47: =($M$47/$N$6)/$N$5 -> 0
M48: =SUM($M$8:$M$47) -> 1.1410142e+10 | N48: =SUM($N$8:$N$47) -> 330.09449 | O48: =SUM($O$8:$O$47) -> 20.630906

Sheet HPP FRACT
B2: Fractionation Cost
B3: RPO Proses / Day | N3: TPD | O3: ='JULI 2025'!AM24/1000 -> 1270.5342
B4: Working Day | N4: Days | O4: ='JULI 2025'!AM23 -> 25
B5: Total CPO Process | N5: MTD | O5: =O3*O4 -> 31763.356
B6: KURS | N6: Rp/USD | O6: 16000
B7: No | C7: Item Cost | D7: Norma | F7: Pemakaian / Hari | H7: HK | J7: Total Pemakaian | K7: Harga / stn | M7: Total Biaya | N7: Rp / kg | O7: USD/MT
B8: 1 | C8: Steam | D8: ='JULI 2025'!AM254 -> 32.953602 | E8: Kg/MT CPO | F8: =$D$8*$O$3/1000 -> 41.86868 | G8: Ton/day | H8: =$O$4 -> 25 | J8: =$H$8*$F$8 -> 1046.717 | K8: =Steam!H15 -> 58707.905 | M8: =$K$8*$J$8 -> 61450562 | N8: =$M$8/($O$5*1000) -> 1.9346369 | O8: =($M$8/$O$6)/$O$5 -> 0.12091481
B9: 2 | C9: Electrical
C10: For Process | D10: ='JULI 2025'!$AM$282 -> 14.325009 | E10: kW/MT CPO | F10: =$D$10*$O$3 -> 18200.414 | G10: kW/day | H10: =$O$4 -> 25 | I10: 0 | J10: =$H$10*$F$10 -> 455010.36 | K10: =[2]Electric!$L$5 -> 1550 | L10: 3666.6667 | M10: =($F$10*$H$10*$K$10)+($F$10*$I$10*$L$10) -> 7.0526605e+08 | N10: =$M$10/($O$5*1000) -> 22.203764 | O10: =($M$10/$O$6)/$O$5 -> 1.3877352
C11: Cooling Tower | D11: ='JULI 2025'!$AM$280 -> 25.631502 | E11: kW/MT CPO | F11: =$D$11*$O$3 -> 32565.701 | G11: kW/day | H11: =$H$10 -> 25 | I11: 0 | J11: =$H$11*$F$11 -> 814142.52 | K11: =$K$10 -> 1550 | L11: 3666.6667 | M11: =($F$11*$H$11*$K$11)+($F$11*$I$11*$L$11) -> 1.2619209e+09 | N11: =$M$11/($O$5*1000) -> 39.728828 | O11: =($M$11/$O$6)/$O$5 -> 2.4830517
B12: 3 | C12: Water
C13: Make Up CT | D13: ='JULI 2025'!$AM$264 -> 6.4413848 | E13: M3/day | F13: =$D$13 -> 6.4413848 | G13: M3/day | H13: =$H$11 -> 25 | J13: =$H$13*$F$13 -> 161.03462 | K13: =WTP!H13 -> 9401.4761 | M13: =$K$13*$J$13 -> 1513963.1 | N13: =$M$13/($O$5*1000) -> 0.047663828 | O13: =($M$13/$O$6)/$O$5 -> 0.0029789893
B14: 4 | C14: Chemical Water
C15: EONBAC BC 3108 | D15: 0.4 | E15: Kg/day | F15: =$D$15 -> 0.4 | G15: Kg/day | H15: =$H$13 -> 25 | J15: =$H$15*$F$15 -> 10 | K15: 27240 | M15: =$K$15*$J$15 -> 272400 | N15: =$M$15/($O$5*1000) -> 0.00857592 | O15: =($M$15/$O$6)/$O$5 -> 0.000535995
C16: EONLINE T722 | D16: 0.66 | E16: Kg/day | F16: =$D$16 -> 0.66 | G16: Kg/day | H16: =$H$15 -> 25 | J16: =$H$16*$F$16 -> 16.5 | K16: 29120 | M16: =$K$16*$J$16 -> 480480 | N16: =$M$16/($O$5*1000) -> 0.015126865 | O16: =($M$16/$O$6)/$O$5 -> 0.00094542907
C17: EONLINE AG5770 | D17: 0.41 | E17: Kg/day | F17: =$D$17 -> 0.41 | G17: Kg/day | H17: =$H$15 -> 25 | J17: =$H$17*$F$17 -> 10.25 | K17: 117212 | M17: =$K$17*$J$17 -> 1201423 | N17: =$M$17/($O$5*1000) -> 0.037824183 | O17: =($M$17/$O$6)/$O$5 -> 0.0023640115
C18: EONScale T2511 | D18: 0.1 | E18: Kg/day | F18: =$D$18 -> 0.1 | G18: Kg/day | H18: =$H$16 -> 25 | J18: =$H$18*$F$18 -> 2.5 | K18: 45940 | M18: =$K$18*$J$18 -> 114850 | N18: =$M$18/($O$5*1000) -> 0.0036158018 | O18: =($M$18/$O$6)/$O$5 -> 0.00022598761
B19: 5 | C19: Others
C20: Filter Cloth | D20: 0.33333333 | E20: Pcs/day | F20: =$D$20 -> 0.33333333 | G20: Pcs/day | H20: =$H$18 -> 25 | J20: =$H$20*$F$20 -> 8.3333333 | K20: 895000 | M20: =$K$20*$J$20 -> 7458333.3 | N20: =$M$20/($O$5*1000) -> 0.23480936 | O20: =($M$20/$O$6)/$O$5 -> 0.014675585
C21: Filter Bag 100 Microne | D21: 0.63253012 | E21: Pcs/day | F21: =$D$21 -> 0.63253012 | G21: Pcs/day | H21: =$H$20 -> 25 | J21: =$H$21*$F$21 -> 15.813253 | K21: 125000 | M21: =$K$21*$J$21 -> 1976656.6 | N21: =$M$21/($O$5*1000) -> 0.062230724 | O21: =($M$21/$O$6)/$O$5 -> 0.0038894202
M22: =SUM(M8:M21) -> 2.0416556e+09 | N22: =SUM(N8:N21) -> 64.277075 | O22: =SUM($O$8:$O$21) -> 4.0173172

Sheet SUMMARY HPP 
B2: Production Cost MARET 2025
B3: Through Put CPO Proses (Ton/Day) | H3: TPD | I3: ='HPP REF '!$N$3 -> 1382.6516
B4: Working Day | F4: 1 | H4: Days | I4: ='HPP REF '!$N$4 -> 25
B5: Refined CPO ( Ton/month ) | H5: MTD | I5: =$I$4*$I$3 -> 34566.291
B6: Through Put RPO Proses (Ton/Day) | H6: TPD | I6: ='HPP FRACT'!$O$3 -> 1270.5342
B7: Working Day | H7: Days | I7: ='HPP FRACT'!$O$4 -> 25
B8: Fract RPO ( ton/month ) | H8: MTD | I8: =$I$7*$I$6 -> 31763.356
B9: KURS | H9: Rp/USD | I9: 16000
B10: No | C10: Items | D10: Description | G10: Rupiah | H10: Rp/Kg | I10: USD/MT
B11: I | C11: Production Cost | D11: ● | E11: Refining Cost | G11: ='HPP REF '!$M$48 -> 1.1410142e+10 | H11: =$G$11/($I$5*1000) -> 330.09449 | I11: =(G11/$I$9)/$I$5 -> 20.630906
D12: ● | E12: Fractionation Cost | G12: ='HPP FRACT'!$M$22 -> 2.0416556e+09 | H12: =$G$12/($I$8*1000) -> 64.277075 | I12: =(G12/$I$9)/$I$8 -> 4.0173172
D13: ● | E13: Preventive Maintenance Cost | F13: 0 | G13: =MTC!$F$18*F13 -> 0 | H13: =$G$13/($I$5*1000) -> 0 | I13: =(G13/$I$9)/$I$5 -> 0
G14: =SUM(G11:$G$13) -> 1.3451798e+10 | H14: =SUM($H$11:$H$13) -> 394.37157 | I14: =SUM(I11:I13) -> 24.648223
B16: II | C16: Port Cost | D16: ● | E16: Trucking Komoditi ke Kuala Tanjung | G16: =LOG!I8+LOG!I9+LOG!$I$10 -> 3.5888106e+09 | H16: =$G$16/($I$5*1000) -> 103.824 | I16: =($G$16/$I$9)/$I$5 -> 6.489
D17: ● | E17: Sewa Tank PTI Total Volume : 24.000 MT ( 5 Unit ) | F17: =F4 -> 1 | G17: =LOG!I11+LOG!I12+LOG!I13+LOG!$I$14*F17 -> 1886000000 | H17: =$G$17/($I$5*1000) -> 54.561827 | I17: =($G$17/$I$9)/$I$5 -> 3.4101142
D18: ● | E18: Instalasi & Pemanasan, Pompa, Surveyor dan Documen | G18: =LOG!I18+LOG!I19+LOG!I20+LOG!$I$21 -> 1.8516471e+09 | H18: =$G$18/($I$5*1000) -> 53.568 | I18: =($G$18/$I$9)/$I$5 -> 3.348
D19: ● | E19: Finalty Over Capacity Tank | G19: =LOG!I15+LOG!I16+LOG!$I$17 -> 1.4744597e+09 | H19: =$G$19/($I$5*1000) -> 42.656 | I19: =($G$19/$I$9)/$I$5 -> 2.666
G20: =SUM($G$16:$G$19) -> 8.8009174e+09 | H20: =SUM($H$16:$H$19) -> 254.60983 | I20: =SUM($I$16:$I$19) -> 15.913114
B22: II | C22: Fix Cost | D22: ● | E22: Manpower Cost | F22: =F4 -> 1 | G22: =[2]MPC!$H$29*$F$22 -> 2.1846655e+09 | H22: =$G$22/($I$5*1000) -> 63.202197 | I22: =($G$22/$I$9)/$I$5 -> 3.9501373
D23: ● | E23: Admin OH Cost | F23: =F4 -> 1 | G23: =OH!G51*$F$23 -> 1.4360564e+09 | H23: =$G$23/($I$5*1000) -> 41.544995 | I23: =($G$23/$I$9)/$I$5 -> 2.5965622
D24: ● | E24: Depresiasi Cost | F24: =F4 -> 1 | G24: =DEP!I9*$F$24 -> 4.1811848e+09 | H24: =$G$24/($I$5*1000) -> 120.96134 | I24: =($G$24/$I$9)/$I$5 -> 7.5600836
D25: ● | E25: Amortisation of leasehold land Cost | F25: =F4 -> 1 | G25: =AMOR!$G$20*$F$25 -> 1.0484098e+09 | H25: =$G$25/($I$5*1000) -> 30.330411 | I25: =($G$25/$I$9)/$I$5 -> 1.8956507
G26: =SUM($G$22:$G$25) -> 8.8503165e+09 | H26: =SUM($H$22:$H$25) -> 256.03894 | I26: =SUM($I$22:$I$25) -> 16.002434
B28: Total Production Cost | G28: =$G$26+$G$20+$G$14 -> 3.1103032e+10 | H28: =$H$26+$H$20+$H$14 -> 905.02033 | I28: =$I$26+$I$20+$I$14 -> 56.563771

Sheet Convert Gas
B3: CONVERT PEMAKAIAN GAS HP BOILER & MP BOILER
D4: 2024
C5: HP BOILER | F5: TOTAL CORRECTED VOLUME (Sm3) | K5: ENERGY MP BOILER (MMBTU) | L5: TOTAL GAS CONSUMPTION (MMBTU) | M5: PERCENTAGE
C6: UNCORRECTED VOLUME (UV) (Nm3) | D6: PRESS. Bar | E6: CORRECTED VOLUME (CV) (Sm3) | G6: Convert Sm3 to SCF | H6: VOLUME (MSCF) | I6: HEATING VALUE (BTU / SCF) | J6: ENERGY HP BOILER (MMBTU) | M6: HP Boiler | N6: MP Boiler
C7: 1 | D7: 2 | E7: 3 = 1 x 2 | F7: 4 = 3 | G7: 5 | H7: 6 = (4 x 5) / 1000 | I7: 7 | J7: 8 = (6 x 7) / 1000 | K7: 9 = 10 - 8 | L7: 10 | M7: 11 = 8 / 10 | N7: 12 = 9 / 10
B8: 1 | D8: 5 | E8: =C8*D8 -> 0 | F8: =E8 -> 0 | G8: 35.314667 | H8: =(F8*G8)/1000 -> 0 | I8: 0 | J8: =(H8*I8)/1000 -> 0 | K8: =L8-J8 -> 0 | L8: 0 | M8: =(J8/L8) -> #DIV/0! | N8: =K8/L8 -> #DIV/0!
B9: =B8+1 -> 2 | D9: 5 | E9: =C9*D9 -> 0 | F9: =E9 -> 0 | G9: 35.314667 | H9: =(F9*G9)/1000 -> 0 | I9: 0 | J9: =(H9*I9)/1000 -> 0 | K9: =L9-J9 -> 0 | L9: 0 | M9: =(J9/L9) -> #DIV/0! | N9: =K9/L9 -> #DIV/0!
B10: =B9+1 -> 3 | C10: 0 | D10: 5 | E10: =C10*D10 -> 0 | F10: =E10 -> 0 | G10: 35.314667 | H10: =(F10*G10)/1000 -> 0 | I10: 0 | J10: =(H10*I10)/1000 -> 0 | K10: =L10-J10 -> 0 | L10: 0 | M10: =(J10/L10) -> #DIV/0! | N10: =K10/L10 -> #DIV/0!
B11: =B10+1 -> 4 | C11: 0 | D11: 5 | E11: =C11*D11 -> 0 | F11: =E11 -> 0 | G11: 35.314667 | H11: =(F11*G11)/1000 -> 0 | I11: 0 | J11: =(H11*I11)/1000 -> 0 | K11: =L11-J11 -> 0 | L11: 0 | M11: =(J11/L11) -> #DIV/0! | N11: =K11/L11 -> #DIV/0!
B12: =B11+1 -> 5 | C12: 0 | D12: 5 | E12: =C12*D12 -> 0 | F12: =E12 -> 0 | G12: 35.314667 | H12: =(F12*G12)/1000 -> 0 | I12: 0 | J12: =(H12*I12)/1000 -> 0 | K12: =L12-J12 -> 0 | L12: 0 | M12: =(J12/L12) -> #DIV/0! | N12: =K12/L12 -> #DIV/0!
B13: =B12+1 -> 6 | C13: 0 | D13: 5 | E13: =C13*D13 -> 0 | F13: =E13 -> 0 | G13: 35.314667 | H13: =(F13*G13)/1000 -> 0 | I13: 0 | J13: =(H13*I13)/1000 -> 0 | K13: =L13-J13 -> 0 | L13: 0 | M13: =(J13/L13) -> #DIV/0! | N13: =K13/L13 -> #DIV/0!
B14: =B13+1 -> 7 | C14: 5445.8 | D14: 5 | E14: =C14*D14 -> 27229 | F14: =E14 -> 27229 | G14: 35.314667 | H14: =(F14*G14)/1000 -> 961.58307 | I14: 1070.1539 | J14: =(H14*I14)/1000 -> 1029.0419 | K14: =L14-J14 -> -104.99096 | L14: 924.05094 | M14: =(J14/L14) -> 1.1136203 | N14: =K14/L14 -> -0.11362031
B15: =B14+1 -> 8 | C15: 5810.5 | D15: 5 | E15: =C15*D15 -> 29052.5 | F15: =E15 -> 29052.5 | G15: 35.314667 | H15: =(F15*G15)/1000 -> 1025.9794 | I15: 1073.6387 | J15: =(H15*I15)/1000 -> 1101.5311 | K15: =L15-J15 -> -21.234858 | L15: 1080.2963 | M15: =(J15/L15) -> 1.0196565 | N15: =K15/L15 -> -0.019656514
B16: =B15+1 -> 9 | C16: 5849.8 | D16: 5 | E16: =C16*D16 -> 29249 | F16: =E16 -> 29249 | G16: 35.314667 | H16: =(F16*G16)/1000 -> 1032.9187 | I16: 1077.4325 | J16: =(H16*I16)/1000 -> 1112.9002 | K16: =L16-J16 -> 68.943764 | L16: 1181.8439 | M16: =(J16/L16) -> 0.94166424 | N16: =K16/L16 -> 0.05833576
B17: =B16+1 -> 10 | C17: 6108.5 | D17: 5 | E17: =C17*D17 -> 30542.5 | F17: =E17 -> 30542.5 | G17: 35.314667 | H17: =(F17*G17)/1000 -> 1078.5982 | I17: 1057.6573 | J17: =(H17*I17)/1000 -> 1140.7873 | K17: =L17-J17 -> 27.883244 | L17: 1168.6706 | M17: =(J17/L17) -> 0.97614106 | N17: =K17/L17 -> 0.023858942
B18: =B17+1 -> 11 | C18: 5078.5 | D18: 5 | E18: =C18*D18 -> 25392.5 | F18: =E18 -> 25392.5 | G18: 35.314667 | H18: =(F18*G18)/1000 -> 896.72768 | I18: 1042.4353 | J18: =(H18*I18)/1000 -> 934.78059 | K18: =L18-J18 -> 9.2041238 | L18: 943.98471 | M18: =(J18/L18) -> 0.99024971 | N18: =K18/L18 -> 0.009750289
B19: =B18+1 -> 12 | C19: 5266.9 | D19: 5 | E19: =C19*D19 -> 26334.5 | F19: =E19 -> 26334.5 | G19: 35.314667 | H19: =(F19*G19)/1000 -> 929.9941 | I19: 1049.662 | J19: =(H19*I19)/1000 -> 976.17945 | K19: =L19-J19 -> -87.64916 | L19: 888.53029 | M19: =(J19/L19) -> 1.0986451 | N19: =K19/L19 -> -0.098645101
B20: =B19+1 -> 13 | C20: 5177.5 | D20: 5 | E20: =C20*D20 -> 25887.5 | F20: =E20 -> 25887.5 | G20: 35.314667 | H20: =(F20*G20)/1000 -> 914.20844 | I20: 1058.6798 | J20: =(H20*I20)/1000 -> 967.85402 | K20: =L20-J20 -> -86.894691 | L20: 880.95933 | M20: =(J20/L20) -> 1.0986364 | N20: =K20/L20 -> -0.098636439
B21: =B20+1 -> 14 | C21: 6466.2 | D21: 5 | E21: =C21*D21 -> 32331 | F21: =E21 -> 32331 | G21: 35.314667 | H21: =(F21*G21)/1000 -> 1141.7585 | I21: 1062.4056 | J21: 981.9593 | K21: =L21-J21 -> 14.775555 | L21: 996.73485 | M21: =(J21/L21) -> 0.98517604 | N21: =K21/L21 -> 0.014823957
B22: =B21+1 -> 15 | C22: 6087.8 | D22: 5 | E22: =C22*D22 -> 30439 | F22: =E22 -> 30439 | G22: 36.314667 | H22: =(F22*G22)/1000 -> 1105.3821 | I22: 1052.2938 | J22: =(H22*I22)/1000 -> 1163.1868 | K22: =L22-J22 -> -128.11069 | L22: 1035.0761 | M22: =(J22/L22) -> 1.1237693 | N22: =K22/L22 -> -0.12376935
B23: =B22+1 -> 16 | C23: 4873.1 | D23: 5 | E23: =C23*D23 -> 24365.5 | F23: =E23 -> 24365.5 | G23: 37.314667 | H23: =(F23*G23)/1000 -> 909.19052 | I23: 1053.3732 | J23: =(H23*I23)/1000 -> 957.71689 | K23: =L23-J23 -> 56.552119 | L23: 1014.269 | M23: =(J23/L23) -> 0.94424347 | N23: =K23/L23 -> 0.055756528
B24: =B23+1 -> 17 | C24: 5075.4 | D24: 5 | E24: =C24*D24 -> 25377 | F24: =E24 -> 25377 | G24: 38.314667 | H24: =(F24*G24)/1000 -> 972.3113 | I24: 1053.6904 | J24: =(H24*I24)/1000 -> 1024.5151 | K24: =L24-J24 -> -103.99445 | L24: 920.52067 | M24: =(J24/L24) -> 1.1129735 | N24: =K24/L24 -> -0.11297351
B25: =B24+1 -> 18 | C25: 4606.6 | D25: 5 | E25: =C25*D25 -> 23033 | F25: =E25 -> 23033 | G25: 39.314667 | H25: =(F25*G25)/1000 -> 905.53473 | I25: 1062.8414 | J25: =(H25*I25)/1000 -> 962.43982 | K25: =L25-J25 -> 26.636388 | L25: 989.07621 | M25: =(J25/L25) -> 0.97306943 | N25: =K25/L25 -> 0.026930572
B26: =B25+1 -> 19 | C26: 5261.1 | D26: 5 | E26: =C26*D26 -> 26305.5 | F26: =E26 -> 26305.5 | G26: 40.314667 | H26: =(F26*G26)/1000 -> 1060.4975 | I26: 1082.6918 | J26: =(H26*I26)/1000 -> 1148.1919 | K26: =L26-J26 -> -209.58953 | L26: 938.60235 | M26: =(J26/L26) -> 1.2232996 | N26: =K26/L26 -> -0.2232996
B27: =B26+1 -> 20 | C27: 5977.4 | D27: 5 | E27: =C27*D27 -> 29887 | F27: =E27 -> 29887 | G27: 41.314667 | H27: =(F27*G27)/1000 -> 1234.7715 | I27: 1069.7089 | J27: =(H27*I27)/1000 -> 1320.846 | K27: =L27-J27 -> -338.8867 | L27: 981.95926 | M27: =(J27/L27) -> 1.3451128 | N27: =K27/L27 -> -0.34511279
B28: =B27+1 -> 21 | C28: 6186.5 | D28: 5 | E28: =C28*D28 -> 30932.5 | F28: =E28 -> 30932.5 | G28: 42.314667 | H28: =(F28*G28)/1000 -> 1308.8984 | I28: 1062.3425 | J28: =(H28*I28)/1000 -> 1390.4985 | K28: =L28-J28 -> -363.93485 | L28: 1026.5636 | M28: =(J28/L28) -> 1.3545176 | N28: =K28/L28 -> -0.35451758
B29: =B28+1 -> 22 | C29: 6815.5 | D29: 5 | E29: =C29*D29 -> 34077.5 | F29: =E29 -> 34077.5 | G29: 42.314667 | H29: =(F29*G29)/1000 -> 1441.9781 | I29: 1069.4774 | J29: =(H29*I29)/1000 -> 1542.163 | K29: =L29-J29 -> -403.20768 | L29: 1138.9553 | M29: =(J29/L29) -> 1.3540154 | N29: =K29/L29 -> -0.35401538
B30: =B29+1 -> 23 | C30: 6251.8 | D30: 5 | E30: =C30*D30 -> 31259 | F30: =E30 -> 31259 | G30: 44.314667 | H30: =(F30*G30)/1000 -> 1385.2322 | I30: 1073.8507 | J30: =(H30*I30)/1000 -> 1487.5325 | K30: =L30-J30 -> -410.8689 | L30: 1076.6636 | M30: =(J30/L30) -> 1.3816131 | N30: =K30/L30 -> -0.38161306
B31: =B30+1 -> 24 | C31: 5082.1 | D31: 5 | E31: =C31*D31 -> 25410.5 | F31: =E31 -> 25410.5 | G31: 45.314667 | H31: =(F31*G31)/1000 -> 1151.4683 | I31: 1076.3122 | J31: =(H31*I31)/1000 -> 1239.3395 | K31: =L31-J31 -> -290.50519 | L31: 948.8343 | M31: =(J31/L31) -> 1.3061706 | N31: =K31/L31 -> -0.30617062
B32: =B31+1 -> 25 | C32: 5137.6 | D32: 5 | E32: =C32*D32 -> 25688 | F32: =E32 -> 25688 | G32: 46.314667 | H32: =(F32*G32)/1000 -> 1189.7312 | I32: 1078.7582 | J32: =(H32*I32)/1000 -> 1283.4322 | K32: =L32-J32 -> -341.59792 | L32: 941.8343 | M32: =(J32/L32) -> 1.3626943 | N32: =K32/L32 -> -0.36269428
B33: =B32+1 -> 26 | C33: 5733.3 | D33: 5 | E33: =C33*D33 -> 28666.5 | F33: =E33 -> 28666.5 | G33: 47.314667 | H33: =(F33*G33)/1000 -> 1356.3459 | I33: 1089.0374 | J33: =(H33*I33)/1000 -> 1477.1113 | K33: =L33-J33 -> -550.52535 | L33: 926.586 | M33: =(J33/L33) -> 1.5941438 | N33: =K33/L33 -> -0.59414382
... B38: =B37+1 -> 31 | C38: 4295 | D38: 5 | E38: =C38*D38 -> 21475 | F38: =E38 -> 21475 | G38: 51.314667 | H38: =(F38*G38)/1000 -> 1101.9825 | I38: 1093.9934 | J38: =(H38*I38)/1000 -> 1205.5616 | K38: =L38-J38 -> -241.15245 | L38: 964.4091 | M38: =(J38/L38) -> 1.250052 | N38: =K38/L38 -> -0.25005203
B39: Average | F39: =AVERAGE(F8:F38) -> 21369.403 | H39: =AVERAGE(H8:H38) -> 873.11189 | I39: =AVERAGE(I8:I38) -> 863.84979 | J39: =AVERAGE(J8:J38) -> 928.22604 | K39: =AVERAGE(K8:K38) -> -135.19303 | L39: =AVERAGE(L8:L38) -> 793.03301 | M39: =AVERAGE(M8:M38) -> #DIV/0! | N39: =AVERAGE(N8:N38) -> #DIV/0!
B40: TOTAL | C40: =SUM(C8:C37) -> 128195.3 | E40: =SUM(E8:E38) -> 662451.5 | F40: =SUM(F8:F38) -> 662451.5 | H40: =SUM(H8:H38) -> 27066.469 | J40: =SUM(J8:J38) -> 28775.007
B41: Koreksi
B42: Total Setelah Koreksi | H42: =H40+H41 -> 27066.469 | J42: =J40+J41 -> 28775.007
C44: CONVERT HP Boiler from Utility
C45: =C40 -> 128195.3 | D45: m3 | F45: =C40*5 -> 640976.5 | G45: 9983.7
C46: 5 | D46: bar | F46: 21286.9 | G46: =G45-C40 -> -118211.6
C47: =C45*C46 -> 640976.5 | D47: Sm3 | F47: =F45/F46 -> 30.111313
C48: =#REF! -> #REF! | D48: Scf
C49: =(C47*C48)/1000 -> #REF! | D49: Volume (MSCF)
C50: =I39 -> 863.84979 | D50: Heating Value
C51: =(C49*C50)/1000 -> #REF! | D51: Energy (mmbtu)

Sheet OIP Refinery 
B4: Oil In Plant (OIP) Refinery pmg 2 | I4: FEBUARI | J4: OIP | M4: TK131 RPO | P4: TK132 RPO | S4: TOTAL STOK RPO DI PLANT
B5: Vessel | C5: Operating Volume (m3) | D5: Oil Density (kg/m3) | E5: MT | F5: Level yg diisi | G5: Actual OIP (Kg) | I5: Tanggal | J5: Opening Stock | K5: Closing Stock | L5: balance stok | M5: Opening Stock | N5: Closing Stock | O5: CONSUMP stok | P5: Opening Stock | Q5: Closing Stock | R5: CONSUMP stok
B6: 2MX312 | C6: 5.67 | D6: 850 | E6: =C6*D6/1000 -> 4.8195 | F6: 100 | G6: =(F6*E6/100)*1000 -> 4819.5 | I6: 45839
B7: 2VE611A | C7: 47.22 | D7: 850 | E7: =C7*D7/1000 -> 40.137 | F7: 80 | G7: =(F7*E7/100)*1000 -> 32109.6 | I7: 45840
B8: 2VE611B | C8: 47.22 | D8: 850 | E8: =C8*D8/1000 -> 40.137 | F8: 80 | G8: =(F8*E8/100)*1000 -> 32109.6 | I8: 45841
B9: 2VE612 | C9: 35.68 | D9: 850 | E9: =C9*D9/1000 -> 30.328 | F9: 0 | G9: =(F9*E9/100)*1000 -> 0 | I9: 45842
B10: 2VE661 | C10: 10.8 | D10: 850 | E10: =C10*D10/1000 -> 9.18 | F10: 17 | G10: =(F10*E10/100)*1000 -> 1560.6 | I10: 45843
B11: FL621 | C11: 10.1 | D11: 850 | E11: =C11*D11/1000 -> 8.585 | F11: 0 | G11: =(F11*E11/100)*1000 -> 0 | I11: 45844 | L11: =J11-K11 -> 0
B12: FL622 | C12: 10.1 | D12: 850 | E12: =C12*D12/1000 -> 8.585 | F12: 0 | G12: =(F12*E12/100)*1000 -> 0 | I12: 45845 | K12: 300569.36 | L12: =J12-K12 -> -300569.36
B13: FL623 | C13: 10.1 | D13: 850 | E13: =C13*D13/1000 -> 8.585 | F13: 0 | G13: =(F13*E13/100)*1000 -> 0 | I13: 45846 | J13: 300569.36 | K13: 310412 | L13: =J13-K13 -> -9842.64 | N13: 0 | Q13: 174609
B14: FL624 | C14: 10.1 | D14: 850 | E14: =C14*D14/1000 -> 8.585 | F14: 0 | G14: =(F14*E14/100)*1000 -> 0 | I14: 45847 | J14: 310412 | K14: 301214 | L14: =J14-K14 -> 9198 | N14: 44191 | P14: 174609 | Q14: 38852 | R14: =P14-Q14 -> 135757 | S14: =R14+O14+L14 -> 144955
B15: FL625 | C15: 10.1 | D15: 850 | E15: =C15*D15/1000 -> 8.585 | F15: 0 | G15: =(F15*E15/100)*1000 -> 0 | I15: 45848 | J15: 301214 | K15: 294983 | L15: =J15-K15 -> 6231 | M15: 44191 | N15: 405272 | O15: =M15-N15 -> -361081 | P15: 38852 | Q15: 38852 | R15: =P15-Q15 -> 0 | S15: =R15+O15+L15 -> -354850
B16: 2VE701 | C16: 72.13 | D16: 850 | E16: =C16*D16/1000 -> 61.3105 | F16: 0 | G16: =(F16*E16/100)*1000 -> 0 | I16: 45849 | J16: 294983 | K16: 298492 | L16: =J16-K16 -> -3509
B17: 2VE751 | C17: 4.28 | D17: 860 | E17: =C17*D17/1000 -> 3.6808 | F17: 50 | G17: =(F17*E17/100)*1000 -> 1840.4 | I17: 45850 | J17: 298492 | K17: 279848 | L17: =J17-K17 -> 18644
B18: 2HE721A (tube) | C18: 10 | D18: 810 | E18: =C18*D18/1000 -> 8.1 | F18: 100 | G18: =(F18*E18/100)*1000 -> 8100 | I18: 45851 | J18: 279848 | K18: 307500 | L18: =J18-K18 -> -27652
B19: 2HE721A (shell) | C19: 21.8 | D19: 800 | E19: =C19*D19/1000 -> 17.44 | F19: 40 | G19: =(F19*E19/100)*1000 -> 6976 | I19: 45852 | J19: 307500 | K19: 298308 | L19: =J19-K19 -> 9192
B20: HE721B (tube) | C20: 10 | D20: 810 | E20: =C20*D20/1000 -> 8.1 | F20: 100 | G20: =(F20*E20/100)*1000 -> 8100 | I20: 45853 | J20: 298308 | K20: 301410 | L20: =J20-K20 -> -3102
B21: 2HE722 | C21: 11.4 | D21: 790 | E21: =C21*D21/1000 -> 9.006 | F21: 80 | G21: =(F21*E21/100)*1000 -> 7204.8 | I21: 45854 | J21: 301410 | K21: 304623 | L21: =J21-K21 -> -3213
B22: 2PR731 | C22: 14 | D22: 790 | E22: =C22*D22/1000 -> 11.06 | F22: 40 | G22: =(F22*E22/100)*1000 -> 4424 | I22: 45855 | J22: 304623 | K22: 293070 | L22: =J22-K22 -> 11553
B23: 2DE732 | C23: 149.76 | D23: 790 | E23: =C23*D23/1000 -> 118.3104 | F23: 100 | G23: =(F23*E23/100)*1000 -> 118310.4 | I23: 45856 | J23: 293070 | K23: 302448 | L23: =J23-K23 -> -9378
C24: =SUM(C6:C23) -> 490.46 | E24: =SUM(E6:E23) -> 404.5342 | I24: 45857 | J24: 302448 | K24: 294782 | L24: =J24-K24 -> 7666
F25: Total OIP = | G25: =SUM(G6:G24) -> 225554.9 | I25: 45858 | J25: 294782 | K25: 302448 | L25: =J25-K25 -> -7666
I26: 45859 | J26: 302448 | K26: 307090 | L26: =J26-K26 -> -4642 | U26: =L26+L25 -> -12308
I27: 45860 | J27: 307090 | K27: 301876 | L27: =J27-K27 -> 5214
I28: 45861 | J28: 301876 | K28: 312139 | L28: =J28-K28 -> -10263
I29: 45862 | J29: 312139 | K29: 283528 | L29: =J29-K29 -> 28611
B30: Solar Daily Tank HPB | I30: 45863 | J30: 283528 | K30: 313730 | L30: =J30-K30 -> -30202
B31: 2TK726 | C31: =5.3+0.78 -> 6.08 | D31: 840 | E31: =C31*D31/1000 -> 5.1072 | F31: 0 | G31: =F31*E31/100*1000 -> 0 | H31: 0 | I31: 45864 | J31: 313730 | K31: 313427 | L31: =J31-K31 -> 303
I32: 45865 | J32: 313427 | K32: 298308 | L32: =J32-K32 -> 15119
B33: Stock Chemicals In Plant | I33: 45866 | J33: 298308 | K33: 208557 | L33: =J33-K33 -> 89751
C34: Read | D34: End Read | E34: Consumption | I34: 45867 | J34: 208557 | K34: 295949 | L34: =J34-K34 -> -87392
B35: BE | I35: 45868 | J35: 295949 | K35: 199965 | L35: =J35-K35 -> 95984
B36: 630A | I36: 45869 | J36: 199965 | K36: 225555 | L36: =J36-K36 -> -25590
B37: 630B
B38: H3PO4
B39: NaOH
B40: Citrid Acid

Sheet Oip Fract .
A4: Oil In Plant (OIP) Fraksinasi | I4: OIP | S4: BUFFER TANK | W4: DIRECT
A5: RBDPO OIP pmg 2 | I5: RPO CR | M5: OLEIN | P5: STEARIN | S5: TK131 RPO | U5: TK132 RPO
A6: Vessel | B6: Operating Volume (m3) | C6: Oil Density (kg/m3) | D6: MT | E6: Level Transmitter (1%/MT) | F6: Level (%) | G6: Kg | I6: Tanggal | J6: Opening Stock | K6: Closing Stock | L6: balance stok | M6: Opening Stock | N6: Closing Stock | O6: balance stok | P6: Opening Stock | Q6: Closing Stock | R6: balance stok | S6: Opening Stock | T6: Closing Stock | U6: Opening Stock | V6: Closing Stock
A7: 2CR1201 | B7: 70.51 | C7: 890 | D7: 60 | E7: =D7/100 -> 0.6 | F7: 0 | G7: =E7*F7*1000 -> 0 | I7: 45839
A8: 2CR1202 | B8: 70.51 | C8: 890 | D8: 60 | E8: =D8/100 -> 0.6 | F8: 0 | G8: =E8*F8*1000 -> 0 | I8: 45840
A9: 2CR1203 | B9: 70.51 | C9: 890 | D9: 60 | E9: =D9/100 -> 0.6 | F9: 100 | G9: =E9*F9*1000 -> 60000 | I9: 45841
A10: 2CR1204 | B10: 70.51 | C10: 890 | D10: 60 | E10: =D10/100 -> 0.6 | F10: 98.9 | G10: =E10*F10*1000 -> 59340 | I10: 45842
A11: 2CR1205 | B11: 70.51 | C11: 890 | D11: 60 | E11: =D11/100 -> 0.6 | F11: 100 | G11: =E11*F11*1000 -> 60000 | I11: 45843
A12: 2CR1206 | B12: 70.51 | C12: 890 | D12: 60 | E12: =D12/100 -> 0.6 | F12: 99.9 | G12: =E12*F12*1000 -> 59940 | I12: 45844
A13: 2CR1207 | B13: 70.51 | C13: 890 | D13: 60 | E13: =D13/100 -> 0.6 | F13: 100 | G13: =E13*F13*1000 -> 60000 | I13: 45845 | S13: 34859 | T13: 34831 | U13: 272307 | V13: 33986
A14: 2CR1208 | B14: 70.51 | C14: 890 | D14: 60 | E14: =D14/100 -> 0.6 | F14: 100 | G14: =E14*F14*1000 -> 60000 | I14: 45846 | J14: 0 | K14: 420000 | L14: =J14-K14 -> -420000 | M14: 0 | N14: 21696 | P14: 0 | Q14: 0 | S14: 34831 | T14: 106130 | U14: 33986 | V14: 33991
A15: 2CR1209 | B15: 70.51 | C15: 890 | D15: 60 | E15: =D15/100 -> 0.6 | F15: 100 | G15: =E15*F15*1000 -> 60000 | I15: 45847 | J15: 420000 | K15: 360000 | L15: =J15-K15 -> 60000 | M15: 216969 | N15: 22253 | Q15: 0 | R15: 0 | S15: 106130 | T15: 34893 | U15: 33991 | V15: 34003 | W15: 53843
A16: 2CR1210 | B16: 70.51 | C16: 890 | D16: 60 | E16: =D16/100 -> 0.6 | F16: 99.9 | G16: =E16*F16*1000 -> 59940 | I16: 45848 | J16: 360000 | K16: 600000 | L16: =J16-J17 -> -240000 | M16: 22253 | N16: 12490 | O16: =M16-N16 -> 9763 | P16: 0 | Q16: 0 | R16: =P16-Q16 -> 0 | S16: 34893 | T16: 68629 | U16: 34003 | V16: 40538
A17: 2CR1211 | B17: 70.51 | C17: 890 | D17: 60 | E17: =D17/100 -> 0.6 | F17: 100 | G17: =E17*F17*1000 -> 60000 | I17: 45849 | J17: 600000 | K17: 419580 | L17: =#REF!-K17 -> #REF! | M17: 12490 | N17: 17315 | O17: =M17-N17 -> -4825 | P17: 0 | Q17: 0 | R17: =P17-Q17 -> 0 | S17: 68629 | T17: 34876 | U17: 40538 | V17: 59415
A18: 2CR1212 | B18: 70.51 | C18: 890 | D18: 60 | E18: =D18/100 -> 0.6 | F18: 99.9 | G18: =E18*F18*1000 -> 59940 | I18: 45850 | J18: 419580 | K18: 479100 | L18: =J18-K18 -> -59520 | M18: 17315 | N18: 21738 | O18: =M18-N18 -> -4423 | P18: 0 | Q18: 0 | R18: =P18-Q18 -> 0 | S18: 34876 | T18: 34876 | U18: 59415 | V18: 71991
A19: 2CR1213 | B19: 70.51 | C19: 890 | D19: 60 | E19: =D19/100 -> 0.6 | F19: 99.8 | G19: =E19*F19*1000 -> 59880 | I19: 45851 | J19: 479100 | K19: 418500 | L19: =J19-K19 -> 60600 | M19: 21738 | N19: 22623 | O19: =M19-N19 -> -885 | P19: 0 | Q19: 0 | R19: =P19-Q19 -> 0 | S19: 34876 | T19: 85045 | U19: 71991 | V19: 86131
A20: 2CR1214 | B20: 70.51 | C20: 890 | D20: 60 | E20: =D20/100 -> 0.6 | F20: 99.6 | G20: =E20*F20*1000 -> 59760 | I20: 45852 | J20: 418500 | K20: 540000 | L20: =J20-K20 -> -121500 | M20: 22623 | N20: 39470 | O20: =M20-N20 -> -16847 | P20: 0 | Q20: 0 | R20: =P20-Q20 -> 0 | S20: 85045 | T20: 81918 | U20: 86131 | V20: 102628
A21: 2CR1215 | B21: 70.51 | C21: 890 | D21: 60 | E21: =D21/100 -> 0.6 | F21: 99.5 | G21: =E21*F21*1000 -> 59700 | I21: 45853 | J21: 540000 | K21: 780000 | L21: =J21-K21 -> -240000 | M21: 39470 | N21: 25248 | O21: =M21-N21 -> 14222 | P21: 0 | Q21: 0 | R21: =P21-Q21 -> 0 | S21: 85045 | T21: 81918 | U21: 86131 | V21: 102628
I22: 45854 | J22: 780000 | K22: 701880 | L22: =J22-K22 -> 78120 | M22: 25248 | N22: 40262 | O22: =M22-N22 -> -15014 | P22: 0 | R22: =P22-Q22 -> 0 | S22: 81918 | T22: 84269 | U22: 102628 | V22: 115980
F23: Total RBDPO | G23: =SUM(G7:G21) -> 778500 | I23: 45855 | J23: 701880 | K23: 540000 | M23: 40262 | N23: 56197 | O23: =M23-N23 -> -15935 | R23: =P23-Q23 -> 0 | S23: 34870 | T23: 34856 | U23: 136404 | V23: 157615
I24: 45856 | J24: 540000 | K24: 300000 | M24: 56197 | N24: 23201 | R24: =P24-Q24 -> 0 | S24: 34856 | T24: 58883 | U24: 157615 | V24: 170967
A25: Olein OIP | I25: 45857 | J25: 300000 | K25: 780000 | M25: 23201 | N25: 24721 | R25: =P25-Q25 -> 0 | S25: 58883 | T25: 98338 | U25: 170967 | V25: 195337
A26: Vessel | B26: Operating Volume (m3) | C26: Oil Density (kg/m3) | D26: MT | E26: Level Transmitter (1%/MT) | F26: Level (%) | G26: Kg | I26: 45858 | J26: 780000 | K26: 720000 | M26: 24721 | N26: 24721 | S26: 98338 | T26: 113968 | U26: 195337 | V26: 209474
A27: 2TK261 | B27: 15.95 | C27: 885 | D27: =B27*C27/1000 -> 14.11575 | E27: =D27/100 -> 0.1411575 | F27: 72.3 | G27: =E27*F27*1000 -> 10205.687 | I27: 45859 | J27: 720000 | K27: 658920 | M27: 24721 | N27: 19504 | S27: 113968 | T27: 67849 | U27: 209474 | V27: 232257
A28: 2CL251 | B28: 3.02 | C28: 885 | D28: =B28*C28/1000 -> 2.6727 | E28: =D28/100 -> 0.026727 | F28: 0 | G28: =E28*F28*1000 -> 0 | I28: 45860 | J28: 658920 | K28: 658860 | M28: 19504 | N28: 20809 | S28: 67849 | T28: 163972 | U28: 232257 | V28: 152224
A29: 2TK221 | B29: 82.48 | C29: 885 | D29: =B29*C29/1000 -> 72.9948 | E29: =D29/100 -> 0.729948 | F29: 0 | G29: =E29*F29*1000 -> 0 | I29: 45861 | J29: 658860 | K29: 635580 | M29: 20809 | N29: 19215 | S29: 163972 | T29: 47434 | U29: 152224 | V29: 160023
A30: 2TK241 | B30: 16.95 | C30: 885 | D30: =B30*C30/1000 -> 15.00075 | E30: =D30/100 -> 0.1500075 | F30: 93 | G30: =E30*F30*1000 -> 13950.697 | I30: 45862 | J30: 635580 | K30: 360000 | M30: 19215 | N30: 31795 | S30: 43586 | T30: 51413 | U30: 160023 | V30: 181229
G31: =SUM(G27:G30) -> 24156.385 | I31: 45863 | J31: 360000 | K31: 168240 | M31: 31795 | N31: 32417 | S31: 51413 | T31: 34860 | U31: 181229 | V31: 197739
A32: Stearin OIP | I32: 45864 | J32: 168240 | K32: 598680 | M32: 32417 | N32: 23135 | S32: 34860 | T32: 34975 | U32: 197739 | V32: 213446
A33: Melting Tank | B33: Panjang (m) | C33: Lebar (m) | D33: tinggi (m) | E33: Density | F33: Tinggi Sounding (Cm) Maks 4,4 m | G33: Kg | I33: 45865 | J33: 598680 | K33: 480000 | M33: 23135 | N33: 23032 | S33: 34975 | T33: 67850 | U33: 213446 | V33: 226007
A34: TK231 A | B34: 12.2 | C34: 1.75 | D34: 1.52 | E34: 0.88 | F34: 0 | G34: =B34*C34*D34*E34*F34/100 -> 0 | I34: 45866 | J34: 480000 | K34: 120000 | M34: 23032 | N34: 22191 | S34: 67850 | T34: 34881 | U34: 226007 | V34: 93213
A35: TK231 B | B35: 12.2 | C35: 1.75 | D35: 1.52 | E35: 0.88 | F35: 0 | G35: =B35*C35*D35*E35*F35/100 -> 0 | I35: 45867 | J35: 120000 | K35: 359820 | M35: 22191 | N35: 19700 | S35: 34881 | T35: 34891 | U35: 93213 | V35: 97917
F36: Total STEARIN | G36: =SUM(G34:G35) -> 0 | I36: 45868 | J36: 359820 | K36: 658200 | M36: 19700 | N36: 20597 | S36: 34891 | T36: 44368 | U36: 97917 | V36: 106549
I37: 45869 | J37: 658200 | K37: 778500 | M37: 20597 | N37: 24156 | S37: 44368 | T37: 34894 | U37: 106549 | V37: 118327

Sheet 2025
B2: PRODUCTION REPORT 2025
F3: ok | M3: ok | N3: ok
B4: No | C4: ITEM | D4: Budget / Norma | E4: UoM | F4: YEARLY REPORT | T4: Yearly Report | U4: Yearly Report RKAP (Budget) | V4: Yearly Report RKAP
F5: JANUARI | G5: FEBRUARI | H5: MARET | I5: APRIL | J5: MEI | K5: JUNI | L5: JULI | M5: AGUSTUS | N5: SEPTEMBER | O5: OKTOBER | P5: NOVEMBER | Q5: DESEMBER | R5: DESEMBER | T5: TOTAL (Kg) | U5: TOTAL (Kg) | V5: TOTAL (%)
B6: 1 | C6: PRODUCTION | T6: Production | U6: Production | V6: Production | DG6: 29 | DH6: 30 | DI6: 31
C7: Refinery | T7: Refinery | U7: Refinery | V7: Refinery | DE7: CPO Olah | DF7: Kg | DG7: 1971320 | DH7: 2015120 | DI7: 2015230 | AIU7: Sounding | AIV7: Production | AIW7: Diff
C8: Running Days | D8: 300 | E8: Day | F8: 0 | G8: 13 | H8: 6 | K8: 10 | L8: ='JULI 2025'!AM6 -> 25 | R8: ='[3]Desember 24'!AL9 -> 0 | T8: =SUM(F8:R8) -> 54 | U8: 231 | V8: =T8/U8*100 -> 23.376623 | OR8: Poram | AEE8: 14 Juni | AEF8: 15 Juni | AIT8: CPO | AIU8: 11008948 | AIV8: =T11 -> 74559975 | AIW8: =AIU8-AIV8 -> -63551027
C9: Ratio Run CPO | G9: 0 | H9: 0 | K9: 0 | R9: ='[3]Desember 24'!AL10 -> 0
C10: Utilitas CPO | G10: 0 | H10: 0 | K10: 0 | R10: =R11/R14*100 -> #DIV/0! | T10: =AVERAGE(F10:Q10) -> 0
C11: CPO Consume Total | D11: 707651000 | E11: Kg | F11: 0 | G11: 16619582 | H11: 5560915 | I11: 0 | K11: 17813187 | L11: ='JULI 2025'!AM9 -> 34566291 | R11: ='[3]Desember 24'!AL11 -> 0 | T11: =SUM(F11:Q11) -> 74559975 | U11: 421374000 | V11: =T11/U11 -> 0.17694489 | AX11: =T11/D11 -> 0.10536264 | DE11: HP Boiler | DF11: mmbtu | DG11: 251.19642 | DH11: 257.91391 | DI11: 251.51265 | OO11: 26946.108 | OP11: 17383.234 | OR11: RBDPO Olah | AEE11: =35.8500000000058*1000 -> 35850 | AIT11: PFAD | AIU11: 566885 | AIV11: =T20 -> 3372812 | AIW11: =AIU11-AIV11 -> -2805927
C12: CPO Consume Poram | E12: Kg | F12: 0 | G12: 16619582 | H12: 5560915 | I12: =I11 -> 0 | J12: =J11 -> 0 | K12: 17813187 | L12: =L11 -> 34566291 | R12: ='[3]Desember 24'!AL12 -> #DIV/0! | T12: =SUM(F12:Q12) -> 74559975
C13: CPO Consume Brand | E13: Kg | F13: 0 | G13: 0 | H13: 0 | R13: ='[3]Desember 24'!AL13 -> #DIV/0! | T13: =SUM(F13:Q13) -> 0 | AX13: =AW13/Q13 -> #DIV/0!
C14: Budget CPO Olah | E14: Kg | F14: 0 | G14: 58900 | H14: 58900 | I14: 58900 | J14: 58900 | K14: 58900 | L14: 58900 | T14: =SUM(F14:Q14) -> 353400
C15: - FFA | D15: 5 | E15: % | F15: 0 | G15: 3.5869231 | H15: 4.163 | K15: 4.5701667 | L15: ='JULI 2025'!AM13 -> 3.952 | R15: ='[3]Desember 24'!AL14 -> #DIV/0! | T15: =AVERAGE(F15:Q15) -> 3.2544179 | U15: =AVERAGE(G15:S15) -> #DIV/0! | V15: =AVERAGE(H15:T15) -> #DIV/0! | Z15: =39993684/2500000/29 -> 0.55163702 | DE15: Steam Ref | DF15: Kg | DG15: 182230 | DH15: 190070 | DI15: 197800 | OO15: =T11/1000 -> 74559.975 | OP15: =(T26+T49+T35)/1000 -> 36329.116 | OR15: =SUM(OR16:OR17) -> #REF! | AGV15: 2000
C16: - Moist & Impurities | D16: 0.5 | E16: % | F16: 0 | G16: 0.36807692 | H16: 0.452 | K16: 0.43 | L16: ='JULI 2025'!AC14 -> 0.445 | R16: ='[3]Desember 24'!AL15 -> #DIV/0! | T16: =AVERAGE(F16:Q16) -> 0.33901538 | U16: =AVERAGE(G16:S16) -> #DIV/0! | V16: =AVERAGE(H16:T16) -> #DIV/0! | DF16: Kg/MT | DG16: =DG15/(DG7/1000) -> 92.440598 | DH16: =DH15/(DH7/1000) -> 94.321926 | DI16: =DI15/(DI7/1000) -> 98.152568 | OR16: =#REF!/1000 -> #REF! | OS16: =OR16/OR15*100 -> #REF! | AGU16: 0.942 | AGV16: =AGU16*AGV15 -> 1884 | AGW16: Refinery | AIT16: Olein IV 56 | AIU16: 9594130 | AIV16: =T27 -> 29198350 | AIW16: =AIU16-AIV16 -> -19604220
C17: - DOBI | D17: 2,20 Min | E17: % | F17: 0 | G17: 0 | H17: 0 | R17: ='[3]Desember 24'!AL16 -> #DIV/0! | T17: =AVERAGE(F17:Q17) -> 0 | U17: =AVERAGE(G17:S17) -> #DIV/0! | V17: =AVERAGE(H17:T17) -> #DIV/0! | OO17: =SUM(OO15:OO16) -> 74559.975 | OP17: =SUM(OP15:OP16) -> 36329.116 | OR17: =#REF!/1000 -> #REF! | OS17: =OR17/OR15*100 -> #REF! | AGU17: 0.05 | AGV17: =AGU17*AGV15 -> 100 | AIT17: Stearin | AIU17: 2161151 | AIV17: =T28 -> 6990318 | AIW17: =AIU17-AIV17 -> -4829167
C18: Product | G18: 0 | T18: Product | U18: Product | V18: Product | OO18: =OO17/OO11*100 -> 276.70035 | OP18: =OP17/OP11*100 -> 208.9894 | AEG18: Product OIP | AEQ18: Juni | AER18: Sisa Product OIP
C19: RbdPO | D19: 668731 | E19: Kg | F19: 0 | G19: 15725291 | H19: 5221351 | K19: 16884686 | L19: ='JULI 2025'!AM20 -> 32809301 | R19: ='[3]Desember 24'!AL18 -> 0 | T19: =SUM(F19:Q19) -> 70640629 | U19: 399336000 | V19: =T19/U19*100 -> 17.689522 | AX19: =AX20/D19 -> 103.73232 | DE19: Tahun 2021 | AEE19: 136360 | AEF19: 109340 | AEG19: =SUM(AEE19:AEF19) -> 245700 | AEQ19: 34157.88 | AER19: =AEG19-AEQ19 -> 211542.12 | AGV19: =AGV16 -> 1884
C20: PFAD | D20: 33967 | E20: Kg | F20: 0 | G20: 769266 | H20: 250161 | K20: 866309 | L20: ='JULI 2025'!AM21 -> 1487076 | R20: ='[3]Desember 24'!AL19 -> 0 | T20: =SUM(F20:Q20) -> 3372812 | U20: 19024000 | V20: =T20/U20*100 -> 17.729247 | AX20: =T26+T30+T35+T49+T39 -> 69369020 | DE20: Items | DG20: Agustus | DH20: Oktober | OO20: =OO11-OO17 -> -47613.867 | OP20: =OP11-OP17 -> -18945.882 | OR20: Olein IV 58 | OS20: 0 | PE20: 564.70507 | PF20: =OS20/PE20*100 -> 0 | AEE20: 13800 | AEF20: 2800 | AEG20: =SUM(AEE20:AEF20) -> 16600 | AEQ20: 1469.85 | AER20: =AEG20-AEQ20 -> 15130.15 | AGU20: 0.75 | AGV20: =AGU20*AGV19 -> 1413
C21: Fractionation
C22: Running Days | H22: 6
C23: Total Filling Crystalizer ( Feed ) | D23: 426016000 | E23: Kg | F23: =F231 -> 0 | G23: 13740404 | H23: 5642619 | K23: 17223447 | L23: ='JULI 2025'!AM25 -> 32775474 | T23: =SUM(F23:Q23) -> 69381944
C24: Total Proses RBDPO | E24: Kg | F24: 0 | G24: 13936434 | H24: 5876623 | I24: 0 | K24: 17792607 | L24: ='JULI 2025'!AM29 -> 31763356 | T24: =SUM(F24:Q24) -> 69369020
C25: Fractionation OLEIN IV 56 | T25: Olein IV 56 | U25: Olein IV 56 | V25: Olein IV 56 | DG25: 24 | DH25: 2 | DI25: 3 | OR25: Olein IV 60 | OS25: =80.53776+PF35 -> 120.78492 | PE25: 4695.7554 | PF25: =OS25/PE25*100 -> 2.5722149 | AGU25: 0.25 | AGV25: =AGU25*AGV19 -> 471
C26: RBDPO Consume | E26: Kg | F26: 0 | G26: 210210 | H26: 5876623 | I26: =I27+I28 -> 0 | J26: =J27+J28 -> 0 | K26: 17792607 | L26: ='JULI 2025'!AM32 -> 12309228 | R26: =R27+R28 -> 0 | T26: =T27+T28 -> 36188668 | U26: =U27+U28 -> 87311000 | V26: =T26/U26*100 -> 41.448005 | DE26: CPO Olah | DF26: Kg | DG26: 2000530 | DH26: 2005167 | DI26: 2025879 | AEE26: =95.28%*AEE11 -> 34157.88 | AEG26: =AEE19-AEQ19 -> 102202.12 | AIQ26: CPO Feed - Sounding
C27: OLEIN IV 56 | D27: 349333 | E27: Kg | F27: 0 | G27: 169210 | H27: 4808488 | K27: 14325558 | L27: ='JULI 2025'!AM33 -> 9895094 | R27: ='[3]Desember 24'!AL22 -> 0 | T27: =SUM(F27:Q27) -> 29198350 | U27: 71627000 | V27: =T27/U27*100 -> 40.764446 | DE27: HP Boiler | DF27: mmbtu | DG27: 255.53619 | DH27: 255.09239 | DI27: 260.82455 | OO27: =#REF!/1000 -> #REF! | OR27: INL 900 ml | OS27: 0 | PE27: 9.75348 | PF27: =(OS27*PE27)/1000 -> 0 | AEE27: =4.1%*AEE11 -> 1469.85 | AEG27: =AEE20-AEQ20 -> 12330.15
C28: STEARIN | D28: 76683 | E28: Kg | F28: 0 | G28: 41000 | H28: 1068135 | K28: 3467049 | L28: ='JULI 2025'!AM34 -> 2414134 | R28: ='[3]Desember 24'!AL23 -> 0 | T28: =SUM(F28:Q28) -> 6990318 | U28: 15684000 | V28: =T28/U28*100 -> 44.56974 | DE28: Steam Ref | DF28: Kg | DG28: 146000 | DH28: 151100 | DI28: 152900 | OO28: 1796 | OR28: Salvaco 1L | OS28: 1262 | PE28: 10.86 | PF28: =(OS28*PE28)/1000 -> 13.70532 | AIQ28: Report Prod
C29: Fractionation OLEIN IV 57 ( Bulk ) | G29: 0 | T29: Olein IV 57 ( Bulk ) | U29: Olein IV 57 ( Bulk ) | V29: Olein IV 57 ( Bulk )
C30: RBDPO Consume | E30: Kg | F30: 0 | G30: 0 | H30: 0 | R30: =R31+R32 -> 0 | T30: =T31+T32 -> 0 | U30: =U31+U32 -> 5121000 | V30: =T30/U30*100 -> 0 | AX30: =T30+T35 -> 0
C31: OLEIN IV 57 | E31: Kg | F31: 0 | G31: 0 | H31: 0 | R31: ='[3]Desember 24'!AL26 -> 0 | T31: =SUM(F31:Q31) -> 0 | U31: 3934000 | V31: =T31/U31*100 -> 0 | AX31: =T31+T36 -> 0
C32: STEARIN | E32: Kg | F32: 0 | H32: 0 | R32: ='[3]Desember 24'!AL27 -> 0 | T32: =SUM(F32:Q32) -> 0 | U32: 1187000 | V32: =T32/U32*100 -> 0 | AX32: =T32+T37 -> 0
C33: Fractionation OLEIN IV 57 ( Retail ) | G33: 0 | T33: Olein IV 57 ( Retail ) | U33: Olein IV 57 ( Retail ) | V33: Olein IV 57 ( Retail ) | DF33: Kg/MT | DG33: =DG28/(DG26/1000) -> 72.98066 | DH33: =DH28/(DH26/1000) -> 75.35532 | DI33: =DI28/(DI26/1000) -> 75.473412 | OO33: =OO27/OO28*100 -> #REF! | OR33: Salvaco 2L | OS33: 2444 | PE33: 10.86 | PF33: =(OS33*PE33)/1000 -> 26.54184 | AIQ33: Diff
C34: CPO Consume | E34: Kg | F34: 0 | G34: 0 | H34: 0 | R34: ='[3]Desember 24'!AL29 -> 0 | T34: =SUM(F34:Q34) -> 0 | U34: =U35/U57% -> 32338304 | V34: =(T34/U34)*100 -> 0 | DF34: Kg/MT | DG34: =DG28/(DG20/1000) -> #VALUE! | DH34: =DI28/(DH20/1000) -> #VALUE! | DI34: =#REF!/(DI20/1000) -> #REF!
C35: RBDPO Brand Consume | D35: =SUM(D36:D37) -> 15000 | E35: Kg | F35: 0 | G35: 0 | H35: 0 | R35: =R36+R37 -> 0 | T35: =T36+T37 -> 0 | U35: =U36+U37 -> 30647000 | V35: =(T35/U35)*100 -> 0 | PF35: =SUM(PF28:PF33) -> 40.24716
C36: OLEIN IV 57 ( Retail ) | D36: 12000 | E36: Kg | F36: 0 | G36: 0 | H36: 0 | R36: ='[3]Desember 24'!AL31 -> 0 | T36: =SUM(F36:Q36) -> 0 | U36: 23002000 | V36: =T36/U36*100 -> 0
C37: STEARIN | D37: 3000 | E37: Kg | F37: 0 | H37: 0 | R37: ='[3]Desember 24'!AL32 -> 0 | T37: =SUM(F37:Q37) -> 0 | U37: 7645000 | V37: =T37/U37*100 -> 0
C38: Fractionation OLEIN IV 58 ( BULK ) | T38: Olein IV 58 | U38: Olein IV 58 | V38: Olein IV 58
C39: RBDPO Consume | E39: Kg | F39: 0 | G39: 13585776 | H39: 0 | L39: ='JULI 2025'!AM45 -> 19454128 | R39: =R40+R41 -> 0 | T39: =T40+T41 -> 33039904 | U39: =U40+U41 -> 249961000 | V39: =T39/U39*100 -> 13.218024
C40: OLEIN IV 58 ( Bulk ) | D40: 205714 | E40: Kg | F40: 0 | G40: 10107561 | H40: 0 | L40: ='JULI 2025'!AM46 -> 13698839 | R40: ='[3]Desember 24'!AL35 -> 0 | T40: =SUM(F40:Q40) -> 23806400 | U40: 175000000 | V40: =T40/U40*100 -> 13.603657
C41: STEARIN | D41: 61714 | E41: Kg | F41: 0 | G41: 3478215 | H41: 0 | L41: ='JULI 2025'!AM47 -> 5755289 | R41: ='[3]Desember 24'!AL36 -> 0 | T41: =SUM(F41:Q41) -> 9233504 | U41: 74961000 | V41: =T41/U41*100 -> 12.317744
C42: Fractionation OLEIN IV 58 ( Retail ) | H42: 0
C43: CPO Consume | E43: Kg
C44: RBDPO Consume | E44: Kg
C45: OLEIN IV 58 | E45: Kg
C46: STEARIN | E46: Kg
C47: Fractionation OLEIN IV 60 | G47: 0 | T47: Olein IV 60 | U47: Olein IV 60 | V47: Olein IV 60
C48: CPO Consume | E48: Kg | F48: 0 | G48: 0 | H48: 0 | T48: =SUM(F48:Q48) -> 0 | U48: =U49/U57% -> 25913273 | V48: =T48/U48*100 -> 0
C49: RBDPO Brand Consume | E49: Kg | F49: 0 | G49: 140448 | H49: 0 | T49: =T51+T52 -> 140448 | U49: =U51+U52 -> 24558000 | V49: =T49/U49*100 -> 0.57190325 | DG49: 2136
C50: OLEIN IV 60 Bulk | E50: Kg | F50: 0 | G50: 0 | H50: 0 | T50: =SUM(F50:Q50) -> 0 | U50: =SUM(F50:R50) -> 0 | V50: =SUM(H50:T50) -> 0
C51: OLEIN IV 60 Salvaco | D51: 25000 | E51: Kg | F51: 0 | G51: 87368 | H51: 0 | T51: =SUM(F51:Q51) -> 87368 | U51: 14736000 | V51: =T51/U51*100 -> 0.59288817 | DG51: 1796
C52: SOFT STEARIN | D52: 10000 | E52: Kg | F52: 0 | G52: 53080 | H52: 0 | T52: =SUM(F52:Q52) -> 53080 | U52: 9822000 | V52: =T52/U52*100 -> 0.54041947 | DG52: =DG49/DG51*100 -> 118.93096
C53: Ratio Run RBDPO | F53: 0 | G53: 0 | H53: 0 | T53: =+AVERAGE(F53:Q53) -> 0
C54: Utilitas RBDPO | F54: =(F49+F39+F35+F31+F27)/F55*100 -> #DIV/0! | G54: 0 | H54: 0 | T54: =+AVERAGE(F54:Q54) -> #DIV/0!
C55: Budget RBDPO | F55: 0 | G55: 0 | H55: 0 | T55: =SUM(F55:Q55) -> 0
C56: YIELD | H56: 0 | T56: Yield | U56: Yield | V56: Yield | OP56: 678
C57: RBDPO | D57: 94.2 | E57: % | F57: 0 | G57: 94.619052 | H57: 93.893739 | K57: 94.787564 | L57: ='JULI 2025'!AM60 -> 94.917042 | T57: =(T19/(T11))*100 -> 94.743365 | U57: =(U19/(U11))*100 -> 94.769967 | OP57: 420 | OR57: =OP57/OP56*100 -> 61.946903
C58: PFAD | D58: 5 | E58: % | F58: 0 | G58: 4.6286724 | H58: 4.4985582 | K58: 4.8633016 | L58: ='JULI 2025'!AM61 -> 4.3020988 | T58: =(T20/(T11))*100 -> 4.5236228 | U58: =(U20/(U11))*100 -> 4.5147541 | OP58: =OP56-OP57 -> 258 | OR58: =OP58/OP56*100 -> 38.053097
C59: Olein IV 56 | D59: 82 | E59: % | F59: 0 | G59: 80.495695 | H59: 81.824 | K59: 80.514103 | L59: ='JULI 2025'!AM62 -> 80.387608 | T59: =(T27/T26)*100 -> 80.683683 | U59: =(U27/U26)*100 -> 82.036628
C60: Stearin | D60: 18 | E60: % | F60: 0 | G60: 19.504305 | H60: 18.176 | K60: 19.485897 | L60: ='JULI 2025'!AM63 -> 19.612392 | T60: =(T28/T26)*100 -> 19.316317 | U60: =(U28/U26)*100 -> 17.963372
C61: Olein IV 57 ( Bulk ) | D61: 75 | E61: % | F61: 0 | G61: 0 | H61: 0 | T61: =(T31/T30)*100 -> #DIV/0! | U61: 75
C62: Stearin | D62: 25 | E62: % | F62: 0 | G62: 0 | H62: 0 | T62: =(T32/T30)*100 -> #DIV/0! | U62: 25
C63: Olein IV 57 ( Retail ) | D63: 75 | E63: % | F63: #DIV/0! | G63: 0 | H63: 0 | T63: =(T36/T35)*100 -> #DIV/0! | U63: 75
C64: Stearin | D64: 25 | E64: % | F64: #DIV/0! | G64: 0 | H64: 0 | T64: =(T37/T35)*100 -> #DIV/0! | U64: 25 | FN64: 95.03
C65: Olein IV 58 ( Bulk ) | D65: 70 | E65: % | F65: 0 | G65: 74.398113 | H65: 0 | L65: ='JULI 2025'!AM68 -> 70.416104 | T65: =(T40/T39)*100 -> 72.053478 | U65: 70
C66: Stearin | D66: 30 | E66: % | F66: 0 | G66: 25.601887 | H66: 0 | L66: ='JULI 2025'!AM69 -> 29.583896 | T66: =(T41/T39)*100 -> 27.946522 | U66: 30
C67: Olein IV 60 | D67: 60 | E67: % | F67: 0 | G67: 62.206653 | H67: 0 | T67: =(T51/T49)*100 -> 62.206653 | U67: =U51/U49*100 -> 60.004886 | FN67: 4.23 | OR67: =OR68/94.2% -> 1307.8556 | OS67: MT CPO
C68: Soft Stearin | D68: 40 | E68: % | F68: 0 | G68: 37.793347 | H68: 0 | T68: =(T52/T49)*100 -> 37.793347 | U68: =U52/U49*100 -> 39.995114 | FN68: =100-FN64-FN67 -> 0.74 | OR68: =22*56 -> 1232 | OS68: MT RBDPO Brand
B69: 3 | C69: CHEMICAL CONSUMABLE | H69: 0 | T69: Chemical | U69: Chemical | V69: Chemical | OR69: =16.5*OR67 -> 21579.618
C70: Bleaching Earth (BE) to Poram Spec | D70: 9 | E70: Kg | F70: 0 | G70: 134694 | H70: 52420 | K70: 153073 | L70: ='JULI 2025'!AM75 -> 271394.2 | T70: =SUM(F70:Q70) -> 611581.2 | U70: 2767753 | V70: =T70/U70*100 -> 22.096668
E71: % | F71: 0 | G71: 0.8104536 | H71: 0.94265062 | K71: 0.85932405 | L71: ='JULI 2025'!AM76 -> 7.8514122 | T71: =T70/(T11)*100 -> 0.82025403 | U71: 0.8 | V71: 0 | AX71: =T71*10 -> 8.2025403 | FN71: =#REF!*10 -> #REF! | OR71: =OR67+(T48/1000) -> 1307.8556 | OS71: Total CPO Brand
C72: Bleaching Earth (BE) to Branded Spec | D72: 16 | E72: Kg | F72: 0 | G72: 0 | H72: 0 | T72: =SUM(F72:Q72) -> 0 | U72: 1357284 | V72: =T72/U72*100 -> 0 | OR72: =OR69+T72 -> 21579.618 | OS72: Total BE Brand
E73: % | F73: 0 | G73: 0 | H73: 0 | T73: =T72/(T13)*100 -> #DIV/0! | U73: 1.8 | V73: 0 | AX73: =T73*10 -> #DIV/0! | OR73: =OR72/OR71 -> 16.5 | OS73: Kg/MT CPO
C74: Phosporic Acid (PA) | D74: 0.6 | E74: Kg | F74: 0 | G74: 8196.91 | H74: 2623.92 | K74: 8793.24 | L74: ='JULI 2025'!AM83 -> 16506.73 | T74: =SUM(F74:Q74) -> 36120.8 | U74: 252824 | V74: =SUM(H74:T74) -> 64044.69 | OR74: 16 | OS74: Budget (Kg/MT)
E75: % | F75: 0 | G75: 0.049320795 | H75: 0.47185041 | K75: 0.49363654 | L75: ='JULI 2025'!AM84 -> 0.47753836 | T75: =T74/(T11+71450)*100 -> 0.048398915 | U75: 0.06 | V75: =V74/(V11+71450)*100 -> 89.635453 | AX75: =T75*10 -> 0.48398915 | FN75: =Q75*10 -> 0 | OR75: =OR73-OR74 -> 0.5 | OS75: Over (Kg/MT)
B76: 4 | C76: Oil Losses | D76: 0.8 | E76: % | F76: 0 | G76: -0.75227524 | H76: -1.607703 | K76: -0.3491346 | L76: ='JULI 2025'!AM85 -> -0.78085902 | T76: =((SUM(T19:T20))-(SUM(T11)))/(SUM(T11))*100 -> -0.73301258 | U76: =((SUM(U19:U20))-(SUM(U11)))/(SUM(U11))*100 -> -0.71527906 | V76: =T76/U76*100 -> 102.47925
C77: % Oil Content | D77: 22 | E77: % | F77: 0 | G77: 19.381667 | H77: 26.4475 | K77: 21.014 | L77: ='JULI 2025'!AM87 -> 21.640833 | T77: =AVERAGE(G77:K77) -> 22.281056 | U77: 22 | V77: =AVERAGE(H77:T77) -> 22.845847
C78: Spent Bleaching Earth | E78: Kg | F78: 0 | G78: 136702.15 | H78: 66283.78 | K78: 156289.68 | L78: ='JULI 2025'!AM88 -> 273743.48 | T78: =SUM(T70,T72)+(T77%*SUM(T70,T72)) -> 747847.95 | U78: 7811279 | V78: =SUM(V70,V72)+(V77%*SUM(V70,V72)) -> 27.144839 | GA78: =X78+400 -> 400
B79: 5 | C79: PACKAGING (Brand Salvaco) | G79: #REF! | T79: Packaging | U79: Packaging | V79: Packaging | FX79: 17292 | OY79: =#REF!-FX79 -> #REF!
C80: Olein IV 60 Received | E80: Kg | F80: ='[3]Januari 24'!AL68 -> 845858 | G80: #REF! | H80: 0 | T80: =SUM(F80:R80) -> #REF! | U80: =SUM(G80:S80) -> #REF! | V80: =(T80/U80)*100 -> #REF!
C81: Olein IV 60 Consume | E81: Kg | F81: ='[3]Januari 24'!AL69 -> 399021.28 | G81: #REF! | H81: 0 | T81: =SUM(T82:T84) -> #REF! | U81: =SUM(U82:U84) -> 32269046 | V81: =(T81/U81)*100 -> #REF! | AFR81: Kg | AFS81: Olein Filling to Packaging
C82: - finished product | E82: Kg | F82: =SUM(F86:F87)*10.86 -> 400256.16 | G82: #REF! | H82: 0 | T82: =SUM(T86:T87)*10.86 -> #REF! | U82: =SUM(U86:U87)*10.86 -> 32269046 | V82: =(T82/U82)*100 -> #REF! | FX82: =#REF!/1000 -> #REF! | OY82: 4696 | OZ82: =FX82/OY82*100 -> #REF!
C83: - sample | E83: Kg | F83: =F81-F82 -> -1234.88 | G83: 0 | H83: 0 | T83: =SUM(F83:R83) -> -1234.88 | U83: =SUM(G83:S83) -> 0 | V83: =(T83/U83)*100 -> #DIV/0! | FX83: =#REF!/1000 -> #REF! | OY83: 565 | OZ83: =FX83/OY83*100 -> #REF!
C84: - remelt, flushing, downgrade | E84: Kg | F84: ='[3]Januari 24'!AL72 -> 0 | H84: 0 | T84: =SUM(F84:R84) -> 0 | U84: =SUM(G84:S84) -> 0
C85: Carton | G85: #REF! | T85: Carton | U85: Carton | V85: Carton
C86: Salvaco 1 Liter | E86: Box | F86: ='[3]Januari 24'!AL74 -> 17197 | G86: #REF! | H86: 0 | T86: =SUM(F86:R86) -> #REF! | U86: 1254577 | V86: =(T86/U86)*100 -> #REF!
C87: Salvaco 2 Liter | E87: Box | F87: ='[3]Januari 24'!AL75 -> 19659 | H87: 0 | T87: =SUM(F87:R87) -> 19659 | U87: 1716790 | V87: =(T87/U87)*100 -> 1.1451022
C88: Pouch | G88: #REF! | T88: Pouch | U88: Pouch | V88: Pouch
C89: Salvaco 1 Liter | E89: Pouch | F89: =F86*12 -> 206364 | G89: #REF! | H89: 0 | T89: =T86*12 -> #REF! | U89: =U86*12 -> 15054924 | V89: =(T89/U89)*100 -> #REF!
C90: Salvaco 2 Liter | E90: Pouch | F90: =F87*6 -> 117954 | G90: #REF! | H90: 0 | T90: =T87*6 -> 117954 | U90: =U87*6 -> 10300740 | V90: =(T90/U90)*100 -> 1.1451022
C91: Consumable Vit. A | E91: gram | F91: =(F81*45)/1700 -> 10562.328 | G91: #REF! | H91: 0 | T91: =SUM(F91:R91) -> #REF! | U91: =(U81*45)/1700 -> 854180.62 | V91: =(T91/U91)*100 -> #REF!
C92: Consumable Packing Tape | E92: Roll | F92: =SUM(F86:F87)/500 -> 73.712 | H92: 0 | T92: =SUM(F92:R92) -> 73.712 | U92: =SUM(U86:U87)/500 -> 5942.734 | V92: =(T92/U92)*100 -> 1.2403719
C93: REJECT MATERIAL QTY | T93: Loss Material | U93: Loss Material | V93: Loss Material
C94: Carton | G94: #REF! | T94: Carton | U94: Carton | V94: Carton
C95: Salvaco 1 Liter | E95: Box | F95: ='[3]Januari 24'!AL74 -> 17197 | G95: #REF! | H95: 0 | T95: =SUM(F95:R95) -> #REF! | U95: =SUM(G95:S95) -> #REF! | V95: =SUM(H95:T95) -> #REF!
C96: Salvaco 2 Liter | E96: Box | F96: ='[3]Januari 24'!AL75 -> 19659 | H96: 0 | T96: =SUM(F96:R96) -> 19659 | U96: =SUM(G96:S96) -> 0 | V96: =SUM(H96:T96) -> 19659
C97: Pouch | G97: #REF! | T97: Pouch | U97: Pouch | V97: Pouch
C98: Salvaco 1 Liter | E98: Pouch | F98: =F95*12 -> 206364 | G98: #REF! | H98: 0 | T98: =SUM(F98:R98) -> #REF! | U98: =SUM(G98:S98) -> #REF! | V98: =SUM(H98:T98) -> #REF!
C99: Salvaco 2 Liter | E99: Pouch | F99: =F96*6 -> 117954 | H99: 0 | T99: =SUM(F99:R99) -> 117954 | U99: =SUM(G99:S99) -> 0 | V99: =SUM(H99:T99) -> 117954
C100: REJECT MATERIAL (%) | T100: Loss Material | U100: Loss Material | V100: Loss Material
C101: Carton | G101: #REF! | T101: Carton | U101: Carton | V101: Carton
...

Sheet Prod
B2: MONTHLY PRODUCTION REPORT
B3: PT. INDUSTRI NABATI LESTARI
B4: Periode 01 s/d 31 Juli 2025
B5: NO | C5: Item | D5: Unit | E5: Juli | H5: Remaks
E6: Budget | F6: Actual | G6: Percentage Act.
B7: 1. | C7: PRODUCTION
C8: Refinery Plant
C9: Running Days | D9: Days | E9: 25 | F9: ='JULI 2025'!$AM$6 -> 25 | G9: =(F9/E9) -> 1 | H9: Tercapai
C10: Utilisasi Kapasitas Olah | D10: Kg | F10: =F9*2500 -> 62500 | G10: =(F12/F10)/1000 -> 0.55306066
C11: CPO Incoming | D11: Kg | F11: ='JULI 2025'!AM7 -> 29011628
C12: Total CPO Consume | D12: Kg | E12: 58971 | F12: =F13+F14 -> 34566291 | G12: =(F12/E12)/1000 -> 0.58615745 | H12: Tidak Tercapai
C13: CPO Consume Poram | F13: ='JULI 2025'!$AM$11 -> 34566291
C14: CPO Consume Brand | F14: ='JULI 2025'!$AM$12 -> 0
C15: - Avg. FFA | D15: % | E15: 5 | F15: ='JULI 2025'!$AM$13 -> 3.952 | G15: =(F15/E15) -> 0.7904
C16: - Avg. Moist & Impurities | D16: % | E16: 0.5 | F16: ='JULI 2025'!$AM$14 -> 0.43926667 | G16: =(F16/E16) -> 0.87853333
C17: - Avg. DOBI | D17: % | E17: 2.2 | F17: ='JULI 2025'!$O$15 -> 0 | G17: =(F17/E17) -> 0
C18: Product
C19: RBDPO | D19: Kg | E19: 55728 | F19: ='JULI 2025'!$AM$20 -> 32809301 | G19: =(F19/E19)/1000 -> 0.58873997
C20: PFAD | D20: Kg | E20: 2831 | F20: ='JULI 2025'!$AM$21 -> 1487076 | G20: =(F20/E20)/1000 -> 0.52528294
C22: Fraksinasi Plant
C23: Total Proses RBDPO | D23: Kg | E23: ='JULI 2025'!E29 -> 35501000 | F23: ='JULI 2025'!$AM$29 -> 31763356 | G23: =(F23/E23) -> 0.89471722 | H23: Tidak Tercapai
C24: Total Olah RBDPO ( Feed ) | D24: Kg | E24: 35501000 | F24: ='JULI 2025'!$AM$25 -> 32775474 | G24: =(F24/E24) -> 0.92322678 | H24: Tidak Tercapai
C25: Fractionation Olein IV 56
C26: RBDPO Consume | D26: Kg | E26: =E27+E28 -> 25639000 | F26: =F27+F28 -> 12309228 | G26: =(F26/E26) -> 0.48009782 | H26: Tidak Tercapai
C27: Olein IV 56 | D27: Kg | E27: ='JULI 2025'!E33 -> 25000000 | F27: ='JULI 2025'!$AM$33 -> 9895094 | G27: =(F27/E27) -> 0.39580376 | H27: Tidak Tercapai
C28: Stearin | D28: Kg | E28: ='JULI 2025'!E34 -> 639000 | F28: ='JULI 2025'!$AM$34 -> 2414134 | G28: =(F28/E28) -> 3.7779875 | H28: Tercapai
C29: Fractionation Olein IV 57 ( Bulk )
C30: RBDPO Consume | D30: Kg | E30: 0
C31: Olein IV 57 | D31: Kg | E31: 0 | F31: 0 | G31: 0
C32: Stearin | D32: Kg | E32: 0
C33: Fractionation Olein IV 58 ( bulk )
C34: CPO | D34: Kg | E34: 1812101.9 | G34: =(F34/E34)*100 -> 0
C35: RBDPO Consume | D35: Kg | E35: =E36+E37 -> 12514300 | F35: =F36+F37 -> 19454128 | G35: =(F35/E35) -> 1.5545518 | H35: Tercapai
C36: Olein IV 58 | D36: Kg | E36: ='JULI 2025'!E46 -> 12000000 | F36: ='JULI 2025'!AM46 -> 13698839 | G36: =(F36/E36) -> 1.1415699 | H36: Tercapai
C37: Stearin | D37: Kg | E37: ='JULI 2025'!E47 -> 514300 | F37: ='JULI 2025'!AM47 -> 5755289 | G37: =(F37/E37) -> 11.190529 | H37: Tercapai
C38: Fractionation Olein IV 58
C39: RBDPO Consume | D39: Kg | E39: 21429000 | F39: =F40+F41 -> 19454128 | G39: =(F39/E39)*100 -> 90.784115 | H39: Tidak Tercapai
C40: Olein IV 58 | D40: Kg | E40: 15000000 | F40: ='JULI 2025'!$AM$46 -> 13698839 | G40: =(F40/E40)*100 -> 91.325593 | H40: Tidak Tercapai
C41: Stearin | D41: Kg | E41: 6429000 | F41: ='JULI 2025'!$AM$47 -> 5755289 | G41: =(F41/E41)*100 -> 89.52075 | H41: Tidak Tercapai
C42: Fractionation Olein IV 60
C43: CPO | E43: 2234607.2 | F43: 0 | G43: =(F43/E43)*100 -> 0
C44: RBDPO Consume | D44: Kg | E44: =E45+E46 -> 1333300 | F44: 0 | G44: =(F44/E44)*100 -> 0 | H44: Tidak Tercapai
C45: Olein IV 60 Salvaco | D45: Kg | E45: ='JULI 2025'!E56 -> 1250000 | F45: ='JULI 2025'!AM56 -> 0 | G45: =(F45/E45)*100 -> 0 | H45: Tidak Tercapai
C46: Soft Stearin | D46: Kg | E46: ='JULI 2025'!E57 -> 83300 | F46: ='JULI 2025'!AM57 -> 0 | G46: =(F46/E46)*100 -> 0 | H46: Tidak Tercapai
B47: 2. | C47: % YIELD
C48: RBDPO | D48: % | E48: 94.77 | F48: =(F19/F12)*100 -> 94.917042 | G48: =(F48/E48) -> 1.0015516 | H48: Tercapai
C49: PFAD | D49: % | E49: 4.5 | F49: =(F20/(F12))*100 -> 4.3020988 | G49: =(F49/E49) -> 0.95602196 | H49: Tidak Tercapai
C50: Olein IV 56 | D50: % | E50: 82 | F50: =F27/(F27+F28)*100 -> 80.387608 | G50: =(F50/E50) -> 0.98033669 | H50: Tidak Tercapai
C51: Stearin | D51: % | E51: 18 | F51: =(F28/F26)*100 -> 19.612392 | G51: =(F51/E51) -> 1.0895773 | H51: Tercapai
C52: Olein IV 57 ( Bulk ) | D52: % | E52: 75 | F52: 0 | G52: =(F52/E52)*100 -> 0
C53: Stearin | D53: % | E53: 25 | F53: 0 | G53: =(F53/E53)*100 -> 0
C54: Olein IV 57 ( Retail ) | D54: % | E54: 75 | F54: 0 | G54: =(F54/E54)*100 -> 0
C55: Stearin | D55: % | E55: 25 | F55: 0 | G55: =(F55/E55)*100 -> 0
C56: Olein IV 58 ( Bulk ) | D56: % | E56: 70 | F56: =F40/(F40+F41)*100 -> 70.416104 | G56: =(F56/E56) -> 1.0059443 | H56: Tercapai
C57: Stearin | D57: % | E57: 30 | F57: =(F41/F39)*100 -> 29.583896 | G57: =(F57/E57) -> 0.98612987 | H57: Tidak Tercapai
C58: Olein IV 60 | D58: % | E58: 60 | F58: 0 | G58: =(F58/E58)*100 -> 0
C59: Soft Stearin | D59: % | E59: 40 | F59: 0 | G59: =(F59/E59)*100 -> 0
B60: 3. | C60: CHEMICAL CONSUMABLE
C61: Bleaching Earth to Poram Spec | D61: Kg | E61: 530100 | F61: ='JULI 2025'!$AM$75 -> 271394.2 | G61: =(F61/E61) -> 0.51196793
D62: Kg/MT | E62: ='JULI 2025'!E75 -> 9 | F62: =(F61/F13)*1000 -> 7.8514122 | G62: =(F62/E62) -> 0.87237914 | H62: Tercapai
C63: Bleaching Earth to Branded Spec | D63: Kg | E63: 106326 | F63: ='JULI 2025'!AM12 -> 0 | G63: =(F63/E63) -> 0
D64: Kg/MT | E64: 1060 | G64: =(F64/E64) -> 0
C65: Phosporic Acid | D65: Kg | E65: 35340 | F65: ='JULI 2025'!$AM$83 -> 16506.73 | G65: =(F65/E65) -> 0.46708347
D66: Kg/MT | E66: 0.6 | F66: =(F65/F12)*1000 -> 0.47753836 | G66: =(F66/E66) -> 0.79589727 | H66: Tercapai
B67: 4. | C67: OIL LOSSES
C68: (Loss)/Gain | D68: % | E68: -0.8 | F68: -0.78085902 | G68: =(F68/E68)*100 -> 97.607377 | H68: Tercapai
C69: % Oil Content | D69: % | E69: 22 | F69: ='JULI 2025'!$AM$87 -> 21.640833 | G69: =(F69/E69)*100 -> 98.367424 | H69: Tercapai
C70: Spent Bleaching Earth | D70: Kg | E70: 413199.36 | F70: ='JULI 2025'!$AM$88 -> 273743.48 | G70: =(F70/E70)*100 -> 66.249734
B71: NB :
B72: - BE Achieve dengan pemakaian consume Bleaching Earth 7,9 Kg/MT
B73: - Untuk hari olah Produksi adalah 25 Hari, menyesuaikan dengan jadwal shipment Adesa 23 & 1,2 sebanyak 15.900 MT (IV 58)
B74: dan Olam 12.000 MT (IV 56)
B75: - Total CPO Proses sebesar : 34.566 MT dengan total CPO Incoming ke INL sebanyak : 29.011 MT
B76: - Rata rata incoming CPO perhari 1.160 MT
B77: - IV 56 Yield tidak tercapai di karenakan supply minyak ke Packaging menggunakan IV 57
A79: Prepared by, | D79: Checked by, | H79: Approved by,
A83: Bany Subana | D83: Reza P. Panjaitan | F83: Sudarianto | H83: Eben Jaya Ginting
A84: Admin Operation | D84: Supervisor Produksi | F84: Jr. Manager Produksi | H84: Manager Plant

Sheet Utility
D2: UTILITY (GAS, STEAM, WATER & POWER) REPORT
D3: PT. INDUSTRI NABATI LESTARI
D5: Periode 01 s/d 31 Juli 2025
D6: No | E6: Item | F6: Norma | G6: UoM | H6: Juli | K6: Consume CPO ( MT ) | L6: Remaks
H7: Budget | I7: Actual | J7: Percentage Act.
E9: Total Feed Raw Material CPO | K9: 34566291
E10: Total Proses RBDPO | K10: ='JULI 2025'!AM29 -> 31763356
D11: 1. | E11: GAS CONSUMPTION
E12: Incoming *base on INL | G12: mmbtu | I12: ='JULI 2025'!$AM$241 -> 24283.514
E13: Incoming *base on Pertagas | F13: 1460.001 | G13: mmbtu | H13: 26051.47 | I13: ='JULI 2025'!$AM$239 -> 24588.162 | J13: =I13/H13 -> 0.94383013 | K13: =I13/K9*1000 -> 0.71133355
E14: Distribution to
E15: HP Boiler Refinery | G15: mmbtu | H15: 5907.73 | I15: ='JULI 2025'!AM244 -> 4834.8953 | J15: =I15/H15 -> 0.81840154 | K15: =I15/K9*1000 -> 0.13987313
E16: MP Boiler | G16: mmbtu | H16: 20143.74 | I16: ='JULI 2025'!AM246 -> 19753.267 | J16: =I16/H16 -> 0.98061567 | K16: =I16/K9*1000 -> 0.57146042
E17: Total | G17: mmbtu | H17: =H15+H16 -> 26051.47 | I17: =I16+I15 -> 24588.162 | J17: =I17/H17 -> 0.94383013 | K17: =SUM(K15+K16) -> 0.71133355
D18: 2. | E18: STEAM CONSUMPTION
E19: Incoming | G19: Kg | H19: 11424000 | I19: ='JULI 2025'!$AM$249 -> 3165.707 | J19: =I19/H19*100 -> 0.027711021 | K19: =I19/K9*1000000 -> 91.583647
E20: Distribution to
E21: Refinery | F21: < 28 | G21: Kg | H21: 3420000 | I21: ='JULI 2025'!$AM$251 -> 1611.59 | J21: =I21/H21*100 -> 0.047122515 | K21: =I21/$K$9*1000000 -> 46.623168
E22: Fractionation | F22: < 45 | G22: Kg | H22: 2318000 | I22: ='JULI 2025'!$AM$253 -> 1046.717 | J22: =I22/H22*100 -> 0.04515604 | K22: =I22/$K$10*1000000 -> 32.953602
E23: Others | F23: 106000 | G23: Kg | H23: 5686000 | I23: ='JULI 2025'!AM255 -> 507.4 | J23: =I23/H23*100 -> 0.0089236722 | K23: =I23/$K$9*1000000 -> 14.679041
E24: Total | G24: Kg | H24: =SUM(H21:H23) -> 11424000 | I24: =SUM(I21:I23) -> 3165.707 | J24: =I24/H24*100 -> 0.027711021 | K24: =I24/$K$9*1000000 -> 91.583647
D25: 3. | E25: WATER CONSUMPTION
E26: Incoming Raw Water | G26: m3 | H26: =SUM(H30:H32) -> 41253 | I26: =SUM(I27:$I$28) -> 19684 | J26: =I26/H26 -> 0.47715318 | K26: =I26/$K$9*1000 -> 0.56945653
E27: - Suplay To RO Product | I27: ='JULI 2025'!$AM$265 -> 8302.2 | K27: =I27/$K$9*1000 -> 0.24018197
E28: - Suplay To Proses dan Sanitary | I28: =SUM(I30:$I$32) -> 11381.8 | K28: =I28/$K$9*1000 -> 0.32927455
E29: Rincian Outgoing Proses | K29: =I29/$K$9 -> 0
E30: Softener Product (to Refinery) | F30: < 0,04 | G30: m3 | H30: 11745 | I30: ='JULI 2025'!$AM$261 -> 4470 | J30: =I30/H30 -> 0.38058748 | K30: =I30/$K$9*1000 -> 0.12931674
E31: Softener Product (to Fractionation) | F31: < 0,13 | G31: m3 | H31: 20895 | I31: ='JULI 2025'!$AM$263 -> 2046 | J31: =I31/H31 -> 0.097918162 | K31: =I31/$K$10*1000 -> 0.064413848
E32: Others | G32: m3 | H32: 8613 | I32: ='JULI 2025'!$AM$266 -> 4865.8 | J32: =I32/H32 -> 0.56493672 | K32: =I32/$K$9*1000 -> 0.1407672
E33: Total | G33: m3 | H33: =H26 -> 41253 | I33: =SUM(I27:I28) -> 19684 | J33: =I33/H33 -> 0.47715318 | K33: =I33/$K$9*1000 -> 0.56945653
D34: 4 | E34: POWER CONSUMPTION
E35: Incoming
E36: PLN *base on BA Kinra | G36: Kwh | H36: =H38+H39+H41+H42 -> 704938 | I36: ='JULI 2025'!$AM$271 -> 43.224 | J36: =I36/H36*1000 -> 0.061316031 | K36: =I36/$K$9*100000 -> 0.12504668
E37: Outgoing | K37: =I37/$K$9 -> 0
E38: - Physical Refinery Plant | F38: 4.4 | G38: Kwh | H38: 162973 | I38: ='JULI 2025'!$AM$276 -> 225833 | J38: =I38/H38/10 -> 0.13857081 | K38: =I38/$K$9*1000 -> 6.5333304
E39: - Refinery - Cooling Water System | F39: 7.3 | G39: Kwh | H39: 100660 | I39: ='JULI 2025'!$AM$274 -> 319944.72 | J39: =I39/H39/10 -> 0.31784693 | K39: =I39/$K$9*1000 -> 9.2559748
E40: - Refinery - Utilities | F40: 11.81 | G40: Kwh | H40: 0 | I40: ='JULI 2025'!$AM$284 -> 0 | J40: =I40/H40/10 -> #DIV/0! | K40: =I40/$K$9*1000 -> 0
E41: - Dry Fractionation Plant | F41: 4.5 | G41: Kwh | H41: 287808 | I41: ='JULI 2025'!$AM$281 -> 176329.8 | J41: =I41/H41/10 -> 0.061266469 | K41: =I41/$K$10*1000 -> 5.5513592
E42: - Dry Fractionation CW System | F42: 4.1 | G42: Kwh | H42: 153497 | I42: ='JULI 2025'!$AM$279 -> 315504 | J42: =I42/H42/10 -> 0.20554408 | K42: =I42/$K$10*1000 -> 9.9329554
E43: - Lighting - Refinery & Dry Fractionation | F43: 241.12 | G43: Kwh | H43: 4581 | I43: ='JULI 2025'!$AM$285 -> 0 | J43: =I43/H43 -> 0 | K43: =I43/$K$9*1000 -> 0
E51: Prepared by, | F51: Checked by, | K51: Approved by,
E55: Bany Subana | F55: Reza P. Panjaitan | I55: Sudarianto | K55: Eben Jaya Ginting
E56: Admin Operation | F56: Supervisor Produksi | I56: Jr. Manager Produksi | K56: Manager Plant

Sheet Qty cons analysis
D2: Quantity Utility Consumption Analysis (based on Guarantee Utility Consumption)
D3: Refinery & Fractionation Plant
D4: Periode 01 s/d 31 Juli 2025
D5: Consumption | E5: UoM | F5: Budget | G5: Actual | H5: Under (Over) Budget | I5: Explanation Under / Over budget
D6: CPO Consume | E6: Kg | F6: ='JULI 2025'!E9 -> 58900000 | G6: ='JULI 2025'!$AM$9 -> 34566291 | H6: =G6/F6 -> 0.58686402
D7: RbdPO Consume | E7: Kg | F7: ='JULI 2025'!E20 -> 55661000 | G7: ='JULI 2025'!$AM$25 -> 32775474 | H7: =G7/F7 -> 0.58884091
D8: TOTAL ACTUAL CONSUMPTION
D9: Refinery
D10: Bleaching Earth to Poram Spec | E10: Kg | F10: 232362 | G10: ='JULI 2025'!$AM$75 -> 271394.2 | H10: =F10-G10 -> -39032.2 | I10: Over Budget
D11: Bleaching Earth to Branded Spec | E11: Kg | F11: 106326 | G11: 0 | H11: 0
D12: Phosporic Acid | E12: Kg | F12: 20971 | G12: ='JULI 2025'!$AM$83 -> 16506.73 | H12: =F12-G12 -> 4464.27 | I12: Under Budget
D13: Gas Consumption (MP Boiler) | E13: mmbtu | F13: 22143.74 | G13: ='JULI 2025'!$AM$246+'JULI 2025'!$AM$245 -> 19753.407 | H13: =F13-G13 -> 2390.3331 | I13: Under Budget
D14: Gas Consumption (HP Boiler) | E14: mmbtu | F14: 3907.73 | G14: ='JULI 2025'!AM244 -> 4834.8953 | H14: =F14-G14 -> -927.16533 | I14: Over Budget
D15: Cooling Water top up to Cooling Tower | E15: m3 | F15: 1521.33 | G15: ='JULI 2025'!$AM$261 -> 4470 | H15: =F15-G15 -> -2948.67 | I15: Over Budget
D16: Steam | E16: Kg | F16: 11424000 | G16: ='JULI 2025'!AM251 -> 1611.59 | H16: =F16-G16 -> 11422388 | I16: Under Budget
D17: Power (Process Plant) | E17: Kwh | F17: 102679 | G17: ='JULI 2025'!AM276 -> 225833 | H17: =F17-G17 -> -123154 | I17: Over Budget
D18: Power (Cooling Tower) | E18: Kwh | F18: 73158 | G18: ='JULI 2025'!AM274 -> 319944.72 | H18: =F18-G18 -> -246786.72 | I18: Over Budget
D19: Fractionation
D20: Cooling Water top up to Cooling Tower | E20: m3 | F20: 2622 | G20: ='JULI 2025'!AM263 -> 2046 | H20: =F20-G20 -> 576 | I20: Under Budget
D21: Steam | E21: Kg | F21: 2318000 | G21: ='JULI 2025'!AM253 -> 1046.717 | H21: =F21-G21 -> 2316953.3 | I21: Under Budget
D22: Power (Process Plant) | E22: Kwh | F22: 109440 | G22: ='JULI 2025'!$AM$281 -> 176329.8 | H22: =F22-G22 -> -66889.8 | I22: Under Budget
D23: Power (Cooling Tower) | E23: Kwh | F23: 28747 | G23: ='JULI 2025'!$AM$279 -> 315504 | H23: =F23-G23 -> -286757 | I23: Over Budget
D24: ACTUAL CONSUMPTION PER MT RAW MATERIAL
D25: Refinery
D26: Bleaching Earth to Poram Spec | E26: Kg/MT | F26: 9 | G26: =(G10/$G$6)*1000 -> 7.8514122 | H26: =F26-G26 -> 1.1485878 | I26: Under Budget
D27: Bleaching Earth to Branded Spec | E27: Kg/MT | F27: 18 | G27: 0 | H27: 0
D28: Phosporic Acid | E28: Kg/MT | F28: 0.6 | G28: =(G12/$G$6)*1000 -> 0.47753836 | H28: =F28-G28 -> 0.12246164 | I28: Under Budget
D29: Gas Consumption (HP Boiler) | E29: Nm3/MT | F29: 4.2 | G29: =(G13/$G$6)*1000 -> 0.57146446 | H29: =F29-G29 -> 3.6285355 | I29: Under Budget
D30: Gas Consumption (HP Boiler) **) | E30: mmbtu/MT | F30: 0.2 | G30: =(G14/$G$6)*1000 -> 0.13987313 | H30: =F30-G30 -> 0.060126869 | I30: Under Budget
D31: Cooling Water top up to Cooling Tower | E31: m3/MT | F31: 0.04 | G31: =(G15/$G$6)*1000 -> 0.12931674 | H31: =F31-G31 -> -0.089316738 | I31: Over Budget
D32: Steam | E32: Kg/MT | F32: 28 | G32: =(G16/$G$6)*1000 -> 0.046623168 | H32: =F32-G32 -> 27.953377 | I32: Under Budget
D33: Power (Process Plant) | E33: Kwh/MT | F33: 4.4 | G33: =(G17/$G$6)*1000 -> 6.5333304 | H33: =F33-G33 -> -2.1333304 | I33: Over Budget
D34: utility section ( chiller ) | E34: Kwh/MT | F34: 7.3 | G34: =(G18/$G$6)*1000 -> 9.2559748 | H34: =F34-G34 -> -1.9559748 | I34: Over Budget
D35: Fractionation
D36: Cooling Water top up to Cooling Tower | E36: m3/MT | F36: 0.13 | G36: =(G20/$G$6)*1000 -> 0.059190614 | H36: =F36-G36 -> 0.070809386 | I36: Under Budget
D37: Steam | E37: Kg/MT | F37: 45 | G37: =(G21/$G$6)*1000 -> 0.030281438 | H37: =F37-G37 -> 44.969719 | I37: Under Budget
D38: Power (Process Plant) | E38: Kwh/MT | F38: 4.1 | G38: =(G22/$G$6)*1000 -> 5.1012068 | H38: =F38-G38 -> -1.0012068 | I38: Over Budget
D39: utility section ( chiller ) | E39: Kwh/MT | F39: 4.5 | G39: =(G23/$G$6)*1000 -> 9.1275052 | H39: =F39-G39 -> -4.6275052 | I39: Over Budget
D42: - BE Achieve dengan pemakaian consume Bleaching Earth 7,9 Kg/MT
D43: * Pemakaian Listrik Fractination Over terkait penggunaan dua unit chiller
D47: Prepared by, | G47: Checked by, | I47: Approved by,
D51: Bany Subana | F51: Reza P. Panjaitan | H51: Sudarianto | I51: Eben Jaya Ginting
D52: Admin Operation | F52: Supervisor Produksi | H52: Jr. Manager Produksi | I52: Manager Plant

Sheet Downtime Ref Juli
D3: DOWN TIME SLOW FLOWRATE PRODUCTION REFINERY
D5: Periode 01/31 Juli 2025
D6: TANGGAL | E6: CAPACITY (Kg) | F6: REMARKS | G6: Down time | K6: Tph
G7: Stop | H7: Slow | I7: %
D8: 1 | E8: 0 | F8: SHUT DOWN | H8: =(2500-(E8/1000))/105 -> 23.809524 | I8: =E8/2500/1000 -> 0 | K8: =(E8/1000)/24 -> 0
D9: 2 | E9: 0 | F9: SHUT DOWN | H9: =(2500-(E9/1000))/105 -> 23.809524 | I9: =E9/2500/1000 -> 0 | K9: =(E9/1000)/24 -> 0
D10: 3 | E10: 0 | F10: SHUT DOWN | H10: =(2500-(E10/1000))/105 -> 23.809524 | I10: =E10/2500/1000 -> 0 | K10: =(E10/1000)/24 -> 0
D11: 4 | E11: 0 | F11: SHUT DOWN | H11: =(2500-(E11/1000))/105 -> 23.809524 | I11: =E11/2500/1000 -> 0 | K11: =(E11/1000)/24 -> 0
D12: 5 | E12: 0 | F12: SHUT DOWN | H12: =(2500-(E12/1000))/105 -> 23.809524 | I12: =E12/2500/1000 -> 0 | K12: =(E12/1000)/24 -> 0
D13: 6 | E13: 0 | F13: SHUT DOWN | H13: =(2500-(E13/1000))/105 -> 23.809524 | I13: =E13/2500/1000 -> 0 | K13: =(E13/1000)/24 -> 0
D14: 7 | E14: 297079 | F14: START UP | H14: =(2500-(E14/1000))/105 -> 20.9802 | I14: =E14/2500/1000 -> 0.1188316 | K14: =(E14/1000)/24 -> 12.378292
D15: 8 | E15: 1517541 | F15: Heating Up | H15: =(2500-(E15/1000))/105 -> 9.3567524 | I15: =E15/2500/1000 -> 0.6070164 | K15: =(E15/1000)/24 -> 63.230875
D16: 9 | E16: 1497201 | F16: Koreksi LC RBDPO | H16: =(2500-(E16/1000))/105 -> 9.5504667 | I16: =E16/2500/1000 -> 0.5988804 | K16: =(E16/1000)/24 -> 62.383375
D17: 10 | E17: 1850610 | F17: Koreksi LC RBDPO | H17: =(2500-(E17/1000))/105 -> 6.1846667 | I17: =E17/2500/1000 -> 0.740244 | K17: =(E17/1000)/24 -> 77.10875
D18: 11 | E18: 1679451 | F18: Koreksi LC RBDPO | H18: =(2500-(E18/1000))/105 -> 7.8147524 | I18: =E18/2500/1000 -> 0.6717804 | K18: =(E18/1000)/24 -> 69.977125
D19: 12 | E19: 1385322 | F19: HPB TRIP | H19: =(2500-(E19/1000))/105 -> 10.615981 | I19: =E19/2500/1000 -> 0.5541288 | K19: =(E19/1000)/24 -> 57.72175
... D38: 31 | E38: 1079850 | F38: CPO Sortage | H38: =(2500-(E38/1000))/105 -> 13.525238 | I38: =E38/2500/1000 -> 0.43194 | K38: =(E38/1000)/24 -> 44.99375
D39: TOTAL | E39: =SUM(E8:E38) -> 34566291 | G39: =SUM(G8:G37) -> 0 | H39: =SUM(H8:H38) -> 408.89247 | K39: =AVERAGE(K8:K38) -> 46.460069
E41: Summary
E42: 1. Slow flow rate due to Space Tank High | G42: 0 | H42: hours
E43: 2. Pulstube Trouble | G43: =SUM(H24,H25) -> 26.411438 | H43: hours
E44: 3. Hold plant due to trip HP boiler & maintenance | G44: =SUM(H19,H27) -> 16.414619 | H44: hours
E45: 4. Penyesuaian incoming CPO | G45: =SUM(H18,H21,H22,H23,H26) -> 35.130152 | H45: hours
E46: 5. Downtime due to Start Up Plant | G46: =SUM(H14) -> 20.9802 | H46: hours
E47: 6. Running Normal Plant | H47: hours
E48: 7. Trouble hoist rusak | G48: =SUM(H20) -> 8.3851333 | H48: hours
E49: 8. Energizing PMG II | G49: 0 | H49: hours
E50: 9. Sirkulasi Quality Ouspek | G50: =SUM(H15,H16,H17) -> 25.091886 | H50: hours
E51: 10, Shut Down | G51: =SUM(H8,H9,H10,H11,H12,H13) -> 142.85714 | H51: hours
E52: 11.HOLD CPO Shortage | G52: =SUM(H28,H29,H30,H31,H32,H33,H34,H35,H36,H37,H38) -> 133.6219 | H52: hours
E53: Total | G53: =SUM(G42:G52) -> 408.89247 | H53: hours
E54: Note : Kapasitas 2500 TPD
C62: Prepared by, | F62: Checked by, | H62: Approved by,
C66: Bany Subana | F66: Reza P. Panjaitan | H66: Sudarianto
C67: Admin. Process | F67: Supervisor Produksi | H67: Jr. Manager Produksi

Sheet Downtime Fract Juli
C2: DOWN TIME SLOW FLOWRATE PRODUCTION FRACTIONATION
C4: Periode 01/31 Juli 2025
C5: TANGGAL | D5: CAPACITY (Kg) | E5: REMARKS | F5: Down time | J5: Tph
F6: Stop | G6: Slow | H6: %
C7: 1 | D7: 0 | E7: SHUT DOWN | G7: =(2500-(D7/1000))/105 -> 23.809524 | H7: =D7/2000/1000 -> 0 | J7: =(D7/1000)/24 -> 0
C8: 2 | D8: 0 | E8: SHUT DOWN | G8: =(2500-(D8/1000))/105 -> 23.809524 | H8: =D8/2000/1000 -> 0 | J8: =(D8/1000)/24 -> 0
C9: 3 | D9: 0 | E9: SHUT DOWN | G9: =(2500-(D9/1000))/105 -> 23.809524 | H9: =D9/2000/1000 -> 0 | J9: =(D9/1000)/24 -> 0
C10: 4 | D10: 0 | E10: SHUT DOWN | G10: =(2500-(D10/1000))/105 -> 23.809524 | H10: =D10/2000/1000 -> 0 | J10: =(D10/1000)/24 -> 0
C11: 5 | D11: 0 | E11: SHUT DOWN | G11: =(2500-(D11/1000))/105 -> 23.809524 | H11: =D11/2000/1000 -> 0 | J11: =(D11/1000)/24 -> 0
C12: 6 | D12: 0 | E12: SHUT DOWN | G12: =(2500-(D12/1000))/105 -> 23.809524 | H12: =D12/2000/1000 -> 0 | J12: =(D12/1000)/24 -> 0
C13: 7 | D13: 207543 | E13: Start Up | G13: =(2500-(D13/1000))/105 -> 21.832924 | H13: =D13/2000/1000 -> 0.1037715 | J13: =(D13/1000)/24 -> 8.647625
C14: 8 | D14: 368700 | E14: Koreksi Quality (LC) IV 56 | G14: =(2500-(D14/1000))/105 -> 20.298095 | H14: =D14/2000/1000 -> 0.18435 | J14: =(D14/1000)/24 -> 15.3625
C15: 9 | D15: 1392984 | E15: Koreksi Quality (LC) IV 56 | G15: =(2500-(D15/1000))/105 -> 10.54301 | H15: =D15/2000/1000 -> 0.696492 | J15: =(D15/1000)/24 -> 58.041
C16: 10 | D16: 1575153 | E16: Koreksi Quality (LC) IV 56 | G16: =(2500-(D16/1000))/105 -> 8.8080667 | H16: =D16/2000/1000 -> 0.7875765 | J16: =(D16/1000)/24 -> 65.631375
C17: 11 | D17: 1878169 | E17: Koreksi Quality (LC) IV 56 | G17: =(2500-(D17/1000))/105 -> 5.9222 | H17: =D17/2000/1000 -> 0.9390845 | J17: =(D17/1000)/24 -> 78.257042
C18: 12 | D18: 1342545 | E18: Koreksi Quality (LC) IV 56 | G18: =(2500-(D18/1000))/105 -> 11.023381 | H18: =D18/2000/1000 -> 0.6712725 | J18: =(D18/1000)/24 -> 55.939375
... C37: 31 | D37: 844552 | E37: Proses IV 58 dan Low Material | G37: =(2500-(D37/1000))/105 -> 15.766171 | H37: =D37/2000/1000 -> 0.422276 | J37: =(D37/1000)/24 -> 35.189667
C38: TOTAL | D38: =SUM(D7:D37) -> 31763356 | F38: =SUM(F7:F36) -> 0 | G38: =SUM(G7:G37) -> 435.58709 | J38: =AVERAGE(J7:J37) -> 42.692683
D40: Summary
D41: 1. Slow flow rate due to Space Tank High | F41: 0 | G41: hours
D42: 2. Slow flow rate due to Olein IV 60 process | F42: 0 | G42: hours
D43: 2. Koreksi Quality (LC) | F43: =SUM(G14,G15,G16,G17,G18,G19,G20) -> 73.761762 | G43: hours
D44: 3. Slow Flow rate terkait material sortage & menyesuaikan | F44: 0 | G44: hours
D45: 4. Downtime due to Start/Stop Up Plant | F45: =SUM(G13) -> 21.832924 | G45: hours
D46: 5. Running Normal Plant | F46: 0 | G46: hours
D47: 7. Stop Plant due to Preventive Maintenance Plant | F47: 0 | G47: hours
D48: 6. Low Material | F48: =SUM(G21,G22,G23,G24,G25,G26,G27,G28,G29,G30,G31,G32,G33,G34,G35,G36,G37) -> 197.13526 | G48: hours
D49: 9. Zero Suplay Gas (Problem Pertagas) | F49: 0 | G49: hours
D50: 7. Slow flow rate due to Olein IV 58 process | F50: 0 | G50: hours
D51: 8. STOP PLANT | F51: =SUM(G7,G8,G9,G10,G11,G12) -> 142.85714 | G51: hours
D52: 12.Slow flow rate due to Olein IV 56 process | F52: 0 | G52: hours
D53: 13. Slow flow rate due to Olein IV 58 process & IV 60 process | F53: 0 | G53: hours
D54: 14. Slow flow rate due to Olein IV 56 process & IV 58 process | F54: 0 | G54: hours
D55: Total | F55: =SUM(F41:F54) -> 435.58709 | G55: hours
D56: Note : Kapasitas 2500 TPD
B64: Prepared by, | E64: Checked by, | G64: Approved by,
B68: Bany Subana | E68: Reza P. Panjaitan | G68: Sudarianto
B69: Admin. Process | E69: Supervisor Produksi | G69: Jr. Manager Produksi

Sheet Steam
B2: Steam Price Package Boiler | G2: Kurs | H2: 16000
B3: Consumable Item | C3: Norma | E3: Consumption, Ton/day | F3: Unit Price | H3: Total Cost
B4: Steam Production (Including Dearator) | C4: =408/24 -> 17 | D4: Ton/jam | E4: ='JULI 2025'!AM249 -> 3165.707 | H4: Rp/day
B5: Gas | C5: 1000 | D5: MMBTU/day | E5: ='JULI 2025'!$AM$240 -> 983.5265 | F5: 11.5 | G5: USD/MMBTU | H5: =E5*H2*F5 -> 1.8096888e+08 | I5: Harga steam tinggi dikarenakan oleh unit price gas yang tinggi, ideal (9.6)
B6: Chemical Treatment
B7: EONALKALOX B1414 | C7: 7.3 | D7: l/day | E7: =C7 -> 7.3 | F7: 25340 | G7: Rp/l | H7: =E7*F7 -> 184982
B8: EONCONDENS B1720 | C8: 2.4 | D8: l/day | E8: =C8 -> 2.4 | F8: 110000 | G8: Rp/l | H8: =E8*F8 -> 264000
B9: EONOXY B8100 | C9: 2.4 | D9: l/day | E9: =C9 -> 2.4 | F9: 20160 | G9: Rp/l | H9: =E9*F9 -> 48384
B10: EONSCALE B5100 | C10: 5.8 | D10: l/day | E10: =C10 -> 5.8 | F10: 31800 | G10: Rp/l | H10: =E10*F10 -> 184440
B11: EONDESCALER B2550 | C11: 1.4 | D11: l/day | E11: =C11 -> 1.4 | F11: 39320 | G11: Rp/l | H11: =E11*F11 -> 55048
B12: Water Demin | C12: =[4]L.Water!C12*83% -> 408.0197 | D12: M3/day | E12: =C12 -> 408.0197 | F12: =[4]L.Water!F12 -> 10162 | G12: Rp/m3 | H12: =E12*F12 -> 4146296.2
B13: Preventive Maintenance | D13: Rp/day | H13: =C13 -> 0
B14: Total Pakage Boiler | H14: =SUM(H5:H13) -> 1.8585203e+08
F15: Unit Price, Rp/Ton | H15: =H14/E4 -> 58707.905
B17: Note :
B18: 1. Harga gas, secara general untuk industri adalah 9,21-9,6 usd/mmBtu
C26: Kurita H-504 18:25

Sheet WWTP
B2: Water Waste Treatment Plant | G2: Kurs | H2: ='SUMMARY HPP '!I9 -> 16000
B3: Consumable Item | C3: Norma | E3: Consumption, M3/day | F3: Unit Price | H3: Total Cost
B4: Waste Water Feed | C4: =200/24 -> 8.3333333 | D4: M3/jam | E4: ='JULI 2025'!AM268 -> 213.48 | H4: Rp/day
B5: biaya transfer ke kawasan | F5: 0 | G5: Rp/m3 | H5: 8700
B6: Chemical Treatment
B7: Sugar | C7: 0 | D7: kg/day | E7: =C7 -> 0 | F7: 24890 | G7: Rp/kg | H7: =E7*F7 -> 0
B8: PE | C8: =E8*C4 -> 0.62305296 | D8: kg/day | E8: 0.074766355 | F8: 65340 | G8: Rp/kg | H8: =E8*F8 -> 4885.2336
B9: PAC | C9: =E9*C4 -> 46.728972 | D9: kg/day | E9: 5.6074766 | F9: 7702 | G9: Rp/kg | H9: =E9*F9 -> 43188.785
B10: Urea | C10: =E10*C4 -> 6.2305296 | D10: kg/day | E10: 0.74766355 | F10: 18634 | G10: Rp/kg | H10: =E10*F10 -> 13931.963
B11: TSP | C11: =E11*C4 -> 1.2461059 | D11: kg/day | E11: 0.14953271 | F11: 44722 | G11: Rp/kg | H11: =E11*F11 -> 6687.4019
B12: HCL | C12: 0 | D12: kg/day | E12: =C12 -> 0 | F12: 5700 | G12: Rp/kg | H12: =E12*F12 -> 0
B13: NaOH | C13: 0 | D13: kg/day | E13: =C13 -> 0 | F13: 15700 | G13: Rp/kg | H13: =E13*F13 -> 0
B14: Power | C14: 2675 | D14: kW/day | E14: =C14 -> 2675 | F14: =[5]UP.E!C28 -> 1550 | G14: Rp/kW | H14: =E14*F14 -> 4146250
B15: Preventive Maintenance | D15: Rp/day | H15: =E15*F15 -> 0
H16: =IFERROR(SUM(H5:H15),"") -> 4223643.4
F17: Unit Price, Rp/M3 | H17: =H16/E4 -> 19784.726
C29: Kurita H-504 18:25

Sheet WTP
B2: Water Treatment Plant | G2: Kurs | H2: 16000
B3: Consumable Item | C3: Norma | E3: Consumption, M3/day | F3: Unit Price | H3: Total Cost
B4: Water Treatment Plant | C4: =1000/24 -> 41.666667 | D4: M3/jam | E4: ='JULI 2025'!AM259 -> 19684 | H4: Rp/day
B5: Chemical | F5: 8700 | G5: Rp/m3 | H5: =F5*E4 -> 171250800
B6: anti scalant | C6: 0.1 | D6: kg/day | E6: =C6 -> 0.1 | F6: 44500 | G6: Rp/kg | H6: =E6*F6 -> 4450
B7: caustic soda | C7: 0.1 | D7: kg/day | E7: =C7 -> 0.1 | F7: 65340 | G7: Rp/kg | H7: =E7*F7 -> 6534
B8: citrid acid | C8: 0.1 | D8: kg/day | E8: =C8 -> 0.1 | F8: 33275 | G8: Rp/kg | H8: =E8*F8 -> 3327.5
B9: bioside | C9: 0.1 | D9: kg/day | E9: =C9 -> 0.1 | F9: 47450 | G9: Rp/kg | H9: =E9*F9 -> 4745
B10: Power | C10: 8896 | D10: kW/day | E10: =C10 -> 8896 | F10: =[5]UP.E!C28 -> 1550 | G10: Rp/kW | H10: =E10*F10 -> 13788800
B11: Preventive Maintenance | D11: Rp/day | H11: =E11*F11 -> 0
H12: =IFERROR(SUM(H5:H11),"") -> 1.8505866e+08
F13: Unit Price, Rp/M3 | H13: =H12/E4 -> 9401.4761
C25: Kurita H-504 18:25

Sheet lab
B2: Laboratorium Chemical Cost
B3: Consumable Item | C3: Norma | E3: Consumption/ Hari | F3: Unit Price | H3: Total Biaya
H4: Per Hari
B5: Refinery, Fraksinasi, Packaging & Sotrage tank
B6: Acetic Acid Glacial | C6: 50 | D6: ml | E6: =C6 -> 50 | F6: 374 | G6: ml | H6: =E6*F6 -> 18700
B7: Aquadest | C7: 2 | D7: liter | E7: =C7 -> 2 | F7: 7250 | G7: liter | H7: =E7*F7 -> 14500
B8: BF3-methanol solution, Reagen Grade | C8: 0.5 | D8: ml | E8: =C8 -> 0.5 | F8: 500 | G8: ml | H8: =E8*F8 -> 250
B9: Chloroform | C9: 70 | D9: ml | E9: =C9 -> 70 | F9: 388 | G9: ml | H9: =E9*F9 -> 27160
B10: Cyclohexane | C10: 70 | D10: ml | E10: =C10 -> 70 | F10: 612 | G10: ml | H10: =E10*F10 -> 42840
B11: Hydrazine Sulphate | C11: 0.05 | D11: gr | E11: =C11 -> 0.05 | F11: 21000 | G11: gr | H11: =E11*F11 -> 1050
B12: Hydrochloric Acid 37% | C12: 2.6 | D12: ml | E12: =C12 -> 2.6 | F12: 236 | G12: ml | H12: =E12*F12 -> 613.6
B13: Iso Propanol Alcohol TG | C13: 5.5 | D13: liter | E13: =C13 -> 5.5 | F13: 35000 | G13: liter | H13: =E13*F13 -> 192500
B14: Isooctane | C14: 150 | D14: ml | E14: =C14 -> 150 | F14: 480 | G14: ml | H14: =E14*F14 -> 72000
B15: Indikator Phenolpthalaein 1 % | C15: 0.3 | D15: gr | E15: =C15 -> 0.3 | F15: 6750 | G15: gr | H15: =E15*F15 -> 2025
B16: Indikator Thymolpthalaein | C16: =36/357 -> 0.10084034 | D16: gr | E16: =C16 -> 0.10084034 | F16: 90000 | G16: gr | H16: =E16*F16 -> 9075.6303
B17: Starch | C17: =107/357 -> 0.29971989 | D17: gr | E17: =C17 -> 0.29971989 | F17: 3000 | G17: gr | H17: =E17*F17 -> 899.15966
B18: Liquid standard Lovibond 3,4R 30,0 Y 0,9N | C18: 0.1 | D18: ml | E18: =C18 -> 0.1 | F18: 70000 | G18: ml | H18: =E18*F18 -> 7000
B19: Liquid standard Lovibond 3,0R 28,0Y | C19: 0.1 | D19: ml | E19: =C19 -> 0.1 | F19: 70000 | G19: ml | H19: =E19*F19 -> 7000
B20: n-HexaneTehcnis | C20: 0.5 | D20: liter | E20: =C20 -> 0.5 | F20: 19300 | G20: liter | H20: =E20*F20 -> 9650
B21: p-Anisidine | C21: =48/357 -> 0.13445378 | D21: gr | E21: =C21 -> 0.13445378 | F21: 7600 | G21: gr | H21: =E21*F21 -> 1021.8487
B22: Wijs Solution | C22: 120 | D22: ml | E22: =C22 -> 120 | F22: 502 | G22: ml | H22: =E22*F22 -> 60240
B23: N2 (UHP) gas refill for GC & Foam test | C23: 0.02 | D23: Liter | E23: =C23 -> 0.02 | F23: 5000000 | G23: Liter | H23: =E23*F23 -> 100000
B24: H2 (UHP) gas refill for GC | C24: 0.03 | D24: Liter | E24: =C24 -> 0.03 | F24: 2500000 | G24: Liter | H24: =E24*F24 -> 75000
B25: UT (UHP) gas refill for GC | C25: 0.03 | D25: Liter | E25: =C25 -> 0.03 | F25: 1250000 | G25: Liter | H25: =E25*F25 -> 37500
B26: Zinc Oksida GR | C26: =179/357 -> 0.50140056 | D26: gr | E26: =C26 -> 0.50140056 | F26: 2000 | G26: gr | H26: =E26*F26 -> 1002.8011
B27: Potassium Dihydrogen Phosphate | C27: =250/357 -> 0.70028011 | D27: gr | E27: =C27 -> 0.70028011 | F27: 765 | G27: gr | H27: =E27*F27 -> 535.71429
B28: Pottasium Hydrogen Phtalate | C28: =250/357 -> 0.70028011 | D28: gr | E28: =C28 -> 0.70028011 | F28: 5200 | G28: gr | H28: =E28*F28 -> 3641.4566
B29: Sodium Thiosulphate | C29: =6069/357 -> 17 | D29: gr | E29: =C29 -> 17 | F29: 950 | G29: gr | H29: =E29*F29 -> 16150
B30: Potassium Iodide | C30: 12 | D30: gr | E30: =C30 -> 12 | F30: 2400 | G30: gr | H30: =E30*F30 -> 28800
B31: Pottasium Dichromate | C31: =357/357 -> 1 | D31: gr | E31: =C31 -> 1 | F31: 4200 | G31: gr | H31: =E31*F31 -> 4200
B32: Sodium Hydroxide | C32: =6069/357 -> 17 | D32: gr | E32: =C32 -> 17 | F32: 700 | G32: gr | H32: =E32*F32 -> 11900
B33: Sub Total | H33: =SUM(H6:H32) -> 745255.21
B35: Consumable Item | C35: Norma | E35: Consumption/day | F35: Unit Price | H35: Total Price
H36: Per Day
B37: Chemical Boiler & WTP
B38: Sodium Molybdate | C38: =286/357 -> 0.80112045 | D38: gr | E38: =C38 -> 0.80112045 | F38: 4000 | G38: gr | H38: =E38*F38 -> 3204.4818
B39: Iron test 0.0025 - 5.00 mg/l | C39: =1785/357 -> 5 | D39: Test | E39: =C39 -> 5 | F39: 10100 | G39: Test | H39: =E39*F39 -> 50500
B40: Phosphate Test 0.5 - 30 mg/l PO4-P | C40: =714/357 -> 2 | D40: pcs | E40: =C40 -> 2 | F40: 8160 | G40: pcs | H40: =E40*F40 -> 16320
B41: Sulfite Test 1,0-60,0 mg/l SO3 | C41: =360/357 -> 1.0084034 | D41: Pcs | E41: =C41 -> 1.0084034 | F41: 26550 | G41: Pcs | H41: =E41*F41 -> 26773.109
B42: Silica Test 0-800 mg/L | C42: =714/357 -> 2 | D42: pcs | E42: =C42 -> 2 | F42: 31700 | G42: pcs | H42: =E42*F42 -> 63400
B43: Silicate (Silicic Acid) 0,3-10 mg/L | C43: 2.5 | D43: pcs | E43: =C43 -> 2.5 | F43: 31006 | G43: pcs | H43: =E43*F43 -> 77515
B44: Ammonium Vanadate | C44: =179/357 -> 0.50140056 | D44: gr | E44: =C44 -> 0.50140056 | F44: 11950 | G44: gr | H44: =E44*F44 -> 5991.7367
B45: Ammonium Chloride | C45: =214/357 -> 0.59943978 | D45: gr | E45: =C45 -> 0.59943978 | F45: 2545 | G45: gr | H45: =E45*F45 -> 1525.5742
B46: Ammonium Hidroksida | C46: =1714/357 -> 4.8011204 | D46: mL | E46: =C46 -> 4.8011204 | F46: 930 | G46: mL | H46: =E46*F46 -> 4465.042
B47: Mg EDTA | C47: =71/357 -> 0.19887955 | D47: gr | E47: =C47 -> 0.19887955 | F47: 21050 | G47: gr | H47: =E47*F47 -> 4186.4146
B48: Pottasium Carbonat | C48: =12/357 -> 0.033613445 | D48: gr | E48: =C48 -> 0.033613445 | F48: 12500 | G48: gr | H48: =E48*F48 -> 420.16807
B49: Trietanolamin | C49: 0.08 | D49: mL | E49: =C49 -> 0.08 | F49: 8160 | G49: mL | H49: =E49*F49 -> 652.8
B50: Indikator EBT | C50: =12/357 -> 0.033613445 | D50: gr | E50: =C50 -> 0.033613445 | F50: 23400 | G50: gr | H50: =E50*F50 -> 786.55462
B51: Indikator Calcon | C51: =12/357 -> 0.033613445 | D51: gr | E51: =C51 -> 0.033613445 | F51: 50800 | G51: gr | H51: =E51*F51 -> 1707.563
B52: Hydroxylammonium Chloride GR | C52: 0.08 | D52: gr | E52: =C52 -> 0.08 | F52: 6250 | G52: gr | H52: =E52*F52 -> 500
B53: Eriocrom Black T-Metal | C53: 0.05 | D53: gr | E53: =C53 -> 0.05 | F53: 24260 | G53: gr | H53: =E53*F53 -> 1213
B54: Sub Total | H54: =SUM(H38:H53) -> 259161.44
B56: Consumable Item | C56: Norma | E56: Consumption/day | F56: Unit Price | H56: Total Price
H57: Per Day
B58: Chemical WWTP
B59: COD cell test 50 - 500 mg/l | C59: =59/357 -> 0.16526611 | D59: pcs | E59: =C59 -> 0.16526611 | F59: 82000 | G59: pcs | H59: =E59*F59 -> 13551.821
B60: COD cell test 500 - 10000 mg/l | C60: =59/357 -> 0.16526611 | D60: pcs | E60: =C60 -> 0.16526611 | F60: 82000 | G60: pcs | H60: =E60*F60 -> 13551.821
B61: Sub Total | H61: =SUM(H59:H60) -> 27103.641
B63: Total keseluruhan | H63: =H61+H54+H33 -> 1031520.3
C67: Spere Part Laboratorium
B68: No | C68: Consumable Item | D68: Norma | F68: Consumption/day | G68: Unit Price | I68: Total Price
I69: Per Day
B70: 1 | C70: Batang pengaduk | D70: 12 | E70: Pcs/Tahun | F70: =D70/357 -> 0.033613445 | G70: 35000 | H70: Rp/Pcs | I70: =F70*G70 -> 1176.4706
B71: =B70+1 -> 2 | C71: Beaker glass 100 mL | D71: 72 | E71: Pcs/Tahun | F71: =D71/357 -> 0.20168067 | G71: 48000 | H71: Rp/Pcs | I71: =F71*G71 -> 9680.6723
B72: =B71+1 -> 3 | C72: Beaker glass 500 mL | D72: 12 | E72: Pcs/Tahun | F72: =D72/357 -> 0.033613445 | G72: 100000 | H72: Rp/Pcs | I72: =F72*G72 -> 3361.3445
B73: =B72+1 -> 4 | C73: Beaker glass 1000 mL | D73: 6 | E73: Pcs/Tahun | F73: =D73/357 -> 0.016806723 | G73: 120000 | H73: Rp/Pcs | I73: =F73*G73 -> 2016.8067
B74: =B73+1 -> 5 | C74: Beaker glass 2000 mL | D74: 6 | E74: Pcs/Tahun | F74: =D74/357 -> 0.016806723 | G74: 142000 | H74: Rp/Pcs | I74: =F74*G74 -> 2386.5546
B75: =B74+1 -> 6 | C75: Beaker Plastik with handle 1000 mL | D75: 6 | E75: Pcs/Tahun | F75: =D75/357 -> 0.016806723 | G75: 70000 | H75: Rp/Pcs | I75: =F75*G75 -> 1176.4706
B76: =B75+1 -> 7 | C76: Boiling Round Bottom Flask 250 mL | D76: 6 | E76: Pcs/Tahun | F76: =D76/357 -> 0.016806723 | G76: 180000 | H76: Rp/Pcs | I76: =F76*G76 -> 3025.2101
B77: =B76+1 -> 8 | C77: Boiling Round Bottom Flask 1000 mL IKA | D77: 2 | E77: Pcs/Tahun | F77: =D77/357 -> 0.0056022409 | G77: 350000 | H77: Rp/Pcs | I77: =F77*G77 -> 1960.7843
B78: =B77+1 -> 9 | C78: Rotary flask 1000 mL IKA | D78: 2 | E78: Pcs/Tahun | F78: =D78/357 -> 0.0056022409 | G78: 350000 | H78: Rp/Pcs | I78: =F78*G78 -> 1960.7843
B79: =B78+1 -> 10 | C79: Corong 75 mm | D79: 6 | E79: Pcs/Tahun | F79: =D79/357 -> 0.016806723 | G79: 75000 | H79: Rp/Pcs | I79: =F79*G79 -> 1260.5042
B80: =B79+1 -> 11 | C80: Erlenmeyer 250 mL | D80: 72 | E80: Pcs/Tahun | F80: =D80/357 -> 0.20168067 | G80: 90000 | H80: Rp/Pcs | I80: =F80*G80 -> 18151.261
B81: =B80+1 -> 12 | C81: Filtering Flask 500 mL | D81: 2 | E81: Pcs/Tahun | F81: =D81/357 -> 0.0056022409 | G81: 400000 | H81: Rp/Pcs | I81: =F81*G81 -> 2240.8964
B82: =B81+1 -> 13 | C82: Gelas ukur 100 mL | D82: 2 | E82: Pcs/Tahun | F82: =D82/357 -> 0.0056022409 | G82: 85000 | H82: Rp/Pcs | I82: =F82*G82 -> 476.19048
... B110: =B109+1 -> 41 | C110: Magnetic Stirer 8 cm | D110: 12 | E110: Pcs/Tahun | F110: =D110/357 -> 0.033613445 | G110: 85000 | H110: Rp/Pcs | I110: =F110*G110 -> 2857.1429
G111: Total Cost/Days | I111: =SUM(I70:I110) -> 135770.31

Sheet genset
B2: Warming Up Genset
B3: Consumable Item | C3: Norma | E3: Consumption/day | F3: Unit Price | H3: Total Cost | K3: PLN - Power Unit Price
B4: Genset Warming Up | D4: kW/Jam | E4: 0 | H4: Rp/day | K4: Consumable Item | L4: Unit Price
B5: Solar | H5: 0 | K5: PLN Fee | L5: 1550 | M5: Rp/kWh
B6: Genset - 1 (1044 kW) | C6: 100 | D6: Ltr/Jam | E6: =(C6*25%*4)/30 -> 3.3333333 | F6: 14500 | G6: Rp/ltr | H6: =F6*E6 -> 48333.333
B7: Genset - 2 (1044 kW) | C7: 100 | D7: Ltr/Jam | E7: =(C7*25%*4)/30 -> 3.3333333 | F7: 14500 | G7: Rp/ltr | H7: =F7*E7 -> 48333.333
B8: Genset - 3 (1044 kW) | C8: 100 | D8: Ltr/Jam | E8: =(C8*25%*4)/30 -> 3.3333333 | F8: 14500 | G8: Rp/ltr | H8: =F8*E8 -> 48333.333
B9: Preventive Maintenance | D9: Rp/day | H9: 0
B10: Cost Power by Genset | H10: =SUM(H5:H9) -> 145000
B12: Genset - Power Unit Price
B13: Consumable Item | C13: Norma | E13: Power, kW/day | F13: Unit Price | H13: Total Cost
B14: Power Production by Genset | C14: 2088 | D14: kW/Jam | E14: =C14*24 -> 50112 | H14: Rp/day
B15: Solar | H15: 0
B16: Genset - 1 (1044 kW) | C16: 800 | D16: Ltr/Jam | E16: =C16*24 -> 19200 | F16: 14500 | G16: Rp/ltr | H16: =F16*E16 -> 278400000
B17: Genset - 2 (1044 kW) | C17: 800 | D17: Ltr/Jam | E17: =C17*24 -> 19200 | F17: 14500 | G17: Rp/ltr | H17: =F17*E17 -> 278400000
B18: Genset - 3 (1044 kW) | D18: Ltr/Jam | E18: 0 | F18: 14500 | G18: Rp/ltr | H18: =F18*E18 -> 0
B19: Preventive Maintenance | D19: Rp/day | H19: 0
B20: Cost Power by Genset | H20: =SUM(H15:H19) -> 556800000
F21: Unit Price, Rp/Kw | H21: =H20/E14 -> 11111.111 | I21: Unit price terlalu tinggi
B23: Note :
B24: 1. Cross cek kembali consumption solar genset per unit

Sheet AMOR
B2: Amortization
B3: Through Put CPO Proses | H3: TPD | I3: ='HPP REF '!N3 -> 1382.6516
B4: Working Day | H4: Day | I4: ='HPP REF '!N4 -> 25
B5: Total CPO Refined | H5: TPM | I5: =I4*I3 -> 34566.291
B6: Kurs Rupiah | I6: 16000
B7: No | C7: Description | D7: Actual 2023 | F7: Budget 2024
D8: Years | E8: Month | F8: Years | G8: Month | H8: RP/KG | I8: USD/MT
B9: 1 | C9: Perangkat Lunak/Software | D9: 9.6270931e+08 | E9: =D9/12 -> 80225776 | F9: =G9*12 -> 5.3192735e+08 | G9: 44327279 | H9: =$G$9/($I$5*1000) -> 1.2823846 | I9: =($G$9/$I$6)/$I$5 -> 0.080149037 | J9: =D9/12 -> 80225776
B10: =B9+1 -> 2 | C10: Sertifikat/Surat Izin | D10: 2.6961444e+08 | E10: =D10/12 -> 22467870 | F10: 0 | G10: 0 | H10: =$G$10/($I$5*1000) -> 0 | I10: =($G$10/$I$6)/$I$5 -> 0
B11: =B10+1 -> 3 | C11: Inventaris Kecil (Aset Sewa) | D11: 0 | E11: =D11/12 -> 0 | F11: 0 | G11: 0 | H11: =$G$11/($I$5*1000) -> 0 | I11: =($G$11/$I$6)/$I$5 -> 0
B12: =B11+1 -> 4 | C12: Aset Hak Guna (ROU) - Kendaraan | D12: 0 | E12: =D12/12 -> 0 | F12: 0 | G12: 0 | H12: =$G$12/($I$5*1000) -> 0 | I12: =($G$12/$I$6)/$I$5 -> 0
B13: =B12+1 -> 5 | C13: Aset Hak Guna (ROU) - Tangki Timbun | D13: 0 | E13: =D13/12 -> 0 | F13: 0 | G13: 0 | H13: =$G$13/($I$5*1000) -> 0 | I13: =($G$13/$I$6)/$I$5 -> 0
B14: =B13+1 -> 6 | C14: Aset Atas Biaya Penyambungan | D14: 0 | E14: =D14/12 -> 0 | F14: 0 | G14: 0 | H14: =$G$14/($I$5*1000) -> 0 | I14: =($G$14/$I$6)/$I$5 -> 0
B15: =B14+1 -> 7 | C15: Aset Hak Guna (ROU) - Pemanfaatan Lahan Sei Mangkei + Surabaya | D15: 1.2576903e+10 | E15: =D15/12 -> 1.0480752e+09 | F15: =G15*12 -> 12048990312 | G15: 1004082526 | H15: =$G$15/($I$5*1000) -> 29.048026 | I15: =($G$15/$I$6)/$I$5 -> 1.8155016
B20: Total Cost Depreciation | D20: =SUM(D9:D19) -> 1.3809227e+10 | E20: =SUM(E9:E19) -> 1.1507689e+09 | F20: =SUM(F9:F19) -> 1.2580918e+10 | G20: =SUM(G9:G19) -> 1.0484098e+09 | H20: =SUM(H9:H19) -> 30.330411 | I20: =SUM(I9:I19) -> 1.8956507

Sheet DEP
B2: Depreciation
B3: Through Put CPO Proses | J3: TPD | K3: ='HPP REF '!N3 -> 1382.6516
B4: Working Day | J4: Day | K4: ='HPP REF '!N4 -> 25
B5: Total CPO Refined | J5: TPM | K5: =K4*K3 -> 34566.291
B6: Kurs Rupiah | K6: 16000
B7: No | C7: Description | D7: Actual 2023 (Audited) | G7: Budget 2024
D8: Asset | E8: Years | F8: Month | G8: Asset | H8: Years | I8: Month | J8: RP/KG | K8: USD/MT
B9: Total Cost Depreciation | D9: =SUM(D10:D75) -> 6.7971213e+11 | E9: =SUM(E10:E75) -> 4.1807174e+10 | F9: =SUM(F10:F75) -> 3.4839312e+09 | G9: =SUM(G10:G75) -> 7.7503139e+11 | H9: =SUM(H10:H75) -> 5.0174217e+10 | I9: =SUM(I10:I75) -> 4.1811848e+09 | J9: =SUM(J10:J75) -> 120.96134 | K9: =SUM(K10:K75) -> 7.5600836
B10: 1 | C10: Front Office + Canteen | D10: 3844320790 | E10: 1.9221604e+08 | F10: 16018003 | G10: 3.8443208e+09 | H10: =I10*12 -> 1.9221604e+08 | I10: 16018003 | J10: =$I$10/($K$5*1000) -> 0.46339954 | K10: =($I$10/$K$6)/$K$5 -> 0.028962471
B11: =B10+1 -> 2 | C11: Bea Cukai Building | D11: 247144032 | E11: 12357202 | F11: 1029766.8 | G11: 2.4714403e+08 | H11: =I11*12 -> 12357202 | I11: 1029766.8 | J11: =$I$11/($K$5*1000) -> 0.02979107 | K11: =($I$11/$K$6)/$K$5 -> 0.0018619419
B12: =B11+1 -> 3 | C12: Security Building | D12: 199088248 | E12: 12429395 | F12: 1035782.9 | G12: 3.9708686e+08 | H12: =I12*12 -> 19854343 | I12: 1654528.6 | J12: =$I$12/($K$5*1000) -> 0.047865378 | K12: =($I$12/$K$6)/$K$5 -> 0.0029915861
B13: =B12+1 -> 4 | C13: Bangunan Shelter / Pelataran | D13: 53111657402 | E13: 2.6555829e+09 | F13: 2.2129857e+08 | G13: 5.3111657e+10 | H13: =I13*12 -> 2.6555829e+09 | I13: 2.2129857e+08 | J13: =$I$13/($K$5*1000) -> 6.4021498 | K13: =($I$13/$K$6)/$K$5 -> 0.40013436
B14: =B13+1 -> 5 | C14: Laboratorium Building | D14: 1.3920764e+09 | E14: 70956822 | F14: 5913068.5 | G14: 1.5003164e+09 | H14: =I14*12 -> 75015820 | I14: 6251318.3 | J14: =$I$14/($K$5*1000) -> 0.18085013 | K14: =($I$14/$K$6)/$K$5 -> 0.011303133
B15: =B14+1 -> 6 | C15: Refinery Room | D15: 22378266872 | E15: 1.1189133e+09 | F15: 93242779 | G15: 2.2378267e+10 | H15: =I15*12 -> 1.1189133e+09 | I15: 93242779 | J15: =$I$15/($K$5*1000) -> 2.697506 | K15: =($I$15/$K$6)/$K$5 -> 0.16859413
B16: =B15+1 -> 7 | C16: Fractionation Room | D16: 22378266872 | E16: 1.1189133e+09 | F16: 93242779 | G16: 2.2378267e+10 | H16: =I16*12 -> 1.1189133e+09 | I16: 93242779 | J16: =$I$16/($K$5*1000) -> 2.697506 | K16: =($I$16/$K$6)/$K$5 -> 0.16859413
B17: =B16+1 -> 8 | C17: Utility Building | D17: 22548996820 | E17: 1.1274498e+09 | F17: 93954153 | G17: 2.2548997e+10 | H17: =I17*12 -> 1.1274498e+09 | I17: 93954153 | J17: =$I$17/($K$5*1000) -> 2.7180861 | K17: =($I$17/$K$6)/$K$5 -> 0.16988038
B18: =B17+1 -> 9 | C18: Power House & Electrical Building | D18: 3242778116 | E18: 1.6663346e+08 | F18: 13886122 | G18: 3.6023423e+09 | H18: =I18*12 -> 1.8011712e+08 | I18: 15009760 | J18: =$I$18/($K$5*1000) -> 0.43423113 | K18: =($I$18/$K$6)/$K$5 -> 0.027139446
B19: =B18+1 -> 10 | C19: Weight Bridge Building (Timbangan) | D19: 3.0883582e+09 | E19: 1.6798762e+08 | F19: 13998968 | G19: 4.173935e+09 | H19: =I19*12 -> 2.0869675e+08 | I19: 17391396 | J19: =$I$19/($K$5*1000) -> 0.50313167 | K19: =($I$19/$K$6)/$K$5 -> 0.03144573
B20: =B19+1 -> 11 | C20: Warehouse TPS Spent Earth | D20: 1.3067146e+09 | E20: 65335728 | F20: 5444644 | G20: 1.3067146e+09 | H20: =I20*12 -> 65335728 | I20: 5444644 | J20: =$I$20/($K$5*1000) -> 0.15751311 | K20: =($I$20/$K$6)/$K$5 -> 0.0098445694
B21: =B20+1 -> 12 | C21: Bangunan Shelter / Pelataran | D21: 0 | E21: 0 | F21: 0 | G21: 0 | H21: =I21*12 -> 0 | I21: 0 | J21: =$I$21/($K$5*1000) -> 0 | K21: =($I$21/$K$6)/$K$5 -> 0
B22: =B21+1 -> 13 | C22: Packaging Building | D22: 26865966199 | E22: 1.3432983e+09 | F22: 1.1194153e+08 | G22: 2.6865966e+10 | H22: =I22*12 -> 1.895783e+09 | I22: 1.5798192e+08 | J22: =$I$22/($K$5*1000) -> 4.5704041 | K22: =($I$22/$K$6)/$K$5 -> 0.28565026
B23: =B22+1 -> 14 | C23: Warehouse TPS Limbah B3 | D23: 808088751 | E23: 52164853 | F23: 4347071.1 | G23: 1.748922e+09 | H23: =I23*12 -> 87446098 | I23: 7287174.8 | J23: =$I$23/($K$5*1000) -> 0.21081738 | K23: =($I$23/$K$6)/$K$5 -> 0.013176086
B24: =B23+1 -> 15 | C24: Panel Room Loading - Unloading | D24: 669445527 | E24: 33472276 | F24: 2789356.4 | G24: 6.6944553e+08 | H24: =I24*12 -> 33472276 | I24: 2789356.4 | J24: =$I$24/($K$5*1000) -> 0.080695854 | K24: =($I$24/$K$6)/$K$5 -> 0.0050434909
B25: =B24+1 -> 16 | C25: Bangunan Shelter / Pelataran | D25: 0 | E25: 0 | F25: 0 | G25: 0 | H25: =I25*12 -> 0 | I25: 0 | J25: =$I$25/($K$5*1000) -> 0 | K25: =($I$25/$K$6)/$K$5 -> 0
B26: =B25+1 -> 17 | C26: Kantor RO Medan | D26: 35739000 | E26: 3573900 | F26: 297825 | G26: 35739000 | H26: =I26*12 -> 3573900 | I26: 297825 | J26: =$I$26/($K$5*1000) -> 0.0086160531 | K26: =($I$26/$K$6)/$K$5 -> 0.00053850332
B27: =B26+1 -> 18 | C27: Gedung Logistic | D27: 537402145 | E27: 26870107 | F27: 2239175.6 | G27: 537402145 | H27: =I27*12 -> 26870107 | I27: 2239175.6 | J27: =$I$27/($K$5*1000) -> 0.064779169 | K27: =($I$27/$K$6)/$K$5 -> 0.0040486981
B28: =B27+1 -> 19 | C28: Ruang Expansi Filling Packaging | D28: 1071796228 | E28: 26794906 | F28: 2232908.8 | G28: 1071796228 | H28: =I28*12 -> 53589811 | I28: 4465817.6 | J28: =$I$28/($K$5*1000) -> 0.12919574 | K28: =($I$28/$K$6)/$K$5 -> 0.0080747339
B29: =B28+1 -> 20 | C29: Bangunan Lainnya | D29: 236594750 | E29: 67601093 | F29: 5633424.5 | G29: 3.7519242e+09 | H29: =I29*12 -> 1.9942595e+08 | I29: 16618829 | J29: =$I$29/($K$5*1000) -> 0.48078138 | K29: =($I$29/$K$6)/$K$5 -> 0.030048836
B30: =B29+1 -> 21 | C30: Power House System | D30: 30414179484 | E30: 1.6120305e+09 | F30: 1.3433587e+08 | G30: 3.0414179e+10 | H30: =I30*12 -> 1.7106159e+09 | I30: 1.4255132e+08 | J30: =$I$30/($K$5*1000) -> 4.1239983 | K30: =($I$30/$K$6)/$K$5 -> 0.25774989
B31: =B30+1 -> 22 | C31: Reception from Road Tanker System | D31: 15714477178 | E31: 1.5906981e+09 | F31: 1.3255817e+08 | G31: 1.5714477e+10 | H31: =I31*12 -> 1.6892835e+09 | I31: 1.4077362e+08 | J31: =$I$31/($K$5*1000) -> 4.0725696 | K31: =($I$31/$K$6)/$K$5 -> 0.2545356
B32: =B31+1 -> 23 | C32: Reception & CPO Storage Tank System | D32: 3.9160256e+10 | E32: 1.8156968e+09 | F32: 1.5130807e+08 | G32: 3.9160256e+10 | H32: =I32*12 -> 1.9142822e+09 | I32: 1.5952352e+08 | J32: =$I$32/($K$5*1000) -> 4.6150025 | K32: =($I$32/$K$6)/$K$5 -> 0.28843766
B33: =B32+1 -> 24 | C33: Refinery Product System | D33: 26158484525 | E33: 1.546139e+09 | F33: 1.2884492e+08 | G33: 2.6158485e+10 | H33: =I33*12 -> 2.1043359e+09 | I33: 1.7536132e+08 | J33: =$I$33/($K$5*1000) -> 5.0731889 | K33: =($I$33/$K$6)/$K$5 -> 0.31707431
B34: =B33+1 -> 25 | C34: Fractionation Product System | D34: 44700543389 | E34: 2.5257813e+09 | F34: 2.1048177e+08 | G34: 4.4700543e+10 | H34: =I34*12 -> 2.6243667e+09 | I34: 2.1869722e+08 | J34: =$I$34/($K$5*1000) -> 6.326893 | K34: =($I$34/$K$6)/$K$5 -> 0.39543081
B35: =B34+1 -> 26 | C35: Compressed Air System | D35: 12406716786 | E35: 6.9726354e+08 | F35: 58105295 | G35: 1.2406717e+10 | H35: =I35*12 -> 6.9726354e+08 | I35: 58105295 | J35: =$I$35/($K$5*1000) -> 1.6809815 | K35: =($I$35/$K$6)/$K$5 -> 0.10506134
B36: =B35+1 -> 27 | C36: Fuel Distribution System | D36: 2279256408 | E36: 1.6844371e+08 | F36: 14036976 | G36: 2.2792564e+09 | H36: =I36*12 -> 2.0366838e+08 | I36: 16972365 | J36: =$I$36/($K$5*1000) -> 0.49100916 | K36: =($I$36/$K$6)/$K$5 -> 0.030688072
B37: =B36+1 -> 28 | C37: Waste Water Treatment System | D37: 8173671310 | E37: 5.0165483e+08 | F37: 41804569 | G37: 8.1736713e+09 | H37: =I37*12 -> 5.1840723e+08 | I37: 43200602 | J37: =$I$37/($K$5*1000) -> 1.2497899 | K37: =($I$37/$K$6)/$K$5 -> 0.07811187
B38: =B37+1 -> 29 | C38: Clean Water System | D38: 8.1369458e+09 | E38: 4.697884e+08 | F38: 39149033 | G38: 8.1369458e+09 | H38: =I38*12 -> 4.697884e+08 | I38: 39149033 | J38: =$I$38/($K$5*1000) -> 1.1325784 | K38: =($I$38/$K$6)/$K$5 -> 0.070786147
B39: =B38+1 -> 30 | C39: Demin Water Distribution System | D39: 5554219736 | E39: 3.7021373e+08 | F39: 30851144 | G39: 5.5542197e+09 | H39: =I39*12 -> 3.7021373e+08 | I39: 30851144 | J39: =$I$39/($K$5*1000) -> 0.8925211 | K39: =($I$39/$K$6)/$K$5 -> 0.055782569
B40: =B39+1 -> 31 | C40: Steam Generation System | D40: 28411905935 | E40: 1.6009903e+09 | F40: 1.3341586e+08 | G40: 2.8411906e+10 | H40: =I40*12 -> 1.6009903e+09 | I40: 1.3341586e+08 | J40: =$I$40/($K$5*1000) -> 3.8597099 | K40: =($I$40/$K$6)/$K$5 -> 0.24123187 | L40: =H40/12 -> 1.3341586e+08
B41: =B40+1 -> 32 | C41: Cooling Water Distribution System | D41: 8813632097 | E41: 5.5719688e+08 | F41: 46433074 | G41: 8.8136321e+09 | H41: =I41*12 -> 5.5719688e+08 | I41: 46433074 | J41: =$I$41/($K$5*1000) -> 1.3433051 | K41: =($I$41/$K$6)/$K$5 -> 0.083956566
B42: =B41+1 -> 33 | C42: Fire Water System | D42: 4990631887 | E42: 3.5991574e+08 | F42: 29992978 | G42: 4.9906319e+09 | H42: =I42*12 -> 3.5991574e+08 | I42: 29992978 | J42: =$I$42/($K$5*1000) -> 0.86769443 | K42: =($I$42/$K$6)/$K$5 -> 0.054230902
B43: =B42+1 -> 34 | C43: Dual Fuel Emergency Generator | D43: 11752092639 | E43: 6.1186193e+08 | F43: 50988494 | G43: 1.1752093e+10 | H43: =I43*12 -> 6.1186193e+08 | I43: 50988494 | J43: =$I$43/($K$5*1000) -> 1.475093 | K43: =($I$43/$K$6)/$K$5 -> 0.092193314
B44: =B43+1 -> 35 | C44: Steam Distribution & Condensate Recovery System | D44: 9891619567 | E44: 8.9987659e+08 | F44: 74989716 | G44: 9.8916196e+09 | H44: =I44*12 -> 8.9987659e+08 | I44: 74989716 | J44: =$I$44/($K$5*1000) -> 2.1694464 | K44: =($I$44/$K$6)/$K$5 -> 0.1355904
B45: =B44+1 -> 36 | C45: Fire Water Main Ring System | D45: 4518985787 | E45: 2.4463794e+08 | F45: 20386495 | G45: 4.5189858e+09 | H45: =I45*12 -> 2.4463794e+08 | I45: 20386495 | J45: =$I$45/($K$5*1000) -> 0.58977965 | K45: =($I$45/$K$6)/$K$5 -> 0.036861228
B46: =B45+1 -> 37 | C46: Packaging System | D46: 34206697993 | E46: 3.1394346e+09 | F46: 2.6161955e+08 | G46: 1.2163436e+11 | H46: =I46*12 -> 7.8746236e+09 | I46: 6.5621863e+08 | J46: =$I$46/($K$5*1000) -> 18.984352 | K46: =($I$46/$K$6)/$K$5 -> 1.186522
B47: =B46+1 -> 38 | C47: Refinery System | D47: 93804025615 | E47: 6.3108388e+09 | F47: 5.2590324e+08 | G47: 9.3804026e+10 | H47: =I47*12 -> 6.3327722e+09 | I47: 5.2773101e+08 | J47: =$I$47/($K$5*1000) -> 15.267216 | K47: =($I$47/$K$6)/$K$5 -> 0.95420097
B48: =B47+1 -> 39 | C48: Fractionation System | D48: 69305898501 | E48: 4.7141422e+09 | F48: 3.9284518e+08 | G48: 6.9305899e+10 | H48: =I48*12 -> 4.7141422e+09 | I48: 3.9284518e+08 | J48: =$I$48/($K$5*1000) -> 11.364979 | K48: =($I$48/$K$6)/$K$5 -> 0.71031121
B49: =B48+1 -> 40 | C49: Fat Pit System | D49: 1222833568 | E49: 76427098 | F49: 6368924.8 | G49: 1.2228336e+09 | H49: =I49*12 -> 76427098 | I49: 6368924.8 | J49: =$I$49/($K$5*1000) -> 0.18425248 | K49: =($I$49/$K$6)/$K$5 -> 0.01151578
B50: =B49+1 -> 41 | C50: Weight Bridge | D50: 2557397646 | E50: 1.2786988e+08 | F50: 10655824 | G50: 2.5573976e+09 | H50: =I50*12 -> 1.2786988e+08 | I50: 10655824 | J50: =$I$50/($K$5*1000) -> 0.30827211 | K50: =($I$50/$K$6)/$K$5 -> 0.019267007
B51: =B50+1 -> 42 | C51: Mesin Dan Perlengkapan Pabrik | D51: 30580769059 | E51: 1.6581493e+09 | F51: 1.3817911e+08 | G51: 3.0797884e+10 | H51: =I51*12 -> 2.8889928e+09 | I51: 2.407494e+08 | J51: =$I$51/($K$5*1000) -> 6.9648606 | K51: =($I$51/$K$6)/$K$5 -> 0.43530379
B52: =B51+1 -> 43 | C52: Installation System Electrical (Auxiliary) | D52: 2460303143 | E52: 1.5376895e+08 | F52: 12814079 | G52: 2460303143 | H52: =I52*12 -> 1.5376895e+08 | I52: 12814079 | J52: =$I$52/($K$5*1000) -> 0.37071026 | K52: =($I$52/$K$6)/$K$5 -> 0.023169392
B53: =B52+1 -> 44 | C53: Mesin Dan Perlengkapan Pabrik | D53: 0 | E53: 0 | F53: 0 | G53: 0 | H53: =I53*12 -> 0 | I53: 0 | J53: =$I$53/($K$5*1000) -> 0 | K53: =($I$53/$K$6)/$K$5 -> 0
B54: =B53+1 -> 45 | C54: Mesin Dan Perlengkapan Pabrik | D54: 0 | E54: 0 | F54: 0 | G54: 0 | H54: =I54*12 -> 0 | I54: 0 | J54: =$I$54/($K$5*1000) -> 0 | K54: =($I$54/$K$6)/$K$5 -> 0
B55: =B54+1 -> 46 | C55: Refinery Product System | D55: 0 | E55: 0 | F55: 0 | G55: 0 | H55: =I55*12 -> 0 | I55: 0 | J55: =$I$55/($K$5*1000) -> 0 | K55: =($I$55/$K$6)/$K$5 -> 0
B56: =B55+1 -> 47 | C56: Perlengkapan Pabrik Lainnya | D56: 814629325 | E56: 1.3842046e+08 | F56: 11535038 | G56: 814629325 | H56: =I56*12 -> 1.3842046e+08 | I56: 11535038 | J56: =$I$56/($K$5*1000) -> 0.33370772 | K56: =($I$56/$K$6)/$K$5 -> 0.020856733
B57: =B56+1 -> 48 | C57: Bangunan Shelter / Pelataran | D57: 0 | E57: 0 | F57: 0 | G57: 0 | H57: =I57*12 -> 0 | I57: 0 | J57: =$I$57/($K$5*1000) -> 0 | K57: =($I$57/$K$6)/$K$5 -> 0
B58: =B57+1 -> 49 | C58: Saluran Drainase | D58: 3324550757 | E58: 1.6622754e+08 | F58: 13852295 | G58: 3.3245508e+09 | H58: =I58*12 -> 1.6622754e+08 | I58: 13852295 | J58: =$I$58/($K$5*1000) -> 0.40074577 | K58: =($I$58/$K$6)/$K$5 -> 0.02504661
B59: =B58+1 -> 50 | C59: Fence | D59: 1457273906 | E59: 72863695 | F59: 6071974.6 | G59: 1457273906 | H59: =I59*12 -> 72863695 | I59: 6071974.6 | J59: =$I$59/($K$5*1000) -> 0.17566173 | K59: =($I$59/$K$6)/$K$5 -> 0.010978858
B60: =B59+1 -> 51 | C60: Bangunan Shelter / Pelataran | D60: 0 | E60: 0 | F60: 0 | G60: 0 | H60: =I60*12 -> 0 | I60: 0 | J60: =$I$60/($K$5*1000) -> 0 | K60: =($I$60/$K$6)/$K$5 -> 0
B61: =B60+1 -> 52 | C61: Alat Pengangkutan | D61: 702420000 | E61: 58515250 | F61: 4876270.8 | G61: 702420000 | H61: =I61*12 -> 92109000 | I61: 7675750 | J61: =$I$61/($K$5*1000) -> 0.22205883 | K61: =($I$61/$K$6)/$K$5 -> 0.013878677
B62: =B61+1 -> 53 | C62: Perabot & Perlengkapan Kantor | D62: 2093240354 | E62: 2.8749571e+08 | F62: 23957976 | G62: 2093240354 | H62: =I62*12 -> 2.8749571e+08 | I62: 23957976 | J62: =$I$62/($K$5*1000) -> 0.69310231 | K62: =($I$62/$K$6)/$K$5 -> 0.043318894
B63: =B62+1 -> 54 | C63: Perabot dan Perlengkapan Mess | D63: 0 | E63: 0 | F63: 0 | G63: 0 | H63: =I63*12 -> 0 | I63: 0 | J63: =$I$63/($K$5*1000) -> 0 | K63: =($I$63/$K$6)/$K$5 -> 0
B64: =B63+1 -> 55 | C64: Alat & Perlengkapan Pabrik | D64: 68073000 | E64: 13614600 | F64: 1134550 | G64: 68073000 | H64: =I64*12 -> 13614600 | I64: 1134550 | J64: =$I$64/($K$5*1000) -> 0.03282244 | K64: =($I$64/$K$6)/$K$5 -> 0.0020514025
B65: =B64+1 -> 56 | C65: Alat dan Perlengkapan Bengkel | D65: 140550000 | E65: 28110000 | F65: 2342500 | G65: 140550000 | H65: =I65*12 -> 28110000 | I65: 2342500 | J65: =$I$65/($K$5*1000) -> 0.067768335 | K65: =($I$65/$K$6)/$K$5 -> 0.004235521
B66: =B65+1 -> 57 | C66: Alat dan Perlengkapan Laboratorium | D66: 3453064640 | E66: 3.7398892e+08 | F66: 31165744 | G66: 4405170868 | H66: =I66*12 -> 8.9603417e+08 | I66: 74669514 | J66: =$I$66/($K$5*1000) -> 2.160183 | K66: =($I$66/$K$6)/$K$5 -> 0.13501144
B67: =B66+1 -> 58 | C67: Alat IT / Komputer | D67: 1542535419 | E67: 2.9444276e+08 | F67: 24536897 | G67: 1.9760604e+09 | H67: =I67*12 -> 2.9825396e+08 | I67: 24854497 | J67: =$I$67/($K$5*1000) -> 0.71903858 | K67: =($I$67/$K$6)/$K$5 -> 0.044939911
B68: =B67+1 -> 59 | C68: Perabot & Perlengkapan Lainnya | D68: 11270000 | E68: 2254000 | F68: 187833.33 | G68: 11270000 | H68: =I68*12 -> 2254000 | I68: 187833.33 | J68: =$I$68/($K$5*1000) -> 0.0054340031 | K68: =($I$68/$K$6)/$K$5 -> 0.0003396252
B69: =B68+1 -> 60 | C69: Aktiva Tetap Non Produktif | D69: 26932688 | E69: 5386537.6 | F69: 448878.13 | G69: 26932688 | H69: =I69*12 -> 5386537.5 | I69: 448878.13 | J69: =$I$69/($K$5*1000) -> 0.012986008 | K69: =($I$69/$K$6)/$K$5 -> 0.00081162549
B70: =B69+1 -> 61 | C70: Totem AKHLAK | D70: 30000000 | E70: 6000000 | F70: 500000 | G70: 30000000 | H70: =I70*12 -> 6000000.1 | I70: 500000.01 | J70: =$I$70/($K$5*1000) -> 0.01446496 | K70: =($I$70/$K$6)/$K$5 -> 0.00090405998
B71: =B70+1 -> 62 | C71: Main Office | D71: 6869341541 | E71: 3.4448348e+08 | F71: 28706957 | G71: 6.9506539e+09 | H71: =I71*12 -> 3.4753269e+08 | I71: 28961058 | J71: =$I$71/($K$5*1000) -> 0.83784106 | K71: =($I$71/$K$6)/$K$5 -> 0.052365066

Sheet MTC
C1: working days | F1: working days
B2: Summary - PM Electrical | C2: ='JULI 2025'!AM6 -> 25 | E2: Summary - PM Mechanical | F2: ='JULI 2025'!AM6 -> 25
B3: Consumable Item | C3: Total Price | E3: Consumable Item | F3: Total Price
C4: Per Day | F4: Per Day
B5: Biaya Pemeliharaan Unit Refinery(Listrik) | C5: 1648879.6 | E5: Biaya Pemeliharaan Unit Refinery | F5: 4911824.3
B6: HP Boiler | C6: 2678431.4 | E6: Biaya Pemeliharaan Unit Fraksinasi | F6: 1230672.3
B7: Dry Fractination - Crystalizer & Filter Press | C7: 288459.38 | E7: Biaya Pemeliharaan Unit Cooling Tower | F7: 1084733.9
B8: Physical Refinery-Bleaching and Deodorization | C8: 404271.71 | E8: Biaya Pemeliharaan Unit Packaging | F8: 833815.52
B9: BOILER | C9: 150891.4 | E9: Biaya Pemeliharaan Unit Material Handling | F9: 949299.72
B10: Water Plant, Effluent & Hydrant | C10: 58543.417 | E10: Biaya Pemeliharaan Unit Utility | F10: 1106022.4
B11: Pump House | C11: 87425.77 | E11: Barang Consumable Maintenance | F11: 5634698.9
B12: DCS-CCR ISBL | C12: 254341.74
B13: Lighting All Area | C13: 114733.89 | E13: Total | F13: =SUM(F5:F12) -> 15751067
B14: Consumable | C14: 203159.66 | E14: Total/Month | F14: =F13*F2 -> 3.9377667e+08
B15: Kalibrasi Instrument Pabrik | C15: 580672.27 | E15: Total/Yearly | F15: =F14*12 -> 4.7253201e+09
B16: Service Special Equipment | C16: 4089635.9
B17: Total/Day | C17: =SUM(C5:C16) -> 10559446 | E17: TOTAL COST
B18: Total/Month | C18: =C17*C2 -> 2.6398615e+08 | E18: PM E + PM M | F18: =F14+C18 -> 6.5776282e+08
B19: Total/Yearly | C19: =C18*12 -> 3.1678338e+09 | E19: TOTAL | F19: =F18*12 -> 7.8931539e+09

Sheet LOG
B2: Port Cost Kuala Tanjung
B3: Through Put CPO Proses | J3: TPD | K3: ='HPP REF '!N3 -> 1382.6516
B4: Working Day | J4: Day | K4: ='HPP REF '!N4 -> 25
B5: Total CPO Refined | J5: TPM | K5: =K4*K3 -> 34566.291
B6: Kurs Rupiah | K6: 16000
B7: No | C7: Description | G7: Norma | I7: Total Biaya ( Rp ) | J7: RP/KG | K7: USD/MT
B8: 1 | C8: Trucking Komoditi ke Kuala Tanjung | E8: Olein ( Ton ) | F8: =(100%-0.8%-1.1*5%)*80%*K5 -> 25910.892 | G8: Rp/Kg | H8: 90 | I8: =H8*F8*1000 -> 2.3319803e+09 | J8: =I8/($K$5*1000) -> 67.464 | K8: =(I8/$K$6)/$K$5 -> 4.2165
E9: Stearin ( Ton ) Iso Tank | F9: =(100%-0.8%-1.1*5%)*20%*K5 -> 6477.7229 | G9: Rp/Kg | H9: 150 | I9: =H9*F9*1000 -> 9.7165844e+08 | J9: =I9/($K$5*1000) -> 28.11 | K9: =(I9/$K$6)/$K$5 -> 1.756875
E10: PFAD ( Ton ) Iso Tank | F10: =1.1*5%*K5 -> 1901.146 | G10: Rp/Kg | H10: 150 | I10: =H10*F10*1000 -> 2.851719e+08 | J10: =I10/($K$5*1000) -> 8.25 | K10: =(I10/$K$6)/$K$5 -> 0.515625
B11: 2 | C11: Sewa Tank PTI Total Volume : 24.000 MT ( 5 Unit ) | E11: Tank 8.000 MT >> Olein | F11: 1 | G11: Rp/Kg | H11: 77 | I11: =H11*8000*F11*1000 -> 616000000 | J11: =I11/($K$5*1000) -> 17.82083 | K11: =(I11/$K$6)/$K$5 -> 1.1138019
E12: Tank 5.000 MT >> Stearin | F12: 2 | G12: Rp/Kg | H12: 79 | I12: =H12*5000*F12*1000 -> 790000000 | J12: =I12/($K$5*1000) -> 22.854636 | K12: =(I12/$K$6)/$K$5 -> 1.4284148
E13: Tank 3.000 MT >> RBDPO | F13: 1 | G13: Rp/Kg | H13: 77 | I13: =H13*3000*F13*1000 -> 231000000 | J13: =I13/($K$5*1000) -> 6.6828113 | K13: =(I13/$K$6)/$K$5 -> 0.41767571
E14: Tank 3.000 MT S/S >> PFAD | F14: 1 | G14: Rp/Kg | H14: 83 | I14: =H14*3000*F14*1000 -> 249000000 | J14: =I14/($K$5*1000) -> 7.2035498 | K14: =(I14/$K$6)/$K$5 -> 0.45022186
B15: 3 | C15: Finalty Over Capacity dari tank | D15: 0 | E15: Over Volume Olein | F15: =F8-(8000*D15) -> 25910.892 | G15: Rp/Kg | H15: 43 | I15: =H15*F15*1000 -> 1.1141683e+09 | J15: =I15/($K$5*1000) -> 32.2328 | K15: =(I15/$K$6)/$K$5 -> 2.01455
D16: 0 | E16: Over Volume Stearin | F16: =F9-(10000*D16) -> 6477.7229 | G16: Rp/Kg | H16: 43 | I16: =H16*F16*1000 -> 2.7854209e+08 | J16: =I16/($K$5*1000) -> 8.0582 | K16: =(I16/$K$6)/$K$5 -> 0.5036375
D17: 0 | E17: Over Volume PFAD | F17: =F10-(3000*D17) -> 1901.146 | G17: Rp/Kg | H17: 43 | I17: =H17*F17*1000 -> 81749278 | J17: =I17/($K$5*1000) -> 2.365 | K17: =(I17/$K$6)/$K$5 -> 0.1478125
B18: 3 | C18: Beban Instalasi Pemompaan dan Pemanasan | E18: Total Volume | F18: =SUM(F8:F10) -> 34289.761 | G18: Rp/Kg | H18: 22 | I18: =H18*F18*1000 -> 7.5437473e+08 | J18: =I18/($K$5*1000) -> 21.824 | K18: =(I18/$K$6)/$K$5 -> 1.364
B19: =B18+1 -> 4 | C19: Pompa | E19: Total Volume | F19: =F18 -> 34289.761 | G19: Rp/Kg | H19: 26 | I19: =H19*F18*1000 -> 8.9153378e+08 | J19: =I19/($K$5*1000) -> 25.792 | K19: =(I19/$K$6)/$K$5 -> 1.612
B20: =B19+1 -> 5 | C20: Beban Analisa ( Surveyor ) | E20: Total Volume | F20: =F18 -> 34289.761 | G20: Rp/Kg | H20: 3 | I20: =H20*F20*1000 -> 1.0286928e+08 | J20: =I20/($K$5*1000) -> 2.976 | K20: =(I20/$K$6)/$K$5 -> 0.186
B21: =B20+1 -> 6 | C21: Beban Pelabuhan ( Documen-Documen Pelabuhan ) | E21: Total Volume | F21: =F20 -> 34289.761 | G21: Rp/Kg | H21: 3 | I21: =H21*F21*1000 -> 1.0286928e+08 | J21: =I21/($K$5*1000) -> 2.976 | K21: =(I21/$K$6)/$K$5 -> 0.186
B22: =B21+1 -> 7 | C22: Beban Asuransi (Cost Insurance Freight)
B23: =B22+1 -> 8 | C23: Beban Sewa Kapal
B24: =B23+1 -> 9 | C24: Beban Pengangkutan Di Pelabuhan
B25: Total Biaya Transfer Product ke Kuala Tanjung Port | I25: =SUM(I8:I24) -> 8.8009174e+09 | J25: =SUM(J8:J24) -> 254.60983 | K25: =SUM(K8:K24) -> 15.913114

Sheet OH
B2: Overhead ( OH )
B3: Through Put CPO Proses | H3: TPD | I3: ='HPP REF '!N3 -> 1382.6516
B4: Working Day | H4: Day | I4: ='SUMMARY HPP '!I4 -> 25
B5: Total CPO Refined | H5: TPM | I5: =I4*I3 -> 34566.291
B6: Kurs Rupiah | I6: 16000
B7: No | C7: Description | D7: Actual 2023 (Audited) | F7: Budget 2024
D8: Years | E8: Month | F8: Years | G8: Month | H8: RP/KG | I8: USD/MT
B9: 1 | C9: Biaya Perjalanan Dinas (Dalam Provinsi) | D9: 305458258 | E9: =IFERROR(D9/12,0) -> 25454855 | F9: =G9*12 -> 3.6654991e+08 | G9: 30545826 | H9: =G9/($I$5*1000) -> 0.88368827 | I9: =(G9/$I$6)/$I$5 -> 0.055230517
B10: =B9+1 -> 2 | C10: Biaya Perjalanan Dinas (Luar Provinsi) | D10: 2.6287295e+09 | E10: =IFERROR(D10/12,0) -> 2.1906079e+08 | F10: =G10*12 -> 3.5487849e+09 | G10: 2.9573207e+08 | H10: =G10/($I$5*1000) -> 8.5555049 | I10: =(G10/$I$6)/$I$5 -> 0.53471906
B11: =B10+1 -> 3 | C11: Beban BBM Kendaraan | D11: 720175678 | E11: =IFERROR(D11/12,0) -> 60014640 | F11: =G11*12 -> 7.5618446e+08 | G11: 63015372 | H11: =G11/($I$5*1000) -> 1.8230296 | I11: =(G11/$I$6)/$I$5 -> 0.11393935
B12: =B11+1 -> 4 | C12: Beban Sewa Kendaraan | D12: 2428347903 | E12: =IFERROR(D12/12,0) -> 2.0236233e+08 | F12: =G12*12 -> 2220000000 | G12: 185000000 | H12: =G12/($I$5*1000) -> 5.352035 | I12: =(G12/$I$6)/$I$5 -> 0.33450219
B13: =B12+1 -> 5 | C13: Beban Kendaraan Lainnya | D13: 110862850 | E13: =IFERROR(D13/12,0) -> 9238570.8 | F13: =G13*12 -> 110862850 | G13: 9238570.8 | H13: =G13/($I$5*1000) -> 0.26727111 | I13: =(G13/$I$6)/$I$5 -> 0.016704444
B14: =B13+1 -> 6 | C14: Beban Sewa Bangunan / Inventaris / Aset | D14: 126990400 | E14: =IFERROR(D14/12,0) -> 10582533 | F14: =G14*12 -> 110000400 | G14: 9166700 | H14: =G14/($I$5*1000) -> 0.26519189 | I14: =(G14/$I$6)/$I$5 -> 0.016574493
B15: =B14+1 -> 7 | C15: Beban Penelitian, Percobaan & Pengembangan | D15: 108868060 | E15: =IFERROR(D15/12,0) -> 9072338.3 | F15: =G15*12 -> 100000000 | G15: 8333333.3 | H15: =G15/($I$5*1000) -> 0.24108266 | I15: =(G15/$I$6)/$I$5 -> 0.015067666
B16: =B15+1 -> 8 | C16: Beban Pemeliharaan Bangunan Rumah | D16: 203000 | E16: =IFERROR(D16/12,0) -> 16916.667 | F16: =G16*12 -> 0 | G16: 0 | H16: =G16/($I$5*1000) -> 0 | I16: =(G16/$I$6)/$I$5 -> 0
B17: =B16+1 -> 9 | C17: Beban Pemeliharaan Bangunan Perusahaan | D17: 108952486 | E17: =IFERROR(D17/12,0) -> 9079373.8 | F17: =G17*12 -> 1.1440011e+08 | G17: 9533342.5 | H17: =G17/($I$5*1000) -> 0.27579883 | I17: =(G17/$I$6)/$I$5 -> 0.017237427
B18: =B17+1 -> 10 | C18: Beban Pemeliharaan Mesin & Instalansi | D18: 32369030 | E18: =IFERROR(D18/12,0) -> 2697419.2 | F18: =G18*12 -> 33987482 | G18: 2832290.1 | H18: =G18/($I$5*1000) -> 0.081937924 | I18: =(G18/$I$6)/$I$5 -> 0.0051211203
B19: =B18+1 -> 11 | C19: Beban Pemeliharaan Jalan, Jembatan & Saluran Air | D19: 179265600 | E19: =IFERROR(D19/12,0) -> 14938800 | F19: =G19*12 -> 188228880 | G19: 15685740 | H19: =G19/($I$5*1000) -> 0.45378719 | I19: =(G19/$I$6)/$I$5 -> 0.028361699
B20: =B19+1 -> 12 | C20: Beban Pemeliharaan Alat Inventaris Kecil | D20: 253700695 | E20: =IFERROR(D20/12,0) -> 21141725 | F20: =G20*12 -> 2.6638573e+08 | G20: 22198811 | H20: =G20/($I$5*1000) -> 0.6422098 | I20: =(G20/$I$6)/$I$5 -> 0.040138112
B21: =B20+1 -> 13 | C21: Beban Pemakaian Inventaris Kecil | D21: 1859843066 | E21: =IFERROR(D21/12,0) -> 1.5498692e+08 | F21: =G21*12 -> 335473201 | G21: 27956100 | H21: =G21/($I$5*1000) -> 0.80876771 | I21: =(G21/$I$6)/$I$5 -> 0.050547982
B22: =B21+1 -> 14 | C22: Beban Iuran, Sumbangan, & Bina Lingkungan | D22: 694460474 | E22: =IFERROR(D22/12,0) -> 57871706 | F22: =G22*12 -> 2.6839105e+08 | G22: 22365921 | H22: =G22/($I$5*1000) -> 0.64704429 | I22: =(G22/$I$6)/$I$5 -> 0.040440268
B23: =B22+1 -> 15 | C23: Beban Instansi Kelembagaan | E23: =IFERROR(D23/12,0) -> 0 | F23: =G23*12 -> 60000000 | G23: 5000000 | H23: =G23/($I$5*1000) -> 0.1446496 | I23: =(G23/$I$6)/$I$5 -> 0.0090405997
B24: =B23+1 -> 16 | C24: Beban Pajak & Retribusi | D24: 659276883 | E24: =IFERROR(D24/12,0) -> 54939740 | F24: =G24*12 -> 1518332400 | G24: 126527700 | H24: =G24/($I$5*1000) -> 3.6604361 | I24: =(G24/$I$6)/$I$5 -> 0.22877726
B25: =B24+1 -> 17 | C25: Beban Premi Assuransi | E25: =IFERROR(D25/12,0) -> 0 | F25: =G25*12 -> 197000000 | G25: 16416667 | H25: =G25/($I$5*1000) -> 0.47493284 | I25: =(G25/$I$6)/$I$5 -> 0.029683302
B26: =B25+1 -> 18 | C26: Beban Penerangan | D26: 62716328 | E26: =IFERROR(D26/12,0) -> 5226360.7 | F26: =G26*12 -> 80400000 | G26: 6700000 | H26: =G26/($I$5*1000) -> 0.19383046 | I26: =(G26/$I$6)/$I$5 -> 0.012114404
B27: =B26+1 -> 19 | C27: Beban Persediaan Air | D27: 1756590 | E27: =IFERROR(D27/12,0) -> 146382.5 | F27: =G27*12 -> 6840000 | G27: 570000 | H27: =G27/($I$5*1000) -> 0.016490054 | I27: =(G27/$I$6)/$I$5 -> 0.0010306284
B28: =B27+1 -> 20 | C28: Beban Pemakaian Perlengkapan Kantor | D28: 1.1936208e+09 | E28: =IFERROR(D28/12,0) -> 99468402 | F28: =G28*12 -> 1.1936208e+09 | G28: 99468402 | H28: =G28/($I$5*1000) -> 2.8776128 | I28: =(G28/$I$6)/$I$5 -> 0.1798508
B29: =B28+1 -> 21 | C29: Beban Pengendalian Lingkungan (ISO 14000) | D29: 488020500 | E29: =IFERROR(D29/12,0) -> 40668375 | F29: =G29*12 -> 264000000 | G29: 22000000 | H29: =G29/($I$5*1000) -> 0.63645822 | I29: =(G29/$I$6)/$I$5 -> 0.039778639
B30: =B29+1 -> 22 | C30: Beban Sistem Manajemen Keselamatan & Kesehatan Kerja (SMK3) | D30: 68171900 | E30: =IFERROR(D30/12,0) -> 5680991.7 | F30: =G30*12 -> 258000000 | G30: 21500000 | H30: =G30/($I$5*1000) -> 0.62199326 | I30: =(G30/$I$6)/$I$5 -> 0.038874579
B31: =B30+1 -> 23 | C31: Beban Pendidikan & Pengembangan SDM | D31: 1186354647 | E31: =IFERROR(D31/12,0) -> 98862887 | F31: =G31*12 -> 10000000 | G31: 833333.33 | H31: =G31/($I$5*1000) -> 0.024108266 | I31: =(G31/$I$6)/$I$5 -> 0.0015067666
B32: =B31+1 -> 24 | C32: Beban Audit (Independent Auditor) | D32: 8.477783e+08 | E32: =IFERROR(D32/12,0) -> 70648192 | F32: =G32*12 -> 9.0712278e+08 | G32: 75593565 | H32: =G32/($I$5*1000) -> 2.1869157 | I32: =(G32/$I$6)/$I$5 -> 0.13668223
B33: =B32+1 -> 25 | C33: Beban Konsultan - Eksternal | D33: 245454645 | E33: =IFERROR(D33/12,0) -> 20454554 | F33: =G33*12 -> 2.7000011e+08 | G33: 22500009 | H33: =G33/($I$5*1000) -> 0.65092344 | I33: =(G33/$I$6)/$I$5 -> 0.040682715
B34: =B33+1 -> 26 | C34: Beban Insentif Karyawan | E34: =IFERROR(D34/12,0) -> 0 | F34: =G34*12 -> 0 | G34: 0 | H34: =G34/($I$5*1000) -> 0 | I34: =(G34/$I$6)/$I$5 -> 0
B35: =B34+1 -> 27 | C35: Beban Jasa Produksi Karyawan | E35: =IFERROR(D35/12,0) -> 0 | F35: =G35*12 -> 0 | G35: 0 | H35: =G35/($I$5*1000) -> 0 | I35: =(G35/$I$6)/$I$5 -> 0
B36: =B35+1 -> 28 | C36: Beban Uang Jasa (Jubilium, SHT, Dll) | D36: 188207400 | E36: =IFERROR(D36/12,0) -> 15683950 | F36: =G36*12 -> 207028140 | G36: 17252345 | H36: =G36/($I$5*1000) -> 0.49910894 | I36: =(G36/$I$6)/$I$5 -> 0.031194309
B37: =B36+1 -> 29 | C37: Beban Imbalan Pasca Kerja | D37: 4384212523 | E37: =IFERROR(D37/12,0) -> 3.6535104e+08 | F37: =G37*12 -> 666345107 | G37: 55528759 | H37: =G37/($I$5*1000) -> 1.6064425 | I37: =(G37/$I$6)/$I$5 -> 0.10040266
B38: =B37+1 -> 30 | C38: Beban Pengurusan Sertifikasi / Hak Merk / Izin / Dll | D38: 108648500 | E38: =IFERROR(D38/12,0) -> 9054041.7 | F38: =G38*12 -> 114080925 | G38: 9506743.8 | H38: =G38/($I$5*1000) -> 0.27502933 | I38: =(G38/$I$6)/$I$5 -> 0.017189333
B39: =B38+1 -> 31 | C39: Beban Entertainment | D39: 80056015 | E39: =IFERROR(D39/12,0) -> 6671334.6 | F39: =G39*12 -> 0 | G39: 0 | H39: =G39/($I$5*1000) -> 0 | I39: =(G39/$I$6)/$I$5 -> 0
B40: =B39+1 -> 32 | C40: Beban Akomodasi Rapat | D40: 84564877 | E40: =IFERROR(D40/12,0) -> 7047073.1 | F40: =G40*12 -> 88793121 | G40: 7399426.7 | H40: =G40/($I$5*1000) -> 0.21406482 | I40: =(G40/$I$6)/$I$5 -> 0.013379051
B41: =B40+1 -> 33 | C41: Beban Bonus Karyawan | E41: =IFERROR(D41/12,0) -> 0 | F41: =G41*12 -> 0 | G41: 0 | H41: =G41/($I$5*1000) -> 0 | I41: =(G41/$I$6)/$I$5 -> 0
B42: =B41+1 -> 34 | C42: Beban Tantiem | E42: =IFERROR(D42/12,0) -> 0 | F42: =G42*12 -> 0 | G42: 0 | H42: =G42/($I$5*1000) -> 0 | I42: =(G42/$I$6)/$I$5 -> 0
B43: =B42+1 -> 35 | C43: Beban Konsumsi | D43: 3864122096 | E43: =IFERROR(D43/12,0) -> 3.2201017e+08 | F43: =G43*12 -> 2223000000 | G43: 185250000 | H43: =G43/($I$5*1000) -> 5.3592675 | I43: =(G43/$I$6)/$I$5 -> 0.33495422
B44: =B43+1 -> 36 | C44: Beban Ekstra Fooding | D44: 810000 | E44: =IFERROR(D44/12,0) -> 67500 | F44: =G44*12 -> 0 | G44: 0 | H44: =G44/($I$5*1000) -> 0 | I44: =(G44/$I$6)/$I$5 -> 0
B45: =B44+1 -> 37 | C45: Beban Pemeriksaan Kesehatan / Perobatan | D45: 185612516 | E45: =IFERROR(D45/12,0) -> 15467710 | F45: =G45*12 -> 41405668 | G45: 3450472.3 | H45: =G45/($I$5*1000) -> 0.099821885 | I45: =(G45/$I$6)/$I$5 -> 0.0062388678
B46: =B45+1 -> 38 | C46: Beban Peringatan Hari Besar | D46: 300000 | E46: =IFERROR(D46/12,0) -> 25000 | F46: =G46*12 -> 25000000 | G46: 2083333.3 | H46: =G46/($I$5*1000) -> 0.060270665 | I46: =(G46/$I$6)/$I$5 -> 0.0037669165
B47: =B46+1 -> 39 | C47: Beban Perlengkapan Karyawan | D47: 497881607 | E47: =IFERROR(D47/12,0) -> 41490134 | F47: =G47*12 -> 420000000 | G47: 35000000 | H47: =G47/($I$5*1000) -> 1.0125472 | I47: =(G47/$I$6)/$I$5 -> 0.063284198
B48: =B47+1 -> 40 | C48: Beban Keperluan Dapur / Pantry | D48: 79298165 | E48: =IFERROR(D48/12,0) -> 6608180.4 | F48: =G48*12 -> 12458700 | G48: 1038225 | H48: =G48/($I$5*1000) -> 0.030035765 | I48: =(G48/$I$6)/$I$5 -> 0.0018772353
B49: =B48+1 -> 41 | C49: Beban Employee Gathering | E49: =IFERROR(D49/12,0) -> 0 | F49: =G49*12 -> 250000000 | G49: 20833333 | H49: =G49/($I$5*1000) -> 0.60270665 | I49: =(G49/$I$6)/$I$5 -> 0.037669165
B50: =B49+1 -> 42 | C50: Beban Kebersihan | D50: 11059767 | E50: =IFERROR(D50/12,0) -> 921647.25 | F50: =G50*12 -> 0 | G50: 0 | H50: =G50/($I$5*1000) -> 0 | I50: =(G50/$I$6)/$I$5 -> 0
D51: =SUM(D9:D50) -> 2.3796151e+10 | E51: =SUM(E9:E50) -> 1.9830126e+09 | F51: =SUM(F9:F50) -> 1.7232677e+10 | G51: =SUM(G9:G50) -> 1.4360564e+09 | H51: =SUM(H9:H50) -> 41.544995 | I51: =SUM(I9:I50) -> 2.5965622

Sheet Time Sheet Bulanan
A1: Nomor | B1: Tanggal | C1: Keterangan
C2: Refinery | D2: Fraksinasi
A3: 1 | B3: 45536
A4: 2 | B4: 45537
A5: 3 | B5: 45538
A6: 4 | B6: 45539
A7: 5 | B7: 45540
A8: 6 | B8: 45541
A9: 7 | B9: 45542
A10: 8 | B10: 45543
A11: 9 | B11: 45544
A12: 10 | B12: 45545
A13: 11 | B13: 45546
A14: 12 | B14: 45547
... A25: 23 | B25: 45558
A26: 24 | B26: 45559 | C26: Update tgal 24/09/2024 Refinery * 07.00 ref HOLD * 22.00 steam masuk ke plant * 01.20 ref firing hpb * 02.00 sirkulasi * 03.00-07.00 plant HOLD terkait pressure gas HPB drop | D26: Stop sementara & aktifitas cleaning chiller
A27: 25 | B27: 45560 | C27: Refinery * 07.40 start sirkulasi | D27: Fraksinasi * Stop sementara dan pagi ini kunci mainhole chiller pak
A28: 26 | B28: 45561
A29: 27 | B29: 45562
A30: 28 | B30: 45563
A31: 29 | B31: 45564
A32: 30 | B32: 45565

Sheet Flow Meter
A2: TOTAL TONASE FLOWMETER PRODUK
A3: REFINERY
A5: TANGGAL VALIDASI
A6: NO | B6: NAMA PRODUK | C6: 01 Juli | D6: 02 Juli | E6: 03 Juli | F6: 04 Juli | G6: 05 Juli | H6: 06 Juli | I6: 07 Juli | J6: 08 Juli | K6: 09 Juli | L6: 10 Juli | M6: 11 Juli | N6: 12 Juli | O6: 13 Juli | P6: 14 Juli | Q6: 15 Juli | R6: TOTAL | S6: Sounding | T6: Yield Theory | U6: Yield Aktual
A7: 1 | B7: CPO | C7: ='[6]01 '!$Q$14 -> 744924 | D7: ='[6]02'!$Q$14 -> 743972 | E7: ='[6]03'!$Q$14 -> 1048435 | F7: ='[6]04'!$Q$14 -> 1114821 | G7: 248126 | H7: 389481 | I7: 104168 | J7: 320907 | K7: 100743 | L7: 512647 | M7: 441064 | N7: 524002 | O7: 568358 | P7: 430750 | R7: =SUM(C7:Q7) -> 7292398
A8: 2 | B8: RBDPO | C8: 713300 | D8: 708000 | E8: 993100 | F8: 1056000 | G8: 237021 | H8: 365100 | I8: 44001 | J8: 300010 | K8: 94507 | L8: 488153 | M8: 414337 | N8: 492952 | O8: 532902 | P8: 497845 | R8: =SUM(C8:Q8) -> 6937228 | T8: =R8/R7 -> 0.95129586 | U8: =S8/S7 -> #DIV/0! | W8: =4984655+#REF! -> #REF!
A9: 3 | B9: PFAD | C9: ='[6]01 '!$P$25 -> 25659 | D9: 28786 | E9: ='[6]03'!$P$25 -> 46938 | F9: ='[6]04'!$P$24 -> 48667 | G9: 8070 | H9: 19280 | I9: 3234 | J9: 18283 | K9: 5131 | L9: 20426 | M9: 23275 | N9: 27655 | O9: 25803 | P9: 20173 | R9: =SUM(C9:Q9) -> 321380 | T9: =R9/R7 -> 0.044070551 | U9: =S9/S7 -> #DIV/0!
C10: =C8/C7 -> 0.95754735 | D10: =D8/D7 -> 0.95164872 | E10: =E8/E7 -> 0.94722133 | F10: =F8/F7 -> 0.94723727 | G10: =G8/G7 -> 0.95524451 | H10: =H8/H7 -> 0.93740131 | I10: =I8/I7 -> 0.42240419 | J10: =J8/J7 -> 0.93488145 | ... P10: =P8/P7 -> 1.1557632
C11: =C9/C7*1 -> 0.034445125 | D11: =D9/D7*1 -> 0.038692316 | E11: =E9/E7*1 -> 0.044769585 | F11: =F9/F7*1 -> 0.043654542 | G11: =G9/G7*1 -> 0.032523798 | H11: =H9/H7*1 -> 0.049501773 | I11: =I9/I7*1 -> 0.031046003 | J11: =J9/J7*1 -> 0.056972892 | ... P11: =P9/P7*1 -> 0.046832269
B12: LOSIS | C12: =(C7-C8-C9)/C7 -> 0.0080075283 | D12: =(D7-D8-D9)/D7 -> 0.0096589657 | E12: =(E7-E8-E9)/E7 -> 0.0080090802 | F12: =(F7-F8-F9)/F7 -> 0.0091081887 | G12: =(G7-G8-G9)/G7 -> 0.012231689 | H12: =(H7-H8-H9)/H7 -> 0.013096916 | I12: =(I7-I8-I9)/I7 -> 0.5465498 | J12: =(J7-J8-J9)/J7 -> 0.0081456621 | ... P12: =(P7-P8-P9)/P7 -> -0.20259547
A14: TANGGAL flow meter
A15: NO | B15: NAMA PRODUK | C15: 01 Juli | D15: 02 Juli | E15: 03 Juli | F15: 04 Juli | G15: 05 Juli | H15: 06 Juli | I15: 07 Juli | J15: 08 Juli | K15: 09 Juli | L15: 10 Juli | M15: 11 Juli | N15: 12 Juli | O15: 13 Juli | P15: 14 Juli | Q15: 15 Juli | R15: TOTAL | S15: Sounding | T15: Yield Theory | U15: Yield Aktual
A16: 1 | B16: CPO | C16: 680800 | D16: 806400 | E16: 858600 | F16: 898100 | G16: 26100 | H16: 513200 | I16: 119200 | J16: 208900 | K16: 147700 | L16: 425800 | M16: 347900 | N16: 459100 | O16: 509200 | P16: 396700 | Q16: 20200 | R16: =SUM(C16:Q16) -> 6417900 | S16: =5745000+14073+R19 -> 7292813
A17: 2 | B17: RBDPO | C17: 722400 | D17: 826700 | E17: 980700 | F17: 980600 | G17: 19900 | H17: 582000 | I17: 150500 | J17: 215300 | K17: 70837 | L17: 488153 | M17: 379337 | N17: 502200 | O17: 535800 | P17: 412600 | Q17: 92100 | R17: =SUM(C17:Q17) -> 6959127 | S17: =SUM(C17:M17)+R20 -> 6940126 | T17: =R17/R16 -> 1.0843309 | U17: =S17/S16 -> 0.9516391 | W17: =4984655+R20 -> 6508354
A18: 3 | B18: PFAD | C18: 37300 | D18: 38700 | E18: 49500 | F18: 47100 | G18: 3800 | H18: 30300 | I18: 9300 | J18: 14000 | K18: 14800 | L18: 25100 | M18: 23400 | N18: 23900 | O18: 26800 | P18: 22200 | Q18: 5900 | R18: =SUM(C18:Q18) -> 372100 | S18: =248746+R21 -> 322377 | T18: =R18/R16 -> 0.057978466 | U18: =S18/S16 -> 0.044204753
C19: =C17/C16 -> 1.0611046 | D19: =D17/D16 -> 1.0251736 | E19: =E17/E16 -> 1.1422082 | F19: =F17/F16 -> 1.0918606 | G19: =G17/G16 -> 0.76245211 | H19: =H17/H16 -> 1.1340608 | I19: =I17/I16 -> 1.2625839 | J19: =J17/J16 -> 1.0306367 | K19: =K17/K16 -> 0.47960054 | L19: 269515 | M19: CPO | N19: 534002 | O19: 568773 | P19: 430750 | Q19: 269300 | R19: =L19+N19+O19+P19-Q19 -> 1533740 | U19: =100%-U17-U18 -> 0.0041561466 | V19: Losses
M20: RBDPO | N20: 492952 | O20: 532902 | P20: 497845 | R20: =SUM(N20:P20) -> 1523699
N21: 27655 | O21: 25803 | P21: 20173 | R21: =SUM(N21:P21) -> 73631
B22: Nb : | C22: 1. 5.745.000 adalaha angka consume CPO tanggal 1 - 11 ( Opening Stock + Incoming - Closing tanggal 11 )
C23: 2. 14.073 ( Beda Pembacaan antara sounding dan timbangan )
C24: 3. 1.533.740 adalah angka sounding CPO 12, 13, 14
A25: FRAKSINASI
A26: TANGGAL
A27: NO | B27: NAMA PRODUK | C27: 01 Juli | D27: 02 Juli | E27: 03 Juli | F27: 04 Juli | G27: 05 Juli | H27: 06 Juli | I27: 07 Juli | J27: 08 Juli | K27: 09 Juli | L27: 10 Juli | M27: 11 Juli | N27: 12 Juli | O27: 13 Juli | P27: 14 Juli | Q27: 15 Juli | R27: TOTAL | S27: Sounding | T27: Yield
A28: 1 | B28: RBDPO | C28: 667300 | D28: 695000 | E28: 814100 | F28: 760000 | G28: 620300 | H28: 587100 | I28: 118500 | J28: 0 | K28: 253000 | L28: 0 | M28: 466900 | N28: 258400 | O28: 584400 | P28: 680200 | R28: =SUM(C28:Q28) -> 6505200
A29: 2 | B29: OLEIN IV 58 | C29: 518400 | D29: 487200 | E29: 539100 | F29: 571900 | G29: 554300 | H29: 449900 | I29: 209900 | J29: 0 | K29: 297100 | L29: 0 | M29: 472500 | N29: 207400 | O29: 239100 | P29: 414100 | R29: =SUM(C29:Q29) -> 4960900
A30: 3 | B30: STEARIN | C30: 207500 | D30: 202900 | E30: 215500 | F30: =27400+151100+55600 -> 234100 | G30: 213300 | H30: 183700 | I30: 104800 | J30: 0 | K30: 93900 | L30: 0 | M30: 172400 | N30: 111100 | O30: 81200 | P30: 193200 | R30: =SUM(C30:Q30) -> 2013600
O32: STOCK OPNAME | R32: =1311190 -> 1311190
O33: TOTAL TERIMA 1- 11 TIMBANGAN | R33: 3865830
O34: PIPANISASI DAN GK 1 - 11 | R34: 1888995
O35: STOCK AKHIR OPNAME 11 JULI | R35: 1320540.6
R36: =R32+R33+R34-R35 -> 5745474.4
O38: STOCK OPNAME 1 JULI | R38: 178489.22
O39: TOTAL FLOW METER 11 | R39: =SUM(C28:M28) -> 4982200
O40: STOCK AKHIR OPNAME 11 JULI
