Workbook

Sheet Agustus - 2024
C1: PRODUCTION REPORT
C2: No | D2: ITEM | E2: Budget / Norma | F2: UoM | G2: Agustus | AN2: TOTAL MONTHLY (Kg)
G3: 1 | H3: 2 | I3: 3 | J3: 4 | K3: 5 | L3: 6 | M3: 7 | N3: 8 | O3: 9 | P3: 10 | Q3: 11 | R3: 12 | S3: 13 | T3: 14 | U3: 15 | V3: 16 | W3: 17 | X3: 18 | Y3: 19 | Z3: 20 | AA3: 21 | AB3: 22 | AC3: 23 | AD3: 24 | AE3: 25 | AF3: 26 | AG3: 27 | AH3: 28 | AI3: 29 | AJ3: 30 | AK3: 31 | AL3: 31
C4: 1 | D4: PRODUCTION | AN4: Production
D5: Refinery | AN5: Refinery
D6: Running Days | F6: Day | G6: 1 | H6: 1 | I6: 1 | J6: 1 | K6: 1 | L6: 1 | M6: 1 | N6: 1 | O6: 1 | P6: 1 | Q6: 1 | R6: 1 | S6: 1 | T6: 1 | U6: 1 | V6: 1 | W6: 0 | X6: 0 | Y6: 0 | Z6: 1 | AA6: 1 | AB6: 1 | AC6: 1 | AD6: 1 | AE6: 1 | AF6: 1 | AG6: 1 | AH6: 1 | AI6: 1 | AJ6: 1 | AK6: 1 | AN6: =SUM(G6:AL6) -> 28
D7: Incoming CPO | F7: Kg | G7: ='[1]01'!$P$13 -> 489345 | H7: ='[2]02'!$P$14 -> 1012278 | I7: ='[2]03'!$P$14 -> 802407 | J7: =0 -> 0 | K7: =453628+'[3]05'!$P$13 -> 714345 | L7: 449365 | M7: ='[3]07'!$P$14 -> 211955 | N7: 417327 | O7: 682500 | P7: 472840 | R7: 1150409 | S7: ='[4]13'!$P$14 -> 518236 | T7: ='[4]14'!$P$14 -> 327333 | U7: 607907 | V7: ='[5]16'!$P$14 -> 281390 | W7: ='[5]17'!$P$14 -> 161291 | X7: ='[5]18'!$P$14 -> 64256 | Y7: 1642352 | Z7: ='[6]20'!$P$15 -> 990208 | AA7: ='[7]21'!$P$15 -> 1561101 | AB7: ='[8]22'!$P$15 -> 1408409 | AC7: ='[9]23'!$P$15 -> 395196 | AD7: ='[9]24'!$P$15 -> 851110 | AE7: ='[9]25'!$P$15 -> 0 | AF7: 804622 | AG7: ='[10]27'!$P$15 -> 583740 | AH7: ='[11]28'!$P$15 -> 937351 | AI7: ='[12]29'!$P$15 -> 254530 | AJ7: ='[13]30'!$P$15 -> 596514 | AK7: ='[5]31 Stok Opname'!$P$15 -> 801007 | AN7: =SUM(G7:AL7) -> 19189324 | AO7: =AVERAGE(H7:AA7) -> 635131.58
D8: Ratio Run CPO | F8: % | G8: =G9/2200000*100 -> 64.436273 | H8: =H9/2200000*100 -> 50.225045 | I8: =I9/2200000*100 -> 47.389545 | J8: =J9/2200000*100 -> 48.294682 | K8: =K9/2200000*100 -> 18.650409 | L8: =L9/2200000*100 -> 34.512318 | M8: =M9/2200000*100 -> 9.8673182 | N8: =N9/2200000*100 -> 15.987364 | ... AL8: =AL9/2200000*100 -> 0 | AN8: =AVERAGE(G8:AK8) -> 33.834848
D9: CPO Consume Total | E9: 36359000 | F9: Kg | G9: ='[3]01'!$Q$13+'[3]01'!$Q$11 -> 1417598 | H9: ='[3]02'!$Q$14 -> 1104951 | I9: 1042570 | J9: ='[3]04'!$Q$14 -> 1062483 | K9: ='[3]05'!$Q$11 -> 410309 | L9: ='[3]06'!$Q$9+'[3]06'!$Q$13 -> 759271 | M9: ='[3]07'!$Q$14 -> 217081 | N9: =348722+3000 -> 351722 | O9: 743456 | P9: 1152731 | Q9: 521179 | R9: 337454 | S9: =1333353 -> 1333353 | T9: ='[14]14 Rev'!$Q$14 -> 723542 | U9: 261913 | V9: ='[5]16'!$Q$14 -> 843222 | W9: 0 | X9: 0 | Y9: 0 | Z9: ='[6]20'!$Q$15 -> 997925 | AA9: ='[7]21'!$Q$15 -> 1452148 | AB9: ='[8]22'!$Q$15 -> 720213 | AC9: ='[9]23'!$Q$15 -> 976465 | AD9: ='[9]24'!$Q$15 -> 1563156 | AE9: ='[9]25'!$Q$15 -> 1396380 | AF9: 225122 | AG9: ='[10]27'!$Q$15 -> 672238 | AH9: ='[11]28'!$Q$15 -> 1017095 | AI9: ='[12]29'!$Q$15 -> 596307 | AJ9: ='[13]30'!$Q$15 -> 347783 | AK9: ='[5]31 Stok Opname'!$Q$10+'[5]31 Stok Opname'!$Q$14 -> 827699 | AN9: =SUM(G9:AL9) -> 23075366 | AO9: =AN9/E9 -> 0.63465348 | AP9: =AN9/AN6 -> 824120.21
D10: CPO Consume Poram | E10: 29045000 | F10: Kg | G10: =G9-G33-G42 -> 1417598 | H10: =H9-H33-H42 -> 1104951 | I10: =I9-I33-I42 -> 1042570 | J10: =J9-J33-J42 -> 1062483 | K10: =K9-K33-K42 -> 410309 | L10: =L9-L33-L42 -> 759271 | M10: =M9-M33-M42 -> 217081 | N10: =N9-N33-N42 -> 351722 | ... AG10: =AG9-AG33-AG42 -> 672238 | AH10: =AH9-AH33-AH42-AH11 -> 832400 | AI10: =AI9-AI33-AI42 -> 596307 | AJ10: =AJ9-AJ33-AJ42 -> 347783 | AK10: =AK9-AK33-AK42 -> 827699 | AL10: =AL9-AL33-AL42 -> 0 | AN10: =SUM(G10:AL10) -> 22890671
D11: CPO Consume Brand | E11: 7314000 | F11: Kg | G11: =G33+G42 -> 0 | H11: =H33+H42 -> 0 | I11: =I33+I42 -> 0 | J11: =J33+J42 -> 0 | K11: =K33+K42 -> 0 | L11: =L33+L42 -> 0 | M11: =M33+M42 -> 0 | N11: =N33+N42 -> 0 | ... AG11: =AG33+AG42 -> 0 | AH11: 184695 | AI11: =AI33+AI42 -> 0 | AJ11: =AJ33+AJ42 -> 0 | AK11: =AK33+AK42 -> 0 | AL11: =AL33+AL42 -> 0 | AN11: =SUM(G11:AL11) -> 184695
D12: - FFA | E12: 5 | F12: % | G12: 4.15 | H12: 4.34 | I12: 4.14 | J12: =(3.85+3.7)/2 -> 3.775 | K12: 4.16 | L12: =(4.09+3.46)/2 -> 3.775 | M12: 4.3 | N12: 4.32 | O12: 4.32 | P12: 4.475 | Q12: 3.79 | R12: 4.09 | S12: =(4.1+3.57)/2 -> 3.835 | T12: =(4.1+3.5)/2 -> 3.8 | U12: 4.3 | V12: =(4.1+4.35)/2 -> 4.225 | W12: 0 | X12: 0 | Y12: 0 | Z12: =(3.8+3.65)/2 -> 3.725 | AA12: =(3.71+3.62)/2 -> 3.665 | AB12: 3.59 | AC12: =(2.84+3.78+3.59)/3 -> 3.4033333 | AD12: =(3.92+3.85)/2 -> 3.885 | AE12: =(3.85+3.52)/2 -> 3.685 | AF12: 4.09 | AG12: 3.92 | AH12: =(4.04+3.51)/2 -> 3.775 | AI12: =(4.01+4.12+3.58)/3 -> 3.9033333 | AJ12: 3.7 | AK12: =(3.91+3.66)/2 -> 3.785 | AN12: =SUM(G12:AK12)/AN6 -> 3.9614881
D13: - Moist & Impurities | E13: 0.5 | F13: % | G13: 0.42 | H13: 0.41 | I13: 0.41 | J13: =(0.4+0.42)/2 -> 0.41 | K13: 0.43 | L13: 0.47 | M13: 0.42 | N13: 0.42 | O13: 0.42 | P13: 0.42 | Q13: 0.49 | R13: 0.44 | S13: =(0.4+0.48)/2 -> 0.44 | T13: 0.49 | U13: 0.4 | V13: =(0.4+0.42)/2 -> 0.41 | W13: 0 | X13: 0 | Y13: 0 | Z13: =(0.42+0.46)/2 -> 0.44 | AA13: =(0.44+0.47)/2 -> 0.455 | AB13: 0.42 | AC13: =(0.34+0.4+0.48)/3 -> 0.40666667 | AD13: =(0.42+0.41)/2 -> 0.415 | AE13: =(0.41+0.46)/2 -> 0.435 | AF13: 0.42 | AG13: 0.46 | AH13: =(0.39+0.44)/2 -> 0.415 | AI13: =(0.44+0.38+0.46)/3 -> 0.42666667 | AJ13: 0.43 | AK13: =(0.4+0.48)/2 -> 0.44 | AN13: =SUM(G13:AK13)/AN6 -> 0.43083333
D14: - DOBI | E14: 2,20 Min | F14: % | G14: 2.21 | H14: 2.21 | I14: 2.22 | J14: 2.21 | K14: 2.22 | L14: 2.21 | M14: 2.21 | N14: 2.21 | O14: 2.21 | P14: 2.21 | Q14: 2.21 | R14: 2.22 | S14: 2.21 | T14: 2.22 | U14: 2.21 | V14: 2.21 | W14: 0 | X14: 0 | Y14: 0 | Z14: 2.222 | AA14: 2.21 | AB14: 2.21 | AC14: 2.22 | AD14: 2.21 | AE14: 2.22 | AF14: 2.21 | AG14: 2.2 | AH14: 2.21 | AI14: 2.22 | AJ14: 2.21 | AK14: 2.22 | AN14: =SUM(G14:AL14)/AN6 -> 2.2129286
D15: Product | AN15: Product
D16: RBDPO | E16: 34458000 | F16: Kg | G16: ='[1]01'!$P$17 -> 1337671 | H16: ='[2]02'!$P$17 -> 1062915 | I16: ='[2]03'!$P$17 -> 1004399 | J16: ='[2]04'!$P$17 -> 1014004 | K16: ='[3]05'!$P$17 -> 375835 | L16: 751036 | M16: ='[3]07'!$P$17 -> 205973 | N16: 300695 | O16: 723509 | P16: 1082408 | Q16: 522678 | R16: 291425 | S16: =1251548+12500 -> 1264048 | T16: =688994-25961 -> 663033 | U16: =286771-30559 -> 256212 | V16: ='[5]16'!$P$17-23295 -> 764988 | W16: 0 | X16: 0 | Y16: 0 | Z16: ='[6]20'!$P$18+Z20+'OIP Refinery'!G24 -> 974136 | AA16: ='[7]21'!$P$17+AA20+'OIP Refinery'!G25 -> 1374725 | AB16: ='[8]22'!$P$18+AB20 -> 684147 | AC16: ='[9]23'!$P$18+AC20-24268 -> 886585 | AD16: ='[9]24'!$P$18+'OIP Refinery'!G28 -> 1543843 | AE16: ='[9]25'!$P$18-10084 -> 1313723 | AF16: =187550+33039 -> 220589 | AG16: ='[10]27'!$P$18-4779 -> 640699 | AH16: ='[11]28'!$P$18+AH20+'OIP Refinery'!G32 -> 983679.2 | AI16: ='[12]29'!$P$18-26834 -> 796939 | AJ16: ='[13]30'!$P$18+7092 -> 318511 | AK16: ='[5]31 Stok Opname'!$P$18+'OIP Refinery'!G35 -> 793401 | AN16: =SUM(G16:AL16) -> 22151806
D17: PFAD | E17: 1636000 | F17: Kg | G17: ='[1]01'!$P$23 -> 54840 | H17: ='[2]02'!$P$25 -> 43942 | I17: ='[2]03'!$P$25 -> 37168 | J17: ='[2]04'!$P$25 -> 43898 | K17: ='[3]05'!$P$25 -> 17690 | L17: 28851 | M17: ='[3]07'!$P$25 -> 8686 | N17: 20527 | O17: 25468 | P17: 50238 | Q17: 20927 | R17: 15400 | S17: 57789 | T17: 27742 | U17: 15397 | V17: ='[5]16'!$P$25 -> 41535 | W17: 0 | X17: 0 | Y17: 0 | Z17: ='[6]20'!$P$26 -> 45493 | AA17: ='[7]21'!$P$26 -> 54837 | AB17: ='[8]22'!$P$26 -> 28814 | AC17: ='[9]23'!$P$26 -> 42594 | AD17: ='[9]24'!$P$26 -> 58048 | AE17: ='[9]25'!$P$26 -> 53833 | AF17: 13940 | AG17: ='[10]27'!$P$26 -> 30763 | AH17: ='[11]28'!$P$26 -> 35257 | AI17: ='[12]29'!$P$26 -> 25789 | AJ17: ='[13]30'!$P$26 -> 13679 | AK17: ='[5]31 Stok Opname'!$P$26 -> 34315 | AN17: =SUM(G17:AL17) -> 947460
D18: Fractionation
D19: Running Days | F19: Day | G19: 1 | H19: 1 | I19: 1 | J19: 1 | K19: 1 | L19: 1 | M19: 1 | N19: 1 | O19: 1 | P19: 1 | Q19: 1 | R19: 1 | S19: 1 | T19: 1 | U19: 1 | V19: 1 | W19: 1 | X19: 0 | Y19: 0 | Z19: 1 | AA19: 1 | AB19: 1 | AC19: 1 | AD19: 1 | AE19: 1 | AF19: 1 | AG19: 1 | AH19: 1 | AI19: 1 | AJ19: 1 | AK19: 1 | AN19: =SUM(G19:AL19) -> 29
D20: Filling Langsung CR Fr Refinery | F20: Kg | K20: 0 | L20: 0 | M20: 0 | N20: 0 | O20: 0 | P20: 0 | Q20: 0 | R20: 0 | S20: 0 | T20: 0 | U20: 0 | V20: 0 | W20: 0 | X20: 0 | Y20: 0 | Z20: 118100 | AA20: 935500 | AB20: 219100 | AC20: 230700 | AD20: 0 | AE20: 0 | AF20: 0 | AG20: 0 | AH20: 175900 | AI20: 0 | AJ20: 0 | AK20: 0 | AN20: =SUM(G20:AK20) -> 1679300
D21: Total Filling Crystalizer ( Feed ) | F21: Kg | G21: ='[13]01'!$Q$17 -> 858578 | H21: ='[13]02'!$Q$17 -> 1054796 | I21: ='[13]03'!$Q$17 -> 860932 | J21: ='[13]04'!$Q$17 -> 922447 | K21: ='[13]05'!$Q$17 -> 1038779 | L21: ='[13]06'!$Q$17 -> 1410359 | M21: ='[13]07'!$Q$17 -> 1171827 | N21: ='[13]08'!$Q$17 -> 1048480 | O21: ='[13]09'!$Q$17 -> 518065 | P21: ='[13]10'!$Q$17 -> 1272374 | Q21: ='[13]11'!$Q$17 -> 702972 | R21: ='[13]12'!$Q$17 -> 50573 | S21: ='[13]13'!$Q$17 -> 931812 | T21: ='[13]14'!$Q$17 -> 1278793 | U21: ='[13]15'!$Q$17 -> 0 | V21: ='[5]16'!$Q$17 -> 895292 | W21: ='[5]17'!$Q$17 -> 266317 | X21: ='[13]15'!$Q$17 -> 0 | Y21: ='[13]15'!$Q$17 -> 0 | Z21: ='[6]20'!$Q$18+Z20 -> 574027 | AA21: ='[7]21'!$Q$18+AA20 -> 1109871 | AB21: =AB20+'[8]22'!$Q$18 -> 1144787 | AC21: ='[9]23'!$Q$18+AC20 -> 358903 | AD21: ='[9]24'!$Q$18 -> 1073186 | AE21: ='[9]25'!$Q$18 -> 806379 | AF21: 813937 | AG21: ='[10]27'!$Q$18 -> 809229 | AH21: ='[11]28'!$Q$18+AH20 -> 654036 | AI21: ='[12]29'!$Q$18 -> 926106 | AJ21: ='[13]30'!$Q$18 -> 862504 | AK21: ='[5]31 Stok Opname'!$Q$18 -> 1036869 | AN21: =SUM(G21:AK21) -> 24452230 | AO21: =AN21/E16 -> 0.70962418
D22: Total Proses RBDPO | F22: Kg | G22: =SUM(G25,G29,G34,G38,G43) -> 930616 | H22: =SUM(H25,H29,H34,H38,H43) -> 971961 | I22: =SUM(I25,I29,I34,I38,I43) -> 860808 | J22: =SUM(J25,J29,J34,J38,J43) -> 963967 | K22: =SUM(K25,K29,K34,K38,K43) -> 1052818 | L22: =SUM(L25,L29,L34,L38,L43) -> 1321319 | M22: =SUM(M25,M29,M34,M38,M43) -> 1212660 | N22: =SUM(N25,N29,N34,N38,N43) -> 1250229 | ... AK22: =SUM(AK25,AK29,AK34,AK38,AK43) -> 983160 | AN22: =SUM(G22:AK22) -> 24206356
D23: Sisa Filling Crystalizer | F23: Kg | G23: =G21-G22 -> -72038 | H23: =H21-H22 -> 82835 | I23: =I21-I22 -> 124 | J23: =J21-J22 -> -41520 | K23: =K21-K22 -> -14039 | L23: =L21-L22 -> 89040 | M23: =M21-M22 -> -40833 | N23: =N21-N22 -> -201749 | ... AK23: =AK21-AK22 -> 53709 | AN23: =SUM(G23:AK23) -> 245874
D24: Fractionation OLEIN IV 56 | AN24: Olein IV 56
D25: RBDPO Consume | F25: Kg | G25: =G26+G27 -> 351441 | H25: =H26+H27 -> 578725 | I25: =I26+I27 -> 0 | J25: =J26+J27 -> 0 | K25: =K26+K27 -> 432307 | L25: =L26+L27 -> 1321319 | M25: =M26+M27 -> 1212660 | N25: =N26+N27 -> 1250229 | ... AK25: =AK26+AK27 -> 0 | AN25: =SUM(G25:AL25) -> 14223412
D26: OLEIN IV 56 | F26: Kg | G26: ='[1]01'!$P$20 -> 310941 | H26: ='[2]02'!$P$20 -> 518225 | I26: 0 | J26: 0 | K26: ='[3]05'!$P$20 -> 384558 | L26: 1080575 | M26: ='[3]07'!$P$22 -> 1006716 | N26: 1023788 | O26: 665308 | P26: 722385 | Q26: 913100 | R26: 165357 | S26: 478290 | T26: 1006655 | U26: 329308 | V26: ='[5]16'!$P$20 -> 558630 | W26: ='[5]17'!$P$20 -> 355043 | X26: 0 | Y26: 0 | Z26: ='[6]20'!$P$21 -> 237525 | AA26: ='[14]21'!$P$23 -> 673349 | AB26: ='[8]22'!$P$21 -> 872454 | AC26: ='[9]23'!$P$21 -> 368020 | AD26: 0 | AE26: 0 | AF26: 0 | AG26: 0 | AH26: 0 | AI26: 0 | AJ26: 0 | AK26: 0 | AL26: 0 | AN26: =SUM(G26:AL26) -> 11670227
D27: STEARIN | F27: Kg | G27: 40500 | H27: 60500 | I27: 0 | J27: 0 | K27: 47749 | L27: 240744 | M27: ='[3]07'!$P$30 -> 205944 | N27: 226441 | O27: 145526 | P27: 152583 | Q27: 215093 | R27: 43380 | S27: 85165 | T27: 194412 | U27: 131652 | V27: ='[5]16'!$P$29 -> 86388 | W27: ='[5]17'!$P$30 -> 137403 | X27: 0 | Y27: 0 | Z27: ='[6]20'!$P$29 -> 47314 | AA27: ='[14]21'!$P$30 -> 185623 | AB27: ='[8]22'!$P$27 -> 246668 | AC27: 60100 | AD27: 0 | AE27: 0 | AF27: 0 | AG27: 0 | AH27: 0 | AI27: 0 | AJ27: 0 | AK27: 0 | AL27: 0 | AN27: =SUM(G27:AL27) -> 2553185 | AS27: =AN27+AN31+AN36+AN40+AN46 -> 5456593
D28: Fractionation OLEIN IV 57 ( Bulk ) | AN28: Olein IV 57 ( Bulk )
D29: RBDPO Consume | F29: Kg | G29: =G30+G31 -> 0 | H29: =H30+H31 -> 0 | I29: =I30+I31 -> 0 | J29: =J30+J31 -> 0 | L29: =L30+L31 -> 0 | M29: =M30+M31 -> 0 | N29: =N30+N31 -> 0 | O29: =O30+O31 -> 0 | P29: =P30+P31 -> 0 | Q29: =Q30+Q31 -> 0 | R29: =R30+R31 -> 0 | S29: =S30+S31 -> 0 | ... AL29: =AL30+AL31 -> 0 | AN29: =SUM(G29:AK29) -> 0
D30: OLEIN IV 57 | F30: Kg | G30: 0 | H30: 0 | I30: 0 | J30: 0 | K30: 0 | L30: 0 | M30: 0 | N30: 0 | O30: 0 | P30: 0 | Q30: 0 | R30: 0 | S30: 0 | T30: 0 | U30: 0 | V30: 0 | W30: 0 | X30: 0 | Y30: 0 | Z30: 0 | AA30: 0 | AB30: 0 | AC30: 0 | AD30: 0 | AE30: 0 | AF30: 0 | AG30: 0 | AH30: 0 | AI30: 0 | AJ30: 0 | AK30: 0 | AL30: 0 | AN30: =SUM(G30:AK30) -> 0
D31: STEARIN | F31: Kg | G31: 0 | H31: 0 | I31: 0 | J31: 0 | K31: 0 | L31: 0 | M31: 0 | N31: 0 | O31: 0 | P31: 0 | Q31: 0 | R31: 0 | S31: 0 | T31: 0 | U31: 0 | V31: 0 | W31: 0 | X31: 0 | Y31: 0 | Z31: 0 | AA31: 0 | AB31: 0 | AC31: 0 | AD31: 0 | AE31: 0 | AF31: 0 | AG31: 0 | AH31: 0 | AI31: 0 | AJ31: 0 | AK31: 0 | AL31: 0 | AN31: =SUM(G31:AK31) -> 0
D32: Fractionation OLEIN IV 57 ( Retail ) | AN32: Olein IV 57 ( Retail )
D33: CPO Consume | F33: Kg | P33: 0 | Q33: 0 | R33: 0 | S33: 0 | T33: 0 | U33: 0 | V33: 0 | W33: 0 | X33: 0 | Y33: 0 | Z33: 0 | AA33: 0 | AB33: 0 | AC33: 0 | AD33: 0 | AE33: 0 | AF33: 0 | AG33: 0 | AH33: 0 | AI33: 0 | AJ33: 0 | AK33: 0 | AL33: 0 | AN33: =SUM(G33:AK33) -> 0
D34: RBDPO Brand Consume | F34: Kg | G34: =G35+G36 -> 0 | H34: =H35+H36 -> 0 | I34: =I35+I36 -> 0 | J34: =J35+J36 -> 0 | K34: =K35+K36 -> 0 | L34: =L35+L36 -> 0 | M34: =M35+M36 -> 0 | N34: =N35+N36 -> 0 | ... AL34: =AL35+AL36 -> 0 | AN34: =SUM(G34:AK34) -> 0
D35: OLEIN IV 57 Low Color | F35: Kg | G35: 0 | H35: 0 | I35: 0 | J35: 0 | K35: 0 | L35: 0 | M35: 0 | N35: 0 | O35: 0 | P35: 0 | Q35: 0 | R35: 0 | S35: 0 | T35: 0 | U35: 0 | V35: 0 | W35: 0 | X35: 0 | Y35: 0 | Z35: 0 | AA35: 0 | AB35: 0 | AC35: 0 | AD35: 0 | AE35: 0 | AF35: 0 | AG35: 0 | AH35: 0 | AI35: 0 | AJ35: 0 | AN35: =SUM(G35:AK35) -> 0
D36: STEARIN | F36: Kg | G36: 0 | H36: 0 | I36: 0 | J36: 0 | K36: 0 | L36: 0 | M36: 0 | N36: 0 | O36: 0 | P36: 0 | Q36: 0 | R36: 0 | S36: 0 | T36: 0 | U36: 0 | V36: 0 | W36: 0 | X36: 0 | Y36: 0 | Z36: 0 | AA36: 0 | AB36: 0 | AC36: 0 | AD36: 0 | AE36: 0 | AF36: 0 | AG36: 0 | AH36: 0 | AI36: 0 | AJ36: 0 | AN36: =SUM(G36:AK36) -> 0
D37: Fractionation OLEIN IV 58 ( Bulk ) | AN37: Olein IV 58 ( Bulk )
D38: RBDPO Consume | E38: =E39+E40 -> 21429000 | F38: Kg | G38: =G39+G40 -> 579175 | H38: =H39+H40 -> 393236 | I38: =I39+I40 -> 860808 | J38: =J39+J40 -> 963967 | K38: =K39+K40 -> 620511 | L38: =L39+L40 -> 0 | M38: =M39+M40 -> 0 | N38: =N39+N40 -> 0 | ... AL38: =AL39+AL40 -> 0 | AN38: =SUM(G38:AL38) -> 9837344
D39: OLEIN IV 58 | E39: 15000000 | F39: Kg | G39: ='[1]01'!$P$21 -> 396390 | H39: ='[2]02'!$P$21 -> 273297 | I39: ='[2]03'!$P$21 -> 637018 | J39: ='[2]04'!$P$21 -> 714860 | K39: ='[3]05'!$P$21 -> 443511 | L39: 0 | M39: 0 | N39: 0 | O39: 0 | P39: 0 | Q39: 0 | R39: 0 | S39: 0 | T39: 0 | U39: 0 | V39: 0 | W39: 0 | X39: 0 | Y39: 0 | Z39: 0 | AA39: 0 | AB39: 0 | AC39: ='[9]23'!$P$22 -> 158029 | AD39: ='[9]24'!$P$22 -> 449001 | AE39: ='[9]25'!$P$22 -> 547847 | AF39: 598477 | AG39: ='[10]27'!$P$22 -> 558944 | AH39: ='[11]28'!$P$22 -> 644632 | AI39: ='[12]29'!$P$22 -> 193043 | AJ39: ='[13]30'!$P$22 -> 670371 | AK39: ='[5]31 Stok Opname'!$P$22 -> 706516 | AN39: =SUM(G39:AL39) -> 6991936
D40: STEARIN | E40: 6429000 | F40: Kg | G40: ='[1]01'!$P$30-G27 -> 182785 | H40: ='[2]02'!$P$30-H27 -> 119939 | I40: ='[2]03'!$P$30 -> 223790 | J40: ='[2]04'!$P$30 -> 249107 | K40: ='[9]05'!$P$30-K27 -> 177000 | L40: 0 | M40: 0 | N40: 0 | O40: 0 | P40: 0 | Q40: 0 | R40: 0 | S40: 0 | T40: 0 | U40: 0 | V40: 0 | W40: 0 | X40: 0 | Y40: 0 | Z40: 0 | AA40: 0 | AB40: 0 | AC40: ='[9]23'!$P$30-AC27 -> 88370 | AD40: ='[9]24'!$P$30 -> 205696 | AE40: ='[9]25'!$P$30 -> 240847 | AF40: 233031 | AG40: ='[10]27'!$P$28 -> 222549 | AH40: ='[11]28'!$P$30 -> 286390 | AI40: ='[12]29'!$P$30-AI46 -> 92356 | AJ40: ='[13]30'!$P$28 -> 246904 | AK40: ='[5]31 Stok Opname'!$P$30 -> 276644 | AN40: =SUM(G40:AL40) -> 2845408
D41: Fractionation OLEIN IV 60 | AN41: Olein IV 60
D42: CPO Consume | F42: Kg | AN42: =SUM(G42:AL42) -> 0
D43: RBDPO Brand Consume | F43: Kg | G43: =G45+G46 -> 0 | H43: =H45+H46 -> 0 | I43: =I45+I46 -> 0 | J43: =J45+J46 -> 0 | K43: =K45+K46 -> 0 | L43: =L45+L46 -> 0 | M43: =M45+M46 -> 0 | N43: =N45+N46 -> 0 | ... AL43: =AL45+AL46 -> 0 | AN43: =SUM(G43:AL43) -> 145600
D44: OLEIN IV 60 Bulk | F44: Kg | G44: 0 | H44: 0 | I44: 0 | J44: 0 | K44: 0 | L44: 0 | M44: 0 | N44: 0 | O44: 0 | P44: 0 | Q44: 0 | R44: 0 | S44: 0 | T44: 0 | U44: 0 | V44: 0 | W44: 0 | X44: 0 | Y44: 0 | Z44: 0 | AA44: 0 | AB44: 0 | AC44: 0 | AD44: 0 | AE44: 0 | AF44: 0 | AG44: 0 | AH44: 0 | AI44: 0 | AJ44: 0 | AK44: 0 | AL44: 0 | AN44: =SUM(G44:AL44) -> 0
D45: OLEIN IV 60 Salvaco | F45: Kg | G45: 0 | H45: 0 | I45: 0 | J45: 0 | K45: 0 | L45: 0 | M45: 0 | N45: 0 | O45: 0 | P45: 0 | Q45: 0 | R45: 0 | S45: 0 | T45: 0 | U45: 0 | V45: 0 | W45: 0 | X45: 0 | Y45: 0 | Z45: 0 | AA45: 0 | AB45: 0 | AC45: 0 | AD45: 0 | AE45: 0 | AF45: 0 | AG45: 0 | AH45: 0 | AI45: 87600 | AJ45: 0 | AK45: 0 | AL45: 0 | AN45: =SUM(G45:AL45) -> 87600
D46: SOFT STEARIN | F46: Kg | G46: 0 | H46: 0 | I46: 0 | J46: 0 | K46: 0 | L46: 0 | M46: 0 | N46: 0 | O46: 0 | P46: 0 | Q46: 0 | R46: 0 | S46: 0 | T46: 0 | U46: 0 | V46: 0 | W46: 0 | X46: 0 | Y46: 0 | Z46: 0 | AA46: 0 | AB46: 0 | AC46: 0 | AD46: 0 | AE46: 0 | AF46: 0 | AG46: 0 | AH46: 0 | AI46: 58000 | AJ46: 0 | AK46: 0 | AL46: 0 | AN46: =SUM(G46:AL46) -> 58000
D47: Ratio Run RBDPO | F47: % | G47: 0 | AN47: =SUM(G47:AL47) -> 0
D48: YIELD | AN48: Yield
D49: RBDPO | E49: 94.2 | F49: % | G49: =(G16/(G9))*100 -> 94.361801 | H49: =(H16/(H9))*100 -> 96.195668 | I49: =(I16/(I9))*100 -> 96.338759 | J49: =(J16/(J9))*100 -> 95.437198 | K49: =(K16/(K9))*100 -> 91.59804 | L49: =(L16/(L9))*100 -> 98.915407 | M49: =(M16/(M9))*100 -> 94.883016 | N49: =(N16/(N9))*100 -> 85.492235 | ... AL49: =(AL16/(AL9))*100 -> #DIV/0! | AN49: =(AN16/(AN9))*100 -> 95.997637
D50: PFAD | E50: 5 | F50: % | G50: =(G17/(G9))*100 -> 3.8685156 | H50: =(H17/(H9))*100 -> 3.9768279 | I50: =(I17/(I9))*100 -> 3.5650364 | J50: =(J17/(J9))*100 -> 4.1316426 | K50: =(K17/(K9))*100 -> 4.3113848 | L50: =(L17/(L9))*100 -> 3.799829 | M50: =(M17/(M9))*100 -> 4.0012714 | N50: =(N17/(N9))*100 -> 5.8361433 | ... AL50: =(AL17/(AL9))*100 -> #DIV/0! | AN50: =(AN17/(AN9))*100 -> 4.105937
D51: Olein IV 56 | E51: 82 | F51: % | G51: =G26/(G26+G27)*100 -> 88.476017 | H51: =H26/(H26+H27)*100 -> 89.545985 | I51: =I26/(I26+I27)*100 -> #DIV/0! | J51: =J26/(J26+J27)*100 -> #DIV/0! | K51: =K26/(K26+K27)*100 -> 88.95484 | L51: =L26/(L26+L27)*100 -> 81.780024 | M51: =M26/(M26+M27)*100 -> 83.017169 | N51: =N26/(N26+N27)*100 -> 81.888038 | ... AL51: =AL26/(AL26+AL27)*100 -> #DIV/0! | AN51: =AN26/(AN26+AN27)*100 -> 82.04942
D52: Stearin | E52: 18 | F52: % | H52: =H27/(H26+H27)*100 -> 10.454015 | I52: =I27/(I26+I27)*100 -> #DIV/0! | J52: =J27/(J26+J27)*100 -> #DIV/0! | K52: =K27/(K26+K27)*100 -> 11.04516 | L52: =L27/(L26+L27)*100 -> 18.219976 | M52: =M27/(M26+M27)*100 -> 16.982831 | N52: =N27/(N26+N27)*100 -> 18.111962 | O52: =O27/(O26+O27)*100 -> 17.947693 | ... AL52: =AL27/(AL26+AL27)*100 -> #DIV/0! | AN52: =AN27/(AN26+AN27)*100 -> 17.95058
D53: Olein IV 57 ( Bulk ) | E53: 75 | G53: =(G30/G29)*100 -> #DIV/0! | H53: =(H30/H29)*100 -> #DIV/0! | I53: =(I30/I29)*100 -> #DIV/0! | J53: =(J30/J29)*100 -> #DIV/0! | K53: =(K30/K29)*100 -> #DIV/0! | L53: =(L30/L29)*100 -> #DIV/0! | M53: =(M30/M29)*100 -> #DIV/0! | N53: =(N30/N29)*100 -> #DIV/0! | ... AL53: =(AL30/AL29)*100 -> #DIV/0! | AN53: =(AN35/AN34)*100 -> #DIV/0!
D54: Stearin | E54: 25 | G54: =(G31/G29)*100 -> #DIV/0! | H54: =(H31/H29)*100 -> #DIV/0! | I54: =(I31/I29)*100 -> #DIV/0! | J54: =(J31/J29)*100 -> #DIV/0! | K54: =(K31/K29)*100 -> #DIV/0! | L54: =(L31/L29)*100 -> #DIV/0! | M54: =(M31/M29)*100 -> #DIV/0! | N54: =(N31/N29)*100 -> #DIV/0! | ... AL54: =(AL31/AL29)*100 -> #DIV/0! | AN54: =(AN36/AN34)*100 -> #DIV/0!
D55: Olein IV 57 ( Retail ) | E55: 75 | F55: % | G55: =G35/G34*100 -> #DIV/0! | H55: =H35/H34*100 -> #DIV/0! | I55: =I35/I34*100 -> #DIV/0! | J55: =J35/J34*100 -> #DIV/0! | K55: =K35/K34*100 -> #DIV/0! | L55: =L35/L34*100 -> #DIV/0! | M55: =M35/M34*100 -> #DIV/0! | N55: =N35/N34*100 -> #DIV/0! | ... AL55: =AL35/AL34*100 -> #DIV/0! | AN55: =AN35/AN34*100 -> #DIV/0!
D56: Stearin | E56: 25 | F56: % | G56: =G36/G34*100 -> #DIV/0! | H56: =H36/H34*100 -> #DIV/0! | I56: =I36/I34*100 -> #DIV/0! | J56: =J36/J34*100 -> #DIV/0! | K56: =K36/K34*100 -> #DIV/0! | L56: =L36/L34*100 -> #DIV/0! | M56: =M36/M34*100 -> #DIV/0! | N56: =N36/N34*100 -> #DIV/0! | ... AL56: =AL36/AL34*100 -> #DIV/0! | AN56: =AN36/AN34*100 -> #DIV/0!
D57: Olein IV 58 ( Bulk ) | E57: 70 | F57: % | G57: =G39/(G39+G40)*100 -> 68.440454 | H57: =H39/(H39+H40)*100 -> 69.499486 | I57: =I39/(I39+I40)*100 -> 74.002333 | J57: =J39/(J39+J40)*100 -> 74.15814 | K57: =K39/(K39+K40)*100 -> 71.475123 | L57: =L39/(L39+L40)*100 -> #DIV/0! | M57: =M39/(M39+M40)*100 -> #DIV/0! | N57: =N39/(N39+N40)*100 -> #DIV/0! | ... P57: =P39/(P39+P40)*100 -> #DIV/0! | Q57: =Q39/Q38*100 -> #DIV/0! | R57: =R39/R38*100 -> #DIV/0! | S57: =S39/S38*100 -> #DIV/0! | T57: =T39/T38*100 -> #DIV/0! | U57: =U39/U38*100 -> #DIV/0! | V57: =V39/V38*100 -> #DIV/0! | W57: =W39/W38*100 -> #DIV/0! | X57: =X39/X38*100 -> #DIV/0! | ... AL57: =AL39/AL38*100 -> #DIV/0! | AN57: =AN39/(AN39+AN40)*100 -> 71.075445
D58: Stearin | E58: 30 | F58: % | G58: =G40/(G40+G39)*100 -> 31.559546 | H58: =H40/(H40+H39)*100 -> 30.500514 | I58: =I40/(I40+I39)*100 -> 25.997667 | J58: =J40/(J40+J39)*100 -> 25.84186 | K58: =K40/(K40+K39)*100 -> 28.524877 | L58: =L40/(L40+L39)*100 -> #DIV/0! | M58: =M40/(M40+M39)*100 -> #DIV/0! | N58: =N40/(N40+N39)*100 -> #DIV/0! | ... P58: =P40/(P40+P39)*100 -> #DIV/0! | Q58: =Q40/Q38*100 -> #DIV/0! | R58: =R40/R38*100 -> #DIV/0! | S58: =S40/S38*100 -> #DIV/0! | T58: =T40/T38*100 -> #DIV/0! | U58: =U40/U38*100 -> #DIV/0! | V58: =V40/V38*100 -> #DIV/0! | W58: =W40/W38*100 -> #DIV/0! | X58: =X40/X38*100 -> #DIV/0! | ... AL58: =AL40/AL38*100 -> #DIV/0! | AN58: =AN40/AN38*100 -> 28.924555
D59: Olein IV 60 | E59: 60 | F59: % | G59: =G44/G43*100 -> #DIV/0! | H59: =H44/H43*100 -> #DIV/0! | I59: =I44/I43*100 -> #DIV/0! | J59: =J44/J43*100 -> #DIV/0! | K59: =K44/K43*100 -> #DIV/0! | L59: =L44/L43*100 -> #DIV/0! | M59: =M44/M43*100 -> #DIV/0! | N59: =N44/N43*100 -> #DIV/0! | ... AH59: =AH44/AH43*100 -> #DIV/0! | AI59: =AI45/AI43*100 -> 60.164835 | AJ59: =AJ44/AJ43*100 -> #DIV/0! | AK59: =AK44/AK43*100 -> #DIV/0! | AL59: =AL44/AL43*100 -> #DIV/0! | AN59: =(AN45+AN44)/AN43*100 -> 60.164835
D60: Soft Stearin | E60: 40 | F60: % | G60: =G46/G43*100 -> #DIV/0! | H60: =H46/H43*100 -> #DIV/0! | I60: =I46/I43*100 -> #DIV/0! | J60: =J46/J43*100 -> #DIV/0! | K60: =K46/K43*100 -> #DIV/0! | L60: =L46/L43*100 -> #DIV/0! | M60: =M46/M43*100 -> #DIV/0! | N60: =N46/N43*100 -> #DIV/0! | ... AL60: =AL46/AL43*100 -> #DIV/0! | AN60: =AN46/AN43*100 -> 39.835165
C61: 2 | D61: CHEMICAL CONSUMABLE | AN61: Chemical
D62: Bleaching Earth (BE) to Poram Spec | E62: 8 | F62: Kg | G62: 18736 | H62: 12845 | I62: 11929 | J62: 10676 | K62: 5049 | L62: 7309 | M62: 2178 | N62: 3449 | O62: 10049 | P62: 16400 | Q62: 4934 | R62: 3382 | S62: 11600 | T62: 6122 | U62: 2738 | V62: 10924 | W62: 0 | X62: 0 | Y62: 0 | Z62: 11384 | AA62: 16022 | AB62: 8184 | AC62: 18562 | AD62: 14999 | AE62: 13374 | AF62: 2160 | AG62: 5436 | AH62: 9584 | AI62: 5892 | AJ62: 2508 | AK62: =6484+3500 -> 9984 | AN62: =SUM(G62:AL62) -> 256409
F63: % | G63: =G62/(G10)*100 -> 1.3216723 | H63: =H62/(H10)*100 -> 1.162495 | I63: =I62/(I10)*100 -> 1.1441918 | J63: =J62/(J10)*100 -> 1.0048161 | K63: =K62/(K10)*100 -> 1.230536 | L63: =L62/(L10)*100 -> 0.96263389 | M63: =M62/(M10)*100 -> 1.0033121 | N63: =N62/(N10)*100 -> 0.980604 | ... AL63: =AL62/(AL10)*100 -> #DIV/0! | AN63: =AN62/(AN10)*100 -> 1.1201463 | AO63: =AN63*10 -> 11.201463 | BL63: #DIV/0! | BM63: #DIV/0!
D64: Bleaching Earth (BE) to Branded Spec | E64: 18 | F64: Kg | G64: 0 | H64: 0 | I64: 0 | J64: 0 | L64: 0 | M64: 0 | N64: 0 | O64: 0 | P64: 0 | Q64: 0 | R64: 0 | S64: 0 | T64: 0 | U64: 0 | V64: 0 | W64: 0 | X64: 0 | Y64: 0 | Z64: 0 | AA64: 0 | AB64: 0 | AC64: 0 | AD64: 0 | AE64: 0 | AF64: 0 | AH64: =2550+380 -> 2930 | AI64: 0 | AJ64: 0 | AK64: 0 | AL64: 0 | AN64: =SUM(G64:AL64) -> 2930
F65: % | G65: =G64/(G11)*100 -> #DIV/0! | H65: =H64/(H11)*100 -> #DIV/0! | I65: =I64/(I11)*100 -> #DIV/0! | J65: =J64/(J11)*100 -> #DIV/0! | K65: =K64/(K11)*100 -> #DIV/0! | L65: =L64/(L11)*100 -> #DIV/0! | M65: =M64/(M11)*100 -> #DIV/0! | N65: =N64/(N11)*100 -> #DIV/0! | ... AL65: =AL64/(AL11)*100 -> #DIV/0! | AN65: =AN64/(AN11)*100 -> 1.5863992
D66: Phosporic Acid (PA) | E66: 0.6 | F66: Kg | G66: 720.588 | H66: 539.858 | I66: 515.372 | J66: 534.028 | K66: 206.38 | L66: 347.47 | M66: 115.434 | N66: 176.066 | O66: 371.94 | P66: 610.98 | Q66: 264.678 | R66: 177.23 | S66: 715.916 | T66: 376.614 | U66: 125.928 | V66: 429.08 | W66: 0 | X66: 0 | Y66: 0 | Z66: 493.22 | AA66: 662.28 | AB66: 343.97 | AC66: 714.76 | AD66: 847.68 | AE66: 617.98 | AF66: 124.762 | AG66: 361.462 | AH66: 489.72 | AI66: 296.164 | AJ66: 157.41 | AK66: 402.27 | AN66: =SUM(G66:AL66) -> 11739.24
F67: % | G67: =G66/(G9)*100 -> 0.050831618 | H67: =H66/(H9)*100 -> 0.048858094 | I67: =I66/(I9)*100 -> 0.049432844 | J67: =J66/(J9)*100 -> 0.050262263 | K67: =K66/(K9)*100 -> 0.050298677 | L67: =L66/(L9)*100 -> 0.045763634 | M67: =M66/(M9)*100 -> 0.053175543 | N67: =N66/(N9)*100 -> 0.050058285 | ... AL67: =AL66/(AL9)*100 -> #DIV/0! | AN67: =AN66/(AN9)*100 -> 0.050873473 | AO67: =AN67*10 -> 0.50873473
C68: 3 | D68: OIL LOSSES | E68: 0.8 | F68: % | G68: =((SUM(G16:G17))-(SUM(G9)))/(SUM(G9))*100 -> -1.7696836 | H68: =((SUM(H16:H17))-(SUM(H9)))/(SUM(H9))*100 -> 0.17249634 | I68: =((SUM(I16:I17))-(SUM(I9)))/(SUM(I9))*100 -> -0.096204571 | J68: =((SUM(J16:J17))-(SUM(J9)))/(SUM(J9))*100 -> -0.43115984 | K68: =((SUM(K16:K17))-(SUM(K9)))/(SUM(K9))*100 -> -4.0905756 | L68: =((SUM(L16:L17))-(SUM(L9)))/(SUM(L9))*100 -> 2.7152361 | M68: =((SUM(M16:M17))-(SUM(M9)))/(SUM(M9))*100 -> -1.1157126 | N68: =((SUM(N16:N17))-(SUM(N9)))/(SUM(N9))*100 -> -8.6716213 | ... AL68: =((SUM(AL16:AL17))-(SUM(AL9)))/(SUM(AL9))*100 -> #DIV/0! | AN68: =((SUM(AN16:AN17))-(SUM(AN9)))/(SUM(AN9))*100 -> 0.10357452
F69: Kg | G69: =G68%*G9 -> -25087 | H69: =H68%*H9 -> 1906 | I69: =I68%*I9 -> -1003 | J69: =J68%*J9 -> -4581 | K69: =K68%*K9 -> -16784 | L69: =L68%*L9 -> 20616 | M69: =M68%*M9 -> -2422 | N69: =N68%*N9 -> -30500 | ... AL69: =AL68%*AL9 -> #DIV/0! | AN69: =AN68%*AN9 -> 23900.2
D70: % Oil Content | E70: 22 | F70: % | G70: 21.92 | H70: 21.58 | I70: 21.49 | J70: 21.5 | K70: 21.54 | L70: 21.55 | M70: 21.5 | N70: 21.7 | O70: 21.6 | P70: 21.71 | Q70: 21.65 | R70: 21.46 | S70: 21.37 | T70: 21.5 | U70: 21.79 | V70: 21.76 | W70: 0 | X70: 0 | Z70: 21.75 | AA70: 21.78 | AB70: 21.78 | AC70: 21.75 | AD70: 21.8 | AE70: 21.86 | AF70: 21.8 | AG70: 21.82 | AH70: 21.79 | AI70: 22.18 | AJ70: 21.31 | AK70: 22.38 | AN70: =SUM(G70:AL70)/AN6 -> 21.700714
D71: Spent Bleaching Earth | F71: Kg | G71: =SUM(G62,G64)+(G70%*SUM(G62,G64)) -> 22842.931 | H71: =SUM(H62,H64)+(H70%*SUM(H62,H64)) -> 15616.951 | I71: =SUM(I62,I64)+(I70%*SUM(I62,I64)) -> 14492.542 | J71: =SUM(J62,J64)+(J70%*SUM(J62,J64)) -> 12971.34 | K71: =SUM(K62,K64)+(K70%*SUM(K62,K64)) -> 6136.5546 | L71: =SUM(L62,L64)+(L70%*SUM(L62,L64)) -> 8884.0895 | M71: =SUM(M62,M64)+(M70%*SUM(M62,M64)) -> 2646.27 | N71: =SUM(N62,N64)+(N70%*SUM(N62,N64)) -> 4197.433 | ... AL71: =SUM(AL62,AL64)+(AL70%*SUM(AL62,AL64)) -> 0 | AN71: =SUM(AN62,AN64)+(AN70%*SUM(AN62,AN64)) -> 315617.42
C72: 4 | D72: PACKAGING (Brand Salvaco) | AN72: Packaging
D73: Olein IV 60 Received | F73: Kg | AN73: 0
D74: Olein IV 60 Consume | F74: Kg | AN74: 0
D75: - finished product | F75: Kg | G75: 0 | H75: 0 | I75: 0 | J75: 0 | K75: 0 | L75: 0 | M75: 0 | N75: 0 | O75: 0 | P75: 0 | Q75: 0 | R75: 0 | S75: 0 | T75: 0 | U75: 0 | V75: 0 | W75: 0 | X75: 0 | Y75: 0 | Z75: 0 | AA75: 0 | AB75: 0 | AC75: 0 | AD75: 0 | AE75: 0 | AF75: 0 | AG75: 0 | AH75: 0 | AI75: 0 | AL75: 0 | AN75: 0
D76: - sample | F76: Kg | G76: 0 | H76: 0 | I76: 0 | J76: 0 | K76: 0 | L76: 0 | M76: 0 | N76: 0 | O76: 0 | P76: 0 | Q76: 0 | R76: 0 | S76: 0 | T76: 0 | U76: 0 | V76: 0 | W76: 0 | X76: 0 | Y76: 0 | Z76: 0 | AA76: 0 | AB76: 0 | AC76: 0 | AD76: 0 | AE76: 0 | AF76: 0 | AG76: 0 | AH76: 0 | AI76: 0 | AL76: 0 | AN76: 0
D77: - remelt, flushing, downgrade | F77: Kg | G77: 0 | I77: 0 | J77: 0 | K77: 0 | L77: 0 | M77: 0 | N77: 0 | O77: 0 | P77: 0 | Q77: 0 | R77: 0 | S77: 0 | T77: 0 | U77: 0 | V77: 0 | W77: 0 | X77: 0 | Y77: 0 | Z77: 0 | AA77: 0 | AB77: 0 | AC77: 0 | AD77: 0 | AE77: 0 | AF77: 0 | AG77: 0 | AH77: 0 | AI77: 0 | AL77: 0 | AN77: 0
D78: Carton | AN78: Carton
D79: Salvaco 1 Liter | F79: Box | AN79: 0
D80: Salvaco 2 Liter | F80: Box | AN80: 0
D81: Pouch | AN81: Pouch
D82: Salvaco 1 Liter | F82: Pouch | G82: 0 | H82: 0 | I82: 0 | J82: 0 | K82: 0 | L82: 0 | M82: 0 | N82: 0 | O82: 0 | P82: 0 | Q82: 0 | R82: 0 | S82: 0 | T82: 0 | U82: 0 | V82: 0 | W82: 0 | X82: 0 | Y82: 0 | Z82: 0 | AA82: 0 | AB82: 0 | AC82: 0 | AD82: 0 | AE82: 0 | AF82: 0 | AG82: 0 | AH82: 0 | AI82: 0 | AL82: 0 | AN82: 0
D83: Salvaco 2 Liter | F83: Pouch | G83: 0 | H83: 0 | I83: 0 | J83: 0 | K83: 0 | L83: 0 | M83: 0 | N83: 0 | O83: 0 | P83: 0 | Q83: 0 | R83: 0 | S83: 0 | T83: 0 | U83: 0 | V83: 0 | W83: 0 | X83: 0 | Y83: 0 | Z83: 0 | AA83: 0 | AB83: 0 | AC83: 0 | AD83: 0 | AE83: 0 | AF83: 0 | AG83: 0 | AH83: 0 | AI83: 0 | AL83: 0 | AN83: 0
D84: Consumable Vit. A | F84: gram | G84: 0 | H84: 0 | I84: 0 | J84: 0 | K84: 0 | L84: 0 | M84: 0 | N84: 0 | O84: 0 | P84: 0 | Q84: 0 | R84: 0 | S84: 0 | T84: 0 | U84: 0 | V84: 0 | W84: 0 | X84: 0 | Y84: 0 | Z84: 0 | AA84: 0 | AB84: 0 | AC84: 0 | AD84: 0 | AE84: 0 | AF84: 0 | AG84: 0 | AH84: 0 | AI84: 0 | AL84: 0 | AN84: 0
D85: Consumable Packing Tape | F85: Roll | G85: 0 | H85: 0 | I85: 0 | J85: 0 | K85: 0 | L85: 0 | M85: 0 | N85: 0 | O85: 0 | P85: 0 | Q85: 0 | R85: 0 | S85: 0 | T85: 0 | U85: 0 | V85: 0 | W85: 0 | X85: 0 | Y85: 0 | Z85: 0 | AA85: 0 | AB85: 0 | AC85: 0 | AD85: 0 | AE85: 0 | AF85: 0 | AG85: 0 | AH85: 0 | AI85: 0 | AL85: 0 | AN85: 0
D86: REJECT MATERIAL QTY | AN86: Loss Material
D87: Carton | AN87: Carton
D88: Salvaco 1 Liter | F88: Box | AN88: 0
D89: Salvaco 2 Liter | F89: Box | AN89: 0
D90: Pouch | AN90: Pouch
D91: Salvaco 1 Liter | F91: Pouch | G91: 0 | H91: 0 | I91: 0 | J91: 0 | K91: 0 | L91: 0 | M91: 0 | N91: 0 | O91: 0 | P91: 0 | Q91: 0 | R91: 0 | S91: 0 | T91: 0 | U91: 0 | V91: 0 | W91: 0 | X91: 0 | Y91: 0 | Z91: 0 | AA91: 0 | AB91: 0 | AC91: 0 | AD91: 0 | AE91: 0 | AF91: 0 | AG91: 0 | AH91: 0 | AI91: 0 | AL91: 0 | AN91: 0
D92: Salvaco 2 Liter | F92: Pouch | G92: 0 | H92: 0 | I92: 0 | J92: 0 | K92: 0 | L92: 0 | M92: 0 | N92: 0 | O92: 0 | P92: 0 | Q92: 0 | R92: 0 | S92: 0 | T92: 0 | U92: 0 | V92: 0 | W92: 0 | X92: 0 | Y92: 0 | Z92: 0 | AA92: 0 | AB92: 0 | AC92: 0 | AD92: 0 | AE92: 0 | AF92: 0 | AG92: 0 | AH92: 0 | AI92: 0 | AL92: 0 | AN92: 0
D93: REJECT MATERIAL (%) | AN93: Loss Material
D94: Carton | AN94: Carton
D95: Salvaco 1 Liter | E95: 0.3 | F95: % | G95: #DIV/0! | H95: #DIV/0! | I95: #DIV/0! | J95: #DIV/0! | K95: #DIV/0! | L95: #DIV/0! | M95: #DIV/0! | N95: #DIV/0! | O95: #DIV/0! | P95: #DIV/0! | Q95: #DIV/0! | R95: #DIV/0! | S95: #DIV/0! | T95: #DIV/0! | U95: #DIV/0! | V95: #DIV/0! | W95: #DIV/0! | X95: #DIV/0! | Y95: #DIV/0! | Z95: #DIV/0! | AA95: #DIV/0! | AB95: #DIV/0! | AC95: #DIV/0! | AD95: #DIV/0! | AE95: #DIV/0! | AF95: #DIV/0! | AG95: #DIV/0! | AH95: #DIV/0! | AI95: #DIV/0! | AL95: #DIV/0! | AN95: #DIV/0!
D96: Salvaco 2 Liter | E96: 0.3 | F96: % | G96: #DIV/0! | H96: #DIV/0! | I96: #DIV/0! | J96: #DIV/0! | K96: #DIV/0! | L96: #DIV/0! | M96: #DIV/0! | N96: #DIV/0! | O96: #DIV/0! | P96: #DIV/0! | Q96: #DIV/0! | R96: #DIV/0! | S96: #DIV/0! | T96: #DIV/0! | U96: #DIV/0! | V96: #DIV/0! | W96: #DIV/0! | X96: #DIV/0! | Y96: #DIV/0! | Z96: #DIV/0! | AA96: #DIV/0! | AB96: #DIV/0! | AC96: #DIV/0! | AD96: #DIV/0! | AE96: #DIV/0! | AF96: #DIV/0! | AG96: #DIV/0! | AH96: #DIV/0! | AI96: #DIV/0! | AL96: #DIV/0! | AN96: #DIV/0!
D97: Pouch | AN97: Pouch
D98: Salvaco 1 Liter | E98: 0.5 | F98: % | G98: #DIV/0! | H98: #DIV/0! | I98: #DIV/0! | J98: #DIV/0! | K98: #DIV/0! | L98: #DIV/0! | M98: #DIV/0! | N98: #DIV/0! | O98: #DIV/0! | P98: #DIV/0! | Q98: #DIV/0! | R98: #DIV/0! | S98: #DIV/0! | T98: #DIV/0! | U98: #DIV/0! | V98: #DIV/0! | W98: #DIV/0! | X98: #DIV/0! | Y98: #DIV/0! | Z98: #DIV/0! | AA98: #DIV/0! | AB98: #DIV/0! | AC98: #DIV/0! | AD98: #DIV/0! | AE98: #DIV/0! | AF98: #DIV/0! | AG98: #DIV/0! | AH98: #DIV/0! | AI98: #DIV/0! | AL98: #DIV/0! | AN98: #DIV/0!
D99: Salvaco 2 Liter | E99: 0.5 | F99: % | G99: #DIV/0! | H99: #DIV/0! | I99: #DIV/0! | J99: #DIV/0! | K99: #DIV/0! | L99: #DIV/0! | M99: #DIV/0! | N99: #DIV/0! | O99: #DIV/0! | P99: #DIV/0! | Q99: #DIV/0! | R99: #DIV/0! | S99: #DIV/0! | T99: #DIV/0! | U99: #DIV/0! | V99: #DIV/0! | W99: #DIV/0! | X99: #DIV/0! | Y99: #DIV/0! | Z99: #DIV/0! | AA99: #DIV/0! | AB99: #DIV/0! | AC99: #DIV/0! | AD99: #DIV/0! | AE99: #DIV/0! | AF99: #DIV/0! | AG99: #DIV/0! | AH99: #DIV/0! | AI99: #DIV/0! | AL99: #DIV/0! | AN99: #DIV/0!
C100: 5 | D100: PACKAGING (Brand Nusakita) | AN100: Packaging
...

Sheet HPP REF 
B2: Refinery Cost
B3: No | C3: Item Cost | D3: Norma | F3: Pemakaian / Hari | H3: HK | J3: Total Pemakaian | K3: Harga / stn | M3: Total Biaya | N3: Rp / kg | O3: Kurs | P3: USD/MT
B4: Through Put CPO Proses (Ton/Day) | O4: ='Agustus - 2024'!AQ7 -> 0 | P4: Days
B5: Working Day | O5: 18 | P5: Days
B6: Operation By PLN | O6: 300 | P6: Days
B7: Operation By Genset | O7: =[15]Formula!G6 -> 0 | P7: Days
B8: Total CPO Process | O8: 600000 | P8: MTPY
B9: KURS | O9: 16200 | P9: Rp/USD
B10: 1 | C10: Bleaching Earth | D10: ='Agustus - 2024'!AN63 -> 1.1201463 | E10: kg/ton | F10: =D10*$O$4*1000 -> 0 | G10: Kg/day | H10: =O5 -> 18 | J10: =H10*F10 -> 0 | K10: 2750 | M10: =K10*J10 -> 0 | N10: =M10/($O$5*$O$4*1000) -> #DIV/0! | O10: =O9 -> 16200 | P10: =(M10/O10)/($O$4*$O$5) -> #DIV/0! | Q10: 44.1 | R10: 3.0413793
B11: 2 | C11: Phosporic acid | D11: ='Agustus - 2024'!AN67 -> 0.050873473 | E11: kg/ton | F11: =D11*$O$4*1000 -> 0 | G11: Kg/day | H11: =O5 -> 18 | J11: =H11*F11 -> 0 | K11: 18100 | M11: =K11*J11 -> 0 | N11: =M11/($O$5*$O$4*1000) -> #DIV/0! | O11: =O10 -> 16200 | P11: =(M11/O11)/($O$4*$O$5) -> #DIV/0! | Q11: 9.35 | R11: 0.64482759
B12: 3 | C12: Caustic Soda | D12: =(35*25)/30 -> 29.166667 | E12: kg/day | F12: =D12 -> 29.166667 | G12: kg/day | H12: =O5 -> 18 | J12: =H12*F12 -> 525 | K12: 15700 | M12: =K12*J12 -> 8242500 | N12: =M12/($O$5*$O$4*1000) -> #DIV/0! | O12: =O11 -> 16200 | P12: =(M12/O12)/($O$4*$O$5) -> #DIV/0!
B13: 4 | C13: Pemakaian Natural Gas HPB Geka | Q13: 32 | R13: 2.2068966
C14: Normal Consumption | D14: 0.18 | E14: MMBTU/MT CPO | F14: =D14*O4 -> 0 | G14: MMBTU/day | H14: =O5 -> 18 | J14: =H14*F14 -> 0 | K14: =L14*O9 -> 205740 | L14: 12.7 | M14: =K14*J14 -> 0 | N14: =M14/($O$5*$O$4*1000) -> #DIV/0! | O14: =O11 -> 16200 | P14: =(M14/O14)/($O$4*$O$5) -> #DIV/0!
C15: Penalty Below Consumption | D15: 0 | E15: MMBTU/MT CPO | F15: =D15*O4 -> 0 | G15: MMBTU/day | H15: =O5 -> 18 | J15: =H15*F15 -> 0 | K15: =12.7*O9 -> 205740 | M15: =K15*J15 -> 0 | N15: =M15/($O$5*$O$4*1000) -> #DIV/0! | O15: =O14 -> 16200 | P15: =(M15/O15)/($O$4*$O$5) -> #DIV/0!
C16: Penalty Above Consumption | D16: 0 | E16: MMBTU/MT CPO | F16: =D16*O4 -> 0 | G16: MMBTU/day | H16: =O5 -> 18 | J16: =H16*F16 -> 0 | K16: =12.7*O9 -> 205740 | M16: =K16*J16 -> 0 | N16: =M16/($O$5*$O$4*1000) -> #DIV/0! | O16: =O15 -> 16200 | P16: =(M16/O16)/($O$4*$O$5) -> #DIV/0!
B17: 5 | C17: Steam
C18: For Process | D18: 45.12 | E18: Kg/MT CPO | F18: =(D18*$O$4)/1000 -> 0 | G18: Ton/day | H18: =O5 -> 18 | J18: =(H18*F18) -> 0 | K18: ='[16]MP BOILER'!H15 -> 516233.21 | M18: =(F18*H18*K18)+(F18*I18*L18) -> 0 | N18: =M18/($O$5*$O$4*1000) -> #DIV/0! | O18: =O16 -> 16200 | P18: =(M18/O18)/($O$4*$O$5) -> #DIV/0! | Q18: 32.16 | R18: 2.217931
C19: Storage Tank for Heating | D19: 30 | E19: Kg/MT CPO | F19: =(D19*$O$4)/1000 -> 0 | G19: Ton/day | H19: =O5 -> 18 | J19: =H19*F19 -> 0 | K19: ='[16]MP BOILER'!H15 -> 516233.21 | M19: =(F19*H19*K19)+(F19*I19*L19) -> 0 | N19: =M19/($O$5*$O$4*1000) -> #DIV/0! | O19: =O18 -> 16200 | P19: =(M19/O19)/($O$4*$O$5) -> #DIV/0!
B20: 6 | C20: Electrical
C21: For Process | D21: =1.5 -> 1.5 | E21: kW/MT CPO | F21: =D21*$O$4 -> 0 | G21: kW/day | H21: =O6 -> 300 | I21: =O7 -> 0 | J21: =(H21*F21)+(F21*I21) -> 0 | K21: 1550 | M21: =(F21*H21*K21)+(F21*I21*L21) -> 0 | N21: =M21/($O$5*$O$4*1000) -> #DIV/0! | O21: =O19 -> 16200 | P21: =(M21/O21)/($O$4*$O$5) -> #DIV/0!
C22: Cooling Tower | D22: =1.18 -> 1.18 | E22: kW/MT CPO | F22: =D22*$O$4 -> 0 | G22: kW/day | H22: =H21 -> 300 | I22: =$O$7 -> 0 | J22: =(H22*F22)+(F22*I22) -> 0 | K22: 1550 | M22: =(F22*H22*K22)+(F22*I22*L22) -> 0 | N22: =M22/($O$5*$O$4*1000) -> #DIV/0! | O22: =O21 -> 16200 | P22: =(M22/O22)/($O$4*$O$5) -> #DIV/0!
C23: Storage Tank | D23: =(680.98/24)/84 -> 0.3377877 | E23: kW/MT CPO | F23: =D23*$O$4 -> 0 | G23: kW/day | H23: =H22 -> 300 | I23: =$O$7 -> 0 | J23: =(H23*F23)+(F23*I23) -> 0 | K23: 1550 | M23: =(F23*H23*K23)+(F23*I23*L23) -> 0 | N23: =M23/($O$5*$O$4*1000) -> #DIV/0! | O23: =O22 -> 16200 | P23: =(M23/O23)/($O$4*$O$5) -> #DIV/0!
B24: 7 | C24: Water | Q24: 0.29484 | R24: 0.020333793
C25: Make Up CT | D25: 60 | E25: M3/day | F25: =D25 -> 60 | G25: =E25 -> M3/day | H25: =O5 -> 18 | J25: =H25*F25 -> 1080 | K25: =[15]L.Water!F6 -> 8700 | M25: =K25*J25 -> 9396000 | N25: =M25/($O$5*$O$4*1000) -> #DIV/0! | O25: =O23 -> 16200 | P25: =(M25/O25)/($O$4*$O$5) -> #DIV/0!
B26: 8 | C26: Chemical Water | Q26: 32.592264 | R26: 2.2477424
C27: EONBAC BC 3108 | D27: 0.4 | E27: Kg/day | F27: =D27 -> 0.4 | G27: =E27 -> Kg/day | H27: =O5 -> 18 | J27: =H27*F27 -> 7.2 | K27: 27240 | M27: =K27*J27 -> 196128 | N27: =M27/($O$5*$O$4*1000) -> #DIV/0! | O27: =O25 -> 16200 | P27: =(M27/O27)/($O$4*$O$5) -> #DIV/0!
C28: EONLINE T722 | D28: 0.66 | E28: Kg/day | F28: =D28 -> 0.66 | G28: =E28 -> Kg/day | H28: =O5 -> 18 | J28: =H28*F28 -> 11.88 | K28: 29120 | M28: =K28*J28 -> 345945.6 | N28: =M28/($O$5*$O$4*1000) -> #DIV/0! | O28: =O27 -> 16200 | P28: =(M28/O28)/($O$4*$O$5) -> #DIV/0!
C29: EONLINE AG5770 | D29: 0.41 | E29: Kg/day | F29: =D29 -> 0.41 | G29: =E29 -> Kg/day | H29: =O5 -> 18 | J29: =H29*F29 -> 7.38 | K29: 117212 | M29: =K29*J29 -> 865024.56 | N29: =M29/($O$5*$O$4*1000) -> #DIV/0! | O29: =O27 -> 16200 | P29: =(M29/O29)/($O$4*$O$5) -> #DIV/0!
C30: EONScale T2511 | D30: 0.1 | E30: Kg/day | F30: =D30 -> 0.1 | G30: =E30 -> Kg/day | H30: =O5 -> 18 | J30: =H30*F30 -> 1.8 | K30: 45940 | M30: =K30*J30 -> 82692 | N30: =M30/($O$5*$O$4*1000) -> #DIV/0! | O30: =O28 -> 16200 | P30: =(M30/O30)/($O$4*$O$5) -> #DIV/0!
B31: 9 | C31: Others | Q31: 2.7410526 | R31: 0.18903811
C32: Filter Bag 10 Microne | D32: =300/332 -> 0.90361446 | E32: Pcs/day | F32: =D32 -> 0.90361446 | G32: =E32 -> Pcs/day | H32: =O5 -> 18 | J32: =H32*F32 -> 16.26506 | K32: 40000 | M32: =J32*K32 -> 650602.41 | N32: =M32/($O$5*$O$4*1000) -> #DIV/0! | O32: =O30 -> 16200 | P32: =(M32/O32)/($O$4*$O$5) -> #DIV/0!
C33: Filter Bag 100 Microne | D33: =210/332 -> 0.63253012 | E33: Pcs/day | F33: =D33 -> 0.63253012 | G33: =E33 -> Pcs/day | H33: =O5 -> 18 | J33: =H33*F33 -> 11.385542 | K33: 125000 | M33: =J33*K33 -> 1423192.8 | N33: =M33/($O$5*$O$4*1000) -> #DIV/0! | O33: =O32 -> 16200 | P33: =(M33/O33)/($O$4*$O$5) -> #DIV/0!
C34: Filter Cartridge 10 Microne | D34: =47/30 -> 1.5666667 | E34: Pcs/day | F34: =D34 -> 1.5666667 | G34: =E34 -> Pcs/day | H34: =O5 -> 18 | J34: =H34*F34 -> 28.2 | K34: 145000 | M34: =J34*K34 -> 4089000 | N34: =M34/($O$5*$O$4*1000) -> #DIV/0! | O34: =O33 -> 16200 | P34: =(M34/O34)/($O$4*$O$5) -> #DIV/0!
C35: Filter Dustbag | D35: =40/332 -> 0.12048193 | E35: Pcs/day | F35: =D35 -> 0.12048193 | G35: =E35 -> Pcs/day | H35: =O5 -> 18 | J35: =H35*F35 -> 2.1686747 | K35: 682500 | M35: =J35*K35 -> 1480120.5 | N35: =M35/($O$5*$O$4*1000) -> #DIV/0! | O35: =O34 -> 16200 | P35: =(M35/O35)/($O$4*$O$5) -> #DIV/0!
C36: O Ring Filter Leaves | D36: =1200/332 -> 3.6144578 | E36: Pcs/day | F36: =D36 -> 3.6144578 | G36: =E36 -> Pcs/day | H36: =O5 -> 18 | J36: =H36*F36 -> 65.060241 | K36: 14500 | M36: =J36*K36 -> 943373.49 | N36: =M36/($O$5*$O$4*1000) -> #DIV/0! | O36: =O35 -> 16200 | P36: =(M36/O36)/($O$4*$O$5) -> #DIV/0!
B37: 10 | C37: Waste Water | D37: =200 -> 200 | E37: M3/day | F37: =D37 -> 200 | G37: =E37 -> M3/day | H37: =O5 -> 18 | J37: =H37*F37 -> 3600 | K37: =[16]L.WWTP!H17 -> 27499.717 | M37: =J37*K37 -> 98998981 | N37: =M37/($O$5*$O$4*1000) -> #DIV/0! | O37: =O36 -> 16200 | P37: =(M37/O37)/($O$4*$O$5) -> #DIV/0! | Q37: 1.0462652 | R37: 0.072156222
B38: 11 | C38: SHE
C39: SBE | D39: =(D10*O4*1000)*120% -> 0 | E39: Kg/day | F39: =D39 -> 0 | G39: Kg/day | H39: =O5 -> 18 | J39: =H39*F39 -> 0 | K39: 300 | M39: =J39*K39 -> 0 | N39: =M39/($O$5*$O$4*1000) -> #DIV/0! | O39: =O37 -> 16200 | P39: =(M39/O39)/($O$4*$O$5) -> #DIV/0!
C40: Domestic | D40: 0.1 | E40: Trip/day | F40: =D40 -> 0.1 | G40: Trip/day | H40: =O5 -> 18 | J40: =H40*F40 -> 1.8 | K40: 303030.3 | M40: =J40*K40 -> 545454.55 | N40: =M40/($O$5*$O$4*1000) -> #DIV/0! | O40: =O39 -> 16200 | P40: =(M40/O40)/($O$4*$O$5) -> #DIV/0!
B41: 12 | C41: Lab
C42: LAB Chemical | D42: =[15]L.Lab!H132*13% -> 1046459.9 | E42: Rp/day | F42: =D42 -> 1046459.9 | G42: =E42 -> Rp/day | H42: =O5 -> 18 | J42: =H42*F42 -> 18836277 | M42: =J42 -> 18836277 | N42: =M42/($O$5*$O$4*1000) -> #DIV/0! | O42: =O40 -> 16200 | P42: =(M42/O42)/($O$4*$O$5) -> #DIV/0!
C43: Sample and Analysis | D43: 13909.091 | E43: Rp/day | F43: =D43 -> 13909.091 | G43: =E43 -> Rp/day | H43: =O5 -> 18 | J43: =H43*F43 -> 250363.64 | M43: =J43 -> 250363.64 | N43: =M43/($O$5*$O$4*1000) -> #DIV/0! | O43: =O42 -> 16200 | P43: =(M43/O43)/($O$4*$O$5) -> #DIV/0!
C44: Consumable Part | D44: =[17]UP.Lab!H131 -> 135770.31 | E44: Rp/day | F44: =D44 -> 135770.31 | G44: =E44 -> Rp/day | H44: =O5 -> 18 | J44: =H44*F44 -> 2443865.5 | M44: =J44 -> 2443865.5 | N44: =M44/($O$5*$O$4*1000) -> #DIV/0! | O44: =O43 -> 16200 | P44: =(M44/O44)/($O$4*$O$5) -> #DIV/0!
B45: 13 | C45: Solar
C46: Forklift -1 (3 Ton) | D46: =2.2*7 -> 15.4 | E46: Ltr/day | F46: =D46 -> 15.4 | G46: Ltr/day | H46: =O5 -> 18 | J46: =H46*F46 -> 277.2 | K46: 14500 | M46: =J46*K46 -> 4019400 | N46: =M46/($O$5*$O$4*1000) -> #DIV/0! | O46: =O42 -> 16200 | P46: =(M46/O46)/($O$4*$O$5) -> #DIV/0!
C47: WA Loader | D47: 50 | E47: Ltr/day | F47: =D47 -> 50 | G47: Ltr/day | H47: =O5 -> 18 | J47: =H47*F47 -> 900 | K47: 14500 | M47: =J47*K47 -> 13050000 | N47: =M47/($O$5*$O$4*1000) -> #DIV/0! | O47: =O43 -> 16200 | P47: =(M47/O47)/($O$4*$O$5) -> #DIV/0!
M48: =SUM(M10:M47) -> 1.6585892e+08 | N48: =SUM(N10:N47) -> #DIV/0! | P48: =SUM(P10:P47) -> #DIV/0! | Q48: =SUM(Q10:Q37) -> 154.28442 | R48: =SUM(R10:R37) -> 10.640305

Sheet HPP FRACT 
B2: Fractionation Cost
B3: No | C3: Item Cost | D3: Norma | F3: Pemakaian / Hari | H3: HK | J3: Total Pemakaian | K3: Harga / stn | M3: Total Biaya | N3: Rp / kg | O3: Kurs | P3: USD/MT
B4: RPO Proses / Day | O4: 2000 | P4: MTD
B5: Working Day | O5: 300 | P5: Days
B6: Operation By PLN | O6: 300 | P6: Days
B7: Operation By Genset | O7: =[15]Formula!G6 -> 0 | P7: Days
B8: Total RBDPO Process | O8: 600000 | P8: MTPY
B9: KURS | O9: 16200 | P9: Rp/USD
B10: 1 | C10: Steam | D10: 60 | E10: Kg/MT CPO | F10: =(D10*$O$4)/1000 -> 120 | G10: Kg/day | H10: =O5 -> 300 | J10: =(H10*F10)+(I10*F10) -> 36000 | K10: ='[18]MP BOILER'!H15 -> 516233.21 | L10: 0 | M10: =(K10*H10*F10)+(L10*I10*F10) -> 1.8584396e+10 | N10: =M10/($O$5*$O$4*1000) -> 30.973993 | O10: =O9 -> 16200 | P10: =(M10/O10)/($O$4*$O$5) -> 1.9119749 | Q10: 32.16 | R10: 2.217931
B11: 2 | C11: Electrical
C12: For Process | D12: 3 | E12: kW/MT CPO | F12: =D12*$O$4 -> 6000 | G12: kW/day | H12: =O6 -> 300 | I12: =O7 -> 0 | J12: =H12*F12 -> 1800000 | K12: 1550 | M12: =(K12*H12*F12)+(L12*I12*F12) -> 2790000000 | N12: =M12/($O$5*$O$4*1000) -> 4.65 | O12: =O10 -> 16200 | P12: =(M12/O12)/($O$4*$O$5) -> 0.28703704
C13: Cooling Tower | D13: 1.97 | E13: kW/MT CPO | F13: =D13*$O$4 -> 3940 | G13: kW/day | H13: =O6 -> 300 | I13: =O7 -> 0 | J13: =H13*F13 -> 1182000 | K13: 1550 | M13: =(K13*H13*F13)+(L13*I13*F13) -> 1832100000 | N13: =M13/($O$5*$O$4*1000) -> 3.0535 | O13: =O12 -> 16200 | P13: =(M13/O13)/($O$4*$O$5) -> 0.18848765
B14: 3 | C14: Water | Q14: 0.29484 | R14: 0.020333793
C15: Make Up CT | D15: =110-60 -> 50 | E15: M3/day | F15: =D15 -> 50 | G15: =E15 -> M3/day | H15: =O5 -> 300 | J15: =H15*F15 -> 15000 | K15: =[18]LWTP!H13 -> 22504.09 | M15: =K15*J15 -> 3.3756135e+08 | N15: =M15/($O$5*$O$4*1000) -> 0.56260226 | O15: =O13 -> 16200 | P15: =(M15/O15)/($O$4*$O$5) -> 0.034728534
B16: 4 | C16: Chemical Water | Q16: 32.592264 | R16: 2.2477424
C17: EONBAC BC 3108 | D17: 0.4 | E17: Kg/day | F17: =D17 -> 0.4 | G17: =E17 -> Kg/day | H17: =O5 -> 300 | J17: =H17*F17 -> 120 | K17: 27240 | M17: =K17*J17 -> 3268800 | N17: =M17/($O$5*$O$4*1000) -> 0.005448 | O17: =O15 -> 16200 | P17: =(M17/O17)/($O$4*$O$5) -> 0.0003362963
C18: EONLINE T722 | D18: 0.66 | E18: Kg/day | F18: =D18 -> 0.66 | G18: =E18 -> Kg/day | H18: =O5 -> 300 | J18: =H18*F18 -> 198 | K18: 29120 | M18: =K18*J18 -> 5765760 | N18: =M18/($O$5*$O$4*1000) -> 0.0096096 | O18: =O17 -> 16200 | P18: =(M18/O18)/($O$4*$O$5) -> 0.00059318519
C19: EONLINE AG5770 | D19: 0.41 | E19: Kg/day | F19: =D19 -> 0.41 | G19: =E19 -> Kg/day | H19: =O5 -> 300 | J19: =H19*F19 -> 123 | K19: 117212 | M19: =K19*J19 -> 14417076 | N19: =M19/($O$5*$O$4*1000) -> 0.02402846 | O19: =O17 -> 16200 | P19: =(M19/O19)/($O$4*$O$5) -> 0.0014832383
C20: EONScale T2511 | D20: 0.1 | E20: Kg/day | F20: =D20 -> 0.1 | G20: =E20 -> Kg/day | H20: =O5 -> 300 | J20: =H20*F20 -> 30 | K20: 45940 | M20: =K20*J20 -> 1378200 | N20: =M20/($O$5*$O$4*1000) -> 0.002297 | O20: =O18 -> 16200 | P20: =(M20/O20)/($O$4*$O$5) -> 0.00014179012
B21: 5 | C21: Others | Q21: 2.7410526 | R21: 0.18903811
C22: Filter Cloth | D22: =110/330 -> 0.33333333 | E22: Pcs/day | F22: =D22*1 -> 0.33333333 | G22: =E22 -> Pcs/day | H22: =O5 -> 300 | J22: =F22*H22 -> 100 | K22: 895000 | M22: =J22*K22 -> 89500000 | N22: =M22/($O$5*$O$4*1000) -> 0.14916667 | O22: =O20 -> 16200 | P22: =(M22/O22)/($O$4*$O$5) -> 0.0092078189 | Q22: 0.27527033 | R22: 0.01898416
C23: Filter Bag 80 Microne monofilament | D23: =150/332 -> 0.45180723 | E23: Pcs/day | F23: =D23 -> 0.45180723 | G23: =E23 -> Pcs/day | H23: =O5 -> 300 | J23: =F23*H23 -> 135.54217 | K23: 130000 | M23: =J23*K23 -> 17620482 | N23: =M23/($O$5*$O$4*1000) -> 0.02936747 | O23: 16200 | P23: =(M23/O23)/($O$4*$O$5) -> 0.0018128068
C24: Filter Bag 100 Microne monofilament | D24: =150/332 -> 0.45180723 | E24: Pcs/day | F24: =D24 -> 0.45180723 | G24: =E24 -> Pcs/day | H24: =O5 -> 300 | J24: =F24*H24 -> 135.54217 | K24: 125000 | M24: =J24*K24 -> 16942771 | N24: =M24/($O$5*$O$4*1000) -> 0.028237952 | O24: =O22 -> 16200 | P24: =(M24/O24)/($O$4*$O$5) -> 0.0017430834
J25: Cost Fractionation/ CPO | M25: =SUM(M10:M24) -> 2.369295e+10 | N25: =SUM(N10:N24) -> 39.48825 | P25: =SUM(P10:P24) -> 2.4375463

Sheet SUMARY HPP
B2: actual cost juni 2024 based on chemical & utility
B3: Through Put CPO Proses (Ton/Day) | G3: =[16]REF!O4 -> 2200 | H3: MTD
B4: Through Put RBDPO Proses (Ton/Day) | G4: =[16]FRACT!O4 -> 4314 | H4: MTD
B5: Working Day | G5: 18 | H5: Days
B6: Operation By PLN | G6: 300 | H6: Days
B7: Operation By Genset | G7: 0 | H7: Days
B8: Total CPO Process | G8: =G3*G5 -> 39600 | H8: MTPY
B9: KURS | G9: 16200 | H9: Rp/USD
B10: No | C10: Items | D10: Description | F10: Rp/Tahun | G10: Rp/Kg | H10: USD/MT
B11: I | C11: Processing Cost | D11: 1 | E11: Refining Cost | F11: =[16]REF!M48 -> 1.6422668e+10 | G11: =F11/($G$8*1000) -> 414.71384 | H11: =(F11/$G$8)/$G$9 -> 25.59962
D12: 2 | E12: Fractionation Cost | F12: =[16]FRACT!M25 -> 1.7406851e+10 | G12: =F12/($G$8*1000) -> 439.56694 | H12: =(F12/$G$8)/$G$9 -> 27.133762
D13: 3 | E13: Preventive Maintenance Cost | F13: =[16]MTC!C15+[16]ELECTRICAL!C19 -> 9.4717847e+09 | G13: =F13/($G$8*1000) -> 239.18648 | H13: =(F13/$G$8)/$G$9 -> 14.764598
G14: =SUM(G11:G13) -> 1093.4673 | H14: =SUM(H11:H13) -> 67.497979
B15: II | C15: Fix Cost | D15: 1 | E15: Manpower Cost | F15: =SUM('[15]FC-1 New'!I17,'[15]FC-1 New'!I38) -> 5.7497185e+10 | G15: =F15/($G$8*1000) -> 1451.9491 | H15: =(F15/$G$8)/$G$9 -> 89.626489
D16: 2 | E16: Admin OH Cost | F16: ='[15]FC-2'!J69 -> 1.1780863e+10 | G16: =F16/($G$8*1000) -> 297.49655 | H16: =(F16/$G$8)/$G$9 -> 18.363984
D17: 3 | E17: Depresiasi Cost | F17: ='[15]FC-4'!E5 -> 4.1807174e+10 | G17: =F17/($G$8*1000) -> 1055.7367 | H17: =(F17/$G$8)/$G$9 -> 65.168933
D18: 4 | E18: Amortisation of leasehold land Cost | F18: ='[15]FC-5'!D5 -> 2.4145564e+10 | G18: =F18/($G$8*1000) -> 609.73647 | H18: =(F18/$G$8)/$G$9 -> 37.638053
G19: =SUM(G15:G18) -> 3414.9189 | H19: =SUM(H15:H18) -> 210.79746
B20: III | C20: Finance Cost | D20: 1 | E20: Beban Keuangan | F20: =[15]Finance!H8 -> 5.7976217e+10 | G20: =F20/($G$8*1000) -> 1464.0459 | H20: =(F20/$G$8)/$G$9 -> 90.373203
D21: 2 | E21: Beban Operasional Lainnya | F21: =[15]Finance!H22 -> 0 | G21: =F21/($G$8*1000) -> 0 | H21: =(F21/$G$8)/$G$9 -> 0
D22: 3 | E22: Beban Lain-Lain | F22: =[15]Finance!H26 -> 0 | G22: =F22/($G$8*1000) -> 0 | H22: =(F22/$G$8)/$G$9 -> 0
G23: =SUM(G20:G22) -> 1464.0459 | H23: =SUM(H20:H22) -> 90.373203
B24: IV | C24: Sales Cost | D24: 1 | E24: Sales Cost Bulk | F24: ='[15]Sales-1'!M26 -> 1.192173e+11 | G24: =F24/($G$8*1000) -> 3010.5378 | H24: =(F24/$G$8)/$G$9 -> 185.83566
D25: 2 | E25: Sales Cost Retail | F25: ='[15]Sales-2'!G13 -> 7.9024016e+10 | G25: =F25/($G$8*1000) -> 1995.5559 | H25: =(F25/$G$8)/$G$9 -> 123.18247
G26: =SUM(G24:G25) -> 5006.0937 | H26: =SUM(H24:H25) -> 309.01813
F27: =(SUM(F11:F26)/G9)/G8 -> 677.68677 | H27: =SUM(H14,H19,H23,H24) -> 554.50431

Sheet Convert Gas
B3: CONVERT PEMAKAIAN GAS HP BOILER & MP BOILER
D4: 2024
C5: HP BOILER | F5: TOTAL CORRECTED VOLUME (Sm3) | K5: ENERGY MP BOILER (MMBTU) | L5: TOTAL GAS CONSUMPTION (MMBTU) | M5: PERCENTAGE
C6: UNCORRECTED VOLUME (UV) (m3) | D6: PRESS. Bar | E6: CORRECTED VOLUME (CV) (Sm3) | G6: Convert Sm3 to SCF | H6: VOLUME (MSCF) | I6: HEATING VALUE (BTU / SCF) | J6: ENERGY HP BOILER (MMBTU) | M6: HP Boiler | N6: MP Boiler
C7: 1 | D7: 2 | E7: 3 = 1 x 2 | F7: 4 = 3 | G7: 5 | H7: 6 = (4 x 5) / 1000 | I7: 7 | J7: 8 = (6 x 7) / 1000 | K7: 9 = 10 - 8 | L7: 10 | M7: 11 = 8 / 10 | N7: 12 = 9 / 10
B8: 1 | C8: 1266.7 | D8: 5 | E8: =C8*D8 -> 6333.5 | F8: =E8 -> 6333.5 | G8: 35.314667 | H8: =(F8*G8)/1000 -> 223.66544 | I8: 1062.2961 | J8: =(H8*I8)/1000 -> 237.59894 | K8: =L8-J8 -> -237.59894 | M8: =(J8/L8) -> #DIV/0! | N8: =K8/L8 -> #DIV/0!
B9: =B8+1 -> 2 | C9: 1335.7 | D9: 5 | E9: =C9*D9 -> 6678.5 | F9: =E9 -> 6678.5 | G9: 35.314667 | H9: =(F9*G9)/1000 -> 235.849 | I9: 1061.8892 | J9: =(H9*I9)/1000 -> 250.4455 | K9: =L9-J9 -> -250.4455 | M9: =(J9/L9) -> #DIV/0! | N9: =K9/L9 -> #DIV/0!
B10: =B9+1 -> 3 | C10: 1352.6 | D10: 5 | E10: =C10*D10 -> 6763 | F10: =E10 -> 6763 | G10: 35.314667 | H10: =(F10*G10)/1000 -> 238.83309 | I10: 1061.3033 | J10: =(H10*I10)/1000 -> 253.47436 | K10: =L10-J10 -> -253.47436 | M10: =(J10/L10) -> #DIV/0! | N10: =K10/L10 -> #DIV/0!
B11: =B10+1 -> 4 | C11: 1378.9 | D11: 5 | E11: =C11*D11 -> 6894.5 | F11: =E11 -> 6894.5 | G11: 35.314667 | H11: =(F11*G11)/1000 -> 243.47697 | I11: 1060.7416 | J11: =(H11*I11)/1000 -> 258.26615 | K11: =L11-J11 -> -258.26615 | M11: =(J11/L11) -> #DIV/0! | N11: =K11/L11 -> #DIV/0!
B12: =B11+1 -> 5 | C12: 654.3 | D12: 5 | E12: =C12*D12 -> 3271.5 | F12: =E12 -> 3271.5 | G12: 35.314667 | H12: =(F12*G12)/1000 -> 115.53193 | I12: 1057.9053 | J12: =(H12*I12)/1000 -> 122.22184 | K12: =L12-J12 -> -122.22184 | M12: =(J12/L12) -> #DIV/0! | N12: =K12/L12 -> #DIV/0!
B13: =B12+1 -> 6 | C13: 1129.3 | D13: 5 | E13: =C13*D13 -> 5646.5 | F13: =E13 -> 5646.5 | G13: 35.314667 | H13: =(F13*G13)/1000 -> 199.40427 | I13: 1059.3735 | J13: =(H13*I13)/1000 -> 211.2436 | K13: =L13-J13 -> -211.2436 | M13: =(J13/L13) -> #DIV/0! | N13: =K13/L13 -> #DIV/0!
B14: =B13+1 -> 7 | C14: 503.2 | D14: 5 | E14: =C14*D14 -> 2516 | F14: =E14 -> 2516 | G14: 35.314667 | H14: =(F14*G14)/1000 -> 88.851702 | I14: 1056.9999 | J14: =(H14*I14)/1000 -> 93.916238 | K14: =L14-J14 -> -93.916238 | M14: =(J14/L14) -> #DIV/0! | N14: =K14/L14 -> #DIV/0!
B15: =B14+1 -> 8 | C15: 610.8 | D15: 5 | E15: =C15*D15 -> 3054 | F15: =E15 -> 3054 | G15: 35.314667 | H15: =(F15*G15)/1000 -> 107.85099 | I15: 1037.3219 | J15: =(H15*I15)/1000 -> 111.87619 | K15: =L15-J15 -> -111.87619 | M15: =(J15/L15) -> #DIV/0! | N15: =K15/L15 -> #DIV/0!
B16: =B15+1 -> 9 | C16: 1327.2 | D16: 5 | E16: =C16*D16 -> 6636 | F16: =E16 -> 6636 | G16: 35.314667 | H16: =(F16*G16)/1000 -> 234.34813 | I16: 1045.3993 | J16: =(H16*I16)/1000 -> 244.98737 | K16: =L16-J16 -> -244.98737 | M16: =(J16/L16) -> #DIV/0! | N16: =K16/L16 -> #DIV/0!
B17: =B16+1 -> 10 | C17: 1237.5 | D17: 5 | E17: =C17*D17 -> 6187.5 | F17: =E17 -> 6187.5 | G17: 35.314667 | H17: =(F17*G17)/1000 -> 218.5095 | I17: 1047.8158 | J17: =(H17*I17)/1000 -> 228.95771 | K17: =L17-J17 -> -228.95771 | M17: =(J17/L17) -> #DIV/0! | N17: =K17/L17 -> #DIV/0!
B18: =B17+1 -> 11 | C18: 541.5 | D18: 5 | E18: =C18*D18 -> 2707.5 | F18: =E18 -> 2707.5 | G18: 35.314667 | H18: =(F18*G18)/1000 -> 95.614461 | I18: 1048.465 | J18: =(H18*I18)/1000 -> 100.24841 | K18: =L18-J18 -> -100.24841 | M18: =(J18/L18) -> #DIV/0! | N18: =K18/L18 -> #DIV/0!
B19: =B18+1 -> 12 | C19: 514.4 | D19: 5 | E19: =C19*D19 -> 2572 | F19: =E19 -> 2572 | G19: 35.314667 | H19: =(F19*G19)/1000 -> 90.829324 | I19: 1044.9255 | J19: =(H19*I19)/1000 -> 94.909879 | K19: =L19-J19 -> -94.909879 | M19: =(J19/L19) -> #DIV/0! | N19: =K19/L19 -> #DIV/0!
B20: =B19+1 -> 13 | C20: 1349.3 | D20: 5 | E20: =C20*D20 -> 6746.5 | F20: =E20 -> 6746.5 | G20: 35.314667 | H20: =(F20*G20)/1000 -> 238.2504 | I20: 1048.4922 | J20: =(H20*I20)/1000 -> 249.80368 | K20: =L20-J20 -> -249.80368 | M20: =(J20/L20) -> #DIV/0! | N20: =K20/L20 -> #DIV/0!
... B38: =B37+1 -> 31 | C38: 1028.9 | D38: 5 | E38: =C38*D38 -> 5144.5 | F38: =E38 -> 5144.5 | G38: 52.314667 | H38: =(F38*G38)/1000 -> 269.1328 | I38: 1063.1716 | J38: =(H38*I38)/1000 -> 286.13436 | K38: =L38-J38 -> -286.13436 | M38: =(J38/L38) -> #DIV/0! | N38: =K38/L38 -> #DIV/0!
B39: Average | F39: =AVERAGE(F8:F38) -> 5031.6129 | H39: =AVERAGE(H8:H38) -> 202.03544 | I39: =AVERAGE(I8:I38) -> 1056.8169 | J39: =AVERAGE(J8:J38) -> 213.80604 | K39: =AVERAGE(K8:K38) -> -213.80604 | L39: =AVERAGE(L8:L38) -> #DIV/0! | M39: =AVERAGE(M8:M38) -> #DIV/0! | N39: =AVERAGE(N8:N38) -> #DIV/0!
B40: TOTAL | C40: =SUM(C8:C38) -> 31196 | E40: =SUM(E8:E38) -> 155980 | F40: =SUM(F8:F38) -> 155980 | H40: =SUM(H8:H38) -> 6263.0988 | J40: =SUM(J8:J38) -> 6627.9873
B41: Koreksi
B42: Total Setelah Koreksi | H42: =H40+H41 -> 6263.0988 | J42: =J40+J41 -> 6627.9873
C44: CONVERT HP Boiler from Utility
C45: =C40 -> 31196 | D45: m3 | F45: =C40*5 -> 155980 | G45: 9983.7
C46: 5 | D46: bar | F46: 21286.9 | G46: =G45-C40 -> -21212.3
C47: =C45*C46 -> 155980 | D47: Sm3 | F47: =F45/F46 -> 7.3275113
C48: =G38 -> 52.314667 | D48: Scf
C49: =(C47*C48)/1000 -> 8160.0418 | D49: Volume (MSCF)
C50: =I39 -> 1056.8169 | D50: Heating Value
C51: =(C49*C50)/1000 -> 8623.6697 | D51: Energy (mmbtu)

Sheet OIP Refinery
B2: Oil In Plant Refinery
B4: No | C4: Tanggal | D4: Opening Stock | E4: Closing Stock | F4: Closing Stock | G4: Selisih OIP Consume
B5: 1 | C5: 01 Agustus 2024 | D5: 268536 | E5: 278115 | F5: 278115 | G5: =E5-D5 -> 9579
B6: 2 | C6: 02 Agustus 2024 | D6: =E5 -> 278115 | E6: 218067 | F6: 218067 | G6: =E6-D6 -> -60048
B7: 3 | C7: 03 Agustus 2024 | D7: =E6 -> 218067 | E7: 257614 | F7: 257614 | G7: =E7-D7 -> 39547
B8: 4 | C8: 04 Agustus 2024 | D8: =E7 -> 257614 | E8: 246851 | F8: 246851 | G8: =E8-D8 -> -10763
B9: 5 | C9: 05 Agustus 2024 | D9: =E8 -> 246851 | E9: 255653 | F9: 255653 | G9: =E9-D9 -> 8802
B10: 6 | C10: 06 Agustus 2024 | D10: =E9 -> 255653 | E10: 258450 | F10: 258450 | G10: =E10-D10 -> 2797
B11: 7 | C11: 07 Agustus 2024 | D11: =E10 -> 258450 | E11: 238552 | F11: 238552 | G11: =E11-D11 -> -19898
B12: 8 | C12: 08 Agustus 2024 | D12: =E11 -> 238552 | E12: 283505 | F12: 283505 | G12: =E12-D12 -> 44953
B13: 9 | C13: 09 Agustus 2024 | D13: =E12 -> 283505 | E13: 269320 | F13: 269320 | G13: =E13-D13 -> -14185
B14: 10 | C14: 10 Agustus 2024 | D14: =E13 -> 269320 | E14: 281809 | F14: 281809 | G14: =E14-D14 -> 12489
B15: 11 | C15: 11 Agustus 2024 | D15: =E14 -> 281809 | E15: 267958 | F15: 267958 | G15: =E15-D15 -> -13851
B16: 12 | C16: 12 Agustus 2024 | D16: =E15 -> 267958 | E16: 267268 | F16: 267268 | G16: =E16-D16 -> -690
B17: 13 | C17: 13 Agustus 2024 | D17: =E16 -> 267268 | E17: 285895 | F17: 285895 | G17: =E17-D17 -> 18627
B18: 14 | C18: 14 Agustus 2024 | D18: =E17 -> 285895 | E18: 259934 | F18: =286934-27000 -> 259934 | G18: =E18-D18 -> -25961
B19: 15 | C19: 15 Agustus 2024 | D19: =E18 -> 259934 | E19: 229375 | F19: =259375-30000 -> 229375 | G19: =E19-D19 -> -30559
B20: 16 | C20: 16 Agustus 2024 | D20: =E19 -> 229375 | E20: 206080 | F20: 206080 | G20: =E20-D20 -> -23295
B21: 17 | C21: 17 Agustus 2024 | D21: =E20 -> 206080 | E21: 205580 | F21: 205580 | G21: =E21-D21 -> -500
B22: 18 | C22: 18 Agustus 2024 | D22: =E21 -> 205580 | E22: 204650 | F22: 204650 | G22: =E22-D22 -> -930
B23: 19 | C23: 19 Agustus 2024 | D23: =E22 -> 204650 | E23: 204650 | F23: 204650 | G23: =E23-D23 -> 0
B24: 20 | C24: 20 Agustus 2024 | D24: =E23 -> 204650 | E24: 239103 | F24: =259103-20000 -> 239103 | G24: =E24-D24 -> 34453
B25: 21 | C25: 21 Agustus 2024 | D25: =E24 -> 239103 | E25: 242878 | F25: =222878+20000 -> 242878 | G25: =E25-D25 -> 3775
B26: 22 | C26: 22 Agustus 2024 | D26: =E25 -> 242878 | E26: 243484 | F26: =222984+20500 -> 243484 | G26: =E26-D26 -> 606
B27: 23 | C27: 23 Agustus 2024 | D27: =E26 -> 243484 | E27: 219216 | F27: 219216 | G27: =E27-D27 -> -24268
B28: 24 | C28: 24 Agustus 2024 | D28: =E27 -> 219216 | E28: 244970 | F28: 244970 | G28: =E28-D28 -> 25754
B29: 25 | C29: 25 Agustus 2024 | D29: =E28 -> 244970 | E29: 234886 | F29: =209886+25000 -> 234886 | G29: =E29-D29 -> -10084
B30: 26 | C30: 26 Agustus 2024 | D30: =E29 -> 234886 | E30: 267925 | F30: 0 | G30: =E30-D30 -> 33039
B31: 27 | C31: 27 Agustus 2024 | D31: =E30 -> 267925 | E31: 263146 | F31: 0 | G31: =E31-D31 -> -4779
B32: 28 | C32: 28 Agustus 2024 | D32: =E31 -> 263146 | E32: 290180.2 | F32: 0 | G32: =E32-D32 -> 27034.2
B33: 29 | C33: 29 Agustus 2024 | D33: =E32 -> 290180.2 | E33: 263346 | F33: 0 | G33: =E33-D33 -> -26834.2
B34: 30 | C34: 30 Agustus 2024 | D34: =E33 -> 263346 | E34: 270438 | F34: 0 | G34: =E34-D34 -> 7092
B35: 31 | C35: 31 Agustus 2024 | D35: =E34 -> 270438 | E35: 283428 | F35: 0 | G35: =E35-D35 -> 12990

Sheet OIP Fract
B2: Oil In Plant Fract
B4: No | C4: Tanggal | D4: Opening Stock | E4: Closing Stock | F4: Stock Minyak
B5: 1 | C5: 01 Agustus 2024 | F5: =E5-D5 -> 0
B6: 2 | C6: 02 Agustus 2024 | D6: =E5 -> 0 | E6: 0 | F6: =E6-D6 -> 0
B7: 3 | C7: 03 Agustus 2024 | D7: =E6 -> 0 | E7: 0 | F7: =E7-D7 -> 0
B8: 4 | C8: 04 Agustus 2024 | D8: =E7 -> 0 | E8: 0 | F8: =E8-D8 -> 0
B9: 5 | C9: 05 Agustus 2024 | D9: =E8 -> 0 | E9: 0 | F9: =E9-D9 -> 0
B10: 6 | C10: 06 Agustus 2024 | D10: =E9 -> 0 | E10: 0 | F10: =E10-D10 -> 0
B11: 7 | C11: 07 Agustus 2024 | D11: =E10 -> 0 | E11: 630010 | F11: =E11-D11 -> 630010
B12: 8 | C12: 08 Agustus 2024 | D12: =E11 -> 630010 | E12: 452800 | F12: =E12-D12 -> -177210
B13: 9 | C13: 09 Agustus 2024 | D13: =E12 -> 452800 | E13: 0 | F13: =E13-D13 -> -452800
B14: 10 | C14: 10 Agustus 2024 | D14: =E13 -> 0 | E14: 0 | F14: =E14-D14 -> 0
B15: 11 | C15: 11 Agustus 2024 | D15: =E14 -> 0 | E15: 0 | F15: =E15-D15 -> 0
B16: 12 | C16: 12 Agustus 2024 | D16: =E15 -> 0 | E16: 32710 | F16: =E16-D16 -> 32710
B17: 13 | C17: 13 Agustus 2024 | D17: =E16 -> 32710 | E17: 386480 | F17: =E17-D17 -> 353770
... B35: 31 | C35: 31 Agustus 2024 | D35: =E34 -> 582820 | E35: 637920 | F35: =E35-D35 -> 55100

Sheet Detail Agustus OIP Akhir Plant
D2: PT. INDUSTRI NABATI LESTARI | L2: Nomor Dokumen | N2: Tanggal Berlaku
D3: PABRIK MINYAK GORENG | L3: INLHO/BOPP-PRD/F-021 | N3: 44866
D4: Kantor Pusat : Komp.KEK Sei Mangkei, Kav.2-3, Kec. Bosar Maligas, Kab. Simalungun, Sumatera Utara, 21184 | L4: Nomor Revisi | N4: Halaman
D5: BERITA ACARA DEPARTEMEN REFINERY & FRACTIONATION | L5: 00 | N5: 2
C6: Hal : Stock Opname Oil In Plant ( Refinery & Fractionation )
C7: Berikut kami lampirkan laporan Stok Opname Oil In Plant Per-tanggal 01 September 2024.
D8: 1. Refinery | J8: 2. Fractination
D9: No. | E9: Tag. | F9: Volume (Ton) | G9: % | H9: Quantity (Ton) | J9: No. | K9: Tag. | L9: Volume (Ton) | M9: % | N9: Quantity (Ton)
F10: By Lipico | L10: By Lipico
D11: 1 | E11: MX312 | F11: 0.81 | G11: 100 | H11: =G11*F11/100 -> 0.81 | J11: 1 | K11: CR 1201 | L11: 56 | M11: 98.1 | N11: =M11*L11/100 -> 54.936
D12: 2 | E12: VE611 | F12: 72.587 | G12: 80 | H12: =G12*F12/100 -> 58.0696 | J12: 2 | K12: CR 1202 | L12: 56 | M12: 97.6 | N12: =M12*L12/100 -> 54.656
D13: 3 | E13: VE612 | F13: 23.884 | G13: 59 | H13: =G13*F13/100 -> 14.09156 | J13: 3 | K13: CR 1203 | L13: 56 | M13: 98.4 | N13: =M13*L13/100 -> 55.104
D14: 4 | E14: FL621 | F14: 7.38 | G14: 100 | H14: =G14*F14/100 -> 7.38 | J14: 4 | K14: CR 1204 | L14: 56 | M14: 98.4 | N14: =M14*L14/100 -> 55.104
D15: 5 | E15: FL622 | F15: 7.38 | G15: 100 | H15: =G15*F15/100 -> 7.38 | J15: 5 | K15: CR 1205 | L15: 56 | M15: 98.4 | N15: =M15*L15/100 -> 55.104
D16: 6 | E16: FL623 | F16: 7.38 | G16: 100 | H16: =G16*F16/100 -> 7.38 | J16: 6 | K16: CR 1206 | L16: 56 | M16: 98.4 | N16: =M16*L16/100 -> 55.104
D17: 7 | E17: FL624 | F17: 7.38 | G17: 0 | H17: =G17*F17/100 -> 0 | J17: 7 | K17: CR 1207 | L17: 56 | M17: 15.5 | N17: =M17*L17/100 -> 8.68
D18: 8 | E18: FL625 | F18: 7.38 | G18: 0 | H18: =G18*F18/100 -> 0 | J18: 8 | K18: CR 1208 | L18: 56 | M18: 98.3 | N18: =M18*L18/100 -> 55.048 | AB18: 55.888
D19: 9 | E19: FL625A/B | F19: 0.369 | G19: 100 | H19: =G19*F19/100 -> 0.369 | J19: 9 | K19: CR 1209 | L19: 56 | M19: 98.3 | N19: =M19*L19/100 -> 55.048 | AB19: 55.888
D20: 10 | E20: FL626A/B | F20: 0.243 | G20: 100 | H20: =G20*F20/100 -> 0.243 | J20: 10 | K20: CR 1210 | L20: 56 | M20: 98.3 | N20: =M20*L20/100 -> 55.048 | AB20: 55.776
D21: 11 | E21: FL741A/B | F21: 0.306 | G21: 100 | H21: =G21*F21/100 -> 0.306 | J21: 11 | K21: CR 1211 | L21: 56 | M21: 98.3 | N21: =M21*L21/100 -> 55.048 | AB21: 55.776
D22: 12 | E22: VE661 | F22: 5.383 | G22: 30 | H22: =G22*F22/100 -> 1.6149 | J22: 12 | K22: CR 1212 | L22: 56 | M22: 98.3 | N22: =M22*L22/100 -> 55.048 | AB22: 55.776
D23: 13 | E23: TK641 | F23: 7.798 | G23: 0 | H23: =G23*F23/100 -> 0 | J23: 13 | K23: T-261 | L23: 14.59 | M23: 80 | N23: =M23*L23/100 -> 11.672 | AB23: 55.664
D24: 14 | E24: VE701 | F24: 51.513 | G24: 70 | H24: =G24*F24/100 -> 36.0591 | J24: 14 | K24: T-241 | L24: 14.39 | M24: 85.6 | N24: =M24*L24/100 -> 12.31784 | AB24: 55.664
D25: 15 | E25: HE721A | F25: 18.45 | G25: 35 | H25: =G25*F25/100 -> 6.4575 | J25: 15 | K25: T-221 | L25: 56 | M25: 0 | N25: =M25*L25/100 -> 0 | AB25: 0
D26: 16 | E26: HE721B | F26: 18.45 | G26: 100 | H26: =G26*F26/100 -> 18.45 | J26: 16 | K26: T-231 A | L26: 23.4 | M26: 0 | N26: =M26*L26/100 -> 0 | AB26: 0
D27: 17 | E27: HE722 | F27: 12.33 | G27: 80 | H27: =G27*F27/100 -> 9.864 | J27: 17 | K27: T-231 B | L27: 23.4 | M27: 0 | N27: =M27*L27/100 -> 0 | AB27: 55.38
D28: 18 | E28: PR731 | F28: 8.171 | G28: 35 | H28: =G28*F28/100 -> 2.85985 | J28: 18 | K28: T-251 A | L28: 2.25 | M28: 0 | N28: =M28*L28/100 -> 0 | AB28: 55.88
D29: 19 | E29: DE732 | F29: 110.7 | G29: 100 | H29: =G29*F29/100 -> 110.7 | J29: 19 | K29: T-251 B | L29: 2.25 | M29: 0 | N29: =M29*L29/100 -> 0 | AB29: 56
D30: 20 | E30: VE 771 | F30: 0.433 | G30: 50 | H30: =G30*F30/100 -> 0.2165 | J30: Total | N30: =SUM(N11:N29) -> 637.91784 | AB30: 7.36
D31: 21 | E31: VE751 | F31: 4.149 | G31: 30 | H31: =G31*F31/100 -> 1.2447 | J31: Dengan Rincian OIP Fract Sebagai berikut : | AB31: 11.44
D32: 22 | E32: VE753 | F32: 0.814 | G32: 0 | H32: =G32*F32/100 -> 0 | K32: RBDPO : | L32: =SUM(N11:N25)+N28+N29 -> 637.91784 | M32: Mt | AB32: 47.88
D33: Total | H33: =SUM(H11:H32) -> 283.49571 | J33: RBDPS : | L33: =N26+N27 -> 0 | M33: Mt | AB33: =SUM(AB18:AB32) -> 624.372
D34: Dengan Rincian OIP Refinery Sebagai berikut :
D35: CPO : | E35: =H12+H13 -> 72.16116 | F35: Mt
D36: RBDPO : | E36: =H33-E35 -> 211.33455 | F36: Mt
C38: Demikian saya sampaikan, Terimakasih.
D39: Dibuat Oleh : | G39: Diperiksa Oleh : | L39: Diketahui Oleh :
C43: Triana Bayu Pramoedito | G43: Sudarianto | L43: Gunawan E. Putra
D44: SPV IBL | G44: Manager Produksi | L44: Head Controller and Tax

Sheet Juli - 2024xx
B1: PRODUCTION REPORT
B2: No | C2: ITEM | D2: Budget / Norma | E2: UoM | F2: JulI | AL2: TOTAL (Kg)
F3: 1 | G3: 2 | H3: 3 | I3: 4 | J3: 5 | K3: 6 | L3: 7 | M3: 8 | N3: 9 | O3: 10 | P3: 11 | Q3: 12 | R3: 13 | S3: 14 | T3: 15 | U3: 16 | V3: 17 | W3: 18 | X3: 19 | Y3: 20 | Z3: 21 | AA3: 22 | AB3: 23 | AC3: 24 | AD3: 25 | AE3: 26 | AF3: 27 | AG3: 28 | AH3: 29 | AI3: 30 | AJ3: 31
B4: 1 | C4: PRODUCTION | AL4: Production
C5: Refinery | AL5: Refinery
C6: Running Days | E6: Day | F6: 1 | G6: 1 | H6: 1 | I6: 1 | J6: 1 | K6: 1 | L6: 1 | M6: 1 | N6: 1 | O6: 1 | P6: 1 | Q6: 1 | R6: 1 | S6: 1 | AL6: =SUM(F6:O6) -> 10
C7: Incoming CPO | E7: Kg | F7: ='[19]01 '!$P$14 -> 865877 | G7: ='[19]02'!$P$14 -> 1020502 | H7: ='[19]03'!$P$14 -> 623069 | I7: ='[19]04'!$P$14 -> 686156 | J7: ='[19]05'!$P$14 -> 500524 | K7: ='[19]06'!$P$14 -> 286477 | L7: ='[19]07'!$P$11 -> 40800 | M7: ='[19]08'!$P$13+168651 -> 335707 | N7: ='[19]09'!$P$13 -> 203264 | O7: ='[20]10'!$P$14-22440 -> 803740 | P7: ='[21]11'!$P$14 -> 474327 | Q7: ='[22]12'!$P$13+156887 -> 486876 | R7: =186434+'[22]13'!$P$13 -> 412792 | S7: 0 | AL7: =SUM(F7:AI7) -> 6740111 | AM7: =AVERAGE(G7:O7) -> 500026.56 | AO7: =AL7/14 -> 481436.5
C8: Ratio Run CPO | E8: % | F8: =F9/2200000*100 -> 33.860182 | G8: =G9/2200000*100 -> 33.816909 | H8: =H9/2200000*100 -> 47.656136 | I8: =I9/2200000*100 -> 50.673682 | J8: =J9/2200000*100 -> 11.278455 | K8: =K9/2200000*100 -> 17.6585 | L8: =L9/2200000*100 -> 2.6320909 | M8: =M9/2200000*100 -> 11.742864 | ... AJ8: =AJ9/2200000*100 -> 0 | AL8: =AVERAGE(F8:S8) -> 23.675701
C9: CPO Consume Total | D9: 36359000 | E9: Kg | F9: ='[19]01 '!$Q$14 -> 744924 | G9: ='[19]02'!$Q$14 -> 743972 | H9: ='[19]03'!$Q$14 -> 1048435 | I9: ='[19]04'!$Q$14 -> 1114821 | J9: ='[19]05'!$Q$14 -> 248126 | K9: ='[19]06'!$Q$14 -> 388487 | L9: ='[19]07'!$Q$14 -> 57906 | M9: ='[19]08'!$Q$13 -> 258343 | N9: ='[19]09'!$Q$11 -> 154743 | O9: 512647 | P9: ='OIP Fract'!D15+'[21]11'!$Q$11-'OIP Fract'!E15 -> 441064 | Q9: ='OIP Fract'!D16+'[22]12'!$Q$13+'[22]12'!$Q$11-'OIP Fract'!E16 -> 493693 | R9: ='[22]13'!$Q$13 -> 568358 | S9: ='OIP Fract'!D18+'[22]14'!$Q$13+'[22]14'!$Q$11-'OIP Fract'!E18 -> 516597 | T9: 0 | AL9: =SUM(F9:AI9) -> 7292116 | AM9: =AL9/D9*100 -> 20.055876 | AN9: =AL9/10 -> 729211.6
C10: CPO Consume Poram | D10: 29045000 | E10: Kg | F10: =F9-F27-F36 -> 744924 | G10: =G9-G27-G36 -> 743972 | H10: =H9-H27-H36 -> 1048435 | I10: =I9-I27-I36 -> 1114821 | J10: =J9-J27-J36 -> 248126 | K10: =K9-K27-K36 -> 388487 | L10: =L9-L27-L36 -> 57906 | M10: =M9-M27-M36 -> 258343 | ... AJ10: =AJ9-AJ27-AJ36 -> 0 | AL10: =SUM(F10:AI10) -> 7292116
C11: CPO Consume Brand | D11: 7314000 | E11: Kg | F11: =F27+F36 -> 0 | G11: =G27+G36 -> 0 | H11: =H27+H36 -> 0 | I11: =I27+I36 -> 0 | J11: =J27+J36 -> 0 | K11: =K27+K36 -> 0 | L11: =L27+L36 -> 0 | M11: =M27+M36 -> 0 | ... AJ11: =AJ27+AJ36 -> 0 | AL11: =SUM(F11:AI11) -> 0
C12: - FFA | D12: 5 | E12: % | F12: 4.03 | G12: 4.14 | H12: 4.06 | I12: =(4.12+4.17+3.97)/3 -> 4.0866667 | J12: 4.18 | K12: =4.14 -> 4.14 | L12: 4.2 | M12: 4.08 | N12: 4.16 | O12: 4.18 | P12: 4.2 | Q12: 4.22 | R12: 3.96 | S12: =(4.29+4.09)/2 -> 4.19 | AL12: =AVERAGE(F12:AI12) -> 4.1304762
C13: - Moist & Impurities | D13: 0.5 | E13: % | F13: 0.44 | G13: 0.46 | H13: 0.455 | I13: =(0.43+0.44+0.48)/3 -> 0.45 | J13: 0.49 | K13: =(0.44+0.49)/2 -> 0.465 | L13: 0.4 | M13: 0.48 | N13: 0.4 | O13: 0.41 | P13: 0.47 | Q13: 0.4 | R13: 0.49 | S13: =(0.4+0.49)/2 -> 0.445 | AL13: =AVERAGE(F13:AI13) -> 0.44678571
C14: - DOBI | D14: 2,20 Min | E14: % | F14: 2.21 | G14: 2.21 | H14: 2.22 | I14: 2.21 | J14: 2.21 | K14: 2.21 | L14: 2.21 | M14: 2.22 | N14: 2.21 | O14: 2.22 | P14: 2.21 | Q14: 2.21 | R14: 2.22 | S14: 2.22 | AL14: =AVERAGE(F14:AI14) -> 2.2135714
C15: Product | AL15: Product
C16: RbdPO | D16: 34458000 | E16: Kg | F16: ='[19]01 '!$P$15 -> 667300 | G16: ='[19]02'!$P$15 -> 695000 | H16: ='[19]03'!$P$15 -> 814100 | I16: ='[19]04'!$P$15 -> 760000 | J16: 0 | K16: ='[19]06'!$P$15 -> 587100 | L16: ='[19]07'!$P$15 -> 92106 | M16: ='[19]08'!$P$16+'[19]08'!$P$15 -> 105220 | N16: ='[19]09'!$P$15+'[19]09'!$P$16 -> 70837 | O16: ='[20]10'!$P$17 -> 488153 | P16: ='[21]11'!$P$17 -> 379337 | Q16: ='[22]12'!$P$17 -> 492952 | R16: ='[22]13'!$P$17 -> 532902 | S16: ='[22]14'!$P$16 -> 497845 | T16: 91674 | AL16: =SUM(F16:AI16) -> 6274526
C17: PFAD | D17: 1636000 | E17: Kg | F17: ='[19]01 '!$P$24 -> 25659 | G17: ='[19]02'!$P$24 -> 18786 | H17: ='[19]03'!$P$24 -> 46938 | I17: ='[19]04'!$P$24 -> 48667 | K17: ='[19]06'!$P$24 -> 32281 | L17: ='[19]07'!$P$24 -> 0 | M17: ='[19]08'!$P$24 -> 26283 | N17: ='[19]09'!$P$23+'[19]09'!$P$24 -> 6431 | O17: ='[20]10'!$P$23 -> 20426 | P17: ='[21]11'!$P$23 -> 23275 | Q17: ='[22]12'!$P$25 -> 27655 | R17: ='[22]13'!$P$25 -> 25803 | S17: ='[22]13'!$P$25 -> 25803 | T17: 6643 | AL17: =SUM(F17:AI17) -> 334650
C18: Fractionation OLEIN IV 56 | AL18: Olein IV 56
C19: RBDPO Consume | E19: Kg | F19: =F20+F21 -> 0 | G19: =G20+G21 -> 0 | H19: =H20+H21 -> 0 | I19: =I20+I21 -> 0 | J19: =J20+J21 -> 0 | K19: =K20+K21 -> 0 | L19: =L20+L21 -> 0 | M19: =M20+M21 -> 0 | ... AJ19: =AJ20+AJ21 -> 0 | AL19: =SUM(F19:AI19) -> 0
C20: OLEIN IV 56 | E20: Kg | F20: 0 | G20: 0 | H20: 0 | AL20: =SUM(F20:AI20) -> 0
C21: STEARIN | E21: Kg | F21: 0 | G21: 0 | H21: 0 | AL21: =SUM(F21:AI21) -> 0
C22: Fractionation OLEIN IV 57 ( Bulk ) | AL22: Olein IV 57 ( Bulk )
C23: RBDPO Consume | E23: Kg | F23: =F24+F25 -> 0 | G23: =G24+G25 -> 0 | H23: =H24+H25 -> 0 | I23: =I24+I25 -> 0 | J23: =J24+J25 -> 0 | K23: =K24+K25 -> 0 | L23: =L24+L25 -> 0 | M23: =M24+M25 -> 0 | ... AJ23: =AJ24+AJ25 -> 0 | AL23: =SUM(F23:O23) -> 0
C24: OLEIN IV 57 | E24: Kg | F24: 0 | G24: 0 | H24: 0 | AL24: =SUM(F24:O24) -> 0
C25: STEARIN | E25: Kg | F25: 0 | G25: 0 | H25: 0 | AL25: =SUM(F25:O25) -> 0
C26: Fractionation OLEIN IV 57 ( Retail ) | AL26: Olein IV 57 ( Retail )
C27: CPO Consume | E27: Kg | AL27: =SUM(F27:O27) -> 0
C28: RBDPO Brand Consume | E28: Kg | F28: =F29+F30 -> 0 | G28: =G29+G30 -> 0 | H28: =H29+H30 -> 0 | I28: =I29+I30 -> 0 | J28: =J29+J30 -> 0 | K28: =K29+K30 -> 0 | L28: =L29+L30 -> 0 | M28: =M29+M30 -> 0 | ... AJ28: =AJ29+AJ30 -> 0 | AL28: =SUM(F28:O28) -> 0
C29: OLEIN IV 57 Low Color | E29: Kg | F29: 0 | G29: 0 | H29: 0 | AL29: =SUM(F29:O29) -> 0
C30: STEARIN | E30: Kg | F30: 0 | G30: 0 | H30: 0 | AL30: =SUM(F30:O30) -> 0
C31: Fractionation OLEIN IV 58 ( Bulk ) | AL31: Olein IV 58 ( Bulk )
C32: RBDPO Consume | D32: =D33+D34 -> 21429000 | E32: Kg | F32: =F33+F34 -> 636794 | G32: =G33+G34 -> 705632 | H32: =H33+H34 -> 727663 | I32: =I33+I34 -> 1053776 | J32: =J33+J34 -> 585552 | K32: =K33+K34 -> 632355 | L32: =L33+L34 -> 315146 | M32: =M33+M34 -> 0 | ... AJ32: =AJ33+AJ34 -> 0 | AL32: =SUM(F32:AI32) -> 7315959
C33: OLEIN IV 58 | D33: 15000000 | E33: Kg | F33: ='[19]01 '!$P$21 -> 437978 | G33: ='[19]02'!$P$21 -> 502403 | H33: ='[19]03'!$P$21 -> 540182 | I33: ='[19]04'!$P$21 -> 762960 | J33: ='[19]05'!$P$21 -> 360256 | K33: ='[19]06'!$P$21 -> 449507 | L33: ='[19]07'!$P$21 -> 208841 | M33: 0 | N33: ='[19]09'!$P$21 -> 295995 | O33: 0 | P33: ='[21]11'!$P$21 -> 478550 | Q33: ='[22]12'!$P$21 -> 209348 | R33: ='[22]13'!$P$21 -> 245921 | S33: ='[22]14'!$P$21 -> 428023 | T33: ='[23]15'!$P$21 -> 212137 | AL33: =SUM(F33:AI33) -> 5132101
C34: STEARIN | D34: 6429000 | E34: Kg | F34: ='[19]01 '!$P$29 -> 198816 | G34: ='[19]02'!$P$29 -> 203229 | H34: ='[19]03'!$P$28 -> 187481 | I34: ='[19]04'!$P$30 -> 290816 | J34: ='[19]05'!$P$28 -> 225296 | K34: ='[19]06'!$P$28 -> 182848 | L34: ='[19]07'!$P$28 -> 106305 | M34: 0 | N34: ='[19]09'!$P$28 -> 96081 | O34: 0 | P34: ='[21]11'!$P$28 -> 169774 | Q34: ='[22]12'!$P$28 -> 111127 | R34: ='[22]13'!$P$30 -> 83059 | S34: ='[22]14'!$P$30 -> 191480 | T34: ='[23]15'!$P$29 -> 137546 | AL34: =SUM(F34:AI34) -> 2183858
C35: Fractionation OLEIN IV 60 | AL35: Olein IV 60
C36: CPO Consume | E36: Kg | AL36: =SUM(F36:O36) -> 0
C37: RBDPO Brand Consume | E37: Kg | F37: =F39+F40 -> 0 | G37: =G39+G40 -> 0 | H37: =H39+H40 -> 0 | I37: =I39+I40 -> 0 | J37: =J39+J40 -> 0 | K37: =K39+K40 -> 0 | L37: =L39+L40 -> 0 | M37: =M39+M40 -> 0 | ... AJ37: =AJ39+AJ40 -> 0 | AL37: =SUM(F37:O37) -> 0
C38: OLEIN IV 60 Bulk | E38: Kg | F38: 0 | G38: 0 | H38: 0 | AL38: =SUM(F38:O38) -> 0
C39: OLEIN IV 60 Salvaco | E39: Kg | F39: 0 | G39: 0 | H39: 0 | AL39: =SUM(F39:O39) -> 0
C40: SOFT STEARIN | E40: Kg | F40: 0 | G40: 0 | H40: 0 | AL40: =SUM(F40:O40) -> 0
C41: Ratio Run RBDPO | E41: % | F41: 0 | AL41: =AVERAGE(F41:O41) -> 0
C42: YIELD | AL42: Yield
C43: RBDPO | D43: 94.2 | E43: % | F43: =(F16/(F9))*100 -> 89.579608 | G43: =(G16/(G9))*100 -> 93.417494 | H43: =(H16/(H9))*100 -> 77.649067 | I43: =(I16/(I9))*100 -> 68.172379 | J43: =(J16/(J9))*100 -> 0 | K43: =(K16/(K9))*100 -> 151.12475 | L43: =(L16/(L9))*100 -> 159.06124 | M43: =(M16/(M9))*100 -> 40.728799 | ... AJ43: =(AJ16/(AJ9))*100 -> #DIV/0! | AL43: =(AL16/(AL9))*100 -> 86.04534
C44: PFAD | D44: 5 | E44: % | F44: =(F17/(F9))*100 -> 3.4445125 | G44: =(G17/(G9))*100 -> 2.525095 | H44: =(H17/(H9))*100 -> 4.4769585 | I44: =(I17/(I9))*100 -> 4.3654542 | J44: =(J17/(J9))*100 -> 0 | K44: =(K17/(K9))*100 -> 8.3094158 | L44: =(L17/(L9))*100 -> 0 | M44: =(M17/(M9))*100 -> 10.173684 | ... AJ44: =(AJ17/(AJ9))*100 -> #DIV/0! | AL44: =(AL17/(AL9))*100 -> 4.5892029
C45: Olein IV 56 | D45: 82 | E45: % | F45: =(F20/F19)*100 -> #DIV/0! | G45: =(G20/G19)*100 -> #DIV/0! | H45: =(H20/H19)*100 -> #DIV/0! | I45: =(I20/I19)*100 -> #DIV/0! | J45: =(J20/J19)*100 -> #DIV/0! | K45: =(K20/K19)*100 -> #DIV/0! | L45: =(L20/L19)*100 -> #DIV/0! | M45: =(M20/M19)*100 -> #DIV/0! | ... AJ45: =(AJ20/AJ19)*100 -> #DIV/0! | AL45: =AL20/AL19*100 -> #DIV/0!
C46: Stearin | D46: 18 | E46: % | F46: =(F21/F19)*100 -> #DIV/0! | G46: =(G21/G19)*100 -> #DIV/0! | H46: =(H21/H19)*100 -> #DIV/0! | I46: =(I21/I19)*100 -> #DIV/0! | J46: =(J21/J19)*100 -> #DIV/0! | K46: =(K21/K19)*100 -> #DIV/0! | L46: =(L21/L19)*100 -> #DIV/0! | M46: =(M21/M19)*100 -> #DIV/0! | ... AJ46: =(AJ21/AJ19)*100 -> #DIV/0! | AL46: =AL25/AL23*100 -> #DIV/0!
C47: Olein IV 57 ( Bulk ) | D47: 75 | F47: =(F24/F23)*100 -> #DIV/0! | G47: =(G24/G23)*100 -> #DIV/0! | H47: =(H24/H23)*100 -> #DIV/0! | I47: =(I24/I23)*100 -> #DIV/0! | J47: =(J24/J23)*100 -> #DIV/0! | K47: =(K24/K23)*100 -> #DIV/0! | L47: =(L24/L23)*100 -> #DIV/0! | M47: =(M24/M23)*100 -> #DIV/0! | ... AJ47: =(AJ24/AJ23)*100 -> #DIV/0! | AL47: =(AL29/AL28)*100 -> #DIV/0!
C48: Stearin | D48: 25 | F48: =(F25/F23)*100 -> #DIV/0! | G48: =(G25/G23)*100 -> #DIV/0! | H48: =(H25/H23)*100 -> #DIV/0! | I48: =(I25/I23)*100 -> #DIV/0! | J48: =(J25/J23)*100 -> #DIV/0! | K48: =(K25/K23)*100 -> #DIV/0! | L48: =(L25/L23)*100 -> #DIV/0! | M48: =(M25/M23)*100 -> #DIV/0! | ... AJ48: =(AJ25/AJ23)*100 -> #DIV/0! | AL48: =(AL30/AL28)*100 -> #DIV/0!
C49: Olein IV 57 ( Retail ) | D49: 75 | E49: % | F49: =F29/F28*100 -> #DIV/0! | G49: =G29/G28*100 -> #DIV/0! | H49: =H29/H28*100 -> #DIV/0! | I49: =I29/I28*100 -> #DIV/0! | J49: =J29/J28*100 -> #DIV/0! | K49: =K29/K28*100 -> #DIV/0! | L49: =L29/L28*100 -> #DIV/0! | M49: =M29/M28*100 -> #DIV/0! | ... AJ49: =AJ29/AJ28*100 -> #DIV/0! | AL49: =AL29/AL28*100 -> #DIV/0!
C50: Stearin | D50: 25 | E50: % | F50: =F30/F28*100 -> #DIV/0! | G50: =G30/G28*100 -> #DIV/0! | H50: =H30/H28*100 -> #DIV/0! | I50: =I30/I28*100 -> #DIV/0! | J50: =J30/J28*100 -> #DIV/0! | K50: =K30/K28*100 -> #DIV/0! | L50: =L30/L28*100 -> #DIV/0! | M50: =M30/M28*100 -> #DIV/0! | ... AJ50: =AJ30/AJ28*100 -> #DIV/0! | AL50: =AL30/AL28*100 -> #DIV/0!
C51: Olein IV 58 ( Bulk ) | D51: 70 | E51: % | F51: =F33/F32*100 -> 68.7786 | G51: =G33/G32*100 -> 71.19901 | H51: =H33/H32*100 -> 74.235189 | I51: =I33/I32*100 -> 72.402484 | J51: =J33/J32*100 -> 61.524169 | K51: =K33/K32*100 -> 71.084596 | L51: =L33/L32*100 -> 66.268015 | M51: =M33/M32*100 -> #DIV/0! | ... AJ51: =AJ33/AJ32*100 -> #DIV/0! | AL51: =AL33/AL32*100 -> 70.149395
C52: Stearin | D52: 30 | E52: % | F52: =F34/F32*100 -> 31.2214 | G52: =G34/G32*100 -> 28.80099 | H52: =H34/H32*100 -> 25.764811 | I52: =I34/I32*100 -> 27.597516 | J52: =J34/J32*100 -> 38.475831 | K52: =K34/K32*100 -> 28.915404 | L52: =L34/L32*100 -> 33.731985 | M52: =M34/M32*100 -> #DIV/0! | ... AJ52: =AJ34/AJ32*100 -> #DIV/0! | AL52: =AL34/AL32*100 -> 29.850605
C53: Olein IV 60 | D53: 60 | E53: % | F53: =F38/F37*100 -> #DIV/0! | G53: =G38/G37*100 -> #DIV/0! | H53: =H38/H37*100 -> #DIV/0! | I53: =I38/I37*100 -> #DIV/0! | J53: =J38/J37*100 -> #DIV/0! | K53: =K38/K37*100 -> #DIV/0! | L53: =L38/L37*100 -> #DIV/0! | M53: =M38/M37*100 -> #DIV/0! | ... AJ53: =AJ38/AJ37*100 -> #DIV/0! | AL53: =(AL39+AL38)/AL37*100 -> #DIV/0!
C54: Soft Stearin | D54: 40 | E54: % | F54: =F40/F37*100 -> #DIV/0! | G54: =G40/G37*100 -> #DIV/0! | H54: =H40/H37*100 -> #DIV/0! | I54: =I40/I37*100 -> #DIV/0! | J54: =J40/J37*100 -> #DIV/0! | K54: =K40/K37*100 -> #DIV/0! | L54: =L40/L37*100 -> #DIV/0! | M54: =M40/M37*100 -> #DIV/0! | ... AJ54: =AJ40/AJ37*100 -> #DIV/0! | AL54: =AL40/AL37*100 -> #DIV/0!
B55: 2 | C55: CHEMICAL CONSUMABLE | AL55: Chemical
C56: Bleaching Earth (BE) to Poram Spec | D56: 8 | E56: Kg | F56: 7096 | G56: 10494 | H56: 9008 | I56: 9356 | J56: 280 | K56: 5099 | L56: 1205 | M56: 2788 | N56: 2079 | O56: 5395 | P56: 4274 | Q56: 7474 | R56: 8184 | S56: 6386 | T56: 0 | AL56: =SUM(F56:AI56) -> 79118
E57: % | F57: =F56/(F10)*100 -> 0.9525804 | G57: =G56/(G10)*100 -> 1.410537 | H57: =H56/(H10)*100 -> 0.85918536 | I57: =I56/(I10)*100 -> 0.83923787 | J57: =J56/(J10)*100 -> 0.11284589 | K57: =K56/(K10)*100 -> 1.3125278 | L57: =L56/(L10)*100 -> 2.0809588 | M57: =M56/(M10)*100 -> 1.0791854 | ... AJ57: =AJ56/(AJ10)*100 -> #DIV/0! | AL57: =AL56/(AL10)*100 -> 1.08498 | AM57: =AL57*10 -> 10.8498 | BJ57: #DIV/0! | BK57: #DIV/0!
C58: Bleaching Earth (BE) to Branded Spec | D58: 18 | E58: Kg | F58: 0 | G58: 0 | H58: 0 | I58: 0 | J58: 0 | K58: 0 | L58: 0 | M58: 0 | N58: 0 | O58: 0 | P58: 0 | Q58: 0 | R58: 0 | S58: 0 | T58: 0 | AL58: =SUM(F58:O58) -> 0
E59: % | F59: =F58/(F11)*100 -> #DIV/0! | G59: =G58/(G11)*100 -> #DIV/0! | H59: =H58/(H11)*100 -> #DIV/0! | I59: =I58/(I11)*100 -> #DIV/0! | J59: =J58/(J11)*100 -> #DIV/0! | K59: =K58/(K11)*100 -> #DIV/0! | L59: =L58/(L11)*100 -> #DIV/0! | M59: =M58/(M11)*100 -> #DIV/0! | ... AJ59: =AJ58/(AJ11)*100 -> #DIV/0! | AL59: =AL58/(AL11)*100 -> #DIV/0!
C60: Phosporic Acid (PA) | D60: 0.6 | E60: Kg | F60: 315.986 | G60: 398.732 | H60: 486.214 | I60: 494.384 | J60: 17.49 | K60: 277.508 | L60: 61.798 | M60: 129.422 | N60: 80.45 | O60: 227.37 | P60: 186.56 | Q60: 286.836 | R60: 281.006 | S60: 228.536 | T60: 0 | AL60: =SUM(F60:AI60) -> 3472.292
E61: % | F61: =F60/(F9)*100 -> 0.042418555 | G61: =G60/(G9)*100 -> 0.053595028 | H61: =H60/(H9)*100 -> 0.046375216 | I61: =I60/(I9)*100 -> 0.044346491 | J61: =J60/(J9)*100 -> 0.0070488381 | K61: =K60/(K9)*100 -> 0.071433021 | L61: =L60/(L9)*100 -> 0.10672124 | M61: =M60/(M9)*100 -> 0.050096964 | ... AJ61: =AJ60/(AJ9)*100 -> #DIV/0! | AL61: =AL60/(AL9)*100 -> 0.04761707
B62: 3 | C62: OIL LOSSES | D62: 0.8 | E62: % | F62: =((SUM(F16:F17))-(SUM(F9)))/(SUM(F9))*100 -> -6.9758794 | G62: =((SUM(G16:G17))-(SUM(G9)))/(SUM(G9))*100 -> -4.0574108 | H62: =((SUM(H16:H17))-(SUM(H9)))/(SUM(H9))*100 -> -17.873974 | I62: =((SUM(I16:I17))-(SUM(I9)))/(SUM(I9))*100 -> -27.462167 | J62: =((SUM(J16:J17))-(SUM(J9)))/(SUM(J9))*100 -> -100 | K62: =((SUM(K16:K17))-(SUM(K9)))/(SUM(K9))*100 -> 59.434164 | L62: =((SUM(L16:L17))-(SUM(L9)))/(SUM(L9))*100 -> 59.061237 | M62: =((SUM(M16:M17))-(SUM(M9)))/(SUM(M9))*100 -> -49.097518 | ... AJ62: =((SUM(AJ16:AJ17))-(SUM(AJ9)))/(SUM(AJ9))*100 -> #DIV/0! | AL62: =((SUM(AL16:AL17))-(SUM(AL9)))/(SUM(AL9))*100 -> -9.3654572
E63: Kg | F63: =F62%*F9 -> -51965 | G63: =G62%*G9 -> -30186 | H63: =H62%*H9 -> -187397 | I63: =I62%*I9 -> -306154 | J63: =J62%*J9 -> -248126 | K63: =K62%*K9 -> 230894 | L63: =L62%*L9 -> 34200 | M63: =M62%*M9 -> -126840 | ... S63: =S62%*S9 -> 7051 | U63: =U62%*U9 -> #DIV/0! | V63: =V62%*V9 -> #DIV/0! | W63: =W62%*W9 -> #DIV/0! | X63: =X62%*X9 -> #DIV/0! | Y63: =Y62%*Y9 -> #DIV/0! | Z63: =Z62%*Z9 -> #DIV/0! | AA63: =AA62%*AA9 -> #DIV/0! | AB63: =AB62%*AB9 -> #DIV/0! | ... AI63: =AI62%*AI9 -> #DIV/0! | AL63: =SUM(F63:AJ63) -> #DIV/0!
C64: % Oil Content | D64: 22 | E64: % | F64: 21.85 | G64: 21.96 | H64: 21.92 | I64: 21.87 | J64: 21.9 | K64: 21.9 | L64: 21.9 | M64: 21.87 | N64: 22 | O64: 22.17 | P64: 22.21 | Q64: 21.99 | R64: 22.17 | S64: 22.03 | T64: 0 | AL64: =AVERAGE(F64:AI64) -> 20.516
C65: Spent Bleaching Earth | E65: Kg | F65: =SUM(F56,F58)+(F64%*SUM(F56,F58)) -> 8646.476 | G65: =SUM(G56,G58)+(G64%*SUM(G56,G58)) -> 12798.482 | H65: =SUM(H56,H58)+(H64%*SUM(H56,H58)) -> 10982.554 | I65: =SUM(I56,I58)+(I64%*SUM(I56,I58)) -> 11402.157 | J65: =SUM(J56,J58)+(J64%*SUM(J56,J58)) -> 341.32 | K65: =SUM(K56,K58)+(K64%*SUM(K56,K58)) -> 6215.681 | L65: =SUM(L56,L58)+(L64%*SUM(L56,L58)) -> 1468.895 | M65: =SUM(M56,M58)+(M64%*SUM(M56,M58)) -> 3397.7356 | ... AJ65: =SUM(AJ56,AJ58)+(AJ64%*SUM(AJ56,AJ58)) -> 0 | AL65: =SUM(AL56,AL58)+(AL64%*SUM(AL56,AL58)) -> 95349.849
B66: 4 | C66: PACKAGING (Brand Salvaco) | AL66: Packaging
C67: Olein IV 60 Received | E67: Kg | AL67: 0
C68: Olein IV 60 Consume | E68: Kg | AL68: 0
C69: - finished product | E69: Kg | F69: 0 | G69: 0 | H69: 0 | I69: 0 | J69: 0 | K69: 0 | L69: 0 | M69: 0 | N69: 0 | O69: 0 | P69: 0 | Q69: 0 | R69: 0 | S69: 0 | T69: 0 | U69: 0 | V69: 0 | W69: 0 | X69: 0 | Y69: 0 | Z69: 0 | AA69: 0 | AB69: 0 | AC69: 0 | AD69: 0 | AE69: 0 | AF69: 0 | AG69: 0 | AH69: 0 | AI69: 0 | AJ69: 0 | AL69: 0
C70: - sample | E70: Kg | F70: 0 | G70: 0 | H70: 0 | I70: 0 | J70: 0 | K70: 0 | L70: 0 | M70: 0 | N70: 0 | O70: 0 | P70: 0 | Q70: 0 | R70: 0 | S70: 0 | T70: 0 | U70: 0 | V70: 0 | W70: 0 | X70: 0 | Y70: 0 | Z70: 0 | AA70: 0 | AB70: 0 | AC70: 0 | AD70: 0 | AE70: 0 | AF70: 0 | AG70: 0 | AH70: 0 | AI70: 0 | AJ70: 0 | AL70: 0
C71: - remelt, flushing, downgrade | E71: Kg | F71: 0 | H71: 0 | I71: 0 | J71: 0 | K71: 0 | L71: 0 | M71: 0 | N71: 0 | O71: 0 | P71: 0 | Q71: 0 | R71: 0 | S71: 0 | T71: 0 | U71: 0 | V71: 0 | W71: 0 | X71: 0 | Y71: 0 | Z71: 0 | AA71: 0 | AB71: 0 | AC71: 0 | AD71: 0 | AE71: 0 | AF71: 0 | AG71: 0 | AH71: 0 | AI71: 0 | AJ71: 0 | AL71: 0
C72: Carton | AL72: Carton
C73: Salvaco 1 Liter | E73: Box | AL73: 0
C74: Salvaco 2 Liter | E74: Box | AL74: 0
C75: Pouch | AL75: Pouch
C76: Salvaco 1 Liter | E76: Pouch | F76: 0 | G76: 0 | H76: 0 | I76: 0 | J76: 0 | K76: 0 | L76: 0 | M76: 0 | N76: 0 | O76: 0 | P76: 0 | Q76: 0 | R76: 0 | S76: 0 | T76: 0 | U76: 0 | V76: 0 | W76: 0 | X76: 0 | Y76: 0 | Z76: 0 | AA76: 0 | AB76: 0 | AC76: 0 | AD76: 0 | AE76: 0 | AF76: 0 | AG76: 0 | AH76: 0 | AI76: 0 | AJ76: 0 | AL76: 0
C77: Salvaco 2 Liter | E77: Pouch | F77: 0 | G77: 0 | H77: 0 | I77: 0 | J77: 0 | K77: 0 | L77: 0 | M77: 0 | N77: 0 | O77: 0 | P77: 0 | Q77: 0 | R77: 0 | S77: 0 | T77: 0 | U77: 0 | V77: 0 | W77: 0 | X77: 0 | Y77: 0 | Z77: 0 | AA77: 0 | AB77: 0 | AC77: 0 | AD77: 0 | AE77: 0 | AF77: 0 | AG77: 0 | AH77: 0 | AI77: 0 | AJ77: 0 | AL77: 0
C78: Consumable Vit. A | E78: gram | F78: 0 | G78: 0 | H78: 0 | I78: 0 | J78: 0 | K78: 0 | L78: 0 | M78: 0 | N78: 0 | O78: 0 | P78: 0 | Q78: 0 | R78: 0 | S78: 0 | T78: 0 | U78: 0 | V78: 0 | W78: 0 | X78: 0 | Y78: 0 | Z78: 0 | AA78: 0 | AB78: 0 | AC78: 0 | AD78: 0 | AE78: 0 | AF78: 0 | AG78: 0 | AH78: 0 | AI78: 0 | AJ78: 0 | AL78: 0
C79: Consumable Packing Tape | E79: Roll | F79: 0 | G79: 0 | H79: 0 | I79: 0 | J79: 0 | K79: 0 | L79: 0 | M79: 0 | N79: 0 | O79: 0 | P79: 0 | Q79: 0 | R79: 0 | S79: 0 | T79: 0 | U79: 0 | V79: 0 | W79: 0 | X79: 0 | Y79: 0 | Z79: 0 | AA79: 0 | AB79: 0 | AC79: 0 | AD79: 0 | AE79: 0 | AF79: 0 | AG79: 0 | AH79: 0 | AI79: 0 | AJ79: 0 | AL79: 0
C80: REJECT MATERIAL QTY | AL80: Loss Material
C81: Carton | AL81: Carton
C82: Salvaco 1 Liter | E82: Box | AL82: 0
C83: Salvaco 2 Liter | E83: Box | AL83: 0
C84: Pouch | AL84: Pouch
C85: Salvaco 1 Liter | E85: Pouch | F85: 0 | G85: 0 | H85: 0 | I85: 0 | J85: 0 | K85: 0 | L85: 0 | M85: 0 | N85: 0 | O85: 0 | P85: 0 | Q85: 0 | R85: 0 | S85: 0 | T85: 0 | U85: 0 | V85: 0 | W85: 0 | X85: 0 | Y85: 0 | Z85: 0 | AA85: 0 | AB85: 0 | AC85: 0 | AD85: 0 | AE85: 0 | AF85: 0 | AG85: 0 | AH85: 0 | AI85: 0 | AJ85: 0 | AL85: 0
C86: Salvaco 2 Liter | E86: Pouch | F86: 0 | G86: 0 | H86: 0 | I86: 0 | J86: 0 | K86: 0 | L86: 0 | M86: 0 | N86: 0 | O86: 0 | P86: 0 | Q86: 0 | R86: 0 | S86: 0 | T86: 0 | U86: 0 | V86: 0 | W86: 0 | X86: 0 | Y86: 0 | Z86: 0 | AA86: 0 | AB86: 0 | AC86: 0 | AD86: 0 | AE86: 0 | AF86: 0 | AG86: 0 | AH86: 0 | AI86: 0 | AJ86: 0 | AL86: 0
C87: REJECT MATERIAL (%) | AL87: Loss Material
C88: Carton | AL88: Carton
C89: Salvaco 1 Liter | D89: 0.3 | E89: % | F89: #DIV/0! | G89: #DIV/0! | H89: #DIV/0! | I89: #DIV/0! | J89: #DIV/0! | K89: #DIV/0! | L89: #DIV/0! | M89: #DIV/0! | N89: #DIV/0! | O89: #DIV/0! | P89: #DIV/0! | Q89: #DIV/0! | R89: #DIV/0! | S89: #DIV/0! | T89: #DIV/0! | U89: #DIV/0! | V89: #DIV/0! | W89: #DIV/0! | X89: #DIV/0! | Y89: #DIV/0! | Z89: #DIV/0! | AA89: #DIV/0! | AB89: #DIV/0! | AC89: #DIV/0! | AD89: #DIV/0! | AE89: #DIV/0! | AF89: #DIV/0! | AG89: #DIV/0! | AH89: #DIV/0! | AI89: #DIV/0! | AJ89: #DIV/0! | AL89: #DIV/0!
C90: Salvaco 2 Liter | D90: 0.3 | E90: % | F90: #DIV/0! | G90: #DIV/0! | H90: #DIV/0! | I90: #DIV/0! | J90: #DIV/0! | K90: #DIV/0! | L90: #DIV/0! | M90: #DIV/0! | N90: #DIV/0! | O90: #DIV/0! | P90: #DIV/0! | Q90: #DIV/0! | R90: #DIV/0! | S90: #DIV/0! | T90: #DIV/0! | U90: #DIV/0! | V90: #DIV/0! | W90: #DIV/0! | X90: #DIV/0! | Y90: #DIV/0! | Z90: #DIV/0! | AA90: #DIV/0! | AB90: #DIV/0! | AC90: #DIV/0! | AD90: #DIV/0! | AE90: #DIV/0! | AF90: #DIV/0! | AG90: #DIV/0! | AH90: #DIV/0! | AI90: #DIV/0! | AJ90: #DIV/0! | AL90: #DIV/0!
C91: Pouch | AL91: Pouch
C92: Salvaco 1 Liter | D92: 0.5 | E92: % | F92: #DIV/0! | G92: #DIV/0! | H92: #DIV/0! | I92: #DIV/0! | J92: #DIV/0! | K92: #DIV/0! | L92: #DIV/0! | M92: #DIV/0! | N92: #DIV/0! | O92: #DIV/0! | P92: #DIV/0! | Q92: #DIV/0! | R92: #DIV/0! | S92: #DIV/0! | T92: #DIV/0! | U92: #DIV/0! | V92: #DIV/0! | W92: #DIV/0! | X92: #DIV/0! | Y92: #DIV/0! | Z92: #DIV/0! | AA92: #DIV/0! | AB92: #DIV/0! | AC92: #DIV/0! | AD92: #DIV/0! | AE92: #DIV/0! | AF92: #DIV/0! | AG92: #DIV/0! | AH92: #DIV/0! | AI92: #DIV/0! | AJ92: #DIV/0! | AL92: #DIV/0!
C93: Salvaco 2 Liter | D93: 0.5 | E93: % | F93: #DIV/0! | G93: #DIV/0! | H93: #DIV/0! | I93: #DIV/0! | J93: #DIV/0! | K93: #DIV/0! | L93: #DIV/0! | M93: #DIV/0! | N93: #DIV/0! | O93: #DIV/0! | P93: #DIV/0! | Q93: #DIV/0! | R93: #DIV/0! | S93: #DIV/0! | T93: #DIV/0! | U93: #DIV/0! | V93: #DIV/0! | W93: #DIV/0! | X93: #DIV/0! | Y93: #DIV/0! | Z93: #DIV/0! | AA93: #DIV/0! | AB93: #DIV/0! | AC93: #DIV/0! | AD93: #DIV/0! | AE93: #DIV/0! | AF93: #DIV/0! | AG93: #DIV/0! | AH93: #DIV/0! | AI93: #DIV/0! | AJ93: #DIV/0! | AL93: #DIV/0!
B94: 5 | C94: PACKAGING (Brand Nusakita) | AL94: Packaging
C95: Olein IV 60 Consume | E95: Kg | AL95: 0
C96: - finished product | E96: Kg | F96: 0 | G96: 0 | H96: 0 | I96: 0 | J96: 0 | K96: 0 | L96: 0 | M96: 0 | N96: 0 | O96: 0 | P96: 0 | Q96: 0 | R96: 0 | S96: 0 | T96: 0 | U96: 0 | V96: 0 | W96: 0 | X96: 0 | Y96: 0 | Z96: 0 | AA96: 0 | AB96: 0 | AC96: 0 | AD96: 0 | AE96: 0 | AF96: 0 | AG96: 0 | AH96: 0 | AI96: 0 | AJ96: 0 | AL96: 0
C97: - sample | E97: Kg | F97: 0 | G97: 0 | H97: 0 | I97: 0 | J97: 0 | K97: 0 | L97: 0 | M97: 0 | N97: 0 | O97: 0 | P97: 0 | Q97: 0 | R97: 0 | S97: 0 | T97: 0 | U97: 0 | V97: 0 | W97: 0 | X97: 0 | Y97: 0 | Z97: 0 | AA97: 0 | AB97: 0 | AC97: 0 | AD97: 0 | AE97: 0 | AF97: 0 | AG97: 0 | AH97: 0 | AI97: 0 | AJ97: 0 | AL97: 0
C98: - remelt, flushing, downgrade | E98: Kg | F98: 0 | H98: 0 | I98: 0 | J98: 0 | K98: 0 | L98: 0 | M98: 0 | N98: 0 | O98: 0 | P98: 0 | Q98: 0 | R98: 0 | S98: 0 | T98: 0 | U98: 0 | V98: 0 | W98: 0 | X98: 0 | Y98: 0 | Z98: 0 | AA98: 0 | AB98: 0 | AC98: 0 | AD98: 0 | AE98: 0 | AF98: 0 | AG98: 0 | AH98: 0 | AI98: 0 | AJ98: 0 | AL98: 0
C99: Carton | AL99: Carton
C100: Nusakita 1 Liter | E100: Box | AL100: 0
...

Sheet 2024
C2: PRODUCTION REPORT 2024
B4: No | C4: ITEM | D4: Budget / Norma | E4: UoM | F4: MONTHLY REPORT | S4: Yearly Report | T4: Yearly Report RKAP (Budget) | U4: Yearly Report RKAP
F5: JANUARI | G5: FEBRUARI | H5: MARET | I5: APRIL | J5: MEI | K5: JUNI | L5: JULI | M5: AGUSTUS | N5: SEPTEMBER | O5: OKTOBER | P5: NOVEMBER | Q5: DESEMBER | S5: TOTAL (Kg) | T5: TOTAL (Kg) | U5: TOTAL (%)
B6: 1 | C6: PRODUCTION | S6: Production | T6: Production | U6: Production | DG6: 29 | DH6: 30 | DI6: 31
C7: Refinery | S7: Refinery | T7: Refinery | U7: Refinery | DE7: CPO Olah | DF7: Kg | DG7: 1971320 | DH7: 2015120 | DI7: 2015230 | AIU7: Sounding | AIV7: Production | AIW7: Diff
C8: Running Days | E8: Day | F8: ='[24]Januari 24'!AL9 -> 18 | G8: ='[24]Februari 24'!AL9 -> 11 | H8: ='[24]Maret 24'!AL9 -> 5 | I8: ='[25]April - 24'!$AK$9 -> 0 | J8: ='[26]Mei - 24'!$AL$9 -> 0 | K8: ='[27]Juni - 24'!$AL$9 -> 18 | L8: ='[28]Juli - 2024 ( Revisi )'!$AL$6 -> 22 | M8: ='Agustus - 2024'!AN6 -> 28 | N8: ='[24]September 24'!AL9 -> 0 | O8: ='[24]Oktober 24'!AL9 -> 0 | P8: ='[24]November 24'!AL9 -> 0 | Q8: ='[24]Desember 24'!AL9 -> 0 | S8: =SUM(F8:Q8) -> 102 | T8: 231 | U8: =S8/T8*100 -> 44.155844 | OR8: Poram | AEE8: 14 Juni | AEF8: 15 Juni | AIT8: CPO | AIU8: 11008948 | AIV8: =S11 -> 74746909 | AIW8: =AIU8-AIV8 -> -63737961
C9: Ratio Run CPO | F9: ='[24]Januari 24'!AL10 -> 17.457609 | G9: ='[24]Februari 24'!AL10 -> 17.224767 | H9: ='[24]Maret 24'!AL10 -> 4.5497713 | I9: ='[25]April - 24'!$AK$11 -> 0 | J9: ='[26]Mei - 24'!$AL$11 -> 0 | K9: ='[27]Juni - 24'!$AL$11 -> 13.078035 | L9: ='[28]Juli - 2024 ( Revisi )'!$AL$8 -> 23.454544 | M9: ='Agustus - 2024'!AN8 -> 33.834848 | N9: ='[24]September 24'!AL10 -> 0 | O9: ='[24]Oktober 24'!AL10 -> 0 | P9: ='[24]November 24'!AL10 -> 0 | Q9: ='[24]Desember 24'!AL10 -> 0
C10: Utilitas CPO | F10: =F11/F14*100 -> 18.288923 | G10: =G11/G14*100 -> 25.986707 | H10: =H11/H14*100 -> 7.9383545 | I10: =I11/I14*100 -> #VALUE! | J10: =J11/J14*100 -> 0 | K10: =K11/K14*100 -> 24.530983 | L10: =L11/L14*100 -> 43.994607 | M10: =M11/M14*100 -> 63.465348 | ... Q10: =Q11/Q14*100 -> 0 | S10: =AVERAGE(F10:O10) -> #VALUE!
C11: CPO Consume Total | D11: 701400000 | E11: Kg | F11: ='[24]Januari 24'!AL11 -> 11906089 | G11: ='[24]Februari 24'!AL11 -> 11747291 | H11: ='[24]Maret 24'!AL11 -> 3102944 | I11: ='[25]April - 24'!$AK$12 -> 0 | J11: ='[26]Mei - 24'!$AL$12 -> 0 | K11: ='[27]Juni - 24'!$AL$12 -> 8919220 | L11: ='[28]Juli - 2024 ( Revisi )'!$AL$9 -> 15995999 | M11: ='Agustus - 2024'!AN9 -> 23075366 | N11: ='[24]September 24'!AL11 -> 0 | O11: ='[24]Oktober 24'!AL11 -> 0 | P11: ='[24]November 24'!AL11 -> 0 | Q11: ='[24]Desember 24'!AL11 -> 0 | S11: =SUM(F11:Q11) -> 74746909 | T11: 421374000 | U11: =S11/T11 -> 0.17738852 | AX11: =S11/D11 -> 0.10656816 | DE11: HP Boiler | DF11: mmbtu | DG11: 251.19642 | DH11: 257.91391 | DI11: 251.51265 | OO11: 26946.108 | OP11: 17383.234 | OR11: RBDPO Olah | AEE11: =35.8500000000058*1000 -> 35850 | AIT11: PFAD | AIU11: 566885 | AIV11: =S20 -> 3394842 | AIW11: =AIU11-AIV11 -> -2827957
C12: CPO Consume Poram | E12: Kg | F12: ='[24]Januari 24'!AL12 -> 10284033 | G12: ='[24]Februari 24'!AL12 -> 10885811 | H12: ='[24]Maret 24'!AL12 -> 2891954.7 | I12: ='[25]April - 24'!$AK$13 -> 0 | J12: ='[26]Mei - 24'!$AL$13 -> 0 | K12: ='[27]Juni - 24'!$AL$13 -> 8919220 | L12: ='[28]Juli - 2024 ( Revisi )'!$AL$10 -> 15995999 | M12: ='Agustus - 2024'!AN10 -> 22890671 | N12: 0 | O12: 0 | P12: ='[24]November 24'!AL12 -> #DIV/0! | Q12: ='[24]Desember 24'!AL12 -> #DIV/0! | S12: =SUM(F12:O12) -> 71867688
C13: CPO Consume Brand | E13: Kg | F13: ='[24]Januari 24'!AL13 -> 1622056.5 | G13: ='[24]Februari 24'!AL13 -> 861480.39 | H13: ='[24]Maret 24'!AL13 -> 210989.34 | I13: 0 | J13: 0 | K13: 0 | L13: ='[28]Juli - 2024 ( Revisi )'!$AL$11 -> 0 | M13: ='Agustus - 2024'!AN11 -> 184695 | N13: 0 | O13: 0 | P13: ='[24]November 24'!AL13 -> #DIV/0! | Q13: ='[24]Desember 24'!AL13 -> #DIV/0! | S13: =SUM(F13:O13) -> 2879221.2 | AX13: =AW13/P13 -> #DIV/0!
C14: Budget CPO Olah | E14: Kg | F14: 65100000 | G14: 45205000 | H14: 39088000 | I14: ='[25]April - 24'!$C$12 -> CPO Consume Total | J14: ='[26]Mei - 24'!$D$12 -> 36359000 | K14: ='[27]Juni - 24'!$D$12 -> 36359000 | L14: ='[29]Juli - 2024'!$D$9 -> 36359000 | M14: ='[29]Juli - 2024'!$D$9 -> 36359000 | N14: ='[29]Juli - 2024'!$D$9 -> 36359000 | O14: ='[29]Juli - 2024'!$D$9 -> 36359000 | P14: ='[29]Juli - 2024'!$D$9 -> 36359000 | Q14: ='[29]Juli - 2024'!$D$9 -> 36359000 | S14: =SUM(F14:Q14) -> 440265000
C15: - FFA | D15: 5 | E15: % | F15: 4.38 | G15: 4.56 | H15: 4.19 | I15: 4.11 | J15: 3.86 | K15: 4.25 | L15: ='[28]Juli - 2024 ( Revisi )'!$AL$12 -> 3.8848485 | M15: ='Agustus - 2024'!AN12 -> 3.9614881 | N15: 0 | O15: 0 | P15: ='[24]November 24'!AL14 -> #DIV/0! | Q15: ='[24]Desember 24'!AL14 -> #DIV/0! | S15: =AVERAGE(F15:O15) -> 3.3196337 | T15: =AVERAGE(G15:R15) -> #DIV/0! | U15: =AVERAGE(H15:S15) -> #DIV/0! | DE15: Steam Ref | DF15: Kg | DG15: 182230 | DH15: 190070 | DI15: 197800 | OO15: =S11/1000 -> 74746.909 | OP15: =(S25+S43+S34)/1000 -> 18951.156 | OR15: =SUM(OR16:OR17) -> #REF! | AGV15: 2000
C16: - Moist & Impurities | D16: 0.5 | E16: % | F16: ='[24]Januari 24'!AL15 -> 0.42388889 | G16: ='[24]Februari 24'!AL15 -> 0.43545455 | H16: ='[24]Maret 24'!AL15 -> 0.43 | I16: ='[25]April - 24'!$AK$16 -> 0 | J16: ='[26]Mei - 24'!$AL$16 -> 0 | K16: ='[27]Juni - 24'!$AL$16 -> 0.45375 | L16: ='[28]Juli - 2024 ( Revisi )'!$AL$13 -> 0.41795455 | M16: ='Agustus - 2024'!AN13 -> 0.43083333 | N16: 0 | O16: 0 | P16: ='[24]November 24'!AL15 -> #DIV/0! | Q16: ='[24]Desember 24'!AL15 -> #DIV/0! | S16: =AVERAGE(F16:O16) -> 0.25918813 | T16: =AVERAGE(G16:R16) -> #DIV/0! | U16: =AVERAGE(H16:S16) -> #DIV/0! | DF16: Kg/MT | DG16: =DG15/(DG7/1000) -> 92.440598 | DH16: =DH15/(DH7/1000) -> 94.321926 | DI16: =DI15/(DI7/1000) -> 98.152568 | OR16: =#REF!/1000 -> #REF! | OS16: =OR16/OR15*100 -> #REF! | AGU16: 0.942 | AGV16: =AGU16*AGV15 -> 1884 | AGW16: Refinery | AIT16: Olein IV 56 | AIU16: 9594130 | AIV16: =S26 -> 13830654 | AIW16: =AIU16-AIV16 -> -4236524
C17: - DOBI | D17: 2,20 Min | E17: % | F17: ='[24]Januari 24'!AL16 -> 2.2105556 | G17: ='[24]Februari 24'!AL16 -> 2.2127273 | H17: ='[24]Maret 24'!AL16 -> 2.21 | I17: ='[25]April - 24'!$AK$17 -> 0 | J17: ='[26]Mei - 24'!$AL$17 -> 0 | K17: ='[27]Juni - 24'!$AL$17 -> 2.21 | L17: ='[29]Juli - 2024'!$AL$14 -> 2.2135714 | M17: ='Agustus - 2024'!AN14 -> 2.2129286 | N17: 0 | O17: 0 | P17: ='[24]November 24'!AL16 -> #DIV/0! | Q17: ='[24]Desember 24'!AL16 -> #DIV/0! | S17: =AVERAGE(F17:O17) -> 1.3269783 | T17: =AVERAGE(G17:R17) -> #DIV/0! | U17: =AVERAGE(H17:S17) -> #DIV/0! | OO17: =SUM(OO15:OO16) -> 74746.909 | OP17: =SUM(OP15:OP16) -> 18951.156 | OR17: =#REF!/1000 -> #REF! | OS17: =OR17/OR15*100 -> #REF! | AGU17: 0.05 | AGV17: =AGU17*AGV15 -> 100 | AIT17: Stearin | AIU17: 2161151 | AIV17: =S27 -> 2982810 | AIW17: =AIU17-AIV17 -> -821659
C18: Product | S18: Product | T18: Product | U18: Product | OO18: =OO17/OO11*100 -> 277.39408 | OP18: =OP17/OP11*100 -> 109.01974 | AEG18: Product OIP | AEQ18: Juni | AER18: Sisa Product OIP
C19: RbdPO | D19: =D51%*D11 -> 660718800 | E19: Kg | F19: ='[24]Januari 24'!AL18 -> 11255730 | G19: ='[24]Februari 24'!AL18 -> 11075536 | H19: ='[24]Maret 24'!AL18 -> 2943785 | I19: ='[25]April - 24'!$AK$19 -> 0 | J19: ='[26]Mei - 24'!$AL$19 -> 0 | K19: ='[27]Juni - 24'!$AL$19 -> 8432668 | L19: ='[28]Juli - 2024 ( Revisi )'!$AL$16 -> 14396709 | M19: ='Agustus - 2024'!AN16 -> 22151806 | N19: ='[24]September 24'!AL18 -> 0 | O19: ='[24]Oktober 24'!AL18 -> 0 | P19: ='[24]November 24'!AL18 -> 0 | Q19: ='[24]Desember 24'!AL18 -> 0 | S19: =SUM(F19:Q19) -> 70256234 | T19: 399336000 | U19: =S19/T19*100 -> 17.593263 | AX19: =AX20/D19 -> 0.091422859 | DE19: Tahun 2021 | AEE19: 136360 | AEF19: 109340 | AEG19: =SUM(AEE19:AEF19) -> 245700 | AEQ19: 34157.88 | AER19: =AEG19-AEQ19 -> 211542.12 | AGV19: =AGV16 -> 1884
C20: PFAD | D20: =D52%*D11 -> 35070000 | E20: Kg | F20: ='[24]Januari 24'!AL19 -> 568791 | G20: ='[24]Februari 24'!AL19 -> 594383 | H20: ='[24]Maret 24'!AL19 -> 137988 | I20: ='[25]April - 24'!$AK$20 -> 0 | J20: ='[26]Mei - 24'!$AL$20 -> 0 | K20: ='[27]Juni - 24'!$AL$20 -> 432588 | L20: ='[28]Juli - 2024 ( Revisi )'!$AL$17 -> 713632 | M20: ='Agustus - 2024'!AN17 -> 947460 | N20: ='[24]September 24'!AL19 -> 0 | O20: ='[24]Oktober 24'!AL19 -> 0 | P20: ='[24]November 24'!AL19 -> 0 | Q20: ='[24]Desember 24'!AL19 -> 0 | S20: =SUM(F20:Q20) -> 3394842 | T20: 19024000 | U20: =S20/T20*100 -> 17.845048 | AX20: =S25+S29+S34+S43+S38 -> 60404802 | DE20: Items | DG20: Agustus | DH20: Oktober | OO20: =OO11-OO17 -> -47800.801 | OP20: =OP11-OP17 -> -1567.9225 | OR20: Olein IV 58 | OS20: 0 | PE20: 564.70507 | PF20: =OS20/PE20*100 -> 0 | AEE20: 13800 | AEF20: 2800 | AEG20: =SUM(AEE20:AEF20) -> 16600 | AEQ20: 1469.85 | AER20: =AEG20-AEQ20 -> 15130.15 | AGU20: 0.75 | AGV20: =AGU20*AGV19 -> 1413
C21: Fractionation
C22: Total Filling Crystalizer ( Feed ) | D22: =399289.3*1000 -> 399289300 | E22: Kg | F22: =F23 -> 6744590 | G22: =G23 -> 7673369 | H22: =H23 -> 1794600 | I22: =I23 -> 0 | J22: =J23 -> 0 | K22: =K23 -> 7764784 | L22: =L23 -> 11686063 | M22: ='Agustus - 2024'!AN21 -> 24452230 | S22: =SUM(F22:M22) -> 60115636
C23: Total Proses RBDPO | E23: Kg | F23: =SUM(F25,F29,F34,F38,F43) -> 6744590 | G23: =SUM(G25,G29,G34,G38,G43) -> 7673369 | H23: =SUM(H25,H29,H34,H38,H43) -> 1794600 | I23: =SUM(I25,I29,I34,I38,I43) -> 0 | J23: =SUM(J25,J29,J34,J38,J43) -> 0 | K23: =SUM(K25,K29,K34,K38,K43) -> 7764784 | L23: =SUM(L25,L29,L34,L38,L43) -> 11686063 | M23: =SUM(M25,M29,M34,M38,M43) -> 24060756 | S23: =SUM(F23:M23) -> 59724162
C24: Fractionation OLEIN IV 56 | S24: Olein IV 56 | T24: Olein IV 56 | U24: Olein IV 56 | DG24: 24 | DH24: 2 | DI24: 3 | OR24: Olein IV 60 | OS24: =80.53776+PF34 -> 120.78492 | PE24: 4695.7554 | PF24: =OS24/PE24*100 -> 2.5722149 | AGU24: 0.25 | AGV24: =AGU24*AGV19 -> 471
C25: RBDPO Consume | D25: =SUM(D26:D27) -> 0 | E25: Kg | F25: =F26+F27 -> 2379082 | G25: ='[24]Februari 24'!AL21 -> 50570 | H25: ='[24]Maret 24'!AL21 -> 0 | I25: ='[24]April 24'!AL21 -> 0 | J25: ='[24]Mei 24'!AL21 -> 0 | K25: =K26+K27 -> 0 | L25: ='[28]Juli - 2024 ( Revisi )'!$AL$19 -> 0 | M25: ='Agustus - 2024'!AN25 -> 14223412 | N25: =N26+N27 -> 0 | O25: =O26+O27 -> 0 | P25: =P26+P27 -> 0 | Q25: =Q26+Q27 -> 0 | S25: =S26+S27 -> 16813464 | T25: =T26+T27 -> 87311000 | U25: =S25/T25*100 -> 19.256983 | DE25: CPO Olah | DF25: Kg | DG25: 2000530 | DH25: 2005167 | DI25: 2025879 | AEE25: =95.28%*AEE11 -> 34157.88 | AEG25: =AEE19-AEQ19 -> 102202.12 | AIQ25: CPO Feed - Sounding
C26: OLEIN IV 56 | E26: Kg | F26: ='[24]Januari 24'!AL22 -> 1982807 | G26: ='[24]Februari 24'!AL22 -> 42320 | H26: ='[24]Maret 24'!AL22 -> 0 | I26: ='[24]April 24'!AL22 -> 0 | J26: ='[24]Mei 24'!AL22 -> 0 | K26: ='[24]Juny 24'!AL22 -> 0 | L26: ='[28]Juli - 2024 ( Revisi )'!$AL$20 -> 135300 | M26: ='Agustus - 2024'!AN26 -> 11670227 | N26: ='[24]September 24'!AL22 -> 0 | O26: ='[24]Oktober 24'!AL22 -> 0 | P26: ='[24]November 24'!AL22 -> 0 | Q26: ='[24]Desember 24'!AL22 -> 0 | S26: =SUM(F26:Q26) -> 13830654 | T26: 71627000 | U26: =S26/T26*100 -> 19.309274 | DE26: HP Boiler | DF26: mmbtu | DG26: 255.53619 | DH26: 255.09239 | DI26: 260.82455 | OO26: =#REF!/1000 -> #REF! | OR26: INL 900 ml | OS26: 0 | PE26: 9.75348 | PF26: =(OS26*PE26)/1000 -> 0 | AEE26: =4.1%*AEE11 -> 1469.85 | AEG26: =AEE20-AEQ20 -> 12330.15
C27: STEARIN | E27: Kg | F27: ='[24]Januari 24'!AL23 -> 396275 | G27: ='[24]Februari 24'!AL23 -> 8250 | H27: ='[24]Maret 24'!AL23 -> 0 | I27: ='[24]April 24'!AL23 -> 0 | J27: ='[24]Mei 24'!AL23 -> 0 | K27: ='[24]Juny 24'!AL23 -> 0 | L27: ='[28]Juli - 2024 ( Revisi )'!$AL$21 -> 25100 | M27: ='Agustus - 2024'!AN27 -> 2553185 | N27: ='[24]September 24'!AL23 -> 0 | O27: ='[24]Oktober 24'!AL23 -> 0 | P27: ='[24]November 24'!AL23 -> 0 | Q27: ='[24]Desember 24'!AL23 -> 0 | S27: =SUM(F27:Q27) -> 2982810 | T27: 15684000 | U27: =S27/T27*100 -> 19.018171 | DE27: Steam Ref | DF27: Kg | DG27: 146000 | DH27: 151100 | DI27: 152900 | OO27: 1796 | OR27: Salvaco 1L | OS27: 1262 | PE27: 10.86 | PF27: =(OS27*PE27)/1000 -> 13.70532 | AIQ27: Report Prod
C28: Fractionation OLEIN IV 57 ( Bulk ) | S28: Olein IV 57 ( Bulk ) | T28: Olein IV 57 ( Bulk ) | U28: Olein IV 57 ( Bulk )
C29: RBDPO Consume | E29: Kg | F29: =F30+F31 -> 2827867 | G29: ='[30]Februari - 24'!$AL$34 -> 7224129 | H29: ='[24]Maret 24'!AL25 -> 0 | I29: ='[25]April - 24'!$AK$26 -> 0 | J29: ='[24]Mei 24'!AL25 -> 0 | K29: =K30+K31 -> 0 | L29: =L30+L31 -> 0 | M29: =M30+M31 -> 0 | N29: =N30+N31 -> 0 | O29: =O30+O31 -> 0 | P29: =P30+P31 -> 0 | Q29: =Q30+Q31 -> 0 | S29: =S30+S31 -> 10051996 | T29: =T30+T31 -> 5121000 | U29: =S29/T29*100 -> 196.28971 | AX29: =S29+S34 -> 10253377
C30: OLEIN IV 57 | E30: Kg | F30: ='[24]Januari 24'!AL26 -> 2230587 | G30: ='[30]Februari - 24'!$AL$35 -> 5178274 | H30: ='[24]Maret 24'!AL26 -> 0 | I30: ='[25]April - 24'!$AK$27 -> 0 | J30: ='[24]Mei 24'!AL26 -> 0 | K30: ='[24]Juny 24'!AL26 -> 0 | L30: ='[24]July 24'!AL26 -> 0 | M30: ='[24]Agustus 24'!AL26 -> 0 | N30: ='[24]September 24'!AL26 -> 0 | O30: ='[24]Oktober 24'!AL26 -> 0 | P30: ='[24]November 24'!AL26 -> 0 | Q30: ='[24]Desember 24'!AL26 -> 0 | S30: =SUM(F30:Q30) -> 7408861 | T30: 3934000 | U30: =S30/T30*100 -> 188.32895 | AX30: =S30+S35 -> 7560308
C31: STEARIN | E31: Kg | F31: ='[24]Januari 24'!AL27 -> 597280 | G31: ='[30]Februari - 24'!$AL$36 -> 2045855 | H31: ='[24]Maret 24'!AL27 -> 0 | I31: ='[25]April - 24'!$AK$28 -> 0 | J31: ='[24]Mei 24'!AL27 -> 0 | K31: ='[24]Juny 24'!AL27 -> 0 | L31: ='[24]July 24'!AL27 -> 0 | M31: ='[24]Agustus 24'!AL27 -> 0 | N31: ='[24]September 24'!AL27 -> 0 | O31: ='[24]Oktober 24'!AL27 -> 0 | P31: ='[24]November 24'!AL27 -> 0 | Q31: ='[24]Desember 24'!AL27 -> 0 | S31: =SUM(F31:Q31) -> 2643135 | T31: 1187000 | U31: =S31/T31*100 -> 222.67355 | AX31: =S31+S36 -> 2693069
C32: Fractionation OLEIN IV 57 ( Retail ) | S32: Olein IV 57 ( Retail ) | T32: Olein IV 57 ( Retail ) | U32: Olein IV 57 ( Retail ) | DF32: Kg/MT | DG32: =DG27/(DG25/1000) -> 72.98066 | DH32: =DH27/(DH25/1000) -> 75.35532 | DI32: =DI27/(DI25/1000) -> 75.473412 | OO32: =OO26/OO27*100 -> #REF! | OR32: Salvaco 2L | OS32: 2444 | PE32: 10.86 | PF32: =(OS32*PE32)/1000 -> 26.54184 | AIQ32: Diff
C33: CPO Consume | E33: Kg | F33: ='[24]Januari 24'!AL29 -> 0 | H33: ='[24]Maret 24'!AL29 -> 210989.34 | I33: ='[24]April 24'!AL29 -> 0 | J33: ='[24]Mei 24'!AL29 -> 0 | K33: ='[24]Juny 24'!AL29 -> 0 | L33: ='[24]July 24'!AL29 -> 0 | M33: ='[24]Agustus 24'!AL29 -> 0 | N33: ='[24]September 24'!AL29 -> 0 | O33: ='[24]Oktober 24'!AL29 -> 0 | P33: ='[24]November 24'!AL29 -> 0 | Q33: ='[24]Desember 24'!AL29 -> 0 | S33: =SUM(F33:Q33) -> 210989.34 | T33: =T34/T51% -> 32338304 | U33: =(S33/T33)*100 -> 0.65244405 | DF33: Kg/MT | DG33: =DG27/(DG20/1000) -> #VALUE! | DH33: =DI27/(DH20/1000) -> #VALUE! | DI33: =#REF!/(DI20/1000) -> #REF!
C34: RBDPO Brand Consume | D34: =SUM(D35:D36) -> 0 | E34: Kg | F34: =F35+F36 -> 0 | G34: =G35+G36 -> 0 | H34: =H35+H36 -> 201381 | I34: =I35+I36 -> 0 | J34: =J35+J36 -> 0 | K34: =K35+K36 -> 0 | L34: =L35+L36 -> 0 | M34: =M35+M36 -> 0 | N34: =N35+N36 -> 0 | O34: ='[24]Oktober 24'!AL30 -> 0 | P34: =P35+P36 -> 0 | Q34: =Q35+Q36 -> 0 | S34: =S35+S36 -> 201381 | T34: =T35+T36 -> 30647000 | U34: =(S34/T34)*100 -> 0.65709857 | PF34: =SUM(PF27:PF32) -> 40.24716
C35: OLEIN IV 57 ( Retail ) | E35: Kg | F35: ='[24]Januari 24'!AL31 -> 0 | H35: ='[24]Maret 24'!AL31 -> 151447 | I35: ='[24]April 24'!AL31 -> 0 | J35: ='[24]Mei 24'!AL31 -> 0 | K35: ='[24]Juny 24'!AL31 -> 0 | L35: ='[24]July 24'!AL31 -> 0 | M35: ='[24]Agustus 24'!AL31 -> 0 | N35: ='[24]September 24'!AL31 -> 0 | O35: ='[24]Oktober 24'!AL31 -> 0 | P35: ='[24]November 24'!AL31 -> 0 | Q35: ='[24]Desember 24'!AL31 -> 0 | S35: =SUM(F35:Q35) -> 151447 | T35: 23002000 | U35: =S35/T35*100 -> 0.65840796
C36: STEARIN | E36: Kg | F36: ='[24]Januari 24'!AL32 -> 0 | H36: ='[24]Maret 24'!AL32 -> 49934 | I36: ='[24]April 24'!AL32 -> 0 | J36: ='[24]Mei 24'!AL32 -> 0 | K36: ='[24]Juny 24'!AL32 -> 0 | L36: ='[24]July 24'!AL32 -> 0 | M36: ='[24]Agustus 24'!AL32 -> 0 | N36: ='[24]September 24'!AL32 -> 0 | O36: ='[24]Oktober 24'!AL32 -> 0 | P36: ='[24]November 24'!AL32 -> 0 | Q36: ='[24]Desember 24'!AL32 -> 0 | S36: =SUM(F36:Q36) -> 49934 | T36: 7645000 | U36: =S36/T36*100 -> 0.65315893
C37: Fractionation OLEIN IV 58 ( BULK ) | S37: Olein IV 58 | T37: Olein IV 58 | U37: Olein IV 58
C38: RBDPO Consume | E38: Kg | F38: =F39+F40 -> 0 | G38: 0 | H38: =H39+H40 -> 1593219 | I38: ='[25]April - 24'!$AK$35 -> 0 | J38: ='[26]Mei - 24'!$AL$35 -> 0 | K38: ='[27]Juni - 24'!$AL$35 -> 7764784 | L38: ='[28]Juli - 2024 ( Revisi )'!$AL$32 -> 11686063 | M38: ='Agustus - 2024'!AN38 -> 9837344 | N38: =N39+N40 -> 0 | O38: =O39+O40 -> 0 | P38: =P39+P40 -> 0 | Q38: =Q39+Q40 -> 0 | S38: =S39+S40 -> 31401650 | T38: =T39+T40 -> 249961000 | U38: =S38/T38*100 -> 12.56262
C39: OLEIN IV 58 ( Bulk ) | E39: Kg | F39: ='[24]Januari 24'!AL31 -> 0 | G39: 0 | H39: ='[24]Maret 24'!AL35 -> 1075806 | I39: ='[25]April - 24'!$AK$36 -> 0 | J39: ='[26]Mei - 24'!$AL$36 -> 0 | K39: ='[27]Juni - 24'!$AL$36 -> 5498655 | L39: ='[28]Juli - 2024 ( Revisi )'!$AL$33 -> 8627479 | M39: ='Agustus - 2024'!AN39 -> 6991936 | N39: ='[24]September 24'!AL35 -> 0 | O39: ='[24]Oktober 24'!AL35 -> 0 | P39: ='[24]November 24'!AL35 -> 0 | Q39: ='[24]Desember 24'!AL35 -> 0 | S39: =SUM(F39:Q39) -> 22193876 | T39: 175000000 | U39: =S39/T39*100 -> 12.682215
C40: STEARIN | E40: Kg | F40: ='[24]Januari 24'!AL32 -> 0 | G40: 0 | H40: ='[24]Maret 24'!AL36 -> 517413 | I40: ='[25]April - 24'!$AK$37 -> 0 | J40: ='[26]Mei - 24'!$AL$37 -> 0 | K40: ='[27]Juni - 24'!$AL$37 -> 2266129 | L40: ='[28]Juli - 2024 ( Revisi )'!$AL$34 -> 3578824 | M40: ='Agustus - 2024'!AN40 -> 2845408 | N40: ='[24]September 24'!AL36 -> 0 | O40: ='[24]Oktober 24'!AL36 -> 0 | P40: ='[24]November 24'!AL36 -> 0 | Q40: ='[24]Desember 24'!AL36 -> 0 | S40: =SUM(F40:Q40) -> 9207774 | T40: 74961000 | U40: =S40/T40*100 -> 12.283419
C41: Fractionation OLEIN IV 60 | S41: Olein IV 60 | T41: Olein IV 60 | U41: Olein IV 60
C42: CPO Consume | E42: Kg | F42: ='[24]Januari 24'!AL38 -> 1622056.5 | G42: ='[30]Februari - 24'!$AL$38 -> 421426.65 | H42: ='[24]Maret 24'!AL38 -> 0 | I42: 0 | J42: 0 | K42: 0 | L42: 0 | M42: 0 | N42: 0 | O42: 0 | S42: =SUM(F42:Q42) -> 2043483.1 | T42: =T43/T51% -> 25913273 | U42: =S42/T42*100 -> 7.885855
C43: RBDPO Brand Consume | D43: =SUM(D45:D46) -> 0 | E43: Kg | F43: ='[24]Januari 24'!AL39 -> 1537641 | G43: ='[30]Februari - 24'!$AL$39 -> 398670 | H43: =H45+H46 -> 0 | I43: ='[24]April 24'!AL39 -> 0 | J43: ='[24]Mei 24'!AL39 -> 0 | K43: =K45+K46 -> 0 | L43: ='[24]July 24'!AL39 -> 0 | M43: =M45+M46 -> 0 | N43: =N45+N46 -> 0 | O43: ='[24]Oktober 24'!AL39 -> 0 | P43: ='[24]November 24'!AL39 -> 0 | Q43: =Q45+Q46 -> 0 | S43: =S45+S46 -> 1936311 | T43: =T45+T46 -> 24558000 | U43: =S43/T43*100 -> 7.8846445 | DG43: 2136
C44: OLEIN IV 60 Bulk | E44: Kg | F44: ='[24]Januari 24'!AL40 -> 0 | H44: ='[24]Maret 24'!AL40 -> 0 | I44: ='[24]April 24'!AL40 -> 0 | J44: ='[24]Mei 24'!AL40 -> 0 | K44: ='[24]Juny 24'!AL40 -> 0 | L44: ='[24]July 24'!AL40 -> 0 | M44: ='[24]Agustus 24'!AL40 -> 0 | N44: ='[24]September 24'!AL40 -> 0 | O44: ='[24]Oktober 24'!AL40 -> 0 | Q44: ='[24]Desember 24'!AL40 -> 0 | S44: =SUM(F44:Q44) -> 0 | T44: =SUM(F44:Q44) -> 0 | U44: =SUM(H44:S44) -> 0
C45: OLEIN IV 60 Salvaco | E45: Kg | F45: ='[24]Januari 24'!AL41 -> 923976 | G45: ='[30]Februari - 24'!$AL$41 -> 248300 | H45: ='[24]Maret 24'!AL41 -> 0 | I45: ='[24]April 24'!AL41 -> 0 | J45: ='[24]Mei 24'!AL41 -> 0 | K45: ='[24]Juny 24'!AL41 -> 0 | L45: ='[24]July 24'!AL41 -> 0 | M45: ='[24]Agustus 24'!AL41 -> 0 | N45: ='[24]September 24'!AL41 -> 0 | O45: ='[24]Oktober 24'!AL41 -> 0 | P45: ='[24]November 24'!AL41 -> 0 | Q45: ='[24]Desember 24'!AL41 -> 0 | S45: =SUM(F45:Q45) -> 1172276 | T45: 14736000 | U45: =S45/T45*100 -> 7.9551846 | DG45: 1796
C46: SOFT STEARIN | E46: Kg | F46: ='[24]Januari 24'!AL42 -> 613665 | G46: ='[30]Februari - 24'!$AL$42 -> 150370 | H46: ='[24]Maret 24'!AL42 -> 0 | I46: ='[24]April 24'!AL42 -> 0 | J46: ='[24]Mei 24'!AL42 -> 0 | K46: ='[24]Juny 24'!AL42 -> 0 | L46: ='[24]July 24'!AL42 -> 0 | M46: ='[24]Agustus 24'!AL42 -> 0 | N46: ='[24]September 24'!AL42 -> 0 | O46: ='[24]Oktober 24'!AL42 -> 0 | P46: ='[24]November 24'!AL42 -> 0 | Q46: ='[24]Desember 24'!AL42 -> 0 | S46: =SUM(F46:Q46) -> 764035 | T46: 9822000 | U46: =S46/T46*100 -> 7.7788129 | DG46: =DG43/DG45*100 -> 118.93096
C47: Ratio Run RBDPO | F47: ='[24]Januari 24'!AL43 -> 17.42364 | G47: ='[30]Februari - 24'!$AL$43 -> 13.049053 | H47: ='[24]Maret 24'!AL43 -> 2.8945161 | I47: ='[24]April 24'!AL43 -> 0 | J47: ='[26]Mei - 24'!$AL$44 -> 0 | K47: ='[27]Juni - 24'!$AL$44 -> 12.523845 | L47: =(L38+L34+L29+L25)/(60000000) -> 0.19476772 | M47: =(M38+M34+M29+M25)/(60000000) -> 0.4010126 | N47: =(N38+N34+N29+N25)/(60000000) -> 0 | O47: =(O38+O34+O29+O25)/(60000000) -> 0 | P47: =(P38+P34+P29+P25)/(60000000) -> 0 | Q47: =(Q38+Q34+Q29+Q25)/(60000000) -> 0 | S47: =+AVERAGE(F47:O47) -> 4.6486835
C48: Utilitas RBDPO | F48: =(F43+F38+F34+F30+F26)/F49*100 -> 53.914268 | G48: =(G43+G38+G34+G30+G26)/G49*100 -> 13.116557 | H48: =(H43+H38+H34+H30+H26)/H49*100 -> 4.8445092 | J48: =(J43+J38+J34+J30+J26)/J49*100 -> 0 | K48: =(K43+K38+K34+K30+K26)/K49*100 -> 22.670784 | L48: =(L43+L38+L34+L30+L26)/L49*100 -> 34.514749 | M48: =(M43+M38+M34+M30+M25)/M49*100 -> 70.250017 | N48: =(N43+N38+N34+N30+N26)/N49*100 -> 0 | O48: =(O43+O38+O34+O30+O26)/O49*100 -> 0 | P48: =(P43+P38+P34+P30+P26)/P49*100 -> 0 | Q48: =(Q43+Q38+Q34+Q30+Q26)/Q49*100 -> 0 | S48: =+AVERAGE(F48:O48) -> 22.145654
C49: Budget RBDPO | F49: 10667000 | G49: 42841000 | H49: 37044000 | J49: ='[26]Mei - 24'!$D$19 -> 34250178 | K49: ='[27]Juni - 24'!$D$19 -> 34250178 | L49: ='[27]Juni - 24'!$D$19 -> 34250178 | M49: ='[27]Juni - 24'!$D$19 -> 34250178 | N49: ='[27]Juni - 24'!$D$19 -> 34250178 | O49: ='[27]Juni - 24'!$D$19 -> 34250178 | P49: ='[27]Juni - 24'!$D$19 -> 34250178 | Q49: ='[27]Juni - 24'!$D$19 -> 34250178 | S49: =SUM(F49:O49) -> 296053068
C50: YIELD | S50: Yield | T50: Yield | U50: Yield | OP50: 678
C51: RBDPO | D51: 94.2 | E51: % | F51: =(F19/(F11))*100 -> 94.537593 | G51: =(G19/(G11))*100 -> 94.281618 | H51: =(H19/(H11))*100 -> 94.87071 | I51: =(I19/(I11))*100 -> #DIV/0! | J51: =(J19/(J11))*100 -> #DIV/0! | K51: =(K19/(K11))*100 -> 94.544904 | L51: =(L19/(L11))*100 -> 90.001937 | M51: =(M19/(M11))*100 -> 95.997637 | ... Q51: =(Q19/(Q11))*100 -> #DIV/0! | S51: =(S19/(S11))*100 -> 93.99216 | T51: =(T19/(T11))*100 -> 94.769967 | OP51: 420 | OR51: =OP51/OP50*100 -> 61.946903
C52: PFAD | D52: 5 | E52: % | F52: =(F20/(F11))*100 -> 4.7773118 | G52: =(G20/(G11))*100 -> 5.0597453 | H52: =(H20/(H11))*100 -> 4.4470026 | I52: =(I20/(I11))*100 -> #DIV/0! | J52: =(J20/(J11))*100 -> #DIV/0! | K52: =(K20/(K11))*100 -> 4.8500654 | L52: =(L20/(L11))*100 -> 4.4613156 | M52: =(M20/(M11))*100 -> 4.105937 | ... Q52: =(Q20/(Q11))*100 -> #DIV/0! | S52: =(S20/(S11))*100 -> 4.5417825 | T52: =(T20/(T11))*100 -> 4.5147541 | OP52: =OP50-OP51 -> 258 | OR52: =OP52/OP50*100 -> 38.053097
C53: Olein IV 56 | D53: 82 | E53: % | F53: =(F26/F25)*100 -> 83.343365 | G53: =(G26/G25)*100 -> 83.68598 | H53: =(H26/H25)*100 -> #DIV/0! | I53: =(I26/I25)*100 -> #DIV/0! | J53: =(J26/J25)*100 -> #DIV/0! | K53: =(K26/K25)*100 -> #DIV/0! | L53: =(L26/L25)*100 -> #DIV/0! | M53: =M26/(M26+M27)*100 -> 82.04942 | N53: =(N26/N25)*100 -> #DIV/0! | O53: =(O26/O25)*100 -> #DIV/0! | P53: =(P26/P25)*100 -> #DIV/0! | Q53: =(Q26/Q25)*100 -> #DIV/0! | S53: =(S26/S25)*100 -> 82.259396 | T53: =(T26/T25)*100 -> 82.036628
C54: Stearin | D54: 18 | E54: % | F54: =(F27/F25)*100 -> 16.656635 | G54: =(G27/G25)*100 -> 16.31402 | H54: =(H27/H25)*100 -> #DIV/0! | I54: =(I27/I25)*100 -> #DIV/0! | J54: =(J27/J25)*100 -> #DIV/0! | K54: =(K27/K25)*100 -> #DIV/0! | L54: =(L27/L25)*100 -> #DIV/0! | M54: =M27/(M27+M26)*100 -> 17.95058 | N54: =(N27/N25)*100 -> #DIV/0! | O54: =(O27/O25)*100 -> #DIV/0! | P54: =(P27/P25)*100 -> #DIV/0! | Q54: =(Q27/Q25)*100 -> #DIV/0! | S54: =(S27/S25)*100 -> 17.740604 | T54: =(T27/T25)*100 -> 17.963372
C55: Olein IV 57 ( Bulk ) | D55: 75 | E55: % | F55: =(F30/F29)*100 -> 78.87878 | G55: =(G30/G29)*100 -> 71.680254 | H55: =(H30/H29)*100 -> #DIV/0! | I55: =(I30/I29)*100 -> #DIV/0! | J55: =(J30/J29)*100 -> #DIV/0! | K55: =(K30/K29)*100 -> #DIV/0! | L55: =(L30/L29)*100 -> #DIV/0! | M55: =(M30/M29)*100 -> #DIV/0! | ... Q55: =(Q30/Q29)*100 -> #DIV/0! | S55: =(S30/S29)*100 -> 73.705372 | T55: 75
C56: Stearin | D56: 25 | E56: % | F56: =(F31/F29)*100 -> 21.12122 | G56: =(G31/G29)*100 -> 28.319746 | H56: =(H31/H29)*100 -> #DIV/0! | I56: =(I31/I29)*100 -> #DIV/0! | J56: =(J31/J29)*100 -> #DIV/0! | K56: =(K31/K29)*100 -> #DIV/0! | L56: =(L31/L29)*100 -> #DIV/0! | M56: =(M31/M29)*100 -> #DIV/0! | ... Q56: =(Q31/Q29)*100 -> #DIV/0! | S56: =(S31/S29)*100 -> 26.294628 | T56: 25
C57: Olein IV 57 ( Retail ) | D57: 75 | E57: % | F57: =F35/F34*100 -> #DIV/0! | G57: =G35/G34*100 -> #DIV/0! | H57: =H35/H34*100 -> 75.204215 | I57: =I35/I34*100 -> #DIV/0! | J57: =J35/J34*100 -> #DIV/0! | K57: =K35/K34*100 -> #DIV/0! | L57: =L35/L34*100 -> #DIV/0! | M57: =M35/M34*100 -> #DIV/0! | ... Q57: =Q35/Q34*100 -> #DIV/0! | S57: =(S35/S34)*100 -> 75.204215 | T57: 75
C58: Stearin | D58: 25 | E58: % | F58: =F36/F34*100 -> #DIV/0! | G58: =G36/G34*100 -> #DIV/0! | H58: =H36/H34*100 -> 24.795785 | I58: =I36/I34*100 -> #DIV/0! | J58: =J36/J34*100 -> #DIV/0! | K58: =K36/K34*100 -> #DIV/0! | L58: =L36/L34*100 -> #DIV/0! | M58: =M36/M34*100 -> #DIV/0! | ... Q58: =Q36/Q34*100 -> #DIV/0! | S58: =(S36/S34)*100 -> 24.795785 | T58: 25 | FN58: 95.03
C59: Olein IV 58 ( Bulk ) | D59: 70 | E59: % | F59: =(F39/F38)*100 -> #DIV/0! | G59: =(G39/G38)*100 -> #DIV/0! | H59: =(H39/H38)*100 -> 67.52405 | I59: =(I39/I38)*100 -> #DIV/0! | J59: =(J39/J38)*100 -> #DIV/0! | K59: =(K39/K38)*100 -> 70.815299 | L59: ='[28]Juli - 2024 ( Revisi )'!$AL$51 -> 70.680525 | M59: ='Agustus - 2024'!AN57 -> 71.075445 | N59: =(N39/N38)*100 -> #DIV/0! | O59: =(O39/O38)*100 -> #DIV/0! | Q59: =(Q39/Q38)*100 -> #DIV/0! | S59: =(S39/S38)*100 -> 70.67742 | T59: 70
C60: Stearin | D60: 30 | E60: % | F60: =(F40/F38)*100 -> #DIV/0! | G60: =(G40/G38)*100 -> #DIV/0! | H60: =(H40/H38)*100 -> 32.47595 | I60: =(I40/I38)*100 -> #DIV/0! | J60: =(J40/J38)*100 -> #DIV/0! | K60: =(K40/K38)*100 -> 29.184701 | L60: ='[28]Juli - 2024 ( Revisi )'!$AL$52 -> 29.319475 | M60: ='Agustus - 2024'!AN58 -> 28.924555 | N60: =(N40/N38)*100 -> #DIV/0! | O60: =(O40/O38)*100 -> #DIV/0! | Q60: =(Q40/Q38)*100 -> #DIV/0! | S60: =(S40/S38)*100 -> 29.32258 | T60: 30
C61: Olein IV 60 | D61: 60 | E61: % | F61: =F45/F43*100 -> 60.090489 | G61: =G45/G43*100 -> 62.282088 | H61: =H45/H43*100 -> #DIV/0! | I61: =I45/I43*100 -> #DIV/0! | J61: =J45/J43*100 -> #DIV/0! | K61: =K45/K43*100 -> #DIV/0! | L61: =L45/L43*100 -> #DIV/0! | M61: =M45/M43*100 -> #DIV/0! | ... Q61: =Q45/Q43*100 -> #DIV/0! | S61: =(S45/S43)*100 -> 60.541721 | T61: =T45/T43*100 -> 60.004886 | FN61: 4.23 | OR61: =OR62/94.2% -> 1307.8556 | OS61: MT CPO
C62: Soft Stearin | D62: 40 | E62: % | F62: =F46/F43*100 -> 39.909511 | G62: =G46/G43*100 -> 37.717912 | H62: =H46/H43*100 -> #DIV/0! | I62: =I46/I43*100 -> #DIV/0! | J62: =J46/J43*100 -> #DIV/0! | K62: =K46/K43*100 -> #DIV/0! | L62: =L46/L43*100 -> #DIV/0! | M62: =M46/M43*100 -> #DIV/0! | ... Q62: =Q46/Q43*100 -> #DIV/0! | S62: =(S46/S43)*100 -> 39.458279 | T62: =T46/T43*100 -> 39.995114 | FN62: =100-FN58-FN61 -> 0.74 | OR62: =22*56 -> 1232 | OS62: MT RBDPO Brand
B63: 3 | C63: CHEMICAL CONSUMABLE | S63: Chemical | T63: Chemical | U63: Chemical | OR63: =16.5*OR61 -> 21579.618
C64: Bleaching Earth (BE) to Poram Spec | D64: 8 | E64: Kg | F64: ='[24]Januari 24'!AL58 -> 128586 | G64: ='[30]Februari - 24'!$AL$58 -> 148066 | H64: ='[24]Maret 24'!AL58 -> 29654 | I64: ='[25]April - 24'!$AK$59 -> 0 | J64: ='[26]Mei - 24'!$AL$59 -> 0 | K64: ='[27]Juni - 24'!$AL$59 -> 88126 | L64: ='[28]Juli - 2024 ( Revisi )'!$AL$56 -> 162476 | M64: ='Agustus - 2024'!AN62 -> 256409 | N64: ='[24]September 24'!AL58 -> 0 | O64: ='[24]Oktober 24'!AL58 -> 0 | P64: ='[24]November 24'!AL58 -> 0 | Q64: ='[24]Desember 24'!AL58 -> 0 | S64: =SUM(F64:Q64) -> 813317 | T64: 2767753 | U64: =S64/T64*100 -> 29.385462
E65: % | F65: ='[24]Januari 24'!AL59 -> 1.2503461 | G65: =G64/(G12)*100 -> 1.3601743 | H65: =H64/(H12)*100 -> 1.0253964 | I65: =I64/(I12)*100 -> #DIV/0! | J65: =J64/(J12)*100 -> #DIV/0! | K65: =K64/(K12)*100 -> 0.98804604 | L65: =L64/(L12)*100 -> 1.015729 | M65: =M64/(M11)*100 -> 1.1111806 | N65: =N64/(N12)*100 -> #DIV/0! | O65: =O64/(O12)*100 -> #DIV/0! | P65: =P64/(P12)*100 -> #DIV/0! | Q65: =Q64/(Q12)*100 -> #DIV/0! | S65: =S64/(S11)*100 -> 1.0880945 | T65: 0.8 | U65: 0 | AX65: =S65*10 -> 10.880945 | FN65: =#REF!*10 -> #REF! | OR65: =OR61+(S42/1000) -> 3351.3388 | OS65: Total CPO Brand
C66: Bleaching Earth (BE) to Branded Spec | D66: 16 | E66: Kg | F66: ='[24]Januari 24'!AL60 -> 25923 | G66: ='[30]Februari - 24'!$AL$60 -> 15015 | H66: ='[24]Maret 24'!AL60 -> 2901 | I66: ='[24]April 24'!AL60 -> 0 | J66: ='[24]Mei 24'!AL60 -> 0 | K66: ='[24]Juny 24'!AL60 -> 0 | L66: ='[28]Juli - 2024 ( Revisi )'!$AL$58 -> 0 | M66: ='Agustus - 2024'!AN64 -> 2930 | N66: ='[24]September 24'!AL60 -> 0 | O66: ='[24]Oktober 24'!AL60 -> 0 | P66: ='[24]November 24'!AL60 -> 0 | Q66: ='[24]Desember 24'!AL60 -> 0 | S66: =SUM(F66:Q66) -> 46769 | T66: 1357284 | U66: =S66/T66*100 -> 3.4457785 | OR66: =OR63+S66 -> 68348.618 | OS66: Total BE Brand
E67: % | F67: ='[24]Januari 24'!AL61 -> 1.5981564 | G67: =G66/(G13)*100 -> 1.74293 | H67: =H66/(H13)*100 -> 1.374951 | I67: =I66/(I13)*100 -> #DIV/0! | J67: =J66/(J13)*100 -> #DIV/0! | K67: =K66/(K13)*100 -> #DIV/0! | L67: =L66/(L13)*100 -> #DIV/0! | M67: =M66/(M13)*100 -> 1.5863992 | N67: =N66/(N13)*100 -> #DIV/0! | ... Q67: =Q66/(Q13)*100 -> #DIV/0! | S67: =S66/(S13)*100 -> 1.6243629 | T67: 1.8 | U67: 0 | AX67: =S67*10 -> 16.243629 | OR67: =OR66/OR65 -> 20.394422 | OS67: Kg/MT CPO
C68: Phosporic Acid (PA) | D68: 0.55 | E68: Kg | F68: ='[24]Januari 24'!AL62 -> 6664.856 | G68: ='[30]Februari - 24'!$AL$62 -> 6551.932 | H68: ='[24]Maret 24'!AL62 -> 1744.336 | I68: ='[25]April - 24'!$AK$63 -> 0 | J68: ='[26]Mei - 24'!$AL$63 -> 0 | K68: ='[27]Juni - 24'!$AL$63 -> 4040.198 | L68: ='[28]Juli - 2024 ( Revisi )'!$AL$60 -> 7823.782 | M68: ='Agustus - 2024'!AN66 -> 11739.24 | N68: ='[24]September 24'!AL62 -> 0 | O68: ='[24]Oktober 24'!AL62 -> 0 | P68: ='[24]November 24'!AL62 -> 0 | Q68: ='[24]Desember 24'!AL62 -> 0 | S68: =SUM(F68:Q68) -> 38564.344 | T68: 252824 | U68: =SUM(H68:S68) -> 63911.9 | OR68: 16 | OS68: Budget (Kg/MT)
E69: % | F69: ='[24]Januari 24'!AL63 -> 0.05597855 | G69: =G68/(G11)*100 -> 0.055773982 | H69: =H68/(H11)*100 -> 0.056215517 | I69: =I68/(I11)*100 -> #DIV/0! | J69: =J68/(J11)*100 -> #DIV/0! | K69: =K68/(K11)*100 -> 0.045297661 | L69: =L68/(L11)*100 -> 0.048910868 | M69: ='Agustus - 2024'!AN67 -> 0.050873473 | N69: =N68/(N11)*100 -> #DIV/0! | O69: =O68/(O11)*100 -> #DIV/0! | P69: =P68/(P11)*100 -> #DIV/0! | Q69: =Q68/(Q11)*100 -> #DIV/0! | S69: =S68/(S11+71450)*100 -> 0.051543959 | T69: 0.06 | U69: =U68/(U11+71450)*100 -> 89.449603 | AX69: =S69*10 -> 0.51543959 | FN69: =P69*10 -> #DIV/0! | OR69: =OR67-OR68 -> 4.3944223 | OS69: Over (Kg/MT)
B70: 4 | C70: Oil Losses | D70: 0.8 | E70: % | F70: =((SUM(F19:F20))-(SUM(F11)))/(SUM(F11))*100 -> -0.68509483 | G70: =((SUM(G19:G20))-(SUM(G11)))/(SUM(G11))*100 -> -0.65863696 | H70: =((SUM(H19:H20))-(SUM(H11)))/(SUM(H11))*100 -> -0.68228753 | I70: =((SUM(I19:I20))-(SUM(I11)))/(SUM(I11))*100 -> #DIV/0! | J70: =((SUM(J19:J20))-(SUM(J11)))/(SUM(J11))*100 -> #DIV/0! | K70: =((SUM(K19:K20))-(SUM(K11)))/(SUM(K11))*100 -> -0.60503048 | L70: =((SUM(L19:L20))-(SUM(L11)))/(SUM(L11))*100 -> -5.536747 | M70: =((SUM(M19:M20))-(SUM(M11)))/(SUM(M11))*100 -> 0.10357452 | ... Q70: =((SUM(Q19:Q20))-(SUM(Q11)))/(SUM(Q11))*100 -> #DIV/0! | S70: =((SUM(S19:S20))-(SUM(S11)))/(SUM(S11))*100 -> -1.4660577 | T70: =((SUM(T19:T20))-(SUM(T11)))/(SUM(T11))*100 -> -0.71527906 | U70: =S70/T70*100 -> 204.96304
C71: % Oil Content | D71: 22 | E71: % | F71: ='[31]Januari - 24'!$AL$65 -> 21.923529 | G71: ='[30]Februari - 24'!$AL$65 -> 21.991 | H71: ='[24]Maret 24'!AL65 -> 21.958 | I71: ='[25]April - 24'!$AK$66 -> 0 | J71: ='[26]Mei - 24'!$AL$66 -> 0 | K71: ='[27]Juni - 24'!$AL$66 -> 21.886471 | L71: ='[28]Juli - 2024 ( Revisi )'!$AL$64 -> 21.912727 | M71: ='Agustus - 2024'!AN70 -> 21.700714 | N71: ='[24]September 24'!AK62 -> #REF! | P71: ='[24]November 24'!AL65 -> #DIV/0! | Q71: ='[24]Desember 24'!AL65 -> #DIV/0! | S71: =AVERAGE(F71:L71) -> 15.66739 | T71: 22 | U71: =AVERAGE(H71:S71) -> #REF!
C72: Spent Bleaching Earth | E72: Kg | F72: =SUM(F64,F66)+(F71%*SUM(F64,F66)) -> 188382.83 | G72: =SUM(G64,G66)+(G71%*SUM(G64,G66)) -> 198944.14 | H72: =SUM(H64,H66)+(H71%*SUM(H64,H66)) -> 39703.427 | I72: =SUM(I64,I66)+(I71%*SUM(I64,I66)) -> 0 | J72: =SUM(J64,J66)+(J71%*SUM(J64,J66)) -> 0 | K72: =SUM(K64,K66)+(K71%*SUM(K64,K66)) -> 107413.67 | L72: =SUM(L64,L66)+(L71%*SUM(L64,L66)) -> 198078.92 | M72: ='Agustus - 2024'!AN71 -> 315617.42 | N72: =SUM(N64,N66)+(N71%*SUM(N64,N66)) -> #REF! | O72: =SUM(O64,O66)+(O71%*SUM(O64,O66)) -> 0 | P72: =SUM(P64,P66)+(P71%*SUM(P64,P66)) -> #DIV/0! | Q72: =SUM(Q64,Q66)+(Q71%*SUM(Q64,Q66)) -> #DIV/0! | S72: =SUM(S64,S66)+(S71%*SUM(S64,S66)) -> 994839.02 | T72: 7811279 | U72: =SUM(U64,U66)+(U71%*SUM(U64,U66)) -> #REF! | GA72: =W72+400 -> 400
B73: 5 | C73: PACKAGING (Brand Salvaco) | S73: Packaging | T73: Packaging | U73: Packaging | FX73: 17292 | OY73: =#REF!-FX73 -> #REF!
C74: Olein IV 60 Received | E74: Kg | F74: ='[24]Januari 24'!AL68 -> 845858 | G74: ='[24]Februari 24'!AI68 -> #REF! | H74: ='[24]Maret 24'!AL68 -> 0 | I74: ='[24]April 24'!AL68 -> 0 | J74: ='[24]Mei 24'!AL68 -> 0 | K74: ='[24]Juny 24'!AL68 -> 0 | L74: ='[24]July 24'!AL68 -> 0 | M74: ='[24]Agustus 24'!AL68 -> 0 | N74: ='[24]September 24'!AL68 -> 0 | O74: ='[24]Oktober 24'!AL68 -> 0 | P74: ='[24]November 24'!AL68 -> 0 | Q74: ='[24]Desember 24'!AL68 -> 0 | S74: =SUM(F74:Q74) -> #REF! | T74: =SUM(G74:R74) -> #REF! | U74: =(S74/T74)*100 -> #REF!
C75: Olein IV 60 Consume | E75: Kg | F75: ='[24]Januari 24'!AL69 -> 399021.28 | G75: ='[24]Februari 24'!AI69 -> #REF! | H75: ='[24]Maret 24'!AL69 -> 0 | I75: ='[24]April 24'!AL69 -> 0 | J75: ='[24]Mei 24'!AL69 -> 0 | K75: ='[24]Juny 24'!AL69 -> 0 | L75: ='[24]July 24'!AL69 -> 0 | M75: ='[24]Agustus 24'!AL69 -> 0 | N75: ='[24]September 24'!AL69 -> 0 | O75: ='[24]Oktober 24'!AL69 -> 0 | P75: ='[24]November 24'!AL69 -> 0 | Q75: ='[24]Desember 24'!AL69 -> 0 | S75: =SUM(S76:S78) -> #REF! | T75: =SUM(T76:T78) -> #REF! | U75: =(S75/T75)*100 -> #REF! | AFR75: Kg | AFS75: Olein Filling to Packaging
C76: - finished product | E76: Kg | F76: =SUM(F80:F81)*10.86 -> 400256.16 | G76: =SUM(G80:G81)*10.86 -> #REF! | H76: =SUM(H80:H81)*10.86 -> 0 | I76: ='[24]April 24'!AL70 -> 0 | J76: =SUM(J80:J81)*10.86 -> 0 | K76: =SUM(K80:K81)*10.86 -> 0 | L76: =SUM(L80:L81)*10.86 -> 0 | M76: =SUM(M80:M81)*10.86 -> 0 | N76: =SUM(N80:N81)*10.86 -> 0 | O76: =SUM(O80:O81)*10.86 -> 0 | P76: =SUM(P80:P81)*10.86 -> 0 | Q76: =SUM(Q80:Q81)*10.86 -> 0 | S76: =SUM(S80:S81)*10.86 -> #REF! | T76: =SUM(T80:T81)*10.86 -> 32269046 | U76: =(S76/T76)*100 -> #REF! | FX76: =#REF!/1000 -> #REF! | OY76: 4696 | OZ76: =FX76/OY76*100 -> #REF!
C77: - sample | E77: Kg | F77: =F75-F76 -> -1234.88 | G77: =G75-G76 -> #REF! | H77: =H75-H76 -> 0 | I77: ='[24]April 24'!AL71 -> 0 | J77: =J75-J76 -> 0 | K77: =K75-K76 -> 0 | L77: =L75-L76 -> 0 | M77: =M75-M76 -> 0 | N77: =N75-N76 -> 0 | O77: =O75-O76 -> 0 | P77: =P75-P76 -> 0 | Q77: =Q75-Q76 -> 0 | S77: =SUM(F77:Q77) -> #REF! | T77: =SUM(G77:R77) -> #REF! | U77: =(S77/T77)*100 -> #REF! | FX77: =#REF!/1000 -> #REF! | OY77: 565 | OZ77: =FX77/OY77*100 -> #REF!
C78: - remelt, flushing, downgrade | E78: Kg | F78: ='[24]Januari 24'!AL72 -> 0 | G78: ='[24]Februari 24'!AI72 -> 0 | H78: ='[24]Maret 24'!AL72 -> 0 | I78: ='[24]April 24'!AL72 -> 0 | P78: 0 | Q78: 0 | S78: =SUM(F78:Q78) -> 0 | T78: =SUM(G78:R78) -> 0
C79: Carton | S79: Carton | T79: Carton | U79: Carton
C80: Salvaco 1 Liter | E80: Box | F80: ='[24]Januari 24'!AL74 -> 17197 | G80: ='[24]Februari 24'!AI74 -> #REF! | H80: ='[24]Maret 24'!AL74 -> 0 | I80: ='[24]April 24'!AL74 -> 0 | J80: ='[24]Mei 24'!AL74 -> 0 | K80: ='[24]Juny 24'!AL74 -> 0 | L80: ='[24]July 24'!AL74 -> 0 | M80: ='[24]Agustus 24'!AL74 -> 0 | N80: ='[24]September 24'!AL74 -> 0 | O80: ='[24]Oktober 24'!AL74 -> 0 | P80: ='[24]November 24'!AL74 -> 0 | Q80: ='[24]Desember 24'!AL74 -> 0 | S80: =SUM(F80:Q80) -> #REF! | T80: 1254577 | U80: =(S80/T80)*100 -> #REF!
C81: Salvaco 2 Liter | E81: Box | F81: ='[24]Januari 24'!AL75 -> 19659 | G81: ='[24]Februari 24'!AI75 -> #REF! | H81: ='[24]Maret 24'!AL75 -> 0 | I81: ='[24]April 24'!AL75 -> 0 | J81: ='[24]Mei 24'!AL75 -> 0 | K81: ='[24]Juny 24'!AL75 -> 0 | L81: ='[24]July 24'!AL75 -> 0 | M81: ='[24]Agustus 24'!AL75 -> 0 | N81: ='[24]September 24'!AL75 -> 0 | O81: ='[24]Oktober 24'!AL75 -> 0 | P81: ='[24]November 24'!AL75 -> 0 | Q81: ='[24]Desember 24'!AL75 -> 0 | S81: =SUM(F81:Q81) -> #REF! | T81: 1716790 | U81: =(S81/T81)*100 -> #REF!
C82: Pouch | S82: Pouch | T82: Pouch | U82: Pouch
C83: Salvaco 1 Liter | E83: Pouch | F83: =F80*12 -> 206364 | G83: =G80*12 -> #REF! | H83: =H80*12 -> 0 | I83: =I80*12 -> 0 | J83: =J80*12 -> 0 | K83: =K80*12 -> 0 | L83: =L80*12 -> 0 | M83: =M80*12 -> 0 | ... Q83: =Q80*12 -> 0 | S83: =S80*12 -> #REF! | T83: =T80*12 -> 15054924 | U83: =(S83/T83)*100 -> #REF!
C84: Salvaco 2 Liter | E84: Pouch | F84: =F81*6 -> 117954 | G84: =G81*6 -> #REF! | H84: =H81*6 -> 0 | I84: =I81*6 -> 0 | J84: =J81*6 -> 0 | K84: =K81*6 -> 0 | L84: =L81*6 -> 0 | M84: =M81*6 -> 0 | ... Q84: =Q81*6 -> 0 | S84: =S81*6 -> #REF! | T84: =T81*6 -> 10300740 | U84: =(S84/T84)*100 -> #REF!
C85: Consumable Vit. A | E85: gram | F85: =(F75*45)/1700 -> 10562.328 | G85: =(G75*45)/1700 -> #REF! | H85: =(H75*45)/1700 -> 0 | I85: =(I75*45)/1700 -> 0 | J85: =(J75*45)/1700 -> 0 | K85: =(K75*45)/1700 -> 0 | L85: =(L75*45)/1700 -> 0 | M85: =(M75*45)/1700 -> 0 | ... Q85: =(Q75*45)/1700 -> 0 | S85: =SUM(F85:Q85) -> #REF! | T85: =(T75*45)/1700 -> #REF! | U85: =(S85/T85)*100 -> #REF!
C86: Consumable Packing Tape | E86: Roll | F86: =SUM(F80:F81)/500 -> 73.712 | G86: =SUM(G80:G81)/500 -> #REF! | H86: =SUM(H80:H81)/500 -> 0 | I86: =SUM(I80:I81)/500 -> 0 | J86: =SUM(J80:J81)/500 -> 0 | K86: =SUM(K80:K81)/500 -> 0 | L86: =SUM(L80:L81)/500 -> 0 | M86: =SUM(M80:M81)/500 -> 0 | ... Q86: =SUM(Q80:Q81)/500 -> 0 | S86: =SUM(F86:Q86) -> #REF! | T86: =SUM(T80:T81)/500 -> 5942.734 | U86: =(S86/T86)*100 -> #REF!
C87: REJECT MATERIAL QTY | S87: Loss Material | T87: Loss Material | U87: Loss Material
C88: Carton | S88: Carton | T88: Carton | U88: Carton
C89: Salvaco 1 Liter | E89: Box | F89: ='[24]Januari 24'!AL74 -> 17197 | G89: ='[24]Februari 24'!AI83 -> #REF! | H89: ='[24]Maret 24'!AL83 -> 0 | I89: ='[24]April 24'!AL83 -> 0 | J89: ='[24]Mei 24'!AL83 -> 0 | K89: ='[24]Juny 24'!AL83 -> 0 | L89: ='[24]July 24'!AL83 -> 0 | M89: ='[24]Agustus 24'!AL83 -> 0 | N89: ='[24]September 24'!AL83 -> 0 | O89: ='[24]Oktober 24'!AL83 -> 0 | P89: ='[24]November 24'!AL83 -> 0 | Q89: ='[24]Desember 24'!AL83 -> 0 | S89: =SUM(F89:Q89) -> #REF! | T89: =SUM(G89:R89) -> #REF! | U89: =SUM(H89:S89) -> #REF!
C90: Salvaco 2 Liter | E90: Box | F90: ='[24]Januari 24'!AL75 -> 19659 | G90: ='[24]Februari 24'!AI84 -> #REF! | H90: ='[24]Maret 24'!AL84 -> 0 | I90: ='[24]April 24'!AL84 -> 0 | J90: ='[24]Mei 24'!AL84 -> 0 | K90: ='[24]Juny 24'!AL84 -> 0 | L90: ='[24]July 24'!AL84 -> 0 | M90: ='[24]Agustus 24'!AL84 -> 0 | N90: ='[24]September 24'!AL84 -> 0 | O90: ='[24]Oktober 24'!AL84 -> 0 | P90: ='[24]November 24'!AL84 -> 0 | Q90: ='[24]Desember 24'!AL84 -> 0 | S90: =SUM(F90:Q90) -> #REF! | T90: =SUM(G90:R90) -> #REF! | U90: =SUM(H90:S90) -> #REF!
C91: Pouch | S91: Pouch | T91: Pouch | U91: Pouch
C92: Salvaco 1 Liter | E92: Pouch | F92: =F89*12 -> 206364 | G92: =G89*12 -> #REF! | H92: =H89*12 -> 0 | I92: =I89*12 -> 0 | J92: =J89*12 -> 0 | K92: =K89*12 -> 0 | L92: =L89*12 -> 0 | M92: =M89*12 -> 0 | ... Q92: =Q89*12 -> 0 | S92: =SUM(F92:Q92) -> #REF! | T92: =SUM(G92:R92) -> #REF! | U92: =SUM(H92:S92) -> #REF!
C93: Salvaco 2 Liter | E93: Pouch | F93: =F90*6 -> 117954 | G93: =G90*6 -> #REF! | H93: =H90*6 -> 0 | I93: =I90*6 -> 0 | J93: =J90*6 -> 0 | K93: =K90*6 -> 0 | L93: =L90*6 -> 0 | M93: =M90*6 -> 0 | ... Q93: =Q90*6 -> 0 | S93: =SUM(F93:Q93) -> #REF! | T93: =SUM(G93:R93) -> #REF! | U93: =SUM(H93:S93) -> #REF!
C94: REJECT MATERIAL (%) | S94: Loss Material | T94: Loss Material | U94: Loss Material
C95: Carton | S95: Carton | T95: Carton | U95: Carton
C96: Salvaco 1 Liter | D96: 0.3 | E96: % | F96: =F89/F80*100 -> 100 | G96: =G89/G80*100 -> #REF! | H96: =H89/H80*100 -> #DIV/0! | I96: =I89/I80*100 -> #DIV/0! | J96: =J89/J80*100 -> #DIV/0! | K96: =K89/K80*100 -> #DIV/0! | L96: =L89/L80*100 -> #DIV/0! | M96: =M89/M80*100 -> #DIV/0! | ... Q96: =Q89/Q80*100 -> #DIV/0! | S96: =S89/S80*100 -> #REF! | T96: =T89/T80*100 -> #REF! | U96: =U89/U80*100 -> #REF!
C97: Salvaco 2 Liter | D97: 0.3 | E97: % | F97: =F90/F81*100 -> 100 | G97: =G90/G81*100 -> #REF! | H97: =H90/H81*100 -> #DIV/0! | I97: =I90/I81*100 -> #DIV/0! | J97: =J90/J81*100 -> #DIV/0! | K97: =K90/K81*100 -> #DIV/0! | L97: =L90/L81*100 -> #DIV/0! | M97: =M90/M81*100 -> #DIV/0! | ... Q97: =Q90/Q81*100 -> #DIV/0! | S97: =S90/S81*100 -> #REF! | T97: =T90/T81*100 -> #REF! | U97: =U90/U81*100 -> #REF!
C98: Pouch | S98: Pouch | T98: Pouch | U98: Pouch
C99: Salvaco 1 Liter | D99: 0.5 | E99: % | F99: =F92/F83*100 -> 100 | G99: =G92/G83*100 -> #REF! | H99: =H92/H83*100 -> #DIV/0! | I99: =I92/I83*100 -> #DIV/0! | J99: =J92/J83*100 -> #DIV/0! | K99: =K92/K83*100 -> #DIV/0! | L99: =L92/L83*100 -> #DIV/0! | M99: =M92/M83*100 -> #DIV/0! | ... Q99: =Q92/Q83*100 -> #DIV/0! | S99: =S92/S83*100 -> #REF! | T99: =T92/T83*100 -> #REF! | U99: =U92/U83*100 -> #REF!
C100: Salvaco 2 Liter | D100: 0.5 | E100: % | F100: =F93/F84*100 -> 100 | G100: =G93/G84*100 -> #REF! | H100: =H93/H84*100 -> #DIV/0! | I100: =I93/I84*100 -> #DIV/0! | J100: =J93/J84*100 -> #DIV/0! | K100: =K93/K84*100 -> #DIV/0! | L100: =L93/L84*100 -> #DIV/0! | M100: =M93/M84*100 -> #DIV/0! | ... Q100: =Q93/Q84*100 -> #DIV/0! | S100: =S93/S84*100 -> #REF! | T100: =T93/T84*100 -> #REF! | U100: =U93/U84*100 -> #REF!
B101: 6 | C101: PACKAGING (Brand Nusakita) | S101: Packaging | T101: Packaging | U101: Packaging
C102: Olein IV 60 Consume | E102: Kg | F102: ='[24]Januari 24'!AL96 -> 461724.08 | G102: ='[24]Februari 24'!AI96 -> #REF! | H102: ='[24]Maret 24'!AL96 -> 0 | I102: ='[24]April 24'!AL96 -> 0 | J102: ='[24]Mei 24'!AL96 -> 0 | K102: ='[24]Juny 24'!AL96 -> 0 | L102: ='[24]July 24'!AL96 -> 0 | M102: ='[24]Agustus 24'!AL96 -> 0 | N102: ='[24]September 24'!AL96 -> 0 | O102: ='[24]Oktober 24'!AL96 -> 0 | P102: ='[24]November 24'!AL96 -> 0 | Q102: ='[24]Desember 24'!AL96 -> 0 | S102: =SUM(S103:S104) -> #REF! | T102: =SUM(T103:T104) -> #REF! | U102: =SUM(U103:U104) -> #REF!
...

Sheet Flow Meter
A2: TOTAL TONASE FLOWMETER PRODUK
A3: REFINERY
A5: TANGGAL VALIDASI
A6: NO | B6: NAMA PRODUK | C6: 01 Juli | D6: 02 Juli | E6: 03 Juli | F6: 04 Juli | G6: 05 Juli | H6: 06 Juli | I6: 07 Juli | J6: 08 Juli | K6: 09 Juli | L6: 10 Juli | M6: 11 Juli | N6: 12 Juli | O6: 13 Juli | P6: 14 Juli | Q6: 15 Juli | R6: TOTAL | S6: Sounding | T6: Yield Theory | U6: Yield Aktual
A7: 1 | B7: CPO | C7: ='[23]01 '!$Q$14 -> 744924 | D7: ='[23]02'!$Q$14 -> 743972 | E7: ='[23]03'!$Q$14 -> 1048435 | F7: ='[23]04'!$Q$14 -> 1114821 | G7: 248126 | H7: 389481 | I7: 104168 | J7: 320907 | K7: 100743 | L7: 512647 | M7: 441064 | N7: 524002 | O7: 568358 | P7: 430750 | R7: =SUM(C7:Q7) -> 7292398
A8: 2 | B8: RBDPO | C8: 713300 | D8: 708000 | E8: 993100 | F8: 1056000 | G8: 237021 | H8: 365100 | I8: 44001 | J8: 300010 | K8: 94507 | L8: 488153 | M8: 414337 | N8: 492952 | O8: 532902 | P8: 497845 | R8: =SUM(C8:Q8) -> 6937228 | T8: =R8/R7 -> 0.95129586 | U8: =S8/S7 -> #DIV/0! | W8: =4984655+#REF! -> #REF!
A9: 3 | B9: PFAD | C9: ='[23]01 '!$P$25 -> 25659 | D9: 28786 | E9: ='[23]03'!$P$25 -> 46938 | F9: ='[23]04'!$P$24 -> 48667 | G9: 8070 | H9: 19280 | I9: 3234 | J9: 18283 | K9: 5131 | L9: 20426 | M9: 23275 | N9: 27655 | O9: 25803 | P9: 20173 | R9: =SUM(C9:Q9) -> 321380 | T9: =R9/R7 -> 0.044070551 | U9: =S9/S7 -> #DIV/0!
C10: =C8/C7 -> 0.95754735 | D10: =D8/D7 -> 0.95164872 | E10: =E8/E7 -> 0.94722133 | F10: =F8/F7 -> 0.94723727 | G10: =G8/G7 -> 0.95524451 | H10: =H8/H7 -> 0.93740131 | I10: =I8/I7 -> 0.42240419 | J10: =J8/J7 -> 0.93488145 | ... P10: =P8/P7 -> 1.1557632
C11: =C9/C7*1 -> 0.034445125 | D11: =D9/D7*1 -> 0.038692316 | E11: =E9/E7*1 -> 0.044769585 | F11: =F9/F7*1 -> 0.043654542 | G11: =G9/G7*1 -> 0.032523798 | H11: =H9/H7*1 -> 0.049501773 | I11: =I9/I7*1 -> 0.031046003 | J11: =J9/J7*1 -> 0.056972892 | ... P11: =P9/P7*1 -> 0.046832269
B12: LOSIS | C12: =(C7-C8-C9)/C7 -> 0.0080075283 | D12: =(D7-D8-D9)/D7 -> 0.0096589657 | E12: =(E7-E8-E9)/E7 -> 0.0080090802 | F12: =(F7-F8-F9)/F7 -> 0.0091081887 | G12: =(G7-G8-G9)/G7 -> 0.012231689 | H12: =(H7-H8-H9)/H7 -> 0.013096916 | I12: =(I7-I8-I9)/I7 -> 0.5465498 | J12: =(J7-J8-J9)/J7 -> 0.0081456621 | ... P12: =(P7-P8-P9)/P7 -> -0.20259547
A14: TANGGAL flow meter
A15: NO | B15: NAMA PRODUK | C15: 01 Juli | D15: 02 Juli | E15: 03 Juli | F15: 04 Juli | G15: 05 Juli | H15: 06 Juli | I15: 07 Juli | J15: 08 Juli | K15: 09 Juli | L15: 10 Juli | M15: 11 Juli | N15: 12 Juli | O15: 13 Juli | P15: 14 Juli | Q15: 15 Juli | R15: TOTAL | S15: Sounding | T15: Yield Theory | U15: Yield Aktual
A16: 1 | B16: CPO | C16: 680800 | D16: 806400 | E16: 858600 | F16: 898100 | G16: 26100 | H16: 513200 | I16: 119200 | J16: 208900 | K16: 147700 | L16: 425800 | M16: 347900 | N16: 459100 | O16: 509200 | P16: 396700 | Q16: 20200 | R16: =SUM(C16:Q16) -> 6417900 | S16: =5745000+14073+R19 -> 7292813
A17: 2 | B17: RBDPO | C17: 722400 | D17: 826700 | E17: 980700 | F17: 980600 | G17: 19900 | H17: 582000 | I17: 150500 | J17: 215300 | K17: 70837 | L17: 488153 | M17: 379337 | N17: 502200 | O17: 535800 | P17: 412600 | Q17: 92100 | R17: =SUM(C17:Q17) -> 6959127 | S17: =SUM(C17:M17)+R20 -> 6940126 | T17: =R17/R16 -> 1.0843309 | U17: =S17/S16 -> 0.9516391 | W17: =4984655+R20 -> 6508354
A18: 3 | B18: PFAD | C18: 37300 | D18: 38700 | E18: 49500 | F18: 47100 | G18: 3800 | H18: 30300 | I18: 9300 | J18: 14000 | K18: 14800 | L18: 25100 | M18: 23400 | N18: 23900 | O18: 26800 | P18: 22200 | Q18: 5900 | R18: =SUM(C18:Q18) -> 372100 | S18: =248746+R21 -> 322377 | T18: =R18/R16 -> 0.057978466 | U18: =S18/S16 -> 0.044204753
C19: =C17/C16 -> 1.0611046 | D19: =D17/D16 -> 1.0251736 | E19: =E17/E16 -> 1.1422082 | F19: =F17/F16 -> 1.0918606 | G19: =G17/G16 -> 0.76245211 | H19: =H17/H16 -> 1.1340608 | I19: =I17/I16 -> 1.2625839 | J19: =J17/J16 -> 1.0306367 | K19: =K17/K16 -> 0.47960054 | L19: 269515 | M19: CPO | N19: 534002 | O19: 568773 | P19: 430750 | Q19: 269300 | R19: =L19+N19+O19+P19-Q19 -> 1533740 | U19: =100%-U17-U18 -> 0.0041561466 | V19: Losses
M20: RBDPO | N20: 492952 | O20: 532902 | P20: 497845 | R20: =SUM(N20:P20) -> 1523699
N21: 27655 | O21: 25803 | P21: 20173 | R21: =SUM(N21:P21) -> 73631
B22: Nb : | C22: 1. 5.745.000 adalaha angka consume CPO tanggal 1 - 11 ( Opening Stock + Incoming - Closing tanggal 11 )
C23: 2. 14.073 ( Beda Pembacaan antara sounding dan timbangan )
C24: 3. 1.533.740 adalah angka sounding CPO 12, 13, 14
A25: FRAKSINASI
A26: TANGGAL
A27: NO | B27: NAMA PRODUK | C27: 01 Juli | D27: 02 Juli | E27: 03 Juli | F27: 04 Juli | G27: 05 Juli | H27: 06 Juli | I27: 07 Juli | J27: 08 Juli | K27: 09 Juli | L27: 10 Juli | M27: 11 Juli | N27: 12 Juli | O27: 13 Juli | P27: 14 Juli | Q27: 15 Juli | R27: TOTAL | S27: Sounding | T27: Yield
A28: 1 | B28: RBDPO | C28: 667300 | D28: 695000 | E28: 814100 | F28: 760000 | G28: 620300 | H28: 587100 | I28: 118500 | J28: 0 | K28: 253000 | L28: 0 | M28: 466900 | N28: 258400 | O28: 584400 | P28: 680200 | R28: =SUM(C28:Q28) -> 6505200
A29: 2 | B29: OLEIN IV 58 | C29: 518400 | D29: 487200 | E29: 539100 | F29: 571900 | G29: 554300 | H29: 449900 | I29: 209900 | J29: 0 | K29: 297100 | L29: 0 | M29: 472500 | N29: 207400 | O29: 239100 | P29: 414100 | R29: =SUM(C29:Q29) -> 4960900
A30: 3 | B30: STEARIN | C30: 207500 | D30: 202900 | E30: 215500 | F30: =27400+151100+55600 -> 234100 | G30: 213300 | H30: 183700 | I30: 104800 | J30: 0 | K30: 93900 | L30: 0 | M30: 172400 | N30: 111100 | O30: 81200 | P30: 193200 | R30: =SUM(C30:Q30) -> 2013600
O32: STOCK OPNAME | R32: =1311190 -> 1311190
O33: TOTAL TERIMA 1- 11 TIMBANGAN | R33: 3865830
O34: PIPANISASI DAN GK 1 - 11 | R34: 1888995
O35: STOCK AKHIR OPNAME 11 JULI | R35: 1320540.6
R36: =R32+R33+R34-R35 -> 5745474.4
O38: STOCK OPNAME 1 JULI | R38: 178489.22
O39: TOTAL FLOW METER 11 | R39: =SUM(C28:M28) -> 4982200
O40: STOCK AKHIR OPNAME 11 JULI
