Workbook

Sheet September - 2024
P1: PRODUCTION REPORT
C2: No | D2: ITEM | E2: Budget / Norma | F2: UoM | G2: September | AM2: TOTAL MONTHLY (Kg)
G3: 1 | H3: 2 | I3: 3 | J3: 4 | K3: 5 | L3: 6 | M3: 7 | N3: 8 | O3: 9 | P3: 10 | Q3: 11 | R3: 12 | S3: 13 | T3: 14 | U3: 15 | V3: 16 | W3: 17 | X3: 18 | Y3: 19 | Z3: 20 | AA3: 21 | AB3: 22 | AC3: 23 | AD3: 24 | AE3: 25 | AF3: 26 | AG3: 27 | AH3: 28 | AI3: 29 | AJ3: 30 | AK3: 31
C4: 1 | D4: PRODUCTION | AM4: Production
D5: Refinery | AM5: Refinery
D6: Running Days | F6: Day | G6: 1 | H6: 1 | I6: 1 | J6: 1 | K6: 1 | L6: 1 | M6: 1 | N6: 1 | O6: 1 | P6: 1 | Q6: 1 | R6: 1 | S6: 1 | T6: 1 | U6: 1 | V6: 0 | W6: 1 | X6: 1 | Y6: 1 | Z6: 1 | AA6: 1 | AB6: 1 | AC6: 0 | AD6: 0 | AE6: 1 | AF6: 1 | AG6: 1 | AH6: 1 | AI6: 1 | AJ6: 1 | AM6: =SUM(G6:AK6) -> 27
D7: Incoming CPO | F7: Kg | G7: ='[1]01'!$P$15 -> 0 | H7: ='[2]02'!$P$15 -> 1091462 | I7: ='[3]03'!$P$15 -> 775948 | J7: ='[4]04'!$P$15 -> 411548 | K7: ='[5]05'!$P$15 -> 662586 | L7: ='[6]06'!$P$15 -> 581111 | M7: ='[7]07'!$P$15 -> 1040334 | N7: ='[7]08'!$P$15 -> 0 | O7: ='[6]09'!$P$15 -> 1393093 | P7: ='[3]10'!$P$15 -> 1072925 | Q7: ='[5]11'!$P$15 -> 820575 | R7: ='[6]12'!$P$15 -> 544250 | S7: ='[8]13'!$P$15 -> 646901 | T7: ='[9]14'!$P$15 -> 1738216 | U7: ='[9]15'!$P$15 -> 511082 | V7: 0 | W7: ='[10]17'!$P$15 -> 885719 | X7: ='[7]18'!$P$15 -> 1402234 | Y7: ='[11]19'!$P$15-3000 -> 901325 | Z7: ='[12]20'!$P$15 -> 870362 | AA7: ='[13]21'!$P$15 -> 1413850 | AB7: ='[13]22'!$P$15 -> 577458 | AC7: ='[13]23'!$P$15-9880 -> 727575 | AD7: ='[14]24'!$P$15 -> 733336 | AE7: ='[15]25'!$P$15 -> 786729 | AF7: ='[16]26'!$P$15 -> 792985 | AG7: =956721+110099+463387 -> 1530207 | AH7: ='[17]28'!$P$15 -> 1209719 | AI7: ='[18]29'!$P$15 -> 914652 | AJ7: ='[14]30 (Stock Opname)'!$P$15 -> 950954 | AM7: =SUM(G7:AK7) -> 24987136 | AN7: =AVERAGE(H7:AA7) -> 838176.05
D8: Ratio Run CPO | F8: % | G8: =G9/2200000*100 -> 14.784727 | H8: =H9/2200000*100 -> 11.107818 | I8: =I9/2200000*100 -> 51.390636 | J8: =J9/2200000*100 -> 31.202818 | K8: =K9/2200000*100 -> 27.664455 | L8: =L9/2200000*100 -> 30.109727 | M8: =M9/2200000*100 -> 27.837318 | N8: =N9/2200000*100 -> 17.565727 | ... AK8: =AK9/2200000*100 -> 0 | AM8: =SUM(G8:AJ8)/AM6 -> 40.48197 | AW8: =AM9/30 -> 801543
D9: CPO Consume Total | E9: 36359000 | F9: Kg | G9: ='[1]01'!$Q$15 -> 325264 | H9: ='[2]02'!$Q$15 -> 244372 | I9: ='[3]03'!$Q$15 -> 1130594 | J9: ='[4]04'!$Q$15 -> 686462 | K9: ='[5]05'!$Q$15 -> 608618 | L9: ='[6]06'!$Q$15 -> 662414 | M9: ='[7]07'!$Q$15 -> 612421 | N9: ='[7]08'!$Q$15 -> 386446 | O9: ='[6]09'!$Q$15 -> 1041561 | P9: ='[3]10'!$Q$12+'[3]10'!$Q$14 -> 1056809 | Q9: ='[5]11'!$Q$15 -> 1067764 | R9: ='[6]12'!$Q$15 -> 701797 | S9: ='[8]13'!$Q$15 -> 563620 | T9: 605861 | U9: 1587899 | W9: ='[10]17'!$Q$15 -> 430122 | X9: ='[7]18'!$Q$15 -> 1154162 | Y9: ='[11]19'!$Q$15 -> 1380669 | Z9: ='[12]20'!$Q$15 -> 938737 | AA9: ='[13]21'!$Q$15 -> 875019 | AB9: ='[13]22 Rev'!$Q$15 -> 41122 | AC9: 0 | AD9: 0 | AE9: ='[15]25'!$Q$15 -> 879838 | AF9: 1623131 | AG9: 1648997 | AH9: 1718627 | AI9: 1528732 | AJ9: ='[14]30 (Stock Opname)'!$Q$10 -> 545232 | AM9: =SUM(G9:AK9) -> 24046290 | AN9: =AM9/E9 -> 0.6613573 | AO9: =AM9/AM6 -> 890603.33 | AP9: =AO9/E9 -> 0.024494715 | AR9: =AM9/E9 -> 0.6613573 | AS9: =AM9/E9 -> 0.6613573
D10: Avg Daily Consump CPO ( MTD ) | AM10: =AM9/AM6 -> 890603.33 | AW10: =AM7/30 -> 832904.53
D11: CPO Consume Poram | E11: 29045000 | F11: Kg | G11: =G9-G36-G45 -> 325264 | H11: =H9-H36-H45 -> 244372 | I11: =I9-I36-I45 -> 1130594 | J11: =J9-J36-J45 -> 686462 | K11: =K9-K36-K45 -> 608618 | L11: =L9-L36-L45 -> 662414 | M11: =M9-M36-M45 -> 612421 | N11: =N9-N36-N45 -> 386446 | ... AK11: =AK9-AK36-AK45 -> 0 | AM11: =SUM(G11:AK11) -> 24046290
D12: CPO Consume Brand | E12: 7314000 | F12: Kg | G12: =G36+G45 -> 0 | H12: =H36+H45 -> 0 | I12: =I36+I45 -> 0 | J12: =J36+J45 -> 0 | K12: =K36+K45 -> 0 | L12: =L36+L45 -> 0 | M12: =M36+M45 -> 0 | N12: =N36+N45 -> 0 | ... AK12: =AK36+AK45 -> 0 | AM12: =SUM(G12:AK12) -> 0
D13: - FFA | E13: 5 | F13: % | G13: 4.16 | H13: =3.99 -> 3.99 | I13: 3.58 | J13: =(3.6+3.65+3.95)/3 -> 3.7333333 | K13: =(4.17+3.99)/2 -> 4.08 | L13: =(3.55+3.59)/2 -> 3.57 | M13: =(3.99) -> 3.99 | N13: 3.6 | O13: =(3.83+3.78)/2 -> 3.805 | P13: =(3.61+3.43)/2 -> 3.52 | Q13: =(3.62+3.69)/2 -> 3.655 | R13: 3.77 | S13: =(3.83+3.55)/2 -> 3.69 | T13: 3.85 | U13: 3.74 | V13: 0 | W13: 3.64 | X13: =(3.56+3.58)/2 -> 3.57 | Y13: 3.71 | Z13: =(3.98+3.78)/2 -> 3.88 | AA13: 3.85 | AB13: 0 | AC13: 0 | AD13: 0 | AE13: 3.95 | AF13: =(4.15+3.76)/2 -> 3.955 | AG13: =(3.41+3.74)/2 -> 3.575 | AH13: =(3.74+3.77)/2 -> 3.755 | AI13: =(4.02+3.77)/2 -> 3.895 | AJ13: 3.88 | AM13: =SUM(G13:AJ13)/AM6 -> 3.6441975
D14: - Moist & Impurities | E14: 0.5 | F14: % | G14: 0.48 | H14: 0.48 | I14: 0.4 | J14: =(0.38+0.35+0.48)/3 -> 0.40333333 | K14: =(0.4+0.49)/2 -> 0.445 | L14: =(0.44+0.47)/2 -> 0.455 | M14: 0.41 | N14: 0.47 | O14: =(0.42+0.49)/2 -> 0.455 | P14: =(0.4+0.42)/2 -> 0.41 | Q14: =(0.42+0.38)/2 -> 0.4 | R14: 0.4 | S14: 0.44 | T14: 0.46 | U14: 0.44 | V14: 0 | W14: 0.4 | X14: =(0.38+0.46)/2 -> 0.42 | Y14: 0.38 | Z14: 0.39 | AA14: =(0.42+0.45)/2 -> 0.435 | AB14: 0 | AC14: 0 | AD14: 0 | AE14: 0.41 | AF14: 0.42 | AG14: 0.46 | AH14: =(0.41+0.47)/2 -> 0.44 | AI14: =(0.43+0.48)/2 -> 0.455 | AJ14: 0.42 | AM14: =SUM(G14:AJ14)/AM6 -> 0.41401235
D15: - DOBI | E15: 2,20 Min | F15: % | G15: 22.18 | H15: 22.18 | I15: 22.18 | J15: 22.15 | K15: 22.17 | L15: 22.16 | M15: 22.18 | N15: 22.18 | O15: 22.1 | P15: 22.1 | Q15: 22.18 | R15: 22.1 | S15: 22 | T15: 22.02 | U15: 22.02 | V15: 0 | W15: 22.08 | X15: 22.02 | Y15: 22.02 | Z15: 22.01 | AA15: 22.02 | AB15: 0 | AC15: 0 | AD15: 0 | AE15: 22.02 | AF15: 22.02 | AG15: 22.02 | AH15: 22.02 | AI15: 22.01 | AJ15: 22.02 | AM15: =SUM(G15:AK15)/AM6 -> 21.265185
D16: Product | AM16: Product
D17: OIP RBDPO | G17: -25058 | H17: 5184 | I17: 12794 | J17: -15208 | K17: -2710 | L17: 4240 | M17: 3950 | N17: 8077 | O17: -16405 | P17: 2258 | Q17: 3187 | R17: 2456 | S17: ='OIP Refinery'!G17 -> 20802 | T17: -9534 | U17: -592 | V17: 0 | W17: 13769 | X17: -2231 | Y17: -24516 | Z17: -2682 | AA17: -8332 | AB17: -5229 | AC17: -4192 | AD17: 4232 | AE17: 21733 | AF17: -6956 | AG17: -12010 | AH17: 12177 | AI17: -7816 | AJ17: 3740
D18: RBDPO | E18: 34458000 | F18: Kg | G18: ='[1]01'!$P$18+G17 -> 288137 | H18: ='[2]02'!$P$18+H17 -> 229820 | I18: ='[6]03'!$P$18+I17 -> 1094261 | J18: ='[4]04'!$P$18+J17 -> 651579 | K18: ='[5]05'!$P$18+K22+K17 -> 582876 | L18: ='[6]06'!$P$18+L17 -> 619308 | M18: ='[7]07'!$P$18+M22+M17 -> 583790 | N18: ='[7]08'!$P$18+N17 -> 364733 | O18: ='[2]09'!$P$18+O17 -> 962440 | P18: ='[3]10'!$P$18+P17 -> 1024438 | Q18: ='[5]11'!$P$18+Q17 -> 1038100 | R18: ='[6]12'!$P$18+R17 -> 657990 | S18: ='[8]13'!$P$18+S17 -> 532167 | T18: =580282+T17 -> 570748 | U18: =1519300+U17 -> 1518708 | V18: 0 | W18: ='[10]17'!$P$18+W17 -> 416007 | X18: ='[7]18'!$P$18+X17 -> 1100547 | Y18: ='[11]19'!$P$18+Y17 -> 1309668 | Z18: ='[12]20'!$P$18+Z17 -> 896963 | AA18: ='[13]21'!$P$18+AA17 -> 818274 | AB18: ='[13]22'!$P$18+AB17 -> 29377 | AC18: 0 | AD18: 0 | AE18: ='[15]25'!$P$18+AE22+AE17 -> 818213 | AF18: =1548139+AF17 -> 1541183 | AG18: =1587278+AG17 -> 1575268 | AH18: =1612436+AH17 -> 1624613 | AI18: =1301424+AI22+AI17 -> 1411508 | AJ18: ='[14]30 (Stock Opname)'!$P$18+AJ17 -> 522775 | AM18: =SUM(G18:AK18) -> 22783491 | AR18: =AM18/E18 -> 0.66119598 | AS18: =SUM(Q18:Z18) -> 8040898
D19: PFAD | E19: 1636000 | F19: Kg | G19: ='[1]01'!$P$26 -> 17895 | H19: ='[2]02'!$P$26 -> 9543 | I19: 47327 | J19: ='[4]04'!$P$26 -> 27444 | K19: ='[5]05'!$P$26 -> 24771 | L19: ='[6]06'!$P$26 -> 25126 | M19: ='[7]07'!$P$26 -> 25986 | N19: ='[7]08'!$P$26 -> 16762 | O19: ='[2]09'!$P$26 -> 39994 | P19: ='[3]10'!$P$26 -> 42272 | Q19: ='[5]11'!$P$26 -> 45133 | R19: ='[6]12'!$P$26 -> 37189 | S19: ='[8]13'!$P$26 -> 16219 | T19: 26322 | U19: 71848 | V19: =3083 -> 3083 | W19: ='[10]17'!$P$26 -> 11052 | X19: ='[7]18'!$P$26 -> 45065 | Y19: ='[11]19'!$P$26 -> 58214 | Z19: ='[12]20'!$P$26 -> 40299 | AA19: ='[13]21'!$P$26 -> 38288 | AB19: ='[13]22'!$P$26 -> 1071 | AC19: 0 | AD19: 0 | AE19: ='[15]25'!$P$26 -> 56619 | AF19: 70755 | AG19: 49063 | AH19: 69396 | AI19: 56417 | AJ19: ='[14]30 (Stock Opname)'!$P$26 -> 25365 | AM19: =SUM(G19:AK19) -> 998518
D20: Fractionation
D21: Running Days | F21: Day | G21: 1 | H21: 1 | I21: 1 | J21: 1 | K21: 1 | L21: 1 | M21: 1 | N21: 1 | O21: 1 | P21: 1 | Q21: 1 | R21: 1 | S21: 1 | T21: 1 | U21: 1 | V21: 1 | W21: 0 | X21: 1 | Y21: 1 | Z21: 1 | AA21: 1 | AB21: 1 | AC21: 0 | AD21: 0 | AE21: 1 | AF21: 1 | AG21: 1 | AH21: 1 | AI21: 1 | AJ21: 1 | AM21: =SUM(G21:AK21) -> 27
D22: Filling Langsung CR Fr Refinery | F22: Kg | G22: 0 | H22: 0 | I22: 0 | J22: 0 | K22: 119600 | L22: 0 | M22: 126600 | N22: 0 | O22: 0 | P22: 0 | Q22: 0 | R22: 0 | S22: 0 | T22: 0 | U22: 0 | V22: 0 | W22: 0 | X22: 0 | Y22: 0 | Z22: 0 | AA22: 0 | AB22: 0 | AC22: 0 | AD22: 0 | AE22: =60800 -> 60800 | AF22: 0 | AG22: 0 | AH22: 0 | AI22: 117900 | AJ22: 0 | AK22: 0 | AM22: =SUM(G22:AJ22) -> 424900
D23: Total Filling Crystalizer ( Feed ) | F23: Kg | G23: ='[1]01'!$Q$18 -> 526736 | H23: ='[2]02'!$Q$18 -> 224510 | I23: =509400+165400 -> 674800 | J23: ='[4]04'!$Q$18 -> 695363 | K23: ='[5]05'!$Q$18+K22 -> 747977 | L23: ='[6]06'!$Q$18 -> 524444 | M23: ='[7]07'!$Q$18 -> 501574 | N23: ='[7]08'!$Q$18 -> 680764 | O23: ='[6]09'!$Q$18 -> 589345 | P23: ='[3]10'!$Q$18 -> 817090 | Q23: ='[5]11'!$Q$18 -> 1110923 | R23: ='[6]12'!$Q$18 -> 411103 | S23: ='[8]13'!$Q$18 -> 634120 | T23: =578566+290444 -> 869010 | U23: =584944+567152 -> 1152096 | V23: ='[9]16'!$Q$18 -> 688986 | W23: 0 | X23: ='[7]18'!$Q$18 -> 1221935 | Y23: ='[11]19'!$Q$18 -> 867293 | Z23: ='[13]20'!$Q$18 -> 1218693 | AA23: ='[13]21'!$Q$18 -> 998551 | AB23: ='[13]22'!$Q$18 -> 284335 | AC23: 0 | AD23: 0 | AE23: ='[15]25'!$Q$18+AE22 -> 296046 | AF23: ='[16]26'!$Q$18 -> 1562863 | AG23: =931340+642286 -> 1573626 | AH23: ='[17]28'!$Q$18 -> 1569616 | AI23: =340263+818995 -> 1159258 | AJ23: ='[14]30 (Stock Opname)'!$Q$18 -> 991912 | AM23: =SUM(G23:AJ23) -> 22592969 | AN23: =AM23/E18 -> 0.65566687
D24: Avg Daily Consump RPO ( MTD ) | AM24: =AM23/AM21 -> 836776.63
D25: Total Proses RBDPO | F25: Kg | G25: =SUM(G28,G32,G37,G41,G46) -> 921143 | H25: =SUM(H28,H32,H37,H41,H46) -> 250811 | I25: =SUM(I28,I32,I37,I41,I46) -> 519670 | J25: =SUM(J28,J32,J37,J41,J46) -> 738041 | K25: =SUM(K28,K32,K37,K41,K46) -> 756126 | L25: =SUM(L28,L32,L37,L41,L46) -> 570133 | M25: =SUM(M28,M32,M37,M41,M46) -> 638607 | N25: =SUM(N28,N32,N37,N41,N46) -> 813834 | ... AJ25: =SUM(AJ28,AJ32,AJ37,AJ41,AJ46) -> 1153492 | AM25: =SUM(G25:AJ25) -> 23189025
D26: Sisa Filling Crystalizer | F26: Kg | G26: =G23-G25 -> -394407 | H26: =H23-H25 -> -26301 | I26: =I23-I25 -> 155130 | J26: =J23-J25 -> -42678 | K26: =K23-K25 -> -8149 | L26: =L23-L25 -> -45689 | M26: =M23-M25 -> -137033 | N26: =N23-N25 -> -133070 | ... AJ26: =AJ23-AJ25 -> -161580 | AM26: =SUM(G26:AJ26) -> -596056
D27: Fractionation OLEIN IV 56 | AM27: Olein IV 56
D28: RBDPO Consume | F28: Kg | G28: =G29+G30 -> 0 | H28: =H29+H30 -> 0 | I28: =I29+I30 -> 0 | J28: =J29+J30 -> 0 | K28: =K29+K30 -> 222848 | L28: =L29+L30 -> 0 | M28: =M29+M30 -> 0 | N28: =N29+N30 -> 0 | ... AJ28: =AJ29+AJ30 -> 0 | AM28: =SUM(G28:AK28) -> 16566545
D29: OLEIN IV 56 | F29: Kg | K29: 190348 | O29: ='[6]09'!$P$21 -> 95794 | P29: ='[3]10'!$P$21 -> 772516 | Q29: ='[5]11'!$P$21+237105 -> 967571 | R29: ='[6]12'!$P$21 -> 538270 | S29: ='[8]13'!$P$21 -> 572873 | T29: 469337 | U29: 822558 | V29: ='[9]16'!$P$23 -> 964480 | W29: 0 | X29: ='[7]18'!$P$21 -> 526646 | Y29: ='[11]19'!$P$23 -> 822471 | Z29: ='[12]20'!$P$21 -> 977688 | AA29: ='[13]21'!$P$21 -> 908032 | AB29: ='[13]22'!$P$21 -> 343197 | AC29: 0 | AD29: 0 | AE29: ='[15]25'!$P$21 -> 217590 | AF29: ='[16]26'!$P$23 -> 1097545 | AG29: 1298759 | AH29: 1426210 | AI29: ='[19]29'!$P$21 -> 777910 | AJ29: 0 | AK29: 0 | AM29: =SUM(G29:AK29) -> 13789795
D30: STEARIN | F30: Kg | K30: 32500 | O30: 18345 | P30: ='[3]10'!$P$30 -> 173336 | Q30: ='[5]11'!$P$28 -> 186831 | R30: ='[6]12'!$P$28 -> 118662 | S30: ='[8]13'!$P$30 -> 124438 | T30: 96521 | U30: 147543 | V30: ='[9]16'!$P$30 -> 208479 | W30: 0 | X30: ='[7]18'!$P$27 -> 99947 | Y30: ='[11]19'!$P$30-Y39 -> 186549 | Z30: ='[12]20'!$P$30 -> 185126 | AA30: ='[13]21'!$P$30 -> 193691 | AB30: ='[13]22'!$P$30 -> 88321 | AC30: 0 | AD30: 0 | AE30: ='[15]25'!$P$30 -> 27470 | AF30: ='[16]26'!$P$30 -> 234400 | AG30: 226378 | AH30: 278163 | AI30: 150050 | AJ30: 0 | AK30: 0 | AM30: =SUM(G30:AK30) -> 2776750 | AU30: =AM30+AM34+AM39+AM43+AM49 -> 4579832
D31: Fractionation OLEIN IV 57 ( Bulk ) | AM31: Olein IV 57 ( Bulk )
D32: RBDPO Consume | F32: Kg | G32: =G33+G34 -> 0 | H32: =H33+H34 -> 0 | I32: =I33+I34 -> 0 | J32: =J33+J34 -> 0 | K32: =K33+K34 -> 0 | L32: =L33+L34 -> 0 | M32: =M33+M34 -> 0 | N32: =N33+N34 -> 0 | ... AK32: =AK33+AK34 -> 0 | AM32: =SUM(G32:AJ32) -> 0
D33: OLEIN IV 57 | F33: Kg | G33: 0 | H33: 0 | I33: 0 | J33: 0 | K33: 0 | L33: 0 | M33: 0 | N33: 0 | O33: 0 | P33: 0 | Q33: 0 | R33: 0 | S33: 0 | T33: 0 | U33: 0 | V33: 0 | W33: 0 | X33: 0 | Y33: 0 | Z33: 0 | AA33: 0 | AB33: 0 | AC33: 0 | AD33: 0 | AE33: 0 | AF33: 0 | AG33: 0 | AH33: 0 | AI33: 0 | AJ33: 0 | AK33: 0 | AM33: =SUM(G33:AJ33) -> 0
D34: STEARIN | F34: Kg | G34: 0 | H34: 0 | I34: 0 | J34: 0 | K34: 0 | L34: 0 | M34: 0 | N34: 0 | O34: 0 | P34: 0 | Q34: 0 | R34: 0 | S34: 0 | T34: 0 | U34: 0 | V34: 0 | W34: 0 | X34: 0 | Y34: 0 | Z34: 0 | AA34: 0 | AB34: 0 | AC34: 0 | AD34: 0 | AE34: 0 | AF34: 0 | AG34: 0 | AH34: 0 | AI34: 0 | AJ34: 0 | AK34: 0 | AM34: =SUM(G34:AJ34) -> 0
D35: Fractionation OLEIN IV 57 ( Retail ) | AM35: Olein IV 57 ( Retail )
D36: CPO Consume | F36: Kg | G36: 0 | H36: 0 | I36: 0 | J36: 0 | K36: 0 | L36: 0 | M36: 0 | N36: 0 | O36: 0 | P36: 0 | Q36: 0 | R36: 0 | T36: 0 | U36: 0 | V36: 0 | W36: 0 | X36: 0 | AK36: 0 | AM36: =SUM(G36:AJ36) -> 0
D37: RBDPO Brand Consume | F37: Kg | G37: =G38+G39 -> 0 | H37: =H38+H39 -> 0 | I37: =I38+I39 -> 0 | J37: =J38+J39 -> 0 | K37: =K38+K39 -> 0 | L37: =L38+L39 -> 0 | M37: =M38+M39 -> 0 | N37: =N38+N39 -> 0 | ... AK37: =AK38+AK39 -> 0 | AM37: =SUM(G37:AJ37) -> 40950
D38: OLEIN IV 57 Low Color | F38: Kg | G38: 0 | H38: 0 | I38: 0 | J38: 0 | K38: 0 | L38: 0 | M38: 0 | N38: 0 | O38: 0 | P38: 0 | Q38: 0 | R38: 0 | S38: 0 | T38: 0 | U38: 0 | V38: 0 | W38: 0 | X38: 0 | Y38: 30800 | Z38: 0 | AA38: 0 | AB38: 0 | AC38: 0 | AD38: 0 | AE38: 0 | AF38: 0 | AG38: 0 | AH38: 0 | AI38: 0 | AJ38: 0 | AM38: =SUM(G38:AJ38) -> 30800
D39: STEARIN | F39: Kg | G39: 0 | H39: 0 | I39: 0 | J39: 0 | K39: 0 | L39: 0 | M39: 0 | N39: 0 | O39: 0 | P39: 0 | Q39: 0 | R39: 0 | S39: 0 | T39: 0 | U39: 0 | V39: 0 | W39: 0 | X39: 0 | Y39: 10150 | Z39: 0 | AA39: 0 | AB39: 0 | AC39: 0 | AD39: 0 | AE39: 0 | AF39: 0 | AG39: 0 | AH39: 0 | AI39: 0 | AJ39: 0 | AM39: =SUM(G39:AJ39) -> 10150
D40: Fractionation OLEIN IV 58 | AM40: Olein IV 58 ( Bulk )
D41: RBDPO Consume | E41: =E42+E43 -> 21429000 | F41: Kg | G41: =G42+G43 -> 921143 | H41: =H42+H43 -> 250811 | I41: =I42+I43 -> 519670 | J41: =J42+J43 -> 738041 | K41: =K42+K43 -> 533278 | L41: =L42+L43 -> 570133 | M41: =M42+M43 -> 638607 | N41: =N42+N43 -> 813834 | ... AK41: =AK42+AK43 -> 0 | AM41: =SUM(G41:AK41) -> 6581530
D42: OLEIN IV 58 | E42: 15000000 | F42: Kg | G42: ='[1]01'!$P$22 -> 668457 | H42: ='[2]02'!$P$22 -> 169785 | I42: ='[3]03'!$P$23 -> 392392 | J42: ='[4]04'!$P$22 -> 521490 | K42: ='[5]05'!$P$22 -> 374594 | L42: ='[6]06'!$P$22 -> 411892 | M42: ='[7]07'!$P$22 -> 464613 | N42: ='[7]08'!$P$22 -> 604158 | O42: ='[6]09'!$P$22 -> 117352 | P42: 0 | Q42: 0 | R42: 0 | S42: 0 | T42: 0 | U42: 0 | V42: 0 | W42: 0 | X42: 0 | Y42: 0 | Z42: 0 | AA42: 0 | AB42: 0 | AC42: 0 | AD42: 0 | AE42: 0 | AF42: 0 | AG42: 0 | AH42: 0 | AI42: 215238 | AJ42: ='[14]30 (Stock Opname)'!$P$22+71400 -> 848627 | AK42: 0 | AM42: =SUM(G42:AK42) -> 4788598
D43: STEARIN | E43: 6429000 | F43: Kg | G43: ='[1]01'!$P$29 -> 252686 | H43: ='[2]02'!$P$30 -> 81026 | I43: ='[3]03'!$P$30 -> 127278 | J43: ='[4]04'!$P$30 -> 216551 | K43: ='[5]05'!$P$30-K30 -> 158684 | L43: ='[6]06'!$P$30 -> 158241 | M43: ='[7]07'!$P$30 -> 173994 | N43: ='[7]08'!$P$30 -> 209676 | O43: 37047 | P43: 0 | Q43: 0 | R43: 0 | S43: 0 | T43: 0 | U43: 0 | V43: 0 | W43: ='[13]17'!$P$30 -> 5569 | X43: 0 | Y43: 0 | Z43: 0 | AA43: 0 | AB43: 0 | AC43: 0 | AD43: 0 | AE43: 0 | AF43: 0 | AG43: 0 | AH43: 0 | AI43: =217365-AI30 -> 67315 | AJ43: ='[14]30 (Stock Opname)'!$P$30 -> 304865 | AK43: 0 | AM43: =SUM(G43:AK43) -> 1792932
D44: Fractionation OLEIN IV 60 | AM44: Olein IV 60
D45: CPO Consume | F45: Kg | G45: 0 | H45: 0 | I45: 0 | J45: 0 | K45: 0 | L45: 0 | M45: 0 | N45: 0 | O45: 0 | P45: 0 | Q45: 0 | R45: 0 | AM45: =SUM(G45:AK45) -> 0
D46: RBDPO Brand Consume | F46: Kg | G46: =G48+G49 -> 0 | H46: =H48+H49 -> 0 | I46: =I48+I49 -> 0 | J46: =J48+J49 -> 0 | K46: =K48+K49 -> 0 | L46: =L48+L49 -> 0 | M46: =M48+M49 -> 0 | N46: =N48+N49 -> 0 | ... AK46: =AK48+AK49 -> 0 | AM46: =SUM(G46:AK46) -> 0
D47: OLEIN IV 60 Bulk | F47: Kg | G47: 0 | H47: 0 | I47: 0 | J47: 0 | K47: 0 | L47: 0 | M47: 0 | N47: 0 | O47: 0 | P47: 0 | Q47: 0 | R47: 0 | S47: 0 | T47: 0 | U47: 0 | V47: 0 | W47: 0 | X47: 0 | Y47: 0 | Z47: 0 | AA47: 0 | AB47: 0 | AC47: 0 | AD47: 0 | AE47: 0 | AF47: 0 | AG47: 0 | AH47: 0 | AI47: 0 | AJ47: 0 | AK47: 0 | AM47: =SUM(G47:AK47) -> 0
D48: OLEIN IV 60 Salvaco | F48: Kg | G48: 0 | H48: 0 | I48: 0 | J48: 0 | K48: 0 | L48: 0 | M48: 0 | N48: 0 | O48: 0 | P48: 0 | Q48: 0 | R48: 0 | S48: 0 | T48: 0 | U48: 0 | V48: 0 | W48: 0 | X48: 0 | Y48: 0 | Z48: 0 | AA48: 0 | AB48: 0 | AC48: 0 | AD48: 0 | AE48: 0 | AF48: 0 | AG48: 0 | AH48: 0 | AI48: 0 | AJ48: 0 | AK48: 0 | AM48: =SUM(G48:AK48) -> 0
D49: SOFT STEARIN | F49: Kg | G49: 0 | H49: 0 | I49: 0 | J49: 0 | K49: 0 | L49: 0 | M49: 0 | N49: 0 | O49: 0 | P49: 0 | Q49: 0 | R49: 0 | S49: 0 | T49: 0 | U49: 0 | V49: 0 | W49: 0 | X49: 0 | Y49: 0 | Z49: 0 | AA49: 0 | AB49: 0 | AC49: 0 | AD49: 0 | AE49: 0 | AF49: 0 | AG49: 0 | AH49: 0 | AI49: 0 | AJ49: 0 | AK49: 0 | AM49: =SUM(G49:AK49) -> 0
D50: Ratio Run RBDPO | F50: % | G50: 0 | H50: 0 | I50: 0 | J50: 0 | K50: 0 | L50: 0 | M50: 0 | N50: 0 | O50: 0 | P50: 0 | Q50: 0 | R50: 0 | S50: 0 | T50: 0 | U50: 0 | V50: 0 | W50: 0 | X50: 0 | Y50: 0 | Z50: 0 | AA50: 0 | AB50: 0 | AC50: 0 | AD50: 0 | AE50: 0 | AF50: 0 | AG50: 0 | AH50: 0 | AI50: 0 | AJ50: 0 | AM50: =SUM(G50:AK50) -> 0
D51: YIELD | AM51: Yield
D52: RBDPO | E52: 94.2 | F52: % | G52: =(G18/(G9))*100 -> 88.58558 | H52: =(H18/(H9))*100 -> 94.045144 | I52: =(I18/(I9))*100 -> 96.78638 | J52: =(J18/(J9))*100 -> 94.918437 | K52: =(K18/(K9))*100 -> 95.770418 | L52: =(L18/(L9))*100 -> 93.492589 | M52: =(M18/(M9))*100 -> 95.324948 | N52: =(N18/(N9))*100 -> 94.381362 | ... AK52: =(AK18/(AK9))*100 -> #DIV/0! | AM52: =(AM18/(AM9))*100 -> 94.748466
D53: PFAD | E53: 5 | F53: % | G53: =(G19/(G9))*100 -> 5.5016848 | H53: =(H19/(H9))*100 -> 3.9051119 | I53: =(I19/(I9))*100 -> 4.1860296 | J53: =(J19/(J9))*100 -> 3.9978906 | K53: =(K19/(K9))*100 -> 4.0700406 | L53: =(L19/(L9))*100 -> 3.7930962 | M53: =(M19/(M9))*100 -> 4.2431595 | N53: =(N19/(N9))*100 -> 4.3374754 | ... AK53: =(AK19/(AK9))*100 -> #DIV/0! | AM53: =(AM19/(AM9))*100 -> 4.1524826
D54: Olein IV 56 | E54: 82 | F54: % | G54: =G29/(G29+G30)*100 -> #DIV/0! | H54: =H29/(H29+H30)*100 -> #DIV/0! | I54: =I29/(I29+I30)*100 -> #DIV/0! | J54: =J29/(J29+J30)*100 -> #DIV/0! | K54: =K29/(K29+K30)*100 -> 85.416068 | L54: =L29/(L29+L30)*100 -> #DIV/0! | M54: =M29/(M29+M30)*100 -> #DIV/0! | N54: =N29/(N29+N30)*100 -> #DIV/0! | ... AK54: =AK29/(AK29+AK30)*100 -> #DIV/0! | AM54: =AM29/(AM29+AM30)*100 -> 83.238811
D55: Stearin | E55: 18 | F55: % | G55: =(G32/G30)*100 -> #DIV/0! | H55: =(H32/H30)*100 -> #DIV/0! | I55: =(I32/I30)*100 -> #DIV/0! | J55: =(J32/J30)*100 -> #DIV/0! | K55: =(K30/K28)*100 -> 14.583932 | O55: =(O30/O28)*100 -> 16.072508 | P55: =(P30/P28)*100 -> 18.325911 | Q55: =(Q30/Q28)*100 -> 16.184224 | R55: =(R30/R28)*100 -> 18.063057 | S55: =(S30/S28)*100 -> 17.845409 | T55: =(T30/T28)*100 -> 17.05746 | U55: =(U30/U28)*100 -> 15.209035 | V55: =(V30/V28)*100 -> 17.773767 | ... AJ55: =(AJ30/AJ28)*100 -> #DIV/0! | AK55: =AK30/(AK29+AK30)*100 -> #DIV/0! | AM55: =AM30/(AM29+AM30)*100 -> 16.761189
D56: Olein IV 57 ( Bulk ) | E56: 75 | G56: =(G33/G32)*100 -> #DIV/0! | H56: =(H33/H32)*100 -> #DIV/0! | I56: =(I33/I32)*100 -> #DIV/0! | J56: =(J33/J32)*100 -> #DIV/0! | K56: =(K33/K32)*100 -> #DIV/0! | L56: =(L33/L32)*100 -> #DIV/0! | M56: =(M33/M32)*100 -> #DIV/0! | N56: =(N33/N32)*100 -> #DIV/0! | ... AK56: =(AK33/AK32)*100 -> #DIV/0! | AM56: =(AM38/AM37)*100 -> 75.213675
D57: Stearin | E57: 25 | G57: =(G34/G32)*100 -> #DIV/0! | H57: =(H34/H32)*100 -> #DIV/0! | I57: =(I34/I32)*100 -> #DIV/0! | J57: =(J34/J32)*100 -> #DIV/0! | K57: =(K34/K32)*100 -> #DIV/0! | L57: =(L34/L32)*100 -> #DIV/0! | M57: =(M34/M32)*100 -> #DIV/0! | N57: =(N34/N32)*100 -> #DIV/0! | ... AK57: =(AK34/AK32)*100 -> #DIV/0! | AM57: =(AM39/AM37)*100 -> 24.786325
D58: Olein IV 57 ( Retail ) | E58: 75 | F58: % | G58: =G38/G37*100 -> #DIV/0! | H58: =H38/H37*100 -> #DIV/0! | I58: =I38/I37*100 -> #DIV/0! | J58: =J38/J37*100 -> #DIV/0! | K58: =K38/K37*100 -> #DIV/0! | L58: =L38/L37*100 -> #DIV/0! | M58: =M38/M37*100 -> #DIV/0! | N58: =N38/N37*100 -> #DIV/0! | ... AK58: =AK38/AK37*100 -> #DIV/0! | AM58: =AM38/AM37*100 -> 75.213675
D59: Stearin | E59: 25 | F59: % | G59: =G39/G37*100 -> #DIV/0! | H59: =H39/H37*100 -> #DIV/0! | I59: =I39/I37*100 -> #DIV/0! | J59: =J39/J37*100 -> #DIV/0! | K59: =K39/K37*100 -> #DIV/0! | L59: =L39/L37*100 -> #DIV/0! | M59: =M39/M37*100 -> #DIV/0! | N59: =N39/N37*100 -> #DIV/0! | ... AK59: =AK39/AK37*100 -> #DIV/0! | AM59: =AM39/AM37*100 -> 24.786325
D60: Olein IV 58 ( Bulk ) | E60: 70 | F60: % | G60: =G42/(G42+G43)*100 -> 72.568211 | H60: =H42/(H42+H43)*100 -> 67.694399 | I60: =I42/(I42+I43)*100 -> 75.507918 | J60: =J42/(J42+J43)*100 -> 70.658676 | K60: =K42/(K42+K43)*100 -> 70.243663 | L60: =L42/(L42+L43)*100 -> 72.244897 | M60: =M42/(M42+M43)*100 -> 72.754135 | N60: =N42/(N42+N43)*100 -> 74.236024 | ... AJ60: =AJ42/(AJ42+AJ43)*100 -> 73.570254 | AK60: =AK42/AK41*100 -> #DIV/0! | AM60: =AM42/(AM42+AM43)*100 -> 72.758128
D61: Stearin | E61: 30 | F61: % | G61: =G43/(G43+G42)*100 -> 27.431789 | H61: =H43/(H43+H42)*100 -> 32.305601 | I61: =I43/(I43+I42)*100 -> 24.492082 | J61: =J43/(J43+J42)*100 -> 29.341324 | K61: =K43/(K43+K42)*100 -> 29.756337 | L61: =L43/(L43+L42)*100 -> 27.755103 | M61: =M43/(M43+M42)*100 -> 27.245865 | N61: =N43/(N43+N42)*100 -> 25.763976 | ... AJ61: =AJ43/(AJ43+AJ42)*100 -> 26.429746 | AK61: =AK43/AK41*100 -> #DIV/0! | AM61: =AM43/AM41*100 -> 27.241872
D62: Olein IV 60 | E62: 60 | F62: % | G62: =G47/G46*100 -> #DIV/0! | H62: =H47/H46*100 -> #DIV/0! | I62: =I47/I46*100 -> #DIV/0! | J62: =J47/J46*100 -> #DIV/0! | K62: =K47/K46*100 -> #DIV/0! | L62: =L47/L46*100 -> #DIV/0! | M62: =M47/M46*100 -> #DIV/0! | N62: =N47/N46*100 -> #DIV/0! | ... AK62: =AK47/AK46*100 -> #DIV/0! | AM62: =(AM48+AM47)/AM46*100 -> #DIV/0!
D63: Soft Stearin | E63: 40 | F63: % | G63: =G49/G46*100 -> #DIV/0! | H63: =H49/H46*100 -> #DIV/0! | I63: =I49/I46*100 -> #DIV/0! | J63: =J49/J46*100 -> #DIV/0! | K63: =K49/K46*100 -> #DIV/0! | L63: =L49/L46*100 -> #DIV/0! | M63: =M49/M46*100 -> #DIV/0! | N63: =N49/N46*100 -> #DIV/0! | ... AK63: =AK49/AK46*100 -> #DIV/0! | AM63: =AM49/AM46*100 -> #DIV/0!
C64: 2 | D64: CHEMICAL CONSUMABLE | AM64: Chemical
D65: Bleaching Earth (BE) to Poram Spec | E65: 8 | F65: Kg | G65: 3762 | H65: 2459 | I65: 9966 | J65: 5601 | K65: 4735 | L65: 5264 | M65: 5082 | N65: 2855 | O65: 8216 | P65: 8077 | Q65: 8300 | R65: 5470 | S65: 4586 | T65: 4497 | U65: 12333 | V65: 0 | W65: 3391 | X65: 8060 | Y65: 9010 | Z65: 5931 | AA65: 5907 | AB65: 297 | AC65: 0 | AD65: 0 | AE65: 6213 | AF65: 13100 | AG65: 13498 | AH65: 14923 | AI65: 12218 | AJ65: 3762 | AM65: =SUM(G65:AK65) -> 187513
F66: % | G66: =G65/(G11)*100 -> 1.1565989 | H66: =H65/(H11)*100 -> 1.0062528 | I66: =I65/(I11)*100 -> 0.88148354 | J66: =J65/(J11)*100 -> 0.8159228 | K66: =K65/(K11)*100 -> 0.77799211 | L66: =L65/(L11)*100 -> 0.79466919 | M66: =M65/(M11)*100 -> 0.82982132 | N66: =N65/(N11)*100 -> 0.73878369 | ... AK66: =AK65/(AK11)*100 -> #DIV/0! | AM66: =AM65/(AM11)*100 -> 0.77980013 | AN66: =AM66*10 -> 7.7980013 | BH66: #DIV/0! | BI66: #DIV/0!
D67: Bleaching Earth (BE) to Branded Spec | E67: 18 | F67: Kg | G67: 0 | H67: 0 | I67: 0 | J67: 0 | K67: 0 | L67: 0 | M67: 0 | N67: 0 | O67: 0 | P67: 0 | Q67: 0 | R67: 0 | S67: 0 | T67: 0 | U67: 0 | V67: 0 | W67: 0 | X67: 0 | Y67: 0 | Z67: 0 | AA67: 0 | AB67: 0 | AC67: 0 | AK67: 0 | AM67: =SUM(G67:AK67) -> 0
F68: % | G68: =G67/(G12)*100 -> #DIV/0! | H68: =H67/(H12)*100 -> #DIV/0! | I68: =I67/(I12)*100 -> #DIV/0! | J68: =J67/(J12)*100 -> #DIV/0! | K68: =K67/(K12)*100 -> #DIV/0! | L68: =L67/(L12)*100 -> #DIV/0! | M68: =M67/(#REF!)*100 -> #REF! | N68: =N67/(#REF!)*100 -> #REF! | O68: =O67/(O12)*100 -> #DIV/0! | P68: =P67/(P12)*100 -> #DIV/0! | Q68: =Q67/(Q12)*100 -> #DIV/0! | R68: =R67/(R12)*100 -> #DIV/0! | S68: =S67/(S12)*100 -> #DIV/0! | T68: =T67/(T12)*100 -> #DIV/0! | U68: =U67/(U12)*100 -> #DIV/0! | V68: =V67/(V12)*100 -> #DIV/0! | ... AK68: =AK67/(AK12)*100 -> #DIV/0! | AM68: =AM67/(AM12)*100 -> #DIV/0!
D69: Phosporic Acid (PA) | E69: 0.6 | F69: Kg | G69: 170.236 | H69: 121.26 | I69: 580.668 | J69: 343.97 | K69: 301.994 | L69: 331.144 | M69: 325.32 | N69: 194.722 | O69: 546.854 | P69: 571.34 | Q69: 567.842 | R69: 369.622 | S69: 290.334 | T69: 300.828 | U69: 845.35 | V69: 0 | W69: 229.702 | X69: 576.004 | Y69: 745.074 | Z69: 496.716 | AA69: 447.744 | AB69: 20.988 | AC69: 0 | AD69: 0 | AE69: 488.554 | AF69: 817.366 | AG69: 825.528 | AH69: 876.832 | AI69: 815.036 | AJ69: 298.49 | AM69: =SUM(G69:AK69) -> 12499.518
F70: % | G70: =G69/(G9)*100 -> 0.052337793 | H70: =H69/(H9)*100 -> 0.04962107 | I70: =I69/(I9)*100 -> 0.051359551 | J70: =J69/(J9)*100 -> 0.050107653 | K70: =K69/(K9)*100 -> 0.04961963 | L70: =L69/(L9)*100 -> 0.049990489 | M70: =M69/(M9)*100 -> 0.053120321 | N70: =N69/(N9)*100 -> 0.050387894 | ... AK70: =AK69/(AK9)*100 -> #DIV/0! | AM70: =AM69/(AM9)*100 -> 0.051981067 | AN70: =AM70*10 -> 0.51981067
C71: 3 | D71: OIL LOSSES | E71: 0.8 | F71: % | G71: =((SUM(G18:G19))-(SUM(G9)))/(SUM(G9))*100 -> -5.9127355 | H71: =((SUM(H18:H19))-(SUM(H9)))/(SUM(H9))*100 -> -2.0497438 | I71: =((SUM(I18:I19))-(SUM(I9)))/(SUM(I9))*100 -> 0.97240919 | J71: =((SUM(J18:J19))-(SUM(J9)))/(SUM(J9))*100 -> -1.0836725 | K71: =((SUM(K18:K19))-(SUM(K9)))/(SUM(K9))*100 -> -0.15954178 | L71: =((SUM(L18:L19))-(SUM(L9)))/(SUM(L9))*100 -> -2.7143146 | M71: =((SUM(M18:M19))-(SUM(M9)))/(SUM(M9))*100 -> -0.43189244 | N71: =((SUM(N18:N19))-(SUM(N9)))/(SUM(N9))*100 -> -1.2811622 | ... AK71: =((SUM(AK18:AK19))-(SUM(AK9)))/(SUM(AK9))*100 -> #DIV/0! | AM71: =((SUM(AM18:AM19))-(SUM(AM9)))/(SUM(AM9))*100 -> -1.099051
F72: Kg | G72: =G71%*G9 -> -19232 | H72: =H71%*H9 -> -5009 | I72: =I71%*I9 -> 10994 | J72: =J71%*J9 -> -7439 | K72: =K71%*K9 -> -971 | L72: =L71%*L9 -> -17980 | M72: =M71%*M9 -> -2645 | N72: =N71%*N9 -> -4951 | ... AK72: =AK71%*AK9 -> #DIV/0! | AM72: =AM71%*AM9 -> -264281
D73: % Oil Content | E73: 22 | F73: % | G73: 22.18 | H73: 22.23 | I73: 22.19 | J73: 22.2 | K73: 22.09 | L73: 22.13 | M73: 22.07 | N73: 22.09 | O73: 22.08 | P73: 22.09 | Q73: 22.03 | R73: 22 | S73: 22.02 | T73: 22.04 | U73: 22.05 | V73: 0 | W73: 22.02 | X73: 22.07 | Y73: 21.96 | Z73: 22.01 | AA73: 22.07 | AB73: 22.01 | AC73: 0 | AD73: 0 | AE73: 22.08 | AF73: 22 | AG73: 21.97 | AH73: 21.95 | AI73: 21.95 | AJ73: 21.99 | AM73: =SUM(G73:AJ73)/AM6 -> 22.058148
D74: Spent Bleaching Earth | F74: Kg | G74: =SUM(G65,G67)+(G73%*SUM(G65,G67)) -> 4596.4116 | H74: =SUM(H65,H67)+(H73%*SUM(H65,H67)) -> 3005.6357 | I74: =SUM(I65,I67)+(I73%*SUM(I65,I67)) -> 12177.455 | J74: =SUM(J65,J67)+(J73%*SUM(J65,J67)) -> 6844.422 | K74: =SUM(K65,K67)+(K73%*SUM(K65,K67)) -> 5780.9615 | L74: =SUM(L65,L67)+(L73%*SUM(L65,L67)) -> 6428.9232 | M74: =SUM(M65,M67)+(M73%*SUM(M65,M67)) -> 6203.5974 | N74: =SUM(N65,N67)+(N73%*SUM(N65,N67)) -> 3485.6695 | ... AK74: =SUM(AK65,AK67)+(AK73%*SUM(AK65,AK67)) -> 0 | AM74: =SUM(AM65,AM67)+(AM73%*SUM(AM65,AM67))/AM6 -> 189044.92
C75: 4 | D75: PACKAGING (Brand Salvaco) | AM75: Packaging
D76: Olein IV 60 Received | F76: Kg | AM76: 0
D77: Olein IV 60 Consume | F77: Kg | AM77: 0
D78: - finished product | F78: Kg | G78: 0 | H78: 0 | I78: 0 | J78: 0 | K78: 0 | L78: 0 | M78: 0 | N78: 0 | O78: 0 | P78: 0 | Q78: 0 | R78: 0 | S78: 0 | T78: 0 | U78: 0 | V78: 0 | W78: 0 | X78: 0 | Y78: 0 | Z78: 0 | AA78: 0 | AB78: 0 | AC78: 0 | AD78: 0 | AE78: 0 | AF78: 0 | AG78: 0 | AH78: 0 | AI78: 0 | AJ78: 0 | AK78: 0 | AM78: 0
D79: - sample | F79: Kg | G79: 0 | H79: 0 | I79: 0 | J79: 0 | K79: 0 | L79: 0 | M79: 0 | N79: 0 | O79: 0 | P79: 0 | Q79: 0 | R79: 0 | S79: 0 | T79: 0 | U79: 0 | V79: 0 | W79: 0 | X79: 0 | Y79: 0 | Z79: 0 | AA79: 0 | AB79: 0 | AC79: 0 | AD79: 0 | AE79: 0 | AF79: 0 | AG79: 0 | AH79: 0 | AI79: 0 | AJ79: 0 | AK79: 0 | AM79: 0
D80: - remelt, flushing, downgrade | F80: Kg | G80: 0 | H80: 0 | I80: 0 | J80: 0 | K80: 0 | L80: 0 | M80: 0 | N80: 0 | O80: 0 | P80: 0 | Q80: 0 | R80: 0 | S80: 0 | T80: 0 | U80: 0 | V80: 0 | W80: 0 | X80: 0 | Y80: 0 | Z80: 0 | AA80: 0 | AB80: 0 | AC80: 0 | AD80: 0 | AE80: 0 | AF80: 0 | AG80: 0 | AH80: 0 | AI80: 0 | AJ80: 0 | AK80: 0 | AM80: 0
D81: Carton | AM81: Carton
D82: Salvaco 1 Liter | F82: Box | AM82: 0
D83: Salvaco 2 Liter | F83: Box | AM83: 0
D84: Pouch | AM84: Pouch
D85: Salvaco 1 Liter | F85: Pouch | G85: 0 | H85: 0 | I85: 0 | J85: 0 | K85: 0 | L85: 0 | M85: 0 | N85: 0 | O85: 0 | P85: 0 | Q85: 0 | R85: 0 | S85: 0 | T85: 0 | U85: 0 | V85: 0 | W85: 0 | X85: 0 | Y85: 0 | Z85: 0 | AA85: 0 | AB85: 0 | AC85: 0 | AD85: 0 | AE85: 0 | AF85: 0 | AG85: 0 | AH85: 0 | AI85: 0 | AJ85: 0 | AK85: 0 | AM85: 0
D86: Salvaco 2 Liter | F86: Pouch | G86: 0 | H86: 0 | I86: 0 | J86: 0 | K86: 0 | L86: 0 | M86: 0 | N86: 0 | O86: 0 | P86: 0 | Q86: 0 | R86: 0 | S86: 0 | T86: 0 | U86: 0 | V86: 0 | W86: 0 | X86: 0 | Y86: 0 | Z86: 0 | AA86: 0 | AB86: 0 | AC86: 0 | AD86: 0 | AE86: 0 | AF86: 0 | AG86: 0 | AH86: 0 | AI86: 0 | AJ86: 0 | AK86: 0 | AM86: 0
D87: Consumable Vit. A | F87: gram | G87: 0 | H87: 0 | I87: 0 | J87: 0 | K87: 0 | L87: 0 | M87: 0 | N87: 0 | O87: 0 | P87: 0 | Q87: 0 | R87: 0 | S87: 0 | T87: 0 | U87: 0 | V87: 0 | W87: 0 | X87: 0 | Y87: 0 | Z87: 0 | AA87: 0 | AB87: 0 | AC87: 0 | AD87: 0 | AE87: 0 | AF87: 0 | AG87: 0 | AH87: 0 | AI87: 0 | AJ87: 0 | AK87: 0 | AM87: 0
D88: Consumable Packing Tape | F88: Roll | G88: 0 | H88: 0 | I88: 0 | J88: 0 | K88: 0 | L88: 0 | M88: 0 | N88: 0 | O88: 0 | P88: 0 | Q88: 0 | R88: 0 | S88: 0 | T88: 0 | U88: 0 | V88: 0 | W88: 0 | X88: 0 | Y88: 0 | Z88: 0 | AA88: 0 | AB88: 0 | AC88: 0 | AD88: 0 | AE88: 0 | AF88: 0 | AG88: 0 | AH88: 0 | AI88: 0 | AJ88: 0 | AK88: 0 | AM88: 0
D89: REJECT MATERIAL QTY | AM89: Loss Material
D90: Carton | AM90: Carton
D91: Salvaco 1 Liter | F91: Box | AM91: 0
D92: Salvaco 2 Liter | F92: Box | AM92: 0
D93: Pouch | AM93: Pouch
D94: Salvaco 1 Liter | F94: Pouch | G94: 0 | H94: 0 | I94: 0 | J94: 0 | K94: 0 | L94: 0 | M94: 0 | N94: 0 | O94: 0 | P94: 0 | Q94: 0 | R94: 0 | S94: 0 | T94: 0 | U94: 0 | V94: 0 | W94: 0 | X94: 0 | Y94: 0 | Z94: 0 | AA94: 0 | AB94: 0 | AC94: 0 | AD94: 0 | AE94: 0 | AF94: 0 | AG94: 0 | AH94: 0 | AI94: 0 | AJ94: 0 | AK94: 0 | AM94: 0
D95: Salvaco 2 Liter | F95: Pouch | G95: 0 | H95: 0 | I95: 0 | J95: 0 | K95: 0 | L95: 0 | M95: 0 | N95: 0 | O95: 0 | P95: 0 | Q95: 0 | R95: 0 | S95: 0 | T95: 0 | U95: 0 | V95: 0 | W95: 0 | X95: 0 | Y95: 0 | Z95: 0 | AA95: 0 | AB95: 0 | AC95: 0 | AD95: 0 | AE95: 0 | AF95: 0 | AG95: 0 | AH95: 0 | AI95: 0 | AJ95: 0 | AK95: 0 | AM95: 0
D96: REJECT MATERIAL (%) | AM96: Loss Material
D97: Carton | AM97: Carton
D98: Salvaco 1 Liter | E98: 0.3 | F98: % | G98: #DIV/0! | H98: #DIV/0! | I98: #DIV/0! | J98: #DIV/0! | K98: #DIV/0! | L98: #DIV/0! | M98: #DIV/0! | N98: #DIV/0! | O98: #DIV/0! | P98: #DIV/0! | Q98: #DIV/0! | R98: #DIV/0! | S98: #DIV/0! | T98: #DIV/0! | U98: #DIV/0! | V98: #DIV/0! | W98: #DIV/0! | X98: #DIV/0! | Y98: #DIV/0! | Z98: #DIV/0! | AA98: #DIV/0! | AB98: #DIV/0! | AC98: #DIV/0! | AD98: #DIV/0! | AE98: #DIV/0! | AF98: #DIV/0! | AG98: #DIV/0! | AH98: #DIV/0! | AI98: #DIV/0! | AJ98: #DIV/0! | AK98: #DIV/0! | AM98: #DIV/0!
D99: Salvaco 2 Liter | E99: 0.3 | F99: % | G99: #DIV/0! | H99: #DIV/0! | I99: #DIV/0! | J99: #DIV/0! | K99: #DIV/0! | L99: #DIV/0! | M99: #DIV/0! | N99: #DIV/0! | O99: #DIV/0! | P99: #DIV/0! | Q99: #DIV/0! | R99: #DIV/0! | S99: #DIV/0! | T99: #DIV/0! | U99: #DIV/0! | V99: #DIV/0! | W99: #DIV/0! | X99: #DIV/0! | Y99: #DIV/0! | Z99: #DIV/0! | AA99: #DIV/0! | AB99: #DIV/0! | AC99: #DIV/0! | AD99: #DIV/0! | AE99: #DIV/0! | AF99: #DIV/0! | AG99: #DIV/0! | AH99: #DIV/0! | AI99: #DIV/0! | AJ99: #DIV/0! | AK99: #DIV/0! | AM99: #DIV/0!
D100: Pouch | AM100: Pouch
...

Sheet SUMMARY HPP 
B2: Production Cost September
B3: Through Put CPO Proses (Ton/Day) | H3: TPD | I3: ='HPP REF '!$N$3 -> 890.60333
B4: Working Day | F4: 1 | H4: Days | I4: ='HPP REF '!$N$4 -> 27
B5: Refined CPO ( Ton/month ) | H5: MTD | I5: =$I$4*$I$3 -> 24046.29
B6: Through Put RPO Proses (Ton/Day) | H6: TPD | I6: ='HPP FRACT'!$O$3 -> 836.77663
B7: Working Day | H7: Days | I7: ='HPP FRACT'!$O$4 -> 27
B8: Fract RPO ( ton/month ) | H8: MTD | I8: =$I$7*$I$6 -> 22592.969
B9: KURS | H9: Rp/USD | I9: 16000
B10: No | C10: Items | D10: Description | G10: Rupiah | H10: Rp/Kg | I10: USD/MT
B11: I | C11: Production Cost | D11: ● | E11: Refining Cost | G11: ='HPP REF '!$M$48 -> 4.7511346e+09 | H11: =$G$11/($I$5*1000) -> 197.58285 | I11: =(G11/$I$9)/$I$5 -> 12.348928
D12: ● | E12: Fractionation Cost | G12: ='HPP FRACT'!$M$22 -> 1.0424867e+09 | H12: =$G$12/($I$8*1000) -> 46.142086 | I12: =(G12/$I$9)/$I$8 -> 2.8838804
D13: ● | E13: Preventive Maintenance Cost | F13: 1 | G13: =MTC!$F$18 -> 7.1038385e+08 | H13: =$G$13/($I$5*1000) -> 29.542347 | I13: =(G13/$I$9)/$I$5 -> 1.8463967
G14: =SUM(G11:$G$13) -> 6.5040051e+09 | H14: =SUM($H$11:$H$13) -> 273.26729 | I14: =SUM(I11:I13) -> 17.079205
B16: II | C16: Port Cost | D16: ● | E16: Trucking Komoditi ke Kuala Tanjung | G16: =LOG!I8+LOG!I9+LOG!$I$10 -> 2.496582e+09 | H16: =$G$16/($I$5*1000) -> 103.824 | I16: =($G$16/$I$9)/$I$5 -> 6.489
D17: ● | E17: Sewa Tank PTI Total Volume : 24.000 MT ( 5 Unit ) | F17: 1 | G17: =LOG!I11+LOG!I12+LOG!I13+LOG!$I$14 -> 1886000000 | H17: =$G$17/($I$5*1000) -> 78.432058 | I17: =($G$17/$I$9)/$I$5 -> 4.9020036
D18: ● | E18: Instalasi & Pemanasan, Pompa, Surveyor dan Documen | G18: =LOG!I18+LOG!I19+LOG!I20+LOG!$I$21 -> 1.2881117e+09 | H18: =$G$18/($I$5*1000) -> 53.568 | I18: =($G$18/$I$9)/$I$5 -> 3.348
D19: ● | E19: Finalty Over Capacity Tank | G19: =LOG!I15+LOG!I16+LOG!$I$17 -> 6.8171855e+08 | H19: =$G$19/($I$5*1000) -> 28.350259 | I19: =($G$19/$I$9)/$I$5 -> 1.7718912
G20: =SUM($G$16:$G$19) -> 6.3524122e+09 | H20: =SUM($H$16:$H$19) -> 264.17432 | I20: =SUM($I$16:$I$19) -> 16.510895
B22: II | C22: Fix Cost | D22: ● | E22: Manpower Cost | F22: =F4 -> 1 | G22: =[20]MPC!$H$29*$F$22 -> 2.1846655e+09 | H22: =$G$22/($I$5*1000) -> 90.852499 | I22: =($G$22/$I$9)/$I$5 -> 5.6782812
D23: ● | E23: Admin OH Cost | F23: =F4 -> 1 | G23: =OH!G51*$F$23 -> 1.4360564e+09 | H23: =$G$23/($I$5*1000) -> 59.720497 | I23: =($G$23/$I$9)/$I$5 -> 3.7325311
D24: ● | E24: Depresiasi Cost | F24: =F4 -> 1 | G24: =DEP!I9*$F$24 -> 4.1811848e+09 | H24: =$G$24/($I$5*1000) -> 173.88066 | I24: =($G$24/$I$9)/$I$5 -> 10.867541
D25: ● | E25: Amortisation of leasehold land Cost | F25: =F4 -> 1 | G25: =AMOR!$G$20*$F$25 -> 1.0484098e+09 | H25: =$G$25/($I$5*1000) -> 43.599649 | I25: =($G$25/$I$9)/$I$5 -> 2.7249781
G26: =SUM($G$22:$G$25) -> 8.8503165e+09 | H26: =SUM($H$22:$H$25) -> 368.05331 | I26: =SUM($I$22:$I$25) -> 23.003332 | K26: =I26+I14 -> 40.082537
B28: Total Production Cost | G28: =$G$26+$G$20+$G$14 -> 2.1706734e+10 | H28: =$H$26+$H$20+$H$14 -> 905.49491 | I28: =$I$26+$I$20+$I$14 -> 56.593432

Sheet HPP REF 
B2: Refinery Cost
B3: Through Put CPO Proses | N3: =('September - 2024'!AM10)/1000 -> 890.60333 | O3: TPD
B4: Working Day | N4: ='September - 2024'!AM6 -> 27 | O4: Days
B5: Total CPO Process | N5: =N4*N3 -> 24046.29 | O5: MTD
B6: KURS | N6: 16000 | O6: Rp/USD
B7: No | C7: Item Cost | D7: Norma | F7: Pemakaian / Hari | H7: HK | J7: Total Pemakaian | K7: Harga / stn | M7: Total Biaya | N7: Rp / kg | O7: USD/MT
B8: 1 | C8: Bleaching Earth | D8: ='September - 2024'!$AM$66 -> 0.77980013 | F8: =($D$8*$N$3*10) -> 6944.9259 | G8: Kg/day | H8: =$N$4 -> 27 | J8: =$H$8*$F$8 -> 187513 | K8: 2400 | M8: =$J$8*$K$8 -> 450031200 | N8: =$M$8/($N$5*1000) -> 18.715203 | O8: =($M$8/$N$6)/$N$5 -> 1.1697002
B9: 2 | C9: Phosporic acid | D9: ='September - 2024'!$AM$70 -> 0.051981067 | F9: =($D$9*$N$3*10) -> 462.94511 | G9: Kg/day | H9: =$H$8 -> 27 | J9: =$H$9*$F$9 -> 12499.518 | K9: 17420 | M9: =$J$9*$K$9 -> 2.177416e+08 | N9: =$M$9/($N$5*1000) -> 9.0551018 | O9: =($M$9/$N$6)/$N$5 -> 0.56594386
B10: 3 | C10: Caustic Soda | D10: 29.166667 | E10: kg/day | F10: =D10 -> 29.166667 | G10: kg/day | H10: =$H$8 -> 27 | J10: =$H$10*$F$10 -> 787.5 | K10: 15700 | M10: =$J$10*$K$10 -> 12363750 | N10: =$M$10/($N$5*1000) -> 0.51416456 | O10: =($M$10/$N$6)/$N$5 -> 0.032135285
B11: 4 | C11: Pemakaian Natural Gas HPB Geka
C12: Normal Consumption | D12: ='September - 2024'!$AM$229 -> 0.24405569 | E12: MMBTU/MT CPO | F12: =$D$12*$N$3 -> 217.35681 | G12: MMBTU/day | H12: =$H$8 -> 27 | J12: =$H$12*$F$12 -> 5868.6339 | K12: =12.7*$N$6 -> 203200 | M12: =$J$12*$K$12 -> 1.1925064e+09 | N12: =$M$12/($N$5*1000) -> 49.592116 | O12: =($M$12/$N$6)/$N$5 -> 3.0995073
C13: Penalty Below Consumption | D13: 0 | E13: MMBTU/MT CPO | F13: =$D$13*$N$3 -> 0 | G13: MMBTU/day | H13: =$H$8 -> 27 | J13: =$H$13*$F$13 -> 0 | K13: =12.7*$N$6 -> 203200 | M13: =$J$13*$K$13 -> 0 | N13: =$M$13/($N$5*1000) -> 0 | O13: =($M$13/$N$6)/$N$5 -> 0
C14: Penalty Above Consumption | D14: 0 | E14: MMBTU/MT CPO | F14: =$D$14*$N$3 -> 0 | G14: MMBTU/day | H14: =$H$8 -> 27 | J14: =$H$14*$F$14 -> 0 | K14: =12.7*$N$6 -> 203200 | M14: =$J$14*$K$14 -> 0 | N14: =$M$14/($N$5*1000) -> 0 | O14: =($M$14/$N$6)/$N$5 -> 0
B15: 5 | C15: Pemakaian Steam
C16: For Process | D16: ='September - 2024'!$AM$236 -> 163.35135 | E16: Kg/MT CPO | F16: =$D$16*$N$3/1000 -> 145.48126 | G16: Ton/day | H16: =$H$8 -> 27 | J16: =$H$16*$F$16 -> 3927.994 | K16: 507006 | M16: =$J$16*$K$16 -> 1.9915165e+09 | N16: =$M$16/($N$5*1000) -> 82.820116 | O16: =($M$16/$N$6)/$N$5 -> 5.1762572
C17: Storage Tank for Heating | D17: 30 | E17: Kg/MT CPO | F17: =$D$17*$N$3/1000 -> 26.7181 | G17: Ton/day | H17: =$H$8 -> 27 | J17: =$H$17*$F$17 -> 721.3887 | K17: 507006 | M17: =$J$17*$K$17 -> 3.657484e+08 | N17: =$M$17/($N$5*1000) -> 15.21018 | O17: =($M$17/$N$6)/$N$5 -> 0.95063625
B18: 6 | C18: Pemakaian Electrical
C19: For Process | D19: ='September - 2024'!$AM$258 -> 3.4001087 | E19: kW/MT CPO | F19: =$D$19*$N$3 -> 3028.1481 | G19: kW/day | H19: =$H$8 -> 27 | I19: 0 | J19: =$H$19*$F$19 -> 81760 | K19: 1550 | L19: =[20]Electric!H21 -> 3666.6667 | M19: =($F$19*$H$19*$K$19)+($F$19*$I$19*$L$19) -> 126728000 | N19: =$M$19/($N$5*1000) -> 5.2701685 | O19: =($M$19/$N$6)/$N$5 -> 0.32938553
C20: Cooling Tower | D20: ='September - 2024'!$AM$260 -> 4.0837901 | E20: kW/MT CPO | F20: =$D$20*$N$3 -> 3637.037 | G20: kW/day | H20: =$H$8 -> 27 | I20: 0 | J20: =$H$20*$F$20 -> 98200 | K20: 1550 | L20: =L19 -> 3666.6667 | M20: =(F20*H20*K20)+(F20*I20*L20) -> 1.5221e+08 | N20: =$M$20/($N$5*1000) -> 6.3298746 | O20: =($M$20/$N$6)/$N$5 -> 0.39561716
C21: Storage Tank | D21: 0.3377877 | E21: kW/MT CPO | F21: =$D$21*$N$3 -> 300.83485 | G21: kW/day | H21: =$H$8 -> 27 | I21: 0 | J21: =$H$21*$F$21 -> 8122.541 | K21: 1550 | L21: =L20 -> 3666.6667 | M21: =($F$21*$H$21*$K$21)+($F$21*$I$21*$L$21) -> 12589938 | N21: =$M$21/($N$5*1000) -> 0.52357093 | O21: =($M$21/$N$6)/$N$5 -> 0.032723183
B22: 7 | C22: Pemakaian Water
C23: Make Up CT | D23: ='September - 2024'!$AM$245 -> 112.24185 | E23: M3/day | F23: =$D$23 -> 112.24185 | G23: M3/day | H23: =$H$8 -> 27 | J23: =$H$23*$F$23 -> 3030.5299 | K23: 8700 | M23: =$J$23*$K$23 -> 26365610 | N23: =$M$23/($N$5*1000) -> 1.0964523 | O23: =($M$23/$N$6)/$N$5 -> 0.068528268
B24: 8 | C24: Chemical Water | N24: =$M$24/($N$5*1000) -> 0 | O24: =($M$24/$N$6)/$N$5 -> 0
C25: EONBAC BC 3108 | D25: 0.4 | E25: Kg/day | F25: =D25 -> 0.4 | G25: Kg/day | H25: =$H$8 -> 27 | J25: =$H$25*$F$25 -> 10.8 | K25: 27240 | M25: =$J$25*$K$25 -> 294192 | N25: =$M$25/($N$5*1000) -> 0.012234403 | O25: =($M$25/$N$6)/$N$5 -> 0.00076465018
C26: EONLINE T722 | D26: 0.66 | E26: Kg/day | F26: =D26 -> 0.66 | G26: Kg/day | H26: =$H$8 -> 27 | J26: =$H$26*$F$26 -> 17.82 | K26: 29120 | M26: =$J$26*$K$26 -> 518918.4 | N26: =$M$26/($N$5*1000) -> 0.021579978 | O26: =($M$26/$N$6)/$N$5 -> 0.0013487486
C27: EONLINE AG5770 | D27: 0.41 | E27: Kg/day | F27: =D27 -> 0.41 | G27: Kg/day | H27: =$H$8 -> 27 | J27: =$H$27*$F$27 -> 11.07 | K27: 117212 | M27: =$J$27*$K$27 -> 1297536.8 | N27: =$M$27/($N$5*1000) -> 0.05395996 | O27: =($M$27/$N$6)/$N$5 -> 0.0033724975
C28: EONScale T2511 | D28: 0.1 | E28: Kg/day | F28: =D28 -> 0.1 | G28: Kg/day | H28: =$H$8 -> 27 | J28: =$H$28*$F$28 -> 2.7 | K28: 45940 | M28: =$J$28*$K$28 -> 124038 | N28: =$M$28/($N$5*1000) -> 0.0051583009 | O28: =($M$28/$N$6)/$N$5 -> 0.00032239381
B29: 9 | C29: Others
C30: Filter Bag 10 Microne | D30: 0.90361446 | E30: Pcs/day | F30: =D30 -> 0.90361446 | G30: Pcs/day | H30: =$H$8 -> 27 | J30: =$H$30*$F$30 -> 24.39759 | K30: 40000 | M30: =$J$30*$K$30 -> 975903.61 | N30: =$M$30/($N$5*1000) -> 0.040584373 | O30: =($M$30/$N$6)/$N$5 -> 0.0025365233
C31: Filter Bag 100 Microne | D31: 0.63253012 | E31: Pcs/day | F31: =D31 -> 0.63253012 | G31: Pcs/day | H31: =$H$8 -> 27 | J31: =$H$31*$F$31 -> 17.078313 | K31: 125000 | M31: =$J$31*$K$31 -> 2134789.2 | N31: =$M$31/($N$5*1000) -> 0.088778317 | O31: =($M$31/$N$6)/$N$5 -> 0.0055486448
C32: Filter Cartridge 10 Microne | D32: 1.5666667 | E32: Pcs/day | F32: =D32 -> 1.5666667 | G32: Pcs/day | H32: =$H$8 -> 27 | J32: =$H$32*$F$32 -> 42.3 | K32: 145000 | M32: =$J$32*$K$32 -> 6133500 | N32: =$M$32/($N$5*1000) -> 0.25507053 | O32: =($M$32/$N$6)/$N$5 -> 0.015941908
C33: Filter Dustbag | D33: 0.12048193 | E33: Pcs/day | F33: =D33 -> 0.12048193 | G33: Pcs/day | H33: =$H$8 -> 27 | J33: =$H$33*$F$33 -> 3.253012 | K33: 682500 | M33: =$J$33*$K$33 -> 2220180.7 | N33: =$M$33/($N$5*1000) -> 0.09232945 | O33: =($M$33/$N$6)/$N$5 -> 0.0057705906
C34: O Ring Filter Leaves | D34: 3.6144578 | E34: Pcs/day | F34: =D34 -> 3.6144578 | G34: Pcs/day | H34: =$H$8 -> 27 | J34: =$H$34*$F$34 -> 97.590361 | K34: 14500 | M34: =$J$34*$K$34 -> 1415060.2 | N34: =$M$34/($N$5*1000) -> 0.058847342 | O34: =($M$34/$N$6)/$N$5 -> 0.0036779588
B35: 10 | C35: Waste Water Treatment Plant ( WWTP ) | D35: ='September - 2024'!$AM$251 -> 193.96296 | E35: M3/day | F35: =D35 -> 193.96296 | G35: M3/day | H35: =$H$8 -> 27 | J35: =$H$35*$F$35 -> 5237 | K35: 18616 | M35: =$J$35*$K$35 -> 97491992 | N35: =$M$35/($N$5*1000) -> 4.0543465 | O35: =($M$35/$N$6)/$N$5 -> 0.25339666
B36: 11 | C36: SHE
C37: SBE | D37: ='September - 2024'!$AM$74 -> 189044.92 | E37: Kg/day | F37: =D37 -> 189044.92 | G37: Kg/day | H37: =$H$8 -> 27 | J37: =$F$37 -> 189044.92 | K37: 275 | M37: =$J$37*$K$37 -> 51987354 | N37: =$M$37/($N$5*1000) -> 2.1619698 | O37: =($M$37/$N$6)/$N$5 -> 0.13512311
C38: Domestic | D38: 0.1 | E38: Trip/day | F38: =D38 -> 0.1 | G38: Trip/day | H38: =$H$8 -> 27 | J38: =$H$38*$F$38 -> 2.7 | K38: 303030.3 | M38: =$J$38*$K$38 -> 818181.82 | N38: =$M$38/($N$5*1000) -> 0.034025283 | O38: =($M$38/$N$6)/$N$5 -> 0.0021265802
B39: 12 | C39: Chemical Consumption | N39: =$M$39/($N$5*1000) -> 0 | O39: =($M$39/$N$6)/$N$5 -> 0
C40: LAB Chemical | D40: =[20]Chemical!$H$33 -> 745255.21 | E40: Rp/day | F40: =D40 -> 745255.21 | G40: Rp/day | H40: =$H$8 -> 27 | M40: =$H$40*$F$40 -> 20121891 | N40: =$M$40/($N$5*1000) -> 0.83679814 | O40: =($M$40/$N$6)/$N$5 -> 0.052299884
C41: Chemical Boiler dan WTP | D41: =[20]Chemical!$H$54 -> 259161.44 | E41: Rp/day | F41: =D41 -> 259161.44 | G41: Rp/day | H41: =$H$8 -> 27 | M41: =$H$41*$F$41 -> 6997359 | N41: =$M$41/($N$5*1000) -> 0.29099537 | O41: =($M$41/$N$6)/$N$5 -> 0.01818721
C42: Sample and Analysis | D42: 13909.091 | E42: Rp/day | F42: =D42 -> 13909.091 | G42: Rp/day | H42: =$H$8 -> 27 | M42: =$H$42*$F$42 -> 375545.45 | N42: =$M$42/($N$5*1000) -> 0.015617605 | O42: =($M$42/$N$6)/$N$5 -> 0.0009761003
C43: Chemical WWTP | D43: =[20]Chemical!$H$61 -> 27103.641 | E43: Rp/day | F43: =D43 -> 27103.641 | G43: Rp/day | H43: =$H$8 -> 27 | M43: =$H$43*$F$43 -> 731798.32 | N43: =$M$43/($N$5*1000) -> 0.030432899 | O43: =($M$43/$N$6)/$N$5 -> 0.0019020562
C44: Consumable Part | D44: ='[20]Spere part Lab'!$I$46 -> 135770.31 | E44: Rp/day | F44: =D44 -> 135770.31 | G44: Rp/day | H44: =$H$8 -> 27 | M44: =$H$44*$F$44 -> 3665798.3 | N44: =$M$44/($N$5*1000) -> 0.15244756 | O44: =($M$44/$N$6)/$N$5 -> 0.0095279727
B45: 13 | C45: Solar
C46: Forklift -1 (3 Ton) | D46: 15.4 | E46: Ltr/day | F46: =D46 -> 15.4 | G46: Ltr/day | H46: =$H$8 -> 27 | J46: =$H$46*$F$46 -> 415.8 | K46: 14500 | M46: =$J$46*$K$46 -> 6029100 | N46: =$M$46/($N$5*1000) -> 0.25072891 | O46: =($M$46/$N$6)/$N$5 -> 0.015670557
C47: WA Loader | D47: 0 | E47: Ltr/day | F47: =D47 -> 0 | G47: Ltr/day | H47: =$H$8 -> 27 | J47: =$H$47*$F$47 -> 0 | K47: 14500 | M47: =$J$47*$K$47 -> 0 | N47: =$M$47/($N$5*1000) -> 0 | O47: =($M$47/$N$6)/$N$5 -> 0
M48: =SUM($M$8:$M$47) -> 4.7511346e+09 | N48: =SUM($N$8:$N$47) -> 197.58285 | O48: =SUM($O$8:$O$47) -> 12.348928

Sheet HPP FRACT
B2: Fractionation Cost
B3: RPO Proses / Day | N3: TPD | O3: =('September - 2024'!AM24)/1000 -> 836.77663
B4: Working Day | N4: Days | O4: ='September - 2024'!AM21 -> 27
B5: Total CPO Process | N5: MTD | O5: =O3*O4 -> 22592.969
B6: KURS | N6: Rp/USD | O6: =[20]Formula!I6 -> 16000
B7: No | C7: Item Cost | D7: Norma | F7: Pemakaian / Hari | H7: HK | J7: Total Pemakaian | K7: Harga / stn | M7: Total Biaya | N7: Rp / kg | O7: USD/MT
B8: 1 | C8: Steam | D8: ='September - 2024'!$AM$238 -> 72.243714 | E8: Kg/MT CPO | F8: =$D$8*$O$3/1000 -> 60.451852 | G8: Ton/day | H8: =$O$4 -> 27 | J8: =$H$8*$F$8 -> 1632.2 | K8: =[20]Steam!$H$15 -> 507005.63 | M8: =$K$8*$J$8 -> 8.2753459e+08 | N8: =$M$8/($O$5*1000) -> 36.62797 | O8: =($M$8/$O$6)/$O$5 -> 2.2892481
B9: 2 | C9: Electrical
C10: For Process | D10: ='September - 2024'!$AM$265 -> 4.1694387 | E10: kW/MT CPO | F10: =$D$10*$O$3 -> 3488.8889 | G10: kW/day | H10: =$O$4 -> 27 | I10: 0 | J10: =$H$10*$F$10 -> 94200 | K10: =[20]Electric!$L$5 -> 1550 | L10: 3666.6667 | M10: =($F$10*$H$10*$K$10)+($F$10*$I$10*$L$10) -> 146010000 | N10: =$M$10/($O$5*1000) -> 6.46263 | O10: =($M$10/$O$6)/$O$5 -> 0.40391438
C11: Cooling Tower | D11: ='September - 2024'!$AM$263 -> 1.002303 | E11: kW/MT CPO | F11: =$D$11*$O$3 -> 838.7037 | G11: kW/day | H11: =$H$10 -> 27 | I11: 0 | J11: =$H$11*$F$11 -> 22645 | K11: =$K$10 -> 1550 | L11: 3666.6667 | M11: =($F$11*$H$11*$K$11)+($F$11*$I$11*$L$11) -> 35099750 | N11: =$M$11/($O$5*1000) -> 1.5535696 | O11: =($M$11/$O$6)/$O$5 -> 0.097098101
B12: 3 | C12: Water
C13: Make Up CT | D13: ='September - 2024'!$AM$247 -> 91.178809 | E13: M3/day | F13: =$D$13 -> 91.178809 | G13: M3/day | H13: =$H$11 -> 27 | J13: =$H$13*$F$13 -> 2461.8278 | K13: =[20]Water!$F$10 -> 8700 | M13: =$K$13*$J$13 -> 21417902 | N13: =$M$13/($O$5*1000) -> 0.94798971 | O13: =($M$13/$O$6)/$O$5 -> 0.059249357
B14: 4 | C14: Chemical Water
C15: EONBAC BC 3108 | D15: 0.4 | E15: Kg/day | F15: =$D$15 -> 0.4 | G15: Kg/day | H15: =$H$13 -> 27 | J15: =$H$15*$F$15 -> 10.8 | K15: 27240 | M15: =$K$15*$J$15 -> 294192 | N15: =$M$15/($O$5*1000) -> 0.013021396 | O15: =($M$15/$O$6)/$O$5 -> 0.00081383726
C16: EONLINE T722 | D16: 0.66 | E16: Kg/day | F16: =$D$16 -> 0.66 | G16: Kg/day | H16: =$H$15 -> 27 | J16: =$H$16*$F$16 -> 17.82 | K16: 29120 | M16: =$K$16*$J$16 -> 518918.4 | N16: =$M$16/($O$5*1000) -> 0.022968137 | O16: =($M$16/$O$6)/$O$5 -> 0.0014355085
C17: EONLINE AG5770 | D17: 0.41 | E17: Kg/day | F17: =$D$17 -> 0.41 | G17: Kg/day | H17: =$H$15 -> 27 | J17: =$H$17*$F$17 -> 11.07 | K17: 117212 | M17: =$K$17*$J$17 -> 1297536.8 | N17: =$M$17/($O$5*1000) -> 0.057431002 | O17: =($M$17/$O$6)/$O$5 -> 0.0035894376
C18: EONScale T2511 | D18: 0.1 | E18: Kg/day | F18: =$D$18 -> 0.1 | G18: Kg/day | H18: =$H$16 -> 27 | J18: =$H$18*$F$18 -> 2.7 | K18: 45940 | M18: =$K$18*$J$18 -> 124038 | N18: =$M$18/($O$5*1000) -> 0.0054901151 | O18: =($M$18/$O$6)/$O$5 -> 0.00034313219
B19: 5 | C19: Others
C20: Filter Cloth | D20: 0.33333333 | E20: Pcs/day | F20: =$D$20 -> 0.33333333 | G20: Pcs/day | H20: =$H$18 -> 27 | J20: =$H$20*$F$20 -> 9 | K20: 895000 | M20: =$K$20*$J$20 -> 8055000 | N20: =$M$20/($O$5*1000) -> 0.35652685 | O20: =($M$20/$O$6)/$O$5 -> 0.022282928
C21: Filter Bag 100 Microne | D21: 0.63253012 | E21: Pcs/day | F21: =$D$21 -> 0.63253012 | G21: Pcs/day | H21: =$H$20 -> 27 | J21: =$H$21*$F$21 -> 17.078313 | K21: 125000 | M21: =$K$21*$J$21 -> 2134789.2 | N21: =$M$21/($O$5*1000) -> 0.094489093 | O21: =($M$21/$O$6)/$O$5 -> 0.0059055683
M22: =SUM(M8:M21) -> 1.0424867e+09 | N22: =SUM(N8:N21) -> 46.142086 | O22: =SUM($O$8:$O$21) -> 2.8838804

Sheet AMOR
B2: Amortization
B3: Through Put CPO Proses | H3: TPD | I3: ='HPP REF '!N3 -> 890.60333
B4: Working Day | H4: Day | I4: ='HPP REF '!N4 -> 27
B5: Total CPO Refined | H5: TPM | I5: =I4*I3 -> 24046.29
B6: Kurs Rupiah | I6: =[21]Formula!I6 -> 16000
B7: No | C7: Description | D7: Actual 2023 | F7: Budget 2024
D8: Years | E8: Month | F8: Years | G8: Month | H8: RP/KG | I8: USD/MT
B9: 1 | C9: Perangkat Lunak/Software | D9: 9.6270931e+08 | E9: =D9/12 -> 80225776 | F9: =G9*12 -> 5.3192735e+08 | G9: 44327279 | H9: =$G$9/($I$5*1000) -> 1.8434145 | I9: =($G$9/$I$6)/$I$5 -> 0.1152134 | J9: =D9/12 -> 80225776
B10: =B9+1 -> 2 | C10: Sertifikat/Surat Izin | D10: 2.6961444e+08 | E10: =D10/12 -> 22467870 | F10: 0 | G10: 0 | H10: =$G$10/($I$5*1000) -> 0 | I10: =($G$10/$I$6)/$I$5 -> 0
B11: =B10+1 -> 3 | C11: Inventaris Kecil (Aset Sewa) | D11: 0 | E11: =D11/12 -> 0 | F11: 0 | G11: 0 | H11: =$G$11/($I$5*1000) -> 0 | I11: =($G$11/$I$6)/$I$5 -> 0
B12: =B11+1 -> 4 | C12: Aset Hak Guna (ROU) - Kendaraan | D12: 0 | E12: =D12/12 -> 0 | F12: 0 | G12: 0 | H12: =$G$12/($I$5*1000) -> 0 | I12: =($G$12/$I$6)/$I$5 -> 0
B13: =B12+1 -> 5 | C13: Aset Hak Guna (ROU) - Tangki Timbun | D13: 0 | E13: =D13/12 -> 0 | F13: 0 | G13: 0 | H13: =$G$13/($I$5*1000) -> 0 | I13: =($G$13/$I$6)/$I$5 -> 0
B14: =B13+1 -> 6 | C14: Aset Atas Biaya Penyambungan | D14: 0 | E14: =D14/12 -> 0 | F14: 0 | G14: 0 | H14: =$G$14/($I$5*1000) -> 0 | I14: =($G$14/$I$6)/$I$5 -> 0
B15: =B14+1 -> 7 | C15: Aset Hak Guna (ROU) - Pemanfaatan Lahan Sei Mangkei + Surabaya | D15: 1.2576903e+10 | E15: =D15/12 -> 1.0480752e+09 | F15: =G15*12 -> 12048990312 | G15: 1004082526 | H15: =$G$15/($I$5*1000) -> 41.756235 | I15: =($G$15/$I$6)/$I$5 -> 2.6097647
B20: Total Cost Depreciation | D20: =SUM(D9:D19) -> 1.3809227e+10 | E20: =SUM(E9:E19) -> 1.1507689e+09 | F20: =SUM(F9:F19) -> 1.2580918e+10 | G20: =SUM(G9:G19) -> 1.0484098e+09 | H20: =SUM(H9:H19) -> 43.599649 | I20: =SUM(I9:I19) -> 2.7249781

Sheet DEP
B2: Depreciation
B3: Through Put CPO Proses | J3: TPD | K3: ='HPP REF '!N3 -> 890.60333
B4: Working Day | J4: Day | K4: ='HPP REF '!N4 -> 27
B5: Total CPO Refined | J5: TPM | K5: =K4*K3 -> 24046.29
B6: Kurs Rupiah | K6: =[21]Formula!I6 -> 16000
B7: No | C7: Description | D7: Actual 2023 (Audited) | G7: Budget 2024
D8: Asset | E8: Years | F8: Month | G8: Asset | H8: Years | I8: Month | J8: RP/KG | K8: USD/MT
B9: Total Cost Depreciation | D9: =SUM(D10:D75) -> 6.7971213e+11 | E9: =SUM(E10:E75) -> 4.1807174e+10 | F9: =SUM(F10:F75) -> 3.4839312e+09 | G9: =SUM(G10:G75) -> 7.7503139e+11 | H9: =SUM(H10:H75) -> 5.0174217e+10 | I9: =SUM(I10:I75) -> 4.1811848e+09 | J9: =SUM(J10:J75) -> 173.88066 | K9: =SUM(K10:K75) -> 10.867541
B10: 1 | C10: Front Office + Canteen | D10: 3844320790 | E10: 1.9221604e+08 | F10: 16018003 | G10: 3.8443208e+09 | H10: =I10*12 -> 1.9221604e+08 | I10: 16018003 | J10: =$I$10/($K$5*1000) -> 0.666132 | K10: =($I$10/$K$6)/$K$5 -> 0.04163325
B11: =B10+1 -> 2 | C11: Bea Cukai Building | D11: 247144032 | E11: 12357202 | F11: 1029766.8 | G11: 2.4714403e+08 | H11: =I11*12 -> 12357202 | I11: 1029766.8 | J11: =$I$11/($K$5*1000) -> 0.042824352 | K11: =($I$11/$K$6)/$K$5 -> 0.002676522
B12: =B11+1 -> 3 | C12: Security Building | D12: 199088248 | E12: 12429395 | F12: 1035782.9 | G12: 3.9708686e+08 | H12: =I12*12 -> 19854343 | I12: 1654528.6 | J12: =$I$12/($K$5*1000) -> 0.068805982 | K12: =($I$12/$K$6)/$K$5 -> 0.0043003739
B13: =B12+1 -> 4 | C13: Bangunan Shelter / Pelataran | D13: 53111657402 | E13: 2.6555829e+09 | F13: 2.2129857e+08 | G13: 5.3111657e+10 | H13: =I13*12 -> 2.6555829e+09 | I13: 2.2129857e+08 | J13: =$I$13/($K$5*1000) -> 9.2030235 | K13: =($I$13/$K$6)/$K$5 -> 0.57518897
B14: =B13+1 -> 5 | C14: Laboratorium Building | D14: 1.3920764e+09 | E14: 70956822 | F14: 5913068.5 | G14: 1.5003164e+09 | H14: =I14*12 -> 75015820 | I14: 6251318.3 | J14: =$I$14/($K$5*1000) -> 0.25997018 | K14: =($I$14/$K$6)/$K$5 -> 0.016248136
B15: =B14+1 -> 6 | C15: Refinery Room | D15: 22378266872 | E15: 1.1189133e+09 | F15: 93242779 | G15: 2.2378267e+10 | H15: =I15*12 -> 1.1189133e+09 | I15: 93242779 | J15: =$I$15/($K$5*1000) -> 3.8776368 | K15: =($I$15/$K$6)/$K$5 -> 0.2423523
B16: =B15+1 -> 7 | C16: Fractionation Room | D16: 22378266872 | E16: 1.1189133e+09 | F16: 93242779 | G16: 2.2378267e+10 | H16: =I16*12 -> 1.1189133e+09 | I16: 93242779 | J16: =$I$16/($K$5*1000) -> 3.8776368 | K16: =($I$16/$K$6)/$K$5 -> 0.2423523
B17: =B16+1 -> 8 | C17: Utility Building | D17: 22548996820 | E17: 1.1274498e+09 | F17: 93954153 | G17: 2.2548997e+10 | H17: =I17*12 -> 1.1274498e+09 | I17: 93954153 | J17: =$I$17/($K$5*1000) -> 3.9072203 | K17: =($I$17/$K$6)/$K$5 -> 0.24420127
B18: =B17+1 -> 9 | C18: Power House & Electrical Building | D18: 3242778116 | E18: 1.6663346e+08 | F18: 13886122 | G18: 3.6023423e+09 | H18: =I18*12 -> 1.8011712e+08 | I18: 15009760 | J18: =$I$18/($K$5*1000) -> 0.62420272 | K18: =($I$18/$K$6)/$K$5 -> 0.03901267
B19: =B18+1 -> 10 | C19: Weight Bridge Building (Timbangan) | D19: 3.0883582e+09 | E19: 1.6798762e+08 | F19: 13998968 | G19: 4.173935e+09 | H19: =I19*12 -> 2.0869675e+08 | I19: 17391396 | J19: =$I$19/($K$5*1000) -> 0.72324653 | K19: =($I$19/$K$6)/$K$5 -> 0.045202908
B20: =B19+1 -> 11 | C20: Warehouse TPS Spent Earth | D20: 1.3067146e+09 | E20: 65335728 | F20: 5444644 | G20: 1.3067146e+09 | H20: =I20*12 -> 65335728 | I20: 5444644 | J20: =$I$20/($K$5*1000) -> 0.22642345 | K20: =($I$20/$K$6)/$K$5 -> 0.014151466
B21: =B20+1 -> 12 | C21: Bangunan Shelter / Pelataran | D21: 0 | E21: 0 | F21: 0 | G21: 0 | H21: =I21*12 -> 0 | I21: 0 | J21: =$I$21/($K$5*1000) -> 0 | K21: =($I$21/$K$6)/$K$5 -> 0
B22: =B21+1 -> 13 | C22: Packaging Building | D22: 26865966199 | E22: 1.3432983e+09 | F22: 1.1194153e+08 | G22: 2.6865966e+10 | H22: =I22*12 -> 1.895783e+09 | I22: 1.5798192e+08 | J22: =$I$22/($K$5*1000) -> 6.5699083 | K22: =($I$22/$K$6)/$K$5 -> 0.41061927
B23: =B22+1 -> 14 | C23: Warehouse TPS Limbah B3 | D23: 808088751 | E23: 52164853 | F23: 4347071.1 | G23: 1.748922e+09 | H23: =I23*12 -> 87446098 | I23: 7287174.8 | J23: =$I$23/($K$5*1000) -> 0.30304778 | K23: =($I$23/$K$6)/$K$5 -> 0.018940486
B24: =B23+1 -> 15 | C24: Panel Room Loading - Unloading | D24: 669445527 | E24: 33472276 | F24: 2789356.4 | G24: 6.6944553e+08 | H24: =I24*12 -> 33472276 | I24: 2789356.4 | J24: =$I$24/($K$5*1000) -> 0.11599945 | K24: =($I$24/$K$6)/$K$5 -> 0.0072499655
B25: =B24+1 -> 16 | C25: Bangunan Shelter / Pelataran | D25: 0 | E25: 0 | F25: 0 | G25: 0 | H25: =I25*12 -> 0 | I25: 0 | J25: =$I$25/($K$5*1000) -> 0 | K25: =($I$25/$K$6)/$K$5 -> 0
B26: =B25+1 -> 17 | C26: Kantor RO Medan | D26: 35739000 | E26: 3573900 | F26: 297825 | G26: 35739000 | H26: =I26*12 -> 3573900 | I26: 297825 | J26: =$I$26/($K$5*1000) -> 0.012385486 | K26: =($I$26/$K$6)/$K$5 -> 0.00077409291
B27: =B26+1 -> 18 | C27: Gedung Logistic | D27: 537402145 | E27: 26870107 | F27: 2239175.6 | G27: 537402145 | H27: =I27*12 -> 26870107 | I27: 2239175.6 | J27: =$I$27/($K$5*1000) -> 0.09311938 | K27: =($I$27/$K$6)/$K$5 -> 0.0058199612
B28: =B27+1 -> 19 | C28: Ruang Expansi Filling Packaging | D28: 1071796228 | E28: 26794906 | F28: 2232908.8 | G28: 1071796228 | H28: =I28*12 -> 53589811 | I28: 4465817.6 | J28: =$I$28/($K$5*1000) -> 0.18571753 | K28: =($I$28/$K$6)/$K$5 -> 0.011607346
B29: =B28+1 -> 20 | C29: Bangunan Lainnya | D29: 236594750 | E29: 67601093 | F29: 5633424.5 | G29: 3.7519242e+09 | H29: =I29*12 -> 1.9942595e+08 | I29: 16618829 | J29: =$I$29/($K$5*1000) -> 0.69111822 | K29: =($I$29/$K$6)/$K$5 -> 0.043194889
B30: =B29+1 -> 21 | C30: Power House System | D30: 30414179484 | E30: 1.6120305e+09 | F30: 1.3433587e+08 | G30: 3.0414179e+10 | H30: =I30*12 -> 1.7106159e+09 | I30: 1.4255132e+08 | J30: =$I$30/($K$5*1000) -> 5.9282045 | K30: =($I$30/$K$6)/$K$5 -> 0.37051278
B31: =B30+1 -> 22 | C31: Reception from Road Tanker System | D31: 15714477178 | E31: 1.5906981e+09 | F31: 1.3255817e+08 | G31: 1.5714477e+10 | H31: =I31*12 -> 1.6892835e+09 | I31: 1.4077362e+08 | J31: =$I$31/($K$5*1000) -> 5.8542763 | K31: =($I$31/$K$6)/$K$5 -> 0.36589227
B32: =B31+1 -> 23 | C32: Reception & CPO Storage Tank System | D32: 3.9160256e+10 | E32: 1.8156968e+09 | F32: 1.5130807e+08 | G32: 3.9160256e+10 | H32: =I32*12 -> 1.9142822e+09 | I32: 1.5952352e+08 | J32: =$I$32/($K$5*1000) -> 6.634018 | K32: =($I$32/$K$6)/$K$5 -> 0.41462612
B33: =B32+1 -> 24 | C33: Refinery Product System | D33: 26158484525 | E33: 1.546139e+09 | F33: 1.2884492e+08 | G33: 2.6158485e+10 | H33: =I33*12 -> 2.1043359e+09 | I33: 1.7536132e+08 | J33: =$I$33/($K$5*1000) -> 7.2926561 | K33: =($I$33/$K$6)/$K$5 -> 0.45579101
B34: =B33+1 -> 25 | C34: Fractionation Product System | D34: 44700543389 | E34: 2.5257813e+09 | F34: 2.1048177e+08 | G34: 4.4700543e+10 | H34: =I34*12 -> 2.6243667e+09 | I34: 2.1869722e+08 | J34: =$I$34/($K$5*1000) -> 9.0948426 | K34: =($I$34/$K$6)/$K$5 -> 0.56842766
B35: =B34+1 -> 26 | C35: Compressed Air System | D35: 12406716786 | E35: 6.9726354e+08 | F35: 58105295 | G35: 1.2406717e+10 | H35: =I35*12 -> 6.9726354e+08 | I35: 58105295 | J35: =$I$35/($K$5*1000) -> 2.4163933 | K35: =($I$35/$K$6)/$K$5 -> 0.15102458
B36: =B35+1 -> 27 | C36: Fuel Distribution System | D36: 2279256408 | E36: 1.6844371e+08 | F36: 14036976 | G36: 2.2792564e+09 | H36: =I36*12 -> 2.0366838e+08 | I36: 16972365 | J36: =$I$36/($K$5*1000) -> 0.70582054 | K36: =($I$36/$K$6)/$K$5 -> 0.044113784
B37: =B36+1 -> 28 | C37: Waste Water Treatment System | D37: 8173671310 | E37: 5.0165483e+08 | F37: 41804569 | G37: 8.1736713e+09 | H37: =I37*12 -> 5.1840723e+08 | I37: 43200602 | J37: =$I$37/($K$5*1000) -> 1.79656 | K37: =($I$37/$K$6)/$K$5 -> 0.112285
B38: =B37+1 -> 29 | C38: Clean Water System | D38: 8.1369458e+09 | E38: 4.697884e+08 | F38: 39149033 | G38: 8.1369458e+09 | H38: =I38*12 -> 4.697884e+08 | I38: 39149033 | J38: =$I$38/($K$5*1000) -> 1.6280696 | K38: =($I$38/$K$6)/$K$5 -> 0.10175435
B39: =B38+1 -> 30 | C39: Demin Water Distribution System | D39: 5554219736 | E39: 3.7021373e+08 | F39: 30851144 | G39: 5.5542197e+09 | H39: =I39*12 -> 3.7021373e+08 | I39: 30851144 | J39: =$I$39/($K$5*1000) -> 1.2829898 | K39: =($I$39/$K$6)/$K$5 -> 0.080186861
B40: =B39+1 -> 31 | C40: Steam Generation System | D40: 28411905935 | E40: 1.6009903e+09 | F40: 1.3341586e+08 | G40: 2.8411906e+10 | H40: =I40*12 -> 1.6009903e+09 | I40: 1.3341586e+08 | J40: =$I$40/($K$5*1000) -> 5.5482928 | K40: =($I$40/$K$6)/$K$5 -> 0.3467683 | L40: =H40/12 -> 1.3341586e+08
B41: =B40+1 -> 32 | C41: Cooling Water Distribution System | D41: 8813632097 | E41: 5.5719688e+08 | F41: 46433074 | G41: 8.8136321e+09 | H41: =I41*12 -> 5.5719688e+08 | I41: 46433074 | J41: =$I$41/($K$5*1000) -> 1.930987 | K41: =($I$41/$K$6)/$K$5 -> 0.12068669
B42: =B41+1 -> 33 | C42: Fire Water System | D42: 4990631887 | E42: 3.5991574e+08 | F42: 29992978 | G42: 4.9906319e+09 | H42: =I42*12 -> 3.5991574e+08 | I42: 29992978 | J42: =$I$42/($K$5*1000) -> 1.2473017 | K42: =($I$42/$K$6)/$K$5 -> 0.077956356
B43: =B42+1 -> 34 | C43: Dual Fuel Emergency Generator | D43: 11752092639 | E43: 6.1186193e+08 | F43: 50988494 | G43: 1.1752093e+10 | H43: =I43*12 -> 6.1186193e+08 | I43: 50988494 | J43: =$I$43/($K$5*1000) -> 2.1204308 | K43: =($I$43/$K$6)/$K$5 -> 0.13252693
B44: =B43+1 -> 35 | C44: Steam Distribution & Condensate Recovery System | D44: 9891619567 | E44: 8.9987659e+08 | F44: 74989716 | G44: 9.8916196e+09 | H44: =I44*12 -> 8.9987659e+08 | I44: 74989716 | J44: =$I$44/($K$5*1000) -> 3.1185566 | K44: =($I$44/$K$6)/$K$5 -> 0.19490979
B45: =B44+1 -> 36 | C45: Fire Water Main Ring System | D45: 4518985787 | E45: 2.4463794e+08 | F45: 20386495 | G45: 4.5189858e+09 | H45: =I45*12 -> 2.4463794e+08 | I45: 20386495 | J45: =$I$45/($K$5*1000) -> 0.8478021 | K45: =($I$45/$K$6)/$K$5 -> 0.052987631
B46: =B45+1 -> 37 | C46: Packaging System | D46: 34206697993 | E46: 3.1394346e+09 | F46: 2.6161955e+08 | G46: 1.2163436e+11 | H46: =I46*12 -> 7.8746236e+09 | I46: 6.5621863e+08 | J46: =$I$46/($K$5*1000) -> 27.289808 | K46: =($I$46/$K$6)/$K$5 -> 1.705613
B47: =B46+1 -> 38 | C47: Refinery System | D47: 93804025615 | E47: 6.3108388e+09 | F47: 5.2590324e+08 | G47: 9.3804026e+10 | H47: =I47*12 -> 6.3327722e+09 | I47: 5.2773101e+08 | J47: =$I$47/($K$5*1000) -> 21.946463 | K47: =($I$47/$K$6)/$K$5 -> 1.3716539
B48: =B47+1 -> 39 | C48: Fractionation System | D48: 69305898501 | E48: 4.7141422e+09 | F48: 3.9284518e+08 | G48: 6.9305899e+10 | H48: =I48*12 -> 4.7141422e+09 | I48: 3.9284518e+08 | J48: =$I$48/($K$5*1000) -> 16.337039 | K48: =($I$48/$K$6)/$K$5 -> 1.021065
B49: =B48+1 -> 40 | C49: Fat Pit System | D49: 1222833568 | E49: 76427098 | F49: 6368924.8 | G49: 1.2228336e+09 | H49: =I49*12 -> 76427098 | I49: 6368924.8 | J49: =$I$49/($K$5*1000) -> 0.26486102 | K49: =($I$49/$K$6)/$K$5 -> 0.016553814
B50: =B49+1 -> 41 | C50: Weight Bridge | D50: 2557397646 | E50: 1.2786988e+08 | F50: 10655824 | G50: 2.5573976e+09 | H50: =I50*12 -> 1.2786988e+08 | I50: 10655824 | J50: =$I$50/($K$5*1000) -> 0.44313794 | K50: =($I$50/$K$6)/$K$5 -> 0.027696122
B51: =B50+1 -> 42 | C51: Mesin Dan Perlengkapan Pabrik | D51: 30580769059 | E51: 1.6581493e+09 | F51: 1.3817911e+08 | G51: 3.0797884e+10 | H51: =I51*12 -> 2.8889928e+09 | I51: 2.407494e+08 | J51: =$I$51/($K$5*1000) -> 10.011914 | K51: =($I$51/$K$6)/$K$5 -> 0.62574465
B52: =B51+1 -> 43 | C52: Installation System Electrical (Auxiliary) | D52: 2460303143 | E52: 1.5376895e+08 | F52: 12814079 | G52: 2460303143 | H52: =I52*12 -> 1.5376895e+08 | I52: 12814079 | J52: =$I$52/($K$5*1000) -> 0.53289214 | K52: =($I$52/$K$6)/$K$5 -> 0.033305759
B53: =B52+1 -> 44 | C53: Mesin Dan Perlengkapan Pabrik | D53: 0 | E53: 0 | F53: 0 | G53: 0 | H53: =I53*12 -> 0 | I53: 0 | J53: =$I$53/($K$5*1000) -> 0 | K53: =($I$53/$K$6)/$K$5 -> 0
B54: =B53+1 -> 45 | C54: Mesin Dan Perlengkapan Pabrik | D54: 0 | E54: 0 | F54: 0 | G54: 0 | H54: =I54*12 -> 0 | I54: 0 | J54: =$I$54/($K$5*1000) -> 0 | K54: =($I$54/$K$6)/$K$5 -> 0
B55: =B54+1 -> 46 | C55: Refinery Product System | D55: 0 | E55: 0 | F55: 0 | G55: 0 | H55: =I55*12 -> 0 | I55: 0 | J55: =$I$55/($K$5*1000) -> 0 | K55: =($I$55/$K$6)/$K$5 -> 0
B56: =B55+1 -> 47 | C56: Perlengkapan Pabrik Lainnya | D56: 814629325 | E56: 1.3842046e+08 | F56: 11535038 | G56: 814629325 | H56: =I56*12 -> 1.3842046e+08 | I56: 11535038 | J56: =$I$56/($K$5*1000) -> 0.47970137 | K56: =($I$56/$K$6)/$K$5 -> 0.029981336
B57: =B56+1 -> 48 | C57: Bangunan Shelter / Pelataran | D57: 0 | E57: 0 | F57: 0 | G57: 0 | H57: =I57*12 -> 0 | I57: 0 | J57: =$I$57/($K$5*1000) -> 0 | K57: =($I$57/$K$6)/$K$5 -> 0
B58: =B57+1 -> 49 | C58: Saluran Drainase | D58: 3324550757 | E58: 1.6622754e+08 | F58: 13852295 | G58: 3.3245508e+09 | H58: =I58*12 -> 1.6622754e+08 | I58: 13852295 | J58: =$I$58/($K$5*1000) -> 0.57606786 | K58: =($I$58/$K$6)/$K$5 -> 0.036004241
B59: =B58+1 -> 50 | C59: Fence | D59: 1457273906 | E59: 72863695 | F59: 6071974.6 | G59: 1457273906 | H59: =I59*12 -> 72863695 | I59: 6071974.6 | J59: =$I$59/($K$5*1000) -> 0.25251191 | K59: =($I$59/$K$6)/$K$5 -> 0.015781994
B60: =B59+1 -> 51 | C60: Bangunan Shelter / Pelataran | D60: 0 | E60: 0 | F60: 0 | G60: 0 | H60: =I60*12 -> 0 | I60: 0 | J60: =$I$60/($K$5*1000) -> 0 | K60: =($I$60/$K$6)/$K$5 -> 0
B61: =B60+1 -> 52 | C61: Alat Pengangkutan | D61: 702420000 | E61: 58515250 | F61: 4876270.8 | G61: 702420000 | H61: =I61*12 -> 92109000 | I61: 7675750 | J61: =$I$61/($K$5*1000) -> 0.31920725 | K61: =($I$61/$K$6)/$K$5 -> 0.019950453
B62: =B61+1 -> 53 | C62: Perabot & Perlengkapan Kantor | D62: 2093240354 | E62: 2.8749571e+08 | F62: 23957976 | G62: 2093240354 | H62: =I62*12 -> 2.8749571e+08 | I62: 23957976 | J62: =$I$62/($K$5*1000) -> 0.99632734 | K62: =($I$62/$K$6)/$K$5 -> 0.062270458
B63: =B62+1 -> 54 | C63: Perabot dan Perlengkapan Mess | D63: 0 | E63: 0 | F63: 0 | G63: 0 | H63: =I63*12 -> 0 | I63: 0 | J63: =$I$63/($K$5*1000) -> 0 | K63: =($I$63/$K$6)/$K$5 -> 0
B64: =B63+1 -> 55 | C64: Alat & Perlengkapan Pabrik | D64: 68073000 | E64: 13614600 | F64: 1134550 | G64: 68073000 | H64: =I64*12 -> 13614600 | I64: 1134550 | J64: =$I$64/($K$5*1000) -> 0.047181915 | K64: =($I$64/$K$6)/$K$5 -> 0.0029488697
B65: =B64+1 -> 56 | C65: Alat dan Perlengkapan Bengkel | D65: 140550000 | E65: 28110000 | F65: 2342500 | G65: 140550000 | H65: =I65*12 -> 28110000 | I65: 2342500 | J65: =$I$65/($K$5*1000) -> 0.097416275 | K65: =($I$65/$K$6)/$K$5 -> 0.0060885172
B66: =B65+1 -> 57 | C66: Alat dan Perlengkapan Laboratorium | D66: 3453064640 | E66: 3.7398892e+08 | F66: 31165744 | G66: 4405170868 | H66: =I66*12 -> 8.9603417e+08 | I66: 74669514 | J66: =$I$66/($K$5*1000) -> 3.1052405 | K66: =($I$66/$K$6)/$K$5 -> 0.19407753
B67: =B66+1 -> 58 | C67: Alat IT / Komputer | D67: 1542535419 | E67: 2.9444276e+08 | F67: 24536897 | G67: 1.9760604e+09 | H67: =I67*12 -> 2.9825396e+08 | I67: 24854497 | J67: =$I$67/($K$5*1000) -> 1.0336105 | K67: =($I$67/$K$6)/$K$5 -> 0.064600653
B68: =B67+1 -> 59 | C68: Perabot & Perlengkapan Lainnya | D68: 11270000 | E68: 2254000 | F68: 187833.33 | G68: 11270000 | H68: =I68*12 -> 2254000 | I68: 187833.33 | J68: =$I$68/($K$5*1000) -> 0.0078113228 | K68: =($I$68/$K$6)/$K$5 -> 0.00048820768
B69: =B68+1 -> 60 | C69: Aktiva Tetap Non Produktif | D69: 26932688 | E69: 5386537.6 | F69: 448878.13 | G69: 26932688 | H69: =I69*12 -> 5386537.5 | I69: 448878.13 | J69: =$I$69/($K$5*1000) -> 0.018667251 | K69: =($I$69/$K$6)/$K$5 -> 0.0011667032
B70: =B69+1 -> 61 | C70: Totem AKHLAK | D70: 30000000 | E70: 6000000 | F70: 500000 | G70: 30000000 | H70: =I70*12 -> 6000000.1 | I70: 500000.01 | J70: =$I$70/($K$5*1000) -> 0.020793229 | K70: =($I$70/$K$6)/$K$5 -> 0.0012995768
B71: =B70+1 -> 62 | C71: Main Office | D71: 6869341541 | E71: 3.4448348e+08 | F71: 28706957 | G71: 6.9506539e+09 | H71: =I71*12 -> 3.4753269e+08 | I71: 28961058 | J71: =$I$71/($K$5*1000) -> 1.2043878 | K71: =($I$71/$K$6)/$K$5 -> 0.075274236

Sheet MTC
C1: working days | F1: working days
B2: Summary - PM Electrical | C2: ='September - 2024'!AM6 -> 27 | E2: Summary - PM Mechanical | F2: ='September - 2024'!AM6 -> 27
B3: Consumable Item | C3: Total Price | E3: Consumable Item | F3: Total Price
C4: Per Day | F4: Per Day
B5: Biaya Pemeliharaan Unit Refinery(Listrik) | C5: 1648879.6 | E5: Biaya Pemeliharaan Unit Refinery | F5: 4911824.3
B6: HP Boiler | C6: 2678431.4 | E6: Biaya Pemeliharaan Unit Fraksinasi | F6: 1230672.3
B7: Dry Fractination - Crystalizer & Filter Press | C7: 288459.38 | E7: Biaya Pemeliharaan Unit Cooling Tower | F7: 1084733.9
B8: Physical Refinery-Bleaching and Deodorization | C8: 404271.71 | E8: Biaya Pemeliharaan Unit Packaging | F8: 833815.52
B9: BOILER | C9: 150891.4 | E9: Biaya Pemeliharaan Unit Material Handling | F9: 949299.72
B10: Water Plant, Effluent & Hydrant | C10: 58543.417 | E10: Biaya Pemeliharaan Unit Utility | F10: 1106022.4
B11: Pump House | C11: 87425.77 | E11: Barang Consumable Maintenance | F11: 5634698.9
B12: DCS-CCR ISBL | C12: 254341.74
B13: Lighting All Area | C13: 114733.89 | E13: Total | F13: =SUM(F5:F12) -> 15751067
B14: Consumable | C14: 203159.66 | E14: Total/Month | F14: =F13*F2 -> 4.2527881e+08
B15: Kalibrasi Instrument Pabrik | C15: 580672.27 | E15: Total/Yearly | F15: =F14*12 -> 5.1033457e+09
B16: Service Special Equipment | C16: 4089635.9
B17: Total/Day | C17: =SUM(C5:C16) -> 10559446 | E17: TOTAL COST
B18: Total/Month | C18: =C17*C2 -> 2.8510504e+08 | E18: PM E + PM M | F18: =F14+C18 -> 7.1038385e+08
B19: Total/Yearly | C19: =C18*12 -> 3.4212605e+09 | E19: TOTAL | F19: =F18*12 -> 8.5246062e+09

Sheet LOG
B2: Port Cost Kuala Tanjung
B3: Through Put CPO Proses | J3: TPD | K3: ='HPP REF '!N3 -> 890.60333
B4: Working Day | J4: Day | K4: ='HPP REF '!N4 -> 27
B5: Total CPO Refined | J5: TPM | K5: =K4*K3 -> 24046.29
B6: Kurs Rupiah | K6: =[21]Formula!I6 -> 16000
B7: No | C7: Description | G7: Norma | I7: Total Biaya ( Rp ) | J7: RP/KG | K7: USD/MT
B8: 1 | C8: Trucking Komoditi ke Kuala Tanjung | E8: Olein ( Ton ) | F8: =(100%-0.8%-1.1*5%)*80%*K5 -> 18025.099 | G8: Rp/Kg | H8: 90 | I8: =H8*F8*1000 -> 1.6222589e+09 | J8: =I8/($K$5*1000) -> 67.464 | K8: =(I8/$K$6)/$K$5 -> 4.2165
E9: Stearin ( Ton ) Iso Tank | F9: =(100%-0.8%-1.1*5%)*20%*K5 -> 4506.2747 | G9: Rp/Kg | H9: 150 | I9: =H9*F9*1000 -> 6.7594121e+08 | J9: =I9/($K$5*1000) -> 28.11 | K9: =(I9/$K$6)/$K$5 -> 1.756875
E10: PFAD ( Ton ) Iso Tank | F10: =1.1*5%*K5 -> 1322.546 | G10: Rp/Kg | H10: 150 | I10: =H10*F10*1000 -> 1.9838189e+08 | J10: =I10/($K$5*1000) -> 8.25 | K10: =(I10/$K$6)/$K$5 -> 0.515625
B11: 2 | C11: Sewa Tank PTI Total Volume : 24.000 MT ( 5 Unit ) | E11: Tank 8.000 MT >> Olein | F11: 1 | G11: Rp/Kg | H11: 77 | I11: =H11*8000*F11*1000 -> 616000000 | J11: =I11/($K$5*1000) -> 25.617257 | K11: =(I11/$K$6)/$K$5 -> 1.6010786
E12: Tank 5.000 MT >> Stearin | F12: 2 | G12: Rp/Kg | H12: 79 | I12: =H12*5000*F12*1000 -> 790000000 | J12: =I12/($K$5*1000) -> 32.853301 | K12: =(I12/$K$6)/$K$5 -> 2.0533313
E13: Tank 3.000 MT >> RBDPO | F13: 1 | G13: Rp/Kg | H13: 77 | I13: =H13*3000*F13*1000 -> 231000000 | J13: =I13/($K$5*1000) -> 9.6064715 | K13: =(I13/$K$6)/$K$5 -> 0.60040447
E14: Tank 3.000 MT S/S >> PFAD | F14: 1 | G14: Rp/Kg | H14: 83 | I14: =H14*3000*F14*1000 -> 249000000 | J14: =I14/($K$5*1000) -> 10.355028 | K14: =(I14/$K$6)/$K$5 -> 0.64718923
B15: 3 | C15: Finalty Over Capacity dari tank | D15: =[21]Formula!F14 -> 1 | E15: Over Volume Olein | F15: =F8-(8000*D15) -> 10025.099 | G15: Rp/Kg | H15: 43 | I15: =H15*F15*1000 -> 4.3107926e+08 | J15: =I15/($K$5*1000) -> 17.927059 | K15: =(I15/$K$6)/$K$5 -> 1.1204412
D16: 0 | E16: Over Volume Stearin | F16: =F9-(10000*D16) -> 4506.2747 | G16: Rp/Kg | H16: 43 | I16: =H16*F16*1000 -> 1.9376981e+08 | J16: =I16/($K$5*1000) -> 8.0582 | K16: =(I16/$K$6)/$K$5 -> 0.5036375
D17: 0 | E17: Over Volume PFAD | F17: =F10-(3000*D17) -> 1322.546 | G17: Rp/Kg | H17: 43 | I17: =H17*F17*1000 -> 56869476 | J17: =I17/($K$5*1000) -> 2.365 | K17: =(I17/$K$6)/$K$5 -> 0.1478125
B18: 3 | C18: Beban Instalasi Pemompaan dan Pemanasan | E18: Total Volume | F18: =SUM(F8:F10) -> 23853.92 | G18: Rp/Kg | H18: 22 | I18: =H18*F18*1000 -> 5.2478623e+08 | J18: =I18/($K$5*1000) -> 21.824 | K18: =(I18/$K$6)/$K$5 -> 1.364
B19: =B18+1 -> 4 | C19: Pompa | E19: Total Volume | F19: =F18 -> 23853.92 | G19: Rp/Kg | H19: 26 | I19: =H19*F18*1000 -> 6.2020191e+08 | J19: =I19/($K$5*1000) -> 25.792 | K19: =(I19/$K$6)/$K$5 -> 1.612
B20: =B19+1 -> 5 | C20: Beban Analisa ( Surveyor ) | E20: Total Volume | F20: =F18 -> 23853.92 | G20: Rp/Kg | H20: 3 | I20: =H20*F20*1000 -> 71561759 | J20: =I20/($K$5*1000) -> 2.976 | K20: =(I20/$K$6)/$K$5 -> 0.186
B21: =B20+1 -> 6 | C21: Beban Pelabuhan ( Documen-Documen Pelabuhan ) | E21: Total Volume | F21: =F20 -> 23853.92 | G21: Rp/Kg | H21: 3 | I21: =H21*F21*1000 -> 71561759 | J21: =I21/($K$5*1000) -> 2.976 | K21: =(I21/$K$6)/$K$5 -> 0.186
B22: =B21+1 -> 7 | C22: Beban Asuransi (Cost Insurance Freight)
B23: =B22+1 -> 8 | C23: Beban Sewa Kapal
B24: =B23+1 -> 9 | C24: Beban Pengangkutan Di Pelabuhan
B25: Total Biaya Transfer Product ke Kuala Tanjung Port | I25: =SUM(I8:I24) -> 6.3524122e+09 | J25: =SUM(J8:J24) -> 264.17432 | K25: =SUM(K8:K24) -> 16.510895

Sheet OH
B2: Overhead ( OH )
B3: Through Put CPO Proses | H3: TPD | I3: ='HPP REF '!N3 -> 890.60333
B4: Working Day | H4: Day | I4: ='SUMMARY HPP '!I4 -> 27
B5: Total CPO Refined | H5: TPM | I5: =I4*I3 -> 24046.29
B6: Kurs Rupiah | I6: =[21]Formula!I6 -> 16000
B7: No | C7: Description | D7: Actual 2023 (Audited) | F7: Budget 2024
D8: Years | E8: Month | F8: Years | G8: Month | H8: RP/KG | I8: USD/MT
B9: 1 | C9: Biaya Perjalanan Dinas (Dalam Provinsi) | D9: 305458258 | E9: =IFERROR(D9/12,0) -> 25454855 | F9: =G9*12 -> 3.6654991e+08 | G9: 30545826 | H9: =G9/($I$5*1000) -> 1.2702927 | I9: =(G9/$I$6)/$I$5 -> 0.079393292
B10: =B9+1 -> 2 | C10: Biaya Perjalanan Dinas (Luar Provinsi) | D10: 2.6287295e+09 | E10: =IFERROR(D10/12,0) -> 2.1906079e+08 | F10: =G10*12 -> 3.5487849e+09 | G10: 2.9573207e+08 | H10: =G10/($I$5*1000) -> 12.298449 | I10: =(G10/$I$6)/$I$5 -> 0.76865306
B11: =B10+1 -> 3 | C11: Beban BBM Kendaraan | D11: 720175678 | E11: =IFERROR(D11/12,0) -> 60014640 | F11: =G11*12 -> 7.5618446e+08 | G11: 63015372 | H11: =G11/($I$5*1000) -> 2.620586 | I11: =(G11/$I$6)/$I$5 -> 0.16378663
B12: =B11+1 -> 4 | C12: Beban Sewa Kendaraan | D12: 2428347903 | E12: =IFERROR(D12/12,0) -> 2.0236233e+08 | F12: =G12*12 -> 2220000000 | G12: 185000000 | H12: =G12/($I$5*1000) -> 7.6934945 | I12: =(G12/$I$6)/$I$5 -> 0.48084341
B13: =B12+1 -> 5 | C13: Beban Kendaraan Lainnya | D13: 110862850 | E13: =IFERROR(D13/12,0) -> 9238570.8 | F13: =G13*12 -> 110862850 | G13: 9238570.8 | H13: =G13/($I$5*1000) -> 0.38419943 | I13: =(G13/$I$6)/$I$5 -> 0.024012464
B14: =B13+1 -> 6 | C14: Beban Sewa Bangunan / Inventaris / Aset | D14: 126990400 | E14: =IFERROR(D14/12,0) -> 10582533 | F14: =G14*12 -> 110000400 | G14: 9166700 | H14: =G14/($I$5*1000) -> 0.38121057 | I14: =(G14/$I$6)/$I$5 -> 0.023825661
B15: =B14+1 -> 7 | C15: Beban Penelitian, Percobaan & Pengembangan | D15: 108868060 | E15: =IFERROR(D15/12,0) -> 9072338.3 | F15: =G15*12 -> 100000000 | G15: 8333333.3 | H15: =G15/($I$5*1000) -> 0.34655381 | I15: =(G15/$I$6)/$I$5 -> 0.021659613
B16: =B15+1 -> 8 | C16: Beban Pemeliharaan Bangunan Rumah | D16: 203000 | E16: =IFERROR(D16/12,0) -> 16916.667 | F16: =G16*12 -> 0 | G16: 0 | H16: =G16/($I$5*1000) -> 0 | I16: =(G16/$I$6)/$I$5 -> 0
B17: =B16+1 -> 9 | C17: Beban Pemeliharaan Bangunan Perusahaan | D17: 108952486 | E17: =IFERROR(D17/12,0) -> 9079373.8 | F17: =G17*12 -> 1.1440011e+08 | G17: 9533342.5 | H17: =G17/($I$5*1000) -> 0.39645794 | I17: =(G17/$I$6)/$I$5 -> 0.024778621
B18: =B17+1 -> 10 | C18: Beban Pemeliharaan Mesin & Instalansi | D18: 32369030 | E18: =IFERROR(D18/12,0) -> 2697419.2 | F18: =G18*12 -> 33987482 | G18: 2832290.1 | H18: =G18/($I$5*1000) -> 0.11778491 | I18: =(G18/$I$6)/$I$5 -> 0.0073615569
B19: =B18+1 -> 11 | C19: Beban Pemeliharaan Jalan, Jembatan & Saluran Air | D19: 179265600 | E19: =IFERROR(D19/12,0) -> 14938800 | F19: =G19*12 -> 188228880 | G19: 15685740 | H19: =G19/($I$5*1000) -> 0.65231435 | I19: =(G19/$I$6)/$I$5 -> 0.040769647
B20: =B19+1 -> 12 | C20: Beban Pemeliharaan Alat Inventaris Kecil | D20: 253700695 | E20: =IFERROR(D20/12,0) -> 21141725 | F20: =G20*12 -> 2.6638573e+08 | G20: 22198811 | H20: =G20/($I$5*1000) -> 0.92316989 | I20: =(G20/$I$6)/$I$5 -> 0.057698118
B21: =B20+1 -> 13 | C21: Beban Pemakaian Inventaris Kecil | D21: 1859843066 | E21: =IFERROR(D21/12,0) -> 1.5498692e+08 | F21: =G21*12 -> 335473201 | G21: 27956100 | H21: =G21/($I$5*1000) -> 1.1625951 | I21: =(G21/$I$6)/$I$5 -> 0.072662197
B22: =B21+1 -> 14 | C22: Beban Iuran, Sumbangan, & Bina Lingkungan | D22: 694460474 | E22: =IFERROR(D22/12,0) -> 57871706 | F22: =G22*12 -> 2.6839105e+08 | G22: 22365921 | H22: =G22/($I$5*1000) -> 0.93011941 | I22: =(G22/$I$6)/$I$5 -> 0.058132463
B23: =B22+1 -> 15 | C23: Beban Instansi Kelembagaan | E23: =IFERROR(D23/12,0) -> 0 | F23: =G23*12 -> 60000000 | G23: 5000000 | H23: =G23/($I$5*1000) -> 0.20793228 | I23: =(G23/$I$6)/$I$5 -> 0.012995768
B24: =B23+1 -> 16 | C24: Beban Pajak & Retribusi | D24: 659276883 | E24: =IFERROR(D24/12,0) -> 54939740 | F24: =G24*12 -> 1518332400 | G24: 126527700 | H24: =G24/($I$5*1000) -> 5.2618387 | I24: =(G24/$I$6)/$I$5 -> 0.32886492
B25: =B24+1 -> 17 | C25: Beban Premi Assuransi | E25: =IFERROR(D25/12,0) -> 0 | F25: =G25*12 -> 197000000 | G25: 16416667 | H25: =G25/($I$5*1000) -> 0.682711 | I25: =(G25/$I$6)/$I$5 -> 0.042669437
B26: =B25+1 -> 18 | C26: Beban Penerangan | D26: 62716328 | E26: =IFERROR(D26/12,0) -> 5226360.7 | F26: =G26*12 -> 80400000 | G26: 6700000 | H26: =G26/($I$5*1000) -> 0.27862926 | I26: =(G26/$I$6)/$I$5 -> 0.017414329
B27: =B26+1 -> 19 | C27: Beban Persediaan Air | D27: 1756590 | E27: =IFERROR(D27/12,0) -> 146382.5 | F27: =G27*12 -> 6840000 | G27: 570000 | H27: =G27/($I$5*1000) -> 0.02370428 | I27: =(G27/$I$6)/$I$5 -> 0.0014815175
B28: =B27+1 -> 20 | C28: Beban Pemakaian Perlengkapan Kantor | D28: 1.1936208e+09 | E28: =IFERROR(D28/12,0) -> 99468402 | F28: =G28*12 -> 1.1936208e+09 | G28: 99468402 | H28: =G28/($I$5*1000) -> 4.1365384 | I28: =(G28/$I$6)/$I$5 -> 0.25853365
B29: =B28+1 -> 21 | C29: Beban Pengendalian Lingkungan (ISO 14000) | D29: 488020500 | E29: =IFERROR(D29/12,0) -> 40668375 | F29: =G29*12 -> 264000000 | G29: 22000000 | H29: =G29/($I$5*1000) -> 0.91490205 | I29: =(G29/$I$6)/$I$5 -> 0.057181378
B30: =B29+1 -> 22 | C30: Beban Sistem Manajemen Keselamatan & Kesehatan Kerja (SMK3) | D30: 68171900 | E30: =IFERROR(D30/12,0) -> 5680991.7 | F30: =G30*12 -> 258000000 | G30: 21500000 | H30: =G30/($I$5*1000) -> 0.89410882 | I30: =(G30/$I$6)/$I$5 -> 0.055881801
B31: =B30+1 -> 23 | C31: Beban Pendidikan & Pengembangan SDM | D31: 1186354647 | E31: =IFERROR(D31/12,0) -> 98862887 | F31: =G31*12 -> 10000000 | G31: 833333.33 | H31: =G31/($I$5*1000) -> 0.034655381 | I31: =(G31/$I$6)/$I$5 -> 0.0021659613
B32: =B31+1 -> 24 | C32: Beban Audit (Independent Auditor) | D32: 8.477783e+08 | E32: =IFERROR(D32/12,0) -> 70648192 | F32: =G32*12 -> 9.0712278e+08 | G32: 75593565 | H32: =G32/($I$5*1000) -> 3.1436685 | I32: =(G32/$I$6)/$I$5 -> 0.19647928
B33: =B32+1 -> 25 | C33: Beban Konsultan - Eksternal | D33: 245454645 | E33: =IFERROR(D33/12,0) -> 20454554 | F33: =G33*12 -> 2.7000011e+08 | G33: 22500009 | H33: =G33/($I$5*1000) -> 0.93569566 | I33: =(G33/$I$6)/$I$5 -> 0.058480979
B34: =B33+1 -> 26 | C34: Beban Insentif Karyawan | E34: =IFERROR(D34/12,0) -> 0 | F34: =G34*12 -> 0 | G34: 0 | H34: =G34/($I$5*1000) -> 0 | I34: =(G34/$I$6)/$I$5 -> 0
B35: =B34+1 -> 27 | C35: Beban Jasa Produksi Karyawan | E35: =IFERROR(D35/12,0) -> 0 | F35: =G35*12 -> 0 | G35: 0 | H35: =G35/($I$5*1000) -> 0 | I35: =(G35/$I$6)/$I$5 -> 0
B36: =B35+1 -> 28 | C36: Beban Uang Jasa (Jubilium, SHT, Dll) | D36: 188207400 | E36: =IFERROR(D36/12,0) -> 15683950 | F36: =G36*12 -> 207028140 | G36: 17252345 | H36: =G36/($I$5*1000) -> 0.7174639 | I36: =(G36/$I$6)/$I$5 -> 0.044841494
B37: =B36+1 -> 29 | C37: Beban Imbalan Pasca Kerja | D37: 4384212523 | E37: =IFERROR(D37/12,0) -> 3.6535104e+08 | F37: =G37*12 -> 666345107 | G37: 55528759 | H37: =G37/($I$5*1000) -> 2.3092443 | I37: =(G37/$I$6)/$I$5 -> 0.14432777
B38: =B37+1 -> 30 | C38: Beban Pengurusan Sertifikasi / Hak Merk / Izin / Dll | D38: 108648500 | E38: =IFERROR(D38/12,0) -> 9054041.7 | F38: =G38*12 -> 114080925 | G38: 9506743.8 | H38: =G38/($I$5*1000) -> 0.39535179 | I38: =(G38/$I$6)/$I$5 -> 0.024709487
B39: =B38+1 -> 31 | C39: Beban Entertainment | D39: 80056015 | E39: =IFERROR(D39/12,0) -> 6671334.6 | F39: =G39*12 -> 0 | G39: 0 | H39: =G39/($I$5*1000) -> 0 | I39: =(G39/$I$6)/$I$5 -> 0
B40: =B39+1 -> 32 | C40: Beban Akomodasi Rapat | D40: 84564877 | E40: =IFERROR(D40/12,0) -> 7047073.1 | F40: =G40*12 -> 88793121 | G40: 7399426.7 | H40: =G40/($I$5*1000) -> 0.30771594 | I40: =(G40/$I$6)/$I$5 -> 0.019232246
B41: =B40+1 -> 33 | C41: Beban Bonus Karyawan | E41: =IFERROR(D41/12,0) -> 0 | F41: =G41*12 -> 0 | G41: 0 | H41: =G41/($I$5*1000) -> 0 | I41: =(G41/$I$6)/$I$5 -> 0
B42: =B41+1 -> 34 | C42: Beban Tantiem | E42: =IFERROR(D42/12,0) -> 0 | F42: =G42*12 -> 0 | G42: 0 | H42: =G42/($I$5*1000) -> 0 | I42: =(G42/$I$6)/$I$5 -> 0
B43: =B42+1 -> 35 | C43: Beban Konsumsi | D43: 3864122096 | E43: =IFERROR(D43/12,0) -> 3.2201017e+08 | F43: =G43*12 -> 2223000000 | G43: 185250000 | H43: =G43/($I$5*1000) -> 7.7038911 | I43: =(G43/$I$6)/$I$5 -> 0.4814932
B44: =B43+1 -> 36 | C44: Beban Ekstra Fooding | D44: 810000 | E44: =IFERROR(D44/12,0) -> 67500 | F44: =G44*12 -> 0 | G44: 0 | H44: =G44/($I$5*1000) -> 0 | I44: =(G44/$I$6)/$I$5 -> 0
B45: =B44+1 -> 37 | C45: Beban Pemeriksaan Kesehatan / Perobatan | D45: 185612516 | E45: =IFERROR(D45/12,0) -> 15467710 | F45: =G45*12 -> 41405668 | G45: 3450472.3 | H45: =G45/($I$5*1000) -> 0.14349292 | I45: =(G45/$I$6)/$I$5 -> 0.0089683074
B46: =B45+1 -> 38 | C46: Beban Peringatan Hari Besar | D46: 300000 | E46: =IFERROR(D46/12,0) -> 25000 | F46: =G46*12 -> 25000000 | G46: 2083333.3 | H46: =G46/($I$5*1000) -> 0.086638452 | I46: =(G46/$I$6)/$I$5 -> 0.0054149032
B47: =B46+1 -> 39 | C47: Beban Perlengkapan Karyawan | D47: 497881607 | E47: =IFERROR(D47/12,0) -> 41490134 | F47: =G47*12 -> 420000000 | G47: 35000000 | H47: =G47/($I$5*1000) -> 1.455526 | I47: =(G47/$I$6)/$I$5 -> 0.090970374
B48: =B47+1 -> 40 | C48: Beban Keperluan Dapur / Pantry | D48: 79298165 | E48: =IFERROR(D48/12,0) -> 6608180.4 | F48: =G48*12 -> 12458700 | G48: 1038225 | H48: =G48/($I$5*1000) -> 0.043176099 | I48: =(G48/$I$6)/$I$5 -> 0.0026985062
B49: =B48+1 -> 41 | C49: Beban Employee Gathering | E49: =IFERROR(D49/12,0) -> 0 | F49: =G49*12 -> 250000000 | G49: 20833333 | H49: =G49/($I$5*1000) -> 0.86638452 | I49: =(G49/$I$6)/$I$5 -> 0.054149032
B50: =B49+1 -> 42 | C50: Beban Kebersihan | D50: 11059767 | E50: =IFERROR(D50/12,0) -> 921647.25 | F50: =G50*12 -> 0 | G50: 0 | H50: =G50/($I$5*1000) -> 0 | I50: =(G50/$I$6)/$I$5 -> 0
D51: =SUM(D9:D50) -> 2.3796151e+10 | E51: =SUM(E9:E50) -> 1.9830126e+09 | F51: =SUM(F9:F50) -> 1.7232677e+10 | G51: =SUM(G9:G50) -> 1.4360564e+09 | H51: =SUM(H9:H50) -> 59.720497 | I51: =SUM(I9:I50) -> 3.7325311

Sheet Convert Gas
B3: CONVERT PEMAKAIAN GAS HP BOILER & MP BOILER
D4: 2024
C5: HP BOILER | F5: TOTAL CORRECTED VOLUME (Sm3) | K5: ENERGY MP BOILER (MMBTU) | L5: TOTAL GAS CONSUMPTION (MMBTU) | M5: PERCENTAGE
C6: UNCORRECTED VOLUME (UV) (m3) | D6: PRESS. Bar | E6: CORRECTED VOLUME (CV) (Sm3) | G6: Convert Sm3 to SCF | H6: VOLUME (MSCF) | I6: HEATING VALUE (BTU / SCF) | J6: ENERGY HP BOILER (MMBTU) | M6: HP Boiler | N6: MP Boiler
C7: 1 | D7: 2 | E7: 3 = 1 x 2 | F7: 4 = 3 | G7: 5 | H7: 6 = (4 x 5) / 1000 | I7: 7 | J7: 8 = (6 x 7) / 1000 | K7: 9 = 10 - 8 | L7: 10 | M7: 11 = 8 / 10 | N7: 12 = 9 / 10
B8: 1 | C8: 750.8 | D8: 5 | E8: =C8*D8 -> 3754 | F8: =E8 -> 3754 | G8: 35.314667 | H8: =(F8*G8)/1000 -> 132.57126 | I8: 1063.6404 | J8: =(H8*I8)/1000 -> 141.00815 | K8: =L8-J8 -> -141.00815 | M8: =(J8/L8) -> #DIV/0! | N8: =K8/L8 -> #DIV/0!
B9: =B8+1 -> 2 | C9: 928.9 | D9: 5 | E9: =C9*D9 -> 4644.5 | F9: =E9 -> 4644.5 | G9: 35.314667 | H9: =(F9*G9)/1000 -> 164.01897 | I9: 1063.7814 | J9: =(H9*I9)/1000 -> 174.48033 | K9: =L9-J9 -> -174.48033 | M9: =(J9/L9) -> #DIV/0! | N9: =K9/L9 -> #DIV/0!
B10: =B9+1 -> 3 | C10: 1286 | D10: 5 | E10: =C10*D10 -> 6430 | F10: =E10 -> 6430 | G10: 35.314667 | H10: =(F10*G10)/1000 -> 227.07331 | I10: 1064.493 | J10: =(H10*I10)/1000 -> 241.71796 | K10: =L10-J10 -> -241.71796 | M10: =(J10/L10) -> #DIV/0! | N10: =K10/L10 -> #DIV/0!
B11: =B10+1 -> 4 | C11: 1351.5 | D11: 5 | E11: =C11*D11 -> 6757.5 | F11: =E11 -> 6757.5 | G11: 35.314667 | H11: =(F11*G11)/1000 -> 238.63886 | I11: 1065.46 | J11: =(H11*I11)/1000 -> 254.26015 | K11: =L11-J11 -> -254.26015 | M11: =(J11/L11) -> #DIV/0! | N11: =K11/L11 -> #DIV/0!
B12: =B11+1 -> 5 | C12: 673.7 | D12: 5 | E12: =C12*D12 -> 3368.5 | F12: =E12 -> 3368.5 | G12: 35.314667 | H12: =(F12*G12)/1000 -> 118.95746 | I12: 1064.3053 | J12: =(H12*I12)/1000 -> 126.60705 | K12: =L12-J12 -> -126.60705 | M12: =(J12/L12) -> #DIV/0! | N12: =K12/L12 -> #DIV/0!
B13: =B12+1 -> 6 | C13: 736.9 | D13: 5 | E13: =C13*D13 -> 3684.5 | F13: =E13 -> 3684.5 | G13: 35.314667 | H13: =(F13*G13)/1000 -> 130.11689 | I13: 1059.8926 | J13: =(H13*I13)/1000 -> 137.90993 | K13: =L13-J13 -> -137.90993 | M13: =(J13/L13) -> #DIV/0! | N13: =K13/L13 -> #DIV/0!
B14: =B13+1 -> 7 | C14: 681.7 | D14: 5 | E14: =C14*D14 -> 3408.5 | F14: =E14 -> 3408.5 | G14: 35.314667 | H14: =(F14*G14)/1000 -> 120.37004 | I14: 1063.2268 | J14: =(H14*I14)/1000 -> 127.98066 | K14: =L14-J14 -> -127.98066 | M14: =(J14/L14) -> #DIV/0! | N14: =K14/L14 -> #DIV/0!
B15: =B14+1 -> 8 | C15: 402.4 | D15: 5 | E15: =C15*D15 -> 2012 | F15: =E15 -> 2012 | G15: 35.314667 | H15: =(F15*G15)/1000 -> 71.05311 | I15: 1067.715 | J15: =(H15*I15)/1000 -> 75.864469 | K15: =L15-J15 -> -75.864469 | M15: =(J15/L15) -> #DIV/0! | N15: =K15/L15 -> #DIV/0!
B16: =B15+1 -> 9 | C16: 1008 | D16: 5 | E16: =C16*D16 -> 5040 | F16: =E16 -> 5040 | G16: 35.314667 | H16: =(F16*G16)/1000 -> 177.98592 | I16: 1067.715 | J16: =(H16*I16)/1000 -> 190.03823 | K16: =L16-J16 -> -190.03823 | M16: =(J16/L16) -> #DIV/0! | N16: =K16/L16 -> #DIV/0!
B17: =B16+1 -> 10 | C17: 1307.1 | D17: 5 | E17: =C17*D17 -> 6535.5 | F17: =E17 -> 6535.5 | G17: 35.314667 | H17: =(F17*G17)/1000 -> 230.79901 | I17: 1065.3777 | J17: =(H17*I17)/1000 -> 245.88812 | K17: =L17-J17 -> -245.88812 | M17: =(J17/L17) -> #DIV/0! | N17: =K17/L17 -> #DIV/0!
B18: =B17+1 -> 11 | C18: 1361.4 | D18: 5 | E18: =C18*D18 -> 6807 | F18: =E18 -> 6807 | G18: 35.314667 | H18: =(F18*G18)/1000 -> 240.38694 | I18: 1069.3462 | J18: =(H18*I18)/1000 -> 257.05687 | K18: =L18-J18 -> -257.05687 | M18: =(J18/L18) -> #DIV/0! | N18: =K18/L18 -> #DIV/0!
B19: =B18+1 -> 12 | C19: 645.6 | D19: 5 | E19: =C19*D19 -> 3228 | F19: =E19 -> 3228 | G19: 35.314667 | H19: =(F19*G19)/1000 -> 113.99575 | I19: 1051.8029 | J19: =(H19*I19)/1000 -> 119.90105 | K19: =L19-J19 -> -119.90105 | M19: =(J19/L19) -> #DIV/0! | N19: =K19/L19 -> #DIV/0!
B20: =B19+1 -> 13 | C20: 848.8 | D20: 5 | E20: =C20*D20 -> 4244 | F20: =E20 -> 4244 | G20: 35.314667 | H20: =(F20*G20)/1000 -> 149.87545 | I20: 1056.0701 | J20: =(H20*I20)/1000 -> 158.27897 | K20: =L20-J20 -> -158.27897 | M20: =(J20/L20) -> #DIV/0! | N20: =K20/L20 -> #DIV/0!
... B37: =B36+1 -> 30 | C37: 809.9 | D37: 5 | E37: =C37*D37 -> 4049.5 | F37: =E37 -> 4049.5 | G37: 51.314667 | H37: =(F37*G37)/1000 -> 207.79874 | I37: 1041.5933 | J37: =(H37*I37)/1000 -> 216.44177 | K37: =L37-J37 -> -216.44177 | M37: =(J37/L37) -> #DIV/0! | N37: =K37/L37 -> #DIV/0!
B38: =B37+1 -> 31 | D38: 5 | E38: =C38*D38 -> 0 | F38: =E38 -> 0 | G38: 52.314667 | H38: =(F38*G38)/1000 -> 0 | J38: =(H38*I38)/1000 -> 0 | K38: =L38-J38 -> 0 | M38: =(J38/L38) -> #DIV/0! | N38: =K38/L38 -> #DIV/0!
B39: Average | F39: =AVERAGE(F8:F38) -> 4473.129 | H39: =AVERAGE(H8:H38) -> 179.39688 | I39: =AVERAGE(I8:I38) -> 1055.7775 | J39: =AVERAGE(J8:J38) -> 189.31077 | K39: =AVERAGE(K8:K38) -> -189.31077 | L39: =AVERAGE(L8:L38) -> #DIV/0! | M39: =AVERAGE(M8:M38) -> #DIV/0! | N39: =AVERAGE(N8:N38) -> #DIV/0!
B40: TOTAL | C40: =SUM(C8:C38) -> 27733.4 | E40: =SUM(E8:E38) -> 138667 | F40: =SUM(F8:F38) -> 138667 | H40: =SUM(H8:H38) -> 5561.3034 | J40: =SUM(J8:J38) -> 5868.634
B41: Koreksi
B42: Total Setelah Koreksi | H42: =H40+H41 -> 5561.3034 | J42: =J40+J41 -> 5868.634
C44: CONVERT HP Boiler from Utility
C45: =C40 -> 27733.4 | D45: m3 | F45: =C40*5 -> 138667 | G45: 9983.7
C46: 5 | D46: bar | F46: 21286.9 | G46: =G45-C40 -> -17749.7
C47: =C45*C46 -> 138667 | D47: Sm3 | F47: =F45/F46 -> 6.5141942
C48: =G38 -> 52.314667 | D48: Scf
C49: =(C47*C48)/1000 -> 7254.3179 | D49: Volume (MSCF)
C50: =I39 -> 1055.7775 | D50: Heating Value
C51: =(C49*C50)/1000 -> 7658.9453 | D51: Energy (mmbtu)

Sheet OIP Refinery
B2: Oil In Plant Refinery
B4: No | C4: Tanggal | D4: Opening Stock | E4: Closing Stock | F4: Closing Stock | G4: Selisih OIP Consume
B5: 1 | C5: 45536 | D5: 283428 | E5: 258370 | F5: 278115 | G5: =E5-D5 -> -25058
B6: 2 | C6: 45537 | D6: =E5 -> 258370 | E6: 263554 | F6: 218067 | G6: =E6-D6 -> 5184
B7: 3 | C7: 45538 | D7: =E6 -> 263554 | E7: 276348 | F7: 257614 | G7: =E7-D7 -> 12794
B8: 4 | C8: 45539 | D8: =E7 -> 276348 | E8: 261140 | F8: 246851 | G8: =E8-D8 -> -15208
B9: 5 | C9: 45540 | D9: =E8 -> 261140 | E9: 258430 | F9: 255653 | G9: =E9-D9 -> -2710
B10: 6 | C10: 45541 | D10: =E9 -> 258430 | E10: 262670 | F10: 258450 | G10: =E10-D10 -> 4240
B11: 7 | C11: 45542 | D11: =E10 -> 262670 | E11: 266620 | F11: 238552 | G11: =E11-D11 -> 3950
B12: 8 | C12: 45543 | D12: =E11 -> 266620 | E12: 274697 | F12: 283505 | G12: =E12-D12 -> 8077
B13: 9 | C13: 45544 | D13: =E12 -> 274697 | E13: 258292 | F13: 269320 | G13: =E13-D13 -> -16405
B14: 10 | C14: 45545 | D14: =E13 -> 258292 | E14: 260550 | F14: 281809 | G14: =E14-D14 -> 2258
B15: 11 | C15: 45546 | D15: =E14 -> 260550 | E15: 263737 | F15: 267958 | G15: =E15-D15 -> 3187
B16: 12 | C16: 45547 | D16: =E15 -> 263737 | E16: 266193 | F16: 267268 | G16: =E16-D16 -> 2456
B17: 13 | C17: 45548 | D17: =E16 -> 266193 | E17: 286995 | F17: 285895 | G17: =E17-D17 -> 20802
B18: 14 | C18: 45549 | D18: =E17 -> 286995 | E18: 277461 | F18: =286934-27000 -> 259934 | G18: =E18-D18 -> -9534
B19: 15 | C19: 45550 | D19: =E18 -> 277461 | E19: 276869 | F19: =259375-30000 -> 229375 | G19: =E19-D19 -> -592
B20: 16 | C20: 45551 | D20: =E19 -> 276869 | E20: 276843 | F20: 206080 | G20: =E20-D20 -> -26
B21: 17 | C21: 45552 | D21: =E20 -> 276843 | E21: 290612 | F21: 205580 | G21: =E21-D21 -> 13769
B22: 18 | C22: 45553 | D22: =E21 -> 290612 | E22: 288381 | F22: 204650 | G22: =E22-D22 -> -2231
B23: 19 | C23: 45554 | D23: =E22 -> 288381 | E23: 263865 | F23: 204650 | G23: =E23-D23 -> -24516
B24: 20 | C24: 45555 | D24: =E23 -> 263865 | E24: 261183 | F24: =259103-20000 -> 239103 | G24: =E24-D24 -> -2682
B25: 21 | C25: 45556 | D25: =E24 -> 261183 | E25: 252851 | F25: =222878+20000 -> 242878 | G25: =E25-D25 -> -8332
B26: 22 | C26: 45557 | D26: =E25 -> 252851 | E26: 247622 | F26: =222984+20500 -> 243484 | G26: =E26-D26 -> -5229
B27: 23 | C27: 45558 | D27: =E26 -> 247622 | E27: 243430 | F27: 219216 | G27: =E27-D27 -> -4192
B28: 24 | C28: 45559 | D28: =E27 -> 243430 | E28: 247662 | F28: 244970 | G28: =E28-D28 -> 4232
B29: 25 | C29: 45560 | D29: =E28 -> 247662 | E29: 269395 | F29: =209886+25000 -> 234886 | G29: =E29-D29 -> 21733
B30: 26 | C30: 45561 | D30: =E29 -> 269395 | E30: 262439 | F30: 0 | G30: =E30-D30 -> -6956
B31: 27 | C31: 45562 | D31: =E30 -> 262439 | E31: 250429 | F31: 0 | G31: =E31-D31 -> -12010
B32: 28 | C32: 45563 | D32: =E31 -> 250429 | E32: 262606 | F32: 0 | G32: =E32-D32 -> 12177
B33: 29 | C33: 45564 | D33: =E32 -> 262606 | E33: 254790 | F33: 0 | G33: =E33-D33 -> -7816
B34: 30 | C34: 45565 | D34: =E33 -> 254790 | E34: 258530 | F34: 0 | G34: =E34-D34 -> 3740

Sheet OIP Fract
B2: Oil In Plant Fract
B4: No | C4: Tanggal | D4: Opening Stock | E4: Closing Stock | F4: Stock Minyak
B5: 1 | C5: 45536 | D5: 637920 | E5: 245680 | F5: =E5-D5 -> -392240
B6: 2 | C6: 45537 | D6: =E5 -> 245680 | E6: 246050 | F6: =E6-D6 -> 370
B7: 3 | C7: 45538 | D7: =E6 -> 246050 | E7: 381770 | F7: =E7-D7 -> 135720
B8: 4 | C8: 45539 | D8: =E7 -> 381770 | E8: 354940 | F8: =E8-D8 -> -26830
B9: 5 | C9: 45540 | D9: =E8 -> 354940 | E9: 354600 | F9: =E9-D9 -> -340
B10: 6 | C10: 45541 | D10: =E9 -> 354600 | E10: 300810 | F10: =E10-D10 -> -53790
B11: 7 | C11: 45542 | D11: =E10 -> 300810 | E11: 300790 | F11: =E11-D11 -> -20
B12: 8 | C12: 45543 | D12: =E11 -> 300790 | E12: 159610 | F12: =E12-D12 -> -141180
B13: 9 | C13: 45544 | D13: =E12 -> 159610 | E13: 464780 | F13: =E13-D13 -> 305170
B14: 10 | C14: 45545 | D14: =E13 -> 464780 | E14: 354710 | F14: =E14-D14 -> -110070
B15: 11 | C15: 45546 | D15: =E14 -> 354710 | E15: 299810 | F15: =E15-D15 -> -54900
B16: 12 | C16: 45547 | D16: =E15 -> 299810 | E16: 81190 | F16: =E16-D16 -> -218620
B17: 13 | C17: 45548 | D17: =E16 -> 81190 | E17: 33350 | F17: =E17-D17 -> -47840
... B34: 30 | C34: 45565 | D34: =E33 -> 648940 | E34: 509720 | F34: =E34-D34 -> -139220

Sheet Time Sheet Bulanan
A1: Nomor | B1: Tanggal | C1: Keterangan
C2: Refinery | D2: Fraksinasi
A3: 1 | B3: 45536
A4: 2 | B4: 45537
A5: 3 | B5: 45538
A6: 4 | B6: 45539
A7: 5 | B7: 45540
A8: 6 | B8: 45541
A9: 7 | B9: 45542
A10: 8 | B10: 45543
A11: 9 | B11: 45544
A12: 10 | B12: 45545
A13: 11 | B13: 45546
A14: 12 | B14: 45547
... A25: 23 | B25: 45558
A26: 24 | B26: 45559 | C26: Update tgal 24/09/2024 Refinery * 07.00 ref HOLD * 22.00 steam masuk ke plant * 01.20 ref firing hpb * 02.00 sirkulasi * 03.00-07.00 plant HOLD terkait pressure gas HPB drop | D26: Stop sementara & aktifitas cleaning chiller
A27: 25 | B27: 45560 | C27: Refinery * 07.40 start sirkulasi | D27: Fraksinasi * Stop sementara dan pagi ini kunci mainhole chiller pak
A28: 26 | B28: 45561
A29: 27 | B29: 45562
A30: 28 | B30: 45563
A31: 29 | B31: 45564
A32: 30 | B32: 45565

Sheet 2024
C2: PRODUCTION REPORT 2024
B4: No | C4: ITEM | D4: Budget / Norma | E4: UoM | F4: MONTHLY REPORT | S4: Yearly Report | T4: Yearly Report RKAP (Budget) | U4: Yearly Report RKAP
F5: JANUARI | G5: FEBRUARI | H5: MARET | I5: APRIL | J5: MEI | K5: JUNI | L5: JULI | M5: AGUSTUS | N5: SEPTEMBER | O5: OKTOBER | P5: NOVEMBER | Q5: DESEMBER | S5: TOTAL (Kg) | T5: TOTAL (Kg) | U5: TOTAL (%)
B6: 1 | C6: PRODUCTION | S6: Production | T6: Production | U6: Production | DG6: 29 | DH6: 30 | DI6: 31
C7: Refinery | S7: Refinery | T7: Refinery | U7: Refinery | DE7: CPO Olah | DF7: Kg | DG7: 1971320 | DH7: 2015120 | DI7: 2015230 | AIU7: Sounding | AIV7: Production | AIW7: Diff
C8: Running Days | E8: Day | F8: ='[22]Januari 24'!AL9 -> 18 | G8: ='[22]Februari 24'!AL9 -> 11 | H8: ='[22]Maret 24'!AL9 -> 5 | I8: ='[23]April - 24'!$AK$9 -> 0 | J8: ='[24]Mei - 24'!$AL$9 -> 0 | K8: ='[25]Juni - 24'!$AL$9 -> 18 | L8: ='[26]Juli - 2024 ( Revisi )'!$AL$6 -> 22 | M8: ='[27]Agustus - 2024'!$AN$6 -> 0 | N8: ='September - 2024'!$AM$6 -> 27 | O8: ='[22]Oktober 24'!AL9 -> 0 | P8: ='[22]November 24'!AL9 -> 0 | Q8: ='[22]Desember 24'!AL9 -> 0 | S8: =SUM(F8:Q8) -> 101 | T8: 231 | U8: =S8/T8*100 -> 43.722944 | OR8: Poram | AEE8: 14 Juni | AEF8: 15 Juni | AIT8: CPO | AIU8: 11008948 | AIV8: =S11 -> 75717833 | AIW8: =AIU8-AIV8 -> -64708885
C9: Ratio Run CPO | F9: ='[22]Januari 24'!AL10 -> 17.457609 | G9: ='[22]Februari 24'!AL10 -> 17.224767 | H9: ='[22]Maret 24'!AL10 -> 4.5497713 | I9: ='[23]April - 24'!$AK$11 -> 0 | J9: ='[24]Mei - 24'!$AL$11 -> 0 | K9: ='[25]Juni - 24'!$AL$11 -> 13.078035 | L9: ='[26]Juli - 2024 ( Revisi )'!$AL$8 -> 23.454544 | M9: ='[27]Agustus - 2024'!$AN$8 -> 0 | N9: ='September - 2024'!$AM$8 -> 40.48197 | O9: ='[22]Oktober 24'!AL10 -> 0 | P9: ='[22]November 24'!AL10 -> 0 | Q9: ='[22]Desember 24'!AL10 -> 0
C10: Utilitas CPO | F10: =F11/F14*100 -> 18.288923 | G10: =G11/G14*100 -> 25.986707 | H10: =H11/H14*100 -> 7.9383545 | I10: =I11/I14*100 -> #VALUE! | J10: =J11/J14*100 -> 0 | K10: =K11/K14*100 -> 24.530983 | L10: =L11/L14*100 -> 43.994607 | M10: =M11/M14*100 -> 9.2501421e-07 | ... Q10: =Q11/Q14*100 -> 0 | S10: =AVERAGE(F10:O10) -> #VALUE!
C11: CPO Consume Total | D11: 701400000 | E11: Kg | F11: ='[22]Januari 24'!AL11 -> 11906089 | G11: ='[22]Februari 24'!AL11 -> 11747291 | H11: ='[22]Maret 24'!AL11 -> 3102944 | I11: ='[23]April - 24'!$AK$12 -> 0 | J11: ='[24]Mei - 24'!$AL$12 -> 0 | K11: ='[25]Juni - 24'!$AL$12 -> 8919220 | L11: ='[26]Juli - 2024 ( Revisi )'!$AL$9 -> 15995999 | M11: ='[27]Agustus - 2024'!$AN$9 -> 0.33632592 | N11: ='September - 2024'!$AM$9 -> 24046290 | O11: ='[22]Oktober 24'!AL11 -> 0 | P11: ='[22]November 24'!AL11 -> 0 | Q11: ='[22]Desember 24'!AL11 -> 0 | S11: =SUM(F11:Q11) -> 75717833 | T11: 421374000 | U11: =S11/T11 -> 0.1796927 | V11: =S11/D11 -> 0.10795243 | AX11: =S11/D11 -> 0.10795243 | DE11: HP Boiler | DF11: mmbtu | DG11: 251.19642 | DH11: 257.91391 | DI11: 251.51265 | OO11: 26946.108 | OP11: 17383.234 | OR11: RBDPO Olah | AEE11: =35.8500000000058*1000 -> 35850 | AIT11: PFAD | AIU11: 566885 | AIV11: =S20 -> 3445900 | AIW11: =AIU11-AIV11 -> -2879015
C12: CPO Consume Poram | E12: Kg | F12: ='[22]Januari 24'!AL12 -> 10284033 | G12: ='[22]Februari 24'!AL12 -> 10885811 | H12: ='[22]Maret 24'!AL12 -> 2891954.7 | I12: ='[23]April - 24'!$AK$13 -> 0 | J12: ='[24]Mei - 24'!$AL$13 -> 0 | K12: ='[25]Juni - 24'!$AL$13 -> 8919220 | L12: ='[26]Juli - 2024 ( Revisi )'!$AL$10 -> 15995999 | M12: ='[27]Agustus - 2024'!$AN$10 -> 0 | N12: =N11-N13 -> 24046290 | O12: 0 | P12: ='[22]November 24'!AL12 -> #DIV/0! | Q12: ='[22]Desember 24'!AL12 -> #DIV/0! | S12: =SUM(F12:O12) -> 73023307
C13: CPO Consume Brand | E13: Kg | F13: ='[22]Januari 24'!AL13 -> 1622056.5 | G13: ='[22]Februari 24'!AL13 -> 861480.39 | H13: ='[22]Maret 24'!AL13 -> 210989.34 | I13: 0 | J13: 0 | K13: 0 | L13: ='[26]Juli - 2024 ( Revisi )'!$AL$11 -> 0 | M13: ='[27]Agustus - 2024'!$AN$11 -> 0 | N13: 0 | O13: 0 | P13: ='[22]November 24'!AL13 -> #DIV/0! | Q13: ='[22]Desember 24'!AL13 -> #DIV/0! | S13: =SUM(F13:O13) -> 2694526.2 | AX13: =AW13/P13 -> #DIV/0!
C14: Budget CPO Olah | E14: Kg | F14: 65100000 | G14: 45205000 | H14: 39088000 | I14: ='[23]April - 24'!$C$12 -> CPO Consume Total | J14: ='[24]Mei - 24'!$D$12 -> 36359000 | K14: ='[25]Juni - 24'!$D$12 -> 36359000 | L14: ='[28]Juli - 2024'!$D$9 -> 36359000 | M14: ='[28]Juli - 2024'!D$9 -> 36359000 | N14: ='[28]Juli - 2024'!$D$9 -> 36359000 | O14: ='[28]Juli - 2024'!$D$9 -> 36359000 | P14: ='[28]Juli - 2024'!$D$9 -> 36359000 | Q14: ='[28]Juli - 2024'!$D$9 -> 36359000 | S14: =SUM(F14:Q14) -> 440265000
C15: - FFA | D15: 5 | E15: % | F15: 4.38 | G15: 4.56 | H15: 4.19 | I15: 4.11 | J15: 3.86 | K15: 4.25 | L15: ='[26]Juli - 2024 ( Revisi )'!$AL$12 -> 3.8848485 | M15: ='[27]Agustus - 2024'!$AN$12 -> 0 | N15: ='September - 2024'!AM13 -> 3.6441975 | O15: 0 | P15: ='[22]November 24'!AL14 -> #DIV/0! | Q15: ='[22]Desember 24'!AL14 -> #DIV/0! | S15: =AVERAGE(F15:O15) -> 3.2879046 | T15: =AVERAGE(G15:R15) -> #DIV/0! | U15: =AVERAGE(H15:S15) -> #DIV/0! | DE15: Steam Ref | DF15: Kg | DG15: 182230 | DH15: 190070 | DI15: 197800 | OO15: =S11/1000 -> 75717.833 | OP15: =(S25+S43+S34)/1000 -> 21294.289 | OR15: =SUM(OR16:OR17) -> #REF! | AGV15: 2000
C16: - Moist & Impurities | D16: 0.5 | E16: % | F16: ='[22]Januari 24'!AL15 -> 0.42388889 | G16: ='[22]Februari 24'!AL15 -> 0.43545455 | H16: ='[22]Maret 24'!AL15 -> 0.43 | I16: ='[23]April - 24'!$AK$16 -> 0 | J16: ='[24]Mei - 24'!$AL$16 -> 0 | K16: ='[25]Juni - 24'!$AL$16 -> 0.45375 | L16: ='[26]Juli - 2024 ( Revisi )'!$AL$13 -> 0.41795455 | M16: ='[27]Agustus - 2024'!$AN$13 -> 0 | N16: ='September - 2024'!AM14 -> 0.41401235 | O16: 0 | P16: ='[22]November 24'!AL15 -> #DIV/0! | Q16: ='[22]Desember 24'!AL15 -> #DIV/0! | S16: =AVERAGE(F16:O16) -> 0.25750603 | T16: =AVERAGE(G16:R16) -> #DIV/0! | U16: =AVERAGE(H16:S16) -> #DIV/0! | DF16: Kg/MT | DG16: =DG15/(DG7/1000) -> 92.440598 | DH16: =DH15/(DH7/1000) -> 94.321926 | DI16: =DI15/(DI7/1000) -> 98.152568 | OR16: =#REF!/1000 -> #REF! | OS16: =OR16/OR15*100 -> #REF! | AGU16: 0.942 | AGV16: =AGU16*AGV15 -> 1884 | AGW16: Refinery | AIT16: Olein IV 56 | AIU16: 9594130 | AIV16: =S26 -> 15950222 | AIW16: =AIU16-AIV16 -> -6356092
C17: - DOBI | D17: 2,20 Min | E17: % | F17: ='[22]Januari 24'!AL16 -> 2.2105556 | G17: ='[22]Februari 24'!AL16 -> 2.2127273 | H17: ='[22]Maret 24'!AL16 -> 2.21 | I17: ='[23]April - 24'!$AK$17 -> 0 | J17: ='[24]Mei - 24'!$AL$17 -> 0 | K17: ='[25]Juni - 24'!$AL$17 -> 2.21 | L17: ='[28]Juli - 2024'!$AL$14 -> 2.2135714 | M17: ='[27]Agustus - 2024'!$AN$14 -> 0 | N17: ='September - 2024'!AM15 -> 21.265185 | O17: 0 | P17: ='[22]November 24'!AL16 -> #DIV/0! | Q17: ='[22]Desember 24'!AL16 -> #DIV/0! | S17: =AVERAGE(F17:O17) -> 3.2322039 | T17: =AVERAGE(G17:R17) -> #DIV/0! | U17: =AVERAGE(H17:S17) -> #DIV/0! | OO17: =SUM(OO15:OO16) -> 75717.833 | OP17: =SUM(OP15:OP16) -> 21294.289 | OR17: =#REF!/1000 -> #REF! | OS17: =OR17/OR15*100 -> #REF! | AGU17: 0.05 | AGV17: =AGU17*AGV15 -> 100 | AIT17: Stearin | AIU17: 2161151 | AIV17: =S27 -> 3206375 | AIW17: =AIU17-AIV17 -> -1045224
C18: Product | S18: Product | T18: Product | U18: Product | OO18: =OO17/OO11*100 -> 280.99729 | OP18: =OP17/OP11*100 -> 122.49901 | AEG18: Product OIP | AEQ18: Juni | AER18: Sisa Product OIP
C19: RbdPO | D19: =D51%*D11 -> 660718800 | E19: Kg | F19: ='[22]Januari 24'!AL18 -> 11255730 | G19: ='[22]Februari 24'!AL18 -> 11075536 | H19: ='[22]Maret 24'!AL18 -> 2943785 | I19: ='[23]April - 24'!$AK$19 -> 0 | J19: ='[24]Mei - 24'!$AL$19 -> 0 | K19: ='[25]Juni - 24'!$AL$19 -> 8432668 | L19: ='[26]Juli - 2024 ( Revisi )'!$AL$16 -> 14396709 | M19: ='[27]Agustus - 2024'!$AN$16 -> 0 | N19: ='September - 2024'!$AM$18 -> 22783491 | O19: ='[22]Oktober 24'!AL18 -> 0 | P19: ='[22]November 24'!AL18 -> 0 | Q19: ='[22]Desember 24'!AL18 -> 0 | S19: =SUM(F19:Q19) -> 70887919 | T19: 399336000 | U19: =S19/T19*100 -> 17.751447 | AX19: =AX20/D19 -> 0.090381672 | DE19: Tahun 2021 | AEE19: 136360 | AEF19: 109340 | AEG19: =SUM(AEE19:AEF19) -> 245700 | AEQ19: 34157.88 | AER19: =AEG19-AEQ19 -> 211542.12 | AGV19: =AGV16 -> 1884
C20: PFAD | D20: =D52%*D11 -> 35070000 | E20: Kg | F20: ='[22]Januari 24'!AL19 -> 568791 | G20: ='[22]Februari 24'!AL19 -> 594383 | H20: ='[22]Maret 24'!AL19 -> 137988 | I20: ='[23]April - 24'!$AK$20 -> 0 | J20: ='[24]Mei - 24'!$AL$20 -> 0 | K20: ='[25]Juni - 24'!$AL$20 -> 432588 | L20: ='[26]Juli - 2024 ( Revisi )'!$AL$17 -> 713632 | M20: ='[27]Agustus - 2024'!$AN$17 -> 0 | N20: ='September - 2024'!$AM$19 -> 998518 | O20: ='[22]Oktober 24'!AL19 -> 0 | P20: ='[22]November 24'!AL19 -> 0 | Q20: ='[22]Desember 24'!AL19 -> 0 | S20: =SUM(F20:Q20) -> 3445900 | T20: 19024000 | U20: =S20/T20*100 -> 18.113436 | AX20: =S25+S29+S34+S43+S38 -> 59716870 | DE20: Items | DG20: Agustus | DH20: Oktober | OO20: =OO11-OO17 -> -48771.726 | OP20: =OP11-OP17 -> -3911.0555 | OR20: Olein IV 58 | OS20: 0 | PE20: 564.70507 | PF20: =OS20/PE20*100 -> 0 | AEE20: 13800 | AEF20: 2800 | AEG20: =SUM(AEE20:AEF20) -> 16600 | AEQ20: 1469.85 | AER20: =AEG20-AEQ20 -> 15130.15 | AGU20: 0.75 | AGV20: =AGU20*AGV19 -> 1413
C21: Fractionation
C22: Total Filling Crystalizer ( Feed ) | D22: =399289.3*1000 -> 399289300 | E22: Kg | F22: =F23 -> 6744590 | G22: =G23 -> 7673369 | H22: =H23 -> 1794600 | I22: =I23 -> 0 | J22: =J23 -> 0 | K22: =K23 -> 7764784 | L22: =L23 -> 11686063 | M22: ='[27]Agustus - 2024'!$AN$21 -> 0 | N22: ='September - 2024'!AM23 -> 22592969 | S22: =SUM(F22:N22) -> 58256375 | V22: =S22/D22 -> 0.14590017
C23: Total Proses RBDPO | E23: Kg | F23: =SUM(F25,F29,F34,F38,F43) -> 6744590 | G23: =SUM(G25,G29,G34,G38,G43) -> 7673369 | H23: =SUM(H25,H29,H34,H38,H43) -> 1794600 | I23: =SUM(I25,I29,I34,I38,I43) -> 0 | J23: =SUM(J25,J29,J34,J38,J43) -> 0 | K23: =SUM(K25,K29,K34,K38,K43) -> 7764784 | L23: =SUM(L25,L29,L34,L38,L43) -> 11686063 | M23: =SUM($M$25,$M$29,$M$34,$M$38,$M$43) -> 224749 | N23: ='September - 2024'!AM25 -> 23189025 | S23: =SUM(F23:N23) -> 59077180
C24: Fractionation OLEIN IV 56 | S24: Olein IV 56 | T24: Olein IV 56 | U24: Olein IV 56 | DG24: 24 | DH24: 2 | DI24: 3 | OR24: Olein IV 60 | OS24: =80.53776+PF34 -> 120.78492 | PE24: 4695.7554 | PF24: =OS24/PE24*100 -> 2.5722149 | AGU24: 0.25 | AGV24: =AGU24*AGV19 -> 471
C25: RBDPO Consume | D25: =SUM(D26:D27) -> 0 | E25: Kg | F25: =F26+F27 -> 2379082 | G25: ='[22]Februari 24'!AL21 -> 50570 | H25: ='[22]Maret 24'!AL21 -> 0 | I25: ='[22]April 24'!AL21 -> 0 | J25: ='[22]Mei 24'!AL21 -> 0 | K25: =K26+K27 -> 0 | L25: ='[26]Juli - 2024 ( Revisi )'!$AL$19 -> 0 | M25: ='[27]Agustus - 2024'!$AN$25 -> 0 | N25: =$N$26+$N$27 -> 16566545 | O25: =O26+O27 -> 0 | P25: =P26+P27 -> 0 | Q25: =Q26+Q27 -> 0 | S25: =S26+S27 -> 19156597 | T25: =T26+T27 -> 87311000 | U25: =S25/T25*100 -> 21.940646 | DE25: CPO Olah | DF25: Kg | DG25: 2000530 | DH25: 2005167 | DI25: 2025879 | AEE25: =95.28%*AEE11 -> 34157.88 | AEG25: =AEE19-AEQ19 -> 102202.12 | AIQ25: CPO Feed - Sounding
C26: OLEIN IV 56 | E26: Kg | F26: ='[22]Januari 24'!AL22 -> 1982807 | G26: ='[22]Februari 24'!AL22 -> 42320 | H26: ='[22]Maret 24'!AL22 -> 0 | I26: ='[22]April 24'!AL22 -> 0 | J26: ='[22]Mei 24'!AL22 -> 0 | K26: ='[22]Juny 24'!AL22 -> 0 | L26: ='[26]Juli - 2024 ( Revisi )'!$AL$20 -> 135300 | M26: ='[27]Agustus - 2024'!$AN$26 -> 0 | N26: ='September - 2024'!$AM$29 -> 13789795 | O26: ='[22]Oktober 24'!AL22 -> 0 | P26: ='[22]November 24'!AL22 -> 0 | Q26: ='[22]Desember 24'!AL22 -> 0 | S26: =SUM(F26:Q26) -> 15950222 | T26: 71627000 | U26: =S26/T26*100 -> 22.268449 | DE26: HP Boiler | DF26: mmbtu | DG26: 255.53619 | DH26: 255.09239 | DI26: 260.82455 | OO26: =#REF!/1000 -> #REF! | OR26: INL 900 ml | OS26: 0 | PE26: 9.75348 | PF26: =(OS26*PE26)/1000 -> 0 | AEE26: =4.1%*AEE11 -> 1469.85 | AEG26: =AEE20-AEQ20 -> 12330.15
C27: STEARIN | E27: Kg | F27: ='[22]Januari 24'!AL23 -> 396275 | G27: ='[22]Februari 24'!AL23 -> 8250 | H27: ='[22]Maret 24'!AL23 -> 0 | I27: ='[22]April 24'!AL23 -> 0 | J27: ='[22]Mei 24'!AL23 -> 0 | K27: ='[22]Juny 24'!AL23 -> 0 | L27: ='[26]Juli - 2024 ( Revisi )'!$AL$21 -> 25100 | M27: ='[27]Agustus - 2024'!$AN$27 -> 0 | N27: ='September - 2024'!$AM$30 -> 2776750 | O27: ='[22]Oktober 24'!AL23 -> 0 | P27: ='[22]November 24'!AL23 -> 0 | Q27: ='[22]Desember 24'!AL23 -> 0 | S27: =SUM(F27:Q27) -> 3206375 | T27: 15684000 | U27: =S27/T27*100 -> 20.443605 | DE27: Steam Ref | DF27: Kg | DG27: 146000 | DH27: 151100 | DI27: 152900 | OO27: 1796 | OR27: Salvaco 1L | OS27: 1262 | PE27: 10.86 | PF27: =(OS27*PE27)/1000 -> 13.70532 | AIQ27: Report Prod
C28: Fractionation OLEIN IV 57 ( Bulk ) | S28: Olein IV 57 ( Bulk ) | T28: Olein IV 57 ( Bulk ) | U28: Olein IV 57 ( Bulk )
C29: RBDPO Consume | E29: Kg | F29: =F30+F31 -> 2827867 | G29: ='[29]Februari - 24'!$AL$34 -> 7224129 | H29: ='[22]Maret 24'!AL25 -> 0 | I29: ='[23]April - 24'!$AK$26 -> 0 | J29: ='[22]Mei 24'!AL25 -> 0 | K29: =K30+K31 -> 0 | L29: =L30+L31 -> 0 | M29: =M30+M31 -> 0 | N29: =N30+N31 -> 0 | O29: =O30+O31 -> 0 | P29: =P30+P31 -> 0 | Q29: =Q30+Q31 -> 0 | S29: =S30+S31 -> 10051996 | T29: =T30+T31 -> 5121000 | U29: =S29/T29*100 -> 196.28971 | AX29: =S29+S34 -> 10253377
C30: OLEIN IV 57 | E30: Kg | F30: ='[22]Januari 24'!AL26 -> 2230587 | G30: ='[29]Februari - 24'!$AL$35 -> 5178274 | H30: ='[22]Maret 24'!AL26 -> 0 | I30: ='[23]April - 24'!$AK$27 -> 0 | J30: ='[22]Mei 24'!AL26 -> 0 | K30: ='[22]Juny 24'!AL26 -> 0 | L30: ='[22]July 24'!AL26 -> 0 | M30: ='[22]Agustus 24'!AL26 -> 0 | N30: ='[22]September 24'!AL26 -> 0 | O30: ='[22]Oktober 24'!AL26 -> 0 | P30: ='[22]November 24'!AL26 -> 0 | Q30: ='[22]Desember 24'!AL26 -> 0 | S30: =SUM(F30:Q30) -> 7408861 | T30: 3934000 | U30: =S30/T30*100 -> 188.32895 | AX30: =S30+S35 -> 7560308
C31: STEARIN | E31: Kg | F31: ='[22]Januari 24'!AL27 -> 597280 | G31: ='[29]Februari - 24'!$AL$36 -> 2045855 | H31: ='[22]Maret 24'!AL27 -> 0 | I31: ='[23]April - 24'!$AK$28 -> 0 | J31: ='[22]Mei 24'!AL27 -> 0 | K31: ='[22]Juny 24'!AL27 -> 0 | L31: ='[22]July 24'!AL27 -> 0 | M31: ='[22]Agustus 24'!AL27 -> 0 | N31: ='[22]September 24'!AL27 -> 0 | O31: ='[22]Oktober 24'!AL27 -> 0 | P31: ='[22]November 24'!AL27 -> 0 | Q31: ='[22]Desember 24'!AL27 -> 0 | S31: =SUM(F31:Q31) -> 2643135 | T31: 1187000 | U31: =S31/T31*100 -> 222.67355 | AX31: =S31+S36 -> 2693069
C32: Fractionation OLEIN IV 57 ( Retail ) | S32: Olein IV 57 ( Retail ) | T32: Olein IV 57 ( Retail ) | U32: Olein IV 57 ( Retail ) | DF32: Kg/MT | DG32: =DG27/(DG25/1000) -> 72.98066 | DH32: =DH27/(DH25/1000) -> 75.35532 | DI32: =DI27/(DI25/1000) -> 75.473412 | OO32: =OO26/OO27*100 -> #REF! | OR32: Salvaco 2L | OS32: 2444 | PE32: 10.86 | PF32: =(OS32*PE32)/1000 -> 26.54184 | AIQ32: Diff
C33: CPO Consume | E33: Kg | F33: ='[22]Januari 24'!AL29 -> 0 | H33: ='[22]Maret 24'!AL29 -> 210989.34 | I33: ='[22]April 24'!AL29 -> 0 | J33: ='[22]Mei 24'!AL29 -> 0 | K33: ='[22]Juny 24'!AL29 -> 0 | L33: ='[22]July 24'!AL29 -> 0 | M33: ='[22]Agustus 24'!AL29 -> 0 | N33: ='[22]September 24'!AL29 -> 0 | O33: ='[22]Oktober 24'!AL29 -> 0 | P33: ='[22]November 24'!AL29 -> 0 | Q33: ='[22]Desember 24'!AL29 -> 0 | S33: =SUM(F33:Q33) -> 210989.34 | T33: =T34/T51% -> 32338304 | U33: =(S33/T33)*100 -> 0.65244405 | DF33: Kg/MT | DG33: =DG27/(DG20/1000) -> #VALUE! | DH33: =DI27/(DH20/1000) -> #VALUE! | DI33: =#REF!/(DI20/1000) -> #REF!
C34: RBDPO Brand Consume | D34: =SUM(D35:D36) -> 0 | E34: Kg | F34: =F35+F36 -> 0 | G34: =G35+G36 -> 0 | H34: =H35+H36 -> 201381 | I34: =I35+I36 -> 0 | J34: =J35+J36 -> 0 | K34: =K35+K36 -> 0 | L34: =L35+L36 -> 0 | M34: =M35+M36 -> 0 | N34: =N35+N36 -> 0 | O34: ='[22]Oktober 24'!AL30 -> 0 | P34: =P35+P36 -> 0 | Q34: =Q35+Q36 -> 0 | S34: =S35+S36 -> 201381 | T34: =T35+T36 -> 30647000 | U34: =(S34/T34)*100 -> 0.65709857 | PF34: =SUM(PF27:PF32) -> 40.24716
C35: OLEIN IV 57 ( Retail ) | E35: Kg | F35: ='[22]Januari 24'!AL31 -> 0 | H35: ='[22]Maret 24'!AL31 -> 151447 | I35: ='[22]April 24'!AL31 -> 0 | J35: ='[22]Mei 24'!AL31 -> 0 | K35: ='[22]Juny 24'!AL31 -> 0 | L35: ='[22]July 24'!AL31 -> 0 | M35: ='[22]Agustus 24'!AL31 -> 0 | N35: ='[22]September 24'!AL31 -> 0 | O35: ='[22]Oktober 24'!AL31 -> 0 | P35: ='[22]November 24'!AL31 -> 0 | Q35: ='[22]Desember 24'!AL31 -> 0 | S35: =SUM(F35:Q35) -> 151447 | T35: 23002000 | U35: =S35/T35*100 -> 0.65840796
C36: STEARIN | E36: Kg | F36: ='[22]Januari 24'!AL32 -> 0 | H36: ='[22]Maret 24'!AL32 -> 49934 | I36: ='[22]April 24'!AL32 -> 0 | J36: ='[22]Mei 24'!AL32 -> 0 | K36: ='[22]Juny 24'!AL32 -> 0 | L36: ='[22]July 24'!AL32 -> 0 | M36: ='[22]Agustus 24'!AL32 -> 0 | N36: ='[22]September 24'!AL32 -> 0 | O36: ='[22]Oktober 24'!AL32 -> 0 | P36: ='[22]November 24'!AL32 -> 0 | Q36: ='[22]Desember 24'!AL32 -> 0 | S36: =SUM(F36:Q36) -> 49934 | T36: 7645000 | U36: =S36/T36*100 -> 0.65315893
C37: Fractionation OLEIN IV 58 ( BULK ) | S37: Olein IV 58 | T37: Olein IV 58 | U37: Olein IV 58
C38: RBDPO Consume | E38: Kg | F38: =F39+F40 -> 0 | G38: 0 | H38: =H39+H40 -> 1593219 | I38: ='[23]April - 24'!$AK$35 -> 0 | J38: ='[24]Mei - 24'!$AL$35 -> 0 | K38: ='[25]Juni - 24'!$AL$35 -> 7764784 | L38: ='[26]Juli - 2024 ( Revisi )'!$AL$32 -> 11686063 | M38: ='[27]Agustus - 2024'!$AN$38 -> 224749 | N38: =$N$39+$N$40 -> 6581530 | O38: =O39+O40 -> 0 | P38: =P39+P40 -> 0 | Q38: =Q39+Q40 -> 0 | S38: =S39+S40 -> 28370585 | T38: =T39+T40 -> 249961000 | U38: =S38/T38*100 -> 11.350005
C39: OLEIN IV 58 ( Bulk ) | E39: Kg | F39: ='[22]Januari 24'!AL31 -> 0 | G39: 0 | H39: ='[22]Maret 24'!AL35 -> 1075806 | I39: ='[23]April - 24'!$AK$36 -> 0 | J39: ='[24]Mei - 24'!$AL$36 -> 0 | K39: ='[25]Juni - 24'!$AL$36 -> 5498655 | L39: ='[26]Juli - 2024 ( Revisi )'!$AL$33 -> 8627479 | M39: ='[27]Agustus - 2024'!$AN$39 -> 87749 | N39: ='September - 2024'!$AM$42 -> 4788598 | O39: ='[22]Oktober 24'!AL35 -> 0 | P39: ='[22]November 24'!AL35 -> 0 | Q39: ='[22]Desember 24'!AL35 -> 0 | S39: =SUM(F39:Q39) -> 20078287 | T39: 175000000 | U39: =S39/T39*100 -> 11.473307
C40: STEARIN | E40: Kg | F40: ='[22]Januari 24'!AL32 -> 0 | G40: 0 | H40: ='[22]Maret 24'!AL36 -> 517413 | I40: ='[23]April - 24'!$AK$37 -> 0 | J40: ='[24]Mei - 24'!$AL$37 -> 0 | K40: ='[25]Juni - 24'!$AL$37 -> 2266129 | L40: ='[26]Juli - 2024 ( Revisi )'!$AL$34 -> 3578824 | M40: ='[27]Agustus - 2024'!$AN$40 -> 137000 | N40: ='September - 2024'!$AM$43 -> 1792932 | O40: ='[22]Oktober 24'!AL36 -> 0 | P40: ='[22]November 24'!AL36 -> 0 | Q40: ='[22]Desember 24'!AL36 -> 0 | S40: =SUM(F40:Q40) -> 8292298 | T40: 74961000 | U40: =S40/T40*100 -> 11.06215
C41: Fractionation OLEIN IV 60 | S41: Olein IV 60 | T41: Olein IV 60 | U41: Olein IV 60
C42: CPO Consume | E42: Kg | F42: ='[22]Januari 24'!AL38 -> 1622056.5 | G42: ='[29]Februari - 24'!$AL$38 -> 421426.65 | H42: ='[22]Maret 24'!AL38 -> 0 | I42: 0 | J42: 0 | K42: 0 | L42: 0 | M42: 0 | N42: 0 | O42: 0 | S42: =SUM(F42:Q42) -> 2043483.1 | T42: =T43/T51% -> 25913273 | U42: =S42/T42*100 -> 7.885855
C43: RBDPO Brand Consume | D43: =SUM(D45:D46) -> 0 | E43: Kg | F43: ='[22]Januari 24'!AL39 -> 1537641 | G43: ='[29]Februari - 24'!$AL$39 -> 398670 | H43: =H45+H46 -> 0 | I43: ='[22]April 24'!AL39 -> 0 | J43: ='[22]Mei 24'!AL39 -> 0 | K43: =K45+K46 -> 0 | L43: ='[22]July 24'!AL39 -> 0 | M43: =M45+M46 -> 0 | N43: =N45+N46 -> 0 | O43: ='[22]Oktober 24'!AL39 -> 0 | P43: ='[22]November 24'!AL39 -> 0 | Q43: =Q45+Q46 -> 0 | S43: =S45+S46 -> 1936311 | T43: =T45+T46 -> 24558000 | U43: =S43/T43*100 -> 7.8846445 | DG43: 2136
C44: OLEIN IV 60 Bulk | E44: Kg | F44: ='[22]Januari 24'!AL40 -> 0 | H44: ='[22]Maret 24'!AL40 -> 0 | I44: ='[22]April 24'!AL40 -> 0 | J44: ='[22]Mei 24'!AL40 -> 0 | K44: ='[22]Juny 24'!AL40 -> 0 | L44: ='[22]July 24'!AL40 -> 0 | M44: ='[22]Agustus 24'!AL40 -> 0 | N44: ='September - 2024'!AM62 -> #DIV/0! | O44: ='[22]Oktober 24'!AL40 -> 0 | Q44: ='[22]Desember 24'!AL40 -> 0 | S44: =SUM(F44:Q44) -> #DIV/0! | T44: =SUM(F44:Q44) -> #DIV/0! | U44: =SUM(H44:S44) -> #DIV/0!
C45: OLEIN IV 60 Salvaco | E45: Kg | F45: ='[22]Januari 24'!AL41 -> 923976 | G45: ='[29]Februari - 24'!$AL$41 -> 248300 | H45: ='[22]Maret 24'!AL41 -> 0 | I45: ='[22]April 24'!AL41 -> 0 | J45: ='[22]Mei 24'!AL41 -> 0 | K45: ='[22]Juny 24'!AL41 -> 0 | L45: ='[22]July 24'!AL41 -> 0 | M45: ='[27]Agustus - 2024'!$AN$45 -> 0 | N45: ='September - 2024'!AM47 -> 0 | O45: ='[22]Oktober 24'!AL41 -> 0 | P45: ='[22]November 24'!AL41 -> 0 | Q45: ='[22]Desember 24'!AL41 -> 0 | S45: =SUM(F45:Q45) -> 1172276 | T45: 14736000 | U45: =S45/T45*100 -> 7.9551846 | DG45: 1796
C46: SOFT STEARIN | E46: Kg | F46: ='[22]Januari 24'!AL42 -> 613665 | G46: ='[29]Februari - 24'!$AL$42 -> 150370 | H46: ='[22]Maret 24'!AL42 -> 0 | I46: ='[22]April 24'!AL42 -> 0 | J46: ='[22]Mei 24'!AL42 -> 0 | K46: ='[22]Juny 24'!AL42 -> 0 | L46: ='[22]July 24'!AL42 -> 0 | M46: ='[27]Agustus - 2024'!$AN$46 -> 0 | N46: ='[22]September 24'!AL42 -> 0 | O46: ='[22]Oktober 24'!AL42 -> 0 | P46: ='[22]November 24'!AL42 -> 0 | Q46: ='[22]Desember 24'!AL42 -> 0 | S46: =SUM(F46:Q46) -> 764035 | T46: 9822000 | U46: =S46/T46*100 -> 7.7788129 | DG46: =DG43/DG45*100 -> 118.93096
C47: Ratio Run RBDPO | F47: ='[22]Januari 24'!AL43 -> 17.42364 | G47: ='[29]Februari - 24'!$AL$43 -> 13.049053 | H47: ='[22]Maret 24'!AL43 -> 2.8945161 | I47: ='[22]April 24'!AL43 -> 0 | J47: ='[24]Mei - 24'!$AL$44 -> 0 | K47: ='[25]Juni - 24'!$AL$44 -> 12.523845 | L47: =(L38+L34+L29+L25)/(60000000) -> 0.19476772 | M47: =($M$38+$M$34+$M$29+$M$25)/(60000000) -> 0.0037458167 | N47: =($N$38+$N$34+$N$29+$N$25)/(60000000) -> 0.38580125 | O47: =(O38+O34+O29+O25)/(60000000) -> 0 | P47: =(P38+P34+P29+P25)/(60000000) -> 0 | Q47: =(Q38+Q34+Q29+Q25)/(60000000) -> 0 | S47: =+AVERAGE(F47:O47) -> 4.647537
C48: Utilitas RBDPO | F48: =(F43+F38+F34+F30+F26)/F49*100 -> 53.914268 | G48: =(G43+G38+G34+G30+G26)/G49*100 -> 13.116557 | H48: =(H43+H38+H34+H30+H26)/H49*100 -> 4.8445092 | J48: =(J43+J38+J34+J30+J26)/J49*100 -> 0 | K48: =(K43+K38+K34+K30+K26)/K49*100 -> 22.670784 | L48: =(L43+L38+L34+L30+L26)/L49*100 -> 34.514749 | M48: =($M$43+$M$38+$M$34+$M$30+$M$25)/$M$49*100 -> 0.65619805 | N48: =($N$43+$N$38+$N$34+$N$30+$N$26)/$N$49*100 -> 59.478012 | O48: =(O43+O38+O34+O30+O26)/O49*100 -> 0 | P48: =(P43+P38+P34+P30+P26)/P49*100 -> 0 | Q48: =(Q43+Q38+Q34+Q30+Q26)/Q49*100 -> 0 | S48: =+AVERAGE(F48:O48) -> 21.021675
C49: Budget RBDPO | F49: 10667000 | G49: 42841000 | H49: 37044000 | J49: ='[24]Mei - 24'!$D$19 -> 34250178 | K49: ='[25]Juni - 24'!$D$19 -> 34250178 | L49: ='[25]Juni - 24'!$D$19 -> 34250178 | M49: ='[25]Juni - 24'!$D$19 -> 34250178 | N49: ='[25]Juni - 24'!$D$19 -> 34250178 | O49: ='[25]Juni - 24'!$D$19 -> 34250178 | P49: ='[25]Juni - 24'!$D$19 -> 34250178 | Q49: ='[25]Juni - 24'!$D$19 -> 34250178 | S49: =SUM(F49:O49) -> 296053068
C50: YIELD | S50: Yield | T50: Yield | U50: Yield | OP50: 678
C51: RBDPO | D51: 94.2 | E51: % | F51: =(F19/(F11))*100 -> 94.537593 | G51: =(G19/(G11))*100 -> 94.281618 | H51: =(H19/(H11))*100 -> 94.87071 | I51: =(I19/(I11))*100 -> #DIV/0! | J51: =(J19/(J11))*100 -> #DIV/0! | K51: =(K19/(K11))*100 -> 94.544904 | L51: =(L19/(L11))*100 -> 90.001937 | M51: =($M$19/($M$11))*100 -> 0 | N51: =(N19/(N11))*100 -> 94.748466 | O51: =(O19/(O11))*100 -> #DIV/0! | P51: =(P19/(P11))*100 -> #DIV/0! | Q51: =(Q19/(Q11))*100 -> #DIV/0! | S51: =(S19/(S11))*100 -> 93.621167 | T51: =(T19/(T11))*100 -> 94.769967 | OP51: 420 | OR51: =OP51/OP50*100 -> 61.946903
C52: PFAD | D52: 5 | E52: % | F52: =(F20/(F11))*100 -> 4.7773118 | G52: =(G20/(G11))*100 -> 5.0597453 | H52: =(H20/(H11))*100 -> 4.4470026 | I52: =(I20/(I11))*100 -> #DIV/0! | J52: =(J20/(J11))*100 -> #DIV/0! | K52: =(K20/(K11))*100 -> 4.8500654 | L52: =(L20/(L11))*100 -> 4.4613156 | M52: =($M$20/($M$11))*100 -> 0 | N52: =(N20/(N11))*100 -> 4.1524826 | O52: =(O20/(O11))*100 -> #DIV/0! | P52: =(P20/(P11))*100 -> #DIV/0! | Q52: =(Q20/(Q11))*100 -> #DIV/0! | S52: =(S20/(S11))*100 -> 4.5509754 | T52: =(T20/(T11))*100 -> 4.5147541 | OP52: =OP50-OP51 -> 258 | OR52: =OP52/OP50*100 -> 38.053097
C53: Olein IV 56 | D53: 82 | E53: % | F53: =(F26/F25)*100 -> 83.343365 | G53: =(G26/G25)*100 -> 83.68598 | H53: =(H26/H25)*100 -> #DIV/0! | I53: =(I26/I25)*100 -> #DIV/0! | J53: =(J26/J25)*100 -> #DIV/0! | K53: =(K26/K25)*100 -> #DIV/0! | L53: =(L26/L25)*100 -> #DIV/0! | M53: =$M$26/($M$26+$M$27)*100 -> #DIV/0! | N53: =(N26/N25)*100 -> 83.238811 | O53: =(O26/O25)*100 -> #DIV/0! | P53: =(P26/P25)*100 -> #DIV/0! | Q53: =(Q26/Q25)*100 -> #DIV/0! | S53: =(S26/S25)*100 -> 83.262293 | T53: =(T26/T25)*100 -> 82.036628
C54: Stearin | D54: 18 | E54: % | F54: =(F27/F25)*100 -> 16.656635 | G54: =(G27/G25)*100 -> 16.31402 | H54: =(H27/H25)*100 -> #DIV/0! | I54: =(I27/I25)*100 -> #DIV/0! | J54: =(J27/J25)*100 -> #DIV/0! | K54: =(K27/K25)*100 -> #DIV/0! | L54: =(L27/L25)*100 -> #DIV/0! | M54: =$M$27/($M$27+$M$26)*100 -> #DIV/0! | N54: =(N27/N25)*100 -> 16.761189 | O54: =(O27/O25)*100 -> #DIV/0! | P54: =(P27/P25)*100 -> #DIV/0! | Q54: =(Q27/Q25)*100 -> #DIV/0! | S54: =(S27/S25)*100 -> 16.737707 | T54: =(T27/T25)*100 -> 17.963372
C55: Olein IV 57 ( Bulk ) | D55: 75 | E55: % | F55: =(F30/F29)*100 -> 78.87878 | G55: =(G30/G29)*100 -> 71.680254 | H55: =(H30/H29)*100 -> #DIV/0! | I55: =(I30/I29)*100 -> #DIV/0! | J55: =(J30/J29)*100 -> #DIV/0! | K55: =(K30/K29)*100 -> #DIV/0! | L55: =(L30/L29)*100 -> #DIV/0! | M55: =(M30/M29)*100 -> #DIV/0! | ... Q55: =(Q30/Q29)*100 -> #DIV/0! | S55: =(S30/S29)*100 -> 73.705372 | T55: 75
C56: Stearin | D56: 25 | E56: % | F56: =(F31/F29)*100 -> 21.12122 | G56: =(G31/G29)*100 -> 28.319746 | H56: =(H31/H29)*100 -> #DIV/0! | I56: =(I31/I29)*100 -> #DIV/0! | J56: =(J31/J29)*100 -> #DIV/0! | K56: =(K31/K29)*100 -> #DIV/0! | L56: =(L31/L29)*100 -> #DIV/0! | M56: =(M31/M29)*100 -> #DIV/0! | ... Q56: =(Q31/Q29)*100 -> #DIV/0! | S56: =(S31/S29)*100 -> 26.294628 | T56: 25
C57: Olein IV 57 ( Retail ) | D57: 75 | E57: % | F57: =F35/F34*100 -> #DIV/0! | G57: =G35/G34*100 -> #DIV/0! | H57: =H35/H34*100 -> 75.204215 | I57: =I35/I34*100 -> #DIV/0! | J57: =J35/J34*100 -> #DIV/0! | K57: =K35/K34*100 -> #DIV/0! | L57: =L35/L34*100 -> #DIV/0! | M57: =M35/M34*100 -> #DIV/0! | ... Q57: =Q35/Q34*100 -> #DIV/0! | S57: =(S35/S34)*100 -> 75.204215 | T57: 75
C58: Stearin | D58: 25 | E58: % | F58: =F36/F34*100 -> #DIV/0! | G58: =G36/G34*100 -> #DIV/0! | H58: =H36/H34*100 -> 24.795785 | I58: =I36/I34*100 -> #DIV/0! | J58: =J36/J34*100 -> #DIV/0! | K58: =K36/K34*100 -> #DIV/0! | L58: =L36/L34*100 -> #DIV/0! | M58: =M36/M34*100 -> #DIV/0! | ... Q58: =Q36/Q34*100 -> #DIV/0! | S58: =(S36/S34)*100 -> 24.795785 | T58: 25 | FN58: 95.03
C59: Olein IV 58 ( Bulk ) | D59: 70 | E59: % | F59: =(F39/F38)*100 -> #DIV/0! | G59: =(G39/G38)*100 -> #DIV/0! | H59: =(H39/H38)*100 -> 67.52405 | I59: =(I39/I38)*100 -> #DIV/0! | J59: =(J39/J38)*100 -> #DIV/0! | K59: =(K39/K38)*100 -> 70.815299 | L59: ='[26]Juli - 2024 ( Revisi )'!$AL$51 -> 70.680525 | M59: ='[27]Agustus - 2024'!$AN$57 -> 0 | N59: =(N39/N38)*100 -> 72.758128 | O59: =(O39/O38)*100 -> #DIV/0! | Q59: =(Q39/Q38)*100 -> #DIV/0! | S59: =(S39/S38)*100 -> 70.771494 | T59: 70
C60: Stearin | D60: 30 | E60: % | F60: =(F40/F38)*100 -> #DIV/0! | G60: =(G40/G38)*100 -> #DIV/0! | H60: =(H40/H38)*100 -> 32.47595 | I60: =(I40/I38)*100 -> #DIV/0! | J60: =(J40/J38)*100 -> #DIV/0! | K60: =(K40/K38)*100 -> 29.184701 | L60: ='[26]Juli - 2024 ( Revisi )'!$AL$52 -> 29.319475 | M60: ='[27]Agustus - 2024'!$AN$58 -> 0 | N60: =(N40/N38)*100 -> 27.241872 | O60: =(O40/O38)*100 -> #DIV/0! | Q60: =(Q40/Q38)*100 -> #DIV/0! | S60: =(S40/S38)*100 -> 29.228506 | T60: 30
C61: Olein IV 60 | D61: 60 | E61: % | F61: =F45/F43*100 -> 60.090489 | G61: =G45/G43*100 -> 62.282088 | H61: =H45/H43*100 -> #DIV/0! | I61: =I45/I43*100 -> #DIV/0! | J61: =J45/J43*100 -> #DIV/0! | K61: =K45/K43*100 -> #DIV/0! | L61: =L45/L43*100 -> #DIV/0! | M61: =M45/M43*100 -> #DIV/0! | ... Q61: =Q45/Q43*100 -> #DIV/0! | S61: =(S45/S43)*100 -> 60.541721 | T61: =T45/T43*100 -> 60.004886 | FN61: 4.23 | OR61: =OR62/94.2% -> 1307.8556 | OS61: MT CPO
C62: Soft Stearin | D62: 40 | E62: % | F62: =F46/F43*100 -> 39.909511 | G62: =G46/G43*100 -> 37.717912 | H62: =H46/H43*100 -> #DIV/0! | I62: =I46/I43*100 -> #DIV/0! | J62: =J46/J43*100 -> #DIV/0! | K62: =K46/K43*100 -> #DIV/0! | L62: =L46/L43*100 -> #DIV/0! | M62: =M46/M43*100 -> #DIV/0! | ... Q62: =Q46/Q43*100 -> #DIV/0! | S62: =(S46/S43)*100 -> 39.458279 | T62: =T46/T43*100 -> 39.995114 | FN62: =100-FN58-FN61 -> 0.74 | OR62: =22*56 -> 1232 | OS62: MT RBDPO Brand
B63: 3 | C63: CHEMICAL CONSUMABLE | S63: Chemical | T63: Chemical | U63: Chemical | OR63: =16.5*OR61 -> 21579.618
C64: Bleaching Earth (BE) to Poram Spec | D64: 8 | E64: Kg | F64: ='[22]Januari 24'!AL58 -> 128586 | G64: ='[29]Februari - 24'!$AL$58 -> 148066 | H64: ='[22]Maret 24'!AL58 -> 29654 | I64: ='[23]April - 24'!$AK$59 -> 0 | J64: ='[24]Mei - 24'!$AL$59 -> 0 | K64: ='[25]Juni - 24'!$AL$59 -> 88126 | L64: ='[26]Juli - 2024 ( Revisi )'!$AL$56 -> 162476 | M64: ='[27]Agustus - 2024'!$AN$62 -> 11.311305 | N64: ='September - 2024'!$AM$65 -> 187513 | O64: ='[22]Oktober 24'!AL58 -> 0 | P64: ='[22]November 24'!AL58 -> 0 | Q64: ='[22]Desember 24'!AL58 -> 0 | S64: =SUM(F64:Q64) -> 744432.31 | T64: 2767753 | U64: =S64/T64*100 -> 26.896631
E65: % | F65: ='[22]Januari 24'!AL59 -> 1.2503461 | G65: =G64/(G12)*100 -> 1.3601743 | H65: =H64/(H12)*100 -> 1.0253964 | I65: =I64/(I12)*100 -> #DIV/0! | J65: =J64/(J12)*100 -> #DIV/0! | K65: =K64/(K12)*100 -> 0.98804604 | L65: =L64/(L12)*100 -> 1.015729 | M65: =$M$64/($M$11)*100 -> 3363.1976 | N65: =$N$64/($N$12)*100 -> 0.77980013 | O65: =O64/(O12)*100 -> #DIV/0! | P65: =P64/(P12)*100 -> #DIV/0! | Q65: =Q64/(Q12)*100 -> #DIV/0! | S65: =S64/(S11)*100 -> 0.98316642 | T65: 0.8 | U65: 0 | V65: =S65*10 -> 9.8316642 | AX65: =S65*10 -> 9.8316642 | FN65: =#REF!*10 -> #REF! | OR65: =OR61+(S42/1000) -> 3351.3388 | OS65: Total CPO Brand
C66: Bleaching Earth (BE) to Branded Spec | D66: 16 | E66: Kg | F66: ='[22]Januari 24'!AL60 -> 25923 | G66: ='[29]Februari - 24'!$AL$60 -> 15015 | H66: ='[22]Maret 24'!AL60 -> 2901 | I66: ='[22]April 24'!AL60 -> 0 | J66: ='[22]Mei 24'!AL60 -> 0 | K66: ='[22]Juny 24'!AL60 -> 0 | L66: ='[26]Juli - 2024 ( Revisi )'!$AL$58 -> 0 | M66: ='[27]Agustus - 2024'!$AN$64 -> 0 | N66: ='[22]September 24'!AL60 -> 0 | O66: ='[22]Oktober 24'!AL60 -> 0 | P66: ='[22]November 24'!AL60 -> 0 | Q66: ='[22]Desember 24'!AL60 -> 0 | S66: =SUM(F66:Q66) -> 43839 | T66: 1357284 | U66: =S66/T66*100 -> 3.2299062 | OR66: =OR63+S66 -> 65418.618 | OS66: Total BE Brand
E67: % | F67: ='[22]Januari 24'!AL61 -> 1.5981564 | G67: =G66/(G13)*100 -> 1.74293 | H67: =H66/(H13)*100 -> 1.374951 | I67: =I66/(I13)*100 -> #DIV/0! | J67: =J66/(J13)*100 -> #DIV/0! | K67: =K66/(K13)*100 -> #DIV/0! | L67: =L66/(L13)*100 -> #DIV/0! | M67: =$M$66/($M$13)*100 -> #DIV/0! | N67: =N66/(N13)*100 -> #DIV/0! | O67: =O66/(O13)*100 -> #DIV/0! | P67: =P66/(P13)*100 -> #DIV/0! | Q67: =Q66/(Q13)*100 -> #DIV/0! | S67: =S66/(S13)*100 -> 1.6269651 | T67: 1.8 | U67: 0 | AX67: =S67*10 -> 16.269651 | OR67: =OR66/OR65 -> 19.520145 | OS67: Kg/MT CPO
C68: Phosporic Acid (PA) | D68: 0.55 | E68: Kg | F68: ='[22]Januari 24'!AL62 -> 6664.856 | G68: ='[29]Februari - 24'!$AL$62 -> 6551.932 | H68: ='[22]Maret 24'!AL62 -> 1744.336 | I68: ='[23]April - 24'!$AK$63 -> 0 | J68: ='[24]Mei - 24'!$AL$63 -> 0 | K68: ='[25]Juni - 24'!$AL$63 -> 4040.198 | L68: ='[26]Juli - 2024 ( Revisi )'!$AL$60 -> 7823.782 | M68: ='[27]Agustus - 2024'!$AN$66 -> 0.50926731 | N68: ='September - 2024'!$AM$69 -> 12499.518 | O68: ='[22]Oktober 24'!AL62 -> 0 | P68: ='[22]November 24'!AL62 -> 0 | Q68: ='[22]Desember 24'!AL62 -> 0 | S68: =SUM(F68:Q68) -> 39325.131 | T68: 252824 | U68: =SUM(H68:S68) -> 65433.475 | OR68: 16 | OS68: Budget (Kg/MT)
E69: % | F69: ='[22]Januari 24'!AL63 -> 0.05597855 | G69: =G68/(G11)*100 -> 0.055773982 | H69: =H68/(H11)*100 -> 0.056215517 | I69: =I68/(I11)*100 -> #DIV/0! | J69: =J68/(J11)*100 -> #DIV/0! | K69: =K68/(K11)*100 -> 0.045297661 | L69: =L68/(L11)*100 -> 0.048910868 | M69: ='[27]Agustus - 2024'!$AN$67 -> 0 | N69: =N68/(N11)*100 -> 0.051981067 | O69: =O68/(O11)*100 -> #DIV/0! | P69: =P68/(P11)*100 -> #DIV/0! | Q69: =Q68/(Q11)*100 -> #DIV/0! | S69: =S68/(S11+71450)*100 -> 0.051887456 | T69: 0.06 | U69: =U68/(U11+71450)*100 -> 91.57916 | AX69: =S69*10 -> 0.51887456 | FN69: =P69*10 -> #DIV/0! | OR69: =OR67-OR68 -> 3.5201448 | OS69: Over (Kg/MT)
B70: 4 | C70: Oil Losses | D70: 0.8 | E70: % | F70: =((SUM(F19:F20))-(SUM(F11)))/(SUM(F11))*100 -> -0.68509483 | G70: =((SUM(G19:G20))-(SUM(G11)))/(SUM(G11))*100 -> -0.65863696 | H70: =((SUM(H19:H20))-(SUM(H11)))/(SUM(H11))*100 -> -0.68228753 | I70: =((SUM(I19:I20))-(SUM(I11)))/(SUM(I11))*100 -> #DIV/0! | J70: =((SUM(J19:J20))-(SUM(J11)))/(SUM(J11))*100 -> #DIV/0! | K70: =((SUM(K19:K20))-(SUM(K11)))/(SUM(K11))*100 -> -0.60503048 | L70: =((SUM(L19:L20))-(SUM(L11)))/(SUM(L11))*100 -> -5.536747 | M70: =((SUM(M19:M20))-(SUM(M11)))/(SUM(M11))*100 -> -100 | ... Q70: =((SUM(Q19:Q20))-(SUM(Q11)))/(SUM(Q11))*100 -> #DIV/0! | S70: =((SUM(S19:S20))-(SUM(S11)))/(SUM(S11))*100 -> -1.8278578 | T70: =((SUM(T19:T20))-(SUM(T11)))/(SUM(T11))*100 -> -0.71527906 | U70: =S70/T70*100 -> 255.54471
C71: % Oil Content | D71: 22 | E71: % | F71: ='[30]Januari - 24'!$AL$65 -> 21.923529 | G71: ='[29]Februari - 24'!$AL$65 -> 21.991 | H71: ='[22]Maret 24'!AL65 -> 21.958 | I71: ='[23]April - 24'!$AK$66 -> 0 | J71: ='[24]Mei - 24'!$AL$66 -> 0 | K71: ='[25]Juni - 24'!$AL$66 -> 21.886471 | L71: ='[26]Juli - 2024 ( Revisi )'!$AL$64 -> 21.912727 | M71: ='[27]Agustus - 2024'!$AN$70 -> 0 | N71: ='September - 2024'!$AM$73 -> 22.058148 | P71: ='[22]November 24'!AL65 -> #DIV/0! | Q71: ='[22]Desember 24'!AL65 -> #DIV/0! | S71: =AVERAGE(F71:L71) -> 15.66739 | T71: 22 | U71: =AVERAGE(H71:S71) -> #DIV/0!
C72: Spent Bleaching Earth | E72: Kg | F72: =SUM(F64,F66)+(F71%*SUM(F64,F66)) -> 188382.83 | G72: =SUM(G64,G66)+(G71%*SUM(G64,G66)) -> 198944.14 | H72: =SUM(H64,H66)+(H71%*SUM(H64,H66)) -> 39703.427 | I72: =SUM(I64,I66)+(I71%*SUM(I64,I66)) -> 0 | J72: =SUM(J64,J66)+(J71%*SUM(J64,J66)) -> 0 | K72: =SUM(K64,K66)+(K71%*SUM(K64,K66)) -> 107413.67 | L72: =SUM(L64,L66)+(L71%*SUM(L64,L66)) -> 198078.92 | M72: ='[27]Agustus - 2024'!$AN$71 -> 0 | N72: =SUM($N$64,$N$66)+($N$71%*SUM($N$64,$N$66)) -> 228874.9 | O72: =SUM(O64,O66)+(O71%*SUM(O64,O66)) -> 0 | P72: =SUM(P64,P66)+(P71%*SUM(P64,P66)) -> #DIV/0! | Q72: =SUM(Q64,Q66)+(Q71%*SUM(Q64,Q66)) -> #DIV/0! | S72: =SUM(S64,S66)+(S71%*SUM(S64,S66)) -> 911772.85 | T72: 7811279 | U72: =SUM(U64,U66)+(U71%*SUM(U64,U66)) -> #DIV/0! | GA72: =W72+400 -> 400
B73: 5 | C73: PACKAGING (Brand Salvaco) | S73: Packaging | T73: Packaging | U73: Packaging | FX73: 17292 | OY73: =#REF!-FX73 -> #REF!
C74: Olein IV 60 Received | E74: Kg | F74: ='[22]Januari 24'!AL68 -> 845858 | G74: ='[22]Februari 24'!AI68 -> #REF! | H74: ='[22]Maret 24'!AL68 -> 0 | I74: ='[22]April 24'!AL68 -> 0 | J74: ='[22]Mei 24'!AL68 -> 0 | K74: ='[22]Juny 24'!AL68 -> 0 | L74: ='[22]July 24'!AL68 -> 0 | M74: ='[22]Agustus 24'!AL68 -> 0 | N74: ='[22]September 24'!AL68 -> 0 | O74: ='[22]Oktober 24'!AL68 -> 0 | P74: ='[22]November 24'!AL68 -> 0 | Q74: ='[22]Desember 24'!AL68 -> 0 | S74: =SUM(F74:Q74) -> #REF! | T74: =SUM(G74:R74) -> #REF! | U74: =(S74/T74)*100 -> #REF!
C75: Olein IV 60 Consume | E75: Kg | F75: ='[22]Januari 24'!AL69 -> 399021.28 | G75: ='[22]Februari 24'!AI69 -> #REF! | H75: ='[22]Maret 24'!AL69 -> 0 | I75: ='[22]April 24'!AL69 -> 0 | J75: ='[22]Mei 24'!AL69 -> 0 | K75: ='[22]Juny 24'!AL69 -> 0 | L75: ='[22]July 24'!AL69 -> 0 | M75: ='[22]Agustus 24'!AL69 -> 0 | N75: ='[22]September 24'!AL69 -> 0 | O75: ='[22]Oktober 24'!AL69 -> 0 | P75: ='[22]November 24'!AL69 -> 0 | Q75: ='[22]Desember 24'!AL69 -> 0 | S75: =SUM(S76:S78) -> #REF! | T75: =SUM(T76:T78) -> #REF! | U75: =(S75/T75)*100 -> #REF! | AFR75: Kg | AFS75: Olein Filling to Packaging
C76: - finished product | E76: Kg | F76: =SUM(F80:F81)*10.86 -> 400256.16 | G76: =SUM(G80:G81)*10.86 -> #REF! | H76: =SUM(H80:H81)*10.86 -> 0 | I76: ='[22]April 24'!AL70 -> 0 | J76: =SUM(J80:J81)*10.86 -> 0 | K76: =SUM(K80:K81)*10.86 -> 0 | L76: =SUM(L80:L81)*10.86 -> 0 | M76: =SUM(M80:M81)*10.86 -> 0 | N76: =SUM(N80:N81)*10.86 -> 0 | O76: =SUM(O80:O81)*10.86 -> 0 | P76: =SUM(P80:P81)*10.86 -> 0 | Q76: =SUM(Q80:Q81)*10.86 -> 0 | S76: =SUM(S80:S81)*10.86 -> #REF! | T76: =SUM(T80:T81)*10.86 -> 32269046 | U76: =(S76/T76)*100 -> #REF! | FX76: =#REF!/1000 -> #REF! | OY76: 4696 | OZ76: =FX76/OY76*100 -> #REF!
C77: - sample | E77: Kg | F77: =F75-F76 -> -1234.88 | G77: =G75-G76 -> #REF! | H77: =H75-H76 -> 0 | I77: ='[22]April 24'!AL71 -> 0 | J77: =J75-J76 -> 0 | K77: =K75-K76 -> 0 | L77: =L75-L76 -> 0 | M77: =M75-M76 -> 0 | N77: =N75-N76 -> 0 | O77: =O75-O76 -> 0 | P77: =P75-P76 -> 0 | Q77: =Q75-Q76 -> 0 | S77: =SUM(F77:Q77) -> #REF! | T77: =SUM(G77:R77) -> #REF! | U77: =(S77/T77)*100 -> #REF! | FX77: =#REF!/1000 -> #REF! | OY77: 565 | OZ77: =FX77/OY77*100 -> #REF!
C78: - remelt, flushing, downgrade | E78: Kg | F78: ='[22]Januari 24'!AL72 -> 0 | G78: ='[22]Februari 24'!AI72 -> 0 | H78: ='[22]Maret 24'!AL72 -> 0 | I78: ='[22]April 24'!AL72 -> 0 | P78: 0 | Q78: 0 | S78: =SUM(F78:Q78) -> 0 | T78: =SUM(G78:R78) -> 0
C79: Carton | S79: Carton | T79: Carton | U79: Carton
C80: Salvaco 1 Liter | E80: Box | F80: ='[22]Januari 24'!AL74 -> 17197 | G80: ='[22]Februari 24'!AI74 -> #REF! | H80: ='[22]Maret 24'!AL74 -> 0 | I80: ='[22]April 24'!AL74 -> 0 | J80: ='[22]Mei 24'!AL74 -> 0 | K80: ='[22]Juny 24'!AL74 -> 0 | L80: ='[22]July 24'!AL74 -> 0 | M80: ='[22]Agustus 24'!AL74 -> 0 | N80: ='[22]September 24'!AL74 -> 0 | O80: ='[22]Oktober 24'!AL74 -> 0 | P80: ='[22]November 24'!AL74 -> 0 | Q80: ='[22]Desember 24'!AL74 -> 0 | S80: =SUM(F80:Q80) -> #REF! | T80: 1254577 | U80: =(S80/T80)*100 -> #REF!
C81: Salvaco 2 Liter | E81: Box | F81: ='[22]Januari 24'!AL75 -> 19659 | G81: ='[22]Februari 24'!AI75 -> #REF! | H81: ='[22]Maret 24'!AL75 -> 0 | I81: ='[22]April 24'!AL75 -> 0 | J81: ='[22]Mei 24'!AL75 -> 0 | K81: ='[22]Juny 24'!AL75 -> 0 | L81: ='[22]July 24'!AL75 -> 0 | M81: ='[22]Agustus 24'!AL75 -> 0 | N81: ='[22]September 24'!AL75 -> 0 | O81: ='[22]Oktober 24'!AL75 -> 0 | P81: ='[22]November 24'!AL75 -> 0 | Q81: ='[22]Desember 24'!AL75 -> 0 | S81: =SUM(F81:Q81) -> #REF! | T81: 1716790 | U81: =(S81/T81)*100 -> #REF!
C82: Pouch | S82: Pouch | T82: Pouch | U82: Pouch
C83: Salvaco 1 Liter | E83: Pouch | F83: =F80*12 -> 206364 | G83: =G80*12 -> #REF! | H83: =H80*12 -> 0 | I83: =I80*12 -> 0 | J83: =J80*12 -> 0 | K83: =K80*12 -> 0 | L83: =L80*12 -> 0 | M83: =M80*12 -> 0 | ... Q83: =Q80*12 -> 0 | S83: =S80*12 -> #REF! | T83: =T80*12 -> 15054924 | U83: =(S83/T83)*100 -> #REF!
C84: Salvaco 2 Liter | E84: Pouch | F84: =F81*6 -> 117954 | G84: =G81*6 -> #REF! | H84: =H81*6 -> 0 | I84: =I81*6 -> 0 | J84: =J81*6 -> 0 | K84: =K81*6 -> 0 | L84: =L81*6 -> 0 | M84: =M81*6 -> 0 | ... Q84: =Q81*6 -> 0 | S84: =S81*6 -> #REF! | T84: =T81*6 -> 10300740 | U84: =(S84/T84)*100 -> #REF!
C85: Consumable Vit. A | E85: gram | F85: =(F75*45)/1700 -> 10562.328 | G85: =(G75*45)/1700 -> #REF! | H85: =(H75*45)/1700 -> 0 | I85: =(I75*45)/1700 -> 0 | J85: =(J75*45)/1700 -> 0 | K85: =(K75*45)/1700 -> 0 | L85: =(L75*45)/1700 -> 0 | M85: =(M75*45)/1700 -> 0 | ... Q85: =(Q75*45)/1700 -> 0 | S85: =SUM(F85:Q85) -> #REF! | T85: =(T75*45)/1700 -> #REF! | U85: =(S85/T85)*100 -> #REF!
C86: Consumable Packing Tape | E86: Roll | F86: =SUM(F80:F81)/500 -> 73.712 | G86: =SUM(G80:G81)/500 -> #REF! | H86: =SUM(H80:H81)/500 -> 0 | I86: =SUM(I80:I81)/500 -> 0 | J86: =SUM(J80:J81)/500 -> 0 | K86: =SUM(K80:K81)/500 -> 0 | L86: =SUM(L80:L81)/500 -> 0 | M86: =SUM(M80:M81)/500 -> 0 | ... Q86: =SUM(Q80:Q81)/500 -> 0 | S86: =SUM(F86:Q86) -> #REF! | T86: =SUM(T80:T81)/500 -> 5942.734 | U86: =(S86/T86)*100 -> #REF!
C87: REJECT MATERIAL QTY | S87: Loss Material | T87: Loss Material | U87: Loss Material
C88: Carton | S88: Carton | T88: Carton | U88: Carton
C89: Salvaco 1 Liter | E89: Box | F89: ='[22]Januari 24'!AL74 -> 17197 | G89: ='[22]Februari 24'!AI83 -> #REF! | H89: ='[22]Maret 24'!AL83 -> 0 | I89: ='[22]April 24'!AL83 -> 0 | J89: ='[22]Mei 24'!AL83 -> 0 | K89: ='[22]Juny 24'!AL83 -> 0 | L89: ='[22]July 24'!AL83 -> 0 | M89: ='[22]Agustus 24'!AL83 -> 0 | N89: ='[22]September 24'!AL83 -> 0 | O89: ='[22]Oktober 24'!AL83 -> 0 | P89: ='[22]November 24'!AL83 -> 0 | Q89: ='[22]Desember 24'!AL83 -> 0 | S89: =SUM(F89:Q89) -> #REF! | T89: =SUM(G89:R89) -> #REF! | U89: =SUM(H89:S89) -> #REF!
C90: Salvaco 2 Liter | E90: Box | F90: ='[22]Januari 24'!AL75 -> 19659 | G90: ='[22]Februari 24'!AI84 -> #REF! | H90: ='[22]Maret 24'!AL84 -> 0 | I90: ='[22]April 24'!AL84 -> 0 | J90: ='[22]Mei 24'!AL84 -> 0 | K90: ='[22]Juny 24'!AL84 -> 0 | L90: ='[22]July 24'!AL84 -> 0 | M90: ='[22]Agustus 24'!AL84 -> 0 | N90: ='[22]September 24'!AL84 -> 0 | O90: ='[22]Oktober 24'!AL84 -> 0 | P90: ='[22]November 24'!AL84 -> 0 | Q90: ='[22]Desember 24'!AL84 -> 0 | S90: =SUM(F90:Q90) -> #REF! | T90: =SUM(G90:R90) -> #REF! | U90: =SUM(H90:S90) -> #REF!
C91: Pouch | S91: Pouch | T91: Pouch | U91: Pouch
C92: Salvaco 1 Liter | E92: Pouch | F92: =F89*12 -> 206364 | G92: =G89*12 -> #REF! | H92: =H89*12 -> 0 | I92: =I89*12 -> 0 | J92: =J89*12 -> 0 | K92: =K89*12 -> 0 | L92: =L89*12 -> 0 | M92: =M89*12 -> 0 | ... Q92: =Q89*12 -> 0 | S92: =SUM(F92:Q92) -> #REF! | T92: =SUM(G92:R92) -> #REF! | U92: =SUM(H92:S92) -> #REF!
C93: Salvaco 2 Liter | E93: Pouch | F93: =F90*6 -> 117954 | G93: =G90*6 -> #REF! | H93: =H90*6 -> 0 | I93: =I90*6 -> 0 | J93: =J90*6 -> 0 | K93: =K90*6 -> 0 | L93: =L90*6 -> 0 | M93: =M90*6 -> 0 | ... Q93: =Q90*6 -> 0 | S93: =SUM(F93:Q93) -> #REF! | T93: =SUM(G93:R93) -> #REF! | U93: =SUM(H93:S93) -> #REF!
C94: REJECT MATERIAL (%) | S94: Loss Material | T94: Loss Material | U94: Loss Material
C95: Carton | S95: Carton | T95: Carton | U95: Carton
C96: Salvaco 1 Liter | D96: 0.3 | E96: % | F96: =F89/F80*100 -> 100 | G96: =G89/G80*100 -> #REF! | H96: =H89/H80*100 -> #DIV/0! | I96: =I89/I80*100 -> #DIV/0! | J96: =J89/J80*100 -> #DIV/0! | K96: =K89/K80*100 -> #DIV/0! | L96: =L89/L80*100 -> #DIV/0! | M96: =M89/M80*100 -> #DIV/0! | ... Q96: =Q89/Q80*100 -> #DIV/0! | S96: =S89/S80*100 -> #REF! | T96: =T89/T80*100 -> #REF! | U96: =U89/U80*100 -> #REF!
C97: Salvaco 2 Liter | D97: 0.3 | E97: % | F97: =F90/F81*100 -> 100 | G97: =G90/G81*100 -> #REF! | H97: =H90/H81*100 -> #DIV/0! | I97: =I90/I81*100 -> #DIV/0! | J97: =J90/J81*100 -> #DIV/0! | K97: =K90/K81*100 -> #DIV/0! | L97: =L90/L81*100 -> #DIV/0! | M97: =M90/M81*100 -> #DIV/0! | ... Q97: =Q90/Q81*100 -> #DIV/0! | S97: =S90/S81*100 -> #REF! | T97: =T90/T81*100 -> #REF! | U97: =U90/U81*100 -> #REF!
C98: Pouch | S98: Pouch | T98: Pouch | U98: Pouch
C99: Salvaco 1 Liter | D99: 0.5 | E99: % | F99: =F92/F83*100 -> 100 | G99: =G92/G83*100 -> #REF! | H99: =H92/H83*100 -> #DIV/0! | I99: =I92/I83*100 -> #DIV/0! | J99: =J92/J83*100 -> #DIV/0! | K99: =K92/K83*100 -> #DIV/0! | L99: =L92/L83*100 -> #DIV/0! | M99: =M92/M83*100 -> #DIV/0! | ... Q99: =Q92/Q83*100 -> #DIV/0! | S99: =S92/S83*100 -> #REF! | T99: =T92/T83*100 -> #REF! | U99: =U92/U83*100 -> #REF!
C100: Salvaco 2 Liter | D100: 0.5 | E100: % | F100: =F93/F84*100 -> 100 | G100: =G93/G84*100 -> #REF! | H100: =H93/H84*100 -> #DIV/0! | I100: =I93/I84*100 -> #DIV/0! | J100: =J93/J84*100 -> #DIV/0! | K100: =K93/K84*100 -> #DIV/0! | L100: =L93/L84*100 -> #DIV/0! | M100: =M93/M84*100 -> #DIV/0! | ... Q100: =Q93/Q84*100 -> #DIV/0! | S100: =S93/S84*100 -> #REF! | T100: =T93/T84*100 -> #REF! | U100: =U93/U84*100 -> #REF!
B101: 6 | C101: PACKAGING (Brand Nusakita) | S101: Packaging | T101: Packaging | U101: Packaging
C102: Olein IV 60 Consume | E102: Kg | F102: ='[22]Januari 24'!AL96 -> 461724.08 | G102: ='[22]Februari 24'!AI96 -> #REF! | H102: ='[22]Maret 24'!AL96 -> 0 | I102: ='[22]April 24'!AL96 -> 0 | J102: ='[22]Mei 24'!AL96 -> 0 | K102: ='[22]Juny 24'!AL96 -> 0 | L102: ='[22]July 24'!AL96 -> 0 | M102: ='[22]Agustus 24'!AL96 -> 0 | N102: ='[22]September 24'!AL96 -> 0 | O102: ='[22]Oktober 24'!AL96 -> 0 | P102: ='[22]November 24'!AL96 -> 0 | Q102: ='[22]Desember 24'!AL96 -> 0 | S102: =SUM(S103:S104) -> #REF! | T102: =SUM(T103:T104) -> #REF! | U102: =SUM(U103:U104) -> #REF!
...

Sheet Detail Septembe OIP Akhir Plant
D2: PT. INDUSTRI NABATI LESTARI | L2: Nomor Dokumen | N2: Tanggal Berlaku
D3: PABRIK MINYAK GORENG | L3: INLHO/BOPP-PRD/F-021 | N3: 44866
D4: Kantor Pusat : Komp.KEK Sei Mangkei, Kav.2-3, Kec. Bosar Maligas, Kab. Simalungun, Sumatera Utara, 21184 | L4: Nomor Revisi | N4: Halaman
D5: BERITA ACARA DEPARTEMEN REFINERY & FRACTIONATION | L5: 00 | N5: 2
C6: Hal : Stock Opname Oil In Plant ( Refinery & Fractionation )
C7: Berikut kami lampirkan laporan Stok Opname Oil In Plant Per-tanggal 01 Oktober 2024.
D8: 1. Refinery | J8: 2. Fractination
D9: No. | E9: Tag. | F9: Volume (Ton) | G9: % | H9: Quantity (Ton) | J9: No. | K9: Tag. | L9: Volume (Ton) | M9: % | N9: Quantity (Ton)
F10: By Lipico | L10: By Lipico
D11: 1 | E11: MX312 | F11: 0.81 | G11: 100 | H11: =G11*F11/100 -> 0.81 | J11: 1 | K11: CR 1201 | L11: 56 | M11: 98 | N11: =M11*L11/100 -> 54.88
D12: 2 | E12: VE611 | F12: 72.587 | G12: 80 | H12: =G12*F12/100 -> 58.0696 | J12: 2 | K12: CR 1202 | L12: 56 | M12: 98 | N12: =M12*L12/100 -> 54.88
D13: 3 | E13: VE612 | F13: 23.884 | G13: 49.5 | H13: =G13*F13/100 -> 11.82258 | J13: 3 | K13: CR 1203 | L13: 56 | M13: 98 | N13: =M13*L13/100 -> 54.88
D14: 4 | E14: FL621 | F14: 7.38 | G14: 0 | H14: =G14*F14/100 -> 0 | J14: 4 | K14: CR 1204 | L14: 56 | M14: 98 | N14: =M14*L14/100 -> 54.88
D15: 5 | E15: FL622 | F15: 7.38 | G15: 100 | H15: =G15*F15/100 -> 7.38 | J15: 5 | K15: CR 1205 | L15: 56 | M15: 98 | N15: =M15*L15/100 -> 54.88
D16: 6 | E16: FL623 | F16: 7.38 | G16: 100 | H16: =G16*F16/100 -> 7.38 | J16: 6 | K16: CR 1206 | L16: 56 | M16: 98 | N16: =M16*L16/100 -> 54.88
D17: 7 | E17: FL624 | F17: 7.38 | G17: 0 | H17: =G17*F17/100 -> 0 | J17: 7 | K17: CR 1207 | L17: 56 | M17: 98 | N17: =M17*L17/100 -> 54.88
D18: 8 | E18: FL625 | F18: 7.38 | G18: 0 | H18: =G18*F18/100 -> 0 | J18: 8 | K18: CR 1208 | L18: 56 | M18: 98 | N18: =M18*L18/100 -> 54.88 | AB18: 55.888
D19: 9 | E19: FL625A/B | F19: 0.369 | G19: 100 | H19: =G19*F19/100 -> 0.369 | J19: 9 | K19: CR 1209 | L19: 56 | M19: 98 | N19: =M19*L19/100 -> 54.88 | AB19: 55.888
D20: 10 | E20: FL626A/B | F20: 0.243 | G20: 100 | H20: =G20*F20/100 -> 0.243 | J20: 10 | K20: CR 1210 | L20: 56 | M20: 98 | N20: =M20*L20/100 -> 54.88 | AB20: 55.776
D21: 11 | E21: FL741A/B | F21: 0.306 | G21: 100 | H21: =G21*F21/100 -> 0.306 | J21: 11 | K21: CR 1211 | L21: 56 | M21: 62.5 | N21: =M21*L21/100 -> 35 | AB21: 55.776
D22: 12 | E22: VE661 | F22: 5.383 | G22: 30 | H22: =G22*F22/100 -> 1.6149 | J22: 12 | K22: CR 1212 | L22: 56 | M22: 98.1 | N22: =M22*L22/100 -> 54.936 | AB22: 55.776
D23: 13 | E23: TK641 | F23: 7.798 | G23: 0 | H23: =G23*F23/100 -> 0 | J23: 13 | K23: T-221 | L23: 56 | M23: 0 | N23: =M23*L23/100 -> 0 | AB23: 55.664
D24: 14 | E24: VE701 | F24: 51.513 | G24: 44.3 | H24: =G24*F24/100 -> 22.820259 | J24: 14 | K24: T-261 | L24: 14.59 | M24: 78.7 | N24: =M24*L24/100 -> 11.48233 | AB24: 55.664
D25: 15 | E25: HE721A | F25: 18.45 | G25: 25 | H25: =G25*F25/100 -> 4.6125 | J25: 15 | K25: T-241 | L25: 14.39 | M25: 81.5 | N25: =M25*L25/100 -> 11.72785 | AB25: 0
D26: 16 | E26: HE721B | F26: 18.45 | G26: 100 | H26: =G26*F26/100 -> 18.45 | J26: 16 | K26: T-231 A | L26: 23.4 | M26: 0 | N26: =M26*L26/100 -> 0 | AB26: 0
D27: 17 | E27: HE722 | F27: 12.33 | G27: 80 | H27: =G27*F27/100 -> 9.864 | J27: 17 | K27: T-231 B | L27: 23.4 | M27: 0 | N27: =M27*L27/100 -> 0 | AB27: 55.38
D28: 18 | E28: PR731 | F28: 8.171 | G28: 25 | H28: =G28*F28/100 -> 2.04275 | J28: 18 | K28: T-251 A | L28: 2.25 | M28: 0 | N28: =M28*L28/100 -> 0 | AB28: 55.88
D29: 19 | E29: DE732 | F29: 110.7 | G29: 100 | H29: =G29*F29/100 -> 110.7 | J29: 19 | K29: T-251 B | L29: 2.25 | M29: 0 | N29: =M29*L29/100 -> 0 | AB29: 56
D30: 20 | E30: VE 771 | F30: 0.433 | G30: 0 | H30: =G30*F30/100 -> 0 | J30: Total | N30: =SUM(N11:N29) -> 661.94618 | AB30: 7.36
D31: 21 | E31: VE751 | F31: 4.149 | G31: 50 | H31: =G31*F31/100 -> 2.0745 | J31: Dengan Rincian OIP Fract Sebagai berikut : | AB31: 11.44
D32: 22 | E32: VE753 | F32: 0.814 | G32: 0 | H32: =G32*F32/100 -> 0 | K32: RBDPO : | L32: =SUM(N11:N27)+N28+N29 -> 661.94618 | M32: Mt | AB32: 47.88
D33: Total | H33: =SUM(H11:H32) -> 258.55909 | J33: RBDPS : | L33: =N26+N27 -> 0 | M33: Mt | AB33: =SUM(AB18:AB32) -> 624.372
D34: Dengan Rincian OIP Refinery Sebagai berikut :
D35: CPO : | E35: =H12+H13 -> 69.89218 | F35: Mt
D36: RBDPO : | E36: =H33-E35 -> 188.66691 | F36: Mt
C38: Demikian saya sampaikan, Terimakasih.
D39: Dibuat Oleh : | G39: Diperiksa Oleh : | L39: Diketahui Oleh :
C43: Reza Pahlevi Panjaitan | G43: Sudarianto | L43: Gunawan E. Putra
D44: SPV Produksi | G44: Manager Produksi | L44: Head Controller and Tax

Sheet Prod
B2: MONTHLY PRODUCTION REPORT
B3: PT. INDUSTRI NABATI LESTARI
B4: Periode 01 s/d 30 September 2024
B5: NO | C5: Item | D5: Unit | E5: September | H5: Remaks
E6: Budget | F6: Actual | G6: Percentage Act.
B7: 1. | C7: PRODUCTION
C8: Refinery Plant
C9: Running Days | D9: Days | E9: 19 | F9: ='September - 2024'!AM6 -> 27 | G9: =(F9/E9) -> 1.4210526 | H9: Tercapai
C10: CPO Incoming | D10: Kg
C11: CPO Consume | D11: Kg | E11: 34952000 | F11: ='September - 2024'!AM9 -> 24046290 | G11: =(F11/E11) -> 0.68798037 | H11: Tidak Tercapai
C12: - Avg. FFA | D12: % | E12: 5 | F12: ='September - 2024'!AM13 -> 3.6441975 | G12: =(F12/E12) -> 0.72883951
C13: - Avg. Moist & Impurities | D13: % | E13: 0.5 | F13: ='September - 2024'!AM14 -> 0.41401235 | G13: =(F13/E13) -> 0.82802469
C14: - Avg. DOBI | D14: % | E14: 22.2 | F14: ='September - 2024'!AM15 -> 21.265185 | G14: =(F14/E14) -> 0.95789122
C15: Product
C16: RBDPO | D16: Kg | E16: 33124010 | F16: ='September - 2024'!AM18 -> 22783491 | G16: =(F16/E16) -> 0.68782405
C17: PFAD | D17: Kg | E17: 1572840 | F17: ='September - 2024'!AM19 -> 998518 | G17: =(F17/E17) -> 0.63485033
C19: Fraksinasi Plant
C20: Total Proses RBDPO | D20: Kg | E20: =E23+E36+E41 -> 31417000 | F20: ='September - 2024'!AM25 -> 23189025 | G20: =(F20/E20) -> 0.73810437 | H20: Tidak Tercapai
C21: Total Olah RBDPO ( Feed ) | D21: Kg | E21: =E23+E36+E41 -> 31417000 | F21: ='September - 2024'!AM23 -> 22592969 | G21: =(F21/E21) -> 0.71913197 | H21: Tidak Tercapai
C22: Fractionation Olein IV 56
C23: RBDPO Consume | D23: Kg | E23: 7883000 | F23: =F24+F25 -> 16566545 | G23: =(F23/E23) -> 2.1015533 | H23: Tercapai
C24: Olein IV 56 | D24: Kg | E24: 6464000 | F24: ='September - 2024'!AM29 -> 13789795 | G24: =(F24/E24) -> 2.1333222 | H24: Tercapai
C25: Stearin | D25: Kg | E25: 1419000 | F25: ='September - 2024'!AM30 -> 2776750 | G25: =(F25/E25) -> 1.9568358 | H25: Tercapai
C26: Fractionation Olein IV 57 ( Bulk )
C27: RBDPO Consume | D27: Kg | E27: 0
C28: Olein IV 57 | D28: Kg | E28: 0 | F28: 0 | G28: 0
C29: Stearin | D29: Kg | E29: 0
C30: Fractionation Olein IV 57 ( Retail )
C31: CPO | D31: Kg | E31: 1812101.9 | G31: =(F31/E31)*100 -> 0
C32: RBDPO Consume | D32: Kg | E32: 1707000 | F32: =F33+F34 -> 40950 | G32: =(F32/E32)*100 -> 2.3989455 | H32: Tidak Tercapai
C33: Olein IV 57 | D33: Kg | E33: 1280000 | F33: ='September - 2024'!AM38 -> 30800 | G33: =(F33/E33)*100 -> 2.40625 | H33: Tidak Tercapai
C34: Stearin | D34: Kg | E34: 427000 | F34: ='September - 2024'!AM39 -> 10150 | G34: =(F34/E34)*100 -> 2.3770492 | H34: Tidak Tercapai
C35: Fractionation Olein IV 58
C36: RBDPO Consume | D36: Kg | E36: 21429000 | F36: =F37+F38 -> 6581530 | G36: =(F36/E36)*100 -> 30.713192 | H36: Tidak Tercapai
C37: Olein IV 58 | D37: Kg | E37: 15000000 | F37: ='September - 2024'!AM42 -> 4788598 | G37: =(F37/E37)*100 -> 31.923987 | H37: Tidak Tercapai
C38: Stearin | D38: Kg | E38: 6429000 | F38: ='September - 2024'!AM43 -> 1792932 | G38: =(F38/E38)*100 -> 27.888194 | H38: Tidak Tercapai
C39: Fractionation Olein IV 60
C40: CPO | E40: 2234607.2 | F40: 0 | G40: =(F40/E40)*100 -> 0
C41: RBDPO Consume | D41: Kg | E41: 2105000 | F41: 0 | G41: =(F41/E41)*100 -> 0 | H41: Tidak Tercapai
C42: Olein IV 60 Salvaco | D42: Kg | E42: 1263000 | F42: 0 | G42: =(F42/E42)*100 -> 0 | H42: Tidak Tercapai
C43: Soft Stearin | D43: Kg | E43: 842000 | F43: 0 | G43: =(F43/E43)*100 -> 0 | H43: Tidak Tercapai
B44: 2. | C44: % YIELD
C45: RBDPO | D45: % | E45: 94.77 | F45: =(F16/(F11))*100 -> 94.748466 | G45: =(F45/E45)*100 -> 99.977278 | H45: Tidak Tercapai
C46: PFAD | D46: % | E46: 4.5 | F46: =(F17/(F11))*100 -> 4.1524826 | G46: =(F46/E46)*100 -> 92.27739 | H46: Tidak Tercapai
C47: Olein IV 56 | D47: % | E47: 82 | F47: =F24/(F24+F25)*100 -> 83.238811 | G47: =(F47/E47)*100 -> 101.51074 | H47: Tercapai
C48: Stearin | D48: % | E48: 18 | F48: =(F25/F23)*100 -> 16.761189 | G48: =(F48/E48)*100 -> 93.117719 | H48: Tercapai
C49: Olein IV 57 ( Bulk ) | D49: % | E49: 75 | F49: 0 | G49: =(F49/E49)*100 -> 0
C50: Stearin | D50: % | E50: 25 | F50: 0 | G50: =(F50/E50)*100 -> 0
C51: Olein IV 57 ( Retail ) | D51: % | E51: 75 | F51: =F33/(F33+F34)*100 -> 75.213675 | G51: =(F51/E51)*100 -> 100.2849 | H51: Tercapai
C52: Stearin | D52: % | E52: 25 | F52: =(F34/F32)*100 -> 24.786325 | G52: =(F52/E52)*100 -> 99.145299 | H52: Tercapai
C53: Olein IV 58 | D53: % | E53: 70 | F53: =F37/(F37+F38)*100 -> 72.758128 | G53: =(F53/E53)*100 -> 103.94018 | H53: Tercapai
C54: Stearin | D54: % | E54: 30 | F54: =(F38/F36)*100 -> 27.241872 | G54: =(F54/E54)*100 -> 90.806241 | H54: Tercapai
C55: Olein IV 60 | D55: % | E55: 60 | F55: 0 | G55: =(F55/E55)*100 -> 0
C56: Soft Stearin | D56: % | E56: 40 | F56: 0 | G56: =(F56/E56)*100 -> 0
B57: 3. | C57: CHEMICAL CONSUMABLE
C58: Bleaching Earth to Poram Spec | D58: Kg | E58: 232362 | F58: ='September - 2024'!AM65 -> 187513 | G58: =(F58/E58)*100 -> 80.698651
D59: Kg/MT | E59: 8 | F59: ='September - 2024'!AM66*10 -> 7.7980013 | G59: =(F59/E59)*100 -> 97.475016 | H59: Tercapai
C60: Bleaching Earth to Branded Spec | D60: Kg | E60: 106326 | F60: 0 | G60: =(F60/E60)*100 -> 0
D61: Kg/MT | E61: 18 | F61: 0 | G61: =(F61/E61)*100 -> 0
C62: Phosporic Acid | D62: Kg | E62: 20971 | F62: ='September - 2024'!AM69 -> 12499.518 | G62: =(F62/E62)*100 -> 59.603824
D63: Kg/MT | E63: 0.6 | F63: ='September - 2024'!AM70*10 -> 0.51981067 | G63: =(F63/E63)*100 -> 86.635111 | H63: Tercapai
B64: 4. | C64: OIL LOSSES
C65: (Loss)/Gain | D65: % | E65: -0.73 | F65: ='September - 2024'!AM71 -> -1.099051 | G65: =(F65/E65)*100 -> 150.55494 | H65: Tidak Tercapai
C66: % Oil Content | D66: % | E66: 22 | F66: 22 | G66: =(F66/E66)*100 -> 100
C67: Spent Bleaching Earth | D67: Kg | E67: 413199.36 | F67: ='September - 2024'!AM74 -> 189044.92 | G67: =(F67/E67)*100 -> 45.751504
B68: NB :
B69: - BE Achieve dengan pemakaian consume Bleaching Earth 7,80 Kg/MT
B70: - Untuk hari olah Produksi terpenuhi namun dalam kondisi Slow Flowrate dikarenakan Shortage CPO dan target Shipment yang tercapai hanya Olein IV 56
B72: - Total CPO Proses sebesar : 24.046 Mt dengan total CPO Incoming ke INL sebanyak : 24.987 MT
B73: - Rata rata incoming CPO perhari 832 MT
A75: Prepared by, | D75: Checked by, | H75: Approved by,
A79: Syaiful Sembiring | D79: Reza P. Panjaitan | F79: Sudarianto | H79: Eben Jaya Ginting
A80: Admin. Process | D80: Supervisor Produksi | F80: Jr. Manager Produksi | H80: Manager Plant

Sheet Utility
D2: UTILITY (GAS, STEAM, WATER & POWER) REPORT
D3: PT. INDUSTRI NABATI LESTARI
D5: Periode 01 s/d 30 September 2024
D6: No | E6: Item | F6: Norma | G6: UoM | H6: September | K6: Consume CPO ( MT ) | L6: Remaks
H7: Budget | I7: Actual | J7: Percentage Act.
E9: Total Feed Raw Material CPO | K9: 24046
D10: 1. | E10: GAS CONSUMPTION
E11: Incoming *base on INL | G11: mmbtu | I11: ='September - 2024'!AM226 -> 33097.49
E12: Incoming *base on Pertagas | F12: 1460.001 | G12: mmbtu | H12: 26051.47 | I12: ='September - 2024'!AM225 -> 32134.349 | J12: =I12/H12 -> 1.2334947 | K12: =I12/K9 -> 1.3363698
E13: Distribution to
E14: HP Boiler Refinery | G14: mmbtu | H14: 3907.73 | I14: ='September - 2024'!AM228 -> 5868.6339 | J14: =I14/H14 -> 1.5018013 | K14: =I14/K9 -> 0.24405863
E15: MP Boiler | G15: mmbtu | H15: 22143.74 | I15: =I12-I14 -> 26265.715 | J15: =I15/H15 -> 1.1861463 | K15: =I15/K9 -> 1.0923112
E16: Total | G16: mmbtu | H16: 26051.47 | I16: =I12 -> 32134.349 | J16: =I16/H16 -> 1.2334947 | K16: =SUM(K14+K15) -> 1.3363698
D17: 2. | E17: STEAM CONSUMPTION
E18: Incoming | G18: Kg | H18: 11424000 | I18: ='September - 2024'!AM233 -> 5670273 | J18: =I18/H18 -> 0.49634743 | K18: =I18/$K$9 -> 235.80941
E19: Distribution to | K19: =I19/$K$9 -> 0
E20: Refinery | F20: < 90 | G20: Kg | H20: 3420000 | I20: ='September - 2024'!AM235 -> 3927994 | J20: =I20/H20 -> 1.1485363 | K20: =I20/$K$9 -> 163.35332
E21: Fractionation | F21: < 61 | G21: Kg | H21: 2318000 | I21: ='September - 2024'!AM237 -> 1632200 | J21: =I21/H21 -> 0.7041415 | K21: =I21/$K$9 -> 67.878233
E22: Others | F22: 106000 | G22: Kg | H22: 5686000 | I22: ='September - 2024'!AM239 -> 110079 | J22: =I22/H22 -> 0.019359655 | K22: =I22/$K$9 -> 4.5778508
E23: Total | G23: Kg | H23: 11424000 | I23: =SUM(I20:I22) -> 5670273 | J23: =I23/H23 -> 0.49634743 | K23: =I23/$K$9 -> 235.80941
D24: 3. | E24: WATER CONSUMPTION
E25: Incoming Raw Water | G25: m3 | H25: 19123.69 | I25: ='September - 2024'!AM242 -> 18965 | J25: =I25/H25 -> 0.99170192 | K25: =I25/$K$9 -> 0.78869666
E26: - Suplay To RO Product | I26: ='September - 2024'!AM248 -> 9920.3 | K26: =I26/$K$9 -> 0.4125551
E27: - Suplay To Proses dan Sanitary | I27: =SUM(I29:I31) -> 9044.7 | K27: =I27/$K$9 -> 0.37614156
E28: Rincian Outgoing Proses | K28: =I28/$K$9 -> 0
E29: Softener Product (to Refinery) | F29: < 0,5 | G29: m3 | H29: 1521.33 | I29: ='September - 2024'!AM244 -> 2699 | J29: =I29/H29 -> 1.7741056 | K29: =I29/$K$9 -> 0.1122432
E30: Softener Product (to Fractionation) | F30: < 0,4 | G30: m3 | H30: 2622 | I30: ='September - 2024'!AM246 -> 2060 | J30: =I30/H30 -> 0.7856598 | K30: =I30/$K$9 -> 0.085669134
E31: Others | G31: m3 | H31: 2730.3 | I31: ='September - 2024'!AM249 -> 4285.7 | J31: =I31/H31 -> 1.569681 | K31: =I31/$K$9 -> 0.17822923
E32: Total | G32: m3 | H32: 6873.63 | I32: =SUM(I26:I27) -> 18965 | J32: =I32/H32 -> 2.7590953 | K32: =I32/$K$9 -> 0.78869666
D33: 4 | E33: POWER CONSUMPTION
E34: Incoming
E35: PLN *base on BA Kinra | G35: Kwh | H35: 568099 | I35: ='September - 2024'!AM254 -> 640500 | J35: =I35/H35 -> 1.1274443 | K35: =I35/$K$9 -> 26.636447
E36: Outgoing | K36: =I36/$K$9 -> 0
E37: - Physical Refinery Plant | F37: 5404.17 | G37: Kwh | H37: 102679 | I37: ='September - 2024'!AM259 -> 98200 | J37: =I37/H37 -> 0.95637862 | K37: =I37/$K$9*1000 -> 4083.8393
E38: - Refinery - Cooling Water System | F38: 3850.42 | G38: Kwh | H38: 73158 | I38: ='September - 2024'!AM257 -> 81760 | J38: =I38/H38 -> 1.1175811 | K38: =I38/$K$9*1000 -> 3400.1497
E39: - Refinery - Utilities | F39: 11.81 | G39: Kwh | H39: 212 | I39: ='September - 2024'!AM267 -> 444.36 | J39: =I39/H39 -> 2.0960377 | K39: =I39/$K$9*1000 -> 18.479581
E40: - Dry Fractionation Plant | F40: 5759.67 | G40: Kwh | H40: 109440 | I40: ='September - 2024'!AM264 -> 94200 | J40: =I40/H40 -> 0.86074561 | K40: =I40/$K$9*1000 -> 3917.4915
E41: - Dry Fractionation CW System | F41: 1308.96 | G41: Kwh | H41: 28747 | I41: ='September - 2024'!AM262 -> 22645 | J41: =I41/H41 -> 0.78773437 | K41: =I41/$K$9*1000 -> 941.73667
E42: - Lighting - Refinery & Dry Fractionation | F42: 241.12 | G42: Kwh | H42: 4581 | I42: ='September - 2024'!AM268 -> 7791.5 | J42: =I42/H42 -> 1.7008295 | K42: =I42/$K$9*1000 -> 324.02479
D44: Note untuk Power Consumption
D45: Selisih antara incoming dan outgoing dikarenakan hal berikut :
D47: - Over pemakaian Gas dikarenakan running sesuai RKAP 19 hari namun plant running 27 hari
E50: Prepared by, | F50: Checked by, | K50: Approved by,
E54: Syaiful Sembiring | F54: Reza P. Panjaitan | I54: Sudarianto | K54: Eben Jaya Ginting
E55: Admin. Process | F55: Supervisor Produksi | I55: Jr. Manager Produksi | K55: Manager Plant

Sheet Qty cons analysis
D2: Quantity Utility Consumption Analysis (based on Guarantee Utility Consumption)
D3: Refinery & Fractionation Plant
D4: Periode 01 s/d 30 September 2024
D5: Consumption | E5: UoM | F5: Budget | G5: Actual | H5: Under (Over) Budget | I5: Explanation Under / Over budget
D6: CPO Consume | E6: Kg | F6: 34952000 | G6: ='September - 2024'!AM9 -> 24046290 | H6: =G6/F6 -> 0.68798037
D7: RbdPO Consume | E7: Kg | F7: 33124010 | G7: ='September - 2024'!AM18 -> 22783491 | H7: =G7/F7 -> 0.68782405
D8: TOTAL ACTUAL CONSUMPTION
D9: Refinery
D10: Bleaching Earth to Poram Spec | E10: Kg | F10: 232362 | G10: ='September - 2024'!AM65 -> 187513 | H10: =F10-G10 -> 44849
D11: Bleaching Earth to Branded Spec | E11: Kg | F11: 106326 | G11: ='September - 2024'!AM67 -> 0 | H11: =F11-G11 -> 106326
D12: Phosporic Acid | E12: Kg | F12: 20971 | G12: ='September - 2024'!AM69 -> 12499.518 | H12: =F12-G12 -> 8471.482
D13: Gas Consumption (HP Boiler) | E13: mmbtu | F13: 22143.74 | G13: ='September - 2024'!AM225 -> 32134.349 | H13: =F13-G13 -> -9990.6091
D14: Gas Consumption (HP Boiler) | E14: mmbtu | F14: 3907.73 | G14: ='September - 2024'!AM226 -> 33097.49 | H14: =F14-G14 -> -29189.76
D15: Cooling Water top up to Cooling Tower | E15: m3 | F15: 1521.33 | G15: ='September - 2024'!AM244 -> 2699 | H15: =F15-G15 -> -1177.67
D16: Steam | E16: Kg | F16: 11424000 | G16: ='September - 2024'!AM235 -> 3927994 | H16: =F16-G16 -> 7496006
D17: Power (Process Plant) | E17: Kwh | F17: 102679 | G17: ='September - 2024'!AM259 -> 98200 | H17: =F17-G17 -> 4479
D18: Power (Cooling Tower) | E18: Kwh | F18: 73158 | G18: ='September - 2024'!AM257 -> 81760 | H18: =F18-G18 -> -8602
D19: Fractionation
D20: Cooling Water top up to Cooling Tower | E20: m3 | F20: 2622 | G20: ='September - 2024'!AM262 -> 22645 | H20: =F20-G20 -> -20023
D21: Steam | E21: Kg | F21: 2318000 | G21: ='September - 2024'!AM237 -> 1632200 | H21: =F21-G21 -> 685800
D22: Power (Process Plant) | E22: Kwh | F22: 109440 | G22: ='September - 2024'!AM264 -> 94200 | H22: =F22-G22 -> 15240
D23: Power (Cooling Tower) | E23: Kwh | F23: 28747 | G23: ='September - 2024'!AM262 -> 22645 | H23: =F23-G23 -> 6102
D24: ACTUAL CONSUMPTION PER MT RAW MATERIAL
D25: Refinery
D26: Bleaching Earth to Poram Spec | E26: Kg/MT | F26: 8 | G26: =(G10/$G$6)*1000 -> 7.7980013 | H26: =F26-G26 -> 0.20199873
D27: Bleaching Earth to Branded Spec | E27: Kg/MT | F27: 16 | G27: =(G11/$G$6)*1000 -> 0 | H27: =F27-G27 -> 16
D28: Phosporic Acid | E28: Kg/MT | F28: 0.55 | G28: =(G12/$G$6)*1000 -> 0.51981067 | H28: =F28-G28 -> 0.030189335
D29: Gas Consumption (HP Boiler) | E29: Nm3/MT | F29: 4.2 | G29: =(G13/$G$6)*1000 -> 1.3363537 | H29: =F29-G29 -> 2.8636463 | I29: Gas Over dikarenakan kapasitas tidak tercapai
D30: Gas Consumption (HP Boiler) **) | E30: mmbtu/MT | F30: 0.147294 | G30: =(G14/$G$6)*1000 -> 1.3764073 | H30: =F30-G30 -> -1.2291133
D31: Cooling Water top up to Cooling Tower | E31: m3/MT | F31: 0.55 | G31: =(G15/$G$6)*1000 -> 0.11224185 | H31: =F31-G31 -> 0.43775815
D32: Steam | E32: Kg/MT | F32: 90 | G32: =(G16/$G$6)*1000 -> 163.35135 | H32: =F32-G32 -> -73.351353 | I32: Steam Refinery Over dikarenakan kapasitas tidak tercapai
D33: Power (Process Plant) | E33: Kwh/MT | F33: 3.6133333 | G33: =(G17/$G$6)*1000 -> 4.0837901 | H33: =F33-G33 -> -0.47045672 | I33: Power Over dikarenakan kapasitas tidak tercapai
D34: Power (Cooling Tower) | E34: Kwh/MT | F34: 2.1290444 | G34: =(G18/$G$6)*1000 -> 3.4001087 | H34: =F34-G34 -> -1.2710643
D35: Fractionation
D36: Cooling Water top up to Cooling Tower | E36: m3/MT | F36: 0.4 | G36: =(G20/$G$6)*1000 -> 0.94172531 | H36: =F36-G36 -> -0.54172531
D37: Steam | E37: Kg/MT | F37: 61 | G37: =(G21/$G$6)*1000 -> 67.877415 | H37: =F37-G37 -> -6.8774148 | I37: Steam Over dikarenakan menggunakan 2 unit chiller
D38: Power (Process Plant) | E38: Kwh/MT | F38: 3.6996983 | G38: =(G22/$G$6)*1000 -> 3.9174442 | H38: =F38-G38 -> -0.21774592 | I38: Power Over dikarenakan kapasitas tidak tercapai
D39: Power (Cooling Tower) | E39: Kwh/MT | F39: 0.98466667 | G39: =(G23/$G$6)*1000 -> 0.94172531 | H39: =F39-G39 -> 0.042941353
D42: - BE Achieve dengan pemakaian consume Bleaching Earth 7,80 Kg/MT
D43: * Steam Refinery Over dikarenakan kapasitas tidak tercapai
D44: * Gas Refinery Over dikarenakan kapasitas tidak tercapai
D45: * Power Fractionation Over dikarenakan kapasitas tidak tercapai
D47: Prepared by, | G47: Checked by, | I47: Approved by,
D51: Syaiful Sembiring | F51: Reza P. Panjaitan | H51: Sudarianto | I51: Eben Jaya Ginting
D52: Admin. Process | F52: Supervisor Produksi | H52: Jr. Manager Produksi | I52: Manager Plant

Sheet Downtime Ref September
F2: DOWN TIME SLOW FLOWRATE PRODUCTION REFINERY
F4: Periode 01/30 September 2024
F5: TANGGAL | G5: CAPACITY (Kg) | H5: REMARKS | I5: Down time | M5: Tph
I6: Stop | J6: Slow | K6: % | AE6: 17 | AF6: 18 | AG6: 19 | AH6: 20 | AI6: 21 | AJ6: 22 | AK6: 23 | AL6: 24 | AM6: 25 | AN6: 26 | AO6: 27 | AP6: 28 | AQ6: 29 | AR6: 30 | AS6: 31
F7: 1 | G7: 325264 | H7: Penyesuaian incoming CPO | J7: =(2200-(G7/1000))/91.7 -> 20.444231 | K7: =G7/2200/1000 -> 0.14784727 | M7: =(G7/1000)/24 -> 13.552667 | O7: =249.262+270.9 -> 520.162 | P7: =1356.367+39.742 -> 1396.109 | Q7: =1086.521+50.6 -> 1137.121 | R7: =1353.558+373.309 -> 1726.867 | S7: 1942.746 | T7: 1868.212 | U7: 2057.011 | V7: 1781.844 | W7: 1250.764 | X7: 1613.486 | Y7: 1325.077 | Z7: =66.442+571.568 -> 638.01 | AA7: =815.429 -> 815.429 | AB7: =352.234+731.627 -> 1083.861 | AC7: =1626.002+13.213 -> 1639.215 | AD7: 2094.791 | AE7: 2075.375 | AF7: 2008.804 | AG7: 1946.712 | AH7: 1998.939 | AI7: =1623.839+281.468 -> 1905.307 | AJ7: 1610.024 | AK7: =1135.181+98.368 -> 1233.549 | AL7: =958.893+543.852 -> 1502.745 | AM7: 2043.15 | AN7: 1762.642 | AO7: 2170.336 | AP7: =1181.38+463.711 -> 1645.091 | AQ7: 219.474 | AR7: =48.153+1225.968+107.3 -> 1381.421
F8: 2 | G8: 244372 | H8: Penyesuaian incoming CPO | J8: =(2200-(G8/1000))/91.7 -> 21.326369 | K8: =G8/2200/1000 -> 0.11107818 | M8: =(G8/1000)/24 -> 10.182167
F9: 3 | G9: 1130594 | H9: Penyesuaian incoming CPO | J9: =(2200-(G9/1000))/91.7 -> 11.662007 | K9: =G9/2200/1000 -> 0.51390636 | M9: =(G9/1000)/24 -> 47.108083
F10: 4 | G10: 686462 | H10: Penyesuaian incoming CPO | J10: =(2200-(G10/1000))/91.7 -> 16.505322 | K10: =G10/2200/1000 -> 0.31202818 | M10: =(G10/1000)/24 -> 28.602583
F11: 5 | G11: 608618 | H11: Penyesuaian incoming CPO | J11: =(2200-(G11/1000))/91.7 -> 17.35422 | K11: =G11/2000/1000 -> 0.304309 | M11: =(G11/1000)/24 -> 25.359083
F12: 6 | G12: 662414 | H12: Penyesuaian incoming CPO | J12: =(2200-(G12/1000))/91.7 -> 16.767568 | K12: =G12/2200/1000 -> 0.30109727 | M12: =(G12/1000)/24 -> 27.600583
F13: 7 | G13: 612421 | H13: Penyesuaian incoming CPO | J13: =(2200-(G13/1000))/91.7 -> 17.312748 | K13: =G13/2200/1000 -> 0.27837318 | M13: =(G13/1000)/24 -> 25.517542
F14: 8 | G14: 386446 | H14: Penyesuaian incoming CPO | J14: =(2200-(G14/1000))/91.7 -> 19.777034 | K14: =G14/2200/1000 -> 0.17565727 | M14: =(G14/1000)/24 -> 16.101917
F15: 9 | G15: 1041561 | H15: Penyesuaian incoming CPO | J15: =(2200-(G15/1000))/91.7 -> 12.632923 | K15: =G15/2200/1000 -> 0.47343682 | M15: =(G15/1000)/24 -> 43.398375
F16: 10 | G16: 1056809 | H16: Penyesuaian incoming CPO | J16: =(2200-(G16/1000))/91.7 -> 12.466641 | K16: =G16/2200/1000 -> 0.48036773 | M16: =(G16/1000)/24 -> 44.033708
F17: 11 | G17: 1067764 | H17: Penyesuaian incoming CPO | J17: =(2200-(G17/1000))/91.7 -> 12.347176 | K17: =G17/2200/1000 -> 0.48534727 | M17: =(G17/1000)/24 -> 44.490167
F18: 12 | G18: 701797 | H18: Penyesuaian incoming CPO | J18: =(2200-(G18/1000))/91.7 -> 16.338092 | K18: =G18/2200/1000 -> 0.31899864 | M18: =(G18/1000)/24 -> 29.241542
F19: 13 | G19: 563620 | H19: Penyesuaian incoming CPO | J19: =(2200-(G19/1000))/91.7 -> 17.844929 | K19: =G19/2200/1000 -> 0.25619091 | M19: =(G19/1000)/24 -> 23.484167
F20: 14 | G20: 605861 | H20: Penyesuaian incoming CPO | J20: =(2200-(G20/1000))/91.7 -> 17.384286 | K20: =G20/2200/1000 -> 0.27539136 | M20: =(G20/1000)/24 -> 25.244208
F21: 15 | G21: 1587899 | H21: Penyesuaian incoming CPO | J21: =(2200-(G21/1000))/91.7 -> 6.6750382 | K21: =G21/2200/1000 -> 0.72177227 | M21: =(G21/1000)/24 -> 66.162458
F22: 16 | G22: 0 | H22: HOLD CPO Shortage | J22: =(2200-(G22/1000))/91.7 -> 23.991276 | K22: =G22/2200/1000 -> 0 | M22: =(G22/1000)/24 -> 0
F23: 17 | G23: 430122 | H23: Penyesuaian incoming CPO | J23: =(2200-(G23/1000))/91.7 -> 19.300742 | K23: =G23/2200/1000 -> 0.19551 | M23: =(G23/1000)/24 -> 17.92175
... F36: 30 | G36: 545232 | H36: Penyesuaian incoming CPO | J36: =(2200-(G36/1000))/91.7 -> 18.045453 | K36: =G36/2200/1000 -> 0.24783273 | M36: =(G36/1000)/24 -> 22.718
F37: TOTAL | G37: =SUM(G7:G36) -> 24005580 | I37: =SUM(I7:I36) -> 0 | J37: =SUM(J7:J36) -> 457.95442 | M37: =AVERAGE(M7:M36) -> 33.341083
G39: Summary
G40: 1. Slow flow rate due to Space Tank High | I40: 0 | J40: hours
G41: 2. Slow flow rate due to Olein IV 60 process | I41: 0 | J41: hours
G42: 3. Hold plant due to trip MP boiler & maintenance | I42: 0 | J42: hours
G43: 4. Penyesuaian incoming CPO | I43: =SUM(J7,J8,J9,J10,J11,J12,J13,J14,J15,J16,J17,J18,J19,J20,J21,J23,J24,J25,J26,J27,J31,J32,J33,J34,J35,J36) -> 361.99381 | J43: hours
G44: 5. Downtime due to Start Up Plant | J44: hours
G45: 6. Running Normal Plant | I45: 0 | J45: hours
G46: 7. Stop Plant due to Preventive Maintenance Plant | I46: 0 | J46: hours
G47: 8. Energizing PMG II | I47: 0 | J47: hours
G48: 9. Zero Suplay Gas (Problem Pertagas) | I48: 0 | J48: hours
G49: 10, Stop Plant | I49: 0 | J49: hours
G50: 11.HOLD CPO Shortage | I50: =SUM(J22,J28,J29,J30) -> 95.960611 | J50: hours
G51: Total | I51: =SUM(I40:I50) -> 457.95442 | J51: hours
G52: Note : Kapasitas 2200 TPD

Sheet Downtime Fract September
F2: DOWN TIME SLOW FLOWRATE PRODUCTION FRACTIONATION
F4: Periode 01/30 September 2024
F5: TANGGAL | G5: CAPACITY (Kg) | H5: REMARKS | I5: Down time | M5: Tph
I6: Stop | J6: Slow | K6: % | AE6: 17 | AF6: 18 | AG6: 19 | AH6: 20 | AI6: 21 | AJ6: 22 | AK6: 23 | AL6: 24 | AM6: 25 | AN6: 26 | AO6: 27 | AP6: 28 | AQ6: 29 | AR6: 30 | AS6: 31
F7: 1 | G7: 921143 | H7: Slow flow rate due to Olein IV 58 process | J7: =(2000-(G7/1000))/83.33 -> 12.946802 | K7: =G7/2000/1000 -> 0.4605715 | M7: =(G7/1000)/24 -> 38.380958 | O7: =249.262+270.9 -> 520.162 | P7: =1356.367+39.742 -> 1396.109 | Q7: =1086.521+50.6 -> 1137.121 | R7: =1353.558+373.309 -> 1726.867 | S7: 1942.746 | T7: 1868.212 | U7: 2057.011 | V7: 1781.844 | W7: 1250.764 | X7: 1613.486 | Y7: 1325.077 | Z7: =66.442+571.568 -> 638.01 | AA7: =815.429 -> 815.429 | AB7: =352.234+731.627 -> 1083.861 | AC7: =1626.002+13.213 -> 1639.215 | AD7: 2094.791 | AE7: 2075.375 | AF7: 2008.804 | AG7: 1946.712 | AH7: 1998.939 | AI7: =1623.839+281.468 -> 1905.307 | AJ7: 1610.024 | AK7: =1135.181+98.368 -> 1233.549 | AL7: =958.893+543.852 -> 1502.745 | AM7: 2043.15 | AN7: 1762.642 | AO7: 2170.336 | AP7: =1181.38+463.711 -> 1645.091 | AQ7: 219.474 | AR7: =48.153+1225.968+107.3 -> 1381.421
F8: 2 | G8: 250811 | H8: Slow flow rate due to Olein IV 58 process | J8: =(2000-(G8/1000))/83.33 -> 20.991108 | K8: =G8/2000/1000 -> 0.1254055 | M8: =(G8/1000)/24 -> 10.450458
F9: 3 | G9: 519670 | H9: Slow flow rate due to Olein IV 58 process | J9: =(2000-(G9/1000))/83.33 -> 17.764671 | K9: =G9/2000/1000 -> 0.259835 | M9: =(G9/1000)/24 -> 21.652917
F10: 4 | G10: 738041 | H10: Slow flow rate due to Olein IV 58 process | J10: =(2000-(G10/1000))/83.33 -> 15.144114 | K10: =G10/2000/1000 -> 0.3690205 | M10: =(G10/1000)/24 -> 30.751708
F11: 5 | G11: 756126 | H11: Slow flow rate due to Olein IV 56 process & IV 58 process | J11: =(2000-(G11/1000))/83.33 -> 14.927085 | K11: =G11/2000/1000 -> 0.378063 | M11: =(G11/1000)/24 -> 31.50525
F12: 6 | G12: 570133 | H12: Slow flow rate due to Olein IV 58 process | J12: =(2000-(G12/1000))/83.33 -> 17.15909 | K12: =G12/2000/1000 -> 0.2850665 | M12: =(G12/1000)/24 -> 23.755542
F13: 7 | G13: 638607 | H13: Slow flow rate due to Olein IV 58 process | J13: =(2000-(G13/1000))/83.33 -> 16.337369 | K13: =G13/2000/1000 -> 0.3193035 | M13: =(G13/1000)/24 -> 26.608625
F14: 8 | G14: 813834 | H14: Slow flow rate due to Olein IV 58 process | J14: =(2000-(G14/1000))/83.33 -> 14.234561 | K14: =G14/2000/1000 -> 0.406917 | M14: =(G14/1000)/24 -> 33.90975
F15: 9 | G15: 268538 | H15: Slow flow rate due to Olein IV 56 process & IV 58 process | J15: =(2000-(G15/1000))/83.33 -> 20.778375 | K15: =G15/2000/1000 -> 0.134269 | M15: =(G15/1000)/24 -> 11.189083
F16: 10 | G16: 945852 | H16: Slow flow rate due to Olein IV 56 process | J16: =(2000-(G16/1000))/83.33 -> 12.650282 | K16: =G16/2000/1000 -> 0.472926 | M16: =(G16/1000)/24 -> 39.4105
F17: 11 | G17: 1154402 | H17: Slow flow rate due to Olein IV 56 process | J17: =(2000-(G17/1000))/83.33 -> 10.147582 | K17: =G17/2000/1000 -> 0.577201 | M17: =(G17/1000)/24 -> 48.100083
F18: 12 | G18: 656932 | H18: Slow flow rate due to Olein IV 56 process | J18: =(2000-(G18/1000))/83.33 -> 16.117461 | K18: =G18/2000/1000 -> 0.328466 | M18: =(G18/1000)/24 -> 27.372167
F19: 13 | G19: 697311 | H19: Slow flow rate due to Olein IV 56 process | J19: =(2000-(G19/1000))/83.33 -> 15.632893 | K19: =G19/2000/1000 -> 0.3486555 | M19: =(G19/1000)/24 -> 29.054625
... F36: 30 | G36: 1153492 | H36: Slow flow rate due to Olein IV 58 process | J36: =(2000-(G36/1000))/83.33 -> 10.158502 | K36: =G36/2000/1000 -> 0.576746 | M36: =(G36/1000)/24 -> 48.062167
F37: TOTAL | G37: =SUM(G7:G36) -> 23189025 | I37: =SUM(I7:I36) -> 0 | J37: =SUM(J7:J36) -> 441.74937 | M37: =AVERAGE(M7:M36) -> 32.206979
G39: Summary
G40: 1. Slow flow rate due to Space Tank High | I40: 0 | J40: hours
G41: 2. Slow flow rate due to Olein IV 60 process | I41: 0 | J41: hours
G42: 3. Slow flow rate due to Olein IV 57 process | I42: 0 | J42: hours
G43: 4. Slow Flow rate terkait material sortage & menyesuaikan | I43: 0 | J43: hours
G44: 5. Downtime due to Start/Stop Up Plant | I44: 0 | J44: hours
G45: 6. Running Normal Plant | I45: 0 | J45: hours
G46: 7. Stop Plant due to Preventive Maintenance Plant | I46: 0 | J46: hours
G47: 8. Energizing PMG II | I47: 0 | J47: hours
G48: 9. Zero Suplay Gas (Problem Pertagas) | I48: 0 | J48: hours
G49: 10. Slow flow rate due to Olein IV 58 process | I49: =SUM(J7,J8,J9,J10,J12,J13,J14,J36) -> 124.73622 | J49: hours
G50: 11. STOP PLANT | I50: =SUM(J23,J29,J30) -> 71.936049 | J50: hours
G51: 12.Slow flow rate due to Olein IV 56 process | I51: =SUM(J16,J17,J18,J19,J20,J21,J22,J24,J26,J27,J28,J31,J32,J33,J34) -> 188.4966 | J51: hours
G52: 13. Slow flow rate due to Olein IV 56 process & IV 57 process | I52: =SUM(J25) -> 11.400816 | J52: hours
G53: 14. Slow flow rate due to Olein IV 56 process & IV 58 process | I53: =SUM(J35,J15,J11) -> 45.179683 | J53: hours
G54: Total | I54: =SUM(I40:I53) -> 441.74937 | J54: hours
G55: 8. Note : Kapasitas 2000 TPD

Sheet Downtime Ref
F2: DOWN TIME SLOW FLOWRATE PRODUCTION REFINERY
F4: =Prod!B4 -> Periode 01 s/d 30 September 2024
F5: TANGGAL | G5: CAPACITY (Kg) | H5: REMARKS | I5: Down time | M5: Tph
I6: Stop | J6: Slow | K6: %
F7: 1 | G7: ='[31]LAPORAN PRODUKSI'!F11 -> 0 | H7: Slow fr terkait penyesuaian material dan set brand iv 57 & iv 60 | J7: =(2200-(G7/1000))/91.66 -> 24.001746 | K7: =G7/2200/1000 -> 0 | M7: =(G7/1000)/24 -> 0
F8: 2 | G8: ='[31]LAPORAN PRODUKSI'!G11 -> 11.231455 | H8: Slow fr terkait penyesuaian material dan set brand iv 57 & iv 60 | J8: =(2200-(G8/1000))/91.66 -> 24.001623 | K8: =G8/2200/1000 -> 5.1052066e-06 | M8: =(G8/1000)/24 -> 0.00046797727
F9: 3 | G9: ='[31]LAPORAN PRODUKSI'!H11 -> 22.424909 | H9: Tidak adanya shipment produk dan proses High FFA | J9: =(2200-(G9/1000))/91.66 -> 24.001501 | K9: =G9/2200/1000 -> 1.019314e-05 | M9: =(G9/1000)/24 -> 0.00093437121
F10: 4 | G10: ='[31]LAPORAN PRODUKSI'!I11 -> 7.7860455 | H10: Tidak adanya shipment produk dan proses High FFA | J10: =(2200-(G10/1000))/91.66 -> 24.001661 | K10: =G10/2200/1000 -> 3.5391116e-06 | M10: =(G10/1000)/24 -> 0.00032441856
F11: 5 | G11: ='[31]LAPORAN PRODUKSI'!J11 -> 11.154136 | H11: Tidak adanya shipment produk dan proses High FFA | J11: =(2200-(G11/1000))/91.66 -> 24.001624 | K11: =G11/2200/1000 -> 5.070062e-06 | M11: =(G11/1000)/24 -> 0.00046475568
F12: 6 | G12: ='[31]LAPORAN PRODUKSI'!K11 -> 0 | H12: Tidak adanya shipment produk dan proses High FFA | J12: =(2200-(G12/1000))/91.66 -> 24.001746 | K12: =G12/2200/1000 -> 0 | M12: =(G12/1000)/24 -> 0
F13: 7 | G13: ='[31]LAPORAN PRODUKSI'!L11 -> 0 | H13: Tidak adanya shipment produk dan proses High FFA | J13: =(2200-(G13/1000))/91.66 -> 24.001746 | K13: =G13/2200/1000 -> 0 | M13: =(G13/1000)/24 -> 0
F14: 8 | G14: ='[31]LAPORAN PRODUKSI'!M11 -> 0 | H14: Tidak adanya shipment produk dan proses High FFA | J14: =(2200-(G14/1000))/91.66 -> 24.001746 | K14: =G14/2200/1000 -> 0 | M14: =(G14/1000)/24 -> 0
F15: 9 | G15: ='[31]LAPORAN PRODUKSI'!N11 -> 0 | H15: Sirkulasi quality ouspek | J15: =(2200-(G15/1000))/91.66 -> 24.001746 | K15: =G15/2200/1000 -> 0 | M15: =(G15/1000)/24 -> 0
F16: 10 | G16: ='[31]LAPORAN PRODUKSI'!O11 -> 0 | H16: Slow fr terkait penyesuaian material | J16: =(2200-(G16/1000))/91.66 -> 24.001746 | K16: =G16/2200/1000 -> 0 | M16: =(G16/1000)/24 -> 0
F17: 11 | G17: ='[31]LAPORAN PRODUKSI'!P11 -> 0 | H17: Tidak adanya shipment produk dan proses High FFA | J17: =(2200-(G17/1000))/91.66 -> 24.001746 | K17: =G17/2200/1000 -> 0 | M17: =(G17/1000)/24 -> 0
F18: 12 | G18: ='[31]LAPORAN PRODUKSI'!Q11 -> 0 | H18: Tidak adanya shipment produk dan proses High FFA | J18: =(2200-(G18/1000))/91.66 -> 24.001746 | K18: =G18/2200/1000 -> 0 | M18: =(G18/1000)/24 -> 0
F19: 13 | G19: ='[31]LAPORAN PRODUKSI'!R11 -> 0 | H19: Slow fr terkait penyesuaian material & Set Brand | J19: =(2200-(G19/1000))/91.66 -> 24.001746 | K19: =G19/2200/1000 -> 0 | M19: =(G19/1000)/24 -> 0
F20: 14 | G20: ='[31]LAPORAN PRODUKSI'!S11 -> 0 | H20: Slow fr terkait penyesuaian material | J20: =(2200-(G20/1000))/91.66 -> 24.001746 | K20: =G20/2200/1000 -> 0 | M20: =(G20/1000)/24 -> 0
F21: 15 | G21: ='[31]LAPORAN PRODUKSI'!T11 -> 0 | H21: Slow fr terkait penyesuaian material | J21: =(2200-(G21/1000))/91.66 -> 24.001746 | K21: =G21/2200/1000 -> 0 | M21: =(G21/1000)/24 -> 0
F22: 16 | G22: ='[31]LAPORAN PRODUKSI'!U11 -> 0 | H22: Slow fr terkait penyesuaian material & Set Brand | J22: =(2200-(G22/1000))/91.66 -> 24.001746 | K22: =G22/2200/1000 -> 0 | M22: =(G22/1000)/24 -> 0
F23: 17 | G23: ='[31]LAPORAN PRODUKSI'!V11 -> 0 | H23: Slow fr terkait penyesuaian material & Set Brand | J23: =(2200-(G23/1000))/91.66 -> 24.001746 | K23: =G23/2200/1000 -> 0 | M23: =(G23/1000)/24 -> 0
F24: 18 | G24: ='[31]LAPORAN PRODUKSI'!W11 -> 0 | H24: Slow fr terkait penyesuaian material & Set Brand | J24: =(2200-(G24/1000))/91.66 -> 24.001746 | K24: =G24/2200/1000 -> 0 | M24: =(G24/1000)/24 -> 0
F25: 19 | G25: ='[31]LAPORAN PRODUKSI'!X11 -> 27.729227 | H25: Slow fr terkait penyesuaian material & Set Brand | J25: =(2200-(G25/1000))/91.66 -> 24.001443 | K25: =G25/2200/1000 -> 1.2604194e-05 | M25: =(G25/1000)/24 -> 0.0011553845
F26: 20 | G26: ='[31]LAPORAN PRODUKSI'!Y11 -> 56.458727 | H26: Slow fr terkait penyesuaian material & proses High FFA | J26: =(2200-(G26/1000))/91.66 -> 24.00113 | K26: =G26/2200/1000 -> 2.5663058e-05 | M26: =(G26/1000)/24 -> 0.002352447
F27: 21 | G27: ='[31]LAPORAN PRODUKSI'!Z11 -> 62.590545 | H27: Power Blackout | J27: =(2200-(G27/1000))/91.66 -> 24.001063 | K27: =G27/2200/1000 -> 2.8450248e-05 | M27: =(G27/1000)/24 -> 0.0026079394
F28: 22 | G28: ='[31]LAPORAN PRODUKSI'!AA11 -> 25.775091 | H28: Slow fr terkait penyesuaian material | J28: =(2200-(G28/1000))/91.66 -> 24.001464 | K28: =G28/2200/1000 -> 1.171595e-05 | M28: =(G28/1000)/24 -> 0.0010739621
F29: 23 | G29: ='[31]LAPORAN PRODUKSI'!AB11 -> 37.957045 | H29: Slow fr terkait penyesuaian material | J29: =(2200-(G29/1000))/91.66 -> 24.001331 | K29: =G29/2200/1000 -> 1.7253202e-05 | M29: =(G29/1000)/24 -> 0.0015815436
F30: 24 | G30: ='[31]LAPORAN PRODUKSI'!AC11 -> 30.107455 | H30: Slow fr terkait penyesuaian material | J30: =(2200-(G30/1000))/91.66 -> 24.001417 | K30: =G30/2200/1000 -> 1.3685207e-05 | M30: =(G30/1000)/24 -> 0.0012544773
F31: 25 | G31: ='[31]LAPORAN PRODUKSI'!AD11 -> 10.408955 | H31: Slow fr terkait penyesuaian material | J31: =(2200-(G31/1000))/91.66 -> 24.001632 | K31: =G31/2200/1000 -> 4.731343e-06 | M31: =(G31/1000)/24 -> 0.00043370644
F32: 26 | G32: ='[31]LAPORAN PRODUKSI'!AE11 -> 28.632636 | H32: MP Boiler Trip | J32: =(2200-(G32/1000))/91.66 -> 24.001433 | K32: =G32/2200/1000 -> 1.3014835e-05 | M32: =(G32/1000)/24 -> 0.0011930265
F33: 27 | G33: ='[31]LAPORAN PRODUKSI'!AF11 -> 22.617955 | H33: HOLD,Plant Sirkulasi | J33: =(2200-(G33/1000))/91.66 -> 24.001499 | K33: =G33/2200/1000 -> 1.0280888e-05 | M33: =(G33/1000)/24 -> 0.00094241477
F34: 28 | G34: ='[31]LAPORAN PRODUKSI'!AG11 -> 14.704818 | H34: Slow fr terkait penyesuaian material & Set Brand | J34: =(2200-(G34/1000))/91.66 -> 24.001585 | K34: =G34/2200/1000 -> 6.6840083e-06
F35: 29 | G35: ='[31]LAPORAN PRODUKSI'!AH11 -> 7.4209091 | H35: Slow fr terkait penyesuaian material & Set Brand | J35: =(2200-(G35/1000))/91.66 -> 24.001665 | K35: =G35/2200/1000 -> 3.3731405e-06 | M35: =(G35/1000)/24 -> 0.00030920455
F36: 30 | G36: ='[31]LAPORAN PRODUKSI'!AI11 -> 28.419182 | H36: Slow fr terkait penyesuaian material & proses High FFA | J36: =(2200-(G36/1000))/91.66 -> 24.001436 | K36: =G36/2200/1000 -> 1.291781e-05
F37: 31 | G37: ='[31]LAPORAN PRODUKSI'!AJ11 -> 0 | H37: Slow fr terkait penyesuaian material | J37: =(2200-(G37/1000))/91.66 -> 24.001746 | K37: =G37/2200/1000 -> 0
F38: TOTAL | G38: =SUM(G7:G37) -> 405.41909 | I38: =SUM(I7:I36) -> 0 | J38: =SUM(J7:J36) -> 720.04794 | M38: =AVERERAGE(M7:M36) -> #NAME?
G40: Summary
G41: 1. Slow flow rate due to Space Tank High | I41: 0 | J41: hours
G42: 2. Slow flow rate due to Olein IV 60 process | I42: 0 | J42: hours
G43: 3. Hold plant due to trip MP boiler & maintenance | I43: 0 | J43: hours
G44: 4. Running Slow flowrate dikarenakan CPO Shortage | I44: =SUM((J7:J36)) -> 720.04794 | J44: hours
G45: 5. Downtime due to Start Up Plant | I45: 0 | J45: hours
G46: 6. Running Normal Plant | I46: 0 | J46: hours
G47: 7. Stop Plant due to Preventive Maintenance Plant | I47: =SUM(I24:I33) -> 0 | J47: hours
G48: Total | I48: =SUM(I41:I47) -> 720.04794 | J48: hours
G49: 8. Total CPO incoming : 41,976 MT ( 64,48 % dari forecast Agustus )
G50: 9. CPO Olah : 46,503 MT ( 71,43 % dari Target RKAP Agustus 2023 )
G51: 10. Note : Kapasitas 2200 TPD
G53: - Total 232,17 hours
G54: - Total CPO incoming : 41,976 MT ( 64,48 % dari forecast Agustus )
G55: - CPO Olah : 46,503 MT ( 71,43 % dari Target RKAP Agustus 2023 )
G56: - Note : Kapasitas 2200 TPD

Sheet Flow Meter
A2: TOTAL TONASE FLOWMETER PRODUK
A3: REFINERY
A5: TANGGAL VALIDASI
A6: NO | B6: NAMA PRODUK | C6: 01 Juli | D6: 02 Juli | E6: 03 Juli | F6: 04 Juli | G6: 05 Juli | H6: 06 Juli | I6: 07 Juli | J6: 08 Juli | K6: 09 Juli | L6: 10 Juli | M6: 11 Juli | N6: 12 Juli | O6: 13 Juli | P6: 14 Juli | Q6: 15 Juli | R6: TOTAL | S6: Sounding | T6: Yield Theory | U6: Yield Aktual
A7: 1 | B7: CPO | C7: ='[32]01 '!$Q$14 -> 744924 | D7: ='[32]02'!$Q$14 -> 743972 | E7: ='[32]03'!$Q$14 -> 1048435 | F7: ='[32]04'!$Q$14 -> 1114821 | G7: 248126 | H7: 389481 | I7: 104168 | J7: 320907 | K7: 100743 | L7: 512647 | M7: 441064 | N7: 524002 | O7: 568358 | P7: 430750 | R7: =SUM(C7:Q7) -> 7292398
A8: 2 | B8: RBDPO | C8: 713300 | D8: 708000 | E8: 993100 | F8: 1056000 | G8: 237021 | H8: 365100 | I8: 44001 | J8: 300010 | K8: 94507 | L8: 488153 | M8: 414337 | N8: 492952 | O8: 532902 | P8: 497845 | R8: =SUM(C8:Q8) -> 6937228 | T8: =R8/R7 -> 0.95129586 | U8: =S8/S7 -> #DIV/0! | W8: =4984655+#REF! -> #REF!
A9: 3 | B9: PFAD | C9: ='[32]01 '!$P$25 -> 25659 | D9: 28786 | E9: ='[32]03'!$P$25 -> 46938 | F9: ='[32]04'!$P$24 -> 48667 | G9: 8070 | H9: 19280 | I9: 3234 | J9: 18283 | K9: 5131 | L9: 20426 | M9: 23275 | N9: 27655 | O9: 25803 | P9: 20173 | R9: =SUM(C9:Q9) -> 321380 | T9: =R9/R7 -> 0.044070551 | U9: =S9/S7 -> #DIV/0!
C10: =C8/C7 -> 0.95754735 | D10: =D8/D7 -> 0.95164872 | E10: =E8/E7 -> 0.94722133 | F10: =F8/F7 -> 0.94723727 | G10: =G8/G7 -> 0.95524451 | H10: =H8/H7 -> 0.93740131 | I10: =I8/I7 -> 0.42240419 | J10: =J8/J7 -> 0.93488145 | ... P10: =P8/P7 -> 1.1557632
C11: =C9/C7*1 -> 0.034445125 | D11: =D9/D7*1 -> 0.038692316 | E11: =E9/E7*1 -> 0.044769585 | F11: =F9/F7*1 -> 0.043654542 | G11: =G9/G7*1 -> 0.032523798 | H11: =H9/H7*1 -> 0.049501773 | I11: =I9/I7*1 -> 0.031046003 | J11: =J9/J7*1 -> 0.056972892 | ... P11: =P9/P7*1 -> 0.046832269
B12: LOSIS | C12: =(C7-C8-C9)/C7 -> 0.0080075283 | D12: =(D7-D8-D9)/D7 -> 0.0096589657 | E12: =(E7-E8-E9)/E7 -> 0.0080090802 | F12: =(F7-F8-F9)/F7 -> 0.0091081887 | G12: =(G7-G8-G9)/G7 -> 0.012231689 | H12: =(H7-H8-H9)/H7 -> 0.013096916 | I12: =(I7-I8-I9)/I7 -> 0.5465498 | J12: =(J7-J8-J9)/J7 -> 0.0081456621 | ... P12: =(P7-P8-P9)/P7 -> -0.20259547
A14: TANGGAL flow meter
A15: NO | B15: NAMA PRODUK | C15: 01 Juli | D15: 02 Juli | E15: 03 Juli | F15: 04 Juli | G15: 05 Juli | H15: 06 Juli | I15: 07 Juli | J15: 08 Juli | K15: 09 Juli | L15: 10 Juli | M15: 11 Juli | N15: 12 Juli | O15: 13 Juli | P15: 14 Juli | Q15: 15 Juli | R15: TOTAL | S15: Sounding | T15: Yield Theory | U15: Yield Aktual
A16: 1 | B16: CPO | C16: 680800 | D16: 806400 | E16: 858600 | F16: 898100 | G16: 26100 | H16: 513200 | I16: 119200 | J16: 208900 | K16: 147700 | L16: 425800 | M16: 347900 | N16: 459100 | O16: 509200 | P16: 396700 | Q16: 20200 | R16: =SUM(C16:Q16) -> 6417900 | S16: =5745000+14073+R19 -> 7292813
A17: 2 | B17: RBDPO | C17: 722400 | D17: 826700 | E17: 980700 | F17: 980600 | G17: 19900 | H17: 582000 | I17: 150500 | J17: 215300 | K17: 70837 | L17: 488153 | M17: 379337 | N17: 502200 | O17: 535800 | P17: 412600 | Q17: 92100 | R17: =SUM(C17:Q17) -> 6959127 | S17: =SUM(C17:M17)+R20 -> 6940126 | T17: =R17/R16 -> 1.0843309 | U17: =S17/S16 -> 0.9516391 | W17: =4984655+R20 -> 6508354
A18: 3 | B18: PFAD | C18: 37300 | D18: 38700 | E18: 49500 | F18: 47100 | G18: 3800 | H18: 30300 | I18: 9300 | J18: 14000 | K18: 14800 | L18: 25100 | M18: 23400 | N18: 23900 | O18: 26800 | P18: 22200 | Q18: 5900 | R18: =SUM(C18:Q18) -> 372100 | S18: =248746+R21 -> 322377 | T18: =R18/R16 -> 0.057978466 | U18: =S18/S16 -> 0.044204753
C19: =C17/C16 -> 1.0611046 | D19: =D17/D16 -> 1.0251736 | E19: =E17/E16 -> 1.1422082 | F19: =F17/F16 -> 1.0918606 | G19: =G17/G16 -> 0.76245211 | H19: =H17/H16 -> 1.1340608 | I19: =I17/I16 -> 1.2625839 | J19: =J17/J16 -> 1.0306367 | K19: =K17/K16 -> 0.47960054 | L19: 269515 | M19: CPO | N19: 534002 | O19: 568773 | P19: 430750 | Q19: 269300 | R19: =L19+N19+O19+P19-Q19 -> 1533740 | U19: =100%-U17-U18 -> 0.0041561466 | V19: Losses
M20: RBDPO | N20: 492952 | O20: 532902 | P20: 497845 | R20: =SUM(N20:P20) -> 1523699
N21: 27655 | O21: 25803 | P21: 20173 | R21: =SUM(N21:P21) -> 73631
B22: Nb : | C22: 1. 5.745.000 adalaha angka consume CPO tanggal 1 - 11 ( Opening Stock + Incoming - Closing tanggal 11 )
C23: 2. 14.073 ( Beda Pembacaan antara sounding dan timbangan )
C24: 3. 1.533.740 adalah angka sounding CPO 12, 13, 14
A25: FRAKSINASI
A26: TANGGAL
A27: NO | B27: NAMA PRODUK | C27: 01 Juli | D27: 02 Juli | E27: 03 Juli | F27: 04 Juli | G27: 05 Juli | H27: 06 Juli | I27: 07 Juli | J27: 08 Juli | K27: 09 Juli | L27: 10 Juli | M27: 11 Juli | N27: 12 Juli | O27: 13 Juli | P27: 14 Juli | Q27: 15 Juli | R27: TOTAL | S27: Sounding | T27: Yield
A28: 1 | B28: RBDPO | C28: 667300 | D28: 695000 | E28: 814100 | F28: 760000 | G28: 620300 | H28: 587100 | I28: 118500 | J28: 0 | K28: 253000 | L28: 0 | M28: 466900 | N28: 258400 | O28: 584400 | P28: 680200 | R28: =SUM(C28:Q28) -> 6505200
A29: 2 | B29: OLEIN IV 58 | C29: 518400 | D29: 487200 | E29: 539100 | F29: 571900 | G29: 554300 | H29: 449900 | I29: 209900 | J29: 0 | K29: 297100 | L29: 0 | M29: 472500 | N29: 207400 | O29: 239100 | P29: 414100 | R29: =SUM(C29:Q29) -> 4960900
A30: 3 | B30: STEARIN | C30: 207500 | D30: 202900 | E30: 215500 | F30: =27400+151100+55600 -> 234100 | G30: 213300 | H30: 183700 | I30: 104800 | J30: 0 | K30: 93900 | L30: 0 | M30: 172400 | N30: 111100 | O30: 81200 | P30: 193200 | R30: =SUM(C30:Q30) -> 2013600
O32: STOCK OPNAME | R32: =1311190 -> 1311190
O33: TOTAL TERIMA 1- 11 TIMBANGAN | R33: 3865830
O34: PIPANISASI DAN GK 1 - 11 | R34: 1888995
O35: STOCK AKHIR OPNAME 11 JULI | R35: 1320540.6
R36: =R32+R33+R34-R35 -> 5745474.4
O38: STOCK OPNAME 1 JULI | R38: 178489.22
O39: TOTAL FLOW METER 11 | R39: =SUM(C28:M28) -> 4982200
O40: STOCK AKHIR OPNAME 11 JULI
