Workbook

Sheet November 2024
C1: PRODUCTION REPORT
C2: No | D2: ITEM | E2: Budget / Norma | F2: UoM | G2: November | AL2: TOTAL MONTHLY (Kg)
G3: 1 | H3: 2 | I3: 3 | J3: 4 | K3: 5 | L3: 6 | M3: 7 | N3: 8 | O3: 9 | P3: 10 | Q3: 11 | R3: 12 | S3: 13 | T3: 14 | U3: 15 | V3: 16 | W3: 17 | X3: 18 | Y3: 19 | Z3: 20 | AA3: 21 | AB3: 22 | AC3: 23 | AD3: 24 | AE3: 25 | AF3: 26 | AG3: 27 | AH3: 28 | AI3: 29 | AJ3: 30
C4: 1 | D4: PRODUCTION | AL4: Production
D5: Refinery | AL5: Refinery
D6: Running Days | F6: Day | G6: 1 | H6: 1 | I6: 1 | J6: 1 | K6: 1 | L6: 1 | M6: 1 | N6: 1 | O6: 1 | P6: 1 | Q6: 1 | R6: 1 | S6: 1 | T6: 1 | U6: 1 | V6: 1 | W6: 1 | X6: 1 | Y6: 1 | Z6: 1 | AA6: 1 | AB6: 1 | AC6: 0 | AD6: 0 | AE6: 0 | AF6: 0 | AG6: 0 | AH6: 0 | AI6: 0 | AJ6: 0 | AL6: =SUM(G6:AJ6) -> 22
D7: Incoming CPO | F7: Kg | G7: ='[1]01'!$P$15 -> 839697 | H7: ='[2]02'!$P$15 -> 1188983 | I7: ='[2]03'!$P$15 -> 686390 | J7: 631759 | K7: 768297 | L7: ='[3]06'!$P$15 -> 265829 | M7: ='[4]07'!$P$15 -> 1355300 | N7: ='[5]08'!$P$15 -> 1709933 | O7: ='[5]09'!$P$15 -> 1254148 | P7: ='[5]10'!$P$15 -> 427434 | Q7: ='[6]11'!$P$15 -> 1046286 | R7: ='[7]12'!$P$15 -> 1337112 | S7: ='[8]13'!$P$15 -> 1544985 | T7: ='[9]14'!$P$15 -> 1532271 | U7: ='[10]15'!$P$15 -> 1051996 | V7: ='[11]16'!$P$15 -> 1149146 | W7: ='[11]17'!$P$15 -> 0 | X7: ='[12]18'!$P$15 -> 1135049 | Y7: ='[13]19'!$P$15 -> 890223 | Z7: ='[14]20'!$P$15 -> 949617 | AA7: ='[15]21'!$P$15 -> 1535903 | AB7: ='[16]22'!$P$15 -> 1313539 | AC7: ='[17]23'!$P$15 -> 1943723 | AD7: ='[17]24'!$P$15 -> 413342 | AE7: ='[18]25'!$P$15 -> 2214932 | AF7: ='[19]26'!$P$15 -> 2308752 | AG7: ='[19]27'!$P$15 -> 434771 | AH7: ='[20]28'!$P$15 -> 1330147 | AI7: ='[1]28'!$P$15 -> 990392 | AJ7: ='[21]30 (Stock Opname)'!$P$15 -> 1416573 | AL7: =SUM(G7:AJ7) -> 33666529
D8: Ratio Run CPO | F8: % | G8: =G9/2200000*100 -> 39.072136 | H8: =H9/2200000*100 -> 24.422727 | I8: =I9/2200000*100 -> 33.490955 | J8: =J9/2200000*100 -> 40.663136 | K8: 40.936545 | L8: =L9/2200000*100 -> 38.4625 | M8: =M9/2200000*100 -> 34.265182 | N8: =N9/2200000*100 -> 31.670136 | O8: =O9/2200000*100 -> 37.663364 | P8: =P9/2200000*100 -> 45.620455 | Q8: =Q9/2200000*100 -> 45.491318 | R8: =R9/2200000*100 -> 42.072636 | S8: =S9/2200000*100 -> 36.530273 | ... AJ8: =AJ9/2200000*100 -> 0 | AL8: =SUM(G8:AJ8)/AL6 -> 42.102025
D9: CPO Consume Total | E9: 36359000 | F9: Kg | G9: ='[1]01'!$Q$15 -> 859587 | H9: ='[2]02'!$Q$15 -> 537300 | I9: ='[2]03'!$Q$15 -> 736801 | J9: 894589 | K9: 900604 | L9: ='[3]06'!$Q$15 -> 846175 | M9: ='[4]07'!$Q$15 -> 753834 | N9: ='[5]08'!$Q$15 -> 696743 | O9: ='[5]09'!$Q$15 -> 828594 | P9: ='[5]10'!$Q$15 -> 1003650 | Q9: ='[6]11'!$Q$15 -> 1000809 | R9: ='[7]12'!$Q$15 -> 925598 | S9: ='[8]13'!$Q$15 -> 803666 | T9: ='[9]14'!$Q$15 -> 1009988 | U9: ='[10]15'!$Q$15 -> 1042124 | V9: ='[11]16'!$Q$15 -> 991679 | W9: ='[11]17'!$Q$15 -> 633826 | X9: ='[12]18'!$Q$15 -> 1114065 | Y9: ='[13]19'!$Q$15 -> 1358019 | Z9: ='[14]20'!$Q$15 -> 1573360 | AA9: ='[15]21'!$Q$15 -> 1433933 | AB9: ='[16]22'!$Q$15 -> 432436 | AC9: ='[17]23'!$Q$15 -> 0 | AD9: ='[17]24'!$Q$15 -> 0 | AE9: ='[18]25'!$Q$15 -> 0 | AF9: ='[19]26'!$Q$15 -> 0 | AG9: ='[19]27'!$Q$15 -> 0 | AH9: ='[20]28'!$Q$15 -> 0 | AI9: ='[1]28'!$Q$15 -> 0 | AJ9: ='[21]30 (Stock Opname)'!$Q$15 -> 0 | AL9: =SUM(G9:AJ9) -> 20377380
D10: Avg Daily Consump CPO ( MTD ) | AL10: =AL9/AL6 -> 926244.55 | AM10: =AL9/E9 -> 0.56044941
D11: CPO Consume Poram | E11: 29045000 | F11: Kg | G11: =G9-G12 -> 859587 | H11: =H9-H12 -> 537300 | I11: =I9-I12 -> 736801 | J11: =J9-J12 -> 894589 | K11: 900604 | L11: =L9-L12 -> 846175 | M11: =M9-M12 -> 753834 | N11: =N9-N12 -> 696743 | O11: =O9-O12 -> 828594 | P11: =P9-P12 -> 1003650 | Q11: =Q9-Q12 -> 1000809 | R11: =R9-R12 -> 925598 | S11: =S9-S12 -> 803666 | ... AJ11: =AJ9-AJ12 -> 0 | AL11: =SUM(G11:AJ11) -> 20377380
D12: CPO Consume Brand | E12: 7314000 | F12: Kg | G12: =G36+G45+G50 -> 0 | H12: =H36+H45+H50 -> 0 | I12: =I36+I45+I50 -> 0 | J12: =J36+J45+J50 -> 0 | K12: 0 | L12: =L36+L45+L50 -> 0 | M12: =M36+M45+M50 -> 0 | N12: =N36+N45+N50 -> 0 | O12: =O36+O45+O50 -> 0 | P12: =P36+P45+P50 -> 0 | Q12: =Q36+Q45+Q50 -> 0 | R12: =R36+R45+R50 -> 0 | S12: =S36+S45+S50 -> 0 | ... AJ12: =AJ36+AJ45+AJ50 -> 0 | AL12: =SUM(G12:AJ12) -> 0
D13: - FFA | E13: 5 | F13: % | G13: 3.95 | H13: =(4.11+3.38)/2 -> 3.745 | I13: =(4.12+3.52)/2 -> 3.82 | J13: 3.84 | K13: 3.87 | L13: 3.93 | M13: 3.65 | N13: =(4.3+3.73)/2 -> 4.015 | O13: 4.04 | P13: =(4.06+3.79)/2 -> 3.925 | Q13: 3.86 | R13: =(3.9+3.87+3.35)/3 -> 3.7066667 | S13: =(3.73+3.33)/2 -> 3.53 | T13: =(3.86+3.36)/2 -> 3.61 | U13: =(3.96+3.45)/2 -> 3.705 | V13: =(3.75+3.52)/2 -> 3.635 | W13: 4.17 | X13: =(4.3+3.83)/2 -> 4.065 | Y13: =(4.33+3.69)/2 -> 4.01 | Z13: =(4.03+3.71)/2 -> 3.87 | AA13: 4.16 | AB13: 4.06 | AC13: 0 | AD13: 0 | AE13: 0 | AF13: 0 | AG13: 0 | AH13: 0 | AI13: 0 | AJ13: 0 | AL13: =SUM(G13:AJ13)/AL6 -> 3.8712121
D14: - Moist & Impurities | E14: 0.5 | F14: % | G14: 0.41 | H14: =(0.48+0.44)/2 -> 0.46 | I14: =(0.48+0.48)/2 -> 0.48 | J14: 0.42 | K14: 0.45 | L14: 0.47 | M14: 0.41 | N14: =(0.41+0.45)/2 -> 0.43 | O14: 0.43 | P14: =(0.4+0.45)/2 -> 0.425 | Q14: 0.48 | R14: =(0.4+0.4+0.45)/3 -> 0.41666667 | S14: =(0.42+0.4)/2 -> 0.41 | T14: =(0.38+0.43)/2 -> 0.405 | U14: =(0.42+0.43)/2 -> 0.425 | V14: =(0.42+0.44)/2 -> 0.43 | W14: 0.45 | X14: =(0.46+0.42)/2 -> 0.44 | Y14: =(0.4+0.39)/2 -> 0.395 | Z14: =(0.42+0.41)/2 -> 0.415 | AA14: 0.45 | AB14: 0.45 | AC14: 0 | AD14: 0 | AE14: 0 | AF14: 0 | AG14: 0 | AH14: 0 | AI14: 0 | AJ14: 0 | AL14: =SUM(G14:AJ14)/AL6 -> 0.43416667
D15: - DOBI | E15: 2,20 Min | F15: % | G15: 2.02 | H15: 2.01 | I15: 2.02 | J15: 2.01 | K15: 2.02 | L15: 2.01 | M15: 2.02 | N15: 2.01 | O15: 2.02 | P15: 2.01 | Q15: 2.02 | R15: 2.01 | S15: 2.02 | T15: 2.01 | U15: 2.02 | V15: 2.01 | W15: 2.02 | X15: 2.01 | Y15: 2.02 | Z15: 2.01 | AA15: 2.02 | AB15: 2.01 | AC15: 0 | AD15: 0 | AE15: 0 | AF15: 0 | AG15: 0 | AH15: 0 | AI15: 0 | AJ15: 0 | AL15: =SUM(G15:AJ15)/AL6 -> 2.015
D16: Product | AL16: Product
D17: OIP RBDPO | G17: ='[22]OIP Refinery'!G5 -> -406 | H17: ='OIP Refinery'!G6 -> -6347 | I17: ='OIP Refinery'!G7 -> 3041 | J17: ='OIP Refinery'!G8 -> -3727 | K17: 3867 | L17: ='OIP Refinery'!G10 -> 4672 | M17: ='OIP Refinery'!G11 -> -3984 | N17: ='OIP Refinery'!G12 -> -49689 | O17: ='OIP Refinery'!G13 -> 42583 | P17: ='OIP Refinery'!G14 -> 9236 | Q17: ='OIP Refinery'!G15 -> 12226 | R17: ='OIP Refinery'!G16 -> 2888 | S17: ='OIP Refinery'!G17 -> -11029 | T17: ='OIP Refinery'!G18 -> 14415 | U17: ='OIP Refinery'!G19 -> -23435 | V17: ='OIP Refinery'!G20 -> 15090 | W17: ='OIP Refinery'!G21 -> -22972 | X17: ='OIP Refinery'!G22 -> 32794 | Y17: ='OIP Refinery'!G23 -> -20863 | Z17: ='OIP Refinery'!G24 -> -38825 | AA17: ='OIP Refinery'!G25 -> 40150 | AB17: ='OIP Refinery'!G26 -> -95665 | AC17: ='OIP Refinery'!G27 -> -179950 | AD17: ='OIP Refinery'!G28 -> 0 | AE17: ='OIP Refinery'!G29 -> 0 | AF17: ='OIP Refinery'!G30 -> 0 | AG17: ='OIP Refinery'!G31 -> 0 | AH17: ='OIP Refinery'!G32 -> 0 | AI17: ='OIP Refinery'!G33 -> 0 | AJ17: ='OIP Refinery'!G34 -> 0
D18: RBDPO | E18: 34458000 | F18: Kg | G18: ='[1]01'!$P$18+G17 -> 832484 | H18: ='[2]02'!$P$18+H17 -> 503888 | I18: ='[2]03'!$P$18+I17 -> 717643 | J18: =854343+J17 -> 850616 | K18: =862559+K17 -> 866426 | L18: ='[3]06'!$P$18+L17 -> 804611 | M18: ='[4]07'!$P$18+M17 -> 717374 | N18: ='[5]08'!$P$18+N17 -> 631067 | O18: ='[5]09'!$P$18+O17 -> 754534 | P18: ='[5]10'!$P$18+P17 -> 966838 | Q18: ='[6]11'!$P$18+Q17 -> 948306 | R18: ='[7]12'!$P$18+R17 -> 870851 | S18: ='[8]13'!$P$18+S17 -> 758174 | T18: ='[9]14'!$P$18+T17 -> 937848 | U18: ='[10]15'!$P$18+U17 -> 978639 | V18: ='[11]16'!$P$18+V17 -> 945977 | W18: ='[11]17'!$P$18+22972 -> 655261 | X18: ='[12]18'!$P$18+X17 -> 1058377 | Y18: ='[13]19'!$P$18+20863 -> 1311371 | Z18: ='[14]20'!$P$18+38825 -> 1504302 | AA18: ='[15]21'!$P$18+40150 -> 1396518 | AB18: ='[16]22'!$P$18+95665 -> 599189 | AC18: ='[17]23'!$P$18+179950 -> 347862 | AD18: ='[17]24'!$P$18 -> 0 | AE18: ='[18]25'!$P$18 -> 0 | AF18: ='[19]26'!$P$18 -> 0 | AG18: ='[19]27'!$P$18 -> 0 | AH18: ='[20]28'!$P$18 -> 0 | AI18: ='[1]28'!$P$18 -> 0 | AJ18: ='[21]30 (Stock Opname)'!$P$18 -> 0 | AL18: =SUM(G18:AJ18) -> 19958156
D19: PFAD | E19: 1636000 | F19: Kg | G19: ='[1]01'!$P$26 -> 34408 | H19: ='[2]02'!$P$26 -> 24264 | I19: ='[2]03'!$P$26 -> 31198 | J19: 43177 | K19: 29951 | L19: ='[3]06'!$P$26 -> 35234 | M19: ='[4]07'!$P$26 -> 30033 | N19: ='[5]08'!$P$26 -> 30410 | O19: ='[5]09'!$P$26 -> 37854 | P19: ='[5]10'!$P$26 -> 43557 | Q19: ='[6]11'!$P$26 -> 43387 | R19: ='[7]12'!$P$26 -> 39212 | S19: ='[8]13'!$P$26 -> 41814 | T19: ='[9]14'!$P$26 -> 33066 | U19: ='[10]15'!$P$26 -> 55468 | V19: ='[11]16'!$P$26 -> 39691 | W19: ='[11]17'!$P$26 -> 31383 | X19: ='[12]18'!$P$26 -> 47540 | Y19: ='[13]19'!$P$26 -> 40680 | Z19: ='[14]20'!$P$26 -> 57733 | AA19: ='[15]21'!$P$26 -> 64108 | AB19: ='[16]22'!$P$26 -> 29969 | AC19: ='[17]23'!$P$26 -> 6321 | AD19: ='[17]24'!$P$26 -> 0 | AE19: ='[18]25'!$P$26 -> 0 | AF19: ='[19]26'!$P$26 -> 0 | AG19: ='[19]27'!$P$26 -> 0 | AH19: ='[20]28'!$P$26 -> 0 | AI19: ='[1]28'!$P$26 -> 0 | AJ19: ='[21]30 (Stock Opname)'!$P$26 -> 0 | AL19: =SUM(G19:AJ19) -> 870458
D20: Fractionation
D21: Running Days | F21: Day | G21: 1 | H21: 1 | I21: 1 | J21: 1 | K21: 1 | L21: 1 | M21: 1 | N21: 1 | O21: 1 | P21: 1 | Q21: 1 | R21: 1 | S21: 1 | T21: 1 | U21: 1 | V21: 1 | W21: 1 | X21: 1 | Y21: 1 | Z21: 1 | AA21: 1 | AB21: 1 | AC21: 1 | AD21: 1 | AE21: 0 | AF21: 0 | AG21: 0 | AH21: 0 | AI21: 0 | AJ21: 0 | AL21: =SUM(G21:AJ21) -> 24
D22: Filling Langsung CR Fr Refinery | F22: Kg | G22: 0 | H22: 0 | I22: 0 | J22: 0 | K22: 0 | L22: 0 | M22: 0 | N22: 0 | O22: 0 | P22: 0 | Q22: 0 | R22: 0 | S22: 0 | T22: 0 | U22: 0 | V22: 0 | W22: 0 | X22: 0 | Y22: 0 | Z22: 0 | AA22: 0 | AB22: 0 | AC22: 0 | AD22: 0 | AE22: 0 | AF22: 0 | AG22: 0 | AH22: 0 | AI22: 0 | AJ22: 0 | AL22: =SUM(G22:AJ22) -> 0
D23: Total Filling Crystalizer ( Feed ) | F23: Kg | G23: ='[1]01'!$Q$18 -> 995005 | H23: ='[2]02'!$Q$18 -> 1111304 | I23: ='[2]03'!$Q$18 -> 1103741 | J23: 952027 | K23: 967829 | L23: ='[3]06'!$Q$18 -> 982946 | M23: ='[4]07'!$Q$18 -> 991841 | N23: ='[5]08'!$Q$18 -> 769268 | O23: ='[5]09'!$Q$18 -> 743523 | P23: ='[5]10'!$Q$18 -> 1142644 | Q23: ='[6]11'!$Q$18 -> 991404 | R23: ='[7]12'!$Q$18 -> 958171 | S23: ='[8]13'!$Q$18 -> 760178 | T23: ='[9]14'!$Q$18 -> 805516 | U23: ='[10]15'!$Q$18 -> 827755 | V23: ='[11]16'!$Q$18 -> 811972 | W23: ='[11]17'!$Q$18 -> 928407 | X23: ='[12]18'!$Q$18 -> 862219 | Y23: ='[13]19'!$Q$18 -> 882883 | Z23: ='[14]20'!$Q$18 -> 920378 | AA23: ='[15]21'!$Q$18 -> 907770 | AB23: ='[16]22'!$Q$18 -> 931307 | AC23: ='[17]23'!$Q$18 -> 871518 | AD23: ='[17]24'!$Q$18 -> 518230 | AE23: ='[18]25'!$Q$18 -> 0 | AF23: ='[19]26'!$Q$18 -> 0 | AG23: ='[19]27'!$Q$18 -> 0 | AH23: ='[20]28'!$Q$18 -> 0 | AI23: ='[1]28'!$Q$18 -> 0 | AJ23: ='[21]30 (Stock Opname)'!$Q$18 -> 0 | AL23: =SUM(G23:AJ23) -> 21737836
D24: Avg Daily Consump RPO ( MTD ) | AL24: =AL23/AL21 -> 905743.17
D25: Total Proses RBDPO | F25: Kg | G25: =SUM(G28,G32,G37,G41,G51) -> 994298 | H25: =SUM(H28,H32,H37,H41,H51) -> 1115291 | I25: =SUM(I28,I32,I37,I41,I51) -> 1038010 | J25: =SUM(J28,J32,J37,J41,J51) -> 1058141 | K25: 899356 | L25: =SUM(L28,L32,L37,L41,L51) -> 939422 | M25: =SUM(M28,M32,M37,M41,M51) -> 1003337 | N25: =SUM(N28,N32,N37,N41,N51) -> 899475 | O25: =SUM(O28,O32,O37,O41,O51) -> 923368 | P25: =SUM(P28,P32,P37,P41,P51) -> 1178496 | Q25: =SUM(Q28,Q32,Q37,Q41,Q51) -> 1073268 | R25: =SUM(R28,R32,R37,R41,R51) -> 927936 | S25: =SUM(S28,S32,S37,S41,S51) -> 732528 | ... AJ25: =SUM(AJ28,AJ32,AJ37,AJ41,AJ51) -> 0 | AL25: =SUM(G25:AJ25) -> 22537659 | AM25: =AL25/E18 -> 0.65406173
D26: Sisa Filling Crystalizer | F26: Kg | G26: =G23-G25 -> 707 | I26: =I23-I25 -> 65731 | J26: =J23-J25 -> -106114 | K26: 68473 | L26: =L23-L25 -> 43524 | M26: =M23-M25 -> -11496 | N26: =N23-N25 -> -130207 | O26: =O23-O25 -> -179845 | P26: =P23-P25 -> -35852 | Q26: =Q23-Q25 -> -81864 | R26: =R23-R25 -> 30235 | S26: =S23-S25 -> 27650 | ... AJ26: =AJ23-AJ25 -> 0 | AL26: =SUM(G26:AJ26) -> -795836
D27: Fractionation OLEIN IV 56 | AL27: Olein IV 56
D28: RBDPO Consume | F28: Kg | G28: =G29+G30 -> 0 | H28: =H29+H30 -> 0 | I28: =I29+I30 -> 0 | J28: =J29+J30 -> 0 | K28: 0 | L28: =L29+L30 -> 0 | M28: =M29+M30 -> 0 | N28: =N29+N30 -> 0 | O28: =O29+O30 -> 0 | P28: =P29+P30 -> 958540 | Q28: =Q29+Q30 -> 1073268 | R28: =R29+R30 -> 927936 | S28: =S29+S30 -> 732528 | ... AJ28: =AJ29+AJ30 -> 0 | AL28: =SUM(G28:AJ28) -> 5970222
D29: OLEIN IV 56 | F29: Kg | G29: 0 | H29: 0 | I29: 0 | J29: 0 | K29: 0 | L29: 0 | M29: 0 | N29: 0 | O29: 0 | P29: ='[5]10'!$P$21 -> 792648 | Q29: ='[6]11'!$P$21 -> 886386 | R29: ='[7]12'!$P$21 -> 785685 | S29: ='[8]13'!$P$21 -> 615419 | T29: ='[9]14'!$P$21 -> 827507 | U29: ='[10]15'!$P$21 -> 420382 | V29: 0 | W29: 0 | X29: 0 | Y29: 0 | Z29: 0 | AA29: 0 | AB29: 0 | AC29: 0 | AD29: ='[17]24'!$P$21 -> 662727 | AE29: 0 | AF29: 0 | AG29: 0 | AH29: 0 | AI29: 0 | AJ29: 0 | AL29: =SUM(G29:AJ29) -> 4990754
D30: STEARIN | F30: Kg | G30: 0 | H30: 0 | I30: 0 | J30: 0 | K30: 0 | L30: 0 | M30: 0 | N30: 0 | O30: 0 | P30: 165892 | Q30: ='[6]11'!$P$30 -> 186882 | R30: ='[7]12'!$P$30 -> 142251 | S30: ='[8]13'!$P$30 -> 117109 | T30: ='[9]14'!$P$30 -> 153671 | U30: 83550 | V30: 0 | W30: 0 | X30: 0 | Y30: 0 | Z30: 0 | AA30: 0 | AB30: 0 | AC30: 0 | AD30: 130113 | AE30: 0 | AF30: 0 | AG30: 0 | AH30: 0 | AI30: 0 | AJ30: 0 | AL30: =SUM(G30:AJ30) -> 979468
D31: Fractionation OLEIN IV 57 ( Bulk ) | AL31: Olein IV 57 ( Bulk )
D32: RBDPO Consume | F32: Kg | G32: =G33+G34 -> 0 | H32: =H33+H34 -> 0 | I32: =I33+I34 -> 0 | J32: =J33+J34 -> 0 | K32: 0 | L32: =L33+L34 -> 0 | M32: =M33+M34 -> 0 | N32: =N33+N34 -> 0 | O32: =O33+O34 -> 0 | P32: =P33+P34 -> 0 | Q32: =Q33+Q34 -> 0 | R32: =R33+R34 -> 0 | S32: =S33+S34 -> 0 | ... AJ32: =AJ33+AJ34 -> 0 | AL32: =SUM(G32:AJ32) -> 0
D33: OLEIN IV 57 | F33: Kg | G33: 0 | H33: 0 | I33: 0 | J33: 0 | K33: 0 | L33: 0 | M33: 0 | N33: 0 | O33: 0 | P33: 0 | Q33: 0 | R33: 0 | S33: 0 | T33: 0 | U33: 0 | V33: 0 | W33: 0 | X33: 0 | Y33: 0 | Z33: 0 | AA33: 0 | AB33: 0 | AC33: 0 | AD33: 0 | AE33: 0 | AF33: 0 | AG33: 0 | AH33: 0 | AI33: 0 | AJ33: 0 | AL33: =SUM(G33:AJ33) -> 0
D34: STEARIN | F34: Kg | G34: 0 | H34: 0 | I34: 0 | J34: 0 | K34: 0 | L34: 0 | M34: 0 | N34: 0 | O34: 0 | P34: 0 | Q34: 0 | R34: 0 | S34: 0 | T34: 0 | U34: 0 | V34: 0 | W34: 0 | X34: 0 | Y34: 0 | Z34: 0 | AA34: 0 | AB34: 0 | AC34: 0 | AD34: 0 | AE34: 0 | AF34: 0 | AG34: 0 | AH34: 0 | AI34: 0 | AJ34: 0 | AL34: =SUM(G34:AJ34) -> 0
D35: Fractionation OLEIN IV 57 ( Retail ) | AL35: Olein IV 57 ( Retail )
D36: CPO Consume | F36: Kg | AL36: =SUM(G36:AJ36) -> 0
D37: RBDPO Brand Consume | F37: Kg | G37: =G38+G39 -> 0 | H37: =H38+H39 -> 0 | I37: =I38+I39 -> 0 | J37: =J38+J39 -> 0 | K37: 0 | L37: =L38+L39 -> 0 | M37: =M38+M39 -> 0 | N37: =N38+N39 -> 0 | O37: =O38+O39 -> 0 | P37: =P38+P39 -> 0 | Q37: =Q38+Q39 -> 0 | R37: =R38+R39 -> 0 | S37: =S38+S39 -> 0 | ... AJ37: =AJ38+AJ39 -> 0 | AL37: =SUM(G37:AJ37) -> 0
D38: OLEIN IV 57 Low Color | F38: Kg | G38: 0 | H38: 0 | I38: 0 | J38: 0 | K38: 0 | L38: 0 | M38: 0 | N38: 0 | O38: 0 | P38: 0 | Q38: 0 | R38: 0 | S38: 0 | T38: 0 | U38: 0 | V38: 0 | W38: 0 | X38: 0 | Y38: 0 | Z38: 0 | AA38: 0 | AB38: 0 | AC38: 0 | AD38: 0 | AE38: 0 | AF38: 0 | AG38: 0 | AH38: 0 | AI38: 0 | AJ38: 0 | AL38: =SUM(G38:AJ38) -> 0
D39: STEARIN | F39: Kg | G39: 0 | H39: 0 | I39: 0 | J39: 0 | K39: 0 | L39: 0 | M39: 0 | N39: 0 | O39: 0 | P39: 0 | Q39: 0 | R39: 0 | S39: 0 | T39: 0 | U39: 0 | V39: 0 | W39: 0 | X39: 0 | Y39: 0 | Z39: 0 | AA39: 0 | AB39: 0 | AC39: 0 | AD39: 0 | AE39: 0 | AF39: 0 | AG39: 0 | AH39: 0 | AI39: 0 | AJ39: 0 | AL39: =SUM(G39:AJ39) -> 0
D40: Fractionation OLEIN IV 58 ( Bulk ) | AL40: Olein IV 58 ( Bulk )
D41: RBDPO Consume | E41: =E42+E43 -> 21429000 | F41: Kg | G41: =G42+G43 -> 994298 | H41: =H42+H43 -> 1115291 | I41: =I42+I43 -> 1038010 | J41: =J42+J43 -> 1058141 | K41: 899356 | L41: =L42+L43 -> 939422 | M41: =M42+M43 -> 1003337 | N41: =N42+N43 -> 899475 | O41: =O42+O43 -> 923368 | P41: =P42+P43 -> 219956 | Q41: =Q42+Q43 -> 0 | R41: =R42+R43 -> 0 | S41: =S42+S43 -> 0 | ... AJ41: =AJ42+AJ43 -> 0 | AL41: =SUM(G41:AJ41) -> 16567437
D42: OLEIN IV 58 | E42: 15000000 | F42: Kg | G42: ='[1]01'!$P$22 -> 755818 | H42: ='[2]02'!$P$22 -> 859079 | I42: ='[2]03'!$P$22 -> 793972 | J42: 810550 | K42: 686817 | L42: ='[3]06'!$P$22 -> 736059 | M42: ='[4]07'!$P$22 -> 763026 | N42: ='[5]08'!$P$22 -> 694832 | O42: ='[5]09'!$P$22 -> 687792 | P42: ='[5]10'!$P$22 -> 154064 | Q42: 0 | R42: 0 | S42: 0 | T42: 0 | U42: ='[10]15'!$P$22 -> 127749 | V42: ='[11]16'!$P$22 -> 613632 | W42: ='[11]17'!$P$22 -> 659915 | X42: ='[12]18'!$P$22 -> 581266 | Y42: ='[13]19'!$P$22 -> 698344 | Z42: ='[14]20'!$P$22 -> 694902 | AA42: ='[15]21'!$P$22 -> 745490 | AB42: ='[16]22'!$P$22 -> 628365 | AC42: ='[17]23'!$P$22 -> 717090 | AD42: ='[17]24'!$P$22 -> 164490 | AE42: 0 | AF42: 0 | AG42: 0 | AH42: 0 | AI42: 0 | AJ42: 0 | AL42: =SUM(G42:AJ42) -> 12573252
D43: STEARIN | E43: 6429000 | F43: Kg | G43: ='[1]01'!$P$30-G30 -> 238480 | H43: ='[2]02'!$P$30-H30 -> 256212 | I43: ='[2]03'!$P$30-I30 -> 244038 | J43: =247591-J30 -> 247591 | K43: =212539-K30 -> 212539 | L43: ='[3]06'!$P$30-L30 -> 203363 | M43: ='[4]07'!$P$30-M30 -> 240311 | N43: ='[5]08'!$P$30-N30 -> 204643 | O43: ='[5]09'!$P$30-O30 -> 235576 | P43: ='[5]10'!$P$30-P30 -> 65892 | Q43: 0 | R43: 0 | S43: 0 | T43: 0 | U43: ='[10]15'!$P$30-U30 -> 52851 | V43: ='[11]16'!$P$30-V30 -> 184988 | W43: ='[11]17'!$P$30-W30 -> 201291 | X43: ='[12]18'!$P$30-X30 -> 194152 | Y43: ='[13]19'!$P$30-Y30 -> 225340 | Z43: ='[14]20'!$P$30-Z30 -> 238527 | AA43: ='[15]21'!$P$30-AA30 -> 215107 | AB43: ='[16]22'!$P$30-AB30 -> 206070 | AC43: ='[17]23'!$P$30-AC30 -> 224876 | AD43: ='[17]24'!$P$30-AD30 -> 102338 | AE43: 0 | AF43: 0 | AG43: 0 | AH43: 0 | AI43: 0 | AJ43: 0 | AL43: =SUM(G43:AJ43) -> 3994185
D44: Fractionation OLEIN IV 58 ( Retail ) | AL44: Olein IV 58 ( Bulk )
D45: CPO Consume | F45: Kg | AL45: =SUM(G45:AJ45) -> 0
D46: RBDPO Consume | E46: =E47+E48 -> 21429000 | F46: Kg | G46: =G47+G48 -> 0 | H46: =H47+H48 -> 0 | I46: =I47+I48 -> 0 | J46: =J47+J48 -> 0 | K46: 0 | L46: =L47+L48 -> 0 | M46: =M47+M48 -> 0 | N46: =N47+N48 -> 0 | O46: =O47+O48 -> 0 | P46: =P47+P48 -> 0 | Q46: =Q47+Q48 -> 0 | R46: =R47+R48 -> 0 | S46: =S47+S48 -> 0 | ... AJ46: =AJ47+AJ48 -> 0 | AL46: =SUM(G46:AJ46) -> 0
D47: OLEIN IV 58 | E47: 15000000 | F47: Kg | G47: 0 | H47: 0 | I47: 0 | J47: 0 | K47: 0 | L47: 0 | M47: 0 | N47: 0 | O47: 0 | P47: 0 | Q47: 0 | R47: 0 | S47: 0 | T47: 0 | U47: 0 | V47: 0 | W47: 0 | X47: 0 | Y47: 0 | Z47: 0 | AA47: 0 | AB47: 0 | AC47: 0 | AD47: 0 | AE47: 0 | AF47: 0 | AG47: 0 | AH47: 0 | AI47: 0 | AJ47: 0 | AL47: =SUM(G47:AJ47) -> 0
D48: STEARIN | E48: 6429000 | F48: Kg | G48: 0 | H48: 0 | I48: 0 | J48: 0 | K48: 0 | L48: 0 | M48: 0 | N48: 0 | O48: 0 | P48: 0 | Q48: 0 | R48: 0 | S48: 0 | T48: 0 | U48: 0 | V48: 0 | W48: 0 | X48: 0 | Y48: 0 | Z48: 0 | AA48: 0 | AB48: 0 | AC48: 0 | AD48: 0 | AE48: 0 | AF48: 0 | AG48: 0 | AH48: 0 | AI48: 0 | AJ48: 0 | AL48: =SUM(G48:AJ48) -> 0
D49: Fractionation OLEIN IV 60 | AL49: Olein IV 60
D50: CPO Consume | F50: Kg | AL50: =SUM(G50:AJ50) -> 0
D51: RBDPO Brand Consume | F51: Kg | G51: =G53+G54 -> 0 | H51: =H53+H54 -> 0 | I51: =I53+I54 -> 0 | J51: =J53+J54 -> 0 | K51: 0 | L51: 0 | M51: =M53+M54 -> 0 | N51: =N53+N54 -> 0 | O51: =O53+O54 -> 0 | P51: =P53+P54 -> 0 | Q51: =Q53+Q54 -> 0 | R51: =R53+R54 -> 0 | S51: =S53+S54 -> 0 | T51: =T53+T54 -> 0 | ... AJ51: =AJ53+AJ54 -> 0 | AL51: =SUM(G51:AJ51) -> 0
D52: OLEIN IV 60 Bulk | F52: Kg | G52: 0 | H52: 0 | I52: 0 | J52: 0 | K52: 0 | L52: 0 | M52: 0 | N52: 0 | O52: 0 | P52: 0 | Q52: 0 | R52: 0 | S52: 0 | T52: 0 | U52: 0 | V52: 0 | W52: 0 | X52: 0 | Y52: 0 | Z52: 0 | AA52: 0 | AB52: 0 | AC52: 0 | AD52: 0 | AE52: 0 | AF52: 0 | AG52: 0 | AH52: 0 | AI52: 0 | AJ52: 0 | AL52: =SUM(G52:AJ52) -> 0
D53: OLEIN IV 60 Salvaco | F53: Kg | G53: 0 | H53: 0 | I53: 0 | J53: 0 | K53: 0 | L53: 0 | M53: 0 | N53: 0 | O53: 0 | P53: 0 | Q53: 0 | R53: 0 | S53: 0 | T53: 0 | U53: 0 | V53: 0 | W53: 0 | X53: 0 | Y53: 0 | Z53: 0 | AA53: 0 | AB53: 0 | AC53: 0 | AD53: 0 | AE53: 0 | AF53: 0 | AG53: 0 | AH53: 0 | AI53: 0 | AJ53: 0 | AL53: =SUM(G53:AJ53) -> 0
D54: SOFT STEARIN | F54: Kg | G54: 0 | H54: 0 | I54: 0 | J54: 0 | K54: 0 | L54: 0 | M54: 0 | N54: 0 | O54: 0 | P54: 0 | Q54: 0 | R54: 0 | S54: 0 | T54: 0 | U54: 0 | V54: 0 | W54: 0 | X54: 0 | Y54: 0 | Z54: 0 | AA54: 0 | AB54: 0 | AC54: 0 | AD54: 0 | AE54: 0 | AF54: 0 | AG54: 0 | AH54: 0 | AI54: 0 | AJ54: 0 | AL54: =SUM(G54:AJ54) -> 0
D55: Ratio Run RBDPO | F55: % | G55: 0 | H55: 0 | I55: 0 | J55: 0 | K55: 0 | L55: 0 | M55: 0 | N55: 0 | O55: 0 | P55: 0 | Q55: 0 | R55: 0 | S55: 0 | T55: 0 | U55: 0 | V55: 0 | W55: 0 | X55: 0 | Y55: 0 | Z55: 0 | AA55: 0 | AB55: 0 | AC55: 0 | AD55: 0 | AE55: 0 | AF55: 0 | AG55: 0 | AH55: 0 | AI55: 0 | AJ55: 0 | AL55: =SUM(G55:AJ55) -> 0
D56: YIELD | AL56: Yield
D57: RBDPO | E57: 94.2 | F57: % | G57: =(G18/(G9))*100 -> 96.846974 | H57: =(H18/(H9))*100 -> 93.7815 | I57: =(I18/(I9))*100 -> 97.399841 | J57: =(J18/(J9))*100 -> 95.084558 | K57: =(K18/(K9))*100 -> 96.204991 | L57: =(L18/(L9))*100 -> 95.088014 | M57: =(M18/(M9))*100 -> 95.163391 | N57: =(N18/(N9))*100 -> 90.573856 | ... AJ57: =(AJ18/(AJ9))*100 -> #DIV/0! | AL57: =(AL18/(AL9))*100 -> 97.942699
D58: PFAD | E58: 5 | F58: % | G58: =(G19/(G9))*100 -> 4.0028525 | H58: =(H19/(H9))*100 -> 4.5159129 | I58: =(I19/(I9))*100 -> 4.2342505 | J58: =(J19/(J9))*100 -> 4.8264622 | K58: 3.325657 | L58: =(L19/(L9))*100 -> 4.1639141 | M58: =(M19/(M9))*100 -> 3.9840336 | N58: =(N19/(N9))*100 -> 4.3645935 | O58: =(O19/(O9))*100 -> 4.5684618 | P58: =(P19/(P9))*100 -> 4.3398595 | Q58: =(Q19/(Q9))*100 -> 4.3351928 | R58: =(R19/(R9))*100 -> 4.2363964 | S58: =(S19/(S9))*100 -> 5.2029077 | ... AJ58: =(AJ19/(AJ9))*100 -> #DIV/0! | AL58: =(AL19/(AL9))*100 -> 4.2716875
D59: Olein IV 56 | E59: 82 | F59: % | G59: =G29/(G29+G30)*100 -> #DIV/0! | H59: =H29/(H29+H30)*100 -> #DIV/0! | I59: =I29/(I29+I30)*100 -> #DIV/0! | J59: =J29/(J29+J30)*100 -> #DIV/0! | K59: #DIV/0! | L59: =L29/(L29+L30)*100 -> #DIV/0! | M59: =M29/(M29+M30)*100 -> #DIV/0! | N59: =N29/(N29+N30)*100 -> #DIV/0! | O59: =O29/(O29+O30)*100 -> #DIV/0! | P59: =P29/(P29+P30)*100 -> 82.693263 | Q59: =Q29/(Q29+Q30)*100 -> 82.587574 | R59: =R29/(R29+R30)*100 -> 84.670171 | S59: =S29/(S29+S30)*100 -> 84.013034 | ... AJ59: =AJ29/(AJ29+AJ30)*100 -> #DIV/0! | AL59: =AL29/(AL29+AL30)*100 -> 83.594111
D60: Stearin | E60: 18 | F60: % | G60: =(G30/G28)*100 -> #DIV/0! | H60: =(H30/H28)*100 -> #DIV/0! | I60: =(I30/I28)*100 -> #DIV/0! | J60: =(J30/J28)*100 -> #DIV/0! | K60: #DIV/0! | L60: =(L30/L28)*100 -> #DIV/0! | M60: =(M30/M28)*100 -> #DIV/0! | N60: =(N30/N28)*100 -> #DIV/0! | O60: =(O30/O28)*100 -> #DIV/0! | P60: =(P30/P28)*100 -> 17.306737 | Q60: =(Q30/Q28)*100 -> 17.412426 | R60: =(R30/R28)*100 -> 15.329829 | S60: =(S30/S28)*100 -> 15.986966 | ... AJ60: =(AJ30/AJ28)*100 -> #DIV/0! | AL60: =AL30/(AL29+AL30)*100 -> 16.405889
D61: Olein IV 57 ( Bulk ) | E61: 75 | G61: =(G33/G32)*100 -> #DIV/0! | H61: =(H33/H32)*100 -> #DIV/0! | I61: =(I33/I32)*100 -> #DIV/0! | J61: =(J33/J32)*100 -> #DIV/0! | K61: #DIV/0! | L61: =(L33/L32)*100 -> #DIV/0! | M61: =(M33/M32)*100 -> #DIV/0! | N61: =(N33/N32)*100 -> #DIV/0! | O61: =(O33/O32)*100 -> #DIV/0! | P61: =(P33/P32)*100 -> #DIV/0! | Q61: =(Q33/Q32)*100 -> #DIV/0! | R61: =(R33/R32)*100 -> #DIV/0! | S61: =(S33/S32)*100 -> #DIV/0! | ... AJ61: =(AJ33/AJ32)*100 -> #DIV/0! | AL61: =(AL38/AL37)*100 -> #DIV/0!
D62: Stearin | E62: 25 | G62: =(G34/G32)*100 -> #DIV/0! | H62: =(H34/H32)*100 -> #DIV/0! | I62: =(I34/I32)*100 -> #DIV/0! | J62: =(J34/J32)*100 -> #DIV/0! | K62: #DIV/0! | L62: =(L34/L32)*100 -> #DIV/0! | M62: =(M34/M32)*100 -> #DIV/0! | N62: =(N34/N32)*100 -> #DIV/0! | O62: =(O34/O32)*100 -> #DIV/0! | P62: =(P34/P32)*100 -> #DIV/0! | Q62: =(Q34/Q32)*100 -> #DIV/0! | R62: =(R34/R32)*100 -> #DIV/0! | S62: =(S34/S32)*100 -> #DIV/0! | ... AJ62: =(AJ34/AJ32)*100 -> #DIV/0! | AL62: =(AL39/AL37)*100 -> #DIV/0!
D63: Olein IV 57 ( Retail ) | E63: 75 | F63: % | G63: =G38/G37*100 -> #DIV/0! | H63: =H38/H37*100 -> #DIV/0! | I63: =I38/I37*100 -> #DIV/0! | J63: =J38/J37*100 -> #DIV/0! | K63: #DIV/0! | L63: =L38/L37*100 -> #DIV/0! | M63: =M38/M37*100 -> #DIV/0! | N63: =N38/N37*100 -> #DIV/0! | O63: =O38/O37*100 -> #DIV/0! | P63: =P38/P37*100 -> #DIV/0! | Q63: =Q38/Q37*100 -> #DIV/0! | R63: =R38/R37*100 -> #DIV/0! | S63: =S38/S37*100 -> #DIV/0! | ... AJ63: =AJ38/AJ37*100 -> #DIV/0! | AL63: =AL38/AL37*100 -> #DIV/0!
D64: Stearin | E64: 25 | F64: % | G64: =G39/G37*100 -> #DIV/0! | H64: =H39/H37*100 -> #DIV/0! | I64: =I39/I37*100 -> #DIV/0! | J64: =J39/J37*100 -> #DIV/0! | K64: #DIV/0! | L64: =L39/L37*100 -> #DIV/0! | M64: =M39/M37*100 -> #DIV/0! | N64: =N39/N37*100 -> #DIV/0! | O64: =O39/O37*100 -> #DIV/0! | P64: =P39/P37*100 -> #DIV/0! | Q64: =Q39/Q37*100 -> #DIV/0! | R64: =R39/R37*100 -> #DIV/0! | S64: =S39/S37*100 -> #DIV/0! | ... AJ64: =AJ39/AJ37*100 -> #DIV/0! | AL64: =AL39/AL37*100 -> #DIV/0!
D65: Olein IV 58 ( Bulk ) | E65: 70 | F65: % | G65: =G42/(G42+G43)*100 -> 76.015239 | H65: =H42/(H42+H43)*100 -> 77.027341 | I65: =I42/(I42+I43)*100 -> 76.489822 | J65: =J42/(J42+J43)*100 -> 76.601323 | K65: 76.367645 | L65: =L42/(L42+L43)*100 -> 78.352327 | M65: =M42/(M42+M43)*100 -> 76.048825 | N65: =N42/(N42+N43)*100 -> 77.248617 | O65: =O42/(O42+O43)*100 -> 74.487312 | P65: =P42/(P42+P43)*100 -> 70.0431 | Q65: =Q42/(Q42+Q43)*100 -> #DIV/0! | R65: =R42/(R42+R43)*100 -> #DIV/0! | S65: =S42/(S42+S43)*100 -> #DIV/0! | ... AJ65: =AJ42/(AJ42+AJ43)*100 -> #DIV/0! | AL65: =AL42/(AL42+AL43)*100 -> 75.891352
D66: Stearin | E66: 30 | F66: % | G66: =G43/(G43+G42)*100 -> 23.984761 | H66: =H43/(H43+H42)*100 -> 22.972659 | I66: =I43/(I43+I42)*100 -> 23.510178 | J66: =J43/(J43+J42)*100 -> 23.398677 | K66: 23.632355 | L66: =L43/(L43+L42)*100 -> 21.647673 | M66: =M43/(M43+M42)*100 -> 23.951175 | N66: =N43/(N43+N42)*100 -> 22.751383 | O66: =O43/(O43+O42)*100 -> 25.512688 | P66: =P43/(P43+P42)*100 -> 29.9569 | Q66: =Q43/(Q43+Q42)*100 -> #DIV/0! | R66: =R43/(R43+R42)*100 -> #DIV/0! | S66: =S43/(S43+S42)*100 -> #DIV/0! | ... AJ66: =AJ43/(AJ43+AJ42)*100 -> #DIV/0! | AL66: =AL43/AL41*100 -> 24.108648
D67: Olein IV 58 ( Retail ) | E67: 70 | F67: % | G67: =G47/(G47+G48)*100 -> #DIV/0! | H67: =H47/(H47+H48)*100 -> #DIV/0! | I67: =I47/(I47+I48)*100 -> #DIV/0! | J67: =J47/(J47+J48)*100 -> #DIV/0! | K67: #DIV/0! | L67: =L47/(L47+L48)*100 -> #DIV/0! | M67: =M47/(M47+M48)*100 -> #DIV/0! | N67: =N47/(N47+N48)*100 -> #DIV/0! | O67: =O47/(O47+O48)*100 -> #DIV/0! | P67: =P47/(P47+P48)*100 -> #DIV/0! | Q67: =Q47/(Q47+Q48)*100 -> #DIV/0! | R67: =R47/(R47+R48)*100 -> #DIV/0! | S67: =S47/(S47+S48)*100 -> #DIV/0! | ... AJ67: =AJ47/(AJ47+AJ48)*100 -> #DIV/0! | AL67: =AL47/(AL47+AL48)*100 -> #DIV/0!
D68: Stearin | E68: 30 | F68: % | G68: =G48/(G47+G48)*100 -> #DIV/0! | H68: =H48/(H47+H48)*100 -> #DIV/0! | I68: =I48/(I47+I48)*100 -> #DIV/0! | J68: =J48/(J47+J48)*100 -> #DIV/0! | K68: #DIV/0! | L68: =L48/(L47+L48)*100 -> #DIV/0! | M68: =M48/(M47+M48)*100 -> #DIV/0! | N68: =N48/(N47+N48)*100 -> #DIV/0! | O68: =O48/(O47+O48)*100 -> #DIV/0! | P68: =P48/(P47+P48)*100 -> #DIV/0! | Q68: =Q48/(Q47+Q48)*100 -> #DIV/0! | R68: =R48/(R47+R48)*100 -> #DIV/0! | S68: =S48/(S47+S48)*100 -> #DIV/0! | ... AJ68: =AJ48/(AJ47+AJ48)*100 -> #DIV/0! | AL68: =AL48/(AL47+AL48)*100 -> #DIV/0!
D69: Olein IV 60 | E69: 60 | F69: % | G69: =G52/G51*100 -> #DIV/0! | H69: =H52/H51*100 -> #DIV/0! | I69: =I52/I51*100 -> #DIV/0! | J69: =J52/J51*100 -> #DIV/0! | K69: #DIV/0! | L69: =L52/L51*100 -> #DIV/0! | M69: =M52/M51*100 -> #DIV/0! | N69: =N52/N51*100 -> #DIV/0! | O69: =O52/O51*100 -> #DIV/0! | P69: =P52/P51*100 -> #DIV/0! | Q69: =Q52/Q51*100 -> #DIV/0! | R69: =R52/R51*100 -> #DIV/0! | S69: =S52/S51*100 -> #DIV/0! | ... AJ69: =AJ52/AJ51*100 -> #DIV/0! | AL69: =(AL53+AL52)/AL51*100 -> #DIV/0!
D70: Soft Stearin | E70: 40 | F70: % | G70: =G54/G51*100 -> #DIV/0! | H70: =H54/H51*100 -> #DIV/0! | I70: =I54/I51*100 -> #DIV/0! | J70: =J54/J51*100 -> #DIV/0! | K70: #DIV/0! | L70: =L54/L51*100 -> #DIV/0! | M70: =M54/M51*100 -> #DIV/0! | N70: =N54/N51*100 -> #DIV/0! | O70: =O54/O51*100 -> #DIV/0! | P70: =P54/P51*100 -> #DIV/0! | Q70: =Q54/Q51*100 -> #DIV/0! | R70: =R54/R51*100 -> #DIV/0! | S70: =S54/S51*100 -> #DIV/0! | ... AJ70: =AJ54/AJ51*100 -> #DIV/0! | AL70: =AL54/AL51*100 -> #DIV/0!
C71: 2 | D71: CHEMICAL CONSUMABLE | AL71: Chemical
D72: Bleaching Earth (BE) to Poram Spec | E72: 8 | F72: Kg | G72: 6031 | H72: 3547 | I72: 4999 | J72: 5981 | K72: 5471 | L72: 4974 | M72: 4629 | N72: 4400 | O72: 4691 | P72: 6930 | Q72: 5718 | R72: 4983 | S72: 4801 | T72: 5643 | U72: 5874 | V72: 5726 | W72: 4802 | X72: 8051 | Y72: 9884 | Z72: 10692 | AA72: 14561 | AB72: 5181 | AC72: 0 | AD72: 0 | AE72: 0 | AF72: 0 | AG72: 0 | AH72: 0 | AI72: 0 | AJ72: 0 | AL72: =SUM(G72:AJ72) -> 137569
F73: % | G73: =G72/(G11)*100 -> 0.70161601 | H73: =H72/(H11)*100 -> 0.66015261 | I73: =I72/(I11)*100 -> 0.67847356 | J73: =J72/(J11)*100 -> 0.66857518 | K73: 0.6074812 | L73: =L72/(L11)*100 -> 0.58782167 | M73: =M72/(M11)*100 -> 0.61406092 | N73: =N72/(N11)*100 -> 0.63150975 | O73: =O72/(O11)*100 -> 0.56613975 | P73: =P72/(P11)*100 -> 0.69047975 | Q73: =Q72/(Q11)*100 -> 0.57133779 | R73: =R72/(R11)*100 -> 0.53835466 | S73: =S72/(S11)*100 -> 0.59738747 | ... AJ73: =AJ72/(AJ11)*100 -> #DIV/0! | AL73: =AL72/(AL11)*100 -> 0.67510642 | BA73: #DIV/0! | BB73: #DIV/0!
D74: Bleaching Earth (BE) to Branded Spec | E74: 18 | F74: Kg | G74: 0 | H74: 0 | I74: 0 | J74: 0 | K74: 0 | L74: 0 | M74: 0 | N74: 0 | O74: 0 | P74: 0 | Q74: 0 | R74: 0 | S74: 0 | T74: 0 | U74: 0 | V74: 0 | W74: 0 | X74: 0 | Y74: 0 | Z74: 0 | AA74: 0 | AB74: 0 | AC74: 0 | AD74: 0 | AE74: 0 | AF74: 0 | AG74: 0 | AH74: 0 | AI74: 0 | AJ74: 0 | AL74: =SUM(G74:AJ74) -> 0
F75: % | G75: =G74/(G12)*100 -> #DIV/0! | H75: =H74/(H12)*100 -> #DIV/0! | I75: =I74/(I12)*100 -> #DIV/0! | J75: =J74/(J12)*100 -> #DIV/0! | K75: #DIV/0! | L75: =L74/(L12)*100 -> #DIV/0! | M75: =M74/(M12)*100 -> #DIV/0! | N75: =N74/(N12)*100 -> #DIV/0! | O75: =O74/(O12)*100 -> #DIV/0! | P75: =P74/(P12)*100 -> #DIV/0! | Q75: =Q74/(Q12)*100 -> #DIV/0! | R75: =R74/(R12)*100 -> #DIV/0! | S75: =S74/(S12)*100 -> #DIV/0! | ... AJ75: =AJ74/(AJ12)*100 -> #DIV/0! | AL75: =AL74/(AL12)*100 -> #DIV/0!
D76: Phosporic Acid (PA) | E76: 0.6 | F76: Kg | G76: 424.424 | H76: 380.116 | I76: 473.396 | J76: 443.08 | K76: 424.424 | L76: 409.266 | M76: 489.72 | N76: 353.304 | O76: 397.6 | P76: 553.85 | Q76: 473.396 | R76: 425.59 | S76: 417.428 | T76: 503.712 | U76: 489.72 | V76: 474.562 | W76: 314.82 | X76: 546.854 | Y76: 684.442 | Z76: 846.516 | AA76: 825.528 | AB76: 343.97 | AC76: 0 | AD76: 0 | AE76: 0 | AF76: 0 | AG76: 0 | AH76: 0 | AI76: 0 | AJ76: 0 | AL76: =SUM(G76:AJ76) -> 10695.718
F77: % | G77: =G76/(G9)*100 -> 0.04937534 | H77: =H76/(H9)*100 -> 0.07074558 | I77: =I76/(I9)*100 -> 0.064250184 | J77: =J76/(J9)*100 -> 0.04952889 | K77: 0.047126595 | L77: =L76/(L9)*100 -> 0.048366591 | M77: =M76/(M9)*100 -> 0.064963905 | N77: =N76/(N9)*100 -> 0.050707937 | O77: =O76/(O9)*100 -> 0.0479849 | P77: =P76/(P9)*100 -> 0.05518358 | Q77: =Q76/(Q9)*100 -> 0.047301333 | R77: =R76/(R9)*100 -> 0.045980004 | S77: =S76/(S9)*100 -> 0.051940483 | ... AJ77: =AJ76/(AJ9)*100 -> #DIV/0! | AL77: =AL76/(AL9)*100 -> 0.05248819
C78: 3 | D78: OIL LOSSES | E78: 0.8 | F78: % | G78: =((SUM(G18:G19))-(SUM(G9)))/(SUM(G9))*100 -> 0.84982672 | H78: =((SUM(H18:H19))-(SUM(H9)))/(SUM(H9))*100 -> -1.702587 | I78: =((SUM(I18:I19))-(SUM(I9)))/(SUM(I9))*100 -> 1.6340912 | J78: =((SUM(J18:J19))-(SUM(J9)))/(SUM(J9))*100 -> -0.088979408 | K78: -0.89873019 | L78: =((SUM(L18:L19))-(SUM(L9)))/(SUM(L9))*100 -> -0.74807221 | M78: =((SUM(M18:M19))-(SUM(M9)))/(SUM(M9))*100 -> -0.85257497 | N78: =((SUM(N18:N19))-(SUM(N9)))/(SUM(N9))*100 -> -5.0615507 | O78: =((SUM(O18:O19))-(SUM(O9)))/(SUM(O9))*100 -> -4.3695706 | P78: =((SUM(P18:P19))-(SUM(P9)))/(SUM(P9))*100 -> 0.67204703 | Q78: =((SUM(Q18:Q19))-(SUM(Q9)))/(SUM(Q9))*100 -> -0.91086311 | R78: =((SUM(R18:R19))-(SUM(R9)))/(SUM(R9))*100 -> -1.6783744 | S78: =((SUM(S18:S19))-(SUM(S9)))/(SUM(S9))*100 -> -0.45765281 | ... AJ78: =((SUM(AJ18:AJ19))-(SUM(AJ9)))/(SUM(AJ9))*100 -> #DIV/0! | AL78: =((SUM(AL18:AL19))-(SUM(AL9)))/(SUM(AL9))*100 -> 2.2143867
F79: Kg | G79: =G78%*G9 -> 7305 | H79: =H78%*H9 -> -9148 | I79: =I78%*I9 -> 12040 | J79: =J78%*J9 -> -796 | K79: -8094 | L79: =L78%*L9 -> -6330 | M79: =M78%*M9 -> -6427 | N79: =N78%*N9 -> -35266 | O79: =O78%*O9 -> -36206 | P79: =P78%*P9 -> 6745 | Q79: =Q78%*Q9 -> -9116 | R79: =R78%*R9 -> -15535 | S79: =S78%*S9 -> -3678 | ... AJ79: =AJ78%*AJ9 -> #DIV/0! | AL79: =AL78%*AL9 -> 451234
D80: % Oil Content | E80: 22 | F80: % | G80: 21.89 | H80: 21.93 | I80: 21.99 | J80: 22.06 | K80: 22.07 | L80: 21.86 | M80: 21.84 | N80: 21.75 | O80: 21.88 | P80: 21.75 | Q80: 21.89 | R80: 21.85 | S80: 21.9 | T80: 21.93 | U80: 21.9 | V80: 21.95 | W80: 21.98 | X80: 22.03 | Y80: 21.99 | Z80: 21.96 | AA80: 21.97 | AB80: 21.8 | AC80: 0 | AD80: 0 | AE80: 0 | AF80: 0 | AG80: 0 | AH80: 0 | AI80: 0 | AJ80: 0 | AL80: =SUM(G80:AJ80)/AL6 -> 21.916818
D81: Spent Bleaching Earth | F81: Kg | G81: =SUM(G72,G74)+(G80%*SUM(G72,G74)) -> 7351.1859 | H81: =SUM(H72,H74)+(H80%*SUM(H72,H74)) -> 4324.8571 | I81: =SUM(I72,I74)+(I80%*SUM(I72,I74)) -> 6098.2801 | J81: =SUM(J72,J74)+(J80%*SUM(J72,J74)) -> 7300.4086 | K81: 6678.4497 | L81: =SUM(L72,L74)+(L80%*SUM(L72,L74)) -> 6061.3164 | M81: =SUM(M72,M74)+(M80%*SUM(M72,M74)) -> 5639.9736 | N81: =SUM(N72,N74)+(N80%*SUM(N72,N74)) -> 5357 | O81: =SUM(O72,O74)+(O80%*SUM(O72,O74)) -> 5717.3908 | P81: =SUM(P72,P74)+(P80%*SUM(P72,P74)) -> 8437.275 | Q81: =SUM(Q72,Q74)+(Q80%*SUM(Q72,Q74)) -> 6969.6702 | R81: =SUM(R72,R74)+(R80%*SUM(R72,R74)) -> 6071.7855 | S81: =SUM(S72,S74)+(S80%*SUM(S72,S74)) -> 5852.419 | ... AJ81: =SUM(AJ72,AJ74)+(AJ80%*SUM(AJ72,AJ74)) -> 0 | AL81: =SUM(AL72,AL74)+(AL80%*SUM(AL72,AL74))/AL6 -> 138939.49
C82: 4 | D82: PACKAGING (Brand Salvaco) | AL82: Packaging
D83: Olein IV 60 Received | F83: Kg | AL83: 0
D84: Olein IV 60 Consume | F84: Kg | AL84: 0
D85: - finished product | F85: Kg | G85: 0 | H85: 0 | I85: 0 | J85: 0 | K85: 0 | L85: 0 | M85: 0 | N85: 0 | O85: 0 | P85: 0 | Q85: 0 | R85: 0 | S85: 0 | T85: 0 | U85: 0 | V85: 0 | W85: 0 | X85: 0 | Y85: 0 | Z85: 0 | AA85: 0 | AB85: 0 | AC85: 0 | AD85: 0 | AE85: 0 | AF85: 0 | AG85: 0 | AH85: 0 | AI85: 0 | AJ85: 0 | AL85: 0
D86: - sample | F86: Kg | G86: 0 | H86: 0 | I86: 0 | J86: 0 | K86: 0 | L86: 0 | M86: 0 | N86: 0 | O86: 0 | P86: 0 | Q86: 0 | R86: 0 | S86: 0 | T86: 0 | U86: 0 | V86: 0 | W86: 0 | X86: 0 | Y86: 0 | Z86: 0 | AA86: 0 | AB86: 0 | AC86: 0 | AD86: 0 | AE86: 0 | AF86: 0 | AG86: 0 | AH86: 0 | AI86: 0 | AJ86: 0 | AL86: 0
D87: - remelt, flushing, downgrade | F87: Kg | G87: 0 | H87: 0 | I87: 0 | J87: 0 | K87: 0 | L87: 0 | M87: 0 | N87: 0 | O87: 0 | P87: 0 | Q87: 0 | R87: 0 | S87: 0 | T87: 0 | U87: 0 | V87: 0 | W87: 0 | X87: 0 | Y87: 0 | Z87: 0 | AA87: 0 | AB87: 0 | AC87: 0 | AD87: 0 | AE87: 0 | AF87: 0 | AG87: 0 | AH87: 0 | AI87: 0 | AJ87: 0 | AL87: 0
D88: Carton | AL88: Carton
D89: Salvaco 1 Liter | F89: Box | AL89: 0
D90: Salvaco 2 Liter | F90: Box | AL90: 0
D91: Pouch | AL91: Pouch
D92: Salvaco 1 Liter | F92: Pouch | G92: 0 | H92: 0 | I92: 0 | J92: 0 | K92: 0 | L92: 0 | M92: 0 | N92: 0 | O92: 0 | P92: 0 | Q92: 0 | R92: 0 | S92: 0 | T92: 0 | U92: 0 | V92: 0 | W92: 0 | X92: 0 | Y92: 0 | Z92: 0 | AA92: 0 | AB92: 0 | AC92: 0 | AD92: 0 | AE92: 0 | AF92: 0 | AG92: 0 | AH92: 0 | AI92: 0 | AJ92: 0 | AL92: 0
D93: Salvaco 2 Liter | F93: Pouch | G93: 0 | H93: 0 | I93: 0 | J93: 0 | K93: 0 | L93: 0 | M93: 0 | N93: 0 | O93: 0 | P93: 0 | Q93: 0 | R93: 0 | S93: 0 | T93: 0 | U93: 0 | V93: 0 | W93: 0 | X93: 0 | Y93: 0 | Z93: 0 | AA93: 0 | AB93: 0 | AC93: 0 | AD93: 0 | AE93: 0 | AF93: 0 | AG93: 0 | AH93: 0 | AI93: 0 | AJ93: 0 | AL93: 0
D94: Consumable Vit. A | F94: gram | G94: 0 | H94: 0 | I94: 0 | J94: 0 | K94: 0 | L94: 0 | M94: 0 | N94: 0 | O94: 0 | P94: 0 | Q94: 0 | R94: 0 | S94: 0 | T94: 0 | U94: 0 | V94: 0 | W94: 0 | X94: 0 | Y94: 0 | Z94: 0 | AA94: 0 | AB94: 0 | AC94: 0 | AD94: 0 | AE94: 0 | AF94: 0 | AG94: 0 | AH94: 0 | AI94: 0 | AJ94: 0 | AL94: 0
D95: Consumable Packing Tape | F95: Roll | G95: 0 | H95: 0 | I95: 0 | J95: 0 | K95: 0 | L95: 0 | M95: 0 | N95: 0 | O95: 0 | P95: 0 | Q95: 0 | R95: 0 | S95: 0 | T95: 0 | U95: 0 | V95: 0 | W95: 0 | X95: 0 | Y95: 0 | Z95: 0 | AA95: 0 | AB95: 0 | AC95: 0 | AD95: 0 | AE95: 0 | AF95: 0 | AG95: 0 | AH95: 0 | AI95: 0 | AJ95: 0 | AL95: 0
D96: REJECT MATERIAL QTY | AL96: Loss Material
D97: Carton | AL97: Carton
D98: Salvaco 1 Liter | F98: Box | AL98: 0
D99: Salvaco 2 Liter | F99: Box | AL99: 0
D100: Pouch | AL100: Pouch
...

Sheet SUMMARY HPP 
B2: Production Cost September
B3: Through Put CPO Proses (Ton/Day) | H3: TPD | I3: ='HPP REF '!$N$3 -> 926.24455
B4: Working Day | F4: 1 | H4: Days | I4: ='HPP REF '!$N$4 -> 22
B5: Refined CPO ( Ton/month ) | H5: MTD | I5: =$I$4*$I$3 -> 20377.38
B6: Through Put RPO Proses (Ton/Day) | H6: TPD | I6: ='HPP FRACT'!$O$3 -> 905.74317
B7: Working Day | H7: Days | I7: ='HPP FRACT'!$O$4 -> 24
B8: Fract RPO ( ton/month ) | H8: MTD | I8: =$I$7*$I$6 -> 21737.836
B9: KURS | H9: Rp/USD | I9: 15546
B10: No | C10: Items | D10: Description | G10: Rupiah | H10: Rp/Kg | I10: USD/MT
B11: I | C11: Production Cost | D11: ● | E11: Refining Cost | G11: ='HPP REF '!$M$48 -> 5.3772519e+09 | H11: =$G$11/($I$5*1000) -> 263.88338 | I11: =(G11/$I$9)/$I$5 -> 16.974359
D12: ● | E12: Fractionation Cost | G12: ='HPP FRACT'!$M$22 -> 1.4786844e+09 | H12: =$G$12/($I$8*1000) -> 68.023534 | I12: =(G12/$I$9)/$I$8 -> 4.3756293
D13: ● | E13: Preventive Maintenance Cost | F13: =F4 -> 1 | G13: =MTC!$F$18*F13 -> 5.7883129e+08 | H13: =$G$13/($I$5*1000) -> 28.405579 | I13: =(G13/$I$9)/$I$5 -> 1.8271954
G14: =SUM(G11:$G$13) -> 7.4347676e+09 | H14: =SUM($H$11:$H$13) -> 360.31249 | I14: =SUM(I11:I13) -> 23.177183 | K14: =I14+I26 -> 51.114957
B16: II | C16: Port Cost | D16: ● | E16: Trucking Komoditi ke Kuala Tanjung | G16: =LOG!I8+LOG!I9+LOG!$I$10 -> 2.1156611e+09 | H16: =$G$16/($I$5*1000) -> 103.824 | I16: =($G$16/$I$9)/$I$5 -> 6.6785025
D17: ● | E17: Sewa Tank PTI Total Volume : 24.000 MT ( 5 Unit ) | F17: =F4 -> 1 | G17: =LOG!I11+LOG!I12+LOG!I13+LOG!$I$14*F17 -> 1886000000 | H17: =$G$17/($I$5*1000) -> 92.553606 | I17: =($G$17/$I$9)/$I$5 -> 5.9535318
D18: ● | E18: Instalasi & Pemanasan, Pompa, Surveyor dan Documen | G18: =LOG!I18+LOG!I19+LOG!I20+LOG!$I$21 -> 1.0915755e+09 | H18: =$G$18/($I$5*1000) -> 53.568 | I18: =($G$18/$I$9)/$I$5 -> 3.4457738
D19: ● | E19: Finalty Over Capacity Tank | G19: =LOG!I15+LOG!I16+LOG!$I$17 -> 8.6921752e+08 | H19: =$G$19/($I$5*1000) -> 42.656 | I19: =($G$19/$I$9)/$I$5 -> 2.7438569
G20: =SUM($G$16:$G$19) -> 5.9624541e+09 | H20: =SUM($H$16:$H$19) -> 292.60161 | I20: =SUM($I$16:$I$19) -> 18.821665
B22: II | C22: Fix Cost | D22: ● | E22: Manpower Cost | F22: =F4 -> 1 | G22: =[23]MPC!$H$29*$F$22 -> 2.1846655e+09 | H22: =$G$22/($I$5*1000) -> 107.21032 | I22: =($G$22/$I$9)/$I$5 -> 6.8963286
D23: ● | E23: Admin OH Cost | F23: =F4 -> 1 | G23: =OH!G51*$F$23 -> 1.4360564e+09 | H23: =$G$23/($I$5*1000) -> 70.473063 | I23: =($G$23/$I$9)/$I$5 -> 4.5331959
D24: ● | E24: Depresiasi Cost | F24: =F4 -> 1 | G24: =DEP!I9*$F$24 -> 4.1811848e+09 | H24: =$G$24/($I$5*1000) -> 205.18756 | I24: =($G$24/$I$9)/$I$5 -> 13.198736
D25: ● | E25: Amortisation of leasehold land Cost | F25: =F4 -> 1 | G25: =AMOR!$G$20*$F$25 -> 1.0484098e+09 | H25: =$G$25/($I$5*1000) -> 51.449686 | I25: =($G$25/$I$9)/$I$5 -> 3.3095128
G26: =SUM($G$22:$G$25) -> 8.8503165e+09 | H26: =SUM($H$22:$H$25) -> 434.32063 | I26: =SUM($I$22:$I$25) -> 27.937774 | K26: =I26+I14 -> 51.114957
B28: Total Production Cost | G28: =$G$26+$G$20+$G$14 -> 2.2247538e+10 | H28: =$H$26+$H$20+$H$14 -> 1087.2347 | I28: =$I$26+$I$20+$I$14 -> 69.936622

Sheet Convert Gas
B3: CONVERT PEMAKAIAN GAS HP BOILER & MP BOILER
D4: 2024
C5: HP BOILER | F5: TOTAL CORRECTED VOLUME (Sm3) | K5: ENERGY MP BOILER (MMBTU) | L5: TOTAL GAS CONSUMPTION (MMBTU) | M5: PERCENTAGE
C6: UNCORRECTED VOLUME (UV) (m3) | D6: PRESS. Bar | E6: CORRECTED VOLUME (CV) (Sm3) | G6: Convert Sm3 to SCF | H6: VOLUME (MSCF) | I6: HEATING VALUE (BTU / SCF) | J6: ENERGY HP BOILER (MMBTU) | M6: HP Boiler | N6: MP Boiler
C7: 1 | D7: 2 | E7: 3 = 1 x 2 | F7: 4 = 3 | G7: 5 | H7: 6 = (4 x 5) / 1000 | I7: 7 | J7: 8 = (6 x 7) / 1000 | K7: 9 = 10 - 8 | L7: 10 | M7: 11 = 8 / 10 | N7: 12 = 9 / 10
B8: 1 | C8: 988.4 | D8: 5 | E8: =C8*D8 -> 4942 | F8: =E8 -> 4942 | G8: 35.314667 | H8: =(F8*G8)/1000 -> 174.52508 | I8: 1038.4131 | J8: =(H8*I8)/1000 -> 181.22913 | K8: =L8-J8 -> -181.22913 | M8: =(J8/L8) -> #DIV/0! | N8: =K8/L8 -> #DIV/0!
B9: =B8+1 -> 2 | C9: 872.9 | D9: 5 | E9: =C9*D9 -> 4364.5 | F9: =E9 -> 4364.5 | G9: 35.314667 | H9: =(F9*G9)/1000 -> 154.13086 | I9: 1044.2698 | J9: =(H9*I9)/1000 -> 160.9542 | K9: =L9-J9 -> -160.9542 | M9: =(J9/L9) -> #DIV/0! | N9: =K9/L9 -> #DIV/0!
B10: =B9+1 -> 3 | C10: 816.9 | D10: 5 | E10: =C10*D10 -> 4084.5 | F10: =E10 -> 4084.5 | G10: 35.314667 | H10: =(F10*G10)/1000 -> 144.24276 | I10: 1044.7709 | J10: =(H10*I10)/1000 -> 150.70063 | K10: =L10-J10 -> -150.70063 | M10: =(J10/L10) -> #DIV/0! | N10: =K10/L10 -> #DIV/0!
B11: =B10+1 -> 4 | C11: 896.2 | D11: 5 | E11: =C11*D11 -> 4481 | F11: =E11 -> 4481 | G11: 35.314667 | H11: =(F11*G11)/1000 -> 158.24502 | I11: 1043.9567 | J11: =(H11*I11)/1000 -> 165.20095 | K11: =L11-J11 -> -165.20095 | M11: =(J11/L11) -> #DIV/0! | N11: =K11/L11 -> #DIV/0!
B12: =B11+1 -> 5 | C12: 891.4 | D12: 5 | E12: =C12*D12 -> 4457 | F12: =E12 -> 4457 | G12: 35.314667 | H12: =(F12*G12)/1000 -> 157.39747 | I12: 1044.7373 | J12: =(H12*I12)/1000 -> 164.43901 | K12: =L12-J12 -> -164.43901 | M12: =(J12/L12) -> #DIV/0! | N12: =K12/L12 -> #DIV/0!
B13: =B12+1 -> 6 | C13: 796.1 | D13: 5 | E13: =C13*D13 -> 3980.5 | F13: =E13 -> 3980.5 | G13: 35.314667 | H13: =(F13*G13)/1000 -> 140.57003 | I13: 1044.793 | J13: =(H13*I13)/1000 -> 146.86659 | K13: =L13-J13 -> -146.86659 | M13: =(J13/L13) -> #DIV/0! | N13: =K13/L13 -> #DIV/0!
B14: =B13+1 -> 7 | C14: 738.6 | D14: 5 | E14: =C14*D14 -> 3693 | F14: =E14 -> 3693 | G14: 35.314667 | H14: =(F14*G14)/1000 -> 130.41707 | I14: 1045.6588 | J14: =(H14*I14)/1000 -> 136.37175 | K14: =L14-J14 -> -136.37175 | M14: =(J14/L14) -> #DIV/0! | N14: =K14/L14 -> #DIV/0!
B15: =B14+1 -> 8 | C15: 777 | D15: 5 | E15: =C15*D15 -> 3885 | F15: =E15 -> 3885 | G15: 35.314667 | H15: =(F15*G15)/1000 -> 137.19748 | I15: 1045.501 | J15: =(H15*I15)/1000 -> 143.4401 | K15: =L15-J15 -> -143.4401 | M15: =(J15/L15) -> #DIV/0! | N15: =K15/L15 -> #DIV/0!
B16: =B15+1 -> 9 | C16: 825.1 | D16: 5 | E16: =C16*D16 -> 4125.5 | F16: =E16 -> 4125.5 | G16: 35.314667 | H16: =(F16*G16)/1000 -> 145.69066 | I16: 1046.5619 | J16: =(H16*I16)/1000 -> 152.47429 | K16: =L16-J16 -> -152.47429 | M16: =(J16/L16) -> #DIV/0! | N16: =K16/L16 -> #DIV/0!
B17: =B16+1 -> 10 | C17: 965.8 | D17: 5 | E17: =C17*D17 -> 4829 | F17: =E17 -> 4829 | G17: 35.314667 | H17: =(F17*G17)/1000 -> 170.53453 | I17: 1045.8094 | J17: =(H17*I17)/1000 -> 178.34662 | K17: =L17-J17 -> -178.34662 | M17: =(J17/L17) -> #DIV/0! | N17: =K17/L17 -> #DIV/0!
B18: =B17+1 -> 11 | C18: 909.1 | D18: 5 | E18: =C18*D18 -> 4545.5 | F18: =E18 -> 4545.5 | G18: 35.314667 | H18: =(F18*G18)/1000 -> 160.52282 | I18: 1047.8197 | J18: =(H18*I18)/1000 -> 168.19897 | K18: =L18-J18 -> -168.19897 | M18: =(J18/L18) -> #DIV/0! | N18: =K18/L18 -> #DIV/0!
B19: =B18+1 -> 12 | C19: 861.1 | D19: 5 | E19: =C19*D19 -> 4305.5 | F19: =E19 -> 4305.5 | G19: 35.314667 | H19: =(F19*G19)/1000 -> 152.0473 | I19: 1047.0739 | J19: =(H19*I19)/1000 -> 159.20476 | K19: =L19-J19 -> -159.20476 | M19: =(J19/L19) -> #DIV/0! | N19: =K19/L19 -> #DIV/0!
B20: =B19+1 -> 13 | C20: 908 | D20: 5 | E20: =C20*D20 -> 4540 | F20: =E20 -> 4540 | G20: 35.314667 | H20: =(F20*G20)/1000 -> 160.32859 | I20: 1047.4429 | J20: =(H20*I20)/1000 -> 167.93504 | K20: =L20-J20 -> -167.93504 | M20: =(J20/L20) -> #DIV/0! | N20: =K20/L20 -> #DIV/0!
... B37: =B36+1 -> 30 | C37: 0 | D37: 5 | E37: =C37*D37 -> 0 | F37: =E37 -> 0 | G37: 51.314667 | H37: =(F37*G37)/1000 -> 0 | I37: 1044.8302 | J37: =(H37*I37)/1000 -> 0 | K37: =L37-J37 -> 0 | M37: =(J37/L37) -> #DIV/0! | N37: =K37/L37 -> #DIV/0!
B38: Average | F38: =AVERAGE(F8:F37) -> 3429.7333 | H38: =AVERAGE(H8:H37) -> 127.60446 | I38: =AVERAGE(I8:I37) -> 1045.774 | J38: =AVERAGE(J8:J37) -> 133.48926 | K38: =AVERAGE(K8:K37) -> -133.48926 | L38: =AVERAGE(L8:L37) -> #DIV/0! | M38: =AVERAGE(M8:M37) -> #DIV/0! | N38: =AVERAGE(N8:N37) -> #DIV/0!
B39: TOTAL | C39: =SUM(C8:C37) -> 20578.4 | E39: =SUM(E8:E37) -> 102892 | F39: =SUM(F8:F37) -> 102892 | H39: =SUM(H8:H37) -> 3828.1337 | J39: =SUM(J8:J37) -> 4004.6778
B40: Koreksi
B41: Total Setelah Koreksi | H41: =H39+H40 -> 3828.1337 | J41: =J39+J40 -> 4004.6778
C43: CONVERT HP Boiler from Utility
C44: =C39 -> 20578.4 | D44: m3 | F44: =C39*5 -> 102892 | G44: 9983.7
C45: 5 | D45: bar | F45: 21286.9 | G45: =G44-C39 -> -10594.7
C46: =C44*C45 -> 102892 | D46: Sm3 | F46: =F44/F45 -> 4.8335831
C47: =G37 -> 51.314667 | D47: Scf
C48: =(C46*C47)/1000 -> 5279.8687 | D48: Volume (MSCF)
C49: =I38 -> 1045.774 | D49: Heating Value
C50: =(C48*C49)/1000 -> 5521.5494 | D50: Energy (mmbtu)

Sheet OIP Refinery
B2: Oil In Plant Refinery
B4: No | C4: Tanggal | D4: Opening Stock | E4: Closing Stock | F4: Closing Stock | G4: Selisih OIP Consume
B5: 1 | C5: 45597 | D5: =265930+10000 -> 275930 | E5: 275524 | F5: 278115 | G5: =E5-D5 -> -406
B6: =B5+1 -> 2 | C6: 45598 | D6: =E5 -> 275524 | E6: 269177 | F6: 218067 | G6: =E6-D6 -> -6347
B7: =B6+1 -> 3 | C7: 45599 | D7: =E6 -> 269177 | E7: 272218 | F7: 257614 | G7: =E7-D7 -> 3041
B8: =B7+1 -> 4 | C8: 45600 | D8: =E7 -> 272218 | E8: 268491 | F8: 246851 | G8: =E8-D8 -> -3727
B9: =B8+1 -> 5 | C9: 45601 | D9: =E8 -> 268491 | E9: 272358 | F9: 255653 | G9: =E9-D9 -> 3867
B10: =B9+1 -> 6 | C10: 45602 | D10: =E9 -> 272358 | E10: 277030 | F10: 258450 | G10: =E10-D10 -> 4672
B11: =B10+1 -> 7 | C11: 45603 | D11: =E10 -> 277030 | E11: 273046 | F11: 238552 | G11: =E11-D11 -> -3984
B12: =B11+1 -> 8 | C12: 45604 | D12: =E11 -> 273046 | E12: 223357 | F12: 283505 | G12: =E12-D12 -> -49689
B13: =B12+1 -> 9 | C13: 45605 | D13: =E12 -> 223357 | E13: 265940 | F13: 269320 | G13: =E13-D13 -> 42583
B14: =B13+1 -> 10 | C14: 45606 | D14: =E13 -> 265940 | E14: 275176 | F14: 281809 | G14: =E14-D14 -> 9236
B15: =B14+1 -> 11 | C15: 45607 | D15: =E14 -> 275176 | E15: 287402 | F15: 267958 | G15: =E15-D15 -> 12226
B16: =B15+1 -> 12 | C16: 45608 | D16: =E15 -> 287402 | E16: =260290+30000 -> 290290 | F16: 267268 | G16: =E16-D16 -> 2888
B17: =B16+1 -> 13 | C17: 45609 | D17: =E16 -> 290290 | E17: 279261 | F17: 285895 | G17: =E17-D17 -> -11029
B18: =B17+1 -> 14 | C18: 45610 | D18: =E17 -> 279261 | E18: 293676 | F18: =286934-27000 -> 259934 | G18: =E18-D18 -> 14415
B19: =B18+1 -> 15 | C19: 45611 | D19: =E18 -> 293676 | E19: =262861+7380 -> 270241 | F19: =259375-30000 -> 229375 | G19: =E19-D19 -> -23435
B20: =B19+1 -> 16 | C20: 45612 | D20: =E19 -> 270241 | E20: 285331 | F20: 206080 | G20: =E20-D20 -> 15090
B21: =B20+1 -> 17 | C21: 45613 | D21: =E20 -> 285331 | E21: 262359 | F21: 205580 | G21: =E21-D21 -> -22972
B22: =B21+1 -> 18 | C22: 45614 | D22: =E21 -> 262359 | E22: 295153 | F22: 204650 | G22: =E22-D22 -> 32794
B23: =B22+1 -> 19 | C23: 45615 | D23: =E22 -> 295153 | E23: 274290 | F23: 204650 | G23: =E23-D23 -> -20863
B24: =B23+1 -> 20 | C24: 45616 | D24: =E23 -> 274290 | E24: 235465 | F24: =259103-20000 -> 239103 | G24: =E24-D24 -> -38825
B25: =B24+1 -> 21 | C25: 45617 | D25: =E24 -> 235465 | E25: 275615 | F25: =222878+20000 -> 242878 | G25: =E25-D25 -> 40150
B26: =B25+1 -> 22 | C26: 45618 | D26: =E25 -> 275615 | E26: 179950 | F26: =222984+20500 -> 243484 | G26: =E26-D26 -> -95665
B27: =B26+1 -> 23 | C27: 45619 | D27: =E26 -> 179950 | E27: 0 | F27: 219216 | G27: =E27-D27 -> -179950
B28: =B27+1 -> 24 | C28: 45620 | D28: =E27 -> 0 | E28: 0 | F28: 244970 | G28: =E28-D28 -> 0
B29: =B28+1 -> 25 | C29: 45621 | D29: =E28 -> 0 | E29: 0 | F29: =209886+25000 -> 234886 | G29: =E29-D29 -> 0
B30: =B29+1 -> 26 | C30: 45622 | D30: =E29 -> 0 | E30: 0 | F30: 0 | G30: =E30-D30 -> 0
B31: =B30+1 -> 27 | C31: 45623 | D31: =E30 -> 0 | E31: 0 | F31: 0 | G31: =E31-D31 -> 0
B32: =B31+1 -> 28 | C32: 45624 | D32: =E31 -> 0 | E32: 0 | F32: 0 | G32: =E32-D32 -> 0
B33: =B32+1 -> 29 | C33: 45625 | D33: =E32 -> 0 | E33: 0 | F33: 0 | G33: =E33-D33 -> 0
B34: =B33+1 -> 30 | C34: 45626 | D34: =E33 -> 0 | E34: 0 | F34: 0 | G34: =E34-D34 -> 0

Sheet OIP Fract
B2: Oil In Plant Fract
B4: No | C4: Tanggal | D4: Opening Stock | E4: Closing Stock | F4: Selisih OIP
B5: 1 | C5: 45597 | D5: 635650 | E5: 652190 | F5: =E5-D5 -> 16540
B6: =B5+1 -> 2 | C6: 45598 | D6: =E5 -> 652190 | E6: 630990 | F6: =E6-D6 -> -21200
B7: =B6+1 -> 3 | C7: 45599 | D7: =E6 -> 630990 | E7: 686700 | F7: =E7-D7 -> 55710
B8: =B7+1 -> 4 | C8: 45600 | D8: =E7 -> 686700 | E8: 612200 | F8: =E8-D8 -> -74500
B9: =B8+1 -> 5 | C9: 45601 | D9: =E8 -> 612200 | E9: 641660 | F9: =E9-D9 -> 29460
B10: =B9+1 -> 6 | C10: 45602 | D10: =E9 -> 641660 | E10: 640430 | F10: =E10-D10 -> -1230
B11: =B10+1 -> 7 | C11: 45603 | D11: =E10 -> 640430 | E11: 640290 | F11: =E11-D11 -> -140
B12: =B11+1 -> 8 | C12: 45604 | D12: =E11 -> 640290 | E12: 513970 | F12: =E12-D12 -> -126320
B13: =B12+1 -> 9 | C13: 45605 | D13: =E12 -> 513970 | E13: 590370 | F13: =E13-D13 -> 76400
B14: =B13+1 -> 10 | C14: 45606 | D14: =E13 -> 590370 | E14: 422220 | F14: =E14-D14 -> -168150
B15: =B14+1 -> 11 | C15: 45607 | D15: =E14 -> 422220 | E15: 332600 | F15: =E15-D15 -> -89620
B16: =B15+1 -> 12 | C16: 45608 | D16: =E15 -> 332600 | E16: 419490 | F16: =E16-D16 -> 86890
B17: =B16+1 -> 13 | C17: 45609 | D17: =E16 -> 419490 | E17: 432330 | F17: =E17-D17 -> 12840
... B34: =B33+1 -> 30 | C34: 45626 | D34: =E33 -> 0 | E34: 0 | F34: =E34-D34 -> 0

Sheet 2024
C2: PRODUCTION REPORT 2024
F3: ok | G3: ok | H3: ok | I3: ok | J3: OK | K3: OK | L3: ok | M3: ok | N3: ok
B4: No | C4: ITEM | D4: Budget / Norma | E4: UoM | F4: MONTHLY REPORT | S4: Yearly Report | T4: Yearly Report RKAP (Budget) | U4: Yearly Report RKAP
F5: JANUARI | G5: FEBRUARI | H5: MARET | I5: APRIL | J5: MEI | K5: JUNI | L5: JULI | M5: AGUSTUS | N5: SEPTEMBER | O5: OKTOBER | P5: NOVEMBER | Q5: DESEMBER | S5: TOTAL (Kg) | T5: TOTAL (Kg) | U5: TOTAL (%)
B6: 1 | C6: PRODUCTION | S6: Production | T6: Production | U6: Production | DF6: 29 | DG6: 30 | DH6: 31
C7: Refinery | S7: Refinery | T7: Refinery | U7: Refinery | DD7: CPO Olah | DE7: Kg | DF7: 1971320 | DG7: 2015120 | DH7: 2015230 | AIT7: Sounding | AIU7: Production | AIV7: Diff
C8: Running Days | E8: Day | F8: 18 | G8: 11 | H8: 27 | I8: 22 | J8: 27 | K8: 18 | L8: 22 | M8: 28 | N8: 27 | O8: 28 | P8: ='November 2024'!AL6 -> 22 | Q8: ='[24]Desember 24'!AL9 -> 0 | S8: =SUM(F8:Q8) -> 250 | T8: 231 | U8: =S8/T8*100 -> 108.22511 | OQ8: Poram | AED8: 14 Juni | AEE8: 15 Juni | AIS8: CPO | AIT8: 11008948 | AIU8: =S11 -> 180889691 | AIV8: =AIT8-AIU8 -> -169880743
C9: Ratio Run CPO | F9: 17.46 | G9: ='[24]Februari 24'!AL10 -> 17.224767 | H9: ='[24]Maret 24'!AL10 -> 4.5497713 | I9: ='[25]April - 24'!$AK$11 -> 0 | J9: ='[26]Mei - 24'!$AL$11 -> 0 | K9: ='[27]Juni - 24'!$AL$11 -> 13.078035 | L9: ='[28]Juli - 2024 ( Revisi )'!$AL$8 -> 23.454544 | M9: ='[29]Agustus - 2024'!$AN$8 -> 33.834848 | N9: ='[30]September - 2024'!$AM$8 -> 40.48197 | O9: ='[31]Oktober- 2024'!$AM$8 -> 37.300669 | P9: ='November 2024'!AL8 -> 42.102025 | Q9: ='[24]Desember 24'!AL10 -> 0
C10: Utilitas CPO | F10: =F11/F14*100 -> 18.288923 | G10: =G11/G14*100 -> 18.044994 | H10: =H11/H14*100 -> 43.450394 | I10: =I11/I14*100 -> 24.340125 | J10: =J11/J14*100 -> 42.665478 | K10: =K11/K14*100 -> 24.530983 | L10: =L11/L14*100 -> 43.994607 | M10: =M11/M14*100 -> 63.465348 | ... Q10: =Q11/Q14*100 -> #DIV/0! | S10: =AVERAGE(F10:P10) -> 42.320696
C11: CPO Consume Total | D11: 701400000 | E11: Kg | F11: 11906089 | G11: 11747291 | H11: 16983890 | I11: 8849826 | J11: 15512741 | K11: 8919220 | L11: 15995999 | M11: 23075366 | N11: 24046290 | O11: 23475599 | P11: ='November 2024'!AL9 -> 20377380 | Q11: ='[24]Desember 24'!AL11 -> 0 | S11: =SUM(F11:P11) -> 180889691 | T11: 421374000 | U11: =S11/T11 -> 0.42928536 | AW11: =S11/D11 -> 0.25789805 | DD11: HP Boiler | DE11: mmbtu | DF11: 251.19642 | DG11: 257.91391 | DH11: 251.51265 | ON11: 26946.108 | OO11: 17383.234 | OQ11: RBDPO Olah | AED11: =35.8500000000058*1000 -> 35850 | AIS11: PFAD | AIT11: 566885 | AIU11: =S20 -> 7877801 | AIV11: =AIT11-AIU11 -> -7310916
C12: CPO Consume Poram | E12: Kg | F12: 10284033 | G12: 10885811 | H12: 16067553 | I12: 8849826 | J12: 15512741 | K12: 8919220 | L12: 15995999 | M12: 22890671 | N12: =N11-N13 -> 24046290 | O12: 23419757 | P12: ='November 2024'!AL9 -> 20377380 | Q12: ='[24]Desember 24'!AL12 -> #DIV/0! | S12: =SUM(F12:P12) -> 1.7724928e+08
C13: CPO Consume Brand | E13: Kg | F13: 1622056.5 | G13: 861480.39 | H13: 916336.51 | I13: 0 | J13: 0 | K13: 0 | L13: 0 | M13: 184695 | N13: 0 | O13: 55842.105 | P13: 0 | Q13: ='[24]Desember 24'!AL13 -> #DIV/0! | S13: =SUM(F13:P13) -> 3640410.5 | AW13: =AV13/P13 -> #DIV/0!
C14: Budget CPO Olah | E14: Kg | F14: 65100000 | G14: 65100000 | H14: 39088000 | I14: 36359000 | J14: 36359000 | K14: 36359000 | L14: 36359000 | M14: 36359000 | N14: 36359000 | O14: ='[31]Oktober- 2024'!$E$9 -> 36359000 | P14: ='November 2024'!E9 -> 36359000 | S14: =SUM(F14:P14) -> 460160000
C15: - FFA | D15: 5 | E15: % | F15: 4.38 | G15: 4.5590909 | H15: 4.135 | I15: 4.11 | J15: 3.859375 | K15: 4.248125 | L15: 3.8848485 | M15: 3.9614881 | N15: 3.6441975 | O15: ='[31]Oktober- 2024'!$AM$13 -> 3.7106548 | P15: ='November 2024'!AL13 -> 3.8712121 | Q15: ='[24]Desember 24'!AL14 -> #DIV/0! | S15: =AVERAGE(F15:P15) -> 4.0330902 | T15: =AVERAGE(G15:R15) -> #DIV/0! | U15: =AVERAGE(H15:S15) -> #DIV/0! | DD15: Steam Ref | DE15: Kg | DF15: 182230 | DG15: 190070 | DH15: 197800 | ON15: =S11/1000 -> 180889.69 | OO15: =(S25+S48+S34)/1000 -> 53829.832 | OQ15: =SUM(OQ16:OQ17) -> #REF! | AGU15: 2000
C16: - Moist & Impurities | D16: 0.5 | E16: % | F16: 0.42 | G16: 0.43545455 | H16: 0.42375 | I16: 0.42 | J16: 0.431875 | K16: 0.45375 | L16: 0.41795455 | M16: 0.43083333 | N16: 0.41401235 | O16: ='[31]Oktober- 2024'!$AM$14 -> 0.37321429 | P16: ='November 2024'!AL14 -> 0.43416667 | Q16: ='[24]Desember 24'!AL15 -> #DIV/0! | S16: =AVERAGE(F16:P16) -> 0.42318279 | T16: =AVERAGE(G16:R16) -> #DIV/0! | U16: =AVERAGE(H16:S16) -> #DIV/0! | DE16: Kg/MT | DF16: =DF15/(DF7/1000) -> 92.440598 | DG16: =DG15/(DG7/1000) -> 94.321926 | DH16: =DH15/(DH7/1000) -> 98.152568 | OQ16: =#REF!/1000 -> #REF! | OR16: =OQ16/OQ15*100 -> #REF! | AGT16: 0.942 | AGU16: =AGT16*AGU15 -> 1884 | AGV16: Refinery | AIS16: Olein IV 56 | AIT16: 9594130 | AIU16: =S26 -> 41876768 | AIV16: =AIT16-AIU16 -> -32282638
C17: - DOBI | D17: 2,20 Min | E17: % | F17: 2.21 | G17: 2.2127273 | H17: 2.2104167 | I17: 2.21 | J17: 2.21 | K17: 2.21 | L17: 2.1131818 | M17: 2.2129286 | N17: 2.27 | O17: ='[31]Oktober- 2024'!$AM$15 -> 19.65575 | P17: ='November 2024'!AL15 -> 2.015 | Q17: ='[24]Desember 24'!AL16 -> #DIV/0! | S17: =AVERAGE(F17:P17) -> 3.7754549 | T17: =AVERAGE(G17:R17) -> #DIV/0! | U17: =AVERAGE(H17:S17) -> #DIV/0! | ON17: =SUM(ON15:ON16) -> 180889.69 | OO17: =SUM(OO15:OO16) -> 53829.832 | OQ17: =#REF!/1000 -> #REF! | OR17: =OQ17/OQ15*100 -> #REF! | AGT17: 0.05 | AGU17: =AGT17*AGU15 -> 100 | AIS17: Stearin | AIT17: 2161151 | AIU17: =S27 -> 8544076 | AIV17: =AIT17-AIU17 -> -6382925
C18: Product | S18: Product | T18: Product | U18: Product | ON18: =ON17/ON11*100 -> 671.30174 | OO18: =OO17/OO11*100 -> 309.66524 | AEF18: Product OIP | AEP18: Juni | AEQ18: Sisa Product OIP
C19: RbdPO | D19: =D56%*D11 -> 660718800 | E19: Kg | F19: 11255730 | G19: 11075536 | H19: 16117978 | I19: 8393524 | J19: 14773343 | K19: 8432668 | L19: 14396709 | M19: 22151806 | N19: 22783491 | O19: 22361608 | P19: ='November 2024'!AL18 -> 19958156 | Q19: ='[24]Desember 24'!AL18 -> 0 | S19: =SUM(F19:P19) -> 1.7170055e+08 | T19: 399336000 | U19: =S19/T19*100 -> 42.996512 | Y19: =S19/11 -> 15609141 | Z19: RBDPO | AW19: =AW20/D19 -> 0.26115599 | DD19: Tahun 2021 | AED19: 136360 | AEE19: 109340 | AEF19: =SUM(AED19:AEE19) -> 245700 | AEP19: 34157.88 | AEQ19: =AEF19-AEP19 -> 211542.12 | AGU19: =AGU16 -> 1884
C20: PFAD | D20: =D57%*D11 -> 35070000 | E20: Kg | F20: 568791 | G20: 594383 | H20: 753150 | I20: 419494 | J20: 630157 | K20: 432588 | L20: 713632 | M20: 947460 | N20: 998518 | O20: 949170 | P20: ='November 2024'!AL19 -> 870458 | Q20: ='[24]Desember 24'!AL19 -> 0 | S20: =SUM(F20:P20) -> 7877801 | T20: 19024000 | U20: =S20/T20*100 -> 41.409803 | Y20: =S20/11 -> 716163.73 | Z20: PFAD | AW20: =S25+S29+S34+S48+S38 -> 172550675 | DD20: Items | DF20: Agustus | DG20: Oktober | ON20: =ON11-ON17 -> -153943.58 | OO20: =OO11-OO17 -> -36446.598 | OQ20: Olein IV 58 | OR20: 0 | PD20: 564.70507 | PE20: =OR20/PD20*100 -> 0 | AED20: 13800 | AEE20: 2800 | AEF20: =SUM(AED20:AEE20) -> 16600 | AEP20: 1469.85 | AEQ20: =AEF20-AEP20 -> 15130.15 | AGT20: 0.75 | AGU20: =AGT20*AGU19 -> 1413
C21: Fractionation
C22: Total Filling Crystalizer ( Feed ) | D22: =399289.3*1000 -> 399289300 | E22: Kg | F22: =F23 -> 13630524 | G22: =G23 -> 8090413 | H22: =H23 -> 16273198 | I22: =I23 -> 9676196 | J22: =J23 -> 14816948 | K22: =K23 -> 7764784 | L22: =L23 -> 11846463 | M22: =M23 -> 24206356 | N22: 22592969 | O22: 20122000 | P22: ='November 2024'!AL23 -> 21737836 | S22: =SUM(F22:P22) -> 170757687
C23: Total Proses RBDPO | E23: Kg | F23: =SUM(F25,F29,F34,F38,F48) -> 13630524 | G23: =SUM(G25,G29,G34,G38,G48) -> 8090413 | H23: =SUM(H25,H29,H34,H38,H48) -> 16273198 | I23: =SUM(I25,I29,I34,I38,I48) -> 9676196 | J23: =SUM(J25,J29,J34,J38,J48) -> 14816948 | K23: =SUM(K25,K29,K34,K38,K48) -> 7764784 | L23: =SUM(L25,L29,L34,L38,L48) -> 11846463 | M23: =SUM(M25,M29,M34,M38,M48) -> 24206356 | N23: =SUM(N25,N29,N34,N38,N48) -> 23189025 | O23: ='[31]Oktober- 2024'!$AM$25 -> 18946789 | P23: ='November 2024'!AL25 -> 22537659 | S23: =SUM(F23:P23) -> 170978355
C24: Fractionation OLEIN IV 56 | S24: Olein IV 56 | T24: Olein IV 56 | U24: Olein IV 56 | DF24: 24 | DG24: 2 | DH24: 3 | OQ24: Olein IV 60 | OR24: =80.53776+PE34 -> 120.78492 | PD24: 4695.7554 | PE24: =OR24/PD24*100 -> 2.5722149 | AGT24: 0.25 | AGU24: =AGT24*AGU19 -> 471
C25: RBDPO Consume | D25: =SUM(D26:D27) -> 0 | E25: Kg | F25: 2379082 | G25: 50570 | H25: 1699905 | I25: ='[24]April 24'!AL21 -> 0 | J25: 0 | K25: 0 | L25: 160400 | M25: 14223412 | N25: 16566545 | O25: 9370708 | P25: ='November 2024'!AL28 -> 5970222 | Q25: =Q26+Q27 -> 0 | S25: =S26+S27 -> 50420844 | T25: =T26+T27 -> 87311000 | U25: =S25/T25*100 -> 57.748559 | DD25: CPO Olah | DE25: Kg | DF25: 2000530 | DG25: 2005167 | DH25: 2025879 | AED25: =95.28%*AED11 -> 34157.88 | AEF25: =AED19-AEP19 -> 102202.12 | AIP25: CPO Feed - Sounding
C26: OLEIN IV 56 | E26: Kg | F26: 1982807 | G26: 42320 | H26: 1394887 | I26: ='[24]April 24'!AL22 -> 0 | J26: 0 | K26: 0 | L26: 135300 | M26: 11670227 | N26: 13789795 | O26: 7870678 | P26: ='November 2024'!AL29 -> 4990754 | Q26: ='[24]Desember 24'!AL22 -> 0 | S26: =SUM(F26:P26) -> 41876768 | T26: 71627000 | U26: =S26/T26*100 -> 58.465059 | DD26: HP Boiler | DE26: mmbtu | DF26: 255.53619 | DG26: 255.09239 | DH26: 260.82455 | ON26: =#REF!/1000 -> #REF! | OQ26: INL 900 ml | OR26: 0 | PD26: 9.75348 | PE26: =(OR26*PD26)/1000 -> 0 | AED26: =4.1%*AED11 -> 1469.85 | AEF26: =AED20-AEP20 -> 12330.15
C27: STEARIN | E27: Kg | F27: 396275 | G27: 8250 | H27: 305018 | I27: ='[24]April 24'!AL23 -> 0 | J27: 0 | K27: 0 | L27: 25100 | M27: 2553185 | N27: 2776750 | O27: 1500030 | P27: ='November 2024'!AL30 -> 979468 | Q27: ='[24]Desember 24'!AL23 -> 0 | S27: =SUM(F27:P27) -> 8544076 | T27: 15684000 | U27: =S27/T27*100 -> 54.476384 | DD27: Steam Ref | DE27: Kg | DF27: 146000 | DG27: 151100 | DH27: 152900 | ON27: 1796 | OQ27: Salvaco 1L | OR27: 1262 | PD27: 10.86 | PE27: =(OR27*PD27)/1000 -> 13.70532 | AIP27: Report Prod
C28: Fractionation OLEIN IV 57 ( Bulk ) | S28: Olein IV 57 ( Bulk ) | T28: Olein IV 57 ( Bulk ) | U28: Olein IV 57 ( Bulk )
C29: RBDPO Consume | E29: Kg | F29: 2827867 | G29: 0 | H29: 0 | I29: 60502 | J29: 0 | K29: 0 | L29: 0 | M29: 0 | N29: 0 | O29: ='[31]Oktober- 2024'!$AM$32 -> 0 | P29: ='November 2024'!AL32 -> 0 | Q29: =Q30+Q31 -> 0 | S29: =S30+S31 -> 2888369 | T29: =T30+T31 -> 5121000 | U29: =S29/T29*100 -> 56.402441 | W29: =S26+S30+S35+S39+S50 -> 129064029 | Y29: =W29/11 -> 11733094 | Z29: Olein | AW29: =S29+S34 -> 4098296
C30: OLEIN IV 57 | E30: Kg | F30: 2230587 | G30: 0 | H30: 0 | I30: 45478 | J30: 0 | K30: 0 | L30: 0 | M30: 0 | N30: 0 | O30: ='[31]Oktober- 2024'!$AM$33 -> 0 | P30: ='November 2024'!AL33 -> 0 | Q30: ='[24]Desember 24'!AL26 -> 0 | S30: =SUM(F30:P30) -> 2276065 | T30: 3934000 | U30: =S30/T30*100 -> 57.856253 | AW30: =S30+S35 -> 3177959
C31: STEARIN | E31: Kg | F31: 597280 | G31: 0 | H31: 0 | I31: 15024 | J31: 0 | K31: 0 | L31: 0 | M31: 0 | N31: 0 | O31: ='[31]Oktober- 2024'!$AM$34 -> 0 | P31: ='November 2024'!AL34 -> 0 | Q31: ='[24]Desember 24'!AL27 -> 0 | S31: =SUM(F31:P31) -> 612304 | T31: 1187000 | U31: =S31/T31*100 -> 51.584162 | W31: =S27+S31+S36+S40+S51 -> 43486646 | Y31: =W31/11 -> 3953331.5 | Z31: stearin | AW31: =S31+S36 -> 920337
C32: Fractionation OLEIN IV 57 ( Retail ) | S32: Olein IV 57 ( Retail ) | T32: Olein IV 57 ( Retail ) | U32: Olein IV 57 ( Retail ) | DE32: Kg/MT | DF32: =DF27/(DF25/1000) -> 72.98066 | DG32: =DG27/(DG25/1000) -> 75.35532 | DH32: =DH27/(DH25/1000) -> 75.473412 | ON32: =ON26/ON27*100 -> #REF! | OQ32: Salvaco 2L | OR32: 2444 | PD32: 10.86 | PE32: =(OR32*PD32)/1000 -> 26.54184 | AIP32: Diff
C33: CPO Consume | E33: Kg | F33: 0 | G33: 440053.75 | H33: 793075.77 | I33: ='[24]April 24'!AL29 -> 0 | J33: 0 | K33: 0 | L33: 0 | M33: 0 | N33: 0 | O33: ='[31]Oktober- 2024'!$AM$36 -> 0 | P33: ='November 2024'!AL36 -> 0 | Q33: ='[24]Desember 24'!AL29 -> 0 | S33: =SUM(F33:P33) -> 1233129.5 | T33: =T34/T56% -> 32338304 | U33: =(S33/T33)*100 -> 3.8132164 | DE33: Kg/MT | DF33: =DF27/(DF20/1000) -> #VALUE! | DG33: =DH27/(DG20/1000) -> #VALUE! | DH33: =#REF!/(DH20/1000) -> #REF!
C34: RBDPO Brand Consume | D34: =SUM(D35:D36) -> 0 | E34: Kg | F34: 0 | G34: 417044 | H34: 751933 | I34: =I35+I36 -> 0 | J34: 0 | K34: 0 | L34: 0 | M34: 0 | N34: 40950 | O34: ='[31]Oktober- 2024'!$AM$37 -> 0 | P34: ='November 2024'!AL37 -> 0 | Q34: =Q35+Q36 -> 0 | S34: =S35+S36 -> 1209927 | T34: =T35+T36 -> 30647000 | U34: =(S34/T34)*100 -> 3.947946 | PE34: =SUM(PE27:PE32) -> 40.24716
C35: OLEIN IV 57 ( Retail ) | E35: Kg | F35: 0 | G35: 327115 | H35: 543979 | I35: ='[24]April 24'!AL31 -> 0 | J35: 0 | K35: 0 | L35: 0 | M35: 0 | N35: 30800 | O35: ='[31]Oktober- 2024'!$AM$38 -> 0 | P35: ='November 2024'!AL38 -> 0 | Q35: ='[24]Desember 24'!AL31 -> 0 | S35: =SUM(F35:P35) -> 901894 | T35: 23002000 | U35: =S35/T35*100 -> 3.9209373
C36: STEARIN | E36: Kg | F36: 0 | G36: 89929 | H36: 207954 | I36: ='[24]April 24'!AL32 -> 0 | J36: 0 | K36: 0 | L36: 0 | M36: 0 | N36: 10150 | O36: ='[31]Oktober- 2024'!$AM$39 -> 0 | P36: ='November 2024'!AL39 -> 0 | Q36: ='[24]Desember 24'!AL32 -> 0 | S36: =SUM(F36:P36) -> 308033 | T36: 7645000 | U36: =S36/T36*100 -> 4.0292086
C37: Fractionation OLEIN IV 58 ( BULK ) | S37: Olein IV 58 | T37: Olein IV 58 | U37: Olein IV 58
C38: RBDPO Consume | E38: Kg | F38: 6885934 | G38: 7224129 | H38: 13704210 | I38: 9615694 | J38: 14816948 | K38: 7764784 | L38: 11686063 | M38: 9837344 | N38: 6581530 | O38: 10628161 | P38: ='November 2024'!AL41 -> 16567437 | Q38: =Q39+Q40 -> 0 | S38: =S39+S40 -> 115832474 | T38: =T39+T40 -> 249961000 | U38: =S38/T38*100 -> 46.340219
C39: OLEIN IV 58 ( Bulk ) | E39: Kg | F39: 4847146 | G39: 5178274 | H39: 8651956 | I39: 6783108 | J39: 10840932 | K39: 5498655 | L39: 8627479 | M39: 6991936 | N39: 4788598 | O39: 7897790 | P39: ='November 2024'!AL42 -> 12573252 | Q39: ='[24]Desember 24'!AL35 -> 0 | S39: =SUM(F39:P39) -> 82679126 | T39: 175000000 | U39: =S39/T39*100 -> 47.245215
C40: STEARIN | E40: Kg | F40: 2038788 | G40: 2045855 | H40: 5052254 | I40: 2832586 | J40: 3976016 | K40: 2266129 | L40: 3578824 | M40: 2845408 | N40: 1792932 | O40: 2730371 | P40: ='November 2024'!AL43 -> 3994185 | Q40: ='[24]Desember 24'!AL36 -> 0 | S40: =SUM(F40:P40) -> 33153348 | T40: 74961000 | U40: =S40/T40*100 -> 44.227462
C41: Fractionation OLEIN IV 58 ( Retail )
C42: CPO Consume | E42: Kg | O42: 55842.105
C43: RBDPO Consume | E43: Kg | O43: 53050
C44: OLEIN IV 58 | E44: Kg | O44: 38000
C45: STEARIN | E45: Kg | O45: 15050
C46: Fractionation OLEIN IV 60 | S46: Olein IV 60 | T46: Olein IV 60 | U46: Olein IV 60
C47: CPO Consume | E47: Kg | F47: 1622056.5 | G47: 421426.65 | H47: 123260.75 | I47: 0 | J47: 0 | K47: 0 | L47: 0 | M47: 0 | N47: 0 | O47: ='[31]Oktober- 2024'!$AM$50 -> 0 | P47: ='November 2024'!AL50 -> 0 | S47: =SUM(F47:P47) -> 2166743.9 | T47: =T48/T56% -> 25913273 | U47: =S47/T47*100 -> 8.3615215
C48: RBDPO Brand Consume | D48: =SUM(D50:D51) -> 0 | E48: Kg | F48: 1537641 | G48: 398670 | H48: 117150 | I48: 0 | J48: 0 | K48: 0 | L48: 0 | M48: 145600 | N48: 0 | P48: ='November 2024'!AL51 -> 0 | Q48: =Q50+Q51 -> 0 | S48: =S50+S51 -> 2199061 | T48: =T50+T51 -> 24558000 | U48: =S48/T48*100 -> 8.9545606 | DF48: 2136
C49: OLEIN IV 60 Bulk | E49: Kg | F49: 0 | G49: 0 | H49: 0 | I49: 0 | J49: 0 | K49: 0 | L49: 0 | M49: 0 | N49: 0 | P49: ='November 2024'!AL52 -> 0 | Q49: ='[24]Desember 24'!AL40 -> 0 | S49: =SUM(F49:P49) -> 0 | T49: =SUM(F49:Q49) -> 0 | U49: =SUM(H49:S49) -> 0
C50: OLEIN IV 60 Salvaco | E50: Kg | F50: 923976 | G50: 248300 | H50: 70300 | I50: 0 | J50: 0 | K50: 0 | L50: 0 | M50: 87600 | N50: 0 | P50: ='November 2024'!AL53 -> 0 | Q50: ='[24]Desember 24'!AL41 -> 0 | S50: =SUM(F50:P50) -> 1330176 | T50: 14736000 | U50: =S50/T50*100 -> 9.0267101 | DF50: 1796
C51: SOFT STEARIN | E51: Kg | F51: 613665 | G51: 150370 | H51: 46850 | I51: 0 | J51: 0 | K51: 0 | L51: 0 | M51: 58000 | N51: 0 | P51: ='November 2024'!AL54 -> 0 | Q51: ='[24]Desember 24'!AL42 -> 0 | S51: =SUM(F51:P51) -> 868885 | T51: 9822000 | U51: =S51/T51*100 -> 8.8463144 | DF51: =DF48/DF50*100 -> 118.93096
C52: Ratio Run RBDPO | F52: 17.42364 | G52: 13.049053 | H52: 26.247094 | I52: 15.606768 | J52: 23.898303 | K52: 12.523845 | L52: 0 | M52: 0 | N52: 0 | O52: =(O38+O34+O29+O25)/(60000000) -> 0.33331448 | P52: =(P38+P34+P29+P25)/(60000000) -> 0.37562765 | Q52: =(Q38+Q34+Q29+Q25)/(60000000) -> 0 | S52: =+AVERAGE(F52:P52) -> 9.950695
C53: Utilitas RBDPO | F53: =(F48+F38+F34+F30+F26)/F54*100 -> 20.606822 | G53: =(G48+G38+G34+G30+G26)/G54*100 -> 13.179402 | H53: =(H48+H38+H34+H30+H26)/H54*100 -> 43.367168 | J53: =(J48+J38+J34+J30+J26)/J54*100 -> 43.260937 | K53: =(K48+K38+K34+K30+K26)/K54*100 -> 22.670784 | L53: =(L48+L38+L34+L30+L26)/L54*100 -> 34.306585 | M53: =($M$48+$M$38+$M$34+$M$30+$M$25)/$M$54*100 -> 70.248871 | N53: =($N$48+$N$38+$N$34+$N$30+$N$26)/$N$54*100 -> 59.23813 | O53: =(O48+O38+O34+O30+O26)/O54*100 -> 54.010928 | P53: =(P48+P38+P34+P30+P26)/P54*100 -> 62.563675 | Q53: =(Q48+Q38+Q34+Q30+Q26)/Q54*100 -> 0 | S53: =+AVERAGE(F53:P53) -> 42.34533
C54: Budget RBDPO | F54: 61324200 | G54: 61324200 | H54: 36820896 | I54: 34250178 | J54: 34250178 | K54: 34250178 | L54: 34458000 | M54: 34458000 | N54: 34458000 | O54: ='[27]Juni - 24'!$D$19 -> 34250178 | P54: ='November 2024'!E18 -> 34458000 | Q54: ='[27]Juni - 24'!$D$19 -> 34250178 | S54: =SUM(F54:P54) -> 434302008
C55: YIELD | S55: Yield | T55: Yield | U55: Yield | OO55: 678
C56: RBDPO | D56: 94.2 | E56: % | F56: 94.537593 | G56: 94.281618 | H56: 94.901568 | I56: 94.843944 | J56: 95.233608 | K56: 94.544904 | L56: 90.001937 | M56: 95.997637 | N56: 94.748466 | O56: =(O19/(O11))*100 -> 95.254686 | P56: ='November 2024'!I57 -> 97.399841 | Q56: =(Q19/(Q11))*100 -> #DIV/0! | S56: =(S19/(S11))*100 -> 94.92003 | T56: =(T19/(T11))*100 -> 94.769967 | OO56: 420 | OQ56: =OO56/OO55*100 -> 61.946903
C57: PFAD | D57: 5 | E57: % | F57: 4.7773118 | G57: 5.0597453 | H57: 4.4344965 | I57: 4.7401384 | J57: 4.0621899 | K57: 4.8500654 | L57: 4.4613156 | M57: 4.105937 | N57: 4.1524826 | O57: =(O20/(O11))*100 -> 4.0432195 | P57: ='November 2024'!I58 -> 4.2342505 | Q57: =(Q20/(Q11))*100 -> #DIV/0! | S57: =(S20/(S11))*100 -> 4.3550304 | T57: =(T20/(T11))*100 -> 4.5147541 | OO57: =OO55-OO56 -> 258 | OQ57: =OO57/OO55*100 -> 38.053097
C58: Olein IV 56 | D58: 82 | E58: % | F58: 83.343365 | G58: 83.68598 | H58: 82.056762 | I58: #DIV/0! | J58: #DIV/0! | K58: #DIV/0! | L58: 84.351621 | M58: 82.04942 | N58: 83.238811 | O58: =(O26/O25)*100 -> 83.992351 | P58: ='November 2024'!I59 -> #DIV/0! | Q58: =(Q26/Q25)*100 -> #DIV/0! | S58: =(S26/S25)*100 -> 83.054476 | T58: =(T26/T25)*100 -> 82.036628
C59: Stearin | D59: 18 | E59: % | F59: 16.656635 | G59: 16.31402 | H59: 17.943238 | I59: #DIV/0! | J59: #DIV/0! | K59: #DIV/0! | L59: #DIV/0! | M59: 17.95058 | N59: 16.761189 | O59: =(O27/O25)*100 -> 16.007649 | P59: ='November 2024'!I60 -> #DIV/0! | Q59: =(Q27/Q25)*100 -> #DIV/0! | S59: =(S27/S25)*100 -> 16.945524 | T59: =(T27/T25)*100 -> 17.963372
C60: Olein IV 57 ( Bulk ) | D60: 75 | E60: % | F60: 78.87878 | G60: #DIV/0! | H60: #DIV/0! | I60: 75.167763 | J60: #DIV/0! | K60: #DIV/0! | L60: #DIV/0! | M60: #DIV/0! | N60: 75.213675 | O60: =(O30/O29)*100 -> #DIV/0! | P60: ='November 2024'!I61 -> #DIV/0! | Q60: =(Q30/Q29)*100 -> #DIV/0! | S60: =(S30/S29)*100 -> 78.801047 | T60: 75
C61: Stearin | D61: 25 | E61: % | F61: 21.12122 | G61: #DIV/0! | H61: #DIV/0! | I61: 24.832237 | J61: #DIV/0! | K61: #DIV/0! | L61: #DIV/0! | M61: #DIV/0! | N61: 24.786325 | O61: =(O31/O29)*100 -> #DIV/0! | P61: ='November 2024'!I62 -> #DIV/0! | Q61: =(Q31/Q29)*100 -> #DIV/0! | S61: =(S31/S29)*100 -> 21.198953 | T61: 25
C62: Olein IV 57 ( Retail ) | D62: 75 | E62: % | F62: #DIV/0! | G62: 78.436568 | H62: 72.344079 | I62: #DIV/0! | J62: #DIV/0! | K62: #DIV/0! | L62: #DIV/0! | M62: #DIV/0! | N62: 75.213675 | O62: =O35/O34*100 -> #DIV/0! | P62: ='November 2024'!AL63 -> #DIV/0! | Q62: =Q35/Q34*100 -> #DIV/0! | S62: =(S35/S34)*100 -> 74.541191 | T62: 75
C63: Stearin | D63: 25 | E63: % | F63: #DIV/0! | G63: 21.563432 | H63: 27.655921 | I63: #DIV/0! | J63: #DIV/0! | K63: #DIV/0! | L63: #DIV/0! | M63: #DIV/0! | N63: 24.786325 | O63: =O36/O34*100 -> #DIV/0! | P63: ='November 2024'!AL64 -> #DIV/0! | Q63: =Q36/Q34*100 -> #DIV/0! | S63: =(S36/S34)*100 -> 25.458809 | T63: 25 | FM63: 95.03
C64: Olein IV 58 ( Bulk ) | D64: 70 | E64: % | F64: 70.39199 | G64: 71.680254 | H64: 63.133563 | I64: 70.542053 | J64: 73.165756 | K64: 70.815299 | L64: 70.680525 | M64: 71.075445 | N64: 72.758128 | O64: =(O39/O38)*100 -> 74.310034 | P64: ='November 2024'!AL65 -> 75.891352 | Q64: =(Q39/Q38)*100 -> #DIV/0! | S64: =(S39/S38)*100 -> 71.378192 | T64: 70
C65: Stearin | D65: 30 | E65: % | F65: 29.60801 | G65: 28.319746 | H65: 36.866437 | I65: 29.457947 | J65: 26.834244 | K65: 29.184701 | L65: 29.319475 | M65: 28.924555 | N65: 27.241872 | O65: =(O40/O38)*100 -> 25.689966 | P65: ='November 2024'!AL66 -> 24.108648 | Q65: =(Q40/Q38)*100 -> #DIV/0! | S65: =(S40/S38)*100 -> 28.621808 | T65: 30
C66: Olein IV 60 | D66: 60 | E66: % | F66: 60.090489 | G66: 62.282088 | H66: 60.008536 | I66: #DIV/0! | J66: #DIV/0! | K66: #DIV/0! | L66: #DIV/0! | M66: 60.164835 | N66: #DIV/0! | O66: =O50/O48*100 -> #DIV/0! | P66: ='November 2024'!AL69 -> #DIV/0! | Q66: =Q50/Q48*100 -> #DIV/0! | S66: =(S50/S48)*100 -> 60.488363 | T66: =T50/T48*100 -> 60.004886 | FM66: 4.23 | OQ66: =OQ67/94.2% -> 1307.8556 | OR66: MT CPO
C67: Soft Stearin | D67: 40 | E67: % | F67: 39.909511 | G67: 37.717912 | H67: 39.991464 | I67: #DIV/0! | J67: #DIV/0! | K67: #DIV/0! | L67: #DIV/0! | M67: 39.835165 | N67: #DIV/0! | O67: =O51/O48*100 -> #DIV/0! | P67: ='November 2024'!AL70 -> #DIV/0! | Q67: =Q51/Q48*100 -> #DIV/0! | S67: =(S51/S48)*100 -> 39.511637 | T67: =T51/T48*100 -> 39.995114 | FM67: =100-FM63-FM66 -> 0.74 | OQ67: =22*56 -> 1232 | OR67: MT RBDPO Brand
B68: 3 | C68: CHEMICAL CONSUMABLE | S68: Chemical | T68: Chemical | U68: Chemical | OQ68: =16.5*OQ66 -> 21579.618
C69: Bleaching Earth (BE) to Poram Spec | D69: 8 | E69: Kg | F69: 128586 | G69: 148066 | H69: 138748 | I69: 130411 | J69: 159056 | K69: 88126 | L69: 162476 | M69: 256409 | N69: 187513 | O69: 161718 | P69: ='November 2024'!AL72 -> 137569 | Q69: ='[24]Desember 24'!AL58 -> 0 | S69: =SUM(F69:P69) -> 1698678 | T69: 2767753 | U69: =S69/T69*100 -> 61.373902
E70: % | F70: 1.2503461 | G70: 1.3601743 | H70: 0.8635291 | I70: 1.4735996 | J70: 1.0253249 | K70: 0.98804604 | L70: 1.015729 | M70: 1.1201463 | N70: 0.77980013 | O70: =$O$69/($O$12)*100 -> 0.69051955 | P70: ='November 2024'!AL73 -> 0.67510642 | Q70: =Q69/(Q12)*100 -> #DIV/0! | S70: =S69/(S11)*100 -> 0.93906844 | T70: 0.8 | U70: 0 | AW70: =S70*10 -> 9.3906844 | FM70: =#REF!*10 -> #REF! | OQ70: =OQ66+(S47/1000) -> 3474.5995 | OR70: Total CPO Brand
C71: Bleaching Earth (BE) to Branded Spec | D71: 16 | E71: Kg | F71: 25923 | G71: 15015 | H71: 16441 | I71: 0 | J71: 0 | K71: 0 | L71: 0 | M71: 2930 | N71: 0 | O71: 998 | P71: ='November 2024'!AL74 -> 0 | Q71: ='[24]Desember 24'!AL60 -> 0 | S71: =SUM(F71:P71) -> 61307 | T71: 1357284 | U71: =S71/T71*100 -> 4.5168881 | OQ71: =OQ68+S71 -> 82886.618 | OR71: Total BE Brand
E72: % | F72: 1.5981564 | G72: 1.74293 | H72: 1.7942098 | I72: #DIV/0! | J72: #DIV/0! | K72: #DIV/0! | L72: #DIV/0! | M72: 1.5863992 | N72: #DIV/0! | O72: 1.7871819 | P72: ='November 2024'!AL75 -> #DIV/0! | Q72: =Q71/(Q13)*100 -> #DIV/0! | S72: =S71/(S13)*100 -> 1.6840683 | T72: 1.8 | U72: 0 | AW72: =S72*10 -> 16.840683 | OQ72: =OQ71/OQ70 -> 23.855013 | OR72: Kg/MT CPO
C73: Phosporic Acid (PA) | D73: 0.55 | E73: Kg | F73: 6664.856 | G73: 6551.932 | H73: 9270.856 | I73: 5139.122 | J73: 7872.554 | K73: 4040.198 | L73: 7823.782 | M73: 11739.24 | N73: 12499.518 | O73: 12588.966 | P73: ='November 2024'!AL76 -> 10695.718 | Q73: ='[24]Desember 24'!AL62 -> 0 | S73: =SUM(F73:P73) -> 94886.742 | T73: 252824 | U73: =SUM(H73:S73) -> 176556.7 | OQ73: 16 | OR73: Budget (Kg/MT)
E74: % | F74: 0.05597855 | G74: 0.055773982 | H74: 0.054586175 | I74: 0.058070317 | J74: 0.050748955 | K74: 0.045297661 | L74: 0.048910868 | M74: 0.050873473 | N74: 0.051981067 | O74: =O73/(O11)*100 -> 0.05362575 | P74: ='November 2024'!AL77 -> 0.05248819 | Q74: =Q73/(Q11)*100 -> #DIV/0! | S74: =S73/(S11+71450)*100 -> 0.052434872 | T74: 0.06 | U74: =U73/(U11+71450)*100 -> 247.10376 | AW74: =S74*10 -> 0.52434872 | FM74: =P74*10 -> 0.5248819 | OQ74: =OQ72-OQ73 -> 7.8550134 | OR74: Over (Kg/MT)
B75: 4 | C75: Oil Losses | D75: 0.8 | E75: % | F75: -0.68509483 | G75: -0.65863696 | H75: -0.66393506 | I75: =((SUM(I19:I20))-(SUM(I11)))/(SUM(I11))*100 -> -0.41591778 | J75: -0.70420179 | K75: -0.60503048 | L75: -5.536747 | M75: 0.10357452 | N75: -1.099051 | O75: =((SUM(O19:O20))-(SUM(O11)))/(SUM(O11))*100 -> -0.70209497 | P75: ='November 2024'!AL78 -> 2.2143867 | Q75: =((SUM(Q19:Q20))-(SUM(Q11)))/(SUM(Q11))*100 -> #DIV/0! | S75: =((SUM(S19:S20))-(SUM(S11)))/(SUM(S11))*100 -> -0.72493949 | T75: =((SUM(T19:T20))-(SUM(T11)))/(SUM(T11))*100 -> -0.71527906 | U75: =S75/T75*100 -> 101.35058
C76: % Oil Content | D76: 22 | E76: % | F76: 21.923529 | G76: 21.991 | H76: 21.974 | I76: 21.953333 | J76: 20.636667 | K76: 21.886471 | L76: 21.912727 | M76: 21.700714 | N76: 22.058148 | O76: 22.009286 | P76: ='November 2024'!AL80 -> 21.916818 | Q76: ='[24]Desember 24'!AL65 -> #DIV/0! | S76: =AVERAGE(F76:L76) -> 21.753961 | T76: 22 | U76: =AVERAGE(H76:S76) -> #DIV/0!
C77: Spent Bleaching Earth | E77: Kg | F77: 188382.83 | G77: 198944.14 | H77: 189290.23 | I77: 159040.56 | J77: 191879.86 | K77: 107413.67 | L77: 198078.92 | M77: 315617.42 | N77: 189044.92 | O77: 163995.02 | P77: ='November 2024'!AL81 -> 138939.49 | Q77: =SUM(Q69,Q71)+(Q76%*SUM(Q69,Q71)) -> #DIV/0! | S77: =SUM(S69,S71)+(S76%*SUM(S69,S71)) -> 2142851.5 | T77: 7811279 | U77: =SUM(U69,U71)+(U76%*SUM(U69,U71)) -> #DIV/0! | FZ77: =W77+400 -> 400
B78: 5 | C78: PACKAGING (Brand Salvaco) | S78: Packaging | T78: Packaging | U78: Packaging | FW78: 17292 | OX78: =#REF!-FW78 -> #REF!
C79: Olein IV 60 Received | E79: Kg | F79: ='[24]Januari 24'!AL68 -> 845858 | G79: ='[24]Februari 24'!AI68 -> #REF! | H79: ='[24]Maret 24'!AL68 -> 0 | I79: ='[24]April 24'!AL68 -> 0 | J79: ='[24]Mei 24'!AL68 -> 0 | K79: ='[24]Juny 24'!AL68 -> 0 | L79: ='[24]July 24'!AL68 -> 0 | M79: ='[24]Agustus 24'!AL68 -> 0 | N79: ='[24]September 24'!AL68 -> 0 | O79: ='[24]September 24'!AM68 -> #REF! | P79: ='[24]November 24'!AL68 -> 0 | Q79: ='[24]Desember 24'!AL68 -> 0 | S79: =SUM(F79:Q79) -> #REF! | T79: =SUM(G79:R79) -> #REF! | U79: =(S79/T79)*100 -> #REF!
C80: Olein IV 60 Consume | E80: Kg | F80: ='[24]Januari 24'!AL69 -> 399021.28 | G80: ='[24]Februari 24'!AI69 -> #REF! | H80: ='[24]Maret 24'!AL69 -> 0 | I80: ='[24]April 24'!AL69 -> 0 | J80: ='[24]Mei 24'!AL69 -> 0 | K80: ='[24]Juny 24'!AL69 -> 0 | L80: ='[24]July 24'!AL69 -> 0 | M80: ='[24]Agustus 24'!AL69 -> 0 | N80: ='[24]September 24'!AL69 -> 0 | O80: ='[24]September 24'!AM69 -> #REF! | P80: ='[24]November 24'!AL69 -> 0 | Q80: ='[24]Desember 24'!AL69 -> 0 | S80: =SUM(S81:S83) -> #REF! | T80: =SUM(T81:T83) -> #REF! | U80: =(S80/T80)*100 -> #REF! | AFQ80: Kg | AFR80: Olein Filling to Packaging
C81: - finished product | E81: Kg | F81: =SUM(F85:F86)*10.86 -> 400256.16 | G81: =SUM(G85:G86)*10.86 -> #REF! | H81: =SUM(H85:H86)*10.86 -> 0 | I81: ='[24]April 24'!AL70 -> 0 | J81: =SUM(J85:J86)*10.86 -> 0 | K81: =SUM(K85:K86)*10.86 -> 0 | L81: =SUM(L85:L86)*10.86 -> 0 | M81: =SUM(M85:M86)*10.86 -> 0 | N81: =SUM(N85:N86)*10.86 -> 0 | O81: =SUM(O85:O86)*10.86 -> #REF! | P81: =SUM(P85:P86)*10.86 -> 0 | Q81: =SUM(Q85:Q86)*10.86 -> 0 | S81: =SUM(S85:S86)*10.86 -> #REF! | T81: =SUM(T85:T86)*10.86 -> 32269046 | U81: =(S81/T81)*100 -> #REF! | FW81: =#REF!/1000 -> #REF! | OX81: 4696 | OY81: =FW81/OX81*100 -> #REF!
C82: - sample | E82: Kg | F82: =F80-F81 -> -1234.88 | G82: =G80-G81 -> #REF! | H82: =H80-H81 -> 0 | I82: ='[24]April 24'!AL71 -> 0 | J82: =J80-J81 -> 0 | K82: =K80-K81 -> 0 | L82: =L80-L81 -> 0 | M82: =M80-M81 -> 0 | N82: =N80-N81 -> 0 | O82: =O80-O81 -> #REF! | P82: =P80-P81 -> 0 | Q82: =Q80-Q81 -> 0 | S82: =SUM(F82:Q82) -> #REF! | T82: =SUM(G82:R82) -> #REF! | U82: =(S82/T82)*100 -> #REF! | FW82: =#REF!/1000 -> #REF! | OX82: 565 | OY82: =FW82/OX82*100 -> #REF!
C83: - remelt, flushing, downgrade | E83: Kg | F83: ='[24]Januari 24'!AL72 -> 0 | G83: ='[24]Februari 24'!AI72 -> 0 | H83: ='[24]Maret 24'!AL72 -> 0 | I83: ='[24]April 24'!AL72 -> 0 | P83: 0 | Q83: 0 | S83: =SUM(F83:Q83) -> 0 | T83: =SUM(G83:R83) -> 0
C84: Carton | S84: Carton | T84: Carton | U84: Carton
C85: Salvaco 1 Liter | E85: Box | F85: ='[24]Januari 24'!AL74 -> 17197 | G85: ='[24]Februari 24'!AI74 -> #REF! | H85: ='[24]Maret 24'!AL74 -> 0 | I85: ='[24]April 24'!AL74 -> 0 | J85: ='[24]Mei 24'!AL74 -> 0 | K85: ='[24]Juny 24'!AL74 -> 0 | L85: ='[24]July 24'!AL74 -> 0 | M85: ='[24]Agustus 24'!AL74 -> 0 | N85: ='[24]September 24'!AL74 -> 0 | O85: ='[24]September 24'!AM74 -> #REF! | P85: ='[24]November 24'!AL74 -> 0 | Q85: ='[24]Desember 24'!AL74 -> 0 | S85: =SUM(F85:Q85) -> #REF! | T85: 1254577 | U85: =(S85/T85)*100 -> #REF!
C86: Salvaco 2 Liter | E86: Box | F86: ='[24]Januari 24'!AL75 -> 19659 | G86: ='[24]Februari 24'!AI75 -> #REF! | H86: ='[24]Maret 24'!AL75 -> 0 | I86: ='[24]April 24'!AL75 -> 0 | J86: ='[24]Mei 24'!AL75 -> 0 | K86: ='[24]Juny 24'!AL75 -> 0 | L86: ='[24]July 24'!AL75 -> 0 | M86: ='[24]Agustus 24'!AL75 -> 0 | N86: ='[24]September 24'!AL75 -> 0 | O86: ='[24]September 24'!AM75 -> #REF! | P86: ='[24]November 24'!AL75 -> 0 | Q86: ='[24]Desember 24'!AL75 -> 0 | S86: =SUM(F86:Q86) -> #REF! | T86: 1716790 | U86: =(S86/T86)*100 -> #REF!
C87: Pouch | S87: Pouch | T87: Pouch | U87: Pouch
C88: Salvaco 1 Liter | E88: Pouch | F88: =F85*12 -> 206364 | G88: =G85*12 -> #REF! | H88: =H85*12 -> 0 | I88: =I85*12 -> 0 | J88: =J85*12 -> 0 | K88: =K85*12 -> 0 | L88: =L85*12 -> 0 | M88: =M85*12 -> 0 | ... Q88: =Q85*12 -> 0 | S88: =S85*12 -> #REF! | T88: =T85*12 -> 15054924 | U88: =(S88/T88)*100 -> #REF!
C89: Salvaco 2 Liter | E89: Pouch | F89: =F86*6 -> 117954 | G89: =G86*6 -> #REF! | H89: =H86*6 -> 0 | I89: =I86*6 -> 0 | J89: =J86*6 -> 0 | K89: =K86*6 -> 0 | L89: =L86*6 -> 0 | M89: =M86*6 -> 0 | ... Q89: =Q86*6 -> 0 | S89: =S86*6 -> #REF! | T89: =T86*6 -> 10300740 | U89: =(S89/T89)*100 -> #REF!
C90: Consumable Vit. A | E90: gram | F90: =(F80*45)/1700 -> 10562.328 | G90: =(G80*45)/1700 -> #REF! | H90: =(H80*45)/1700 -> 0 | I90: =(I80*45)/1700 -> 0 | J90: =(J80*45)/1700 -> 0 | K90: =(K80*45)/1700 -> 0 | L90: =(L80*45)/1700 -> 0 | M90: =(M80*45)/1700 -> 0 | ... Q90: =(Q80*45)/1700 -> 0 | S90: =SUM(F90:Q90) -> #REF! | T90: =(T80*45)/1700 -> #REF! | U90: =(S90/T90)*100 -> #REF!
C91: Consumable Packing Tape | E91: Roll | F91: =SUM(F85:F86)/500 -> 73.712 | G91: =SUM(G85:G86)/500 -> #REF! | H91: =SUM(H85:H86)/500 -> 0 | I91: =SUM(I85:I86)/500 -> 0 | J91: =SUM(J85:J86)/500 -> 0 | K91: =SUM(K85:K86)/500 -> 0 | L91: =SUM(L85:L86)/500 -> 0 | M91: =SUM(M85:M86)/500 -> 0 | ... Q91: =SUM(Q85:Q86)/500 -> 0 | S91: =SUM(F91:Q91) -> #REF! | T91: =SUM(T85:T86)/500 -> 5942.734 | U91: =(S91/T91)*100 -> #REF!
C92: REJECT MATERIAL QTY | S92: Loss Material | T92: Loss Material | U92: Loss Material
C93: Carton | S93: Carton | T93: Carton | U93: Carton
C94: Salvaco 1 Liter | E94: Box | F94: ='[24]Januari 24'!AL74 -> 17197 | G94: ='[24]Februari 24'!AI83 -> #REF! | H94: ='[24]Maret 24'!AL83 -> 0 | I94: ='[24]April 24'!AL83 -> 0 | J94: ='[24]Mei 24'!AL83 -> 0 | K94: ='[24]Juny 24'!AL83 -> 0 | L94: ='[24]July 24'!AL83 -> 0 | M94: ='[24]Agustus 24'!AL83 -> 0 | N94: ='[24]September 24'!AL83 -> 0 | O94: ='[24]September 24'!AM83 -> #REF! | P94: ='[24]November 24'!AL83 -> 0 | Q94: ='[24]Desember 24'!AL83 -> 0 | S94: =SUM(F94:Q94) -> #REF! | T94: =SUM(G94:R94) -> #REF! | U94: =SUM(H94:S94) -> #REF!
C95: Salvaco 2 Liter | E95: Box | F95: ='[24]Januari 24'!AL75 -> 19659 | G95: ='[24]Februari 24'!AI84 -> #REF! | H95: ='[24]Maret 24'!AL84 -> 0 | I95: ='[24]April 24'!AL84 -> 0 | J95: ='[24]Mei 24'!AL84 -> 0 | K95: ='[24]Juny 24'!AL84 -> 0 | L95: ='[24]July 24'!AL84 -> 0 | M95: ='[24]Agustus 24'!AL84 -> 0 | N95: ='[24]September 24'!AL84 -> 0 | O95: ='[24]September 24'!AM84 -> #REF! | P95: ='[24]November 24'!AL84 -> 0 | Q95: ='[24]Desember 24'!AL84 -> 0 | S95: =SUM(F95:Q95) -> #REF! | T95: =SUM(G95:R95) -> #REF! | U95: =SUM(H95:S95) -> #REF!
C96: Pouch | S96: Pouch | T96: Pouch | U96: Pouch
C97: Salvaco 1 Liter | E97: Pouch | F97: =F94*12 -> 206364 | G97: =G94*12 -> #REF! | H97: =H94*12 -> 0 | I97: =I94*12 -> 0 | J97: =J94*12 -> 0 | K97: =K94*12 -> 0 | L97: =L94*12 -> 0 | M97: =M94*12 -> 0 | ... Q97: =Q94*12 -> 0 | S97: =SUM(F97:Q97) -> #REF! | T97: =SUM(G97:R97) -> #REF! | U97: =SUM(H97:S97) -> #REF!
C98: Salvaco 2 Liter | E98: Pouch | F98: =F95*6 -> 117954 | G98: =G95*6 -> #REF! | H98: =H95*6 -> 0 | I98: =I95*6 -> 0 | J98: =J95*6 -> 0 | K98: =K95*6 -> 0 | L98: =L95*6 -> 0 | M98: =M95*6 -> 0 | ... Q98: =Q95*6 -> 0 | S98: =SUM(F98:Q98) -> #REF! | T98: =SUM(G98:R98) -> #REF! | U98: =SUM(H98:S98) -> #REF!
C99: REJECT MATERIAL (%) | S99: Loss Material | T99: Loss Material | U99: Loss Material
C100: Carton | S100: Carton | T100: Carton | U100: Carton
C101: Salvaco 1 Liter | D101: 0.3 | E101: % | F101: =F94/F85*100 -> 100 | G101: =G94/G85*100 -> #REF! | H101: =H94/H85*100 -> #DIV/0! | I101: =I94/I85*100 -> #DIV/0! | J101: =J94/J85*100 -> #DIV/0! | K101: =K94/K85*100 -> #DIV/0! | L101: =L94/L85*100 -> #DIV/0! | M101: =M94/M85*100 -> #DIV/0! | ... Q101: =Q94/Q85*100 -> #DIV/0! | S101: =S94/S85*100 -> #REF! | T101: =T94/T85*100 -> #REF! | U101: =U94/U85*100 -> #REF!
...

Sheet Downtime Ref Nov
F2: DOWN TIME SLOW FLOWRATE PRODUCTION REFINERY
F4: Periode 01 s/d 30 November 2024
F5: TANGGAL | G5: CAPACITY (Kg) | H5: REMARKS | I5: Down time | M5: Tph
I6: Stop | J6: Slow | K6: % | AE6: 17 | AF6: 18 | AG6: 19 | AH6: 20 | AI6: 21 | AJ6: 22 | AK6: 23 | AL6: 24 | AM6: 25 | AN6: 26 | AO6: 27 | AP6: 28 | AQ6: 29 | AR6: 30 | AS6: 31
F7: 1 | G7: 859587 | H7: Penyesuaian incoming CPO | J7: =(2200-(G7/1000))/91.7 -> 14.617372 | K7: =G7/2200/1000 -> 0.39072136 | M7: =(G7/1000)/24 -> 35.816125 | O7: =249.262+270.9 -> 520.162 | P7: =1356.367+39.742 -> 1396.109 | Q7: =1086.521+50.6 -> 1137.121 | R7: =1353.558+373.309 -> 1726.867 | S7: 1942.746 | T7: 1868.212 | U7: 2057.011 | V7: 1781.844 | W7: 1250.764 | X7: 1613.486 | Y7: 1325.077 | Z7: =66.442+571.568 -> 638.01 | AA7: =815.429 -> 815.429 | AB7: =352.234+731.627 -> 1083.861 | AC7: =1626.002+13.213 -> 1639.215 | AD7: 2094.791 | AE7: 2075.375 | AF7: 2008.804 | AG7: 1946.712 | AH7: 1998.939 | AI7: =1623.839+281.468 -> 1905.307 | AJ7: 1610.024 | AK7: =1135.181+98.368 -> 1233.549 | AL7: =958.893+543.852 -> 1502.745 | AM7: 2043.15 | AN7: 1762.642 | AO7: 2170.336 | AP7: =1181.38+463.711 -> 1645.091 | AQ7: 219.474 | AR7: =48.153+1225.968+107.3 -> 1381.421
F8: 2 | G8: 537300 | H8: Penyesuaian incoming CPO | J8: =(2200-(G8/1000))/91.7 -> 18.131952 | K8: =G8/2200/1000 -> 0.24422727 | M8: =(G8/1000)/24 -> 22.3875
F9: 3 | G9: 736801 | H9: Penyesuaian incoming CPO | J9: =(2200-(G9/1000))/91.7 -> 15.956369 | K9: =G9/2200/1000 -> 0.33490955 | M9: =(G9/1000)/24 -> 30.700042
F10: 4 | G10: 894589 | H10: Penyesuaian incoming CPO | J10: =(2200-(G10/1000))/91.7 -> 14.235671 | K10: =G10/2200/1000 -> 0.40663136 | M10: =(G10/1000)/24 -> 37.274542
F11: 5 | G11: 900604 | H11: Penyesuaian incoming CPO | J11: =(2200-(G11/1000))/91.7 -> 14.170076 | K11: =G11/2000/1000 -> 0.450302 | M11: =(G11/1000)/24 -> 37.525167
F12: 6 | G12: 846175 | H12: Penyesuaian incoming CPO | J12: =(2200-(G12/1000))/91.7 -> 14.763631 | K12: =G12/2200/1000 -> 0.384625 | M12: =(G12/1000)/24 -> 35.257292
F13: 7 | G13: 753834 | H13: Penyesuaian incoming CPO | J13: =(2200-(G13/1000))/91.7 -> 15.770622 | K13: =G13/2200/1000 -> 0.34265182 | M13: =(G13/1000)/24 -> 31.40975
F14: 8 | G14: 696743 | H14: Penyesuaian incoming CPO | J14: =(2200-(G14/1000))/91.7 -> 16.393206 | K14: =G14/2200/1000 -> 0.31670136 | M14: =(G14/1000)/24 -> 29.030958
F15: 9 | G15: 828594 | H15: Penyesuaian incoming CPO | J15: =(2200-(G15/1000))/91.7 -> 14.955354 | K15: =G15/2200/1000 -> 0.37663364 | M15: =(G15/1000)/24 -> 34.52475
F16: 10 | G16: 1003650 | H16: Penyesuaian incoming CPO | J16: =(2200-(G16/1000))/91.7 -> 13.046347 | K16: =G16/2200/1000 -> 0.45620455 | M16: =(G16/1000)/24 -> 41.81875
F17: 11 | G17: 1000809 | H17: Penyesuaian incoming CPO | J17: =(2200-(G17/1000))/91.7 -> 13.077328 | K17: =G17/2200/1000 -> 0.45491318 | M17: =(G17/1000)/24 -> 41.700375
F18: 12 | G18: 925598 | H18: Penyesuaian incoming CPO | J18: =(2200-(G18/1000))/91.7 -> 13.897514 | K18: =G18/2200/1000 -> 0.42072636 | M18: =(G18/1000)/24 -> 38.566583
F19: 13 | G19: 803666 | H19: Penyesuaian incoming CPO | J19: =(2200-(G19/1000))/91.7 -> 15.227197 | K19: =G19/2200/1000 -> 0.36530273 | M19: =(G19/1000)/24 -> 33.486083
F20: 14 | G20: 1009988 | H20: Penyesuaian incoming CPO | J20: =(2200-(G20/1000))/91.7 -> 12.97723 | K20: =G20/2200/1000 -> 0.45908545 | M20: =(G20/1000)/24 -> 42.082833
F21: 15 | G21: 1042124 | H21: Penyesuaian incoming CPO | J21: =(2200-(G21/1000))/91.7 -> 12.626783 | K21: =G21/2200/1000 -> 0.47369273 | M21: =(G21/1000)/24 -> 43.421833
F22: 16 | G22: 991679 | H22: Penyesuaian incoming CPO | J22: =(2200-(G22/1000))/91.7 -> 13.176892 | K22: =G22/2200/1000 -> 0.45076318 | M22: =(G22/1000)/24 -> 41.319958
F23: 17 | G23: 633826 | H23: Penyesuaian incoming CPO | J23: =(2200-(G23/1000))/91.7 -> 17.079324 | K23: =G23/2200/1000 -> 0.28810273 | M23: =(G23/1000)/24 -> 26.409417
... F36: 30 | G36: 0 | H36: SHUT DOWN | J36: =(2200-(G36/1000))/91.7 -> 23.991276 | K36: =G36/2200/1000 -> 0 | M36: =(G36/1000)/24 -> 0
F37: TOTAL | G37: =SUM(G7:G36) -> 20377380 | I37: =SUM(I7:I36) -> 0 | J37: =SUM(J7:J36) -> 497.52039 | M37: =AVERAGE(M7:M36) -> 28.301917
G39: Summary
G40: 1. Slow flow rate due to Space Tank High | I40: 0 | J40: hours
G41: 2. Slow flow rate due to Olein IV 60 process | I41: 0 | J41: hours
G42: 3. Hold plant due to trip MP boiler & maintenance | I42: 0 | J42: hours
G43: 4. Penyesuaian incoming CPO | I43: =SUM(J7,J8,J9,J10,J11,J12,J13,J14,J15,J16,J17,J18,J19,J20,J21,J22,J23,J24,J25,J26,J27,J28) -> 305.59019 | J43: hours
G44: 5. Downtime due to Start Up Plant | J44: hours
G45: 6. Running Normal Plant | I45: 0 | J45: hours
G46: 7. Stop Plant due to Preventive Maintenance Plant | I46: 0 | J46: hours
G47: 8. Energizing PMG II | I47: 0 | J47: hours
G48: 9. Zero Suplay Gas (Problem Pertagas) | I48: 0 | J48: hours
G49: 10, Stop Plant | I49: =SUM(J29,J30,J31,J32,J33,J34,J35,J36) -> 191.93021 | J49: hours
G50: 11.HOLD CPO Shortage | J50: hours
G51: Total | I51: =SUM(I40:I50) -> 497.52039 | J51: hours
G52: Note : Kapasitas 2200 TPD
E62: Prepared by, | H62: Checked by, | J62: Approved by,
E66: Bany Subana | H66: Reza P. Panjaitan | J66: Sudarianto
E67: Admin. Process | H67: Supervisor Produksi | J67: Jr. Manager Produksi

Sheet Downtime Fract Oktober
F2: DOWN TIME SLOW FLOWRATE PRODUCTION FRACTIONATION
F4: Periode 01 s/d 30 November 2024
F5: TANGGAL | G5: CAPACITY (Kg) | H5: REMARKS | I5: Down time | M5: Tph
I6: Stop | J6: Slow | K6: % | AE6: 17 | AF6: 18 | AG6: 19 | AH6: 20 | AI6: 21 | AJ6: 22 | AK6: 23 | AL6: 24 | AM6: 25 | AN6: 26 | AO6: 27 | AP6: 28 | AQ6: 29 | AR6: 30 | AS6: 31
F7: 1 | G7: 994298 | H7: Slow flow rate due to Olein IV 58 process | J7: =(2000-(G7/1000))/83.33 -> 12.068907 | K7: =G7/2000/1000 -> 0.497149 | M7: =(G7/1000)/24 -> 41.429083 | O7: =249.262+270.9 -> 520.162 | P7: =1356.367+39.742 -> 1396.109 | Q7: =1086.521+50.6 -> 1137.121 | R7: =1353.558+373.309 -> 1726.867 | S7: 1942.746 | T7: 1868.212 | U7: 2057.011 | V7: 1781.844 | W7: 1250.764 | X7: 1613.486 | Y7: 1325.077 | Z7: =66.442+571.568 -> 638.01 | AA7: =815.429 -> 815.429 | AB7: =352.234+731.627 -> 1083.861 | AC7: =1626.002+13.213 -> 1639.215 | AD7: 2094.791 | AE7: 2075.375 | AF7: 2008.804 | AG7: 1946.712 | AH7: 1998.939 | AI7: =1623.839+281.468 -> 1905.307 | AJ7: 1610.024 | AK7: =1135.181+98.368 -> 1233.549 | AL7: =958.893+543.852 -> 1502.745 | AM7: 2043.15 | AN7: 1762.642 | AO7: 2170.336 | AP7: =1181.38+463.711 -> 1645.091 | AQ7: 219.474 | AR7: =48.153+1225.968+107.3 -> 1381.421
F8: 2 | G8: 1115291 | H8: Slow flow rate due to Olein IV 58 process | J8: =(2000-(G8/1000))/83.33 -> 10.616933 | K8: =G8/2000/1000 -> 0.5576455 | M8: =(G8/1000)/24 -> 46.470458
F9: 3 | G9: 1038010 | H9: Slow flow rate due to Olein IV 58 process | J9: =(2000-(G9/1000))/83.33 -> 11.544342 | K9: =G9/2000/1000 -> 0.519005 | M9: =(G9/1000)/24 -> 43.250417
F10: 4 | G10: 1058141 | H10: Slow flow rate due to Olein IV 58 process | J10: =(2000-(G10/1000))/83.33 -> 11.30276 | K10: =G10/2000/1000 -> 0.5290705 | M10: =(G10/1000)/24 -> 44.089208
F11: 5 | G11: 899356 | H11: Slow flow rate due to Olein IV 58 process | J11: =(2000-(G11/1000))/83.33 -> 13.208256 | K11: =G11/2000/1000 -> 0.449678 | M11: =(G11/1000)/24 -> 37.473167
F12: 6 | G12: 939422 | H12: Slow flow rate due to Olein IV 58 process | J12: =(2000-(G12/1000))/83.33 -> 12.727445 | K12: =G12/2000/1000 -> 0.469711 | M12: =(G12/1000)/24 -> 39.142583
F13: 7 | G13: 1003337 | H13: Slow flow rate due to Olein IV 58 process | J13: =(2000-(G13/1000))/83.33 -> 11.960434 | K13: =G13/2000/1000 -> 0.5016685 | M13: =(G13/1000)/24 -> 41.805708
F14: 8 | G14: 899475 | H14: Slow flow rate due to Olein IV 58 process | J14: =(2000-(G14/1000))/83.33 -> 13.206828 | K14: =G14/2000/1000 -> 0.4497375 | M14: =(G14/1000)/24 -> 37.478125
F15: 9 | G15: 923368 | H15: Slow flow rate due to Olein IV 58 process | J15: =(2000-(G15/1000))/83.33 -> 12.920101 | K15: =G15/2000/1000 -> 0.461684 | M15: =(G15/1000)/24 -> 38.473667
F16: 10 | G16: 1178496 | H16: Slow flow rate due to Olein IV 56 process & IV 58 process | J16: =(2000-(G16/1000))/83.33 -> 9.8584423 | K16: =G16/2000/1000 -> 0.589248 | M16: =(G16/1000)/24 -> 49.104
F17: 11 | G17: 1073268 | H17: Slow flow rate due to Olein IV 56 process | J17: =(2000-(G17/1000))/83.33 -> 11.121229 | K17: =G17/2000/1000 -> 0.536634 | M17: =(G17/1000)/24 -> 44.7195
F18: 12 | G18: 927936 | H18: Slow flow rate due to Olein IV 56 process | J18: =(2000-(G18/1000))/83.33 -> 12.865283 | K18: =G18/2000/1000 -> 0.463968 | M18: =(G18/1000)/24 -> 38.664
F19: 13 | G19: 732528 | H19: Slow flow rate due to Olein IV 56 process | J19: =(2000-(G19/1000))/83.33 -> 15.210272 | K19: =G19/2000/1000 -> 0.366264 | M19: =(G19/1000)/24 -> 30.522
... F37: 31 | G37: 0 | H37: STOP PLANT | J37: =(2000-(G37/1000))/83.33 -> 24.00096 | K37: =G37/2000/1000 -> 0 | M37: =(G37/1000)/24 -> 0
F38: TOTAL | G38: =SUM(G7:G37) -> 22537679 | I38: =SUM(I7:I36) -> 0 | J38: =SUM(J7:J37) -> 473.56679 | M38: =AVERAGE(M7:M37) -> 30.292579
G40: Summary
G41: 1. Slow flow rate due to Space Tank High | I41: 0 | J41: hours
G42: 2. Slow flow rate due to Olein IV 60 process | I42: 0 | J42: hours
G43: 3. Slow flow rate due to Olein IV 57 process | I43: 0 | J43: hours
G44: 4. Slow Flow rate terkait material sortage & menyesuaikan | I44: 0 | J44: hours
G45: 5. Downtime due to Start/Stop Up Plant | I45: 0 | J45: hours
G46: 6. Running Normal Plant | I46: 0 | J46: hours
G47: 7. Stop Plant due to Preventive Maintenance Plant | I47: 0 | J47: hours
G48: 8. Energizing PMG II | I48: 0 | J48: hours
G49: 9. Zero Suplay Gas (Problem Pertagas) | I49: 0 | J49: hours
G50: 10. Slow flow rate due to Olein IV 58 process | I50: =SUM(J7,J8,J9,J10,J11,J12,J13,J14,J15,J22,J23,J24,J25,J26,J27,J28,J29) -> 217.20805 | J50: hours
G51: 11. STOP PLANT | I51: =SUM(J31,J32,J33,J34,J35,J36,J37) -> 168.00672 | J51: hours
G52: 12.Slow flow rate due to Olein IV 56 process | I52: =SUM(J17,J18,J19,J20) -> 51.423137 | J52: hours
G53: 13. Slow flow rate due to Olein IV 56 process & IV 57 process | I53: 0 | J53: hours
G54: 14. Slow flow rate due to Olein IV 56 process & IV 58 process | I54: =SUM(J16,J21,J30) -> 36.928885 | J54: hours
G55: Total | I55: =SUM(I41:I54) -> 473.56679 | J55: hours
G56: Note : Kapasitas 2000 TPD
E65: Prepared by, | H65: Checked by, | J65: Approved by,
E69: Bany Subana | H69: Reza P. Panjaitan | J69: Sudarianto
E70: Admin. Process | H70: Supervisor Produksi | J70: Jr. Manager Produksi

Sheet Prod
B2: MONTHLY PRODUCTION REPORT
B3: PT. INDUSTRI NABATI LESTARI
B4: Periode 01 s/d 30 November 2024
B5: NO | C5: Item | D5: Unit | E5: November | H5: Remaks
E6: Budget | F6: Actual | G6: Percentage Act.
B7: 1. | C7: PRODUCTION
C8: Refinery Plant
C9: Running Days | D9: Days | E9: 18 | F9: ='November 2024'!$AL$6 -> 22 | G9: =(F9/E9) -> 1.2222222 | H9: Tercapai
C10: CPO Incoming | D10: Kg
C11: Total CPO Consume | D11: Kg | E11: ='November 2024'!E9 -> 36359000 | F11: =F12+F13 -> 20377380 | G11: =(F11/E11) -> 0.56044941 | H11: Tidak Tercapai
C12: CPO Consume Poram | F12: ='November 2024'!AL11 -> 20377380
C13: CPO Consume Brand | F13: ='November 2024'!AL12 -> 0
C14: - Avg. FFA | D14: % | E14: 5 | F14: ='November 2024'!AL13 -> 3.8712121 | G14: =(F14/E14) -> 0.77424242
C15: - Avg. Moist & Impurities | D15: % | E15: 0.5 | F15: ='November 2024'!AL14 -> 0.43416667 | G15: =(F15/E15) -> 0.86833333
C16: - Avg. DOBI | D16: % | E16: 22.2 | F16: ='November 2024'!AL15 -> 2.015 | G16: =(F16/E16) -> 0.090765766
C17: Product
C18: RBDPO | D18: Kg | E18: 33124010 | F18: ='November 2024'!AL18 -> 19958156 | G18: =(F18/E18) -> 0.60252837
C19: PFAD | D19: Kg | E19: 1572840 | F19: ='November 2024'!$AL$19 -> 870458 | G19: =(F19/E19) -> 0.55343074
C21: Fraksinasi Plant
C22: Total Proses RBDPO | D22: Kg | E22: =E25+E38+E43 -> 31417000 | F22: ='November 2024'!$AL$25 -> 22537659 | G22: =(F22/E22) -> 0.71737145 | H22: Tidak Tercapai
C23: Total Olah RBDPO ( Feed ) | D23: Kg | E23: =E25+E38+E43 -> 31417000 | F23: ='November 2024'!$AL$23 -> 21737836 | G23: =(F23/E23) -> 0.69191317 | H23: Tidak Tercapai
C24: Fractionation Olein IV 56
C25: RBDPO Consume | D25: Kg | E25: 7883000 | F25: =F26+F27 -> 5970222 | G25: =(F25/E25) -> 0.75735405 | H25: Tercapai
C26: Olein IV 56 | D26: Kg | E26: 6464000 | F26: ='November 2024'!$AL$29 -> 4990754 | G26: =(F26/E26) -> 0.77208447 | H26: Tercapai
C27: Stearin | D27: Kg | E27: 1419000 | F27: ='November 2024'!$AL$30 -> 979468 | G27: =(F27/E27) -> 0.69025229 | H27: Tercapai
C28: Fractionation Olein IV 57 ( Bulk )
C29: RBDPO Consume | D29: Kg | E29: 0
C30: Olein IV 57 | D30: Kg | E30: 0 | F30: 0 | G30: 0
C31: Stearin | D31: Kg | E31: 0
C32: Fractionation Olein IV 57 ( Retail )
C33: CPO | D33: Kg | E33: 1812101.9 | G33: =(F33/E33)*100 -> 0
C34: RBDPO Consume | D34: Kg | E34: 1707000 | F34: =F35+F36 -> 0 | G34: =(F34/E34)*100 -> 0 | H34: Tidak Tercapai
C35: Olein IV 57 | D35: Kg | E35: 1280000 | G35: =(F35/E35)*100 -> 0 | H35: Tidak Tercapai
C36: Stearin | D36: Kg | E36: 427000 | G36: =(F36/E36)*100 -> 0 | H36: Tidak Tercapai
C37: Fractionation Olein IV 58
C38: RBDPO Consume | D38: Kg | E38: 21429000 | F38: =F39+F40 -> 16567437 | G38: =(F38/E38)*100 -> 77.31316 | H38: Tidak Tercapai
C39: Olein IV 58 | D39: Kg | E39: 15000000 | F39: ='November 2024'!$AL$42 -> 12573252 | G39: =(F39/E39)*100 -> 83.82168 | H39: Tidak Tercapai
C40: Stearin | D40: Kg | E40: 6429000 | F40: ='November 2024'!$AL$43 -> 3994185 | G40: =(F40/E40)*100 -> 62.127625 | H40: Tidak Tercapai
C41: Fractionation Olein IV 60
C42: CPO | E42: 2234607.2 | F42: 0 | G42: =(F42/E42)*100 -> 0
C43: RBDPO Consume | D43: Kg | E43: 2105000 | F43: 0 | G43: =(F43/E43)*100 -> 0 | H43: Tidak Tercapai
C44: Olein IV 60 Salvaco | D44: Kg | E44: 1263000 | F44: ='November 2024'!AL53 -> 0 | G44: =(F44/E44)*100 -> 0 | H44: Tidak Tercapai
C45: Soft Stearin | D45: Kg | E45: 842000 | F45: ='November 2024'!AL54 -> 0 | G45: =(F45/E45)*100 -> 0 | H45: Tidak Tercapai
B46: 2. | C46: % YIELD
C47: RBDPO | D47: % | E47: 94.77 | F47: =(F18/F11)*100 -> 97.942699 | G47: =(F47/E47)*100 -> 103.34779 | H47: Tidak Tercapai
C48: PFAD | D48: % | E48: 4.5 | F48: =(F19/(F11))*100 -> 4.2716875 | G48: =(F48/E48)*100 -> 94.92639 | H48: Tidak Tercapai
C49: Olein IV 56 | D49: % | E49: 82 | F49: =F26/(F26+F27)*100 -> 83.594111 | G49: =(F49/E49)*100 -> 101.94404 | H49: Tercapai
C50: Stearin | D50: % | E50: 18 | F50: =(F27/F25)*100 -> 16.405889 | G50: =(F50/E50)*100 -> 91.143828 | H50: Tercapai
C51: Olein IV 57 ( Bulk ) | D51: % | E51: 75 | F51: 0 | G51: =(F51/E51)*100 -> 0
C52: Stearin | D52: % | E52: 25 | F52: 0 | G52: =(F52/E52)*100 -> 0
C53: Olein IV 57 ( Retail ) | D53: % | E53: 75 | F53: =F35/(F35+F36)*100 -> #DIV/0! | G53: =(F53/E53)*100 -> #DIV/0! | H53: Tercapai
C54: Stearin | D54: % | E54: 25 | F54: =(F36/F34)*100 -> #DIV/0! | G54: =(F54/E54)*100 -> #DIV/0! | H54: Tercapai
C55: Olein IV 58 | D55: % | E55: 70 | F55: =F39/(F39+F40)*100 -> 75.891352 | G55: =(F55/E55)*100 -> 108.41622 | H55: Tercapai
C56: Stearin | D56: % | E56: 30 | F56: =(F40/F38)*100 -> 24.108648 | G56: =(F56/E56)*100 -> 80.362159 | H56: Tercapai
C57: Olein IV 60 | D57: % | E57: 60 | F57: 0 | G57: =(F57/E57)*100 -> 0
C58: Soft Stearin | D58: % | E58: 40 | F58: 0 | G58: =(F58/E58)*100 -> 0
B59: 3. | C59: CHEMICAL CONSUMABLE
C60: Bleaching Earth to Poram Spec | D60: Kg | E60: 232362 | F60: ='November 2024'!$AL$72 -> 137569 | G60: =(F60/E60)*100 -> 59.204603
D61: Kg/MT | E61: 8 | F61: =(F60/F12)*1000 -> 6.7510642 | G61: =(F61/E61)*100 -> 84.388302 | H61: Tercapai
C62: Bleaching Earth to Branded Spec | D62: Kg | E62: 106326 | F62: ='November 2024'!AL12 -> 0 | G62: =(F62/E62)*100 -> 0
D63: Kg/MT | E63: 18 | G63: =(F63/E63)*100 -> 0
C64: Phosporic Acid | D64: Kg | E64: 20971 | F64: ='November 2024'!$AL$76 -> 10695.718 | G64: =(F64/E64)*100 -> 51.002422
D65: Kg/MT | E65: 0.6 | F65: =(F64/F11)*1000 -> 0.5248819 | G65: =(F65/E65)*100 -> 87.480317 | H65: Tercapai
B66: 4. | C66: OIL LOSSES
C67: (Loss)/Gain | D67: % | E67: -0.73 | F67: ='November 2024'!$AL$78 -> 2.2143867 | G67: =(F67/E67)*100 -> -303.34065 | H67: Tidak Tercapai
C68: % Oil Content | D68: % | E68: 22 | F68: ='November 2024'!$AL$80 -> 21.916818 | G68: =(F68/E68)*100 -> 99.621901
C69: Spent Bleaching Earth | D69: Kg | E69: 413199.36 | F69: ='November 2024'!$AL$81 -> 138939.49 | G69: =(F69/E69)*100 -> 33.625291
B70: NB :
B71: - BE Achieve dengan pemakaian consume Bleaching Earth 6,8 Kg/MT
B72: - Untuk hari olah Produksi terpenuhi, PMG I Stop pada tanggal 24 November 2024 hal ini dilakukan bertujuan untuk persiapan
B73: Commisioning pada tanggal 03 Desember 2024 dan CPO yang dibutuhkan untuk Commmsioning PMG II sebanyak 17.500 MT
B74: - Total CPO Proses sebesar : 20.377 MT dengan total CPO Incoming ke INL sebanyak : 33.666 MT
B75: - Rata rata incoming CPO perhari 1.1222 MT, Sedangkan rata-rata CPO Feed per hari 926 MT
A77: Prepared by, | D77: Checked by, | H77: Approved by,
A81: Bany Subana | D81: Reza P. Panjaitan | F81: Sudarianto | H81: Eben Jaya Ginting
A82: Admin. Process | D82: Supervisor Produksi | F82: Jr. Manager Produksi | H82: Manager Plant

Sheet Utility
D2: UTILITY (GAS, STEAM, WATER & POWER) REPORT
D3: PT. INDUSTRI NABATI LESTARI
D5: Periode 01 s/d 30 November 2024
D6: No | E6: Item | F6: Norma | G6: UoM | H6: November | K6: Consume CPO ( MT ) | L6: Remaks
H7: Budget | I7: Actual | J7: Percentage Act.
E9: Total Feed Raw Material CPO | K9: 24046
D10: 1. | E10: GAS CONSUMPTION
E11: Incoming *base on INL | G11: mmbtu | I11: ='November 2024'!$AL$234 -> 30948.411
E12: Incoming *base on Pertagas | F12: 1460.001 | G12: mmbtu | H12: 26051.47 | I12: ='November 2024'!$AL$232 -> 28780.462 | J12: =I12/H12 -> 1.1047539 | K12: =I12/K9 -> 1.1968919
E13: Distribution to
E14: HP Boiler Refinery | G14: mmbtu | H14: 3907.73 | I14: ='November 2024'!$AL$236 -> 4004.6778 | J14: =I14/H14 -> 1.0248092 | K14: =I14/K9 -> 0.16654237
E15: MP Boiler | G15: mmbtu | H15: 22143.74 | I15: =I12-$I$14 -> 24775.784 | J15: =I15/H15 -> 1.1188618 | K15: =I15/K9 -> 1.0303495
E16: Total | G16: mmbtu | H16: 26051.47 | I16: =$I$12 -> 28780.462 | J16: =I16/H16 -> 1.1047539 | K16: =SUM(K14+K15) -> 1.1968919
D17: 2. | E17: STEAM CONSUMPTION
E18: Incoming | G18: Kg | H18: 11424000 | I18: ='November 2024'!$AL$241 -> 5582656 | J18: =I18/H18 -> 0.48867787 | K18: =I18/$K$9 -> 232.16568
E19: Distribution to | K19: =I19/$K$9 -> 0
E20: Refinery | F20: < 90 | G20: Kg | H20: 3420000 | I20: ='November 2024'!$AL$243 -> 3611900 | J20: =I20/H20 -> 1.0561111 | K20: =I20/$K$9 -> 150.20793
E21: Fractionation | F21: < 61 | G21: Kg | H21: 2318000 | I21: ='November 2024'!$AL$245 -> 1796900 | J21: =I21/H21 -> 0.77519413 | K21: =I21/$K$9 -> 74.727605
E22: Others | F22: 106000 | G22: Kg | H22: 5686000 | I22: ='November 2024'!$AL$247 -> 173856 | J22: =I22/H22 -> 0.030576152 | K22: =I22/$K$9 -> 7.2301422
E23: Total | G23: Kg | H23: 11424000 | I23: =SUM(I20:I22) -> 5582656 | J23: =I23/H23 -> 0.48867787 | K23: =I23/$K$9 -> 232.16568
D24: 3. | E24: WATER CONSUMPTION
E25: Incoming Raw Water | G25: m3 | H25: 19123.69 | I25: =SUM(I26:$I$27) -> 17740 | J25: =I25/H25 -> 0.92764524 | K25: =I25/$K$9 -> 0.73775264
E26: - Suplay To RO Product | I26: ='November 2024'!$AL$257 -> 8222 | K26: =I26/$K$9 -> 0.34192797
E27: - Suplay To Proses dan Sanitary | I27: =SUM(I29:$I$31) -> 9518 | K27: =I27/$K$9 -> 0.39582467
E28: Rincian Outgoing Proses | K28: =I28/$K$9 -> 0
E29: Softener Product (to Refinery) | F29: < 0,5 | G29: m3 | H29: 1521.33 | I29: ='November 2024'!$AL$253 -> 2042 | J29: =I29/H29 -> 1.3422466 | K29: =I29/$K$9 -> 0.084920569
E30: Softener Product (to Fractionation) | F30: < 0,4 | G30: m3 | H30: 2622 | I30: ='November 2024'!$AL$255 -> 2158 | J30: =I30/H30 -> 0.82303585 | K30: =I30/$K$9 -> 0.089744656
E31: Others | G31: m3 | H31: 2730.3 | I31: ='November 2024'!$AL$258 -> 5318 | J31: =I31/H31 -> 1.9477713 | K31: =I31/$K$9 -> 0.22115944
E32: Total | G32: m3 | H32: 6873.63 | I32: =SUM(I26:I27) -> 17740 | J32: =I32/H32 -> 2.5808779 | K32: =I32/$K$9 -> 0.73775264
D33: 4 | E33: POWER CONSUMPTION
E34: Incoming
E35: PLN *base on BA Kinra | G35: Kwh | H35: 568099 | I35: ='November 2024'!$AL$263 -> 556600 | J35: =I35/H35 -> 0.97975881 | K35: =I35/$K$9 -> 23.147301
E36: Outgoing | K36: =I36/$K$9 -> 0
E37: - Physical Refinery Plant | F37: 5404.17 | G37: Kwh | H37: 102679 | I37: ='November 2024'!$AL$268 -> 73300 | J37: =I37/H37 -> 0.71387528 | K37: =I37/$K$9*1000 -> 3048.324
E38: - Refinery - Cooling Water System | F38: 3850.42 | G38: Kwh | H38: 73158 | I38: ='November 2024'!$AL$266 -> 63690 | J38: =I38/H38 -> 0.87058148 | K38: =I38/$K$9*1000 -> 2648.6734
E39: - Refinery - Utilities | F39: 11.81 | G39: Kwh | H39: 212 | I39: ='November 2024'!$AL$276 -> 18.6 | J39: =I39/H39 -> 0.087735849 | K39: =I39/$K$9*1000 -> 0.77351742
E40: - Dry Fractionation Plant | F40: 5759.67 | G40: Kwh | H40: 109440 | I40: ='November 2024'!$AL$273 -> 96300 | J40: =I40/H40 -> 0.87993421 | K40: =I40/$K$9*1000 -> 4004.8241
E41: - Dry Fractionation CW System | F41: 1308.96 | G41: Kwh | H41: 28747 | I41: ='November 2024'!$AL$271 -> 23460 | J41: =I41/H41 -> 0.81608516 | K41: =I41/$K$9*1000 -> 975.63004
E42: - Lighting - Refinery & Dry Fractionation | F42: 241.12 | G42: Kwh | H42: 4581 | I42: ='November 2024'!$AL$277 -> 5868.7 | J42: =I42/H42 -> 1.2810958 | K42: =I42/$K$9*1000 -> 244.06138
D44: Note untuk Power Consumption
D45: Selisih antara incoming dan outgoing dikarenakan hal berikut :
D47: - Over pemakaian Gas dikarenakan running sesuai RKAP 18 hari namun plant running 22 hari
E50: Prepared by, | F50: Checked by, | K50: Approved by,
E54: Bany Subana | F54: Reza P. Panjaitan | I54: Sudarianto | K54: Eben Jaya Ginting
E55: Admin. Process | F55: Supervisor Produksi | I55: Jr. Manager Produksi | K55: Manager Plant

Sheet Qty cons analysis
D2: Quantity Utility Consumption Analysis (based on Guarantee Utility Consumption)
D3: Refinery & Fractionation Plant
D4: Periode 01 s/d 30 November 2024
D5: Consumption | E5: UoM | F5: Budget | G5: Actual | H5: Under (Over) Budget | I5: Explanation Under / Over budget
D6: CPO Consume | E6: Kg | F6: 34952000 | G6: ='November 2024'!$AL$9 -> 20377380 | H6: =G6/F6 -> 0.58301041
D7: RbdPO Consume | E7: Kg | F7: 33124010 | G7: ='November 2024'!$AL$23 -> 21737836 | H7: =G7/F7 -> 0.65625616
D8: TOTAL ACTUAL CONSUMPTION
D9: Refinery
D10: Bleaching Earth to Poram Spec | E10: Kg | F10: 232362 | G10: ='November 2024'!$AL$72 -> 137569 | H10: =F10-G10 -> 94793
D11: Bleaching Earth to Branded Spec | E11: Kg | F11: 106326 | G11: ='November 2024'!$AL$74 -> 0 | H11: =F11-G11 -> 106326
D12: Phosporic Acid | E12: Kg | F12: 20971 | G12: ='November 2024'!$AL$76 -> 10695.718 | H12: =F12-G12 -> 10275.282
D13: Gas Consumption (MP Boiler) | E13: mmbtu | F13: 22143.74 | G13: ='November 2024'!$AL$238+'November 2024'!$AL$237 -> 24775.981 | H13: =F13-G13 -> -2632.2409
D14: Gas Consumption (HP Boiler) | E14: mmbtu | F14: 3907.73 | G14: ='November 2024'!$AL$236 -> 4004.6778 | H14: =F14-G14 -> -96.947783
D15: Cooling Water top up to Cooling Tower | E15: m3 | F15: 1521.33 | G15: ='November 2024'!$AL$253 -> 2042 | H15: =F15-G15 -> -520.67
D16: Steam | E16: Kg | F16: 11424000 | G16: ='November 2024'!$AL$243 -> 3611900 | H16: =F16-G16 -> 7812100
D17: Power (Process Plant) | E17: Kwh | F17: 102679 | G17: ='November 2024'!$AL$268 -> 73300 | H17: =F17-G17 -> 29379
D18: Power (Cooling Tower) | E18: Kwh | F18: 73158 | G18: ='November 2024'!$AL$266 -> 63690 | H18: =F18-G18 -> 9468
D19: Fractionation
D20: Cooling Water top up to Cooling Tower | E20: m3 | F20: 2622 | G20: ='November 2024'!$AL$255 -> 2158 | H20: =F20-G20 -> 464
D21: Steam | E21: Kg | F21: 2318000 | G21: ='November 2024'!$AL$245 -> 1796900 | H21: =F21-G21 -> 521100
D22: Power (Process Plant) | E22: Kwh | F22: 109440 | G22: ='November 2024'!$AL$273 -> 96300 | H22: =F22-G22 -> 13140
D23: Power (Cooling Tower) | E23: Kwh | F23: 28747 | G23: ='November 2024'!$AL$271 -> 23460 | H23: =F23-G23 -> 5287
D24: ACTUAL CONSUMPTION PER MT RAW MATERIAL
D25: Refinery
D26: Bleaching Earth to Poram Spec | E26: Kg/MT | F26: 8 | G26: =(G10/$G$6)*1000 -> 6.7510642 | H26: =F26-G26 -> 1.2489358
D27: Bleaching Earth to Branded Spec | E27: Kg/MT | F27: 16 | G27: =(G11/$G$6)*1000 -> 0 | H27: =F27-G27 -> 16
D28: Phosporic Acid | E28: Kg/MT | F28: 0.55 | G28: =(G12/$G$6)*1000 -> 0.5248819 | H28: =F28-G28 -> 0.025118097
D29: Gas Consumption (HP Boiler) | E29: Nm3/MT | F29: 4.2 | G29: =(G13/$G$6)*1000 -> 1.215857 | H29: =F29-G29 -> 2.984143 | I29: Gas Over dikarenakan kapasitas tidak tercapai
D30: Gas Consumption (HP Boiler) **) | E30: mmbtu/MT | F30: 0.147294 | G30: =(G14/$G$6)*1000 -> 0.19652565 | H30: =F30-G30 -> -0.049231647
D31: Cooling Water top up to Cooling Tower | E31: m3/MT | F31: 0.55 | G31: =(G15/$G$6)*1000 -> 0.10020915 | H31: =F31-G31 -> 0.44979085
D32: Steam | E32: Kg/MT | F32: 90 | G32: =(G16/$G$6)*1000 -> 177.25046 | H32: =F32-G32 -> -87.250461 | I32: Steam Refinery Over dikarenakan kapasitas tidak tercapai
D33: Power (Process Plant) | E33: Kwh/MT | F33: 3.6133333 | G33: =(G17/$G$6)*1000 -> 3.5971258 | H33: =F33-G33 -> 0.016207501 | I33: Power Over dikarenakan kapasitas tidak tercapai
D34: Power (Cooling Tower) | E34: Kwh/MT | F34: 2.1290444 | G34: =(G18/$G$6)*1000 -> 3.1255245 | H34: =F34-G34 -> -0.99648003
D35: Fractionation
D36: Cooling Water top up to Cooling Tower | E36: m3/MT | F36: 0.4 | G36: =(G20/$G$6)*1000 -> 0.10590174 | H36: =F36-G36 -> 0.29409826
D37: Steam | E37: Kg/MT | F37: 61 | G37: =(G21/$G$6)*1000 -> 88.181111 | H37: =F37-G37 -> -27.181111 | I37: Steam Over dikarenakan menggunakan 2 unit chiller
D38: Power (Process Plant) | E38: Kwh/MT | F38: 3.6996983 | G38: =(G22/$G$6)*1000 -> 4.7258283 | H38: =F38-G38 -> -1.02613 | I38: Power Over dikarenakan kapasitas tidak tercapai
D39: Power (Cooling Tower) | E39: Kwh/MT | F39: 0.98466667 | G39: =(G23/$G$6)*1000 -> 1.1512766 | H39: =F39-G39 -> -0.1666099
D42: - BE Achieve dengan pemakaian consume Bleaching Earth 6,8 Kg/MT
D43: * Steam Refinery Over dikarenakan kapasitas tidak tercapai
D44: * Gas Refinery Over dikarenakan kapasitas tidak tercapai
D45: * Power Fractionation Over dikarenakan kapasitas tidak tercapai
D47: Prepared by, | G47: Checked by, | I47: Approved by,
D51: Bany Subana | F51: Reza P. Panjaitan | H51: Sudarianto | I51: Eben Jaya Ginting
D52: Admin. Process | F52: Supervisor Produksi | H52: Jr. Manager Produksi

Sheet HPP REF 
B2: Refinery Cost
B3: Through Put CPO Proses | N3: =('November 2024'!AL10)/1000 -> 926.24455 | O3: TPD
B4: Working Day | N4: ='November 2024'!AL6 -> 22 | O4: Days
B5: Total CPO Process | N5: =N4*N3 -> 20377.38 | O5: MTD
B6: KURS | N6: ='SUMMARY HPP '!I9 -> 15546 | O6: Rp/USD
B7: No | C7: Item Cost | D7: Norma | F7: Pemakaian / Hari | H7: HK | J7: Total Pemakaian | K7: Harga / stn | M7: Total Biaya | N7: Rp / kg | O7: USD/MT
B8: 1 | C8: Bleaching Earth | D8: ='November 2024'!$AL$73 -> 0.67510642 | F8: =($D$8*$N$3*10) -> 6253.1364 | G8: Kg/day | H8: =$N$4 -> 22 | J8: =$H$8*$F$8 -> 137569 | K8: 2400 | M8: =$J$8*$K$8 -> 330165600 | N8: =$M$8/($N$5*1000) -> 16.202554 | O8: =($M$8/$N$6)/$N$5 -> 1.042233
B9: 2 | C9: Phosporic acid | D9: ='November 2024'!$AL$77 -> 0.05248819 | F9: =($D$9*$N$3*10) -> 486.169 | G9: Kg/day | H9: =$H$8 -> 22 | J9: =$H$9*$F$9 -> 10695.718 | K9: 17420 | M9: =$J$9*$K$9 -> 1.8631941e+08 | N9: =$M$9/($N$5*1000) -> 9.1434428 | O9: =($M$9/$N$6)/$N$5 -> 0.58815404
B10: 3 | C10: Caustic Soda | D10: 29.166667 | E10: kg/day | F10: =D10 -> 29.166667 | G10: kg/day | H10: =$H$8 -> 22 | J10: =$H$10*$F$10 -> 641.66667 | K10: 15700 | M10: =$J$10*$K$10 -> 10074167 | N10: =$M$10/($N$5*1000) -> 0.49437988 | O10: =($M$10/$N$6)/$N$5 -> 0.031801099
B11: 4 | C11: Pemakaian Natural Gas HPB Geka
C12: Normal Consumption | D12: ='November 2024'!$AL$237 -> 0.19652565 | E12: MMBTU/MT CPO | F12: =$D$12*$N$3 -> 182.03081 | G12: MMBTU/day | H12: =$H$8 -> 22 | J12: =$H$12*$F$12 -> 4004.6778 | K12: =11.5*$N$6 -> 178779 | M12: =$J$12*$K$12 -> 7.1595229e+08 | N12: =$M$12/($N$5*1000) -> 35.134659 | O12: =($M$12/$N$6)/$N$5 -> 2.2600449
C13: Penalty Below Consumption | D13: 0 | E13: MMBTU/MT CPO | F13: =$D$13*$N$3 -> 0 | G13: MMBTU/day | H13: =$H$8 -> 22 | J13: =$H$13*$F$13 -> 0 | K13: =11.5*$N$6 -> 178779 | M13: =$J$13*$K$13 -> 0 | N13: =$M$13/($N$5*1000) -> 0 | O13: =($M$13/$N$6)/$N$5 -> 0
C14: Penalty Above Consumption | D14: 0 | E14: MMBTU/MT CPO | F14: =$D$14*$N$3 -> 0 | G14: MMBTU/day | H14: =$H$8 -> 22 | J14: =$H$14*$F$14 -> 0 | K14: =11.5*$N$6 -> 178779 | M14: =$J$14*$K$14 -> 0 | N14: =$M$14/($N$5*1000) -> 0 | O14: =($M$14/$N$6)/$N$5 -> 0
B15: 5 | C15: Pemakaian Steam
C16: For Process | D16: ='November 2024'!$AL$244 -> 177.25046 | E16: Kg/MT CPO | F16: =$D$16*$N$3/1000 -> 164.17727 | G16: Ton/day | H16: =$H$8 -> 22 | J16: =$H$16*$F$16 -> 3611.9 | K16: =Steam!H15 -> 691601.86 | M16: =$J$16*$K$16 -> 2.4979968e+09 | N16: =$M$16/($N$5*1000) -> 122.58675 | O16: =($M$16/$N$6)/$N$5 -> 7.8854206
C17: Storage Tank for Heating | D17: ='November 2024'!$AL$248 -> 85.318132 | E17: Kg/MT CPO | F17: =$D$17*$N$3/1000 -> 79.025455 | G17: Ton/day | H17: =$H$8 -> 22 | J17: =$H$17*$F$17 -> 1738.56 | K17: =Steam!H15 -> 691601.86 | M17: =$J$17*$K$17 -> 1.2023913e+09 | N17: =$M$17/($N$5*1000) -> 59.006179 | O17: =($M$17/$N$6)/$N$5 -> 3.7955859
B18: 6 | C18: Pemakaian Electrical
C19: For Process | D19: ='November 2024'!$AL$267 -> 3.1255245 | E19: kW/MT CPO | F19: =$D$19*$N$3 -> 2895 | G19: kW/day | H19: =$H$8 -> 22 | I19: 0 | J19: =$H$19*$F$19 -> 63690 | K19: 1550 | L19: =[23]Electric!H21 -> 3666.6667 | M19: =($F$19*$H$19*$K$19)+($F$19*$I$19*$L$19) -> 98719500 | N19: =$M$19/($N$5*1000) -> 4.8445629 | O19: =($M$19/$N$6)/$N$5 -> 0.31162762
C20: Cooling Tower | D20: ='November 2024'!$AL$269 -> 3.5971258 | E20: kW/MT CPO | F20: =$D$20*$N$3 -> 3331.8182 | G20: kW/day | H20: =$H$8 -> 22 | I20: 0 | J20: =$H$20*$F$20 -> 73300 | K20: 1550 | L20: =L19 -> 3666.6667 | M20: =(F20*H20*K20)+(F20*I20*L20) -> 113615000 | N20: =$M$20/($N$5*1000) -> 5.575545 | O20: =($M$20/$N$6)/$N$5 -> 0.35864821
C21: Storage Tank | D21: 0.3377877 | E21: kW/MT CPO | F21: =$D$21*$N$3 -> 312.87401 | G21: kW/day | H21: =$H$8 -> 22 | I21: 0 | J21: =$H$21*$F$21 -> 6883.2283 | K21: 1550 | L21: =L20 -> 3666.6667 | M21: =($F$21*$H$21*$K$21)+($F$21*$I$21*$L$21) -> 10669004 | N21: =$M$21/($N$5*1000) -> 0.52357093 | O21: =($M$21/$N$6)/$N$5 -> 0.03367882
B22: 7 | C22: Pemakaian Water
C23: Make Up CT | D23: ='November 2024'!$AL$254 -> 100.20915 | E23: M3/day | F23: =$D$23 -> 100.20915 | G23: M3/day | H23: =$H$8 -> 22 | J23: =$H$23*$F$23 -> 2204.6014 | K23: =WTP!H13 -> 16483.459 | M23: =$J$23*$K$23 -> 36339457 | N23: =$M$23/($N$5*1000) -> 1.7833233 | O23: =($M$23/$N$6)/$N$5 -> 0.11471268
B24: 8 | C24: Chemical Water | N24: =$M$24/($N$5*1000) -> 0 | O24: =($M$24/$N$6)/$N$5 -> 0
C25: EONBAC BC 3108 | D25: 0.4 | E25: Kg/day | F25: =D25 -> 0.4 | G25: Kg/day | H25: =$H$8 -> 22 | J25: =$H$25*$F$25 -> 8.8 | K25: 27240 | M25: =$J$25*$K$25 -> 239712 | N25: =$M$25/($N$5*1000) -> 0.011763632 | O25: =($M$25/$N$6)/$N$5 -> 0.00075669832
C26: EONLINE T722 | D26: 0.66 | E26: Kg/day | F26: =D26 -> 0.66 | G26: Kg/day | H26: =$H$8 -> 22 | J26: =$H$26*$F$26 -> 14.52 | K26: 29120 | M26: =$J$26*$K$26 -> 422822.4 | N26: =$M$26/($N$5*1000) -> 0.020749596 | O26: =($M$26/$N$6)/$N$5 -> 0.0013347225
C27: EONLINE AG5770 | D27: 0.41 | E27: Kg/day | F27: =D27 -> 0.41 | G27: Kg/day | H27: =$H$8 -> 22 | J27: =$H$27*$F$27 -> 9.02 | K27: 117212 | M27: =$J$27*$K$27 -> 1057252.2 | N27: =$M$27/($N$5*1000) -> 0.05188362 | O27: =($M$27/$N$6)/$N$5 -> 0.0033374257
C28: EONScale T2511 | D28: 0.1 | E28: Kg/day | F28: =D28 -> 0.1 | G28: Kg/day | H28: =$H$8 -> 22 | J28: =$H$28*$F$28 -> 2.2 | K28: 45940 | M28: =$J$28*$K$28 -> 101068 | N28: =$M$28/($N$5*1000) -> 0.0049598133 | O28: =($M$28/$N$6)/$N$5 -> 0.00031904112
B29: 9 | C29: Others
C30: Filter Bag 10 Microne | D30: 0.90361446 | E30: Pcs/day | F30: =D30 -> 0.90361446 | G30: Pcs/day | H30: =$H$8 -> 22 | J30: =$H$30*$F$30 -> 19.879518 | K30: 40000 | M30: =$J$30*$K$30 -> 795180.72 | N30: =$M$30/($N$5*1000) -> 0.039022717 | O30: =($M$30/$N$6)/$N$5 -> 0.0025101452
C31: Filter Bag 100 Microne | D31: 0.63253012 | E31: Pcs/day | F31: =D31 -> 0.63253012 | G31: Pcs/day | H31: =$H$8 -> 22 | J31: =$H$31*$F$31 -> 13.915663 | K31: 125000 | M31: =$J$31*$K$31 -> 1739457.8 | N31: =$M$31/($N$5*1000) -> 0.085362192 | O31: =($M$31/$N$6)/$N$5 -> 0.0054909425
C32: Filter Cartridge 10 Microne | D32: 1.5666667 | E32: Pcs/day | F32: =D32 -> 1.5666667 | G32: Pcs/day | H32: =$H$8 -> 22 | J32: =$H$32*$F$32 -> 34.466667 | K32: 145000 | M32: =$J$32*$K$32 -> 4997666.7 | N32: =$M$32/($N$5*1000) -> 0.24525561 | O32: =($M$32/$N$6)/$N$5 -> 0.015776123
C33: Filter Dustbag | D33: 0.12048193 | E33: Pcs/day | F33: =D33 -> 0.12048193 | G33: Pcs/day | H33: =$H$8 -> 22 | J33: =$H$33*$F$33 -> 2.6506024 | K33: 682500 | M33: =$J$33*$K$33 -> 1809036.1 | N33: =$M$33/($N$5*1000) -> 0.08877668 | O33: =($M$33/$N$6)/$N$5 -> 0.0057105802
C34: O Ring Filter Leaves | D34: 3.6144578 | E34: Pcs/day | F34: =D34 -> 3.6144578 | G34: Pcs/day | H34: =$H$8 -> 22 | J34: =$H$34*$F$34 -> 79.518072 | K34: 14500 | M34: =$J$34*$K$34 -> 1153012 | N34: =$M$34/($N$5*1000) -> 0.056582939 | O34: =($M$34/$N$6)/$N$5 -> 0.0036397105
B35: 10 | C35: Waste Water Treatment Plant ( WWTP ) | D35: ='November 2024'!$AL$260 -> 277.77273 | E35: M3/day | F35: =D35 -> 277.77273 | G35: M3/day | H35: =$H$8 -> 22 | J35: =$H$35*$F$35 -> 6111 | K35: =WWTP!H17 -> 15205.393 | M35: =$J$35*$K$35 -> 92920154 | N35: =$M$35/($N$5*1000) -> 4.5599657 | O35: =($M$35/$N$6)/$N$5 -> 0.29332084
B36: 11 | C36: SHE
C37: SBE | D37: ='November 2024'!$AL$81 -> 138939.49 | E37: Kg/day | F37: =D37 -> 138939.49 | G37: Kg/day | H37: =$H$8 -> 22 | J37: =$F$37 -> 138939.49 | K37: 275 | M37: =$J$37*$K$37 -> 38208359 | N37: =$M$37/($N$5*1000) -> 1.8750379 | O37: =($M$37/$N$6)/$N$5 -> 0.12061224
C38: Domestic | D38: 0.1 | E38: Trip/day | F38: =D38 -> 0.1 | G38: Trip/day | H38: =$H$8 -> 22 | J38: =$H$38*$F$38 -> 2.2 | K38: 303030.3 | M38: =$J$38*$K$38 -> 666666.67 | N38: =$M$38/($N$5*1000) -> 0.032716015 | O38: =($M$38/$N$6)/$N$5 -> 0.0021044651
B39: 12 | C39: Chemical Consumption | N39: =$M$39/($N$5*1000) -> 0 | O39: =($M$39/$N$6)/$N$5 -> 0
C40: LAB Chemical | D40: =lab!H33 -> 745255.21 | E40: Rp/day | F40: =D40 -> 745255.21 | G40: Rp/day | H40: =$H$8 -> 22 | M40: =$H$40*$F$40 -> 16395615 | N40: =$M$40/($N$5*1000) -> 0.80459876 | O40: =($M$40/$N$6)/$N$5 -> 0.051755999
C41: Chemical Boiler dan WTP | D41: =lab!H54 -> 259161.44 | E41: Rp/day | F41: =D41 -> 259161.44 | G41: Rp/day | H41: =$H$8 -> 22 | M41: =$H$41*$F$41 -> 5701551.8 | N41: =$M$41/($N$5*1000) -> 0.27979808 | O41: =($M$41/$N$6)/$N$5 -> 0.017998075
C42: Sample and Analysis | D42: 13909.091 | E42: Rp/day | F42: =D42 -> 13909.091 | G42: Rp/day | H42: =$H$8 -> 22 | M42: =$H$42*$F$42 -> 306000 | N42: =$M$42/($N$5*1000) -> 0.015016651 | O42: =($M$42/$N$6)/$N$5 -> 0.00096594949
C43: Chemical WWTP | D43: =[23]Chemical!$H$61 -> 27103.641 | E43: Rp/day | F43: =D43 -> 27103.641 | G43: Rp/day | H43: =$H$8 -> 22 | M43: =$H$43*$F$43 -> 596280.11 | N43: =$M$43/($N$5*1000) -> 0.029261863 | O43: =($M$43/$N$6)/$N$5 -> 0.0018822761
C44: Consumable Part | D44: =lab!I111 -> 135770.31 | E44: Rp/day | F44: =D44 -> 135770.31 | G44: Rp/day | H44: =$H$8 -> 22 | M44: =$H$44*$F$44 -> 2986946.8 | N44: =$M$44/($N$5*1000) -> 0.14658149 | O44: =($M$44/$N$6)/$N$5 -> 0.009428888
B45: 13 | C45: Solar
C46: Forklift -1 (3 Ton) | D46: 15.4 | E46: Ltr/day | F46: =D46 -> 15.4 | G46: Ltr/day | H46: =$H$8 -> 22 | J46: =$H$46*$F$46 -> 338.8 | K46: 14500 | M46: =$J$46*$K$46 -> 4912600 | N46: =$M$46/($N$5*1000) -> 0.24108104 | O46: =($M$46/$N$6)/$N$5 -> 0.015507593
C47: WA Loader | D47: 0 | E47: Ltr/day | F47: =D47 -> 0 | G47: Ltr/day | H47: =$H$8 -> 22 | J47: =$H$47*$F$47 -> 0 | K47: 14500 | M47: =$J$47*$K$47 -> 0 | N47: =$M$47/($N$5*1000) -> 0 | O47: =($M$47/$N$6)/$N$5 -> 0
M48: =SUM($M$8:$M$47) -> 5.3772519e+09 | N48: =SUM($N$8:$N$47) -> 263.88338 | O48: =SUM($O$8:$O$47) -> 16.974359

Sheet HPP FRACT
B2: Fractionation Cost
B3: RPO Proses / Day | N3: TPD | O3: =('November 2024'!AL24)/1000 -> 905.74317
B4: Working Day | N4: Days | O4: ='November 2024'!AL21 -> 24
B5: Total CPO Process | N5: MTD | O5: =O3*O4 -> 21737.836
B6: KURS | N6: Rp/USD | O6: ='SUMMARY HPP '!I9 -> 15546
B7: No | C7: Item Cost | D7: Norma | F7: Pemakaian / Hari | H7: HK | J7: Total Pemakaian | K7: Harga / stn | M7: Total Biaya | N7: Rp / kg | O7: USD/MT
B8: 1 | C8: Steam | D8: ='November 2024'!$AL$246 -> 82.662322 | E8: Kg/MT CPO | F8: =$D$8*$O$3/1000 -> 74.870833 | G8: Ton/day | H8: =$O$4 -> 24 | J8: =$H$8*$F$8 -> 1796.9 | K8: =Steam!H15 -> 691601.86 | M8: =$K$8*$J$8 -> 1.2427394e+09 | N8: =$M$8/($O$5*1000) -> 57.169416 | O8: =($M$8/$O$6)/$O$5 -> 3.6774357
B9: 2 | C9: Electrical
C10: For Process | D10: ='November 2024'!$AL$274 -> 4.4300638 | E10: kW/MT CPO | F10: =$D$10*$O$3 -> 4012.5 | G10: kW/day | H10: =$O$4 -> 24 | I10: 0 | J10: =$H$10*$F$10 -> 96300 | K10: =[23]Electric!$L$5 -> 1550 | L10: 3666.6667 | M10: =($F$10*$H$10*$K$10)+($F$10*$I$10*$L$10) -> 1.49265e+08 | N10: =$M$10/($O$5*1000) -> 6.8665989 | O10: =($M$10/$O$6)/$O$5 -> 0.44169554
C11: Cooling Tower | D11: ='November 2024'!$AL$272 -> 1.0792243 | E11: kW/MT CPO | F11: =$D$11*$O$3 -> 977.5 | G11: kW/day | H11: =$H$10 -> 24 | I11: 0 | J11: =$H$11*$F$11 -> 23460 | K11: =$K$10 -> 1550 | L11: 3666.6667 | M11: =($F$11*$H$11*$K$11)+($F$11*$I$11*$L$11) -> 36363000 | N11: =$M$11/($O$5*1000) -> 1.6727976 | O11: =($M$11/$O$6)/$O$5 -> 0.10760309
B12: 3 | C12: Water
C13: Make Up CT | D13: ='November 2024'!$AL$256 -> 99.273911 | E13: M3/day | F13: =$D$13 -> 99.273911 | G13: M3/day | H13: =$H$11 -> 24 | J13: =$H$13*$F$13 -> 2382.5739 | K13: =WTP!H13 -> 16483.459 | M13: =$K$13*$J$13 -> 39273059 | N13: =$M$13/($O$5*1000) -> 1.8066683 | O13: =($M$13/$O$6)/$O$5 -> 0.11621435
B14: 4 | C14: Chemical Water
C15: EONBAC BC 3108 | D15: 0.4 | E15: Kg/day | F15: =$D$15 -> 0.4 | G15: Kg/day | H15: =$H$13 -> 24 | J15: =$H$15*$F$15 -> 9.6 | K15: 27240 | M15: =$K$15*$J$15 -> 261504 | N15: =$M$15/($O$5*1000) -> 0.0120299 | O15: =($M$15/$O$6)/$O$5 -> 0.00077382608
C16: EONLINE T722 | D16: 0.66 | E16: Kg/day | F16: =$D$16 -> 0.66 | G16: Kg/day | H16: =$H$15 -> 24 | J16: =$H$16*$F$16 -> 15.84 | K16: 29120 | M16: =$K$16*$J$16 -> 461260.8 | N16: =$M$16/($O$5*1000) -> 0.02121926 | O16: =($M$16/$O$6)/$O$5 -> 0.0013649338
C17: EONLINE AG5770 | D17: 0.41 | E17: Kg/day | F17: =$D$17 -> 0.41 | G17: Kg/day | H17: =$H$15 -> 24 | J17: =$H$17*$F$17 -> 9.84 | K17: 117212 | M17: =$K$17*$J$17 -> 1153366.1 | N17: =$M$17/($O$5*1000) -> 0.053057999 | O17: =($M$17/$O$6)/$O$5 -> 0.0034129679
C18: EONScale T2511 | D18: 0.1 | E18: Kg/day | F18: =$D$18 -> 0.1 | G18: Kg/day | H18: =$H$16 -> 24 | J18: =$H$18*$F$18 -> 2.4 | K18: 45940 | M18: =$K$18*$J$18 -> 110256 | N18: =$M$18/($O$5*1000) -> 0.005072078 | O18: =($M$18/$O$6)/$O$5 -> 0.00032626258
B19: 5 | C19: Others
C20: Filter Cloth | D20: 0.33333333 | E20: Pcs/day | F20: =$D$20 -> 0.33333333 | G20: Pcs/day | H20: =$H$18 -> 24 | J20: =$H$20*$F$20 -> 8 | K20: 895000 | M20: =$K$20*$J$20 -> 7160000 | N20: =$M$20/($O$5*1000) -> 0.32937961 | O20: =($M$20/$O$6)/$O$5 -> 0.021187419
C21: Filter Bag 100 Microne | D21: 0.63253012 | E21: Pcs/day | F21: =$D$21 -> 0.63253012 | G21: Pcs/day | H21: =$H$20 -> 24 | J21: =$H$21*$F$21 -> 15.180723 | K21: 125000 | M21: =$K$21*$J$21 -> 1897590.4 | N21: =$M$21/($O$5*1000) -> 0.087294354 | O21: =($M$21/$O$6)/$O$5 -> 0.0056152293
M22: =SUM(M8:M21) -> 1.4786844e+09 | N22: =SUM(N8:N21) -> 68.023534 | O22: =SUM($O$8:$O$21) -> 4.3756293

Sheet Steam
B2: Steam Price Package Boiler | G2: Kurs | H2: ='SUMMARY HPP '!I9 -> 15546
B3: Consumable Item | C3: Norma | E3: Consumption, Ton/day | F3: Unit Price | H3: Total Cost
B4: Steam Production (Including Dearator) | C4: =408/24 -> 17 | D4: Ton/jam | E4: ='November 2024'!AL242 -> 345.23092 | H4: Rp/day
B5: Gas | C5: 1000 | D5: MMBTU/day | E5: ='November 2024'!$AL$233 -> 1308.2028 | F5: 11.5 | G5: USD/MMBTU | H5: =E5*H2*F5 -> 2.3387919e+08 | I5: Harga steam tinggi dikarenakan oleh unit price gas yang tinggi, ideal (9.6)
B6: Chemical Treatment
B7: EONALKALOX B1414 | C7: 7.3 | D7: l/day | E7: =C7 -> 7.3 | F7: 25340 | G7: Rp/l | H7: =E7*F7 -> 184982
B8: EONCONDENS B1720 | C8: 2.4 | D8: l/day | E8: =C8 -> 2.4 | F8: 110000 | G8: Rp/l | H8: =E8*F8 -> 264000
B9: EONOXY B8100 | C9: 2.4 | D9: l/day | E9: =C9 -> 2.4 | F9: 20160 | G9: Rp/l | H9: =E9*F9 -> 48384
B10: EONSCALE B5100 | C10: 5.8 | D10: l/day | E10: =C10 -> 5.8 | F10: 31800 | G10: Rp/l | H10: =E10*F10 -> 184440
B11: EONDESCALER B2550 | C11: 1.4 | D11: l/day | E11: =C11 -> 1.4 | F11: 39320 | G11: Rp/l | H11: =E11*F11 -> 55048
B12: Water Demin | C12: =[32]L.Water!C12*83% -> 408.0197 | D12: M3/day | E12: =C12 -> 408.0197 | F12: =[32]L.Water!F12 -> 10162 | G12: Rp/m3 | H12: =E12*F12 -> 4146296.2
B13: Preventive Maintenance | D13: Rp/day | H13: =C13 -> 0
B14: Total Pakage Boiler | H14: =IFERROR(SUM(H5:H13),"") -> 2.3876234e+08
F15: Unit Price, Rp/Ton | H15: =H14/E4 -> 691601.86
B17: Note :
B18: 1. Harga gas, secara general untuk industri adalah 9,21-9,6 usd/mmBtu
C26: Kurita H-504 18:25

Sheet WWTP
B2: Water Waste Treatment Plant | G2: Kurs | H2: ='SUMMARY HPP '!I9 -> 15546
B3: Consumable Item | C3: Norma | E3: Consumption, M3/day | F3: Unit Price | H3: Total Cost
B4: Waste Water Feed | C4: =200/24 -> 8.3333333 | D4: M3/jam | E4: ='November 2024'!AL260 -> 277.77273 | H4: Rp/day
B5: biaya transfer ke kawasan | F5: 0 | G5: Rp/m3 | H5: 8700
B6: Chemical Treatment
B7: Sugar | C7: 0 | D7: kg/day | E7: =C7 -> 0 | F7: 24890 | G7: Rp/kg | H7: =E7*F7 -> 0
B8: PE | C8: =E8*C4 -> 0.62305296 | D8: kg/day | E8: 0.074766355 | F8: 65340 | G8: Rp/kg | H8: =E8*F8 -> 4885.2336
B9: PAC | C9: =E9*C4 -> 46.728972 | D9: kg/day | E9: 5.6074766 | F9: 7702 | G9: Rp/kg | H9: =E9*F9 -> 43188.785
B10: Urea | C10: =E10*C4 -> 6.2305296 | D10: kg/day | E10: 0.74766355 | F10: 18634 | G10: Rp/kg | H10: =E10*F10 -> 13931.963
B11: TSP | C11: =E11*C4 -> 1.2461059 | D11: kg/day | E11: 0.14953271 | F11: 44722 | G11: Rp/kg | H11: =E11*F11 -> 6687.4019
B12: HCL | C12: 0 | D12: kg/day | E12: =C12 -> 0 | F12: 5700 | G12: Rp/kg | H12: =E12*F12 -> 0
B13: NaOH | C13: 0 | D13: kg/day | E13: =C13 -> 0 | F13: 15700 | G13: Rp/kg | H13: =E13*F13 -> 0
B14: Power | C14: 2675 | D14: kW/day | E14: =C14 -> 2675 | F14: =[33]UP.E!C28 -> 1550 | G14: Rp/kW | H14: =E14*F14 -> 4146250
B15: Preventive Maintenance | D15: Rp/day | H15: =E15*F15 -> 0
H16: =IFERROR(SUM(H5:H15),"") -> 4223643.4
F17: Unit Price, Rp/M3 | H17: =H16/E4 -> 15205.393
C29: Kurita H-504 18:25

Sheet WTP
B2: Water Treatment Plant | G2: Kurs | H2: ='SUMMARY HPP '!I9 -> 15546
B3: Consumable Item | C3: Norma | E3: Consumption, M3/day | F3: Unit Price | H3: Total Cost
B4: Water Treatment Plant | C4: =1000/24 -> 41.666667 | D4: M3/jam | E4: ='November 2024'!AL252 -> 1774 | H4: Rp/day
B5: Chemical | F5: 8700 | G5: Rp/m3 | H5: =F5*E4 -> 15433800
B6: anti scalant | C6: 0.1 | D6: kg/day | E6: =C6 -> 0.1 | F6: 44500 | G6: Rp/kg | H6: =E6*F6 -> 4450
B7: caustic soda | C7: 0.1 | D7: kg/day | E7: =C7 -> 0.1 | F7: 65340 | G7: Rp/kg | H7: =E7*F7 -> 6534
B8: citrid acid | C8: 0.1 | D8: kg/day | E8: =C8 -> 0.1 | F8: 33275 | G8: Rp/kg | H8: =E8*F8 -> 3327.5
B9: bioside | C9: 0.1 | D9: kg/day | E9: =C9 -> 0.1 | F9: 47450 | G9: Rp/kg | H9: =E9*F9 -> 4745
B10: Power | C10: 8896 | D10: kW/day | E10: =C10 -> 8896 | F10: =[33]UP.E!C28 -> 1550 | G10: Rp/kW | H10: =E10*F10 -> 13788800
B11: Preventive Maintenance | D11: Rp/day | H11: =E11*F11 -> 0
H12: =IFERROR(SUM(H5:H11),"") -> 29241656
F13: Unit Price, Rp/M3 | H13: =H12/E4 -> 16483.459
C25: Kurita H-504 18:25

Sheet lab
B2: Laboratorium Chemical Cost
B3: Consumable Item | C3: Norma | E3: Consumption/ Hari | F3: Unit Price | H3: Total Biaya
H4: Per Hari
B5: Refinery, Fraksinasi, Packaging & Sotrage tank
B6: Acetic Acid Glacial | C6: 50 | D6: ml | E6: =C6 -> 50 | F6: 374 | G6: ml | H6: =E6*F6 -> 18700
B7: Aquadest | C7: 2 | D7: liter | E7: =C7 -> 2 | F7: 7250 | G7: liter | H7: =E7*F7 -> 14500
B8: BF3-methanol solution, Reagen Grade | C8: 0.5 | D8: ml | E8: =C8 -> 0.5 | F8: 500 | G8: ml | H8: =E8*F8 -> 250
B9: Chloroform | C9: 70 | D9: ml | E9: =C9 -> 70 | F9: 388 | G9: ml | H9: =E9*F9 -> 27160
B10: Cyclohexane | C10: 70 | D10: ml | E10: =C10 -> 70 | F10: 612 | G10: ml | H10: =E10*F10 -> 42840
B11: Hydrazine Sulphate | C11: 0.05 | D11: gr | E11: =C11 -> 0.05 | F11: 21000 | G11: gr | H11: =E11*F11 -> 1050
B12: Hydrochloric Acid 37% | C12: 2.6 | D12: ml | E12: =C12 -> 2.6 | F12: 236 | G12: ml | H12: =E12*F12 -> 613.6
B13: Iso Propanol Alcohol TG | C13: 5.5 | D13: liter | E13: =C13 -> 5.5 | F13: 35000 | G13: liter | H13: =E13*F13 -> 192500
B14: Isooctane | C14: 150 | D14: ml | E14: =C14 -> 150 | F14: 480 | G14: ml | H14: =E14*F14 -> 72000
B15: Indikator Phenolpthalaein 1 % | C15: 0.3 | D15: gr | E15: =C15 -> 0.3 | F15: 6750 | G15: gr | H15: =E15*F15 -> 2025
B16: Indikator Thymolpthalaein | C16: =36/357 -> 0.10084034 | D16: gr | E16: =C16 -> 0.10084034 | F16: 90000 | G16: gr | H16: =E16*F16 -> 9075.6303
B17: Starch | C17: =107/357 -> 0.29971989 | D17: gr | E17: =C17 -> 0.29971989 | F17: 3000 | G17: gr | H17: =E17*F17 -> 899.15966
B18: Liquid standard Lovibond 3,4R 30,0 Y 0,9N | C18: 0.1 | D18: ml | E18: =C18 -> 0.1 | F18: 70000 | G18: ml | H18: =E18*F18 -> 7000
B19: Liquid standard Lovibond 3,0R 28,0Y | C19: 0.1 | D19: ml | E19: =C19 -> 0.1 | F19: 70000 | G19: ml | H19: =E19*F19 -> 7000
B20: n-HexaneTehcnis | C20: 0.5 | D20: liter | E20: =C20 -> 0.5 | F20: 19300 | G20: liter | H20: =E20*F20 -> 9650
B21: p-Anisidine | C21: =48/357 -> 0.13445378 | D21: gr | E21: =C21 -> 0.13445378 | F21: 7600 | G21: gr | H21: =E21*F21 -> 1021.8487
B22: Wijs Solution | C22: 120 | D22: ml | E22: =C22 -> 120 | F22: 502 | G22: ml | H22: =E22*F22 -> 60240
B23: N2 (UHP) gas refill for GC & Foam test | C23: 0.02 | D23: Liter | E23: =C23 -> 0.02 | F23: 5000000 | G23: Liter | H23: =E23*F23 -> 100000
B24: H2 (UHP) gas refill for GC | C24: 0.03 | D24: Liter | E24: =C24 -> 0.03 | F24: 2500000 | G24: Liter | H24: =E24*F24 -> 75000
B25: UT (UHP) gas refill for GC | C25: 0.03 | D25: Liter | E25: =C25 -> 0.03 | F25: 1250000 | G25: Liter | H25: =E25*F25 -> 37500
B26: Zinc Oksida GR | C26: =179/357 -> 0.50140056 | D26: gr | E26: =C26 -> 0.50140056 | F26: 2000 | G26: gr | H26: =E26*F26 -> 1002.8011
B27: Potassium Dihydrogen Phosphate | C27: =250/357 -> 0.70028011 | D27: gr | E27: =C27 -> 0.70028011 | F27: 765 | G27: gr | H27: =E27*F27 -> 535.71429
B28: Pottasium Hydrogen Phtalate | C28: =250/357 -> 0.70028011 | D28: gr | E28: =C28 -> 0.70028011 | F28: 5200 | G28: gr | H28: =E28*F28 -> 3641.4566
B29: Sodium Thiosulphate | C29: =6069/357 -> 17 | D29: gr | E29: =C29 -> 17 | F29: 950 | G29: gr | H29: =E29*F29 -> 16150
B30: Potassium Iodide | C30: 12 | D30: gr | E30: =C30 -> 12 | F30: 2400 | G30: gr | H30: =E30*F30 -> 28800
B31: Pottasium Dichromate | C31: =357/357 -> 1 | D31: gr | E31: =C31 -> 1 | F31: 4200 | G31: gr | H31: =E31*F31 -> 4200
B32: Sodium Hydroxide | C32: =6069/357 -> 17 | D32: gr | E32: =C32 -> 17 | F32: 700 | G32: gr | H32: =E32*F32 -> 11900
B33: Sub Total | H33: =SUM(H6:H32) -> 745255.21
B35: Consumable Item | C35: Norma | E35: Consumption/day | F35: Unit Price | H35: Total Price
H36: Per Day
B37: Chemical Boiler & WTP
B38: Sodium Molybdate | C38: =286/357 -> 0.80112045 | D38: gr | E38: =C38 -> 0.80112045 | F38: 4000 | G38: gr | H38: =E38*F38 -> 3204.4818
B39: Iron test 0.0025 - 5.00 mg/l | C39: =1785/357 -> 5 | D39: Test | E39: =C39 -> 5 | F39: 10100 | G39: Test | H39: =E39*F39 -> 50500
B40: Phosphate Test 0.5 - 30 mg/l PO4-P | C40: =714/357 -> 2 | D40: pcs | E40: =C40 -> 2 | F40: 8160 | G40: pcs | H40: =E40*F40 -> 16320
B41: Sulfite Test 1,0-60,0 mg/l SO3 | C41: =360/357 -> 1.0084034 | D41: Pcs | E41: =C41 -> 1.0084034 | F41: 26550 | G41: Pcs | H41: =E41*F41 -> 26773.109
B42: Silica Test 0-800 mg/L | C42: =714/357 -> 2 | D42: pcs | E42: =C42 -> 2 | F42: 31700 | G42: pcs | H42: =E42*F42 -> 63400
B43: Silicate (Silicic Acid) 0,3-10 mg/L | C43: 2.5 | D43: pcs | E43: =C43 -> 2.5 | F43: 31006 | G43: pcs | H43: =E43*F43 -> 77515
B44: Ammonium Vanadate | C44: =179/357 -> 0.50140056 | D44: gr | E44: =C44 -> 0.50140056 | F44: 11950 | G44: gr | H44: =E44*F44 -> 5991.7367
B45: Ammonium Chloride | C45: =214/357 -> 0.59943978 | D45: gr | E45: =C45 -> 0.59943978 | F45: 2545 | G45: gr | H45: =E45*F45 -> 1525.5742
B46: Ammonium Hidroksida | C46: =1714/357 -> 4.8011204 | D46: mL | E46: =C46 -> 4.8011204 | F46: 930 | G46: mL | H46: =E46*F46 -> 4465.042
B47: Mg EDTA | C47: =71/357 -> 0.19887955 | D47: gr | E47: =C47 -> 0.19887955 | F47: 21050 | G47: gr | H47: =E47*F47 -> 4186.4146
B48: Pottasium Carbonat | C48: =12/357 -> 0.033613445 | D48: gr | E48: =C48 -> 0.033613445 | F48: 12500 | G48: gr | H48: =E48*F48 -> 420.16807
B49: Trietanolamin | C49: 0.08 | D49: mL | E49: =C49 -> 0.08 | F49: 8160 | G49: mL | H49: =E49*F49 -> 652.8
B50: Indikator EBT | C50: =12/357 -> 0.033613445 | D50: gr | E50: =C50 -> 0.033613445 | F50: 23400 | G50: gr | H50: =E50*F50 -> 786.55462
B51: Indikator Calcon | C51: =12/357 -> 0.033613445 | D51: gr | E51: =C51 -> 0.033613445 | F51: 50800 | G51: gr | H51: =E51*F51 -> 1707.563
B52: Hydroxylammonium Chloride GR | C52: 0.08 | D52: gr | E52: =C52 -> 0.08 | F52: 6250 | G52: gr | H52: =E52*F52 -> 500
B53: Eriocrom Black T-Metal | C53: 0.05 | D53: gr | E53: =C53 -> 0.05 | F53: 24260 | G53: gr | H53: =E53*F53 -> 1213
B54: Sub Total | H54: =SUM(H38:H53) -> 259161.44
B56: Consumable Item | C56: Norma | E56: Consumption/day | F56: Unit Price | H56: Total Price
H57: Per Day
B58: Chemical WWTP
B59: COD cell test 50 - 500 mg/l | C59: =59/357 -> 0.16526611 | D59: pcs | E59: =C59 -> 0.16526611 | F59: 82000 | G59: pcs | H59: =E59*F59 -> 13551.821
B60: COD cell test 500 - 10000 mg/l | C60: =59/357 -> 0.16526611 | D60: pcs | E60: =C60 -> 0.16526611 | F60: 82000 | G60: pcs | H60: =E60*F60 -> 13551.821
B61: Sub Total | H61: =SUM(H59:H60) -> 27103.641
B63: Total keseluruhan | H63: =H61+H54+H33 -> 1031520.3
C67: Spere Part Laboratorium
B68: No | C68: Consumable Item | D68: Norma | F68: Consumption/day | G68: Unit Price | I68: Total Price
I69: Per Day
B70: 1 | C70: Batang pengaduk | D70: 12 | E70: Pcs/Tahun | F70: =D70/357 -> 0.033613445 | G70: 35000 | H70: Rp/Pcs | I70: =F70*G70 -> 1176.4706
B71: =B70+1 -> 2 | C71: Beaker glass 100 mL | D71: 72 | E71: Pcs/Tahun | F71: =D71/357 -> 0.20168067 | G71: 48000 | H71: Rp/Pcs | I71: =F71*G71 -> 9680.6723
B72: =B71+1 -> 3 | C72: Beaker glass 500 mL | D72: 12 | E72: Pcs/Tahun | F72: =D72/357 -> 0.033613445 | G72: 100000 | H72: Rp/Pcs | I72: =F72*G72 -> 3361.3445
B73: =B72+1 -> 4 | C73: Beaker glass 1000 mL | D73: 6 | E73: Pcs/Tahun | F73: =D73/357 -> 0.016806723 | G73: 120000 | H73: Rp/Pcs | I73: =F73*G73 -> 2016.8067
B74: =B73+1 -> 5 | C74: Beaker glass 2000 mL | D74: 6 | E74: Pcs/Tahun | F74: =D74/357 -> 0.016806723 | G74: 142000 | H74: Rp/Pcs | I74: =F74*G74 -> 2386.5546
B75: =B74+1 -> 6 | C75: Beaker Plastik with handle 1000 mL | D75: 6 | E75: Pcs/Tahun | F75: =D75/357 -> 0.016806723 | G75: 70000 | H75: Rp/Pcs | I75: =F75*G75 -> 1176.4706
B76: =B75+1 -> 7 | C76: Boiling Round Bottom Flask 250 mL | D76: 6 | E76: Pcs/Tahun | F76: =D76/357 -> 0.016806723 | G76: 180000 | H76: Rp/Pcs | I76: =F76*G76 -> 3025.2101
B77: =B76+1 -> 8 | C77: Boiling Round Bottom Flask 1000 mL IKA | D77: 2 | E77: Pcs/Tahun | F77: =D77/357 -> 0.0056022409 | G77: 350000 | H77: Rp/Pcs | I77: =F77*G77 -> 1960.7843
B78: =B77+1 -> 9 | C78: Rotary flask 1000 mL IKA | D78: 2 | E78: Pcs/Tahun | F78: =D78/357 -> 0.0056022409 | G78: 350000 | H78: Rp/Pcs | I78: =F78*G78 -> 1960.7843
B79: =B78+1 -> 10 | C79: Corong 75 mm | D79: 6 | E79: Pcs/Tahun | F79: =D79/357 -> 0.016806723 | G79: 75000 | H79: Rp/Pcs | I79: =F79*G79 -> 1260.5042
B80: =B79+1 -> 11 | C80: Erlenmeyer 250 mL | D80: 72 | E80: Pcs/Tahun | F80: =D80/357 -> 0.20168067 | G80: 90000 | H80: Rp/Pcs | I80: =F80*G80 -> 18151.261
B81: =B80+1 -> 12 | C81: Filtering Flask 500 mL | D81: 2 | E81: Pcs/Tahun | F81: =D81/357 -> 0.0056022409 | G81: 400000 | H81: Rp/Pcs | I81: =F81*G81 -> 2240.8964
B82: =B81+1 -> 13 | C82: Gelas ukur 100 mL | D82: 2 | E82: Pcs/Tahun | F82: =D82/357 -> 0.0056022409 | G82: 85000 | H82: Rp/Pcs | I82: =F82*G82 -> 476.19048
... B110: =B109+1 -> 41 | C110: Magnetic Stirer 8 cm | D110: 12 | E110: Pcs/Tahun | F110: =D110/357 -> 0.033613445 | G110: 85000 | H110: Rp/Pcs | I110: =F110*G110 -> 2857.1429
G111: Total Cost/Days | I111: =SUM(I70:I110) -> 135770.31

Sheet genset
B2: Warming Up Genset
B3: Consumable Item | C3: Norma | E3: Consumption/day | F3: Unit Price | H3: Total Cost | K3: PLN - Power Unit Price
B4: Genset Warming Up | D4: kW/Jam | E4: 0 | H4: Rp/day | K4: Consumable Item | L4: Unit Price
B5: Solar | H5: 0 | K5: PLN Fee | L5: 1550 | M5: Rp/kWh
B6: Genset - 1 (1044 kW) | C6: 100 | D6: Ltr/Jam | E6: =(C6*25%*4)/30 -> 3.3333333 | F6: 14500 | G6: Rp/ltr | H6: =F6*E6 -> 48333.333
B7: Genset - 2 (1044 kW) | C7: 100 | D7: Ltr/Jam | E7: =(C7*25%*4)/30 -> 3.3333333 | F7: 14500 | G7: Rp/ltr | H7: =F7*E7 -> 48333.333
B8: Genset - 3 (1044 kW) | C8: 100 | D8: Ltr/Jam | E8: =(C8*25%*4)/30 -> 3.3333333 | F8: 14500 | G8: Rp/ltr | H8: =F8*E8 -> 48333.333
B9: Preventive Maintenance | D9: Rp/day | H9: 0
B10: Cost Power by Genset | H10: =SUM(H5:H9) -> 145000
B12: Genset - Power Unit Price
B13: Consumable Item | C13: Norma | E13: Power, kW/day | F13: Unit Price | H13: Total Cost
B14: Power Production by Genset | C14: 2088 | D14: kW/Jam | E14: =C14*24 -> 50112 | H14: Rp/day
B15: Solar | H15: 0
B16: Genset - 1 (1044 kW) | C16: 800 | D16: Ltr/Jam | E16: =C16*24 -> 19200 | F16: 14500 | G16: Rp/ltr | H16: =F16*E16 -> 278400000
B17: Genset - 2 (1044 kW) | C17: 800 | D17: Ltr/Jam | E17: =C17*24 -> 19200 | F17: 14500 | G17: Rp/ltr | H17: =F17*E17 -> 278400000
B18: Genset - 3 (1044 kW) | D18: Ltr/Jam | E18: 0 | F18: 14500 | G18: Rp/ltr | H18: =F18*E18 -> 0
B19: Preventive Maintenance | D19: Rp/day | H19: 0
B20: Cost Power by Genset | H20: =SUM(H15:H19) -> 556800000
F21: Unit Price, Rp/Kw | H21: =H20/E14 -> 11111.111 | I21: Unit price terlalu tinggi
B23: Note :
B24: 1. Cross cek kembali consumption solar genset per unit

Sheet AMOR
B2: Amortization
B3: Through Put CPO Proses | H3: TPD | I3: ='HPP REF '!N3 -> 926.24455
B4: Working Day | H4: Day | I4: ='HPP REF '!N4 -> 22
B5: Total CPO Refined | H5: TPM | I5: =I4*I3 -> 20377.38
B6: Kurs Rupiah | I6: ='SUMMARY HPP '!I9 -> 15546
B7: No | C7: Description | D7: Actual 2023 | F7: Budget 2024
D8: Years | E8: Month | F8: Years | G8: Month | H8: RP/KG | I8: USD/MT
B9: 1 | C9: Perangkat Lunak/Software | D9: 9.6270931e+08 | E9: =D9/12 -> 80225776 | F9: =G9*12 -> 5.3192735e+08 | G9: 44327279 | H9: =$G$9/($I$5*1000) -> 2.1753179 | I9: =($G$9/$I$6)/$I$5 -> 0.13992782 | J9: =D9/12 -> 80225776
B10: =B9+1 -> 2 | C10: Sertifikat/Surat Izin | D10: 2.6961444e+08 | E10: =D10/12 -> 22467870 | F10: 0 | G10: 0 | H10: =$G$10/($I$5*1000) -> 0 | I10: =($G$10/$I$6)/$I$5 -> 0
B11: =B10+1 -> 3 | C11: Inventaris Kecil (Aset Sewa) | D11: 0 | E11: =D11/12 -> 0 | F11: 0 | G11: 0 | H11: =$G$11/($I$5*1000) -> 0 | I11: =($G$11/$I$6)/$I$5 -> 0
B12: =B11+1 -> 4 | C12: Aset Hak Guna (ROU) - Kendaraan | D12: 0 | E12: =D12/12 -> 0 | F12: 0 | G12: 0 | H12: =$G$12/($I$5*1000) -> 0 | I12: =($G$12/$I$6)/$I$5 -> 0
B13: =B12+1 -> 5 | C13: Aset Hak Guna (ROU) - Tangki Timbun | D13: 0 | E13: =D13/12 -> 0 | F13: 0 | G13: 0 | H13: =$G$13/($I$5*1000) -> 0 | I13: =($G$13/$I$6)/$I$5 -> 0
B14: =B13+1 -> 6 | C14: Aset Atas Biaya Penyambungan | D14: 0 | E14: =D14/12 -> 0 | F14: 0 | G14: 0 | H14: =$G$14/($I$5*1000) -> 0 | I14: =($G$14/$I$6)/$I$5 -> 0
B15: =B14+1 -> 7 | C15: Aset Hak Guna (ROU) - Pemanfaatan Lahan Sei Mangkei + Surabaya | D15: 1.2576903e+10 | E15: =D15/12 -> 1.0480752e+09 | F15: =G15*12 -> 12048990312 | G15: 1004082526 | H15: =$G$15/($I$5*1000) -> 49.274368 | I15: =($G$15/$I$6)/$I$5 -> 3.169585
B20: Total Cost Depreciation | D20: =SUM(D9:D19) -> 1.3809227e+10 | E20: =SUM(E9:E19) -> 1.1507689e+09 | F20: =SUM(F9:F19) -> 1.2580918e+10 | G20: =SUM(G9:G19) -> 1.0484098e+09 | H20: =SUM(H9:H19) -> 51.449686 | I20: =SUM(I9:I19) -> 3.3095128

Sheet DEP
B2: Depreciation
B3: Through Put CPO Proses | J3: TPD | K3: ='HPP REF '!N3 -> 926.24455
B4: Working Day | J4: Day | K4: ='HPP REF '!N4 -> 22
B5: Total CPO Refined | J5: TPM | K5: =K4*K3 -> 20377.38
B6: Kurs Rupiah | K6: ='SUMMARY HPP '!I9 -> 15546
B7: No | C7: Description | D7: Actual 2023 (Audited) | G7: Budget 2024
D8: Asset | E8: Years | F8: Month | G8: Asset | H8: Years | I8: Month | J8: RP/KG | K8: USD/MT
B9: Total Cost Depreciation | D9: =SUM(D10:D75) -> 6.7971213e+11 | E9: =SUM(E10:E75) -> 4.1807174e+10 | F9: =SUM(F10:F75) -> 3.4839312e+09 | G9: =SUM(G10:G75) -> 7.7503139e+11 | H9: =SUM(H10:H75) -> 5.0174217e+10 | I9: =SUM(I10:I75) -> 4.1811848e+09 | J9: =SUM(J10:J75) -> 205.18756 | K9: =SUM(K10:K75) -> 13.198736
B10: 1 | C10: Front Office + Canteen | D10: 3844320790 | E10: 1.9221604e+08 | F10: 16018003 | G10: 3.8443208e+09 | H10: =I10*12 -> 1.9221604e+08 | I10: 16018003 | J10: =$I$10/($K$5*1000) -> 0.78606785 | K10: =($I$10/$K$6)/$K$5 -> 0.050563994
B11: =B10+1 -> 2 | C11: Bea Cukai Building | D11: 247144032 | E11: 12357202 | F11: 1029766.8 | G11: 2.4714403e+08 | H11: =I11*12 -> 12357202 | I11: 1029766.8 | J11: =$I$11/($K$5*1000) -> 0.050534799 | K11: =($I$11/$K$6)/$K$5 -> 0.0032506625
B12: =B11+1 -> 3 | C12: Security Building | D12: 199088248 | E12: 12429395 | F12: 1035782.9 | G12: 3.9708686e+08 | H12: =I12*12 -> 19854343 | I12: 1654528.6 | J12: =$I$12/($K$5*1000) -> 0.081194373 | K12: =($I$12/$K$6)/$K$5 -> 0.0052228466
B13: =B12+1 -> 4 | C13: Bangunan Shelter / Pelataran | D13: 53111657402 | E13: 2.6555829e+09 | F13: 2.2129857e+08 | G13: 5.3111657e+10 | H13: =I13*12 -> 2.6555829e+09 | I13: 2.2129857e+08 | J13: =$I$13/($K$5*1000) -> 10.860011 | K13: =($I$13/$K$6)/$K$5 -> 0.69857269
B14: =B13+1 -> 5 | C14: Laboratorium Building | D14: 1.3920764e+09 | E14: 70956822 | F14: 5913068.5 | G14: 1.5003164e+09 | H14: =I14*12 -> 75015820 | I14: 6251318.3 | J14: =$I$14/($K$5*1000) -> 0.30677733 | K14: =($I$14/$K$6)/$K$5 -> 0.019733522
B15: =B14+1 -> 6 | C15: Refinery Room | D15: 22378266872 | E15: 1.1189133e+09 | F15: 93242779 | G15: 2.2378267e+10 | H15: =I15*12 -> 1.1189133e+09 | I15: 93242779 | J15: =$I$15/($K$5*1000) -> 4.5757982 | K15: =($I$15/$K$6)/$K$5 -> 0.29433926
B16: =B15+1 -> 7 | C16: Fractionation Room | D16: 22378266872 | E16: 1.1189133e+09 | F16: 93242779 | G16: 2.2378267e+10 | H16: =I16*12 -> 1.1189133e+09 | I16: 93242779 | J16: =$I$16/($K$5*1000) -> 4.5757982 | K16: =($I$16/$K$6)/$K$5 -> 0.29433926
B17: =B16+1 -> 8 | C17: Utility Building | D17: 22548996820 | E17: 1.1274498e+09 | F17: 93954153 | G17: 2.2548997e+10 | H17: =I17*12 -> 1.1274498e+09 | I17: 93954153 | J17: =$I$17/($K$5*1000) -> 4.6107082 | K17: =($I$17/$K$6)/$K$5 -> 0.29658486
B18: =B17+1 -> 9 | C18: Power House & Electrical Building | D18: 3242778116 | E18: 1.6663346e+08 | F18: 13886122 | G18: 3.6023423e+09 | H18: =I18*12 -> 1.8011712e+08 | I18: 15009760 | J18: =$I$18/($K$5*1000) -> 0.73658928 | K18: =($I$18/$K$6)/$K$5 -> 0.047381274
B19: =B18+1 -> 10 | C19: Weight Bridge Building (Timbangan) | D19: 3.0883582e+09 | E19: 1.6798762e+08 | F19: 13998968 | G19: 4.173935e+09 | H19: =I19*12 -> 2.0869675e+08 | I19: 17391396 | J19: =$I$19/($K$5*1000) -> 0.85346575 | K19: =($I$19/$K$6)/$K$5 -> 0.054899379
B20: =B19+1 -> 11 | C20: Warehouse TPS Spent Earth | D20: 1.3067146e+09 | E20: 65335728 | F20: 5444644 | G20: 1.3067146e+09 | H20: =I20*12 -> 65335728 | I20: 5444644 | J20: =$I$20/($K$5*1000) -> 0.26719058 | K20: =($I$20/$K$6)/$K$5 -> 0.017187095
B21: =B20+1 -> 12 | C21: Bangunan Shelter / Pelataran | D21: 0 | E21: 0 | F21: 0 | G21: 0 | H21: =I21*12 -> 0 | I21: 0 | J21: =$I$21/($K$5*1000) -> 0 | K21: =($I$21/$K$6)/$K$5 -> 0
B22: =B21+1 -> 13 | C22: Packaging Building | D22: 26865966199 | E22: 1.3432983e+09 | F22: 1.1194153e+08 | G22: 2.6865966e+10 | H22: =I22*12 -> 1.895783e+09 | I22: 1.5798192e+08 | J22: =$I$22/($K$5*1000) -> 7.7528082 | K22: =($I$22/$K$6)/$K$5 -> 0.49870116
B23: =B22+1 -> 14 | C23: Warehouse TPS Limbah B3 | D23: 808088751 | E23: 52164853 | F23: 4347071.1 | G23: 1.748922e+09 | H23: =I23*12 -> 87446098 | I23: 7287174.8 | J23: =$I$23/($K$5*1000) -> 0.35761098 | K23: =($I$23/$K$6)/$K$5 -> 0.023003408
B24: =B23+1 -> 15 | C24: Panel Room Loading - Unloading | D24: 669445527 | E24: 33472276 | F24: 2789356.4 | G24: 6.6944553e+08 | H24: =I24*12 -> 33472276 | I24: 2789356.4 | J24: =$I$24/($K$5*1000) -> 0.13688494 | K24: =($I$24/$K$6)/$K$5 -> 0.0088051548
B25: =B24+1 -> 16 | C25: Bangunan Shelter / Pelataran | D25: 0 | E25: 0 | F25: 0 | G25: 0 | H25: =I25*12 -> 0 | I25: 0 | J25: =$I$25/($K$5*1000) -> 0 | K25: =($I$25/$K$6)/$K$5 -> 0
B26: =B25+1 -> 17 | C26: Kantor RO Medan | D26: 35739000 | E26: 3573900 | F26: 297825 | G26: 35739000 | H26: =I26*12 -> 3573900 | I26: 297825 | J26: =$I$26/($K$5*1000) -> 0.014615471 | K26: =($I$26/$K$6)/$K$5 -> 0.00094014349
B27: =B26+1 -> 18 | C27: Gedung Logistic | D27: 537402145 | E27: 26870107 | F27: 2239175.6 | G27: 537402145 | H27: =I27*12 -> 26870107 | I27: 2239175.6 | J27: =$I$27/($K$5*1000) -> 0.10988535 | K27: =($I$27/$K$6)/$K$5 -> 0.0070684005
B28: =B27+1 -> 19 | C28: Ruang Expansi Filling Packaging | D28: 1071796228 | E28: 26794906 | F28: 2232908.8 | G28: 1071796228 | H28: =I28*12 -> 53589811 | I28: 4465817.6 | J28: =$I$28/($K$5*1000) -> 0.21915563 | K28: =($I$28/$K$6)/$K$5 -> 0.014097236
B29: =B28+1 -> 20 | C29: Bangunan Lainnya | D29: 236594750 | E29: 67601093 | F29: 5633424.5 | G29: 3.7519242e+09 | H29: =I29*12 -> 1.9942595e+08 | I29: 16618829 | J29: =$I$29/($K$5*1000) -> 0.81555279 | K29: =($I$29/$K$6)/$K$5 -> 0.052460619
B30: =B29+1 -> 21 | C30: Power House System | D30: 30414179484 | E30: 1.6120305e+09 | F30: 1.3433587e+08 | G30: 3.0414179e+10 | H30: =I30*12 -> 1.7106159e+09 | I30: 1.4255132e+08 | J30: =$I$30/($K$5*1000) -> 6.9955669 | K30: =($I$30/$K$6)/$K$5 -> 0.44999144
B31: =B30+1 -> 22 | C31: Reception from Road Tanker System | D31: 15714477178 | E31: 1.5906981e+09 | F31: 1.3255817e+08 | G31: 1.5714477e+10 | H31: =I31*12 -> 1.6892835e+09 | I31: 1.4077362e+08 | J31: =$I$31/($K$5*1000) -> 6.908328 | K31: =($I$31/$K$6)/$K$5 -> 0.44437978
B32: =B31+1 -> 23 | C32: Reception & CPO Storage Tank System | D32: 3.9160256e+10 | E32: 1.8156968e+09 | F32: 1.5130807e+08 | G32: 3.9160256e+10 | H32: =I32*12 -> 1.9142822e+09 | I32: 1.5952352e+08 | J32: =$I$32/($K$5*1000) -> 7.8284608 | K32: =($I$32/$K$6)/$K$5 -> 0.50356753
B33: =B32+1 -> 24 | C33: Refinery Product System | D33: 26158484525 | E33: 1.546139e+09 | F33: 1.2884492e+08 | G33: 2.6158485e+10 | H33: =I33*12 -> 2.1043359e+09 | I33: 1.7536132e+08 | J33: =$I$33/($K$5*1000) -> 8.6056855 | K33: =($I$33/$K$6)/$K$5 -> 0.55356269
B34: =B33+1 -> 25 | C34: Fractionation Product System | D34: 44700543389 | E34: 2.5257813e+09 | F34: 2.1048177e+08 | G34: 4.4700543e+10 | H34: =I34*12 -> 2.6243667e+09 | I34: 2.1869722e+08 | J34: =$I$34/($K$5*1000) -> 10.732352 | K34: =($I$34/$K$6)/$K$5 -> 0.69036102
B35: =B34+1 -> 26 | C35: Compressed Air System | D35: 12406716786 | E35: 6.9726354e+08 | F35: 58105295 | G35: 1.2406717e+10 | H35: =I35*12 -> 6.9726354e+08 | I35: 58105295 | J35: =$I$35/($K$5*1000) -> 2.8514605 | K35: =($I$35/$K$6)/$K$5 -> 0.18342085
B36: =B35+1 -> 27 | C36: Fuel Distribution System | D36: 2279256408 | E36: 1.6844371e+08 | F36: 14036976 | G36: 2.2792564e+09 | H36: =I36*12 -> 2.0366838e+08 | I36: 16972365 | J36: =$I$36/($K$5*1000) -> 0.83290223 | K36: =($I$36/$K$6)/$K$5 -> 0.053576626
B37: =B36+1 -> 28 | C37: Waste Water Treatment System | D37: 8173671310 | E37: 5.0165483e+08 | F37: 41804569 | G37: 8.1736713e+09 | H37: =I37*12 -> 5.1840723e+08 | I37: 43200602 | J37: =$I$37/($K$5*1000) -> 2.1200273 | K37: =($I$37/$K$6)/$K$5 -> 0.13637124
B38: =B37+1 -> 29 | C38: Clean Water System | D38: 8.1369458e+09 | E38: 4.697884e+08 | F38: 39149033 | G38: 8.1369458e+09 | H38: =I38*12 -> 4.697884e+08 | I38: 39149033 | J38: =$I$38/($K$5*1000) -> 1.9212005 | K38: =($I$38/$K$6)/$K$5 -> 0.12358166
B39: =B38+1 -> 30 | C39: Demin Water Distribution System | D39: 5554219736 | E39: 3.7021373e+08 | F39: 30851144 | G39: 5.5542197e+09 | H39: =I39*12 -> 3.7021373e+08 | I39: 30851144 | J39: =$I$39/($K$5*1000) -> 1.5139897 | K39: =($I$39/$K$6)/$K$5 -> 0.097387735
B40: =B39+1 -> 31 | C40: Steam Generation System | D40: 28411905935 | E40: 1.6009903e+09 | F40: 1.3341586e+08 | G40: 2.8411906e+10 | H40: =I40*12 -> 1.6009903e+09 | I40: 1.3341586e+08 | J40: =$I$40/($K$5*1000) -> 6.5472527 | K40: =($I$40/$K$6)/$K$5 -> 0.42115353 | L40: =H40/12 -> 1.3341586e+08
B41: =B40+1 -> 32 | C41: Cooling Water Distribution System | D41: 8813632097 | E41: 5.5719688e+08 | F41: 46433074 | G41: 8.8136321e+09 | H41: =I41*12 -> 5.5719688e+08 | I41: 46433074 | J41: =$I$41/($K$5*1000) -> 2.2786577 | K41: =($I$41/$K$6)/$K$5 -> 0.14657518
B42: =B41+1 -> 33 | C42: Fire Water System | D42: 4990631887 | E42: 3.5991574e+08 | F42: 29992978 | G42: 4.9906319e+09 | H42: =I42*12 -> 3.5991574e+08 | I42: 29992978 | J42: =$I$42/($K$5*1000) -> 1.4718761 | K42: =($I$42/$K$6)/$K$5 -> 0.094678765
B43: =B42+1 -> 34 | C43: Dual Fuel Emergency Generator | D43: 11752092639 | E43: 6.1186193e+08 | F43: 50988494 | G43: 1.1752093e+10 | H43: =I43*12 -> 6.1186193e+08 | I43: 50988494 | J43: =$I$43/($K$5*1000) -> 2.5022105 | K43: =($I$43/$K$6)/$K$5 -> 0.16095526
B44: =B43+1 -> 35 | C44: Steam Distribution & Condensate Recovery System | D44: 9891619567 | E44: 8.9987659e+08 | F44: 74989716 | G44: 9.8916196e+09 | H44: =I44*12 -> 8.9987659e+08 | I44: 74989716 | J44: =$I$44/($K$5*1000) -> 3.680047 | K44: =($I$44/$K$6)/$K$5 -> 0.23671986
B45: =B44+1 -> 36 | C45: Fire Water Main Ring System | D45: 4518985787 | E45: 2.4463794e+08 | F45: 20386495 | G45: 4.5189858e+09 | H45: =I45*12 -> 2.4463794e+08 | I45: 20386495 | J45: =$I$45/($K$5*1000) -> 1.0004473 | K45: =($I$45/$K$6)/$K$5 -> 0.064354002
B46: =B45+1 -> 37 | C46: Packaging System | D46: 34206697993 | E46: 3.1394346e+09 | F46: 2.6161955e+08 | G46: 1.2163436e+11 | H46: =I46*12 -> 7.8746236e+09 | I46: 6.5621863e+08 | J46: =$I$46/($K$5*1000) -> 32.203288 | K46: =($I$46/$K$6)/$K$5 -> 2.0714838
B47: =B46+1 -> 38 | C47: Refinery System | D47: 93804025615 | E47: 6.3108388e+09 | F47: 5.2590324e+08 | G47: 9.3804026e+10 | H47: =I47*12 -> 6.3327722e+09 | I47: 5.2773101e+08 | J47: =$I$47/($K$5*1000) -> 25.897884 | K47: =($I$47/$K$6)/$K$5 -> 1.6658873
B48: =B47+1 -> 39 | C48: Fractionation System | D48: 69305898501 | E48: 4.7141422e+09 | F48: 3.9284518e+08 | G48: 6.9305899e+10 | H48: =I48*12 -> 4.7141422e+09 | I48: 3.9284518e+08 | J48: =$I$48/($K$5*1000) -> 19.278493 | K48: =($I$48/$K$6)/$K$5 -> 1.2400935
B49: =B48+1 -> 40 | C49: Fat Pit System | D49: 1222833568 | E49: 76427098 | F49: 6368924.8 | G49: 1.2228336e+09 | H49: =I49*12 -> 76427098 | I49: 6368924.8 | J49: =$I$49/($K$5*1000) -> 0.31254876 | K49: =($I$49/$K$6)/$K$5 -> 0.02010477
B50: =B49+1 -> 41 | C50: Weight Bridge | D50: 2557397646 | E50: 1.2786988e+08 | F50: 10655824 | G50: 2.5573976e+09 | H50: =I50*12 -> 1.2786988e+08 | I50: 10655824 | J50: =$I$50/($K$5*1000) -> 0.52292412 | K50: =($I$50/$K$6)/$K$5 -> 0.033637213
B51: =B50+1 -> 42 | C51: Mesin Dan Perlengkapan Pabrik | D51: 30580769059 | E51: 1.6581493e+09 | F51: 1.3817911e+08 | G51: 3.0797884e+10 | H51: =I51*12 -> 2.8889928e+09 | I51: 2.407494e+08 | J51: =$I$51/($K$5*1000) -> 11.814541 | K51: =($I$51/$K$6)/$K$5 -> 0.75997307
B52: =B51+1 -> 43 | C52: Installation System Electrical (Auxiliary) | D52: 2460303143 | E52: 1.5376895e+08 | F52: 12814079 | G52: 2460303143 | H52: =I52*12 -> 1.5376895e+08 | I52: 12814079 | J52: =$I$52/($K$5*1000) -> 0.62883839 | K52: =($I$52/$K$6)/$K$5 -> 0.040450173
B53: =B52+1 -> 44 | C53: Mesin Dan Perlengkapan Pabrik | D53: 0 | E53: 0 | F53: 0 | G53: 0 | H53: =I53*12 -> 0 | I53: 0 | J53: =$I$53/($K$5*1000) -> 0 | K53: =($I$53/$K$6)/$K$5 -> 0
B54: =B53+1 -> 45 | C54: Mesin Dan Perlengkapan Pabrik | D54: 0 | E54: 0 | F54: 0 | G54: 0 | H54: =I54*12 -> 0 | I54: 0 | J54: =$I$54/($K$5*1000) -> 0 | K54: =($I$54/$K$6)/$K$5 -> 0
B55: =B54+1 -> 46 | C55: Refinery Product System | D55: 0 | E55: 0 | F55: 0 | G55: 0 | H55: =I55*12 -> 0 | I55: 0 | J55: =$I$55/($K$5*1000) -> 0 | K55: =($I$55/$K$6)/$K$5 -> 0
B56: =B55+1 -> 47 | C56: Perlengkapan Pabrik Lainnya | D56: 814629325 | E56: 1.3842046e+08 | F56: 11535038 | G56: 814629325 | H56: =I56*12 -> 1.3842046e+08 | I56: 11535038 | J56: =$I$56/($K$5*1000) -> 0.56607073 | K56: =($I$56/$K$6)/$K$5 -> 0.036412629
B57: =B56+1 -> 48 | C57: Bangunan Shelter / Pelataran | D57: 0 | E57: 0 | F57: 0 | G57: 0 | H57: =I57*12 -> 0 | I57: 0 | J57: =$I$57/($K$5*1000) -> 0 | K57: =($I$57/$K$6)/$K$5 -> 0
B58: =B57+1 -> 49 | C58: Saluran Drainase | D58: 3324550757 | E58: 1.6622754e+08 | F58: 13852295 | G58: 3.3245508e+09 | H58: =I58*12 -> 1.6622754e+08 | I58: 13852295 | J58: =$I$58/($K$5*1000) -> 0.67978782 | K58: =($I$58/$K$6)/$K$5 -> 0.043727507
B59: =B58+1 -> 50 | C59: Fence | D59: 1457273906 | E59: 72863695 | F59: 6071974.6 | G59: 1457273906 | H59: =I59*12 -> 72863695 | I59: 6071974.6 | J59: =$I$59/($K$5*1000) -> 0.29797622 | K59: =($I$59/$K$6)/$K$5 -> 0.019167388
B60: =B59+1 -> 51 | C60: Bangunan Shelter / Pelataran | D60: 0 | E60: 0 | F60: 0 | G60: 0 | H60: =I60*12 -> 0 | I60: 0 | J60: =$I$60/($K$5*1000) -> 0 | K60: =($I$60/$K$6)/$K$5 -> 0
B61: =B60+1 -> 52 | C61: Alat Pengangkutan | D61: 702420000 | E61: 58515250 | F61: 4876270.8 | G61: 702420000 | H61: =I61*12 -> 92109000 | I61: 7675750 | J61: =$I$61/($K$5*1000) -> 0.37667993 | K61: =($I$61/$K$6)/$K$5 -> 0.024230022
B62: =B61+1 -> 53 | C62: Perabot & Perlengkapan Kantor | D62: 2093240354 | E62: 2.8749571e+08 | F62: 23957976 | G62: 2093240354 | H62: =I62*12 -> 2.8749571e+08 | I62: 23957976 | J62: =$I$62/($K$5*1000) -> 1.1757143 | K62: =($I$62/$K$6)/$K$5 -> 0.075628088
B63: =B62+1 -> 54 | C63: Perabot dan Perlengkapan Mess | D63: 0 | E63: 0 | F63: 0 | G63: 0 | H63: =I63*12 -> 0 | I63: 0 | J63: =$I$63/($K$5*1000) -> 0 | K63: =($I$63/$K$6)/$K$5 -> 0
B64: =B63+1 -> 55 | C64: Alat & Perlengkapan Pabrik | D64: 68073000 | E64: 13614600 | F64: 1134550 | G64: 68073000 | H64: =I64*12 -> 13614600 | I64: 1134550 | J64: =$I$64/($K$5*1000) -> 0.055676932 | K64: =($I$64/$K$6)/$K$5 -> 0.0035814314
B65: =B64+1 -> 56 | C65: Alat dan Perlengkapan Bengkel | D65: 140550000 | E65: 28110000 | F65: 2342500 | G65: 140550000 | H65: =I65*12 -> 28110000 | I65: 2342500 | J65: =$I$65/($K$5*1000) -> 0.1149559 | K65: =($I$65/$K$6)/$K$5 -> 0.0073945643
B66: =B65+1 -> 57 | C66: Alat dan Perlengkapan Laboratorium | D66: 3453064640 | E66: 3.7398892e+08 | F66: 31165744 | G66: 4405170868 | H66: =I66*12 -> 8.9603417e+08 | I66: 74669514 | J66: =$I$66/($K$5*1000) -> 3.6643334 | K66: =($I$66/$K$6)/$K$5 -> 0.23570908
B67: =B66+1 -> 58 | C67: Alat IT / Komputer | D67: 1542535419 | E67: 2.9444276e+08 | F67: 24536897 | G67: 1.9760604e+09 | H67: =I67*12 -> 2.9825396e+08 | I67: 24854497 | J67: =$I$67/($K$5*1000) -> 1.2197101 | K67: =($I$67/$K$6)/$K$5 -> 0.078458132
B68: =B67+1 -> 59 | C68: Perabot & Perlengkapan Lainnya | D68: 11270000 | E68: 2254000 | F68: 187833.33 | G68: 11270000 | H68: =I68*12 -> 2254000 | I68: 187833.33 | J68: =$I$68/($K$5*1000) -> 0.0092177372 | K68: =($I$68/$K$6)/$K$5 -> 0.00059293305
B69: =B68+1 -> 60 | C69: Aktiva Tetap Non Produktif | D69: 26932688 | E69: 5386537.6 | F69: 448878.13 | G69: 26932688 | H69: =I69*12 -> 5386537.5 | I69: 448878.13 | J69: =$I$69/($K$5*1000) -> 0.022028255 | K69: =($I$69/$K$6)/$K$5 -> 0.0014169725
B70: =B69+1 -> 61 | C70: Totem AKHLAK | D70: 30000000 | E70: 6000000 | F70: 500000 | G70: 30000000 | H70: =I70*12 -> 6000000.1 | I70: 500000.01 | J70: =$I$70/($K$5*1000) -> 0.024537011 | K70: =($I$70/$K$6)/$K$5 -> 0.0015783489
B71: =B70+1 -> 62 | C71: Main Office | D71: 6869341541 | E71: 3.4448348e+08 | F71: 28706957 | G71: 6.9506539e+09 | H71: =I71*12 -> 3.4753269e+08 | I71: 28961058 | J71: =$I$71/($K$5*1000) -> 1.4212356 | K71: =($I$71/$K$6)/$K$5 -> 0.091421304

Sheet MTC
C1: working days | F1: working days
B2: Summary - PM Electrical | C2: ='November 2024'!AL6 -> 22 | E2: Summary - PM Mechanical | F2: ='November 2024'!AL6 -> 22
B3: Consumable Item | C3: Total Price | E3: Consumable Item | F3: Total Price
C4: Per Day | F4: Per Day
B5: Biaya Pemeliharaan Unit Refinery(Listrik) | C5: 1648879.6 | E5: Biaya Pemeliharaan Unit Refinery | F5: 4911824.3
B6: HP Boiler | C6: 2678431.4 | E6: Biaya Pemeliharaan Unit Fraksinasi | F6: 1230672.3
B7: Dry Fractination - Crystalizer & Filter Press | C7: 288459.38 | E7: Biaya Pemeliharaan Unit Cooling Tower | F7: 1084733.9
B8: Physical Refinery-Bleaching and Deodorization | C8: 404271.71 | E8: Biaya Pemeliharaan Unit Packaging | F8: 833815.52
B9: BOILER | C9: 150891.4 | E9: Biaya Pemeliharaan Unit Material Handling | F9: 949299.72
B10: Water Plant, Effluent & Hydrant | C10: 58543.417 | E10: Biaya Pemeliharaan Unit Utility | F10: 1106022.4
B11: Pump House | C11: 87425.77 | E11: Barang Consumable Maintenance | F11: 5634698.9
B12: DCS-CCR ISBL | C12: 254341.74
B13: Lighting All Area | C13: 114733.89 | E13: Total | F13: =SUM(F5:F12) -> 15751067
B14: Consumable | C14: 203159.66 | E14: Total/Month | F14: =F13*F2 -> 3.4652347e+08
B15: Kalibrasi Instrument Pabrik | C15: 580672.27 | E15: Total/Yearly | F15: =F14*12 -> 4.1582817e+09
B16: Service Special Equipment | C16: 4089635.9
B17: Total/Day | C17: =SUM(C5:C16) -> 10559446 | E17: TOTAL COST
B18: Total/Month | C18: =C17*C2 -> 2.3230781e+08 | E18: PM E + PM M | F18: =F14+C18 -> 5.7883129e+08
B19: Total/Yearly | C19: =C18*12 -> 2.7876937e+09 | E19: TOTAL | F19: =F18*12 -> 6.9459754e+09

Sheet LOG
B2: Port Cost Kuala Tanjung
B3: Through Put CPO Proses | J3: TPD | K3: ='HPP REF '!N3 -> 926.24455
B4: Working Day | J4: Day | K4: ='HPP REF '!N4 -> 22
B5: Total CPO Refined | J5: TPM | K5: =K4*K3 -> 20377.38
B6: Kurs Rupiah | K6: ='SUMMARY HPP '!I9 -> 15546
B7: No | C7: Description | G7: Norma | I7: Total Biaya ( Rp ) | J7: RP/KG | K7: USD/MT
B8: 1 | C8: Trucking Komoditi ke Kuala Tanjung | E8: Olein ( Ton ) | F8: =(100%-0.8%-1.1*5%)*80%*K5 -> 15274.884 | G8: Rp/Kg | H8: 90 | I8: =H8*F8*1000 -> 1.3747396e+09 | J8: =I8/($K$5*1000) -> 67.464 | K8: =(I8/$K$6)/$K$5 -> 4.3396372
E9: Stearin ( Ton ) Iso Tank | F9: =(100%-0.8%-1.1*5%)*20%*K5 -> 3818.721 | G9: Rp/Kg | H9: 150 | I9: =H9*F9*1000 -> 5.7280815e+08 | J9: =I9/($K$5*1000) -> 28.11 | K9: =(I9/$K$6)/$K$5 -> 1.8081822
E10: PFAD ( Ton ) Iso Tank | F10: =1.1*5%*K5 -> 1120.7559 | G10: Rp/Kg | H10: 150 | I10: =H10*F10*1000 -> 168113385 | J10: =I10/($K$5*1000) -> 8.25 | K10: =(I10/$K$6)/$K$5 -> 0.53068313
B11: 2 | C11: Sewa Tank PTI Total Volume : 24.000 MT ( 5 Unit ) | E11: Tank 8.000 MT >> Olein | F11: 1 | G11: Rp/Kg | H11: 77 | I11: =H11*8000*F11*1000 -> 616000000 | J11: =I11/($K$5*1000) -> 30.229598 | K11: =(I11/$K$6)/$K$5 -> 1.9445258
E12: Tank 5.000 MT >> Stearin | F12: 2 | G12: Rp/Kg | H12: 79 | I12: =H12*5000*F12*1000 -> 790000000 | J12: =I12/($K$5*1000) -> 38.768478 | K12: =(I12/$K$6)/$K$5 -> 2.4937912
E13: Tank 3.000 MT >> RBDPO | F13: 1 | G13: Rp/Kg | H13: 77 | I13: =H13*3000*F13*1000 -> 231000000 | J13: =I13/($K$5*1000) -> 11.336099 | K13: =(I13/$K$6)/$K$5 -> 0.72919717
E14: Tank 3.000 MT S/S >> PFAD | F14: 1 | G14: Rp/Kg | H14: 83 | I14: =H14*3000*F14*1000 -> 249000000 | J14: =I14/($K$5*1000) -> 12.219432 | K14: =(I14/$K$6)/$K$5 -> 0.78601772
B15: 3 | C15: Finalty Over Capacity dari tank | D15: 0 | E15: Over Volume Olein | F15: =F8-(8000*D15) -> 15274.884 | G15: Rp/Kg | H15: 43 | I15: =H15*F15*1000 -> 6.5682001e+08 | J15: =I15/($K$5*1000) -> 32.2328 | K15: =(I15/$K$6)/$K$5 -> 2.0733822
D16: 0 | E16: Over Volume Stearin | F16: =F9-(10000*D16) -> 3818.721 | G16: Rp/Kg | H16: 43 | I16: =H16*F16*1000 -> 1.64205e+08 | J16: =I16/($K$5*1000) -> 8.0582 | K16: =(I16/$K$6)/$K$5 -> 0.51834556
D17: 0 | E17: Over Volume PFAD | F17: =F10-(3000*D17) -> 1120.7559 | G17: Rp/Kg | H17: 43 | I17: =H17*F17*1000 -> 48192504 | J17: =I17/($K$5*1000) -> 2.365 | K17: =(I17/$K$6)/$K$5 -> 0.15212917
B18: 3 | C18: Beban Instalasi Pemompaan dan Pemanasan | E18: Total Volume | F18: =SUM(F8:F10) -> 20214.361 | G18: Rp/Kg | H18: 22 | I18: =H18*F18*1000 -> 4.4471594e+08 | J18: =I18/($K$5*1000) -> 21.824 | K18: =(I18/$K$6)/$K$5 -> 1.4038338
B19: =B18+1 -> 4 | C19: Pompa | E19: Total Volume | F19: =F18 -> 20214.361 | G19: Rp/Kg | H19: 26 | I19: =H19*F18*1000 -> 5.2557338e+08 | J19: =I19/($K$5*1000) -> 25.792 | K19: =(I19/$K$6)/$K$5 -> 1.6590763
B20: =B19+1 -> 5 | C20: Beban Analisa ( Surveyor ) | E20: Total Volume | F20: =F18 -> 20214.361 | G20: Rp/Kg | H20: 3 | I20: =H20*F20*1000 -> 60643083 | J20: =I20/($K$5*1000) -> 2.976 | K20: =(I20/$K$6)/$K$5 -> 0.19143188
B21: =B20+1 -> 6 | C21: Beban Pelabuhan ( Documen-Documen Pelabuhan ) | E21: Total Volume | F21: =F20 -> 20214.361 | G21: Rp/Kg | H21: 3 | I21: =H21*F21*1000 -> 60643083 | J21: =I21/($K$5*1000) -> 2.976 | K21: =(I21/$K$6)/$K$5 -> 0.19143188
B22: =B21+1 -> 7 | C22: Beban Asuransi (Cost Insurance Freight)
B23: =B22+1 -> 8 | C23: Beban Sewa Kapal
B24: =B23+1 -> 9 | C24: Beban Pengangkutan Di Pelabuhan
B25: Total Biaya Transfer Product ke Kuala Tanjung Port | I25: =SUM(I8:I24) -> 5.9624541e+09 | J25: =SUM(J8:J24) -> 292.60161 | K25: =SUM(K8:K24) -> 18.821665

Sheet OH
B2: Overhead ( OH )
B3: Through Put CPO Proses | H3: TPD | I3: ='HPP REF '!N3 -> 926.24455
B4: Working Day | H4: Day | I4: ='SUMMARY HPP '!I4 -> 22
B5: Total CPO Refined | H5: TPM | I5: =I4*I3 -> 20377.38
B6: Kurs Rupiah | I6: ='SUMMARY HPP '!I9 -> 15546
B7: No | C7: Description | D7: Actual 2023 (Audited) | F7: Budget 2024
D8: Years | E8: Month | F8: Years | G8: Month | H8: RP/KG | I8: USD/MT
B9: 1 | C9: Biaya Perjalanan Dinas (Dalam Provinsi) | D9: 305458258 | E9: =IFERROR(D9/12,0) -> 25454855 | F9: =G9*12 -> 3.6654991e+08 | G9: 30545826 | H9: =G9/($I$5*1000) -> 1.4990065 | I9: =(G9/$I$6)/$I$5 -> 0.096423938
B10: =B9+1 -> 2 | C10: Biaya Perjalanan Dinas (Luar Provinsi) | D10: 2.6287295e+09 | E10: =IFERROR(D10/12,0) -> 2.1906079e+08 | F10: =G10*12 -> 3.5487849e+09 | G10: 2.9573207e+08 | H10: =G10/($I$5*1000) -> 14.512762 | I10: =(G10/$I$6)/$I$5 -> 0.93353675
B11: =B10+1 -> 3 | C11: Beban BBM Kendaraan | D11: 720175678 | E11: =IFERROR(D11/12,0) -> 60014640 | F11: =G11*12 -> 7.5618446e+08 | G11: 63015372 | H11: =G11/($I$5*1000) -> 3.0924178 | I11: =(G11/$I$6)/$I$5 -> 0.19892048
B12: =B11+1 -> 4 | C12: Beban Sewa Kendaraan | D12: 2428347903 | E12: =IFERROR(D12/12,0) -> 2.0236233e+08 | F12: =G12*12 -> 2220000000 | G12: 185000000 | H12: =G12/($I$5*1000) -> 9.0786941 | I12: =(G12/$I$6)/$I$5 -> 0.58398907
B13: =B12+1 -> 5 | C13: Beban Kendaraan Lainnya | D13: 110862850 | E13: =IFERROR(D13/12,0) -> 9238570.8 | F13: =G13*12 -> 110862850 | G13: 9238570.8 | H13: =G13/($I$5*1000) -> 0.45337383 | I13: =(G13/$I$6)/$I$5 -> 0.029163375
B14: =B13+1 -> 6 | C14: Beban Sewa Bangunan / Inventaris / Aset | D14: 126990400 | E14: =IFERROR(D14/12,0) -> 10582533 | F14: =G14*12 -> 110000400 | G14: 9166700 | H14: =G14/($I$5*1000) -> 0.44984684 | I14: =(G14/$I$6)/$I$5 -> 0.028936501
B15: =B14+1 -> 7 | C15: Beban Penelitian, Percobaan & Pengembangan | D15: 108868060 | E15: =IFERROR(D15/12,0) -> 9072338.3 | F15: =G15*12 -> 100000000 | G15: 8333333.3 | H15: =G15/($I$5*1000) -> 0.40895019 | I15: =(G15/$I$6)/$I$5 -> 0.026305814
B16: =B15+1 -> 8 | C16: Beban Pemeliharaan Bangunan Rumah | D16: 203000 | E16: =IFERROR(D16/12,0) -> 16916.667 | F16: =G16*12 -> 0 | G16: 0 | H16: =G16/($I$5*1000) -> 0 | I16: =(G16/$I$6)/$I$5 -> 0
B17: =B16+1 -> 9 | C17: Beban Pemeliharaan Bangunan Perusahaan | D17: 108952486 | E17: =IFERROR(D17/12,0) -> 9079373.8 | F17: =G17*12 -> 1.1440011e+08 | G17: 9533342.5 | H17: =G17/($I$5*1000) -> 0.46783946 | I17: =(G17/$I$6)/$I$5 -> 0.03009388
B18: =B17+1 -> 10 | C18: Beban Pemeliharaan Mesin & Instalansi | D18: 32369030 | E18: =IFERROR(D18/12,0) -> 2697419.2 | F18: =G18*12 -> 33987482 | G18: 2832290.1 | H18: =G18/($I$5*1000) -> 0.13899187 | I18: =(G18/$I$6)/$I$5 -> 0.0089406837
B19: =B18+1 -> 11 | C19: Beban Pemeliharaan Jalan, Jembatan & Saluran Air | D19: 179265600 | E19: =IFERROR(D19/12,0) -> 14938800 | F19: =G19*12 -> 188228880 | G19: 15685740 | H19: =G19/($I$5*1000) -> 0.76976235 | I19: =(G19/$I$6)/$I$5 -> 0.049515139
B20: =B19+1 -> 12 | C20: Beban Pemeliharaan Alat Inventaris Kecil | D20: 253700695 | E20: =IFERROR(D20/12,0) -> 21141725 | F20: =G20*12 -> 2.6638573e+08 | G20: 22198811 | H20: =G20/($I$5*1000) -> 1.0893849 | I20: =(G20/$I$6)/$I$5 -> 0.070074935
B21: =B20+1 -> 13 | C21: Beban Pemakaian Inventaris Kecil | D21: 1859843066 | E21: =IFERROR(D21/12,0) -> 1.5498692e+08 | F21: =G21*12 -> 335473201 | G21: 27956100 | H21: =G21/($I$5*1000) -> 1.3719183 | I21: =(G21/$I$6)/$I$5 -> 0.088248957
B22: =B21+1 -> 14 | C22: Beban Iuran, Sumbangan, & Bina Lingkungan | D22: 694460474 | E22: =IFERROR(D22/12,0) -> 57871706 | F22: =G22*12 -> 2.6839105e+08 | G22: 22365921 | H22: =G22/($I$5*1000) -> 1.0975857 | I22: =(G22/$I$6)/$I$5 -> 0.070602451
B23: =B22+1 -> 15 | C23: Beban Instansi Kelembagaan | E23: =IFERROR(D23/12,0) -> 0 | F23: =G23*12 -> 60000000 | G23: 5000000 | H23: =G23/($I$5*1000) -> 0.24537011 | I23: =(G23/$I$6)/$I$5 -> 0.015783488
B24: =B23+1 -> 16 | C24: Beban Pajak & Retribusi | D24: 659276883 | E24: =IFERROR(D24/12,0) -> 54939740 | F24: =G24*12 -> 1518332400 | G24: 126527700 | H24: =G24/($I$5*1000) -> 6.2092232 | I24: =(G24/$I$6)/$I$5 -> 0.3994097
B25: =B24+1 -> 17 | C25: Beban Premi Assuransi | E25: =IFERROR(D25/12,0) -> 0 | F25: =G25*12 -> 197000000 | G25: 16416667 | H25: =G25/($I$5*1000) -> 0.80563187 | I25: =(G25/$I$6)/$I$5 -> 0.051822454
B26: =B25+1 -> 18 | C26: Beban Penerangan | D26: 62716328 | E26: =IFERROR(D26/12,0) -> 5226360.7 | F26: =G26*12 -> 80400000 | G26: 6700000 | H26: =G26/($I$5*1000) -> 0.32879595 | I26: =(G26/$I$6)/$I$5 -> 0.021149875
B27: =B26+1 -> 19 | C27: Beban Persediaan Air | D27: 1756590 | E27: =IFERROR(D27/12,0) -> 146382.5 | F27: =G27*12 -> 6840000 | G27: 570000 | H27: =G27/($I$5*1000) -> 0.027972193 | I27: =(G27/$I$6)/$I$5 -> 0.0017993177
B28: =B27+1 -> 20 | C28: Beban Pemakaian Perlengkapan Kantor | D28: 1.1936208e+09 | E28: =IFERROR(D28/12,0) -> 99468402 | F28: =G28*12 -> 1.1936208e+09 | G28: 99468402 | H28: =G28/($I$5*1000) -> 4.8813146 | I28: =(G28/$I$6)/$I$5 -> 0.31399167
B29: =B28+1 -> 21 | C29: Beban Pengendalian Lingkungan (ISO 14000) | D29: 488020500 | E29: =IFERROR(D29/12,0) -> 40668375 | F29: =G29*12 -> 264000000 | G29: 22000000 | H29: =G29/($I$5*1000) -> 1.0796285 | I29: =(G29/$I$6)/$I$5 -> 0.069447349
B30: =B29+1 -> 22 | C30: Beban Sistem Manajemen Keselamatan & Kesehatan Kerja (SMK3) | D30: 68171900 | E30: =IFERROR(D30/12,0) -> 5680991.7 | F30: =G30*12 -> 258000000 | G30: 21500000 | H30: =G30/($I$5*1000) -> 1.0550915 | I30: =(G30/$I$6)/$I$5 -> 0.067869
B31: =B30+1 -> 23 | C31: Beban Pendidikan & Pengembangan SDM | D31: 1186354647 | E31: =IFERROR(D31/12,0) -> 98862887 | F31: =G31*12 -> 10000000 | G31: 833333.33 | H31: =G31/($I$5*1000) -> 0.040895019 | I31: =(G31/$I$6)/$I$5 -> 0.0026305814
B32: =B31+1 -> 24 | C32: Beban Audit (Independent Auditor) | D32: 8.477783e+08 | E32: =IFERROR(D32/12,0) -> 70648192 | F32: =G32*12 -> 9.0712278e+08 | G32: 75593565 | H32: =G32/($I$5*1000) -> 3.7096803 | I32: =(G32/$I$6)/$I$5 -> 0.23862603
B33: =B32+1 -> 25 | C33: Beban Konsultan - Eksternal | D33: 245454645 | E33: =IFERROR(D33/12,0) -> 20454554 | F33: =G33*12 -> 2.7000011e+08 | G33: 22500009 | H33: =G33/($I$5*1000) -> 1.1041659 | I33: =(G33/$I$6)/$I$5 -> 0.071025727
B34: =B33+1 -> 26 | C34: Beban Insentif Karyawan | E34: =IFERROR(D34/12,0) -> 0 | F34: =G34*12 -> 0 | G34: 0 | H34: =G34/($I$5*1000) -> 0 | I34: =(G34/$I$6)/$I$5 -> 0
B35: =B34+1 -> 27 | C35: Beban Jasa Produksi Karyawan | E35: =IFERROR(D35/12,0) -> 0 | F35: =G35*12 -> 0 | G35: 0 | H35: =G35/($I$5*1000) -> 0 | I35: =(G35/$I$6)/$I$5 -> 0
B36: =B35+1 -> 28 | C36: Beban Uang Jasa (Jubilium, SHT, Dll) | D36: 188207400 | E36: =IFERROR(D36/12,0) -> 15683950 | F36: =G36*12 -> 207028140 | G36: 17252345 | H36: =G36/($I$5*1000) -> 0.84664196 | I36: =(G36/$I$6)/$I$5 -> 0.054460438
B37: =B36+1 -> 29 | C37: Beban Imbalan Pasca Kerja | D37: 4384212523 | E37: =IFERROR(D37/12,0) -> 3.6535104e+08 | F37: =G37*12 -> 666345107 | G37: 55528759 | H37: =G37/($I$5*1000) -> 2.7250196 | I37: =(G37/$I$6)/$I$5 -> 0.1752875
B38: =B37+1 -> 30 | C38: Beban Pengurusan Sertifikasi / Hak Merk / Izin / Dll | D38: 108648500 | E38: =IFERROR(D38/12,0) -> 9054041.7 | F38: =G38*12 -> 114080925 | G38: 9506743.8 | H38: =G38/($I$5*1000) -> 0.46653415 | I38: =(G38/$I$6)/$I$5 -> 0.030009916
B39: =B38+1 -> 31 | C39: Beban Entertainment | D39: 80056015 | E39: =IFERROR(D39/12,0) -> 6671334.6 | F39: =G39*12 -> 0 | G39: 0 | H39: =G39/($I$5*1000) -> 0 | I39: =(G39/$I$6)/$I$5 -> 0
B40: =B39+1 -> 32 | C40: Beban Akomodasi Rapat | D40: 84564877 | E40: =IFERROR(D40/12,0) -> 7047073.1 | F40: =G40*12 -> 88793121 | G40: 7399426.7 | H40: =G40/($I$5*1000) -> 0.36311963 | I40: =(G40/$I$6)/$I$5 -> 0.023357753
B41: =B40+1 -> 33 | C41: Beban Bonus Karyawan | E41: =IFERROR(D41/12,0) -> 0 | F41: =G41*12 -> 0 | G41: 0 | H41: =G41/($I$5*1000) -> 0 | I41: =(G41/$I$6)/$I$5 -> 0
B42: =B41+1 -> 34 | C42: Beban Tantiem | E42: =IFERROR(D42/12,0) -> 0 | F42: =G42*12 -> 0 | G42: 0 | H42: =G42/($I$5*1000) -> 0 | I42: =(G42/$I$6)/$I$5 -> 0
B43: =B42+1 -> 35 | C43: Beban Konsumsi | D43: 3864122096 | E43: =IFERROR(D43/12,0) -> 3.2201017e+08 | F43: =G43*12 -> 2223000000 | G43: 185250000 | H43: =G43/($I$5*1000) -> 9.0909626 | I43: =(G43/$I$6)/$I$5 -> 0.58477825
B44: =B43+1 -> 36 | C44: Beban Ekstra Fooding | D44: 810000 | E44: =IFERROR(D44/12,0) -> 67500 | F44: =G44*12 -> 0 | G44: 0 | H44: =G44/($I$5*1000) -> 0 | I44: =(G44/$I$6)/$I$5 -> 0
B45: =B44+1 -> 37 | C45: Beban Pemeriksaan Kesehatan / Perobatan | D45: 185612516 | E45: =IFERROR(D45/12,0) -> 15467710 | F45: =G45*12 -> 41405668 | G45: 3450472.3 | H45: =G45/($I$5*1000) -> 0.16932856 | I45: =(G45/$I$6)/$I$5 -> 0.010892098
B46: =B45+1 -> 38 | C46: Beban Peringatan Hari Besar | D46: 300000 | E46: =IFERROR(D46/12,0) -> 25000 | F46: =G46*12 -> 25000000 | G46: 2083333.3 | H46: =G46/($I$5*1000) -> 0.10223755 | I46: =(G46/$I$6)/$I$5 -> 0.0065764535
B47: =B46+1 -> 39 | C47: Beban Perlengkapan Karyawan | D47: 497881607 | E47: =IFERROR(D47/12,0) -> 41490134 | F47: =G47*12 -> 420000000 | G47: 35000000 | H47: =G47/($I$5*1000) -> 1.7175908 | I47: =(G47/$I$6)/$I$5 -> 0.11048442
B48: =B47+1 -> 40 | C48: Beban Keperluan Dapur / Pantry | D48: 79298165 | E48: =IFERROR(D48/12,0) -> 6608180.4 | F48: =G48*12 -> 12458700 | G48: 1038225 | H48: =G48/($I$5*1000) -> 0.050949877 | I48: =(G48/$I$6)/$I$5 -> 0.0032773625
B49: =B48+1 -> 41 | C49: Beban Employee Gathering | E49: =IFERROR(D49/12,0) -> 0 | F49: =G49*12 -> 250000000 | G49: 20833333 | H49: =G49/($I$5*1000) -> 1.0223755 | I49: =(G49/$I$6)/$I$5 -> 0.065764535
B50: =B49+1 -> 42 | C50: Beban Kebersihan | D50: 11059767 | E50: =IFERROR(D50/12,0) -> 921647.25 | F50: =G50*12 -> 0 | G50: 0 | H50: =G50/($I$5*1000) -> 0 | I50: =(G50/$I$6)/$I$5 -> 0
D51: =SUM(D9:D50) -> 2.3796151e+10 | E51: =SUM(E9:E50) -> 1.9830126e+09 | F51: =SUM(F9:F50) -> 1.7232677e+10 | G51: =SUM(G9:G50) -> 1.4360564e+09 | H51: =SUM(H9:H50) -> 70.473063 | I51: =SUM(I9:I50) -> 4.5331959

Sheet Time Sheet Bulanan
A1: Nomor | B1: Tanggal | C1: Keterangan
C2: Refinery | D2: Fraksinasi
A3: 1 | B3: 45536
A4: 2 | B4: 45537
A5: 3 | B5: 45538
A6: 4 | B6: 45539
A7: 5 | B7: 45540
A8: 6 | B8: 45541
A9: 7 | B9: 45542
A10: 8 | B10: 45543
A11: 9 | B11: 45544
A12: 10 | B12: 45545
A13: 11 | B13: 45546
A14: 12 | B14: 45547
... A25: 23 | B25: 45558
A26: 24 | B26: 45559 | C26: Update tgal 24/09/2024 Refinery * 07.00 ref HOLD * 22.00 steam masuk ke plant * 01.20 ref firing hpb * 02.00 sirkulasi * 03.00-07.00 plant HOLD terkait pressure gas HPB drop | D26: Stop sementara & aktifitas cleaning chiller
A27: 25 | B27: 45560 | C27: Refinery * 07.40 start sirkulasi | D27: Fraksinasi * Stop sementara dan pagi ini kunci mainhole chiller pak
A28: 26 | B28: 45561
A29: 27 | B29: 45562
A30: 28 | B30: 45563
A31: 29 | B31: 45564
A32: 30 | B32: 45565

Sheet Flow Meter
A2: TOTAL TONASE FLOWMETER PRODUK
A3: REFINERY
A5: TANGGAL VALIDASI
A6: NO | B6: NAMA PRODUK | C6: 01 Juli | D6: 02 Juli | E6: 03 Juli | F6: 04 Juli | G6: 05 Juli | H6: 06 Juli | I6: 07 Juli | J6: 08 Juli | K6: 09 Juli | L6: 10 Juli | M6: 11 Juli | N6: 12 Juli | O6: 13 Juli | P6: 14 Juli | Q6: 15 Juli | R6: TOTAL | S6: Sounding | T6: Yield Theory | U6: Yield Aktual
A7: 1 | B7: CPO | C7: ='[34]01 '!$Q$14 -> 744924 | D7: ='[34]02'!$Q$14 -> 743972 | E7: ='[34]03'!$Q$14 -> 1048435 | F7: ='[34]04'!$Q$14 -> 1114821 | G7: 248126 | H7: 389481 | I7: 104168 | J7: 320907 | K7: 100743 | L7: 512647 | M7: 441064 | N7: 524002 | O7: 568358 | P7: 430750 | R7: =SUM(C7:Q7) -> 7292398
A8: 2 | B8: RBDPO | C8: 713300 | D8: 708000 | E8: 993100 | F8: 1056000 | G8: 237021 | H8: 365100 | I8: 44001 | J8: 300010 | K8: 94507 | L8: 488153 | M8: 414337 | N8: 492952 | O8: 532902 | P8: 497845 | R8: =SUM(C8:Q8) -> 6937228 | T8: =R8/R7 -> 0.95129586 | U8: =S8/S7 -> #DIV/0! | W8: =4984655+#REF! -> #REF!
A9: 3 | B9: PFAD | C9: ='[34]01 '!$P$25 -> 25659 | D9: 28786 | E9: ='[34]03'!$P$25 -> 46938 | F9: ='[34]04'!$P$24 -> 48667 | G9: 8070 | H9: 19280 | I9: 3234 | J9: 18283 | K9: 5131 | L9: 20426 | M9: 23275 | N9: 27655 | O9: 25803 | P9: 20173 | R9: =SUM(C9:Q9) -> 321380 | T9: =R9/R7 -> 0.044070551 | U9: =S9/S7 -> #DIV/0!
C10: =C8/C7 -> 0.95754735 | D10: =D8/D7 -> 0.95164872 | E10: =E8/E7 -> 0.94722133 | F10: =F8/F7 -> 0.94723727 | G10: =G8/G7 -> 0.95524451 | H10: =H8/H7 -> 0.93740131 | I10: =I8/I7 -> 0.42240419 | J10: =J8/J7 -> 0.93488145 | ... P10: =P8/P7 -> 1.1557632
C11: =C9/C7*1 -> 0.034445125 | D11: =D9/D7*1 -> 0.038692316 | E11: =E9/E7*1 -> 0.044769585 | F11: =F9/F7*1 -> 0.043654542 | G11: =G9/G7*1 -> 0.032523798 | H11: =H9/H7*1 -> 0.049501773 | I11: =I9/I7*1 -> 0.031046003 | J11: =J9/J7*1 -> 0.056972892 | ... P11: =P9/P7*1 -> 0.046832269
B12: LOSIS | C12: =(C7-C8-C9)/C7 -> 0.0080075283 | D12: =(D7-D8-D9)/D7 -> 0.0096589657 | E12: =(E7-E8-E9)/E7 -> 0.0080090802 | F12: =(F7-F8-F9)/F7 -> 0.0091081887 | G12: =(G7-G8-G9)/G7 -> 0.012231689 | H12: =(H7-H8-H9)/H7 -> 0.013096916 | I12: =(I7-I8-I9)/I7 -> 0.5465498 | J12: =(J7-J8-J9)/J7 -> 0.0081456621 | ... P12: =(P7-P8-P9)/P7 -> -0.20259547
A14: TANGGAL flow meter
A15: NO | B15: NAMA PRODUK | C15: 01 Juli | D15: 02 Juli | E15: 03 Juli | F15: 04 Juli | G15: 05 Juli | H15: 06 Juli | I15: 07 Juli | J15: 08 Juli | K15: 09 Juli | L15: 10 Juli | M15: 11 Juli | N15: 12 Juli | O15: 13 Juli | P15: 14 Juli | Q15: 15 Juli | R15: TOTAL | S15: Sounding | T15: Yield Theory | U15: Yield Aktual
A16: 1 | B16: CPO | C16: 680800 | D16: 806400 | E16: 858600 | F16: 898100 | G16: 26100 | H16: 513200 | I16: 119200 | J16: 208900 | K16: 147700 | L16: 425800 | M16: 347900 | N16: 459100 | O16: 509200 | P16: 396700 | Q16: 20200 | R16: =SUM(C16:Q16) -> 6417900 | S16: =5745000+14073+R19 -> 7292813
A17: 2 | B17: RBDPO | C17: 722400 | D17: 826700 | E17: 980700 | F17: 980600 | G17: 19900 | H17: 582000 | I17: 150500 | J17: 215300 | K17: 70837 | L17: 488153 | M17: 379337 | N17: 502200 | O17: 535800 | P17: 412600 | Q17: 92100 | R17: =SUM(C17:Q17) -> 6959127 | S17: =SUM(C17:M17)+R20 -> 6940126 | T17: =R17/R16 -> 1.0843309 | U17: =S17/S16 -> 0.9516391 | W17: =4984655+R20 -> 6508354
A18: 3 | B18: PFAD | C18: 37300 | D18: 38700 | E18: 49500 | F18: 47100 | G18: 3800 | H18: 30300 | I18: 9300 | J18: 14000 | K18: 14800 | L18: 25100 | M18: 23400 | N18: 23900 | O18: 26800 | P18: 22200 | Q18: 5900 | R18: =SUM(C18:Q18) -> 372100 | S18: =248746+R21 -> 322377 | T18: =R18/R16 -> 0.057978466 | U18: =S18/S16 -> 0.044204753
C19: =C17/C16 -> 1.0611046 | D19: =D17/D16 -> 1.0251736 | E19: =E17/E16 -> 1.1422082 | F19: =F17/F16 -> 1.0918606 | G19: =G17/G16 -> 0.76245211 | H19: =H17/H16 -> 1.1340608 | I19: =I17/I16 -> 1.2625839 | J19: =J17/J16 -> 1.0306367 | K19: =K17/K16 -> 0.47960054 | L19: 269515 | M19: CPO | N19: 534002 | O19: 568773 | P19: 430750 | Q19: 269300 | R19: =L19+N19+O19+P19-Q19 -> 1533740 | U19: =100%-U17-U18 -> 0.0041561466 | V19: Losses
M20: RBDPO | N20: 492952 | O20: 532902 | P20: 497845 | R20: =SUM(N20:P20) -> 1523699
N21: 27655 | O21: 25803 | P21: 20173 | R21: =SUM(N21:P21) -> 73631
B22: Nb : | C22: 1. 5.745.000 adalaha angka consume CPO tanggal 1 - 11 ( Opening Stock + Incoming - Closing tanggal 11 )
C23: 2. 14.073 ( Beda Pembacaan antara sounding dan timbangan )
C24: 3. 1.533.740 adalah angka sounding CPO 12, 13, 14
A25: FRAKSINASI
A26: TANGGAL
A27: NO | B27: NAMA PRODUK | C27: 01 Juli | D27: 02 Juli | E27: 03 Juli | F27: 04 Juli | G27: 05 Juli | H27: 06 Juli | I27: 07 Juli | J27: 08 Juli | K27: 09 Juli | L27: 10 Juli | M27: 11 Juli | N27: 12 Juli | O27: 13 Juli | P27: 14 Juli | Q27: 15 Juli | R27: TOTAL | S27: Sounding | T27: Yield
A28: 1 | B28: RBDPO | C28: 667300 | D28: 695000 | E28: 814100 | F28: 760000 | G28: 620300 | H28: 587100 | I28: 118500 | J28: 0 | K28: 253000 | L28: 0 | M28: 466900 | N28: 258400 | O28: 584400 | P28: 680200 | R28: =SUM(C28:Q28) -> 6505200
A29: 2 | B29: OLEIN IV 58 | C29: 518400 | D29: 487200 | E29: 539100 | F29: 571900 | G29: 554300 | H29: 449900 | I29: 209900 | J29: 0 | K29: 297100 | L29: 0 | M29: 472500 | N29: 207400 | O29: 239100 | P29: 414100 | R29: =SUM(C29:Q29) -> 4960900
A30: 3 | B30: STEARIN | C30: 207500 | D30: 202900 | E30: 215500 | F30: =27400+151100+55600 -> 234100 | G30: 213300 | H30: 183700 | I30: 104800 | J30: 0 | K30: 93900 | L30: 0 | M30: 172400 | N30: 111100 | O30: 81200 | P30: 193200 | R30: =SUM(C30:Q30) -> 2013600
O32: STOCK OPNAME | R32: =1311190 -> 1311190
O33: TOTAL TERIMA 1- 11 TIMBANGAN | R33: 3865830
O34: PIPANISASI DAN GK 1 - 11 | R34: 1888995
O35: STOCK AKHIR OPNAME 11 JULI | R35: 1320540.6
R36: =R32+R33+R34-R35 -> 5745474.4
O38: STOCK OPNAME 1 JULI | R38: 178489.22
O39: TOTAL FLOW METER 11 | R39: =SUM(C28:M28) -> 4982200
O40: STOCK AKHIR OPNAME 11 JULI
