Workbook

Sheet Desember 2024
C1: PRODUCTION REPORT PMG II
C2: No | D2: ITEM | E2: Budget / Norma | F2: UoM | G2: DESEMBER | AM2: TOTAL MONTHLY (Kg)
G3: 1 | H3: 2 | I3: 3 | J3: 4 | K3: 5 | L3: 6 | M3: 7 | N3: 8 | O3: 9 | P3: 10 | Q3: 11 | R3: 12 | S3: 13 | T3: 14 | U3: 15 | V3: 16 | W3: 17 | X3: 18 | Y3: 19 | Z3: 20 | AA3: 21 | AB3: 22 | AC3: 23 | AD3: 24 | AE3: 25 | AF3: 26 | AG3: 27 | AH3: 28 | AI3: 29 | AJ3: 30 | AK3: 31
C4: 1 | D4: PRODUCTION | AM4: Production
D5: Refinery | AM5: Refinery
D6: Running Days | F6: Day | I6: 1 | J6: 1 | K6: 1 | L6: 1 | M6: 1 | N6: 1 | O6: 1 | P6: 1 | Q6: 1 | R6: 1 | S6: 1 | T6: 1 | U6: 1 | V6: 1 | W6: 1 | X6: 1 | Y6: 1 | Z6: 1 | AA6: 1 | AB6: 1 | AC6: 1 | AD6: 1 | AE6: 1 | AM6: =SUM(G6:AJ6) -> 23
D7: Incoming CPO | F7: Kg | G7: ='[1]01'!$P$15 -> 864484 | H7: ='[1]02'!$P$15 -> 920182 | I7: ='[1]03'!$P$15 -> 464321 | J7: ='[2]30 (Stock Opname)'!$P$15 -> 1416573 | K7: ='[3]02'!$P$15 -> 920182 | L7: ='[4]06'!$P$15 -> 1133688 | M7: ='[4]07'!$P$15 -> 1225114 | O7: ='[5]09'!$P$15 -> 600192 | P7: ='[6]10'!$P$15 -> 397080 | Q7: ='[7]11'!$P$15 -> 902048 | R7: ='[8]12'!$P$15 -> 558257 | S7: ='[9]13'!$P$15 -> 248740 | T7: ='[10]14'!$P$15 -> 598141 | U7: 0 | V7: ='[11]16'!$P$15 -> 313454 | W7: 0 | X7: ='[8]18'!$P$15 -> 111765 | Y7: ='[10]19'!$P$15 -> 0 | Z7: ='[12]20'!$P$15 -> 28079 | AA7: 0 | AB7: 0 | AC7: 0 | AD7: 0 | AE7: 0 | AF7: 0 | AG7: ='[9]27'!$P$15 -> 326528 | AH7: 172434 | AM7: =SUM(G7:AJ7) -> 11201262
D8: Ratio Run CPO | F8: % | G8: =G9/2500000*100 -> 0 | H8: =H9/2500000*100 -> 0 | I8: =I9/2500000 -> 0 | J8: =J9/2500000 -> 0 | K8: =K9/2500000 -> 0 | L8: =L9/2500000 -> 0 | M8: =M9/2500000 -> 0.1978084 | N8: =N9/2500000 -> 0.7459128 | O8: =O9/2500000 -> 0.63258 | P8: =P9/2500000 -> 0.24841 | Q8: =Q9/2500000 -> 0.0991936 | R8: =R9/2500000*100 -> 42.528 | S8: =S9/2500000 -> 0.8785152 | T8: =T9/2500000*100 -> 65.56452 | U8: =U9/2500000*100 -> 64.66848 | V8: =V9/2500000 -> 0.3628544 | W8: =W9/2500000 -> 0.7848968 | X8: =X9/2500000 -> 0.9665644 | Y8: =Y9/2500000 -> 0.8621888 | Z8: =Z9/2500000 -> 0.5995688 | AA8: =AA9/2500000 -> 0.279426 | AB8: =AB9/2500000 -> 0.67005 | AC8: =AC9/2500000 -> 0.7161404 | ... AE8: =AE9/2500000 -> 0.0420068 | AF8: =AF9/2500000*100 -> 0 | AG8: =AG9/2500000*100 -> 0 | AH8: =AH9/2500000*100 -> 0 | AI8: =AI9/2500000*100 -> 0 | AJ8: =AJ9/2500000*100 -> 0 | AK8: =AK9/2500000*100 -> 0 | AM8: =AM9/2500000/AM6 -> 0.43952621
D9: CPO Consume Total | E9: 36359000 | F9: Kg | I9: ='[2]30 (Stock Opname)'!$Q$15 -> 0 | J9: ='[2]30 (Stock Opname)'!$Q$15 -> 0 | M9: 494521 | N9: ='[4]08'!$Q$15 -> 1864782 | O9: 1581450 | P9: ='[6]10'!$Q$15 -> 621025 | Q9: ='[7]11'!$Q$15 -> 247984 | R9: ='[8]12'!$Q$15 -> 1063200 | S9: ='[9]13'!$Q$15 -> 2196288 | T9: ='[10]14'!$Q$15 -> 1639113 | U9: ='[10]15'!$Q$15 -> 1616712 | V9: ='[11]16'!$Q$15 -> 907136 | W9: ='[13]17'!$Q$15 -> 1962242 | X9: ='[8]18'!$Q$15 -> 2416411 | Y9: ='[10]19'!$Q$15 -> 2155472 | Z9: ='[12]20'!$Q$15 -> 1498922 | AA9: ='[12]21'!$Q$15 -> 698565 | AB9: ='[12]22'!$Q$15 -> 1675125 | AC9: ='[14]23'!$Q$15 -> 1790351 | AD9: ='[15]24'!$Q$15 -> 738441 | AE9: ='[15]25'!$Q$15 -> 105017 | AG9: ='[9]27'!$Q$15 -> 0 | AM9: =SUM(G9:AJ9) -> 25272757
D10: Avg Daily Consump CPO ( MTD ) | AM10: =AM9/AM6 -> 1098815.5 | AN10: =AM9/E9 -> 0.69508944
D11: CPO Consume Poram | E11: 29045000 | F11: Kg | G11: =G9-G12 -> 0 | H11: =H9-H12 -> 0 | I11: =I9-I12 -> 0 | J11: =J9-J12 -> 0 | L11: =L9-L12 -> 0 | M11: =M9-M12 -> 494521 | N11: =N9-N12 -> 1864782 | O11: =O9-O12 -> 1581450 | P11: =P9-P12 -> 621025 | Q11: =Q9-Q12 -> 247984 | R11: =R9-R12 -> 1063200 | S11: =S9-S12 -> 2196288 | ... AK11: =AK9-AK12 -> 0 | AM11: =SUM(G11:AJ11) -> 25272757
D12: CPO Consume Brand | E12: 7314000 | F12: Kg | G12: =G39+G48+G53 -> 0 | H12: =H39+H48+H53 -> 0 | I12: =I39+I48+I53 -> 0 | J12: =J39+J48+J53 -> 0 | K12: 0 | L12: =L39+L48+L53 -> 0 | M12: =M39+M48+M53 -> 0 | N12: =N39+N48+N53 -> 0 | O12: =O39+O48+O53 -> 0 | P12: =P39+P48+P53 -> 0 | Q12: =Q39+Q48+Q53 -> 0 | R12: =R39+R48+R53 -> 0 | S12: =S39+S48+S53 -> 0 | ... AK12: =AK39+AK48+AK53 -> 0 | AM12: =SUM(G12:AJ12) -> 0
D13: - FFA | E13: 5 | F13: % | I13: 3.92 | J13: 3.9 | M13: 3.94 | N13: 3.95 | O13: 3.98 | P13: 4.03 | Q13: 4.06 | R13: 3.95 | S13: 4.01 | T13: 4.01 | U13: 3.99 | V13: 4.03 | W13: 3.85 | X13: 4 | Y13: =(4.09+4.06)/2 -> 4.075 | Z13: 4.1 | AA13: 4.08 | AB13: 4.11 | AC13: 4.12 | AD13: 4.6 | AG13: 0 | AM13: =SUM(G13:AJ13)/AM6 -> 3.3336957
D14: - Moist & Impurities | E14: 0.5 | F14: % | I14: 0.4 | J14: 0.42 | M14: 0.39 | N14: 0.39 | O14: 0.39 | P14: 0.4 | Q14: 0.42 | R14: 0.44 | S14: 0.39 | T14: 0.4 | U14: 0.4 | V14: 0.41 | W14: 0.42 | X14: 0.43 | Y14: =(0.44+0.42)/2 -> 0.43 | Z14: 0.4 | AA14: 0.4 | AB14: 0.4 | AC14: 0.44 | AD14: 0.6 | AG14: 0 | AM14: =SUM(G14:AJ14)/AM6 -> 0.36391304
D15: - DOBI | E15: 2,20 Min | F15: % | I15: 2.22 | J15: 2.22 | M15: 2.21 | N15: 2.2 | O15: 2.21 | P15: 2.2 | Q15: 2.21 | R15: 2.4 | S15: 2.4 | T15: 2.2 | U15: 2.2 | V15: 2.38 | W15: 2.2 | X15: 2.2 | Y15: 2.2 | Z15: 2.2 | AA15: 2.2 | AB15: 2.2 | AC15: 2.21 | AD15: 2.2 | AG15: 0 | AM15: =SUM(G15:AJ15)/AM6 -> 1.8452174
D16: TANK | I16: 104 | J16: 104 | M16: 103 | N16: 104 | O16: 104 | P16: 104 | Q16: 104 | R16: 105 | S16: 105 | T16: 106 | U16: 106 | V16: 106 | W16: 107 | X16: 107 | Y16: 107.103 | Z16: 103 | AA16: 103 | AB16: 104 | AC16: 105 | AD16: "105/107 | AG16: 0
D17: Product | AM17: Product
D18: OIP RBDPO | J18: ='OIP Refinery '!K9 -> 308515.38 | K18: ='OIP Refinery '!L10 -> 0 | L18: ='OIP Refinery '!L11 -> 24423 | M18: ='OIP Refinery '!L12 -> -23693 | N18: ='OIP Refinery '!L13 -> 8781 | O18: ='OIP Refinery '!L14 -> -6501 | P18: ='OIP Refinery '!L15 -> -1620 | Q18: ='OIP Refinery '!L16 -> 727 | S18: ='[16]OIP Refinery '!L18 -> 16100 | V18: ='OIP Refinery '!L21 -> 9196 | W18: ='OIP Refinery '!L22 -> -35039 | X18: ='OIP Refinery '!L23 -> -426 | Y18: ='OIP Refinery '!L24 -> 4784 | Z18: ='OIP Refinery '!L25 -> 22542 | AA18: ='OIP Refinery '!L26 -> 9106 | AB18: ='OIP Refinery '!L27 -> -1526 | AC18: ='OIP Refinery '!L28 -> -17952 | AD18: ='OIP Refinery '!L29 -> 108237 | AE18: ='OIP Refinery '!L30 -> 9535 | AG18: ='OIP Refinery '!L32 -> 0
D19: RBDPO | E19: 34458000 | F19: Kg | M19: =457152+23693 -> 480845 | N19: ='[4]08'!$P$18+8781 -> 1684248 | O19: =1441290+45083 -> 1486373 | P19: ='[6]10'!$P$18+1620 -> 664578 | Q19: ='[7]11'!$P$18+727 -> 246488 | R19: ='[8]12'!$P$18+2355 -> 923422 | S19: ='[9]13'!$P$18+16100 -> 2130396 | T19: ='[10]14'!$P$18+17373 -> 1575805 | U19: ='[10]15'!$P$18+23544 -> 1589390 | V19: ='[11]16'!$P$23+9196 -> 863761 | W19: ='[13]17'!$P$18+35039 -> 1815060 | X19: ='[8]18'!$P$18+426 -> 2519497 | Y19: ='[10]19'!$P$18+4784 -> 2031197 | Z19: ='[12]20'!$P$18+22542 -> 1454272 | AA19: ='[12]21'!$P$18+9106 -> 694376 | AB19: ='[12]22'!$P$18+1526 -> 1576860 | AC19: ='[14]23'!$P$18+17952 -> 1730769 | AD19: ='[15]24'!$P$18+108237 -> 682583 | AE19: ='[15]25'!$P$18+9535 -> 185490 | AF19: 54158 | AG19: ='[9]27'!$P$18 -> 0 | AM19: =SUM(G19:AJ19) -> 24389568
D20: PFAD | E20: 1636000 | F20: Kg | M20: 21360 | N20: ='[4]08'!$P$27 -> 74300 | O20: 63960 | P20: 25820 | Q20: ='[7]11'!$P$27 -> 10475 | R20: ='[8]12'!$P$27 -> 42351 | S20: ='[9]13'!$P$27 -> 100021 | T20: ='[10]14'!$P$27 -> 71404 | U20: ='[10]15'!$P$27 -> 70951 | V20: ='[11]16'!$P$27 -> 40085 | W20: ='[13]17'!$P$27 -> 75721 | X20: ='[8]18'!$P$27 -> 105866 | Y20: ='[10]19'!$P$27 -> 87291 | Z20: ='[12]20'!$P$27 -> 64662 | AA20: ='[12]21'!$P$27 -> 28286 | AB20: ='[12]22'!$P$27 -> 69976 | AC20: ='[14]23'!$P$27 -> 73470 | AD20: ='[15]24'!$P$27 -> 36964 | AE20: ='[15]25'!$P$27 -> 18342 | AF20: 7825 | AG20: ='[9]27'!$P$27 -> 0 | AM20: =SUM(G20:AJ20) -> 1089130
D21: Fractionation
D22: Running Days | F22: Day | N22: 1 | O22: 1 | P22: 1 | Q22: 1 | R22: 1 | S22: 1 | T22: 1 | U22: 1 | V22: 1 | W22: 1 | X22: 1 | Y22: 1 | Z22: 1 | AA22: 1 | AB22: 1 | AC22: 1 | AD22: 1 | AE22: 1 | AF22: 1 | AG22: 1 | AH22: 1 | AM22: =SUM(G22:AK22) -> 21
D23: Avg Daily Consump RBDPO ( MTD ) | F23: Kg | G23: 0 | H23: 0 | I23: 0 | J23: 0 | K23: 0 | L23: 0 | M23: 0 | N23: 0 | O23: 0 | P23: 0 | Q23: 0 | R23: 0 | S23: 0 | T23: 0 | U23: 0 | V23: 0 | W23: 0 | X23: 0 | Y23: 0 | Z23: 0 | AA23: 0 | AB23: 0 | AC23: 0 | AD23: 0 | AE23: 0 | AF23: 0 | AG23: 0 | AH23: 0 | AI23: 0 | AJ23: 0 | AK23: 0 | AM23: =AM28/AM22 -> 1147468.4
D24: Total RBDPO transfer to plant | F24: Kg | N24: ='Oip Fract .'!L14 -> 281577 | O24: 392100 | P24: ='[6]10'!$Q$18 -> 366697 | Q24: ='[7]11'!$Q$18 -> 1206767 | R24: ='[8]12'!$Q$18 -> 1107426 | S24: ='[9]13'!$Q$18 -> 985016 | T24: ='[10]14'!$Q$18 -> 2026430 | U24: ='[10]15'!$Q$18 -> 2148697 | V24: ='[11]16'!$Q$18 -> 657964 | W24: ='[13]17'!$Q$18 -> 2347734 | X24: ='[8]18'!$Q$18 -> 3737260 | Y24: ='[10]19'!$Q$18 -> 1378873 | Z24: ='[12]20'!$Q$18 -> 30924 | AA24: ='[12]21'!$Q$18 -> 476133 | AB24: ='[12]22'!$Q$18 -> 1230701 | AC24: ='[14]23'!$Q$18 -> 1954027 | AD24: ='[15]24'!$Q$18 -> 1112757 | AE24: ='[15]25'!$Q$18 -> 1485846 | AF24: 1185518 | AG24: ='[9]27'!$Q$18 -> 0 | AM24: =SUM(G24:AJ24) -> 24112447
D25: Stok TK 131 | E25: 559 | F25: ton | P25: 361081 | Q25: 312272 | R25: ='[17]Oip Fract .'!U18 -> 447800 | S25: ='[16]Oip Fract .'!U19 -> 160000 | T25: ='Oip Fract .'!U20 -> 156000 | U25: ='Oip Fract .'!U21 -> 265000 | V25: ='Oip Fract .'!U22 -> 88200 | W25: ='Oip Fract .'!U23 -> 35220 | X25: ='Oip Fract .'!U24 -> 95225 | Y25: ='Oip Fract .'!U25 -> 234123 | Z25: ='Oip Fract .'!U26 -> 223284 | AA25: ='Oip Fract .'!U27 -> 158003 | AB25: ='Oip Fract .'!U28 -> 167918 | AC25: ='Oip Fract .'!U29 -> 340216 | AD25: ='Oip Fract .'!U30 -> 156238 | AE25: ='Oip Fract .'!U31 -> 78021 | AF25: ='Oip Fract .'!U32 -> 37638 | AG25: ='Oip Fract .'!U33 -> 37954 | AH25: ='Oip Fract .'!U33 -> 37954
D26: Stok TK 132 | E26: 559 | F26: ton | P26: ='Oip Fract .'!W16 -> 38852 | Q26: 312272 | R26: ='[17]Oip Fract .'!W18 -> 347595 | S26: ='[16]Oip Fract .'!W19 -> 112000 | T26: ='Oip Fract .'!W20 -> 85000 | U26: ='Oip Fract .'!W21 -> 265000 | V26: ='Oip Fract .'!W22 -> 80200 | W26: ='Oip Fract .'!W23 -> 35220 | X26: ='Oip Fract .'!W24 -> 105225 | Y26: ='Oip Fract .'!W25 -> 234125 | Z26: ='Oip Fract .'!W26 -> 216280 | AA26: ='Oip Fract .'!W27 -> 155107 | AB26: ='Oip Fract .'!W28 -> 164248 | AC26: ='Oip Fract .'!W29 -> 330359 | AD26: ='Oip Fract .'!W30 -> 156022 | AE26: ='Oip Fract .'!W31 -> 156240 | AF26: ='Oip Fract .'!W32 -> 197872 | AG26: ='Oip Fract .'!W33 -> 108106 | AH26: ='Oip Fract .'!W33 -> 108106
D27: Ratio Run RBDPO | P27: =P28/2500000 -> 0.0715696 | Q27: =Q28/2500000 -> 0.2793592 | R27: =R28/2500000 -> 0.4093536 | S27: =S28/2500000 -> 0.546472 | T27: =T28/2500000 -> 0.7772728 | U27: =U28/2500000 -> 0.8476676 | V27: =V28/2500000 -> 0.4410548 | W27: =W28/2500000 -> 0.907438 | ... AH27: =AH28/2500000 -> 0.058144 | AM27: =AM28/2500000/10 -> 0.96387348
D28: Total Proses RBDPO | F28: Kg | G28: =SUM(G31,G35,G40,G44,G54) -> 0 | H28: =SUM(H31,H35,H40,H44,H54) -> 0 | I28: =SUM(I31,I35,I40,I44,I54) -> 0 | J28: =SUM(J31,J35,J40,J44,J54) -> 0 | L28: =SUM(L31,L35,L40,L44,L54) -> 0 | M28: =SUM(M31,M35,M40,M44,M54) -> 0 | N28: =SUM(N31,N35,N40,N44,N54) -> 0 | O28: =SUM(O31,O35,O40,O44,O54) -> 0 | P28: =SUM(P31,P35,P40,P44,P54) -> 178924 | Q28: =SUM(Q31,Q35,Q40,Q44,Q54) -> 698398 | R28: =SUM(R31,R35,R40,R44,R54) -> 1023384 | S28: =SUM(S31,S35,S40,S44,S54) -> 1366180 | ... AA28: =SUM(AA31,AA35,AA40,AA44,AA54) -> 546176 | AB28: ='[12]22'!$Q$18 -> 1230701 | AC28: =SUM(AC31,AC35,AC40,AC44,AC54) -> 1595581 | AD28: =SUM(AD31,AD35,AD40,AD44,AD54) -> 1493796 | AE28: =SUM(AE31,AE35,AE40,AE44,AE54) -> 1574199 | AF28: =SUM(AF31,AF35,AF40,AF44,AF54) -> 2042339 | AG28: =SUM(AG31,AG35,AG40,AG44,AG54) -> 223353 | AH28: =SUM(AH31,AH35,AH40,AH44,AH54) -> 145360 | AI28: =SUM(AI31,AI35,AI40,AI44,AI54) -> 0 | AJ28: =SUM(AJ31,AJ35,AJ40,AJ44,AJ54) -> 0 | AK28: =SUM(AK31,AK35,AK40,AK44,AK54) -> 0 | AM28: =SUM(G28:AJ28) -> 24096837 | AN28: =AM28/E19 -> 0.69931038
D29: Sisa Filling Crystalizer | F29: Kg | G29: =G24-G28 -> 0 | I29: =I24-I28 -> 0 | J29: =SUM(J32,J36,J41,J45,#REF!) -> #REF! | K29: 68473 | L29: =L24-L28 -> 0 | M29: =M24-M28 -> 0 | N29: =N24-N28 -> 281577 | O29: =O24-O28 -> 392100 | P29: =P24-P28 -> 187773 | Q29: =Q24-Q28 -> 508369 | R29: =R24-R28 -> 84042 | S29: =S24-S28 -> -381164 | ... AK29: =AK24-AK28 -> 0 | AM29: =SUM(G29:AJ29) -> #REF!
D30: Fractionation OLEIN IV 56 | AM30: Olein IV 56
D31: RBDPO Consume | F31: Kg | G31: =G32+G33 -> 0 | H31: =H32+H33 -> 0 | I31: =I32+I33 -> 0 | J31: =J32+J33 -> 0 | K31: 0 | L31: =L32+L33 -> 0 | M31: =M32+M33 -> 0 | N31: =N32+N33 -> 0 | O31: =O32+O33 -> 0 | P31: =P32+P33 -> 178924 | Q31: =Q32+Q33 -> 111217 | R31: =R32+R33 -> 114465 | S31: =S32+S33 -> 0 | ... AK31: =AK32+AK33 -> 0 | AM31: =SUM(G31:AJ31) -> 7003508
D32: OLEIN IV 56 | F32: Kg | G32: 0 | H32: 0 | I32: 0 | J32: 0 | K32: 0 | L32: 0 | M32: 0 | N32: 0 | O32: 0 | P32: ='[6]10'!$P$23 -> 144963 | Q32: ='[7]11'!$P$21 -> 91214 | R32: ='[8]12'!$P$21 -> 92131 | V32: ='[11]16'!$P$21 -> 275346 | W32: ='[13]17'!$P$19 -> 1618321 | X32: ='[8]18'!$P$23 -> 2369769 | Y32: 123327 | AA32: 0 | AB32: 0 | AC32: 0 | AE32: 0 | AF32: 734495 | AG32: ='[9]27'!$P$21 -> 134128 | AH32: 0 | AI32: 0 | AJ32: 0 | AK32: 0 | AM32: =SUM(G32:AJ32) -> 5583694
D33: STEARIN | F33: Kg | G33: 0 | H33: 0 | I33: 0 | J33: 0 | K33: 0 | L33: 0 | M33: 0 | N33: 0 | O33: 0 | P33: ='[6]10'!$P$31 -> 33961 | Q33: 20003 | R33: 22334 | V33: 59345 | W33: 384307 | X33: ='[8]18'!$P$31 -> 547180 | Y33: 28223 | AA33: 0 | AB33: 0 | AC33: 0 | AE33: 0 | AF33: 235236 | AG33: 89225 | AJ33: 0 | AK33: 0 | AM33: =SUM(G33:AJ33) -> 1419814
D34: Fractionation OLEIN IV 57 ( Bulk ) | AM34: Olein IV 57 ( Bulk )
D35: RBDPO Consume | F35: Kg | G35: =G36+G37 -> 0 | H35: =H36+H37 -> 0 | I35: =I36+I37 -> 0 | J35: =J36+J37 -> 0 | K35: 0 | L35: =L36+L37 -> 0 | M35: =M36+M37 -> 0 | N35: =N36+N37 -> 0 | O35: =O36+O37 -> 0 | P35: =P36+P37 -> 0 | Q35: =Q36+Q37 -> 0 | R35: =R36+R37 -> 0 | S35: =S36+S37 -> 0 | ... X35: =X36+X37 -> 0 | AA35: =AA36+AA37 -> 0 | AB35: =AB36+AB37 -> 0 | AC35: =AC36+AC37 -> 0 | AD35: =AD36+AD37 -> 0 | AE35: =AE36+AE37 -> 0 | AF35: =AF36+AF37 -> 0 | AG35: =AG36+AG37 -> 0 | AH35: =AH36+AH37 -> 0 | ... AK35: =AK36+AK37 -> 0 | AM35: =SUM(G35:AJ35) -> 0
D36: OLEIN IV 57 | F36: Kg | G36: 0 | H36: 0 | I36: 0 | J36: 0 | K36: 0 | L36: 0 | M36: 0 | N36: 0 | O36: 0 | P36: 0 | Q36: 0 | R36: 0 | S36: 0 | T36: 0 | U36: 0 | V36: 0 | W36: 0 | X36: 0 | AA36: 0 | AB36: 0 | AC36: 0 | AD36: 0 | AE36: 0 | AF36: 0 | AG36: 0 | AM36: =SUM(G36:AJ36) -> 0
D37: STEARIN | F37: Kg | G37: 0 | H37: 0 | I37: 0 | J37: 0 | K37: 0 | L37: 0 | M37: 0 | N37: 0 | O37: 0 | P37: 0 | Q37: 0 | R37: 0 | S37: 0 | T37: 0 | U37: 0 | V37: 0 | W37: 0 | X37: 0 | AA37: 0 | AB37: 0 | AC37: 0 | AD37: 0 | AE37: 0 | AF37: 0 | AG37: 0 | AM37: =SUM(G37:AJ37) -> 0
D38: Fractionation OLEIN IV 57 ( Retail ) | AM38: Olein IV 57 ( Retail )
D39: CPO Consume | F39: Kg | AM39: =SUM(G39:AJ39) -> 0
D40: RBDPO Brand Consume | F40: Kg | G40: =G41+G42 -> 0 | H40: =H41+H42 -> 0 | I40: =I41+I42 -> 0 | J40: =J41+J42 -> 0 | K40: 0 | L40: =L41+L42 -> 0 | M40: =M41+M42 -> 0 | N40: =N41+N42 -> 0 | O40: =O41+O42 -> 0 | P40: =P41+P42 -> 0 | Q40: =Q41+Q42 -> 0 | R40: =R41+R42 -> 0 | S40: =S41+S42 -> 0 | ... X40: =X41+X42 -> 0 | AA40: =AA41+AA42 -> 0 | AB40: =AB41+AB42 -> 0 | AC40: =AC41+AC42 -> 0 | AD40: =AD41+AD42 -> 0 | AE40: =AE41+AE42 -> 0 | AF40: =AF41+AF42 -> 0 | AG40: =AG41+AG42 -> 0 | AH40: =AH41+AH42 -> 0 | ... AK40: =AK41+AK42 -> 0 | AM40: =SUM(G40:AJ40) -> 0
D41: OLEIN IV 57 Low Color | F41: Kg | G41: 0 | H41: 0 | I41: 0 | J41: 0 | K41: 0 | L41: 0 | M41: 0 | N41: 0 | O41: 0 | P41: 0 | Q41: 0 | R41: 0 | S41: 0 | T41: 0 | U41: 0 | V41: 0 | W41: 0 | X41: 0 | AA41: 0 | AB41: 0 | AC41: 0 | AD41: 0 | AE41: 0 | AF41: 0 | AG41: 0 | AM41: =SUM(G41:AJ41) -> 0
D42: STEARIN | F42: Kg | G42: 0 | H42: 0 | I42: 0 | J42: 0 | K42: 0 | L42: 0 | M42: 0 | N42: 0 | O42: 0 | P42: 0 | Q42: 0 | R42: 0 | S42: 0 | T42: 0 | U42: 0 | V42: 0 | W42: 0 | X42: 0 | AA42: 0 | AB42: 0 | AC42: 0 | AD42: 0 | AE42: 0 | AF42: 0 | AG42: 0 | AM42: =SUM(G42:AJ42) -> 0
D43: Fractionation OLEIN IV 58 ( Bulk ) | AM43: Olein IV 58 ( Bulk )
D44: RBDPO Consume | E44: =E45+E46 -> 21429000 | F44: Kg | G44: =G45+G46 -> 0 | H44: =H45+H46 -> 0 | I44: =I45+I46 -> 0 | J44: =J45+J46 -> 0 | L44: =L45+L46 -> 0 | M44: =M45+M46 -> 0 | N44: =N45+N46 -> 0 | O44: =O45+O46 -> 0 | Q44: =Q45+Q46 -> 587181 | R44: =R45+R46 -> 908919 | S44: =S45+S46 -> 1366180 | T44: =T45+T46 -> 1943182 | U44: =U45+U46 -> 2119169 | V44: =V45+V46 -> 767946 | W44: =W45+W46 -> 265967 | X44: =X45+X46 -> 0 | ... AK44: =AK45+AK46 -> 0 | AM44: =SUM(G44:AJ44) -> 16973017
D45: OLEIN IV 58 | E45: 15000000 | F45: Kg | N45: =O45-P45 -> 0 | Q45: ='[7]11'!$P$22 -> 422273 | R45: ='[8]12'!$P$22 -> 600664 | S45: 976066 | T45: ='[10]14'!$P$23 -> 1484274 | U45: ='[10]15'!$P$23 -> 1603408 | V45: ='[11]16'!$P$22 -> 579219 | W45: ='[13]17'!$P$22 -> 186695 | X45: 0 | Y45: ='[12]19'!$P$23-123327 -> 902933 | Z45: ='[12]20'!$P$23 -> 102005 | AA45: ='[12]21'!$P$23 -> 355278 | AB45: ='[12]22'!$P$23 -> 803105 | AC45: ='[14]23'!$P$23 -> 1168886 | AD45: ='[15]24'!$P$23 -> 977923 | AE45: ='[15]25'!$P$23 -> 1029443 | AF45: 795403 | AG45: 0 | AH45: 0 | AJ45: 0 | AK45: 0 | AM45: =SUM(G45:AJ45) -> 11987575
D46: STEARIN | E46: 6429000 | F46: Kg | Q46: 164908 | R46: 308255 | S46: 390114 | T46: ='[10]14'!$P$31 -> 458908 | U46: ='[10]15'!$P$31 -> 515761 | V46: 188727 | W46: 79272 | X46: 0 | Y46: ='[12]19'!$P$31-28223 -> 345252 | Z46: ='[12]20'!$P$31 -> 126174 | AA46: ='[12]21'!$P$31 -> 190898 | AB46: ='[12]22'!$P$31 -> 452644 | AC46: ='[14]23'!$P$31 -> 426695 | AD46: ='[15]24'!$P$31 -> 515873 | AE46: ='[15]25'!$P$31 -> 544756 | AF46: 277205 | AG46: 0 | AJ46: 0 | AK46: 0 | AM46: =SUM(G46:AJ46) -> 4985442
D47: Fractionation OLEIN IV 58 ( Retail ) | AM47: Olein IV 58 ( Bulk )
D48: CPO Consume | F48: Kg | AM48: =SUM(G48:AJ48) -> 0
D49: RBDPO Consume | E49: =E50+E51 -> 21429000 | F49: Kg | G49: =G50+G51 -> 0 | H49: =H50+H51 -> 0 | I49: =I50+I51 -> 0 | J49: =J50+J51 -> 0 | K49: 0 | L49: =L50+L51 -> 0 | M49: =M50+M51 -> 0 | N49: =N50+N51 -> 0 | O49: =O50+O51 -> 0 | P49: =P50+P51 -> 0 | Q49: =Q50+Q51 -> 0 | R49: =R50+R51 -> 0 | S49: =S50+S51 -> 0 | ... AK49: =AK50+AK51 -> 0 | AM49: =SUM(G49:AJ49) -> 0
D50: OLEIN IV 58 | E50: 15000000 | F50: Kg | G50: 0 | H50: 0 | I50: 0 | J50: 0 | K50: 0 | L50: 0 | M50: 0 | N50: 0 | O50: 0 | P50: 0 | Q50: 0 | R50: 0 | S50: 0 | T50: 0 | U50: 0 | V50: 0 | W50: 0 | X50: 0 | Y50: 0 | Z50: 0 | AA50: 0 | AB50: 0 | AC50: 0 | AD50: 0 | AE50: 0 | AF50: 0 | AG50: 0 | AH50: 0 | AI50: 0 | AM50: =SUM(G50:AJ50) -> 0
D51: STEARIN | E51: 6429000 | F51: Kg | G51: 0 | H51: 0 | I51: 0 | J51: 0 | K51: 0 | L51: 0 | M51: 0 | N51: 0 | O51: 0 | P51: 0 | Q51: 0 | R51: 0 | S51: 0 | T51: 0 | U51: 0 | V51: 0 | W51: 0 | X51: 0 | Y51: 0 | Z51: 0 | AA51: 0 | AB51: 0 | AC51: 0 | AD51: 0 | AE51: 0 | AF51: 0 | AG51: 0 | AH51: 0 | AI51: 0 | AM51: =SUM(G51:AJ51) -> 0
D52: Fractionation OLEIN IV 60 | AM52: Olein IV 60
D53: CPO Consume | F53: Kg | AM53: =SUM(G53:AJ53) -> 0
D54: RBDPO Brand Consume | F54: Kg | G54: =G55+G56 -> 0 | H54: =H55+H56 -> 0 | I54: =I55+I56 -> 0 | J54: =J55+J56 -> 0 | K54: 0 | L54: 0 | M54: =M55+M56 -> 0 | N54: =N55+N56 -> 0 | O54: =O55+O56 -> 0 | P54: =P55+P56 -> 0 | Q54: =Q55+Q56 -> 0 | R54: =R55+R56 -> 0 | S54: =S55+S56 -> 0 | T54: =T55+T56 -> 0 | ... AK54: =AK55+AK56 -> 0 | AM54: =SUM(G54:AJ54) -> 145360
D55: OLEIN IV 60 Salvaco | F55: Kg | G55: 0 | H55: 0 | I55: 0 | J55: 0 | K55: 0 | L55: 0 | M55: 0 | N55: 0 | O55: 0 | P55: 0 | Q55: 0 | R55: 0 | S55: 0 | T55: 0 | U55: 0 | V55: 0 | W55: 0 | X55: 0 | Y55: 0 | Z55: 0 | AA55: 0 | AB55: 0 | AC55: 0 | AD55: 0 | AE55: 0 | AF55: 0 | AH55: 87260 | AI55: 0 | AM55: =SUM(G55:AJ55) -> 87260
D56: SOFT STEARIN | F56: Kg | G56: 0 | H56: 0 | I56: 0 | J56: 0 | K56: 0 | L56: 0 | M56: 0 | N56: 0 | O56: 0 | P56: 0 | Q56: 0 | R56: 0 | S56: 0 | T56: 0 | U56: 0 | V56: 0 | W56: 0 | X56: 0 | Y56: 0 | Z56: 0 | AA56: 0 | AB56: 0 | AC56: 0 | AD56: 0 | AE56: 0 | AH56: 58100 | AI56: 0 | AM56: =SUM(G56:AJ56) -> 58100
D57: Ratio Run RBDPO | F57: % | G57: 0 | H57: 0 | I57: 0 | J57: 0 | K57: 0 | L57: 0 | M57: 0 | N57: 0 | O57: 0 | P57: 0 | Q57: 0 | R57: 0 | S57: 0 | T57: 0 | U57: 0 | V57: 0 | W57: 0 | X57: 0 | Y57: 0 | Z57: 0 | AA57: 0 | AB57: 0 | AC57: 0 | AD57: 0 | AE57: 0 | AF57: 0 | AG57: 0 | AH57: 0 | AI57: 0 | AJ57: 0 | AK57: 0 | AM57: =SUM(G57:AJ57) -> 0
D58: YIELD | AM58: Yield
D59: RBDPO | E59: 94.2 | F59: % | G59: =(G19/(G9))*100 -> #DIV/0! | H59: =(H19/(H9))*100 -> #DIV/0! | I59: =(I19/(I9))*100 -> #DIV/0! | J59: =(J19/(J9))*100 -> #DIV/0! | K59: =(K19/(K9))*100 -> #DIV/0! | L59: =(L19/(L9))*100 -> #DIV/0! | M59: =(M19/(M9))*100 -> 97.234496 | N59: =(N19/(N9))*100 -> 90.318761 | ... AK59: =(AK19/(AK9))*100 -> #DIV/0! | AM59: =(AM19/(AM9))*100 -> 96.505371
D60: PFAD | E60: 5 | F60: % | G60: =(G20/(G9))*100 -> #DIV/0! | H60: =(H20/(H9))*100 -> #DIV/0! | I60: =(I20/(I9))*100 -> #DIV/0! | J60: =(J20/(J9))*100 -> #DIV/0! | L60: =(L20/(L9))*100 -> #DIV/0! | M60: =(M20/(M9))*100 -> 4.3193312 | N60: =(N20/(N9))*100 -> 3.9843799 | O60: =(O20/(O9))*100 -> 4.0443896 | P60: =(P20/(P9))*100 -> 4.1576426 | Q60: =(Q20/(Q9))*100 -> 4.2240628 | R60: =(R20/(R9))*100 -> 3.9833521 | S60: =(S20/(S9))*100 -> 4.5540931 | ... AK60: =(AK20/(AK9))*100 -> #DIV/0! | AM60: =(AM20/(AM9))*100 -> 4.3095021
D61: Olein IV 56 | E61: 82 | F61: % | G61: =G32/(G32+G33)*100 -> #DIV/0! | H61: =H32/(H32+H33)*100 -> #DIV/0! | I61: =I32/(I32+I33)*100 -> #DIV/0! | J61: =J32/(J32+J33)*100 -> #DIV/0! | K61: #DIV/0! | L61: =L32/(L32+L33)*100 -> #DIV/0! | M61: =M32/(M32+M33)*100 -> #DIV/0! | N61: =N32/(N32+N33)*100 -> #DIV/0! | O61: =O32/(O32+O33)*100 -> #DIV/0! | P61: =P32/(P32+P33)*100 -> 81.019315 | Q61: =Q32/(Q32+Q33)*100 -> 82.01444 | R61: =R32/(R32+R33)*100 -> 80.488359 | S61: =S32/(S32+S33)*100 -> #DIV/0! | ... AK61: =AK32/(AK32+AK33)*100 -> #DIV/0! | AM61: =AM32/(AM32+AM33)*100 -> 79.727102
D62: Stearin | E62: 18 | F62: % | G62: =(G33/G31)*100 -> #DIV/0! | H62: =(H33/H31)*100 -> #DIV/0! | I62: =(I33/I31)*100 -> #DIV/0! | J62: =(J33/J31)*100 -> #DIV/0! | K62: #DIV/0! | L62: =(L33/L31)*100 -> #DIV/0! | M62: =(M33/M31)*100 -> #DIV/0! | N62: =(N33/N31)*100 -> #DIV/0! | O62: =(O33/O31)*100 -> #DIV/0! | P62: =(P33/P31)*100 -> 18.980685 | Q62: =(Q33/Q31)*100 -> 17.98556 | R62: =(R33/R31)*100 -> 19.511641 | S62: =(S33/S31)*100 -> #DIV/0! | ... U62: =(U33/U31)*100 -> #DIV/0! | V62: =V33/(V33+V32)*100 -> 17.73128 | W62: =W33/(W33+W32)*100 -> 19.190134 | X62: =(X33/X31)*100 -> 18.758641 | Y62: =(Y33/Y31)*100 -> 18.622897 | Z62: =(Z33/Z31)*100 -> #DIV/0! | AA62: =(AA33/AA31)*100 -> #DIV/0! | AB62: =(AB33/AB31)*100 -> #DIV/0! | AC62: =(AC33/AC31)*100 -> #DIV/0! | AD62: =(AD33/AD31)*100 -> #DIV/0! | AE62: =(AE33/AE31)*100 -> #DIV/0! | ... AK62: =(AK33/AK31)*100 -> #DIV/0! | AM62: =AM33/(AM32+AM33)*100 -> 20.272898
D63: Olein IV 57 ( Bulk ) | E63: 75 | G63: =(G36/G35)*100 -> #DIV/0! | H63: =(H36/H35)*100 -> #DIV/0! | I63: =(I36/I35)*100 -> #DIV/0! | J63: =(J36/J35)*100 -> #DIV/0! | K63: #DIV/0! | L63: =(L36/L35)*100 -> #DIV/0! | M63: =(M36/M35)*100 -> #DIV/0! | N63: =(N36/N35)*100 -> #DIV/0! | O63: =(O36/O35)*100 -> #DIV/0! | P63: =(P36/P35)*100 -> #DIV/0! | Q63: =(Q36/Q35)*100 -> #DIV/0! | R63: =(R36/R35)*100 -> #DIV/0! | S63: =(S36/S35)*100 -> #DIV/0! | ... AK63: =(AK36/AK35)*100 -> #DIV/0! | AM63: =(AM41/AM40)*100 -> #DIV/0!
D64: Stearin | E64: 25 | G64: =(G37/G35)*100 -> #DIV/0! | H64: =(H37/H35)*100 -> #DIV/0! | I64: =(I37/I35)*100 -> #DIV/0! | J64: =(J37/J35)*100 -> #DIV/0! | K64: #DIV/0! | L64: =(L37/L35)*100 -> #DIV/0! | M64: =(M37/M35)*100 -> #DIV/0! | N64: =(N37/N35)*100 -> #DIV/0! | O64: =(O37/O35)*100 -> #DIV/0! | P64: =(P37/P35)*100 -> #DIV/0! | Q64: =(Q37/Q35)*100 -> #DIV/0! | R64: =(R37/R35)*100 -> #DIV/0! | S64: =(S37/S35)*100 -> #DIV/0! | ... AK64: =(AK37/AK35)*100 -> #DIV/0! | AM64: =(AM42/AM40)*100 -> #DIV/0!
D65: Olein IV 57 ( Retail ) | E65: 75 | F65: % | G65: =G41/G40*100 -> #DIV/0! | H65: =H41/H40*100 -> #DIV/0! | I65: =I41/I40*100 -> #DIV/0! | J65: =J41/J40*100 -> #DIV/0! | K65: #DIV/0! | L65: =L41/L40*100 -> #DIV/0! | M65: =M41/M40*100 -> #DIV/0! | N65: =N41/N40*100 -> #DIV/0! | O65: =O41/O40*100 -> #DIV/0! | P65: =P41/P40*100 -> #DIV/0! | Q65: =Q41/Q40*100 -> #DIV/0! | R65: =R41/R40*100 -> #DIV/0! | S65: =S41/S40*100 -> #DIV/0! | ... AK65: =AK41/AK40*100 -> #DIV/0! | AM65: =AM41/AM40*100 -> #DIV/0!
D66: Stearin | E66: 25 | F66: % | G66: =G42/G40*100 -> #DIV/0! | H66: =H42/H40*100 -> #DIV/0! | I66: =I42/I40*100 -> #DIV/0! | J66: =J42/J40*100 -> #DIV/0! | K66: #DIV/0! | L66: =L42/L40*100 -> #DIV/0! | M66: =M42/M40*100 -> #DIV/0! | N66: =N42/N40*100 -> #DIV/0! | O66: =O42/O40*100 -> #DIV/0! | P66: =P42/P40*100 -> #DIV/0! | Q66: =Q42/Q40*100 -> #DIV/0! | R66: =R42/R40*100 -> #DIV/0! | S66: =S42/S40*100 -> #DIV/0! | ... AK66: =AK42/AK40*100 -> #DIV/0! | AM66: =AM42/AM40*100 -> #DIV/0!
D67: Olein IV 58 ( Bulk ) | E67: 70 | F67: % | G67: =G45/(G45+G46)*100 -> #DIV/0! | H67: =H45/(H45+H46)*100 -> #DIV/0! | I67: =I45/(I45+I46)*100 -> #DIV/0! | J67: =J45/(J45+J46)*100 -> #DIV/0! | L67: =L45/(L45+L46)*100 -> #DIV/0! | M67: =M45/(M45+M46)*100 -> #DIV/0! | N67: =N45/(N45+N46)*100 -> #DIV/0! | O67: =O45/(O45+O46)*100 -> #DIV/0! | P67: =P45/(P45+P46)*100 -> #DIV/0! | Q67: =Q45/(Q45+Q46)*100 -> 71.915304 | R67: =R45/(R45+R46)*100 -> 66.085537 | S67: =S45/(S45+S46)*100 -> 71.444905 | ... AK67: =AK45/(AK45+AK46)*100 -> #DIV/0! | AM67: =AM45/(AM45+AM46)*100 -> 70.627249
D68: Stearin | E68: 30 | F68: % | G68: =G46/(G46+G45)*100 -> #DIV/0! | H68: =H46/(H46+H45)*100 -> #DIV/0! | I68: =I46/(I46+I45)*100 -> #DIV/0! | J68: =J46/(J46+J45)*100 -> #DIV/0! | L68: =L46/(L46+L45)*100 -> #DIV/0! | M68: =M46/(M46+M45)*100 -> #DIV/0! | N68: =N46/(N46+N45)*100 -> #DIV/0! | O68: =O46/(O46+O45)*100 -> #DIV/0! | P68: =P46/(P46+P45)*100 -> #DIV/0! | Q68: =Q46/(Q46+Q45)*100 -> 28.084696 | R68: =R46/(R46+R45)*100 -> 33.914463 | S68: =S46/(S46+S45)*100 -> 28.555095 | ... AK68: =AK46/(AK46+AK45)*100 -> #DIV/0! | AM68: =AM46/AM44*100 -> 29.372751
D69: Olein IV 58 ( Retail ) | E69: 70 | F69: % | G69: =G50/(G50+G51)*100 -> #DIV/0! | H69: =H50/(H50+H51)*100 -> #DIV/0! | I69: =I50/(I50+I51)*100 -> #DIV/0! | J69: =J50/(J50+J51)*100 -> #DIV/0! | K69: #DIV/0! | L69: =L50/(L50+L51)*100 -> #DIV/0! | M69: =M50/(M50+M51)*100 -> #DIV/0! | N69: =N50/(N50+N51)*100 -> #DIV/0! | O69: =O50/(O50+O51)*100 -> #DIV/0! | P69: =P50/(P50+P51)*100 -> #DIV/0! | Q69: =Q50/(Q50+Q51)*100 -> #DIV/0! | R69: =R50/(R50+R51)*100 -> #DIV/0! | S69: =S50/(S50+S51)*100 -> #DIV/0! | ... AK69: =AK50/(AK50+AK51)*100 -> #DIV/0! | AM69: =AM50/(AM50+AM51)*100 -> #DIV/0!
D70: Stearin | E70: 30 | F70: % | G70: =G51/(G50+G51)*100 -> #DIV/0! | H70: =H51/(H50+H51)*100 -> #DIV/0! | I70: =I51/(I50+I51)*100 -> #DIV/0! | J70: =J51/(J50+J51)*100 -> #DIV/0! | K70: #DIV/0! | L70: =L51/(L50+L51)*100 -> #DIV/0! | M70: =M51/(M50+M51)*100 -> #DIV/0! | N70: =N51/(N50+N51)*100 -> #DIV/0! | O70: =O51/(O50+O51)*100 -> #DIV/0! | P70: =P51/(P50+P51)*100 -> #DIV/0! | Q70: =Q51/(Q50+Q51)*100 -> #DIV/0! | R70: =R51/(R50+R51)*100 -> #DIV/0! | S70: =S51/(S50+S51)*100 -> #DIV/0! | ... AK70: =AK51/(AK50+AK51)*100 -> #DIV/0! | AM70: =AM51/(AM50+AM51)*100 -> #DIV/0!
D71: Olein IV 60 | E71: 60 | F71: % | G71: =G55/(G55+G56)*100 -> #DIV/0! | H71: =H55/(H55+H56)*100 -> #DIV/0! | I71: =I55/(I55+I56)*100 -> #DIV/0! | J71: =J55/(J55+J56)*100 -> #DIV/0! | K71: =K55/(K55+K56)*100 -> #DIV/0! | L71: =L55/(L55+L56)*100 -> #DIV/0! | M71: =M55/(M55+M56)*100 -> #DIV/0! | N71: =N55/(N55+N56)*100 -> #DIV/0! | ... AH71: =AH55/(AH55+AH56)*100 -> 60.03027 | AI71: =#REF!/AI54*100 -> #REF! | AJ71: =#REF!/AJ54*100 -> #REF! | AK71: =#REF!/AK54*100 -> #REF! | AM71: =AM55/(AM54+AM50)*100 -> 60.03027
D72: Soft Stearin | E72: 40 | F72: % | G72: =G56/G54*100 -> #DIV/0! | H72: =H56/H54*100 -> #DIV/0! | I72: =I56/I54*100 -> #DIV/0! | J72: =J56/J54*100 -> #DIV/0! | K72: #DIV/0! | L72: =L56/L54*100 -> #DIV/0! | M72: =M56/M54*100 -> #DIV/0! | N72: =N56/N54*100 -> #DIV/0! | O72: =O56/O54*100 -> #DIV/0! | P72: =P56/P54*100 -> #DIV/0! | Q72: =Q56/Q54*100 -> #DIV/0! | R72: =R56/R54*100 -> #DIV/0! | S72: =S56/S54*100 -> #DIV/0! | ... AG72: =AG56/AG54*100 -> #DIV/0! | AH72: =AH56/(AH56+AH55)*100 -> 39.96973 | AI72: =AI56/AI54*100 -> #DIV/0! | AJ72: =AJ56/AJ54*100 -> #DIV/0! | AK72: =AK56/AK54*100 -> #DIV/0! | AM72: =AM56/AM54*100 -> 39.96973
C73: 2 | D73: CHEMICAL CONSUMABLE | AM73: Chemical
D74: Bleaching Earth (BE) to Poram Spec | E74: 9 | F74: Kg | I74: 2045 | J74: 2842 | M74: 3559 | N74: 15831 | O74: 13122 | P74: 3528 | Q74: 3636 | R74: 9198 | S74: 20502 | T74: 16649 | U74: 14958 | V74: 8226 | W74: =17316 -> 17316 | X74: =21096 -> 21096 | Y74: 18233 | Z74: 10116 | AA74: 5670 | AB74: 14058 | AC74: 13400.91 | AD74: 14884 | AE74: 434 | AG74: 0 | AM74: =SUM(G74:AJ74) -> 229303.91
F75: % | G75: =G74/(G11)*100 -> #DIV/0! | H75: =H74/(H11)*100 -> #DIV/0! | I75: =I74/(I11)*100 -> #DIV/0! | J75: =J74/(J11)*100 -> #DIV/0! | L75: =L74/(L11)*100 -> #DIV/0! | M75: =M74/(M11)*100 -> 0.71968632 | N75: =N74/(N11)*100 -> 0.84894642 | O75: =O74/(O11)*100 -> 0.82974485 | P75: =P74/(P11)*100 -> 0.56809307 | Q75: =Q74/(Q11)*100 -> 1.4662236 | R75: =R74/(R11)*100 -> 0.86512415 | S75: =S74/(S11)*100 -> 0.93348413 | ... AK75: =AK74/(AK11)*100 -> #DIV/0! | AM75: =AM74/(AM11)*100 -> 0.90731656 | BB75: #DIV/0! | BC75: #DIV/0!
D76: TK 630 A ( TRANSFER ) | E76: 40000 | F76: Kg | W76: 110 | X76: 362 | Y76: 40 | Z76: 2960 | AA76: 2790 | AB76: 330 | AG76: 0 | AM76: =SUM(G76:AJ76) -> 6592
D78: TK 630 B ( TRANSFER ) | E78: 40000 | F78: Kg | W78: 560 | X78: 180 | Y78: 1266 | Z78: 9220 | AA78: 2350 | AB78: 9160 | AC78: 6840 | AD78: 1230 | AG78: 0 | AM78: =SUM(G78:AJ78) -> 30806
D80: Bleaching Earth (BE) to Branded Spec | E80: 18 | F80: Kg | G80: 0 | H80: 0 | I80: 0 | J80: 0 | K80: 0 | L80: 0 | M80: 0 | N80: 0 | O80: 0 | P80: 0 | Q80: 0 | R80: 0 | S80: 0 | T80: 0 | U80: 0 | V80: 0 | W80: 0 | X80: 0 | Y80: 0 | Z80: 0 | AA80: 0 | AB80: 0 | AC80: 0 | AD80: 0 | AE80: 0 | AF80: 0 | AG80: 0 | AH80: 0 | AI80: 0 | AJ80: 0 | AK80: 0 | AM80: =SUM(G80:AJ80) -> 0
F81: % | G81: =G80/(G12)*100 -> #DIV/0! | H81: =H80/(H12)*100 -> #DIV/0! | I81: =I80/(I12)*100 -> #DIV/0! | J81: =J80/(J12)*100 -> #DIV/0! | K81: #DIV/0! | L81: =L80/(L12)*100 -> #DIV/0! | M81: =M80/(M12)*100 -> #DIV/0! | N81: =N80/(N12)*100 -> #DIV/0! | O81: =O80/(O12)*100 -> #DIV/0! | P81: =P80/(P12)*100 -> #DIV/0! | Q81: =Q80/(Q12)*100 -> #DIV/0! | R81: =R80/(R12)*100 -> #DIV/0! | S81: =S80/(S12)*100 -> #DIV/0! | ... AK81: =AK80/(AK12)*100 -> #DIV/0! | AM81: =AM80/(AM12)*100 -> #DIV/0!
D82: Phosporic Acid (PA) | E82: 0.6 | F82: Kg | I82: =44*1.6 -> 70.4 | J82: =73.97*1.6 -> 118.352 | M82: =132.76*1.6 -> 212.416 | N82: =559.41*1.6 -> 895.056 | O82: =483.6*1.6 -> 773.76 | P82: =132.8*1.6 -> 212.48 | Q82: 176.8 | R82: =487.76 -> 487.76 | S82: 990.08 | T82: 806 | U82: 752.96 | V82: 407.68 | W82: 856.96 | X82: 1157.52 | Y82: 940.16 | Z82: 674.96 | AA82: 327.6 | AB82: 781.04 | AC82: 819.52 | AD82: 479.44 | AE82: 832 | AG82: 0 | AM82: =SUM(G82:AJ82) -> 12772.944
F83: % | G83: =G82/(G9)*100 -> #DIV/0! | H83: =H82/(H9)*100 -> #DIV/0! | I83: =I82/(I9)*1000 -> #DIV/0! | J83: =J82/(J9)*1000 -> #DIV/0! | L83: =L82/(L9)*100 -> #DIV/0! | M83: =M82/(M9)*100 -> 0.042953889 | N83: =N82/(N9)*100 -> 0.047997889 | O83: =O82/(O9)*100 -> 0.04892725 | P83: =P82/(P9)*100 -> 0.034214404 | Q83: =Q82/(Q9)*100 -> 0.071294922 | R83: =R82/(R9)*100 -> 0.045876599 | S83: =S82/(S9)*100 -> 0.045079698 | ... AK83: =AK82/(AK9)*100 -> #DIV/0! | AM83: =AM82/(AM9)*100 -> 0.050540366
C84: 3 | D84: OIL LOSSES | E84: 0.8 | F84: % | G84: =((SUM(G19:G20))-(SUM(G9)))/(SUM(G9))*100 -> #DIV/0! | H84: =((SUM(H19:H20))-(SUM(H9)))/(SUM(H9))*100 -> #DIV/0! | I84: =((SUM(I19:I20))-(SUM(I9)))/(SUM(I9))*100 -> #DIV/0! | J84: =((SUM(J19:J20))-(SUM(J9)))/(SUM(J9))*100 -> #DIV/0! | K84: =((SUM(K19:K20))-(SUM(K9)))/(SUM(K9))*100 -> #DIV/0! | L84: =((SUM(L19:L20))-(SUM(L9)))/(SUM(L9))*100 -> #DIV/0! | M84: =((SUM(M19:M20))-(SUM(M9)))/(SUM(M9))*100 -> 1.5538268 | N84: =((SUM(N19:N20))-(SUM(N9)))/(SUM(N9))*100 -> -5.6968589 | ... AK84: =((SUM(AK19:AK20))-(SUM(AK9)))/(SUM(AK9))*100 -> #DIV/0! | AM84: =((SUM(AM19:AM20))-(SUM(AM9)))/(SUM(AM9))*100 -> 0.8148735
F85: Kg | G85: =G84%*G9 -> #DIV/0! | H85: =H84%*H9 -> #DIV/0! | I85: =I84%*I9 -> #DIV/0! | J85: =J84%*J9 -> #DIV/0! | K85: =K84%*K9 -> #DIV/0! | L85: =L84%*L9 -> #DIV/0! | M85: =M84%*M9 -> 7684 | N85: =N84%*N9 -> -106234 | ... AK85: =AK84%*AK9 -> #DIV/0! | AM85: =AM84%*AM9 -> 205941
D86: % Oil Content | E86: 22 | F86: % | M86: 31.65 | N86: 25.59 | O86: 22.06 | P86: 21.78 | Q86: 21.71 | R86: 21.88 | S86: 21.66 | T86: 20.51 | U86: 20.7 | V86: 20.28 | W86: 20.03 | X86: 19.87 | Y86: 19.78 | Z86: 20.2 | AA86: 20.09 | AB86: 20.03 | AC86: 20.04 | AD86: 20.07 | AM86: =AVERAGE(G86:AJ86) -> 21.551667
D87: Spent Bleaching Earth | F87: Kg | G87: =SUM(G74,G80)+(G86%*SUM(G74,G80)) -> 0 | H87: =SUM(H74,H80)+(H86%*SUM(H74,H80)) -> 0 | I87: =SUM(I74,I80)+(I86%*SUM(I74,I80)) -> 2045 | J87: =SUM(J74,J80)+(J86%*SUM(J74,J80)) -> 2842 | L87: =SUM(L74,L80)+(L86%*SUM(L74,L80)) -> 0 | M87: =SUM(M74,M80)+(M86%*SUM(M74,M80)) -> 4685.4235 | N87: =SUM(N74,N80)+(N86%*SUM(N74,N80)) -> 19882.153 | O87: =SUM(O74,O80)+(O86%*SUM(O74,O80)) -> 16016.713 | P87: =SUM(P74,P80)+(P86%*SUM(P74,P80)) -> 4296.3984 | Q87: =SUM(Q74,Q80)+(Q86%*SUM(Q74,Q80)) -> 4425.3756 | R87: =SUM(R74,R80)+(R86%*SUM(R74,R80)) -> 11210.522 | S87: =SUM(S74,S80)+(S86%*SUM(S74,S80)) -> 24942.733 | ... AK87: =SUM(AK74,AK80)+(AK86%*SUM(AK74,AK80)) -> 0 | AM87: =SUM(AM74,AM80)+(AM86%*SUM(AM74,AM80))/AM6 -> 231452.55
C88: 4 | D88: PACKAGING (Brand Salvaco) | AM88: Packaging
D89: Olein IV 60 Received | F89: Kg | AM89: 0
D90: Olein IV 60 Consume | F90: Kg | AM90: 0
D91: - finished product | F91: Kg | G91: 0 | H91: 0 | I91: 0 | J91: 0 | K91: 0 | L91: 0 | M91: 0 | N91: 0 | O91: 0 | P91: 0 | Q91: 0 | R91: 0 | S91: 0 | T91: 0 | U91: 0 | V91: 0 | W91: 0 | X91: 0 | Y91: 0 | Z91: 0 | AA91: 0 | AB91: 0 | AC91: 0 | AD91: 0 | AE91: 0 | AF91: 0 | AG91: 0 | AH91: 0 | AI91: 0 | AJ91: 0 | AK91: 0 | AM91: 0
D92: - sample | F92: Kg | G92: 0 | H92: 0 | I92: 0 | J92: 0 | K92: 0 | L92: 0 | M92: 0 | N92: 0 | O92: 0 | P92: 0 | Q92: 0 | R92: 0 | S92: 0 | T92: 0 | U92: 0 | V92: 0 | W92: 0 | X92: 0 | Y92: 0 | Z92: 0 | AA92: 0 | AB92: 0 | AC92: 0 | AD92: 0 | AE92: 0 | AF92: 0 | AG92: 0 | AH92: 0 | AI92: 0 | AJ92: 0 | AK92: 0 | AM92: 0
D93: - remelt, flushing, downgrade | F93: Kg | G93: 0 | H93: 0 | I93: 0 | J93: 0 | K93: 0 | L93: 0 | M93: 0 | N93: 0 | O93: 0 | P93: 0 | Q93: 0 | R93: 0 | S93: 0 | T93: 0 | U93: 0 | V93: 0 | W93: 0 | X93: 0 | Y93: 0 | Z93: 0 | AA93: 0 | AB93: 0 | AC93: 0 | AD93: 0 | AE93: 0 | AF93: 0 | AG93: 0 | AH93: 0 | AI93: 0 | AJ93: 0 | AK93: 0 | AM93: 0
D94: Carton | AM94: Carton
D95: Salvaco 1 Liter | F95: Box | AM95: 0
D96: Salvaco 2 Liter | F96: Box | AM96: 0
D97: Pouch | AM97: Pouch
D98: Salvaco 1 Liter | F98: Pouch | G98: 0 | H98: 0 | I98: 0 | J98: 0 | K98: 0 | L98: 0 | M98: 0 | N98: 0 | O98: 0 | P98: 0 | Q98: 0 | R98: 0 | S98: 0 | T98: 0 | U98: 0 | V98: 0 | W98: 0 | X98: 0 | Y98: 0 | Z98: 0 | AA98: 0 | AB98: 0 | AC98: 0 | AD98: 0 | AE98: 0 | AF98: 0 | AG98: 0 | AH98: 0 | AI98: 0 | AJ98: 0 | AK98: 0 | AM98: 0
D99: Salvaco 2 Liter | F99: Pouch | G99: 0 | H99: 0 | I99: 0 | J99: 0 | K99: 0 | L99: 0 | M99: 0 | N99: 0 | O99: 0 | P99: 0 | Q99: 0 | R99: 0 | S99: 0 | T99: 0 | U99: 0 | V99: 0 | W99: 0 | X99: 0 | Y99: 0 | Z99: 0 | AA99: 0 | AB99: 0 | AC99: 0 | AD99: 0 | AE99: 0 | AF99: 0 | AG99: 0 | AH99: 0 | AI99: 0 | AJ99: 0 | AK99: 0 | AM99: 0
D100: Consumable Vit. A | F100: gram | G100: 0 | H100: 0 | I100: 0 | J100: 0 | K100: 0 | L100: 0 | M100: 0 | N100: 0 | O100: 0 | P100: 0 | Q100: 0 | R100: 0 | S100: 0 | T100: 0 | U100: 0 | V100: 0 | W100: 0 | X100: 0 | Y100: 0 | Z100: 0 | AA100: 0 | AB100: 0 | AC100: 0 | AD100: 0 | AE100: 0 | AF100: 0 | AG100: 0 | AH100: 0 | AI100: 0 | AJ100: 0 | AK100: 0 | AM100: 0
D101: Consumable Packing Tape | F101: Roll | G101: 0 | H101: 0 | I101: 0 | J101: 0 | K101: 0 | L101: 0 | M101: 0 | N101: 0 | O101: 0 | P101: 0 | Q101: 0 | R101: 0 | S101: 0 | T101: 0 | U101: 0 | V101: 0 | W101: 0 | X101: 0 | Y101: 0 | Z101: 0 | AA101: 0 | AB101: 0 | AC101: 0 | AD101: 0 | AE101: 0 | AF101: 0 | AG101: 0 | AH101: 0 | AI101: 0 | AJ101: 0 | AK101: 0 | AM101: 0
D102: REJECT MATERIAL QTY | AM102: Loss Material
...

Sheet Peformance test Fract 1
C1: PT.INDUSTRI NABATI LESTARI
C2: Pabrik Minyak Goreng ( PMG 2 )
C3: Kantor Pusat: Komp. KEK Sei Mangkei, Kav.2-3, Kec. Bosar Maligas, Kab. Simalungun, Sumatera Utara, 21184
C4: ACTUAL PEFORMANCE / CONSUMPT REPORT FRAKSINASI PLANT | H4: Trial | I4: 1
H5: Start / Date / Time | I5: 17/12/24 ( 07.00 Wib )
H6: Finish / Date / Time | I6: 17/12/24 ( 07.00 Wib )
A8: No | B8: ITEM | C8: Kontrak LIPICO | D8: UOM | E8: TOTALIZER
A10: 1 | B10: PRODUCTION | C10: IV 56 | D10: 24 jam | E10: BEFORE | F10: AFTER | G10: TOTAL | H10: YIELD % | I10: STATUS/REMAKS
B11: Fraksinasi
B12: Running Days
B13: Incoming CPO
B14: Ratio Run CPO
B15: RBDPO Consume Total | C15: 2500 | D15: TPD | E15: 8982.8 | F15: 11717.8 | G15: =F15-E15 -> 2735 | H15: =G15/25000*10 -> 1.094 | I15: OK
B16: Avg Daily Consump CPO ( MTD )
B17: CPO Consume Poram | C17: 29045000
B18: CPO Consume Brand | C18: 7314000 | E18: =E49+E58+E63 -> 0
B19: QUALITY
B20: - FFA | C20: 0.1 | D20: % Max | H20: 0.063
B21: - Moist & Impurities | C21: 0.1 | D21: % Max | H21: 0.05
B22: - IV | C22: 52 - 52,5 | H22: 51.8
B23: - LC | H23: 2,6/20
B24: - Temp | C24: 68 | D24: ˚C Min | H24: 65
B25: TANK | H25: 108/109
B26: Product
B27: OLEIN IV 56 | C27: =C15*84% -> 2100 | D27: TPD | E27: 6537.1 | F27: 8213 | G27: =F27-E27 -> 1675.9 | H27: =G27/(G27+G32) -> 0.82838219 | I27: OK
B28: QUALITY
B29: - IV | C29: 56 | D29: Min
B30: - LC
B31: - Cloud Point ( metter ) | C31: 10 | D31: ˚C Max
B32: STEARIN | C32: =C15*16% -> 400 | E32: 2268.1 | F32: 2615.3 | G32: =F32-E32 -> 347.2 | H32: =G32/(G32+G27) -> 0.17161781 | I32: OK
B33: Fractionation
B34: Running Days
B35: Filling Langsung CR Fr Refinery | E35: 0
B36: Total Filling Crystalizer ( Feed ) | E36: 392100
B37: Avg Daily Consump RPO ( MTD )
B38: Total Proses RBDPO | E38: =SUM(E41,E45,E50,E54,E64) -> 0
B39: Sisa Filling Crystalizer | E39: =E36-E38 -> 392100
B40: Fractionation OLEIN IV 56
B41: RBDPO Consume | E41: =E42+E43 -> 0
B42: OLEIN IV 56 | E42: 0
B43: STEARIN | E43: 0
B44: Fractionation OLEIN IV 57 ( Bulk )
B45: RBDPO Consume | E45: =E46+E47 -> 0
B46: OLEIN IV 57 | E46: 0
B47: STEARIN | E47: 0
B48: Fractionation OLEIN IV 57 ( Retail )
B49: CPO Consume
B50: RBDPO Brand Consume | E50: =E51+E52 -> 0
B51: OLEIN IV 57 Low Color | E51: 0
B52: STEARIN | E52: 0
B53: Fractionation OLEIN IV 58 ( Bulk )
B54: RBDPO Consume | C54: =C55+C56 -> 21429000 | E54: =E55+E56 -> 0
B55: OLEIN IV 58 | C55: 15000000
B56: STEARIN | C56: 6429000
B57: Fractionation OLEIN IV 58 ( Retail )
B58: CPO Consume
B59: RBDPO Consume | C59: =C60+C61 -> 21429000 | E59: =E60+E61 -> 0
B60: OLEIN IV 58 | C60: 15000000 | E60: 0
B61: STEARIN | C61: 6429000 | E61: 0
B62: Fractionation OLEIN IV 60
B63: CPO Consume
B64: RBDPO Brand Consume | E64: =E66+E67 -> 0
B65: OLEIN IV 60 Bulk | E65: 0
B66: OLEIN IV 60 Salvaco | E66: 0
B67: SOFT STEARIN | E67: 0
B68: Ratio Run RBDPO | E68: 0
B69: YIELD
B70: RBDPO | C70: 94.2 | E70: =(#REF!/(E15))*100 -> #REF!
B71: PFAD | C71: 5 | E71: =(E32/(E15))*100 -> 25.249365
B72: Olein IV 56 | C72: 82 | E72: =E42/(E42+E43)*100 -> #DIV/0!
B73: Stearin | C73: 18 | E73: =(E43/E41)*100 -> #DIV/0!
B74: Olein IV 57 ( Bulk ) | C74: 75 | E74: =(E46/E45)*100 -> #DIV/0!
B75: Stearin | C75: 25 | E75: =(E47/E45)*100 -> #DIV/0!
B76: Olein IV 57 ( Retail ) | C76: 75 | E76: =E51/E50*100 -> #DIV/0!
B77: Stearin | C77: 25 | E77: =E52/E50*100 -> #DIV/0!
B78: Olein IV 58 ( Bulk ) | C78: 70 | E78: =E55/(E55+E56)*100 -> #DIV/0!
B79: Stearin | C79: 30 | E79: =E56/(E56+E55)*100 -> #DIV/0!
B80: Olein IV 58 ( Retail ) | C80: 70 | E80: =E60/(E60+E61)*100 -> #DIV/0!
B81: Stearin | C81: 30 | E81: =E61/(E60+E61)*100 -> #DIV/0!
B82: Olein IV 60 | C82: 60 | E82: =E65/E64*100 -> #DIV/0!
B83: Soft Stearin | C83: 40 | E83: =E67/E64*100 -> #DIV/0!
B84: QUALITY
B85: - IV | C85: 32 | D85: Max
B86: - Melting Point | C86: 52-52,5 | D86: ˚C Min
A87: 2 | B87: STEAM CONSUMPTION | E87: BEFORE | F87: AFTER | G87: TOTAL | H87: Kg/Ton RBDPO
B88: Incoming | C88: 408000 | D88: Kg/Day | G88: 183211
B89: Distribution to
B90: fraksinasi | C90: 87.5 | D90: Kg/Day | E90: 308052 | F90: 366933 | G90: =F90-E90 -> 58881 | H90: =G90/G15 -> 21.528702 | I90: OK
C91: =C90/2000 -> 0.04375
C92: =C90/2.5 -> 35 | D92: Kg/ton
B93: Fractionation | C93: 122000
B94: Others ( Tank farm & spurging OSBL ) | C94: 106000 | D94: Kg/Day
B95: Total | C95: 408000 | D95: Kg/Day | G95: =SUM(G90,G93,G94) -> 58881
A96: 3 | B96: WATER CONSUMPTION | E96: BEFORE | F96: AFTER | G96: TOTAL | H96: M³/Ton RBDPO
B97: Incoming from Kinra | C97: 1100 | D97: M³/Day | G97: 818
B98: Outgoing
B99: Softener Product (to Fraksinasi ) | C99: 0.13 | D99: M³/Day | E99: 58 | F99: 106 | G99: =F99-E99 -> 48 | H99: =G99/G15 -> 0.017550274
B100: Softener Product (to Fractionation) | C100: 179.63
C101: =C99/2500 -> 5.2e-05 | D101: M³/ton
B102: RO Product | C102: 491.59 | D102: M³/Day | G102: 304
...

Sheet Peformance Test REFINERY 1
C1: PT.INDUSTRI NABATI LESTARI
C2: Pabrik Minyak Goreng ( PMG 2 )
C3: Kantor Pusat: Komp. KEK Sei Mangkei, Kav.2-3, Kec. Bosar Maligas, Kab. Simalungun, Sumatera Utara, 21184
C4: ACTUAL PEFORMANCE / CONSUMPT REPORT REFINERY PLANT | H4: Peformance | I4: 1
H5: Start / Date / Time | I5: 17/12/24 ( 21.00 Wib )
H6: Finish / Date / Time | I6: 18/12/24 ( 21.00 Wib )
A7: No | B7: ITEM | C7: Kontrak LIPICO | D7: UOM | E7: TOTALIZER
A9: 1 | B9: PRODUCTION | E9: BEFORE | F9: AFTER | G9: TOTAL | H9: Yield ( % ) | I9: STATUS/REMAKS
B10: Refinery
B11: Running Days
B12: Incoming CPO
B13: Ratio Run CPO
B14: CPO Consume Total | C14: 2500 | D14: TPD | E14: 13533.82 | F14: 16053.42 | G14: =F14-E14 -> 2519.6 | I14: OK
B15: Avg Daily Consump CPO ( MTD )
B16: CPO Consume Poram | C16: 29045000
B17: CPO Consume Brand | C17: 7314000 | E17: =E53+E62+E67 -> 0
B18: - FFA | C18: 5 | D18: % | G18: 4
B19: - Moist & Impurities | C19: 0.5 | D19: % | G19: 0.41
B20: - DOBI | C20: 2.2 | D20: Min | G20: 2.42
B21: - TOTOX 2PV + AV | C21: 12 | D21: Max | G21: N/A
B22: - FE Content | C22: < 5 | D22: ppm | G22: N/A
B23: - PV | C23: < 4 | D23: Meg/kg | G23: N/A
B24: - Phosporus Max | C24: 25 | D24: ppm | G24: N/A
B25: TANK / TEMP | C25: 50 | D25: ˚C | G25: 50
B26: Product
B27: RBDPO | C27: =C14*94.2% -> 2355 | D27: TPD | E27: 12357.54 | F27: 14705.95 | G27: =F27-E27 -> 2348.41 | H27: =G27/G14 -> 0.93205668
B28: - FFA | C28: 0.05 | D28: % | G28: 0.06
B29: - Moist & Impurities | C29: 0.03 | D29: % | G29: 0.05
B30: - Peroxide value | D30: Nil | G30: -
B31: - Phosporous max | C31: 2 | D31: ppm | G31: N/A
B32: - LC | C32: 2.5 | D32: % | G32: 2.5
B33: - Aom stability min ( hr ) | C33: 60 | D33: min ( hr ) | G33: N/A
B34: - teste & Odor | C34: bland/Odorless | G34: N/A
B35: - temp max ( C ) | C35: 50 | D35: max˚C | G35: 50
B36: PFAD | C36: =C14*5% -> 125 | D36: TPD | E36: 572.71 | F36: 675.39 | G36: =F36-E36 -> 102.68 | H36: =G36/G14 -> 0.0407525
B37: Fractionation
B38: Running Days
B39: Filling Langsung CR Fr Refinery | E39: 0
B40: Total Filling Crystalizer ( Feed ) | E40: 392100
B41: Avg Daily Consump RPO ( MTD )
B42: Total Proses RBDPO | E42: =SUM(E45,E49,E54,E58,E68) -> 0
B43: Sisa Filling Crystalizer | E43: =E40-E42 -> 392100
B44: Fractionation OLEIN IV 56
B45: RBDPO Consume | E45: =E46+E47 -> 0
B46: OLEIN IV 56 | E46: 0
B47: STEARIN | E47: 0
B48: Fractionation OLEIN IV 57 ( Bulk )
B49: RBDPO Consume | E49: =E50+E51 -> 0
B50: OLEIN IV 57 | E50: 0
B51: STEARIN | E51: 0
B52: Fractionation OLEIN IV 57 ( Retail )
B53: CPO Consume
B54: RBDPO Brand Consume | E54: =E55+E56 -> 0
B55: OLEIN IV 57 Low Color | E55: 0
B56: STEARIN | E56: 0
B57: Fractionation OLEIN IV 58 ( Bulk )
B58: RBDPO Consume | C58: =C59+C60 -> 21429000 | E58: =E59+E60 -> 0
B59: OLEIN IV 58 | C59: 15000000
B60: STEARIN | C60: 6429000
B61: Fractionation OLEIN IV 58 ( Retail )
B62: CPO Consume
B63: RBDPO Consume | C63: =C64+C65 -> 21429000 | E63: =E64+E65 -> 0
B64: OLEIN IV 58 | C64: 15000000 | E64: 0
B65: STEARIN | C65: 6429000 | E65: 0
B66: Fractionation OLEIN IV 60
B67: CPO Consume
B68: RBDPO Brand Consume | E68: =E70+E71 -> 0
B69: OLEIN IV 60 Bulk | E69: 0
B70: OLEIN IV 60 Salvaco | E70: 0
B71: SOFT STEARIN | E71: 0
B72: Ratio Run RBDPO | E72: 0
B73: YIELD
B74: RBDPO | C74: 94.2 | E74: =(E27/(E14))*100 -> 91.308588
B75: PFAD | C75: 5 | E75: =(E36/(E14))*100 -> 4.2316951
B76: Olein IV 56 | C76: 82 | E76: =E46/(E46+E47)*100 -> #DIV/0!
B77: Stearin | C77: 18 | E77: =(E47/E45)*100 -> #DIV/0!
B78: Olein IV 57 ( Bulk ) | C78: 75 | E78: =(E50/E49)*100 -> #DIV/0!
B79: Stearin | C79: 25 | E79: =(E51/E49)*100 -> #DIV/0!
B80: Olein IV 57 ( Retail ) | C80: 75 | E80: =E55/E54*100 -> #DIV/0!
B81: Stearin | C81: 25 | E81: =E56/E54*100 -> #DIV/0!
B82: Olein IV 58 ( Bulk ) | C82: 70 | E82: =E59/(E59+E60)*100 -> #DIV/0!
B83: Stearin | C83: 30 | E83: =E60/(E60+E59)*100 -> #DIV/0!
B84: Olein IV 58 ( Retail ) | C84: 70 | E84: =E64/(E64+E65)*100 -> #DIV/0!
B85: Stearin | C85: 30 | E85: =E65/(E64+E65)*100 -> #DIV/0!
B86: Olein IV 60 | C86: 60 | E86: =E69/E68*100 -> #DIV/0!
B87: Soft Stearin | C87: 40 | E87: =E71/E68*100 -> #DIV/0!
B88: - FFA | C88: ~93 | D88: % | G88: 90.21
B89: - Moist & Impurities | C89: 0.5 | D89: % | G89: 0.33
A90: 2 | B90: CHEMICAL CONSUMABLE | E90: BEFORE | F90: AFTER | G90: TOTAL | H90: ( % )
B91: Bleaching Earth (BE) to Poram Spec | C91: 9 | D91: kg | E91: 122737 | F91: 143761 | G91: =F91-E91 -> 21024 | H91: =G91/G14/10 -> 0.83441816 | I91: OK
E92: =E91/(E16)*100 -> #DIV/0!
B93: Bleaching Earth (BE) to Branded Spec | C93: 18 | E93: 0
E94: =E93/(E17)*100 -> #DIV/0! | I94: OK
B95: Phosporic Acid (PA) | C95: 0,4 - 0,5 | D95: kg | E95: 1970.8 | F95: 867.36 | G95: =E95-F95 -> 1103.44 | H95: =G95/G14/10 -> 0.043794253 | I95: OK
A97: 3 | B97: OIL LOSSES | C97: - 0,8 | D97: % | H97: =((SUM(G27+G36))-(SUM(G14)))/(SUM(G14))*100 -> -2.7190824
H98: =H97%*G14 -> -68.51
B99: % Oil Content | C99: 20 to 21 | D99: %
B100: Spent Bleaching Earth | H100: =SUM(G91,G93)+(H99%*SUM(G91,G93)) -> 21024
A101: 4 | B101: PACKAGING (Brand Salvaco)
B102: Olein IV 60 Received
...

Sheet peformance  test REFINERY 2
A1: REFINERY PMG 2
A2: No | B2: ITEM | C2: Norma LIPICO | D2: UOM | E2: Day 2 tanggal 12/12/2024
A4: 1 | B4: PRODUCTION | E4: BEFORE | F4: AFTER | G4: TOTAL | H4: Yield ( % )
B5: Refinery
B6: Running Days
B7: Incoming CPO
B8: Ratio Run CPO
B9: CPO Consume Total | C9: 2500 | D9: TPD | E9: 5880.74 | F9: 8383.74 | G9: =F9-E9 -> 2503 | H9: =G9/2500000*100000 -> 100.12
B10: Avg Daily Consump CPO ( MTD )
B11: CPO Consume Poram | C11: 29045000
B12: CPO Consume Brand | C12: 7314000 | E12: =E43+E52+E57 -> 0
B13: - FFA | C13: 5 | D13: % | G13: 3.97
B14: - Moist & Impurities | C14: 0.5 | D14: % | G14: 0.4
B15: - DOBI | C15: 2.2 | D15: Min | G15: 2.42
B16: TANK | G16: 105
B17: Product
B18: OIP RBDPO
B19: RBDPO | C19: =C9*94.2% -> 2355 | D19: TPD | E19: 5143.38 | F19: 7493.18 | G19: =F19-E19 -> 2349.8 | H19: =G19/G9*100 -> 93.879345
B20: - FFA | C20: 0.05 | D20: % | G20: 0.043
B21: - Moist & Impurities | C21: 0.03 | D21: % | G21: 0.04
B22: - LC | C22: 2.5 | D22: % | G22: 2.5
B23: - Aom stability min ( hr ) | C23: 60 | D23: min ( hr )
B24: - teste & Odor | C24: bland/Odorless
B25: - temp max ( C ) | C25: 50 | D25: max˚C
B26: PFAD | C26: =C9*5% -> 125 | D26: TPD | E26: 243.04 | F26: 347.1 | G26: =F26-E26 -> 104.06 | H26: =G26/G9*100 -> 4.1574111
B27: Fractionation
B28: Running Days
B29: Filling Langsung CR Fr Refinery | E29: 0
B30: Total Filling Crystalizer ( Feed ) | E30: 392100
B31: Avg Daily Consump RPO ( MTD )
B32: Total Proses RBDPO | E32: =SUM(E35,E39,E44,E48,E58) -> 0
B33: Sisa Filling Crystalizer | E33: =E30-E32 -> 392100
B34: Fractionation OLEIN IV 56
B35: RBDPO Consume | E35: =E36+E37 -> 0
B36: OLEIN IV 56 | E36: 0
B37: STEARIN | E37: 0
B38: Fractionation OLEIN IV 57 ( Bulk )
B39: RBDPO Consume | E39: =E40+E41 -> 0
B40: OLEIN IV 57 | E40: 0
B41: STEARIN | E41: 0
B42: Fractionation OLEIN IV 57 ( Retail )
B43: CPO Consume
B44: RBDPO Brand Consume | E44: =E45+E46 -> 0
B45: OLEIN IV 57 Low Color | E45: 0
B46: STEARIN | E46: 0
B47: Fractionation OLEIN IV 58 ( Bulk )
B48: RBDPO Consume | C48: =C49+C50 -> 21429000 | E48: =E49+E50 -> 0
B49: OLEIN IV 58 | C49: 15000000
B50: STEARIN | C50: 6429000
B51: Fractionation OLEIN IV 58 ( Retail )
B52: CPO Consume
B53: RBDPO Consume | C53: =C54+C55 -> 21429000 | E53: =E54+E55 -> 0
B54: OLEIN IV 58 | C54: 15000000 | E54: 0
B55: STEARIN | C55: 6429000 | E55: 0
B56: Fractionation OLEIN IV 60
B57: CPO Consume
B58: RBDPO Brand Consume | E58: =E60+E61 -> 0
B59: OLEIN IV 60 Bulk | E59: 0
B60: OLEIN IV 60 Salvaco | E60: 0
B61: SOFT STEARIN | E61: 0
B62: Ratio Run RBDPO | E62: 0
B63: YIELD
B64: RBDPO | C64: 94.2 | E64: =(E19/(E9))*100 -> 87.461442
B65: PFAD | C65: 5 | E65: =(E26/(E9))*100 -> 4.1328132
B66: Olein IV 56 | C66: 82 | E66: =E36/(E36+E37)*100 -> #DIV/0!
B67: Stearin | C67: 18 | E67: =(E37/E35)*100 -> #DIV/0!
B68: Olein IV 57 ( Bulk ) | C68: 75 | E68: =(E40/E39)*100 -> #DIV/0!
B69: Stearin | C69: 25 | E69: =(E41/E39)*100 -> #DIV/0!
B70: Olein IV 57 ( Retail ) | C70: 75 | E70: =E45/E44*100 -> #DIV/0!
B71: Stearin | C71: 25 | E71: =E46/E44*100 -> #DIV/0!
B72: Olein IV 58 ( Bulk ) | C72: 70 | E72: =E49/(E49+E50)*100 -> #DIV/0!
B73: Stearin | C73: 30 | E73: =E50/(E50+E49)*100 -> #DIV/0!
B74: Olein IV 58 ( Retail ) | C74: 70 | E74: =E54/(E54+E55)*100 -> #DIV/0!
B75: Stearin | C75: 30 | E75: =E55/(E54+E55)*100 -> #DIV/0!
B76: Olein IV 60 | C76: 60 | E76: =E59/E58*100 -> #DIV/0!
B77: Soft Stearin | C77: 40 | E77: =E61/E58*100 -> #DIV/0!
B78: - FFA | C78: ~93 | D78: % | G78: 90.62
B79: - Moist & Impurities | C79: 0.5 | D79: % | G79: 0.33
A80: 2 | B80: CHEMICAL CONSUMABLE | E80: BEFORE | F80: AFTER | G80: TOTAL | H80: ( % )
B81: Bleaching Earth (BE) to Poram Spec | C81: 9 | D81: kg | E81: 51223 | F81: 74245 | G81: =F81-E81 -> 23022 | H81: =G81/G9/10 -> 0.91977627
E82: =E81/(E11)*100 -> #DIV/0!
B83: Bleaching Earth (BE) to Branded Spec | C83: 18 | E83: 0
E84: =E83/(E12)*100 -> #DIV/0!
B85: Phosporic Acid (PA) | C85: 0,4 - 0,5 | D85: kg | E85: 539.5 | F85: 1342.1 | G85: =F85-E85 -> 802.6 | H85: =G85/G9/10 -> 0.032065521
A87: 3 | B87: OIL LOSSES | C87: - 0,8 | D87: % | G87: =((SUM(G19+G26))-(SUM(G9)))/(SUM(G9))*100 -> -1.9632441
G88: =G87%*G9 -> -49.14
B89: % Oil Content | C89: 20 to 21 | D89: % | G89: 21.66
B90: Spent Bleaching Earth | G90: =SUM(G81,G83)+(G89%*SUM(G81,G83)) -> 28008.565
A91: 4 | B91: PACKAGING (Brand Salvaco)
B92: Olein IV 60 Received
B93: Olein IV 60 Consume
B94: - finished product | E94: 0
B95: - sample | E95: 0
B96: - remelt, flushing, downgrade | E96: 0
B97: Carton
B98: Salvaco 1 Liter
B99: Salvaco 2 Liter
B100: Pouch
B101: Salvaco 1 Liter | E101: 0
B102: Salvaco 2 Liter | E102: 0
...

Sheet HPP REF 
B2: Refinery Cost
B3: Through Put CPO Proses | N3: =('Desember 2024'!AM10)/1000 -> 1098.8155 | O3: TPD
B4: Working Day | N4: ='Desember 2024'!AM6 -> 23 | O4: Days
B5: Total CPO Process | N5: =N4*N3 -> 25272.757 | O5: MTD
B6: KURS | N6: ='SUMMARY HPP '!I9 -> 15546 | O6: Rp/USD
B7: No | C7: Item Cost | D7: Norma | F7: Pemakaian / Hari | H7: HK | J7: Total Pemakaian | K7: Harga / stn | M7: Total Biaya | N7: Rp / kg | O7: USD/MT
B8: 1 | C8: Bleaching Earth | D8: ='Desember 2024'!$AM$75 -> 0.90731656 | F8: =($D$8*$N$3*10) -> 9969.7352 | G8: Kg/day | H8: =$N$4 -> 23 | J8: =$H$8*$F$8 -> 229303.91 | K8: 2400 | M8: =$J$8*$K$8 -> 550329384 | N8: =$M$8/($N$5*1000) -> 21.775597 | O8: =($M$8/$N$6)/$N$5 -> 1.4007203
B9: 2 | C9: Phosporic acid | D9: ='Desember 2024'!$AM$83 -> 0.050540366 | F9: =($D$9*$N$3*10) -> 555.34539 | G9: Kg/day | H9: =$H$8 -> 23 | J9: =$H$9*$F$9 -> 12772.944 | K9: 17420 | M9: =$J$9*$K$9 -> 2.2250468e+08 | N9: =$M$9/($N$5*1000) -> 8.8041318 | O9: =($M$9/$N$6)/$N$5 -> 0.56632779
B10: 3 | C10: Caustic Soda | D10: 29.166667 | E10: kg/day | F10: =D10 -> 29.166667 | G10: kg/day | H10: =$H$8 -> 23 | J10: =$H$10*$F$10 -> 670.83333 | K10: 15700 | M10: =$J$10*$K$10 -> 10532083 | N10: =$M$10/($N$5*1000) -> 0.41673662 | O10: =($M$10/$N$6)/$N$5 -> 0.026806678
B11: 4 | C11: Pemakaian Natural Gas HPB Geka
C12: Normal Consumption | D12: ='Desember 2024'!$AM$243 -> 0.30264218 | E12: MMBTU/MT CPO | F12: =$D$12*$N$3 -> 332.54793 | G12: MMBTU/day | H12: =$H$8 -> 23 | J12: =$H$12*$F$12 -> 7648.6024 | K12: =11.5*$N$6 -> 178779 | M12: =$J$12*$K$12 -> 1.3674095e+09 | N12: =$M$12/($N$5*1000) -> 54.106067 | O12: =($M$12/$N$6)/$N$5 -> 3.4803851
C13: Penalty Below Consumption | D13: 0 | E13: MMBTU/MT CPO | F13: =$D$13*$N$3 -> 0 | G13: MMBTU/day | H13: =$H$8 -> 23 | J13: =$H$13*$F$13 -> 0 | K13: =11.5*$N$6 -> 178779 | M13: =$J$13*$K$13 -> 0 | N13: =$M$13/($N$5*1000) -> 0 | O13: =($M$13/$N$6)/$N$5 -> 0
C14: Penalty Above Consumption | D14: 0 | E14: MMBTU/MT CPO | F14: =$D$14*$N$3 -> 0 | G14: MMBTU/day | H14: =$H$8 -> 23 | J14: =$H$14*$F$14 -> 0 | K14: =11.5*$N$6 -> 178779 | M14: =$J$14*$K$14 -> 0 | N14: =$M$14/($N$5*1000) -> 0 | O14: =($M$14/$N$6)/$N$5 -> 0
B15: 5 | C15: Pemakaian Steam
C16: For Process | D16: ='Desember 2024'!$AM$250 -> 34.678451 | E16: Kg/MT CPO | F16: =$D$16*$N$3/1000 -> 38.10522 | G16: Ton/day | H16: =$H$8 -> 23 | J16: =$H$16*$F$16 -> 876.42007 | K16: =Steam!H15 -> 183326.68 | M16: =$J$16*$K$16 -> 1.6067118e+08 | N16: =$M$16/($N$5*1000) -> 6.3574853 | O16: =($M$16/$N$6)/$N$5 -> 0.40894669
C17: Storage Tank for Heating | D17: ='Desember 2024'!$AM$254 -> 18.21772 | E17: Kg/MT CPO | F17: =$D$17*$N$3/1000 -> 20.017913 | G17: Ton/day | H17: =$H$8 -> 23 | J17: =$H$17*$F$17 -> 460.41201 | K17: =Steam!H15 -> 183326.68 | M17: =$J$17*$K$17 -> 84405804 | N17: =$M$17/($N$5*1000) -> 3.3397941 | O17: =($M$17/$N$6)/$N$5 -> 0.21483302
B18: 6 | C18: Pemakaian Electrical
C19: For Process | D19: ='Desember 2024'!$AM$273 -> 29.759471 | E19: kW/MT CPO | F19: =$D$19*$N$3 -> 32700.169 | G19: kW/day | H19: =$H$8 -> 23 | I19: 0 | J19: =$H$19*$F$19 -> 752103.89 | K19: 1550 | L19: =[18]Electric!H21 -> 3666.6667 | M19: =($F$19*$H$19*$K$19)+($F$19*$I$19*$L$19) -> 1.165761e+09 | N19: =$M$19/($N$5*1000) -> 46.127181 | O19: =($M$19/$N$6)/$N$5 -> 2.9671414
C20: Cooling Tower | D20: ='Desember 2024'!$AM$275 -> 7.1115462 | E20: kW/MT CPO | F20: =$D$20*$N$3 -> 7814.2774 | G20: kW/day | H20: =$H$8 -> 23 | I20: 0 | J20: =$H$20*$F$20 -> 179728.38 | K20: 1550 | L20: =L19 -> 3666.6667 | M20: =(F20*H20*K20)+(F20*I20*L20) -> 2.7857899e+08 | N20: =$M$20/($N$5*1000) -> 11.022897 | O20: =($M$20/$N$6)/$N$5 -> 0.70905035
C21: Storage Tank | D21: 0.3377877 | E21: kW/MT CPO | F21: =$D$21*$N$3 -> 371.16637 | G21: kW/day | H21: =$H$8 -> 23 | I21: 0 | J21: =$H$21*$F$21 -> 8536.8264 | K21: 1550 | L21: =L20 -> 3666.6667 | M21: =($F$21*$H$21*$K$21)+($F$21*$I$21*$L$21) -> 13232081 | N21: =$M$21/($N$5*1000) -> 0.52357093 | O21: =($M$21/$N$6)/$N$5 -> 0.03367882
B22: 7 | C22: Pemakaian Water
C23: Make Up CT | D23: ='Desember 2024'!$AM$260 -> 39.884845 | E23: M3/day | F23: =$D$23 -> 39.884845 | G23: M3/day | H23: =$H$8 -> 23 | J23: =$H$23*$F$23 -> 917.35144 | K23: =WTP!H13 -> 16370.605 | M23: =$J$23*$K$23 -> 15017598 | N23: =$M$23/($N$5*1000) -> 0.59422082 | O23: =($M$23/$N$6)/$N$5 -> 0.03822339
B24: 8 | C24: Chemical Water | N24: =$M$24/($N$5*1000) -> 0 | O24: =($M$24/$N$6)/$N$5 -> 0
C25: EONBAC BC 3108 | D25: 0.4 | E25: Kg/day | F25: =D25 -> 0.4 | G25: Kg/day | H25: =$H$8 -> 23 | J25: =$H$25*$F$25 -> 9.2 | K25: 27240 | M25: =$J$25*$K$25 -> 250608 | N25: =$M$25/($N$5*1000) -> 0.0099161322 | O25: =($M$25/$N$6)/$N$5 -> 0.00063785747
C26: EONLINE T722 | D26: 0.66 | E26: Kg/day | F26: =D26 -> 0.66 | G26: Kg/day | H26: =$H$8 -> 23 | J26: =$H$26*$F$26 -> 15.18 | K26: 29120 | M26: =$J$26*$K$26 -> 442041.6 | N26: =$M$26/($N$5*1000) -> 0.017490834 | O26: =($M$26/$N$6)/$N$5 -> 0.0011251019
C27: EONLINE AG5770 | D27: 0.41 | E27: Kg/day | F27: =D27 -> 0.41 | G27: Kg/day | H27: =$H$8 -> 23 | J27: =$H$27*$F$27 -> 9.43 | K27: 117212 | M27: =$J$27*$K$27 -> 1105309.2 | N27: =$M$27/($N$5*1000) -> 0.043735203 | O27: =($M$27/$N$6)/$N$5 -> 0.0028132769
C28: EONScale T2511 | D28: 0.1 | E28: Kg/day | F28: =D28 -> 0.1 | G28: Kg/day | H28: =$H$8 -> 23 | J28: =$H$28*$F$28 -> 2.3 | K28: 45940 | M28: =$J$28*$K$28 -> 105662 | N28: =$M$28/($N$5*1000) -> 0.0041808656 | O28: =($M$28/$N$6)/$N$5 -> 0.00026893513
B29: 9 | C29: Others
C30: Filter Bag 10 Microne | D30: 0.90361446 | E30: Pcs/day | F30: =D30 -> 0.90361446 | G30: Pcs/day | H30: =$H$8 -> 23 | J30: =$H$30*$F$30 -> 20.783133 | K30: 40000 | M30: =$J$30*$K$30 -> 831325.3 | N30: =$M$30/($N$5*1000) -> 0.032894128 | O30: =($M$30/$N$6)/$N$5 -> 0.0021159223
C31: Filter Bag 100 Microne | D31: 0.63253012 | E31: Pcs/day | F31: =D31 -> 0.63253012 | G31: Pcs/day | H31: =$H$8 -> 23 | J31: =$H$31*$F$31 -> 14.548193 | K31: 125000 | M31: =$J$31*$K$31 -> 1818524.1 | N31: =$M$31/($N$5*1000) -> 0.071955905 | O31: =($M$31/$N$6)/$N$5 -> 0.00462858
C32: Filter Cartridge 10 Microne | D32: 1.5666667 | E32: Pcs/day | F32: =D32 -> 1.5666667 | G32: Pcs/day | H32: =$H$8 -> 23 | J32: =$H$32*$F$32 -> 36.033333 | K32: 145000 | M32: =$J$32*$K$32 -> 5224833.3 | N32: =$M$32/($N$5*1000) -> 0.20673777 | O32: =($M$32/$N$6)/$N$5 -> 0.013298454
C33: Filter Dustbag | D33: 0.12048193 | E33: Pcs/day | F33: =D33 -> 0.12048193 | G33: Pcs/day | H33: =$H$8 -> 23 | J33: =$H$33*$F$33 -> 2.7710843 | K33: 682500 | M33: =$J$33*$K$33 -> 1891265.1 | N33: =$M$33/($N$5*1000) -> 0.074834141 | O33: =($M$33/$N$6)/$N$5 -> 0.0048137232
C34: O Ring Filter Leaves | D34: 3.6144578 | E34: Pcs/day | F34: =D34 -> 3.6144578 | G34: Pcs/day | H34: =$H$8 -> 23 | J34: =$H$34*$F$34 -> 83.13253 | K34: 14500 | M34: =$J$34*$K$34 -> 1205421.7 | N34: =$M$34/($N$5*1000) -> 0.047696485 | O34: =($M$34/$N$6)/$N$5 -> 0.0030680873
B35: 10 | C35: Waste Water Treatment Plant ( WWTP ) | D35: ='Desember 2024'!$AM$266 -> 165.91304 | E35: M3/day | F35: =D35 -> 165.91304 | G35: M3/day | H35: =$H$8 -> 23 | J35: =$H$35*$F$35 -> 3816 | K35: =WWTP!H17 -> 25456.97 | M35: =$J$35*$K$35 -> 97143798 | N35: =$M$35/($N$5*1000) -> 3.8438148 | O35: =($M$35/$N$6)/$N$5 -> 0.24725427
B36: 11 | C36: SHE
C37: SBE | D37: ='Desember 2024'!$AM$87 -> 231452.55 | E37: Kg/day | F37: =D37 -> 231452.55 | G37: Kg/day | H37: =$H$8 -> 23 | J37: =$F$37 -> 231452.55 | K37: 275 | M37: =$J$37*$K$37 -> 63649452 | N37: =$M$37/($N$5*1000) -> 2.5185005 | O37: =($M$37/$N$6)/$N$5 -> 0.16200312
C38: Domestic | D38: 0.1 | E38: Trip/day | F38: =D38 -> 0.1 | G38: Trip/day | H38: =$H$8 -> 23 | J38: =$H$38*$F$38 -> 2.3 | K38: 303030.3 | M38: =$J$38*$K$38 -> 696969.7 | N38: =$M$38/($N$5*1000) -> 0.027577905 | O38: =($M$38/$N$6)/$N$5 -> 0.0017739551
B39: 12 | C39: Chemical Consumption | N39: =$M$39/($N$5*1000) -> 0 | O39: =($M$39/$N$6)/$N$5 -> 0
C40: LAB Chemical | D40: =lab!H33 -> 745255.21 | E40: Rp/day | F40: =D40 -> 745255.21 | G40: Rp/day | H40: =$H$8 -> 23 | M40: =$H$40*$F$40 -> 17140870 | N40: =$M$40/($N$5*1000) -> 0.67823506 | O40: =($M$40/$N$6)/$N$5 -> 0.043627625
C41: Chemical Boiler dan WTP | D41: =lab!H54 -> 259161.44 | E41: Rp/day | F41: =D41 -> 259161.44 | G41: Rp/day | H41: =$H$8 -> 23 | M41: =$H$41*$F$41 -> 5960713.2 | N41: =$M$41/($N$5*1000) -> 0.23585528 | O41: =($M$41/$N$6)/$N$5 -> 0.015171445
C42: Sample and Analysis | D42: 13909.091 | E42: Rp/day | F42: =D42 -> 13909.091 | G42: Rp/day | H42: =$H$8 -> 23 | M42: =$H$42*$F$42 -> 319909.09 | N42: =$M$42/($N$5*1000) -> 0.012658258 | O42: =($M$42/$N$6)/$N$5 -> 0.00081424537
C43: Chemical WWTP | D43: =[18]Chemical!$H$61 -> 27103.641 | E43: Rp/day | F43: =D43 -> 27103.641 | G43: Rp/day | H43: =$H$8 -> 23 | M43: =$H$43*$F$43 -> 623383.75 | N43: =$M$43/($N$5*1000) -> 0.024666235 | O43: =($M$43/$N$6)/$N$5 -> 0.0015866612
C44: Consumable Part | D44: =lab!I111 -> 135770.31 | E44: Rp/day | F44: =D44 -> 135770.31 | G44: Rp/day | H44: =$H$8 -> 23 | M44: =$H$44*$F$44 -> 3122717.1 | N44: =$M$44/($N$5*1000) -> 0.1235606 | O44: =($M$44/$N$6)/$N$5 -> 0.007948064
B45: 13 | C45: Solar
C46: Forklift -1 (3 Ton) | D46: 15.4 | E46: Ltr/day | F46: =D46 -> 15.4 | G46: Ltr/day | H46: =$H$8 -> 23 | J46: =$H$46*$F$46 -> 354.2 | K46: 14500 | M46: =$J$46*$K$46 -> 5135900 | N46: =$M$46/($N$5*1000) -> 0.20321883 | O46: =($M$46/$N$6)/$N$5 -> 0.013072097
C47: WA Loader | D47: 0 | E47: Ltr/day | F47: =D47 -> 0 | G47: Ltr/day | H47: =$H$8 -> 23 | J47: =$H$47*$F$47 -> 0 | K47: 14500 | M47: =$J$47*$K$47 -> 0 | N47: =$M$47/($N$5*1000) -> 0 | O47: =($M$47/$N$6)/$N$5 -> 0
M48: =SUM($M$8:$M$47) -> 4.075111e+09 | N48: =SUM($N$8:$N$47) -> 161.24521 | O48: =SUM($O$8:$O$47) -> 10.372135

Sheet HPP FRACT
B2: Fractionation Cost
B3: RPO Proses / Day | N3: TPD | O3: ='Desember 2024'!AM23/1000 -> 1147.4684
B4: Working Day | N4: Days | O4: ='Desember 2024'!AM22 -> 21
B5: Total CPO Process | N5: MTD | O5: =O3*O4 -> 24096.837
B6: KURS | N6: Rp/USD | O6: ='SUMMARY HPP '!I9 -> 15546
B7: No | C7: Item Cost | D7: Norma | F7: Pemakaian / Hari | H7: HK | J7: Total Pemakaian | K7: Harga / stn | M7: Total Biaya | N7: Rp / kg | O7: USD/MT
B8: 1 | C8: Steam | D8: ='Desember 2024'!AM252 -> 59.116634 | E8: Kg/MT CPO | F8: =$D$8*$O$3/1000 -> 67.834471 | G8: Ton/day | H8: =$O$4 -> 21 | J8: =$H$8*$F$8 -> 1424.5239 | K8: =Steam!H15 -> 183326.68 | M8: =$K$8*$J$8 -> 2.6115323e+08 | N8: =$M$8/($O$5*1000) -> 10.837656 | O8: =($M$8/$O$6)/$O$5 -> 0.69713471
B9: 2 | C9: Electrical
C10: For Process | D10: ='Desember 2024'!$AM$280 -> 6.8307775 | E10: kW/MT CPO | F10: =$D$10*$O$3 -> 7838.1015 | G10: kW/day | H10: =$O$4 -> 21 | I10: 0 | J10: =$H$10*$F$10 -> 164600.13 | K10: =[18]Electric!$L$5 -> 1550 | L10: 3666.6667 | M10: =($F$10*$H$10*$K$10)+($F$10*$I$10*$L$10) -> 2.551302e+08 | N10: =$M$10/($O$5*1000) -> 10.587705 | O10: =($M$10/$O$6)/$O$5 -> 0.68105655
C11: Cooling Tower | D11: ='Desember 2024'!$AM$278 -> 6.8299995 | E11: kW/MT CPO | F11: =$D$11*$O$3 -> 7837.2087 | G11: kW/day | H11: =$H$10 -> 21 | I11: 0 | J11: =$H$11*$F$11 -> 164581.38 | K11: =$K$10 -> 1550 | L11: 3666.6667 | M11: =($F$11*$H$11*$K$11)+($F$11*$I$11*$L$11) -> 2.5510114e+08 | N11: =$M$11/($O$5*1000) -> 10.586499 | O11: =($M$11/$O$6)/$O$5 -> 0.68097898
B12: 3 | C12: Water
C13: Make Up CT | D13: ='Desember 2024'!$AM$262 -> 46.313132 | E13: M3/day | F13: =$D$13 -> 46.313132 | G13: M3/day | H13: =$H$11 -> 21 | J13: =$H$13*$F$13 -> 972.57578 | K13: =WTP!H13 -> 16370.605 | M13: =$K$13*$J$13 -> 15921654 | N13: =$M$13/($O$5*1000) -> 0.66073627 | O13: =($M$13/$O$6)/$O$5 -> 0.042502011
B14: 4 | C14: Chemical Water
C15: EONBAC BC 3108 | D15: 0.4 | E15: Kg/day | F15: =$D$15 -> 0.4 | G15: Kg/day | H15: =$H$13 -> 21 | J15: =$H$15*$F$15 -> 8.4 | K15: 27240 | M15: =$K$15*$J$15 -> 228816 | N15: =$M$15/($O$5*1000) -> 0.0094956861 | O15: =($M$15/$O$6)/$O$5 -> 0.00061081218
C16: EONLINE T722 | D16: 0.66 | E16: Kg/day | F16: =$D$16 -> 0.66 | G16: Kg/day | H16: =$H$15 -> 21 | J16: =$H$16*$F$16 -> 13.86 | K16: 29120 | M16: =$K$16*$J$16 -> 403603.2 | N16: =$M$16/($O$5*1000) -> 0.016749219 | O16: =($M$16/$O$6)/$O$5 -> 0.0010773973
C17: EONLINE AG5770 | D17: 0.41 | E17: Kg/day | F17: =$D$17 -> 0.41 | G17: Kg/day | H17: =$H$15 -> 21 | J17: =$H$17*$F$17 -> 8.61 | K17: 117212 | M17: =$K$17*$J$17 -> 1009195.3 | N17: =$M$17/($O$5*1000) -> 0.041880821 | O17: =($M$17/$O$6)/$O$5 -> 0.0026939934
C18: EONScale T2511 | D18: 0.1 | E18: Kg/day | F18: =$D$18 -> 0.1 | G18: Kg/day | H18: =$H$16 -> 21 | J18: =$H$18*$F$18 -> 2.1 | K18: 45940 | M18: =$K$18*$J$18 -> 96474 | N18: =$M$18/($O$5*1000) -> 0.004003596 | O18: =($M$18/$O$6)/$O$5 -> 0.00025753223
B19: 5 | C19: Others
C20: Filter Cloth | D20: 0.33333333 | E20: Pcs/day | F20: =$D$20 -> 0.33333333 | G20: Pcs/day | H20: =$H$18 -> 21 | J20: =$H$20*$F$20 -> 7 | K20: 895000 | M20: =$K$20*$J$20 -> 6265000 | N20: =$M$20/($O$5*1000) -> 0.25999263 | O20: =($M$20/$O$6)/$O$5 -> 0.016724085
C21: Filter Bag 100 Microne | D21: 0.63253012 | E21: Pcs/day | F21: =$D$21 -> 0.63253012 | G21: Pcs/day | H21: =$H$20 -> 21 | J21: =$H$21*$F$21 -> 13.283133 | K21: 125000 | M21: =$K$21*$J$21 -> 1660391.6 | N21: =$M$21/($O$5*1000) -> 0.068904959 | O21: =($M$21/$O$6)/$O$5 -> 0.0044323272
M22: =SUM(M8:M21) -> 7.9696972e+08 | N22: =SUM(N8:N21) -> 33.073624 | O22: =SUM($O$8:$O$21) -> 2.1274684

Sheet SUMMARY HPP 
B2: Production Cost September
B3: Through Put CPO Proses (Ton/Day) | H3: TPD | I3: ='HPP REF '!$N$3 -> 1098.8155
B4: Working Day | F4: 1 | H4: Days | I4: ='HPP REF '!$N$4 -> 23
B5: Refined CPO ( Ton/month ) | H5: MTD | I5: =$I$4*$I$3 -> 25272.757
B6: Through Put RPO Proses (Ton/Day) | H6: TPD | I6: ='HPP FRACT'!$O$3 -> 1147.4684
B7: Working Day | H7: Days | I7: ='HPP FRACT'!$O$4 -> 21
B8: Fract RPO ( ton/month ) | H8: MTD | I8: =$I$7*$I$6 -> 24096.837
B9: KURS | H9: Rp/USD | I9: 15546
B10: No | C10: Items | D10: Description | G10: Rupiah | H10: Rp/Kg | I10: USD/MT
B11: I | C11: Production Cost | D11: ● | E11: Refining Cost | G11: ='HPP REF '!$M$48 -> 4.075111e+09 | H11: =$G$11/($I$5*1000) -> 161.24521 | I11: =(G11/$I$9)/$I$5 -> 10.372135
D12: ● | E12: Fractionation Cost | G12: ='HPP FRACT'!$M$22 -> 7.9696972e+08 | H12: =$G$12/($I$8*1000) -> 33.073624 | I12: =(G12/$I$9)/$I$8 -> 2.1274684
D13: ● | E13: Preventive Maintenance Cost | F13: 0 | G13: =MTC!$F$18*F13 -> 0 | H13: =$G$13/($I$5*1000) -> 0 | I13: =(G13/$I$9)/$I$5 -> 0
G14: =SUM(G11:$G$13) -> 4.8720807e+09 | H14: =SUM($H$11:$H$13) -> 194.31883 | I14: =SUM(I11:I13) -> 12.499603 | K14: =I14+I26 -> 35.025782
B16: II | C16: Port Cost | D16: ● | E16: Trucking Komoditi ke Kuala Tanjung | G16: =LOG!I8+LOG!I9+LOG!$I$10 -> 2.6239187e+09 | H16: =$G$16/($I$5*1000) -> 103.824 | I16: =($G$16/$I$9)/$I$5 -> 6.6785025
D17: ● | E17: Sewa Tank PTI Total Volume : 24.000 MT ( 5 Unit ) | F17: =F4 -> 1 | G17: =LOG!I11+LOG!I12+LOG!I13+LOG!$I$14*F17 -> 1886000000 | H17: =$G$17/($I$5*1000) -> 74.625812 | I17: =($G$17/$I$9)/$I$5 -> 4.8003224
D18: ● | E18: Instalasi & Pemanasan, Pompa, Surveyor dan Documen | G18: =LOG!I18+LOG!I19+LOG!I20+LOG!$I$21 -> 1.353811e+09 | H18: =$G$18/($I$5*1000) -> 53.568 | I18: =($G$18/$I$9)/$I$5 -> 3.4457738
D19: ● | E19: Finalty Over Capacity Tank | G19: =LOG!I15+LOG!I16+LOG!$I$17 -> 1.0780347e+09 | H19: =$G$19/($I$5*1000) -> 42.656 | I19: =($G$19/$I$9)/$I$5 -> 2.7438569
G20: =SUM($G$16:$G$19) -> 6.9417645e+09 | H20: =SUM($H$16:$H$19) -> 274.67381 | I20: =SUM($I$16:$I$19) -> 17.668456
B22: II | C22: Fix Cost | D22: ● | E22: Manpower Cost | F22: =F4 -> 1 | G22: =[18]MPC!$H$29*$F$22 -> 2.1846655e+09 | H22: =$G$22/($I$5*1000) -> 86.443499 | I22: =($G$22/$I$9)/$I$5 -> 5.5604978
D23: ● | E23: Admin OH Cost | F23: =F4 -> 1 | G23: =OH!G51*$F$23 -> 1.4360564e+09 | H23: =$G$23/($I$5*1000) -> 56.822308 | I23: =($G$23/$I$9)/$I$5 -> 3.655108
D24: ● | E24: Depresiasi Cost | F24: =F4 -> 1 | G24: =DEP!I9*$F$24 -> 4.1811848e+09 | H24: =$G$24/($I$5*1000) -> 165.44237 | I24: =($G$24/$I$9)/$I$5 -> 10.642118
D25: ● | E25: Amortisation of leasehold land Cost | F25: =F4 -> 1 | G25: =AMOR!$G$20*$F$25 -> 1.0484098e+09 | H25: =$G$25/($I$5*1000) -> 41.483792 | I25: =($G$25/$I$9)/$I$5 -> 2.6684544
G26: =SUM($G$22:$G$25) -> 8.8503165e+09 | H26: =SUM($H$22:$H$25) -> 350.19197 | I26: =SUM($I$22:$I$25) -> 22.526178 | K26: =I26+I14 -> 35.025782
B28: Total Production Cost | G28: =$G$26+$G$20+$G$14 -> 2.0664162e+10 | H28: =$H$26+$H$20+$H$14 -> 819.18461 | I28: =$I$26+$I$20+$I$14 -> 52.694237

Sheet Convert Gas
B3: CONVERT PEMAKAIAN GAS HP BOILER & MP BOILER
D4: 2024
C5: HP BOILER | F5: TOTAL CORRECTED VOLUME (Sm3) | K5: ENERGY MP BOILER (MMBTU) | L5: TOTAL GAS CONSUMPTION (MMBTU) | M5: PERCENTAGE
C6: UNCORRECTED VOLUME (UV) (Nm3) | D6: PRESS. Bar | E6: CORRECTED VOLUME (CV) (Sm3) | G6: Convert Sm3 to SCF | H6: VOLUME (MSCF) | I6: HEATING VALUE (BTU / SCF) | J6: ENERGY HP BOILER (MMBTU) | M6: HP Boiler | N6: MP Boiler
C7: 1 | D7: 2 | E7: 3 = 1 x 2 | F7: 4 = 3 | G7: 5 | H7: 6 = (4 x 5) / 1000 | I7: 7 | J7: 8 = (6 x 7) / 1000 | K7: 9 = 10 - 8 | L7: 10 | M7: 11 = 8 / 10 | N7: 12 = 9 / 10
B8: 1 | D8: 5 | E8: =C8*D8 -> 0 | F8: =E8 -> 0 | G8: 35.314667 | H8: =(F8*G8)/1000 -> 0 | I8: 1047.7934 | J8: =(H8*I8)/1000 -> 0 | K8: =L8-J8 -> 0 | L8: 0 | M8: =(J8/L8) -> #DIV/0! | N8: =K8/L8 -> #DIV/0!
B9: =B8+1 -> 2 | D9: 5 | E9: =C9*D9 -> 0 | F9: =E9 -> 0 | G9: 35.314667 | H9: =(F9*G9)/1000 -> 0 | I9: 1042.7042 | J9: =(H9*I9)/1000 -> 0 | K9: =L9-J9 -> 0.7969 | L9: 0.7969 | M9: =(J9/L9) -> 0 | N9: =K9/L9 -> 1
B10: =B9+1 -> 3 | C10: 159.69 | D10: 5 | E10: =C10*D10 -> 798.45 | F10: =E10 -> 798.45 | G10: 35.314667 | H10: =(F10*G10)/1000 -> 28.196996 | I10: 1044.8302 | J10: =(H10*I10)/1000 -> 29.461073 | K10: =L10-J10 -> 656.37333 | L10: 685.8344 | M10: =(J10/L10) -> 0.04295654 | N10: =K10/L10 -> 0.95704346
B11: =B10+1 -> 4 | C11: 788.24 | D11: 5 | E11: =C11*D11 -> 3941.2 | F11: =E11 -> 3941.2 | G11: 35.314667 | H11: =(F11*G11)/1000 -> 139.18217 | I11: 1050.3635 | J11: =(H11*I11)/1000 -> 146.19187 | K11: =L11-J11 -> 696.04741 | L11: 842.23928 | M11: =(J11/L11) -> 0.17357522 | N11: =K11/L11 -> 0.82642478
B12: =B11+1 -> 5 | C12: 3.33 | D12: 5 | E12: =C12*D12 -> 16.65 | F12: =E12 -> 16.65 | G12: 35.314667 | H12: =(F12*G12)/1000 -> 0.58798921 | I12: 1050.6498 | J12: =(H12*I12)/1000 -> 0.61777073 | K12: =L12-J12 -> 767.54333 | L12: 768.1611 | M12: =(J12/L12) -> 0.00080422027 | N12: =K12/L12 -> 0.99919578
B13: =B12+1 -> 6 | C13: 1356.95 | D13: 5 | E13: =C13*D13 -> 6784.75 | F13: =E13 -> 6784.75 | G13: 35.314667 | H13: =(F13*G13)/1000 -> 239.60119 | I13: 1051.3912 | J13: =(H13*I13)/1000 -> 251.91459 | K13: =L13-J13 -> 389.14956 | L13: 641.06415 | M13: =(J13/L13) -> 0.39296315 | N13: =K13/L13 -> 0.60703685
B14: =B13+1 -> 7 | C14: 4051.52 | D14: 5 | E14: =C14*D14 -> 20257.6 | F14: =E14 -> 20257.6 | G14: 35.314667 | H14: =(F14*G14)/1000 -> 715.3904 | I14: 1053.7683 | J14: =(H14*I14)/1000 -> 753.85573 | K14: =L14-J14 -> 105.66983 | L14: 859.52556 | M14: =(J14/L14) -> 0.87706028 | N14: =K14/L14 -> 0.12293972
B15: =B14+1 -> 8 | C15: 5815.62 | D15: 5 | E15: =C15*D15 -> 29078.1 | F15: =E15 -> 29078.1 | G15: 35.314667 | H15: =(F15*G15)/1000 -> 1026.8834 | I15: 1055.9121 | J15: =(H15*I15)/1000 -> 1084.2986 | K15: =L15-J15 -> -55.066247 | L15: 1029.2324 | M15: =(J15/L15) -> 1.0535022 | N15: =K15/L15 -> -0.053502249
B16: =B15+1 -> 9 | C16: 5220.53 | D16: 5 | E16: =C16*D16 -> 26102.65 | F16: =E16 -> 26102.65 | G16: 35.314667 | H16: =(F16*G16)/1000 -> 921.80639 | I16: 1058.5967 | J16: =(H16*I16)/1000 -> 975.82117 | K16: =L16-J16 -> 139.90533 | L16: 1115.7265 | M16: =(J16/L16) -> 0.87460607 | N16: =K16/L16 -> 0.12539393
B17: =B16+1 -> 10 | C17: 2188 | D17: 5 | E17: =C17*D17 -> 10940 | F17: =E17 -> 10940 | G17: 35.314667 | H17: =(F17*G17)/1000 -> 386.34246 | I17: 1055.6055 | J17: =(H17*I17)/1000 -> 407.82521 | K17: =L17-J17 -> 551.84729 | L17: 959.6725 | M17: =(J17/L17) -> 0.4249629 | N17: =K17/L17 -> 0.5750371
B18: =B17+1 -> 11 | C18: 1796.49 | D18: 5 | E18: =C18*D18 -> 8982.45 | F18: =E18 -> 8982.45 | G18: 35.314667 | H18: =(F18*G18)/1000 -> 317.21223 | I18: 1056.3096 | J18: =(H18*I18)/1000 -> 335.07431 | K18: =L18-J18 -> 538.27709 | L18: 873.3514 | M18: =(J18/L18) -> 0.38366494 | N18: =K18/L18 -> 0.61633506
B19: =B18+1 -> 12 | C19: 4866.75 | D19: 5 | E19: =C19*D19 -> 24333.75 | F19: =E19 -> 24333.75 | G19: 35.314667 | H19: =(F19*G19)/1000 -> 859.33828 | I19: 1051.5483 | J19: =(H19*I19)/1000 -> 903.63574 | K19: =L19-J19 -> 6.6809602 | L19: 910.3167 | M19: =(J19/L19) -> 0.99266084 | N19: =K19/L19 -> 0.0073391603
B20: =B19+1 -> 13 | C20: 6932.28 | D20: 5 | E20: =C20*D20 -> 34661.4 | F20: =E20 -> 34661.4 | G20: 35.314667 | H20: =(F20*G20)/1000 -> 1224.0558 | I20: 1053.7374 | J20: =(H20*I20)/1000 -> 1289.8334 | K20: =L20-J20 -> -53.700699 | L20: 1236.1327 | M20: =(J20/L20) -> 1.0434425 | N20: =K20/L20 -> -0.043442504
B21: =B20+1 -> 14 | C21: 6338.15 | D21: 5 | E21: =C21*D21 -> 31690.75 | F21: =E21 -> 31690.75 | G21: 35.314667 | H21: =(F21*G21)/1000 -> 1119.1483 | I21: 1054.6459 | J21: =(H21*I21)/1000 -> 1180.3051 | K21: =L21-J21 -> -24.066515 | L21: 1156.2386 | M21: =(J21/L21) -> 1.0208145 | N21: =K21/L21 -> -0.020814488
... B24: =B23+1 -> 17 | C24: 6388.24 | D24: 5 | E24: =C24*D24 -> 31941.2 | F24: =E24 -> 31941.2 | G24: 38.314667 | H24: =(F24*G24)/1000 -> 1223.8164 | I24: 1041.3329 | J24: =(H24*I24)/1000 -> 1274.4003 | K24: =L24-J24 -> -125.496 | L24: 1148.9043 | M24: =(J24/L24) -> 1.109231 | N24: =K24/L24 -> -0.10923103
B25: =B24+1 -> 18 | C25: 7607.66 | D25: 5 | E25: =C25*D25 -> 38038.3 | F25: =E25 -> 38038.3 | G25: 39.314667 | H25: =(F25*G25)/1000 -> 1495.4631 | I25: 1042.2141 | J25: =(H25*I25)/1000 -> 1558.5927 | K25: =L25-J25 -> -1558.5927 | M25: =(J25/L25) -> #DIV/0! | N25: =K25/L25 -> #DIV/0!
B26: =B25+1 -> 19 | C26: 6514.97 | D26: 5 | E26: =C26*D26 -> 32574.85 | F26: =E26 -> 32574.85 | G26: 40.314667 | H26: =(F26*G26)/1000 -> 1313.2442 | I26: 1042.5071 | J26: =(H26*I26)/1000 -> 1369.0664 | K26: =L26-J26 -> -1369.0664 | M26: =(J26/L26) -> #DIV/0! | N26: =K26/L26 -> #DIV/0!
B27: =B26+1 -> 20 | C27: 4942.41 | D27: 5 | E27: =C27*D27 -> 24712.05 | F27: =E27 -> 24712.05 | G27: 41.314667 | H27: =(F27*G27)/1000 -> 1020.9701 | I27: 1042.9853 | J27: =(H27*I27)/1000 -> 1064.8569 | K27: =L27-J27 -> -1064.8569 | M27: =(J27/L27) -> #DIV/0! | N27: =K27/L27 -> #DIV/0!
B28: =B27+1 -> 21 | C28: 3073.52 | D28: 5 | E28: =C28*D28 -> 15367.6 | F28: =E28 -> 15367.6 | G28: 42.314667 | H28: =(F28*G28)/1000 -> 650.27488 | I28: 1043.1149 | J28: =(H28*I28)/1000 -> 678.31139 | K28: =L28-J28 -> -678.31139 | M28: =(J28/L28) -> #DIV/0! | N28: =K28/L28 -> #DIV/0!
B29: =B28+1 -> 22 | D29: 5 | E29: =C29*D29 -> 0 | F29: =E29 -> 0 | G29: 42.314667 | H29: =(F29*G29)/1000 -> 0 | I29: 1042.5884 | J29: =(H29*I29)/1000 -> 0 | K29: =L29-J29 -> 0 | M29: =(J29/L29) -> #DIV/0! | N29: =K29/L29 -> #DIV/0!
B30: =B29+1 -> 23 | D30: 5 | E30: =C30*D30 -> 0 | F30: =E30 -> 0 | G30: 44.314667 | H30: =(F30*G30)/1000 -> 0 | I30: 1042.7497 | J30: =(H30*I30)/1000 -> 0 | K30: =L30-J30 -> 0 | M30: =(J30/L30) -> #DIV/0! | N30: =K30/L30 -> #DIV/0!
B31: =B30+1 -> 24 | D31: 5 | E31: =C31*D31 -> 0 | F31: =E31 -> 0 | G31: 45.314667 | H31: =(F31*G31)/1000 -> 0 | I31: 1042.2931 | J31: =(H31*I31)/1000 -> 0 | K31: =L31-J31 -> 0 | M31: =(J31/L31) -> #DIV/0! | N31: =K31/L31 -> #DIV/0!
B32: =B31+1 -> 25 | D32: 5 | E32: =C32*D32 -> 0 | F32: =E32 -> 0 | G32: 46.314667 | H32: =(F32*G32)/1000 -> 0 | I32: 1039.4114 | J32: =(H32*I32)/1000 -> 0 | K32: =L32-J32 -> 0 | M32: =(J32/L32) -> #DIV/0! | N32: =K32/L32 -> #DIV/0!
B33: =B32+1 -> 26 | D33: 5 | E33: =C33*D33 -> 0 | F33: =E33 -> 0 | G33: 47.314667 | H33: =(F33*G33)/1000 -> 0 | I33: 1039.4407 | J33: =(H33*I33)/1000 -> 0 | K33: =L33-J33 -> 0 | M33: =(J33/L33) -> #DIV/0! | N33: =K33/L33 -> #DIV/0!
B34: =B33+1 -> 27 | D34: 5 | E34: =C34*D34 -> 0 | F34: =E34 -> 0 | G34: 48.314667 | H34: =(F34*G34)/1000 -> 0 | I34: 1040.2491 | J34: =(H34*I34)/1000 -> 0 | K34: =L34-J34 -> 0 | M34: =(J34/L34) -> #DIV/0! | N34: =K34/L34 -> #DIV/0!
B35: =B34+1 -> 28 | D35: 5 | E35: =C35*D35 -> 0 | F35: =E35 -> 0 | G35: 49.314667 | H35: =(F35*G35)/1000 -> 0 | J35: =(H35*I35)/1000 -> 0 | K35: =L35-J35 -> 0 | M35: =(J35/L35) -> #DIV/0! | N35: =K35/L35 -> #DIV/0!
B36: =B35+1 -> 29 | D36: 5 | E36: =C36*D36 -> 0 | F36: =E36 -> 0 | G36: 50.314667 | H36: =(F36*G36)/1000 -> 0 | J36: =(H36*I36)/1000 -> 0 | K36: =L36-J36 -> 0 | M36: =(J36/L36) -> #DIV/0! | N36: =K36/L36 -> #DIV/0!
B37: =B36+1 -> 30 | D37: 5 | E37: =C37*D37 -> 0 | F37: =E37 -> 0 | G37: 51.314667 | H37: =(F37*G37)/1000 -> 0 | J37: =(H37*I37)/1000 -> 0 | K37: =L37-J37 -> 0 | M37: =(J37/L37) -> #DIV/0! | N37: =K37/L37 -> #DIV/0!
B38: Average | F38: =AVERAGE(F8:F37) -> 12674.528 | H38: =AVERAGE(H8:H37) -> 471.76255 | I38: =AVERAGE(I8:I37) -> 1047.1339 | J38: =AVERAGE(J8:J37) -> 494.65048 | K38: =AVERAGE(K8:K37) -> -12.578486 | L38: =AVERAGE(L8:L37) -> 850.71528 | M38: =AVERAGE(M8:M37) -> #DIV/0! | N38: =AVERAGE(N8:N37) -> #DIV/0!
B39: TOTAL | C39: =SUM(C8:C37) -> 76047.17 | E39: =SUM(E8:E37) -> 380235.85 | F39: =SUM(F8:F37) -> 380235.85 | H39: =SUM(H8:H37) -> 14152.877 | J39: =SUM(J8:J37) -> 14839.514
B40: Koreksi
B41: Total Setelah Koreksi | H41: =H39+H40 -> 14152.877 | J41: =J39+J40 -> 14839.514
C43: CONVERT HP Boiler from Utility
C44: =C39 -> 76047.17 | D44: m3 | F44: =C39*5 -> 380235.85 | G44: 9983.7
C45: 5 | D45: bar | F45: 21286.9 | G45: =G44-C39 -> -66063.47
C46: =C44*C45 -> 380235.85 | D46: Sm3 | F46: =F44/F45 -> 17.862434
C47: =#REF! -> #REF! | D47: Scf
C48: =(C46*C47)/1000 -> #REF! | D48: Volume (MSCF)
C49: =I38 -> 1047.1339 | D49: Heating Value
C50: =(C48*C49)/1000 -> #REF! | D50: Energy (mmbtu)

Sheet Qty cons analysis
D2: Quantity Utility Consumption Analysis (based on Guarantee Utility Consumption)
D3: Refinery & Fractionation Plant
D4: Periode 01 s/d 31 Desember 2024
D5: Consumption | E5: UoM | F5: Budget | G5: Actual | H5: Under (Over) Budget | I5: Explanation Under / Over budget
D6: CPO Consume | E6: Kg | F6: 36359000 | G6: ='Desember 2024'!$AM$9 -> 25272757 | H6: =G6/F6 -> 0.69508944
D7: RbdPO Consume | E7: Kg | F7: 34458000 | G7: ='Desember 2024'!$AM$24 -> 24112447 | H7: =G7/F7 -> 0.69976339
D8: TOTAL ACTUAL CONSUMPTION
D9: Refinery
D10: Bleaching Earth to Poram Spec | E10: Kg | F10: 232362 | G10: ='Desember 2024'!$AM$74 -> 229303.91 | H10: =F10-G10 -> 3058.09
D11: Bleaching Earth to Branded Spec | E11: Kg | F11: 131651 | G11: ='Desember 2024'!$AM$80 -> 0 | H11: =F11-G11 -> 131651
D12: Phosporic Acid | E12: Kg | F12: 21815 | G12: ='Desember 2024'!$AM$82 -> 12772.944 | H12: =F12-G12 -> 9042.056
D13: Gas Consumption (MP Boiler) | E13: mmbtu | F13: 20978.28 | G13: ='Desember 2024'!$AM$244+'Desember 2024'!$AM$243 -> -50695.652 | H13: =F13-G13 -> 71673.932
D14: Gas Consumption (HP Boiler) | E14: mmbtu | F14: 3702.06 | G14: ='Desember 2024'!$AM$242 -> 76486.024 | H14: =F14-G14 -> -72783.964
D15: Cooling Water top up to Cooling Tower | E15: m3 | F15: 1441.26 | G15: ='Desember 2024'!$AM$259 -> 1008 | H15: =F15-G15 -> 433.26
D16: Steam | E16: Kg | F16: 8640000 | G16: ='Desember 2024'!$AM$249 -> 876420.07 | H16: =F16-G16 -> 7763579.9
D17: Power (Process Plant) | E17: Kwh | F17: 97275 | G17: ='Desember 2024'!$AM$274 -> 179728.38 | H17: =F17-G17 -> -82453.38
D18: Power (Cooling Tower) | E18: Kwh | F18: 69307 | G18: ='Desember 2024'!$AM$272 -> 752103.89 | H18: =F18-G18 -> -682796.89
D19: Fractionation
D20: Cooling Water top up to Cooling Tower | E20: m3 | F20: 2489 | G20: ='Desember 2024'!$AM$261 -> 1116 | H20: =F20-G20 -> 1373
D21: Steam | E21: Kg | F21: 2196000 | G21: ='Desember 2024'!$AM$251 -> 1425446.7 | H21: =F21-G21 -> 770553.3
D22: Power (Process Plant) | E22: Kwh | F22: 103680 | G22: ='Desember 2024'!$AM$279 -> 164706.76 | H22: =F22-G22 -> -61026.76
D23: Power (Cooling Tower) | E23: Kwh | F23: 27234 | G23: ='Desember 2024'!$AM$277 -> 164688 | H23: =F23-G23 -> -137454
D24: ACTUAL CONSUMPTION PER MT RAW MATERIAL
D25: Refinery
D26: Bleaching Earth to Poram Spec | E26: Kg/MT | F26: 9 | G26: =(G10/$G$6)*1000 -> 9.0731656 | H26: =F26-G26 -> -0.073165623
D27: Bleaching Earth to Branded Spec | E27: Kg/MT | F27: 18 | G27: =(G11/$G$6)*1000 -> 0 | H27: =F27-G27 -> 18
D28: Phosporic Acid | E28: Kg/MT | F28: 0.6 | G28: =(G12/$G$6)*1000 -> 0.50540366 | H28: =F28-G28 -> 0.094596335
D29: Gas Consumption (HP Boiler) | E29: Nm3/MT | F29: 4.2 | G29: =(G13/$G$6)*1000 -> -2.0059407 | H29: =F29-G29 -> 6.2059407 | I29: Gas Over dikarenakan kapasitas tidak tercapai
D30: Gas Consumption (HP Boiler) **) | E30: mmbtu/MT | F30: 0.147294 | G30: =(G14/$G$6)*1000 -> 3.0264218 | H30: =F30-G30 -> -2.8791278
D31: Cooling Water top up to Cooling Tower | E31: m3/MT | F31: 0.6 | G31: =(G15/$G$6)*1000 -> 0.039884845 | H31: =F31-G31 -> 0.56011515
D32: Steam | E32: Kg/MT | F32: 46 | G32: =(G16/$G$6)*1000 -> 34.678451 | H32: =F32-G32 -> 11.321549 | I32: Steam Refinery Over dikarenakan kapasitas tidak tercapai
D33: Power (Process Plant) | E33: Kwh/MT | F33: 4.3033333 | G33: =(G17/$G$6)*1000 -> 7.1115462 | H33: =F33-G33 -> -2.8082129 | I33: Power Over dikarenakan kapasitas tidak tercapai
D34: Power (Utility System/Chiller) | E34: Kwh/MT | F34: 7.3 | G34: =(G18/$G$6)*1000 -> 29.759471 | H34: =F34-G34 -> -22.459471
D35: Fractionation
D36: Cooling Water top up to Cooling Tower | E36: m3/MT | F36: 0.4 | G36: =(G20/$G$6)*1000 -> 0.044158221 | H36: =F36-G36 -> 0.35584178
D37: Steam | E37: Kg/MT | F37: 45 | G37: =(G21/$G$6)*1000 -> 56.402501 | H37: =F37-G37 -> -11.402501 | I37: Steam Over dikarenakan menggunakan 2 unit chiller
D38: Power (Process Plant) | E38: Kwh/MT | F38: 4.5 | G38: =(G22/$G$6)*1000 -> 6.5171663 | H38: =F38-G38 -> -2.0171663 | I38: Power Over dikarenakan kapasitas tidak tercapai
D39: Power (utility System/chiller ) | E39: Kwh/MT | F39: 4.1 | G39: =(G23/$G$6)*1000 -> 6.516424 | H39: =F39-G39 -> -2.416424
D42: - PMG II Commissioning
D43: - BE Achieve dengan pemakaian consume Bleaching Earth 7,80 Kg/MT
D44: * Steam Refinery Over dikarenakan kapasitas tidak tercapai
D45: * Gas Refinery Over dikarenakan kapasitas tidak tercapai
D46: * Power Fractionation Over dikarenakan kapasitas tidak tercapai
D48: Prepared by, | G48: Checked by, | I48: Approved by,
D52: Bany Subana | F52: Reza P. Panjaitan | H52: Sudarianto | I52: Eben Jaya Ginting
D53: Admin. Process | F53: Supervisor Produksi | H53: Jr. Manager Produksi | I53: Manager Plant

Sheet Utility
D2: UTILITY (GAS, STEAM, WATER & POWER) REPORT
D3: PT. INDUSTRI NABATI LESTARI
D5: Periode 01 s/d 31 Desember 2024
D6: No | E6: Item | F6: Norma | G6: UoM | H6: Desember | K6: Consume CPO ( MT ) | L6: Remaks
H7: Budget | I7: Actual | J7: Percentage Act.
E9: Total Feed Raw Material CPO | K9: 29045
D10: 1. | E10: GAS CONSUMPTION
E11: Incoming *base on INL | G11: mmbtu | I11: ='Desember 2024'!$AM$240 -> 25913.808
E12: Incoming *base on Pertagas | F12: 1460.001 | G12: mmbtu | H12: 24680.34 | I12: ='Desember 2024'!$AM$238 -> 25790.069 | J12: =I12/H12 -> 1.0449641 | K12: =I12/K9 -> 0.88793489
E13: Distribution to
E14: HP Boiler Refinery | G14: mmbtu | H14: 3702.06 | I14: ='Desember 2024'!$AM$242 -> 76486.024 | J14: =I14/H14 -> 20.660396 | K14: =I14/K9 -> 2.6333628
E15: MP Boiler | G15: mmbtu | H15: 22143.74 | I15: =I12-$I$14 -> -50695.955 | J15: =I15/H15 -> -2.2894035 | K15: =I15/K9 -> -1.745428
E16: Total | G16: mmbtu | H16: =H12 -> 24680.34 | I16: =I14+I12 -> 102276.09 | J16: =I16/H16 -> 4.144031 | K16: =SUM(K14+K15) -> 0.88793489
D17: 2. | E17: STEAM CONSUMPTION
E18: Incoming | G18: Kg | H18: =480*'Desember 2024'!AM6 -> 11040 | I18: ='Desember 2024'!$AM$247 -> 2568027.3 | J18: =I18/H18 -> 232.61117 | K18: =I18/$K$9 -> 88.41547
E19: Distribution to | K19: =I19/$K$9 -> 0
E20: Refinery | F20: < 28 | G20: Kg | H20: 3240000 | I20: ='Desember 2024'!$AM$249 -> 876420.07 | J20: =I20/H20 -> 0.27050002 | K20: =I20/$K$9 -> 30.174559
E21: Fractionation | F21: < 35 | G21: Kg | H21: 2196000 | I21: ='Desember 2024'!$AM$251 -> 1425446.7 | J21: =I21/H21 -> 0.64911052 | K21: =I21/$K$9 -> 49.07718
E22: Others | F22: 106000 | G22: Kg | H22: 3204000 | I22: ='Desember 2024'!$AM$253 -> 460412.01 | J22: =I22/H22 -> 0.14369913 | K22: =I22/$K$9 -> 15.851679
E23: Total | G23: Kg | H23: =H20+H21+H22 -> 8640000 | I23: =SUM(I20:I22) -> 2762278.8 | J23: =I23/H23 -> 0.31970819 | K23: =I23/$K$9 -> 95.103418
D24: 3. | E24: WATER CONSUMPTION
E25: Incoming Raw Water | G25: m3 | H25: 18117.18 | I25: =SUM(I26:$I$27) -> 18195 | J25: =I25/H25 -> 1.0042954 | K25: =I25/$K$9 -> 0.62644173
E26: - Suplay To RO Product | I26: ='Desember 2024'!$AM$263 -> 7710 | K26: =I26/$K$9 -> 0.26545016
E27: - Suplay To Proses dan Sanitary | I27: =SUM(I29:$I$31) -> 10485 | K27: =I27/$K$9 -> 0.36099156
E28: Rincian Outgoing Proses | K28: =I28/$K$9 -> 0
E29: Softener Product (to Refinery) | F29: < 0,04 | G29: m3 | H29: 1441.26 | I29: ='Desember 2024'!$AM$259 -> 1008 | J29: =I29/H29 -> 0.69938804 | K29: =I29/$K$9 -> 0.034704768
E30: Softener Product (to Fractionation) | F30: < 0,13 | G30: m3 | H30: 2489.58 | I30: ='Desember 2024'!$AM$261 -> 1116 | J30: =I30/H30 -> 0.44826838 | K30: =I30/$K$9 -> 0.038423137
E31: Others | G31: m3 | H31: 14186.34 | I31: ='Desember 2024'!$AM$264 -> 8361 | J31: =I31/H31 -> 0.58936977 | K31: =I31/$K$9 -> 0.28786366
E32: Total | G32: m3 | H32: =H29+H30+H31 -> 18117.18 | I32: =SUM(I26:I27) -> 18195 | J32: =I32/H32 -> 1.0042954 | K32: =I32/$K$9 -> 0.62644173
D33: 4 | E33: POWER CONSUMPTION
E34: Incoming
E35: PLN *base on BA Kinra | G35: Kwh | H35: 538199 | I35: ='Desember 2024'!$AM$269 -> 504.24 | J35: =I35/H35 -> 0.00093690252 | K35: =I35/$K$9 -> 0.017360647
E36: Outgoing | K36: =I36/$K$9 -> 0
E37: - Physical Refinery Plant | F37: 10946.3 | G37: Kwh | H37: 97275 | I37: ='Desember 2024'!$AM$274 -> 179728.38 | J37: =I37/H37 -> 1.8476318 | K37: =I37/$K$9*1000 -> 6187.9284
E38: - Refinery - Utility / Chiller | F38: 18374.4 | G38: Kwh | H38: 69307 | I38: ='Desember 2024'!$AM$272 -> 752103.89 | J38: =I38/H38 -> 10.851774 | K38: =I38/$K$9*1000 -> 25894.436
E39: - Refinery - Utilities | F39: 11.81 | G39: Kwh | H39: 212 | I39: ='Desember 2024'!$AM$282 -> 0 | J39: =I39/H39 -> 0 | K39: =I39/$K$9*1000 -> 0
E40: - Dry Fractionation Plant | F40: 11201.3 | G40: Kwh | H40: 103680 | I40: ='Desember 2024'!$AM$279 -> 164706.76 | J40: =I40/H40 -> 1.5886069 | K40: =I40/$K$9*1000 -> 5670.744
E41: - Utility Chiller | F41: 10272 | G41: Kwh | H41: 27234 | I41: ='Desember 2024'!$AM$277 -> 164688 | J41: =I41/H41 -> 6.0471469 | K41: =I41/$K$9*1000 -> 5670.0981
E42: - Lighting - Refinery & Dry Fractionation | F42: 241.12 | G42: Kwh | H42: 4581 | I42: ='Desember 2024'!$AM$283 -> 0 | J42: =I42/H42 -> 0 | K42: =I42/$K$9*1000 -> 0
D44: Note untuk Power Consumption
D45: Selisih antara incoming dan outgoing dikarenakan hal berikut :
D47: - Over pemakaian Gas dikarenakan running sesuai RKAP 18 hari namun plant running 23 hari
E50: Prepared by, | F50: Checked by, | K50: Approved by,
E54: Bany Subana | F54: Reza P. Panjaitan | I54: Sudarianto | K54: Eben Jaya Ginting
E55: Admin. Process | F55: Supervisor Produksi | I55: Jr. Manager Produksi | K55: Manager Plant
E59: ='[19]Planning Production Plant 1 (22'!$S$112+'[19]Planning Production Plant 1 (22'!$S$114+'[19]Planning Production Plant 1 (22'!$S$128 -> 101816.32

Sheet Prod
B2: MONTHLY PRODUCTION REPORT PMG II
B3: PT. INDUSTRI NABATI LESTARI
B4: Periode 01 s/d 31 Desember 2024
B5: NO | C5: Item | D5: Unit | E5: Desember | H5: Remaks
E6: Budget | F6: Actual | G6: Percentage Act.
B7: 1. | C7: PRODUCTION
C8: Refinery Plant
C9: Running Days | D9: Days | E9: 18 | F9: ='Desember 2024'!$AM$6 -> 23 | G9: =(F9/E9) -> 1.2777778 | H9: Tercapai
C10: CPO Incoming | D10: Kg
C11: Total CPO Consume | D11: Kg | E11: 36359000 | F11: =F12+F13 -> 25272757 | G11: =(F11/E11) -> 0.69508944 | H11: Tidak Tercapai
C12: CPO Consume Poram | F12: ='Desember 2024'!$AM$11 -> 25272757
C13: CPO Consume Brand | F13: ='Desember 2024'!$AM$12 -> 0
C14: - Avg. FFA | D14: % | E14: 5 | F14: ='Desember 2024'!$AM$13 -> 3.3336957 | G14: =(F14/E14) -> 0.66673913
C15: - Avg. Moist & Impurities | D15: % | E15: 0.5 | F15: ='Desember 2024'!$AM$14 -> 0.36391304 | G15: =(F15/E15) -> 0.72782609
C16: - Avg. DOBI | D16: % | E16: 22.2 | F16: ='Desember 2024'!AM15 -> 1.8452174 | G16: =(F16/E16) -> 0.083117901
C17: Product
C18: RBDPO | D18: Kg | E18: 34458000 | F18: ='Desember 2024'!$AM$19 -> 24389568 | G18: =(F18/E18) -> 0.70780568
C19: PFAD | D19: Kg | E19: 1636000 | F19: ='Desember 2024'!$AM$20 -> 1089130 | G19: =(F19/E19) -> 0.66572738
C21: Fraksinasi Plant
C22: Total Proses RBDPO | D22: Kg | E22: =E25+E38+E43 -> 31417000 | F22: ='Desember 2024'!$AM$28 -> 24096837 | G22: =(F22/E22) -> 0.76699994 | H22: Tidak Tercapai
C23: Total Olah RBDPO ( Feed ) | D23: Kg | E23: =E25+E38+E43 -> 31417000 | F23: ='Desember 2024'!$AM$24 -> 24112447 | G23: =(F23/E23) -> 0.7674968 | H23: Tidak Tercapai
C24: Fractionation Olein IV 56
C25: RBDPO Consume | D25: Kg | E25: =E26+E27 -> 7883000 | F25: =F26+F27 -> 7003508 | G25: =(F25/E25) -> 0.88843182 | H25: Tercapai
C26: Olein IV 56 | D26: Kg | E26: 6464000 | F26: ='Desember 2024'!$AM$32 -> 5583694 | G26: =(F26/E26) -> 0.86381405 | H26: Tercapai
C27: Stearin | D27: Kg | E27: 1419000 | F27: ='Desember 2024'!$AM$33 -> 1419814 | G27: =(F27/E27) -> 1.0005736 | H27: Tercapai
C28: Fractionation Olein IV 57 ( Bulk )
C29: RBDPO Consume | D29: Kg | E29: 0
C30: Olein IV 57 | D30: Kg | E30: 0 | F30: 0 | G30: 0
C31: Stearin | D31: Kg | E31: 0
C32: Fractionation Olein IV 57 ( Retail )
C33: CPO | D33: Kg | E33: 1812101.9 | G33: =(F33/E33)*100 -> 0
C34: RBDPO Consume | D34: Kg | E34: =E35+E36 -> 3040000 | F34: =F35+F36 -> 0 | G34: =(F34/E34)*100 -> 0 | H34: Tidak Produksi
C35: Olein IV 57 | D35: Kg | E35: 2280000 | G35: =(F35/E35)*100 -> 0 | H35: Tidak Produksi
C36: Stearin | D36: Kg | E36: 760000 | G36: =(F36/E36)*100 -> 0 | H36: Tidak Produksi
C37: Fractionation Olein IV 58
C38: RBDPO Consume | D38: Kg | E38: =E39+E40 -> 21429000 | F38: =F39+F40 -> 16973017 | G38: =(F38/E38)*100 -> 79.205829 | H38: Tidak Tercapai
C39: Olein IV 58 | D39: Kg | E39: 15000000 | F39: ='Desember 2024'!$AM$45 -> 11987575 | G39: =(F39/E39)*100 -> 79.917167 | H39: Tidak Tercapai
C40: Stearin | D40: Kg | E40: 6429000 | F40: ='Desember 2024'!$AM$46 -> 4985442 | G40: =(F40/E40)*100 -> 77.54615 | H40: Tidak Tercapai
C41: Fractionation Olein IV 60
C42: CPO | E42: 2234607.2 | F42: 0 | G42: =(F42/E42)*100 -> 0
C43: RBDPO Consume | D43: Kg | E43: =E44+E45 -> 2105000 | F43: =F44+F45 -> 145360 | G43: =(F43/E43)*100 -> 6.9054632 | H43: Tidak Tercapai
C44: Olein IV 60 Salvaco | D44: Kg | E44: 1263000 | F44: ='Desember 2024'!AM55 -> 87260 | G44: =(F44/E44)*100 -> 6.908947 | H44: Tidak Tercapai
C45: Soft Stearin | D45: Kg | E45: 842000 | F45: ='Desember 2024'!AM56 -> 58100 | G45: =(F45/E45)*100 -> 6.9002375 | H45: Tidak Tercapai
B46: 2. | C46: % YIELD
C47: RBDPO | D47: % | E47: 94.77 | F47: =(F18/F11)*100 -> 96.505371 | G47: =(F47/E47)*100 -> 101.83114 | H47: Tercapai
C48: PFAD | D48: % | E48: 4.5 | F48: =(F19/(F11))*100 -> 4.3095021 | G48: =(F48/E48)*100 -> 95.766714 | H48: Tercapai
C49: Olein IV 56 | D49: % | E49: 82 | F49: =F26/(F26+F27)*100 -> 79.727102 | G49: =(F49/E49)*100 -> 97.228174 | H49: Tercapai
C50: Stearin | D50: % | E50: 18 | F50: =(F27/F25)*100 -> 20.272898 | G50: =(F50/E50)*100 -> 112.62721 | H50: Tercapai
C51: Olein IV 57 ( Bulk ) | D51: % | E51: 75 | F51: 0 | G51: =(F51/E51)*100 -> 0
C52: Stearin | D52: % | E52: 25 | F52: 0 | G52: =(F52/E52)*100 -> 0 | J52: =F47+F48 -> 100.81487
C53: Olein IV 57 ( Retail ) | D53: % | E53: 75 | F53: =F35/(F35+F36)*100 -> #DIV/0! | G53: =(F53/E53)*100 -> #DIV/0! | H53: Tercapai | J53: =J52-100% -> 99.814874
C54: Stearin | D54: % | E54: 25 | F54: =(F36/F34)*100 -> #DIV/0! | G54: =(F54/E54)*100 -> #DIV/0! | H54: Tercapai | J54: =100-J52 -> -0.8148735
C55: Olein IV 58 | D55: % | E55: 70 | F55: =F39/(F39+F40)*100 -> 70.627249 | G55: =(F55/E55)*100 -> 100.89607 | H55: Tercapai
C56: Stearin | D56: % | E56: 30 | F56: =(F40/F38)*100 -> 29.372751 | G56: =(F56/E56)*100 -> 97.90917 | H56: Tercapai
C57: Olein IV 60 | D57: % | E57: 60 | F57: =F44/(F44+F45)*100 -> 60.03027 | G57: =(F57/E57)*100 -> 100.05045 | H57: Tercapai
C58: Soft Stearin | D58: % | E58: 40 | F58: =(F45/F43)*100 -> 39.96973 | G58: =(F58/E58)*100 -> 99.924326 | H58: Tercapai
B59: 3. | C59: CHEMICAL CONSUMABLE
C60: Bleaching Earth to Poram Spec | D60: Kg | E60: 232362 | F60: ='Desember 2024'!$AM$74 -> 229303.91 | G60: =(F60/E60)*100 -> 98.683911
D61: Kg/MT | E61: 9 | F61: =(F60/F12)*1000 -> 9.0731656 | G61: =(F61/E61)*100 -> 100.81295 | H61: Tercapai
C62: Bleaching Earth to Branded Spec | D62: Kg | E62: 131651 | F62: ='Desember 2024'!AM12 -> 0 | G62: =(F62/E62)*100 -> 0
D63: Kg/MT | E63: 18 | G63: =(F63/E63)*100 -> 0
C64: Phosporic Acid | D64: Kg | E64: 21815 | F64: ='Desember 2024'!$AM$82 -> 12772.944 | G64: =(F64/E64)*100 -> 58.551199
D65: Kg/MT | E65: 0.6 | F65: =(F64/F11)*1000 -> 0.50540366 | G65: =(F65/E65)*100 -> 84.233944 | H65: Tercapai
B66: 4. | C66: OIL LOSSES
C67: (Loss)/Gain | D67: % | E67: -0,73 | F67: -0,64 | G67: =(F67/E67)*100 -> 87.671233 | H67: Tercapai
C68: % Oil Content | D68: % | E68: 22 | F68: ='Desember 2024'!$AM$86 -> 21.551667 | G68: =(F68/E68)*100 -> 97.962121 | H68: Tercapai
C69: Spent Bleaching Earth | D69: Kg | E69: 413199.36 | F69: ='Desember 2024'!$AM$87 -> 231452.55 | G69: =(F69/E69)*100 -> 56.014742
B70: NB :
B71: - PMG II Commissioning
B72: - Start 03 Desember end 20 Desember
B73: - BE Achieve dengan pemakaian consume Bleaching Earth 8,9 Kg/MT
B74: - Untuk hari olah Produksi terpenuhi namun dalam kondisi Slow Flowrate dikarenakan Shortage CPO dan target Shipment yang tercapai hanya Olein IV 56
B76: - Total CPO Proses sebesar : 25.641 Mt dengan total CPO Incoming ke INL sebanyak : 9.134 MT
B77: - Rata rata incoming CPO perhari 294 MT
A79: Prepared by, | D79: Checked by, | H79: Approved by,
A83: Bany Subana | D83: Reza P. Panjaitan | F83: Sudarianto | H83: Eben Jaya Ginting
A84: Admin. Process | D84: Supervisor Produksi | F84: Jr. Manager Produksi | H84: Manager Plant

Sheet OIP Refinery 
B4: Oil In Plant (OIP) Refinery | I4: DESEMBER | J4: OIP | M4: TK131 RPO | P4: TK132 RPO | S4: TOTAL STOK RPO DI PLANT
B5: Vessel | C5: Operating Volume (m3) | D5: Oil Density (kg/m3) | E5: MT | F5: Level yg diisi | G5: Actual OIP (Kg) | I5: Tanggal | J5: Opening Stock | K5: Closing Stock | L5: balance stok | M5: Opening Stock | N5: Closing Stock | O5: CONSUMP stok | P5: Opening Stock | Q5: Closing Stock | R5: CONSUMP stok
B6: 2MX312 | C6: 5.67 | D6: 850 | E6: =C6*D6/1000 -> 4.8195 | F6: 0 | G6: =(F6*E6/100)*1000 -> 0 | I6: 45627
B7: 2VE611A | C7: 47.22 | D7: 850 | E7: =C7*D7/1000 -> 40.137 | F7: 0 | G7: =(F7*E7/100)*1000 -> 0 | I7: 45628
B8: 2VE611B | C8: 47.22 | D8: 850 | E8: =C8*D8/1000 -> 40.137 | F8: 0 | G8: =(F8*E8/100)*1000 -> 0 | I8: 45629
B9: 2VE612 | C9: 35.68 | D9: 850 | E9: =C9*D9/1000 -> 30.328 | F9: 0 | G9: =(F9*E9/100)*1000 -> 0 | I9: 45630 | K9: 308515.38
B10: 2VE661 | C10: 10.8 | D10: 850 | E10: =C10*D10/1000 -> 9.18 | F10: 0 | G10: =(F10*E10/100)*1000 -> 0 | I10: 45631 | J10: 308515
B11: FL621 | C11: 10.1 | D11: 850 | E11: =C11*D11/1000 -> 8.585 | F11: 0 | G11: =(F11*E11/100)*1000 -> 0 | I11: 45632 | J11: 308515 | K11: 284092 | L11: =J11-K11 -> 24423
B12: FL622 | C12: 10.1 | D12: 850 | E12: =C12*D12/1000 -> 8.585 | F12: 0 | G12: =(F12*E12/100)*1000 -> 0 | I12: 45633 | J12: 284092 | K12: 307785 | L12: =J12-K12 -> -23693
B13: FL623 | C13: 10.1 | D13: 850 | E13: =C13*D13/1000 -> 8.585 | F13: 0 | G13: =(F13*E13/100)*1000 -> 0 | I13: 45634 | J13: 307798 | K13: 299017 | L13: =J13-K13 -> 8781 | N13: 0 | Q13: 174609
B14: FL624 | C14: 10.1 | D14: 850 | E14: =C14*D14/1000 -> 8.585 | F14: 0 | G14: =(F14*E14/100)*1000 -> 0 | I14: 45635 | J14: 299017 | K14: 305518 | L14: =J14-K14 -> -6501 | N14: 44191 | P14: 174609 | Q14: 38852 | R14: =P14-Q14 -> 135757 | S14: =R14+O14+L14 -> 129256
B15: FL625 | C15: 10.1 | D15: 850 | E15: =C15*D15/1000 -> 8.585 | F15: 0 | G15: =(F15*E15/100)*1000 -> 0 | I15: 45636 | J15: 305518 | K15: 307138 | L15: =J15-K15 -> -1620 | M15: 44191 | N15: 405272 | O15: =M15-N15 -> -361081 | P15: 38852 | Q15: 38852 | R15: =P15-Q15 -> 0 | S15: =R15+O15+L15 -> -362701
B16: 2VE701 | C16: 72.13 | D16: 850 | E16: =C16*D16/1000 -> 61.3105 | F16: 40.8 | G16: =(F16*E16/100)*1000 -> 25014.684 | I16: 45637 | J16: 307138 | K16: 306411 | L16: =J16-K16 -> 727
B17: 2VE751 | C17: 4.28 | D17: 860 | E17: =C17*D17/1000 -> 3.6808 | F17: 50 | G17: =(F17*E17/100)*1000 -> 1840.4 | I17: 45638 | J17: 306411 | K17: 304056 | L17: =J17-K17 -> 2355
B18: 2HE721A (tube) | C18: 10 | D18: 810 | E18: =C18*D18/1000 -> 8.1 | F18: 100 | G18: =(F18*E18/100)*1000 -> 8100 | I18: 45639 | J18: 304056 | K18: 287956 | L18: =J18-K18 -> 16100
B19: 2HE721A (shell) | C19: 21.8 | D19: 800 | E19: =C19*D19/1000 -> 17.44 | F19: 60 | G19: =(F19*E19/100)*1000 -> 10464 | I19: 45640 | J19: 287956 | K19: 270583 | L19: =J19-K19 -> 17373
B20: HE721B (tube) | C20: 10 | D20: 810 | E20: =C20*D20/1000 -> 8.1 | F20: 100 | G20: =(F20*E20/100)*1000 -> 8100 | I20: 45641 | J20: 270583 | K20: 294127 | L20: =J20-K20 -> -23544
B21: 2HE722 | C21: 11.4 | D21: 790 | E21: =C21*D21/1000 -> 9.006 | F21: 80 | G21: =(F21*E21/100)*1000 -> 7204.8 | I21: 45642 | J21: 294127 | K21: 284931 | L21: =J21-K21 -> 9196
B22: 2PR731 | C22: 14 | D22: 790 | E22: =C22*D22/1000 -> 11.06 | F22: 60 | G22: =(F22*E22/100)*1000 -> 6636 | I22: 45643 | J22: 284931 | K22: 319970 | L22: =J22-K22 -> -35039
B23: 2DE732 | C23: 149.76 | D23: 790 | E23: =C23*D23/1000 -> 118.3104 | F23: 100 | G23: =(F23*E23/100)*1000 -> 118310.4 | I23: 45644 | J23: 319970 | K23: 320396 | L23: =J23-K23 -> -426
C24: =SUM(C6:C23) -> 490.46 | E24: =SUM(E6:E23) -> 404.5342 | I24: 45645 | J24: 320396 | K24: 315612 | L24: =J24-K24 -> 4784
F25: Total OIP = | G25: =SUM(G6:G24) -> 185670.28 | I25: 45646 | J25: 315612 | K25: 293070 | L25: =J25-K25 -> 22542
B26: Buffer tank RBDPO | C26: Operating Volume (m3) | D26: Oil Density (kg/m3) | E26: MT | F26: Level yg diisi | G26: Aktual ( Kg ) | I26: 45647 | J26: 293070 | K26: 283964 | L26: =J26-K26 -> 9106
B27: TK131 | C27: 559 | D27: 880 | E27: =C27*D27/1000 -> 491.92 | G27: =F27*E27/100*1000 -> 0 | I27: 45648 | J27: 283964 | K27: 285490 | L27: =J27-K27 -> -1526
B28: TK132 | C28: 559 | D28: 880 | E28: =C28*D28/1000 -> 491.92 | I28: 45649 | J28: 285490 | K28: 303442 | L28: =J28-K28 -> -17952
I29: 45650 | J29: 303442 | K29: 195205 | L29: =J29-K29 -> 108237
B30: Solar Daily Tank HPB | I30: 45651 | J30: 195205 | K30: 185670 | L30: =J30-K30 -> 9535
B31: 2TK726 | C31: =5.3+0.78 -> 6.08 | D31: 840 | E31: =C31*D31/1000 -> 5.1072 | F31: 0 | G31: =F31*E31/100*1000 -> 0 | H31: 0 | I31: 45652 | J31: 185670 | K31: 0 | L31: =J31-K31 -> 185670
I32: 45653 | J32: =K31 -> 0 | L32: =J32-K32 -> 0
B33: Stock Chemicals In Plant | I33: 45654 | J33: =K32 -> 0 | L33: =J33-K33 -> 0
C34: Read | D34: End Read | E34: Consumption | I34: 45655 | J34: =K33 -> 0 | L34: =J34-K34 -> 0
B35: BE | I35: 45656 | J35: =K34 -> 0 | L35: =J35-K35 -> 0
B36: 630A | I36: 45657 | J36: =K35 -> 0 | L36: =J36-K36 -> 0
B37: 630B
B38: H3PO4
B39: NaOH
B40: Citrid Acid

Sheet Oip Fract .
B4: Oil In Plant (OIP) Fraksinasi | J4: OIP | T4: BUFFER TANK
B5: RBDPO OIP | J5: RPO CR | N5: OLEIN | Q5: STEARIN | T5: TK131 RPO | V5: TK132 RPO
A6: Suhu CR (°C) | B6: Vessel | C6: Operating Volume (m3) | D6: Oil Density (kg/m3) | E6: MT | F6: Level Transmitter (1%/MT) | G6: Level (%) | H6: Kg | J6: Tanggal | K6: Opening Stock | L6: Closing Stock | M6: balance stok | N6: Opening Stock | O6: Closing Stock | P6: balance stok | Q6: Opening Stock | R6: Closing Stock | S6: balance stok | T6: Opening Stock | U6: Closing Stock | V6: Opening Stock | W6: Closing Stock
B7: 2CR1201 | C7: 70.51 | D7: 890 | E7: =C7*D7/1000 -> 62.7539 | F7: =E7/100 -> 0.627539 | G7: 0 | H7: =F7*G7*1000 -> 0 | J7: 45627
B8: 2CR1202 | C8: 70.51 | D8: 890 | E8: =C8*D8/1000 -> 62.7539 | F8: =E8/100 -> 0.627539 | G8: 0 | H8: =F8*G8*1000 -> 0 | J8: 45628
B9: 2CR1203 | C9: 70.51 | D9: 890 | E9: =C9*D9/1000 -> 62.7539 | F9: =E9/100 -> 0.627539 | G9: 0 | H9: =F9*G9*1000 -> 0 | J9: 45629
B10: 2CR1204 | C10: 70.51 | D10: 890 | E10: =C10*D10/1000 -> 62.7539 | F10: =E10/100 -> 0.627539 | G10: 0 | H10: =F10*G10*1000 -> 0 | J10: 45630
B11: 2CR1205 | C11: 70.51 | D11: 890 | E11: =C11*D11/1000 -> 62.7539 | F11: =E11/100 -> 0.627539 | G11: 0 | H11: =F11*G11*1000 -> 0 | J11: 45631
B12: 2CR1206 | C12: 70.51 | D12: 890 | E12: =C12*D12/1000 -> 62.7539 | F12: =E12/100 -> 0.627539 | G12: 100 | H12: =F12*G12*1000 -> 62753.9 | J12: 45632
B13: 2CR1207 | C13: 70.51 | D13: 890 | E13: =C13*D13/1000 -> 62.7539 | F13: =E13/100 -> 0.627539 | G13: 100 | H13: =F13*G13*1000 -> 62753.9 | J13: 45633
B14: 2CR1208 | C14: 70.51 | D14: 890 | E14: =C14*D14/1000 -> 62.7539 | F14: =E14/100 -> 0.627539 | G14: 100 | H14: =F14*G14*1000 -> 62753.9 | J14: 45634 | L14: 281577 | M14: =K14-L14 -> -281577 | U14: 0 | W14: 174609
B15: 2CR1209 | C15: 70.51 | D15: 890 | E15: =C15*D15/1000 -> 62.7539 | F15: =E15/100 -> 0.627539 | G15: 0 | H15: =F15*G15*1000 -> 0 | J15: 45635 | K15: 281577 | L15: 777326 | M15: =K15-L15 -> -495749 | O15: 52378 | R15: 14279 | U15: 44191 | V15: 174609 | W15: 38852
B16: 2CR1210 | C16: 70.51 | D16: 890 | E16: =C16*D16/1000 -> 62.7539 | F16: =E16/100 -> 0.627539 | G16: 0 | H16: =F16*G16*1000 -> 0 | J16: 45636 | K16: 777326 | L16: 450259 | M16: =K16-L16 -> 327067 | N16: 52378 | O16: 95638 | P16: =N16-O16 -> -43260 | Q16: 14279 | R16: 8567 | S16: =Q16-R16 -> 5712 | T16: 44191 | U16: 405272 | V16: 38852 | W16: 38852
B17: 2CR1211 | C17: 70.51 | D17: 890 | E17: =C17*D17/1000 -> 62.7539 | F17: =E17/100 -> 0.627539 | G17: 0 | H17: =F17*G17*1000 -> 0 | J17: 45637 | K17: 450259 | L17: 833623 | M17: =K17-L17 -> -383364 | N17: 95638 | O17: 50626 | P17: =N17-O17 -> 45012 | Q17: 8567 | R17: 22846 | S17: =Q17-R17 -> -14279 | T17: 405272 | U17: 312272 | V17: 38852 | W17: 312272
B18: 2CR1212 | C18: 70.51 | D18: 890 | E18: =C18*D18/1000 -> 62.7539 | F18: =E18/100 -> 0.627539 | G18: 0 | H18: =F18*G18*1000 -> 0 | J18: 45638 | K18: 833623 | L18: 853328 | M18: =K18-L18 -> -19705 | N18: 50626 | O18: 29049 | P18: =N18-O18 -> 21577 | Q18: 22846 | R18: 14279 | S18: =Q18-R18 -> 8567 | T18: 312272 | U18: 447800 | V18: 312272 | W18: 347595
B19: 2CR1213 | C19: 70.51 | D19: 890 | E19: =C19*D19/1000 -> 62.7539 | F19: =E19/100 -> 0.627539 | G19: 0 | H19: =F19*G19*1000 -> 0 | J19: 45639 | K19: 853328 | L19: 699831 | M19: =K19-L19 -> 153497 | N19: 29049 | O19: 65200 | P19: =N19-O19 -> -36151 | Q19: 14279 | R19: 19990 | S19: =Q19-R19 -> -5711 | T19: 447800 | U19: 160000 | V19: 347595 | W19: 112000
B20: 2CR1214 | C20: 70.51 | D20: 890 | E20: =C20*D20/1000 -> 62.7539 | F20: =E20/100 -> 0.627539 | G20: 0 | H20: =F20*G20*1000 -> 0 | J20: 45640 | K20: 699831 | L20: 870648 | M20: =K20-L20 -> -170817 | N20: 65200 | O20: 47784 | P20: =N20-O20 -> 17416 | Q20: 19990 | R20: 25702 | S20: =Q20-R20 -> -5712 | T20: 160000 | U20: 156000 | V20: 112000 | W20: 85000
B21: 2CR1215 | C21: 70.51 | D21: 890 | E21: =C21*D21/1000 -> 62.7539 | F21: =E21/100 -> 0.627539 | G21: 0 | H21: =F21*G21*1000 -> 0 | J21: 45641 | K21: 870648 | L21: 822076 | M21: =K21-L21 -> 48572 | N21: 47784 | O21: 44032 | P21: =N21-O21 -> 3752 | Q21: 25702 | R21: 17135 | S21: =Q21-R21 -> 8567 | T21: 156000 | U21: 265000 | V21: 85000 | W21: 265000
J22: 45642 | K22: 822076 | L22: 152178 | M22: =K22-L22 -> 669898 | N22: 44032 | O22: 69851 | P22: =N22-O22 -> -25819 | Q22: 17135 | R22: 0 | S22: =Q22-R22 -> 17135 | T22: 265000 | U22: 88200 | V22: 265000 | W22: 80200
G23: Total RBDPO | H23: =SUM(H7:H21) -> 188261.7 | J23: 45643 | K23: 152178 | L23: 627539 | N23: 69851 | O23: 66851 | Q23: 0 | R23: 4855 | T23: 88200 | U23: 35220 | V23: 80200 | W23: 35220
I24: =H23+H31+H36 -> 257618.45 | J24: 45644 | K24: 627539 | L24: 876044 | N24: 66851 | O24: 63943 | Q24: 4855 | R24: 25.702 | T24: 35220 | U24: 95225 | V24: 35220 | W24: 105225
B25: Olein OIP | J25: 45645 | K25: 876044 | L25: 853453 | N25: 63943 | O25: 22284 | Q25: 25.702 | R25: 34.269 | T25: 95225 | U25: 234123 | V25: 105225 | W25: 234125
B26: Vessel | C26: Operating Volume (m3) | D26: Oil Density (kg/m3) | E26: MT | F26: Level Transmitter (1%/MT) | G26: Level (%) | H26: Kg | J26: 45646 | K26: 853453 | L26: 859666 | N26: 22284 | O26: 23136 | Q26: 34.269 | R26: 15421 | T26: 234123 | U26: 223284 | V26: 234125 | W26: 216280
B27: 2TK261 | C27: 15.95 | D27: 885 | E27: =C27*D27/1000 -> 14.11575 | F27: =E27/100 -> 0.1411575 | G27: 72.1 | H27: =F27*G27*1000 -> 10177.456 | J27: 45647 | K27: 859666 | L27: 859666 | N27: =O26 -> 23136 | O27: 15421 | Q27: =R26 -> 15421 | R27: 12851 | T27: =U26 -> 223284 | U27: 158003 | V27: =W26 -> 216280 | W27: 155107
B28: 2CL251 | C28: 3.02 | D28: 885 | E28: =C28*D28/1000 -> 2.6727 | F28: =E28/100 -> 0.026727 | G28: 0 | H28: =F28*G28*1000 -> 0 | J28: 45648 | K28: =L27 -> 859666 | L28: 878555 | N28: =O27 -> 15421 | O28: 12851 | Q28: =R27 -> 12851 | R28: 20847 | T28: =U27 -> 158003 | U28: 167918 | V28: =W27 -> 155107 | W28: 164248
B29: 2TK221 | C29: 82.48 | D29: 885 | E29: =C29*D29/1000 -> 72.9948 | F29: =E29/100 -> 0.729948 | G29: 63.9 | H29: =F29*G29*1000 -> 46643.677 | J29: 45649 | K29: =L28 -> 878555 | L29: 878555 | N29: =O28 -> 12851 | O29: 66552 | Q29: =R28 -> 20847 | R29: 17706 | T29: =U28 -> 167918 | U29: 340216 | V29: =W28 -> 164248 | W29: 330359
B30: 2TK241 | C30: 16.95 | D30: 885 | E30: =C30*D30/1000 -> 15.00075 | F30: =E30/100 -> 0.1500075 | G30: 83.5 | H30: =F30*G30*1000 -> 12525.626 | J30: 45650 | K30: 878555 | L30: 835568 | N30: =O29 -> 66552 | O30: 67509 | Q30: 17706 | R30: 11423 | T30: =U29 -> 340216 | U30: 156238 | V30: =W29 -> 330359 | W30: 156022
G31: Total OLEIN | H31: =SUM(H27:H30) -> 69346.759 | J31: 45651 | K31: =L30 -> 835568 | L31: 842157 | N31: =O30 -> 67509 | O31: 67509 | Q31: 11423 | R31: 15421 | T31: =U30 -> 156238 | U31: 78021 | V31: =W30 -> 156022 | W31: 156240
B32: Stearin OIP | J32: 45652 | K32: =L31 -> 842157 | L32: 336361 | N32: =O31 -> 67509 | O32: 44184 | Q32: =R31 -> 15421 | R32: 9995 | T32: =U31 -> 78021 | U32: 37638 | V32: =W31 -> 156240 | W32: 197872
B33: Melting Tank | C33: Panjang (m) | D33: Lebar (m) | E33: tinggi (m) | F33: Density | G33: Tinggi Sounding (Cm) Maks 4,4 m | H33: Kg | J33: 45653 | K33: =L32 -> 336361 | L33: 188262 | N33: =O32 -> 44184 | O33: 69347 | Q33: =R32 -> 9995 | T33: =U32 -> 37638 | U33: 37954 | V33: =W32 -> 197872 | W33: 108106
B34: TK231 A | C34: 12.2 | D34: 1.75 | E34: 1.52 | F34: 0.88 | G34: 20 | H34: =C34*D34*E34*F34*G34/100 -> 5.711552 | J34: 45654 | K34: =L33 -> 188262 | N34: =O33 -> 69347 | Q34: =R33 -> 0 | T34: =U33 -> 37954 | V34: =W33 -> 108106
B35: TK231 B | C35: 12.2 | D35: 1.75 | E35: 1.52 | F35: 0.88 | G35: 15 | H35: =C35*D35*E35*F35*G35/100 -> 4.283664 | J35: 45655 | K35: =L34 -> 0 | N35: =O34 -> 0 | Q35: =R34 -> 0 | T35: =U34 -> 0 | V35: =W34 -> 0
G36: Total STEARIN | H36: =SUM(H34:H35) -> 9.995216 | J36: 45656 | K36: =L35 -> 0 | N36: =O35 -> 0 | Q36: =R35 -> 0 | T36: =U35 -> 0 | V36: =W35 -> 0
J37: 45657 | K37: =L36 -> 0 | N37: =O36 -> 0 | Q37: =R36 -> 0 | T37: =U36 -> 0 | V37: =W36 -> 0

Sheet Downtime Ref Des
F2: DOWN TIME SLOW FLOWRATE PRODUCTION REFINERY
F4: Periode 01/31 Desember 2024
F5: TANGGAL | G5: CAPACITY (Kg) | H5: REMARKS | I5: Down time | M5: Tph
I6: Stop | J6: Slow | K6: % | AE6: 17 | AF6: 18 | AG6: 19 | AH6: 20 | AI6: 21 | AJ6: 22 | AK6: 23 | AL6: 24 | AM6: 25 | AN6: 26 | AO6: 27 | AP6: 28 | AQ6: 29 | AR6: 30 | AS6: 31
F7: 1 | H7: SHUT DOWN | J7: =(2500-(G7/1000))/105 -> 23.809524 | K7: =G7/2500/1000 -> 0 | M7: =(G7/1000)/24 -> 0 | O7: =249.262+270.9 -> 520.162 | P7: =1356.367+39.742 -> 1396.109 | Q7: =1086.521+50.6 -> 1137.121 | R7: =1353.558+373.309 -> 1726.867 | S7: 1942.746 | T7: 1868.212 | U7: 2057.011 | V7: 1781.844 | W7: 1250.764 | X7: 1613.486 | Y7: 1325.077 | Z7: =66.442+571.568 -> 638.01 | AA7: =815.429 -> 815.429 | AB7: =352.234+731.627 -> 1083.861 | AC7: =1626.002+13.213 -> 1639.215 | AD7: 2094.791 | AE7: 2075.375 | AF7: 2008.804 | AG7: 1946.712 | AH7: 1998.939 | AI7: =1623.839+281.468 -> 1905.307 | AJ7: 1610.024 | AK7: =1135.181+98.368 -> 1233.549 | AL7: =958.893+543.852 -> 1502.745 | AM7: 2043.15 | AN7: 1762.642 | AO7: 2170.336 | AP7: =1181.38+463.711 -> 1645.091 | AQ7: 219.474 | AR7: =48.153+1225.968+107.3 -> 1381.421
F8: 2 | H8: SHUT DOWN | J8: =(2500-(G8/1000))/105 -> 23.809524 | K8: =G8/2500/1000 -> 0 | M8: =(G8/1000)/24 -> 0
F9: 3 | G9: 132992 | H9: Downtime due to Start Up Plant | J9: =(2500-(G9/1000))/105 -> 22.542933 | K9: =G9/2500/1000 -> 0.0531968 | M9: =(G9/1000)/24 -> 5.5413333
F10: 4 | G10: 235848 | H10: Penyesuaian incoming CPO | J10: =(2500-(G10/1000))/105 -> 21.563352 | K10: =G10/2500/1000 -> 0.0943392 | M10: =(G10/1000)/24 -> 9.827
F11: 5 | H11: SHUT DOWN | J11: =(2500-(G11/1000))/105 -> 23.809524 | K11: =G11/2500/1000 -> 0 | M11: =(G11/1000)/24 -> 0
F12: 6 | H12: SHUT DOWN | J12: =(2500-(G12/1000))/105 -> 23.809524 | K12: =G12/2500/1000 -> 0 | M12: =(G12/1000)/24 -> 0
F13: 7 | G13: 494521 | H13: Penyesuaian incoming CPO | J13: =(2500-(G13/1000))/105 -> 19.0998 | K13: =G13/2500/1000 -> 0.1978084 | M13: =(G13/1000)/24 -> 20.605042
F14: 8 | G14: 1864782 | H14: Penyesuaian incoming CPO | J14: =(2500-(G14/1000))/105 -> 6.0496952 | K14: =G14/2500/1000 -> 0.7459128 | M14: =(G14/1000)/24 -> 77.69925
F15: 9 | G15: 1581450 | H15: Penyesuaian incoming CPO | J15: =(2500-(G15/1000))/105 -> 8.7480952 | K15: =G15/2500/1000 -> 0.63258 | M15: =(G15/1000)/24 -> 65.89375
F16: 10 | G16: 621025 | H16: Penyesuaian incoming CPO | J16: =(2500-(G16/1000))/105 -> 17.895 | K16: =G16/2500/1000 -> 0.24841 | M16: =(G16/1000)/24 -> 25.876042
F17: 11 | G17: 247984 | H17: Penyesuaian incoming CPO | J17: =(2500-(G17/1000))/105 -> 21.447771 | K17: =G17/2500/1000 -> 0.0991936 | M17: =(G17/1000)/24 -> 10.332667
F18: 12 | G18: 1063200 | H18: Penyesuaian incoming CPO | J18: =(2500-(G18/1000))/105 -> 13.68381 | K18: =G18/2500/1000 -> 0.42528 | M18: =(G18/1000)/24 -> 44.3
F19: 13 | G19: 2196288 | H19: Penyesuaian incoming CPO | J19: =(2500-(G19/1000))/105 -> 2.8924952 | K19: =G19/2500/1000 -> 0.8785152 | M19: =(G19/1000)/24 -> 91.512
F20: 14 | G20: 1639113 | H20: Penyesuaian incoming CPO | J20: =(2500-(G20/1000))/105 -> 8.1989238 | K20: =G20/2500/1000 -> 0.6556452 | M20: =(G20/1000)/24 -> 68.296375
F21: 15 | G21: 1616712 | H21: Penyesuaian incoming CPO | J21: =(2500-(G21/1000))/105 -> 8.4122667 | K21: =G21/2500/1000 -> 0.6466848 | M21: =(G21/1000)/24 -> 67.363
F22: 16 | G22: 907136 | H22: Penyesuaian incoming CPO | J22: =(2500-(G22/1000))/105 -> 15.170133 | K22: =G22/2500/1000 -> 0.3628544 | M22: =(G22/1000)/24 -> 37.797333
F23: 17 | G23: 1962242 | H23: Penyesuaian incoming CPO | J23: =(2500-(G23/1000))/105 -> 5.1215048 | K23: =G23/2500/1000 -> 0.7848968 | M23: =(G23/1000)/24 -> 81.760083
F24: 18 | G24: 2416411 | H24: Penyesuaian incoming CPO | J24: =(2500-(G24/1000))/105 -> 0.79608571 | K24: =G24/2500/1000 -> 0.9665644 | M24: =(G24/1000)/24 -> 100.68379
... F36: 30 | G36: 0 | H36: SHUT DOWN | J36: =(2500-(G36/1000))/105 -> 23.809524 | K36: =G36/2500/1000 -> 0 | M36: =(G36/1000)/24 -> 0
F37: TOTAL | G37: =SUM(G7:G36) -> 25641597 | I37: =SUM(I7:I36) -> 0 | J37: =SUM(J7:J36) -> 470.08003 | M37: =AVERAGE(M7:M36) -> 35.613329
G39: Summary
G40: 1. Slow flow rate due to Space Tank High | I40: 0 | J40: hours
G41: 2. Slow flow rate due to Olein IV 60 process | I41: =SUM(J30) -> 16.776752 | J41: hours
G42: 3. Hold plant due to trip MP boiler & maintenance | I42: 0 | J42: hours
G43: 4. Penyesuaian incoming CPO | I43: =SUM(J10,J13,J14,J15,J16,J17,J18,J20,J19,J21,J22,J23,J24,J25,J26,J27,J28,J29,J31) -> 216.47463 | J43: hours
G44: 5. Downtime due to Start Up Plant | I44: =SUM(J9) -> 22.542933 | J44: hours
G45: 6. Running Normal Plant | I45: 0 | J45: hours
G46: 7. Stop Plant due to Preventive Maintenance Plant | I46: 0 | J46: hours
G47: 8. Energizing PMG II | I47: 0 | J47: hours
G48: 9. Zero Suplay Gas (Problem Pertagas) | I48: 0 | J48: hours
G49: 10, Stop Plant | I49: =SUM(J7,J8,J11,J12,J32,J33,J34,J35,J36) -> 214.28571 | J49: hours
G50: 11.HOLD CPO Shortage | J50: hours
G51: Total | I51: =SUM(I40:I50) -> 470.08003 | J51: hours
G52: Note : Kapasitas 2500 TPD | I52: =I51/24 -> 19.586668
E60: Prepared by, | H60: Checked by, | J60: Approved by,
E64: Bany Subana | H64: Reza P. Panjaitan | J64: Sudarianto
E65: Admin. Process | H65: Supervisor Produksi | J65: Jr. Manager Produksi

Sheet Downtime Fract Des
F2: DOWN TIME SLOW FLOWRATE PRODUCTION FRACTIONATION
F4: Periode 01/31 Desember 2024
F5: TANGGAL | G5: CAPACITY (Kg) | H5: REMARKS | I5: Down time | M5: Tph
I6: Stop | J6: Slow | K6: % | AE6: 17 | AF6: 18 | AG6: 19 | AH6: 20 | AI6: 21 | AJ6: 22 | AK6: 23 | AL6: 24 | AM6: 25 | AN6: 26 | AO6: 27 | AP6: 28 | AQ6: 29 | AR6: 30 | AS6: 31
F7: 1 | H7: STOP PLANT | J7: =(2500-(G7/1000))/105 -> 23.809524 | K7: =G7/2000/1000 -> 0 | M7: =(G7/1000)/24 -> 0 | O7: =249.262+270.9 -> 520.162 | P7: =1356.367+39.742 -> 1396.109 | Q7: =1086.521+50.6 -> 1137.121 | R7: =1353.558+373.309 -> 1726.867 | S7: 1942.746 | T7: 1868.212 | U7: 2057.011 | V7: 1781.844 | W7: 1250.764 | X7: 1613.486 | Y7: 1325.077 | Z7: =66.442+571.568 -> 638.01 | AA7: =815.429 -> 815.429 | AB7: =352.234+731.627 -> 1083.861 | AC7: =1626.002+13.213 -> 1639.215 | AD7: 2094.791 | AE7: 2075.375 | AF7: 2008.804 | AG7: 1946.712 | AH7: 1998.939 | AI7: =1623.839+281.468 -> 1905.307 | AJ7: 1610.024 | AK7: =1135.181+98.368 -> 1233.549 | AL7: =958.893+543.852 -> 1502.745 | AM7: 2043.15 | AN7: 1762.642 | AO7: 2170.336 | AP7: =1181.38+463.711 -> 1645.091 | AQ7: 219.474 | AR7: =48.153+1225.968+107.3 -> 1381.421
F8: 2 | H8: STOP PLANT | J8: =(2500-(G8/1000))/105 -> 23.809524 | K8: =G8/2000/1000 -> 0 | M8: =(G8/1000)/24 -> 0
F9: 3 | H9: STOP PLANT | J9: =(2500-(G9/1000))/105 -> 23.809524 | K9: =G9/2000/1000 -> 0 | M9: =(G9/1000)/24 -> 0
F10: 4 | H10: STOP PLANT | J10: =(2500-(G10/1000))/105 -> 23.809524 | K10: =G10/2000/1000 -> 0 | M10: =(G10/1000)/24 -> 0
F11: 5 | H11: STOP PLANT | J11: =(2500-(G11/1000))/105 -> 23.809524 | K11: =G11/2000/1000 -> 0 | M11: =(G11/1000)/24 -> 0
F12: 6 | H12: STOP PLANT | J12: =(2500-(G12/1000))/105 -> 23.809524 | K12: =G12/2000/1000 -> 0 | M12: =(G12/1000)/24 -> 0
F13: 7 | H13: STOP PLANT | J13: =(2500-(G13/1000))/105 -> 23.809524 | K13: =G13/2000/1000 -> 0 | M13: =(G13/1000)/24 -> 0
F14: 8 | H14: STOP PLANT | J14: =(2500-(G14/1000))/105 -> 23.809524 | K14: =G14/2000/1000 -> 0 | M14: =(G14/1000)/24 -> 0
F15: 9 | H15: STOP PLANT | J15: =(2500-(G15/1000))/105 -> 23.809524 | K15: =G15/2000/1000 -> 0 | M15: =(G15/1000)/24 -> 0
F16: 10 | G16: 178924 | H16: Slow flow rate due to Olein IV 56 process | J16: =(2500-(G16/1000))/105 -> 22.105486 | K16: =G16/2000/1000 -> 0.089462 | M16: =(G16/1000)/24 -> 7.4551667
F17: 11 | G17: 698398 | H17: Slow flow rate due to Olein IV 56 process & IV 58 process | J17: =(2500-(G17/1000))/105 -> 17.158114 | K17: =G17/2000/1000 -> 0.349199 | M17: =(G17/1000)/24 -> 29.099917
F18: 12 | G18: 1023384 | H18: Slow flow rate due to Olein IV 56 process & IV 58 process | J18: =(2500-(G18/1000))/105 -> 14.06301 | K18: =G18/2000/1000 -> 0.511692 | M18: =(G18/1000)/24 -> 42.641
F19: 13 | G19: 1366180 | H19: Slow flow rate due to Olein IV 58 process | J19: =(2500-(G19/1000))/105 -> 10.798286 | K19: =G19/2000/1000 -> 0.68309 | M19: =(G19/1000)/24 -> 56.924167
F20: 14 | G20: 1943182 | H20: Slow flow rate due to Olein IV 58 process | J20: =(2500-(G20/1000))/105 -> 5.3030286 | K20: =G20/2000/1000 -> 0.971591 | M20: =(G20/1000)/24 -> 80.965917
F21: 15 | G21: 2119169 | H21: Slow flow rate due to Olein IV 58 process | J21: =(2500-(G21/1000))/105 -> 3.6269619 | K21: =G21/2000/1000 -> 1.0595845 | M21: =(G21/1000)/24 -> 88.298708
F22: 16 | G22: 1102637 | H22: Slow flow rate due to Olein IV 56 process & IV 58 process | J22: =(2500-(G22/1000))/105 -> 13.308219 | K22: =G22/2000/1000 -> 0.5513185 | M22: =(G22/1000)/24 -> 45.943208
F23: 17 | G23: 2268595 | H23: Slow flow rate due to Olein IV 56 process & IV 58 process | J23: =(2500-(G23/1000))/105 -> 2.2038571 | K23: =G23/2000/1000 -> 1.1342975 | M23: =(G23/1000)/24 -> 94.524792
F24: 18 | G24: 2916949 | H24: Slow flow rate due to Olein IV 56 process | J24: =(2500-(G24/1000))/105 -> -3.9709429 | K24: =G24/2000/1000 -> 1.4584745 | M24: =(G24/1000)/24 -> 121.53954
F25: 19 | G25: 1399735 | H25: Slow flow rate due to Olein IV 56 process & IV 58 process | J25: =(2500-(G25/1000))/105 -> 10.478714 | K25: =G25/2000/1000 -> 0.6998675 | M25: =(G25/1000)/24 -> 58.322292
F26: 20 | G26: 228179 | H26: Slow flow rate due to Olein IV 58 process | J26: =(2500-(G26/1000))/105 -> 21.63639 | K26: =G26/2000/1000 -> 0.1140895 | M26: =(G26/1000)/24 -> 9.5074583
F27: 21 | G27: 546176 | H27: Slow flow rate due to Olein IV 58 process | J27: =(2500-(G27/1000))/105 -> 18.607848 | K27: =G27/2000/1000 -> 0.273088 | M27: =(G27/1000)/24 -> 22.757333
... F37: 31 | G37: 0 | H37: STOP PLANT | J37: =(2500-(G37/1000))/105 -> 23.809524 | K37: =G37/2000/1000 -> 0 | M37: =(G37/1000)/24 -> 0
F38: TOTAL | G38: =SUM(G7:G37) -> 24096837 | I38: =SUM(I7:I36) -> 0 | J38: =SUM(J7:J37) -> 508.60155 | M38: =AVERAGE(M7:M37) -> 32.388222
G40: Summary
G41: 1. Slow flow rate due to Space Tank High | I41: 0 | J41: hours
G42: 2. Slow flow rate due to Olein IV 60 process | I42: =SUM(J34) -> 22.425143 | J42: hours
G43: 3. Slow flow rate due to Olein IV 57 process | I43: 0 | J43: hours
G44: 4. Slow Flow rate terkait material sortage & menyesuaikan | I44: 0 | J44: hours
G45: 5. Downtime due to Start/Stop Up Plant | I45: 0 | J45: hours
G46: 6. Running Normal Plant | I46: 0 | J46: hours
G47: 7. Stop Plant due to Preventive Maintenance Plant | I47: 0 | J47: hours
G48: 8. Energizing PMG II | I48: 0 | J48: hours
G49: 9. Zero Suplay Gas (Problem Pertagas) | I49: 0 | J49: hours
G50: 10. Slow flow rate due to Olein IV 58 process | I50: =SUM(J19,J20,J21,J26,J27,J28,J29,J30,J31) -> 99.074638 | J50: hours
G51: 11. STOP PLANT | I51: =SUM(J37,J36,J35,J15,J14,J13,J12,J11,J10,J9,J8,J7) -> 285.71429 | J51: hours
G52: 12.Slow flow rate due to Olein IV 56 process | I52: =SUM(J16,J24,J33) -> 39.816895 | J52: hours
G53: 13. Slow flow rate due to Olein IV 56 process & IV 57 process | I53: 0 | J53: hours
G54: 14. Slow flow rate due to Olein IV 56 process & IV 58 process | I54: =SUM(J17,J18,J22,J23,J25,J32) -> 61.57059 | J54: hours
G55: Total | I55: =SUM(I41:I54) -> 508.60155 | J55: hours
G56: Note : Kapasitas 2500 TPD
E64: Prepared by, | H64: Checked by, | J64: Approved by,
E68: Bany Subana | H68: Reza P. Panjaitan | J68: Sudarianto
E69: Admin. Process | H69: Supervisor Produksi | J69: Jr. Manager Produksi

Sheet 2024
C2: PRODUCTION REPORT 2024
B4: No | C4: ITEM | D4: Budget / Norma | E4: UoM | F4: MONTHLY REPORT | T4: Yearly Report | U4: Yearly Report RKAP (Budget) | V4: Yearly Report RKAP
F5: JANUARI | G5: FEBRUARI | H5: MARET | I5: APRIL | J5: MEI | K5: JUNI | L5: JULI | M5: AGUSTUS | N5: SEPTEMBER | O5: OKTOBER | P5: NOVEMBER | Q5: DESEMBER | R5: DESEMBER | T5: TOTAL (Kg) | U5: TOTAL (Kg) | V5: TOTAL (%)
B6: 1 | C6: PRODUCTION | T6: Production | U6: Production | V6: Production | DG6: 29 | DH6: 30 | DI6: 31
C7: Refinery | T7: Refinery | U7: Refinery | V7: Refinery | DE7: CPO Olah | DF7: Kg | DG7: 1971320 | DH7: 2015120 | DI7: 2015230 | AIU7: Sounding | AIV7: Production | AIW7: Diff
C8: Running Days | E8: Day | F8: 18 | G8: 11 | H8: 27 | I8: 22 | J8: 27 | K8: 18 | L8: 22 | M8: 28 | N8: 27 | O8: 28 | P8: 22 | Q8: ='Desember 2024'!AM6 -> 23 | R8: ='[20]Desember 24'!AL9 -> 0 | T8: =SUM(F8:R8) -> 273 | U8: 231 | V8: =T8/U8*100 -> 118.18182 | X8: =T8-Q8 -> 250 | OR8: Poram | AEE8: 14 Juni | AEF8: 15 Juni | AIT8: CPO | AIU8: 11008948 | AIV8: =T11 -> 206162448 | AIW8: =AIU8-AIV8 -> -195153500
C9: Ratio Run CPO | F9: 17.46 | G9: ='[20]Februari 24'!AL10 -> 17.224767 | H9: ='[20]Maret 24'!AL10 -> 4.5497713 | I9: ='[21]April - 24'!$AK$11 -> 0 | J9: ='[22]Mei - 24'!$AL$11 -> 0 | K9: ='[23]Juni - 24'!$AL$11 -> 13.078035 | L9: ='[24]Juli - 2024 ( Revisi )'!$AL$8 -> 23.454544 | M9: ='[25]Agustus - 2024'!$AN$8 -> 0 | N9: ='[26]September - 2024'!$AM$8 -> 0 | O9: ='[27]Oktober- 2024'!$AM$8 -> 55.059061 | P9: 33666529 | Q9: ='Desember 2024'!AM8 -> 0.43952621 | R9: ='[20]Desember 24'!AL10 -> 0
C10: Utilitas CPO | F10: =F11/F14*100 -> 18.288923 | G10: =G11/G14*100 -> 18.044994 | H10: =H11/H14*100 -> 43.450394 | I10: =I11/I14*100 -> 24.340125 | J10: =J11/J14*100 -> 42.665478 | K10: =K11/K14*100 -> 24.530983 | L10: =L11/L14*100 -> 43.994607 | M10: =M11/M14*100 -> 63.465348 | ... O10: =O11/O14*100 -> 64.566129 | P10: 42.102025 | Q10: =Q11/Q14*100 -> 69.508944 | R10: =R11/R14*100 -> #DIV/0! | T10: =AVERAGE(F10:Q10) -> 43.424473
C11: CPO Consume Total | D11: 701400000 | E11: Kg | F11: 11906089 | G11: 11747291 | H11: 16983890 | I11: 8849826 | J11: 15512741 | K11: 8919220 | L11: 15995999 | M11: 23075366 | N11: 24046290 | O11: 23475599 | P11: 20377380 | Q11: ='Desember 2024'!AM9 -> 25272757 | R11: ='[20]Desember 24'!AL11 -> 0 | T11: =SUM(F11:Q11) -> 206162448 | U11: 421374000 | V11: =T11/U11 -> 0.48926238 | AX11: =T11/D11 -> 0.29392992 | DE11: HP Boiler | DF11: mmbtu | DG11: 251.19642 | DH11: 257.91391 | DI11: 251.51265 | OO11: 26946.108 | OP11: 17383.234 | OR11: RBDPO Olah | AEE11: =35.8500000000058*1000 -> 35850 | AIT11: PFAD | AIU11: 566885 | AIV11: =T20 -> 8966931 | AIW11: =AIU11-AIV11 -> -8400046
C12: CPO Consume Poram | E12: Kg | F12: 10284033 | G12: 10885811 | H12: 16067553 | I12: 8849826 | J12: 15512741 | K12: 8919220 | L12: 15995999 | M12: 22890671 | N12: =N11-N13 -> 24046290 | O12: 23419757 | P12: 20377380 | Q12: ='Desember 2024'!AM9 -> 25272757 | R12: ='[20]Desember 24'!AL12 -> #DIV/0! | T12: =SUM(F12:Q12) -> 2.0252204e+08
C13: CPO Consume Brand | E13: Kg | F13: 1622056.5 | G13: 861480.39 | H13: 916336.51 | I13: 0 | J13: 0 | K13: 0 | L13: 0 | M13: 184695 | N13: 0 | O13: 55842.105 | Q13: 0 | R13: ='[20]Desember 24'!AL13 -> #DIV/0! | T13: =SUM(F13:Q13) -> 3640410.5 | AX13: =AW13/Q13 -> #DIV/0!
C14: Budget CPO Olah | E14: Kg | F14: 65100000 | G14: 65100000 | H14: 39088000 | I14: 36359000 | J14: 36359000 | K14: 36359000 | L14: 36359000 | M14: 36359000 | N14: 36359000 | O14: ='[27]Oktober- 2024'!$E$9 -> 36359000 | P14: ='[27]Oktober- 2024'!$E$9 -> 36359000 | Q14: ='Desember 2024'!E9 -> 36359000 | T14: =SUM(F14:Q14) -> 496519000
C15: - FFA | D15: 5 | E15: % | F15: 4.38 | G15: 4.5590909 | H15: 4.135 | I15: 4.11 | J15: 3.859375 | K15: 4.248125 | L15: 3.8848485 | M15: 3.9614881 | N15: 3.6441975 | O15: ='[27]Oktober- 2024'!$AM$13 -> 3.8133333 | P15: 3.8712121 | Q15: ='Desember 2024'!AM13 -> 3.3336957 | R15: ='[20]Desember 24'!AL14 -> #DIV/0! | T15: =AVERAGE(F15:Q15) -> 3.9833638 | U15: =AVERAGE(G15:S15) -> #DIV/0! | V15: =AVERAGE(H15:T15) -> #DIV/0! | DE15: Steam Ref | DF15: Kg | DG15: 182230 | DH15: 190070 | DI15: 197800 | OO15: =T11/1000 -> 206162.45 | OP15: =(T25+T48+T34)/1000 -> 60978.7 | OR15: =SUM(OR16:OR17) -> #REF! | AGV15: 2000
C16: - Moist & Impurities | D16: 0.5 | E16: % | F16: 0.42 | G16: 0.43545455 | H16: 0.42375 | I16: 0.42 | J16: 0.431875 | K16: 0.45375 | L16: 0.41795455 | M16: 0.43083333 | N16: 0.41401235 | O16: ='[27]Oktober- 2024'!$AM$14 -> 0.43333333 | P16: 0.43416667 | Q16: ='Desember 2024'!AM14 -> 0.36391304 | R16: ='[20]Desember 24'!AL15 -> #DIV/0! | T16: =AVERAGE(F16:Q16) -> 0.42325357 | U16: =AVERAGE(G16:S16) -> #DIV/0! | V16: =AVERAGE(H16:T16) -> #DIV/0! | DF16: Kg/MT | DG16: =DG15/(DG7/1000) -> 92.440598 | DH16: =DH15/(DH7/1000) -> 94.321926 | DI16: =DI15/(DI7/1000) -> 98.152568 | OR16: =#REF!/1000 -> #REF! | OS16: =OR16/OR15*100 -> #REF! | AGU16: 0.942 | AGV16: =AGU16*AGV15 -> 1884 | AGW16: Refinery | AIT16: Olein IV 56 | AIU16: 9594130 | AIV16: =T26 -> 47460462 | AIW16: =AIU16-AIV16 -> -37866332
C17: - DOBI | D17: 2,20 Min | E17: % | F17: 2.21 | G17: 2.2127273 | H17: 2.2104167 | I17: 2.21 | J17: 2.21 | K17: 2.21 | L17: 2.1131818 | M17: 2.2129286 | N17: 2.27 | O17: ='[27]Oktober- 2024'!$AM$15 -> 22.02 | P17: 2.015 | Q17: ='Desember 2024'!AM15 -> 1.8452174 | R17: ='[20]Desember 24'!AL16 -> #DIV/0! | T17: =AVERAGE(F17:Q17) -> 3.8116226 | U17: =AVERAGE(G17:S17) -> #DIV/0! | V17: =AVERAGE(H17:T17) -> #DIV/0! | OO17: =SUM(OO15:OO16) -> 206162.45 | OP17: =SUM(OP15:OP16) -> 60978.7 | OR17: =#REF!/1000 -> #REF! | OS17: =OR17/OR15*100 -> #REF! | AGU17: 0.05 | AGV17: =AGU17*AGV15 -> 100 | AIT17: Stearin | AIU17: 2161151 | AIV17: =T27 -> 9963890 | AIW17: =AIU17-AIV17 -> -7802739
C18: Product | T18: Product | U18: Product | V18: Product | OO18: =OO17/OO11*100 -> 765.09175 | OP18: =OP17/OP11*100 -> 350.79032 | AEG18: Product OIP | AEQ18: Juni | AER18: Sisa Product OIP
C19: RbdPO | D19: =D56%*D11 -> 660718800 | E19: Kg | F19: 11255730 | G19: 11075536 | H19: 16117978 | I19: 8393524 | J19: 14773343 | K19: 8432668 | L19: 14396709 | M19: 22151806 | N19: 22783491 | O19: 22272728 | P19: 19958156 | Q19: ='Desember 2024'!AM19 -> 24389568 | R19: ='[20]Desember 24'!AL18 -> 0 | T19: =SUM(F19:Q19) -> 1.9600124e+08 | U19: 399336000 | V19: =T19/U19*100 -> 49.081785 | AX19: =AX20/D19 -> 0.29766454 | DE19: Tahun 2021 | AEE19: 136360 | AEF19: 109340 | AEG19: =SUM(AEE19:AEF19) -> 245700 | AEQ19: 34157.88 | AER19: =AEG19-AEQ19 -> 211542.12 | AGV19: =AGV16 -> 1884
C20: PFAD | D20: =D57%*D11 -> 35070000 | E20: Kg | F20: 568791 | G20: 594383 | H20: 753150 | I20: 419494 | J20: 630157 | K20: 432588 | L20: 713632 | M20: 947460 | N20: 998518 | O20: 949170 | P20: 870458 | Q20: ='Desember 2024'!AM20 -> 1089130 | R20: ='[20]Desember 24'!AL19 -> 0 | T20: =SUM(F20:Q20) -> 8966931 | U20: 19024000 | V20: =T20/U20*100 -> 47.134835 | AX20: =T25+T29+T34+T48+T38 -> 196672560 | DE20: Items | DG20: Agustus | DH20: Oktober | OO20: =OO11-OO17 -> -179216.34 | OP20: =OP11-OP17 -> -43595.466 | OR20: Olein IV 58 | OS20: 0 | PE20: 564.70507 | PF20: =OS20/PE20*100 -> 0 | AEE20: 13800 | AEF20: 2800 | AEG20: =SUM(AEE20:AEF20) -> 16600 | AEQ20: 1469.85 | AER20: =AEG20-AEQ20 -> 15130.15 | AGU20: 0.75 | AGV20: =AGU20*AGV19 -> 1413
C21: Fractionation
C22: Total Filling Crystalizer ( Feed ) | D22: =399289.3*1000 -> 399289300 | E22: Kg | F22: =F23 -> 13630524 | G22: =G23 -> 8090413 | H22: =H23 -> 16273198 | I22: =I23 -> 9676196 | J22: =J23 -> 14816948 | K22: =K23 -> 7764784 | L22: =L23 -> 11846463 | M22: =M23 -> 24206356 | N22: 22592969 | O22: 20122000 | P22: 21737836 | Q22: ='Desember 2024'!AM28 -> 24096837 | T22: =SUM(F22:Q22) -> 194854524
C23: Total Proses RBDPO | E23: Kg | F23: =SUM(F25,F29,F34,F38,F48) -> 13630524 | G23: =SUM(G25,G29,G34,G38,G48) -> 8090413 | H23: =SUM(H25,H29,H34,H38,H48) -> 16273198 | I23: =SUM(I25,I29,I34,I38,I48) -> 9676196 | J23: =SUM(J25,J29,J34,J38,J48) -> 14816948 | K23: =SUM(K25,K29,K34,K38,K48) -> 7764784 | L23: =SUM(L25,L29,L34,L38,L48) -> 11846463 | M23: =SUM(M25,M29,M34,M38,M48) -> 24206356 | N23: =SUM(N25,N29,N34,N38,N48) -> 23189025 | O23: ='[27]Oktober- 2024'!$AM$25 -> 3069861 | P23: 22537659 | Q23: ='Desember 2024'!AM28 -> 24096837 | T23: =SUM(F23:Q23) -> 179198264
C24: Fractionation OLEIN IV 56 | T24: Olein IV 56 | U24: Olein IV 56 | V24: Olein IV 56 | DG24: 24 | DH24: 2 | DI24: 3 | OR24: Olein IV 60 | OS24: =80.53776+PF34 -> 120.78492 | PE24: 4695.7554 | PF24: =OS24/PE24*100 -> 2.5722149 | AGU24: 0.25 | AGV24: =AGU24*AGV19 -> 471
C25: RBDPO Consume | D25: =SUM(D26:D27) -> 0 | E25: Kg | F25: 2379082 | G25: 50570 | H25: 1699905 | I25: ='[20]April 24'!AL21 -> 0 | J25: 0 | K25: 0 | L25: 160400 | M25: 14223412 | N25: 16566545 | O25: 9370708 | P25: 5970222 | Q25: ='Desember 2024'!AM31 -> 7003508 | R25: =R26+R27 -> 0 | T25: =T26+T27 -> 57424352 | U25: =U26+U27 -> 87311000 | V25: =T25/U25*100 -> 65.769894 | DE25: CPO Olah | DF25: Kg | DG25: 2000530 | DH25: 2005167 | DI25: 2025879 | AEE25: =95.28%*AEE11 -> 34157.88 | AEG25: =AEE19-AEQ19 -> 102202.12 | AIQ25: CPO Feed - Sounding
C26: OLEIN IV 56 | E26: Kg | F26: 1982807 | G26: 42320 | H26: 1394887 | I26: ='[20]April 24'!AL22 -> 0 | J26: 0 | K26: 0 | L26: 135300 | M26: 11670227 | N26: 13789795 | O26: 7870678 | P26: 4990754 | Q26: ='Desember 2024'!AM32 -> 5583694 | R26: ='[20]Desember 24'!AL22 -> 0 | T26: =SUM(F26:Q26) -> 47460462 | U26: 71627000 | V26: =T26/U26*100 -> 66.260575 | DE26: HP Boiler | DF26: mmbtu | DG26: 255.53619 | DH26: 255.09239 | DI26: 260.82455 | OO26: =#REF!/1000 -> #REF! | OR26: INL 900 ml | OS26: 0 | PE26: 9.75348 | PF26: =(OS26*PE26)/1000 -> 0 | AEE26: =4.1%*AEE11 -> 1469.85 | AEG26: =AEE20-AEQ20 -> 12330.15
C27: STEARIN | E27: Kg | F27: 396275 | G27: 8250 | H27: 305018 | I27: ='[20]April 24'!AL23 -> 0 | J27: 0 | K27: 0 | L27: 25100 | M27: 2553185 | N27: 2776750 | O27: 1500030 | P27: 979468 | Q27: ='Desember 2024'!AM33 -> 1419814 | R27: ='[20]Desember 24'!AL23 -> 0 | T27: =SUM(F27:Q27) -> 9963890 | U27: 15684000 | V27: =T27/U27*100 -> 63.52901 | DE27: Steam Ref | DF27: Kg | DG27: 146000 | DH27: 151100 | DI27: 152900 | OO27: 1796 | OR27: Salvaco 1L | OS27: 1262 | PE27: 10.86 | PF27: =(OS27*PE27)/1000 -> 13.70532 | AIQ27: Report Prod
C28: Fractionation OLEIN IV 57 ( Bulk ) | T28: Olein IV 57 ( Bulk ) | U28: Olein IV 57 ( Bulk ) | V28: Olein IV 57 ( Bulk )
C29: RBDPO Consume | E29: Kg | F29: 2827867 | G29: 0 | H29: 0 | I29: 60502 | J29: 0 | K29: 0 | L29: 0 | M29: 0 | N29: 0 | O29: ='[27]Oktober- 2024'!$AM$32 -> 0 | Q29: ='Desember 2024'!AM35 -> 0 | R29: =R30+R31 -> 0 | T29: =T30+T31 -> 2888369 | U29: =U30+U31 -> 5121000 | V29: =T29/U29*100 -> 56.402441 | AX29: =T29+T34 -> 4098296
C30: OLEIN IV 57 | E30: Kg | F30: 2230587 | G30: 0 | H30: 0 | I30: 45478 | J30: 0 | K30: 0 | L30: 0 | M30: 0 | N30: 0 | O30: ='[27]Oktober- 2024'!$AM$33 -> 0 | Q30: ='Desember 2024'!AM36 -> 0 | R30: ='[20]Desember 24'!AL26 -> 0 | T30: =SUM(F30:Q30) -> 2276065 | U30: 3934000 | V30: =T30/U30*100 -> 57.856253 | AX30: =T30+T35 -> 3177959
C31: STEARIN | E31: Kg | F31: 597280 | G31: 0 | H31: 0 | I31: 15024 | J31: 0 | K31: 0 | L31: 0 | M31: 0 | N31: 0 | O31: ='[27]Oktober- 2024'!$AM$34 -> 0 | Q31: ='Desember 2024'!AM37 -> 0 | R31: ='[20]Desember 24'!AL27 -> 0 | T31: =SUM(F31:Q31) -> 612304 | U31: 1187000 | V31: =T31/U31*100 -> 51.584162 | AX31: =T31+T36 -> 920337
C32: Fractionation OLEIN IV 57 ( Retail ) | T32: Olein IV 57 ( Retail ) | U32: Olein IV 57 ( Retail ) | V32: Olein IV 57 ( Retail ) | DF32: Kg/MT | DG32: =DG27/(DG25/1000) -> 72.98066 | DH32: =DH27/(DH25/1000) -> 75.35532 | DI32: =DI27/(DI25/1000) -> 75.473412 | OO32: =OO26/OO27*100 -> #REF! | OR32: Salvaco 2L | OS32: 2444 | PE32: 10.86 | PF32: =(OS32*PE32)/1000 -> 26.54184 | AIQ32: Diff
C33: CPO Consume | E33: Kg | F33: 0 | G33: 440053.75 | H33: 793075.77 | I33: ='[20]April 24'!AL29 -> 0 | J33: 0 | K33: 0 | L33: 0 | M33: 0 | N33: 0 | O33: ='[27]Oktober- 2024'!$AM$36 -> 0 | Q33: ='Desember 2024'!AM39 -> 0 | R33: ='[20]Desember 24'!AL29 -> 0 | T33: =SUM(F33:Q33) -> 1233129.5 | U33: =U34/U56% -> 32338304 | V33: =(T33/U33)*100 -> 3.8132164 | DF33: Kg/MT | DG33: =DG27/(DG20/1000) -> #VALUE! | DH33: =DI27/(DH20/1000) -> #VALUE! | DI33: =#REF!/(DI20/1000) -> #REF!
C34: RBDPO Brand Consume | D34: =SUM(D35:D36) -> 0 | E34: Kg | F34: 0 | G34: 417044 | H34: 751933 | I34: =I35+I36 -> 0 | J34: 0 | K34: 0 | L34: 0 | M34: 0 | N34: 40950 | O34: ='[27]Oktober- 2024'!$AM$37 -> 0 | Q34: ='Desember 2024'!AM40 -> 0 | R34: =R35+R36 -> 0 | T34: =T35+T36 -> 1209927 | U34: =U35+U36 -> 30647000 | V34: =(T34/U34)*100 -> 3.947946 | PF34: =SUM(PF27:PF32) -> 40.24716
C35: OLEIN IV 57 ( Retail ) | E35: Kg | F35: 0 | G35: 327115 | H35: 543979 | I35: ='[20]April 24'!AL31 -> 0 | J35: 0 | K35: 0 | L35: 0 | M35: 0 | N35: 30800 | O35: ='[27]Oktober- 2024'!$AM$38 -> 0 | Q35: ='Desember 2024'!AM41 -> 0 | R35: ='[20]Desember 24'!AL31 -> 0 | T35: =SUM(F35:Q35) -> 901894 | U35: 23002000 | V35: =T35/U35*100 -> 3.9209373
C36: STEARIN | E36: Kg | F36: 0 | G36: 89929 | H36: 207954 | I36: ='[20]April 24'!AL32 -> 0 | J36: 0 | K36: 0 | L36: 0 | M36: 0 | N36: 10150 | O36: ='[27]Oktober- 2024'!$AM$39 -> 0 | Q36: ='Desember 2024'!AM42 -> 0 | R36: ='[20]Desember 24'!AL32 -> 0 | T36: =SUM(F36:Q36) -> 308033 | U36: 7645000 | V36: =T36/U36*100 -> 4.0292086
C37: Fractionation OLEIN IV 58 ( BULK ) | T37: Olein IV 58 | U37: Olein IV 58 | V37: Olein IV 58
C38: RBDPO Consume | E38: Kg | F38: 6885934 | G38: 7224129 | H38: 13704210 | I38: 9615694 | J38: 14816948 | K38: 7764784 | L38: 11686063 | M38: 9837344 | N38: 6581530 | O38: 10628161 | P38: 16567437 | Q38: ='Desember 2024'!AM44 -> 16973017 | R38: =R39+R40 -> 0 | T38: =T39+T40 -> 132805491 | U38: =U39+U40 -> 249961000 | V38: =T38/U38*100 -> 53.130485
C39: OLEIN IV 58 ( Bulk ) | E39: Kg | F39: 4847146 | G39: 5178274 | H39: 8651956 | I39: 6783108 | J39: 10840932 | K39: 5498655 | L39: 8627479 | M39: 6991936 | N39: 4788598 | O39: 7897790 | P39: 12573252 | Q39: ='Desember 2024'!AM45 -> 11987575 | R39: ='[20]Desember 24'!AL35 -> 0 | T39: =SUM(F39:Q39) -> 94666701 | U39: 175000000 | V39: =T39/U39*100 -> 54.095258
C40: STEARIN | E40: Kg | F40: 2038788 | G40: 2045855 | H40: 5052254 | I40: 2832586 | J40: 3976016 | K40: 2266129 | L40: 3578824 | M40: 2845408 | N40: 1792932 | O40: 2730371 | P40: 3994185 | Q40: ='Desember 2024'!AM46 -> 4985442 | R40: ='[20]Desember 24'!AL36 -> 0 | T40: =SUM(F40:Q40) -> 38138790 | U40: 74961000 | V40: =T40/U40*100 -> 50.878177
C41: Fractionation OLEIN IV 58 ( Retail )
C42: CPO Consume | E42: Kg | O42: 55842.105
C43: RBDPO Consume | E43: Kg | O43: 53050
C44: OLEIN IV 58 | E44: Kg | O44: 38000
C45: STEARIN | E45: Kg | O45: 15050
C46: Fractionation OLEIN IV 60 | T46: Olein IV 60 | U46: Olein IV 60 | V46: Olein IV 60
C47: CPO Consume | E47: Kg | F47: 1622056.5 | G47: 421426.65 | H47: 123260.75 | I47: 0 | J47: 0 | K47: 0 | L47: 0 | M47: 0 | N47: 0 | O47: ='[27]Oktober- 2024'!$AM$50 -> 0 | Q47: ='Desember 2024'!AM53 -> 0 | T47: =SUM(F47:Q47) -> 2166743.9 | U47: =U48/U56% -> 25913273 | V47: =T47/U47*100 -> 8.3615215
C48: RBDPO Brand Consume | D48: =SUM(D50:D51) -> 0 | E48: Kg | F48: 1537641 | G48: 398670 | H48: 117150 | I48: 0 | J48: 0 | K48: 0 | L48: 0 | M48: 145600 | N48: 0 | Q48: ='Desember 2024'!AM54 -> 145360 | R48: =R50+R51 -> 0 | T48: =T50+T51 -> 2344421 | U48: =U50+U51 -> 24558000 | V48: =T48/U48*100 -> 9.5464655 | DG48: 2136
C49: OLEIN IV 60 Bulk | E49: Kg | F49: 0 | G49: 0 | H49: 0 | I49: 0 | J49: 0 | K49: 0 | L49: 0 | M49: 0 | N49: 0 | R49: ='[20]Desember 24'!AL40 -> 0 | T49: =SUM(F49:Q49) -> 0 | U49: =SUM(F49:R49) -> 0 | V49: =SUM(H49:T49) -> 0
C50: OLEIN IV 60 Salvaco | E50: Kg | F50: 923976 | G50: 248300 | H50: 70300 | I50: 0 | J50: 0 | K50: 0 | L50: 0 | M50: 87600 | N50: 0 | Q50: ='Desember 2024'!AM55 -> 87260 | R50: ='[20]Desember 24'!AL41 -> 0 | T50: =SUM(F50:Q50) -> 1417436 | U50: 14736000 | V50: =T50/U50*100 -> 9.6188654 | DG50: 1796
C51: SOFT STEARIN | E51: Kg | F51: 613665 | G51: 150370 | H51: 46850 | I51: 0 | J51: 0 | K51: 0 | L51: 0 | M51: 58000 | N51: 0 | Q51: ='Desember 2024'!AM56 -> 58100 | R51: ='[20]Desember 24'!AL42 -> 0 | T51: =SUM(F51:Q51) -> 926985 | U51: 9822000 | V51: =T51/U51*100 -> 9.4378436 | DG51: =DG48/DG50*100 -> 118.93096
C52: Ratio Run RBDPO | F52: 17.42364 | G52: 13.049053 | H52: 26.247094 | I52: 15.606768 | J52: 23.898303 | K52: 12.523845 | L52: 0 | M52: 0 | N52: 0 | O52: =(O38+O34+O29+O25)/(60000000) -> 0.33331448 | P52: =(P38+P34+P29+P25)/(60000000) -> 0.37562765 | Q52: =(Q38+Q34+Q29+Q25)/(60000000) -> 0.39960875 | R52: =(R38+R34+R29+R25)/(60000000) -> 0 | T52: =+AVERAGE(F52:Q52) -> 9.1547712
C53: Utilitas RBDPO | F53: =(F48+F38+F34+F30+F26)/F54*100 -> 20.606822 | G53: =(G48+G38+G34+G30+G26)/G54*100 -> 13.179402 | H53: =(H48+H38+H34+H30+H26)/H54*100 -> 43.367168 | J53: =(J48+J38+J34+J30+J26)/J54*100 -> 43.260937 | K53: =(K48+K38+K34+K30+K26)/K54*100 -> 22.670784 | L53: =(L48+L38+L34+L30+L26)/L54*100 -> 34.306585 | M53: =($M$48+$M$38+$M$34+$M$30+$M$25)/$M$54*100 -> 70.248871 | N53: =($N$48+$N$38+$N$34+$N$30+$N$26)/$N$54*100 -> 59.23813 | O53: =(O48+O38+O34+O29+O25)/O54*100 -> 58.390555 | P53: =(P48+P38+P34+P29+P25)/P54*100 -> 65.803042 | Q53: =(Q48+Q38+Q34+Q30+Q26)/Q54*100 -> 65.88331 | R53: =(R48+R38+R34+R30+R26)/R54*100 -> 0 | T53: =+AVERAGE(F53:Q53) -> 45.177783
C54: Budget RBDPO | F54: 61324200 | G54: 61324200 | H54: 36820896 | I54: 34250178 | J54: 34250178 | K54: 34250178 | L54: 34458000 | M54: 34458000 | N54: 34458000 | O54: ='[23]Juni - 24'!$D$19 -> 34250178 | P54: ='[23]Juni - 24'!$D$19 -> 34250178 | Q54: ='Desember 2024'!E19 -> 34458000 | R54: ='[23]Juni - 24'!$D$19 -> 34250178 | T54: =SUM(F54:Q54) -> 468552186
C55: YIELD | T55: Yield | U55: Yield | V55: Yield | OP55: 678
C56: RBDPO | D56: 94.2 | E56: % | F56: 94.537593 | G56: 94.281618 | H56: 94.901568 | I56: 94.843944 | J56: 95.233608 | K56: 94.544904 | L56: 90.001937 | M56: 95.997637 | N56: 94.748466 | O56: =(O19/(O11))*100 -> 94.87608 | P56: 97.942699 | Q56: =(Q19/(Q11))*100 -> 96.505371 | R56: =(R19/(R11))*100 -> #DIV/0! | T56: =(T19/(T11))*100 -> 95.07126 | U56: =(U19/(U11))*100 -> 94.769967 | OP56: 420 | OR56: =OP56/OP55*100 -> 61.946903
C57: PFAD | D57: 5 | E57: % | F57: 4.7773118 | G57: 5.0597453 | H57: 4.4344965 | I57: 4.7401384 | J57: 4.0621899 | K57: 4.8500654 | L57: 4.4613156 | M57: 4.105937 | N57: 4.1524826 | O57: =(O20/(O11))*100 -> 4.0432195 | P57: 4.2716875 | Q57: =(Q20/(Q11))*100 -> 4.3095021 | R57: =(R20/(R11))*100 -> #DIV/0! | T57: =(T20/(T11))*100 -> 4.3494492 | U57: =(U20/(U11))*100 -> 4.5147541 | OP57: =OP55-OP56 -> 258 | OR57: =OP57/OP55*100 -> 38.053097
C58: Olein IV 56 | D58: 82 | E58: % | F58: 83.343365 | G58: 83.68598 | H58: 82.056762 | I58: #DIV/0! | J58: #DIV/0! | K58: #DIV/0! | L58: 84.351621 | M58: 82.04942 | N58: 83.238811 | O58: =(O26/O25)*100 -> 83.992351 | P58: 83.594111 | Q58: =(Q26/Q25)*100 -> 79.727102 | R58: =(R26/R25)*100 -> #DIV/0! | T58: =(T26/T25)*100 -> 82.648668 | U58: =(U26/U25)*100 -> 82.036628
C59: Stearin | D59: 18 | E59: % | F59: 16.656635 | G59: 16.31402 | H59: 17.943238 | I59: #DIV/0! | J59: #DIV/0! | K59: #DIV/0! | L59: #DIV/0! | M59: 17.95058 | N59: 16.761189 | O59: =(O27/O25)*100 -> 16.007649 | P59: 16.405889 | Q59: =(Q27/Q25)*100 -> 20.272898 | R59: =(R27/R25)*100 -> #DIV/0! | T59: =(T27/T25)*100 -> 17.351332 | U59: =(U27/U25)*100 -> 17.963372
C60: Olein IV 57 ( Bulk ) | D60: 75 | E60: % | F60: 78.87878 | G60: #DIV/0! | H60: #DIV/0! | I60: 75.167763 | J60: #DIV/0! | K60: #DIV/0! | L60: #DIV/0! | M60: #DIV/0! | N60: 75.213675 | O60: =(O30/O29)*100 -> #DIV/0! | Q60: ='Desember 2024'!I63 -> #DIV/0! | R60: =(R30/R29)*100 -> #DIV/0! | T60: =(T30/T29)*100 -> 78.801047 | U60: 75
C61: Stearin | D61: 25 | E61: % | F61: 21.12122 | G61: #DIV/0! | H61: #DIV/0! | I61: 24.832237 | J61: #DIV/0! | K61: #DIV/0! | L61: #DIV/0! | M61: #DIV/0! | N61: 24.786325 | O61: =(O31/O29)*100 -> #DIV/0! | Q61: ='Desember 2024'!I64 -> #DIV/0! | R61: =(R31/R29)*100 -> #DIV/0! | T61: =(T31/T29)*100 -> 21.198953 | U61: 25
C62: Olein IV 57 ( Retail ) | D62: 75 | E62: % | F62: #DIV/0! | G62: 78.436568 | H62: 72.344079 | I62: #DIV/0! | J62: #DIV/0! | K62: #DIV/0! | L62: #DIV/0! | M62: #DIV/0! | N62: 75.213675 | O62: =O35/O34*100 -> #DIV/0! | Q62: ='Desember 2024'!AM65 -> #DIV/0! | R62: =R35/R34*100 -> #DIV/0! | T62: =(T35/T34)*100 -> 74.541191 | U62: 75
C63: Stearin | D63: 25 | E63: % | F63: #DIV/0! | G63: 21.563432 | H63: 27.655921 | I63: #DIV/0! | J63: #DIV/0! | K63: #DIV/0! | L63: #DIV/0! | M63: #DIV/0! | N63: 24.786325 | O63: =O36/O34*100 -> #DIV/0! | Q63: ='Desember 2024'!AM66 -> #DIV/0! | R63: =R36/R34*100 -> #DIV/0! | T63: =(T36/T34)*100 -> 25.458809 | U63: 25 | FN63: 95.03
C64: Olein IV 58 ( Bulk ) | D64: 70 | E64: % | F64: 70.39199 | G64: 71.680254 | H64: 63.133563 | I64: 70.542053 | J64: 73.165756 | K64: 70.815299 | L64: 70.680525 | M64: 71.075445 | N64: 72.758128 | O64: =(O39/O38)*100 -> 74.310034 | P64: 75.891352 | Q64: ='Desember 2024'!AM67 -> 70.627249 | R64: =(R39/R38)*100 -> #DIV/0! | T64: =(T39/T38)*100 -> 71.282219 | U64: 70
C65: Stearin | D65: 30 | E65: % | F65: 29.60801 | G65: 28.319746 | H65: 36.866437 | I65: 29.457947 | J65: 26.834244 | K65: 29.184701 | L65: 29.319475 | M65: 28.924555 | N65: 27.241872 | O65: =(O40/O38)*100 -> 25.689966 | P65: 24.108648 | Q65: ='Desember 2024'!AM68 -> 29.372751 | R65: =(R40/R38)*100 -> #DIV/0! | T65: =(T40/T38)*100 -> 28.717781 | U65: 30
C66: Olein IV 60 | D66: 60 | E66: % | F66: 60.090489 | G66: 62.282088 | H66: 60.008536 | I66: #DIV/0! | J66: #DIV/0! | K66: #DIV/0! | L66: #DIV/0! | M66: 60.164835 | N66: #DIV/0! | O66: =O50/O48*100 -> #DIV/0! | Q66: ='Desember 2024'!AM71 -> 60.03027 | R66: =R50/R48*100 -> #DIV/0! | T66: =(T50/T48)*100 -> 60.45996 | U66: =U50/U48*100 -> 60.004886 | FN66: 4.23 | OR66: =OR67/94.2% -> 1307.8556 | OS66: MT CPO
C67: Soft Stearin | D67: 40 | E67: % | F67: 39.909511 | G67: 37.717912 | H67: 39.991464 | I67: #DIV/0! | J67: #DIV/0! | K67: #DIV/0! | L67: #DIV/0! | M67: 39.835165 | N67: #DIV/0! | O67: =O51/O48*100 -> #DIV/0! | Q67: ='Desember 2024'!AM72 -> 39.96973 | R67: =R51/R48*100 -> #DIV/0! | T67: =(T51/T48)*100 -> 39.54004 | U67: =U51/U48*100 -> 39.995114 | FN67: =100-FN63-FN66 -> 0.74 | OR67: =22*56 -> 1232 | OS67: MT RBDPO Brand
B68: 3 | C68: CHEMICAL CONSUMABLE | T68: Chemical | U68: Chemical | V68: Chemical | OR68: =16.5*OR66 -> 21579.618
C69: Bleaching Earth (BE) to Poram Spec | D69: 8 | E69: Kg | F69: 128586 | G69: 148066 | H69: 138748 | I69: 130411 | J69: 159056 | K69: 88126 | L69: 162476 | M69: 256409 | N69: 187513 | O69: 161718 | P69: 137569 | Q69: ='Desember 2024'!AM74 -> 229303.91 | R69: ='[20]Desember 24'!AL58 -> 0 | T69: =SUM(F69:Q69) -> 1927981.9 | U69: 2767753 | V69: =T69/U69*100 -> 69.658742
E70: % | F70: 1.2503461 | G70: 1.3601743 | H70: 0.8635291 | I70: 1.4735996 | J70: 1.0253249 | K70: 0.98804604 | L70: 1.015729 | M70: 1.1201463 | N70: 0.77980013 | O70: =$O$69/($O$12)*100 -> 0.69051955 | P70: 0.67510642 | Q70: ='Desember 2024'!AM75 -> 0.90731656 | R70: =R69/(R12)*100 -> #DIV/0! | T70: =T69/(T11)*100 -> 0.93517609 | U70: 0.8 | V70: 0 | AX70: =T70*10 -> 9.3517609 | FN70: =#REF!*10 -> #REF! | OR70: =OR66+(T47/1000) -> 3474.5995 | OS70: Total CPO Brand
C71: Bleaching Earth (BE) to Branded Spec | D71: 16 | E71: Kg | F71: 25923 | G71: 15015 | H71: 16441 | I71: 0 | J71: 0 | K71: 0 | L71: 0 | M71: 2930 | N71: 0 | O71: 998 | Q71: ='Desember 2024'!AM80 -> 0 | R71: ='[20]Desember 24'!AL60 -> 0 | T71: =SUM(F71:Q71) -> 61307 | U71: 1357284 | V71: =T71/U71*100 -> 4.5168881 | OR71: =OR68+T71 -> 82886.618 | OS71: Total BE Brand
E72: % | F72: 1.5981564 | G72: 1.74293 | H72: 1.7942098 | I72: #DIV/0! | J72: #DIV/0! | K72: #DIV/0! | L72: #DIV/0! | M72: 1.5863992 | N72: #DIV/0! | O72: 1.7871819 | Q72: ='Desember 2024'!AM81 -> #DIV/0! | R72: =R71/(R13)*100 -> #DIV/0! | T72: =T71/(T13)*100 -> 1.6840683 | U72: 1.8 | V72: 0 | AX72: =T72*10 -> 16.840683 | OR72: =OR71/OR70 -> 23.855013 | OS72: Kg/MT CPO
C73: Phosporic Acid (PA) | D73: 0.55 | E73: Kg | F73: 6664.856 | G73: 6551.932 | H73: 9270.856 | I73: 5139.122 | J73: 7872.554 | K73: 4040.198 | L73: 7823.782 | M73: 11739.24 | N73: 12499.518 | O73: 12588.966 | P73: 10695.718 | Q73: ='Desember 2024'!AM82 -> 12772.944 | R73: ='[20]Desember 24'!AL62 -> 0 | T73: =SUM(F73:Q73) -> 107659.69 | U73: 252824 | V73: =SUM(H73:T73) -> 202102.58 | OR73: 16 | OS73: Budget (Kg/MT)
E74: % | F74: 0.05597855 | G74: 0.055773982 | H74: 0.054586175 | I74: 0.058070317 | J74: 0.050748955 | K74: 0.045297661 | L74: 0.048910868 | M74: 0.050873473 | N74: 0.051981067 | O74: =O73/(O11)*100 -> 0.05362575 | P74: 0.05248819 | Q74: ='Desember 2024'!AM83 -> 0.050540366 | R74: =R73/(R11)*100 -> #DIV/0! | T74: =T73/(T11+71450)*100 -> 0.052202711 | U74: 0.06 | V74: =V73/(V11+71450)*100 -> 282.85682 | AX74: =T74*10 -> 0.52202711 | FN74: =Q74*10 -> 0.50540366 | OR74: =OR72-OR73 -> 7.8550134 | OS74: Over (Kg/MT)
B75: 4 | C75: Oil Losses | D75: 0.8 | E75: % | F75: -0.68509483 | G75: -0.65863696 | H75: -0.66393506 | I75: =((SUM(I19:I20))-(SUM(I11)))/(SUM(I11))*100 -> -0.41591778 | J75: -0.70420179 | K75: -0.60503048 | L75: -5.536747 | M75: 0.10357452 | N75: -1.099051 | O75: =((SUM(O19:O20))-(SUM(O11)))/(SUM(O11))*100 -> -1.0807009 | P75: 2.2143867 | Q75: ='Desember 2024'!AM84 -> 0.8148735 | R75: =((SUM(R19:R20))-(SUM(R11)))/(SUM(R11))*100 -> #DIV/0! | T75: =((SUM(T19:T20))-(SUM(T11)))/(SUM(T11))*100 -> -0.57929066 | U75: =((SUM(U19:U20))-(SUM(U11)))/(SUM(U11))*100 -> -0.71527906 | V75: =T75/U75*100 -> 80.988063
C76: % Oil Content | D76: 22 | E76: % | F76: 21.923529 | G76: 21.991 | H76: 21.974 | I76: 21.953333 | J76: 20.636667 | K76: 21.886471 | L76: 21.912727 | M76: 21.700714 | N76: 22.058148 | O76: 22.009286 | P76: 21.916818 | Q76: ='Desember 2024'!AM86 -> 21.551667 | R76: ='[20]Desember 24'!AL65 -> #DIV/0! | T76: =AVERAGE(F76:Q76) -> 21.792863 | U76: 22 | V76: =AVERAGE(H76:T76) -> #DIV/0!
C77: Spent Bleaching Earth | E77: Kg | F77: 188382.83 | G77: 198944.14 | H77: 189290.23 | I77: 159040.56 | J77: 191879.86 | K77: 107413.67 | L77: 198078.92 | M77: 315617.42 | N77: 189044.92 | O77: 163995.02 | P77: 138939.49 | Q77: ='Desember 2024'!AM87 -> 231452.55 | R77: =SUM(R69,R71)+(R76%*SUM(R69,R71)) -> #DIV/0! | T77: =SUM(T69,T71)+(T76%*SUM(T69,T71)) -> 2422811.9 | U77: 7811279 | V77: =SUM(V69,V71)+(V76%*SUM(V69,V71)) -> #DIV/0! | GA77: =X77+400 -> 400
B78: 5 | C78: PACKAGING (Brand Salvaco) | T78: Packaging | U78: Packaging | V78: Packaging | FX78: 17292 | OY78: =#REF!-FX78 -> #REF!
C79: Olein IV 60 Received | E79: Kg | F79: ='[20]Januari 24'!AL68 -> 845858 | G79: ='[20]Februari 24'!AI68 -> #REF! | H79: ='[20]Maret 24'!AL68 -> 0 | I79: ='[20]April 24'!AL68 -> 0 | J79: ='[20]Mei 24'!AL68 -> 0 | K79: ='[20]Juny 24'!AL68 -> 0 | L79: ='[20]July 24'!AL68 -> 0 | M79: ='[20]Agustus 24'!AL68 -> 0 | N79: ='[20]September 24'!AL68 -> 0 | O79: ='[20]September 24'!AM68 -> #REF! | Q79: ='[20]November 24'!AL68 -> 0 | R79: ='[20]Desember 24'!AL68 -> 0 | T79: =SUM(F79:R79) -> #REF! | U79: =SUM(G79:S79) -> #REF! | V79: =(T79/U79)*100 -> #REF!
C80: Olein IV 60 Consume | E80: Kg | F80: ='[20]Januari 24'!AL69 -> 399021.28 | G80: ='[20]Februari 24'!AI69 -> #REF! | H80: ='[20]Maret 24'!AL69 -> 0 | I80: ='[20]April 24'!AL69 -> 0 | J80: ='[20]Mei 24'!AL69 -> 0 | K80: ='[20]Juny 24'!AL69 -> 0 | L80: ='[20]July 24'!AL69 -> 0 | M80: ='[20]Agustus 24'!AL69 -> 0 | N80: ='[20]September 24'!AL69 -> 0 | O80: ='[20]September 24'!AM69 -> #REF! | Q80: ='[20]November 24'!AL69 -> 0 | R80: ='[20]Desember 24'!AL69 -> 0 | T80: =SUM(T81:T83) -> #REF! | U80: =SUM(U81:U83) -> #REF! | V80: =(T80/U80)*100 -> #REF! | AFR80: Kg | AFS80: Olein Filling to Packaging
C81: - finished product | E81: Kg | F81: =SUM(F85:F86)*10.86 -> 400256.16 | G81: =SUM(G85:G86)*10.86 -> #REF! | H81: =SUM(H85:H86)*10.86 -> 0 | I81: ='[20]April 24'!AL70 -> 0 | J81: =SUM(J85:J86)*10.86 -> 0 | K81: =SUM(K85:K86)*10.86 -> 0 | L81: =SUM(L85:L86)*10.86 -> 0 | M81: =SUM(M85:M86)*10.86 -> 0 | N81: =SUM(N85:N86)*10.86 -> 0 | O81: =SUM(O85:O86)*10.86 -> #REF! | Q81: =SUM(Q85:Q86)*10.86 -> 0 | R81: =SUM(R85:R86)*10.86 -> 0 | T81: =SUM(T85:T86)*10.86 -> #REF! | U81: =SUM(U85:U86)*10.86 -> 32269046 | V81: =(T81/U81)*100 -> #REF! | FX81: =#REF!/1000 -> #REF! | OY81: 4696 | OZ81: =FX81/OY81*100 -> #REF!
C82: - sample | E82: Kg | F82: =F80-F81 -> -1234.88 | G82: =G80-G81 -> #REF! | H82: =H80-H81 -> 0 | I82: ='[20]April 24'!AL71 -> 0 | J82: =J80-J81 -> 0 | K82: =K80-K81 -> 0 | L82: =L80-L81 -> 0 | M82: =M80-M81 -> 0 | N82: =N80-N81 -> 0 | O82: =O80-O81 -> #REF! | Q82: =Q80-Q81 -> 0 | R82: =R80-R81 -> 0 | T82: =SUM(F82:R82) -> #REF! | U82: =SUM(G82:S82) -> #REF! | V82: =(T82/U82)*100 -> #REF! | FX82: =#REF!/1000 -> #REF! | OY82: 565 | OZ82: =FX82/OY82*100 -> #REF!
C83: - remelt, flushing, downgrade | E83: Kg | F83: ='[20]Januari 24'!AL72 -> 0 | G83: ='[20]Februari 24'!AI72 -> 0 | H83: ='[20]Maret 24'!AL72 -> 0 | I83: ='[20]April 24'!AL72 -> 0 | Q83: 0 | R83: 0 | T83: =SUM(F83:R83) -> 0 | U83: =SUM(G83:S83) -> 0
C84: Carton | T84: Carton | U84: Carton | V84: Carton
C85: Salvaco 1 Liter | E85: Box | F85: ='[20]Januari 24'!AL74 -> 17197 | G85: ='[20]Februari 24'!AI74 -> #REF! | H85: ='[20]Maret 24'!AL74 -> 0 | I85: ='[20]April 24'!AL74 -> 0 | J85: ='[20]Mei 24'!AL74 -> 0 | K85: ='[20]Juny 24'!AL74 -> 0 | L85: ='[20]July 24'!AL74 -> 0 | M85: ='[20]Agustus 24'!AL74 -> 0 | N85: ='[20]September 24'!AL74 -> 0 | O85: ='[20]September 24'!AM74 -> #REF! | Q85: ='[20]November 24'!AL74 -> 0 | R85: ='[20]Desember 24'!AL74 -> 0 | T85: =SUM(F85:R85) -> #REF! | U85: 1254577 | V85: =(T85/U85)*100 -> #REF!
C86: Salvaco 2 Liter | E86: Box | F86: ='[20]Januari 24'!AL75 -> 19659 | G86: ='[20]Februari 24'!AI75 -> #REF! | H86: ='[20]Maret 24'!AL75 -> 0 | I86: ='[20]April 24'!AL75 -> 0 | J86: ='[20]Mei 24'!AL75 -> 0 | K86: ='[20]Juny 24'!AL75 -> 0 | L86: ='[20]July 24'!AL75 -> 0 | M86: ='[20]Agustus 24'!AL75 -> 0 | N86: ='[20]September 24'!AL75 -> 0 | O86: ='[20]September 24'!AM75 -> #REF! | Q86: ='[20]November 24'!AL75 -> 0 | R86: ='[20]Desember 24'!AL75 -> 0 | T86: =SUM(F86:R86) -> #REF! | U86: 1716790 | V86: =(T86/U86)*100 -> #REF!
C87: Pouch | T87: Pouch | U87: Pouch | V87: Pouch
C88: Salvaco 1 Liter | E88: Pouch | F88: =F85*12 -> 206364 | G88: =G85*12 -> #REF! | H88: =H85*12 -> 0 | I88: =I85*12 -> 0 | J88: =J85*12 -> 0 | K88: =K85*12 -> 0 | L88: =L85*12 -> 0 | M88: =M85*12 -> 0 | ... O88: =O85*12 -> #REF! | Q88: =Q85*12 -> 0 | R88: =R85*12 -> 0 | T88: =T85*12 -> #REF! | U88: =U85*12 -> 15054924 | V88: =(T88/U88)*100 -> #REF!
C89: Salvaco 2 Liter | E89: Pouch | F89: =F86*6 -> 117954 | G89: =G86*6 -> #REF! | H89: =H86*6 -> 0 | I89: =I86*6 -> 0 | J89: =J86*6 -> 0 | K89: =K86*6 -> 0 | L89: =L86*6 -> 0 | M89: =M86*6 -> 0 | ... O89: =O86*6 -> #REF! | Q89: =Q86*6 -> 0 | R89: =R86*6 -> 0 | T89: =T86*6 -> #REF! | U89: =U86*6 -> 10300740 | V89: =(T89/U89)*100 -> #REF!
C90: Consumable Vit. A | E90: gram | F90: =(F80*45)/1700 -> 10562.328 | G90: =(G80*45)/1700 -> #REF! | H90: =(H80*45)/1700 -> 0 | I90: =(I80*45)/1700 -> 0 | J90: =(J80*45)/1700 -> 0 | K90: =(K80*45)/1700 -> 0 | L90: =(L80*45)/1700 -> 0 | M90: =(M80*45)/1700 -> 0 | ... O90: =(O80*45)/1700 -> #REF! | Q90: =(Q80*45)/1700 -> 0 | R90: =(R80*45)/1700 -> 0 | T90: =SUM(F90:R90) -> #REF! | U90: =(U80*45)/1700 -> #REF! | V90: =(T90/U90)*100 -> #REF!
C91: Consumable Packing Tape | E91: Roll | F91: =SUM(F85:F86)/500 -> 73.712 | G91: =SUM(G85:G86)/500 -> #REF! | H91: =SUM(H85:H86)/500 -> 0 | I91: =SUM(I85:I86)/500 -> 0 | J91: =SUM(J85:J86)/500 -> 0 | K91: =SUM(K85:K86)/500 -> 0 | L91: =SUM(L85:L86)/500 -> 0 | M91: =SUM(M85:M86)/500 -> 0 | ... O91: =SUM(O85:O86)/500 -> #REF! | Q91: =SUM(Q85:Q86)/500 -> 0 | R91: =SUM(R85:R86)/500 -> 0 | T91: =SUM(F91:R91) -> #REF! | U91: =SUM(U85:U86)/500 -> 5942.734 | V91: =(T91/U91)*100 -> #REF!
C92: REJECT MATERIAL QTY | T92: Loss Material | U92: Loss Material | V92: Loss Material
C93: Carton | T93: Carton | U93: Carton | V93: Carton
C94: Salvaco 1 Liter | E94: Box | F94: ='[20]Januari 24'!AL74 -> 17197 | G94: ='[20]Februari 24'!AI83 -> #REF! | H94: ='[20]Maret 24'!AL83 -> 0 | I94: ='[20]April 24'!AL83 -> 0 | J94: ='[20]Mei 24'!AL83 -> 0 | K94: ='[20]Juny 24'!AL83 -> 0 | L94: ='[20]July 24'!AL83 -> 0 | M94: ='[20]Agustus 24'!AL83 -> 0 | N94: ='[20]September 24'!AL83 -> 0 | O94: ='[20]September 24'!AM83 -> #REF! | Q94: ='[20]November 24'!AL83 -> 0 | R94: ='[20]Desember 24'!AL83 -> 0 | T94: =SUM(F94:R94) -> #REF! | U94: =SUM(G94:S94) -> #REF! | V94: =SUM(H94:T94) -> #REF!
C95: Salvaco 2 Liter | E95: Box | F95: ='[20]Januari 24'!AL75 -> 19659 | G95: ='[20]Februari 24'!AI84 -> #REF! | H95: ='[20]Maret 24'!AL84 -> 0 | I95: ='[20]April 24'!AL84 -> 0 | J95: ='[20]Mei 24'!AL84 -> 0 | K95: ='[20]Juny 24'!AL84 -> 0 | L95: ='[20]July 24'!AL84 -> 0 | M95: ='[20]Agustus 24'!AL84 -> 0 | N95: ='[20]September 24'!AL84 -> 0 | O95: ='[20]September 24'!AM84 -> #REF! | Q95: ='[20]November 24'!AL84 -> 0 | R95: ='[20]Desember 24'!AL84 -> 0 | T95: =SUM(F95:R95) -> #REF! | U95: =SUM(G95:S95) -> #REF! | V95: =SUM(H95:T95) -> #REF!
C96: Pouch | T96: Pouch | U96: Pouch | V96: Pouch
C97: Salvaco 1 Liter | E97: Pouch | F97: =F94*12 -> 206364 | G97: =G94*12 -> #REF! | H97: =H94*12 -> 0 | I97: =I94*12 -> 0 | J97: =J94*12 -> 0 | K97: =K94*12 -> 0 | L97: =L94*12 -> 0 | M97: =M94*12 -> 0 | ... O97: =O94*12 -> #REF! | Q97: =Q94*12 -> 0 | R97: =R94*12 -> 0 | T97: =SUM(F97:R97) -> #REF! | U97: =SUM(G97:S97) -> #REF! | V97: =SUM(H97:T97) -> #REF!
C98: Salvaco 2 Liter | E98: Pouch | F98: =F95*6 -> 117954 | G98: =G95*6 -> #REF! | H98: =H95*6 -> 0 | I98: =I95*6 -> 0 | J98: =J95*6 -> 0 | K98: =K95*6 -> 0 | L98: =L95*6 -> 0 | M98: =M95*6 -> 0 | ... O98: =O95*6 -> #REF! | Q98: =Q95*6 -> 0 | R98: =R95*6 -> 0 | T98: =SUM(F98:R98) -> #REF! | U98: =SUM(G98:S98) -> #REF! | V98: =SUM(H98:T98) -> #REF!
C99: REJECT MATERIAL (%) | T99: Loss Material | U99: Loss Material | V99: Loss Material
C100: Carton | T100: Carton | U100: Carton | V100: Carton
C101: Salvaco 1 Liter | D101: 0.3 | E101: % | F101: =F94/F85*100 -> 100 | G101: =G94/G85*100 -> #REF! | H101: =H94/H85*100 -> #DIV/0! | I101: =I94/I85*100 -> #DIV/0! | J101: =J94/J85*100 -> #DIV/0! | K101: =K94/K85*100 -> #DIV/0! | L101: =L94/L85*100 -> #DIV/0! | M101: =M94/M85*100 -> #DIV/0! | ... O101: =O94/O85*100 -> #REF! | Q101: =Q94/Q85*100 -> #DIV/0! | R101: =R94/R85*100 -> #DIV/0! | T101: =T94/T85*100 -> #REF! | U101: =U94/U85*100 -> #REF! | V101: =V94/V85*100 -> #REF!
C102: Salvaco 2 Liter | D102: 0.3 | E102: % | F102: =F95/F86*100 -> 100 | G102: =G95/G86*100 -> #REF! | H102: =H95/H86*100 -> #DIV/0! | I102: =I95/I86*100 -> #DIV/0! | J102: =J95/J86*100 -> #DIV/0! | K102: =K95/K86*100 -> #DIV/0! | L102: =L95/L86*100 -> #DIV/0! | M102: =M95/M86*100 -> #DIV/0! | ... O102: =O95/O86*100 -> #REF! | Q102: =Q95/Q86*100 -> #DIV/0! | R102: =R95/R86*100 -> #DIV/0! | T102: =T95/T86*100 -> #REF! | U102: =U95/U86*100 -> #REF! | V102: =V95/V86*100 -> #REF!
...

Sheet Steam
B2: Steam Price Package Boiler | G2: Kurs | H2: ='SUMMARY HPP '!I9 -> 15546
B3: Consumable Item | C3: Norma | E3: Consumption, Ton/day | F3: Unit Price | H3: Total Cost
B4: Steam Production (Including Dearator) | C4: =408/24 -> 17 | D4: Ton/jam | E4: ='Desember 2024'!AM248 -> 112.0128 | H4: Rp/day
B5: Gas | C5: 1000 | D5: MMBTU/day | E5: ='Desember 2024'!$AM$239 -> 1121.3073 | F5: 11.5 | G5: USD/MMBTU | H5: =E5*H2*F5 -> 2.0046621e+08 | I5: Harga steam tinggi dikarenakan oleh unit price gas yang tinggi, ideal (9.6)
B6: Chemical Treatment
B7: EONALKALOX B1414 | C7: 7.3 | D7: l/day | E7: =C7 -> 7.3 | F7: 25340 | G7: Rp/l | H7: =E7*F7 -> 184982
B8: EONCONDENS B1720 | C8: 2.4 | D8: l/day | E8: =C8 -> 2.4 | F8: 110000 | G8: Rp/l | H8: =E8*F8 -> 264000
B9: EONOXY B8100 | C9: 2.4 | D9: l/day | E9: =C9 -> 2.4 | F9: 20160 | G9: Rp/l | H9: =E9*F9 -> 48384
B10: EONSCALE B5100 | C10: 5.8 | D10: l/day | E10: =C10 -> 5.8 | F10: 31800 | G10: Rp/l | H10: =E10*F10 -> 184440
B11: EONDESCALER B2550 | C11: 1.4 | D11: l/day | E11: =C11 -> 1.4 | F11: 39320 | G11: Rp/l | H11: =E11*F11 -> 55048
B12: Water Demin | C12: =[28]L.Water!C12*83% -> 408.0197 | D12: M3/day | E12: =C12 -> 408.0197 | F12: =[28]L.Water!F12 -> 10162 | G12: Rp/m3 | H12: =E12*F12 -> 4146296.2
B13: Preventive Maintenance | D13: Rp/day | H13: =C13 -> 0
B14: Total Pakage Boiler | H14: =IFERROR(SUM(H5:H13),"") -> 2.0534936e+08
F15: Unit Price, Rp/Ton | H15: =H14/E4/10 -> 183326.68
B17: Note :
B18: 1. Harga gas, secara general untuk industri adalah 9,21-9,6 usd/mmBtu
C26: Kurita H-504 18:25

Sheet WWTP
B2: Water Waste Treatment Plant | G2: Kurs | H2: ='SUMMARY HPP '!I9 -> 15546
B3: Consumable Item | C3: Norma | E3: Consumption, M3/day | F3: Unit Price | H3: Total Cost
B4: Waste Water Feed | C4: =200/24 -> 8.3333333 | D4: M3/jam | E4: ='Desember 2024'!AM266 -> 165.91304 | H4: Rp/day
B5: biaya transfer ke kawasan | F5: 0 | G5: Rp/m3 | H5: 8700
B6: Chemical Treatment
B7: Sugar | C7: 0 | D7: kg/day | E7: =C7 -> 0 | F7: 24890 | G7: Rp/kg | H7: =E7*F7 -> 0
B8: PE | C8: =E8*C4 -> 0.62305296 | D8: kg/day | E8: 0.074766355 | F8: 65340 | G8: Rp/kg | H8: =E8*F8 -> 4885.2336
B9: PAC | C9: =E9*C4 -> 46.728972 | D9: kg/day | E9: 5.6074766 | F9: 7702 | G9: Rp/kg | H9: =E9*F9 -> 43188.785
B10: Urea | C10: =E10*C4 -> 6.2305296 | D10: kg/day | E10: 0.74766355 | F10: 18634 | G10: Rp/kg | H10: =E10*F10 -> 13931.963
B11: TSP | C11: =E11*C4 -> 1.2461059 | D11: kg/day | E11: 0.14953271 | F11: 44722 | G11: Rp/kg | H11: =E11*F11 -> 6687.4019
B12: HCL | C12: 0 | D12: kg/day | E12: =C12 -> 0 | F12: 5700 | G12: Rp/kg | H12: =E12*F12 -> 0
B13: NaOH | C13: 0 | D13: kg/day | E13: =C13 -> 0 | F13: 15700 | G13: Rp/kg | H13: =E13*F13 -> 0
B14: Power | C14: 2675 | D14: kW/day | E14: =C14 -> 2675 | F14: =[29]UP.E!C28 -> 1550 | G14: Rp/kW | H14: =E14*F14 -> 4146250
B15: Preventive Maintenance | D15: Rp/day | H15: =E15*F15 -> 0
H16: =IFERROR(SUM(H5:H15),"") -> 4223643.4
F17: Unit Price, Rp/M3 | H17: =H16/E4 -> 25456.97
C29: Kurita H-504 18:25

Sheet WTP
B2: Water Treatment Plant | G2: Kurs | H2: ='SUMMARY HPP '!I9 -> 15546
B3: Consumable Item | C3: Norma | E3: Consumption, M3/day | F3: Unit Price | H3: Total Cost
B4: Water Treatment Plant | C4: =1000/24 -> 41.666667 | D4: M3/jam | E4: ='Desember 2024'!AM258 -> 1800.1 | H4: Rp/day
B5: Chemical | F5: 8700 | G5: Rp/m3 | H5: =F5*E4 -> 15660870
B6: anti scalant | C6: 0.1 | D6: kg/day | E6: =C6 -> 0.1 | F6: 44500 | G6: Rp/kg | H6: =E6*F6 -> 4450
B7: caustic soda | C7: 0.1 | D7: kg/day | E7: =C7 -> 0.1 | F7: 65340 | G7: Rp/kg | H7: =E7*F7 -> 6534
B8: citrid acid | C8: 0.1 | D8: kg/day | E8: =C8 -> 0.1 | F8: 33275 | G8: Rp/kg | H8: =E8*F8 -> 3327.5
B9: bioside | C9: 0.1 | D9: kg/day | E9: =C9 -> 0.1 | F9: 47450 | G9: Rp/kg | H9: =E9*F9 -> 4745
B10: Power | C10: 8896 | D10: kW/day | E10: =C10 -> 8896 | F10: =[29]UP.E!C28 -> 1550 | G10: Rp/kW | H10: =E10*F10 -> 13788800
B11: Preventive Maintenance | D11: Rp/day | H11: =E11*F11 -> 0
H12: =IFERROR(SUM(H5:H11),"") -> 29468726
F13: Unit Price, Rp/M3 | H13: =H12/E4 -> 16370.605
C25: Kurita H-504 18:25

Sheet lab
B2: Laboratorium Chemical Cost
B3: Consumable Item | C3: Norma | E3: Consumption/ Hari | F3: Unit Price | H3: Total Biaya
H4: Per Hari
B5: Refinery, Fraksinasi, Packaging & Sotrage tank
B6: Acetic Acid Glacial | C6: 50 | D6: ml | E6: =C6 -> 50 | F6: 374 | G6: ml | H6: =E6*F6 -> 18700
B7: Aquadest | C7: 2 | D7: liter | E7: =C7 -> 2 | F7: 7250 | G7: liter | H7: =E7*F7 -> 14500
B8: BF3-methanol solution, Reagen Grade | C8: 0.5 | D8: ml | E8: =C8 -> 0.5 | F8: 500 | G8: ml | H8: =E8*F8 -> 250
B9: Chloroform | C9: 70 | D9: ml | E9: =C9 -> 70 | F9: 388 | G9: ml | H9: =E9*F9 -> 27160
B10: Cyclohexane | C10: 70 | D10: ml | E10: =C10 -> 70 | F10: 612 | G10: ml | H10: =E10*F10 -> 42840
B11: Hydrazine Sulphate | C11: 0.05 | D11: gr | E11: =C11 -> 0.05 | F11: 21000 | G11: gr | H11: =E11*F11 -> 1050
B12: Hydrochloric Acid 37% | C12: 2.6 | D12: ml | E12: =C12 -> 2.6 | F12: 236 | G12: ml | H12: =E12*F12 -> 613.6
B13: Iso Propanol Alcohol TG | C13: 5.5 | D13: liter | E13: =C13 -> 5.5 | F13: 35000 | G13: liter | H13: =E13*F13 -> 192500
B14: Isooctane | C14: 150 | D14: ml | E14: =C14 -> 150 | F14: 480 | G14: ml | H14: =E14*F14 -> 72000
B15: Indikator Phenolpthalaein 1 % | C15: 0.3 | D15: gr | E15: =C15 -> 0.3 | F15: 6750 | G15: gr | H15: =E15*F15 -> 2025
B16: Indikator Thymolpthalaein | C16: =36/357 -> 0.10084034 | D16: gr | E16: =C16 -> 0.10084034 | F16: 90000 | G16: gr | H16: =E16*F16 -> 9075.6303
B17: Starch | C17: =107/357 -> 0.29971989 | D17: gr | E17: =C17 -> 0.29971989 | F17: 3000 | G17: gr | H17: =E17*F17 -> 899.15966
B18: Liquid standard Lovibond 3,4R 30,0 Y 0,9N | C18: 0.1 | D18: ml | E18: =C18 -> 0.1 | F18: 70000 | G18: ml | H18: =E18*F18 -> 7000
B19: Liquid standard Lovibond 3,0R 28,0Y | C19: 0.1 | D19: ml | E19: =C19 -> 0.1 | F19: 70000 | G19: ml | H19: =E19*F19 -> 7000
B20: n-HexaneTehcnis | C20: 0.5 | D20: liter | E20: =C20 -> 0.5 | F20: 19300 | G20: liter | H20: =E20*F20 -> 9650
B21: p-Anisidine | C21: =48/357 -> 0.13445378 | D21: gr | E21: =C21 -> 0.13445378 | F21: 7600 | G21: gr | H21: =E21*F21 -> 1021.8487
B22: Wijs Solution | C22: 120 | D22: ml | E22: =C22 -> 120 | F22: 502 | G22: ml | H22: =E22*F22 -> 60240
B23: N2 (UHP) gas refill for GC & Foam test | C23: 0.02 | D23: Liter | E23: =C23 -> 0.02 | F23: 5000000 | G23: Liter | H23: =E23*F23 -> 100000
B24: H2 (UHP) gas refill for GC | C24: 0.03 | D24: Liter | E24: =C24 -> 0.03 | F24: 2500000 | G24: Liter | H24: =E24*F24 -> 75000
B25: UT (UHP) gas refill for GC | C25: 0.03 | D25: Liter | E25: =C25 -> 0.03 | F25: 1250000 | G25: Liter | H25: =E25*F25 -> 37500
B26: Zinc Oksida GR | C26: =179/357 -> 0.50140056 | D26: gr | E26: =C26 -> 0.50140056 | F26: 2000 | G26: gr | H26: =E26*F26 -> 1002.8011
B27: Potassium Dihydrogen Phosphate | C27: =250/357 -> 0.70028011 | D27: gr | E27: =C27 -> 0.70028011 | F27: 765 | G27: gr | H27: =E27*F27 -> 535.71429
B28: Pottasium Hydrogen Phtalate | C28: =250/357 -> 0.70028011 | D28: gr | E28: =C28 -> 0.70028011 | F28: 5200 | G28: gr | H28: =E28*F28 -> 3641.4566
B29: Sodium Thiosulphate | C29: =6069/357 -> 17 | D29: gr | E29: =C29 -> 17 | F29: 950 | G29: gr | H29: =E29*F29 -> 16150
B30: Potassium Iodide | C30: 12 | D30: gr | E30: =C30 -> 12 | F30: 2400 | G30: gr | H30: =E30*F30 -> 28800
B31: Pottasium Dichromate | C31: =357/357 -> 1 | D31: gr | E31: =C31 -> 1 | F31: 4200 | G31: gr | H31: =E31*F31 -> 4200
B32: Sodium Hydroxide | C32: =6069/357 -> 17 | D32: gr | E32: =C32 -> 17 | F32: 700 | G32: gr | H32: =E32*F32 -> 11900
B33: Sub Total | H33: =SUM(H6:H32) -> 745255.21
B35: Consumable Item | C35: Norma | E35: Consumption/day | F35: Unit Price | H35: Total Price
H36: Per Day
B37: Chemical Boiler & WTP
B38: Sodium Molybdate | C38: =286/357 -> 0.80112045 | D38: gr | E38: =C38 -> 0.80112045 | F38: 4000 | G38: gr | H38: =E38*F38 -> 3204.4818
B39: Iron test 0.0025 - 5.00 mg/l | C39: =1785/357 -> 5 | D39: Test | E39: =C39 -> 5 | F39: 10100 | G39: Test | H39: =E39*F39 -> 50500
B40: Phosphate Test 0.5 - 30 mg/l PO4-P | C40: =714/357 -> 2 | D40: pcs | E40: =C40 -> 2 | F40: 8160 | G40: pcs | H40: =E40*F40 -> 16320
B41: Sulfite Test 1,0-60,0 mg/l SO3 | C41: =360/357 -> 1.0084034 | D41: Pcs | E41: =C41 -> 1.0084034 | F41: 26550 | G41: Pcs | H41: =E41*F41 -> 26773.109
B42: Silica Test 0-800 mg/L | C42: =714/357 -> 2 | D42: pcs | E42: =C42 -> 2 | F42: 31700 | G42: pcs | H42: =E42*F42 -> 63400
B43: Silicate (Silicic Acid) 0,3-10 mg/L | C43: 2.5 | D43: pcs | E43: =C43 -> 2.5 | F43: 31006 | G43: pcs | H43: =E43*F43 -> 77515
B44: Ammonium Vanadate | C44: =179/357 -> 0.50140056 | D44: gr | E44: =C44 -> 0.50140056 | F44: 11950 | G44: gr | H44: =E44*F44 -> 5991.7367
B45: Ammonium Chloride | C45: =214/357 -> 0.59943978 | D45: gr | E45: =C45 -> 0.59943978 | F45: 2545 | G45: gr | H45: =E45*F45 -> 1525.5742
B46: Ammonium Hidroksida | C46: =1714/357 -> 4.8011204 | D46: mL | E46: =C46 -> 4.8011204 | F46: 930 | G46: mL | H46: =E46*F46 -> 4465.042
B47: Mg EDTA | C47: =71/357 -> 0.19887955 | D47: gr | E47: =C47 -> 0.19887955 | F47: 21050 | G47: gr | H47: =E47*F47 -> 4186.4146
B48: Pottasium Carbonat | C48: =12/357 -> 0.033613445 | D48: gr | E48: =C48 -> 0.033613445 | F48: 12500 | G48: gr | H48: =E48*F48 -> 420.16807
B49: Trietanolamin | C49: 0.08 | D49: mL | E49: =C49 -> 0.08 | F49: 8160 | G49: mL | H49: =E49*F49 -> 652.8
B50: Indikator EBT | C50: =12/357 -> 0.033613445 | D50: gr | E50: =C50 -> 0.033613445 | F50: 23400 | G50: gr | H50: =E50*F50 -> 786.55462
B51: Indikator Calcon | C51: =12/357 -> 0.033613445 | D51: gr | E51: =C51 -> 0.033613445 | F51: 50800 | G51: gr | H51: =E51*F51 -> 1707.563
B52: Hydroxylammonium Chloride GR | C52: 0.08 | D52: gr | E52: =C52 -> 0.08 | F52: 6250 | G52: gr | H52: =E52*F52 -> 500
B53: Eriocrom Black T-Metal | C53: 0.05 | D53: gr | E53: =C53 -> 0.05 | F53: 24260 | G53: gr | H53: =E53*F53 -> 1213
B54: Sub Total | H54: =SUM(H38:H53) -> 259161.44
B56: Consumable Item | C56: Norma | E56: Consumption/day | F56: Unit Price | H56: Total Price
H57: Per Day
B58: Chemical WWTP
B59: COD cell test 50 - 500 mg/l | C59: =59/357 -> 0.16526611 | D59: pcs | E59: =C59 -> 0.16526611 | F59: 82000 | G59: pcs | H59: =E59*F59 -> 13551.821
B60: COD cell test 500 - 10000 mg/l | C60: =59/357 -> 0.16526611 | D60: pcs | E60: =C60 -> 0.16526611 | F60: 82000 | G60: pcs | H60: =E60*F60 -> 13551.821
B61: Sub Total | H61: =SUM(H59:H60) -> 27103.641
B63: Total keseluruhan | H63: =H61+H54+H33 -> 1031520.3
C67: Spere Part Laboratorium
B68: No | C68: Consumable Item | D68: Norma | F68: Consumption/day | G68: Unit Price | I68: Total Price
I69: Per Day
B70: 1 | C70: Batang pengaduk | D70: 12 | E70: Pcs/Tahun | F70: =D70/357 -> 0.033613445 | G70: 35000 | H70: Rp/Pcs | I70: =F70*G70 -> 1176.4706
B71: =B70+1 -> 2 | C71: Beaker glass 100 mL | D71: 72 | E71: Pcs/Tahun | F71: =D71/357 -> 0.20168067 | G71: 48000 | H71: Rp/Pcs | I71: =F71*G71 -> 9680.6723
B72: =B71+1 -> 3 | C72: Beaker glass 500 mL | D72: 12 | E72: Pcs/Tahun | F72: =D72/357 -> 0.033613445 | G72: 100000 | H72: Rp/Pcs | I72: =F72*G72 -> 3361.3445
B73: =B72+1 -> 4 | C73: Beaker glass 1000 mL | D73: 6 | E73: Pcs/Tahun | F73: =D73/357 -> 0.016806723 | G73: 120000 | H73: Rp/Pcs | I73: =F73*G73 -> 2016.8067
B74: =B73+1 -> 5 | C74: Beaker glass 2000 mL | D74: 6 | E74: Pcs/Tahun | F74: =D74/357 -> 0.016806723 | G74: 142000 | H74: Rp/Pcs | I74: =F74*G74 -> 2386.5546
B75: =B74+1 -> 6 | C75: Beaker Plastik with handle 1000 mL | D75: 6 | E75: Pcs/Tahun | F75: =D75/357 -> 0.016806723 | G75: 70000 | H75: Rp/Pcs | I75: =F75*G75 -> 1176.4706
B76: =B75+1 -> 7 | C76: Boiling Round Bottom Flask 250 mL | D76: 6 | E76: Pcs/Tahun | F76: =D76/357 -> 0.016806723 | G76: 180000 | H76: Rp/Pcs | I76: =F76*G76 -> 3025.2101
B77: =B76+1 -> 8 | C77: Boiling Round Bottom Flask 1000 mL IKA | D77: 2 | E77: Pcs/Tahun | F77: =D77/357 -> 0.0056022409 | G77: 350000 | H77: Rp/Pcs | I77: =F77*G77 -> 1960.7843
B78: =B77+1 -> 9 | C78: Rotary flask 1000 mL IKA | D78: 2 | E78: Pcs/Tahun | F78: =D78/357 -> 0.0056022409 | G78: 350000 | H78: Rp/Pcs | I78: =F78*G78 -> 1960.7843
B79: =B78+1 -> 10 | C79: Corong 75 mm | D79: 6 | E79: Pcs/Tahun | F79: =D79/357 -> 0.016806723 | G79: 75000 | H79: Rp/Pcs | I79: =F79*G79 -> 1260.5042
B80: =B79+1 -> 11 | C80: Erlenmeyer 250 mL | D80: 72 | E80: Pcs/Tahun | F80: =D80/357 -> 0.20168067 | G80: 90000 | H80: Rp/Pcs | I80: =F80*G80 -> 18151.261
B81: =B80+1 -> 12 | C81: Filtering Flask 500 mL | D81: 2 | E81: Pcs/Tahun | F81: =D81/357 -> 0.0056022409 | G81: 400000 | H81: Rp/Pcs | I81: =F81*G81 -> 2240.8964
B82: =B81+1 -> 13 | C82: Gelas ukur 100 mL | D82: 2 | E82: Pcs/Tahun | F82: =D82/357 -> 0.0056022409 | G82: 85000 | H82: Rp/Pcs | I82: =F82*G82 -> 476.19048
... B110: =B109+1 -> 41 | C110: Magnetic Stirer 8 cm | D110: 12 | E110: Pcs/Tahun | F110: =D110/357 -> 0.033613445 | G110: 85000 | H110: Rp/Pcs | I110: =F110*G110 -> 2857.1429
G111: Total Cost/Days | I111: =SUM(I70:I110) -> 135770.31

Sheet genset
B2: Warming Up Genset
B3: Consumable Item | C3: Norma | E3: Consumption/day | F3: Unit Price | H3: Total Cost | K3: PLN - Power Unit Price
B4: Genset Warming Up | D4: kW/Jam | E4: 0 | H4: Rp/day | K4: Consumable Item | L4: Unit Price
B5: Solar | H5: 0 | K5: PLN Fee | L5: 1550 | M5: Rp/kWh
B6: Genset - 1 (1044 kW) | C6: 100 | D6: Ltr/Jam | E6: =(C6*25%*4)/30 -> 3.3333333 | F6: 14500 | G6: Rp/ltr | H6: =F6*E6 -> 48333.333
B7: Genset - 2 (1044 kW) | C7: 100 | D7: Ltr/Jam | E7: =(C7*25%*4)/30 -> 3.3333333 | F7: 14500 | G7: Rp/ltr | H7: =F7*E7 -> 48333.333
B8: Genset - 3 (1044 kW) | C8: 100 | D8: Ltr/Jam | E8: =(C8*25%*4)/30 -> 3.3333333 | F8: 14500 | G8: Rp/ltr | H8: =F8*E8 -> 48333.333
B9: Preventive Maintenance | D9: Rp/day | H9: 0
B10: Cost Power by Genset | H10: =SUM(H5:H9) -> 145000
B12: Genset - Power Unit Price
B13: Consumable Item | C13: Norma | E13: Power, kW/day | F13: Unit Price | H13: Total Cost
B14: Power Production by Genset | C14: 2088 | D14: kW/Jam | E14: =C14*24 -> 50112 | H14: Rp/day
B15: Solar | H15: 0
B16: Genset - 1 (1044 kW) | C16: 800 | D16: Ltr/Jam | E16: =C16*24 -> 19200 | F16: 14500 | G16: Rp/ltr | H16: =F16*E16 -> 278400000
B17: Genset - 2 (1044 kW) | C17: 800 | D17: Ltr/Jam | E17: =C17*24 -> 19200 | F17: 14500 | G17: Rp/ltr | H17: =F17*E17 -> 278400000
B18: Genset - 3 (1044 kW) | D18: Ltr/Jam | E18: 0 | F18: 14500 | G18: Rp/ltr | H18: =F18*E18 -> 0
B19: Preventive Maintenance | D19: Rp/day | H19: 0
B20: Cost Power by Genset | H20: =SUM(H15:H19) -> 556800000
F21: Unit Price, Rp/Kw | H21: =H20/E14 -> 11111.111 | I21: Unit price terlalu tinggi
B23: Note :
B24: 1. Cross cek kembali consumption solar genset per unit

Sheet AMOR
B2: Amortization
B3: Through Put CPO Proses | H3: TPD | I3: ='HPP REF '!N3 -> 1098.8155
B4: Working Day | H4: Day | I4: ='HPP REF '!N4 -> 23
B5: Total CPO Refined | H5: TPM | I5: =I4*I3 -> 25272.757
B6: Kurs Rupiah | I6: ='SUMMARY HPP '!I9 -> 15546
B7: No | C7: Description | D7: Actual 2023 | F7: Budget 2024
D8: Years | E8: Month | F8: Years | G8: Month | H8: RP/KG | I8: USD/MT
B9: 1 | C9: Perangkat Lunak/Software | D9: 9.6270931e+08 | E9: =D9/12 -> 80225776 | F9: =G9*12 -> 5.3192735e+08 | G9: 44327279 | H9: =$G$9/($I$5*1000) -> 1.753955 | I9: =($G$9/$I$6)/$I$5 -> 0.11282356 | J9: =D9/12 -> 80225776
B10: =B9+1 -> 2 | C10: Sertifikat/Surat Izin | D10: 2.6961444e+08 | E10: =D10/12 -> 22467870 | F10: 0 | G10: 0 | H10: =$G$10/($I$5*1000) -> 0 | I10: =($G$10/$I$6)/$I$5 -> 0
B11: =B10+1 -> 3 | C11: Inventaris Kecil (Aset Sewa) | D11: 0 | E11: =D11/12 -> 0 | F11: 0 | G11: 0 | H11: =$G$11/($I$5*1000) -> 0 | I11: =($G$11/$I$6)/$I$5 -> 0
B12: =B11+1 -> 4 | C12: Aset Hak Guna (ROU) - Kendaraan | D12: 0 | E12: =D12/12 -> 0 | F12: 0 | G12: 0 | H12: =$G$12/($I$5*1000) -> 0 | I12: =($G$12/$I$6)/$I$5 -> 0
B13: =B12+1 -> 5 | C13: Aset Hak Guna (ROU) - Tangki Timbun | D13: 0 | E13: =D13/12 -> 0 | F13: 0 | G13: 0 | H13: =$G$13/($I$5*1000) -> 0 | I13: =($G$13/$I$6)/$I$5 -> 0
B14: =B13+1 -> 6 | C14: Aset Atas Biaya Penyambungan | D14: 0 | E14: =D14/12 -> 0 | F14: 0 | G14: 0 | H14: =$G$14/($I$5*1000) -> 0 | I14: =($G$14/$I$6)/$I$5 -> 0
B15: =B14+1 -> 7 | C15: Aset Hak Guna (ROU) - Pemanfaatan Lahan Sei Mangkei + Surabaya | D15: 1.2576903e+10 | E15: =D15/12 -> 1.0480752e+09 | F15: =G15*12 -> 12048990312 | G15: 1004082526 | H15: =$G$15/($I$5*1000) -> 39.729837 | I15: =($G$15/$I$6)/$I$5 -> 2.5556309
B20: Total Cost Depreciation | D20: =SUM(D9:D19) -> 1.3809227e+10 | E20: =SUM(E9:E19) -> 1.1507689e+09 | F20: =SUM(F9:F19) -> 1.2580918e+10 | G20: =SUM(G9:G19) -> 1.0484098e+09 | H20: =SUM(H9:H19) -> 41.483792 | I20: =SUM(I9:I19) -> 2.6684544

Sheet DEP
B2: Depreciation
B3: Through Put CPO Proses | J3: TPD | K3: ='HPP REF '!N3 -> 1098.8155
B4: Working Day | J4: Day | K4: ='HPP REF '!N4 -> 23
B5: Total CPO Refined | J5: TPM | K5: =K4*K3 -> 25272.757
B6: Kurs Rupiah | K6: ='SUMMARY HPP '!I9 -> 15546
B7: No | C7: Description | D7: Actual 2023 (Audited) | G7: Budget 2024
D8: Asset | E8: Years | F8: Month | G8: Asset | H8: Years | I8: Month | J8: RP/KG | K8: USD/MT
B9: Total Cost Depreciation | D9: =SUM(D10:D75) -> 6.7971213e+11 | E9: =SUM(E10:E75) -> 4.1807174e+10 | F9: =SUM(F10:F75) -> 3.4839312e+09 | G9: =SUM(G10:G75) -> 7.7503139e+11 | H9: =SUM(H10:H75) -> 5.0174217e+10 | I9: =SUM(I10:I75) -> 4.1811848e+09 | J9: =SUM(J10:J75) -> 165.44237 | K9: =SUM(K10:K75) -> 10.642118
B10: 1 | C10: Front Office + Canteen | D10: 3844320790 | E10: 1.9221604e+08 | F10: 16018003 | G10: 3.8443208e+09 | H10: =I10*12 -> 1.9221604e+08 | I10: 16018003 | J10: =$I$10/($K$5*1000) -> 0.63380514 | K10: =($I$10/$K$6)/$K$5 -> 0.04076966
B11: =B10+1 -> 2 | C11: Bea Cukai Building | D11: 247144032 | E11: 12357202 | F11: 1029766.8 | G11: 2.4714403e+08 | H11: =I11*12 -> 12357202 | I11: 1029766.8 | J11: =$I$11/($K$5*1000) -> 0.04074612 | K11: =($I$11/$K$6)/$K$5 -> 0.0026210035
B12: =B11+1 -> 3 | C12: Security Building | D12: 199088248 | E12: 12429395 | F12: 1035782.9 | G12: 3.9708686e+08 | H12: =I12*12 -> 19854343 | I12: 1654528.6 | J12: =$I$12/($K$5*1000) -> 0.065466882 | K12: =($I$12/$K$6)/$K$5 -> 0.0042111721
B13: =B12+1 -> 4 | C13: Bangunan Shelter / Pelataran | D13: 53111657402 | E13: 2.6555829e+09 | F13: 2.2129857e+08 | G13: 5.3111657e+10 | H13: =I13*12 -> 2.6555829e+09 | I13: 2.2129857e+08 | J13: =$I$13/($K$5*1000) -> 8.756408 | K13: =($I$13/$K$6)/$K$5 -> 0.56325795
B14: =B13+1 -> 5 | C14: Laboratorium Building | D14: 1.3920764e+09 | E14: 70956822 | F14: 5913068.5 | G14: 1.5003164e+09 | H14: =I14*12 -> 75015820 | I14: 6251318.3 | J14: =$I$14/($K$5*1000) -> 0.24735403 | K14: =($I$14/$K$6)/$K$5 -> 0.015911104
B15: =B14+1 -> 6 | C15: Refinery Room | D15: 22378266872 | E15: 1.1189133e+09 | F15: 93242779 | G15: 2.2378267e+10 | H15: =I15*12 -> 1.1189133e+09 | I15: 93242779 | J15: =$I$15/($K$5*1000) -> 3.6894581 | K15: =($I$15/$K$6)/$K$5 -> 0.23732524
B16: =B15+1 -> 7 | C16: Fractionation Room | D16: 22378266872 | E16: 1.1189133e+09 | F16: 93242779 | G16: 2.2378267e+10 | H16: =I16*12 -> 1.1189133e+09 | I16: 93242779 | J16: =$I$16/($K$5*1000) -> 3.6894581 | K16: =($I$16/$K$6)/$K$5 -> 0.23732524
B17: =B16+1 -> 8 | C17: Utility Building | D17: 22548996820 | E17: 1.1274498e+09 | F17: 93954153 | G17: 2.2548997e+10 | H17: =I17*12 -> 1.1274498e+09 | I17: 93954153 | J17: =$I$17/($K$5*1000) -> 3.717606 | K17: =($I$17/$K$6)/$K$5 -> 0.23913586
B18: =B17+1 -> 9 | C18: Power House & Electrical Building | D18: 3242778116 | E18: 1.6663346e+08 | F18: 13886122 | G18: 3.6023423e+09 | H18: =I18*12 -> 1.8011712e+08 | I18: 15009760 | J18: =$I$18/($K$5*1000) -> 0.59391066 | K18: =($I$18/$K$6)/$K$5 -> 0.038203439
B19: =B18+1 -> 10 | C19: Weight Bridge Building (Timbangan) | D19: 3.0883582e+09 | E19: 1.6798762e+08 | F19: 13998968 | G19: 4.173935e+09 | H19: =I19*12 -> 2.0869675e+08 | I19: 17391396 | J19: =$I$19/($K$5*1000) -> 0.68814795 | K19: =($I$19/$K$6)/$K$5 -> 0.044265274
B20: =B19+1 -> 11 | C20: Warehouse TPS Spent Earth | D20: 1.3067146e+09 | E20: 65335728 | F20: 5444644 | G20: 1.3067146e+09 | H20: =I20*12 -> 65335728 | I20: 5444644 | J20: =$I$20/($K$5*1000) -> 0.2154353 | K20: =($I$20/$K$6)/$K$5 -> 0.013857925
B21: =B20+1 -> 12 | C21: Bangunan Shelter / Pelataran | D21: 0 | E21: 0 | F21: 0 | G21: 0 | H21: =I21*12 -> 0 | I21: 0 | J21: =$I$21/($K$5*1000) -> 0 | K21: =($I$21/$K$6)/$K$5 -> 0
B22: =B21+1 -> 13 | C22: Packaging Building | D22: 26865966199 | E22: 1.3432983e+09 | F22: 1.1194153e+08 | G22: 2.6865966e+10 | H22: =I22*12 -> 1.895783e+09 | I22: 1.5798192e+08 | J22: =$I$22/($K$5*1000) -> 6.2510758 | K22: =($I$22/$K$6)/$K$5 -> 0.40210188
B23: =B22+1 -> 14 | C23: Warehouse TPS Limbah B3 | D23: 808088751 | E23: 52164853 | F23: 4347071.1 | G23: 1.748922e+09 | H23: =I23*12 -> 87446098 | I23: 7287174.8 | J23: =$I$23/($K$5*1000) -> 0.28834111 | K23: =($I$23/$K$6)/$K$5 -> 0.018547608
B24: =B23+1 -> 15 | C24: Panel Room Loading - Unloading | D24: 669445527 | E24: 33472276 | F24: 2789356.4 | G24: 6.6944553e+08 | H24: =I24*12 -> 33472276 | I24: 2789356.4 | J24: =$I$24/($K$5*1000) -> 0.11037009 | K24: =($I$24/$K$6)/$K$5 -> 0.007099581
B25: =B24+1 -> 16 | C25: Bangunan Shelter / Pelataran | D25: 0 | E25: 0 | F25: 0 | G25: 0 | H25: =I25*12 -> 0 | I25: 0 | J25: =$I$25/($K$5*1000) -> 0 | K25: =($I$25/$K$6)/$K$5 -> 0
B26: =B25+1 -> 17 | C26: Kantor RO Medan | D26: 35739000 | E26: 3573900 | F26: 297825 | G26: 35739000 | H26: =I26*12 -> 3573900 | I26: 297825 | J26: =$I$26/($K$5*1000) -> 0.011784429 | K26: =($I$26/$K$6)/$K$5 -> 0.00075803606
B27: =B26+1 -> 18 | C27: Gedung Logistic | D27: 537402145 | E27: 26870107 | F27: 2239175.6 | G27: 537402145 | H27: =I27*12 -> 26870107 | I27: 2239175.6 | J27: =$I$27/($K$5*1000) -> 0.088600369 | K27: =($I$27/$K$6)/$K$5 -> 0.005699239
B28: =B27+1 -> 19 | C28: Ruang Expansi Filling Packaging | D28: 1071796228 | E28: 26794906 | F28: 2232908.8 | G28: 1071796228 | H28: =I28*12 -> 53589811 | I28: 4465817.6 | J28: =$I$28/($K$5*1000) -> 0.17670481 | K28: =($I$28/$K$6)/$K$5 -> 0.011366577
B29: =B28+1 -> 20 | C29: Bangunan Lainnya | D29: 236594750 | E29: 67601093 | F29: 5633424.5 | G29: 3.7519242e+09 | H29: =I29*12 -> 1.9942595e+08 | I29: 16618829 | J29: =$I$29/($K$5*1000) -> 0.65757879 | K29: =($I$29/$K$6)/$K$5 -> 0.042298906
B30: =B29+1 -> 21 | C30: Power House System | D30: 30414179484 | E30: 1.6120305e+09 | F30: 1.3433587e+08 | G30: 3.0414179e+10 | H30: =I30*12 -> 1.7106159e+09 | I30: 1.4255132e+08 | J30: =$I$30/($K$5*1000) -> 5.6405134 | K30: =($I$30/$K$6)/$K$5 -> 0.36282731
B31: =B30+1 -> 22 | C31: Reception from Road Tanker System | D31: 15714477178 | E31: 1.5906981e+09 | F31: 1.3255817e+08 | G31: 1.5714477e+10 | H31: =I31*12 -> 1.6892835e+09 | I31: 1.4077362e+08 | J31: =$I$31/($K$5*1000) -> 5.5701728 | K31: =($I$31/$K$6)/$K$5 -> 0.35830264
B32: =B31+1 -> 23 | C32: Reception & CPO Storage Tank System | D32: 3.9160256e+10 | E32: 1.8156968e+09 | F32: 1.5130807e+08 | G32: 3.9160256e+10 | H32: =I32*12 -> 1.9142822e+09 | I32: 1.5952352e+08 | J32: =$I$32/($K$5*1000) -> 6.3120743 | K32: =($I$32/$K$6)/$K$5 -> 0.40602562
B33: =B32+1 -> 24 | C33: Refinery Product System | D33: 26158484525 | E33: 1.546139e+09 | F33: 1.2884492e+08 | G33: 2.6158485e+10 | H33: =I33*12 -> 2.1043359e+09 | I33: 1.7536132e+08 | J33: =$I$33/($K$5*1000) -> 6.9387493 | K33: =($I$33/$K$6)/$K$5 -> 0.44633663
B34: =B33+1 -> 25 | C34: Fractionation Product System | D34: 44700543389 | E34: 2.5257813e+09 | F34: 2.1048177e+08 | G34: 4.4700543e+10 | H34: =I34*12 -> 2.6243667e+09 | I34: 2.1869722e+08 | J34: =$I$34/($K$5*1000) -> 8.6534771 | K34: =($I$34/$K$6)/$K$5 -> 0.55663689
B35: =B34+1 -> 26 | C35: Compressed Air System | D35: 12406716786 | E35: 6.9726354e+08 | F35: 58105295 | G35: 1.2406717e+10 | H35: =I35*12 -> 6.9726354e+08 | I35: 58105295 | J35: =$I$35/($K$5*1000) -> 2.2991277 | K35: =($I$35/$K$6)/$K$5 -> 0.14789191
B36: =B35+1 -> 27 | C36: Fuel Distribution System | D36: 2279256408 | E36: 1.6844371e+08 | F36: 14036976 | G36: 2.2792564e+09 | H36: =I36*12 -> 2.0366838e+08 | I36: 16972365 | J36: =$I$36/($K$5*1000) -> 0.67156762 | K36: =($I$36/$K$6)/$K$5 -> 0.043198741
B37: =B36+1 -> 28 | C37: Waste Water Treatment System | D37: 8173671310 | E37: 5.0165483e+08 | F37: 41804569 | G37: 8.1736713e+09 | H37: =I37*12 -> 5.1840723e+08 | I37: 43200602 | J37: =$I$37/($K$5*1000) -> 1.7093743 | K37: =($I$37/$K$6)/$K$5 -> 0.10995589
B38: =B37+1 -> 29 | C38: Clean Water System | D38: 8.1369458e+09 | E38: 4.697884e+08 | F38: 39149033 | G38: 8.1369458e+09 | H38: =I38*12 -> 4.697884e+08 | I38: 39149033 | J38: =$I$38/($K$5*1000) -> 1.5490606 | K38: =($I$38/$K$6)/$K$5 -> 0.099643679
B39: =B38+1 -> 30 | C39: Demin Water Distribution System | D39: 5554219736 | E39: 3.7021373e+08 | F39: 30851144 | G39: 5.5542197e+09 | H39: =I39*12 -> 3.7021373e+08 | I39: 30851144 | J39: =$I$39/($K$5*1000) -> 1.2207273 | K39: =($I$39/$K$6)/$K$5 -> 0.078523561
B40: =B39+1 -> 31 | C40: Steam Generation System | D40: 28411905935 | E40: 1.6009903e+09 | F40: 1.3341586e+08 | G40: 2.8411906e+10 | H40: =I40*12 -> 1.6009903e+09 | I40: 1.3341586e+08 | J40: =$I$40/($K$5*1000) -> 5.2790385 | K40: =($I$40/$K$6)/$K$5 -> 0.33957536 | L40: =H40/12 -> 1.3341586e+08
B41: =B40+1 -> 32 | C41: Cooling Water Distribution System | D41: 8813632097 | E41: 5.5719688e+08 | F41: 46433074 | G41: 8.8136321e+09 | H41: =I41*12 -> 5.5719688e+08 | I41: 46433074 | J41: =$I$41/($K$5*1000) -> 1.8372777 | K41: =($I$41/$K$6)/$K$5 -> 0.11818331
B42: =B41+1 -> 33 | C42: Fire Water System | D42: 4990631887 | E42: 3.5991574e+08 | F42: 29992978 | G42: 4.9906319e+09 | H42: =I42*12 -> 3.5991574e+08 | I42: 29992978 | J42: =$I$42/($K$5*1000) -> 1.1867711 | K42: =($I$42/$K$6)/$K$5 -> 0.076339323
B43: =B42+1 -> 34 | C43: Dual Fuel Emergency Generator | D43: 11752092639 | E43: 6.1186193e+08 | F43: 50988494 | G43: 1.1752093e+10 | H43: =I43*12 -> 6.1186193e+08 | I43: 50988494 | J43: =$I$43/($K$5*1000) -> 2.017528 | K43: =($I$43/$K$6)/$K$5 -> 0.12977795
B44: =B43+1 -> 35 | C44: Steam Distribution & Condensate Recovery System | D44: 9891619567 | E44: 8.9987659e+08 | F44: 74989716 | G44: 9.8916196e+09 | H44: =I44*12 -> 8.9987659e+08 | I44: 74989716 | J44: =$I$44/($K$5*1000) -> 2.9672155 | K44: =($I$44/$K$6)/$K$5 -> 0.19086681
B45: =B44+1 -> 36 | C45: Fire Water Main Ring System | D45: 4518985787 | E45: 2.4463794e+08 | F45: 20386495 | G45: 4.5189858e+09 | H45: =I45*12 -> 2.4463794e+08 | I45: 20386495 | J45: =$I$45/($K$5*1000) -> 0.80665893 | K45: =($I$45/$K$6)/$K$5 -> 0.05188852
B46: =B45+1 -> 37 | C46: Packaging System | D46: 34206697993 | E46: 3.1394346e+09 | F46: 2.6161955e+08 | G46: 1.2163436e+11 | H46: =I46*12 -> 7.8746236e+09 | I46: 6.5621863e+08 | J46: =$I$46/($K$5*1000) -> 25.965455 | K46: =($I$46/$K$6)/$K$5 -> 1.6702338
B47: =B46+1 -> 38 | C47: Refinery System | D47: 93804025615 | E47: 6.3108388e+09 | F47: 5.2590324e+08 | G47: 9.3804026e+10 | H47: =I47*12 -> 6.3327722e+09 | I47: 5.2773101e+08 | J47: =$I$47/($K$5*1000) -> 20.881418 | K47: =($I$47/$K$6)/$K$5 -> 1.343202
B48: =B47+1 -> 39 | C48: Fractionation System | D48: 69305898501 | E48: 4.7141422e+09 | F48: 3.9284518e+08 | G48: 6.9305899e+10 | H48: =I48*12 -> 4.7141422e+09 | I48: 3.9284518e+08 | J48: =$I$48/($K$5*1000) -> 15.544216 | K48: =($I$48/$K$6)/$K$5 -> 0.99988522
B49: =B48+1 -> 40 | C49: Fat Pit System | D49: 1222833568 | E49: 76427098 | F49: 6368924.8 | G49: 1.2228336e+09 | H49: =I49*12 -> 76427098 | I49: 6368924.8 | J49: =$I$49/($K$5*1000) -> 0.25200752 | K49: =($I$49/$K$6)/$K$5 -> 0.016210441
B50: =B49+1 -> 41 | C50: Weight Bridge | D50: 2557397646 | E50: 1.2786988e+08 | F50: 10655824 | G50: 2.5573976e+09 | H50: =I50*12 -> 1.2786988e+08 | I50: 10655824 | J50: =$I$50/($K$5*1000) -> 0.42163281 | K50: =($I$50/$K$6)/$K$5 -> 0.027121627
B51: =B50+1 -> 42 | C51: Mesin Dan Perlengkapan Pabrik | D51: 30580769059 | E51: 1.6581493e+09 | F51: 1.3817911e+08 | G51: 3.0797884e+10 | H51: =I51*12 -> 2.8889928e+09 | I51: 2.407494e+08 | J51: =$I$51/($K$5*1000) -> 9.5260441 | K51: =($I$51/$K$6)/$K$5 -> 0.61276496
B52: =B51+1 -> 43 | C52: Installation System Electrical (Auxiliary) | D52: 2460303143 | E52: 1.5376895e+08 | F52: 12814079 | G52: 2460303143 | H52: =I52*12 -> 1.5376895e+08 | I52: 12814079 | J52: =$I$52/($K$5*1000) -> 0.5070313 | K52: =($I$52/$K$6)/$K$5 -> 0.032614904
B53: =B52+1 -> 44 | C53: Mesin Dan Perlengkapan Pabrik | D53: 0 | E53: 0 | F53: 0 | G53: 0 | H53: =I53*12 -> 0 | I53: 0 | J53: =$I$53/($K$5*1000) -> 0 | K53: =($I$53/$K$6)/$K$5 -> 0
B54: =B53+1 -> 45 | C54: Mesin Dan Perlengkapan Pabrik | D54: 0 | E54: 0 | F54: 0 | G54: 0 | H54: =I54*12 -> 0 | I54: 0 | J54: =$I$54/($K$5*1000) -> 0 | K54: =($I$54/$K$6)/$K$5 -> 0
B55: =B54+1 -> 46 | C55: Refinery Product System | D55: 0 | E55: 0 | F55: 0 | G55: 0 | H55: =I55*12 -> 0 | I55: 0 | J55: =$I$55/($K$5*1000) -> 0 | K55: =($I$55/$K$6)/$K$5 -> 0
B56: =B55+1 -> 47 | C56: Perlengkapan Pabrik Lainnya | D56: 814629325 | E56: 1.3842046e+08 | F56: 11535038 | G56: 814629325 | H56: =I56*12 -> 1.3842046e+08 | I56: 11535038 | J56: =$I$56/($K$5*1000) -> 0.45642184 | K56: =($I$56/$K$6)/$K$5 -> 0.029359439
B57: =B56+1 -> 48 | C57: Bangunan Shelter / Pelataran | D57: 0 | E57: 0 | F57: 0 | G57: 0 | H57: =I57*12 -> 0 | I57: 0 | J57: =$I$57/($K$5*1000) -> 0 | K57: =($I$57/$K$6)/$K$5 -> 0
B58: =B57+1 -> 49 | C58: Saluran Drainase | D58: 3324550757 | E58: 1.6622754e+08 | F58: 13852295 | G58: 3.3245508e+09 | H58: =I58*12 -> 1.6622754e+08 | I58: 13852295 | J58: =$I$58/($K$5*1000) -> 0.54811174 | K58: =($I$58/$K$6)/$K$5 -> 0.035257413
B59: =B58+1 -> 50 | C59: Fence | D59: 1457273906 | E59: 72863695 | F59: 6071974.6 | G59: 1457273906 | H59: =I59*12 -> 72863695 | I59: 6071974.6 | J59: =$I$59/($K$5*1000) -> 0.24025771 | K59: =($I$59/$K$6)/$K$5 -> 0.015454632
B60: =B59+1 -> 51 | C60: Bangunan Shelter / Pelataran | D60: 0 | E60: 0 | F60: 0 | G60: 0 | H60: =I60*12 -> 0 | I60: 0 | J60: =$I$60/($K$5*1000) -> 0 | K60: =($I$60/$K$6)/$K$5 -> 0
B61: =B60+1 -> 52 | C61: Alat Pengangkutan | D61: 702420000 | E61: 58515250 | F61: 4876270.8 | G61: 702420000 | H61: =I61*12 -> 92109000 | I61: 7675750 | J61: =$I$61/($K$5*1000) -> 0.30371637 | K61: =($I$61/$K$6)/$K$5 -> 0.019536625
B62: =B61+1 -> 53 | C62: Perabot & Perlengkapan Kantor | D62: 2093240354 | E62: 2.8749571e+08 | F62: 23957976 | G62: 2093240354 | H62: =I62*12 -> 2.8749571e+08 | I62: 23957976 | J62: =$I$62/($K$5*1000) -> 0.94797635 | K62: =($I$62/$K$6)/$K$5 -> 0.060978795
B63: =B62+1 -> 54 | C63: Perabot dan Perlengkapan Mess | D63: 0 | E63: 0 | F63: 0 | G63: 0 | H63: =I63*12 -> 0 | I63: 0 | J63: =$I$63/($K$5*1000) -> 0 | K63: =($I$63/$K$6)/$K$5 -> 0
B64: =B63+1 -> 55 | C64: Alat & Perlengkapan Pabrik | D64: 68073000 | E64: 13614600 | F64: 1134550 | G64: 68073000 | H64: =I64*12 -> 13614600 | I64: 1134550 | J64: =$I$64/($K$5*1000) -> 0.044892213 | K64: =($I$64/$K$6)/$K$5 -> 0.0028877019
B65: =B64+1 -> 56 | C65: Alat dan Perlengkapan Bengkel | D65: 140550000 | E65: 28110000 | F65: 2342500 | G65: 140550000 | H65: =I65*12 -> 28110000 | I65: 2342500 | J65: =$I$65/($K$5*1000) -> 0.09268874 | K65: =($I$65/$K$6)/$K$5 -> 0.0059622244
B66: =B65+1 -> 57 | C66: Alat dan Perlengkapan Laboratorium | D66: 3453064640 | E66: 3.7398892e+08 | F66: 31165744 | G66: 4405170868 | H66: =I66*12 -> 8.9603417e+08 | I66: 74669514 | J66: =$I$66/($K$5*1000) -> 2.9545457 | K66: =($I$66/$K$6)/$K$5 -> 0.19005182
B67: =B66+1 -> 58 | C67: Alat IT / Komputer | D67: 1542535419 | E67: 2.9444276e+08 | F67: 24536897 | G67: 1.9760604e+09 | H67: =I67*12 -> 2.9825396e+08 | I67: 24854497 | J67: =$I$67/($K$5*1000) -> 0.98345015 | K67: =($I$67/$K$6)/$K$5 -> 0.063260655
B68: =B67+1 -> 59 | C68: Perabot & Perlengkapan Lainnya | D68: 11270000 | E68: 2254000 | F68: 187833.33 | G68: 11270000 | H68: =I68*12 -> 2254000 | I68: 187833.33 | J68: =$I$68/($K$5*1000) -> 0.0074322455 | K68: =($I$68/$K$6)/$K$5 -> 0.00047808089
B69: =B68+1 -> 60 | C69: Aktiva Tetap Non Produktif | D69: 26932688 | E69: 5386537.6 | F69: 448878.13 | G69: 26932688 | H69: =I69*12 -> 5386537.5 | I69: 448878.13 | J69: =$I$69/($K$5*1000) -> 0.017761344 | K69: =($I$69/$K$6)/$K$5 -> 0.0011425025
B70: =B69+1 -> 61 | C70: Totem AKHLAK | D70: 30000000 | E70: 6000000 | F70: 500000 | G70: 30000000 | H70: =I70*12 -> 6000000.1 | I70: 500000.01 | J70: =$I$70/($K$5*1000) -> 0.01978415 | K70: =($I$70/$K$6)/$K$5 -> 0.0012726199
B71: =B70+1 -> 62 | C71: Main Office | D71: 6869341541 | E71: 3.4448348e+08 | F71: 28706957 | G71: 6.9506539e+09 | H71: =I71*12 -> 3.4753269e+08 | I71: 28961058 | J71: =$I$71/($K$5*1000) -> 1.1459398 | K71: =($I$71/$K$6)/$K$5 -> 0.073712839

Sheet MTC
C1: working days | F1: working days
B2: Summary - PM Electrical | C2: ='Desember 2024'!AM6 -> 23 | E2: Summary - PM Mechanical | F2: ='Desember 2024'!AM6 -> 23
B3: Consumable Item | C3: Total Price | E3: Consumable Item | F3: Total Price
C4: Per Day | F4: Per Day
B5: Biaya Pemeliharaan Unit Refinery(Listrik) | C5: 1648879.6 | E5: Biaya Pemeliharaan Unit Refinery | F5: 4911824.3
B6: HP Boiler | C6: 2678431.4 | E6: Biaya Pemeliharaan Unit Fraksinasi | F6: 1230672.3
B7: Dry Fractination - Crystalizer & Filter Press | C7: 288459.38 | E7: Biaya Pemeliharaan Unit Cooling Tower | F7: 1084733.9
B8: Physical Refinery-Bleaching and Deodorization | C8: 404271.71 | E8: Biaya Pemeliharaan Unit Packaging | F8: 833815.52
B9: BOILER | C9: 150891.4 | E9: Biaya Pemeliharaan Unit Material Handling | F9: 949299.72
B10: Water Plant, Effluent & Hydrant | C10: 58543.417 | E10: Biaya Pemeliharaan Unit Utility | F10: 1106022.4
B11: Pump House | C11: 87425.77 | E11: Barang Consumable Maintenance | F11: 5634698.9
B12: DCS-CCR ISBL | C12: 254341.74
B13: Lighting All Area | C13: 114733.89 | E13: Total | F13: =SUM(F5:F12) -> 15751067
B14: Consumable | C14: 203159.66 | E14: Total/Month | F14: =F13*F2 -> 3.6227454e+08
B15: Kalibrasi Instrument Pabrik | C15: 580672.27 | E15: Total/Yearly | F15: =F14*12 -> 4.3472945e+09
B16: Service Special Equipment | C16: 4089635.9
B17: Total/Day | C17: =SUM(C5:C16) -> 10559446 | E17: TOTAL COST
B18: Total/Month | C18: =C17*C2 -> 2.4286726e+08 | E18: PM E + PM M | F18: =F14+C18 -> 6.051418e+08
B19: Total/Yearly | C19: =C18*12 -> 2.9144071e+09 | E19: TOTAL | F19: =F18*12 -> 7.2617016e+09

Sheet LOG
B2: Port Cost Kuala Tanjung
B3: Through Put CPO Proses | J3: TPD | K3: ='HPP REF '!N3 -> 1098.8155
B4: Working Day | J4: Day | K4: ='HPP REF '!N4 -> 23
B5: Total CPO Refined | J5: TPM | K5: =K4*K3 -> 25272.757
B6: Kurs Rupiah | K6: ='SUMMARY HPP '!I9 -> 15546
B7: No | C7: Description | G7: Norma | I7: Total Biaya ( Rp ) | J7: RP/KG | K7: USD/MT
B8: 1 | C8: Trucking Komoditi ke Kuala Tanjung | E8: Olein ( Ton ) | F8: =(100%-0.8%-1.1*5%)*80%*K5 -> 18944.459 | G8: Rp/Kg | H8: 90 | I8: =H8*F8*1000 -> 1.7050013e+09 | J8: =I8/($K$5*1000) -> 67.464 | K8: =(I8/$K$6)/$K$5 -> 4.3396372
E9: Stearin ( Ton ) Iso Tank | F9: =(100%-0.8%-1.1*5%)*20%*K5 -> 4736.1147 | G9: Rp/Kg | H9: 150 | I9: =H9*F9*1000 -> 7.104172e+08 | J9: =I9/($K$5*1000) -> 28.11 | K9: =(I9/$K$6)/$K$5 -> 1.8081822
E10: PFAD ( Ton ) Iso Tank | F10: =1.1*5%*K5 -> 1390.0016 | G10: Rp/Kg | H10: 150 | I10: =H10*F10*1000 -> 2.0850025e+08 | J10: =I10/($K$5*1000) -> 8.25 | K10: =(I10/$K$6)/$K$5 -> 0.53068313
B11: 2 | C11: Sewa Tank PTI Total Volume : 24.000 MT ( 5 Unit ) | E11: Tank 8.000 MT >> Olein | F11: 1 | G11: Rp/Kg | H11: 77 | I11: =H11*8000*F11*1000 -> 616000000 | J11: =I11/($K$5*1000) -> 24.374072 | K11: =(I11/$K$6)/$K$5 -> 1.5678678
E12: Tank 5.000 MT >> Stearin | F12: 2 | G12: Rp/Kg | H12: 79 | I12: =H12*5000*F12*1000 -> 790000000 | J12: =I12/($K$5*1000) -> 31.258956 | K12: =(I12/$K$6)/$K$5 -> 2.0107395
E13: Tank 3.000 MT >> RBDPO | F13: 1 | G13: Rp/Kg | H13: 77 | I13: =H13*3000*F13*1000 -> 231000000 | J13: =I13/($K$5*1000) -> 9.140277 | K13: =(I13/$K$6)/$K$5 -> 0.58795041
E14: Tank 3.000 MT S/S >> PFAD | F14: 1 | G14: Rp/Kg | H14: 83 | I14: =H14*3000*F14*1000 -> 249000000 | J14: =I14/($K$5*1000) -> 9.8525064 | K14: =(I14/$K$6)/$K$5 -> 0.63376472
B15: 3 | C15: Finalty Over Capacity dari tank | D15: 0 | E15: Over Volume Olein | F15: =F8-(8000*D15) -> 18944.459 | G15: Rp/Kg | H15: 43 | I15: =H15*F15*1000 -> 8.1461172e+08 | J15: =I15/($K$5*1000) -> 32.2328 | K15: =(I15/$K$6)/$K$5 -> 2.0733822
D16: 0 | E16: Over Volume Stearin | F16: =F9-(10000*D16) -> 4736.1147 | G16: Rp/Kg | H16: 43 | I16: =H16*F16*1000 -> 2.0365293e+08 | J16: =I16/($K$5*1000) -> 8.0582 | K16: =(I16/$K$6)/$K$5 -> 0.51834556
D17: 0 | E17: Over Volume PFAD | F17: =F10-(3000*D17) -> 1390.0016 | G17: Rp/Kg | H17: 43 | I17: =H17*F17*1000 -> 59770070 | J17: =I17/($K$5*1000) -> 2.365 | K17: =(I17/$K$6)/$K$5 -> 0.15212917
B18: 3 | C18: Beban Instalasi Pemompaan dan Pemanasan | E18: Total Volume | F18: =SUM(F8:F10) -> 25070.575 | G18: Rp/Kg | H18: 22 | I18: =H18*F18*1000 -> 5.5155265e+08 | J18: =I18/($K$5*1000) -> 21.824 | K18: =(I18/$K$6)/$K$5 -> 1.4038338
B19: =B18+1 -> 4 | C19: Pompa | E19: Total Volume | F19: =F18 -> 25070.575 | G19: Rp/Kg | H19: 26 | I19: =H19*F18*1000 -> 6.5183495e+08 | J19: =I19/($K$5*1000) -> 25.792 | K19: =(I19/$K$6)/$K$5 -> 1.6590763
B20: =B19+1 -> 5 | C20: Beban Analisa ( Surveyor ) | E20: Total Volume | F20: =F18 -> 25070.575 | G20: Rp/Kg | H20: 3 | I20: =H20*F20*1000 -> 75211725 | J20: =I20/($K$5*1000) -> 2.976 | K20: =(I20/$K$6)/$K$5 -> 0.19143188
B21: =B20+1 -> 6 | C21: Beban Pelabuhan ( Documen-Documen Pelabuhan ) | E21: Total Volume | F21: =F20 -> 25070.575 | G21: Rp/Kg | H21: 3 | I21: =H21*F21*1000 -> 75211725 | J21: =I21/($K$5*1000) -> 2.976 | K21: =(I21/$K$6)/$K$5 -> 0.19143188
B22: =B21+1 -> 7 | C22: Beban Asuransi (Cost Insurance Freight)
B23: =B22+1 -> 8 | C23: Beban Sewa Kapal
B24: =B23+1 -> 9 | C24: Beban Pengangkutan Di Pelabuhan
B25: Total Biaya Transfer Product ke Kuala Tanjung Port | I25: =SUM(I8:I24) -> 6.9417645e+09 | J25: =SUM(J8:J24) -> 274.67381 | K25: =SUM(K8:K24) -> 17.668456

Sheet OH
B2: Overhead ( OH )
B3: Through Put CPO Proses | H3: TPD | I3: ='HPP REF '!N3 -> 1098.8155
B4: Working Day | H4: Day | I4: ='SUMMARY HPP '!I4 -> 23
B5: Total CPO Refined | H5: TPM | I5: =I4*I3 -> 25272.757
B6: Kurs Rupiah | I6: ='SUMMARY HPP '!I9 -> 15546
B7: No | C7: Description | D7: Actual 2023 (Audited) | F7: Budget 2024
D8: Years | E8: Month | F8: Years | G8: Month | H8: RP/KG | I8: USD/MT
B9: 1 | C9: Biaya Perjalanan Dinas (Dalam Provinsi) | D9: 305458258 | E9: =IFERROR(D9/12,0) -> 25454855 | F9: =G9*12 -> 3.6654991e+08 | G9: 30545826 | H9: =G9/($I$5*1000) -> 1.2086464 | I9: =(G9/$I$6)/$I$5 -> 0.077746453
B10: =B9+1 -> 2 | C10: Biaya Perjalanan Dinas (Luar Provinsi) | D10: 2.6287295e+09 | E10: =IFERROR(D10/12,0) -> 2.1906079e+08 | F10: =G10*12 -> 3.5487849e+09 | G10: 2.9573207e+08 | H10: =G10/($I$5*1000) -> 11.701615 | I10: =(G10/$I$6)/$I$5 -> 0.75270906
B11: =B10+1 -> 3 | C11: Beban BBM Kendaraan | D11: 720175678 | E11: =IFERROR(D11/12,0) -> 60014640 | F11: =G11*12 -> 7.5618446e+08 | G11: 63015372 | H11: =G11/($I$5*1000) -> 2.4934111 | I11: =(G11/$I$6)/$I$5 -> 0.16038924
B12: =B11+1 -> 4 | C12: Beban Sewa Kendaraan | D12: 2428347903 | E12: =IFERROR(D12/12,0) -> 2.0236233e+08 | F12: =G12*12 -> 2220000000 | G12: 185000000 | H12: =G12/($I$5*1000) -> 7.3201353 | I12: =(G12/$I$6)/$I$5 -> 0.47086937
B13: =B12+1 -> 5 | C13: Beban Kendaraan Lainnya | D13: 110862850 | E13: =IFERROR(D13/12,0) -> 9238570.8 | F13: =G13*12 -> 110862850 | G13: 9238570.8 | H13: =G13/($I$5*1000) -> 0.36555453 | I13: =(G13/$I$6)/$I$5 -> 0.023514379
B14: =B13+1 -> 6 | C14: Beban Sewa Bangunan / Inventaris / Aset | D14: 126990400 | E14: =IFERROR(D14/12,0) -> 10582533 | F14: =G14*12 -> 110000400 | G14: 9166700 | H14: =G14/($I$5*1000) -> 0.36271072 | I14: =(G14/$I$6)/$I$5 -> 0.02333145
B15: =B14+1 -> 7 | C15: Beban Penelitian, Percobaan & Pengembangan | D15: 108868060 | E15: =IFERROR(D15/12,0) -> 9072338.3 | F15: =G15*12 -> 100000000 | G15: 8333333.3 | H15: =G15/($I$5*1000) -> 0.32973582 | I15: =(G15/$I$6)/$I$5 -> 0.021210332
B16: =B15+1 -> 8 | C16: Beban Pemeliharaan Bangunan Rumah | D16: 203000 | E16: =IFERROR(D16/12,0) -> 16916.667 | F16: =G16*12 -> 0 | G16: 0 | H16: =G16/($I$5*1000) -> 0 | I16: =(G16/$I$6)/$I$5 -> 0
B17: =B16+1 -> 9 | C17: Beban Pemeliharaan Bangunan Perusahaan | D17: 108952486 | E17: =IFERROR(D17/12,0) -> 9079373.8 | F17: =G17*12 -> 1.1440011e+08 | G17: 9533342.5 | H17: =G17/($I$5*1000) -> 0.37721815 | I17: =(G17/$I$6)/$I$5 -> 0.024264643
B18: =B17+1 -> 10 | C18: Beban Pemeliharaan Mesin & Instalansi | D18: 32369030 | E18: =IFERROR(D18/12,0) -> 2697419.2 | F18: =G18*12 -> 33987482 | G18: 2832290.1 | H18: =G18/($I$5*1000) -> 0.1120689 | I18: =(G18/$I$6)/$I$5 -> 0.0072088577
B19: =B18+1 -> 11 | C19: Beban Pemeliharaan Jalan, Jembatan & Saluran Air | D19: 179265600 | E19: =IFERROR(D19/12,0) -> 14938800 | F19: =G19*12 -> 188228880 | G19: 15685740 | H19: =G19/($I$5*1000) -> 0.62065805 | I19: =(G19/$I$6)/$I$5 -> 0.039923971
B20: =B19+1 -> 12 | C20: Beban Pemeliharaan Alat Inventaris Kecil | D20: 253700695 | E20: =IFERROR(D20/12,0) -> 21141725 | F20: =G20*12 -> 2.6638573e+08 | G20: 22198811 | H20: =G20/($I$5*1000) -> 0.87836918 | I20: =(G20/$I$6)/$I$5 -> 0.056501298
B21: =B20+1 -> 13 | C21: Beban Pemakaian Inventaris Kecil | D21: 1859843066 | E21: =IFERROR(D21/12,0) -> 1.5498692e+08 | F21: =G21*12 -> 335473201 | G21: 27956100 | H21: =G21/($I$5*1000) -> 1.1061753 | I21: =(G21/$I$6)/$I$5 -> 0.07115498
B22: =B21+1 -> 14 | C22: Beban Iuran, Sumbangan, & Bina Lingkungan | D22: 694460474 | E22: =IFERROR(D22/12,0) -> 57871706 | F22: =G22*12 -> 2.6839105e+08 | G22: 22365921 | H22: =G22/($I$5*1000) -> 0.88498145 | I22: =(G22/$I$6)/$I$5 -> 0.056926634
B23: =B22+1 -> 15 | C23: Beban Instansi Kelembagaan | E23: =IFERROR(D23/12,0) -> 0 | F23: =G23*12 -> 60000000 | G23: 5000000 | H23: =G23/($I$5*1000) -> 0.19784149 | I23: =(G23/$I$6)/$I$5 -> 0.012726199
B24: =B23+1 -> 16 | C24: Beban Pajak & Retribusi | D24: 659276883 | E24: =IFERROR(D24/12,0) -> 54939740 | F24: =G24*12 -> 1518332400 | G24: 126527700 | H24: =G24/($I$5*1000) -> 5.0064858 | I24: =(G24/$I$6)/$I$5 -> 0.32204334
B25: =B24+1 -> 17 | C25: Beban Premi Assuransi | E25: =IFERROR(D25/12,0) -> 0 | F25: =G25*12 -> 197000000 | G25: 16416667 | H25: =G25/($I$5*1000) -> 0.64957957 | I25: =(G25/$I$6)/$I$5 -> 0.041784354
B26: =B25+1 -> 18 | C26: Beban Penerangan | D26: 62716328 | E26: =IFERROR(D26/12,0) -> 5226360.7 | F26: =G26*12 -> 80400000 | G26: 6700000 | H26: =G26/($I$5*1000) -> 0.2651076 | I26: =(G26/$I$6)/$I$5 -> 0.017053107
B27: =B26+1 -> 19 | C27: Beban Persediaan Air | D27: 1756590 | E27: =IFERROR(D27/12,0) -> 146382.5 | F27: =G27*12 -> 6840000 | G27: 570000 | H27: =G27/($I$5*1000) -> 0.02255393 | I27: =(G27/$I$6)/$I$5 -> 0.0014507867
B28: =B27+1 -> 20 | C28: Beban Pemakaian Perlengkapan Kantor | D28: 1.1936208e+09 | E28: =IFERROR(D28/12,0) -> 99468402 | F28: =G28*12 -> 1.1936208e+09 | G28: 99468402 | H28: =G28/($I$5*1000) -> 3.9357954 | I28: =(G28/$I$6)/$I$5 -> 0.25317094
B29: =B28+1 -> 21 | C29: Beban Pengendalian Lingkungan (ISO 14000) | D29: 488020500 | E29: =IFERROR(D29/12,0) -> 40668375 | F29: =G29*12 -> 264000000 | G29: 22000000 | H29: =G29/($I$5*1000) -> 0.87050257 | I29: =(G29/$I$6)/$I$5 -> 0.055995277
B30: =B29+1 -> 22 | C30: Beban Sistem Manajemen Keselamatan & Kesehatan Kerja (SMK3) | D30: 68171900 | E30: =IFERROR(D30/12,0) -> 5680991.7 | F30: =G30*12 -> 258000000 | G30: 21500000 | H30: =G30/($I$5*1000) -> 0.85071842 | I30: =(G30/$I$6)/$I$5 -> 0.054722657
B31: =B30+1 -> 23 | C31: Beban Pendidikan & Pengembangan SDM | D31: 1186354647 | E31: =IFERROR(D31/12,0) -> 98862887 | F31: =G31*12 -> 10000000 | G31: 833333.33 | H31: =G31/($I$5*1000) -> 0.032973582 | I31: =(G31/$I$6)/$I$5 -> 0.0021210332
B32: =B31+1 -> 24 | C32: Beban Audit (Independent Auditor) | D32: 8.477783e+08 | E32: =IFERROR(D32/12,0) -> 70648192 | F32: =G32*12 -> 9.0712278e+08 | G32: 75593565 | H32: =G32/($I$5*1000) -> 2.9911088 | I32: =(G32/$I$6)/$I$5 -> 0.19240375
B33: =B32+1 -> 25 | C33: Beban Konsultan - Eksternal | D33: 245454645 | E33: =IFERROR(D33/12,0) -> 20454554 | F33: =G33*12 -> 2.7000011e+08 | G33: 22500009 | H33: =G33/($I$5*1000) -> 0.89028708 | I33: =(G33/$I$6)/$I$5 -> 0.05726792
B34: =B33+1 -> 26 | C34: Beban Insentif Karyawan | E34: =IFERROR(D34/12,0) -> 0 | F34: =G34*12 -> 0 | G34: 0 | H34: =G34/($I$5*1000) -> 0 | I34: =(G34/$I$6)/$I$5 -> 0
B35: =B34+1 -> 27 | C35: Beban Jasa Produksi Karyawan | E35: =IFERROR(D35/12,0) -> 0 | F35: =G35*12 -> 0 | G35: 0 | H35: =G35/($I$5*1000) -> 0 | I35: =(G35/$I$6)/$I$5 -> 0
B36: =B35+1 -> 28 | C36: Beban Uang Jasa (Jubilium, SHT, Dll) | D36: 188207400 | E36: =IFERROR(D36/12,0) -> 15683950 | F36: =G36*12 -> 207028140 | G36: 17252345 | H36: =G36/($I$5*1000) -> 0.68264594 | I36: =(G36/$I$6)/$I$5 -> 0.043911356
B37: =B36+1 -> 29 | C37: Beban Imbalan Pasca Kerja | D37: 4384212523 | E37: =IFERROR(D37/12,0) -> 3.6535104e+08 | F37: =G37*12 -> 666345107 | G37: 55528759 | H37: =G37/($I$5*1000) -> 2.1971785 | I37: =(G37/$I$6)/$I$5 -> 0.14133401
B38: =B37+1 -> 30 | C38: Beban Pengurusan Sertifikasi / Hak Merk / Izin / Dll | D38: 108648500 | E38: =IFERROR(D38/12,0) -> 9054041.7 | F38: =G38*12 -> 114080925 | G38: 9506743.8 | H38: =G38/($I$5*1000) -> 0.37616568 | I38: =(G38/$I$6)/$I$5 -> 0.024196943
B39: =B38+1 -> 31 | C39: Beban Entertainment | D39: 80056015 | E39: =IFERROR(D39/12,0) -> 6671334.6 | F39: =G39*12 -> 0 | G39: 0 | H39: =G39/($I$5*1000) -> 0 | I39: =(G39/$I$6)/$I$5 -> 0
B40: =B39+1 -> 32 | C40: Beban Akomodasi Rapat | D40: 84564877 | E40: =IFERROR(D40/12,0) -> 7047073.1 | F40: =G40*12 -> 88793121 | G40: 7399426.7 | H40: =G40/($I$5*1000) -> 0.29278273 | I40: =(G40/$I$6)/$I$5 -> 0.018833316
B41: =B40+1 -> 33 | C41: Beban Bonus Karyawan | E41: =IFERROR(D41/12,0) -> 0 | F41: =G41*12 -> 0 | G41: 0 | H41: =G41/($I$5*1000) -> 0 | I41: =(G41/$I$6)/$I$5 -> 0
B42: =B41+1 -> 34 | C42: Beban Tantiem | E42: =IFERROR(D42/12,0) -> 0 | F42: =G42*12 -> 0 | G42: 0 | H42: =G42/($I$5*1000) -> 0 | I42: =(G42/$I$6)/$I$5 -> 0
B43: =B42+1 -> 35 | C43: Beban Konsumsi | D43: 3864122096 | E43: =IFERROR(D43/12,0) -> 3.2201017e+08 | F43: =G43*12 -> 2223000000 | G43: 185250000 | H43: =G43/($I$5*1000) -> 7.3300273 | I43: =(G43/$I$6)/$I$5 -> 0.47150568
B44: =B43+1 -> 36 | C44: Beban Ekstra Fooding | D44: 810000 | E44: =IFERROR(D44/12,0) -> 67500 | F44: =G44*12 -> 0 | G44: 0 | H44: =G44/($I$5*1000) -> 0 | I44: =(G44/$I$6)/$I$5 -> 0
B45: =B44+1 -> 37 | C45: Beban Pemeriksaan Kesehatan / Perobatan | D45: 185612516 | E45: =IFERROR(D45/12,0) -> 15467710 | F45: =G45*12 -> 41405668 | G45: 3450472.3 | H45: =G45/($I$5*1000) -> 0.13652932 | I45: =(G45/$I$6)/$I$5 -> 0.0087822797
B46: =B45+1 -> 38 | C46: Beban Peringatan Hari Besar | D46: 300000 | E46: =IFERROR(D46/12,0) -> 25000 | F46: =G46*12 -> 25000000 | G46: 2083333.3 | H46: =G46/($I$5*1000) -> 0.082433956 | I46: =(G46/$I$6)/$I$5 -> 0.005302583
B47: =B46+1 -> 39 | C47: Beban Perlengkapan Karyawan | D47: 497881607 | E47: =IFERROR(D47/12,0) -> 41490134 | F47: =G47*12 -> 420000000 | G47: 35000000 | H47: =G47/($I$5*1000) -> 1.3848905 | I47: =(G47/$I$6)/$I$5 -> 0.089083395
B48: =B47+1 -> 40 | C48: Beban Keperluan Dapur / Pantry | D48: 79298165 | E48: =IFERROR(D48/12,0) -> 6608180.4 | F48: =G48*12 -> 12458700 | G48: 1038225 | H48: =G48/($I$5*1000) -> 0.041080797 | I48: =(G48/$I$6)/$I$5 -> 0.0026425316
B49: =B48+1 -> 41 | C49: Beban Employee Gathering | E49: =IFERROR(D49/12,0) -> 0 | F49: =G49*12 -> 250000000 | G49: 20833333 | H49: =G49/($I$5*1000) -> 0.82433956 | I49: =(G49/$I$6)/$I$5 -> 0.05302583
B50: =B49+1 -> 42 | C50: Beban Kebersihan | D50: 11059767 | E50: =IFERROR(D50/12,0) -> 921647.25 | F50: =G50*12 -> 0 | G50: 0 | H50: =G50/($I$5*1000) -> 0 | I50: =(G50/$I$6)/$I$5 -> 0
D51: =SUM(D9:D50) -> 2.3796151e+10 | E51: =SUM(E9:E50) -> 1.9830126e+09 | F51: =SUM(F9:F50) -> 1.7232677e+10 | G51: =SUM(G9:G50) -> 1.4360564e+09 | H51: =SUM(H9:H50) -> 56.822308 | I51: =SUM(I9:I50) -> 3.655108

Sheet Time Sheet Bulanan
A1: Nomor | B1: Tanggal | C1: Keterangan
C2: Refinery | D2: Fraksinasi
A3: 1 | B3: 45536
A4: 2 | B4: 45537
A5: 3 | B5: 45538
A6: 4 | B6: 45539
A7: 5 | B7: 45540
A8: 6 | B8: 45541
A9: 7 | B9: 45542
A10: 8 | B10: 45543
A11: 9 | B11: 45544
A12: 10 | B12: 45545
A13: 11 | B13: 45546
A14: 12 | B14: 45547
... A25: 23 | B25: 45558
